Workbook

Sheet README
A1: Peer KPI comps - CoreWeave (CRWV) - quarterly Q1'24 to Q2'26. Built 2026-10-04 (ET); polished 2026-10-05 (ET) — Notes_Gaps reorganized, K02b≡K02 alignment, EDGAR scan (no new ops data). File: /workspace/nebius/peers/coreweave/crwv_kpis.xlsx; builder: build_crwv_kpis.py.
A2: PURPOSE: CoreWeave KPI history on the SAME definitions as the Nebius work (see Definitions tab: every KPI cites the Nebius file/row it mirrors).
A3: TABS: KPIs (quarterly, live formulas off Inputs/Debt_Facilities; each KPI = value row + tag row) | Inputs (raw figures, colour-coded by tag) | Debt_Facilities (facility-level principal x effective rate per quarter-end) | Sources (one row per input cell: document, section, URL, formula for derived cells) | Definitions | Notes_Gaps | Comparison (template vs Nebius; CRWV linked live).
A4: TAGS / COLOURS: blue = Reported (as disclosed); black = Derived (arithmetic on reported figures; formula in Sources/KPIs); orange = Estimated (uses an assumption, e.g. interpolated MW, GPUs from MW x density); grey 'n/d' = not disclosed. KPI cells inherit the WEAKEST tag of their inputs (shown on the tag row under each KPI).
A5: COLUMN E (Q4'23*) is an opening-balance column for stock items (MW, PP&E, debt, GPUs) used for averages/deltas in Q1'24; flow KPIs start in column F (Q1'24).
A6: TEMPLATE USE (IREN, Oracle OCI, private peers): copy this workbook, keep every row ID (I01..I27, P01..P03, K01..K40) and column layout, overwrite Inputs values/tags/sources and the Debt_Facilities rows for the new peer. KPI formulas reference fixed Inputs rows, so they recompute unchanged. Leave unavailable inputs blank or 'n/d' - KPIs return 'n/d'. Then link the peer's latest-quarter KPI column into the Comparison tab.
A7: UNITS: $M unless stated; $/MW KPIs are annualized ($M per MW-year = quarterly revenue x 4 / MW); $/GPU in $K per GPU-year; rates in % p.a.
A8: Caveat summary: CoreWeave does not state IT vs gross MW, has not disclosed GPU counts since the S-1, and did not publish 2024 interim balance sheets or MW (pre-IPO). See Notes_Gaps.
A9: POLISH 2026-10-05: (1) Notes_Gaps rebuilt as A=n/d inventory / B=caveats / C=post-quarter+cross-pack. (2) K02b added (=K02); I09B alias = I09E. (3) EDGAR through Oct 5: latest ops still Q2'26 10-Q; Oct 2–3 = Form 4 only. No quarterly number changes vs Oct-4 pack.
A10: FIX 2026-10-08 (ET): KPI K18 'Implied average depreciable life' now = 100 / K17 (depreciation yield) in every quarter (Q2'26 ~6.47 yrs). Previously 100 / K16 (6-yr useful-life row) = 16.67 for all quarters after the in-place K02b row insert; polish merged into build_crwv_kpis.py.

Sheet KPIs
A1: KPIs - CoreWeave (CRWV) - quarterly, Nebius definitions (Definitions tab). Value row = live formula; row below = tag (R/D/E/n/d = weakest input). Annualized where $/MW or $/GPU.
E2: 2023-12-31 | F2: 2024-03-31 | G2: 2024-06-30 | H2: 2024-09-30 | I2: 2024-12-31 | J2: 2025-03-31 | K2: 2025-06-30 | L2: 2025-09-30 | M2: 2025-12-31 | N2: 2026-03-31 | O2: 2026-06-30
A3: ID | B3: KPI | C3: Unit | D3: Def | E3: Q4'23* | F3: Q1'24 | G3: Q2'24 | H3: Q3'24 | I3: Q4'24 | J3: Q1'25 | K3: Q2'25 | L3: Q3'25 | M3: Q4'25 | N3: Q1'26 | O3: Q2'26 | P3: Method / caveat
A4: A. Revenue per MW ($M per MW-year, annualized: quarterly revenue x 4 / MW)
A5: K01 | B5: Revenue per active MW - period-end reported MW | C5: $M/MW-yr | D5: D1 | E5: n/d | F5: n/d | G5: n/d | H5: n/d | I5: =IFERROR(Inputs!I4*4/Inputs!I12,"n/d") -> 8.3047778 | J5: =IFERROR(Inputs!J4*4/Inputs!J12,"n/d") -> 9.3488762 | K5: =IFERROR(Inputs!K4*4/Inputs!K12,"n/d") -> 10.3216 | L5: =IFERROR(Inputs!L4*4/Inputs!L12,"n/d") -> 9.2520407 | M5: =IFERROR(Inputs!M4*4/Inputs!M12,"n/d") -> 7.3976471 | N5: =IFERROR(Inputs!N4*4/Inputs!N12,"n/d") -> 8.312 | O5: =IFERROR(Inputs!O4*4/Inputs!O12,"n/d") -> 6.8666667 | P5: Nebius KPIs!F17 'Revenue per energized/active MW' (= AI rev x4 / MW) and parts/comps_rev_per_mw.csv (CRWV Q2'26 6.87 on period-end MW). Understates when MW ramps late in quarter.
B6: tag | E6: n/d | F6: n/d | G6: n/d | H6: n/d | I6: Derived | J6: Derived | K6: Derived | L6: Derived | M6: Derived | N6: Derived | O6: Derived
A7: K02 | B7: Revenue per active MW - average MW (2024 uses interpolated MW) | C7: $M/MW-yr | D7: D1 | E7: n/d | F7: =IFERROR(Inputs!F4*4/Inputs!F37,"n/d") -> 7.1033976 | G7: =IFERROR(Inputs!G4*4/Inputs!G37,"n/d") -> 8.8474629 | H7: =IFERROR(Inputs!H4*4/Inputs!H37,"n/d") -> 9.2965731 | I7: =IFERROR(Inputs!I4*4/Inputs!I37,"n/d") -> 9.2346564 | J7: =IFERROR(Inputs!J4*4/Inputs!J37,"n/d") -> 10.068021 | K7: =IFERROR(Inputs!K4*4/Inputs!K37,"n/d") -> 10.901465 | L7: =IFERROR(Inputs!L4*4/Inputs!L37,"n/d") -> 10.299442 | M7: =IFERROR(Inputs!M4*4/Inputs!M37,"n/d") -> 8.7333333 | ... O7: =IFERROR(Inputs!O4*4/Inputs!O37,"n/d") -> 8.24 | P7: Same numerator on (open+close)/2 MW - the comps file's 'avg Q2 MW est.' variant (8.24 on 1,250 MW). Preferred trend line.
B8: tag | E8: n/d | F8: Estimated | G8: Estimated | H8: Estimated | I8: Estimated | J8: Derived | K8: Derived | L8: Derived | M8: Derived | N8: Derived | O8: Derived
A9: K02b | B9: Revenue per BILLING IT MW - average MW (= K02; CRWV has no separate billed series) | C9: $M/MW-yr | D9: D1 | E9: n/d | F9: =IFERROR(Inputs!F4*4/Inputs!F37,"n/d") -> 7.1033976 | G9: =IFERROR(Inputs!G4*4/Inputs!G37,"n/d") -> 8.8474629 | H9: =IFERROR(Inputs!H4*4/Inputs!H37,"n/d") -> 9.2965731 | I9: =IFERROR(Inputs!I4*4/Inputs!I37,"n/d") -> 9.2346564 | J9: =IFERROR(Inputs!J4*4/Inputs!J37,"n/d") -> 10.068021 | K9: =IFERROR(Inputs!K4*4/Inputs!K37,"n/d") -> 10.901465 | L9: =IFERROR(Inputs!L4*4/Inputs!L37,"n/d") -> 10.299442 | M9: =IFERROR(Inputs!M4*4/Inputs!M37,"n/d") -> 8.7333333 | ... O9: =IFERROR(Inputs!O4*4/Inputs!O37,"n/d") -> 8.24 | P9: ALIGN: K02b ≡ K02. CRWV discloses active power only (≈ billed/revenue-generating). No Capacity-style billing MW path. See Notes_Gaps B1 / Definitions D1. Cross-pack: comparison.xlsx K02b CRWV = K02; price_or_mw treats active≈billed.
B10: tag | E10: n/d | F10: Estimated | G10: Estimated | H10: Estimated | I10: Estimated | J10: Derived | K10: Derived | L10: Derived | M10: Derived | N10: Derived | O10: Derived
A11: K03 | B11: Revenue per contracted MW | C11: $M/MW-yr | D11: D1 | E11: n/d | F11: n/d | G11: n/d | H11: n/d | I11: =IFERROR(Inputs!I4*4/Inputs!I13,"n/d") -> 2.2997846 | J11: =IFERROR(Inputs!J4*4/Inputs!J13,"n/d") -> 2.45408 | K11: =IFERROR(Inputs!K4*4/Inputs!K13,"n/d") -> 2.2050691 | L11: =IFERROR(Inputs!L4*4/Inputs!L13,"n/d") -> 1.8823117 | M11: =IFERROR(Inputs!M4*4/Inputs!M13,"n/d") -> 2.0283871 | N11: =IFERROR(Inputs!N4*4/Inputs!N13,"n/d") -> 2.3748571 | O11: =IFERROR(Inputs!O4*4/Inputs!O13,"n/d") -> 2.7837838 | P11: Nebius KPIs 'Revenue per contracted MW'. Contracted = power under contract incl. not yet built.
B12: tag | E12: n/d | F12: n/d | G12: n/d | H12: n/d | I12: Derived | J12: Derived | K12: Derived | L12: Derived | M12: Derived | N12: Derived | O12: Derived
A13: K04 | B13: Contracted / active MW (build-out multiple) | C13: x | D13: D1 | E13: n/d | F13: n/d | G13: n/d | H13: n/d | I13: =IFERROR(Inputs!I13/Inputs!I12,"n/d") -> 3.6111111 | J13: =IFERROR(Inputs!J13/Inputs!J12,"n/d") -> 3.8095238 | K13: =IFERROR(Inputs!K13/Inputs!K12,"n/d") -> 4.6808511 | L13: =IFERROR(Inputs!L13/Inputs!L12,"n/d") -> 4.9152542 | M13: =IFERROR(Inputs!M13/Inputs!M12,"n/d") -> 3.6470588 | N13: =IFERROR(Inputs!N13/Inputs!N12,"n/d") -> 3.5 | O13: =IFERROR(Inputs!O13/Inputs!O12,"n/d") -> 2.4666667 | P13: Pipeline still to be energized relative to the live base.
B14: tag | E14: n/d | F14: n/d | G14: n/d | H14: n/d | I14: Derived | J14: Derived | K14: Derived | L14: Derived | M14: Derived | N14: Derived | O14: Derived
A15: K05 | B15: Adj. EBITDA per active MW (average MW) | C15: $M/MW-yr | D15: D1 | E15: n/d | F15: =IFERROR(Inputs!F5*4/Inputs!F37,"n/d") -> 3.9358494 | G15: =IFERROR(Inputs!G5*4/Inputs!G37,"n/d") -> 5.5908476 | H15: =IFERROR(Inputs!H5*4/Inputs!H37,"n/d") -> 6.0299622 | I15: =IFERROR(Inputs!I5*4/Inputs!I37,"n/d") -> 6.0060417 | J15: =IFERROR(Inputs!J5*4/Inputs!J37,"n/d") -> 6.2167282 | K15: =IFERROR(Inputs!K5*4/Inputs!K37,"n/d") -> 6.7700584 | L15: =IFERROR(Inputs!L5*4/Inputs!L37,"n/d") -> 6.3254642 | M15: =IFERROR(Inputs!M5*4/Inputs!M37,"n/d") -> 4.9888889 | ... O15: =IFERROR(Inputs!O5*4/Inputs!O37,"n/d") -> 4.832 | P15: Nebius KPIs 'Adj. EBITDA per energized MW'. CRWV leases all DCs, so EBITDA is after DC rent (Nebius 'leased cohort' analogue).
B16: tag | E16: n/d | F16: Estimated | G16: Estimated | H16: Estimated | I16: Estimated | J16: Derived | K16: Derived | L16: Derived | M16: Derived | N16: Derived | O16: Derived
A17: B. Revenue per GPU and implied utilization (GPU counts ESTIMATED after YE24)
A18: K06 | B18: Revenue per GPU ($K per GPU-year, avg GPUs) | C18: $K/GPU-yr | D18: D2 | E18: n/d | F18: =IFERROR(Inputs!F4*4000/Inputs!F41,"n/d") -> 9.722847 | G18: =IFERROR(Inputs!G4*4000/Inputs!G41,"n/d") -> 12.464899 | H18: =IFERROR(Inputs!H4*4000/Inputs!H41,"n/d") -> 13.261967 | I18: =IFERROR(Inputs!I4*4000/Inputs!I41,"n/d") -> 13.265535 | J18: =IFERROR(Inputs!J4*4000/Inputs!J41,"n/d") -> 14.753618 | K18: =IFERROR(Inputs!K4*4000/Inputs!K41,"n/d") -> 16.40399 | L18: =IFERROR(Inputs!L4*4000/Inputs!L41,"n/d") -> 15.986364 | M18: =IFERROR(Inputs!M4*4000/Inputs!M41,"n/d") -> 14.172376 | ... O18: =IFERROR(Inputs!O4*4000/Inputs!O41,"n/d") -> 14.506634 | P18: Nebius KPIs 'Revenue per GPU' = AI rev x 4000 / GPU_Avg. GPUs estimated (I11E). FY24 on reported counts: 1,915 / ((53k+250k)/2) = $12.6K/GPU-yr (Derived, lower-bound counts).
B19: tag | E19: n/d | F19: Estimated | G19: Estimated | H19: Estimated | I19: Estimated | J19: Estimated | K19: Estimated | L19: Estimated | M19: Estimated | N19: Estimated | O19: Estimated
A20: K07 | B20: Implied blended realized price ($/GPU-hr) | C20: $/GPU-hr | D20: D2 | E20: n/d | F20: =IFERROR(Inputs!F4*1000000/(Inputs!F41*Inputs!F29*24),"n/d") -> 1.1129633 | G20: =IFERROR(Inputs!G4*1000000/(Inputs!G41*Inputs!G29*24),"n/d") -> 1.4268428 | H20: =IFERROR(Inputs!H4*1000000/(Inputs!H41*Inputs!H29*24),"n/d") -> 1.5015814 | I20: =IFERROR(Inputs!I4*1000000/(Inputs!I41*Inputs!I29*24),"n/d") -> 1.5019854 | J20: =IFERROR(Inputs!J4*1000000/(Inputs!J41*Inputs!J29*24),"n/d") -> 1.7075947 | K20: =IFERROR(Inputs!K4*1000000/(Inputs!K41*Inputs!K29*24),"n/d") -> 1.8777461 | L20: =IFERROR(Inputs!L4*1000000/(Inputs!L41*Inputs!L29*24),"n/d") -> 1.8100503 | M20: =IFERROR(Inputs!M4*1000000/(Inputs!M41*Inputs!M29*24),"n/d") -> 1.6046622 | ... O20: =IFERROR(Inputs!O4*1000000/(Inputs!O41*Inputs!O29*24),"n/d") -> 1.6605579 | P20: Nebius KPIs 'Implied blended $/GPU-hr' = revenue / (avg GPUs x hours). Revenue includes storage/networking/software, so this is all-in revenue per GPU-hour.
B21: tag | E21: n/d | F21: Estimated | G21: Estimated | H21: Estimated | I21: Estimated | J21: Estimated | K21: Estimated | L21: Estimated | M21: Estimated | N21: Estimated | O21: Estimated
A22: K08 | B22: Fleet-weighted on-demand list price ($/GPU-hr) | C22: $/GPU-hr | D22: D3 | E22: n/d | F22: =Inputs!F42 -> 6.155 | G22: =Inputs!G42 -> 6.155 | H22: =Inputs!H42 -> 6.155 | I22: =Inputs!I42 -> 6.155 | J22: =Inputs!J42 -> 6.6518705 | K22: =Inputs!K42 -> 6.9866744 | L22: =Inputs!L42 -> 7.5935677 | M22: =Inputs!M42 -> 8.3851096 | ... O22: =Inputs!O42 -> 9.1956182 | P22: Nebius KPIs 'Fleet-weighted on-demand list price'. CRWV list from GPU Market agent's Wayback series (H100 $6.155, GB200 $10.50; flat over the period).
B23: tag | E23: n/d | F23: Estimated | G23: Estimated | H23: Estimated | I23: Estimated | J23: Estimated | K23: Estimated | L23: Estimated | M23: Estimated | N23: Estimated | O23: Estimated
A24: K09 | B24: Implied utilization (realized $/GPU-hr / weighted list) | C24: % | D24: D3 | E24: n/d | F24: =IFERROR(Inputs!F4*1000000/(Inputs!F41*Inputs!F29*24)/Inputs!F42*100,"n/d") -> 18.082263 | G24: =IFERROR(Inputs!G4*1000000/(Inputs!G41*Inputs!G29*24)/Inputs!G42*100,"n/d") -> 23.181849 | H24: =IFERROR(Inputs!H4*1000000/(Inputs!H41*Inputs!H29*24)/Inputs!H42*100,"n/d") -> 24.396124 | I24: =IFERROR(Inputs!I4*1000000/(Inputs!I41*Inputs!I29*24)/Inputs!I42*100,"n/d") -> 24.402688 | J24: =IFERROR(Inputs!J4*1000000/(Inputs!J41*Inputs!J29*24)/Inputs!J42*100,"n/d") -> 25.670896 | K24: =IFERROR(Inputs!K4*1000000/(Inputs!K41*Inputs!K29*24)/Inputs!K42*100,"n/d") -> 26.876107 | L24: =IFERROR(Inputs!L4*1000000/(Inputs!L41*Inputs!L29*24)/Inputs!L42*100,"n/d") -> 23.836626 | M24: =IFERROR(Inputs!M4*1000000/(Inputs!M41*Inputs!M29*24)/Inputs!M42*100,"n/d") -> 19.137045 | ... O24: =IFERROR(Inputs!O4*1000000/(Inputs!O41*Inputs!O29*24)/Inputs!O42*100,"n/d") -> 18.058143 | P24: Nebius KPIs row 'Implied utilization (blended $/hr / weighted list)' - 'mixes realized-price discount with utilization'. CRWV discloses contract discounts up to ~60% vs on-demand, so a low % is mainly discount, not idle GPUs. NOT a physical utilization rate.
B25: tag | E25: n/d | F25: Estimated | G25: Estimated | H25: Estimated | I25: Estimated | J25: Estimated | K25: Estimated | L25: Estimated | M25: Estimated | N25: Estimated | O25: Estimated
A26: C. Capex per MW ($M per MW)
A27: K10 | B27: Cash capex per new active MW (reported MW) | C27: $M/MW | D27: D4 | E27: n/d | F27: n/d | G27: n/d | H27: n/d | I27: n/d | J27: =IFERROR(Inputs!J7/Inputs!J38,"n/d") -> 23.456667 | K27: =IFERROR(Inputs!K7/Inputs!K38,"n/d") -> 49.06 | L27: =IFERROR(Inputs!L7/Inputs!L38,"n/d") -> 19.906667 | M27: =IFERROR(Inputs!M7/Inputs!M38,"n/d") -> 15.614615 | N27: =IFERROR(Inputs!N7/Inputs!N38,"n/d") -> 51.3 | O27: =IFERROR(Inputs!O7/Inputs!O38,"n/d") -> 12.844 | P27: Nebius KPIs 'Capex per new active MW' = Capex / MW_New. Timing mismatch: capex leads energization by 1-3 qtrs, so single quarters are noisy; see K12 (in-service basis) and K13 (trailing 4Q).
B28: tag | E28: n/d | F28: n/d | G28: n/d | H28: n/d | I28: n/d | J28: Derived | K28: Derived | L28: Derived | M28: Derived | N28: Derived | O28: Derived
A29: K11 | B29: Cash capex per new active MW (incl. estimated 2024 MW) | C29: $M/MW | D29: D4 | E29: n/d | F29: =IFERROR(Inputs!F7/Inputs!F39,"n/d") -> 24.026207 | G29: =IFERROR(Inputs!G7/Inputs!G39,"n/d") -> 30.995862 | H29: =IFERROR(Inputs!H7/Inputs!H39,"n/d") -> 16.761379 | I29: =IFERROR(Inputs!I7/Inputs!I39,"n/d") -> 48.244138 | J29: =IFERROR(Inputs!J7/Inputs!J39,"n/d") -> 23.456667 | K29: =IFERROR(Inputs!K7/Inputs!K39,"n/d") -> 49.06 | L29: =IFERROR(Inputs!L7/Inputs!L39,"n/d") -> 19.906667 | M29: =IFERROR(Inputs!M7/Inputs!M39,"n/d") -> 15.614615 | ... O29: =IFERROR(Inputs!O7/Inputs!O39,"n/d") -> 12.844 | P29: 2024 quarters use interpolated MW (+72.5 MW/qtr) -> Estimated. FY24 total: 8,702 / 290 MW = $30.0M/MW (Derived).
B30: tag | E30: n/d | F30: Estimated | G30: Estimated | H30: Estimated | I30: Estimated | J30: Derived | K30: Derived | L30: Derived | M30: Derived | N30: Derived | O30: Derived
A31: K12 | B31: In-service additions per new active MW (CRWV capex definition) | C31: $M/MW | D31: D4 | E31: n/d | F31: n/d | G31: n/d | H31: n/d | I31: n/d | J31: =IFERROR(Inputs!J44/Inputs!J38,"n/d") -> 30.96 | K31: =IFERROR(Inputs!K44/Inputs!K38,"n/d") -> 58.74244 | L31: =IFERROR(Inputs!L44/Inputs!L38,"n/d") -> 15.415267 | M31: =IFERROR(Inputs!M44/Inputs!M38,"n/d") -> 31.697335 | N31: =IFERROR(Inputs!N44/Inputs!N38,"n/d") -> 45.246667 | O31: =IFERROR(Inputs!O44/Inputs!O38,"n/d") -> 18.704 | P31: calc: delta(gross PP&E - CIP) / delta active MW. Better matched in time (assets placed in service vs MW going live). FY24: (9,679-1,344)/290 = $28.7M/MW.
B32: tag | E32: n/d | F32: n/d | G32: n/d | H32: n/d | I32: n/d | J32: Derived | K32: Derived | L32: Derived | M32: Derived | N32: Derived | O32: Derived
A33: K13 | B33: Trailing-4Q cash capex per trailing-4Q new active MW | C33: $M/MW | D33: D4 | E33: n/d | F33: n/d | G33: n/d | H33: n/d | I33: n/d | J33: n/d | K33: n/d | L33: n/d | M33: =IFERROR(SUM(Inputs!J7:M7)/(Inputs!M12-Inputs!I12),"n/d") -> 21.038776 | N33: =IFERROR(SUM(Inputs!K7:N7)/(Inputs!N12-Inputs!J12),"n/d") -> 28.614828 | O33: =IFERROR(SUM(Inputs!L7:O7)/(Inputs!O12-Inputs!K12),"n/d") -> 19.966602 | P33: Smooths timing. Uses reported MW only (needs MW 4 quarters back).
B34: tag | E34: n/d | F34: n/d | G34: n/d | H34: n/d | I34: n/d | J34: n/d | K34: n/d | L34: n/d | M34: Derived | N34: Derived | O34: Derived
A35: K14 | B35: Net PP&E per active MW (EoP) | C35: $M/MW | D35: D4 | E35: =IFERROR(Inputs!E10/Inputs!E12,"n/d") -> 49.771286 | F35: n/d | G35: n/d | H35: n/d | I35: =IFERROR(Inputs!I10/Inputs!I12,"n/d") -> 33.096594 | J35: =IFERROR(Inputs!J10/Inputs!J12,"n/d") -> 33.835695 | K35: =IFERROR(Inputs!K10/Inputs!K12,"n/d") -> 35.386191 | L35: =IFERROR(Inputs!L10/Inputs!L12,"n/d") -> 35.015561 | M35: =IFERROR(Inputs!M10/Inputs!M12,"n/d") -> 35.949412 | N35: =IFERROR(Inputs!N10/Inputs!N12,"n/d") -> 36.424 | O35: =IFERROR(Inputs!O10/Inputs!O12,"n/d") -> 31.157333 | P35: Cross-check used in Nebius capacity/gpu_mw_capex.xlsx Peers tab (CRWV $36M YE25, $31M Q2'26). Includes CIP for not-yet-live capacity -> overstates.
B36: tag | E36: Derived | F36: n/d | G36: n/d | H36: n/d | I36: Derived | J36: Derived | K36: Derived | L36: Derived | M36: Derived | N36: Derived | O36: Derived
A37: K15 | B37: Gross in-service PP&E per active MW (EoP) | C37: $M/MW | D37: D4 | E37: =IFERROR(Inputs!E43/Inputs!E12,"n/d") -> 19.201614 | F37: n/d | G37: n/d | H37: n/d | I37: =IFERROR(Inputs!I43/Inputs!I12,"n/d") -> 26.886497 | J37: =IFERROR(Inputs!J43/Inputs!J12,"n/d") -> 27.468426 | K37: =IFERROR(Inputs!K43/Inputs!K12,"n/d") -> 30.795449 | L37: =IFERROR(Inputs!L43/Inputs!L12,"n/d") -> 27.667276 | M37: =IFERROR(Inputs!M43/Inputs!M12,"n/d") -> 28.9 | N37: =IFERROR(Inputs!N43/Inputs!N12,"n/d") -> 31.352 | O37: =IFERROR(Inputs!O43/Inputs!O12,"n/d") -> 27.136 | P37: Nebius 'Nebius checks' row 'in-service servers+network per active MW' analogue (Nebius YE25 $18.4M/MW). CRWV leases DCs, so mostly GPU/network + DC fit-out.
B38: tag | E38: Derived | F38: n/d | G38: n/d | H38: n/d | I38: Derived | J38: Derived | K38: Derived | L38: Derived | M38: Derived | N38: Derived | O38: Derived
A39: D. D&A useful lives and depreciation yield
A40: K16 | B40: Useful life - technology equipment (GPUs/servers/network) | C40: years | D40: D5 | E40: n/d | F40: =6 -> 6 | G40: =6 -> 6 | H40: =6 -> 6 | I40: =6 -> 6 | J40: =6 -> 6 | K40: =6 -> 6 | L40: =6 -> 6 | M40: =6 -> 6 | ... O40: =6 -> 6 | P40: S-1 & 10-K FY25 Note 1: 'Technology equipment 6 years'. Last change: effective 1-Jan-2023 computing equipment 5 -> 6 yrs (FY23 expense -$20M). No change disclosed in any 10-Q through Q2'26. Nebius: 4 -> 5 yrs from 1-Jan-2026.
B41: tag | E41: n/d | F41: Reported | G41: Reported | H41: Reported | I41: Reported | J41: Reported | K41: Reported | L41: Reported | M41: Reported | N41: Reported | O41: Reported
A42: K17 | B42: Depreciation yield (D&A x4 / avg in-service gross PP&E) | C42: % | D42: D5 | E42: n/d | F42: n/d | G42: n/d | H42: n/d | I42: n/d | J42: =IFERROR(Inputs!J6*4/((Inputs!I43+Inputs!J43)/2)*100,"n/d") -> 16.723324 | K42: =IFERROR(Inputs!K6*4/((Inputs!J43+Inputs!K43)/2)*100,"n/d") -> 17.208369 | L42: =IFERROR(Inputs!L6*4/((Inputs!K43+Inputs!L43)/2)*100,"n/d") -> 16.377924 | M42: =IFERROR(Inputs!M6*4/((Inputs!L43+Inputs!M43)/2)*100,"n/d") -> 16.053338 | N42: =IFERROR(Inputs!N6*4/((Inputs!M43+Inputs!N43)/2)*100,"n/d") -> 16.410036 | O42: =IFERROR(Inputs!O6*4/((Inputs!N43+Inputs!O43)/2)*100,"n/d") -> 15.465749 | P42: Mirrors Nebius Capex_DA 'Depreciation yield - reported basis' (D&A / avg in-service gross PP&E). A 6-yr straight-line fleet would yield ~16.7% on tech equipment; lower values = lives >6 yrs on DC equipment (up to 12 yrs) and new assets placed in service late in quarter.
B43: tag | E43: n/d | F43: n/d | G43: n/d | H43: n/d | I43: n/d | J43: Derived | K43: Derived | L43: Derived | M43: Derived | N43: Derived | O43: Derived
A44: K18 | B44: Implied average depreciable life (1 / yield) | C44: years | D44: D5 | E44: n/d | F44: n/d | G44: n/d | H44: n/d | I44: n/d | J44: =IFERROR(100/J42,"n/d") -> 5.9796725 | K44: =IFERROR(100/K42,"n/d") -> 5.811126 | L44: =IFERROR(100/L42,"n/d") -> 6.1057799 | M44: =IFERROR(100/M42,"n/d") -> 6.2292342 | N44: =IFERROR(100/N42,"n/d") -> 6.0938317 | O44: =IFERROR(100/O42,"n/d") -> 6.4659009 | P44: Blended across tech equipment (6y), software (3-6y), DC equipment/leaseholds (up to 12y).
B45: tag | E45: n/d | F45: n/d | G45: n/d | H45: n/d | I45: n/d | J45: Derived | K45: Derived | L45: Derived | M45: Derived | N45: Derived | O45: Derived
A46: K19 | B46: D&A as % of revenue | C46: % | D46: D5 | E46: n/d | F46: =IFERROR(Inputs!F6/Inputs!F4*100,"n/d") -> 42.139238 | G46: =IFERROR(Inputs!G6/Inputs!G4*100,"n/d") -> 41.596374 | H46: =IFERROR(Inputs!H6/Inputs!H4*100,"n/d") -> 43.501655 | I46: =IFERROR(Inputs!I6/Inputs!I4*100,"n/d") -> 48.890063 | J46: =IFERROR(Inputs!J6/Inputs!J4*100,"n/d") -> 45.179864 | K46: =IFERROR(Inputs!K6/Inputs!K4*100,"n/d") -> 46.133372 | L46: =IFERROR(Inputs!L6/Inputs!L4*100,"n/d") -> 46.201443 | M46: =IFERROR(Inputs!M6/Inputs!M4*100,"n/d") -> 52.194656 | ... O46: =IFERROR(Inputs!O6/Inputs!O4*100,"n/d") -> 54.097087 | P46: Context row.
B47: tag | E47: n/d | F47: Derived | G47: Derived | H47: Derived | I47: Derived | J47: Derived | K47: Derived | L47: Derived | M47: Derived | N47: Derived | O47: Derived
A48: E. Backlog / RPO
A49: K20 | B49: RPO (ASC 606, EoP) | C49: $B | D49: D6 | E49: =Inputs!E17 -> 9.9 | F49: n/d | G49: n/d | H49: n/d | I49: =Inputs!I17 -> 15.1 | J49: =Inputs!J17 -> 14.7 | K49: =Inputs!K17 -> 30.1 | L49: =Inputs!L17 -> 50 | M49: =Inputs!M17 -> 60.7 | N49: =Inputs!N17 -> 98.8 | O49: =Inputs!O17 -> 103.7 | P49: Nebius Hist 'Remaining performance obligations' (same ASC 606 basis).
B50: tag | E50: Reported | F50: n/d | G50: n/d | H50: n/d | I50: Reported | J50: Reported | K50: Reported | L50: Reported | M50: Reported | N50: Reported | O50: Reported
A51: K21 | B51: Revenue backlog (company metric, EoP) | C51: $B | D51: D6 | E51: =Inputs!E18 -> 9.9 | F51: n/d | G51: n/d | H51: n/d | I51: =Inputs!I18 -> 15.1 | J51: =Inputs!J18 -> 25.9 | K51: =Inputs!K18 -> 30.1 | L51: =Inputs!L18 -> 55.6 | M51: =Inputs!M18 -> 66.8 | N51: =Inputs!N18 -> 99.4 | O51: =Inputs!O18 -> 104.2 | P51: calc: RPO + other committed amounts subject to delivery (e.g., Q1'25 OpenAI $11.2B before contract effectiveness). Not GAAP.
B52: tag | E52: Reported | F52: n/d | G52: n/d | H52: n/d | I52: Reported | J52: Reported | K52: Reported | L52: Reported | M52: Reported | N52: Reported | O52: Reported
A53: K22 | B53: RPO % recognized within 24 months | C53: % | D53: D6 | E53: n/d | F53: n/d | G53: n/d | H53: n/d | I53: =Inputs!I19 -> 54 | J53: =Inputs!J19 -> 58 | K53: =Inputs!K19 -> 50 | L53: =Inputs!L19 -> 42 | M53: =Inputs!M19 -> 43 | N53: =Inputs!N19 -> 36 | O53: =Inputs!O19 -> 41 | P53: Nebius tracks the same split (36% <24m at 6/30/26).
B54: tag | E54: n/d | F54: n/d | G54: n/d | H54: n/d | I54: Reported | J54: Reported | K54: Reported | L54: Reported | M54: Reported | N54: Reported | O54: Reported
A55: K23 | B55: RPO / annualized quarterly revenue | C55: years | D55: D6 | E55: n/d | F55: n/d | G55: n/d | H55: n/d | I55: =IFERROR(Inputs!I17*1000/(Inputs!I4*4),"n/d") -> 5.0506402 | J55: =IFERROR(Inputs!J17*1000/(Inputs!J4*4),"n/d") -> 3.7437655 | K55: =IFERROR(Inputs!K17*1000/(Inputs!K4*4),"n/d") -> 6.2047118 | L55: =IFERROR(Inputs!L17*1000/(Inputs!L4*4),"n/d") -> 9.1596833 | M55: =IFERROR(Inputs!M17*1000/(Inputs!M4*4),"n/d") -> 9.6533079 | N55: =IFERROR(Inputs!N17*1000/(Inputs!N4*4),"n/d") -> 11.886429 | O55: =IFERROR(Inputs!O17*1000/(Inputs!O4*4),"n/d") -> 10.067961 | P55: Coverage of current run-rate.
B56: tag | E56: n/d | F56: n/d | G56: n/d | H56: n/d | I56: Derived | J56: Derived | K56: Derived | L56: Derived | M56: Derived | N56: Derived | O56: Derived
A57: F. Customer concentration (% of quarter revenue; customers <10% not disclosed)
A58: K24 | B58: Largest customer % of revenue | C58: % | D58: D7 | E58: n/d | F58: =Inputs!F20 -> 33 | G58: =Inputs!G20 -> 59 | H58: =Inputs!H20 -> 65 | I58: =Inputs!I20 -> 68.2 | J58: =Inputs!J20 -> 72 | K58: =Inputs!K20 -> 71 | L58: =Inputs!L20 -> 67 | M58: =Inputs!M20 -> 60.2 | ... O58: =Inputs!O20 -> 36 | P58: Note 2 'customers >=10% of revenue'. Q4 = FY less 9M (Derived, +/-2pp rounding).
B59: tag | E59: n/d | F59: Reported | G59: Reported | H59: Reported | I59: Derived | J59: Reported | K59: Reported | L59: Reported | M59: Derived | N59: Reported | O59: Reported
A60: K25 | B60: 2nd-largest customer % | C60: % | D60: D7 | E60: n/d | F60: =Inputs!F21 -> 32 | G60: =Inputs!G21 -> 20 | H60: =Inputs!H21 -> 12 | I60: =Inputs!I21 -> 10.3 | J60: n/d | K60: n/d | L60: n/d | M60: n/d | N60: =Inputs!N21 -> 20 | O60: =Inputs!O21 -> 26 | P60: n/d = below 10% threshold (not disclosed).
B61: tag | E61: n/d | F61: Reported | G61: Reported | H61: Reported | I61: Derived | J61: n/d | K61: n/d | L61: n/d | M61: n/d | N61: Reported | O61: Reported
A62: K26 | B62: Top-N >=10% customers combined % | C62: % | D62: D7 | E62: n/d | F62: =SUM(Inputs!F20,Inputs!F21,Inputs!F22) -> 83 | G62: =SUM(Inputs!G20,Inputs!G21,Inputs!G22) -> 79 | H62: =SUM(Inputs!H20,Inputs!H21,Inputs!H22) -> 77 | I62: =SUM(Inputs!I20,Inputs!I21,Inputs!I22) -> 78.5 | J62: =SUM(Inputs!J20,Inputs!J21,Inputs!J22) -> 72 | K62: =SUM(Inputs!K20,Inputs!K21,Inputs!K22) -> 71 | L62: =SUM(Inputs!L20,Inputs!L21,Inputs!L22) -> 67 | M62: =SUM(Inputs!M20,Inputs!M21,Inputs!M22) -> 60.2 | ... O62: =SUM(Inputs!O20,Inputs!O21,Inputs!O22) -> 72 | P62: Sum of disclosed >=10% customers (Q1'24 top-3, Q2'26 top-3). FY24 top-2 = 77% (10-K FY25).
B63: tag | E63: n/d | F63: Reported | G63: Reported | H63: Reported | I63: Derived | J63: Reported | K63: Reported | L63: Reported | M63: Derived | N63: Reported | O63: Reported
A64: K27 | B64: Number of customers >=10% of revenue | C64: # | D64: D7 | E64: n/d | F64: =Inputs!F23 -> 3 | G64: =Inputs!G23 -> 2 | H64: =Inputs!H23 -> 2 | I64: =Inputs!I23 -> 2 | J64: =Inputs!J23 -> 1 | K64: =Inputs!K23 -> 1 | L64: =Inputs!L23 -> 1 | M64: =Inputs!M23 -> 1 | ... O64: =Inputs!O23 -> 3
B65: tag | E65: n/d | F65: Reported | G65: Reported | H65: Reported | I65: Derived | J65: Reported | K65: Reported | L65: Reported | M65: Derived | N65: Reported | O65: Reported
A66: G. Funding cost (% p.a.)
A67: K28 | B67: Weighted effective cost of debt (principal-weighted, EoP) - all facilities | C67: % | D67: D8 | E67: =Debt_Facilities!D29 -> 14.668981 | F67: n/d | G67: n/d | H67: n/d | I67: =Debt_Facilities!F29 -> 11.980004 | J67: =Debt_Facilities!H29 -> 11.766482 | K67: =Debt_Facilities!J29 -> 11.088981 | L67: =Debt_Facilities!L29 -> 10.280255 | M67: =Debt_Facilities!N29 -> 9.0757344 | N67: =Debt_Facilities!P29 -> 9.0647739 | O67: =Debt_Facilities!R29 -> 8.4134342 | P67: Mirrors comps.csv 'Wtd effective cost of debt (%) = principal-weighted effective rates, Note 10 debt table' (CRWV 8.41 at 6/30/26). Rates rounded to whole % in filings -> +/-0.5pp.
B68: tag | E68: Derived | F68: n/d | G68: n/d | H68: n/d | I68: Derived | J68: Derived | K68: Derived | L68: Derived | M68: Derived | N68: Derived | O68: Derived
A69: K29 | B69: of which DDTL - weighted eff. rate | C69: % | D69: D8 | E69: =Debt_Facilities!D30 -> 15 | F69: n/d | G69: n/d | H69: n/d | I69: =Debt_Facilities!F30 -> 12.374584 | J69: =Debt_Facilities!H30 -> 12.207867 | K69: =Debt_Facilities!J30 -> 12.058418 | L69: =Debt_Facilities!L30 -> 10.811266 | M69: =Debt_Facilities!N30 -> 10.484335 | N69: =Debt_Facilities!P30 -> 10.265161 | O69: =Debt_Facilities!R30 -> 9.6234699 | P69: n/d where facility type not outstanding.
B70: tag | E70: Derived | F70: n/d | G70: n/d | H70: n/d | I70: Derived | J70: Derived | K70: Derived | L70: Derived | M70: Derived | N70: Derived | O70: Derived
A71: K30 | B71: of which Senior notes - weighted eff. rate | C71: % | D71: D8 | E71: =Debt_Facilities!D31 -> 10 | F71: n/d | G71: n/d | H71: n/d | I71: =Debt_Facilities!F31 -> n/d | J71: =Debt_Facilities!H31 -> n/d | K71: =Debt_Facilities!J31 -> 10 | L71: =Debt_Facilities!L31 -> 10 | M71: =Debt_Facilities!N31 -> 10 | N71: =Debt_Facilities!P31 -> 10 | O71: =Debt_Facilities!R31 -> 9.772759 | P71: n/d where facility type not outstanding.
B72: tag | E72: Derived | F72: n/d | G72: n/d | H72: n/d | I72: Derived | J72: Derived | K72: Derived | L72: Derived | M72: Derived | N72: Derived | O72: Derived
A73: K31 | B73: of which Converts - weighted eff. rate | C73: % | D73: D8 | E73: =Debt_Facilities!D32 -> 17 | F73: n/d | G73: n/d | H73: n/d | I73: =Debt_Facilities!F32 -> n/d | J73: =Debt_Facilities!H32 -> n/d | K73: =Debt_Facilities!J32 -> n/d | L73: =Debt_Facilities!L32 -> n/d | M73: =Debt_Facilities!N32 -> 2.3047896 | N73: =Debt_Facilities!P32 -> 2.3098949 | O73: =Debt_Facilities!R32 -> 2 | P73: n/d where facility type not outstanding.
B74: tag | E74: Derived | F74: n/d | G74: n/d | H74: n/d | I74: Derived | J74: Derived | K74: Derived | L74: Derived | M74: Derived | N74: Derived | O74: Derived
A75: K32 | B75: of which OEM / vendor financing - weighted eff. rate | C75: % | D75: D8 | E75: =Debt_Facilities!D33 -> n/d | F75: n/d | G75: n/d | H75: n/d | I75: =Debt_Facilities!F33 -> 10 | J75: =Debt_Facilities!H33 -> 9.5 | K75: =Debt_Facilities!J33 -> 9.5 | L75: =Debt_Facilities!L33 -> 9 | M75: =Debt_Facilities!N33 -> 10 | N75: =Debt_Facilities!P33 -> 10 | O75: =Debt_Facilities!R33 -> 10.654253 | P75: n/d where facility type not outstanding.
B76: tag | E76: Derived | F76: n/d | G76: n/d | H76: n/d | I76: Derived | J76: Derived | K76: Derived | L76: Derived | M76: Derived | N76: Derived | O76: Derived
A77: K33 | B77: of which Revolver - weighted eff. rate | C77: % | D77: D8 | E77: =Debt_Facilities!D34 -> n/d | F77: n/d | G77: n/d | H77: n/d | I77: =Debt_Facilities!F34 -> n/d | J77: =Debt_Facilities!H34 -> 6 | K77: =Debt_Facilities!J34 -> 7 | L77: =Debt_Facilities!L34 -> 7 | M77: =Debt_Facilities!N34 -> 6 | N77: =Debt_Facilities!P34 -> 6 | O77: =Debt_Facilities!R34 -> n/d | P77: n/d where facility type not outstanding.
B78: tag | E78: Derived | F78: n/d | G78: n/d | H78: n/d | I78: Derived | J78: Derived | K78: Derived | L78: Derived | M78: Derived | N78: Derived | O78: Derived
A79: K34 | B79: of which Other term loans - weighted eff. rate | C79: % | D79: D8 | E79: =Debt_Facilities!D35 -> n/d | F79: n/d | G79: n/d | H79: n/d | I79: =Debt_Facilities!F35 -> 12 | J79: =Debt_Facilities!H35 -> 12 | K79: =Debt_Facilities!J35 -> 12 | L79: =Debt_Facilities!L35 -> 12 | M79: =Debt_Facilities!N35 -> 12 | N79: =Debt_Facilities!P35 -> 12 | O79: =Debt_Facilities!R35 -> 12 | P79: n/d where facility type not outstanding.
B80: tag | E80: Derived | F80: n/d | G80: n/d | H80: n/d | I80: Derived | J80: Derived | K80: Derived | L80: Derived | M80: Derived | N80: Derived | O80: Derived
A81: K35 | B81: DDTL (secured asset-level) share of principal | C81: % | D81: D8 | E81: =Debt_Facilities!D36 -> 88.416764 | F81: n/d | G81: n/d | H81: n/d | I81: =Debt_Facilities!F36 -> 72.898933 | J81: =Debt_Facilities!H36 -> 71.342636 | K81: =Debt_Facilities!J36 -> 60.300551 | L81: =Debt_Facilities!L36 -> 58.463473 | M81: =Debt_Facilities!N36 -> 44.742077 | N81: =Debt_Facilities!P36 -> 47.01181 | O81: =Debt_Facilities!R36 -> 38.375854
B82: tag | E82: Derived | F82: n/d | G82: n/d | H82: n/d | I82: Derived | J82: Derived | K82: Derived | L82: Derived | M82: Derived | N82: Derived | O82: Derived
A83: K36 | B83: Implied cash cost: contractual interest x4 / avg principal | C83: % | D83: D8 | E83: n/d | F83: n/d | G83: n/d | H83: n/d | I83: n/d | J83: =IFERROR(Inputs!J24*4/Inputs!J45*100,"n/d") -> 11.057134 | K83: =IFERROR(Inputs!K24*4/Inputs!K45*100,"n/d") -> 10.0228 | L83: =IFERROR(Inputs!L24*4/Inputs!L45*100,"n/d") -> 10.218202 | M83: =IFERROR(Inputs!M24*4/Inputs!M45*100,"n/d") -> 9.2190265 | N83: =IFERROR(Inputs!N24*4/Inputs!N45*100,"n/d") -> 8.2627662 | O83: =IFERROR(Inputs!O24*4/Inputs!O45*100,"n/d") -> 7.8023064 | P83: Before capitalization; excludes discount amortization. FY24: 474.8 / avg(1,555; 8,033) = 9.9% (Derived; average understates mid-year balances).
B84: tag | E84: n/d | F84: n/d | G84: n/d | H84: n/d | I84: n/d | J84: Derived | K84: Derived | L84: Derived | M84: Derived | N84: Derived | O84: Derived
A85: K37 | B85: Company-reported weighted average interest rate | C85: % | D85: D8 | E85: =Inputs!E27 -> 14.9 | F85: n/d | G85: n/d | H85: n/d | I85: =Inputs!I27 -> 12.2 | J85: n/d | K85: n/d | L85: n/d | M85: =Inputs!M27 -> 9 | N85: n/d | O85: =Inputs!O27 -> 8.3 | P85: Sep-26 convert deck slide 27 (OEM assumed 10%). Q2'26 PF 7.8%.
B86: tag | E86: Reported | F86: n/d | G86: n/d | H86: n/d | I86: Reported | J86: n/d | K86: n/d | L86: n/d | M86: Reported | N86: n/d | O86: Reported
A87: K38 | B87: Total debt principal (EoP) | C87: $B | D87: D8 | E87: =IFERROR(Inputs!E26/1000,"n/d") -> 1.555049 | F87: n/d | G87: n/d | H87: n/d | I87: =IFERROR(Inputs!I26/1000,"n/d") -> 8.033477 | J87: =IFERROR(Inputs!J26/1000,"n/d") -> 8.807921 | K87: =IFERROR(Inputs!K26/1000,"n/d") -> 11.171485 | L87: =IFERROR(Inputs!L26/1000,"n/d") -> 14.205268 | M87: =IFERROR(Inputs!M26/1000,"n/d") -> 21.615 | N87: =IFERROR(Inputs!N26/1000,"n/d") -> 25.149 | O87: =IFERROR(Inputs!O26/1000,"n/d") -> 35.551 | P87: Excl. leases (operating lease liabilities $10.1B at 3/31/26 per Q1'26 10-Q risk factors).
B88: tag | E88: Reported | F88: n/d | G88: n/d | H88: n/d | I88: Reported | J88: Reported | K88: Reported | L88: Reported | M88: Reported | N88: Reported | O88: Reported
A89: K39 | B89: Debt principal / RPO | C89: x | D89: D8 | E89: =IFERROR(Inputs!E26/1000/Inputs!E17,"n/d") -> 0.15707566 | F89: n/d | G89: n/d | H89: n/d | I89: =IFERROR(Inputs!I26/1000/Inputs!I17,"n/d") -> 0.53201834 | J89: =IFERROR(Inputs!J26/1000/Inputs!J17,"n/d") -> 0.5991783 | K89: =IFERROR(Inputs!K26/1000/Inputs!K17,"n/d") -> 0.37114568 | L89: =IFERROR(Inputs!L26/1000/Inputs!L17,"n/d") -> 0.28410536 | M89: =IFERROR(Inputs!M26/1000/Inputs!M17,"n/d") -> 0.35609555 | N89: =IFERROR(Inputs!N26/1000/Inputs!N17,"n/d") -> 0.25454453 | O89: =IFERROR(Inputs!O26/1000/Inputs!O17,"n/d") -> 0.34282546 | P89: Company shows debt / backlog 0.2x-0.5x.
B90: tag | E90: Derived | F90: n/d | G90: n/d | H90: n/d | I90: Derived | J90: Derived | K90: Derived | L90: Derived | M90: Derived | N90: Derived | O90: Derived
A91: K40 | B91: Capitalized interest % of contractual interest | C91: % | D91: D8 | E91: n/d | F91: =IFERROR(Inputs!F25/Inputs!F24*100,"n/d") -> 49.79264 | G91: =IFERROR(Inputs!G25/Inputs!G24*100,"n/d") -> 40.5908 | H91: =IFERROR(Inputs!H25/Inputs!H24*100,"n/d") -> 26.977839 | I91: =IFERROR(Inputs!I25/Inputs!I24*100,"n/d") -> 28.381171 | J91: =IFERROR(Inputs!J25/Inputs!J24*100,"n/d") -> 5.6243878 | K91: =IFERROR(Inputs!K25/Inputs!K24*100,"n/d") -> 9.26284 | L91: =IFERROR(Inputs!L25/Inputs!L24*100,"n/d") -> 19.055259 | M91: =IFERROR(Inputs!M25/Inputs!M24*100,"n/d") -> 20.339402 | ... O91: =IFERROR(Inputs!O25/Inputs!O24*100,"n/d") -> 13.344595 | P91: Context: share of interest deferred into PP&E (later depreciated).
B92: tag | E92: n/d | F92: Reported | G92: Reported | H92: Reported | I92: Derived | J92: Reported | K92: Reported | L92: Reported | M92: Derived | N92: Reported | O92: Reported

Sheet Inputs
A1: Inputs - CoreWeave (CRWV). Raw reported figures (blue), derived (black), estimated (orange), n/d (grey). Per-cell source detail on Sources tab.
A3: ID | B3: Item | C3: Unit | D3: Tag mix | E3: Q4'23* | F3: Q1'24 | G3: Q2'24 | H3: Q3'24 | I3: Q4'24 | J3: Q1'25 | K3: Q2'25 | L3: Q3'25 | M3: Q4'25 | N3: Q1'26 | O3: Q2'26 | P3: Source summary / notes
A4: I01 | B4: Revenue | C4: $M | D4: Reported | E4: n/d | F4: 188.684 | G4: 395.371 | H4: 583.941 | I4: 747.43 | J4: 981.632 | K4: 1212.788 | L4: 1364.676 | M4: 1572 | N4: 2078 | O4: 2575 | P4: 424B4 prospectus (IPO), filed 2025-03-31; Q1'25 earnings PR (8-K Ex.99.1, 2025-05-14); Q2'25 earnings PR (8-K Ex.99.1, 2025-08-12); Q3'25 earnings PR (8-K Ex.99.1, 2025-11-10); Q4'25 earnings PR (8-K Ex.99.1, 2026-02-26); Q1'26 earnings PR (8-K Ex.99.1, 2026-05-07); Q2'26 earnings PR (8-K Ex.99.1, 2026-08-11)
A5: I02 | B5: Adjusted EBITDA (company non-GAAP) | C5: $M | D5: Reported | E5: n/d | F5: 104.546 | G5: 249.841 | H5: 378.757 | I5: 486.114 | J5: 606.131 | K5: 753.169 | L5: 838.124 | M5: 898 | N5: 1157 | O5: 1510 | P5: 424B4 prospectus (IPO), filed 2025-03-31; Q1'25 earnings PR (8-K Ex.99.1, 2025-05-14); Q2'25 earnings PR (8-K Ex.99.1, 2025-08-12); Q3'25 earnings PR (8-K Ex.99.1, 2025-11-10); Q4'25 earnings PR (8-K Ex.99.1, 2026-02-26); Q1'26 earnings PR (8-K Ex.99.1, 2026-05-07); Q2'26 earnings PR (8-K Ex.99.1, 2026-08-11)
A6: I03 | B6: Depreciation & amortization (total, cash-flow basis) | C6: $M | D6: Derived/Reported | E6: n/d | F6: 79.51 | G6: 164.46 | H6: 254.024 | I6: 365.419 | J6: 443.5 | K6: 559.5 | L6: 630.5 | M6: 820.5 | N6: 1147 | O6: 1393 | P6: 424B4 prospectus (IPO), filed 2025-03-31; SEC companyfacts XBRL, CIK 0001769628 (local copy comps_raw/cf_0001769628.json) | NOTE: Nebius depreciation-yield uses PP&E depreciation; CRWV PP&E depreciation is disclosed rounded to $0.1B in 2026, so total D&A (incl. small intangible amortization) is used.
A7: I04 | B7: Cash capex (purchases of property & equipment) | C7: $M | D7: Derived/Reported | E7: n/d | F7: 1741.9 | G7: 2247.2 | H7: 1215.2 | I7: 3497.7 | J7: 1407.4 | K7: 2453 | L7: 2388.8 | M7: 4059.8 | N7: 7695 | O7: 6422 | P7: SEC companyfacts XBRL, CIK 0001769628 (local copy comps_raw/cf_0001769628.json) | NOTE: Mirrors Nebius Hist 'Capex (purchases of PP&E + intangibles, cash)'. CRWV also finances GPUs via OEM/vendor financing, so cash capex understates economic capex in some quarters.
A8: I05 | B8: Gross property & equipment (EoP) | C8: $M | D8: Reported | E8: 3600.786 | F8: n/d | G8: n/d | H8: n/d | I8: 12880.005 | J8: 15610.549 | K8: 18585.117 | L8: 23233.759 | M8: 33941 | N8: 40933 | O8: 52622 | P8: 424B4 prospectus (IPO), filed 2025-03-31; 10-Q Q1'25, filed 2025-05-15; 10-Q Q2'25, filed 2025-08-13; 10-Q Q3'25, filed 2025-11-13; 10-K FY25, filed 2026-03-02; 10-Q Q1'26, filed 2026-05-08; 10-Q Q2'26, filed 2026-08-12
A9: I06 | B9: Construction in progress (EoP; not yet in service) | C9: $M | D9: Reported | E9: 2256.673 | F9: n/d | G9: n/d | H9: n/d | I9: 3200.866 | J9: 4073.81 | K9: 4111.256 | L9: 6910.066 | M9: 9376 | N9: 9581 | O9: 11918 | P9: 424B4 prospectus (IPO), filed 2025-03-31; 10-Q Q1'25, filed 2025-05-15; 10-Q Q2'25, filed 2025-08-13; 10-Q Q3'25, filed 2025-11-13; 10-K FY25, filed 2026-03-02; 10-Q Q1'26, filed 2026-05-08; 10-Q Q2'26, filed 2026-08-12
A10: I07 | B10: Property & equipment, net (EoP) | C10: $M | D10: Reported | E10: 3483.99 | F10: n/d | G10: n/d | H10: n/d | I10: 11914.774 | J10: 14210.992 | K10: 16631.51 | L10: 20659.181 | M10: 30557 | N10: 36424 | O10: 46736 | P10: 424B4 prospectus (IPO), filed 2025-03-31; 10-Q Q1'25, filed 2025-05-15; 10-Q Q2'25, filed 2025-08-13; 10-Q Q3'25, filed 2025-11-13; 10-K FY25, filed 2026-03-02; 10-Q Q1'26, filed 2026-05-08; 10-Q Q2'26, filed 2026-08-12
A11: I08 | B11: Technology equipment, gross (EoP) | C11: $M | D11: Reported | E11: 1298.127 | F11: n/d | G11: n/d | H11: n/d | I11: 9146.575 | J11: 10746.445 | K11: 13170.295 | L11: 14628.79 | M11: 20903 | N11: 26627 | O11: 33823 | P11: 424B4 prospectus (IPO), filed 2025-03-31; 10-Q Q1'25, filed 2025-05-15; 10-Q Q2'25, filed 2025-08-13; 10-Q Q3'25, filed 2025-11-13; 10-K FY25, filed 2026-03-02; 10-Q Q1'26, filed 2026-05-08; 10-Q Q2'26, filed 2026-08-12
A12: I09 | B12: Active power, reported (EoP) | C12: MW | D12: Reported | E12: 70 | F12: n/d | G12: n/d | H12: n/d | I12: 360 | J12: 420 | K12: 470 | L12: 590 | M12: 850 | N12: 1000 | O12: 1500 | P12: 424B4 prospectus (IPO), filed 2025-03-31; Q1'25 earnings PR (8-K Ex.99.1, 2025-05-14); Q2'25 earnings PR (8-K Ex.99.1, 2025-08-12); Q3'25 earnings PR (8-K Ex.99.1, 2025-11-10); Q4'25 earnings PR (8-K Ex.99.1, 2026-02-26); Q1'26 earnings PR (8-K Ex.99.1, 2026-05-07); Q2'26 earnings PR (8-K Ex.99.1, 2026-08-11) | NOTE: MW basis (IT vs gross) never stated by CRWV. YE24 cross-check: >250k GPUs / ~360 MW = ~694 GPUs/MW, close to Nebius Hopper base 713/IT-MW (vs 548/gross-MW) -> CRWV 'active power' most consistent with IT (critical) load. Several values are 'more than'/'approximately' -> treat as lower bounds/rounded. | POLISH: active power ≈ billed/revenue-generating for K02b≡K02 (no separate billing MW).
A13: I10 | B13: Contracted power, reported (EoP) | C13: MW | D13: Reported | E13: n/d | F13: n/d | G13: n/d | H13: n/d | I13: 1300 | J13: 1600 | K13: 2200 | L13: 2900 | M13: 3100 | N13: 3500 | O13: 3700 | P13: 424B4 prospectus (IPO), filed 2025-03-31; Q1'25 earnings PR (8-K Ex.99.1, 2025-05-14); Q2'25 earnings PR (8-K Ex.99.1, 2025-08-12); Q3'25 earnings PR (8-K Ex.99.1, 2025-11-10); Q4'25 earnings PR (8-K Ex.99.1, 2026-02-26); Q1'26 earnings PR (8-K Ex.99.1, 2026-05-07); Q2'26 earnings PR (8-K Ex.99.1, 2026-08-11)
A14: I11 | B14: GPUs deployed, reported (EoP) | C14: GPUs | D14: Reported | E14: 53000 | F14: n/d | G14: n/d | H14: n/d | I14: 250000 | J14: n/d | K14: n/d | L14: n/d | M14: n/d | N14: n/d | O14: n/d | P14: 424B4 prospectus (IPO), filed 2025-03-31 | NOTE: CRWV has not disclosed a fleet GPU count since the S-1 (checked 10-Qs Q1'25-Q2'26, 10-K FY25, all earnings PRs, Sep-26 convert deck).
A15: I12 | B15: Hopper-class on-demand list price (H100 SXM 8-GPU instance / 8) | C15: $/GPU-hr | D15: Derived/Estimated | E15: n/d | F15: 6.155 | G15: 6.155 | H15: 6.155 | I15: 6.155 | J15: 6.155 | K15: 6.155 | L15: 6.155 | M15: 6.155 | N15: 6.155 | O15: 6.155 | P15: Nebius workspace: /workspace/nebius/parts/price_history_quarterly.csv (CoreWeave on-demand list, GPU Market agent; Wayback snapshots) | NOTE: H200 list $6.305 is ~2% higher; A100 ($2.70) and older GPUs are cheaper, so using H100 for all pre-Blackwell GPUs overstates fleet list price.
A16: I13 | B16: Blackwell on-demand list price (GB200 NVL72 4-GPU instance / 4) | C16: $/GPU-hr | D16: Derived | E16: n/d | F16: n/d | G16: n/d | H16: n/d | I16: n/d | J16: 10.5 | K16: 10.5 | L16: 10.5 | M16: 10.5 | N16: 10.5 | O16: 10.5 | P16: Nebius workspace: /workspace/nebius/parts/price_history_quarterly.csv (CoreWeave on-demand list, GPU Market agent; Wayback snapshots) | NOTE: B200 lists at $8.60 (2026); GB300 is contact-sales (no public list). GB200 used for all Blackwell-era additions.
A17: I14 | B17: RPO (ASC 606 remaining performance obligations, EoP) | C17: $B | D17: Reported | E17: 9.9 | F17: n/d | G17: n/d | H17: n/d | I17: 15.1 | J17: 14.7 | K17: 30.1 | L17: 50 | M17: 60.7 | N17: 98.8 | O17: 103.7 | P17: 424B4 prospectus (IPO), filed 2025-03-31; 10-Q Q1'25, filed 2025-05-15; 10-Q Q2'25, filed 2025-08-13; 10-Q Q3'25, filed 2025-11-13; 10-K FY25, filed 2026-03-02; 10-Q Q1'26, filed 2026-05-08; 10-Q Q2'26, filed 2026-08-12
A18: I15 | B18: Revenue backlog (company metric: RPO + other committed amounts) | C18: $B | D18: Reported | E18: 9.9 | F18: n/d | G18: n/d | H18: n/d | I18: 15.1 | J18: 25.9 | K18: 30.1 | L18: 55.6 | M18: 66.8 | N18: 99.4 | O18: 104.2 | P18: Convertible-notes investor presentation (8-K Ex., 2026-09-17); Q1'25 earnings PR (8-K Ex.99.1, 2025-05-14); Q2'25 earnings PR (8-K Ex.99.1, 2025-08-12); Q3'25 earnings PR (8-K Ex.99.1, 2025-11-10); Q4'25 earnings PR (8-K Ex.99.1, 2026-02-26); Q1'26 earnings PR (8-K Ex.99.1, 2026-05-07); Q2'26 earnings PR (8-K Ex.99.1, 2026-08-11)
A19: I16 | B19: RPO % expected to be recognized within 24 months | C19: % | D19: Reported | E19: n/d | F19: n/d | G19: n/d | H19: n/d | I19: 54 | J19: 58 | K19: 50 | L19: 42 | M19: 43 | N19: 36 | O19: 41 | P19: 424B4 prospectus (IPO), filed 2025-03-31; 10-Q Q1'25, filed 2025-05-15; 10-Q Q2'25, filed 2025-08-13; 10-Q Q3'25, filed 2025-11-13; 10-K FY25, filed 2026-03-02; 10-Q Q1'26, filed 2026-05-08; 10-Q Q2'26, filed 2026-08-12
A20: I17 | B20: Largest customer, % of quarter revenue | C20: % | D20: Derived/Reported | E20: n/d | F20: 33 | G20: 59 | H20: 65 | I20: 68.2 | J20: 72 | K20: 71 | L20: 67 | M20: 60.2 | N20: 45 | O20: 36 | P20: 10-Q Q1'25, filed 2025-05-15; 10-Q Q2'25, filed 2025-08-13; 10-Q Q3'25, filed 2025-11-13; 424B4 prospectus (IPO), filed 2025-03-31; 10-K FY25, filed 2026-03-02; 10-Q Q1'26, filed 2026-05-08; 10-Q Q2'26, filed 2026-08-12 | NOTE: Customer letters are per-filing labels; Customer A is historically Microsoft (S-1/10-K name Microsoft as FY23-FY25 top customer). Q1'24: A 33% vs C 32%.
A21: I18 | B21: 2nd-largest customer, % of quarter revenue (<10% = not disclosed) | C21: % | D21: Derived/Reported | E21: n/d | F21: 32 | G21: 20 | H21: 12 | I21: 10.3 | J21: n/d | K21: n/d | L21: n/d | M21: n/d | N21: 20 | O21: 26 | P21: 10-Q Q1'25, filed 2025-05-15; 10-Q Q2'25, filed 2025-08-13; 10-Q Q3'25, filed 2025-11-13; 424B4 prospectus (IPO), filed 2025-03-31; 10-K FY25, filed 2026-03-02; 10-Q Q1'26, filed 2026-05-08; 10-Q Q2'26, filed 2026-08-12
A22: I19 | B22: 3rd-largest customer, % of quarter revenue (<10% = not disclosed) | C22: % | D22: Reported | E22: n/d | F22: 18 | G22: n/d | H22: n/d | I22: n/d | J22: n/d | K22: n/d | L22: n/d | M22: n/d | N22: n/d | O22: 10 | P22: 10-Q Q1'25, filed 2025-05-15; 10-Q Q2'26, filed 2026-08-12
A23: I20 | B23: Customers >=10% of quarter revenue (count) | C23: # | D23: Derived/Reported | E23: n/d | F23: 3 | G23: 2 | H23: 2 | I23: 2 | J23: 1 | K23: 1 | L23: 1 | M23: 1 | N23: 2 | O23: 3 | P23: 10-Q Q1'25, filed 2025-05-15; 10-Q Q2'25, filed 2025-08-13; 10-Q Q3'25, filed 2025-11-13; 424B4 prospectus (IPO), filed 2025-03-31; 10-K FY25, filed 2026-03-02; 10-Q Q1'26, filed 2026-05-08; 10-Q Q2'26, filed 2026-08-12
A24: I21 | B24: Contractual interest expense (before capitalization) | C24: $M | D24: Derived/Reported | E24: n/d | F24: 64.622 | G24: 100.237 | H24: 130.003 | I24: 179.982 | J24: 232.772 | K24: 250.312 | L24: 324.131 | M24: 412.785 | N24: 483 | O24: 592 | P24: 10-Q Q1'25, filed 2025-05-15; 10-Q Q2'25, filed 2025-08-13; 10-Q Q3'25, filed 2025-11-13; 424B4 prospectus (IPO), filed 2025-03-31; 10-K FY25, filed 2026-03-02; 10-Q Q1'26, filed 2026-05-08; 10-Q Q2'26, filed 2026-08-12
A25: I22 | B25: Capitalized interest | C25: $M | D25: Derived/Reported | E25: n/d | F25: 32.177 | G25: 40.687 | H25: 35.072 | I25: 51.081 | J25: 13.092 | K25: 23.186 | L25: 61.764 | M25: 83.958 | N25: 97 | O25: 79 | P25: 10-Q Q1'25, filed 2025-05-15; 10-Q Q2'25, filed 2025-08-13; 10-Q Q3'25, filed 2025-11-13; 424B4 prospectus (IPO), filed 2025-03-31; 10-K FY25, filed 2026-03-02; 10-Q Q1'26, filed 2026-05-08; 10-Q Q2'26, filed 2026-08-12
A26: I23 | B26: Total debt principal (EoP; excl. leases) | C26: $M | D26: Reported | E26: 1555.049 | F26: n/d | G26: n/d | H26: n/d | I26: 8033.477 | J26: 8807.921 | K26: 11171.485 | L26: 14205.268 | M26: 21615 | N26: 25149 | O26: 35551 | P26: 424B4 prospectus (IPO), filed 2025-03-31; 10-Q Q1'25, filed 2025-05-15; 10-Q Q2'25, filed 2025-08-13; 10-Q Q3'25, filed 2025-11-13; 10-K FY25, filed 2026-03-02; 10-Q Q1'26, filed 2026-05-08; 10-Q Q2'26, filed 2026-08-12
A27: I24 | B27: Company-reported weighted average interest rate on debt | C27: % | D27: Reported | E27: 14.9 | F27: n/d | G27: n/d | H27: n/d | I27: 12.2 | J27: n/d | K27: n/d | L27: n/d | M27: 9 | N27: n/d | O27: 8.3 | P27: Convertible-notes investor presentation (8-K Ex., 2026-09-17) | NOTE: Company method: effective rates x EoP principal, OEM/software financing assumed 10%.
A28: I25 | B28: Company-definition capex (additions to PP&E + finance-lease assets - change in CIP), reported | C28: $M | D28: Reported | E28: n/d | F28: n/d | G28: n/d | H28: n/d | I28: n/d | J28: 1858 | K28: n/d | L28: n/d | M28: n/d | N28: 6786 | O28: 9400 | P28: Q1'26 earnings presentation (IR site PDF); Convertible-notes investor presentation (8-K Ex., 2026-09-17)
A29: I26 | B29: Days in quarter | C29: days | D29: Reported | E29: n/d | F29: 91 | G29: 91 | H29: 92 | I29: 92 | J29: 90 | K29: 91 | L29: 92 | M29: 92 | N29: 90 | O29: 91
A30: I27 | B30: Active data centers (EoP) | C30: # | D30: Reported | E30: 10 | F30: n/d | G30: n/d | H30: n/d | I30: 32 | J30: n/d | K30: n/d | L30: n/d | M30: 43 | N30: 49 | O30: 51 | P30: 424B4 prospectus (IPO), filed 2025-03-31; 10-K FY25, filed 2026-03-02; Q1'26 earnings presentation (IR site PDF); Convertible-notes investor presentation (8-K Ex., 2026-09-17)
A32: Derived & estimated input rows (formulas)
A33: P01 | B33: GB200 NVL72 GPUs per IT-MW (base) | C33: GPUs/MW | D33: Estimated | E33: 538 | P33: Nebius workspace: /workspace/nebius/capacity/gpu_mw_capex.xlsx (GPUsPerMW base IT-MW rows) / gpu_mw_capex.md s.1 - GPUsPerMW base IT-MW row (gpu_mw_capex.md s.1: 487/538/571)
A34: P02 | B34: GB300 NVL72 GPUs per IT-MW (base) | C34: GPUs/MW | D34: Estimated | E34: 491 | P34: Nebius workspace: /workspace/nebius/capacity/gpu_mw_capex.xlsx (GPUsPerMW base IT-MW rows) / gpu_mw_capex.md s.1 - GPUsPerMW base IT-MW row (453/491/519)
A35: P03 | B35: Hopper HGX GPUs per IT-MW (base; cross-check only) | C35: GPUs/MW | D35: Estimated | E35: 713 | P35: Nebius workspace: /workspace/nebius/capacity/gpu_mw_capex.xlsx (GPUsPerMW base IT-MW rows) / gpu_mw_capex.md s.1 - GPUsPerMW base IT-MW row (665/713/813)
A36: I09E | B36: Active power incl. estimates (EoP) - 2024 interim interpolated | C36: MW | D36: Reported/Estimated | E36: =E12 -> 70 | F36: =$E$12+($I$12-$E$12)*1/4 -> 142.5 | G36: =$E$12+($I$12-$E$12)*2/4 -> 215 | H36: =$E$12+($I$12-$E$12)*3/4 -> 287.5 | I36: =I12 -> 360 | J36: =J12 -> 420 | K36: =K12 -> 470 | L36: =L12 -> 590 | M36: =M12 -> 850 | N36: =N12 -> 1000 | O36: =O12 -> 1500 | P36: ESTIMATED for Q1-Q3'24: straight-line between ~70 MW (YE23) and ~360 MW (YE24). CRWV did not disclose interim 2024 MW. Other quarters = reported.
A37: I09A | B37: Average active power in quarter ((open+close)/2) | C37: MW | D37: Derived/Estimated | E37: n/d | F37: =(E36+F36)/2 -> 106.25 | G37: =(F36+G36)/2 -> 178.75 | H37: =(G36+H36)/2 -> 251.25 | I37: =(H36+I36)/2 -> 323.75 | J37: =(I36+J36)/2 -> 390 | K37: =(J36+K36)/2 -> 445 | L37: =(K36+L36)/2 -> 530 | M37: =(L36+M36)/2 -> 720 | ... O37: =(N36+O36)/2 -> 1250 | P37: Average of opening/closing active MW (I09E). Q1'24-Q4'24 use the interpolated estimates -> Estimated.
A38: I09N | B38: New active MW added in quarter (reported MW only) | C38: MW | D38: Derived | E38: n/d | F38: n/d | G38: n/d | H38: n/d | I38: n/d | J38: =J12-I12 -> 60 | K38: =K12-J12 -> 50 | L38: =L12-K12 -> 120 | M38: =M12-L12 -> 260 | N38: =N12-M12 -> 150 | O38: =O12-N12 -> 500 | P38: calc: closing - opening reported active MW. Q4'24 n/d (Q3'24 MW not disclosed). Lower-bound wording ('more than') makes single-quarter deltas noisy (+/-10-50 MW).
A39: I09NE | B39: New active MW added in quarter (incl. estimated 2024 MW) | C39: MW | D39: Derived/Estimated | E39: n/d | F39: =F36-E36 -> 72.5 | G39: =G36-F36 -> 72.5 | H39: =H36-G36 -> 72.5 | I39: =I36-H36 -> 72.5 | J39: =J36-I36 -> 60 | K39: =K36-J36 -> 50 | L39: =L36-K36 -> 120 | M39: =M36-L36 -> 260 | ... O39: =O36-N36 -> 500 | P39: Uses I09E; 2024 quarters each +72.5 MW by construction (Estimated).
A40: I11E | B40: GPUs incl. estimates (EoP) | C40: GPUs | D40: Reported/Estimated | E40: =E14 -> 53000 | F40: =$E$14+($I$14-$E$14)*1/4 -> 102250 | G40: =$E$14+($I$14-$E$14)*2/4 -> 151500 | H40: =$E$14+($I$14-$E$14)*3/4 -> 200750 | I40: =I14 -> 250000 | J40: =$I$14+(J12-$I$12)*$E$33 -> 282280 | K40: =$I$14+(K12-$I$12)*$E$33 -> 309180 | L40: =$I$14+(L12-$I$12)*$E$33 -> 373740 | M40: =$I$14+(M12-$I$12)*$E$33 -> 513620 | N40: =$M$40+(N12-$M$12)*$E$34 -> 587270 | O40: =$M$40+(O12-$M$12)*$E$34 -> 832770 | P40: ESTIMATED except YE23/YE24 (reported lower bounds). 2024 interim: linear 53k->250k. 2025: 250k + (active MW - 360) x GB200 base 538 GPUs/IT-MW. 2026: YE25 est + (MW - 850) x GB300 base 491. Mirrors Nebius capacity method 'GPUs = MW x GPUs/MW (gpu_mw_capex.xlsx base rows)'. Assumes no retirements and all post-YE24 MW is Blackwell.
A41: I11A | B41: Average GPUs in quarter ((open+close)/2) | C41: GPUs | D41: Estimated | E41: n/d | F41: =(E40+F40)/2 -> 77625 | G41: =(F40+G40)/2 -> 126875 | H41: =(G40+H40)/2 -> 176125 | I41: =(H40+I40)/2 -> 225375 | J41: =(I40+J40)/2 -> 266140 | K41: =(J40+K40)/2 -> 295730 | L41: =(K40+L40)/2 -> 341460 | M41: =(L40+M40)/2 -> 443680 | ... O41: =(N40+O40)/2 -> 710020 | P41: Average of I11E.
A42: I12W | B42: Fleet-weighted on-demand list price (EoP GPU weights) | C42: $/GPU-hr | D42: Estimated | E42: n/d | F42: =F15 -> 6.155 | G42: =G15 -> 6.155 | H42: =H15 -> 6.155 | I42: =I15 -> 6.155 | J42: =(J15*$I$14+J16*(J40-$I$14))/J40 -> 6.6518705 | K42: =(K15*$I$14+K16*(K40-$I$14))/K40 -> 6.9866744 | L42: =(L15*$I$14+L16*(L40-$I$14))/L40 -> 7.5935677 | M42: =(M15*$I$14+M16*(M40-$I$14))/M40 -> 8.3851096 | N42: =(N15*$I$14+N16*(N40-$I$14))/N40 -> 8.6503397 | O42: =(O15*$I$14+O16*(O40-$I$14))/O40 -> 9.1956182 | P42: Mirrors Nebius KPIs row 'Fleet-weighted on-demand list price' (GPU_End_H x P_OD_H + GPU_End_B x P_OD_B ...)/GPUs. Legacy 250k GPUs (YE24) priced at Hopper H100 list; all later GPUs at GB200 list.
A43: I05S | B43: In-service gross PP&E (gross - CIP, EoP) | C43: $M | D43: Derived | E43: =E8-E9 -> 1344.113 | F43: n/d | G43: n/d | H43: n/d | I43: =I8-I9 -> 9679.139 | J43: =J8-J9 -> 11536.739 | K43: =K8-K9 -> 14473.861 | L43: =L8-L9 -> 16323.693 | M43: =M8-M9 -> 24565 | N43: =N8-N9 -> 31352 | O43: =O8-O9 -> 40704 | P43: Mirrors Nebius Capex_DA 'In-service gross PP&E' = gross PP&E - assets not yet in use.
A44: I25D | B44: Company-definition capex, derived = change in in-service gross PP&E | C44: $M | D44: Derived | E44: n/d | F44: n/d | G44: n/d | H44: n/d | I44: n/d | J44: =J43-I43 -> 1857.6 | K44: =K43-J43 -> 2937.122 | L44: =L43-K43 -> 1849.832 | M44: =M43-L43 -> 8241.307 | N44: =N43-M43 -> 6787 | O44: =O43-N43 -> 9352 | P44: calc: delta(gross PP&E) - delta(CIP). Matches CRWV's own capex definition (Q1'26 deck: 'Increase in total gross P&E less change in CIP'): Q1'25 1,858 / Q1'26 6,786 / Q2'26 ~9.4B reported. Also = Nebius 'Transfer into service'.
A45: I23A | B45: Average debt principal ((open+close)/2) | C45: $M | D45: Derived | E45: n/d | F45: n/d | G45: n/d | H45: n/d | I45: n/d | J45: =(I26+J26)/2 -> 8420.699 | K45: =(J26+K26)/2 -> 9989.703 | L45: =(K26+L26)/2 -> 12688.377 | M45: =(L26+M26)/2 -> 17910.134 | N45: =(M26+N26)/2 -> 23382 | O45: =(N26+O26)/2 -> 30350 | P45: Q1'24-Q4'24 n/d (no 2024 interim debt tables).
A46: I09B | B46: Billed / billing MW alias — EQUALS I09E (documentation only; CRWV has no separate billed series) | C46: MW | D46: Align | E46: =E36 -> 70 | F46: =F36 -> 142.5 | G46: =G36 -> 215 | H46: =H36 -> 287.5 | I46: =I36 -> 360 | J46: =J36 -> 420 | K46: =K36 -> 470 | L46: =L36 -> 590 | ... O46: =O36 -> 1500 | P46: POLISH 2026-10-05: alias for cross-pack K02b alignment. Do not treat as a new estimate. Notes_Gaps B1.

Sheet Debt_Facilities
A1: Debt by facility - CoreWeave (CRWV). Principal ($M) and effective interest rate (%) as printed in each quarter-end debt table (Note 10 / S-1 Note 10). Excludes operating/finance leases.
A2: Effective rates are as printed in each filing's Note 10 debt table (rounded to whole %). Ranges are entered at midpoint: OEM 'Mar-25/Jun-25 9-10%' -> 9.5; 'Sep-25 8-10%' -> 9; S-1 Dec-24 OEM '9%-11%' -> 10. Dec-25 OEM recourse/non-recourse combined (10-K shows a single 10% line of $4,165M).
A4: Facility | B4: Category | C4: Dec-23 principal | D4: Dec-23 eff. rate % | E4: Dec-24 principal | F4: Dec-24 eff. rate % | G4: Mar-25 principal | H4: Mar-25 eff. rate % | I4: Jun-25 principal | J4: Jun-25 eff. rate % | K4: Sep-25 principal | L4: Sep-25 eff. rate % | M4: Dec-25 principal | N4: Dec-25 eff. rate % | O4: Mar-26 principal | P4: Mar-26 eff. rate % | Q4: Jun-26 principal | R4: Jun-26 eff. rate %
A5: 2021 Convertible Senior Secured Notes | B5: Converts | C5: 55.125 | D5: 17
A6: 2022 Senior Secured Notes | B6: Senior notes | C6: 125 | D6: 10
A7: DDTL 1.0 Facility | B7: DDTL | C7: 1374.924 | D7: 15 | E7: 2012.5 | F7: 15 | G7: 1897.5 | H7: 15 | I7: 1782.5 | J7: 15 | K7: 1667.5 | L7: 15 | M7: 1553 | N7: 15 | O7: 1438 | P7: 15 | Q7: 1300 | R7: 15
A8: DDTL 2.0 Facility | B8: DDTL | E8: 3843.819 | F8: 11 | G8: 4386.303 | H8: 11 | I8: 4953.967 | J8: 11 | K8: 5037.372 | L8: 10 | M8: 5037 | N8: 10 | O8: 4425 | P8: 11 | Q8: 3190 | R8: 11
A9: DDTL 2.1 Facility | B9: DDTL | K9: 1241.325 | L9: 9 | M9: 2741 | N9: 9 | O9: 3000 | P9: 9 | Q9: 3000 | R9: 9
A10: DDTL 3.0 Facility | B10: DDTL | K10: 358.696 | L10: 9 | M10: 340 | N10: 9 | O10: 1700 | P10: 9 | Q10: 2215 | R10: 9
A11: DDTL 4.0 Facility (non-recourse; IG) | B11: DDTL | O11: 1260 | P11: 7 | Q11: 2837 | R11: 7
A12: DDTL 5.0 Facility | B12: DDTL | Q12: 1101 | R12: 9
A13: 2024 Term Loan Facility | B13: Other term loans | E13: 1000 | F13: 12 | G13: 1000 | H13: 12
A14: Magnetar Loan | B14: Other term loans | G14: 248.917 | H14: 12 | I14: 256.63 | J14: 12 | K14: 264.666 | L14: 12 | M14: 273 | N14: 12 | O14: 281 | P14: 12 | Q14: 189 | R14: 12
A15: 2030 Senior Notes (9.25%) | B15: Senior notes | I15: 2000 | J15: 10 | K15: 2000 | L15: 10 | M15: 2000 | N15: 10 | O15: 2000 | P15: 10 | Q15: 2000 | R15: 10
A16: 2031 9.00% Senior Notes | B16: Senior notes | K16: 1750 | L16: 10 | M16: 1750 | N16: 10 | O16: 1750 | P16: 10 | Q16: 1750 | R16: 10
A17: 2031 9.75% Senior Notes | B17: Senior notes | Q17: 2750 | R17: 10
A18: 2032 9.625% Senior Notes | B18: Senior notes | Q18: 1250 | R18: 10
A19: 2032 EUR Senior Notes (8.50%) | B19: Senior notes | Q19: 2279 | R19: 9
A20: 2031 Convertible Senior Notes (1.75%) | B20: Converts | M20: 2588 | N20: 2 | O20: 2588 | P20: 2 | Q20: 2588 | R20: 2
A21: 2032 Convertible Senior Notes (1.75%) | B21: Converts | Q21: 4000 | R21: 2
A22: Convertible Promissory Notes | B22: Converts | M22: 168 | N22: 7 | O22: 171 | P22: 7
A23: Revolving Credit Facility | B23: Revolver | G23: 50 | H23: 6 | I23: 450 | J23: 7 | K23: 700 | L23: 7 | M23: 1000 | N23: 6 | O23: 1500 | P23: 6 | Q23: 0 | R23: 7
A24: OEM & software-license financing (recourse) | B24: OEM / vendor financing | E24: 1177.158 | F24: 10 | G24: 1225.201 | H24: 9.5 | I24: 1728.388 | J24: 9.5 | K24: 1185.709 | L24: 9 | M24: 4165 | N24: 10 | O24: 5036 | P24: 10 | Q24: 4220 | R24: 11
A25: OEM & software-license financing (non-recourse) | B25: OEM / vendor financing | Q25: 882 | R25: 9
A27: Total principal | C27: =SUM(C5:C25) -> 1555.049 | E27: =SUM(E5:E25) -> 8033.477 | G27: =SUM(G5:G25) -> 8807.921 | I27: =SUM(I5:I25) -> 11171.485 | K27: =SUM(K5:K25) -> 14205.268 | M27: =SUM(M5:M25) -> 21615 | O27: =SUM(O5:O25) -> 25149 | Q27: =SUM(Q5:Q25) -> 35551
A28: Check vs reported total principal (Inputs I23) | C28: =C27-Inputs!E26 -> 0 | E28: =E27-Inputs!I26 -> 0 | G28: =G27-Inputs!J26 -> 0 | I28: =I27-Inputs!K26 -> 0 | K28: =K27-Inputs!L26 -> 0 | M28: =M27-Inputs!M26 -> 0 | O28: =O27-Inputs!N26 -> 0 | Q28: =Q27-Inputs!O26 -> 0
A29: WEIGHTED EFFECTIVE COST OF DEBT (principal-weighted, all facilities) | D29: =IFERROR(SUMPRODUCT(C5:C25,D5:D25)/SUM(C5:C25),"n/d") -> 14.668981 | F29: =IFERROR(SUMPRODUCT(E5:E25,F5:F25)/SUM(E5:E25),"n/d") -> 11.980004 | H29: =IFERROR(SUMPRODUCT(G5:G25,H5:H25)/SUM(G5:G25),"n/d") -> 11.766482 | J29: =IFERROR(SUMPRODUCT(I5:I25,J5:J25)/SUM(I5:I25),"n/d") -> 11.088981 | L29: =IFERROR(SUMPRODUCT(K5:K25,L5:L25)/SUM(K5:K25),"n/d") -> 10.280255 | N29: =IFERROR(SUMPRODUCT(M5:M25,N5:N25)/SUM(M5:M25),"n/d") -> 9.0757344 | P29: =IFERROR(SUMPRODUCT(O5:O25,P5:P25)/SUM(O5:O25),"n/d") -> 9.0647739 | R29: =IFERROR(SUMPRODUCT(Q5:Q25,R5:R25)/SUM(Q5:Q25),"n/d") -> 8.4134342
A30: DDTL: principal / weighted eff. rate | C30: =SUMIF($B$5:$B$25,"DDTL",C5:C25) -> 1374.924 | D30: =IFERROR(SUMPRODUCT(($B$5:$B$25="DDTL")*C5:C25*D5:D25)/C30,"n/d") -> 15 | E30: =SUMIF($B$5:$B$25,"DDTL",E5:E25) -> 5856.319 | F30: =IFERROR(SUMPRODUCT(($B$5:$B$25="DDTL")*E5:E25*F5:F25)/E30,"n/d") -> 12.374584 | G30: =SUMIF($B$5:$B$25,"DDTL",G5:G25) -> 6283.803 | H30: =IFERROR(SUMPRODUCT(($B$5:$B$25="DDTL")*G5:G25*H5:H25)/G30,"n/d") -> 12.207867 | I30: =SUMIF($B$5:$B$25,"DDTL",I5:I25) -> 6736.467 | J30: =IFERROR(SUMPRODUCT(($B$5:$B$25="DDTL")*I5:I25*J5:J25)/I30,"n/d") -> 12.058418 | K30: =SUMIF($B$5:$B$25,"DDTL",K5:K25) -> 8304.893 | L30: =IFERROR(SUMPRODUCT(($B$5:$B$25="DDTL")*K5:K25*L5:L25)/K30,"n/d") -> 10.811266 | M30: =SUMIF($B$5:$B$25,"DDTL",M5:M25) -> 9671 | N30: =IFERROR(SUMPRODUCT(($B$5:$B$25="DDTL")*M5:M25*N5:N25)/M30,"n/d") -> 10.484335 | O30: =SUMIF($B$5:$B$25,"DDTL",O5:O25) -> 11823 | P30: =IFERROR(SUMPRODUCT(($B$5:$B$25="DDTL")*O5:O25*P5:P25)/O30,"n/d") -> 10.265161 | Q30: =SUMIF($B$5:$B$25,"DDTL",Q5:Q25) -> 13643 | R30: =IFERROR(SUMPRODUCT(($B$5:$B$25="DDTL")*Q5:Q25*R5:R25)/Q30,"n/d") -> 9.6234699
A31: Senior notes: principal / weighted eff. rate | C31: =SUMIF($B$5:$B$25,"Senior notes",C5:C25) -> 125 | D31: =IFERROR(SUMPRODUCT(($B$5:$B$25="Senior notes")*C5:C25*D5:D25)/C31,"n/d") -> 10 | E31: =SUMIF($B$5:$B$25,"Senior notes",E5:E25) -> 0 | F31: =IFERROR(SUMPRODUCT(($B$5:$B$25="Senior notes")*E5:E25*F5:F25)/E31,"n/d") -> n/d | G31: =SUMIF($B$5:$B$25,"Senior notes",G5:G25) -> 0 | H31: =IFERROR(SUMPRODUCT(($B$5:$B$25="Senior notes")*G5:G25*H5:H25)/G31,"n/d") -> n/d | I31: =SUMIF($B$5:$B$25,"Senior notes",I5:I25) -> 2000 | J31: =IFERROR(SUMPRODUCT(($B$5:$B$25="Senior notes")*I5:I25*J5:J25)/I31,"n/d") -> 10 | K31: =SUMIF($B$5:$B$25,"Senior notes",K5:K25) -> 3750 | L31: =IFERROR(SUMPRODUCT(($B$5:$B$25="Senior notes")*K5:K25*L5:L25)/K31,"n/d") -> 10 | M31: =SUMIF($B$5:$B$25,"Senior notes",M5:M25) -> 3750 | N31: =IFERROR(SUMPRODUCT(($B$5:$B$25="Senior notes")*M5:M25*N5:N25)/M31,"n/d") -> 10 | O31: =SUMIF($B$5:$B$25,"Senior notes",O5:O25) -> 3750 | P31: =IFERROR(SUMPRODUCT(($B$5:$B$25="Senior notes")*O5:O25*P5:P25)/O31,"n/d") -> 10 | Q31: =SUMIF($B$5:$B$25,"Senior notes",Q5:Q25) -> 10029 | R31: =IFERROR(SUMPRODUCT(($B$5:$B$25="Senior notes")*Q5:Q25*R5:R25)/Q31,"n/d") -> 9.772759
A32: Converts: principal / weighted eff. rate | C32: =SUMIF($B$5:$B$25,"Converts",C5:C25) -> 55.125 | D32: =IFERROR(SUMPRODUCT(($B$5:$B$25="Converts")*C5:C25*D5:D25)/C32,"n/d") -> 17 | E32: =SUMIF($B$5:$B$25,"Converts",E5:E25) -> 0 | F32: =IFERROR(SUMPRODUCT(($B$5:$B$25="Converts")*E5:E25*F5:F25)/E32,"n/d") -> n/d | G32: =SUMIF($B$5:$B$25,"Converts",G5:G25) -> 0 | H32: =IFERROR(SUMPRODUCT(($B$5:$B$25="Converts")*G5:G25*H5:H25)/G32,"n/d") -> n/d | I32: =SUMIF($B$5:$B$25,"Converts",I5:I25) -> 0 | J32: =IFERROR(SUMPRODUCT(($B$5:$B$25="Converts")*I5:I25*J5:J25)/I32,"n/d") -> n/d | K32: =SUMIF($B$5:$B$25,"Converts",K5:K25) -> 0 | L32: =IFERROR(SUMPRODUCT(($B$5:$B$25="Converts")*K5:K25*L5:L25)/K32,"n/d") -> n/d | M32: =SUMIF($B$5:$B$25,"Converts",M5:M25) -> 2756 | N32: =IFERROR(SUMPRODUCT(($B$5:$B$25="Converts")*M5:M25*N5:N25)/M32,"n/d") -> 2.3047896 | O32: =SUMIF($B$5:$B$25,"Converts",O5:O25) -> 2759 | P32: =IFERROR(SUMPRODUCT(($B$5:$B$25="Converts")*O5:O25*P5:P25)/O32,"n/d") -> 2.3098949 | Q32: =SUMIF($B$5:$B$25,"Converts",Q5:Q25) -> 6588 | R32: =IFERROR(SUMPRODUCT(($B$5:$B$25="Converts")*Q5:Q25*R5:R25)/Q32,"n/d") -> 2
A33: OEM / vendor financing: principal / weighted eff. rate | C33: =SUMIF($B$5:$B$25,"OEM / vendor financing",C5:C25) -> 0 | D33: =IFERROR(SUMPRODUCT(($B$5:$B$25="OEM / vendor financing")*C5:C25*D5:D25)/C33,"n/d") -> n/d | E33: =SUMIF($B$5:$B$25,"OEM / vendor financing",E5:E25) -> 1177.158 | F33: =IFERROR(SUMPRODUCT(($B$5:$B$25="OEM / vendor financing")*E5:E25*F5:F25)/E33,"n/d") -> 10 | G33: =SUMIF($B$5:$B$25,"OEM / vendor financing",G5:G25) -> 1225.201 | H33: =IFERROR(SUMPRODUCT(($B$5:$B$25="OEM / vendor financing")*G5:G25*H5:H25)/G33,"n/d") -> 9.5 | I33: =SUMIF($B$5:$B$25,"OEM / vendor financing",I5:I25) -> 1728.388 | J33: =IFERROR(SUMPRODUCT(($B$5:$B$25="OEM / vendor financing")*I5:I25*J5:J25)/I33,"n/d") -> 9.5 | K33: =SUMIF($B$5:$B$25,"OEM / vendor financing",K5:K25) -> 1185.709 | L33: =IFERROR(SUMPRODUCT(($B$5:$B$25="OEM / vendor financing")*K5:K25*L5:L25)/K33,"n/d") -> 9 | M33: =SUMIF($B$5:$B$25,"OEM / vendor financing",M5:M25) -> 4165 | N33: =IFERROR(SUMPRODUCT(($B$5:$B$25="OEM / vendor financing")*M5:M25*N5:N25)/M33,"n/d") -> 10 | O33: =SUMIF($B$5:$B$25,"OEM / vendor financing",O5:O25) -> 5036 | P33: =IFERROR(SUMPRODUCT(($B$5:$B$25="OEM / vendor financing")*O5:O25*P5:P25)/O33,"n/d") -> 10 | Q33: =SUMIF($B$5:$B$25,"OEM / vendor financing",Q5:Q25) -> 5102 | R33: =IFERROR(SUMPRODUCT(($B$5:$B$25="OEM / vendor financing")*Q5:Q25*R5:R25)/Q33,"n/d") -> 10.654253
A34: Revolver: principal / weighted eff. rate | C34: =SUMIF($B$5:$B$25,"Revolver",C5:C25) -> 0 | D34: =IFERROR(SUMPRODUCT(($B$5:$B$25="Revolver")*C5:C25*D5:D25)/C34,"n/d") -> n/d | E34: =SUMIF($B$5:$B$25,"Revolver",E5:E25) -> 0 | F34: =IFERROR(SUMPRODUCT(($B$5:$B$25="Revolver")*E5:E25*F5:F25)/E34,"n/d") -> n/d | G34: =SUMIF($B$5:$B$25,"Revolver",G5:G25) -> 50 | H34: =IFERROR(SUMPRODUCT(($B$5:$B$25="Revolver")*G5:G25*H5:H25)/G34,"n/d") -> 6 | I34: =SUMIF($B$5:$B$25,"Revolver",I5:I25) -> 450 | J34: =IFERROR(SUMPRODUCT(($B$5:$B$25="Revolver")*I5:I25*J5:J25)/I34,"n/d") -> 7 | K34: =SUMIF($B$5:$B$25,"Revolver",K5:K25) -> 700 | L34: =IFERROR(SUMPRODUCT(($B$5:$B$25="Revolver")*K5:K25*L5:L25)/K34,"n/d") -> 7 | M34: =SUMIF($B$5:$B$25,"Revolver",M5:M25) -> 1000 | N34: =IFERROR(SUMPRODUCT(($B$5:$B$25="Revolver")*M5:M25*N5:N25)/M34,"n/d") -> 6 | O34: =SUMIF($B$5:$B$25,"Revolver",O5:O25) -> 1500 | P34: =IFERROR(SUMPRODUCT(($B$5:$B$25="Revolver")*O5:O25*P5:P25)/O34,"n/d") -> 6 | Q34: =SUMIF($B$5:$B$25,"Revolver",Q5:Q25) -> 0 | R34: =IFERROR(SUMPRODUCT(($B$5:$B$25="Revolver")*Q5:Q25*R5:R25)/Q34,"n/d") -> n/d
A35: Other term loans: principal / weighted eff. rate | C35: =SUMIF($B$5:$B$25,"Other term loans",C5:C25) -> 0 | D35: =IFERROR(SUMPRODUCT(($B$5:$B$25="Other term loans")*C5:C25*D5:D25)/C35,"n/d") -> n/d | E35: =SUMIF($B$5:$B$25,"Other term loans",E5:E25) -> 1000 | F35: =IFERROR(SUMPRODUCT(($B$5:$B$25="Other term loans")*E5:E25*F5:F25)/E35,"n/d") -> 12 | G35: =SUMIF($B$5:$B$25,"Other term loans",G5:G25) -> 1248.917 | H35: =IFERROR(SUMPRODUCT(($B$5:$B$25="Other term loans")*G5:G25*H5:H25)/G35,"n/d") -> 12 | I35: =SUMIF($B$5:$B$25,"Other term loans",I5:I25) -> 256.63 | J35: =IFERROR(SUMPRODUCT(($B$5:$B$25="Other term loans")*I5:I25*J5:J25)/I35,"n/d") -> 12 | K35: =SUMIF($B$5:$B$25,"Other term loans",K5:K25) -> 264.666 | L35: =IFERROR(SUMPRODUCT(($B$5:$B$25="Other term loans")*K5:K25*L5:L25)/K35,"n/d") -> 12 | M35: =SUMIF($B$5:$B$25,"Other term loans",M5:M25) -> 273 | N35: =IFERROR(SUMPRODUCT(($B$5:$B$25="Other term loans")*M5:M25*N5:N25)/M35,"n/d") -> 12 | O35: =SUMIF($B$5:$B$25,"Other term loans",O5:O25) -> 281 | P35: =IFERROR(SUMPRODUCT(($B$5:$B$25="Other term loans")*O5:O25*P5:P25)/O35,"n/d") -> 12 | Q35: =SUMIF($B$5:$B$25,"Other term loans",Q5:Q25) -> 189 | R35: =IFERROR(SUMPRODUCT(($B$5:$B$25="Other term loans")*Q5:Q25*R5:R25)/Q35,"n/d") -> 12
A36: Share of principal: secured asset-level (DDTL) % | D36: =IFERROR(C30/C27*100,"n/d") -> 88.416764 | F36: =IFERROR(E30/E27*100,"n/d") -> 72.898933 | H36: =IFERROR(G30/G27*100,"n/d") -> 71.342636 | J36: =IFERROR(I30/I27*100,"n/d") -> 60.300551 | L36: =IFERROR(K30/K27*100,"n/d") -> 58.463473 | N36: =IFERROR(M30/M27*100,"n/d") -> 44.742077 | P36: =IFERROR(O30/O27*100,"n/d") -> 47.01181 | R36: =IFERROR(Q30/Q27*100,"n/d") -> 38.375854
A38: POST-QUARTER (not in Q2'26 figures): Aug-10-2026 DDTL 5.5 $2.6B delayed-draw at SOFR+5.50% (Ba2/BB+), undrawn fee 0.50% [8-K 2026-08-10]. Sep-22-2026 2.875% convertible senior notes due 2033, $4.2B incl. $0.5B option [8-K 2026-09-22]. Company Q2'26 PF weighted rate 7.8% (incl. $3.5B convert at 2.625% illustrative, excl. DDTL 5.5) [Sep-26 deck slide 27].
A39: Q1'26 PR: DDTL 4.0 $8.5B non-recourse IG facility, floating tranche SOFR+2.25%, fixed tranche ~5.9% (as of initial draw).

Sheet Sources
A1: Input ID | B1: Item | C1: Period | D1: Value | E1: Tag | F1: Document | G1: Section / page / formula | H1: URL
A2: I01 | B2: Revenue | C2: Q1'24 | D2: 188.684 | E2: Reported | F2: 424B4 prospectus (IPO), filed 2025-03-31 | G2: S-1 Quarterly Results of Operations p.117 | H2: https://www.sec.gov/Archives/edgar/data/1769628/000119312525067651/d899798d424b4.htm
A3: I01 | B3: Revenue | C3: Q2'24 | D3: 395.371 | E3: Reported | F3: 424B4 prospectus (IPO), filed 2025-03-31 | G3: p.117 | H3: https://www.sec.gov/Archives/edgar/data/1769628/000119312525067651/d899798d424b4.htm
A4: I01 | B4: Revenue | C4: Q3'24 | D4: 583.941 | E4: Reported | F4: 424B4 prospectus (IPO), filed 2025-03-31 | G4: p.117 | H4: https://www.sec.gov/Archives/edgar/data/1769628/000119312525067651/d899798d424b4.htm
A5: I01 | B5: Revenue | C5: Q4'24 | D5: 747.43 | E5: Reported | F5: 424B4 prospectus (IPO), filed 2025-03-31 | G5: p.117 | H5: https://www.sec.gov/Archives/edgar/data/1769628/000119312525067651/d899798d424b4.htm
A6: I01 | B6: Revenue | C6: Q1'25 | D6: 981.632 | E6: Reported | F6: Q1'25 earnings PR (8-K Ex.99.1, 2025-05-14) | G6: PR financial highlights | H6: https://www.sec.gov/Archives/edgar/data/1769628/000176962825000010/coreweave1q25earningspress.htm
A7: I01 | B7: Revenue | C7: Q2'25 | D7: 1212.788 | E7: Reported | F7: Q2'25 earnings PR (8-K Ex.99.1, 2025-08-12) | G7: PR highlights | H7: https://www.sec.gov/Archives/edgar/data/1769628/000176962825000039/coreweave2q25earningspress.htm
A8: I01 | B8: Revenue | C8: Q3'25 | D8: 1364.676 | E8: Reported | F8: Q3'25 earnings PR (8-K Ex.99.1, 2025-11-10) | G8: PR highlights | H8: https://www.sec.gov/Archives/edgar/data/1769628/000176962825000059/coreweave3q25earningspress.htm
A9: I01 | B9: Revenue | C9: Q4'25 | D9: 1572 | E9: Reported | F9: Q4'25 earnings PR (8-K Ex.99.1, 2026-02-26) | G9: PR highlights ($M) | H9: https://www.sec.gov/Archives/edgar/data/1769628/000176962826000094/coreweave4q25earningspress.htm
A10: I01 | B10: Revenue | C10: Q1'26 | D10: 2078 | E10: Reported | F10: Q1'26 earnings PR (8-K Ex.99.1, 2026-05-07) | G10: PR highlights ($M) | H10: https://www.sec.gov/Archives/edgar/data/1769628/000176962826000220/coreweave1q26earningspress.htm
A11: I01 | B11: Revenue | C11: Q2'26 | D11: 2575 | E11: Reported | F11: Q2'26 earnings PR (8-K Ex.99.1, 2026-08-11) | G11: PR highlights ($M) | H11: https://www.sec.gov/Archives/edgar/data/1769628/000176962826000362/coreweave2q26earningspress.htm
A12: I02 | B12: Adjusted EBITDA (company non-GAAP) | C12: Q1'24 | D12: 104.546 | E12: Reported | F12: 424B4 prospectus (IPO), filed 2025-03-31 | G12: S-1 Quarterly Adj. EBITDA reconciliation p.120 | H12: https://www.sec.gov/Archives/edgar/data/1769628/000119312525067651/d899798d424b4.htm
A13: I02 | B13: Adjusted EBITDA (company non-GAAP) | C13: Q2'24 | D13: 249.841 | E13: Reported | F13: 424B4 prospectus (IPO), filed 2025-03-31 | G13: p.120 | H13: https://www.sec.gov/Archives/edgar/data/1769628/000119312525067651/d899798d424b4.htm
... A192: I25 | B192: Company-definition capex (additions to PP&E + finance-lease assets - change in CIP), reported | C192: Q2'26 | D192: 9400 | E192: Reported | F192: Convertible-notes investor presentation (8-K Ex., 2026-09-17) | G192: Sep-26 deck slide 26 '$9.4B' | H192: https://www.sec.gov/Archives/edgar/data/1769628/000176962826000429/crwv2026convertpresentat.htm
A193: I26 | B193: Days in quarter | C193: Q1'24 | D193: 91 | E193: Reported | G193: calendar
A194: I26 | B194: Days in quarter | C194: Q2'24 | D194: 91 | E194: Reported | G194: calendar
A195: I26 | B195: Days in quarter | C195: Q3'24 | D195: 92 | E195: Reported | G195: calendar
A196: I26 | B196: Days in quarter | C196: Q4'24 | D196: 92 | E196: Reported | G196: calendar
A197: I26 | B197: Days in quarter | C197: Q1'25 | D197: 90 | E197: Reported | G197: calendar
A198: I26 | B198: Days in quarter | C198: Q2'25 | D198: 91 | E198: Reported | G198: calendar
A199: I26 | B199: Days in quarter | C199: Q3'25 | D199: 92 | E199: Reported | G199: calendar
A200: I26 | B200: Days in quarter | C200: Q4'25 | D200: 92 | E200: Reported | G200: calendar
A201: I26 | B201: Days in quarter | C201: Q1'26 | D201: 90 | E201: Reported | G201: calendar
A202: I26 | B202: Days in quarter | C202: Q2'26 | D202: 91 | E202: Reported | G202: calendar
A203: I27 | B203: Active data centers (EoP) | C203: Q4'23* | D203: 10 | E203: Reported | F203: 424B4 prospectus (IPO), filed 2025-03-31 | G203: Business / deck 'Active Data Centers' | H203: https://www.sec.gov/Archives/edgar/data/1769628/000119312525067651/d899798d424b4.htm
A204: I27 | B204: Active data centers (EoP) | C204: Q4'24 | D204: 32 | E204: Reported | F204: 424B4 prospectus (IPO), filed 2025-03-31 | G204: Business / deck 'Active Data Centers' | H204: https://www.sec.gov/Archives/edgar/data/1769628/000119312525067651/d899798d424b4.htm
A205: I27 | B205: Active data centers (EoP) | C205: Q4'25 | D205: 43 | E205: Reported | F205: 10-K FY25, filed 2026-03-02 | G205: Business / deck 'Active Data Centers' | H205: https://www.sec.gov/Archives/edgar/data/1769628/000176962826000104/crwv-20251231.htm
A206: I27 | B206: Active data centers (EoP) | C206: Q1'26 | D206: 49 | E206: Reported | F206: Q1'26 earnings presentation (IR site PDF) | G206: Business / deck 'Active Data Centers' | H206: https://s205.q4cdn.com/133937190/files/doc_financials/2026/q1/CoreWeave-1Q26-Earnings-Presentation.pdf
A207: I27 | B207: Active data centers (EoP) | C207: Q2'26 | D207: 51 | E207: Reported | F207: Convertible-notes investor presentation (8-K Ex., 2026-09-17) | G207: Business / deck 'Active Data Centers' | H207: https://www.sec.gov/Archives/edgar/data/1769628/000176962826000429/crwv2026convertpresentat.htm
A208: P01 | B208: GB200 NVL72 GPUs per IT-MW (base) | C208: param | D208: 538 | E208: Estimated | F208: Nebius workspace: /workspace/nebius/capacity/gpu_mw_capex.xlsx (GPUsPerMW base IT-MW rows) / gpu_mw_capex.md s.1 | G208: GPUsPerMW base IT-MW row (gpu_mw_capex.md s.1: 487/538/571) | H208: local
A209: P02 | B209: GB300 NVL72 GPUs per IT-MW (base) | C209: param | D209: 491 | E209: Estimated | F209: Nebius workspace: /workspace/nebius/capacity/gpu_mw_capex.xlsx (GPUsPerMW base IT-MW rows) / gpu_mw_capex.md s.1 | G209: GPUsPerMW base IT-MW row (453/491/519) | H209: local
A210: P03 | B210: Hopper HGX GPUs per IT-MW (base; cross-check only) | C210: param | D210: 713 | E210: Estimated | F210: Nebius workspace: /workspace/nebius/capacity/gpu_mw_capex.xlsx (GPUsPerMW base IT-MW rows) / gpu_mw_capex.md s.1 | G210: GPUsPerMW base IT-MW row (665/713/813) | H210: local
A211: DEBT | B211: 2021 Convertible Senior Secured Notes (principal / eff. rate) | C211: Dec-23 | D211: 55.125 / 17% | E211: Reported | F211: 424B4 prospectus (IPO), filed 2025-03-31 | G211: Note 10 Debt table | H211: https://www.sec.gov/Archives/edgar/data/1769628/000119312525067651/d899798d424b4.htm
A212: DEBT | B212: 2022 Senior Secured Notes (principal / eff. rate) | C212: Dec-23 | D212: 125.0 / 10% | E212: Reported | F212: 424B4 prospectus (IPO), filed 2025-03-31 | G212: Note 10 Debt table | H212: https://www.sec.gov/Archives/edgar/data/1769628/000119312525067651/d899798d424b4.htm
A213: DEBT | B213: DDTL 1.0 Facility (principal / eff. rate) | C213: Dec-23 | D213: 1374.924 / 15% | E213: Reported | F213: 424B4 prospectus (IPO), filed 2025-03-31 | G213: Note 10 Debt table | H213: https://www.sec.gov/Archives/edgar/data/1769628/000119312525067651/d899798d424b4.htm
A214: DEBT | B214: DDTL 1.0 Facility (principal / eff. rate) | C214: Dec-24 | D214: 2012.5 / 15% | E214: Reported | F214: 424B4 prospectus (IPO), filed 2025-03-31 | G214: Note 10 Debt table | H214: https://www.sec.gov/Archives/edgar/data/1769628/000119312525067651/d899798d424b4.htm
A215: DEBT | B215: DDTL 1.0 Facility (principal / eff. rate) | C215: Mar-25 | D215: 1897.5 / 15% | E215: Reported | F215: 10-Q Q1'25, filed 2025-05-15 | G215: Note 10 Debt table | H215: https://www.sec.gov/Archives/edgar/data/1769628/000176962825000014/crwv-20250331.htm
A216: DEBT | B216: DDTL 1.0 Facility (principal / eff. rate) | C216: Jun-25 | D216: 1782.5 / 15% | E216: Reported | F216: 10-Q Q2'25, filed 2025-08-13 | G216: Note 10 Debt table | H216: https://www.sec.gov/Archives/edgar/data/1769628/000176962825000041/crwv-20250630.htm
A217: DEBT | B217: DDTL 1.0 Facility (principal / eff. rate) | C217: Sep-25 | D217: 1667.5 / 15% | E217: Reported | F217: 10-Q Q3'25, filed 2025-11-13 | G217: Note 10 Debt table | H217: https://www.sec.gov/Archives/edgar/data/1769628/000176962825000062/crwv-20250930.htm
A218: DEBT | B218: DDTL 1.0 Facility (principal / eff. rate) | C218: Dec-25 | D218: 1553 / 15% | E218: Reported | F218: 10-K FY25, filed 2026-03-02 | G218: Note 10 Debt table | H218: https://www.sec.gov/Archives/edgar/data/1769628/000176962826000104/crwv-20251231.htm
A219: DEBT | B219: DDTL 1.0 Facility (principal / eff. rate) | C219: Mar-26 | D219: 1438 / 15% | E219: Reported | F219: 10-Q Q1'26, filed 2026-05-08 | G219: Note 10 Debt table | H219: https://www.sec.gov/Archives/edgar/data/1769628/000176962826000222/crwv-20260331.htm
A220: DEBT | B220: DDTL 1.0 Facility (principal / eff. rate) | C220: Jun-26 | D220: 1300 / 15% | E220: Reported | F220: 10-Q Q2'26, filed 2026-08-12 | G220: Note 10 Debt table | H220: https://www.sec.gov/Archives/edgar/data/1769628/000176962826000366/crwv-20260630.htm
A221: DEBT | B221: DDTL 2.0 Facility (principal / eff. rate) | C221: Dec-24 | D221: 3843.819 / 11% | E221: Reported | F221: 424B4 prospectus (IPO), filed 2025-03-31 | G221: Note 10 Debt table | H221: https://www.sec.gov/Archives/edgar/data/1769628/000119312525067651/d899798d424b4.htm
A222: DEBT | B222: DDTL 2.0 Facility (principal / eff. rate) | C222: Mar-25 | D222: 4386.303 / 11% | E222: Reported | F222: 10-Q Q1'25, filed 2025-05-15 | G222: Note 10 Debt table | H222: https://www.sec.gov/Archives/edgar/data/1769628/000176962825000014/crwv-20250331.htm
... A278: DEBT | B278: OEM & software-license financing (non-recourse) (principal / eff. rate) | C278: Jun-26 | D278: 882 / 9% | E278: Reported | F278: 10-Q Q2'26, filed 2026-08-12 | G278: Note 10 Debt table | H278: https://www.sec.gov/Archives/edgar/data/1769628/000176962826000366/crwv-20260630.htm
A280: Document register
A281: S1 | F281: 424B4 prospectus (IPO), filed 2025-03-31 | H281: https://www.sec.gov/Archives/edgar/data/1769628/000119312525067651/d899798d424b4.htm
A282: Q125 | F282: 10-Q Q1'25, filed 2025-05-15 | H282: https://www.sec.gov/Archives/edgar/data/1769628/000176962825000014/crwv-20250331.htm
A283: Q225 | F283: 10-Q Q2'25, filed 2025-08-13 | H283: https://www.sec.gov/Archives/edgar/data/1769628/000176962825000041/crwv-20250630.htm
A284: Q325 | F284: 10-Q Q3'25, filed 2025-11-13 | H284: https://www.sec.gov/Archives/edgar/data/1769628/000176962825000062/crwv-20250930.htm
A285: K25 | F285: 10-K FY25, filed 2026-03-02 | H285: https://www.sec.gov/Archives/edgar/data/1769628/000176962826000104/crwv-20251231.htm
A286: Q126 | F286: 10-Q Q1'26, filed 2026-05-08 | H286: https://www.sec.gov/Archives/edgar/data/1769628/000176962826000222/crwv-20260331.htm
A287: Q226 | F287: 10-Q Q2'26, filed 2026-08-12 | H287: https://www.sec.gov/Archives/edgar/data/1769628/000176962826000366/crwv-20260630.htm
A288: PR125 | F288: Q1'25 earnings PR (8-K Ex.99.1, 2025-05-14) | H288: https://www.sec.gov/Archives/edgar/data/1769628/000176962825000010/coreweave1q25earningspress.htm
A289: PR225 | F289: Q2'25 earnings PR (8-K Ex.99.1, 2025-08-12) | H289: https://www.sec.gov/Archives/edgar/data/1769628/000176962825000039/coreweave2q25earningspress.htm
A290: PR325 | F290: Q3'25 earnings PR (8-K Ex.99.1, 2025-11-10) | H290: https://www.sec.gov/Archives/edgar/data/1769628/000176962825000059/coreweave3q25earningspress.htm
A291: PR425 | F291: Q4'25 earnings PR (8-K Ex.99.1, 2026-02-26) | H291: https://www.sec.gov/Archives/edgar/data/1769628/000176962826000094/coreweave4q25earningspress.htm
A292: PR126 | F292: Q1'26 earnings PR (8-K Ex.99.1, 2026-05-07) | H292: https://www.sec.gov/Archives/edgar/data/1769628/000176962826000220/coreweave1q26earningspress.htm
... A300: NBPX | F300: Nebius workspace: /workspace/nebius/parts/price_history_quarterly.csv (CoreWeave on-demand list, GPU Market agent; Wayback snapshots) | H300: local
A302: Local copies: /workspace/nebius/peers/coreweave/raw/ (S-1, 10-Qs Q1-Q3'25 & Q1'26, 10-K FY25, earnings PRs, .txt extracts) and /workspace/nebius/comps_raw/ (Q2'26 10-Q, Q2'26/Q4'25 PRs, Aug/Sep-26 8-Ks, convert deck, XBRL).
A304: POLISH | B304: EDGAR scan 2026-10-05 | C304: No new operating filing after Q2'26 10-Q (acc 0001769628-26-000366, filed 2026-08-12). Oct 2–3 2026 Form 4 / Form 144 RSU sell-to-cover only. Convert package Sep 17–22 already in pack (C1). | G304: https://www.stocktitan.net/sec-filings/CRWV/ ; comps_raw/cf_0001769628.json

Sheet Definitions
A1: Def | B1: KPI group | C1: Definition used (formula, units) | D1: Mirrored from (Nebius workspace) | E1: CoreWeave application / basis notes
A2: D1 | B2: Revenue per MW | C2: Quarterly revenue x 4 / MW, $M per MW-year. Denominators: (a) active MW at period end; (b) average of opening/closing active MW; (c) contracted MW. EBITDA/MW same construction. | D2: /workspace/nebius/model/nebius_model.xlsx KPIs rows 'Revenue per BILLING / contracted / energized MW' (=AIRev*4/MW); /workspace/nebius/parts/comps_rev_per_mw.csv (period-end and avg-MW variants); capacity/gpu_mw_capex.md s.4 MW basis. | E2: CRWV 'active power' = power supporting live DCs ('data centers... for which we are receiving active power', S-1 glossary). IT vs gross never stated; YE24 GPU density (~694/MW vs Nebius Hopper 713/IT-MW, 548/gross-MW) suggests IT basis - same reading as Nebius 'active' (IT). CRWV has no 'billing MW' or 'connected MW' disclosure, so Nebius's billing-MW variant is n/d. Whole-company revenue used (CRWV is ~100% AI cloud). POLISH 2026-10-05: K02b ≡ K02 for CRWV — no separate billed-IT MW series; active power ≈ billed (S-1 glossary). Nebius billing-MW variant remains n/d on CRWV.
A3: D2 | B3: Revenue per GPU | C3: Quarterly revenue x 4000 / average GPUs ($K per GPU-year); implied $/GPU-hr = revenue / (avg GPUs x days x 24). | D3: nebius_model.xlsx KPIs 'Revenue per GPU ($K per GPU-yr)' (=AIRev*4000/GPU_Avg) and 'Implied blended $/GPU-hr' (=AIRev*1e6/(GPU_Avg*Hours)); Timeline Hours = days x 24. | E3: GPU counts reported only at YE22/YE23/YE24 (S-1, 'more than'). Post-YE24 GPUs ESTIMATED as MW x GPUs/MW using Nebius gpu_mw_capex.xlsx base IT-MW densities (GB200 538 for 2025 adds, GB300 491 for 2026 adds) - the Nebius capacity workbook's own method ('GPUs: energized base MW x GPUs/MW'). Nebius found its own GPU counts include delivered-not-powered GPUs; CRWV's S-1 count is 'running' GPUs.
A4: D3 | B4: Implied utilization | C4: Implied blended $/GPU-hr / fleet-weighted on-demand list price (period-end GPU mix weights). | D4: nebius_model.xlsx KPIs 'Fleet-weighted on-demand list price' and 'Implied utilization (blended $/hr / weighted list)' - flagged there as 'Mixes realized-price discount with utilization'. Prices: /workspace/nebius/parts/price_history_quarterly.csv. | E4: List prices: H100 SXM $49.24/8 = $6.155 (Hopper proxy), GB200 NVL72 $42/4 = $10.50 (Blackwell proxy). Committed contracts (the vast majority of CRWV revenue) are priced below list (CRWV advertises up to ~60% discounts), so the ratio is a price-realization x utilization index, not physical utilization. CRWV discloses no utilization metric.
A5: D4 | B5: Capex per MW | C5: Capex / new active MW in the quarter ($M per MW). Primary numerator = cash purchases of PP&E (Nebius Hist definition). Variants: in-service additions (delta gross PP&E - delta CIP = CRWV's own capex definition) per new MW; trailing-4Q; stock cross-checks net PP&E / active MW and in-service gross PP&E / active MW. | D5: nebius_model.xlsx KPIs 'Capex per new active MW ($M/MW)' (=Capex/MW_New); Hist 'Capex (purchases of PP&E + intangibles, cash)'; Capex_DA 'Transfer into service'; capacity/gpu_mw_capex.xlsx 'Nebius checks' (servers+network per active MW) and 'Peers' (CRWV net PP&E per active MW). | E5: CRWV leases all data centers, so capex/MW is mostly GPU + network + DC fit-out (compare to Nebius 'leased/colo' case, not owned-shell case). OEM/vendor-financed equipment can appear in PP&E without cash capex (cash basis understates).
A6: D5 | B6: D&A useful lives | C6: Disclosed useful-life table and any change in estimate; depreciation yield = D&A x 4 / average in-service gross PP&E; implied life = 1/yield. | D6: /workspace/nebius/filings/nebius_filings.xlsx D&A_Policy tab; nebius_model.xlsx Capex_DA 'Depreciation yield - REPORTED basis' and 'In-service gross PP&E'. | E6: CRWV: technology equipment 6 yrs; software 3-6; DC equipment & leaseholds up to 12 (shorter of lease); last change 1-Jan-2023 (5->6). Total D&A used (PP&E-only depreciation is rounded to $0.1B in 2026 filings).
A7: D6 | B7: Backlog / RPO | C7: RPO = ASC 606 remaining performance obligations at period end ($B); % within 24 months; company 'revenue backlog' shown separately; RPO / (quarterly revenue x 4). | D7: nebius_model.xlsx Hist 'Remaining performance obligations'; nebius_filings.xlsx Quarterly 'RPO (end of period, $M)'. | E7: RPO is the like-for-like metric vs Nebius. CRWV 'revenue backlog' adds committed amounts not yet in RPO (e.g., $11.2B OpenAI at Q1'25).
A8: D7 | B8: Customer concentration | C8: Each customer >=10% of quarter revenue (% of revenue), top-N combined, count of >=10% customers. | D8: nebius_filings.xlsx Quarterly 'Customer concentration (>10% of revenue, quarter)'; shared/findings_log.xlsx concentration row. | E8: Q4 values derived as FY less 9M (rounded % -> +/-2pp).
A9: D8 | B9: Funding cost | C9: Weighted effective cost of debt = sum(principal x effective interest rate) / sum(principal) at period end, all debt facilities excl. leases; split by facility type (DDTL, senior notes, converts, OEM/vendor, revolver, other). Cross-checks: contractual interest x4 / avg principal; company-reported weighted rate. | D9: /workspace/nebius/parts/comps_sources.csv row 'Wtd effective cost of debt (%) - Principal-weighted effective rates, Note 10 debt table' (CRWV 8.41%) and findings_log cost-of-debt row (Nebius 5.1%). | E9: Effective rates as printed in Note 10 (whole %). Converts carry low effective rates (2%) -> blended rate falls as converts grow, while secured DDTL/HY costs stay ~9-11%.

Sheet Notes_Gaps
A1: Notes & Gaps — CoreWeave KPI pack (polished 2026-10-05 ET). Section A = remaining n/d (do not fill with guesses). Section B = caveats on Derived/Estimated cells. Section C = post-quarter / cross-pack notes.
A3: # | B3: Type | C3: Item (keep tagged; do not invent) | D3: Impact on KPIs | E3: Where it shows / possible fix
A4: A. REMAINING n/d (as of polish date; last operating filing = Q2'26 10-Q filed 2026-08-12; EDGAR scan through 2026-10-05 found only Form 4/144 sell-to-cover on Oct 2-3 — no new MW/revenue/GPU data)
A5: A1 | B5: n/d | C5: Q1–Q3'24 active MW, contracted MW, balance sheet, and debt tables (pre-IPO; S-1 gives YE23 & YE24 only). | D5: K01/K03/K04/K10–K15/K28–K36 n/d or Estimated for those quarters. I09E interpolates MW YE23→YE24 (E) so K02/K05 exist but are Estimated. | E5: Inputs I09/I10/I05–I08/Debt_Facilities cols F–H = n/d. Unlikely to appear in primary filings.
A6: A2 | B6: n/d | C6: GPU counts after YE24. S-1: '>250,000' at YE24; no subsequent disclosure in 10-Q/10-K/PR through Q2'26. | D6: K06–K09 Estimated from MW × density (P01/P02). Density choice alone ≈ ±15–20%. | E6: Inputs I11 = n/d after col I; I11E = Estimated. Fix only if company discloses fleet GPUs.
A7: A3 | B7: n/d | C7: MW basis (IT vs gross / critical IT load). Never stated. Several MW figures are 'more than' / 'approximately' (lower-bound wording). | D7: All $/MW ratios carry PUE ambiguity (~1.2–1.4×) and possible lower-bound bias on MW (→ higher $/MW). Single-quarter ΔMW noisy (±10–50). | E7: Definitions D1; Inputs I09 note. YE24 density ~694 GPUs/MW ≈ Nebius Hopper 713/IT-MW → lean IT (E), not proven. Ask IR / site-level leases.
A8: A4 | B8: n/d | C8: Company-reported physical GPU utilization. Not disclosed. | D8: K09 is NOT physical utilization — it is realized $/GPU-hr ÷ list (price-realization index). | E8: Definitions D3; KPI K09 caveat. Do not compare K09 to peers' physical util %.
A9: A5 | B9: n/d | C9: Billed / billing MW as a separate metric. CRWV discloses only 'active power' and 'contracted power' — no billing-MW or connected-MW series. | D9: Nebius K02b (billed IT) has no CRWV twin series. Pack sets K02b = K02 (see B1 / KPI K02b). | E9: price_or_mw.xlsx MW_Paths: 'active power ≈ billed'. comparison.xlsx K02b CRWV cell = K02.
A10: A6 | B10: n/d | C10: Q1–Q3'24 interim RPO / revenue backlog / customer concentration (pre-IPO). | D10: K20–K27 n/d for those quarters. | E10: Inputs I14–I20 cols F–H.
A11: A7 | B11: n/d | C11: Adj. EBITDA bridge detail / segment EBITDA (CRWV is ~100% AI cloud; company Adj. EBITDA is the perimeter). | D11: None for K05 (uses company Adj. EBITDA). Not a gap for perimeter choice. | E11: —
A12: B. CAVEATS on Derived / Estimated cells (values exist but read carefully)
A13: B1 | B13: Align | C13: K02b = K02 for CoreWeave. Reason: no separate billed-IT MW path. Company 'active power' = power at live DCs receiving power (S-1 glossary) ≈ revenue-generating / billed capacity. price_or_mw and comparison treat CRWV active = billed. | D13: K02b is a documentation/alignment row (same formula as K02 on I09A). Not a second estimate. | E13: KPI K02b; Definitions D1; Inputs I09 note; peers/price_or_mw.xlsx; peers/comparison.xlsx K02b.
A14: B2 | B14: Caveat | C14: Implied utilization (K09) mixes contract discounts with idle capacity (Nebius-defined caveat). | D14: Read K09 as price-realization, not physical utilization (see A4). | E14: KPI K09 tag row + Definitions D3.
A15: B3 | B15: Caveat | C15: Quarterly capex/MW is timing-distorted (GPUs bought ahead of energization; e.g. Q1'26 cash capex $7.7B). | D15: Prefer K12 (in-service additions / new MW) and K13 (trailing-4Q) over single-quarter K10. | E15: KPI K10–K13.
A16: B4 | B16: Caveat | C16: Customer letters (A/B/C) re-assigned per filing; Q4 concentration = FY − 9M (±2pp rounding). | D16: K24–K27 Q4 values Derived with rounding noise. | E16: Inputs I17–I20 notes.
A17: B5 | B17: Caveat | C17: Note 10 effective rates rounded to whole %; ranges entered at midpoint. | D17: ±0.5pp on K28–K34. | E17: Debt_Facilities.
A18: B6 | B18: Caveat | C18: 2024 interim MW (I09E) = straight-line YE23~70 → YE24~360. Capex/BS still n/d for those quarters. | D18: K02/K05 for Q1–Q3'24 are Estimated on interpolated MW only. | E18: Inputs I09E tag = Reported/Estimated.
A19: C. POST-QUARTER / CROSS-PACK notes (not in Q2'26 columns; do not backfill into quarterly grid)
A20: C1 | B20: Note | C20: Post-Q2 financing (already in Debt_Facilities memo / Notes): DDTL 5.5 $2.6B SOFR+5.50% (Aug-26); $4.2B 2.875% converts due 2031 (Sep-26). Not in Q2'26 EoP debt stock. | D20: Blended cost keeps falling via converts; marginal secured still ~9–10%. | E20: Debt_Facilities; comps_raw/crwv_0917_*; crwv_0922_*.
A21: C2 | B21: Note | C21: Sep-26 convert deck: ~70% price increase across SKUs Jul-26; ~$40M/MW marginal short-term contracts (slide 7). | D21: Supports rising rev/MW into H2'26; $40M/MW is marginal, not fleet average (fleet K02 = $8.24 Q2'26). | E21: comps_raw/crwv_0917__crwv2026convertpresentat.htm.txt.
A22: C3 | B22: Note | C22: Q2'26 PR backlog ~$104B excludes >$25B net new commitments early Q3'26; contracted power ~4.2 GW as of Aug-11-2026 (vs 3.7 GW at Jun-30). | D22: K10/K21 as-of Jun-30 understate post-quarter book. | E22: Q2 PR; convert deck.
A23: C4 | B23: Note | C23: Cross-pack: peers/price_or_mw.xlsx uses CRWV active MW path for FY27 $/billed test (active≈billed). peers/payback_dilution.xlsx uses CRWV K02 series for dilution fit. peers/comparison.xlsx K02b CRWV = K02. | D23: Keep I09/I09A as the single MW series; do not invent a parallel billed path. | E23: Those workbooks — do not edit from this polish.
A24: C5 | B24: Scan | C24: EDGAR / comps_raw scan 2026-10-05: no Q3'26 10-Q or earnings PR yet. Latest ops data still Q2'26 (10-Q acc 0001769628-26-000366). Oct 2–3 filings = Form 4 / Form 144 RSU sell-to-cover only — no KPI updates. | D24: Quarterly grid unchanged vs Oct-4 pack on numbers. | E24: stocktitan CRWV filings; comps_raw/cf_0001769628.json latest ends 2026-06-30.

Sheet Comparison
A1: Comparison (template) - latest quarter, same KPI IDs. CoreWeave column is LIVE-linked to KPIs!O (Q2'26). Nebius column = values from existing Nebius workspace files (cited); blanks = to fill. Add peers by linking their KPIs latest column.
A3: ID | B3: KPI | C3: Unit | D3: Nebius (NBIS) Q2'26 | E3: Nebius source / basis | F3: CoreWeave Q2'26 | G3: IREN | H3: Oracle OCI | I3: Private peer 1 | J3: Private peer 2 | K3: Comment
A4: K01 | B4: =KPIs!B5 -> Revenue per active MW - period-end reported MW | C4: =KPIs!C5 -> $M/MW-yr | D4: 13.7 | E4: parts/comps_rev_per_mw.csv: Q2'26 rev x4 / ~170 MW YE25 active (stale MW -> overstated; Q2 active MW n/d) | F4: =KPIs!O5 -> 6.8666667
A5: K02 | B5: =KPIs!B7 -> Revenue per active MW - average MW (2024 uses interpolated MW) | C5: =KPIs!C7 -> $M/MW-yr | D5: to fill | F5: =KPIs!O7 -> 8.24
A6: K02b | B6: =KPIs!B9 -> Revenue per BILLING IT MW - average MW (= K02; CRWV has no separate billed series) | C6: =KPIs!C9 -> $M/MW-yr | D6: see peers/comparison.xlsx K02b (13.06 E) | E6: Capacity billing path | F6: =KPIs!O9 -> 8.24 | H6: ALIGN K02b≡K02 | K6: ALIGN: K02b≡K02 (active≈billed). See Notes_Gaps B1. Canonical peer table: peers/comparison.xlsx
A7: K03 | B7: =KPIs!B11 -> Revenue per contracted MW | C7: =KPIs!C11 -> $M/MW-yr | D7: to fill | F7: =KPIs!O11 -> 2.7837838
A8: K05 | B8: =KPIs!B15 -> Adj. EBITDA per active MW (average MW) | C8: =KPIs!C15 -> $M/MW-yr | D8: to fill | F8: =KPIs!O15 -> 4.832
A9: K06 | B9: =KPIs!B18 -> Revenue per GPU ($K per GPU-year, avg GPUs) | C9: =KPIs!C18 -> $K/GPU-yr | D9: to fill | F9: =KPIs!O18 -> 14.506634
A10: K07 | B10: =KPIs!B20 -> Implied blended realized price ($/GPU-hr) | C10: =KPIs!C20 -> $/GPU-hr | D10: to fill | F10: =KPIs!O20 -> 1.6605579
A11: K09 | B11: =KPIs!B24 -> Implied utilization (realized $/GPU-hr / weighted list) | C11: =KPIs!C24 -> % | D11: to fill | F11: =KPIs!O24 -> 18.058143
A12: K10 | B12: =KPIs!B27 -> Cash capex per new active MW (reported MW) | C12: =KPIs!C27 -> $M/MW | D12: to fill | F12: =KPIs!O27 -> 12.844
A13: K12 | B13: =KPIs!B31 -> In-service additions per new active MW (CRWV capex definition) | C13: =KPIs!C31 -> $M/MW | D13: to fill | F13: =KPIs!O31 -> 18.704
A14: K13 | B14: =KPIs!B33 -> Trailing-4Q cash capex per trailing-4Q new active MW | C14: =KPIs!C33 -> $M/MW | D14: to fill | F14: =KPIs!O33 -> 19.966602
A15: K14 | B15: =KPIs!B35 -> Net PP&E per active MW (EoP) | C15: =KPIs!C35 -> $M/MW | D15: to fill | F15: =KPIs!O35 -> 31.157333
A16: K15 | B16: =KPIs!B37 -> Gross in-service PP&E per active MW (EoP) | C16: =KPIs!C37 -> $M/MW | D16: to fill | F16: =KPIs!O37 -> 27.136
A17: K16 | B17: =KPIs!B40 -> Useful life - technology equipment (GPUs/servers/network) | C17: =KPIs!C40 -> years | D17: 5 | E17: filings D&A_Policy: servers & network 4 -> 5 yrs from 1-Jan-2026 | F17: =KPIs!O40 -> 6
A18: K17 | B18: =KPIs!B42 -> Depreciation yield (D&A x4 / avg in-service gross PP&E) | C18: =KPIs!C42 -> % | D18: to fill | F18: =KPIs!O42 -> 15.465749
A19: K20 | B19: =KPIs!B49 -> RPO (ASC 606, EoP) | C19: =KPIs!C49 -> $B | D19: 37.4906 | E19: filings/nebius_filings.xlsx Quarterly: RPO $37,490.6M at 6/30/26 | F19: =KPIs!O49 -> 103.7
A20: K21 | B20: =KPIs!B51 -> Revenue backlog (company metric, EoP) | C20: =KPIs!C51 -> $B | D20: to fill | F20: =KPIs!O51 -> 104.2
A21: K22 | B21: =KPIs!B53 -> RPO % recognized within 24 months | C21: =KPIs!C53 -> % | D21: 36 | E21: model Hist RPO note: 36% <24 months at 6/30/26 | F21: =KPIs!O53 -> 41
A22: K24 | B22: =KPIs!B58 -> Largest customer % of revenue | C22: =KPIs!C58 -> % | D22: 24 | E22: filings/nebius_filings.xlsx Quarterly: Customer C 24% (Q2'26) | F22: =KPIs!O58 -> 36
A23: K26 | B23: =KPIs!B62 -> Top-N >=10% customers combined % | C23: =KPIs!C62 -> % | D23: 59 | E23: C 24% + D 21% + E 14% (Q2'26) | F23: =KPIs!O62 -> 72
A24: K27 | B24: =KPIs!B64 -> Number of customers >=10% of revenue | C24: =KPIs!C64 -> # | D24: 3 | E24: Q2'26 Quarterly tab | F24: =KPIs!O64 -> 3
A25: K28 | B25: =KPIs!B67 -> Weighted effective cost of debt (principal-weighted, EoP) - all facilities | C25: =KPIs!C67 -> % | D25: 5.1 | E25: shared/findings_log.xlsx (GPU Market & Comps): wtd effective 5.1% on converts + secured | F25: =KPIs!O67 -> 8.4134342
A26: K30 | B26: =KPIs!B71 -> of which Senior notes - weighted eff. rate | C26: =KPIs!C71 -> % | D26: to fill | F26: =KPIs!O71 -> 9.772759
A27: K31 | B27: =KPIs!B73 -> of which Converts - weighted eff. rate | C27: =KPIs!C73 -> % | D27: to fill | F27: =KPIs!O73 -> 2
A28: K36 | B28: =KPIs!B83 -> Implied cash cost: contractual interest x4 / avg principal | C28: =KPIs!C83 -> % | D28: to fill | F28: =KPIs!O83 -> 7.8023064
A30: Basis warnings: Nebius rev/MW uses stale YE25 MW; Nebius MW 'active' is IT basis per its own definition, CRWV basis unstated (likely IT). Nebius capex/MW not on same quarterly basis (2026 guide implies $20.5-34.5M per connected MW, capacity/gpu_mw_capex.md s.3).
