Workbook

Sheet README
A1: Peer KPI comps - IREN Ltd (NASDAQ: IREN), AI Cloud perimeter, calendar Q1'24-Q2'26. Built 2026-10-05 (ET) for the Nebius (NBIS) project. File: /workspace/nebius/peers/iren/iren_kpis.xlsx; builder: build_iren_kpis.py (same folder) on shared engine /workspace/nebius/peers/peer_kpi_template.py.
A2: TEMPLATE: identical to peers/coreweave/crwv_kpis.xlsx - same row IDs (I01-I27, K01-K40), definitions D1-D8, tag colours and sourcing rules. Phase-2 extensions: I28-I32 / K41-K45 (useful life, reported GPU utilization, RPO<12m, incremental rev per incremental MW, revenue / GPU hardware, segment gross margin); I40+ / M01+ are IREN-specific memo rows (mining split).
A3: FISCAL MAPPING: IREN FY ends 30-Jun, so fiscal quarters end on calendar quarter-ends -> exact mapping (Q1'24 = FQ3 FY24 Mar-24 ... Q2'26 = FQ4 FY26 Jun-26). See Fiscal_Map tab and row 2 of KPIs/Inputs.
A4: PERIMETER: I01 = AI Cloud Services segment revenue; MW/GPUs = AI only. Bitcoin mining shown separately (I40, I44-I48, M01-M04). Capex, D&A, PP&E, debt are company-wide (not segmented) - KPIs mixing perimeters are suppressed (n/d with explanation) or labelled company-wide.
A5: ACCOUNTING BASIS: IFRS for FQ3 FY24-FQ3 FY25 (6-K / 20-F); US GAAP from FY25 10-K (FY24/FY25 recast). Basis breaks are flagged on each input.
A6: TAGS / COLOURS: blue = Reported; black = Derived (arithmetic; formula in Sources); orange = Estimated (assumption); grey n/d. KPI tag = weakest input.
A7: UNITS: $M unless stated; $/MW KPIs annualized ($M per MW-year); $/GPU in $K per GPU-year.
A8: Multi-peer Comparison tab: /workspace/nebius/peers/comparison.xlsx (built by peers/build_comparison.py).

Sheet KPIs
A1: KPIs - IREN (IREN) - AI Cloud perimeter - quarterly, Nebius definitions (Definitions tab). Value row = live formula; row below = tag (weakest input). Row 2 = fiscal quarter mapped to each calendar column.
E2: FQ2 FY24 (Dec-23) | F2: FQ3 FY24 (Mar-24) | G2: FQ4 FY24 (Jun-24) | H2: FQ1 FY25 (Sep-24) | I2: FQ2 FY25 (Dec-24) | J2: FQ3 FY25 (Mar-25) | K2: FQ4 FY25 (Jun-25) | L2: FQ1 FY26 (Sep-25) | M2: FQ2 FY26 (Dec-25) | N2: FQ3 FY26 (Mar-26) | O2: FQ4 FY26 (Jun-26)
A3: ID | B3: KPI | C3: Unit | D3: Def | E3: Q4'23* | F3: Q1'24 | G3: Q2'24 | H3: Q3'24 | I3: Q4'24 | J3: Q1'25 | K3: Q2'25 | L3: Q3'25 | M3: Q4'25 | N3: Q1'26 | O3: Q2'26 | P3: Method / caveat (IREN (IREN) - AI Cloud perimeter)
A4: A. Revenue per MW ($M per MW-year, annualized: quarterly revenue x 4 / MW)
A5: K01 | B5: Revenue per active MW - period-end MW | C5: $M/MW-yr | D5: D1 | E5: n/d | F5: n/d | G5: n/d | H5: n/d | I5: n/d | J5: n/d | K5: n/d | L5: n/d | M5: n/d | N5: n/d | O5: =IFERROR(Inputs!O4*4/Inputs!O12,"n/d") -> 7.0515 | P5: AI Cloud revenue x4 / operating AI MW. Only Jun-26 MW reported (~40MW, basis unstated). IREN FY26 PR: recent 3-yr contracts '>$20m revenue per MW (IT)', active discussions at ~$25m/MW -> fleet 7.1 reflects legacy Hopper/on-demand mix and capacity live <1 quarter.
B6: tag | E6: n/d | F6: n/d | G6: n/d | H6: n/d | I6: n/d | J6: n/d | K6: n/d | L6: n/d | M6: n/d | N6: n/d | O6: Derived
A7: K02 | B7: Revenue per active MW - average MW | C7: $M/MW-yr | D7: D1 | E7: n/d | F7: n/d | G7: =IFERROR(Inputs!G4*4/Inputs!G54,"n/d") -> 8.8705588 | H7: =IFERROR(Inputs!H4*4/Inputs!H54,"n/d") -> 11.145868 | I7: =IFERROR(Inputs!I4*4/Inputs!I54,"n/d") -> 5.5967345 | J7: =IFERROR(Inputs!J4*4/Inputs!J54,"n/d") -> 5.3866097 | K7: =IFERROR(Inputs!K4*4/Inputs!K54,"n/d") -> 10.462843 | L7: =IFERROR(Inputs!L4*4/Inputs!L54,"n/d") -> 10.476822 | M7: n/d | N7: n/d | O7: n/d | P7: Average-MW variant. MW ESTIMATED from GPUs / 713 per IT-MW through Sep-25; Dec-25/Mar-26 MW n/d so Q4'25-Q2'26 n/d.
B8: tag | E8: n/d | F8: n/d | G8: Estimated | H8: Estimated | I8: Estimated | J8: Estimated | K8: Estimated | L8: Estimated | M8: n/d | N8: n/d | O8: n/d
A9: K03 | B9: Revenue per contracted MW | C9: $M/MW-yr | D9: D1 | E9: n/d | F9: n/d | G9: n/d | H9: n/d | I9: n/d | J9: n/d | K9: n/d | L9: n/d | M9: n/d | N9: n/d | O9: n/d | P9: n/d - no contracted-MW metric (Microsoft = 4 x 50MW IT Horizons; other contracts' MW not disclosed).
B10: tag | E10: n/d | F10: n/d | G10: n/d | H10: n/d | I10: n/d | J10: n/d | K10: n/d | L10: n/d | M10: n/d | N10: n/d | O10: n/d
A11: K04 | B11: Contracted / active MW (build-out multiple) | C11: x | D11: D1 | E11: n/d | F11: n/d | G11: n/d | H11: n/d | I11: n/d | J11: n/d | K11: n/d | L11: n/d | M11: n/d | N11: n/d | O11: n/d | P11: n/d (no contracted MW).
B12: tag | E12: n/d | F12: n/d | G12: n/d | H12: n/d | I12: n/d | J12: n/d | K12: n/d | L12: n/d | M12: n/d | N12: n/d | O12: n/d
A13: K05 | B13: Adj. EBITDA per active MW (average MW) | C13: $M/MW-yr | D13: D1 | E13: n/d | F13: n/d | G13: n/d | H13: n/d | I13: n/d | J13: n/d | K13: n/d | L13: n/d | M13: n/d | N13: n/d | O13: n/d | P13: n/d - IREN reports Adj. EBITDA only company-wide (memo I47; FY26 $245.7M incl. mining). See K45 for AI segment gross margin.
B14: tag | E14: n/d | F14: n/d | G14: n/d | H14: n/d | I14: n/d | J14: n/d | K14: n/d | L14: n/d | M14: n/d | N14: n/d | O14: n/d
A15: B. Revenue per GPU and implied utilization
A16: K06 | B16: Revenue per GPU ($K per GPU-year, avg GPUs) | C16: $K/GPU-yr | D16: D2 | E16: n/d | F16: n/d | G16: =IFERROR(Inputs!G4*4000/Inputs!G52,"n/d") -> 12.441176 | H16: =IFERROR(Inputs!H4*4000/Inputs!H52,"n/d") -> 15.632353 | I16: =IFERROR(Inputs!I4*4000/Inputs!I52,"n/d") -> 7.8495575 | J16: =IFERROR(Inputs!J4*4000/Inputs!J52,"n/d") -> 7.5548523 | K16: =IFERROR(Inputs!K4*4000/Inputs!K52,"n/d") -> 14.674394 | L16: =IFERROR(Inputs!L4*4000/Inputs!L52,"n/d") -> 14.694 | M16: n/d | N16: n/d | O16: n/d | P16: Avg GPUs (I11A) reported except Sep-24 (Estimated). Last computable Q3'25 (GPU counts stop). Q2'26 memo M07 uses estimated period-end GPUs.
B17: tag | E17: n/d | F17: n/d | G17: Derived | H17: Estimated | I17: Estimated | J17: Derived | K17: Derived | L17: Derived | M17: n/d | N17: n/d | O17: n/d
A18: K07 | B18: Implied blended realized price ($/GPU-hr) | C18: $/GPU-hr | D18: D2 | E18: n/d | F18: n/d | G18: =IFERROR(Inputs!G4*1000000/(Inputs!G52*Inputs!G29*24),"n/d") -> 1.4241273 | H18: =IFERROR(Inputs!H4*1000000/(Inputs!H52*Inputs!H29*24),"n/d") -> 1.7699675 | I18: =IFERROR(Inputs!I4*1000000/(Inputs!I52*Inputs!I29*24),"n/d") -> 0.88876331 | J18: =IFERROR(Inputs!J4*1000000/(Inputs!J52*Inputs!J29*24),"n/d") -> 0.8744042 | K18: =IFERROR(Inputs!K4*1000000/(Inputs!K52*Inputs!K29*24),"n/d") -> 1.6797612 | L18: =IFERROR(Inputs!L4*1000000/(Inputs!L52*Inputs!L29*24),"n/d") -> 1.6637228 | M18: n/d | N18: n/d | O18: n/d | P18: All-in AI revenue per GPU-hour on operating GPUs. Note: IREN H100/H200 fleet; GPUs listed as 'operating' may include unrented capacity.
B19: tag | E19: n/d | F19: n/d | G19: Derived | H19: Estimated | I19: Estimated | J19: Derived | K19: Derived | L19: Derived | M19: n/d | N19: n/d | O19: n/d
A20: K08 | B20: Fleet-weighted on-demand list price ($/GPU-hr) | C20: $/GPU-hr | D20: D3 | E20: n/d | F20: =IFERROR(Inputs!F56,"n/d") -> 2 | G20: =IFERROR(Inputs!G56,"n/d") -> 2 | H20: =IFERROR(Inputs!H56,"n/d") -> 2 | I20: =IFERROR(Inputs!I56,"n/d") -> 2 | J20: =IFERROR(Inputs!J56,"n/d") -> 2 | K20: =IFERROR(Inputs!K56,"n/d") -> 2 | L20: =IFERROR(Inputs!L56,"n/d") -> 2 | M20: n/d | N20: n/d | O20: n/d | P20: ESTIMATED: IREN publishes no list price; uses IREN's own $2.00/GPU-hr 100%-uptime revenue assumption (Q1 FY25 PR). Different basis from CRWV/Nebius (on-demand list).
B21: tag | E21: n/d | F21: Estimated | G21: Estimated | H21: Estimated | I21: Estimated | J21: Estimated | K21: Estimated | L21: Estimated | M21: n/d | N21: n/d | O21: n/d
A22: K09 | B22: Implied utilization (realized $/GPU-hr / weighted list) | C22: % | D22: D3 | E22: n/d | F22: n/d | G22: =IFERROR(Inputs!G4*1000000/(Inputs!G52*Inputs!G29*24)/Inputs!G56*100,"n/d") -> 71.206367 | H22: =IFERROR(Inputs!H4*1000000/(Inputs!H52*Inputs!H29*24)/Inputs!H56*100,"n/d") -> 88.498375 | I22: =IFERROR(Inputs!I4*1000000/(Inputs!I52*Inputs!I29*24)/Inputs!I56*100,"n/d") -> 44.438165 | J22: =IFERROR(Inputs!J4*1000000/(Inputs!J52*Inputs!J29*24)/Inputs!J56*100,"n/d") -> 43.72021 | K22: =IFERROR(Inputs!K4*1000000/(Inputs!K52*Inputs!K29*24)/Inputs!K56*100,"n/d") -> 83.988061 | L22: =IFERROR(Inputs!L4*1000000/(Inputs!L52*Inputs!L29*24)/Inputs!L56*100,"n/d") -> 83.186141 | M22: n/d | N22: n/d | O22: n/d | P22: Realized $/GPU-hr / IREN's own $2.00 assumption -> closer to a physical-utilization x price-realization index than CRWV/Nebius (list-based, which embeds contract discounts). Not comparable 1:1.
B23: tag | E23: n/d | F23: n/d | G23: Estimated | H23: Estimated | I23: Estimated | J23: Estimated | K23: Estimated | L23: Estimated | M23: n/d | N23: n/d | O23: n/d
A24: C. Capex per MW ($M per MW)
A25: K10 | B25: Cash capex per new active MW | C25: $M/MW | D25: D4 | E25: n/d | F25: n/d | G25: n/d | H25: n/d | I25: n/d | J25: n/d | K25: n/d | L25: n/d | M25: n/d | N25: n/d | O25: n/d | P25: n/d - capex is company-wide (mining + AI; no split) and AI MW is n/d quarterly. Context: FY26 cash capex $4.33B vs +~37MW operating AI MW = $116M/MW, meaningless because $3.66B sits in CIP (Childress Horizons, Sweetwater) not yet operating.
B26: tag | E26: n/d | F26: n/d | G26: n/d | H26: n/d | I26: n/d | J26: n/d | K26: n/d | L26: n/d | M26: n/d | N26: n/d | O26: n/d
A27: K11 | B27: Cash capex per new active MW (incl. estimated MW) | C27: $M/MW | D27: D4 | E27: n/d | F27: n/d | G27: n/d | H27: n/d | I27: n/d | J27: n/d | K27: n/d | L27: n/d | M27: n/d | N27: n/d | O27: n/d | P27: n/d (see K10).
B28: tag | E28: n/d | F28: n/d | G28: n/d | H28: n/d | I28: n/d | J28: n/d | K28: n/d | L28: n/d | M28: n/d | N28: n/d | O28: n/d
A29: K12 | B29: In-service additions per new active MW | C29: $M/MW | D29: D4 | E29: n/d | F29: n/d | G29: n/d | H29: n/d | I29: n/d | J29: n/d | K29: n/d | L29: n/d | M29: n/d | N29: n/d | O29: n/d | P29: n/d (no AI new-MW series).
B30: tag | E30: n/d | F30: n/d | G30: n/d | H30: n/d | I30: n/d | J30: n/d | K30: n/d | L30: n/d | M30: n/d | N30: n/d | O30: n/d
A31: K13 | B31: Trailing-4Q cash capex per trailing-4Q new active MW | C31: $M/MW | D31: D4 | E31: n/d | F31: n/d | G31: n/d | H31: n/d | I31: n/d | J31: n/d | K31: n/d | L31: n/d | M31: n/d | N31: n/d | O31: n/d | P31: Suppressed: trailing-4Q company capex / AI MW added would be ~116 $M/MW (timing + perimeter mismatch). See memo M06 (GPU hardware per AI MW).
B32: tag | E32: n/d | F32: n/d | G32: n/d | H32: n/d | I32: n/d | J32: n/d | K32: n/d | L32: n/d | M32: n/d | N32: n/d | O32: n/d
A33: K14 | B33: Net PP&E per active MW (EoP) | C33: $M/MW | D33: D4 | E33: n/d | F33: n/d | G33: n/d | H33: n/d | I33: n/d | J33: n/d | K33: n/d | L33: n/d | M33: n/d | N33: n/d | O33: n/d | P33: n/d on AI perimeter (net PP&E is company-wide). Company-wide analogue in memo M05 (net PP&E / total operating DC MW).
B34: tag | E34: n/d | F34: n/d | G34: n/d | H34: n/d | I34: n/d | J34: n/d | K34: n/d | L34: n/d | M34: n/d | N34: n/d | O34: n/d
A35: K15 | B35: Gross in-service PP&E per active MW (EoP) | C35: $M/MW | D35: D4 | E35: n/d | F35: n/d | G35: n/d | H35: n/d | I35: n/d | J35: n/d | K35: n/d | L35: n/d | M35: n/d | N35: n/d | O35: n/d | P35: n/d on AI perimeter. AI-only analogue: memo M06 = GPU hardware gross / AI MW.
B36: tag | E36: n/d | F36: n/d | G36: n/d | H36: n/d | I36: n/d | J36: n/d | K36: n/d | L36: n/d | M36: n/d | N36: n/d | O36: n/d
A37: D. D&A useful lives and depreciation yield
A38: K16 | B38: Useful life - GPU / server equipment | C38: years | D38: D5 | E38: n/d | F38: =IFERROR(Inputs!F31,"n/d") -> 5 | G38: =IFERROR(Inputs!G31,"n/d") -> 5 | H38: =IFERROR(Inputs!H31,"n/d") -> 5 | I38: =IFERROR(Inputs!I31,"n/d") -> 5 | J38: =IFERROR(Inputs!J31,"n/d") -> 5 | K38: =IFERROR(Inputs!K31,"n/d") -> 5 | L38: =IFERROR(Inputs!L31,"n/d") -> 5 | M38: =IFERROR(Inputs!M31,"n/d") -> 5 | ... O38: =IFERROR(Inputs!O31,"n/d") -> 5 | P38: 10-K FY26 / FY25 / 20-F FY24 useful-life table: HPC (GPU) hardware 5 yrs; mining hardware 4 yrs (2 yrs for S19j Pro/S19 Pro from FY24); buildings 20. No change to GPU life FY24-FY26. Nebius: 4->5 yrs from 1-Jan-2026; CRWV 6 yrs.
B39: tag | E39: n/d | F39: Reported | G39: Reported | H39: Reported | I39: Reported | J39: Reported | K39: Reported | L39: Reported | M39: Reported | N39: Reported | O39: Reported
A40: K17 | B40: Depreciation yield (D&A x4 / avg in-service gross PP&E) | C40: % | D40: D5 | E40: n/d | F40: n/d | G40: =IFERROR(Inputs!G6*4/((Inputs!F57+Inputs!G57)/2)*100,"n/d") -> 29.173424 | H40: =IFERROR(Inputs!H6*4/((Inputs!G57+Inputs!H57)/2)*100,"n/d") -> 21.555296 | I40: =IFERROR(Inputs!I6*4/((Inputs!H57+Inputs!I57)/2)*100,"n/d") -> 14.774968 | J40: =IFERROR(Inputs!J6*4/((Inputs!I57+Inputs!J57)/2)*100,"n/d") -> 14.656716 | K40: =IFERROR(Inputs!K6*4/((Inputs!J57+Inputs!K57)/2)*100,"n/d") -> 15.226899 | L40: =IFERROR(Inputs!L6*4/((Inputs!K57+Inputs!L57)/2)*100,"n/d") -> 17.989985 | M40: =IFERROR(Inputs!M6*4/((Inputs!L57+Inputs!M57)/2)*100,"n/d") -> 18.052806 | N40: =IFERROR(Inputs!N6*4/((Inputs!M57+Inputs!N57)/2)*100,"n/d") -> 18.634414 | O40: =IFERROR(Inputs!O6*4/((Inputs!N57+Inputs!O57)/2)*100,"n/d") -> 14.351359 | P40: Company-wide D&A x4 / avg in-service gross PP&E (gross - CIP - impairment). Q3'24-Q1'25 IFRS, Q2'25 straddles IFRS->GAAP. High yields reflect 2-4 yr mining hardware lives; falling to ~10% as GPU (5y) and buildings (20y) dominate.
B41: tag | E41: n/d | F41: n/d | G41: Derived | H41: Derived | I41: Derived | J41: Derived | K41: Derived | L41: Derived | M41: Derived | N41: Derived | O41: Derived
A42: K18 | B42: Implied average depreciable life (1 / yield) | C42: years | D42: D5 | E42: n/d | F42: n/d | G42: =IFERROR(100/G40,"n/d") -> 3.4277773 | H42: =IFERROR(100/H40,"n/d") -> 4.6392311 | I42: =IFERROR(100/I40,"n/d") -> 6.7682041 | J42: =IFERROR(100/J40,"n/d") -> 6.8228108 | K42: =IFERROR(100/K40,"n/d") -> 6.5673253 | L42: =IFERROR(100/L40,"n/d") -> 5.5586485 | M42: =IFERROR(100/M40,"n/d") -> 5.5393051 | N42: =IFERROR(100/N40,"n/d") -> 5.3664151 | O42: =IFERROR(100/O40,"n/d") -> 6.967981
B43: tag | E43: n/d | F43: n/d | G43: Derived | H43: Derived | I43: Derived | J43: Derived | K43: Derived | L43: Derived | M43: Derived | N43: Derived | O43: Derived
A44: K19 | B44: D&A as % of revenue (company D&A / total revenue) | C44: % | D44: D5 | E44: n/d | F44: =IFERROR(Inputs!F6/Inputs!F59*100,"n/d") -> 16.111214 | G44: =IFERROR(Inputs!G6/Inputs!G59*100,"n/d") -> 47.149548 | H44: =IFERROR(Inputs!H6/Inputs!H59*100,"n/d") -> 64.307103 | I44: =IFERROR(Inputs!I6/Inputs!I59*100,"n/d") -> 31.062302 | J44: =IFERROR(Inputs!J6/Inputs!J59*100,"n/d") -> 32.668154 | K44: =IFERROR(Inputs!K6/Inputs!K59*100,"n/d") -> 34.07335 | L44: =IFERROR(Inputs!L6/Inputs!L59*100,"n/d") -> 35.467238 | M44: =IFERROR(Inputs!M6/Inputs!M59*100,"n/d") -> 53.698049 | ... O44: =IFERROR(Inputs!O6/Inputs!O59*100,"n/d") -> 81.677537 | P44: Overridden to company-wide denominator (D&A is not segmented).
B45: tag | E45: n/d | F45: Derived | G45: Derived | H45: Derived | I45: Derived | J45: Derived | K45: Derived | L45: Derived | M45: Derived | N45: Derived | O45: Derived
A46: E. Backlog / RPO
A47: K20 | B47: RPO (ASC 606, EoP) | C47: $B | D47: D6 | E47: n/d | F47: n/d | G47: n/d | H47: n/d | I47: n/d | J47: n/d | K47: n/d | L47: =IFERROR(Inputs!L17,"n/d") -> 0.195027 | M47: =IFERROR(Inputs!M17,"n/d") -> 0.289411 | N47: =IFERROR(Inputs!N17,"n/d") -> 0.710272 | O47: =IFERROR(Inputs!O17,"n/d") -> 5.1 | P47: AI Cloud RPO only (mining has none). Microsoft $9.7B enters RPO tranche-by-tranche on delivery; Jun-26 RPO $5.1B excludes $11.4B ASC 842 lease value (K21).
B48: tag | E48: n/d | F48: n/d | G48: n/d | H48: n/d | I48: n/d | J48: n/d | K48: n/d | L48: Reported | M48: Reported | N48: Reported | O48: Reported
A49: K21 | B49: Revenue backlog (company metric / incl. contracted non-RPO, EoP) | C49: $B | D49: D6 | E49: n/d | F49: n/d | G49: n/d | H49: n/d | I49: n/d | J49: n/d | K49: n/d | L49: n/d | M49: =IFERROR(Inputs!M18,"n/d") -> 9.989 | N49: =IFERROR(Inputs!N18,"n/d") -> 10.41 | O49: =IFERROR(Inputs!O18,"n/d") -> 16.6 | P49: RPO + contracted value outside RPO: Dec-25/Mar-26 = RPO + undelivered Microsoft TCV (Derived, lower bound); Jun-26 = $16.6B reported (RPO 5.1 + ASC 842 11.4). Microsoft ~$9.7B (~58%) + NVIDIA $3.4B (~20%) = 'substantial majority' (Derived concentration).
B50: tag | E50: n/d | F50: n/d | G50: n/d | H50: n/d | I50: n/d | J50: n/d | K50: n/d | L50: n/d | M50: Derived | N50: Derived | O50: Reported
A51: K22 | B51: RPO % recognized within 24 months | C51: % | D51: D6 | E51: n/d | F51: n/d | G51: n/d | H51: n/d | I51: n/d | J51: n/d | K51: n/d | L51: =IFERROR(Inputs!L19,"n/d") -> 95.8 | M51: =IFERROR(Inputs!M19,"n/d") -> 98.7 | N51: =IFERROR(Inputs!N19,"n/d") -> 80.7 | O51: =IFERROR(Inputs!O19,"n/d") -> 43.1 | P51: Derived from RPO maturity buckets (0-12m, 13-24m). Jun-26 43% (CRWV 41%, Nebius 36%).
B52: tag | E52: n/d | F52: n/d | G52: n/d | H52: n/d | I52: n/d | J52: n/d | K52: n/d | L52: Derived | M52: Derived | N52: Derived | O52: Derived
A53: K23 | B53: RPO / annualized quarterly revenue | C53: years | D53: D6 | E53: n/d | F53: n/d | G53: n/d | H53: n/d | I53: n/d | J53: n/d | K53: n/d | L53: =IFERROR(Inputs!L17*1000/(Inputs!L4*4),"n/d") -> 6.6362801 | M53: =IFERROR(Inputs!M17*1000/(Inputs!M4*4),"n/d") -> 4.1827234 | N53: =IFERROR(Inputs!N17*1000/(Inputs!N4*4),"n/d") -> 5.2792627 | O53: =IFERROR(Inputs!O17*1000/(Inputs!O4*4),"n/d") -> 18.081259 | P53: RPO / (AI Cloud quarterly revenue x4).
B54: tag | E54: n/d | F54: n/d | G54: n/d | H54: n/d | I54: n/d | J54: n/d | K54: n/d | L54: Derived | M54: Derived | N54: Derived | O54: Derived
A55: F. Customer concentration (% of quarter revenue; customers <10% not disclosed)
A56: K24 | B56: Largest customer % of revenue | C56: % | D56: D7 | E56: n/d | F56: n/d | G56: n/d | H56: n/d | I56: n/d | J56: n/d | K56: n/d | L56: n/d | M56: n/d | N56: n/d | O56: n/d | P56: n/d - IREN does not disclose AI customer revenue shares. Mining revenue via 3 pools (97% of FY25 revenue). Backlog concentration (K21 note): Microsoft ~58%, NVIDIA ~20% of $16.6B.
B57: tag | E57: n/d | F57: n/d | G57: n/d | H57: n/d | I57: n/d | J57: n/d | K57: n/d | L57: n/d | M57: n/d | N57: n/d | O57: n/d
A58: K25 | B58: 2nd-largest customer % | C58: % | D58: D7 | E58: n/d | F58: n/d | G58: n/d | H58: n/d | I58: n/d | J58: n/d | K58: n/d | L58: n/d | M58: n/d | N58: n/d | O58: n/d | P58: n/d
B59: tag | E59: n/d | F59: n/d | G59: n/d | H59: n/d | I59: n/d | J59: n/d | K59: n/d | L59: n/d | M59: n/d | N59: n/d | O59: n/d
A60: K26 | B60: Top-N >=10% customers combined % | C60: % | D60: D7 | E60: n/d | F60: n/d | G60: n/d | H60: n/d | I60: n/d | J60: n/d | K60: n/d | L60: n/d | M60: n/d | N60: n/d | O60: n/d | P60: n/d
B61: tag | E61: n/d | F61: n/d | G61: n/d | H61: n/d | I61: n/d | J61: n/d | K61: n/d | L61: n/d | M61: n/d | N61: n/d | O61: n/d
A62: K27 | B62: Number of customers >=10% of revenue | C62: # | D62: D7 | E62: n/d | F62: n/d | G62: n/d | H62: n/d | I62: n/d | J62: n/d | K62: n/d | L62: n/d | M62: n/d | N62: n/d | O62: n/d | P62: n/d
B63: tag | E63: n/d | F63: n/d | G63: n/d | H63: n/d | I63: n/d | J63: n/d | K63: n/d | L63: n/d | M63: n/d | N63: n/d | O63: n/d
A64: G. Funding cost (% p.a.)
A65: K28 | B65: Weighted effective cost of debt (principal-weighted, EoP) - all facilities | C65: % | D65: D8 | E65: n/d | F65: =IFERROR(Debt_Facilities!D17*1,"n/d") -> n/d | G65: =IFERROR(Debt_Facilities!F17*1,"n/d") -> n/d | H65: =IFERROR(Debt_Facilities!H17*1,"n/d") -> n/d | I65: =IFERROR(Debt_Facilities!J17*1,"n/d") -> 3.87 | J65: =IFERROR(Debt_Facilities!L17*1,"n/d") -> 3.87 | K65: =IFERROR(Debt_Facilities!N17*1,"n/d") -> 4.0644444 | L65: =IFERROR(Debt_Facilities!P17*1,"n/d") -> 4.0644444 | M65: =IFERROR(Debt_Facilities!R17*1,"n/d") -> 1.0815181 | N65: =IFERROR(Debt_Facilities!T17*1,"n/d") -> 1.0815181 | O65: =IFERROR(Debt_Facilities!V17*1,"n/d") -> 1.8523437 | P65: Principal-weighted effective rates (converts at 0.4-4.2% effective dominate). Jun-26 incl. first secured GPU debt (DDTL 7.12%, USPP 7.05%). comps.csv had 1.85% (consistent).
B66: tag | E66: n/d | F66: Derived | G66: Derived | H66: Derived | I66: Derived | J66: Derived | K66: Derived | L66: Derived | M66: Derived | N66: Derived | O66: Derived
A67: K29 | B67: of which DDTL - weighted eff. rate | C67: % | D67: D8 | E67: n/d | F67: =Debt_Facilities!D18 -> n/d | G67: =Debt_Facilities!F18 -> n/d | H67: =Debt_Facilities!H18 -> n/d | I67: =Debt_Facilities!J18 -> n/d | J67: =Debt_Facilities!L18 -> n/d | K67: =Debt_Facilities!N18 -> n/d | L67: =Debt_Facilities!P18 -> n/d | M67: =Debt_Facilities!R18 -> n/d | N67: =Debt_Facilities!T18 -> n/d | O67: =Debt_Facilities!V18 -> 7.12 | P67: GPU DDTL (non-recourse, SOFR+2.25%), first drawn FY26 Q4.
B68: tag | E68: n/d | F68: Derived | G68: Derived | H68: Derived | I68: Derived | J68: Derived | K68: Derived | L68: Derived | M68: Derived | N68: Derived | O68: Derived
A69: K30 | B69: of which Senior notes - weighted eff. rate | C69: % | D69: D8 | E69: n/d | F69: =Debt_Facilities!D19 -> n/d | G69: =Debt_Facilities!F19 -> n/d | H69: =Debt_Facilities!H19 -> n/d | I69: =Debt_Facilities!J19 -> n/d | J69: =Debt_Facilities!L19 -> n/d | K69: =Debt_Facilities!N19 -> n/d | L69: =Debt_Facilities!P19 -> n/d | M69: =Debt_Facilities!R19 -> n/d | N69: =Debt_Facilities!T19 -> n/d | O69: =Debt_Facilities!V19 -> 7.05 | P69: USPP senior secured notes (5.96% coupon; 7.05% effective).
B70: tag | E70: n/d | F70: Derived | G70: Derived | H70: Derived | I70: Derived | J70: Derived | K70: Derived | L70: Derived | M70: Derived | N70: Derived | O70: Derived
A71: K31 | B71: of which Converts - weighted eff. rate | C71: % | D71: D8 | E71: n/d | F71: =Debt_Facilities!D20 -> n/d | G71: =Debt_Facilities!F20 -> n/d | H71: =Debt_Facilities!H20 -> n/d | I71: =Debt_Facilities!J20 -> 3.87 | J71: =Debt_Facilities!L20 -> 3.87 | K71: =Debt_Facilities!N20 -> 4.0644444 | L71: =Debt_Facilities!P20 -> 4.0644444 | M71: =Debt_Facilities!R20 -> 1.0815181 | N71: =Debt_Facilities!T20 -> 1.0815181 | O71: =Debt_Facilities!V20 -> 1.1253157 | P71: Convertible notes (zero/low coupon; effective incl. issuance costs).
B72: tag | E72: n/d | F72: Derived | G72: Derived | H72: Derived | I72: Derived | J72: Derived | K72: Derived | L72: Derived | M72: Derived | N72: Derived | O72: Derived
A73: K32 | B73: of which OEM / vendor financing - weighted eff. rate | C73: % | D73: D8 | E73: n/d | F73: =Debt_Facilities!D21 -> n/d | G73: =Debt_Facilities!F21 -> n/d | H73: =Debt_Facilities!H21 -> n/d | I73: =Debt_Facilities!J21 -> n/d | J73: =Debt_Facilities!L21 -> n/d | K73: =Debt_Facilities!N21 -> n/d | L73: =Debt_Facilities!P21 -> n/d | M73: =Debt_Facilities!R21 -> n/d | N73: =Debt_Facilities!T21 -> n/d | O73: =Debt_Facilities!V21 -> n/d | P73: n/d where facility type not outstanding.
B74: tag | E74: n/d | F74: Derived | G74: Derived | H74: Derived | I74: Derived | J74: Derived | K74: Derived | L74: Derived | M74: Derived | N74: Derived | O74: Derived
A75: K33 | B75: of which Revolver - weighted eff. rate | C75: % | D75: D8 | E75: n/d | F75: =Debt_Facilities!D22 -> n/d | G75: =Debt_Facilities!F22 -> n/d | H75: =Debt_Facilities!H22 -> n/d | I75: =Debt_Facilities!J22 -> n/d | J75: =Debt_Facilities!L22 -> n/d | K75: =Debt_Facilities!N22 -> n/d | L75: =Debt_Facilities!P22 -> n/d | M75: =Debt_Facilities!R22 -> n/d | N75: =Debt_Facilities!T22 -> n/d | O75: =Debt_Facilities!V22 -> n/d | P75: n/d where facility type not outstanding.
B76: tag | E76: n/d | F76: Derived | G76: Derived | H76: Derived | I76: Derived | J76: Derived | K76: Derived | L76: Derived | M76: Derived | N76: Derived | O76: Derived
A77: K34 | B77: of which Other term loans - weighted eff. rate | C77: % | D77: D8 | E77: n/d | F77: =Debt_Facilities!D23 -> n/d | G77: =Debt_Facilities!F23 -> n/d | H77: =Debt_Facilities!H23 -> n/d | I77: =Debt_Facilities!J23 -> n/d | J77: =Debt_Facilities!L23 -> n/d | K77: =Debt_Facilities!N23 -> n/d | L77: =Debt_Facilities!P23 -> n/d | M77: =Debt_Facilities!R23 -> n/d | N77: =Debt_Facilities!T23 -> n/d | O77: =Debt_Facilities!V23 -> n/d | P77: n/d where facility type not outstanding.
B78: tag | E78: n/d | F78: Derived | G78: Derived | H78: Derived | I78: Derived | J78: Derived | K78: Derived | L78: Derived | M78: Derived | N78: Derived | O78: Derived
A79: K35 | B79: DDTL share of principal | C79: % | D79: D8 | E79: n/d | F79: =Debt_Facilities!D24 -> n/d | G79: =Debt_Facilities!F24 -> n/d | H79: =Debt_Facilities!H24 -> n/d | I79: =Debt_Facilities!J24 -> 0 | J79: =Debt_Facilities!L24 -> 0 | K79: =Debt_Facilities!N24 -> 0 | L79: =Debt_Facilities!P24 -> 0 | M79: =Debt_Facilities!R24 -> 0 | N79: =Debt_Facilities!T24 -> 0 | O79: =Debt_Facilities!V24 -> 5.3597043
B80: tag | E80: n/d | F80: Derived | G80: Derived | H80: Derived | I80: Derived | J80: Derived | K80: Derived | L80: Derived | M80: Derived | N80: Derived | O80: Derived
A81: K36 | B81: Implied cash cost: interest x4 / avg principal | C81: % | D81: D8 | E81: n/d | F81: n/d | G81: n/d | H81: =IFERROR(Inputs!H24*4/Inputs!H58*100,"n/d") -> n/d | I81: =IFERROR(Inputs!I24*4/Inputs!I58*100,"n/d") -> 11.369091 | J81: =IFERROR(Inputs!J24*4/Inputs!J58*100,"n/d") -> 3.7445455 | K81: =IFERROR(Inputs!K24*4/Inputs!K58*100,"n/d") -> 2.899021 | L81: =IFERROR(Inputs!L24*4/Inputs!L58*100,"n/d") -> 3.7494949 | M81: =IFERROR(Inputs!M24*4/Inputs!M58*100,"n/d") -> 1.8021416 | N81: =IFERROR(Inputs!N24*4/Inputs!N58*100,"n/d") -> 1.5844306 | O81: =IFERROR(Inputs!O24*4/Inputs!O58*100,"n/d") -> 1.7092136 | P81: Finance expense (incl. issuance-cost amortization, finance-lease interest) x4 / avg principal. Annual contractual interest: FY26 $37.2M / avg debt (990; 7,706) = 0.85% (contractual coupons only).
B82: tag | E82: n/d | F82: n/d | G82: n/d | H82: Derived | I82: Derived | J82: Derived | K82: Derived | L82: Derived | M82: Derived | N82: Derived | O82: Derived
A83: K37 | B83: Company-reported weighted average interest rate | C83: % | D83: D8 | E83: n/d | F83: n/d | G83: n/d | H83: n/d | I83: n/d | J83: n/d | K83: n/d | L83: n/d | M83: n/d | N83: n/d | O83: n/d | P83: n/d
B84: tag | E84: n/d | F84: n/d | G84: n/d | H84: n/d | I84: n/d | J84: n/d | K84: n/d | L84: n/d | M84: n/d | N84: n/d | O84: n/d
A85: K38 | B85: Total debt principal (EoP) | C85: $B | D85: D8 | E85: n/d | F85: =IFERROR(Inputs!F26/1000,"n/d") -> 0 | G85: =IFERROR(Inputs!G26/1000,"n/d") -> 0 | H85: =IFERROR(Inputs!H26/1000,"n/d") -> 0 | I85: =IFERROR(Inputs!I26/1000,"n/d") -> 0.44 | J85: =IFERROR(Inputs!J26/1000,"n/d") -> 0.44 | K85: =IFERROR(Inputs!K26/1000,"n/d") -> 0.99 | L85: =IFERROR(Inputs!L26/1000,"n/d") -> 0.99 | M85: =IFERROR(Inputs!M26/1000,"n/d") -> 3.745699 | ... O85: =IFERROR(Inputs!O26/1000,"n/d") -> 7.705649 | P85: Excl. GPU finance leases ($243.8M at Jun-26).
B86: tag | E86: n/d | F86: Reported | G86: Reported | H86: Reported | I86: Reported | J86: Reported | K86: Reported | L86: Reported | M86: Reported | N86: Reported | O86: Reported
A87: K39 | B87: Debt principal / RPO | C87: x | D87: D8 | E87: n/d | F87: n/d | G87: n/d | H87: n/d | I87: n/d | J87: n/d | K87: n/d | L87: =IFERROR(Inputs!L26/1000/Inputs!L17,"n/d") -> 5.0762202 | M87: =IFERROR(Inputs!M26/1000/Inputs!M17,"n/d") -> 12.94249 | N87: =IFERROR(Inputs!N26/1000/Inputs!N17,"n/d") -> 5.2736121 | O87: =IFERROR(Inputs!O26/1000/Inputs!O17,"n/d") -> 1.5109116
B88: tag | E88: n/d | F88: n/d | G88: n/d | H88: n/d | I88: n/d | J88: n/d | K88: n/d | L88: Derived | M88: Derived | N88: Derived | O88: Derived
A89: K40 | B89: Capitalized interest % of contractual interest | C89: % | D89: D8 | E89: n/d | F89: n/d | G89: n/d | H89: n/d | I89: n/d | J89: n/d | K89: n/d | L89: n/d | M89: n/d | N89: n/d | O89: n/d | P89: n/d (capitalized interest not disclosed quarterly).
B90: tag | E90: n/d | F90: n/d | G90: n/d | H90: n/d | I90: n/d | J90: n/d | K90: n/d | L90: n/d | M90: n/d | N90: n/d | O90: n/d
A91: H. Template extensions added in phase 2 (K41+; n/d for CoreWeave unless stated)
A92: K41 | B92: Company-reported GPU utilization (physical) | C92: % | D92: D3 | E92: n/d | F92: n/d | G92: n/d | H92: n/d | I92: n/d | J92: n/d | K92: n/d | L92: n/d | M92: n/d | N92: n/d | O92: n/d | P92: n/d - IREN does not publish GPU utilization.
B93: tag | E93: n/d | F93: n/d | G93: n/d | H93: n/d | I93: n/d | J93: n/d | K93: n/d | L93: n/d | M93: n/d | N93: n/d | O93: n/d
A94: K42 | B94: RPO % recognized within 12 months | C94: % | D94: D6 | E94: n/d | F94: n/d | G94: n/d | H94: n/d | I94: n/d | J94: n/d | K94: n/d | L94: =IFERROR(Inputs!L33,"n/d") -> 47.9 | M94: =IFERROR(Inputs!M33,"n/d") -> 51.9 | N94: =IFERROR(Inputs!N33,"n/d") -> 43.4 | O94: =IFERROR(Inputs!O33,"n/d") -> 17.6 | P94: Derived from RPO maturity buckets.
B95: tag | E95: n/d | F95: n/d | G95: n/d | H95: n/d | I95: n/d | J95: n/d | K95: n/d | L95: Derived | M95: Derived | N95: Derived | O95: Derived
A96: K43 | B96: Incremental annualized revenue per incremental MW (YoY) | C96: $M/MW-yr | D96: D1 | E96: n/d | F96: n/d | G96: n/d | H96: n/d | I96: n/d | J96: =IFERROR((Inputs!J4-Inputs!F4)*4/Inputs!J55,"n/d") -> 7.9591926 | K96: =IFERROR((Inputs!K4-Inputs!G4)*4/Inputs!K55,"n/d") -> 11.642159 | L96: =IFERROR((Inputs!L4-Inputs!H4)*4/Inputs!L55,"n/d") -> 9.2356822 | M96: n/d | N96: n/d | O96: =IFERROR((Inputs!O4-Inputs!K4)*4/Inputs!O55,"n/d") -> 6.8088018 | P96: (AI rev Q2'26 - Q2'25) x4 / (40 MW - est. 2.7 MW at Jun-25). Estimated (Jun-25 MW from GPUs/713). Contract-level IREN claim: >$20M/MW (IT) on recent 3-yr contracts.
B97: tag | E97: n/d | F97: n/d | G97: n/d | H97: n/d | I97: n/d | J97: Estimated | K97: Estimated | L97: Estimated | M97: n/d | N97: n/d | O97: Estimated
A98: K44 | B98: Annualized revenue / avg gross GPU-compute hardware in service | C98: x | D98: D4 | E98: n/d | F98: n/d | G98: =IFERROR(Inputs!G4*4/((Inputs!F34+Inputs!G34)/2),"n/d") -> 0.32270574 | H98: =IFERROR(Inputs!H4*4/((Inputs!G34+Inputs!H34)/2),"n/d") -> 0.38081591 | I98: =IFERROR(Inputs!I4*4/((Inputs!H34+Inputs!I34)/2),"n/d") -> 0.20897632 | J98: =IFERROR(Inputs!J4*4/((Inputs!I34+Inputs!J34)/2),"n/d") -> 0.20820373 | K98: =IFERROR(Inputs!K4*4/((Inputs!J34+Inputs!K34)/2),"n/d") -> 0.38309022 | L98: =IFERROR(Inputs!L4*4/((Inputs!K34+Inputs!L34)/2),"n/d") -> 0.32285991 | M98: =IFERROR(Inputs!M4*4/((Inputs!L34+Inputs!M34)/2),"n/d") -> 0.21073181 | N98: =IFERROR(Inputs!N4*4/((Inputs!M34+Inputs!N34)/2),"n/d") -> 0.19755864 | O98: =IFERROR(Inputs!O4*4/((Inputs!N34+Inputs!O34)/2),"n/d") -> 0.19820104 | P98: AI revenue x4 / avg owned GPU hardware gross (excl. finance-lease ROU and CIP). Falls in Q4'25-Q2'26 because large GPU batches were capitalized ahead of revenue ramp (Horizon/Microsoft).
B99: tag | E99: n/d | F99: n/d | G99: Derived | H99: Derived | I99: Derived | J99: Derived | K99: Derived | L99: Derived | M99: Derived | N99: Derived | O99: Derived
A100: K45 | B100: Segment gross margin (revenue - cost of revenue excl. D&A) / revenue | C100: % | D100: D1 | E100: n/d | F100: n/d | G100: n/d | H100: =IFERROR((Inputs!H4-Inputs!H35)/Inputs!H4*100,"n/d") -> 92.724992 | I100: =IFERROR((Inputs!I4-Inputs!I35)/Inputs!I4*100,"n/d") -> 89.665539 | J100: =IFERROR((Inputs!J4-Inputs!J35)/Inputs!J4*100,"n/d") -> 90.617146 | K100: =IFERROR((Inputs!K4-Inputs!K35)/Inputs!K4*100,"n/d") -> 93.163866 | L100: =IFERROR((Inputs!L4-Inputs!L35)/Inputs!L4*100,"n/d") -> 90.091194 | M100: =IFERROR((Inputs!M4-Inputs!M35)/Inputs!M4*100,"n/d") -> 86.154469 | N100: =IFERROR((Inputs!N4-Inputs!N35)/Inputs!N4*100,"n/d") -> 86.332689 | O100: =IFERROR((Inputs!O4-Inputs!O35)/Inputs!O4*100,"n/d") -> 86.936113 | P100: AI segment (revenue - segment cost of revenue excl. D&A) / revenue; costs mostly power.
...

Sheet Inputs
A1: Inputs - IREN (IREN) - AI Cloud perimeter. Reported (blue), derived (black), estimated (orange), n/d (grey). Per-cell source detail on Sources tab. Row 2 = fiscal quarter / period end mapped to each calendar column.
E2: FQ2 FY24 (Dec-23) | F2: FQ3 FY24 (Mar-24) | G2: FQ4 FY24 (Jun-24) | H2: FQ1 FY25 (Sep-24) | I2: FQ2 FY25 (Dec-24) | J2: FQ3 FY25 (Mar-25) | K2: FQ4 FY25 (Jun-25) | L2: FQ1 FY26 (Sep-25) | M2: FQ2 FY26 (Dec-25) | N2: FQ3 FY26 (Mar-26) | O2: FQ4 FY26 (Jun-26)
A3: ID | B3: Item | C3: Unit | D3: Tag mix | E3: Q4'23* | F3: Q1'24 | G3: Q2'24 | H3: Q3'24 | I3: Q4'24 | J3: Q1'25 | K3: Q2'25 | L3: Q3'25 | M3: Q4'25 | N3: Q1'26 | O3: Q2'26 | P3: Source summary / notes
A4: I01 | B4: AI Cloud Services revenue (segment) | C4: $M | D4: Derived/Reported | E4: n/d | F4: 0.567 | G4: 2.538 | H4: 3.189 | I4: 2.661 | J4: 3.581 | K4: 6.963 | L4: 7.347 | M4: 17.298 | N4: 33.635 | O4: 70.515 | P4: 6-K FQ3 FY25 (Mar-25 qtr; IFRS) - interim FS / MD&A Ex.99.4 / PR, filed 2025-05; 10-K FY26 (FYE 30-Jun-2026), filed 2026-08-27; 10-Q FQ1 FY26 (Sep-25 qtr), filed 2025-11-06; 10-Q FQ2 FY26 (Dec-25 qtr), filed 2026-02-05; 10-Q FQ3 FY26 (Mar-26 qtr), filed 2026-05-07; 10-K FY25 (FYE 30-Jun-2025; first US GAAP annual; incl. unaudited quarterly table), filed 2025-08-28 | NOTE: KPI perimeter = AI Cloud Services segment only (all AI revenue generated in Canada through FY26 Q3 per 10-Q; Childress Texas from H2 CY26). 2024 quarters (FQ3-FQ4 FY24) are IFRS; from FY25 10-K onward US GAAP (FY24/FY25 recast).
A5: I02 | B5: Adj. EBITDA of KPI perimeter (AI segment) | C5: $M | D5: n/d | E5: n/d | F5: n/d | G5: n/d | H5: n/d | I5: n/d | J5: n/d | K5: n/d | L5: n/d | M5: n/d | N5: n/d | O5: n/d | P5: | NOTE: n/d: IREN reports Adj. EBITDA only company-wide (memo I47). Segment measure is gross profit excl. D&A (see K45).
A6: I03 | B6: Depreciation & amortization (company-wide, P&L) | C6: $M | D6: Derived/Reported | E6: n/d | F6: 8.692 | G6: 26.78 | H6: 33.931 | I6: 36.077 | J6: 47.311 | K6: 63.817 | L6: 85.226 | M6: 99.176 | N6: 121.245 | O6: 112.082 | P6: 6-K FQ3 FY24 (Mar-24 qtr; IFRS) - Ex.99.1 results PR / Ex.99.3 interim financial statements, filed 2024-05-15; Form 20-F FY24 (FYE 30-Jun-2024; IFRS), filed 2024-08-28; 10-Q FQ1 FY26 (Sep-25 qtr), filed 2025-11-06; 10-Q FQ3 FY26 (Mar-26 qtr), filed 2026-05-07; 10-K FY25 (FYE 30-Jun-2025; first US GAAP annual; incl. unaudited quarterly table), filed 2025-08-28; 10-K FY26 (FYE 30-Jun-2026), filed 2026-08-27 | NOTE: Company-wide (mining + AI + buildings); IREN does not allocate D&A to segments.
A7: I04 | B7: Cash capex (company-wide: PP&E net of hardware prepayments + computer/mining hardware incl. prepayments) | C7: $M | D7: Derived/Reported | E7: n/d | F7: n/d | G7: 296.6 | H7: 383.4 | I7: 187.6 | J7: 443.8 | K7: 357.9 | L7: 280.6 | M7: 719.1 | N7: 1355.3 | O7: 1978.2 | P7: Form 20-F FY24 (FYE 30-Jun-2024; IFRS), filed 2024-08-28; 10-Q FQ1 FY26 (Sep-25 qtr), filed 2025-11-06; 10-Q FQ2 FY26 (Dec-25 qtr), filed 2026-02-05; 10-Q FQ3 FY26 (Mar-26 qtr), filed 2026-05-07; 10-K FY25 (FYE 30-Jun-2025; first US GAAP annual; incl. unaudited quarterly table), filed 2025-08-28; 10-K FY26 (FYE 30-Jun-2026), filed 2026-08-27 | NOTE: Company-wide; not split AI vs mining. FY26 capex is predominantly AI (Childress Horizon GPU halls, BC ASIC->GPU conversions, GPUs) but no split is disclosed.
A8: I05 | B8: Gross property, plant & equipment (EoP) | C8: $M | D8: Derived/Reported | E8: n/d | F8: 427.51 | G8: 538.026 | H8: 1010.401 | I8: 1288.15 | J8: 1699.48 | K8: 2112.2 | L8: 2396.859 | M8: 3553.7 | N8: 4987 | O8: 7663.316 | P8: 6-K FQ3 FY24 (Mar-24 qtr; IFRS) - Ex.99.1 results PR / Ex.99.3 interim financial statements, filed 2024-05-15; Form 20-F FY24 (FYE 30-Jun-2024; IFRS), filed 2024-08-28; 6-K FQ1 FY25 (Sep-24 qtr; IFRS) - interim FS + results PR, filed 2024-11; 6-K FQ2 FY25 (Dec-24 qtr; IFRS) - interim FS / MD&A Ex.99.4 / PR, filed 2025-02; 6-K FQ3 FY25 (Mar-25 qtr; IFRS) - interim FS / MD&A Ex.99.4 / PR, filed 2025-05; 10-K FY25 (FYE 30-Jun-2025; first US GAAP annual; incl. unaudited quarterly table), filed 2025-08-28; 10-Q FQ1 FY26 (Sep-25 qtr), filed 2025-11-06; 10-Q FQ2 FY26 (Dec-25 qtr), filed 2026-02-05; 10-Q FQ3 FY26 (Mar-26 qtr), filed 2026-05-07; 10-K FY26 (FYE 30-Jun-2026), filed 2026-08-27 | NOTE: IFRS (to Mar-25) shows accumulated impairment separately from gross; GAAP (Jun-25+) likewise ('Less: Impairment'). Basis break between Mar-25 and Jun-25.
A9: I06 | B9: Construction in progress / development assets (EoP; not in service) | C9: $M | D9: Reported | E9: n/d | F9: 76.904 | G9: 102.946 | H9: 153.625 | I9: 177.639 | J9: 213.763 | K9: 237.734 | L9: 464.832 | M9: 1038.321 | N9: 2089.371 | O9: 3657.072 | P9: 6-K FQ3 FY24 (Mar-24 qtr; IFRS) - Ex.99.1 results PR / Ex.99.3 interim financial statements, filed 2024-05-15; Form 20-F FY24 (FYE 30-Jun-2024; IFRS), filed 2024-08-28; 6-K FQ1 FY25 (Sep-24 qtr; IFRS) - interim FS + results PR, filed 2024-11; 6-K FQ2 FY25 (Dec-24 qtr; IFRS) - interim FS / MD&A Ex.99.4 / PR, filed 2025-02; 6-K FQ3 FY25 (Mar-25 qtr; IFRS) - interim FS / MD&A Ex.99.4 / PR, filed 2025-05; 10-K FY25 (FYE 30-Jun-2025; first US GAAP annual; incl. unaudited quarterly table), filed 2025-08-28; 10-Q FQ1 FY26 (Sep-25 qtr), filed 2025-11-06; 10-Q FQ2 FY26 (Dec-25 qtr), filed 2026-02-05; 10-Q FQ3 FY26 (Mar-26 qtr), filed 2026-05-07; 10-K FY26 (FYE 30-Jun-2026), filed 2026-08-27
A10: I07 | B10: Property, plant & equipment, net (EoP) | C10: $M | D10: Reported | E10: n/d | F10: 357.081 | G10: 441.371 | H10: 965.994 | I10: 1209.339 | J10: 1575.107 | K10: 1930.567 | L10: 2115.436 | M10: 3170.5 | N10: 4369.9 | O10: 6753.183 | P10: 6-K FQ3 FY24 (Mar-24 qtr; IFRS) - Ex.99.1 results PR / Ex.99.3 interim financial statements, filed 2024-05-15; Form 20-F FY24 (FYE 30-Jun-2024; IFRS), filed 2024-08-28; 6-K FQ1 FY25 (Sep-24 qtr; IFRS) - interim FS + results PR, filed 2024-11; 6-K FQ2 FY25 (Dec-24 qtr; IFRS) - interim FS / MD&A Ex.99.4 / PR, filed 2025-02; 6-K FQ3 FY25 (Mar-25 qtr; IFRS) - interim FS / MD&A Ex.99.4 / PR, filed 2025-05; 10-K FY25 (FYE 30-Jun-2025; first US GAAP annual; incl. unaudited quarterly table), filed 2025-08-28; 10-Q FQ1 FY26 (Sep-25 qtr), filed 2025-11-06; 10-Q FQ2 FY26 (Dec-25 qtr), filed 2026-02-05; 10-Q FQ3 FY26 (Mar-26 qtr), filed 2026-05-07; 10-K FY26 (FYE 30-Jun-2026), filed 2026-08-27
A11: I08 | B11: Technology equipment, gross (CRWV row; n/d - see I31 GPU hardware, I48 mining hardware) | C11: $M | D11: n/d | E11: n/d | F11: n/d | G11: n/d | H11: n/d | I11: n/d | J11: n/d | K11: n/d | L11: n/d | M11: n/d | N11: n/d | O11: n/d
A12: I09 | B12: Operating AI Cloud capacity, reported (EoP) | C12: MW | D12: Reported | E12: n/d | F12: n/d | G12: n/d | H12: n/d | I12: n/d | J12: n/d | K12: n/d | L12: n/d | M12: n/d | N12: n/d | O12: 40 | P12: 10-K FY26 (FYE 30-Jun-2026), filed 2026-08-27 | NOTE: Only AI MW figure IREN has disclosed. Basis (IT vs gross) not stated. Earlier quarters estimated from GPUs (I09E). Dec-25/Mar-26: n/d (GPU counts no longer disclosed; Horizon 1 at Childress (50MW IT) delivered to Microsoft only after FY26 per FY26 PR).
A13: I10 | B13: Contracted AI MW (EoP) | C13: MW | D13: n/d | E13: n/d | F13: n/d | G13: n/d | H13: n/d | I13: n/d | J13: n/d | K13: n/d | L13: n/d | M13: n/d | N13: n/d | O13: n/d | P13: | NOTE: n/d as a metric. FY26 PR: Microsoft contract = four 50MW (IT) liquid-cooled 'Horizon' deployments at Childress (=200MW IT, D) - not entered because other contracts' MW are not disclosed.
A14: I11 | B14: AI GPUs operating, reported (EoP) | C14: GPUs | D14: Reported | E14: n/d | F14: 816 | G14: 816 | H14: n/d | I14: 1896 | J14: 1896 | K14: 1900 | L14: 2100 | M14: n/d | N14: n/d | O14: n/d | P14: 6-K FQ3 FY24 (Mar-24 qtr; IFRS) - Ex.99.1 results PR / Ex.99.3 interim financial statements, filed 2024-05-15; FY24 results PR (6-K Ex.99.1, 2024-08-28); 6-K FQ3 FY25 (Mar-25 qtr; IFRS) - interim FS / MD&A Ex.99.4 / PR, filed 2025-05; 10-K FY25 (FYE 30-Jun-2025; first US GAAP annual; incl. unaudited quarterly table), filed 2025-08-28; 10-Q FQ1 FY26 (Sep-25 qtr), filed 2025-11-06 | NOTE: Dec-25 onward IREN discloses only GPUs 'installed or contracted/on order' (e.g., 140k expansion target, Q1 FY26 PR) - not operating counts. Sep-24 estimated in I11E.
A15: I12 | B15: Hopper price proxy: IREN's own revenue assumption ($/GPU-hr at 100% uptime) | C15: $/GPU-hr | D15: Estimated | E15: n/d | F15: 2 | G15: 2 | H15: 2 | I15: 2 | J15: 2 | K15: 2 | L15: 2 | M15: n/d | N15: n/d | O15: n/d | P15: 6-K FQ1 FY25 (Sep-24 qtr; IFRS) - interim FS + results PR, filed 2024-11 | NOTE: IREN publishes no on-demand list price ('contact sales'). The $2.00 is IREN's own assumed realized rate, so K09 for IREN is closer to a utilization ratio than CRWV/Nebius (list-based). Not comparable 1:1.
A16: I13 | B16: Blackwell list price | C16: $/GPU-hr | D16: n/d | E16: n/d | F16: n/d | G16: n/d | H16: n/d | I16: n/d | J16: n/d | K16: n/d | L16: n/d | M16: n/d | N16: n/d | O16: n/d | P16: | NOTE: No public list price.
A17: I14 | B17: RPO (ASC 606, EoP) | C17: $B | D17: Reported | E17: n/d | F17: n/d | G17: n/d | H17: n/d | I17: n/d | J17: n/d | K17: n/d | L17: 0.195027 | M17: 0.289411 | N17: 0.710272 | O17: 5.1 | P17: 10-Q FQ1 FY26 (Sep-25 qtr), filed 2025-11-06; 10-Q FQ2 FY26 (Dec-25 qtr), filed 2026-02-05; 10-Q FQ3 FY26 (Mar-26 qtr), filed 2026-05-07; 10-K FY26 (FYE 30-Jun-2026), filed 2026-08-27 | NOTE: Pre-Sep-25 n/d (no RPO disclosure under IFRS 6-Ks / FY25 10-K). Microsoft $9.7B TCV enters RPO only as tranches are delivered and accepted (nil at Dec-25/Mar-26).
A18: I15 | B18: Contracted backlog incl. non-RPO (RPO + undelivered Microsoft TCV / ASC 842 lease value) | C18: $B | D18: Derived/Reported | E18: n/d | F18: n/d | G18: n/d | H18: n/d | I18: n/d | J18: n/d | K18: n/d | L18: n/d | M18: 9.989 | N18: 10.41 | O18: 16.6 | P18: 10-Q FQ2 FY26 (Dec-25 qtr), filed 2026-02-05; 10-Q FQ3 FY26 (Mar-26 qtr), filed 2026-05-07; 10-K FY26 (FYE 30-Jun-2026), filed 2026-08-27 | NOTE: Dec-25/Mar-26 are lower bounds (other signed-not-delivered contracts not quantified in filings).
A19: I16 | B19: RPO % expected to be recognized within 24 months | C19: % | D19: Derived | E19: n/d | F19: n/d | G19: n/d | H19: n/d | I19: n/d | J19: n/d | K19: n/d | L19: 95.8 | M19: 98.7 | N19: 80.7 | O19: 43.1 | P19: 10-Q FQ1 FY26 (Sep-25 qtr), filed 2025-11-06; 10-Q FQ2 FY26 (Dec-25 qtr), filed 2026-02-05; 10-Q FQ3 FY26 (Mar-26 qtr), filed 2026-05-07; 10-K FY26 (FYE 30-Jun-2026), filed 2026-08-27
A20: I17 | B20: Largest customer, % of quarter revenue | C20: % | D20: n/d | E20: n/d | F20: n/d | G20: n/d | H20: n/d | I20: n/d | J20: n/d | K20: n/d | L20: n/d | M20: n/d | N20: n/d | O20: n/d | P20: | NOTE: n/d for AI Cloud. Mining: 97%/98%/100% of FY25/FY24/FY23 revenue via 3/3/2 mining pool operators (FY25 10-K) - pools are not end-customers in the CRWV sense. Microsoft ($9.7B) and NVIDIA ($3.4B) are the 'substantial majority' of contracted value at Jun-26 (backlog, not revenue).
A21: I18 | B21: 2nd-largest customer % | C21: % | D21: n/d | E21: n/d | F21: n/d | G21: n/d | H21: n/d | I21: n/d | J21: n/d | K21: n/d | L21: n/d | M21: n/d | N21: n/d | O21: n/d
A22: I19 | B22: 3rd-largest customer % | C22: % | D22: n/d | E22: n/d | F22: n/d | G22: n/d | H22: n/d | I22: n/d | J22: n/d | K22: n/d | L22: n/d | M22: n/d | N22: n/d | O22: n/d
A23: I20 | B23: Customers >=10% of revenue (count) | C23: # | D23: n/d | E23: n/d | F23: n/d | G23: n/d | H23: n/d | I23: n/d | J23: n/d | K23: n/d | L23: n/d | M23: n/d | N23: n/d | O23: n/d
A24: I21 | B24: Finance expense (P&L; incl. issuance-cost amortization & lease interest) | C24: $M | D24: Derived/Reported | E24: n/d | F24: n/d | G24: n/d | H24: 0.022 | I24: 6.253 | J24: 4.119 | K24: 5.182 | L24: 9.28 | M24: 10.668 | N24: 14.837 | O24: 24.466 | P24: 10-Q FQ1 FY26 (Sep-25 qtr), filed 2025-11-06; 6-K FQ2 FY25 (Dec-24 qtr; IFRS) - interim FS / MD&A Ex.99.4 / PR, filed 2025-02; 10-Q FQ3 FY26 (Mar-26 qtr), filed 2026-05-07; 10-K FY25 (FYE 30-Jun-2025; first US GAAP annual; incl. unaudited quarterly table), filed 2025-08-28; 10-K FY26 (FYE 30-Jun-2026), filed 2026-08-27 | NOTE: Not contractual coupon interest (IREN gives contractual interest only annually: FY26 $37.2M, FY25 $9.1M per 10-K debt note). Zero debt Mar-24-Sep-24.
A25: I22 | B25: Capitalized interest | C25: $M | D25: n/d | E25: n/d | F25: n/d | G25: n/d | H25: n/d | I25: n/d | J25: n/d | K25: n/d | L25: n/d | M25: n/d | N25: n/d | O25: n/d | P25: | NOTE: Not disclosed quarterly.
A26: I23 | B26: Total debt principal (EoP; excl. finance leases) | C26: $M | D26: Reported | E26: n/d | F26: 0 | G26: 0 | H26: 0 | I26: 440 | J26: 440 | K26: 990 | L26: 990 | M26: 3745.699 | N26: 3745.699 | O26: 7705.649 | P26: 6-K FQ3 FY24 (Mar-24 qtr; IFRS) - Ex.99.1 results PR / Ex.99.3 interim financial statements, filed 2024-05-15; Form 20-F FY24 (FYE 30-Jun-2024; IFRS), filed 2024-08-28; 6-K FQ1 FY25 (Sep-24 qtr; IFRS) - interim FS + results PR, filed 2024-11; 6-K FQ2 FY25 (Dec-24 qtr; IFRS) - interim FS / MD&A Ex.99.4 / PR, filed 2025-02; 6-K FQ3 FY25 (Mar-25 qtr; IFRS) - interim FS / MD&A Ex.99.4 / PR, filed 2025-05; 10-K FY25 (FYE 30-Jun-2025; first US GAAP annual; incl. unaudited quarterly table), filed 2025-08-28; 10-Q FQ1 FY26 (Sep-25 qtr), filed 2025-11-06; 10-Q FQ2 FY26 (Dec-25 qtr), filed 2026-02-05; 10-Q FQ3 FY26 (Mar-26 qtr), filed 2026-05-07; 10-K FY26 (FYE 30-Jun-2026), filed 2026-08-27
A27: I24 | B27: Company-reported weighted average interest rate | C27: % | D27: n/d | E27: n/d | F27: n/d | G27: n/d | H27: n/d | I27: n/d | J27: n/d | K27: n/d | L27: n/d | M27: n/d | N27: n/d | O27: n/d
A28: I25 | B28: Company-definition capex | C28: $M | D28: n/d | E28: n/d | F28: n/d | G28: n/d | H28: n/d | I28: n/d | J28: n/d | K28: n/d | L28: n/d | M28: n/d | N28: n/d | O28: n/d
A29: I26 | B29: Days in quarter | C29: days | D29: Reported | E29: n/d | F29: 91 | G29: 91 | H29: 92 | I29: 92 | J29: 90 | K29: 91 | L29: 92 | M29: 92 | N29: 90 | O29: 91 | P29: calendar
A30: I27 | B30: Data center sites (operating) | C30: # | D30: n/d | E30: n/d | F30: n/d | G30: n/d | H30: n/d | I30: n/d | J30: n/d | K30: n/d | L30: n/d | M30: n/d | N30: n/d | O30: n/d
A31: I28 | B31: Useful life - HPC / GPU hardware | C31: years | D31: Reported | E31: n/d | F31: 5 | G31: 5 | H31: 5 | I31: 5 | J31: 5 | K31: 5 | L31: 5 | M31: 5 | N31: 5 | O31: 5 | P31: Form 20-F FY24 (FYE 30-Jun-2024; IFRS), filed 2024-08-28; 10-K FY25 (FYE 30-Jun-2025; first US GAAP annual; incl. unaudited quarterly table), filed 2025-08-28; 10-K FY26 (FYE 30-Jun-2026), filed 2026-08-27 | NOTE: Mining hardware 4 yrs (S19j Pro/S19 Pro shortened to 2 yrs in FY24); buildings 20; other 3-10. No change to HPC life disclosed FY24-FY26.
A32: I29 | B32: Company-reported GPU utilization | C32: % | D32: n/d | E32: n/d | F32: n/d | G32: n/d | H32: n/d | I32: n/d | J32: n/d | K32: n/d | L32: n/d | M32: n/d | N32: n/d | O32: n/d
A33: I30 | B33: RPO % expected to be recognized within 12 months | C33: % | D33: Derived | E33: n/d | F33: n/d | G33: n/d | H33: n/d | I33: n/d | J33: n/d | K33: n/d | L33: 47.9 | M33: 51.9 | N33: 43.4 | O33: 17.6 | P33: 10-Q FQ1 FY26 (Sep-25 qtr), filed 2025-11-06; 10-Q FQ2 FY26 (Dec-25 qtr), filed 2026-02-05; 10-Q FQ3 FY26 (Mar-26 qtr), filed 2026-05-07; 10-K FY26 (FYE 30-Jun-2026), filed 2026-08-27
A34: I31 | B34: GPU / HPC hardware, gross at cost (EoP; owned, excl. finance-lease ROU) | C34: $M | D34: Reported | E34: n/d | F34: 29.603 | G34: 33.315 | H34: 33.678 | I34: 68.19 | J34: 69.406 | K34: 76.001 | L34: 106.047 | M34: 550.636 | N34: 811.39 | O34: 2034.811 | P34: 6-K FQ3 FY24 (Mar-24 qtr; IFRS) - Ex.99.1 results PR / Ex.99.3 interim financial statements, filed 2024-05-15; Form 20-F FY24 (FYE 30-Jun-2024; IFRS), filed 2024-08-28; 6-K FQ1 FY25 (Sep-24 qtr; IFRS) - interim FS + results PR, filed 2024-11; 6-K FQ2 FY25 (Dec-24 qtr; IFRS) - interim FS / MD&A Ex.99.4 / PR, filed 2025-02; 6-K FQ3 FY25 (Mar-25 qtr; IFRS) - interim FS / MD&A Ex.99.4 / PR, filed 2025-05; 10-K FY25 (FYE 30-Jun-2025; first US GAAP annual; incl. unaudited quarterly table), filed 2025-08-28; 10-Q FQ1 FY26 (Sep-25 qtr), filed 2025-11-06; 10-Q FQ2 FY26 (Dec-25 qtr), filed 2026-02-05; 10-Q FQ3 FY26 (Mar-26 qtr), filed 2026-05-07; 10-K FY26 (FYE 30-Jun-2026), filed 2026-08-27 | NOTE: Excludes GPU finance-lease right-of-use assets (I49) and GPUs in CIP/prepayments. In-service AI hardware, so the cleanest AI-only asset base.
A35: I32 | B35: AI Cloud segment cost of revenue (excl. D&A) | C35: $M | D35: Derived/Reported | E35: n/d | F35: n/d | G35: n/d | H35: 0.232 | I35: 0.275 | J35: 0.336 | K35: 0.476 | L35: 0.728 | M35: 2.395 | N35: 4.597 | O35: 9.212 | P35: 10-Q FQ1 FY26 (Sep-25 qtr), filed 2025-11-06; 10-Q FQ2 FY26 (Dec-25 qtr), filed 2026-02-05; 10-Q FQ3 FY26 (Mar-26 qtr), filed 2026-05-07; 10-K FY25 (FYE 30-Jun-2025; first US GAAP annual; incl. unaudited quarterly table), filed 2025-08-28; 10-K FY26 (FYE 30-Jun-2026), filed 2026-08-27 | NOTE: Mostly electricity. IFRS 2024 quarters: no segment cost split.
A36: I40 | B36: Bitcoin mining revenue (segment) | C36: $M | D36: Derived/Reported | E36: n/d | F36: 53.383 | G36: 54.26 | H36: 49.575 | I36: 113.483 | J36: 141.242 | K36: 180.33 | L36: 232.948 | M36: 167.394 | N36: 111.16 | O36: 66.71 | P36: 6-K FQ3 FY25 (Mar-25 qtr; IFRS) - interim FS / MD&A Ex.99.4 / PR, filed 2025-05; 10-K FY26 (FYE 30-Jun-2026), filed 2026-08-27; 10-Q FQ1 FY26 (Sep-25 qtr), filed 2025-11-06; 10-Q FQ2 FY26 (Dec-25 qtr), filed 2026-02-05; 10-Q FQ3 FY26 (Mar-26 qtr), filed 2026-05-07; 10-K FY25 (FYE 30-Jun-2025; first US GAAP annual; incl. unaudited quarterly table), filed 2025-08-28
A37: I42 | B37: Accumulated impairment of PP&E (EoP) | C37: $M | D37: Reported | E37: n/d | F37: 25.714 | G37: 25.605 | H37: 6.941 | I37: 6.934 | J37: 6.942 | K37: 0.385 | L37: 16.177 | M37: 36.3 | N37: 171.5 | O37: 484.491 | P37: 6-K FQ3 FY24 (Mar-24 qtr; IFRS) - Ex.99.1 results PR / Ex.99.3 interim financial statements, filed 2024-05-15; Form 20-F FY24 (FYE 30-Jun-2024; IFRS), filed 2024-08-28; 6-K FQ1 FY25 (Sep-24 qtr; IFRS) - interim FS + results PR, filed 2024-11; 6-K FQ2 FY25 (Dec-24 qtr; IFRS) - interim FS / MD&A Ex.99.4 / PR, filed 2025-02; 6-K FQ3 FY25 (Mar-25 qtr; IFRS) - interim FS / MD&A Ex.99.4 / PR, filed 2025-05; 10-K FY25 (FYE 30-Jun-2025; first US GAAP annual; incl. unaudited quarterly table), filed 2025-08-28; 10-Q FQ1 FY26 (Sep-25 qtr), filed 2025-11-06; 10-Q FQ2 FY26 (Dec-25 qtr), filed 2026-02-05; 10-Q FQ3 FY26 (Mar-26 qtr), filed 2026-05-07; 10-K FY26 (FYE 30-Jun-2026), filed 2026-08-27
A38: I43 | B38: Total operating data-center capacity, company (all uses; gross MW) | C38: MW | D38: Derived/Reported | E38: n/d | F38: 260 | G38: 260 | H38: 360 | I38: 510 | J38: 660 | K38: 810 | L38: 810 | M38: 810 | N38: n/d | O38: 420 | P38: 6-K FQ3 FY24 (Mar-24 qtr; IFRS) - Ex.99.1 results PR / Ex.99.3 interim financial statements, filed 2024-05-15; Form 20-F FY24 (FYE 30-Jun-2024; IFRS), filed 2024-08-28; FY24 results PR (6-K Ex.99.1, 2024-08-28); 6-K FQ2 FY25 (Dec-24 qtr; IFRS) - interim FS / MD&A Ex.99.4 / PR, filed 2025-02; 6-K FQ3 FY25 (Mar-25 qtr; IFRS) - interim FS / MD&A Ex.99.4 / PR, filed 2025-05; 10-K FY25 (FYE 30-Jun-2025; first US GAAP annual; incl. unaudited quarterly table), filed 2025-08-28; 10-Q FQ1 FY26 (Sep-25 qtr), filed 2025-11-06; 10-Q FQ2 FY26 (Dec-25 qtr), filed 2026-02-05; 10-K FY26 (FYE 30-Jun-2026), filed 2026-08-27 | NOTE: Several values are boilerplate 'as of PR date' (5-7 weeks after quarter-end). Gross/grid basis; AI 40MW basis unstated -> sum is approximate.
A39: I44 | B39: Bitcoin mining capacity (MW), reported | C39: MW | D39: Reported | E39: n/d | F39: n/d | G39: n/d | H39: n/d | I39: n/d | J39: n/d | K39: n/d | L39: n/d | M39: n/d | N39: n/d | O39: 380 | P39: 10-K FY26 (FYE 30-Jun-2026), filed 2026-08-27
A40: I45 | B40: Installed hashrate (EoP) | C40: EH/s | D40: Reported | E40: n/d | F40: 10 | G40: 10 | H40: 21 | I40: 31 | J40: 37 | K40: 50 | L40: 50 | M40: 46 | N40: 38 | O40: 23.2 | P40: 6-K FQ3 FY24 (Mar-24 qtr; IFRS) - Ex.99.1 results PR / Ex.99.3 interim financial statements, filed 2024-05-15; Form 20-F FY24 (FYE 30-Jun-2024; IFRS), filed 2024-08-28; 6-K FQ1 FY25 (Sep-24 qtr; IFRS) - interim FS + results PR, filed 2024-11; 6-K FQ2 FY25 (Dec-24 qtr; IFRS) - interim FS / MD&A Ex.99.4 / PR, filed 2025-02; 6-K FQ3 FY25 (Mar-25 qtr; IFRS) - interim FS / MD&A Ex.99.4 / PR, filed 2025-05; 10-K FY25 (FYE 30-Jun-2025; first US GAAP annual; incl. unaudited quarterly table), filed 2025-08-28; 10-Q FQ1 FY26 (Sep-25 qtr), filed 2025-11-06; 10-Q FQ2 FY26 (Dec-25 qtr), filed 2026-02-05; 10-Q FQ3 FY26 (Mar-26 qtr), filed 2026-05-07; 10-K FY26 (FYE 30-Jun-2026), filed 2026-08-27
A41: I46 | B41: Secured grid-connected power (company) | C41: MW | D41: Reported | E41: n/d | F41: 2160 | G41: 2310 | H41: 2310 | I41: 2310 | J41: 2910 | K41: 2910 | L41: 3000 | M41: 4500 | N41: 4510 | O41: 5000 | P41: 6-K FQ3 FY24 (Mar-24 qtr; IFRS) - Ex.99.1 results PR / Ex.99.3 interim financial statements, filed 2024-05-15; FY24 results PR (6-K Ex.99.1, 2024-08-28); 6-K FQ1 FY25 (Sep-24 qtr; IFRS) - interim FS + results PR, filed 2024-11; 6-K FQ2 FY25 (Dec-24 qtr; IFRS) - interim FS / MD&A Ex.99.4 / PR, filed 2025-02; 6-K FQ3 FY25 (Mar-25 qtr; IFRS) - interim FS / MD&A Ex.99.4 / PR, filed 2025-05; 10-K FY25 (FYE 30-Jun-2025; first US GAAP annual; incl. unaudited quarterly table), filed 2025-08-28; Q1 FY26 results PR (8-K Ex.99.1, 2025-11-06); Q2 FY26 results PR (8-K Ex.99.1, 2026-02-05); Q3 FY26 results PR (8-K Ex.99.1, 2026-05-07); FY26 results PR (8-K Ex.99.1, 2026-08-27)
A42: I47 | B42: Adj. EBITDA, company-wide (non-GAAP) | C42: $M | D42: Derived/Reported | E42: n/d | F42: 21.8 | G42: 12.2 | H42: 2.5 | I42: 62.6 | J42: 83.3 | K42: 121.9 | L42: 91.7 | M42: 75.3 | N42: 59.5 | O42: 19.2 | P42: 6-K FQ3 FY25 (Mar-25 qtr; IFRS) - interim FS / MD&A Ex.99.4 / PR, filed 2025-05; Form 20-F FY24 (FYE 30-Jun-2024; IFRS), filed 2024-08-28; Q1 FY26 results PR (8-K Ex.99.1, 2025-11-06); FY25 results PR (8-K Ex.99.1, 2025-08-28); Q2 FY26 results PR (8-K Ex.99.1, 2026-02-05); Q3 FY26 results PR (8-K Ex.99.1, 2026-05-07); FY26 results PR (8-K Ex.99.1, 2026-08-27) | NOTE: Company-wide incl. mining, SG&A, unallocated. Not used in K05.
A43: I48 | B43: Mining hardware, gross at cost (EoP) | C43: $M | D43: Reported | E43: n/d | F43: 144.623 | G43: 177.766 | H43: 521.755 | I43: 643.475 | J43: 877.934 | K43: 1135.584 | L43: 1134.032 | M43: 1079.663 | N43: 1041.767 | O43: 596.988 | P43: 6-K FQ3 FY24 (Mar-24 qtr; IFRS) - Ex.99.1 results PR / Ex.99.3 interim financial statements, filed 2024-05-15; Form 20-F FY24 (FYE 30-Jun-2024; IFRS), filed 2024-08-28; 6-K FQ1 FY25 (Sep-24 qtr; IFRS) - interim FS + results PR, filed 2024-11; 6-K FQ2 FY25 (Dec-24 qtr; IFRS) - interim FS / MD&A Ex.99.4 / PR, filed 2025-02; 6-K FQ3 FY25 (Mar-25 qtr; IFRS) - interim FS / MD&A Ex.99.4 / PR, filed 2025-05; 10-K FY25 (FYE 30-Jun-2025; first US GAAP annual; incl. unaudited quarterly table), filed 2025-08-28; 10-Q FQ1 FY26 (Sep-25 qtr), filed 2025-11-06; 10-Q FQ2 FY26 (Dec-25 qtr), filed 2026-02-05; 10-Q FQ3 FY26 (Mar-26 qtr), filed 2026-05-07; 10-K FY26 (FYE 30-Jun-2026), filed 2026-08-27
A44: I49 | B44: GPU finance-lease right-of-use assets, gross (EoP) | C44: $M | D44: Reported | E44: n/d | F44: n/d | G44: n/d | H44: n/d | I44: n/d | J44: n/d | K44: n/d | L44: n/d | M44: 160.042 | N44: 301.776 | O44: 301.848 | P44: 10-Q FQ2 FY26 (Dec-25 qtr), filed 2026-02-05; 10-Q FQ3 FY26 (Mar-26 qtr), filed 2026-05-07; 10-K FY26 (FYE 30-Jun-2026), filed 2026-08-27
A46: Parameters (estimation assumptions)
A47: P01 | B47: GB200 NVL72 GPUs per IT-MW (base) | C47: GPUs/MW | D47: Estimated | E47: 538 | P47: Nebius workspace: /workspace/nebius/capacity/gpu_mw_capex.xlsx (GPUsPerMW base IT-MW rows) / gpu_mw_capex.md s.1 - GPUsPerMW base IT-MW row (487/538/571)
A48: P03 | B48: Hopper HGX GPUs per IT-MW (base) | C48: GPUs/MW | D48: Estimated | E48: 713 | P48: Nebius workspace: /workspace/nebius/capacity/gpu_mw_capex.xlsx (GPUsPerMW base IT-MW rows) / gpu_mw_capex.md s.1 - GPUsPerMW base IT-MW row (665/713/813); IREN's own economics footnote assumes 1.25kW/GPU (= 800 GPUs/MW)
A50: Derived & estimated input rows (formulas)
A51: I11E | B51: AI GPUs incl. estimates (EoP) | C51: GPUs | D51: Derived/Estimated | E51: n/d | F51: =F14 -> 816 | G51: =G14 -> 816 | H51: =G14 -> 816 | I51: =I14 -> 1896 | J51: =J14 -> 1896 | K51: =K14 -> 1900 | L51: =L14 -> 2100 | M51: n/d | N51: n/d | O51: =O12*$E$47 -> 21520 | P51: Sep-24 ESTIMATED = Jun-24 816 (1,896 expansion went live ~Nov/Dec-24). Jun-26 ESTIMATED = 40 MW x GB200-class 538 GPUs/IT-MW (Nebius base) = ~21.5k; range 19.6k (GB300 491) to 32k (IREN 1.25kW/GPU). Dec-25/Mar-26 n/d.
A52: I11A | B52: Average AI GPUs in quarter | C52: GPUs | D52: Derived/Estimated | E52: n/d | F52: n/d | G52: =(F51+G51)/2 -> 816 | H52: =(G51+H51)/2 -> 816 | I52: =(H51+I51)/2 -> 1356 | J52: =(I51+J51)/2 -> 1896 | K52: =(J51+K51)/2 -> 1898 | L52: =(K51+L51)/2 -> 2000 | M52: n/d | N52: n/d | O52: n/d | P52: Average of I11E.
A53: I09E | B53: AI MW incl. estimates (EoP) | C53: MW | D53: Derived/Estimated | E53: n/d | F53: =F51/$E$48 -> 1.14446 | G53: =G51/$E$48 -> 1.14446 | H53: =H51/$E$48 -> 1.14446 | I53: =I51/$E$48 -> 2.6591865 | J53: =J51/$E$48 -> 2.6591865 | K53: =K51/$E$48 -> 2.6647966 | L53: =L51/$E$48 -> 2.9453015 | M53: n/d | N53: n/d | O53: =O12 -> 40 | P53: ESTIMATED to Sep-25 = operating GPUs / 713 Hopper GPUs per IT-MW (Nebius base); Jun-26 = reported 40MW. (IREN 1.25kW/GPU would give ~12% higher MW.)
A54: I09A | B54: Average AI MW in quarter | C54: MW | D54: Estimated | E54: n/d | F54: n/d | G54: =(F53+G53)/2 -> 1.14446 | H54: =(G53+H53)/2 -> 1.14446 | I54: =(H53+I53)/2 -> 1.9018233 | J54: =(I53+J53)/2 -> 2.6591865 | K54: =(J53+K53)/2 -> 2.6619916 | L54: =(K53+L53)/2 -> 2.8050491 | M54: n/d | N54: n/d | O54: n/d
A55: I09T4 | B55: AI MW added over trailing 4 quarters | C55: MW | D55: Estimated | E55: n/d | F55: n/d | G55: n/d | H55: n/d | I55: n/d | J55: =J53-F53 -> 1.5147265 | K55: =K53-G53 -> 1.5203366 | L55: =L53-H53 -> 1.8008415 | M55: n/d | N55: n/d | O55: =O53-K53 -> 37.335203 | P55: Jun-26: 40 (reported) - Jun-25 est. 2.7 = ~37.3 MW (Estimated).
A56: I12W | B56: Fleet-weighted price proxy | C56: $/GPU-hr | D56: Estimated | E56: n/d | F56: =F15 -> 2 | G56: =G15 -> 2 | H56: =H15 -> 2 | I56: =I15 -> 2 | J56: =J15 -> 2 | K56: =K15 -> 2 | L56: =L15 -> 2 | M56: n/d | N56: n/d | O56: n/d | P56: calc: I12 (all Hopper fleet through Sep-25).
A57: I05S | B57: In-service gross PP&E (gross - CIP - accumulated impairment, EoP) | C57: $M | D57: Derived | E57: n/d | F57: =F8-F9-F37 -> 324.892 | G57: =G8-G9-G37 -> 409.475 | H57: =H8-H9-H37 -> 849.835 | I57: =I8-I9-I37 -> 1103.577 | J57: =J8-J9-J37 -> 1478.775 | K57: =K8-K9-K37 -> 1874.081 | L57: =L8-L9-L37 -> 1915.85 | M57: =M8-M9-M37 -> 2479.079 | ... O57: =O8-O9-O37 -> 3521.753 | P57: Company-wide. Impairment deducted because IREN carries impaired mining hardware gross.
A58: I23A | B58: Average debt principal | C58: $M | D58: Derived | E58: n/d | F58: n/d | G58: =(F26+G26)/2 -> 0 | H58: =(G26+H26)/2 -> 0 | I58: =(H26+I26)/2 -> 220 | J58: =(I26+J26)/2 -> 440 | K58: =(J26+K26)/2 -> 715 | L58: =(K26+L26)/2 -> 990 | M58: =(L26+M26)/2 -> 2367.8495 | N58: =(M26+N26)/2 -> 3745.699 | O58: =(N26+O26)/2 -> 5725.674
A59: I41 | B59: Total revenue (AI + Bitcoin) | C59: $M | D59: Derived | E59: n/d | F59: =F4+F36 -> 53.95 | G59: =G4+G36 -> 56.798 | H59: =H4+H36 -> 52.764 | I59: =I4+I36 -> 116.144 | J59: =J4+J36 -> 144.823 | K59: =K4+K36 -> 187.293 | L59: =L4+L36 -> 240.295 | M59: =M4+M36 -> 184.692 | ... O59: =O4+O36 -> 137.225 | P59: Segment sum = consolidated revenue.
A60: I44E | B60: Bitcoin mining MW incl. estimates | C60: MW | D60: Derived/Estimated | E60: n/d | F60: =F38-F53 -> 258.85554 | G60: =G38-G53 -> 258.85554 | H60: =H38-H53 -> 358.85554 | I60: =I38-I53 -> 507.34081 | J60: =J38-J53 -> 657.34081 | K60: =K38-K53 -> 807.3352 | L60: =L38-L53 -> 807.0547 | M60: n/d | N60: n/d | O60: =O39 -> 380 | P60: ESTIMATED = total operating DC MW - est. AI MW (mixes gross and IT bases; AI share was <2% so error is small). Jun-26 reported 380MW.

Sheet Debt_Facilities
A1: Debt by facility - IREN (IREN) - AI Cloud perimeter. Principal ($M) and effective interest rate (%) as printed in each period-end debt table. Excludes leases. Weighted rates exclude facilities without a disclosed rate from the denominator.
A2: Effective rates as printed in the FY26 10-K debt note (Note 23) and FY26 10-Qs; for the 2029/2030 converts the same instrument-level effective rate is applied to earlier snapshots (Dec-24-Sep-25). Converts were partly repurchased in Dec-25 (2030: 440->212.3; 2029: 550->233.4). 'Other debt' has no disclosed rate and is excluded from weighted-rate denominators. Mar-24-Sep-24: no debt outstanding (FY24 contractual interest nil).
A4: Facility | B4: Category | C4: Mar-24 principal | D4: Mar-24 eff. rate % | E4: Jun-24 principal | F4: Jun-24 eff. rate % | G4: Sep-24 principal | H4: Sep-24 eff. rate % | I4: Dec-24 principal | J4: Dec-24 eff. rate % | K4: Mar-25 principal | L4: Mar-25 eff. rate % | M4: Jun-25 principal | N4: Jun-25 eff. rate % | O4: Sep-25 principal | P4: Sep-25 eff. rate % | Q4: Dec-25 principal | R4: Dec-25 eff. rate % | S4: Mar-26 principal | T4: Mar-26 eff. rate % | U4: Jun-26 principal | V4: Jun-26 eff. rate %
A5: 3.25% convertible senior notes due 2030 (issued Dec-24) | B5: Converts | I5: 440 | J5: 3.87 | K5: 440 | L5: 3.87 | M5: 440 | N5: 3.87 | O5: 440 | P5: 3.87 | Q5: 212.31 | R5: 3.87 | S5: 212.31 | T5: 3.87 | U5: 212.31 | V5: 3.87
A6: 3.50% convertible senior notes due 2029 (issued Jun-25) | B6: Converts | M6: 550 | N6: 4.22 | O6: 550 | P6: 4.22 | Q6: 233.389 | R6: 4.22 | S6: 233.389 | T6: 4.22 | U6: 233.389 | V6: 4.22
A7: 0.00% convertible senior notes due 2031 (issued Dec-25) | B7: Converts | Q7: 1000 | R7: 0.37 | S7: 1000 | T7: 0.37 | U7: 1000 | V7: 0.37
A8: 0.25% convertible senior notes due 2032 (issued Dec-25) | B8: Converts | Q8: 1150 | R8: 0.45 | S8: 1150 | T8: 0.45 | U8: 1150 | V8: 0.45
A9: 1.00% convertible senior notes due Jun-2033 (issued Dec-25) | B9: Converts | Q9: 1150 | R9: 1.18 | S9: 1150 | T9: 1.18 | U9: 1150 | V9: 1.18
A10: 1.00% convertible senior notes due Dec-2033 (issued FY26 H2) | B10: Converts | U10: 3000 | V10: 1.18
A11: GPU delayed-draw term loan (non-recourse, SOFR+2.25%; $1,545M facility) | B11: DDTL | U11: 413 | V11: 7.12
A12: USPP senior secured notes (5.96% coupon; $2,100M programme) | B12: Senior notes | U12: 525 | V12: 7.05
A13: Other debt (various) | B13: Other term loans | U13: 21.95
A15: Total principal | C15: =SUM(C5:C13) -> 0 | E15: =SUM(E5:E13) -> 0 | G15: =SUM(G5:G13) -> 0 | I15: =SUM(I5:I13) -> 440 | K15: =SUM(K5:K13) -> 440 | M15: =SUM(M5:M13) -> 990 | O15: =SUM(O5:O13) -> 990 | Q15: =SUM(Q5:Q13) -> 3745.699 | S15: =SUM(S5:S13) -> 3745.699 | U15: =SUM(U5:U13) -> 7705.649
A16: Check vs Inputs I23 (total debt principal) | C16: =C15-Inputs!F26 -> 0 | E16: =E15-Inputs!G26 -> 0 | G16: =G15-Inputs!H26 -> 0 | I16: =I15-Inputs!I26 -> 0 | K16: =K15-Inputs!J26 -> 0 | M16: =M15-Inputs!K26 -> 0 | O16: =O15-Inputs!L26 -> 0 | Q16: =Q15-Inputs!M26 -> 0 | S16: =S15-Inputs!N26 -> 0 | U16: =U15-Inputs!O26 -> 0
A17: WEIGHTED EFFECTIVE COST OF DEBT (principal-weighted, facilities with disclosed rate) | D17: =IFERROR(SUMPRODUCT(C5:C13,D5:D13)/SUMPRODUCT((D5:D13<>"")*C5:C13),"n/d") -> n/d | F17: =IFERROR(SUMPRODUCT(E5:E13,F5:F13)/SUMPRODUCT((F5:F13<>"")*E5:E13),"n/d") -> n/d | H17: =IFERROR(SUMPRODUCT(G5:G13,H5:H13)/SUMPRODUCT((H5:H13<>"")*G5:G13),"n/d") -> n/d | J17: =IFERROR(SUMPRODUCT(I5:I13,J5:J13)/SUMPRODUCT((J5:J13<>"")*I5:I13),"n/d") -> 3.87 | L17: =IFERROR(SUMPRODUCT(K5:K13,L5:L13)/SUMPRODUCT((L5:L13<>"")*K5:K13),"n/d") -> 3.87 | N17: =IFERROR(SUMPRODUCT(M5:M13,N5:N13)/SUMPRODUCT((N5:N13<>"")*M5:M13),"n/d") -> 4.0644444 | P17: =IFERROR(SUMPRODUCT(O5:O13,P5:P13)/SUMPRODUCT((P5:P13<>"")*O5:O13),"n/d") -> 4.0644444 | R17: =IFERROR(SUMPRODUCT(Q5:Q13,R5:R13)/SUMPRODUCT((R5:R13<>"")*Q5:Q13),"n/d") -> 1.0815181 | T17: =IFERROR(SUMPRODUCT(S5:S13,T5:T13)/SUMPRODUCT((T5:T13<>"")*S5:S13),"n/d") -> 1.0815181 | V17: =IFERROR(SUMPRODUCT(U5:U13,V5:V13)/SUMPRODUCT((V5:V13<>"")*U5:U13),"n/d") -> 1.8523437
A18: DDTL: principal / weighted eff. rate | C18: =SUMIF($B$5:$B$13,"DDTL",C5:C13) -> 0 | D18: =IFERROR(SUMPRODUCT(($B$5:$B$13="DDTL")*C5:C13*D5:D13)/SUMPRODUCT(($B$5:$B$13="DDTL")*(D5:D13<>"")*C5:C13),"n/d") -> n/d | E18: =SUMIF($B$5:$B$13,"DDTL",E5:E13) -> 0 | F18: =IFERROR(SUMPRODUCT(($B$5:$B$13="DDTL")*E5:E13*F5:F13)/SUMPRODUCT(($B$5:$B$13="DDTL")*(F5:F13<>"")*E5:E13),"n/d") -> n/d | G18: =SUMIF($B$5:$B$13,"DDTL",G5:G13) -> 0 | H18: =IFERROR(SUMPRODUCT(($B$5:$B$13="DDTL")*G5:G13*H5:H13)/SUMPRODUCT(($B$5:$B$13="DDTL")*(H5:H13<>"")*G5:G13),"n/d") -> n/d | I18: =SUMIF($B$5:$B$13,"DDTL",I5:I13) -> 0 | J18: =IFERROR(SUMPRODUCT(($B$5:$B$13="DDTL")*I5:I13*J5:J13)/SUMPRODUCT(($B$5:$B$13="DDTL")*(J5:J13<>"")*I5:I13),"n/d") -> n/d | K18: =SUMIF($B$5:$B$13,"DDTL",K5:K13) -> 0 | L18: =IFERROR(SUMPRODUCT(($B$5:$B$13="DDTL")*K5:K13*L5:L13)/SUMPRODUCT(($B$5:$B$13="DDTL")*(L5:L13<>"")*K5:K13),"n/d") -> n/d | M18: =SUMIF($B$5:$B$13,"DDTL",M5:M13) -> 0 | N18: =IFERROR(SUMPRODUCT(($B$5:$B$13="DDTL")*M5:M13*N5:N13)/SUMPRODUCT(($B$5:$B$13="DDTL")*(N5:N13<>"")*M5:M13),"n/d") -> n/d | O18: =SUMIF($B$5:$B$13,"DDTL",O5:O13) -> 0 | P18: =IFERROR(SUMPRODUCT(($B$5:$B$13="DDTL")*O5:O13*P5:P13)/SUMPRODUCT(($B$5:$B$13="DDTL")*(P5:P13<>"")*O5:O13),"n/d") -> n/d | Q18: =SUMIF($B$5:$B$13,"DDTL",Q5:Q13) -> 0 | R18: =IFERROR(SUMPRODUCT(($B$5:$B$13="DDTL")*Q5:Q13*R5:R13)/SUMPRODUCT(($B$5:$B$13="DDTL")*(R5:R13<>"")*Q5:Q13),"n/d") -> n/d | S18: =SUMIF($B$5:$B$13,"DDTL",S5:S13) -> 0 | T18: =IFERROR(SUMPRODUCT(($B$5:$B$13="DDTL")*S5:S13*T5:T13)/SUMPRODUCT(($B$5:$B$13="DDTL")*(T5:T13<>"")*S5:S13),"n/d") -> n/d | U18: =SUMIF($B$5:$B$13,"DDTL",U5:U13) -> 413 | V18: =IFERROR(SUMPRODUCT(($B$5:$B$13="DDTL")*U5:U13*V5:V13)/SUMPRODUCT(($B$5:$B$13="DDTL")*(V5:V13<>"")*U5:U13),"n/d") -> 7.12
A19: Senior notes: principal / weighted eff. rate | C19: =SUMIF($B$5:$B$13,"Senior notes",C5:C13) -> 0 | D19: =IFERROR(SUMPRODUCT(($B$5:$B$13="Senior notes")*C5:C13*D5:D13)/SUMPRODUCT(($B$5:$B$13="Senior notes")*(D5:D13<>"")*C5:C13),"n/d") -> n/d | E19: =SUMIF($B$5:$B$13,"Senior notes",E5:E13) -> 0 | F19: =IFERROR(SUMPRODUCT(($B$5:$B$13="Senior notes")*E5:E13*F5:F13)/SUMPRODUCT(($B$5:$B$13="Senior notes")*(F5:F13<>"")*E5:E13),"n/d") -> n/d | G19: =SUMIF($B$5:$B$13,"Senior notes",G5:G13) -> 0 | H19: =IFERROR(SUMPRODUCT(($B$5:$B$13="Senior notes")*G5:G13*H5:H13)/SUMPRODUCT(($B$5:$B$13="Senior notes")*(H5:H13<>"")*G5:G13),"n/d") -> n/d | I19: =SUMIF($B$5:$B$13,"Senior notes",I5:I13) -> 0 | J19: =IFERROR(SUMPRODUCT(($B$5:$B$13="Senior notes")*I5:I13*J5:J13)/SUMPRODUCT(($B$5:$B$13="Senior notes")*(J5:J13<>"")*I5:I13),"n/d") -> n/d | K19: =SUMIF($B$5:$B$13,"Senior notes",K5:K13) -> 0 | L19: =IFERROR(SUMPRODUCT(($B$5:$B$13="Senior notes")*K5:K13*L5:L13)/SUMPRODUCT(($B$5:$B$13="Senior notes")*(L5:L13<>"")*K5:K13),"n/d") -> n/d | M19: =SUMIF($B$5:$B$13,"Senior notes",M5:M13) -> 0 | N19: =IFERROR(SUMPRODUCT(($B$5:$B$13="Senior notes")*M5:M13*N5:N13)/SUMPRODUCT(($B$5:$B$13="Senior notes")*(N5:N13<>"")*M5:M13),"n/d") -> n/d | O19: =SUMIF($B$5:$B$13,"Senior notes",O5:O13) -> 0 | P19: =IFERROR(SUMPRODUCT(($B$5:$B$13="Senior notes")*O5:O13*P5:P13)/SUMPRODUCT(($B$5:$B$13="Senior notes")*(P5:P13<>"")*O5:O13),"n/d") -> n/d | Q19: =SUMIF($B$5:$B$13,"Senior notes",Q5:Q13) -> 0 | R19: =IFERROR(SUMPRODUCT(($B$5:$B$13="Senior notes")*Q5:Q13*R5:R13)/SUMPRODUCT(($B$5:$B$13="Senior notes")*(R5:R13<>"")*Q5:Q13),"n/d") -> n/d | S19: =SUMIF($B$5:$B$13,"Senior notes",S5:S13) -> 0 | T19: =IFERROR(SUMPRODUCT(($B$5:$B$13="Senior notes")*S5:S13*T5:T13)/SUMPRODUCT(($B$5:$B$13="Senior notes")*(T5:T13<>"")*S5:S13),"n/d") -> n/d | U19: =SUMIF($B$5:$B$13,"Senior notes",U5:U13) -> 525 | V19: =IFERROR(SUMPRODUCT(($B$5:$B$13="Senior notes")*U5:U13*V5:V13)/SUMPRODUCT(($B$5:$B$13="Senior notes")*(V5:V13<>"")*U5:U13),"n/d") -> 7.05
A20: Converts: principal / weighted eff. rate | C20: =SUMIF($B$5:$B$13,"Converts",C5:C13) -> 0 | D20: =IFERROR(SUMPRODUCT(($B$5:$B$13="Converts")*C5:C13*D5:D13)/SUMPRODUCT(($B$5:$B$13="Converts")*(D5:D13<>"")*C5:C13),"n/d") -> n/d | E20: =SUMIF($B$5:$B$13,"Converts",E5:E13) -> 0 | F20: =IFERROR(SUMPRODUCT(($B$5:$B$13="Converts")*E5:E13*F5:F13)/SUMPRODUCT(($B$5:$B$13="Converts")*(F5:F13<>"")*E5:E13),"n/d") -> n/d | G20: =SUMIF($B$5:$B$13,"Converts",G5:G13) -> 0 | H20: =IFERROR(SUMPRODUCT(($B$5:$B$13="Converts")*G5:G13*H5:H13)/SUMPRODUCT(($B$5:$B$13="Converts")*(H5:H13<>"")*G5:G13),"n/d") -> n/d | I20: =SUMIF($B$5:$B$13,"Converts",I5:I13) -> 440 | J20: =IFERROR(SUMPRODUCT(($B$5:$B$13="Converts")*I5:I13*J5:J13)/SUMPRODUCT(($B$5:$B$13="Converts")*(J5:J13<>"")*I5:I13),"n/d") -> 3.87 | K20: =SUMIF($B$5:$B$13,"Converts",K5:K13) -> 440 | L20: =IFERROR(SUMPRODUCT(($B$5:$B$13="Converts")*K5:K13*L5:L13)/SUMPRODUCT(($B$5:$B$13="Converts")*(L5:L13<>"")*K5:K13),"n/d") -> 3.87 | M20: =SUMIF($B$5:$B$13,"Converts",M5:M13) -> 990 | N20: =IFERROR(SUMPRODUCT(($B$5:$B$13="Converts")*M5:M13*N5:N13)/SUMPRODUCT(($B$5:$B$13="Converts")*(N5:N13<>"")*M5:M13),"n/d") -> 4.0644444 | O20: =SUMIF($B$5:$B$13,"Converts",O5:O13) -> 990 | P20: =IFERROR(SUMPRODUCT(($B$5:$B$13="Converts")*O5:O13*P5:P13)/SUMPRODUCT(($B$5:$B$13="Converts")*(P5:P13<>"")*O5:O13),"n/d") -> 4.0644444 | Q20: =SUMIF($B$5:$B$13,"Converts",Q5:Q13) -> 3745.699 | R20: =IFERROR(SUMPRODUCT(($B$5:$B$13="Converts")*Q5:Q13*R5:R13)/SUMPRODUCT(($B$5:$B$13="Converts")*(R5:R13<>"")*Q5:Q13),"n/d") -> 1.0815181 | S20: =SUMIF($B$5:$B$13,"Converts",S5:S13) -> 3745.699 | T20: =IFERROR(SUMPRODUCT(($B$5:$B$13="Converts")*S5:S13*T5:T13)/SUMPRODUCT(($B$5:$B$13="Converts")*(T5:T13<>"")*S5:S13),"n/d") -> 1.0815181 | U20: =SUMIF($B$5:$B$13,"Converts",U5:U13) -> 6745.699 | V20: =IFERROR(SUMPRODUCT(($B$5:$B$13="Converts")*U5:U13*V5:V13)/SUMPRODUCT(($B$5:$B$13="Converts")*(V5:V13<>"")*U5:U13),"n/d") -> 1.1253157
A21: OEM / vendor financing: principal / weighted eff. rate | C21: =SUMIF($B$5:$B$13,"OEM / vendor financing",C5:C13) -> 0 | D21: =IFERROR(SUMPRODUCT(($B$5:$B$13="OEM / vendor financing")*C5:C13*D5:D13)/SUMPRODUCT(($B$5:$B$13="OEM / vendor financing")*(D5:D13<>"")*C5:C13),"n/d") -> n/d | E21: =SUMIF($B$5:$B$13,"OEM / vendor financing",E5:E13) -> 0 | F21: =IFERROR(SUMPRODUCT(($B$5:$B$13="OEM / vendor financing")*E5:E13*F5:F13)/SUMPRODUCT(($B$5:$B$13="OEM / vendor financing")*(F5:F13<>"")*E5:E13),"n/d") -> n/d | G21: =SUMIF($B$5:$B$13,"OEM / vendor financing",G5:G13) -> 0 | H21: =IFERROR(SUMPRODUCT(($B$5:$B$13="OEM / vendor financing")*G5:G13*H5:H13)/SUMPRODUCT(($B$5:$B$13="OEM / vendor financing")*(H5:H13<>"")*G5:G13),"n/d") -> n/d | I21: =SUMIF($B$5:$B$13,"OEM / vendor financing",I5:I13) -> 0 | J21: =IFERROR(SUMPRODUCT(($B$5:$B$13="OEM / vendor financing")*I5:I13*J5:J13)/SUMPRODUCT(($B$5:$B$13="OEM / vendor financing")*(J5:J13<>"")*I5:I13),"n/d") -> n/d | K21: =SUMIF($B$5:$B$13,"OEM / vendor financing",K5:K13) -> 0 | L21: =IFERROR(SUMPRODUCT(($B$5:$B$13="OEM / vendor financing")*K5:K13*L5:L13)/SUMPRODUCT(($B$5:$B$13="OEM / vendor financing")*(L5:L13<>"")*K5:K13),"n/d") -> n/d | M21: =SUMIF($B$5:$B$13,"OEM / vendor financing",M5:M13) -> 0 | N21: =IFERROR(SUMPRODUCT(($B$5:$B$13="OEM / vendor financing")*M5:M13*N5:N13)/SUMPRODUCT(($B$5:$B$13="OEM / vendor financing")*(N5:N13<>"")*M5:M13),"n/d") -> n/d | O21: =SUMIF($B$5:$B$13,"OEM / vendor financing",O5:O13) -> 0 | P21: =IFERROR(SUMPRODUCT(($B$5:$B$13="OEM / vendor financing")*O5:O13*P5:P13)/SUMPRODUCT(($B$5:$B$13="OEM / vendor financing")*(P5:P13<>"")*O5:O13),"n/d") -> n/d | Q21: =SUMIF($B$5:$B$13,"OEM / vendor financing",Q5:Q13) -> 0 | R21: =IFERROR(SUMPRODUCT(($B$5:$B$13="OEM / vendor financing")*Q5:Q13*R5:R13)/SUMPRODUCT(($B$5:$B$13="OEM / vendor financing")*(R5:R13<>"")*Q5:Q13),"n/d") -> n/d | S21: =SUMIF($B$5:$B$13,"OEM / vendor financing",S5:S13) -> 0 | T21: =IFERROR(SUMPRODUCT(($B$5:$B$13="OEM / vendor financing")*S5:S13*T5:T13)/SUMPRODUCT(($B$5:$B$13="OEM / vendor financing")*(T5:T13<>"")*S5:S13),"n/d") -> n/d | U21: =SUMIF($B$5:$B$13,"OEM / vendor financing",U5:U13) -> 0 | V21: =IFERROR(SUMPRODUCT(($B$5:$B$13="OEM / vendor financing")*U5:U13*V5:V13)/SUMPRODUCT(($B$5:$B$13="OEM / vendor financing")*(V5:V13<>"")*U5:U13),"n/d") -> n/d
A22: Revolver: principal / weighted eff. rate | C22: =SUMIF($B$5:$B$13,"Revolver",C5:C13) -> 0 | D22: =IFERROR(SUMPRODUCT(($B$5:$B$13="Revolver")*C5:C13*D5:D13)/SUMPRODUCT(($B$5:$B$13="Revolver")*(D5:D13<>"")*C5:C13),"n/d") -> n/d | E22: =SUMIF($B$5:$B$13,"Revolver",E5:E13) -> 0 | F22: =IFERROR(SUMPRODUCT(($B$5:$B$13="Revolver")*E5:E13*F5:F13)/SUMPRODUCT(($B$5:$B$13="Revolver")*(F5:F13<>"")*E5:E13),"n/d") -> n/d | G22: =SUMIF($B$5:$B$13,"Revolver",G5:G13) -> 0 | H22: =IFERROR(SUMPRODUCT(($B$5:$B$13="Revolver")*G5:G13*H5:H13)/SUMPRODUCT(($B$5:$B$13="Revolver")*(H5:H13<>"")*G5:G13),"n/d") -> n/d | I22: =SUMIF($B$5:$B$13,"Revolver",I5:I13) -> 0 | J22: =IFERROR(SUMPRODUCT(($B$5:$B$13="Revolver")*I5:I13*J5:J13)/SUMPRODUCT(($B$5:$B$13="Revolver")*(J5:J13<>"")*I5:I13),"n/d") -> n/d | K22: =SUMIF($B$5:$B$13,"Revolver",K5:K13) -> 0 | L22: =IFERROR(SUMPRODUCT(($B$5:$B$13="Revolver")*K5:K13*L5:L13)/SUMPRODUCT(($B$5:$B$13="Revolver")*(L5:L13<>"")*K5:K13),"n/d") -> n/d | M22: =SUMIF($B$5:$B$13,"Revolver",M5:M13) -> 0 | N22: =IFERROR(SUMPRODUCT(($B$5:$B$13="Revolver")*M5:M13*N5:N13)/SUMPRODUCT(($B$5:$B$13="Revolver")*(N5:N13<>"")*M5:M13),"n/d") -> n/d | O22: =SUMIF($B$5:$B$13,"Revolver",O5:O13) -> 0 | P22: =IFERROR(SUMPRODUCT(($B$5:$B$13="Revolver")*O5:O13*P5:P13)/SUMPRODUCT(($B$5:$B$13="Revolver")*(P5:P13<>"")*O5:O13),"n/d") -> n/d | Q22: =SUMIF($B$5:$B$13,"Revolver",Q5:Q13) -> 0 | R22: =IFERROR(SUMPRODUCT(($B$5:$B$13="Revolver")*Q5:Q13*R5:R13)/SUMPRODUCT(($B$5:$B$13="Revolver")*(R5:R13<>"")*Q5:Q13),"n/d") -> n/d | S22: =SUMIF($B$5:$B$13,"Revolver",S5:S13) -> 0 | T22: =IFERROR(SUMPRODUCT(($B$5:$B$13="Revolver")*S5:S13*T5:T13)/SUMPRODUCT(($B$5:$B$13="Revolver")*(T5:T13<>"")*S5:S13),"n/d") -> n/d | U22: =SUMIF($B$5:$B$13,"Revolver",U5:U13) -> 0 | V22: =IFERROR(SUMPRODUCT(($B$5:$B$13="Revolver")*U5:U13*V5:V13)/SUMPRODUCT(($B$5:$B$13="Revolver")*(V5:V13<>"")*U5:U13),"n/d") -> n/d
A23: Other term loans: principal / weighted eff. rate | C23: =SUMIF($B$5:$B$13,"Other term loans",C5:C13) -> 0 | D23: =IFERROR(SUMPRODUCT(($B$5:$B$13="Other term loans")*C5:C13*D5:D13)/SUMPRODUCT(($B$5:$B$13="Other term loans")*(D5:D13<>"")*C5:C13),"n/d") -> n/d | E23: =SUMIF($B$5:$B$13,"Other term loans",E5:E13) -> 0 | F23: =IFERROR(SUMPRODUCT(($B$5:$B$13="Other term loans")*E5:E13*F5:F13)/SUMPRODUCT(($B$5:$B$13="Other term loans")*(F5:F13<>"")*E5:E13),"n/d") -> n/d | G23: =SUMIF($B$5:$B$13,"Other term loans",G5:G13) -> 0 | H23: =IFERROR(SUMPRODUCT(($B$5:$B$13="Other term loans")*G5:G13*H5:H13)/SUMPRODUCT(($B$5:$B$13="Other term loans")*(H5:H13<>"")*G5:G13),"n/d") -> n/d | I23: =SUMIF($B$5:$B$13,"Other term loans",I5:I13) -> 0 | J23: =IFERROR(SUMPRODUCT(($B$5:$B$13="Other term loans")*I5:I13*J5:J13)/SUMPRODUCT(($B$5:$B$13="Other term loans")*(J5:J13<>"")*I5:I13),"n/d") -> n/d | K23: =SUMIF($B$5:$B$13,"Other term loans",K5:K13) -> 0 | L23: =IFERROR(SUMPRODUCT(($B$5:$B$13="Other term loans")*K5:K13*L5:L13)/SUMPRODUCT(($B$5:$B$13="Other term loans")*(L5:L13<>"")*K5:K13),"n/d") -> n/d | M23: =SUMIF($B$5:$B$13,"Other term loans",M5:M13) -> 0 | N23: =IFERROR(SUMPRODUCT(($B$5:$B$13="Other term loans")*M5:M13*N5:N13)/SUMPRODUCT(($B$5:$B$13="Other term loans")*(N5:N13<>"")*M5:M13),"n/d") -> n/d | O23: =SUMIF($B$5:$B$13,"Other term loans",O5:O13) -> 0 | P23: =IFERROR(SUMPRODUCT(($B$5:$B$13="Other term loans")*O5:O13*P5:P13)/SUMPRODUCT(($B$5:$B$13="Other term loans")*(P5:P13<>"")*O5:O13),"n/d") -> n/d | Q23: =SUMIF($B$5:$B$13,"Other term loans",Q5:Q13) -> 0 | R23: =IFERROR(SUMPRODUCT(($B$5:$B$13="Other term loans")*Q5:Q13*R5:R13)/SUMPRODUCT(($B$5:$B$13="Other term loans")*(R5:R13<>"")*Q5:Q13),"n/d") -> n/d | S23: =SUMIF($B$5:$B$13,"Other term loans",S5:S13) -> 0 | T23: =IFERROR(SUMPRODUCT(($B$5:$B$13="Other term loans")*S5:S13*T5:T13)/SUMPRODUCT(($B$5:$B$13="Other term loans")*(T5:T13<>"")*S5:S13),"n/d") -> n/d | U23: =SUMIF($B$5:$B$13,"Other term loans",U5:U13) -> 21.95 | V23: =IFERROR(SUMPRODUCT(($B$5:$B$13="Other term loans")*U5:U13*V5:V13)/SUMPRODUCT(($B$5:$B$13="Other term loans")*(V5:V13<>"")*U5:U13),"n/d") -> n/d
A24: Share of principal: DDTL % | D24: =IFERROR(C18/C15*100,"n/d") -> n/d | F24: =IFERROR(E18/E15*100,"n/d") -> n/d | H24: =IFERROR(G18/G15*100,"n/d") -> n/d | J24: =IFERROR(I18/I15*100,"n/d") -> 0 | L24: =IFERROR(K18/K15*100,"n/d") -> 0 | N24: =IFERROR(M18/M15*100,"n/d") -> 0 | P24: =IFERROR(O18/O15*100,"n/d") -> 0 | R24: =IFERROR(Q18/Q15*100,"n/d") -> 0 | T24: =IFERROR(S18/S15*100,"n/d") -> 0 | V24: =IFERROR(U18/U15*100,"n/d") -> 5.3597043
A26: POST-PERIOD (not in Jun-26): Aug-2026 $2.4B GPU financing (Blue Owl / PIMCO) at 9.0% fixed (FY26 PR / 8-K). Marginal secured GPU cost ~7-9% vs 1.9% blended (converts-heavy).
A27: Finance leases (GPU leases, liability $243.8M at Jun-26) excluded, consistent with CRWV/Nebius template.

Sheet Sources
A1: Input ID | B1: Item | C1: Period | D1: Value | E1: Tag | F1: Document | G1: Section / page / formula | H1: URL
A2: I01 | B2: AI Cloud Services revenue (segment) | C2: Q1'24 | D2: 0.567 | E2: Reported | F2: 6-K FQ3 FY25 (Mar-25 qtr; IFRS) - interim FS / MD&A Ex.99.4 / PR, filed 2025-05 | G2: FQ3 FY25 6-K Ex.99.4 MD&A table, 3m to 31-Mar-24 comparative 'AI cloud service revenue 567' (IFRS) | H2: https://www.sec.gov/Archives/edgar/data/1878848/000187884825000043/iren-20250331_d2.htm
A3: I01 | B3: AI Cloud Services revenue (segment) | C3: Q2'24 | D3: 2.538 | E3: Derived | F3: 10-K FY26 (FYE 30-Jun-2026), filed 2026-08-27 | G3: calc: FY24 3.105 (FY26 10-K segment note, US GAAP recast) - 9M FY24 0.567 (IFRS, FQ3 FY25 MD&A) -> mixed basis | H3: https://www.sec.gov/Archives/edgar/data/1878848/000187884826000052/iren-20260630.htm
A4: I01 | B4: AI Cloud Services revenue (segment) | C4: Q3'24 | D4: 3.189 | E4: Reported | F4: 10-Q FQ1 FY26 (Sep-25 qtr), filed 2025-11-06 | G4: Q1 FY26 10-Q segment note comparative (3m Sep-24) | H4: https://www.sec.gov/Archives/edgar/data/1878848/000187884825000081/iren-20250930.htm
A5: I01 | B5: AI Cloud Services revenue (segment) | C5: Q4'24 | D5: 2.661 | E5: Reported | F5: 10-Q FQ2 FY26 (Dec-25 qtr), filed 2026-02-05 | G5: Q2 FY26 10-Q comparative (3m Dec-24) | H5: https://www.sec.gov/Archives/edgar/data/1878848/000187884826000015/iren-20251231.htm
A6: I01 | B6: AI Cloud Services revenue (segment) | C6: Q1'25 | D6: 3.581 | E6: Reported | F6: 10-Q FQ3 FY26 (Mar-26 qtr), filed 2026-05-07 | G6: Q3 FY26 10-Q comparative (3m Mar-25) | H6: https://www.sec.gov/Archives/edgar/data/1878848/000187884826000026/iren-20260331.htm
A7: I01 | B7: AI Cloud Services revenue (segment) | C7: Q2'25 | D7: 6.963 | E7: Reported | F7: 10-K FY25 (FYE 30-Jun-2025; first US GAAP annual; incl. unaudited quarterly table), filed 2025-08-28 | G7: FY25 10-K unaudited quarterly table (Jun-25 qtr 6,963) | H7: https://www.sec.gov/Archives/edgar/data/1878848/000187884825000063/iren-20250630.htm
A8: I01 | B8: AI Cloud Services revenue (segment) | C8: Q3'25 | D8: 7.347 | E8: Reported | F8: 10-Q FQ1 FY26 (Sep-25 qtr), filed 2025-11-06 | G8: Q1 FY26 10-Q segment note | H8: https://www.sec.gov/Archives/edgar/data/1878848/000187884825000081/iren-20250930.htm
A9: I01 | B9: AI Cloud Services revenue (segment) | C9: Q4'25 | D9: 17.298 | E9: Reported | F9: 10-Q FQ2 FY26 (Dec-25 qtr), filed 2026-02-05 | G9: Q2 FY26 10-Q segment note | H9: https://www.sec.gov/Archives/edgar/data/1878848/000187884826000015/iren-20251231.htm
A10: I01 | B10: AI Cloud Services revenue (segment) | C10: Q1'26 | D10: 33.635 | E10: Reported | F10: 10-Q FQ3 FY26 (Mar-26 qtr), filed 2026-05-07 | G10: Q3 FY26 10-Q segment note | H10: https://www.sec.gov/Archives/edgar/data/1878848/000187884826000026/iren-20260331.htm
A11: I01 | B11: AI Cloud Services revenue (segment) | C11: Q2'26 | D11: 70.515 | E11: Derived | F11: 10-K FY26 (FYE 30-Jun-2026), filed 2026-08-27 | G11: calc: FY26 128.795 (FY26 10-K segment note) - 9M 58.280 (Q3 FY26 10-Q) | H11: https://www.sec.gov/Archives/edgar/data/1878848/000187884826000052/iren-20260630.htm
A12: I03 | B12: Depreciation & amortization (company-wide, P&L) | C12: Q1'24 | D12: 8.692 | E12: Reported | F12: 6-K FQ3 FY24 (Mar-24 qtr; IFRS) - Ex.99.1 results PR / Ex.99.3 interim financial statements, filed 2024-05-15 | G12: FQ3 FY24 6-K Ex.99.3 P&L 'Depreciation (8,692)' (IFRS) | H12: https://www.sec.gov/Archives/edgar/data/1878848/000114036124026268/ef20027345_ex99-3.htm
A13: I03 | B13: Depreciation & amortization (company-wide, P&L) | C13: Q2'24 | D13: 26.78 | E13: Derived | F13: Form 20-F FY24 (FYE 30-Jun-2024; IFRS), filed 2024-08-28 | G13: calc: FY24 50.650 (20-F Note 6) - 9M 23.870 (6-K) (IFRS) | H13: https://www.sec.gov/Archives/edgar/data/1878848/000162828024038677/iren-20240630.htm
... A103: I23 | B103: Total debt principal (EoP; excl. finance leases) | C103: Q2'26 | D103: 7705.649 | E103: Reported | F103: 10-K FY26 (FYE 30-Jun-2026), filed 2026-08-27 | G103: Debt note principal (see Debt_Facilities). Excludes GPU finance leases ($243.8M liability at Jun-26). | H103: https://www.sec.gov/Archives/edgar/data/1878848/000187884826000052/iren-20260630.htm
A104: I26 | B104: Days in quarter | C104: Q1'24 | D104: 91 | E104: Reported | F104: calendar | G104: calendar
A105: I26 | B105: Days in quarter | C105: Q2'24 | D105: 91 | E105: Reported | F105: calendar | G105: calendar
A106: I26 | B106: Days in quarter | C106: Q3'24 | D106: 92 | E106: Reported | F106: calendar | G106: calendar
A107: I26 | B107: Days in quarter | C107: Q4'24 | D107: 92 | E107: Reported | F107: calendar | G107: calendar
A108: I26 | B108: Days in quarter | C108: Q1'25 | D108: 90 | E108: Reported | F108: calendar | G108: calendar
A109: I26 | B109: Days in quarter | C109: Q2'25 | D109: 91 | E109: Reported | F109: calendar | G109: calendar
A110: I26 | B110: Days in quarter | C110: Q3'25 | D110: 92 | E110: Reported | F110: calendar | G110: calendar
A111: I26 | B111: Days in quarter | C111: Q4'25 | D111: 92 | E111: Reported | F111: calendar | G111: calendar
A112: I26 | B112: Days in quarter | C112: Q1'26 | D112: 90 | E112: Reported | F112: calendar | G112: calendar
A113: I26 | B113: Days in quarter | C113: Q2'26 | D113: 91 | E113: Reported | F113: calendar | G113: calendar
A114: I28 | B114: Useful life - HPC / GPU hardware | C114: Q1'24 | D114: 5 | E114: Reported | F114: Form 20-F FY24 (FYE 30-Jun-2024; IFRS), filed 2024-08-28 | G114: 20-F FY24: 'HPC hardware is depreciated over 5 years' | H114: https://www.sec.gov/Archives/edgar/data/1878848/000162828024038677/iren-20240630.htm
A115: I28 | B115: Useful life - HPC / GPU hardware | C115: Q2'24 | D115: 5 | E115: Reported | F115: Form 20-F FY24 (FYE 30-Jun-2024; IFRS), filed 2024-08-28 | G115: same | H115: https://www.sec.gov/Archives/edgar/data/1878848/000162828024038677/iren-20240630.htm
A116: I28 | B116: Useful life - HPC / GPU hardware | C116: Q3'24 | D116: 5 | E116: Reported | F116: 10-K FY25 (FYE 30-Jun-2025; first US GAAP annual; incl. unaudited quarterly table), filed 2025-08-28 | G116: 10-K FY25 useful-life table 'HPC hardware 5' | H116: https://www.sec.gov/Archives/edgar/data/1878848/000187884825000063/iren-20250630.htm
A117: I28 | B117: Useful life - HPC / GPU hardware | C117: Q4'24 | D117: 5 | E117: Reported | F117: 10-K FY25 (FYE 30-Jun-2025; first US GAAP annual; incl. unaudited quarterly table), filed 2025-08-28 | G117: 10-K FY25 useful-life table 'HPC hardware 5' | H117: https://www.sec.gov/Archives/edgar/data/1878848/000187884825000063/iren-20250630.htm
A118: I28 | B118: Useful life - HPC / GPU hardware | C118: Q1'25 | D118: 5 | E118: Reported | F118: 10-K FY25 (FYE 30-Jun-2025; first US GAAP annual; incl. unaudited quarterly table), filed 2025-08-28 | G118: 10-K FY25 useful-life table 'HPC hardware 5' | H118: https://www.sec.gov/Archives/edgar/data/1878848/000187884825000063/iren-20250630.htm
A119: I28 | B119: Useful life - HPC / GPU hardware | C119: Q2'25 | D119: 5 | E119: Reported | F119: 10-K FY25 (FYE 30-Jun-2025; first US GAAP annual; incl. unaudited quarterly table), filed 2025-08-28 | G119: 10-K FY25 useful-life table 'HPC hardware 5' | H119: https://www.sec.gov/Archives/edgar/data/1878848/000187884825000063/iren-20250630.htm
A120: I28 | B120: Useful life - HPC / GPU hardware | C120: Q3'25 | D120: 5 | E120: Reported | F120: 10-K FY26 (FYE 30-Jun-2026), filed 2026-08-27 | G120: 10-K FY26 table 'HPC hardware 5' | H120: https://www.sec.gov/Archives/edgar/data/1878848/000187884826000052/iren-20260630.htm
A121: I28 | B121: Useful life - HPC / GPU hardware | C121: Q4'25 | D121: 5 | E121: Reported | F121: 10-K FY26 (FYE 30-Jun-2026), filed 2026-08-27 | G121: 10-K FY26 table 'HPC hardware 5' | H121: https://www.sec.gov/Archives/edgar/data/1878848/000187884826000052/iren-20260630.htm
A122: I28 | B122: Useful life - HPC / GPU hardware | C122: Q1'26 | D122: 5 | E122: Reported | F122: 10-K FY26 (FYE 30-Jun-2026), filed 2026-08-27 | G122: 10-K FY26 table 'HPC hardware 5' | H122: https://www.sec.gov/Archives/edgar/data/1878848/000187884826000052/iren-20260630.htm
A123: I28 | B123: Useful life - HPC / GPU hardware | C123: Q2'26 | D123: 5 | E123: Reported | F123: 10-K FY26 (FYE 30-Jun-2026), filed 2026-08-27 | G123: 10-K FY26 table 'HPC hardware 5' | H123: https://www.sec.gov/Archives/edgar/data/1878848/000187884826000052/iren-20260630.htm
A124: I30 | B124: RPO % expected to be recognized within 12 months | C124: Q3'25 | D124: 47.9 | E124: Derived | F124: 10-Q FQ1 FY26 (Sep-25 qtr), filed 2025-11-06 | G124: calc: 93.363/195.027 | H124: https://www.sec.gov/Archives/edgar/data/1878848/000187884825000081/iren-20250930.htm
A125: I30 | B125: RPO % expected to be recognized within 12 months | C125: Q4'25 | D125: 51.9 | E125: Derived | F125: 10-Q FQ2 FY26 (Dec-25 qtr), filed 2026-02-05 | G125: calc: 150.072/289.411 | H125: https://www.sec.gov/Archives/edgar/data/1878848/000187884826000015/iren-20251231.htm
... A220: P03 | B220: Hopper HGX GPUs per IT-MW (base) | C220: param | D220: 713 | E220: Estimated | F220: Nebius workspace: /workspace/nebius/capacity/gpu_mw_capex.xlsx (GPUsPerMW base IT-MW rows) / gpu_mw_capex.md s.1 | G220: GPUsPerMW base IT-MW row (665/713/813); IREN's own economics footnote assumes 1.25kW/GPU (= 800 GPUs/MW) | H220: local
A221: DEBT | B221: 3.25% convertible senior notes due 2030 (issued Dec-24) (principal / eff. rate) | C221: Dec-24 | D221: 440 / 3.87% | E221: Reported | F221: 6-K FQ2 FY25 (Dec-24 qtr; IFRS) - interim FS / MD&A Ex.99.4 / PR, filed 2025-02 | G221: Debt / convertible notes note (principal; effective interest rate) | H221: https://www.sec.gov/Archives/edgar/data/1878848/000187884825000009/iren-20241231_d2.htm
A222: DEBT | B222: 3.25% convertible senior notes due 2030 (issued Dec-24) (principal / eff. rate) | C222: Mar-25 | D222: 440 / 3.87% | E222: Reported | F222: 6-K FQ3 FY25 (Mar-25 qtr; IFRS) - interim FS / MD&A Ex.99.4 / PR, filed 2025-05 | G222: Debt / convertible notes note (principal; effective interest rate) | H222: https://www.sec.gov/Archives/edgar/data/1878848/000187884825000043/iren-20250331_d2.htm
A223: DEBT | B223: 3.25% convertible senior notes due 2030 (issued Dec-24) (principal / eff. rate) | C223: Jun-25 | D223: 440 / 3.87% | E223: Reported | F223: 10-K FY25 (FYE 30-Jun-2025; first US GAAP annual; incl. unaudited quarterly table), filed 2025-08-28 | G223: Debt / convertible notes note (principal; effective interest rate) | H223: https://www.sec.gov/Archives/edgar/data/1878848/000187884825000063/iren-20250630.htm
A224: DEBT | B224: 3.25% convertible senior notes due 2030 (issued Dec-24) (principal / eff. rate) | C224: Sep-25 | D224: 440 / 3.87% | E224: Reported | F224: 10-Q FQ1 FY26 (Sep-25 qtr), filed 2025-11-06 | G224: Debt / convertible notes note (principal; effective interest rate) | H224: https://www.sec.gov/Archives/edgar/data/1878848/000187884825000081/iren-20250930.htm
A225: DEBT | B225: 3.25% convertible senior notes due 2030 (issued Dec-24) (principal / eff. rate) | C225: Dec-25 | D225: 212.31 / 3.87% | E225: Reported | F225: 10-Q FQ2 FY26 (Dec-25 qtr), filed 2026-02-05 | G225: Debt / convertible notes note (principal; effective interest rate) | H225: https://www.sec.gov/Archives/edgar/data/1878848/000187884826000015/iren-20251231.htm
A226: DEBT | B226: 3.25% convertible senior notes due 2030 (issued Dec-24) (principal / eff. rate) | C226: Mar-26 | D226: 212.31 / 3.87% | E226: Reported | F226: 10-Q FQ3 FY26 (Mar-26 qtr), filed 2026-05-07 | G226: Debt / convertible notes note (principal; effective interest rate) | H226: https://www.sec.gov/Archives/edgar/data/1878848/000187884826000026/iren-20260331.htm
A227: DEBT | B227: 3.25% convertible senior notes due 2030 (issued Dec-24) (principal / eff. rate) | C227: Jun-26 | D227: 212.31 / 3.87% | E227: Reported | F227: 10-K FY26 (FYE 30-Jun-2026), filed 2026-08-27 | G227: Debt / convertible notes note (principal; effective interest rate) | H227: https://www.sec.gov/Archives/edgar/data/1878848/000187884826000052/iren-20260630.htm
A228: DEBT | B228: 3.50% convertible senior notes due 2029 (issued Jun-25) (principal / eff. rate) | C228: Jun-25 | D228: 550 / 4.22% | E228: Reported | F228: 10-K FY25 (FYE 30-Jun-2025; first US GAAP annual; incl. unaudited quarterly table), filed 2025-08-28 | G228: Debt / convertible notes note (principal; effective interest rate) | H228: https://www.sec.gov/Archives/edgar/data/1878848/000187884825000063/iren-20250630.htm
A229: DEBT | B229: 3.50% convertible senior notes due 2029 (issued Jun-25) (principal / eff. rate) | C229: Sep-25 | D229: 550 / 4.22% | E229: Reported | F229: 10-Q FQ1 FY26 (Sep-25 qtr), filed 2025-11-06 | G229: Debt / convertible notes note (principal; effective interest rate) | H229: https://www.sec.gov/Archives/edgar/data/1878848/000187884825000081/iren-20250930.htm
A230: DEBT | B230: 3.50% convertible senior notes due 2029 (issued Jun-25) (principal / eff. rate) | C230: Dec-25 | D230: 233.389 / 4.22% | E230: Reported | F230: 10-Q FQ2 FY26 (Dec-25 qtr), filed 2026-02-05 | G230: Debt / convertible notes note (principal; effective interest rate) | H230: https://www.sec.gov/Archives/edgar/data/1878848/000187884826000015/iren-20251231.htm
A231: DEBT | B231: 3.50% convertible senior notes due 2029 (issued Jun-25) (principal / eff. rate) | C231: Mar-26 | D231: 233.389 / 4.22% | E231: Reported | F231: 10-Q FQ3 FY26 (Mar-26 qtr), filed 2026-05-07 | G231: Debt / convertible notes note (principal; effective interest rate) | H231: https://www.sec.gov/Archives/edgar/data/1878848/000187884826000026/iren-20260331.htm
A232: DEBT | B232: 3.50% convertible senior notes due 2029 (issued Jun-25) (principal / eff. rate) | C232: Jun-26 | D232: 233.389 / 4.22% | E232: Reported | F232: 10-K FY26 (FYE 30-Jun-2026), filed 2026-08-27 | G232: Debt / convertible notes note (principal; effective interest rate) | H232: https://www.sec.gov/Archives/edgar/data/1878848/000187884826000052/iren-20260630.htm
... A245: DEBT | B245: Other debt (various) (principal / eff. rate) | C245: Jun-26 | D245: 21.95 / n/d% | E245: Reported | F245: 10-K FY26 (FYE 30-Jun-2026), filed 2026-08-27 | G245: Debt / convertible notes note (principal; effective interest rate) | H245: https://www.sec.gov/Archives/edgar/data/1878848/000187884826000052/iren-20260630.htm
A247: Document register
A248: Q24Q3 | F248: 6-K FQ3 FY24 (Mar-24 qtr; IFRS) - Ex.99.1 results PR / Ex.99.3 interim financial statements, filed 2024-05-15 | H248: https://www.sec.gov/Archives/edgar/data/1878848/000114036124026268/ef20027345_ex99-3.htm
A249: K24 | F249: Form 20-F FY24 (FYE 30-Jun-2024; IFRS), filed 2024-08-28 | H249: https://www.sec.gov/Archives/edgar/data/1878848/000162828024038677/iren-20240630.htm
A250: PR24 | F250: FY24 results PR (6-K Ex.99.1, 2024-08-28) | H250: https://www.sec.gov/Archives/edgar/data/1878848/000162828024038679/fy24resultspressreleasev.htm
A251: Q25Q1 | F251: 6-K FQ1 FY25 (Sep-24 qtr; IFRS) - interim FS + results PR, filed 2024-11 | H251: https://www.sec.gov/Archives/edgar/data/1878848/000187884824000036/iren-20240930_d2.htm
A252: Q25Q2 | F252: 6-K FQ2 FY25 (Dec-24 qtr; IFRS) - interim FS / MD&A Ex.99.4 / PR, filed 2025-02 | H252: https://www.sec.gov/Archives/edgar/data/1878848/000187884825000009/iren-20241231_d2.htm
A253: Q25Q3 | F253: 6-K FQ3 FY25 (Mar-25 qtr; IFRS) - interim FS / MD&A Ex.99.4 / PR, filed 2025-05 | H253: https://www.sec.gov/Archives/edgar/data/1878848/000187884825000043/iren-20250331_d2.htm
A254: K25 | F254: 10-K FY25 (FYE 30-Jun-2025; first US GAAP annual; incl. unaudited quarterly table), filed 2025-08-28 | H254: https://www.sec.gov/Archives/edgar/data/1878848/000187884825000063/iren-20250630.htm
A255: PR25 | F255: FY25 results PR (8-K Ex.99.1, 2025-08-28) | H255: https://www.sec.gov/Archives/edgar/data/1878848/000187884825000062/ex991fy25pr.htm
A256: Q26Q1 | F256: 10-Q FQ1 FY26 (Sep-25 qtr), filed 2025-11-06 | H256: https://www.sec.gov/Archives/edgar/data/1878848/000187884825000081/iren-20250930.htm
A257: PR26Q1 | F257: Q1 FY26 results PR (8-K Ex.99.1, 2025-11-06) | H257: https://www.sec.gov/Archives/edgar/data/1878848/000187884825000079/q1fy26resultspressreleas.htm
A258: Q26Q2 | F258: 10-Q FQ2 FY26 (Dec-25 qtr), filed 2026-02-05 | H258: https://www.sec.gov/Archives/edgar/data/1878848/000187884826000015/iren-20251231.htm
A259: PR26Q2 | F259: Q2 FY26 results PR (8-K Ex.99.1, 2026-02-05) | H259: https://www.sec.gov/Archives/edgar/data/1878848/000187884826000014/a991irenreportsq2fy26res.htm
... A265: NBGPU | F265: Nebius workspace: /workspace/nebius/capacity/gpu_mw_capex.xlsx (GPUsPerMW base IT-MW rows) / gpu_mw_capex.md s.1 | H265: local
A266: CAL | F266: calendar

Sheet Definitions
A1: Def | B1: KPI group | C1: Definition used (formula, units) | D1: Mirrored from (Nebius workspace) | E1: IREN (IREN) - AI Cloud perimeter application / basis notes
A2: D1 | B2: Revenue per MW | C2: Quarterly revenue x 4 / MW, $M per MW-year. Denominators: (a) active MW at period end; (b) average of opening/closing active MW; (c) contracted MW. EBITDA/MW same construction. K43 = YoY incremental revenue x4 / MW added in the same 4 quarters. K45 = segment cash gross margin. | D2: /workspace/nebius/model/nebius_model.xlsx KPIs rows 'Revenue per BILLING / contracted / energized MW' (=AIRev*4/MW); /workspace/nebius/parts/comps_rev_per_mw.csv; capacity/gpu_mw_capex.md s.4 MW basis. | E2: I01 = AI Cloud Services revenue. MW = 'operating AI Cloud Services capacity' (~40MW at Jun-26, only disclosure; basis unstated). Earlier AI MW ESTIMATED from operating GPUs / 713 Hopper GPUs per IT-MW. IREN quotes contract economics per MW (IT): '>$20m revenue per MW' on recent 3-yr contracts (FY26 PR).
A3: D2 | B3: Revenue per GPU | C3: Quarterly revenue x 4000 / average GPUs ($K per GPU-year); implied $/GPU-hr = revenue / (avg GPUs x days x 24). | D3: nebius_model.xlsx KPIs 'Revenue per GPU ($K per GPU-yr)' and 'Implied blended $/GPU-hr'. | E3: Operating GPUs disclosed to Sep-25 (816 -> ~2,100); thereafter only installed/contracted targets. Jun-26 GPUs estimated from 40MW x 538.
A4: D3 | B4: Implied utilization | C4: Implied blended $/GPU-hr / fleet-weighted on-demand list price. K41 = company-reported physical GPU utilization (new row). | D4: nebius_model.xlsx KPIs 'Fleet-weighted on-demand list price' / 'Implied utilization (blended $/hr / weighted list)'; prices /workspace/nebius/parts/price_history_quarterly.csv & price_history_raw.csv. | E4: No public list price; IREN's own $2.00/GPU-hr revenue assumption used as price proxy (Estimated). No utilization disclosure.
A5: D4 | B5: Capex per MW | C5: Cash purchases of PP&E / new active MW in the quarter ($M per MW); in-service additions per new MW; trailing-4Q; stock checks net PP&E / MW and in-service gross PP&E / MW. K44 = annualized revenue / average gross compute hardware. | D5: nebius_model.xlsx KPIs 'Capex per new active MW'; Hist 'Capex (purchases of PP&E + intangibles, cash)'; capacity/gpu_mw_capex.xlsx 'Nebius checks' and 'Peers'. | E5: Capex/PP&E company-wide (mining+AI). AI-only asset base = 'HPC/GPU hardware' at cost (I31) -> memo M06 and K44.
A6: D5 | B6: D&A useful lives | C6: Disclosed useful-life table and any change in estimate; depreciation yield = D&A x 4 / average in-service gross PP&E; implied life = 1/yield. | D6: /workspace/nebius/filings/nebius_filings.xlsx D&A_Policy; nebius_model.xlsx Capex_DA 'Depreciation yield - REPORTED basis'. | E6: HPC hardware 5 yrs (unchanged FY24-FY26); mining 4 yrs (S19j Pro 2 yrs); buildings 20. Yield on company in-service PP&E (net of impairment).
A7: D6 | B7: Backlog / RPO | C7: RPO = ASC 606 remaining performance obligations ($B, EoP); % within 24 months (K22) and 12 months (K42); backlog incl. non-RPO contracted value shown separately; RPO / (quarterly revenue x 4). | D7: nebius_model.xlsx Hist 'Remaining performance obligations'; nebius_filings.xlsx Quarterly 'RPO'. | E7: RPO disclosed from Sep-25 (US GAAP 10-Qs). Microsoft $9.7B contract enters RPO tranche-by-tranche; Jun-26 lease (ASC 842) value $11.4B shown in K21.
A8: D7 | B8: Customer concentration | C8: Each customer >=10% of quarter revenue, top-N combined, count of >=10% customers. | D8: nebius_filings.xlsx Quarterly 'Customer concentration (>10% of revenue, quarter)'. | E8: No AI customer % disclosed. Mining revenue via 3 pools.
A9: D8 | B9: Funding cost | C9: Weighted effective cost of debt = sum(principal x effective rate) / sum(principal with a disclosed rate), EoP, excl. leases; split by facility type; cross-checks: interest x4 / avg principal; company-reported rate. | D9: /workspace/nebius/parts/comps_sources.csv 'Wtd effective cost of debt (%)'; shared/findings_log.xlsx cost-of-debt row (Nebius 5.1%). | E9: Converts-heavy capital structure until FY26 Q4; first secured GPU debt (DDTL, USPP) at Jun-26. Finance expense used for K36 (no quarterly contractual interest).

Sheet Fiscal_Map
A1: Template column | B1: Calendar quarter-end used | C1: Company fiscal quarter | D1: Fiscal period end | E1: Offset vs calendar | F1: Notes
A2: Q4'23* | B2: 2023-12-31 | C2: FQ2 FY24 | D2: Dec-23 | E2: 0 (exact) | F2: FY ends 30-Jun; opening-balance column
A3: Q1'24 | B3: 2024-03-31 | C3: FQ3 FY24 | D3: Mar-24 | E3: 0 (exact) | F3: FY ends 30-Jun
A4: Q2'24 | B4: 2024-06-30 | C4: FQ4 FY24 | D4: Jun-24 | E4: 0 (exact) | F4: FY ends 30-Jun
A5: Q3'24 | B5: 2024-09-30 | C5: FQ1 FY25 | D5: Sep-24 | E5: 0 (exact) | F5: FY ends 30-Jun
A6: Q4'24 | B6: 2024-12-31 | C6: FQ2 FY25 | D6: Dec-24 | E6: 0 (exact) | F6: FY ends 30-Jun
A7: Q1'25 | B7: 2025-03-31 | C7: FQ3 FY25 | D7: Mar-25 | E7: 0 (exact) | F7: FY ends 30-Jun
A8: Q2'25 | B8: 2025-06-30 | C8: FQ4 FY25 | D8: Jun-25 | E8: 0 (exact) | F8: FY ends 30-Jun
A9: Q3'25 | B9: 2025-09-30 | C9: FQ1 FY26 | D9: Sep-25 | E9: 0 (exact) | F9: FY ends 30-Jun
A10: Q4'25 | B10: 2025-12-31 | C10: FQ2 FY26 | D10: Dec-25 | E10: 0 (exact) | F10: FY ends 30-Jun
A11: Q1'26 | B11: 2026-03-31 | C11: FQ3 FY26 | D11: Mar-26 | E11: 0 (exact) | F11: FY ends 30-Jun
A12: Q2'26 | B12: 2026-06-30 | C12: FQ4 FY26 | D12: Jun-26 | E12: 0 (exact) | F12: FY ends 30-Jun

Sheet Notes_Gaps
A1: # | B1: Type | C1: Note / gap | D1: Impact | E1: Possible fix
A2: 1 | B2: Gap | C2: AI MW disclosed only once (~40MW at Jun-26); operating GPU counts stop after Sep-25 (~2,100). Dec-25 and Mar-26 AI MW/GPUs n/d. | D2: K02, K06-K09 cannot be computed for Q4'25-Q2'26; K01/K43 rely on one MW datapoint. | E2: Earnings-call transcripts (Horizon commissioning MW), Microsoft tranche acceptance dates; IR request.
A3: 2 | B3: Gap | C3: No AI-vs-mining split of capex, D&A, PP&E (except GPU vs mining hardware at cost), or EBITDA. | D3: Capex/MW (K10-K15) and EBITDA/MW (K05) n/d on the AI perimeter. | E3: Use GPU hardware (I31) as AI asset proxy; segment note changes in FY27.
A4: 3 | B4: Gap | C4: No customer revenue concentration for AI Cloud; backlog concentration only derivable (Microsoft ~58%, NVIDIA ~20% of $16.6B). | D4: K24-K27 n/d.
A5: 4 | B5: Gap | C5: No public GPU list price; IREN's $2.00/GPU-hr revenue assumption used (Estimated). | D5: K08/K09 not comparable 1:1 with CRWV/Nebius list-based utilization.
A6: 5 | B6: Gap | C6: Contractual interest only annual; quarterly finance expense used. | D6: K36 includes issuance-cost amortization / lease interest.
A7: 6 | B7: Caveat | C7: IFRS (to Mar-25) vs US GAAP (from Jun-25) basis break; Q2'24 values derived as FY (GAAP recast) - 9M (IFRS). | D7: Small (<$0.1M on AI revenue; D&A/capex may differ more).
A8: 7 | B8: Caveat | C8: MW figures from PR boilerplate are 'as of PR date' (5-7 weeks after quarter end); total DC MW is gross basis while AI 40MW basis unstated. | D8: Mining MW estimates (I44E) approximate.
A9: 8 | B9: Note | C9: Jun-26 transition: AI 51% of revenue; Bitcoin capacity 23.2 EH/s (~380MW) vs 50 EH/s peak; $16.6B contracted backlog; $4bn contracted ARR / $1bn operating ARR (FY26 PR).
A10: 9 | B10: Note | C10: Post-period: Aug-2026 $2.4B GPU financing at 9.0% fixed (Blue Owl / PIMCO). | D10: Marginal secured cost far above the 1.9% blended rate.

Sheet Comparison
A1: Per-peer stub. The multi-peer Comparison tab (Nebius, CoreWeave, IREN, Oracle OCI) lives in /workspace/nebius/peers/comparison.xlsx (built by peers/build_comparison.py from each peer workbook's KPIs tab).
A3: ID | B3: KPI | C3: Unit | D3: IREN (IREN) - AI Cloud perimeter Q4'25 | E3: IREN (IREN) - AI Cloud perimeter Q1'26 | F3: IREN (IREN) - AI Cloud perimeter Q2'26
A4: K01 | B4: =KPIs!B5 -> Revenue per active MW - period-end MW | C4: =KPIs!C5 -> $M/MW-yr | D4: =KPIs!M5 -> n/d | E4: =KPIs!N5 -> n/d | F4: =KPIs!O5 -> 7.0515
A5: K02 | B5: =KPIs!B7 -> Revenue per active MW - average MW | C5: =KPIs!C7 -> $M/MW-yr | D5: =KPIs!M7 -> n/d | E5: =KPIs!N7 -> n/d | F5: =KPIs!O7 -> n/d
A6: K03 | B6: =KPIs!B9 -> Revenue per contracted MW | C6: =KPIs!C9 -> $M/MW-yr | D6: =KPIs!M9 -> n/d | E6: =KPIs!N9 -> n/d | F6: =KPIs!O9 -> n/d
A7: K05 | B7: =KPIs!B13 -> Adj. EBITDA per active MW (average MW) | C7: =KPIs!C13 -> $M/MW-yr | D7: =KPIs!M13 -> n/d | E7: =KPIs!N13 -> n/d | F7: =KPIs!O13 -> n/d
A8: K06 | B8: =KPIs!B16 -> Revenue per GPU ($K per GPU-year, avg GPUs) | C8: =KPIs!C16 -> $K/GPU-yr | D8: =KPIs!M16 -> n/d | E8: =KPIs!N16 -> n/d | F8: =KPIs!O16 -> n/d
A9: K07 | B9: =KPIs!B18 -> Implied blended realized price ($/GPU-hr) | C9: =KPIs!C18 -> $/GPU-hr | D9: =KPIs!M18 -> n/d | E9: =KPIs!N18 -> n/d | F9: =KPIs!O18 -> n/d
A10: K09 | B10: =KPIs!B22 -> Implied utilization (realized $/GPU-hr / weighted list) | C10: =KPIs!C22 -> % | D10: =KPIs!M22 -> n/d | E10: =KPIs!N22 -> n/d | F10: =KPIs!O22 -> n/d
A11: K10 | B11: =KPIs!B25 -> Cash capex per new active MW | C11: =KPIs!C25 -> $M/MW | D11: =KPIs!M25 -> n/d | E11: =KPIs!N25 -> n/d | F11: =KPIs!O25 -> n/d
A12: K12 | B12: =KPIs!B29 -> In-service additions per new active MW | C12: =KPIs!C29 -> $M/MW | D12: =KPIs!M29 -> n/d | E12: =KPIs!N29 -> n/d | F12: =KPIs!O29 -> n/d
A13: K13 | B13: =KPIs!B31 -> Trailing-4Q cash capex per trailing-4Q new active MW | C13: =KPIs!C31 -> $M/MW | D13: =KPIs!M31 -> n/d | E13: =KPIs!N31 -> n/d | F13: =KPIs!O31 -> n/d
A14: K14 | B14: =KPIs!B33 -> Net PP&E per active MW (EoP) | C14: =KPIs!C33 -> $M/MW | D14: =KPIs!M33 -> n/d | E14: =KPIs!N33 -> n/d | F14: =KPIs!O33 -> n/d
A15: K15 | B15: =KPIs!B35 -> Gross in-service PP&E per active MW (EoP) | C15: =KPIs!C35 -> $M/MW | D15: =KPIs!M35 -> n/d | E15: =KPIs!N35 -> n/d | F15: =KPIs!O35 -> n/d
A16: K16 | B16: =KPIs!B38 -> Useful life - GPU / server equipment | C16: =KPIs!C38 -> years | D16: =KPIs!M38 -> 5 | E16: =KPIs!N38 -> 5 | F16: =KPIs!O38 -> 5
A17: K17 | B17: =KPIs!B40 -> Depreciation yield (D&A x4 / avg in-service gross PP&E) | C17: =KPIs!C40 -> % | D17: =KPIs!M40 -> 18.052806 | E17: =KPIs!N40 -> 18.634414 | F17: =KPIs!O40 -> 14.351359
A18: K20 | B18: =KPIs!B47 -> RPO (ASC 606, EoP) | C18: =KPIs!C47 -> $B | D18: =KPIs!M47 -> 0.289411 | E18: =KPIs!N47 -> 0.710272 | F18: =KPIs!O47 -> 5.1
A19: K21 | B19: =KPIs!B49 -> Revenue backlog (company metric / incl. contracted non-RPO, EoP) | C19: =KPIs!C49 -> $B | D19: =KPIs!M49 -> 9.989 | E19: =KPIs!N49 -> 10.41 | F19: =KPIs!O49 -> 16.6
A20: K22 | B20: =KPIs!B51 -> RPO % recognized within 24 months | C20: =KPIs!C51 -> % | D20: =KPIs!M51 -> 98.7 | E20: =KPIs!N51 -> 80.7 | F20: =KPIs!O51 -> 43.1
A21: K24 | B21: =KPIs!B56 -> Largest customer % of revenue | C21: =KPIs!C56 -> % | D21: =KPIs!M56 -> n/d | E21: =KPIs!N56 -> n/d | F21: =KPIs!O56 -> n/d
A22: K26 | B22: =KPIs!B60 -> Top-N >=10% customers combined % | C22: =KPIs!C60 -> % | D22: =KPIs!M60 -> n/d | E22: =KPIs!N60 -> n/d | F22: =KPIs!O60 -> n/d
A23: K27 | B23: =KPIs!B62 -> Number of customers >=10% of revenue | C23: =KPIs!C62 -> # | D23: =KPIs!M62 -> n/d | E23: =KPIs!N62 -> n/d | F23: =KPIs!O62 -> n/d
A24: K28 | B24: =KPIs!B65 -> Weighted effective cost of debt (principal-weighted, EoP) - all facilities | C24: =KPIs!C65 -> % | D24: =KPIs!M65 -> 1.0815181 | E24: =KPIs!N65 -> 1.0815181 | F24: =KPIs!O65 -> 1.8523437
A25: K30 | B25: =KPIs!B69 -> of which Senior notes - weighted eff. rate | C25: =KPIs!C69 -> % | D25: =KPIs!M69 -> n/d | E25: =KPIs!N69 -> n/d | F25: =KPIs!O69 -> 7.05
A26: K31 | B26: =KPIs!B71 -> of which Converts - weighted eff. rate | C26: =KPIs!C71 -> % | D26: =KPIs!M71 -> 1.0815181 | E26: =KPIs!N71 -> 1.0815181 | F26: =KPIs!O71 -> 1.1253157
A27: K36 | B27: =KPIs!B81 -> Implied cash cost: interest x4 / avg principal | C27: =KPIs!C81 -> % | D27: =KPIs!M81 -> 1.8021416 | E27: =KPIs!N81 -> 1.5844306 | F27: =KPIs!O81 -> 1.7092136
A28: K41 | B28: =KPIs!B92 -> Company-reported GPU utilization (physical) | C28: =KPIs!C92 -> % | D28: =KPIs!M92 -> n/d | E28: =KPIs!N92 -> n/d | F28: =KPIs!O92 -> n/d
A29: K42 | B29: =KPIs!B94 -> RPO % recognized within 12 months | C29: =KPIs!C94 -> % | D29: =KPIs!M94 -> 51.9 | E29: =KPIs!N94 -> 43.4 | F29: =KPIs!O94 -> 17.6
A30: K43 | B30: =KPIs!B96 -> Incremental annualized revenue per incremental MW (YoY) | C30: =KPIs!C96 -> $M/MW-yr | D30: =KPIs!M96 -> n/d | E30: =KPIs!N96 -> n/d | F30: =KPIs!O96 -> 6.8088018
A31: K44 | B31: =KPIs!B98 -> Annualized revenue / avg gross GPU-compute hardware in service | C31: =KPIs!C98 -> x | D31: =KPIs!M98 -> 0.21073181 | E31: =KPIs!N98 -> 0.19755864 | F31: =KPIs!O98 -> 0.19820104
A32: K45 | B32: =KPIs!B100 -> Segment gross margin (revenue - cost of revenue excl. D&A) / revenue | C32: =KPIs!C100 -> % | D32: =KPIs!M100 -> 86.154469 | E32: =KPIs!N100 -> 86.332689 | F32: =KPIs!O100 -> 86.936113
