Workbook

Sheet Assumptions
A1: Input | B1: Value | C1: Unit | D1: Tag | E1: Source / note
A2: Lives
A3: Life scenario A (yrs) | B3: 4 | C3: yrs | D3: Reported (pre-2026 policy) | E3: https://www.sec.gov/Archives/edgar/data/1513845/000110465926052948/nbis-20251231x20f.htm
A4: Life scenario B (yrs) - Nebius policy from 1/1/26 | B4: 5 | C4: yrs | D4: Reported | E4: https://www.sec.gov/Archives/edgar/data/1513845/000110465926094844/nbis-20260812xex99d2.htm Note 1
A5: Life scenario C (yrs) | B5: 6 | C5: yrs | D5: Reported (peer policy: CRWV/GOOGL/ORCL) | E5: v1 Peers sheet
A6: Shell & power (owned) / colo fit-out life | B6: 18 | C6: yrs | D6: Estimated (user assumption) | E6: User instruction 2026-10-04
A7: Existing 6/30 non-server PP&E blended life | B7: 12 | C7: yrs | D7: Estimated | E7: As v1
A8: Capex per IT MW by generation ($M) - Capacity's base case
A9: Hopper H100/H200: GPU/server + network/storage per IT MW | B9: 25.9 | C9: $M/IT MW | D9: Estimated (Capacity base) | E9: /workspace/nebius/capacity/gpu_mw_capex.xlsx + .md (team Capacity & Power) CapexPerMW base split
A10: Hopper H100/H200: DC shell + power, owned, per IT MW | B10: 10 | C10: $M/IT MW | D10: Estimated (Capacity base) | E10: /workspace/nebius/capacity/gpu_mw_capex.xlsx + .md (team Capacity & Power)
A11: Hopper H100/H200: colo capex (no shell) per IT MW | B11: 26.9 | C11: $M/IT MW | D11: Estimated (Capacity base) | E11: /workspace/nebius/capacity/gpu_mw_capex.xlsx + .md (team Capacity & Power) 'Colo capex Base'
A12: Hopper H100/H200: owned all-in per IT MW | B12: =$B$9+$B$10 | C12: $M/IT MW | D12: Derived | E12: GPU+net + shell (Capacity: B200 42, GB200 42, GB300 53)
A13: B200 (HGX): GPU/server + network/storage per IT MW | B13: 32.4 | C13: $M/IT MW | D13: Estimated (Capacity base) | E13: /workspace/nebius/capacity/gpu_mw_capex.xlsx + .md (team Capacity & Power) CapexPerMW base split
A14: B200 (HGX): DC shell + power, owned, per IT MW | B14: 10 | C14: $M/IT MW | D14: Estimated (Capacity base) | E14: /workspace/nebius/capacity/gpu_mw_capex.xlsx + .md (team Capacity & Power)
A15: B200 (HGX): colo capex (no shell) per IT MW | B15: 33.4 | C15: $M/IT MW | D15: Estimated (Capacity base) | E15: /workspace/nebius/capacity/gpu_mw_capex.xlsx + .md (team Capacity & Power) 'Colo capex Base'
A16: B200 (HGX): owned all-in per IT MW | B16: =$B$13+$B$14 | C16: $M/IT MW | D16: Derived | E16: GPU+net + shell (Capacity: B200 42, GB200 42, GB300 53)
A17: GB200 NVL72: GPU/server + network/storage per IT MW | B17: 29.2 | C17: $M/IT MW | D17: Estimated (Capacity base) | E17: /workspace/nebius/capacity/gpu_mw_capex.xlsx + .md (team Capacity & Power) CapexPerMW base split
A18: GB200 NVL72: DC shell + power, owned, per IT MW | B18: 12.5 | C18: $M/IT MW | D18: Estimated (Capacity base) | E18: /workspace/nebius/capacity/gpu_mw_capex.xlsx + .md (team Capacity & Power)
A19: GB200 NVL72: colo capex (no shell) per IT MW | B19: 30.2 | C19: $M/IT MW | D19: Estimated (Capacity base) | E19: /workspace/nebius/capacity/gpu_mw_capex.xlsx + .md (team Capacity & Power) 'Colo capex Base'
A20: GB200 NVL72: owned all-in per IT MW | B20: =$B$17+$B$18 | C20: $M/IT MW | D20: Derived | E20: GPU+net + shell (Capacity: B200 42, GB200 42, GB300 53)
A21: B300 (HGX): GPU/server + network/storage per IT MW | B21: 40.1 | C21: $M/IT MW | D21: Estimated (Capacity base) | E21: /workspace/nebius/capacity/gpu_mw_capex.xlsx + .md (team Capacity & Power) CapexPerMW base split
A22: B300 (HGX): DC shell + power, owned, per IT MW | B22: 10 | C22: $M/IT MW | D22: Estimated (Capacity base) | E22: /workspace/nebius/capacity/gpu_mw_capex.xlsx + .md (team Capacity & Power)
A23: B300 (HGX): colo capex (no shell) per IT MW | B23: 41.1 | C23: $M/IT MW | D23: Estimated (Capacity base) | E23: /workspace/nebius/capacity/gpu_mw_capex.xlsx + .md (team Capacity & Power) 'Colo capex Base'
A24: B300 (HGX): owned all-in per IT MW | B24: =$B$21+$B$22 | C24: $M/IT MW | D24: Derived | E24: GPU+net + shell (Capacity: B200 42, GB200 42, GB300 53)
A25: GB300 NVL72: GPU/server + network/storage per IT MW | B25: 40.2 | C25: $M/IT MW | D25: Estimated (Capacity base) | E25: /workspace/nebius/capacity/gpu_mw_capex.xlsx + .md (team Capacity & Power) CapexPerMW base split
A26: GB300 NVL72: DC shell + power, owned, per IT MW | B26: 12.5 | C26: $M/IT MW | D26: Estimated (Capacity base) | E26: /workspace/nebius/capacity/gpu_mw_capex.xlsx + .md (team Capacity & Power)
A27: GB300 NVL72: colo capex (no shell) per IT MW | B27: 41.3 | C27: $M/IT MW | D27: Estimated (Capacity base) | E27: /workspace/nebius/capacity/gpu_mw_capex.xlsx + .md (team Capacity & Power) 'Colo capex Base'
A28: GB300 NVL72: owned all-in per IT MW | B28: =$B$25+$B$26 | C28: $M/IT MW | D28: Derived | E28: GPU+net + shell (Capacity: B200 42, GB200 42, GB300 53)
A29: Vera Rubin NVL72: GPU/server + network/storage per IT MW | B29: 30.3 | C29: $M/IT MW | D29: Estimated (Capacity base) | E29: /workspace/nebius/capacity/gpu_mw_capex.xlsx + .md (team Capacity & Power) CapexPerMW base split
A30: Vera Rubin NVL72: DC shell + power, owned, per IT MW | B30: 12.5 | C30: $M/IT MW | D30: Estimated (Capacity base) | E30: /workspace/nebius/capacity/gpu_mw_capex.xlsx + .md (team Capacity & Power)
A31: Vera Rubin NVL72: colo capex (no shell) per IT MW | B31: 31.3 | C31: $M/IT MW | D31: Estimated (Capacity base) | E31: /workspace/nebius/capacity/gpu_mw_capex.xlsx + .md (team Capacity & Power) 'Colo capex Base'
A32: Vera Rubin NVL72: owned all-in per IT MW | B32: =$B$29+$B$30 | C32: $M/IT MW | D32: Derived | E32: GPU+net + shell (Capacity: B200 42, GB200 42, GB300 53)
A33: Gross (facility) MW per IT MW | B33: 1.25 | C33: x | D33: Derived (Capacity) | E33: Vineland 300 MW gross ~ 230-250 MW IT => 1.2-1.3; Capacity PUE base 1.20-1.30
A34: Nebius ACV/MW basis = gross MW? (1 = gross, 0 = IT) | B34: 1 | C34: flag | D34: Estimated | E34: Microsoft $11.6M/gross MW-yr ~ the '2026 base ~$12M' in Q2 letter => ACV quoted on gross/contracted MW (Capacity). Not stated by Nebius
A35: Opex per MW
A36: Power cost | B36: 139 | C36: $/MWh | D36: Estimated (Capacity range 93-185, midpoint) | E36: Team inputs relayed 2026-10-04 18:20 ET (Capacity physical evidence / Filings); Bloom is a power purchase (opex), not capex
A37: Average load factor on gross MW | B37: 0.9 | C37: % | D37: Estimated | E37: Calibrates to Capacity's ~$1.1M per gross MW-yr at midpoint: 139 x 8,760 x 0.9 = $1.10M
A38: Power cost per gross MW-yr | B38: =$B$36*8760*$B$37/1000000 | C38: $M | D38: Derived
A39: Colo rent per IT MW-yr (leased sites only) | B39: 2.25 | C39: $M | D39: Estimated (Capacity range 2.0-2.5) | E39: /workspace/nebius/capacity/gpu_mw_capex.xlsx + .md (team Capacity & Power) peers: colo rent $165-205/kW-mo
A40: Q2'26 AI cloud segment adj. EBITDA margin (calibration) | B40: 0.497 | C40: % | D40: Reported | E40: /workspace/nebius/filings/nebius_fact_base.md
A41: Calibration ACV (installed book, per gross MW) | B41: 12 | C41: $M | D41: Reported (approx.) | E41: https://www.sec.gov/Archives/edgar/data/1513845/000110465926094568/tm2622968d1_ex99-2.htm p.3-4
A42: Other cash opex % of revenue (staff, network, support, SG&A) | B42: =1-$B$40-$B$38/$B$41-$B$39/($B$41*$B$33) | C42: % | D42: Derived (calibration) | E42: Assumes the Q2 segment margin = installed book on leased sites: 1 - 49.7% - power/rev - rent/rev
A43: Cohort pricing & terms
A44: Installed book ACV per gross MW-yr | B44: 12 | C44: $M | D44: Reported (approx.) | E44: https://www.sec.gov/Archives/edgar/data/1513845/000110465926094568/tm2622968d1_ex99-2.htm
A45: Q2 new deals ACV - low | B45: 20 | C45: $M | D45: Reported | E45: https://www.sec.gov/Archives/edgar/data/1513845/000110465926094568/tm2622968d1_ex99-2.htm
A46: Q2 new deals ACV - high | B46: 25 | C46: $M | D46: Reported | E46: https://www.sec.gov/Archives/edgar/data/1513845/000110465926094568/tm2622968d1_ex99-2.htm
A47: Q3 short-term deals ACV | B47: 40 | C47: $M | D47: Reported ('>$40M') | E47: https://www.sec.gov/Archives/edgar/data/1513845/000110465926094568/tm2622968d1_ex99-2.htm
A48: Microsoft ACV per gross MW-yr | B48: =17392.9/5/300 | C48: $M | D48: Derived | E48: $17,392.9M / 5 yrs / 300 MW gross = $11.6M (= ~$1,324/MWh)
A49: Microsoft ACV if contract covers 200 MW | B49: =17392.9/5/200 | C49: $M | D49: Derived | E49: Capacity: ~$17.4M at 200 MW
A50: Term - installed book / Q2 deals | B50: 5 | C50: yrs | D50: Estimated | E50: Strategic contracts (MSFT, Meta) are 5-yr (R); Q2-deal terms not disclosed
A51: Term - short-term deals | B51: 1 | C51: yrs | D51: Estimated | E51: 'short-term' not defined by Nebius
A52: Term - Microsoft (per tranche) | B52: 5 | C52: yrs | D52: Reported | E52: 60 months per tranche (https://www.sec.gov/Archives/edgar/data/1513845/000110465925088312/tm2525580d1_6k.htm)
A53: Microsoft SLA / service-credit haircut on billed revenue | B53: 0 | C53: % | D53: Scenario input | E53: Take-or-pay 'irrespective of actual utilization' - haircut is service credits, not demand; 0% base, test 2-5%
A54: Prepayment, % of related capex, for a prepaid deal | B54: 0.55 | C54: % | D54: Reported (company: 50-60%) | E54: /workspace/nebius/filings/nebius_fact_base.md
A55: Share of deals carrying prepayments | B55: 0.7 | C55: % | D55: Reported (company) | E55: /workspace/nebius/filings/nebius_fact_base.md
A56: Microsoft upfront share of TCV | B56: =6958.1/17392.9 | C56: % | D56: Derived | E56: ~$6,958.1M upfront / $17,392.9M TCV (20-F Note 1)
A57: Residual value after contract term (re-rent) - GPU Market A100 evidence (v3.1)
A58: Realized utilization on post-term re-rent | B58: 0.6 | C58: % | D58: Estimated (user bear case) | E58: User instruction
A59: Residual curve: 1 = hyperscaler A100 list (-1.8%/yr), 2 = spot median ~flat, 3 = neocloud composite (+12%/yr), 4 = A100 80GB median, 5 = v3 placeholder (cross-section) | B59: 1 | C59: flag | D59: Scenario input | E59: Default = most conservative LIST series; all are list prices except 2 (spot)
A60: A100 hyperscaler median list, CAGR Nov-20 to Oct-26 | B60: -0.018 | C60: %/yr | D60: Reported (GPU Market) | E60: /workspace/nebius/market/gpu_price_history.xlsx (A100_Decay; team GPU Market): $4.096 -> $3.673
A61: A100 spot/marketplace median CAGR (treated as ~flat) | B61: 0 | C61: %/yr | D61: Reported (GPU Market; file CAGR +2.2%, $0.93 -> $1.055) | E61: /workspace/nebius/market/gpu_price_history.xlsx (A100_Decay; team GPU Market)
A62: A100 neocloud composite median CAGR Jul-22 to Oct-26 | B62: 0.12 | C62: %/yr | D62: Reported (GPU Market) | E62: /workspace/nebius/market/gpu_price_history.xlsx (A100_Decay; team GPU Market): $1.234 -> $2.00
A63: A100 80GB median CAGR (relay: $1.87 -> $2.50 over ~6 yrs) | B63: =(2.5/1.87)^(1/6)-1 | C63: %/yr | D63: Derived (GPU Market relay; file's 80GB neocloud median is $2.04 Apr-23 -> $2.50, +6%/yr) | E63: /workspace/nebius/market/gpu_price_history.xlsx (A100_Decay; team GPU Market)
A64: Cap on residual index (x launch price) | B64: 1 | C64: x | D64: Estimated | E64: Do not assume re-rent above the cohort's own launch price
A65: v3 placeholder index age 1 (superseded) | B65: 1 | C65: x | D65: Superseded placeholder | E65: A100 vs then-flagship cross-section (v3)
A66: v3 placeholder index age 2 (superseded) | B66: 0.82 | C66: x | D66: Superseded placeholder | E66: A100 vs then-flagship cross-section (v3)
A67: v3 placeholder index age 3 (superseded) | B67: 0.64 | C67: x | D67: Superseded placeholder | E67: A100 vs then-flagship cross-section (v3)
A68: v3 placeholder index age 4 (superseded) | B68: 0.53 | C68: x | D68: Superseded placeholder | E68: A100 vs then-flagship cross-section (v3)
A69: v3 placeholder index age 5 (superseded) | B69: 0.46 | C69: x | D69: Superseded placeholder | E69: A100 vs then-flagship cross-section (v3)
A70: v3 placeholder index age 6 (superseded) | B70: 0.39 | C70: x | D70: Superseded placeholder | E70: A100 vs then-flagship cross-section (v3)
A71: Residual price index at asset age 1 yrs (x the cohort's own launch price) | B71: =MIN($B$64,CHOOSE($B$59,(1+$B$60)^0,(1+$B$61)^0,(1+$B$62)^0,(1+$B$63)^0,$B$65)) | C71: x | D71: Derived (GPU Market A100 evidence) | E71: LIST prices; spot median roughly flat. A100 (Nov-20 launch) still rents at ~list after 6 yrs => 5-6 yr economic life supported
A72: Residual price index at asset age 2 yrs (x the cohort's own launch price) | B72: =MIN($B$64,CHOOSE($B$59,(1+$B$60)^1,(1+$B$61)^1,(1+$B$62)^1,(1+$B$63)^1,$B$66)) | C72: x | D72: Derived (GPU Market A100 evidence) | E72: LIST prices; spot median roughly flat. A100 (Nov-20 launch) still rents at ~list after 6 yrs => 5-6 yr economic life supported
A73: Residual price index at asset age 3 yrs (x the cohort's own launch price) | B73: =MIN($B$64,CHOOSE($B$59,(1+$B$60)^2,(1+$B$61)^2,(1+$B$62)^2,(1+$B$63)^2,$B$67)) | C73: x | D73: Derived (GPU Market A100 evidence) | E73: LIST prices; spot median roughly flat. A100 (Nov-20 launch) still rents at ~list after 6 yrs => 5-6 yr economic life supported
A74: Residual price index at asset age 4 yrs (x the cohort's own launch price) | B74: =MIN($B$64,CHOOSE($B$59,(1+$B$60)^3,(1+$B$61)^3,(1+$B$62)^3,(1+$B$63)^3,$B$68)) | C74: x | D74: Derived (GPU Market A100 evidence) | E74: LIST prices; spot median roughly flat. A100 (Nov-20 launch) still rents at ~list after 6 yrs => 5-6 yr economic life supported
A75: Residual price index at asset age 5 yrs (x the cohort's own launch price) | B75: =MIN($B$64,CHOOSE($B$59,(1+$B$60)^4,(1+$B$61)^4,(1+$B$62)^4,(1+$B$63)^4,$B$69)) | C75: x | D75: Derived (GPU Market A100 evidence) | E75: LIST prices; spot median roughly flat. A100 (Nov-20 launch) still rents at ~list after 6 yrs => 5-6 yr economic life supported
A76: Residual price index at asset age 6 yrs (x the cohort's own launch price) | B76: =MIN($B$64,CHOOSE($B$59,(1+$B$60)^5,(1+$B$61)^5,(1+$B$62)^5,(1+$B$63)^5,$B$70)) | C76: x | D76: Derived (GPU Market A100 evidence) | E76: LIST prices; spot median roughly flat. A100 (Nov-20 launch) still rents at ~list after 6 yrs => 5-6 yr economic life supported
A77: Re-rent reference price per gross MW-yr (new-capacity market rate) | B77: =$B$45 | C77: $M | D77: Derived | E77: Q2-deal low ($20M); re-rent = MIN(cohort ACV, ref) x index x utilization
A78: Fleet build mix (Sites sheet)
A79: Owned share of capex: 1 = Capacity tracker (owned sites' share of energized MW added in FY), 2 = all leased (0%), 3 = all owned (100%) | B79: 1 | C79: flag | D79: Scenario input | E79: Nebius is mostly leased today (started leases $1,625M; $12.05B signed not started). Unknown-basis sites run both via modes 2/3
A80: GPU+network share of FY26 capex and not-yet-in-use | B80: 0.79 | C80: % | D80: Estimated (mgmt via secondary) | E80: ~79% GPUs / 20% DC / <1% power (Q4'25 call, secondary). 2027+ share derived from mix and generation
A81: First capex quarter buying Vera Rubin (index; 0 = Q3'26) | B81: 4 | C81: idx | D81: Estimated | E81: Meta #2 Vera Rubin from early 2027 (R); Q3'27 capex onward priced as VR
A82: Lags (Modeling pushback)
A83: Capex -> energized / in service | B83: 2 | C83: quarters | D83: Estimated | E83: Capacity gives no explicit lag (gpu_mw_capex.md caveat 5: GPUs bought ~ at energization); v1 value kept
A84: Capex basis: 1 = consensus capex, 2 = path-consistent (Capacity energized-MW adds x capex per IT MW) - BASE CASE = 2 from v3.2 | B84: 2 | C84: flag | D84: Scenario input | E84: v3.1. Consensus capex implies ~157-200 IT MW bought/qtr, faster than Capacity's base path
A85: Path basis: GPU/IT spend this many quarters BEFORE billing | B85: 1 | C85: quarters | D85: Estimated (team) | E85: Test 2
A86: Path basis: shell/power spend this many quarters before energization (owned) | B86: 2 | C86: quarters | D86: Estimated (user)
A87: Path basis: leased-site capex per IT MW (IT only, no shell) - GB200 | B87: 30 | C87: $M/IT MW | D87: Estimated (Capacity, medium confidence; corrected 2026-10-04 19:02 ET) | E87: /workspace/nebius/capacity/gpu_mw_capex.xlsx + .md (team Capacity & Power)
A88: Path basis: leased-site capex per IT MW - GB300 | B88: 41 | C88: $M/IT MW | D88: Estimated (Capacity, medium confidence) | E88: /workspace/nebius/capacity/gpu_mw_capex.xlsx + .md (team Capacity & Power)
A89: Path basis: leased-site capex per IT MW - Vera Rubin (midpoint of $31-33M) | B89: 32 | C89: $M/IT MW | D89: Estimated (Capacity, medium confidence) | E89: /workspace/nebius/capacity/gpu_mw_capex.xlsx + .md (team Capacity & Power)
A90: Connected/energized -> billing (revenue) | B90: 1 | C90: quarters | D90: Estimated (Filings: mgmt's 'few months' lag runs from connected power to revenue; Capacity uses 1-2 qtrs) | E90: /workspace/nebius/filings/nebius_filings.xlsx; run 1 (default) and 2
A91: Capacity MW scenario: 1 = low, 2 = base, 3 = high | B91: 2 | C91: flag | D91: Scenario input | E91: /workspace/nebius/capacity/nebius_capacity.xlsx 'Quarterly MW' energized rows
A92: Unseen-site MW added (gross), e.g. Oklahoma / Minnesota colos - per quarter from Q4'26 | B92: 0 | C92: MW/qtr | D92: Scenario input | E92: Capacity: MN, OK, France 2nd, UK 3rd MW not disclosed (plug to reach guide ~496 MW at YE26 base)
A93: ACV on incremental (post-Q2'26) MW, per gross MW-yr | B93: 22.5 | C93: $M | D93: Reported range midpoint ($20-25M Q2 deals) | E93: https://www.sec.gov/Archives/edgar/data/1513845/000110465926094568/tm2622968d1_ex99-2.htm
A94: On-demand + Token Factory share of revenue | B94: 0.04 | C94: % | D94: Reported (team GPU Market revenue mix: take-or-pay 45%, reserved ~50%, on-demand+TF ~4%) | E94: /workspace/nebius/market (GPU Market)
A95: Oct 1 2026 on-demand list-price hike | B95: 0.19 | C95: % | D95: Reported (17-21%; H100 3.85->4.50, B300 7.85->9.50) | E95: nebius.com/prices via GPU Market
A96: Price cycle (v3.1 bear input)
A97: Blackwell $/GPU-hr cut in the 12 months after Rubin launch | B97: 0.275 | C97: % | D97: Scenario input (25-30%) | E97: Team bear input; 5-yr life unchanged underneath
A98: Rubin launch quarter (Rev_MW index; 0 = Q3'26, 2 = Q1'27) | B98: 2 | C98: idx | D98: Estimated | E98: GPU Market: Nebius Rubin GA ~Dec'26-Mar'27; cut phases in linearly over 4 quarters
A99: Reserved share of revenue | B99: 0.5 | C99: % | D99: Reported (GPU Market mix) | E99: take-or-pay 45% (not exposed), reserved ~50%, on-demand + Token Factory ~4%
A100: Share of reserved contracts that renew (reprice) inside the window | B100: 0.5 | C100: % | D100: Scenario input | E100: Test 0-100%
...

Sheet Sites
A1: # | B1: Site | C1: Country | D1: Tracker type | E1: Ownership tag (v2) | F1: YE26 MW low | G1: YE26 MW base | H1: YE26 MW high | I1: MW basis | J1: Owned base MW | K1: Source
A2: 1 | B2: Mantsala DC #1 | C2: Finland | D2: Owned greenfield | E2: Owned | F2: 75 | G2: 75 | H2: 75 | I2: not disclosed (PUE ~1.1) | J2: =IF(LEFT(E2,5)="Owned",G2,0) | K2: /workspace/nebius/capacity/site_list.xlsx (team Capacity & Power)
A3: 2 | B3: Mantsala DC #2 | C3: Finland | D3: Owned (implied) | E3: Owned | F3: 0 | G3: 0 | H3: 0 | I3: n/d | J3: =IF(LEFT(E3,5)="Owned",G3,0) | K3: /workspace/nebius/capacity/site_list.xlsx (team Capacity & Power)
A4: 3 | B4: Lappeenranta | C4: Finland | D4: Owned per Nebius; developer says Nebius 'operating Polarnode's campus' | E4: Unknown (conflict) | F4: 0 | G4: 0 | H4: 0 | I4: n/d | J4: =IF(LEFT(E4,5)="Owned",G4,0) | K4: /workspace/nebius/capacity/site_list.xlsx (team Capacity & Power)
A5: 4 | B5: Paris Equinix PA10 | C5: France | D5: Colocation | E5: Leased | F5: 5 | G5: 5 | H5: 5 | I5: n/d | J5: =IF(LEFT(E5,5)="Owned",G5,0) | K5: /workspace/nebius/capacity/site_list.xlsx (team Capacity & Power)
A6: 5 | B6: Bethune | C6: France | D6: Colocation per 20-F | E6: Leased | F6: 0 | G6: 120 | H6: 120 | I6: n/d | J6: =IF(LEFT(E6,5)="Owned",G6,0) | K6: /workspace/nebius/capacity/site_list.xlsx (team Capacity & Power)
A7: 6 | B7: France 2nd colo | C7: France | D7: Colocation | E7: Leased | F7: 0 | G7: 0 | H7: 0 | I7: n/d | J7: =IF(LEFT(E7,5)="Owned",G7,0) | K7: /workspace/nebius/capacity/site_list.xlsx (team Capacity & Power)
A8: 7 | B8: Keflavik Verne | C8: Iceland | D8: Colocation | E8: Leased | F8: 10 | G8: 10 | H8: 10 | I8: n/d | J8: =IF(LEFT(E8,5)="Owned",G8,0) | K8: /workspace/nebius/capacity/site_list.xlsx (team Capacity & Power)
A9: 8 | B9: London Longcross (Ark) | C9: UK | D9: Colocation | E9: Leased | F9: 16 | G9: 19 | H9: 19 | I9: gross (Capacity inference) | J9: =IF(LEFT(E9,5)="Owned",G9,0) | K9: /workspace/nebius/capacity/site_list.xlsx (team Capacity & Power)
A10: 9 | B10: Harlow Kao | C10: UK | D10: Colocation | E10: Leased | F10: 0 | G10: 0 | H10: 4.4 | I10: n/d | J10: =IF(LEFT(E10,5)="Owned",G10,0) | K10: /workspace/nebius/capacity/site_list.xlsx (team Capacity & Power)
A11: 10 | B11: UK 3rd site | C11: UK | D11: not disclosed (likely colo - inference) | E11: Unknown | F11: 0 | G11: 0 | H11: 0 | I11: n/d | J11: =IF(LEFT(E11,5)="Owned",G11,0) | K11: /workspace/nebius/capacity/site_list.xlsx (team Capacity & Power)
A12: 11 | B12: Modi'in Mega Or | C12: Israel | D12: Colocation | E12: Leased | F12: 8 | G12: 8 | H12: 8 | I12: IT (Capacity) | J12: =IF(LEFT(E12,5)="Owned",G12,0) | K12: /workspace/nebius/capacity/site_list.xlsx (team Capacity & Power)
A13: 12 | B13: Masmiyya | C13: Israel | D13: Colocation | E13: Leased | F13: 0 | G13: 22 | H13: 22 | I13: n/d | J13: =IF(LEFT(E13,5)="Owned",G13,0) | K13: /workspace/nebius/capacity/site_list.xlsx (team Capacity & Power)
... A24: 23 | B24: AIB southeastern US | C24: USA | D24: Colocation/leased 12-yr | E24: Leased | F24: 0 | G24: 0 | H24: 0 | I24: IT (50 MW critical IT) | J24: =IF(LEFT(E24,5)="Owned",G24,0) | K24: /workspace/nebius/capacity/site_list.xlsx (team Capacity & Power)
B25: TOTAL | F25: =SUM(F2:F24) | G25: =SUM(G2:G24) | H25: =SUM(H2:H24) | J25: =SUM(J2:J24)
B27: Owned share of YE26 base MW | J27: =J25/G25
B28: Leased (incl. Vineland) share | J28: =SUMPRODUCT((LEFT(E2:E24,6)="Leased")*G2:G24)/G25
B29: Unknown: Lappeenranta, UK 3rd (0 MW in YE26 base) - run owned and leased (Cohorts both; fleet owned-share 0%/100% in md)

Sheet MW
A1: Capacity energized MW (identified sites) - /workspace/nebius/capacity/nebius_capacity.xlsx 'Quarterly MW' (pasted values, blue) | C1: Q2 2026 | D1: Q3 2026 | E1: Q4 2026 | F1: Q1 2027 | G1: Q2 2027 | H1: Q3 2027 | I1: Q4 2027 | J1: Q1 2028 | K1: Q2 2028 | L1: Q3 2028 | M1: Q4 2028 | N1: Q1 2029 | O1: Q2 2029 | P1: Q3 2029 | Q1: Q4 2029 | R1: Q1 2030 | S1: Q2 2030 | T1: Q3 2030 | U1: Q4 2030
A2: Energized MW, identified sites - low (mixed basis) | B2: Capacity Quarterly MW (sum of site rows; ties to COMPANY rows) | C2: 152 | D2: 182 | E2: 185 | F2: 270.4 | G2: 394.4 | H2: 509 | I2: 764 | J2: 824 | K2: 994 | L2: 1019 | M2: 1539 | N2: 1539 | O2: 1769 | P2: 1769 | Q2: 2289 | R2: 2289 | S2: 2289 | T2: 2289 | U2: 2839
A3: of which IT-basis sites (Vineland, AIB) - low | B3: Capacity Basis column = IT | C3: 41 | D3: 65 | E3: 65 | F3: 65 | G3: 115 | H3: 168 | I3: 238 | J3: 263 | K3: 263 | L3: 288 | M3: 288 | N3: 288 | O3: 288 | P3: 288 | Q3: 288 | R3: 288 | S3: 288 | T3: 288 | U3: 288
A4: of which Vineland (IT) - low | B4: Capacity | C4: 33 | D4: 57 | E4: 57 | F4: 57 | G4: 107 | H4: 160 | I4: 230 | J4: 230 | K4: 230 | L4: 230 | M4: 230 | N4: 230 | O4: 230 | P4: 230 | Q4: 230 | R4: 230 | S4: 230 | T4: 230 | U4: 230
A5: of which owned sites (Independence, Butler PA, Birmingham, Lappeenranta, Mantsala) - low | B5: Capacity Sites 'Ownership type' | C5: 75 | D5: 75 | E5: 75 | F5: 75 | G5: 75 | H5: 100 | I5: 210 | J5: 245 | K5: 415 | L5: 415 | M5: 815 | N5: 815 | O5: 1045 | P5: 1045 | Q5: 1565 | R5: 1565 | S5: 1565 | T5: 1565 | U5: 2115
A6: Energized MW, identified sites - base (mixed basis) | B6: Capacity Quarterly MW (sum of site rows; ties to COMPANY rows) | C6: 173 | D6: 207.5 | E6: 304.5 | F6: 444.7 | G6: 591.7 | H6: 751.5 | I6: 1069 | J6: 1181.5 | K6: 1376.5 | L6: 1389 | M6: 1799 | N6: 1799 | O6: 2219 | P6: 2219 | Q6: 2804 | R6: 2804 | S6: 2804 | T6: 2804 | U6: 3379
A7: of which IT-basis sites (Vineland, AIB) - base | B7: Capacity Basis column = IT | C7: 47 | D7: 74 | E7: 89.8 | F7: 126.5 | G7: 176.5 | H7: 225.5 | I7: 273 | J7: 285.5 | K7: 285.5 | L7: 298 | M7: 298 | N7: 298 | O7: 298 | P7: 298 | Q7: 298 | R7: 298 | S7: 298 | T7: 298 | U7: 298
A8: of which Vineland (IT) - base | B8: Capacity | C8: 39 | D8: 66 | E8: 81.8 | F8: 118.5 | G8: 168.5 | H8: 205 | I8: 240 | J8: 240 | K8: 240 | L8: 240 | M8: 240 | N8: 240 | O8: 240 | P8: 240 | Q8: 240 | R8: 240 | S8: 240 | T8: 240 | U8: 240
A9: of which owned sites (Independence, Butler PA, Birmingham, Lappeenranta, Mantsala) - base | B9: Capacity Sites 'Ownership type' | C9: 75 | D9: 75 | E9: 75 | F9: 87.5 | G9: 117.5 | H9: 210 | I9: 410 | J9: 510 | K9: 705 | L9: 705 | M9: 1055 | N9: 1055 | O9: 1475 | P9: 1475 | Q9: 2060 | R9: 2060 | S9: 2060 | T9: 2060 | U9: 2635
A10: Energized MW, identified sites - high (mixed basis) | B10: Capacity Quarterly MW (sum of site rows; ties to COMPANY rows) | C10: 194 | D10: 233 | E10: 424 | F10: 619 | G10: 789 | H10: 994 | I10: 1374 | J10: 1539 | K10: 1759 | L10: 1759 | M10: 2059 | N10: 2059 | O10: 2669 | P10: 2669 | Q10: 3319 | R10: 3319 | S10: 3319 | T10: 3319 | U10: 3919
A11: of which IT-basis sites (Vineland, AIB) - high | B11: Capacity Basis column = IT | C11: 53 | D11: 83 | E11: 114.6 | F11: 188 | G11: 238 | H11: 283 | I11: 308 | J11: 308 | K11: 308 | L11: 308 | M11: 308 | N11: 308 | O11: 308 | P11: 308 | Q11: 308 | R11: 308 | S11: 308 | T11: 308 | U11: 308
A12: of which Vineland (IT) - high | B12: Capacity | C12: 45 | D12: 75 | E12: 106.6 | F12: 180 | G12: 230 | H12: 250 | I12: 250 | J12: 250 | K12: 250 | L12: 250 | M12: 250 | N12: 250 | O12: 250 | P12: 250 | Q12: 250 | R12: 250 | S12: 250 | T12: 250 | U12: 250
A13: of which owned sites (Independence, Butler PA, Birmingham, Lappeenranta, Mantsala) - high | B13: Capacity Sites 'Ownership type' | C13: 75 | D13: 75 | E13: 75 | F13: 100 | G13: 160 | H13: 320 | I13: 610 | J13: 775 | K13: 995 | L13: 995 | M13: 1295 | N13: 1295 | O13: 1905 | P13: 1905 | Q13: 2555 | R13: 2555 | S13: 2555 | T13: 2555 | U13: 3155
A15: Selected energized MW (mixed) | C15: =CHOOSE(Assumptions!$B$91,C2,C6,C10) | D15: =CHOOSE(Assumptions!$B$91,D2,D6,D10) | E15: =CHOOSE(Assumptions!$B$91,E2,E6,E10) | F15: =CHOOSE(Assumptions!$B$91,F2,F6,F10) | G15: =CHOOSE(Assumptions!$B$91,G2,G6,G10) | H15: =CHOOSE(Assumptions!$B$91,H2,H6,H10) | I15: =CHOOSE(Assumptions!$B$91,I2,I6,I10) | J15: =CHOOSE(Assumptions!$B$91,J2,J6,J10) | ... U15: =CHOOSE(Assumptions!$B$91,U2,U6,U10)
A16: Selected IT-basis MW | C16: =CHOOSE(Assumptions!$B$91,C3,C7,C11) | D16: =CHOOSE(Assumptions!$B$91,D3,D7,D11) | E16: =CHOOSE(Assumptions!$B$91,E3,E7,E11) | F16: =CHOOSE(Assumptions!$B$91,F3,F7,F11) | G16: =CHOOSE(Assumptions!$B$91,G3,G7,G11) | H16: =CHOOSE(Assumptions!$B$91,H3,H7,H11) | I16: =CHOOSE(Assumptions!$B$91,I3,I7,I11) | J16: =CHOOSE(Assumptions!$B$91,J3,J7,J11) | ... U16: =CHOOSE(Assumptions!$B$91,U3,U7,U11)
A17: Selected Vineland IT MW | C17: =CHOOSE(Assumptions!$B$91,C4,C8,C12) | D17: =CHOOSE(Assumptions!$B$91,D4,D8,D12) | E17: =CHOOSE(Assumptions!$B$91,E4,E8,E12) | F17: =CHOOSE(Assumptions!$B$91,F4,F8,F12) | G17: =CHOOSE(Assumptions!$B$91,G4,G8,G12) | H17: =CHOOSE(Assumptions!$B$91,H4,H8,H12) | I17: =CHOOSE(Assumptions!$B$91,I4,I8,I12) | J17: =CHOOSE(Assumptions!$B$91,J4,J8,J12) | ... U17: =CHOOSE(Assumptions!$B$91,U4,U8,U12)
A18: Selected owned-site MW | C18: =CHOOSE(Assumptions!$B$91,C5,C9,C13) | D18: =CHOOSE(Assumptions!$B$91,D5,D9,D13) | E18: =CHOOSE(Assumptions!$B$91,E5,E9,E13) | F18: =CHOOSE(Assumptions!$B$91,F5,F9,F13) | G18: =CHOOSE(Assumptions!$B$91,G5,G9,G13) | H18: =CHOOSE(Assumptions!$B$91,H5,H9,H13) | I18: =CHOOSE(Assumptions!$B$91,I5,I9,I13) | J18: =CHOOSE(Assumptions!$B$91,J5,J9,J13) | ... U18: =CHOOSE(Assumptions!$B$91,U5,U9,U13)
A19: Energized GROSS MW (unknown basis treated as gross; IT x PUE) | C19: =C15-C16+C16*Assumptions!$B$33 | D19: =D15-D16+D16*Assumptions!$B$33 | E19: =E15-E16+E16*Assumptions!$B$33 | F19: =F15-F16+F16*Assumptions!$B$33 | G19: =G15-G16+G16*Assumptions!$B$33 | H19: =H15-H16+H16*Assumptions!$B$33 | I19: =I15-I16+I16*Assumptions!$B$33 | J19: =J15-J16+J16*Assumptions!$B$33 | ... U19: =U15-U16+U16*Assumptions!$B$33
A20: + Unseen-site gross MW (cumulative from Q4'26) | C20: =IF(0>=2,(0-1)*Assumptions!$B$92,0) | D20: =IF(1>=2,(1-1)*Assumptions!$B$92,0) | E20: =IF(2>=2,(2-1)*Assumptions!$B$92,0) | F20: =IF(3>=2,(3-1)*Assumptions!$B$92,0) | G20: =IF(4>=2,(4-1)*Assumptions!$B$92,0) | H20: =IF(5>=2,(5-1)*Assumptions!$B$92,0) | I20: =IF(6>=2,(6-1)*Assumptions!$B$92,0) | J20: =IF(7>=2,(7-1)*Assumptions!$B$92,0) | K20: =IF(8>=2,(8-1)*Assumptions!$B$92,0) | L20: =IF(9>=2,(9-1)*Assumptions!$B$92,0) | M20: =IF(10>=2,(10-1)*Assumptions!$B$92,0) | N20: =IF(11>=2,(11-1)*Assumptions!$B$92,0) | O20: =IF(12>=2,(12-1)*Assumptions!$B$92,0) | P20: =IF(13>=2,(13-1)*Assumptions!$B$92,0) | Q20: =IF(14>=2,(14-1)*Assumptions!$B$92,0) | R20: =IF(15>=2,(15-1)*Assumptions!$B$92,0) | S20: =IF(16>=2,(16-1)*Assumptions!$B$92,0) | T20: =IF(17>=2,(17-1)*Assumptions!$B$92,0) | U20: =IF(18>=2,(18-1)*Assumptions!$B$92,0)
A21: Energized gross MW incl. unseen | C21: =C19+C20 | D21: =D19+D20 | E21: =E19+E20 | F21: =F19+F20 | G21: =G19+G20 | H21: =H19+H20 | I21: =I19+I20 | J21: =J19+J20 | ... U21: =U19+U20
A22: IT-equivalent energized MW incl. unseen (gross / PUE) | C22: =C21/Assumptions!$B$33 | D22: =D21/Assumptions!$B$33 | E22: =E21/Assumptions!$B$33 | F22: =F21/Assumptions!$B$33 | G22: =G21/Assumptions!$B$33 | H22: =H21/Assumptions!$B$33 | I22: =I21/Assumptions!$B$33 | J22: =J21/Assumptions!$B$33 | ... U22: =U21/Assumptions!$B$33
A23: IT MW energized in quarter (additions) | C23: =IF(0=0,0,C22-None22) | D23: =IF(1=0,0,D22-C22) | E23: =IF(2=0,0,E22-D22) | F23: =IF(3=0,0,F22-E22) | G23: =IF(4=0,0,G22-F22) | H23: =IF(5=0,0,H22-G22) | I23: =IF(6=0,0,I22-H22) | J23: =IF(7=0,0,J22-I22) | K23: =IF(8=0,0,K22-J22) | L23: =IF(9=0,0,L22-K22) | M23: =IF(10=0,0,M22-L22) | N23: =IF(11=0,0,N22-M22) | O23: =IF(12=0,0,O22-N22) | P23: =IF(13=0,0,P22-O22) | Q23: =IF(14=0,0,Q22-P22) | R23: =IF(15=0,0,R22-Q22) | S23: =IF(16=0,0,S22-R22) | T23: =IF(17=0,0,T22-S22) | U23: =IF(18=0,0,U22-T22)
A24: Vineland gross MW | C24: =C17*Assumptions!$B$33 | D24: =D17*Assumptions!$B$33 | E24: =E17*Assumptions!$B$33 | F24: =F17*Assumptions!$B$33 | G24: =G17*Assumptions!$B$33 | H24: =H17*Assumptions!$B$33 | I24: =I17*Assumptions!$B$33 | J24: =J17*Assumptions!$B$33 | ... U24: =U17*Assumptions!$B$33
A25: BILLING gross MW (energized shifted by billing lag; lag 0/1/2 supported) | C25: =IF(Assumptions!$B$90=0,C21,IF(Assumptions!$B$90=1,IF(0>=1,INDEX($C$21:$U$21,0),C21),IF(0>=2,INDEX($C$21:$U$21,0-1),$C$21))) | D25: =IF(Assumptions!$B$90=0,D21,IF(Assumptions!$B$90=1,IF(1>=1,INDEX($C$21:$U$21,1),D21),IF(1>=2,INDEX($C$21:$U$21,1-1),$C$21))) | E25: =IF(Assumptions!$B$90=0,E21,IF(Assumptions!$B$90=1,IF(2>=1,INDEX($C$21:$U$21,2),E21),IF(2>=2,INDEX($C$21:$U$21,2-1),$C$21))) | F25: =IF(Assumptions!$B$90=0,F21,IF(Assumptions!$B$90=1,IF(3>=1,INDEX($C$21:$U$21,3),F21),IF(3>=2,INDEX($C$21:$U$21,3-1),$C$21))) | G25: =IF(Assumptions!$B$90=0,G21,IF(Assumptions!$B$90=1,IF(4>=1,INDEX($C$21:$U$21,4),G21),IF(4>=2,INDEX($C$21:$U$21,4-1),$C$21))) | H25: =IF(Assumptions!$B$90=0,H21,IF(Assumptions!$B$90=1,IF(5>=1,INDEX($C$21:$U$21,5),H21),IF(5>=2,INDEX($C$21:$U$21,5-1),$C$21))) | I25: =IF(Assumptions!$B$90=0,I21,IF(Assumptions!$B$90=1,IF(6>=1,INDEX($C$21:$U$21,6),I21),IF(6>=2,INDEX($C$21:$U$21,6-1),$C$21))) | J25: =IF(Assumptions!$B$90=0,J21,IF(Assumptions!$B$90=1,IF(7>=1,INDEX($C$21:$U$21,7),J21),IF(7>=2,INDEX($C$21:$U$21,7-1),$C$21))) | K25: =IF(Assumptions!$B$90=0,K21,IF(Assumptions!$B$90=1,IF(8>=1,INDEX($C$21:$U$21,8),K21),IF(8>=2,INDEX($C$21:$U$21,8-1),$C$21))) | L25: =IF(Assumptions!$B$90=0,L21,IF(Assumptions!$B$90=1,IF(9>=1,INDEX($C$21:$U$21,9),L21),IF(9>=2,INDEX($C$21:$U$21,9-1),$C$21))) | M25: =IF(Assumptions!$B$90=0,M21,IF(Assumptions!$B$90=1,IF(10>=1,INDEX($C$21:$U$21,10),M21),IF(10>=2,INDEX($C$21:$U$21,10-1),$C$21))) | N25: =IF(Assumptions!$B$90=0,N21,IF(Assumptions!$B$90=1,IF(11>=1,INDEX($C$21:$U$21,11),N21),IF(11>=2,INDEX($C$21:$U$21,11-1),$C$21))) | O25: =IF(Assumptions!$B$90=0,O21,IF(Assumptions!$B$90=1,IF(12>=1,INDEX($C$21:$U$21,12),O21),IF(12>=2,INDEX($C$21:$U$21,12-1),$C$21))) | P25: =IF(Assumptions!$B$90=0,P21,IF(Assumptions!$B$90=1,IF(13>=1,INDEX($C$21:$U$21,13),P21),IF(13>=2,INDEX($C$21:$U$21,13-1),$C$21))) | Q25: =IF(Assumptions!$B$90=0,Q21,IF(Assumptions!$B$90=1,IF(14>=1,INDEX($C$21:$U$21,14),Q21),IF(14>=2,INDEX($C$21:$U$21,14-1),$C$21))) | R25: =IF(Assumptions!$B$90=0,R21,IF(Assumptions!$B$90=1,IF(15>=1,INDEX($C$21:$U$21,15),R21),IF(15>=2,INDEX($C$21:$U$21,15-1),$C$21))) | S25: =IF(Assumptions!$B$90=0,S21,IF(Assumptions!$B$90=1,IF(16>=1,INDEX($C$21:$U$21,16),S21),IF(16>=2,INDEX($C$21:$U$21,16-1),$C$21))) | T25: =IF(Assumptions!$B$90=0,T21,IF(Assumptions!$B$90=1,IF(17>=1,INDEX($C$21:$U$21,17),T21),IF(17>=2,INDEX($C$21:$U$21,17-1),$C$21))) | U25: =IF(Assumptions!$B$90=0,U21,IF(Assumptions!$B$90=1,IF(18>=1,INDEX($C$21:$U$21,18),U21),IF(18>=2,INDEX($C$21:$U$21,18-1),$C$21)))
A26: Billing gross MW ex-Vineland | C26: =IF(Assumptions!$B$90=0,C21-C24,IF(Assumptions!$B$90=1,IF(0>=1,INDEX($C$21:$U$21,0)-INDEX($C$24:$U$24,0),C21-C24),IF(0>=2,INDEX($C$21:$U$21,0-1)-INDEX($C$24:$U$24,0-1),$C$21-$C$24))) | D26: =IF(Assumptions!$B$90=0,D21-D24,IF(Assumptions!$B$90=1,IF(1>=1,INDEX($C$21:$U$21,1)-INDEX($C$24:$U$24,1),D21-D24),IF(1>=2,INDEX($C$21:$U$21,1-1)-INDEX($C$24:$U$24,1-1),$C$21-$C$24))) | E26: =IF(Assumptions!$B$90=0,E21-E24,IF(Assumptions!$B$90=1,IF(2>=1,INDEX($C$21:$U$21,2)-INDEX($C$24:$U$24,2),E21-E24),IF(2>=2,INDEX($C$21:$U$21,2-1)-INDEX($C$24:$U$24,2-1),$C$21-$C$24))) | F26: =IF(Assumptions!$B$90=0,F21-F24,IF(Assumptions!$B$90=1,IF(3>=1,INDEX($C$21:$U$21,3)-INDEX($C$24:$U$24,3),F21-F24),IF(3>=2,INDEX($C$21:$U$21,3-1)-INDEX($C$24:$U$24,3-1),$C$21-$C$24))) | G26: =IF(Assumptions!$B$90=0,G21-G24,IF(Assumptions!$B$90=1,IF(4>=1,INDEX($C$21:$U$21,4)-INDEX($C$24:$U$24,4),G21-G24),IF(4>=2,INDEX($C$21:$U$21,4-1)-INDEX($C$24:$U$24,4-1),$C$21-$C$24))) | H26: =IF(Assumptions!$B$90=0,H21-H24,IF(Assumptions!$B$90=1,IF(5>=1,INDEX($C$21:$U$21,5)-INDEX($C$24:$U$24,5),H21-H24),IF(5>=2,INDEX($C$21:$U$21,5-1)-INDEX($C$24:$U$24,5-1),$C$21-$C$24))) | I26: =IF(Assumptions!$B$90=0,I21-I24,IF(Assumptions!$B$90=1,IF(6>=1,INDEX($C$21:$U$21,6)-INDEX($C$24:$U$24,6),I21-I24),IF(6>=2,INDEX($C$21:$U$21,6-1)-INDEX($C$24:$U$24,6-1),$C$21-$C$24))) | J26: =IF(Assumptions!$B$90=0,J21-J24,IF(Assumptions!$B$90=1,IF(7>=1,INDEX($C$21:$U$21,7)-INDEX($C$24:$U$24,7),J21-J24),IF(7>=2,INDEX($C$21:$U$21,7-1)-INDEX($C$24:$U$24,7-1),$C$21-$C$24))) | K26: =IF(Assumptions!$B$90=0,K21-K24,IF(Assumptions!$B$90=1,IF(8>=1,INDEX($C$21:$U$21,8)-INDEX($C$24:$U$24,8),K21-K24),IF(8>=2,INDEX($C$21:$U$21,8-1)-INDEX($C$24:$U$24,8-1),$C$21-$C$24))) | L26: =IF(Assumptions!$B$90=0,L21-L24,IF(Assumptions!$B$90=1,IF(9>=1,INDEX($C$21:$U$21,9)-INDEX($C$24:$U$24,9),L21-L24),IF(9>=2,INDEX($C$21:$U$21,9-1)-INDEX($C$24:$U$24,9-1),$C$21-$C$24))) | M26: =IF(Assumptions!$B$90=0,M21-M24,IF(Assumptions!$B$90=1,IF(10>=1,INDEX($C$21:$U$21,10)-INDEX($C$24:$U$24,10),M21-M24),IF(10>=2,INDEX($C$21:$U$21,10-1)-INDEX($C$24:$U$24,10-1),$C$21-$C$24))) | N26: =IF(Assumptions!$B$90=0,N21-N24,IF(Assumptions!$B$90=1,IF(11>=1,INDEX($C$21:$U$21,11)-INDEX($C$24:$U$24,11),N21-N24),IF(11>=2,INDEX($C$21:$U$21,11-1)-INDEX($C$24:$U$24,11-1),$C$21-$C$24))) | O26: =IF(Assumptions!$B$90=0,O21-O24,IF(Assumptions!$B$90=1,IF(12>=1,INDEX($C$21:$U$21,12)-INDEX($C$24:$U$24,12),O21-O24),IF(12>=2,INDEX($C$21:$U$21,12-1)-INDEX($C$24:$U$24,12-1),$C$21-$C$24))) | P26: =IF(Assumptions!$B$90=0,P21-P24,IF(Assumptions!$B$90=1,IF(13>=1,INDEX($C$21:$U$21,13)-INDEX($C$24:$U$24,13),P21-P24),IF(13>=2,INDEX($C$21:$U$21,13-1)-INDEX($C$24:$U$24,13-1),$C$21-$C$24))) | Q26: =IF(Assumptions!$B$90=0,Q21-Q24,IF(Assumptions!$B$90=1,IF(14>=1,INDEX($C$21:$U$21,14)-INDEX($C$24:$U$24,14),Q21-Q24),IF(14>=2,INDEX($C$21:$U$21,14-1)-INDEX($C$24:$U$24,14-1),$C$21-$C$24))) | R26: =IF(Assumptions!$B$90=0,R21-R24,IF(Assumptions!$B$90=1,IF(15>=1,INDEX($C$21:$U$21,15)-INDEX($C$24:$U$24,15),R21-R24),IF(15>=2,INDEX($C$21:$U$21,15-1)-INDEX($C$24:$U$24,15-1),$C$21-$C$24))) | S26: =IF(Assumptions!$B$90=0,S21-S24,IF(Assumptions!$B$90=1,IF(16>=1,INDEX($C$21:$U$21,16)-INDEX($C$24:$U$24,16),S21-S24),IF(16>=2,INDEX($C$21:$U$21,16-1)-INDEX($C$24:$U$24,16-1),$C$21-$C$24))) | T26: =IF(Assumptions!$B$90=0,T21-T24,IF(Assumptions!$B$90=1,IF(17>=1,INDEX($C$21:$U$21,17)-INDEX($C$24:$U$24,17),T21-T24),IF(17>=2,INDEX($C$21:$U$21,17-1)-INDEX($C$24:$U$24,17-1),$C$21-$C$24))) | U26: =IF(Assumptions!$B$90=0,U21-U24,IF(Assumptions!$B$90=1,IF(18>=1,INDEX($C$21:$U$21,18)-INDEX($C$24:$U$24,18),U21-U24),IF(18>=2,INDEX($C$21:$U$21,18-1)-INDEX($C$24:$U$24,18-1),$C$21-$C$24)))
A27: Owned share of cumulative energized MW (selected) | C27: =IF(C15>0,C18/C15,0) | D27: =IF(D15>0,D18/D15,0) | E27: =IF(E15>0,E18/E15,0) | F27: =IF(F15>0,F18/F15,0) | G27: =IF(G15>0,G18/G15,0) | H27: =IF(H15>0,H18/H15,0) | I27: =IF(I15>0,I18/I15,0) | J27: =IF(J15>0,J18/J15,0) | ... U27: =IF(U15>0,U18/U15,0)
A28: Note: FY owned share of energized ADDITIONS (feeds capex mix) is on the Model sheet. Q2'26 column = starting point (energized at 6/30/26 per Capacity).

Sheet Microsoft
A1: Microsoft (Vineland) tranche model - take-or-pay 'irrespective of actual utilization'; haircut = SLA/service credits + per-tranche termination (NOT demand)
A2: Tranche | B2: Scheduled (contract/letter) | C2: Capacity base billing start | D2: Capacity bear billing start | E2: Selected start | F2: Terminate? (1 = cancelled) | G2: Quarterly revenue $M (TCV/9/20) | H2: Source / tag
A3: T1 | B3: Q4 2025 | C3: Q4 2025 | D3: Q4 2025 | E3: =CHOOSE(Assumptions!$B$160,B3,C3,D3) | F3: 0 | G3: =Assumptions!$B$161/9/20*(1-Assumptions!$B$53)*(1-F3) | H3: Equal split (Estimated); dates: 20-F (T1 Nov-25, T2 Feb-26), Q2 letter (two tranches Jul/Aug-26), Capacity estimates T5-T9
A4: T2 | B4: Q1 2026 | C4: Q1 2026 | D4: Q1 2026 | E4: =CHOOSE(Assumptions!$B$160,B4,C4,D4) | F4: 0 | G4: =Assumptions!$B$161/9/20*(1-Assumptions!$B$53)*(1-F4) | H4: Equal split (Estimated); dates: 20-F (T1 Nov-25, T2 Feb-26), Q2 letter (two tranches Jul/Aug-26), Capacity estimates T5-T9
A5: T3 | B5: Q3 2026 | C5: Q3 2026 | D5: Q3 2026 | E5: =CHOOSE(Assumptions!$B$160,B5,C5,D5) | F5: 0 | G5: =Assumptions!$B$161/9/20*(1-Assumptions!$B$53)*(1-F5) | H5: Equal split (Estimated); dates: 20-F (T1 Nov-25, T2 Feb-26), Q2 letter (two tranches Jul/Aug-26), Capacity estimates T5-T9
A6: T4 | B6: Q3 2026 | C6: Q3 2026 | D6: Q3 2026 | E6: =CHOOSE(Assumptions!$B$160,B6,C6,D6) | F6: 0 | G6: =Assumptions!$B$161/9/20*(1-Assumptions!$B$53)*(1-F6) | H6: Equal split (Estimated); dates: 20-F (T1 Nov-25, T2 Feb-26), Q2 letter (two tranches Jul/Aug-26), Capacity estimates T5-T9
A7: T5 | B7: Q3 2026 | C7: Q2 2027 | D7: Q3 2027 | E7: =CHOOSE(Assumptions!$B$160,B7,C7,D7) | F7: 0 | G7: =Assumptions!$B$161/9/20*(1-Assumptions!$B$53)*(1-F7) | H7: Equal split (Estimated); dates: 20-F (T1 Nov-25, T2 Feb-26), Q2 letter (two tranches Jul/Aug-26), Capacity estimates T5-T9
A8: T6 | B8: Q3 2026 | C8: Q2 2027 | D8: Q3 2027 | E8: =CHOOSE(Assumptions!$B$160,B8,C8,D8) | F8: 0 | G8: =Assumptions!$B$161/9/20*(1-Assumptions!$B$53)*(1-F8) | H8: Equal split (Estimated); dates: 20-F (T1 Nov-25, T2 Feb-26), Q2 letter (two tranches Jul/Aug-26), Capacity estimates T5-T9
A9: T7 | B9: Q3 2026 | C9: Q3 2027 | D9: Q4 2027 | E9: =CHOOSE(Assumptions!$B$160,B9,C9,D9) | F9: 0 | G9: =Assumptions!$B$161/9/20*(1-Assumptions!$B$53)*(1-F9) | H9: Equal split (Estimated); dates: 20-F (T1 Nov-25, T2 Feb-26), Q2 letter (two tranches Jul/Aug-26), Capacity estimates T5-T9
A10: T8 | B10: Q3 2026 | C10: Q3 2027 | D10: Q4 2027 | E10: =CHOOSE(Assumptions!$B$160,B10,C10,D10) | F10: 0 | G10: =Assumptions!$B$161/9/20*(1-Assumptions!$B$53)*(1-F10) | H10: Equal split (Estimated); dates: 20-F (T1 Nov-25, T2 Feb-26), Q2 letter (two tranches Jul/Aug-26), Capacity estimates T5-T9
A11: T9 | B11: Q3 2026 | C11: Q3 2027 | D11: Q1 2028 | E11: =CHOOSE(Assumptions!$B$160,B11,C11,D11) | F11: 0 | G11: =Assumptions!$B$161/9/20*(1-Assumptions!$B$53)*(1-F11) | H11: Equal split (Estimated); dates: 20-F (T1 Nov-25, T2 Feb-26), Q2 letter (two tranches Jul/Aug-26), Capacity estimates T5-T9
A13: Quarter | B13: Q4 2025 | C13: Q1 2026 | D13: Q2 2026 | E13: Q3 2026 | F13: Q4 2026 | G13: Q1 2027 | H13: Q2 2027 | I13: Q3 2027 | J13: Q4 2027 | K13: Q1 2028 | L13: Q2 2028 | M13: Q3 2028 | N13: Q4 2028 | O13: Q1 2029 | P13: Q2 2029 | Q13: Q3 2029 | R13: Q4 2029 | S13: Q1 2030 | T13: Q2 2030 | U13: Q3 2030 | V13: Q4 2030 | W13: Q1 2031 | X13: Q2 2031 | Y13: Q3 2031 | Z13: Q4 2031
A14: Revenue $M | B14: =SUMPRODUCT(($G$3:$G$11)*(MATCH($E$3:$E$11,$B$13:$Z$13,0)<=COLUMN()-1)*(MATCH($E$3:$E$11,$B$13:$Z$13,0)>COLUMN()-21)) | C14: =SUMPRODUCT(($G$3:$G$11)*(MATCH($E$3:$E$11,$B$13:$Z$13,0)<=COLUMN()-1)*(MATCH($E$3:$E$11,$B$13:$Z$13,0)>COLUMN()-21)) | D14: =SUMPRODUCT(($G$3:$G$11)*(MATCH($E$3:$E$11,$B$13:$Z$13,0)<=COLUMN()-1)*(MATCH($E$3:$E$11,$B$13:$Z$13,0)>COLUMN()-21)) | E14: =SUMPRODUCT(($G$3:$G$11)*(MATCH($E$3:$E$11,$B$13:$Z$13,0)<=COLUMN()-1)*(MATCH($E$3:$E$11,$B$13:$Z$13,0)>COLUMN()-21)) | F14: =SUMPRODUCT(($G$3:$G$11)*(MATCH($E$3:$E$11,$B$13:$Z$13,0)<=COLUMN()-1)*(MATCH($E$3:$E$11,$B$13:$Z$13,0)>COLUMN()-21)) | G14: =SUMPRODUCT(($G$3:$G$11)*(MATCH($E$3:$E$11,$B$13:$Z$13,0)<=COLUMN()-1)*(MATCH($E$3:$E$11,$B$13:$Z$13,0)>COLUMN()-21)) | H14: =SUMPRODUCT(($G$3:$G$11)*(MATCH($E$3:$E$11,$B$13:$Z$13,0)<=COLUMN()-1)*(MATCH($E$3:$E$11,$B$13:$Z$13,0)>COLUMN()-21)) | I14: =SUMPRODUCT(($G$3:$G$11)*(MATCH($E$3:$E$11,$B$13:$Z$13,0)<=COLUMN()-1)*(MATCH($E$3:$E$11,$B$13:$Z$13,0)>COLUMN()-21)) | ... Z14: =SUMPRODUCT(($G$3:$G$11)*(MATCH($E$3:$E$11,$B$13:$Z$13,0)<=COLUMN()-1)*(MATCH($E$3:$E$11,$B$13:$Z$13,0)>COLUMN()-21))
A15: Billing tranches | B15: =SUMPRODUCT((1-$F$3:$F$11)*(MATCH($E$3:$E$11,$B$13:$Z$13,0)<=COLUMN()-1)*(MATCH($E$3:$E$11,$B$13:$Z$13,0)>COLUMN()-21)) | C15: =SUMPRODUCT((1-$F$3:$F$11)*(MATCH($E$3:$E$11,$B$13:$Z$13,0)<=COLUMN()-1)*(MATCH($E$3:$E$11,$B$13:$Z$13,0)>COLUMN()-21)) | D15: =SUMPRODUCT((1-$F$3:$F$11)*(MATCH($E$3:$E$11,$B$13:$Z$13,0)<=COLUMN()-1)*(MATCH($E$3:$E$11,$B$13:$Z$13,0)>COLUMN()-21)) | E15: =SUMPRODUCT((1-$F$3:$F$11)*(MATCH($E$3:$E$11,$B$13:$Z$13,0)<=COLUMN()-1)*(MATCH($E$3:$E$11,$B$13:$Z$13,0)>COLUMN()-21)) | F15: =SUMPRODUCT((1-$F$3:$F$11)*(MATCH($E$3:$E$11,$B$13:$Z$13,0)<=COLUMN()-1)*(MATCH($E$3:$E$11,$B$13:$Z$13,0)>COLUMN()-21)) | G15: =SUMPRODUCT((1-$F$3:$F$11)*(MATCH($E$3:$E$11,$B$13:$Z$13,0)<=COLUMN()-1)*(MATCH($E$3:$E$11,$B$13:$Z$13,0)>COLUMN()-21)) | H15: =SUMPRODUCT((1-$F$3:$F$11)*(MATCH($E$3:$E$11,$B$13:$Z$13,0)<=COLUMN()-1)*(MATCH($E$3:$E$11,$B$13:$Z$13,0)>COLUMN()-21)) | I15: =SUMPRODUCT((1-$F$3:$F$11)*(MATCH($E$3:$E$11,$B$13:$Z$13,0)<=COLUMN()-1)*(MATCH($E$3:$E$11,$B$13:$Z$13,0)>COLUMN()-21)) | ... Z15: =SUMPRODUCT((1-$F$3:$F$11)*(MATCH($E$3:$E$11,$B$13:$Z$13,0)<=COLUMN()-1)*(MATCH($E$3:$E$11,$B$13:$Z$13,0)>COLUMN()-21))
A17: Q2'26 check: equal-split T1+T2 = $193M/qtr vs top customer 24% x $582.3M = ~$140M (Capacity) - either T1/T2 smaller than 1/9 or customer C is not Microsoft
A18: FY2026 Microsoft revenue | B18: =SUMPRODUCT(($B$14:$Z$14)*(RIGHT($B$13:$Z$13,4)="2026"))
A19: FY2027 Microsoft revenue | B19: =SUMPRODUCT(($B$14:$Z$14)*(RIGHT($B$13:$Z$13,4)="2027"))
A20: FY2028 Microsoft revenue | B20: =SUMPRODUCT(($B$14:$Z$14)*(RIGHT($B$13:$Z$13,4)="2028"))
A21: Total billed over life (TCV after SLA/terminations) | B21: =SUM(G3:G11)*20
A22: PV at Q3'26 of Microsoft revenue Q3'26-Q4'31 at WACC (Microsoft through 2031 only partly visible in the 2030 horizon) | B22: =SUMPRODUCT($B$14:$Z$14*(COLUMN($B$14:$Z$14)>=5)*(1+Assumptions!$B$149)^(-(COLUMN($B$14:$Z$14)-5)/4))
A23: Genset ceiling run-rate (4 tranches) $M/yr | B23: =4*Assumptions!$B$161/9/5

Sheet Rev_MW
A1: Bottom-up revenue from billing-MW path ($M) - leg 3 re-run | C1: Q3 2026 | D1: Q4 2026 | E1: Q1 2027 | F1: Q2 2027 | G1: Q3 2027 | H1: Q4 2027 | I1: Q1 2028 | J1: Q2 2028 | K1: Q3 2028 | L1: Q4 2028 | M1: Q1 2029 | N1: Q2 2029 | O1: Q3 2029 | P1: Q4 2029 | Q1: Q1 2030 | R1: Q2 2030 | S1: Q3 2030 | T1: Q4 2030
A2: Billing gross MW ex-Vineland | C2: =MW!D26 | D2: =MW!E26 | E2: =MW!F26 | F2: =MW!G26 | G2: =MW!H26 | H2: =MW!I26 | I2: =MW!J26 | J2: =MW!K26 | ... T2: =MW!U26
A3: Installed-book MW (Q2'26 billing level, at $12M) | C3: =MIN(C2,MW!$C$26) | D3: =MIN(D2,MW!$C$26) | E3: =MIN(E2,MW!$C$26) | F3: =MIN(F2,MW!$C$26) | G3: =MIN(G2,MW!$C$26) | H3: =MIN(H2,MW!$C$26) | I3: =MIN(I2,MW!$C$26) | J3: =MIN(J2,MW!$C$26) | ... T3: =MIN(T2,MW!$C$26)
A4: Incremental MW (at Q2-deal ACV) | C4: =C2-C3 | D4: =D2-D3 | E4: =E2-E3 | F4: =F2-F3 | G4: =G2-G3 | H4: =H2-H3 | I4: =I2-I3 | J4: =J2-J3 | ... T4: =T2-T3
A5: Non-Microsoft revenue | C5: =(C3*Assumptions!$B$44+C4*Assumptions!$B$93)/4*(1+Assumptions!$B$94*Assumptions!$B$95) | D5: =(D3*Assumptions!$B$44+D4*Assumptions!$B$93)/4*(1+Assumptions!$B$94*Assumptions!$B$95) | E5: =(E3*Assumptions!$B$44+E4*Assumptions!$B$93)/4*(1+Assumptions!$B$94*Assumptions!$B$95) | F5: =(F3*Assumptions!$B$44+F4*Assumptions!$B$93)/4*(1+Assumptions!$B$94*Assumptions!$B$95) | G5: =(G3*Assumptions!$B$44+G4*Assumptions!$B$93)/4*(1+Assumptions!$B$94*Assumptions!$B$95) | H5: =(H3*Assumptions!$B$44+H4*Assumptions!$B$93)/4*(1+Assumptions!$B$94*Assumptions!$B$95) | I5: =(I3*Assumptions!$B$44+I4*Assumptions!$B$93)/4*(1+Assumptions!$B$94*Assumptions!$B$95) | J5: =(J3*Assumptions!$B$44+J4*Assumptions!$B$93)/4*(1+Assumptions!$B$94*Assumptions!$B$95) | ... T5: =(T3*Assumptions!$B$44+T4*Assumptions!$B$93)/4*(1+Assumptions!$B$94*Assumptions!$B$95)
A6: Microsoft revenue (Microsoft sheet) | C6: =INDEX(Microsoft!$B$14:$Z$14,MATCH(C$1,Microsoft!$B$13:$Z$13,0)) | D6: =INDEX(Microsoft!$B$14:$Z$14,MATCH(D$1,Microsoft!$B$13:$Z$13,0)) | E6: =INDEX(Microsoft!$B$14:$Z$14,MATCH(E$1,Microsoft!$B$13:$Z$13,0)) | F6: =INDEX(Microsoft!$B$14:$Z$14,MATCH(F$1,Microsoft!$B$13:$Z$13,0)) | G6: =INDEX(Microsoft!$B$14:$Z$14,MATCH(G$1,Microsoft!$B$13:$Z$13,0)) | H6: =INDEX(Microsoft!$B$14:$Z$14,MATCH(H$1,Microsoft!$B$13:$Z$13,0)) | I6: =INDEX(Microsoft!$B$14:$Z$14,MATCH(I$1,Microsoft!$B$13:$Z$13,0)) | J6: =INDEX(Microsoft!$B$14:$Z$14,MATCH(J$1,Microsoft!$B$13:$Z$13,0)) | ... T6: =INDEX(Microsoft!$B$14:$Z$14,MATCH(T$1,Microsoft!$B$13:$Z$13,0))
A7: TOTAL bottom-up revenue | C7: =C5+C6 | D7: =D5+D6 | E7: =E5+E6 | F7: =F5+F6 | G7: =G5+G6 | H7: =H5+H6 | I7: =I5+I6 | J7: =J5+J6 | ... T7: =T5+T6
A8: Blackwell (incremental-MW) revenue, non-Microsoft | C8: =C4*Assumptions!$B$93/4*(1+Assumptions!$B$94*Assumptions!$B$95) | D8: =D4*Assumptions!$B$93/4*(1+Assumptions!$B$94*Assumptions!$B$95) | E8: =E4*Assumptions!$B$93/4*(1+Assumptions!$B$94*Assumptions!$B$95) | F8: =F4*Assumptions!$B$93/4*(1+Assumptions!$B$94*Assumptions!$B$95) | G8: =G4*Assumptions!$B$93/4*(1+Assumptions!$B$94*Assumptions!$B$95) | H8: =H4*Assumptions!$B$93/4*(1+Assumptions!$B$94*Assumptions!$B$95) | I8: =I4*Assumptions!$B$93/4*(1+Assumptions!$B$94*Assumptions!$B$95) | J8: =J4*Assumptions!$B$93/4*(1+Assumptions!$B$94*Assumptions!$B$95) | ... T8: =T4*Assumptions!$B$93/4*(1+Assumptions!$B$94*Assumptions!$B$95)
A9: Price-cycle phase-in (0-100% over 4 qtrs from Rubin launch) | C9: =MIN(1,MAX(0,(0-Assumptions!$B$98+1)/4)) | D9: =MIN(1,MAX(0,(1-Assumptions!$B$98+1)/4)) | E9: =MIN(1,MAX(0,(2-Assumptions!$B$98+1)/4)) | F9: =MIN(1,MAX(0,(3-Assumptions!$B$98+1)/4)) | G9: =MIN(1,MAX(0,(4-Assumptions!$B$98+1)/4)) | H9: =MIN(1,MAX(0,(5-Assumptions!$B$98+1)/4)) | I9: =MIN(1,MAX(0,(6-Assumptions!$B$98+1)/4)) | J9: =MIN(1,MAX(0,(7-Assumptions!$B$98+1)/4)) | K9: =MIN(1,MAX(0,(8-Assumptions!$B$98+1)/4)) | L9: =MIN(1,MAX(0,(9-Assumptions!$B$98+1)/4)) | M9: =MIN(1,MAX(0,(10-Assumptions!$B$98+1)/4)) | N9: =MIN(1,MAX(0,(11-Assumptions!$B$98+1)/4)) | O9: =MIN(1,MAX(0,(12-Assumptions!$B$98+1)/4)) | P9: =MIN(1,MAX(0,(13-Assumptions!$B$98+1)/4)) | Q9: =MIN(1,MAX(0,(14-Assumptions!$B$98+1)/4)) | R9: =MIN(1,MAX(0,(15-Assumptions!$B$98+1)/4)) | S9: =MIN(1,MAX(0,(16-Assumptions!$B$98+1)/4)) | T9: =MIN(1,MAX(0,(17-Assumptions!$B$98+1)/4))
A10: PRICE-CYCLE revenue hit = cut x phase x Blackwell rev x (on-demand + reserved x renewal share) | C10: =-Assumptions!$B$97*C9*C8*(Assumptions!$B$94+Assumptions!$B$99*Assumptions!$B$100) | D10: =-Assumptions!$B$97*D9*D8*(Assumptions!$B$94+Assumptions!$B$99*Assumptions!$B$100) | E10: =-Assumptions!$B$97*E9*E8*(Assumptions!$B$94+Assumptions!$B$99*Assumptions!$B$100) | F10: =-Assumptions!$B$97*F9*F8*(Assumptions!$B$94+Assumptions!$B$99*Assumptions!$B$100) | G10: =-Assumptions!$B$97*G9*G8*(Assumptions!$B$94+Assumptions!$B$99*Assumptions!$B$100) | H10: =-Assumptions!$B$97*H9*H8*(Assumptions!$B$94+Assumptions!$B$99*Assumptions!$B$100) | I10: =-Assumptions!$B$97*I9*I8*(Assumptions!$B$94+Assumptions!$B$99*Assumptions!$B$100) | J10: =-Assumptions!$B$97*J9*J8*(Assumptions!$B$94+Assumptions!$B$99*Assumptions!$B$100) | ... T10: =-Assumptions!$B$97*T9*T8*(Assumptions!$B$94+Assumptions!$B$99*Assumptions!$B$100)
A11: Consensus quarterly revenue (MarketScreener) | C11: 904.1 | D11: 1452 | E11: 2175 | F11: 2646 | G11: 3304 | H11: 4052
A13: FY2027 bottom-up revenue | B13: =SUMPRODUCT(($C$7:$T$7)*(RIGHT($C$1:$T$1,4)="2027"))
A14: FY2027 consensus revenue | B14: 12300
A15: Gap vs consensus | B15: =B13-B14
A16: Gap % | B16: =B15/B14
A17: $/share at constant EV/FY27 revenue (308.69M sh) | B17: =B15*(Assumptions!$B$152/B14)/Assumptions!$B$154
A18: FY2026 H2 bottom-up vs consensus H2 (2,356) | B18: =SUMPRODUCT(($C$7:$T$7)*(RIGHT($C$1:$T$1,4)="2026"))
A19: FY2027 price-cycle revenue hit (= EBITDA hit; costs fixed; 5-yr life unchanged) | B19: =SUMPRODUCT(($C$10:$T$10)*(RIGHT($C$1:$T$1,4)="2027"))
A20: as % of FY27 bottom-up revenue | B20: =B19/$B$13
A21: scaled to FY27 consensus revenue ($12.3B) | B21: =B20*12300
A22: as % of FY27 consensus EBITDA ($6,728M) | B22: =B21/6728
A23: FY2028 price-cycle revenue hit | B23: =SUMPRODUCT(($C$10:$T$10)*(RIGHT($C$1:$T$1,4)="2028"))
A24: Calibration: Q2'26 implied = MW!C ex-Vin (Q1'26 energized ~134 MW) x $12M/4 + MSFT T1+T2 $193M = ~$595M vs $582.3M reported
A25: Oct 1 hike effect = on-demand share 4% x 19% = ~+0.8% of revenue (applied to non-MSFT revenue)

Sheet Model
A1: Fleet quarterly model ($M) | C1: Q3 2026 | D1: Q4 2026 | E1: Q1 2027 | F1: Q2 2027 | G1: Q3 2027 | H1: Q4 2027 | I1: Q1 2028 | J1: Q2 2028 | K1: Q3 2028 | L1: Q4 2028 | M1: Q1 2029 | N1: Q2 2029 | O1: Q3 2029 | P1: Q4 2029 | Q1: Q1 2030 | R1: Q2 2030 | S1: Q3 2030 | T1: Q4 2030
A2: Quarter index (0 = Q3'26) | C2: 0 | D2: 1 | E2: 2 | F2: 3 | G2: 4 | H2: 5 | I2: 6 | J2: 7 | K2: 8 | L2: 9 | M2: 10 | N2: 11 | O2: 12 | P2: 13 | Q2: 14 | R2: 15 | S2: 16 | T2: 17
A3: Fiscal year | C3: 2026 | D3: 2026 | E3: 2027 | F3: 2027 | G3: 2027 | H3: 2027 | I3: 2028 | J3: 2028 | K3: 2028 | L3: 2028 | M3: 2029 | N3: 2029 | O3: 2029 | P3: 2029 | Q3: 2030 | R3: 2030 | S3: 2030 | T3: 2030
A4: Capex - consensus basis (FY26-28; FY29-30 extrapolated) | C4: =(Assumptions!$B$108-Assumptions!$B$109)/2 | D4: =(Assumptions!$B$108-Assumptions!$B$109)/2 | E4: =Assumptions!$B$110/4 | F4: =Assumptions!$B$110/4 | G4: =Assumptions!$B$110/4 | H4: =Assumptions!$B$110/4 | I4: =Assumptions!$B$111*Assumptions!$B$116 | J4: =Assumptions!$B$111*Assumptions!$B$117 | K4: =Assumptions!$B$111*Assumptions!$B$118 | L4: =Assumptions!$B$111*Assumptions!$B$119 | M4: =Assumptions!$B$111*(1+Assumptions!$B$112)/4 | N4: =Assumptions!$B$111*(1+Assumptions!$B$112)/4 | O4: =Assumptions!$B$111*(1+Assumptions!$B$112)/4 | P4: =Assumptions!$B$111*(1+Assumptions!$B$112)/4 | Q4: =Assumptions!$B$111*(1+Assumptions!$B$112)*(1+Assumptions!$B$113)/4 | R4: =Assumptions!$B$111*(1+Assumptions!$B$112)*(1+Assumptions!$B$113)/4 | S4: =Assumptions!$B$111*(1+Assumptions!$B$112)*(1+Assumptions!$B$113)/4 | T4: =Assumptions!$B$111*(1+Assumptions!$B$112)*(1+Assumptions!$B$113)/4
A5: Owned share of capex (FY energized additions, Capacity tracker) | C5: =CHOOSE(Assumptions!$B$79,IFERROR(IF(MW!E15-MW!C15>0,(MW!E18-MW!C18)/(MW!E15-MW!C15),MW!E18/MW!E15),0),0,1) | D5: =CHOOSE(Assumptions!$B$79,IFERROR(IF(MW!E15-MW!C15>0,(MW!E18-MW!C18)/(MW!E15-MW!C15),MW!E18/MW!E15),0),0,1) | E5: =CHOOSE(Assumptions!$B$79,IFERROR(IF(MW!I15-MW!E15>0,(MW!I18-MW!E18)/(MW!I15-MW!E15),MW!I18/MW!I15),0),0,1) | F5: =CHOOSE(Assumptions!$B$79,IFERROR(IF(MW!I15-MW!E15>0,(MW!I18-MW!E18)/(MW!I15-MW!E15),MW!I18/MW!I15),0),0,1) | G5: =CHOOSE(Assumptions!$B$79,IFERROR(IF(MW!I15-MW!E15>0,(MW!I18-MW!E18)/(MW!I15-MW!E15),MW!I18/MW!I15),0),0,1) | H5: =CHOOSE(Assumptions!$B$79,IFERROR(IF(MW!I15-MW!E15>0,(MW!I18-MW!E18)/(MW!I15-MW!E15),MW!I18/MW!I15),0),0,1) | I5: =CHOOSE(Assumptions!$B$79,IFERROR(IF(MW!M15-MW!I15>0,(MW!M18-MW!I18)/(MW!M15-MW!I15),MW!M18/MW!M15),0),0,1) | J5: =CHOOSE(Assumptions!$B$79,IFERROR(IF(MW!M15-MW!I15>0,(MW!M18-MW!I18)/(MW!M15-MW!I15),MW!M18/MW!M15),0),0,1) | K5: =CHOOSE(Assumptions!$B$79,IFERROR(IF(MW!M15-MW!I15>0,(MW!M18-MW!I18)/(MW!M15-MW!I15),MW!M18/MW!M15),0),0,1) | L5: =CHOOSE(Assumptions!$B$79,IFERROR(IF(MW!M15-MW!I15>0,(MW!M18-MW!I18)/(MW!M15-MW!I15),MW!M18/MW!M15),0),0,1) | M5: =CHOOSE(Assumptions!$B$79,IFERROR(IF(MW!Q15-MW!M15>0,(MW!Q18-MW!M18)/(MW!Q15-MW!M15),MW!Q18/MW!Q15),0),0,1) | N5: =CHOOSE(Assumptions!$B$79,IFERROR(IF(MW!Q15-MW!M15>0,(MW!Q18-MW!M18)/(MW!Q15-MW!M15),MW!Q18/MW!Q15),0),0,1) | O5: =CHOOSE(Assumptions!$B$79,IFERROR(IF(MW!Q15-MW!M15>0,(MW!Q18-MW!M18)/(MW!Q15-MW!M15),MW!Q18/MW!Q15),0),0,1) | P5: =CHOOSE(Assumptions!$B$79,IFERROR(IF(MW!Q15-MW!M15>0,(MW!Q18-MW!M18)/(MW!Q15-MW!M15),MW!Q18/MW!Q15),0),0,1) | Q5: =CHOOSE(Assumptions!$B$79,IFERROR(IF(MW!U15-MW!Q15>0,(MW!U18-MW!Q18)/(MW!U15-MW!Q15),MW!U18/MW!U15),0),0,1) | R5: =CHOOSE(Assumptions!$B$79,IFERROR(IF(MW!U15-MW!Q15>0,(MW!U18-MW!Q18)/(MW!U15-MW!Q15),MW!U18/MW!U15),0),0,1) | S5: =CHOOSE(Assumptions!$B$79,IFERROR(IF(MW!U15-MW!Q15>0,(MW!U18-MW!Q18)/(MW!U15-MW!Q15),MW!U18/MW!U15),0),0,1) | T5: =CHOOSE(Assumptions!$B$79,IFERROR(IF(MW!U15-MW!Q15>0,(MW!U18-MW!Q18)/(MW!U15-MW!Q15),MW!U18/MW!U15),0),0,1)
A6: GPU+network share of capex (consensus basis) | C6: =Assumptions!$B$80 | D6: =Assumptions!$B$80 | E6: =IF(E2>=Assumptions!$B$81,Assumptions!$B$29,Assumptions!$B$25)/(IF(E2>=Assumptions!$B$81,Assumptions!$B$29,Assumptions!$B$25)+E5*IF(E2>=Assumptions!$B$81,Assumptions!$B$30,Assumptions!$B$26)+(1-E5)*(IF(E2>=Assumptions!$B$81,Assumptions!$B$31,Assumptions!$B$27)-IF(E2>=Assumptions!$B$81,Assumptions!$B$29,Assumptions!$B$25))) | F6: =IF(F2>=Assumptions!$B$81,Assumptions!$B$29,Assumptions!$B$25)/(IF(F2>=Assumptions!$B$81,Assumptions!$B$29,Assumptions!$B$25)+F5*IF(F2>=Assumptions!$B$81,Assumptions!$B$30,Assumptions!$B$26)+(1-F5)*(IF(F2>=Assumptions!$B$81,Assumptions!$B$31,Assumptions!$B$27)-IF(F2>=Assumptions!$B$81,Assumptions!$B$29,Assumptions!$B$25))) | G6: =IF(G2>=Assumptions!$B$81,Assumptions!$B$29,Assumptions!$B$25)/(IF(G2>=Assumptions!$B$81,Assumptions!$B$29,Assumptions!$B$25)+G5*IF(G2>=Assumptions!$B$81,Assumptions!$B$30,Assumptions!$B$26)+(1-G5)*(IF(G2>=Assumptions!$B$81,Assumptions!$B$31,Assumptions!$B$27)-IF(G2>=Assumptions!$B$81,Assumptions!$B$29,Assumptions!$B$25))) | H6: =IF(H2>=Assumptions!$B$81,Assumptions!$B$29,Assumptions!$B$25)/(IF(H2>=Assumptions!$B$81,Assumptions!$B$29,Assumptions!$B$25)+H5*IF(H2>=Assumptions!$B$81,Assumptions!$B$30,Assumptions!$B$26)+(1-H5)*(IF(H2>=Assumptions!$B$81,Assumptions!$B$31,Assumptions!$B$27)-IF(H2>=Assumptions!$B$81,Assumptions!$B$29,Assumptions!$B$25))) | I6: =IF(I2>=Assumptions!$B$81,Assumptions!$B$29,Assumptions!$B$25)/(IF(I2>=Assumptions!$B$81,Assumptions!$B$29,Assumptions!$B$25)+I5*IF(I2>=Assumptions!$B$81,Assumptions!$B$30,Assumptions!$B$26)+(1-I5)*(IF(I2>=Assumptions!$B$81,Assumptions!$B$31,Assumptions!$B$27)-IF(I2>=Assumptions!$B$81,Assumptions!$B$29,Assumptions!$B$25))) | J6: =IF(J2>=Assumptions!$B$81,Assumptions!$B$29,Assumptions!$B$25)/(IF(J2>=Assumptions!$B$81,Assumptions!$B$29,Assumptions!$B$25)+J5*IF(J2>=Assumptions!$B$81,Assumptions!$B$30,Assumptions!$B$26)+(1-J5)*(IF(J2>=Assumptions!$B$81,Assumptions!$B$31,Assumptions!$B$27)-IF(J2>=Assumptions!$B$81,Assumptions!$B$29,Assumptions!$B$25))) | K6: =IF(K2>=Assumptions!$B$81,Assumptions!$B$29,Assumptions!$B$25)/(IF(K2>=Assumptions!$B$81,Assumptions!$B$29,Assumptions!$B$25)+K5*IF(K2>=Assumptions!$B$81,Assumptions!$B$30,Assumptions!$B$26)+(1-K5)*(IF(K2>=Assumptions!$B$81,Assumptions!$B$31,Assumptions!$B$27)-IF(K2>=Assumptions!$B$81,Assumptions!$B$29,Assumptions!$B$25))) | L6: =IF(L2>=Assumptions!$B$81,Assumptions!$B$29,Assumptions!$B$25)/(IF(L2>=Assumptions!$B$81,Assumptions!$B$29,Assumptions!$B$25)+L5*IF(L2>=Assumptions!$B$81,Assumptions!$B$30,Assumptions!$B$26)+(1-L5)*(IF(L2>=Assumptions!$B$81,Assumptions!$B$31,Assumptions!$B$27)-IF(L2>=Assumptions!$B$81,Assumptions!$B$29,Assumptions!$B$25))) | ... T6: =IF(T2>=Assumptions!$B$81,Assumptions!$B$29,Assumptions!$B$25)/(IF(T2>=Assumptions!$B$81,Assumptions!$B$29,Assumptions!$B$25)+T5*IF(T2>=Assumptions!$B$81,Assumptions!$B$30,Assumptions!$B$26)+(1-T5)*(IF(T2>=Assumptions!$B$81,Assumptions!$B$31,Assumptions!$B$27)-IF(T2>=Assumptions!$B$81,Assumptions!$B$29,Assumptions!$B$25)))
A7: Path: IT MW whose GPUs are bought this qtr (energized at t + lagb - pglag) | C7: =IF((C2+1+Assumptions!$B$90-Assumptions!$B$85)+1<=19,INDEX(MW!$C$23:$U$23,(C2+1+Assumptions!$B$90-Assumptions!$B$85)+1),AVERAGE(MW!$R$23:$U$23)) | D7: =IF((D2+1+Assumptions!$B$90-Assumptions!$B$85)+1<=19,INDEX(MW!$C$23:$U$23,(D2+1+Assumptions!$B$90-Assumptions!$B$85)+1),AVERAGE(MW!$R$23:$U$23)) | E7: =IF((E2+1+Assumptions!$B$90-Assumptions!$B$85)+1<=19,INDEX(MW!$C$23:$U$23,(E2+1+Assumptions!$B$90-Assumptions!$B$85)+1),AVERAGE(MW!$R$23:$U$23)) | F7: =IF((F2+1+Assumptions!$B$90-Assumptions!$B$85)+1<=19,INDEX(MW!$C$23:$U$23,(F2+1+Assumptions!$B$90-Assumptions!$B$85)+1),AVERAGE(MW!$R$23:$U$23)) | G7: =IF((G2+1+Assumptions!$B$90-Assumptions!$B$85)+1<=19,INDEX(MW!$C$23:$U$23,(G2+1+Assumptions!$B$90-Assumptions!$B$85)+1),AVERAGE(MW!$R$23:$U$23)) | H7: =IF((H2+1+Assumptions!$B$90-Assumptions!$B$85)+1<=19,INDEX(MW!$C$23:$U$23,(H2+1+Assumptions!$B$90-Assumptions!$B$85)+1),AVERAGE(MW!$R$23:$U$23)) | I7: =IF((I2+1+Assumptions!$B$90-Assumptions!$B$85)+1<=19,INDEX(MW!$C$23:$U$23,(I2+1+Assumptions!$B$90-Assumptions!$B$85)+1),AVERAGE(MW!$R$23:$U$23)) | J7: =IF((J2+1+Assumptions!$B$90-Assumptions!$B$85)+1<=19,INDEX(MW!$C$23:$U$23,(J2+1+Assumptions!$B$90-Assumptions!$B$85)+1),AVERAGE(MW!$R$23:$U$23)) | ... T7: =IF((T2+1+Assumptions!$B$90-Assumptions!$B$85)+1<=19,INDEX(MW!$C$23:$U$23,(T2+1+Assumptions!$B$90-Assumptions!$B$85)+1),AVERAGE(MW!$R$23:$U$23))
A8: Path: IT MW whose shell is built this qtr (energized at t + shlag) | C8: =IF((C2+1+Assumptions!$B$86)+1<=19,INDEX(MW!$C$23:$U$23,(C2+1+Assumptions!$B$86)+1),AVERAGE(MW!$R$23:$U$23)) | D8: =IF((D2+1+Assumptions!$B$86)+1<=19,INDEX(MW!$C$23:$U$23,(D2+1+Assumptions!$B$86)+1),AVERAGE(MW!$R$23:$U$23)) | E8: =IF((E2+1+Assumptions!$B$86)+1<=19,INDEX(MW!$C$23:$U$23,(E2+1+Assumptions!$B$86)+1),AVERAGE(MW!$R$23:$U$23)) | F8: =IF((F2+1+Assumptions!$B$86)+1<=19,INDEX(MW!$C$23:$U$23,(F2+1+Assumptions!$B$86)+1),AVERAGE(MW!$R$23:$U$23)) | G8: =IF((G2+1+Assumptions!$B$86)+1<=19,INDEX(MW!$C$23:$U$23,(G2+1+Assumptions!$B$86)+1),AVERAGE(MW!$R$23:$U$23)) | H8: =IF((H2+1+Assumptions!$B$86)+1<=19,INDEX(MW!$C$23:$U$23,(H2+1+Assumptions!$B$86)+1),AVERAGE(MW!$R$23:$U$23)) | I8: =IF((I2+1+Assumptions!$B$86)+1<=19,INDEX(MW!$C$23:$U$23,(I2+1+Assumptions!$B$86)+1),AVERAGE(MW!$R$23:$U$23)) | J8: =IF((J2+1+Assumptions!$B$86)+1<=19,INDEX(MW!$C$23:$U$23,(J2+1+Assumptions!$B$86)+1),AVERAGE(MW!$R$23:$U$23)) | ... T8: =IF((T2+1+Assumptions!$B$86)+1<=19,INDEX(MW!$C$23:$U$23,(T2+1+Assumptions!$B$86)+1),AVERAGE(MW!$R$23:$U$23))
A9: Path: GPU/IT capex (owned: GPU+net by gen; leased: leased $/IT MW by gen - GB300 before VR switch, VR after) | C9: =C7*(C5*IF(C2>=Assumptions!$B$81,Assumptions!$B$29,Assumptions!$B$25)+(1-C5)*IF(C2>=Assumptions!$B$81,Assumptions!$B$89,Assumptions!$B$88)) | D9: =D7*(D5*IF(D2>=Assumptions!$B$81,Assumptions!$B$29,Assumptions!$B$25)+(1-D5)*IF(D2>=Assumptions!$B$81,Assumptions!$B$89,Assumptions!$B$88)) | E9: =E7*(E5*IF(E2>=Assumptions!$B$81,Assumptions!$B$29,Assumptions!$B$25)+(1-E5)*IF(E2>=Assumptions!$B$81,Assumptions!$B$89,Assumptions!$B$88)) | F9: =F7*(F5*IF(F2>=Assumptions!$B$81,Assumptions!$B$29,Assumptions!$B$25)+(1-F5)*IF(F2>=Assumptions!$B$81,Assumptions!$B$89,Assumptions!$B$88)) | G9: =G7*(G5*IF(G2>=Assumptions!$B$81,Assumptions!$B$29,Assumptions!$B$25)+(1-G5)*IF(G2>=Assumptions!$B$81,Assumptions!$B$89,Assumptions!$B$88)) | H9: =H7*(H5*IF(H2>=Assumptions!$B$81,Assumptions!$B$29,Assumptions!$B$25)+(1-H5)*IF(H2>=Assumptions!$B$81,Assumptions!$B$89,Assumptions!$B$88)) | I9: =I7*(I5*IF(I2>=Assumptions!$B$81,Assumptions!$B$29,Assumptions!$B$25)+(1-I5)*IF(I2>=Assumptions!$B$81,Assumptions!$B$89,Assumptions!$B$88)) | J9: =J7*(J5*IF(J2>=Assumptions!$B$81,Assumptions!$B$29,Assumptions!$B$25)+(1-J5)*IF(J2>=Assumptions!$B$81,Assumptions!$B$89,Assumptions!$B$88)) | ... T9: =T7*(T5*IF(T2>=Assumptions!$B$81,Assumptions!$B$29,Assumptions!$B$25)+(1-T5)*IF(T2>=Assumptions!$B$81,Assumptions!$B$89,Assumptions!$B$88))
A10: Path: shell/power capex (owned share only) | C10: =C8*C5*IF(C2>=Assumptions!$B$81,Assumptions!$B$30,Assumptions!$B$26) | D10: =D8*D5*IF(D2>=Assumptions!$B$81,Assumptions!$B$30,Assumptions!$B$26) | E10: =E8*E5*IF(E2>=Assumptions!$B$81,Assumptions!$B$30,Assumptions!$B$26) | F10: =F8*F5*IF(F2>=Assumptions!$B$81,Assumptions!$B$30,Assumptions!$B$26) | G10: =G8*G5*IF(G2>=Assumptions!$B$81,Assumptions!$B$30,Assumptions!$B$26) | H10: =H8*H5*IF(H2>=Assumptions!$B$81,Assumptions!$B$30,Assumptions!$B$26) | I10: =I8*I5*IF(I2>=Assumptions!$B$81,Assumptions!$B$30,Assumptions!$B$26) | J10: =J8*J5*IF(J2>=Assumptions!$B$81,Assumptions!$B$30,Assumptions!$B$26) | ... T10: =T8*T5*IF(T2>=Assumptions!$B$81,Assumptions!$B$30,Assumptions!$B$26)
A11: Capex - path-consistent basis | C11: =C9+C10 | D11: =D9+D10 | E11: =E9+E10 | F11: =F9+F10 | G11: =G9+G10 | H11: =H9+H10 | I11: =I9+I10 | J11: =J9+J10 | ... T11: =T9+T10
A12: CAPEX USED (basis toggle) | C12: =IF(Assumptions!$B$84=1,C4,C11) | D12: =IF(Assumptions!$B$84=1,D4,D11) | E12: =IF(Assumptions!$B$84=1,E4,E11) | F12: =IF(Assumptions!$B$84=1,F4,F11) | G12: =IF(Assumptions!$B$84=1,G4,G11) | H12: =IF(Assumptions!$B$84=1,H4,H11) | I12: =IF(Assumptions!$B$84=1,I4,I11) | J12: =IF(Assumptions!$B$84=1,J4,J11) | ... T12: =IF(Assumptions!$B$84=1,T4,T11)
A13: Capex-implied IT MW bought (consensus capex / all-in $ per IT MW) | C13: =C4/(IF(C2>=Assumptions!$B$81,Assumptions!$B$29,Assumptions!$B$25)+C5*IF(C2>=Assumptions!$B$81,Assumptions!$B$30,Assumptions!$B$26)+(1-C5)*(IF(C2>=Assumptions!$B$81,Assumptions!$B$31,Assumptions!$B$27)-IF(C2>=Assumptions!$B$81,Assumptions!$B$29,Assumptions!$B$25))) | D13: =D4/(IF(D2>=Assumptions!$B$81,Assumptions!$B$29,Assumptions!$B$25)+D5*IF(D2>=Assumptions!$B$81,Assumptions!$B$30,Assumptions!$B$26)+(1-D5)*(IF(D2>=Assumptions!$B$81,Assumptions!$B$31,Assumptions!$B$27)-IF(D2>=Assumptions!$B$81,Assumptions!$B$29,Assumptions!$B$25))) | E13: =E4/(IF(E2>=Assumptions!$B$81,Assumptions!$B$29,Assumptions!$B$25)+E5*IF(E2>=Assumptions!$B$81,Assumptions!$B$30,Assumptions!$B$26)+(1-E5)*(IF(E2>=Assumptions!$B$81,Assumptions!$B$31,Assumptions!$B$27)-IF(E2>=Assumptions!$B$81,Assumptions!$B$29,Assumptions!$B$25))) | F13: =F4/(IF(F2>=Assumptions!$B$81,Assumptions!$B$29,Assumptions!$B$25)+F5*IF(F2>=Assumptions!$B$81,Assumptions!$B$30,Assumptions!$B$26)+(1-F5)*(IF(F2>=Assumptions!$B$81,Assumptions!$B$31,Assumptions!$B$27)-IF(F2>=Assumptions!$B$81,Assumptions!$B$29,Assumptions!$B$25))) | G13: =G4/(IF(G2>=Assumptions!$B$81,Assumptions!$B$29,Assumptions!$B$25)+G5*IF(G2>=Assumptions!$B$81,Assumptions!$B$30,Assumptions!$B$26)+(1-G5)*(IF(G2>=Assumptions!$B$81,Assumptions!$B$31,Assumptions!$B$27)-IF(G2>=Assumptions!$B$81,Assumptions!$B$29,Assumptions!$B$25))) | H13: =H4/(IF(H2>=Assumptions!$B$81,Assumptions!$B$29,Assumptions!$B$25)+H5*IF(H2>=Assumptions!$B$81,Assumptions!$B$30,Assumptions!$B$26)+(1-H5)*(IF(H2>=Assumptions!$B$81,Assumptions!$B$31,Assumptions!$B$27)-IF(H2>=Assumptions!$B$81,Assumptions!$B$29,Assumptions!$B$25))) | I13: =I4/(IF(I2>=Assumptions!$B$81,Assumptions!$B$29,Assumptions!$B$25)+I5*IF(I2>=Assumptions!$B$81,Assumptions!$B$30,Assumptions!$B$26)+(1-I5)*(IF(I2>=Assumptions!$B$81,Assumptions!$B$31,Assumptions!$B$27)-IF(I2>=Assumptions!$B$81,Assumptions!$B$29,Assumptions!$B$25))) | J13: =J4/(IF(J2>=Assumptions!$B$81,Assumptions!$B$29,Assumptions!$B$25)+J5*IF(J2>=Assumptions!$B$81,Assumptions!$B$30,Assumptions!$B$26)+(1-J5)*(IF(J2>=Assumptions!$B$81,Assumptions!$B$31,Assumptions!$B$27)-IF(J2>=Assumptions!$B$81,Assumptions!$B$29,Assumptions!$B$25))) | ... T13: =T4/(IF(T2>=Assumptions!$B$81,Assumptions!$B$29,Assumptions!$B$25)+T5*IF(T2>=Assumptions!$B$81,Assumptions!$B$30,Assumptions!$B$26)+(1-T5)*(IF(T2>=Assumptions!$B$81,Assumptions!$B$31,Assumptions!$B$27)-IF(T2>=Assumptions!$B$81,Assumptions!$B$29,Assumptions!$B$25)))
A14: GPU+network capex | C14: =IF(Assumptions!$B$84=1,C12*C6,C9) | D14: =IF(Assumptions!$B$84=1,D12*D6,D9) | E14: =IF(Assumptions!$B$84=1,E12*E6,E9) | F14: =IF(Assumptions!$B$84=1,F12*F6,F9) | G14: =IF(Assumptions!$B$84=1,G12*G6,G9) | H14: =IF(Assumptions!$B$84=1,H12*H6,H9) | I14: =IF(Assumptions!$B$84=1,I12*I6,I9) | J14: =IF(Assumptions!$B$84=1,J12*J6,J9) | ... T14: =IF(Assumptions!$B$84=1,T12*T6,T9)
A15: Shell/power/fit-out capex | C15: =C12-C14 | D15: =D12-D14 | E15: =E12-E14 | F15: =F12-F14 | G15: =G12-G14 | H15: =H12-H14 | I15: =I12-I14 | J15: =J12-J14 | ... T15: =T12-T14
A16: Effective capex->in-service lag for GPUs (consensus: lage; path: lagb - pglag) | B16: =IF(Assumptions!$B$84=1,Assumptions!$B$83,MAX(0,Assumptions!$B$90-Assumptions!$B$85))
A17: GPU+network placed in service (capex lagged by capex->energized; 6/30 not-in-use first) | C17: =Assumptions!$B$105*Assumptions!$B$80*Assumptions!$B$106 | D17: =Assumptions!$B$105*Assumptions!$B$80*(1-Assumptions!$B$106) | E17: =IF(E2>=$B$16,INDEX($C$14:$T$14,E2-$B$16+1),0) | F17: =IF(F2>=$B$16,INDEX($C$14:$T$14,F2-$B$16+1),0) | G17: =IF(G2>=$B$16,INDEX($C$14:$T$14,G2-$B$16+1),0) | H17: =IF(H2>=$B$16,INDEX($C$14:$T$14,H2-$B$16+1),0) | I17: =IF(I2>=$B$16,INDEX($C$14:$T$14,I2-$B$16+1),0) | J17: =IF(J2>=$B$16,INDEX($C$14:$T$14,J2-$B$16+1),0) | K17: =IF(K2>=$B$16,INDEX($C$14:$T$14,K2-$B$16+1),0) | L17: =IF(L2>=$B$16,INDEX($C$14:$T$14,L2-$B$16+1),0) | ... T17: =IF(T2>=$B$16,INDEX($C$14:$T$14,T2-$B$16+1),0)
A18: Non-GPU placed in service | C18: =Assumptions!$B$105*(1-Assumptions!$B$80)*Assumptions!$B$106 | D18: =Assumptions!$B$105*(1-Assumptions!$B$80)*(1-Assumptions!$B$106) | E18: =IF(E2>=Assumptions!$B$83,INDEX($C$15:$T$15,E2-Assumptions!$B$83+1),0) | F18: =IF(F2>=Assumptions!$B$83,INDEX($C$15:$T$15,F2-Assumptions!$B$83+1),0) | G18: =IF(G2>=Assumptions!$B$83,INDEX($C$15:$T$15,G2-Assumptions!$B$83+1),0) | H18: =IF(H2>=Assumptions!$B$83,INDEX($C$15:$T$15,H2-Assumptions!$B$83+1),0) | I18: =IF(I2>=Assumptions!$B$83,INDEX($C$15:$T$15,I2-Assumptions!$B$83+1),0) | J18: =IF(J2>=Assumptions!$B$83,INDEX($C$15:$T$15,J2-Assumptions!$B$83+1),0) | K18: =IF(K2>=Assumptions!$B$83,INDEX($C$15:$T$15,K2-Assumptions!$B$83+1),0) | L18: =IF(L2>=Assumptions!$B$83,INDEX($C$15:$T$15,L2-Assumptions!$B$83+1),0) | ... T18: =IF(T2>=Assumptions!$B$83,INDEX($C$15:$T$15,T2-Assumptions!$B$83+1),0)
A19: Gross GPU+network in service (end of qtr) | C19: =Assumptions!$B$102+SUM($C$17:C17) | D19: =Assumptions!$B$102+SUM($C$17:D17) | E19: =Assumptions!$B$102+SUM($C$17:E17) | F19: =Assumptions!$B$102+SUM($C$17:F17) | G19: =Assumptions!$B$102+SUM($C$17:G17) | H19: =Assumptions!$B$102+SUM($C$17:H17) | I19: =Assumptions!$B$102+SUM($C$17:I17) | J19: =Assumptions!$B$102+SUM($C$17:J17) | ... T19: =Assumptions!$B$102+SUM($C$17:T17)
A20: Gross GPU+network BILLING (in service lagged by energized->billing) | C20: =IF(C2>=Assumptions!$B$90,INDEX($C$19:$T$19,C2-Assumptions!$B$90+1),Assumptions!$B$102) | D20: =IF(D2>=Assumptions!$B$90,INDEX($C$19:$T$19,D2-Assumptions!$B$90+1),Assumptions!$B$102) | E20: =IF(E2>=Assumptions!$B$90,INDEX($C$19:$T$19,E2-Assumptions!$B$90+1),Assumptions!$B$102) | F20: =IF(F2>=Assumptions!$B$90,INDEX($C$19:$T$19,F2-Assumptions!$B$90+1),Assumptions!$B$102) | G20: =IF(G2>=Assumptions!$B$90,INDEX($C$19:$T$19,G2-Assumptions!$B$90+1),Assumptions!$B$102) | H20: =IF(H2>=Assumptions!$B$90,INDEX($C$19:$T$19,H2-Assumptions!$B$90+1),Assumptions!$B$102) | I20: =IF(I2>=Assumptions!$B$90,INDEX($C$19:$T$19,I2-Assumptions!$B$90+1),Assumptions!$B$102) | J20: =IF(J2>=Assumptions!$B$90,INDEX($C$19:$T$19,J2-Assumptions!$B$90+1),Assumptions!$B$102) | ... T20: =IF(T2>=Assumptions!$B$90,INDEX($C$19:$T$19,T2-Assumptions!$B$90+1),Assumptions!$B$102)
A21: Gross non-GPU in service | C21: =Assumptions!$B$104+SUM($C$18:C18) | D21: =Assumptions!$B$104+SUM($C$18:D18) | E21: =Assumptions!$B$104+SUM($C$18:E18) | F21: =Assumptions!$B$104+SUM($C$18:F18) | G21: =Assumptions!$B$104+SUM($C$18:G18) | H21: =Assumptions!$B$104+SUM($C$18:H18) | I21: =Assumptions!$B$104+SUM($C$18:I18) | J21: =Assumptions!$B$104+SUM($C$18:J18) | ... T21: =Assumptions!$B$104+SUM($C$18:T18)
A22: GPU+network D&A at life L1 | C22: =IF(C2<(4*Assumptions!$B$3)-Assumptions!$B$103,Assumptions!$B$102/(4*Assumptions!$B$3),0)+SUMPRODUCT($C$17:C17,(((C2-$C$2:C2)=0)*0.5+(((C2-$C$2:C2)>0)*((C2-$C$2:C2)<(4*Assumptions!$B$3)))+(((C2-$C$2:C2)=(4*Assumptions!$B$3))*0.5))/(4*Assumptions!$B$3)) | D22: =IF(D2<(4*Assumptions!$B$3)-Assumptions!$B$103,Assumptions!$B$102/(4*Assumptions!$B$3),0)+SUMPRODUCT($C$17:D17,(((D2-$C$2:D2)=0)*0.5+(((D2-$C$2:D2)>0)*((D2-$C$2:D2)<(4*Assumptions!$B$3)))+(((D2-$C$2:D2)=(4*Assumptions!$B$3))*0.5))/(4*Assumptions!$B$3)) | E22: =IF(E2<(4*Assumptions!$B$3)-Assumptions!$B$103,Assumptions!$B$102/(4*Assumptions!$B$3),0)+SUMPRODUCT($C$17:E17,(((E2-$C$2:E2)=0)*0.5+(((E2-$C$2:E2)>0)*((E2-$C$2:E2)<(4*Assumptions!$B$3)))+(((E2-$C$2:E2)=(4*Assumptions!$B$3))*0.5))/(4*Assumptions!$B$3)) | F22: =IF(F2<(4*Assumptions!$B$3)-Assumptions!$B$103,Assumptions!$B$102/(4*Assumptions!$B$3),0)+SUMPRODUCT($C$17:F17,(((F2-$C$2:F2)=0)*0.5+(((F2-$C$2:F2)>0)*((F2-$C$2:F2)<(4*Assumptions!$B$3)))+(((F2-$C$2:F2)=(4*Assumptions!$B$3))*0.5))/(4*Assumptions!$B$3)) | G22: =IF(G2<(4*Assumptions!$B$3)-Assumptions!$B$103,Assumptions!$B$102/(4*Assumptions!$B$3),0)+SUMPRODUCT($C$17:G17,(((G2-$C$2:G2)=0)*0.5+(((G2-$C$2:G2)>0)*((G2-$C$2:G2)<(4*Assumptions!$B$3)))+(((G2-$C$2:G2)=(4*Assumptions!$B$3))*0.5))/(4*Assumptions!$B$3)) | H22: =IF(H2<(4*Assumptions!$B$3)-Assumptions!$B$103,Assumptions!$B$102/(4*Assumptions!$B$3),0)+SUMPRODUCT($C$17:H17,(((H2-$C$2:H2)=0)*0.5+(((H2-$C$2:H2)>0)*((H2-$C$2:H2)<(4*Assumptions!$B$3)))+(((H2-$C$2:H2)=(4*Assumptions!$B$3))*0.5))/(4*Assumptions!$B$3)) | I22: =IF(I2<(4*Assumptions!$B$3)-Assumptions!$B$103,Assumptions!$B$102/(4*Assumptions!$B$3),0)+SUMPRODUCT($C$17:I17,(((I2-$C$2:I2)=0)*0.5+(((I2-$C$2:I2)>0)*((I2-$C$2:I2)<(4*Assumptions!$B$3)))+(((I2-$C$2:I2)=(4*Assumptions!$B$3))*0.5))/(4*Assumptions!$B$3)) | J22: =IF(J2<(4*Assumptions!$B$3)-Assumptions!$B$103,Assumptions!$B$102/(4*Assumptions!$B$3),0)+SUMPRODUCT($C$17:J17,(((J2-$C$2:J2)=0)*0.5+(((J2-$C$2:J2)>0)*((J2-$C$2:J2)<(4*Assumptions!$B$3)))+(((J2-$C$2:J2)=(4*Assumptions!$B$3))*0.5))/(4*Assumptions!$B$3)) | ... T22: =IF(T2<(4*Assumptions!$B$3)-Assumptions!$B$103,Assumptions!$B$102/(4*Assumptions!$B$3),0)+SUMPRODUCT($C$17:T17,(((T2-$C$2:T2)=0)*0.5+(((T2-$C$2:T2)>0)*((T2-$C$2:T2)<(4*Assumptions!$B$3)))+(((T2-$C$2:T2)=(4*Assumptions!$B$3))*0.5))/(4*Assumptions!$B$3))
A23: GPU+network D&A at life L2 | C23: =IF(C2<(4*Assumptions!$B$4)-Assumptions!$B$103,Assumptions!$B$102/(4*Assumptions!$B$4),0)+SUMPRODUCT($C$17:C17,(((C2-$C$2:C2)=0)*0.5+(((C2-$C$2:C2)>0)*((C2-$C$2:C2)<(4*Assumptions!$B$4)))+(((C2-$C$2:C2)=(4*Assumptions!$B$4))*0.5))/(4*Assumptions!$B$4)) | D23: =IF(D2<(4*Assumptions!$B$4)-Assumptions!$B$103,Assumptions!$B$102/(4*Assumptions!$B$4),0)+SUMPRODUCT($C$17:D17,(((D2-$C$2:D2)=0)*0.5+(((D2-$C$2:D2)>0)*((D2-$C$2:D2)<(4*Assumptions!$B$4)))+(((D2-$C$2:D2)=(4*Assumptions!$B$4))*0.5))/(4*Assumptions!$B$4)) | E23: =IF(E2<(4*Assumptions!$B$4)-Assumptions!$B$103,Assumptions!$B$102/(4*Assumptions!$B$4),0)+SUMPRODUCT($C$17:E17,(((E2-$C$2:E2)=0)*0.5+(((E2-$C$2:E2)>0)*((E2-$C$2:E2)<(4*Assumptions!$B$4)))+(((E2-$C$2:E2)=(4*Assumptions!$B$4))*0.5))/(4*Assumptions!$B$4)) | F23: =IF(F2<(4*Assumptions!$B$4)-Assumptions!$B$103,Assumptions!$B$102/(4*Assumptions!$B$4),0)+SUMPRODUCT($C$17:F17,(((F2-$C$2:F2)=0)*0.5+(((F2-$C$2:F2)>0)*((F2-$C$2:F2)<(4*Assumptions!$B$4)))+(((F2-$C$2:F2)=(4*Assumptions!$B$4))*0.5))/(4*Assumptions!$B$4)) | G23: =IF(G2<(4*Assumptions!$B$4)-Assumptions!$B$103,Assumptions!$B$102/(4*Assumptions!$B$4),0)+SUMPRODUCT($C$17:G17,(((G2-$C$2:G2)=0)*0.5+(((G2-$C$2:G2)>0)*((G2-$C$2:G2)<(4*Assumptions!$B$4)))+(((G2-$C$2:G2)=(4*Assumptions!$B$4))*0.5))/(4*Assumptions!$B$4)) | H23: =IF(H2<(4*Assumptions!$B$4)-Assumptions!$B$103,Assumptions!$B$102/(4*Assumptions!$B$4),0)+SUMPRODUCT($C$17:H17,(((H2-$C$2:H2)=0)*0.5+(((H2-$C$2:H2)>0)*((H2-$C$2:H2)<(4*Assumptions!$B$4)))+(((H2-$C$2:H2)=(4*Assumptions!$B$4))*0.5))/(4*Assumptions!$B$4)) | I23: =IF(I2<(4*Assumptions!$B$4)-Assumptions!$B$103,Assumptions!$B$102/(4*Assumptions!$B$4),0)+SUMPRODUCT($C$17:I17,(((I2-$C$2:I2)=0)*0.5+(((I2-$C$2:I2)>0)*((I2-$C$2:I2)<(4*Assumptions!$B$4)))+(((I2-$C$2:I2)=(4*Assumptions!$B$4))*0.5))/(4*Assumptions!$B$4)) | J23: =IF(J2<(4*Assumptions!$B$4)-Assumptions!$B$103,Assumptions!$B$102/(4*Assumptions!$B$4),0)+SUMPRODUCT($C$17:J17,(((J2-$C$2:J2)=0)*0.5+(((J2-$C$2:J2)>0)*((J2-$C$2:J2)<(4*Assumptions!$B$4)))+(((J2-$C$2:J2)=(4*Assumptions!$B$4))*0.5))/(4*Assumptions!$B$4)) | ... T23: =IF(T2<(4*Assumptions!$B$4)-Assumptions!$B$103,Assumptions!$B$102/(4*Assumptions!$B$4),0)+SUMPRODUCT($C$17:T17,(((T2-$C$2:T2)=0)*0.5+(((T2-$C$2:T2)>0)*((T2-$C$2:T2)<(4*Assumptions!$B$4)))+(((T2-$C$2:T2)=(4*Assumptions!$B$4))*0.5))/(4*Assumptions!$B$4))
A24: GPU+network D&A at life L3 | C24: =IF(C2<(4*Assumptions!$B$5)-Assumptions!$B$103,Assumptions!$B$102/(4*Assumptions!$B$5),0)+SUMPRODUCT($C$17:C17,(((C2-$C$2:C2)=0)*0.5+(((C2-$C$2:C2)>0)*((C2-$C$2:C2)<(4*Assumptions!$B$5)))+(((C2-$C$2:C2)=(4*Assumptions!$B$5))*0.5))/(4*Assumptions!$B$5)) | D24: =IF(D2<(4*Assumptions!$B$5)-Assumptions!$B$103,Assumptions!$B$102/(4*Assumptions!$B$5),0)+SUMPRODUCT($C$17:D17,(((D2-$C$2:D2)=0)*0.5+(((D2-$C$2:D2)>0)*((D2-$C$2:D2)<(4*Assumptions!$B$5)))+(((D2-$C$2:D2)=(4*Assumptions!$B$5))*0.5))/(4*Assumptions!$B$5)) | E24: =IF(E2<(4*Assumptions!$B$5)-Assumptions!$B$103,Assumptions!$B$102/(4*Assumptions!$B$5),0)+SUMPRODUCT($C$17:E17,(((E2-$C$2:E2)=0)*0.5+(((E2-$C$2:E2)>0)*((E2-$C$2:E2)<(4*Assumptions!$B$5)))+(((E2-$C$2:E2)=(4*Assumptions!$B$5))*0.5))/(4*Assumptions!$B$5)) | F24: =IF(F2<(4*Assumptions!$B$5)-Assumptions!$B$103,Assumptions!$B$102/(4*Assumptions!$B$5),0)+SUMPRODUCT($C$17:F17,(((F2-$C$2:F2)=0)*0.5+(((F2-$C$2:F2)>0)*((F2-$C$2:F2)<(4*Assumptions!$B$5)))+(((F2-$C$2:F2)=(4*Assumptions!$B$5))*0.5))/(4*Assumptions!$B$5)) | G24: =IF(G2<(4*Assumptions!$B$5)-Assumptions!$B$103,Assumptions!$B$102/(4*Assumptions!$B$5),0)+SUMPRODUCT($C$17:G17,(((G2-$C$2:G2)=0)*0.5+(((G2-$C$2:G2)>0)*((G2-$C$2:G2)<(4*Assumptions!$B$5)))+(((G2-$C$2:G2)=(4*Assumptions!$B$5))*0.5))/(4*Assumptions!$B$5)) | H24: =IF(H2<(4*Assumptions!$B$5)-Assumptions!$B$103,Assumptions!$B$102/(4*Assumptions!$B$5),0)+SUMPRODUCT($C$17:H17,(((H2-$C$2:H2)=0)*0.5+(((H2-$C$2:H2)>0)*((H2-$C$2:H2)<(4*Assumptions!$B$5)))+(((H2-$C$2:H2)=(4*Assumptions!$B$5))*0.5))/(4*Assumptions!$B$5)) | I24: =IF(I2<(4*Assumptions!$B$5)-Assumptions!$B$103,Assumptions!$B$102/(4*Assumptions!$B$5),0)+SUMPRODUCT($C$17:I17,(((I2-$C$2:I2)=0)*0.5+(((I2-$C$2:I2)>0)*((I2-$C$2:I2)<(4*Assumptions!$B$5)))+(((I2-$C$2:I2)=(4*Assumptions!$B$5))*0.5))/(4*Assumptions!$B$5)) | J24: =IF(J2<(4*Assumptions!$B$5)-Assumptions!$B$103,Assumptions!$B$102/(4*Assumptions!$B$5),0)+SUMPRODUCT($C$17:J17,(((J2-$C$2:J2)=0)*0.5+(((J2-$C$2:J2)>0)*((J2-$C$2:J2)<(4*Assumptions!$B$5)))+(((J2-$C$2:J2)=(4*Assumptions!$B$5))*0.5))/(4*Assumptions!$B$5)) | ... T24: =IF(T2<(4*Assumptions!$B$5)-Assumptions!$B$103,Assumptions!$B$102/(4*Assumptions!$B$5),0)+SUMPRODUCT($C$17:T17,(((T2-$C$2:T2)=0)*0.5+(((T2-$C$2:T2)>0)*((T2-$C$2:T2)<(4*Assumptions!$B$5)))+(((T2-$C$2:T2)=(4*Assumptions!$B$5))*0.5))/(4*Assumptions!$B$5))
A25: Non-GPU D&A (existing at ngl, new at shell life) | C25: =Assumptions!$B$104/(4*Assumptions!$B$7)+SUMPRODUCT($C$18:C18,(((C2-$C$2:C2)=0)*0.5+((C2-$C$2:C2)>0))/(4*Assumptions!$B$6)) | D25: =Assumptions!$B$104/(4*Assumptions!$B$7)+SUMPRODUCT($C$18:D18,(((D2-$C$2:D2)=0)*0.5+((D2-$C$2:D2)>0))/(4*Assumptions!$B$6)) | E25: =Assumptions!$B$104/(4*Assumptions!$B$7)+SUMPRODUCT($C$18:E18,(((E2-$C$2:E2)=0)*0.5+((E2-$C$2:E2)>0))/(4*Assumptions!$B$6)) | F25: =Assumptions!$B$104/(4*Assumptions!$B$7)+SUMPRODUCT($C$18:F18,(((F2-$C$2:F2)=0)*0.5+((F2-$C$2:F2)>0))/(4*Assumptions!$B$6)) | G25: =Assumptions!$B$104/(4*Assumptions!$B$7)+SUMPRODUCT($C$18:G18,(((G2-$C$2:G2)=0)*0.5+((G2-$C$2:G2)>0))/(4*Assumptions!$B$6)) | H25: =Assumptions!$B$104/(4*Assumptions!$B$7)+SUMPRODUCT($C$18:H18,(((H2-$C$2:H2)=0)*0.5+((H2-$C$2:H2)>0))/(4*Assumptions!$B$6)) | I25: =Assumptions!$B$104/(4*Assumptions!$B$7)+SUMPRODUCT($C$18:I18,(((I2-$C$2:I2)=0)*0.5+((I2-$C$2:I2)>0))/(4*Assumptions!$B$6)) | J25: =Assumptions!$B$104/(4*Assumptions!$B$7)+SUMPRODUCT($C$18:J18,(((J2-$C$2:J2)=0)*0.5+((J2-$C$2:J2)>0))/(4*Assumptions!$B$6)) | ... T25: =Assumptions!$B$104/(4*Assumptions!$B$7)+SUMPRODUCT($C$18:T18,(((T2-$C$2:T2)=0)*0.5+((T2-$C$2:T2)>0))/(4*Assumptions!$B$6))
A26: Revenue - consensus (Q3'26-Q4'27 quarterly, FY28 weights) | C26: 904.1 | D26: 1452 | E26: 2175 | F26: 2646 | G26: 3304 | H26: 4052 | I26: =Assumptions!$B$115*Assumptions!$B$116 | J26: =Assumptions!$B$115*Assumptions!$B$117 | K26: =Assumptions!$B$115*Assumptions!$B$118 | L26: =Assumptions!$B$115*Assumptions!$B$119
A27: Adj. EBITDA - consensus | C27: 355 | D27: 671 | E27: 1277 | F27: 1581 | G27: 1883 | H27: 2372 | I27: =Assumptions!$B$114*Assumptions!$B$116 | J27: =Assumptions!$B$114*Assumptions!$B$117 | K27: =Assumptions!$B$114*Assumptions!$B$118 | L27: =Assumptions!$B$114*Assumptions!$B$119
A29: FY28 EBITDA yield on avg gross GPU IN SERVICE (v1 basis) | B29: =Assumptions!$B$114/AVERAGE(I19:L19)
A30: FY28 EBITDA yield on avg gross GPU BILLING capital (v2 default) | B30: =Assumptions!$B$114/AVERAGE(I20:L20)
A31: FY28 EBITDA per avg billing gross MW (Capacity path, selected scenario) $M/MW | B31: =Assumptions!$B$114/AVERAGE(MW!J25:MW!M25)
A32: FY28 consensus revenue per avg billing gross MW $M/MW | B32: =Assumptions!$B$115/AVERAGE(MW!J25:MW!M25)
A33: FY29+ yield used | B33: =IF(ISNUMBER(Assumptions!$B$121),Assumptions!$B$121,IF(Assumptions!$B$120=1,B30,B29))
A34: FY28 EBITDA margin (FY29+ revenue = EBITDA / margin) | B34: =Assumptions!$B$114/Assumptions!$B$115
A36: Adj. EBITDA used | C36: =C27 | D36: =D27 | E36: =E27 | F36: =F27 | G36: =G27 | H36: =H27 | I36: =I27 | J36: =J27 | ... L36: =L27 | M36: =$B$33/4*IF(Assumptions!$B$120=1,AVERAGE(INDEX($C$20:$T$20,M2),INDEX($C$20:$T$20,M2+1)),AVERAGE(INDEX($C$19:$T$19,M2),INDEX($C$19:$T$19,M2+1))) | N36: =$B$33/4*IF(Assumptions!$B$120=1,AVERAGE(INDEX($C$20:$T$20,N2),INDEX($C$20:$T$20,N2+1)),AVERAGE(INDEX($C$19:$T$19,N2),INDEX($C$19:$T$19,N2+1))) | O36: =$B$33/4*IF(Assumptions!$B$120=1,AVERAGE(INDEX($C$20:$T$20,O2),INDEX($C$20:$T$20,O2+1)),AVERAGE(INDEX($C$19:$T$19,O2),INDEX($C$19:$T$19,O2+1))) | P36: =$B$33/4*IF(Assumptions!$B$120=1,AVERAGE(INDEX($C$20:$T$20,P2),INDEX($C$20:$T$20,P2+1)),AVERAGE(INDEX($C$19:$T$19,P2),INDEX($C$19:$T$19,P2+1))) | Q36: =$B$33/4*IF(Assumptions!$B$120=1,AVERAGE(INDEX($C$20:$T$20,Q2),INDEX($C$20:$T$20,Q2+1)),AVERAGE(INDEX($C$19:$T$19,Q2),INDEX($C$19:$T$19,Q2+1))) | R36: =$B$33/4*IF(Assumptions!$B$120=1,AVERAGE(INDEX($C$20:$T$20,R2),INDEX($C$20:$T$20,R2+1)),AVERAGE(INDEX($C$19:$T$19,R2),INDEX($C$19:$T$19,R2+1))) | S36: =$B$33/4*IF(Assumptions!$B$120=1,AVERAGE(INDEX($C$20:$T$20,S2),INDEX($C$20:$T$20,S2+1)),AVERAGE(INDEX($C$19:$T$19,S2),INDEX($C$19:$T$19,S2+1))) | T36: =$B$33/4*IF(Assumptions!$B$120=1,AVERAGE(INDEX($C$20:$T$20,T2),INDEX($C$20:$T$20,T2+1)),AVERAGE(INDEX($C$19:$T$19,T2),INDEX($C$19:$T$19,T2+1)))
A37: Revenue used | C37: =C26 | D37: =D26 | E37: =E26 | F37: =F26 | G37: =G26 | H37: =H26 | I37: =I26 | J37: =J26 | ... L37: =L26 | M37: =M36/$B$34 | N37: =N36/$B$34 | O37: =O36/$B$34 | P37: =P36/$B$34 | Q37: =Q36/$B$34 | R37: =R36/$B$34 | S37: =S36/$B$34 | T37: =T36/$B$34
A38: EBIT at life L1 | C38: =C36-C22-C25 | D38: =D36-D22-D25 | E38: =E36-E22-E25 | F38: =F36-F22-F25 | G38: =G36-G22-G25 | H38: =H36-H22-H25 | I38: =I36-I22-I25 | J38: =J36-J22-J25 | ... T38: =T36-T22-T25
A39: EBIT at life L2 | C39: =C36-C23-C25 | D39: =D36-D23-D25 | E39: =E36-E23-E25 | F39: =F36-F23-F25 | G39: =G36-G23-G25 | H39: =H36-H23-H25 | I39: =I36-I23-I25 | J39: =J36-J23-J25 | ... T39: =T36-T23-T25
A40: EBIT at life L3 | C40: =C36-C24-C25 | D40: =D36-D24-D25 | E40: =E36-E24-E25 | F40: =F36-F24-F25 | G40: =G36-G24-G25 | H40: =H36-H24-H25 | I40: =I36-I24-I25 | J40: =J36-J24-J25 | ... T40: =T36-T24-T25
A41: EBIT margin at life L1 | C41: =C38/C37 | D41: =D38/D37 | E41: =E38/E37 | F41: =F38/F37 | G41: =G38/G37 | H41: =H38/H37 | I41: =I38/I37 | J41: =J38/J37 | ... T41: =T38/T37
A42: EBIT margin at life L2 | C42: =C39/C37 | D42: =D39/D37 | E42: =E39/E37 | F42: =F39/F37 | G42: =G39/G37 | H42: =H39/H37 | I42: =I39/I37 | J42: =J39/J37 | ... T42: =T39/T37
A43: EBIT margin at life L3 | C43: =C40/C37 | D43: =D40/D37 | E43: =E40/E37 | F43: =F40/F37 | G43: =G40/G37 | H43: =H40/H37 | I43: =I40/I37 | J43: =J40/J37 | ... T43: =T40/T37
A44: New customer prepayments (pinc x ppct x capex) | C44: =Assumptions!$B$128*Assumptions!$B$55*Assumptions!$B$54*C12 | D44: =Assumptions!$B$128*Assumptions!$B$55*Assumptions!$B$54*D12 | E44: =Assumptions!$B$128*Assumptions!$B$55*Assumptions!$B$54*E12 | F44: =Assumptions!$B$128*Assumptions!$B$55*Assumptions!$B$54*F12 | G44: =Assumptions!$B$128*Assumptions!$B$55*Assumptions!$B$54*G12 | H44: =Assumptions!$B$128*Assumptions!$B$55*Assumptions!$B$54*H12 | I44: =Assumptions!$B$128*Assumptions!$B$55*Assumptions!$B$54*I12 | J44: =Assumptions!$B$128*Assumptions!$B$55*Assumptions!$B$54*J12 | ... T44: =Assumptions!$B$128*Assumptions!$B$55*Assumptions!$B$54*T12
A45: Deferred revenue recognized (non-cash revenue in EBITDA) | C45: =Assumptions!$B$128*(Assumptions!$B$129/Assumptions!$B$130+SUMPRODUCT($C$44:C44,((C2-$C$2:C2)<Assumptions!$B$130)*1)/Assumptions!$B$130) | D45: =Assumptions!$B$128*(Assumptions!$B$129/Assumptions!$B$130+SUMPRODUCT($C$44:D44,((D2-$C$2:D2)<Assumptions!$B$130)*1)/Assumptions!$B$130) | E45: =Assumptions!$B$128*(Assumptions!$B$129/Assumptions!$B$130+SUMPRODUCT($C$44:E44,((E2-$C$2:E2)<Assumptions!$B$130)*1)/Assumptions!$B$130) | F45: =Assumptions!$B$128*(Assumptions!$B$129/Assumptions!$B$130+SUMPRODUCT($C$44:F44,((F2-$C$2:F2)<Assumptions!$B$130)*1)/Assumptions!$B$130) | G45: =Assumptions!$B$128*(Assumptions!$B$129/Assumptions!$B$130+SUMPRODUCT($C$44:G44,((G2-$C$2:G2)<Assumptions!$B$130)*1)/Assumptions!$B$130) | H45: =Assumptions!$B$128*(Assumptions!$B$129/Assumptions!$B$130+SUMPRODUCT($C$44:H44,((H2-$C$2:H2)<Assumptions!$B$130)*1)/Assumptions!$B$130) | I45: =Assumptions!$B$128*(Assumptions!$B$129/Assumptions!$B$130+SUMPRODUCT($C$44:I44,((I2-$C$2:I2)<Assumptions!$B$130)*1)/Assumptions!$B$130) | J45: =Assumptions!$B$128*(Assumptions!$B$129/Assumptions!$B$130+SUMPRODUCT($C$44:J44,((J2-$C$2:J2)<Assumptions!$B$130)*1)/Assumptions!$B$130) | ... T45: =Assumptions!$B$128*(Assumptions!$B$129/Assumptions!$B$130+SUMPRODUCT($C$44:T44,((T2-$C$2:T2)<Assumptions!$B$130)*1)/Assumptions!$B$130)
A46: Cash interest (converts + loan) + interest on funding gap | C46: =Assumptions!$B$142 | D46: =Assumptions!$B$142+MAX(0,-C49)*Assumptions!$B$143/4 | E46: =Assumptions!$B$142+MAX(0,-D49)*Assumptions!$B$143/4 | F46: =Assumptions!$B$142+MAX(0,-E49)*Assumptions!$B$143/4 | G46: =Assumptions!$B$142+MAX(0,-F49)*Assumptions!$B$143/4 | H46: =Assumptions!$B$142+MAX(0,-G49)*Assumptions!$B$143/4 | I46: =Assumptions!$B$142+MAX(0,-H49)*Assumptions!$B$143/4 | J46: =Assumptions!$B$142+MAX(0,-I49)*Assumptions!$B$143/4 | K46: =Assumptions!$B$142+MAX(0,-J49)*Assumptions!$B$143/4 | ... T46: =Assumptions!$B$142+MAX(0,-S49)*Assumptions!$B$143/4
A47: FCF (EBITDA - capex - interest + prepayments - deferred revenue recognized) | C47: =C36-C12-C46+C44-C45 | D47: =D36-D12-D46+D44-D45 | E47: =E36-E12-E46+E44-E45 | F47: =F36-F12-F46+F44-F45 | G47: =G36-G12-G46+G44-G45 | H47: =H36-H12-H46+H44-H45 | I47: =I36-I12-I46+I44-I45 | J47: =J36-J12-J46+J44-J45 | ... T47: =T36-T12-T46+T44-T45
A48: FCF ex-prepayment effects | C48: =C36-C12-C46 | D48: =D36-D12-D46 | E48: =E36-E12-E46 | F48: =F36-F12-F46 | G48: =G36-G12-G46 | H48: =H36-H12-H46 | I48: =I36-I12-I46 | J48: =J36-J12-J46 | ... T48: =T36-T12-T46
A49: Liquidity (starting liquidity + cumulative FCF; negative = funding need) | C49: =Assumptions!$B$147+SUM($C$47:C47) | D49: =Assumptions!$B$147+SUM($C$47:D47) | E49: =Assumptions!$B$147+SUM($C$47:E47) | F49: =Assumptions!$B$147+SUM($C$47:F47) | G49: =Assumptions!$B$147+SUM($C$47:G47) | H49: =Assumptions!$B$147+SUM($C$47:H47) | I49: =Assumptions!$B$147+SUM($C$47:I47) | J49: =Assumptions!$B$147+SUM($C$47:J47) | ... T49: =Assumptions!$B$147+SUM($C$47:T47)
A51: First quarter with negative liquidity | B51: =IFERROR(INDEX($C$1:$T$1,MATCH(TRUE,INDEX($C$49:$T$49<0,0),0)),"none by Q4 2030")
A52: Peak funding need ($M) | B52: =-MIN(0,MIN($C$49:$T$49))
A53: Peak funding need in new shares at $242.81 (M) | B53: =B52/Assumptions!$B$155
A54: Avg billing GPU capital in quarter (for yield) | C54: =AVERAGE(C20,C20) | D54: =AVERAGE(D20,C20) | E54: =AVERAGE(E20,D20) | F54: =AVERAGE(F20,E20) | G54: =AVERAGE(G20,F20) | H54: =AVERAGE(H20,G20) | I54: =AVERAGE(I20,H20) | J54: =AVERAGE(J20,I20) | K54: =AVERAGE(K20,J20) | ... T54: =AVERAGE(T20,S20)
A55: Avg in-service GPU capital in quarter | C55: =AVERAGE(C19,C19) | D55: =AVERAGE(D19,C19) | E55: =AVERAGE(E19,D19) | F55: =AVERAGE(F19,E19) | G55: =AVERAGE(G19,F19) | H55: =AVERAGE(H19,G19) | I55: =AVERAGE(I19,H19) | J55: =AVERAGE(J19,I19) | K55: =AVERAGE(K19,J19) | ... T55: =AVERAGE(T19,S19)

Sheet Annual
A1: Annual roll-up ($M; FY26 = 1H actual + 2H model) | B1: 2026 | C1: 2027 | D1: 2028 | E1: 2029 | F1: 2030
A2: Revenue | B2: =SUMPRODUCT((Model!$C$3:$T$3=2026)*Model!$C$37:$T$37)+Assumptions!$B$123 | C2: =SUMPRODUCT((Model!$C$3:$T$3=2027)*Model!$C$37:$T$37) | D2: =SUMPRODUCT((Model!$C$3:$T$3=2028)*Model!$C$37:$T$37) | E2: =SUMPRODUCT((Model!$C$3:$T$3=2029)*Model!$C$37:$T$37) | F2: =SUMPRODUCT((Model!$C$3:$T$3=2030)*Model!$C$37:$T$37)
A3: Adj. EBITDA | B3: =SUMPRODUCT((Model!$C$3:$T$3=2026)*Model!$C$36:$T$36)+Assumptions!$B$124 | C3: =SUMPRODUCT((Model!$C$3:$T$3=2027)*Model!$C$36:$T$36) | D3: =SUMPRODUCT((Model!$C$3:$T$3=2028)*Model!$C$36:$T$36) | E3: =SUMPRODUCT((Model!$C$3:$T$3=2029)*Model!$C$36:$T$36) | F3: =SUMPRODUCT((Model!$C$3:$T$3=2030)*Model!$C$36:$T$36)
A4: Capex | B4: =SUMPRODUCT((Model!$C$3:$T$3=2026)*Model!$C$12:$T$12)+Assumptions!$B$109 | C4: =SUMPRODUCT((Model!$C$3:$T$3=2027)*Model!$C$12:$T$12) | D4: =SUMPRODUCT((Model!$C$3:$T$3=2028)*Model!$C$12:$T$12) | E4: =SUMPRODUCT((Model!$C$3:$T$3=2029)*Model!$C$12:$T$12) | F4: =SUMPRODUCT((Model!$C$3:$T$3=2030)*Model!$C$12:$T$12)
A5: Total D&A at life L1 (FY26 H1 actual at 5y; 4y adds back 86.1) | B5: =SUMPRODUCT((Model!$C$3:$T$3=2026)*Model!$C$22:$T$22)+SUMPRODUCT((Model!$C$3:$T$3=2026)*Model!$C$25:$T$25)+Assumptions!$B$125+Assumptions!$B$126 | C5: =SUMPRODUCT((Model!$C$3:$T$3=2027)*Model!$C$22:$T$22)+SUMPRODUCT((Model!$C$3:$T$3=2027)*Model!$C$25:$T$25) | D5: =SUMPRODUCT((Model!$C$3:$T$3=2028)*Model!$C$22:$T$22)+SUMPRODUCT((Model!$C$3:$T$3=2028)*Model!$C$25:$T$25) | E5: =SUMPRODUCT((Model!$C$3:$T$3=2029)*Model!$C$22:$T$22)+SUMPRODUCT((Model!$C$3:$T$3=2029)*Model!$C$25:$T$25) | F5: =SUMPRODUCT((Model!$C$3:$T$3=2030)*Model!$C$22:$T$22)+SUMPRODUCT((Model!$C$3:$T$3=2030)*Model!$C$25:$T$25)
A6: Total D&A at life L2 (FY26 H1 actual at 5y; 4y adds back 86.1) | B6: =SUMPRODUCT((Model!$C$3:$T$3=2026)*Model!$C$23:$T$23)+SUMPRODUCT((Model!$C$3:$T$3=2026)*Model!$C$25:$T$25)+Assumptions!$B$125 | C6: =SUMPRODUCT((Model!$C$3:$T$3=2027)*Model!$C$23:$T$23)+SUMPRODUCT((Model!$C$3:$T$3=2027)*Model!$C$25:$T$25) | D6: =SUMPRODUCT((Model!$C$3:$T$3=2028)*Model!$C$23:$T$23)+SUMPRODUCT((Model!$C$3:$T$3=2028)*Model!$C$25:$T$25) | E6: =SUMPRODUCT((Model!$C$3:$T$3=2029)*Model!$C$23:$T$23)+SUMPRODUCT((Model!$C$3:$T$3=2029)*Model!$C$25:$T$25) | F6: =SUMPRODUCT((Model!$C$3:$T$3=2030)*Model!$C$23:$T$23)+SUMPRODUCT((Model!$C$3:$T$3=2030)*Model!$C$25:$T$25)
A7: Total D&A at life L3 (FY26 H1 actual at 5y; 4y adds back 86.1) | B7: =SUMPRODUCT((Model!$C$3:$T$3=2026)*Model!$C$24:$T$24)+SUMPRODUCT((Model!$C$3:$T$3=2026)*Model!$C$25:$T$25)+Assumptions!$B$125 | C7: =SUMPRODUCT((Model!$C$3:$T$3=2027)*Model!$C$24:$T$24)+SUMPRODUCT((Model!$C$3:$T$3=2027)*Model!$C$25:$T$25) | D7: =SUMPRODUCT((Model!$C$3:$T$3=2028)*Model!$C$24:$T$24)+SUMPRODUCT((Model!$C$3:$T$3=2028)*Model!$C$25:$T$25) | E7: =SUMPRODUCT((Model!$C$3:$T$3=2029)*Model!$C$24:$T$24)+SUMPRODUCT((Model!$C$3:$T$3=2029)*Model!$C$25:$T$25) | F7: =SUMPRODUCT((Model!$C$3:$T$3=2030)*Model!$C$24:$T$24)+SUMPRODUCT((Model!$C$3:$T$3=2030)*Model!$C$25:$T$25)
A8: EBIT at life L1 | B8: =B3-B5 | C8: =C3-C5 | D8: =D3-D5 | E8: =E3-E5 | F8: =F3-F5
A9: EBIT at life L2 | B9: =B3-B6 | C9: =C3-C6 | D9: =D3-D6 | E9: =E3-E6 | F9: =F3-F6
A10: EBIT at life L3 | B10: =B3-B7 | C10: =C3-C7 | D10: =D3-D7 | E10: =E3-E7 | F10: =F3-F7
A11: EBIT margin at life L1 | B11: =B8/B2 | C11: =C8/C2 | D11: =D8/D2 | E11: =E8/E2 | F11: =F8/F2
A12: EBIT margin at life L2 | B12: =B9/B2 | C12: =C9/C2 | D12: =D9/D2 | E12: =E9/E2 | F12: =F9/F2
A13: EBIT margin at life L3 | B13: =B10/B2 | C13: =C10/C2 | D13: =D10/D2 | E13: =E10/E2 | F13: =F10/F2
A14: EBIT-margin points added by 4->5 yr life change (governance leg) | B14: =(B5-B6)/B2 | C14: =(C5-C6)/C2 | D14: =(D5-D6)/D2 | E14: =(E5-E6)/E2 | F14: =(F5-F6)/F2
A15: FCF (H2 only for 2026) | B15: =SUMPRODUCT((Model!$C$3:$T$3=2026)*Model!$C$47:$T$47) | C15: =SUMPRODUCT((Model!$C$3:$T$3=2027)*Model!$C$47:$T$47) | D15: =SUMPRODUCT((Model!$C$3:$T$3=2028)*Model!$C$47:$T$47) | E15: =SUMPRODUCT((Model!$C$3:$T$3=2029)*Model!$C$47:$T$47) | F15: =SUMPRODUCT((Model!$C$3:$T$3=2030)*Model!$C$47:$T$47)
A16: FCF ex-prepayments (H2 only for 2026) | B16: =SUMPRODUCT((Model!$C$3:$T$3=2026)*Model!$C$48:$T$48) | C16: =SUMPRODUCT((Model!$C$3:$T$3=2027)*Model!$C$48:$T$48) | D16: =SUMPRODUCT((Model!$C$3:$T$3=2028)*Model!$C$48:$T$48) | E16: =SUMPRODUCT((Model!$C$3:$T$3=2029)*Model!$C$48:$T$48) | F16: =SUMPRODUCT((Model!$C$3:$T$3=2030)*Model!$C$48:$T$48)
A17: Liquidity at year end | B17: =INDEX(Model!$C$49:$T$49,MATCH(2026,Model!$C$3:$T$3,1)) | C17: =INDEX(Model!$C$49:$T$49,MATCH(2027,Model!$C$3:$T$3,1)) | D17: =INDEX(Model!$C$49:$T$49,MATCH(2028,Model!$C$3:$T$3,1)) | E17: =INDEX(Model!$C$49:$T$49,MATCH(2029,Model!$C$3:$T$3,1)) | F17: =INDEX(Model!$C$49:$T$49,MATCH(2030,Model!$C$3:$T$3,1))
A18: Bottom-up revenue from billing MW (Rev_MW) | B18: =SUMPRODUCT((RIGHT(Rev_MW!$C$1:$T$1,4)="2026")*Rev_MW!$C$7:$T$7)+Assumptions!$B$123 | C18: =SUMPRODUCT((RIGHT(Rev_MW!$C$1:$T$1,4)="2027")*Rev_MW!$C$7:$T$7) | D18: =SUMPRODUCT((RIGHT(Rev_MW!$C$1:$T$1,4)="2028")*Rev_MW!$C$7:$T$7) | E18: =SUMPRODUCT((RIGHT(Rev_MW!$C$1:$T$1,4)="2029")*Rev_MW!$C$7:$T$7) | F18: =SUMPRODUCT((RIGHT(Rev_MW!$C$1:$T$1,4)="2030")*Rev_MW!$C$7:$T$7)

Sheet Horizons
A1: Metric (quarter at horizon) | B1: 6-month (Q1 2027) | C1: 1-year (Q3 2027) | D1: 3-year (Q3 2029)
A2: Revenue | B2: =Model!E37 | C2: =Model!G37 | D2: =Model!O37
A3: Adj. EBITDA | B3: =Model!E36 | C3: =Model!G36 | D3: =Model!O36
A4: EBIT 4y | B4: =Model!E38 | C4: =Model!G38 | D4: =Model!O38
A5: EBIT 5y | B5: =Model!E39 | C5: =Model!G39 | D5: =Model!O39
A6: EBIT 6y | B6: =Model!E40 | C6: =Model!G40 | D6: =Model!O40
A7: FCF | B7: =Model!E47 | C7: =Model!G47 | D7: =Model!O47
A8: Liquidity | B8: =Model!E49 | C8: =Model!G49 | D8: =Model!O49
A9: Gross GPU billing capital | B9: =Model!E20 | C9: =Model!G20 | D9: =Model!O20
A10: Billing gross MW (Capacity path) | B10: =MW!F25 | C10: =MW!H25 | D10: =MW!P25

Sheet Reverse_DCF
A1: Unlevered DCF EV ($M) by FY29+ EBITDA yield on billing GPU capital (columns) and GPU life (rows). Pre-2029 = consensus. Discounted from Q3'26 at WACC; terminal at Q4'30 run-rate with maintenance capex = capital/life
A2: Life \ yield | B2: 0.1 | C2: 0.15 | D2: 0.2 | E2: 0.25 | F2: 0.3 | G2: 0.35 | H2: 0.4 | I2: 0.45 | J2: 0.5 | K2: 0.55 | L2: 0.6 | M2: 0.65 | N2: 0.7
A3: EV at life L1 | B3: =SUMPRODUCT(((((Model!$C$3:$T$3<=2028))*Model!$C$36:$T$36+((Model!$C$3:$T$3>=2029))*B$2/4*Model!$C$54:$T$54)-Model!$C$12:$T$12-Assumptions!$B$151*(((((Model!$C$3:$T$3<=2028))*Model!$C$36:$T$36+((Model!$C$3:$T$3>=2029))*B$2/4*Model!$C$54:$T$54)-(Model!$C$22:$T$22+Model!$C$25:$T$25))>0)*((((Model!$C$3:$T$3<=2028))*Model!$C$36:$T$36+((Model!$C$3:$T$3>=2029))*B$2/4*Model!$C$54:$T$54)-(Model!$C$22:$T$22+Model!$C$25:$T$25)))*(1+Assumptions!$B$149)^(-(Model!$C$2:$T$2+0.5)/4))+((B$2*Model!$T$20)-Assumptions!$B$151*MAX(0,(B$2*Model!$T$20)-(Model!$T$20/Assumptions!$B$3+Model!$T$21/Assumptions!$B$6))-(Model!$T$20/Assumptions!$B$3+Model!$T$21/Assumptions!$B$6)-Assumptions!$B$150*(Model!$T$20+Model!$T$21))*(1+Assumptions!$B$150)/(Assumptions!$B$149-Assumptions!$B$150)*(1+Assumptions!$B$149)^(-18/4) | C3: =SUMPRODUCT(((((Model!$C$3:$T$3<=2028))*Model!$C$36:$T$36+((Model!$C$3:$T$3>=2029))*C$2/4*Model!$C$54:$T$54)-Model!$C$12:$T$12-Assumptions!$B$151*(((((Model!$C$3:$T$3<=2028))*Model!$C$36:$T$36+((Model!$C$3:$T$3>=2029))*C$2/4*Model!$C$54:$T$54)-(Model!$C$22:$T$22+Model!$C$25:$T$25))>0)*((((Model!$C$3:$T$3<=2028))*Model!$C$36:$T$36+((Model!$C$3:$T$3>=2029))*C$2/4*Model!$C$54:$T$54)-(Model!$C$22:$T$22+Model!$C$25:$T$25)))*(1+Assumptions!$B$149)^(-(Model!$C$2:$T$2+0.5)/4))+((C$2*Model!$T$20)-Assumptions!$B$151*MAX(0,(C$2*Model!$T$20)-(Model!$T$20/Assumptions!$B$3+Model!$T$21/Assumptions!$B$6))-(Model!$T$20/Assumptions!$B$3+Model!$T$21/Assumptions!$B$6)-Assumptions!$B$150*(Model!$T$20+Model!$T$21))*(1+Assumptions!$B$150)/(Assumptions!$B$149-Assumptions!$B$150)*(1+Assumptions!$B$149)^(-18/4) | D3: =SUMPRODUCT(((((Model!$C$3:$T$3<=2028))*Model!$C$36:$T$36+((Model!$C$3:$T$3>=2029))*D$2/4*Model!$C$54:$T$54)-Model!$C$12:$T$12-Assumptions!$B$151*(((((Model!$C$3:$T$3<=2028))*Model!$C$36:$T$36+((Model!$C$3:$T$3>=2029))*D$2/4*Model!$C$54:$T$54)-(Model!$C$22:$T$22+Model!$C$25:$T$25))>0)*((((Model!$C$3:$T$3<=2028))*Model!$C$36:$T$36+((Model!$C$3:$T$3>=2029))*D$2/4*Model!$C$54:$T$54)-(Model!$C$22:$T$22+Model!$C$25:$T$25)))*(1+Assumptions!$B$149)^(-(Model!$C$2:$T$2+0.5)/4))+((D$2*Model!$T$20)-Assumptions!$B$151*MAX(0,(D$2*Model!$T$20)-(Model!$T$20/Assumptions!$B$3+Model!$T$21/Assumptions!$B$6))-(Model!$T$20/Assumptions!$B$3+Model!$T$21/Assumptions!$B$6)-Assumptions!$B$150*(Model!$T$20+Model!$T$21))*(1+Assumptions!$B$150)/(Assumptions!$B$149-Assumptions!$B$150)*(1+Assumptions!$B$149)^(-18/4) | E3: =SUMPRODUCT(((((Model!$C$3:$T$3<=2028))*Model!$C$36:$T$36+((Model!$C$3:$T$3>=2029))*E$2/4*Model!$C$54:$T$54)-Model!$C$12:$T$12-Assumptions!$B$151*(((((Model!$C$3:$T$3<=2028))*Model!$C$36:$T$36+((Model!$C$3:$T$3>=2029))*E$2/4*Model!$C$54:$T$54)-(Model!$C$22:$T$22+Model!$C$25:$T$25))>0)*((((Model!$C$3:$T$3<=2028))*Model!$C$36:$T$36+((Model!$C$3:$T$3>=2029))*E$2/4*Model!$C$54:$T$54)-(Model!$C$22:$T$22+Model!$C$25:$T$25)))*(1+Assumptions!$B$149)^(-(Model!$C$2:$T$2+0.5)/4))+((E$2*Model!$T$20)-Assumptions!$B$151*MAX(0,(E$2*Model!$T$20)-(Model!$T$20/Assumptions!$B$3+Model!$T$21/Assumptions!$B$6))-(Model!$T$20/Assumptions!$B$3+Model!$T$21/Assumptions!$B$6)-Assumptions!$B$150*(Model!$T$20+Model!$T$21))*(1+Assumptions!$B$150)/(Assumptions!$B$149-Assumptions!$B$150)*(1+Assumptions!$B$149)^(-18/4) | F3: =SUMPRODUCT(((((Model!$C$3:$T$3<=2028))*Model!$C$36:$T$36+((Model!$C$3:$T$3>=2029))*F$2/4*Model!$C$54:$T$54)-Model!$C$12:$T$12-Assumptions!$B$151*(((((Model!$C$3:$T$3<=2028))*Model!$C$36:$T$36+((Model!$C$3:$T$3>=2029))*F$2/4*Model!$C$54:$T$54)-(Model!$C$22:$T$22+Model!$C$25:$T$25))>0)*((((Model!$C$3:$T$3<=2028))*Model!$C$36:$T$36+((Model!$C$3:$T$3>=2029))*F$2/4*Model!$C$54:$T$54)-(Model!$C$22:$T$22+Model!$C$25:$T$25)))*(1+Assumptions!$B$149)^(-(Model!$C$2:$T$2+0.5)/4))+((F$2*Model!$T$20)-Assumptions!$B$151*MAX(0,(F$2*Model!$T$20)-(Model!$T$20/Assumptions!$B$3+Model!$T$21/Assumptions!$B$6))-(Model!$T$20/Assumptions!$B$3+Model!$T$21/Assumptions!$B$6)-Assumptions!$B$150*(Model!$T$20+Model!$T$21))*(1+Assumptions!$B$150)/(Assumptions!$B$149-Assumptions!$B$150)*(1+Assumptions!$B$149)^(-18/4) | G3: =SUMPRODUCT(((((Model!$C$3:$T$3<=2028))*Model!$C$36:$T$36+((Model!$C$3:$T$3>=2029))*G$2/4*Model!$C$54:$T$54)-Model!$C$12:$T$12-Assumptions!$B$151*(((((Model!$C$3:$T$3<=2028))*Model!$C$36:$T$36+((Model!$C$3:$T$3>=2029))*G$2/4*Model!$C$54:$T$54)-(Model!$C$22:$T$22+Model!$C$25:$T$25))>0)*((((Model!$C$3:$T$3<=2028))*Model!$C$36:$T$36+((Model!$C$3:$T$3>=2029))*G$2/4*Model!$C$54:$T$54)-(Model!$C$22:$T$22+Model!$C$25:$T$25)))*(1+Assumptions!$B$149)^(-(Model!$C$2:$T$2+0.5)/4))+((G$2*Model!$T$20)-Assumptions!$B$151*MAX(0,(G$2*Model!$T$20)-(Model!$T$20/Assumptions!$B$3+Model!$T$21/Assumptions!$B$6))-(Model!$T$20/Assumptions!$B$3+Model!$T$21/Assumptions!$B$6)-Assumptions!$B$150*(Model!$T$20+Model!$T$21))*(1+Assumptions!$B$150)/(Assumptions!$B$149-Assumptions!$B$150)*(1+Assumptions!$B$149)^(-18/4) | H3: =SUMPRODUCT(((((Model!$C$3:$T$3<=2028))*Model!$C$36:$T$36+((Model!$C$3:$T$3>=2029))*H$2/4*Model!$C$54:$T$54)-Model!$C$12:$T$12-Assumptions!$B$151*(((((Model!$C$3:$T$3<=2028))*Model!$C$36:$T$36+((Model!$C$3:$T$3>=2029))*H$2/4*Model!$C$54:$T$54)-(Model!$C$22:$T$22+Model!$C$25:$T$25))>0)*((((Model!$C$3:$T$3<=2028))*Model!$C$36:$T$36+((Model!$C$3:$T$3>=2029))*H$2/4*Model!$C$54:$T$54)-(Model!$C$22:$T$22+Model!$C$25:$T$25)))*(1+Assumptions!$B$149)^(-(Model!$C$2:$T$2+0.5)/4))+((H$2*Model!$T$20)-Assumptions!$B$151*MAX(0,(H$2*Model!$T$20)-(Model!$T$20/Assumptions!$B$3+Model!$T$21/Assumptions!$B$6))-(Model!$T$20/Assumptions!$B$3+Model!$T$21/Assumptions!$B$6)-Assumptions!$B$150*(Model!$T$20+Model!$T$21))*(1+Assumptions!$B$150)/(Assumptions!$B$149-Assumptions!$B$150)*(1+Assumptions!$B$149)^(-18/4) | I3: =SUMPRODUCT(((((Model!$C$3:$T$3<=2028))*Model!$C$36:$T$36+((Model!$C$3:$T$3>=2029))*I$2/4*Model!$C$54:$T$54)-Model!$C$12:$T$12-Assumptions!$B$151*(((((Model!$C$3:$T$3<=2028))*Model!$C$36:$T$36+((Model!$C$3:$T$3>=2029))*I$2/4*Model!$C$54:$T$54)-(Model!$C$22:$T$22+Model!$C$25:$T$25))>0)*((((Model!$C$3:$T$3<=2028))*Model!$C$36:$T$36+((Model!$C$3:$T$3>=2029))*I$2/4*Model!$C$54:$T$54)-(Model!$C$22:$T$22+Model!$C$25:$T$25)))*(1+Assumptions!$B$149)^(-(Model!$C$2:$T$2+0.5)/4))+((I$2*Model!$T$20)-Assumptions!$B$151*MAX(0,(I$2*Model!$T$20)-(Model!$T$20/Assumptions!$B$3+Model!$T$21/Assumptions!$B$6))-(Model!$T$20/Assumptions!$B$3+Model!$T$21/Assumptions!$B$6)-Assumptions!$B$150*(Model!$T$20+Model!$T$21))*(1+Assumptions!$B$150)/(Assumptions!$B$149-Assumptions!$B$150)*(1+Assumptions!$B$149)^(-18/4) | ... N3: =SUMPRODUCT(((((Model!$C$3:$T$3<=2028))*Model!$C$36:$T$36+((Model!$C$3:$T$3>=2029))*N$2/4*Model!$C$54:$T$54)-Model!$C$12:$T$12-Assumptions!$B$151*(((((Model!$C$3:$T$3<=2028))*Model!$C$36:$T$36+((Model!$C$3:$T$3>=2029))*N$2/4*Model!$C$54:$T$54)-(Model!$C$22:$T$22+Model!$C$25:$T$25))>0)*((((Model!$C$3:$T$3<=2028))*Model!$C$36:$T$36+((Model!$C$3:$T$3>=2029))*N$2/4*Model!$C$54:$T$54)-(Model!$C$22:$T$22+Model!$C$25:$T$25)))*(1+Assumptions!$B$149)^(-(Model!$C$2:$T$2+0.5)/4))+((N$2*Model!$T$20)-Assumptions!$B$151*MAX(0,(N$2*Model!$T$20)-(Model!$T$20/Assumptions!$B$3+Model!$T$21/Assumptions!$B$6))-(Model!$T$20/Assumptions!$B$3+Model!$T$21/Assumptions!$B$6)-Assumptions!$B$150*(Model!$T$20+Model!$T$21))*(1+Assumptions!$B$150)/(Assumptions!$B$149-Assumptions!$B$150)*(1+Assumptions!$B$149)^(-18/4)
A4: EV at life L2 | B4: =SUMPRODUCT(((((Model!$C$3:$T$3<=2028))*Model!$C$36:$T$36+((Model!$C$3:$T$3>=2029))*B$2/4*Model!$C$54:$T$54)-Model!$C$12:$T$12-Assumptions!$B$151*(((((Model!$C$3:$T$3<=2028))*Model!$C$36:$T$36+((Model!$C$3:$T$3>=2029))*B$2/4*Model!$C$54:$T$54)-(Model!$C$23:$T$23+Model!$C$25:$T$25))>0)*((((Model!$C$3:$T$3<=2028))*Model!$C$36:$T$36+((Model!$C$3:$T$3>=2029))*B$2/4*Model!$C$54:$T$54)-(Model!$C$23:$T$23+Model!$C$25:$T$25)))*(1+Assumptions!$B$149)^(-(Model!$C$2:$T$2+0.5)/4))+((B$2*Model!$T$20)-Assumptions!$B$151*MAX(0,(B$2*Model!$T$20)-(Model!$T$20/Assumptions!$B$4+Model!$T$21/Assumptions!$B$6))-(Model!$T$20/Assumptions!$B$4+Model!$T$21/Assumptions!$B$6)-Assumptions!$B$150*(Model!$T$20+Model!$T$21))*(1+Assumptions!$B$150)/(Assumptions!$B$149-Assumptions!$B$150)*(1+Assumptions!$B$149)^(-18/4) | C4: =SUMPRODUCT(((((Model!$C$3:$T$3<=2028))*Model!$C$36:$T$36+((Model!$C$3:$T$3>=2029))*C$2/4*Model!$C$54:$T$54)-Model!$C$12:$T$12-Assumptions!$B$151*(((((Model!$C$3:$T$3<=2028))*Model!$C$36:$T$36+((Model!$C$3:$T$3>=2029))*C$2/4*Model!$C$54:$T$54)-(Model!$C$23:$T$23+Model!$C$25:$T$25))>0)*((((Model!$C$3:$T$3<=2028))*Model!$C$36:$T$36+((Model!$C$3:$T$3>=2029))*C$2/4*Model!$C$54:$T$54)-(Model!$C$23:$T$23+Model!$C$25:$T$25)))*(1+Assumptions!$B$149)^(-(Model!$C$2:$T$2+0.5)/4))+((C$2*Model!$T$20)-Assumptions!$B$151*MAX(0,(C$2*Model!$T$20)-(Model!$T$20/Assumptions!$B$4+Model!$T$21/Assumptions!$B$6))-(Model!$T$20/Assumptions!$B$4+Model!$T$21/Assumptions!$B$6)-Assumptions!$B$150*(Model!$T$20+Model!$T$21))*(1+Assumptions!$B$150)/(Assumptions!$B$149-Assumptions!$B$150)*(1+Assumptions!$B$149)^(-18/4) | D4: =SUMPRODUCT(((((Model!$C$3:$T$3<=2028))*Model!$C$36:$T$36+((Model!$C$3:$T$3>=2029))*D$2/4*Model!$C$54:$T$54)-Model!$C$12:$T$12-Assumptions!$B$151*(((((Model!$C$3:$T$3<=2028))*Model!$C$36:$T$36+((Model!$C$3:$T$3>=2029))*D$2/4*Model!$C$54:$T$54)-(Model!$C$23:$T$23+Model!$C$25:$T$25))>0)*((((Model!$C$3:$T$3<=2028))*Model!$C$36:$T$36+((Model!$C$3:$T$3>=2029))*D$2/4*Model!$C$54:$T$54)-(Model!$C$23:$T$23+Model!$C$25:$T$25)))*(1+Assumptions!$B$149)^(-(Model!$C$2:$T$2+0.5)/4))+((D$2*Model!$T$20)-Assumptions!$B$151*MAX(0,(D$2*Model!$T$20)-(Model!$T$20/Assumptions!$B$4+Model!$T$21/Assumptions!$B$6))-(Model!$T$20/Assumptions!$B$4+Model!$T$21/Assumptions!$B$6)-Assumptions!$B$150*(Model!$T$20+Model!$T$21))*(1+Assumptions!$B$150)/(Assumptions!$B$149-Assumptions!$B$150)*(1+Assumptions!$B$149)^(-18/4) | E4: =SUMPRODUCT(((((Model!$C$3:$T$3<=2028))*Model!$C$36:$T$36+((Model!$C$3:$T$3>=2029))*E$2/4*Model!$C$54:$T$54)-Model!$C$12:$T$12-Assumptions!$B$151*(((((Model!$C$3:$T$3<=2028))*Model!$C$36:$T$36+((Model!$C$3:$T$3>=2029))*E$2/4*Model!$C$54:$T$54)-(Model!$C$23:$T$23+Model!$C$25:$T$25))>0)*((((Model!$C$3:$T$3<=2028))*Model!$C$36:$T$36+((Model!$C$3:$T$3>=2029))*E$2/4*Model!$C$54:$T$54)-(Model!$C$23:$T$23+Model!$C$25:$T$25)))*(1+Assumptions!$B$149)^(-(Model!$C$2:$T$2+0.5)/4))+((E$2*Model!$T$20)-Assumptions!$B$151*MAX(0,(E$2*Model!$T$20)-(Model!$T$20/Assumptions!$B$4+Model!$T$21/Assumptions!$B$6))-(Model!$T$20/Assumptions!$B$4+Model!$T$21/Assumptions!$B$6)-Assumptions!$B$150*(Model!$T$20+Model!$T$21))*(1+Assumptions!$B$150)/(Assumptions!$B$149-Assumptions!$B$150)*(1+Assumptions!$B$149)^(-18/4) | F4: =SUMPRODUCT(((((Model!$C$3:$T$3<=2028))*Model!$C$36:$T$36+((Model!$C$3:$T$3>=2029))*F$2/4*Model!$C$54:$T$54)-Model!$C$12:$T$12-Assumptions!$B$151*(((((Model!$C$3:$T$3<=2028))*Model!$C$36:$T$36+((Model!$C$3:$T$3>=2029))*F$2/4*Model!$C$54:$T$54)-(Model!$C$23:$T$23+Model!$C$25:$T$25))>0)*((((Model!$C$3:$T$3<=2028))*Model!$C$36:$T$36+((Model!$C$3:$T$3>=2029))*F$2/4*Model!$C$54:$T$54)-(Model!$C$23:$T$23+Model!$C$25:$T$25)))*(1+Assumptions!$B$149)^(-(Model!$C$2:$T$2+0.5)/4))+((F$2*Model!$T$20)-Assumptions!$B$151*MAX(0,(F$2*Model!$T$20)-(Model!$T$20/Assumptions!$B$4+Model!$T$21/Assumptions!$B$6))-(Model!$T$20/Assumptions!$B$4+Model!$T$21/Assumptions!$B$6)-Assumptions!$B$150*(Model!$T$20+Model!$T$21))*(1+Assumptions!$B$150)/(Assumptions!$B$149-Assumptions!$B$150)*(1+Assumptions!$B$149)^(-18/4) | G4: =SUMPRODUCT(((((Model!$C$3:$T$3<=2028))*Model!$C$36:$T$36+((Model!$C$3:$T$3>=2029))*G$2/4*Model!$C$54:$T$54)-Model!$C$12:$T$12-Assumptions!$B$151*(((((Model!$C$3:$T$3<=2028))*Model!$C$36:$T$36+((Model!$C$3:$T$3>=2029))*G$2/4*Model!$C$54:$T$54)-(Model!$C$23:$T$23+Model!$C$25:$T$25))>0)*((((Model!$C$3:$T$3<=2028))*Model!$C$36:$T$36+((Model!$C$3:$T$3>=2029))*G$2/4*Model!$C$54:$T$54)-(Model!$C$23:$T$23+Model!$C$25:$T$25)))*(1+Assumptions!$B$149)^(-(Model!$C$2:$T$2+0.5)/4))+((G$2*Model!$T$20)-Assumptions!$B$151*MAX(0,(G$2*Model!$T$20)-(Model!$T$20/Assumptions!$B$4+Model!$T$21/Assumptions!$B$6))-(Model!$T$20/Assumptions!$B$4+Model!$T$21/Assumptions!$B$6)-Assumptions!$B$150*(Model!$T$20+Model!$T$21))*(1+Assumptions!$B$150)/(Assumptions!$B$149-Assumptions!$B$150)*(1+Assumptions!$B$149)^(-18/4) | H4: =SUMPRODUCT(((((Model!$C$3:$T$3<=2028))*Model!$C$36:$T$36+((Model!$C$3:$T$3>=2029))*H$2/4*Model!$C$54:$T$54)-Model!$C$12:$T$12-Assumptions!$B$151*(((((Model!$C$3:$T$3<=2028))*Model!$C$36:$T$36+((Model!$C$3:$T$3>=2029))*H$2/4*Model!$C$54:$T$54)-(Model!$C$23:$T$23+Model!$C$25:$T$25))>0)*((((Model!$C$3:$T$3<=2028))*Model!$C$36:$T$36+((Model!$C$3:$T$3>=2029))*H$2/4*Model!$C$54:$T$54)-(Model!$C$23:$T$23+Model!$C$25:$T$25)))*(1+Assumptions!$B$149)^(-(Model!$C$2:$T$2+0.5)/4))+((H$2*Model!$T$20)-Assumptions!$B$151*MAX(0,(H$2*Model!$T$20)-(Model!$T$20/Assumptions!$B$4+Model!$T$21/Assumptions!$B$6))-(Model!$T$20/Assumptions!$B$4+Model!$T$21/Assumptions!$B$6)-Assumptions!$B$150*(Model!$T$20+Model!$T$21))*(1+Assumptions!$B$150)/(Assumptions!$B$149-Assumptions!$B$150)*(1+Assumptions!$B$149)^(-18/4) | I4: =SUMPRODUCT(((((Model!$C$3:$T$3<=2028))*Model!$C$36:$T$36+((Model!$C$3:$T$3>=2029))*I$2/4*Model!$C$54:$T$54)-Model!$C$12:$T$12-Assumptions!$B$151*(((((Model!$C$3:$T$3<=2028))*Model!$C$36:$T$36+((Model!$C$3:$T$3>=2029))*I$2/4*Model!$C$54:$T$54)-(Model!$C$23:$T$23+Model!$C$25:$T$25))>0)*((((Model!$C$3:$T$3<=2028))*Model!$C$36:$T$36+((Model!$C$3:$T$3>=2029))*I$2/4*Model!$C$54:$T$54)-(Model!$C$23:$T$23+Model!$C$25:$T$25)))*(1+Assumptions!$B$149)^(-(Model!$C$2:$T$2+0.5)/4))+((I$2*Model!$T$20)-Assumptions!$B$151*MAX(0,(I$2*Model!$T$20)-(Model!$T$20/Assumptions!$B$4+Model!$T$21/Assumptions!$B$6))-(Model!$T$20/Assumptions!$B$4+Model!$T$21/Assumptions!$B$6)-Assumptions!$B$150*(Model!$T$20+Model!$T$21))*(1+Assumptions!$B$150)/(Assumptions!$B$149-Assumptions!$B$150)*(1+Assumptions!$B$149)^(-18/4) | ... N4: =SUMPRODUCT(((((Model!$C$3:$T$3<=2028))*Model!$C$36:$T$36+((Model!$C$3:$T$3>=2029))*N$2/4*Model!$C$54:$T$54)-Model!$C$12:$T$12-Assumptions!$B$151*(((((Model!$C$3:$T$3<=2028))*Model!$C$36:$T$36+((Model!$C$3:$T$3>=2029))*N$2/4*Model!$C$54:$T$54)-(Model!$C$23:$T$23+Model!$C$25:$T$25))>0)*((((Model!$C$3:$T$3<=2028))*Model!$C$36:$T$36+((Model!$C$3:$T$3>=2029))*N$2/4*Model!$C$54:$T$54)-(Model!$C$23:$T$23+Model!$C$25:$T$25)))*(1+Assumptions!$B$149)^(-(Model!$C$2:$T$2+0.5)/4))+((N$2*Model!$T$20)-Assumptions!$B$151*MAX(0,(N$2*Model!$T$20)-(Model!$T$20/Assumptions!$B$4+Model!$T$21/Assumptions!$B$6))-(Model!$T$20/Assumptions!$B$4+Model!$T$21/Assumptions!$B$6)-Assumptions!$B$150*(Model!$T$20+Model!$T$21))*(1+Assumptions!$B$150)/(Assumptions!$B$149-Assumptions!$B$150)*(1+Assumptions!$B$149)^(-18/4)
A5: EV at life L3 | B5: =SUMPRODUCT(((((Model!$C$3:$T$3<=2028))*Model!$C$36:$T$36+((Model!$C$3:$T$3>=2029))*B$2/4*Model!$C$54:$T$54)-Model!$C$12:$T$12-Assumptions!$B$151*(((((Model!$C$3:$T$3<=2028))*Model!$C$36:$T$36+((Model!$C$3:$T$3>=2029))*B$2/4*Model!$C$54:$T$54)-(Model!$C$24:$T$24+Model!$C$25:$T$25))>0)*((((Model!$C$3:$T$3<=2028))*Model!$C$36:$T$36+((Model!$C$3:$T$3>=2029))*B$2/4*Model!$C$54:$T$54)-(Model!$C$24:$T$24+Model!$C$25:$T$25)))*(1+Assumptions!$B$149)^(-(Model!$C$2:$T$2+0.5)/4))+((B$2*Model!$T$20)-Assumptions!$B$151*MAX(0,(B$2*Model!$T$20)-(Model!$T$20/Assumptions!$B$5+Model!$T$21/Assumptions!$B$6))-(Model!$T$20/Assumptions!$B$5+Model!$T$21/Assumptions!$B$6)-Assumptions!$B$150*(Model!$T$20+Model!$T$21))*(1+Assumptions!$B$150)/(Assumptions!$B$149-Assumptions!$B$150)*(1+Assumptions!$B$149)^(-18/4) | C5: =SUMPRODUCT(((((Model!$C$3:$T$3<=2028))*Model!$C$36:$T$36+((Model!$C$3:$T$3>=2029))*C$2/4*Model!$C$54:$T$54)-Model!$C$12:$T$12-Assumptions!$B$151*(((((Model!$C$3:$T$3<=2028))*Model!$C$36:$T$36+((Model!$C$3:$T$3>=2029))*C$2/4*Model!$C$54:$T$54)-(Model!$C$24:$T$24+Model!$C$25:$T$25))>0)*((((Model!$C$3:$T$3<=2028))*Model!$C$36:$T$36+((Model!$C$3:$T$3>=2029))*C$2/4*Model!$C$54:$T$54)-(Model!$C$24:$T$24+Model!$C$25:$T$25)))*(1+Assumptions!$B$149)^(-(Model!$C$2:$T$2+0.5)/4))+((C$2*Model!$T$20)-Assumptions!$B$151*MAX(0,(C$2*Model!$T$20)-(Model!$T$20/Assumptions!$B$5+Model!$T$21/Assumptions!$B$6))-(Model!$T$20/Assumptions!$B$5+Model!$T$21/Assumptions!$B$6)-Assumptions!$B$150*(Model!$T$20+Model!$T$21))*(1+Assumptions!$B$150)/(Assumptions!$B$149-Assumptions!$B$150)*(1+Assumptions!$B$149)^(-18/4) | D5: =SUMPRODUCT(((((Model!$C$3:$T$3<=2028))*Model!$C$36:$T$36+((Model!$C$3:$T$3>=2029))*D$2/4*Model!$C$54:$T$54)-Model!$C$12:$T$12-Assumptions!$B$151*(((((Model!$C$3:$T$3<=2028))*Model!$C$36:$T$36+((Model!$C$3:$T$3>=2029))*D$2/4*Model!$C$54:$T$54)-(Model!$C$24:$T$24+Model!$C$25:$T$25))>0)*((((Model!$C$3:$T$3<=2028))*Model!$C$36:$T$36+((Model!$C$3:$T$3>=2029))*D$2/4*Model!$C$54:$T$54)-(Model!$C$24:$T$24+Model!$C$25:$T$25)))*(1+Assumptions!$B$149)^(-(Model!$C$2:$T$2+0.5)/4))+((D$2*Model!$T$20)-Assumptions!$B$151*MAX(0,(D$2*Model!$T$20)-(Model!$T$20/Assumptions!$B$5+Model!$T$21/Assumptions!$B$6))-(Model!$T$20/Assumptions!$B$5+Model!$T$21/Assumptions!$B$6)-Assumptions!$B$150*(Model!$T$20+Model!$T$21))*(1+Assumptions!$B$150)/(Assumptions!$B$149-Assumptions!$B$150)*(1+Assumptions!$B$149)^(-18/4) | E5: =SUMPRODUCT(((((Model!$C$3:$T$3<=2028))*Model!$C$36:$T$36+((Model!$C$3:$T$3>=2029))*E$2/4*Model!$C$54:$T$54)-Model!$C$12:$T$12-Assumptions!$B$151*(((((Model!$C$3:$T$3<=2028))*Model!$C$36:$T$36+((Model!$C$3:$T$3>=2029))*E$2/4*Model!$C$54:$T$54)-(Model!$C$24:$T$24+Model!$C$25:$T$25))>0)*((((Model!$C$3:$T$3<=2028))*Model!$C$36:$T$36+((Model!$C$3:$T$3>=2029))*E$2/4*Model!$C$54:$T$54)-(Model!$C$24:$T$24+Model!$C$25:$T$25)))*(1+Assumptions!$B$149)^(-(Model!$C$2:$T$2+0.5)/4))+((E$2*Model!$T$20)-Assumptions!$B$151*MAX(0,(E$2*Model!$T$20)-(Model!$T$20/Assumptions!$B$5+Model!$T$21/Assumptions!$B$6))-(Model!$T$20/Assumptions!$B$5+Model!$T$21/Assumptions!$B$6)-Assumptions!$B$150*(Model!$T$20+Model!$T$21))*(1+Assumptions!$B$150)/(Assumptions!$B$149-Assumptions!$B$150)*(1+Assumptions!$B$149)^(-18/4) | F5: =SUMPRODUCT(((((Model!$C$3:$T$3<=2028))*Model!$C$36:$T$36+((Model!$C$3:$T$3>=2029))*F$2/4*Model!$C$54:$T$54)-Model!$C$12:$T$12-Assumptions!$B$151*(((((Model!$C$3:$T$3<=2028))*Model!$C$36:$T$36+((Model!$C$3:$T$3>=2029))*F$2/4*Model!$C$54:$T$54)-(Model!$C$24:$T$24+Model!$C$25:$T$25))>0)*((((Model!$C$3:$T$3<=2028))*Model!$C$36:$T$36+((Model!$C$3:$T$3>=2029))*F$2/4*Model!$C$54:$T$54)-(Model!$C$24:$T$24+Model!$C$25:$T$25)))*(1+Assumptions!$B$149)^(-(Model!$C$2:$T$2+0.5)/4))+((F$2*Model!$T$20)-Assumptions!$B$151*MAX(0,(F$2*Model!$T$20)-(Model!$T$20/Assumptions!$B$5+Model!$T$21/Assumptions!$B$6))-(Model!$T$20/Assumptions!$B$5+Model!$T$21/Assumptions!$B$6)-Assumptions!$B$150*(Model!$T$20+Model!$T$21))*(1+Assumptions!$B$150)/(Assumptions!$B$149-Assumptions!$B$150)*(1+Assumptions!$B$149)^(-18/4) | G5: =SUMPRODUCT(((((Model!$C$3:$T$3<=2028))*Model!$C$36:$T$36+((Model!$C$3:$T$3>=2029))*G$2/4*Model!$C$54:$T$54)-Model!$C$12:$T$12-Assumptions!$B$151*(((((Model!$C$3:$T$3<=2028))*Model!$C$36:$T$36+((Model!$C$3:$T$3>=2029))*G$2/4*Model!$C$54:$T$54)-(Model!$C$24:$T$24+Model!$C$25:$T$25))>0)*((((Model!$C$3:$T$3<=2028))*Model!$C$36:$T$36+((Model!$C$3:$T$3>=2029))*G$2/4*Model!$C$54:$T$54)-(Model!$C$24:$T$24+Model!$C$25:$T$25)))*(1+Assumptions!$B$149)^(-(Model!$C$2:$T$2+0.5)/4))+((G$2*Model!$T$20)-Assumptions!$B$151*MAX(0,(G$2*Model!$T$20)-(Model!$T$20/Assumptions!$B$5+Model!$T$21/Assumptions!$B$6))-(Model!$T$20/Assumptions!$B$5+Model!$T$21/Assumptions!$B$6)-Assumptions!$B$150*(Model!$T$20+Model!$T$21))*(1+Assumptions!$B$150)/(Assumptions!$B$149-Assumptions!$B$150)*(1+Assumptions!$B$149)^(-18/4) | H5: =SUMPRODUCT(((((Model!$C$3:$T$3<=2028))*Model!$C$36:$T$36+((Model!$C$3:$T$3>=2029))*H$2/4*Model!$C$54:$T$54)-Model!$C$12:$T$12-Assumptions!$B$151*(((((Model!$C$3:$T$3<=2028))*Model!$C$36:$T$36+((Model!$C$3:$T$3>=2029))*H$2/4*Model!$C$54:$T$54)-(Model!$C$24:$T$24+Model!$C$25:$T$25))>0)*((((Model!$C$3:$T$3<=2028))*Model!$C$36:$T$36+((Model!$C$3:$T$3>=2029))*H$2/4*Model!$C$54:$T$54)-(Model!$C$24:$T$24+Model!$C$25:$T$25)))*(1+Assumptions!$B$149)^(-(Model!$C$2:$T$2+0.5)/4))+((H$2*Model!$T$20)-Assumptions!$B$151*MAX(0,(H$2*Model!$T$20)-(Model!$T$20/Assumptions!$B$5+Model!$T$21/Assumptions!$B$6))-(Model!$T$20/Assumptions!$B$5+Model!$T$21/Assumptions!$B$6)-Assumptions!$B$150*(Model!$T$20+Model!$T$21))*(1+Assumptions!$B$150)/(Assumptions!$B$149-Assumptions!$B$150)*(1+Assumptions!$B$149)^(-18/4) | I5: =SUMPRODUCT(((((Model!$C$3:$T$3<=2028))*Model!$C$36:$T$36+((Model!$C$3:$T$3>=2029))*I$2/4*Model!$C$54:$T$54)-Model!$C$12:$T$12-Assumptions!$B$151*(((((Model!$C$3:$T$3<=2028))*Model!$C$36:$T$36+((Model!$C$3:$T$3>=2029))*I$2/4*Model!$C$54:$T$54)-(Model!$C$24:$T$24+Model!$C$25:$T$25))>0)*((((Model!$C$3:$T$3<=2028))*Model!$C$36:$T$36+((Model!$C$3:$T$3>=2029))*I$2/4*Model!$C$54:$T$54)-(Model!$C$24:$T$24+Model!$C$25:$T$25)))*(1+Assumptions!$B$149)^(-(Model!$C$2:$T$2+0.5)/4))+((I$2*Model!$T$20)-Assumptions!$B$151*MAX(0,(I$2*Model!$T$20)-(Model!$T$20/Assumptions!$B$5+Model!$T$21/Assumptions!$B$6))-(Model!$T$20/Assumptions!$B$5+Model!$T$21/Assumptions!$B$6)-Assumptions!$B$150*(Model!$T$20+Model!$T$21))*(1+Assumptions!$B$150)/(Assumptions!$B$149-Assumptions!$B$150)*(1+Assumptions!$B$149)^(-18/4) | ... N5: =SUMPRODUCT(((((Model!$C$3:$T$3<=2028))*Model!$C$36:$T$36+((Model!$C$3:$T$3>=2029))*N$2/4*Model!$C$54:$T$54)-Model!$C$12:$T$12-Assumptions!$B$151*(((((Model!$C$3:$T$3<=2028))*Model!$C$36:$T$36+((Model!$C$3:$T$3>=2029))*N$2/4*Model!$C$54:$T$54)-(Model!$C$24:$T$24+Model!$C$25:$T$25))>0)*((((Model!$C$3:$T$3<=2028))*Model!$C$36:$T$36+((Model!$C$3:$T$3>=2029))*N$2/4*Model!$C$54:$T$54)-(Model!$C$24:$T$24+Model!$C$25:$T$25)))*(1+Assumptions!$B$149)^(-(Model!$C$2:$T$2+0.5)/4))+((N$2*Model!$T$20)-Assumptions!$B$151*MAX(0,(N$2*Model!$T$20)-(Model!$T$20/Assumptions!$B$5+Model!$T$21/Assumptions!$B$6))-(Model!$T$20/Assumptions!$B$5+Model!$T$21/Assumptions!$B$6)-Assumptions!$B$150*(Model!$T$20+Model!$T$21))*(1+Assumptions!$B$150)/(Assumptions!$B$149-Assumptions!$B$150)*(1+Assumptions!$B$149)^(-18/4)
A7: Market EV (ex-leases) | B7: =Assumptions!$B$152
A8: Market EV incl. off-BS commitments (debt-like variant) | B8: =Assumptions!$B$159
A10: Life | B10: Implied FY29+ yield (market EV) | C10: Implied yield (EV incl. off-BS) | D10: FY28 yield on billing capital (v2 default) | E10: FY28 yield in service (v1 basis) | F10: EV at v2 default yield | G10: Value gap $/share at v2 yield (308.69M sh) | H10: EV at v1-basis yield | I10: Value gap $/share at v1 yield
A11: =Assumptions!B3 | B11: =IFERROR(INDEX($B$2:$N$2,MATCH($B$7,$B$3:$N$3,1))+($B$7-INDEX($B$3:$N$3,MATCH($B$7,$B$3:$N$3,1)))*(INDEX($B$2:$N$2,MATCH($B$7,$B$3:$N$3,1)+1)-INDEX($B$2:$N$2,MATCH($B$7,$B$3:$N$3,1)))/(INDEX($B$3:$N$3,MATCH($B$7,$B$3:$N$3,1)+1)-INDEX($B$3:$N$3,MATCH($B$7,$B$3:$N$3,1))),IF($B$7<$B$3,"<10%",">70%")) | C11: =IFERROR(INDEX($B$2:$N$2,MATCH($B$8,$B$3:$N$3,1))+($B$8-INDEX($B$3:$N$3,MATCH($B$8,$B$3:$N$3,1)))*(INDEX($B$2:$N$2,MATCH($B$8,$B$3:$N$3,1)+1)-INDEX($B$2:$N$2,MATCH($B$8,$B$3:$N$3,1)))/(INDEX($B$3:$N$3,MATCH($B$8,$B$3:$N$3,1)+1)-INDEX($B$3:$N$3,MATCH($B$8,$B$3:$N$3,1))),IF($B$8<$B$3,"<10%",">70%")) | D11: =Model!B30 | E11: =Model!B29 | F11: =(INDEX($B$3:$N$3,MIN(12,MAX(1,MATCH(D11,$B$2:$N$2,1))))+(D11-INDEX($B$2:$N$2,MIN(12,MAX(1,MATCH(D11,$B$2:$N$2,1)))))*(INDEX($B$3:$N$3,MIN(12,MAX(1,MATCH(D11,$B$2:$N$2,1)))+1)-INDEX($B$3:$N$3,MIN(12,MAX(1,MATCH(D11,$B$2:$N$2,1)))))/(INDEX($B$2:$N$2,MIN(12,MAX(1,MATCH(D11,$B$2:$N$2,1)))+1)-INDEX($B$2:$N$2,MIN(12,MAX(1,MATCH(D11,$B$2:$N$2,1)))))) | G11: =(F11-$B$7)/Assumptions!$B$154 | H11: =(INDEX($B$3:$N$3,MIN(12,MAX(1,MATCH(E11,$B$2:$N$2,1))))+(E11-INDEX($B$2:$N$2,MIN(12,MAX(1,MATCH(E11,$B$2:$N$2,1)))))*(INDEX($B$3:$N$3,MIN(12,MAX(1,MATCH(E11,$B$2:$N$2,1)))+1)-INDEX($B$3:$N$3,MIN(12,MAX(1,MATCH(E11,$B$2:$N$2,1)))))/(INDEX($B$2:$N$2,MIN(12,MAX(1,MATCH(E11,$B$2:$N$2,1)))+1)-INDEX($B$2:$N$2,MIN(12,MAX(1,MATCH(E11,$B$2:$N$2,1)))))) | I11: =(H11-$B$7)/Assumptions!$B$154
A12: =Assumptions!B4 | B12: =IFERROR(INDEX($B$2:$N$2,MATCH($B$7,$B$4:$N$4,1))+($B$7-INDEX($B$4:$N$4,MATCH($B$7,$B$4:$N$4,1)))*(INDEX($B$2:$N$2,MATCH($B$7,$B$4:$N$4,1)+1)-INDEX($B$2:$N$2,MATCH($B$7,$B$4:$N$4,1)))/(INDEX($B$4:$N$4,MATCH($B$7,$B$4:$N$4,1)+1)-INDEX($B$4:$N$4,MATCH($B$7,$B$4:$N$4,1))),IF($B$7<$B$4,"<10%",">70%")) | C12: =IFERROR(INDEX($B$2:$N$2,MATCH($B$8,$B$4:$N$4,1))+($B$8-INDEX($B$4:$N$4,MATCH($B$8,$B$4:$N$4,1)))*(INDEX($B$2:$N$2,MATCH($B$8,$B$4:$N$4,1)+1)-INDEX($B$2:$N$2,MATCH($B$8,$B$4:$N$4,1)))/(INDEX($B$4:$N$4,MATCH($B$8,$B$4:$N$4,1)+1)-INDEX($B$4:$N$4,MATCH($B$8,$B$4:$N$4,1))),IF($B$8<$B$4,"<10%",">70%")) | D12: =Model!B30 | E12: =Model!B29 | F12: =(INDEX($B$4:$N$4,MIN(12,MAX(1,MATCH(D12,$B$2:$N$2,1))))+(D12-INDEX($B$2:$N$2,MIN(12,MAX(1,MATCH(D12,$B$2:$N$2,1)))))*(INDEX($B$4:$N$4,MIN(12,MAX(1,MATCH(D12,$B$2:$N$2,1)))+1)-INDEX($B$4:$N$4,MIN(12,MAX(1,MATCH(D12,$B$2:$N$2,1)))))/(INDEX($B$2:$N$2,MIN(12,MAX(1,MATCH(D12,$B$2:$N$2,1)))+1)-INDEX($B$2:$N$2,MIN(12,MAX(1,MATCH(D12,$B$2:$N$2,1)))))) | G12: =(F12-$B$7)/Assumptions!$B$154 | H12: =(INDEX($B$4:$N$4,MIN(12,MAX(1,MATCH(E12,$B$2:$N$2,1))))+(E12-INDEX($B$2:$N$2,MIN(12,MAX(1,MATCH(E12,$B$2:$N$2,1)))))*(INDEX($B$4:$N$4,MIN(12,MAX(1,MATCH(E12,$B$2:$N$2,1)))+1)-INDEX($B$4:$N$4,MIN(12,MAX(1,MATCH(E12,$B$2:$N$2,1)))))/(INDEX($B$2:$N$2,MIN(12,MAX(1,MATCH(E12,$B$2:$N$2,1)))+1)-INDEX($B$2:$N$2,MIN(12,MAX(1,MATCH(E12,$B$2:$N$2,1)))))) | I12: =(H12-$B$7)/Assumptions!$B$154
A13: =Assumptions!B5 | B13: =IFERROR(INDEX($B$2:$N$2,MATCH($B$7,$B$5:$N$5,1))+($B$7-INDEX($B$5:$N$5,MATCH($B$7,$B$5:$N$5,1)))*(INDEX($B$2:$N$2,MATCH($B$7,$B$5:$N$5,1)+1)-INDEX($B$2:$N$2,MATCH($B$7,$B$5:$N$5,1)))/(INDEX($B$5:$N$5,MATCH($B$7,$B$5:$N$5,1)+1)-INDEX($B$5:$N$5,MATCH($B$7,$B$5:$N$5,1))),IF($B$7<$B$5,"<10%",">70%")) | C13: =IFERROR(INDEX($B$2:$N$2,MATCH($B$8,$B$5:$N$5,1))+($B$8-INDEX($B$5:$N$5,MATCH($B$8,$B$5:$N$5,1)))*(INDEX($B$2:$N$2,MATCH($B$8,$B$5:$N$5,1)+1)-INDEX($B$2:$N$2,MATCH($B$8,$B$5:$N$5,1)))/(INDEX($B$5:$N$5,MATCH($B$8,$B$5:$N$5,1)+1)-INDEX($B$5:$N$5,MATCH($B$8,$B$5:$N$5,1))),IF($B$8<$B$5,"<10%",">70%")) | D13: =Model!B30 | E13: =Model!B29 | F13: =(INDEX($B$5:$N$5,MIN(12,MAX(1,MATCH(D13,$B$2:$N$2,1))))+(D13-INDEX($B$2:$N$2,MIN(12,MAX(1,MATCH(D13,$B$2:$N$2,1)))))*(INDEX($B$5:$N$5,MIN(12,MAX(1,MATCH(D13,$B$2:$N$2,1)))+1)-INDEX($B$5:$N$5,MIN(12,MAX(1,MATCH(D13,$B$2:$N$2,1)))))/(INDEX($B$2:$N$2,MIN(12,MAX(1,MATCH(D13,$B$2:$N$2,1)))+1)-INDEX($B$2:$N$2,MIN(12,MAX(1,MATCH(D13,$B$2:$N$2,1)))))) | G13: =(F13-$B$7)/Assumptions!$B$154 | H13: =(INDEX($B$5:$N$5,MIN(12,MAX(1,MATCH(E13,$B$2:$N$2,1))))+(E13-INDEX($B$2:$N$2,MIN(12,MAX(1,MATCH(E13,$B$2:$N$2,1)))))*(INDEX($B$5:$N$5,MIN(12,MAX(1,MATCH(E13,$B$2:$N$2,1)))+1)-INDEX($B$5:$N$5,MIN(12,MAX(1,MATCH(E13,$B$2:$N$2,1)))))/(INDEX($B$2:$N$2,MIN(12,MAX(1,MATCH(E13,$B$2:$N$2,1)))+1)-INDEX($B$2:$N$2,MIN(12,MAX(1,MATCH(E13,$B$2:$N$2,1)))))) | I13: =(H13-$B$7)/Assumptions!$B$154
A15: Note: off-BS variant compares an EBITDA-after-rent-and-power DCF with an EV that also counts lease/energy commitments - directionally conservative (double-counts), shown as a bound only.

Sheet Cohorts
A1: Case | B1: Cohort | C1: ACV $M/gross MW-yr | D1: Owned (1)/Leased (0) | E1: GPU life (yrs) | F1: Contract term (yrs) | G1: Capex $M/gross MW | H1: Contract EBITDA margin | I1: Project CF yr0 | J1: Project CF yr1 | K1: Project CF yr2 | L1: Project CF yr3 | M1: Project CF yr4 | N1: Project CF yr5 | O1: Project CF yr6 | P1: Project IRR | Q1: Project payback (yrs) | R1: Project NPV @WACC | S1: Breakeven EBITDA margin (NPV=0) | T1: Accounting breakeven margin (D&A/ACV) | U1: Prepayment $M/MW (prepaid deal) | V1: Equity CF yr0 | W1: Equity CF yr1 | X1: Equity CF yr2 | Y1: Equity CF yr3 | Z1: Equity CF yr4 | AA1: Equity CF yr5 | AB1: Equity CF yr6 | AC1: Equity IRR (prepaid deal) | AD1: Equity payback (yrs) | AE1: cumP0 | AF1: cumP1 | AG1: cumP2 | AH1: cumP3 | AI1: cumP4 | AJ1: cumP5 | AK1: cumP6 | AL1: cumE0 | AM1: cumE1 | AN1: cumE2 | AO1: cumE3 | AP1: cumE4 | AQ1: cumE5 | AR1: cumE6
A2: 1 | B2: Installed book ($12M, Hopper-era capex) | C2: =Assumptions!$B$44*(1-0) | D2: 1 | E2: =Assumptions!$B$3 | F2: =Assumptions!$B$50 | G2: =IF(D2=1,Assumptions!$B$9+Assumptions!$B$10,Assumptions!$B$11)/Assumptions!$B$33 | H2: =1-Assumptions!$B$42-(Assumptions!$B$38+(1-D2)*Assumptions!$B$39/Assumptions!$B$33)/C2 | I2: =-G2 | J2: =IF(1>E2,0,IF(1<=F2,C2,MIN(C2,Assumptions!$B$77)*INDEX(Assumptions!$B$71:$B$76,1)*Assumptions!$B$58))-IF(1>E2,0,IF(1>E2,0,IF(1<=F2,C2,MIN(C2,Assumptions!$B$77)*INDEX(Assumptions!$B$71:$B$76,1)*Assumptions!$B$58))*Assumptions!$B$42+Assumptions!$B$38*IF(1<=F2,1,Assumptions!$B$58)+(1-D2)*Assumptions!$B$39/Assumptions!$B$33)+IF(1=E2,D2*Assumptions!$B$10/Assumptions!$B$33*MAX(0,1-E2/Assumptions!$B$6),0) | K2: =IF(2>E2,0,IF(2<=F2,C2,MIN(C2,Assumptions!$B$77)*INDEX(Assumptions!$B$71:$B$76,2)*Assumptions!$B$58))-IF(2>E2,0,IF(2>E2,0,IF(2<=F2,C2,MIN(C2,Assumptions!$B$77)*INDEX(Assumptions!$B$71:$B$76,2)*Assumptions!$B$58))*Assumptions!$B$42+Assumptions!$B$38*IF(2<=F2,1,Assumptions!$B$58)+(1-D2)*Assumptions!$B$39/Assumptions!$B$33)+IF(2=E2,D2*Assumptions!$B$10/Assumptions!$B$33*MAX(0,1-E2/Assumptions!$B$6),0) | L2: =IF(3>E2,0,IF(3<=F2,C2,MIN(C2,Assumptions!$B$77)*INDEX(Assumptions!$B$71:$B$76,3)*Assumptions!$B$58))-IF(3>E2,0,IF(3>E2,0,IF(3<=F2,C2,MIN(C2,Assumptions!$B$77)*INDEX(Assumptions!$B$71:$B$76,3)*Assumptions!$B$58))*Assumptions!$B$42+Assumptions!$B$38*IF(3<=F2,1,Assumptions!$B$58)+(1-D2)*Assumptions!$B$39/Assumptions!$B$33)+IF(3=E2,D2*Assumptions!$B$10/Assumptions!$B$33*MAX(0,1-E2/Assumptions!$B$6),0) | M2: =IF(4>E2,0,IF(4<=F2,C2,MIN(C2,Assumptions!$B$77)*INDEX(Assumptions!$B$71:$B$76,4)*Assumptions!$B$58))-IF(4>E2,0,IF(4>E2,0,IF(4<=F2,C2,MIN(C2,Assumptions!$B$77)*INDEX(Assumptions!$B$71:$B$76,4)*Assumptions!$B$58))*Assumptions!$B$42+Assumptions!$B$38*IF(4<=F2,1,Assumptions!$B$58)+(1-D2)*Assumptions!$B$39/Assumptions!$B$33)+IF(4=E2,D2*Assumptions!$B$10/Assumptions!$B$33*MAX(0,1-E2/Assumptions!$B$6),0) | N2: =IF(5>E2,0,IF(5<=F2,C2,MIN(C2,Assumptions!$B$77)*INDEX(Assumptions!$B$71:$B$76,5)*Assumptions!$B$58))-IF(5>E2,0,IF(5>E2,0,IF(5<=F2,C2,MIN(C2,Assumptions!$B$77)*INDEX(Assumptions!$B$71:$B$76,5)*Assumptions!$B$58))*Assumptions!$B$42+Assumptions!$B$38*IF(5<=F2,1,Assumptions!$B$58)+(1-D2)*Assumptions!$B$39/Assumptions!$B$33)+IF(5=E2,D2*Assumptions!$B$10/Assumptions!$B$33*MAX(0,1-E2/Assumptions!$B$6),0) | O2: =IF(6>E2,0,IF(6<=F2,C2,MIN(C2,Assumptions!$B$77)*INDEX(Assumptions!$B$71:$B$76,6)*Assumptions!$B$58))-IF(6>E2,0,IF(6>E2,0,IF(6<=F2,C2,MIN(C2,Assumptions!$B$77)*INDEX(Assumptions!$B$71:$B$76,6)*Assumptions!$B$58))*Assumptions!$B$42+Assumptions!$B$38*IF(6<=F2,1,Assumptions!$B$58)+(1-D2)*Assumptions!$B$39/Assumptions!$B$33)+IF(6=E2,D2*Assumptions!$B$10/Assumptions!$B$33*MAX(0,1-E2/Assumptions!$B$6),0) | P2: =IFERROR(IRR(I2:O2),-1) | Q2: =IFERROR(MATCH(TRUE,INDEX(AE2:AK2>=0,0),0)-2+(-INDEX(AE2:AK2,MATCH(TRUE,INDEX(AE2:AK2>=0,0),0)-1))/INDEX(I2:O2,MATCH(TRUE,INDEX(AE2:AK2>=0,0),0)),"never") | R2: =NPV(Assumptions!$B$149,J2:O2)+I2 | S2: =(G2-D2*Assumptions!$B$10/Assumptions!$B$33*MAX(0,1-E2/Assumptions!$B$6)/(1+Assumptions!$B$149)^E2)/(IF(1>E2,0,IF(1<=F2,C2,MIN(C2,Assumptions!$B$77)*INDEX(Assumptions!$B$71:$B$76,1)*Assumptions!$B$58))/(1+Assumptions!$B$149)^1+IF(2>E2,0,IF(2<=F2,C2,MIN(C2,Assumptions!$B$77)*INDEX(Assumptions!$B$71:$B$76,2)*Assumptions!$B$58))/(1+Assumptions!$B$149)^2+IF(3>E2,0,IF(3<=F2,C2,MIN(C2,Assumptions!$B$77)*INDEX(Assumptions!$B$71:$B$76,3)*Assumptions!$B$58))/(1+Assumptions!$B$149)^3+IF(4>E2,0,IF(4<=F2,C2,MIN(C2,Assumptions!$B$77)*INDEX(Assumptions!$B$71:$B$76,4)*Assumptions!$B$58))/(1+Assumptions!$B$149)^4+IF(5>E2,0,IF(5<=F2,C2,MIN(C2,Assumptions!$B$77)*INDEX(Assumptions!$B$71:$B$76,5)*Assumptions!$B$58))/(1+Assumptions!$B$149)^5+IF(6>E2,0,IF(6<=F2,C2,MIN(C2,Assumptions!$B$77)*INDEX(Assumptions!$B$71:$B$76,6)*Assumptions!$B$58))/(1+Assumptions!$B$149)^6) | T2: =(IF(D2=1,Assumptions!$B$9/E2+Assumptions!$B$10/Assumptions!$B$6,Assumptions!$B$9/E2+(Assumptions!$B$11-Assumptions!$B$9)/Assumptions!$B$6)/Assumptions!$B$33)/C2 | U2: =Assumptions!$B$54*G2 | V2: =I2+U2 | W2: =J2-IF(1<=F2,$U2/F2,0) | X2: =K2-IF(2<=F2,$U2/F2,0) | Y2: =L2-IF(3<=F2,$U2/F2,0) | Z2: =M2-IF(4<=F2,$U2/F2,0) | AA2: =N2-IF(5<=F2,$U2/F2,0) | AB2: =O2-IF(6<=F2,$U2/F2,0) | AC2: =IFERROR(IRR(V2:AB2),IF(V2>=0,"no equity at risk",-1)) | AD2: =IFERROR(MATCH(TRUE,INDEX(AL2:AR2>=0,0),0)-2+(-INDEX(AL2:AR2,MATCH(TRUE,INDEX(AL2:AR2>=0,0),0)-1))/INDEX(V2:AB2,MATCH(TRUE,INDEX(AL2:AR2>=0,0),0)),"never") | AE2: =SUM($I2:I2) | AF2: =SUM($I2:J2) | AG2: =SUM($I2:K2) | AH2: =SUM($I2:L2) | AI2: =SUM($I2:M2) | AJ2: =SUM($I2:N2) | AK2: =SUM($I2:O2) | AL2: =SUM($V2:V2) | AM2: =SUM($V2:W2) | AN2: =SUM($V2:X2) | AO2: =SUM($V2:Y2) | AP2: =SUM($V2:Z2) | AQ2: =SUM($V2:AA2) | AR2: =SUM($V2:AB2)
A3: 2 | B3: Installed book ($12M, Hopper-era capex) | C3: =Assumptions!$B$44*(1-0) | D3: 1 | E3: =Assumptions!$B$4 | F3: =Assumptions!$B$50 | G3: =IF(D3=1,Assumptions!$B$9+Assumptions!$B$10,Assumptions!$B$11)/Assumptions!$B$33 | H3: =1-Assumptions!$B$42-(Assumptions!$B$38+(1-D3)*Assumptions!$B$39/Assumptions!$B$33)/C3 | I3: =-G3 | J3: =IF(1>E3,0,IF(1<=F3,C3,MIN(C3,Assumptions!$B$77)*INDEX(Assumptions!$B$71:$B$76,1)*Assumptions!$B$58))-IF(1>E3,0,IF(1>E3,0,IF(1<=F3,C3,MIN(C3,Assumptions!$B$77)*INDEX(Assumptions!$B$71:$B$76,1)*Assumptions!$B$58))*Assumptions!$B$42+Assumptions!$B$38*IF(1<=F3,1,Assumptions!$B$58)+(1-D3)*Assumptions!$B$39/Assumptions!$B$33)+IF(1=E3,D3*Assumptions!$B$10/Assumptions!$B$33*MAX(0,1-E3/Assumptions!$B$6),0) | K3: =IF(2>E3,0,IF(2<=F3,C3,MIN(C3,Assumptions!$B$77)*INDEX(Assumptions!$B$71:$B$76,2)*Assumptions!$B$58))-IF(2>E3,0,IF(2>E3,0,IF(2<=F3,C3,MIN(C3,Assumptions!$B$77)*INDEX(Assumptions!$B$71:$B$76,2)*Assumptions!$B$58))*Assumptions!$B$42+Assumptions!$B$38*IF(2<=F3,1,Assumptions!$B$58)+(1-D3)*Assumptions!$B$39/Assumptions!$B$33)+IF(2=E3,D3*Assumptions!$B$10/Assumptions!$B$33*MAX(0,1-E3/Assumptions!$B$6),0) | L3: =IF(3>E3,0,IF(3<=F3,C3,MIN(C3,Assumptions!$B$77)*INDEX(Assumptions!$B$71:$B$76,3)*Assumptions!$B$58))-IF(3>E3,0,IF(3>E3,0,IF(3<=F3,C3,MIN(C3,Assumptions!$B$77)*INDEX(Assumptions!$B$71:$B$76,3)*Assumptions!$B$58))*Assumptions!$B$42+Assumptions!$B$38*IF(3<=F3,1,Assumptions!$B$58)+(1-D3)*Assumptions!$B$39/Assumptions!$B$33)+IF(3=E3,D3*Assumptions!$B$10/Assumptions!$B$33*MAX(0,1-E3/Assumptions!$B$6),0) | M3: =IF(4>E3,0,IF(4<=F3,C3,MIN(C3,Assumptions!$B$77)*INDEX(Assumptions!$B$71:$B$76,4)*Assumptions!$B$58))-IF(4>E3,0,IF(4>E3,0,IF(4<=F3,C3,MIN(C3,Assumptions!$B$77)*INDEX(Assumptions!$B$71:$B$76,4)*Assumptions!$B$58))*Assumptions!$B$42+Assumptions!$B$38*IF(4<=F3,1,Assumptions!$B$58)+(1-D3)*Assumptions!$B$39/Assumptions!$B$33)+IF(4=E3,D3*Assumptions!$B$10/Assumptions!$B$33*MAX(0,1-E3/Assumptions!$B$6),0) | N3: =IF(5>E3,0,IF(5<=F3,C3,MIN(C3,Assumptions!$B$77)*INDEX(Assumptions!$B$71:$B$76,5)*Assumptions!$B$58))-IF(5>E3,0,IF(5>E3,0,IF(5<=F3,C3,MIN(C3,Assumptions!$B$77)*INDEX(Assumptions!$B$71:$B$76,5)*Assumptions!$B$58))*Assumptions!$B$42+Assumptions!$B$38*IF(5<=F3,1,Assumptions!$B$58)+(1-D3)*Assumptions!$B$39/Assumptions!$B$33)+IF(5=E3,D3*Assumptions!$B$10/Assumptions!$B$33*MAX(0,1-E3/Assumptions!$B$6),0) | O3: =IF(6>E3,0,IF(6<=F3,C3,MIN(C3,Assumptions!$B$77)*INDEX(Assumptions!$B$71:$B$76,6)*Assumptions!$B$58))-IF(6>E3,0,IF(6>E3,0,IF(6<=F3,C3,MIN(C3,Assumptions!$B$77)*INDEX(Assumptions!$B$71:$B$76,6)*Assumptions!$B$58))*Assumptions!$B$42+Assumptions!$B$38*IF(6<=F3,1,Assumptions!$B$58)+(1-D3)*Assumptions!$B$39/Assumptions!$B$33)+IF(6=E3,D3*Assumptions!$B$10/Assumptions!$B$33*MAX(0,1-E3/Assumptions!$B$6),0) | P3: =IFERROR(IRR(I3:O3),-1) | Q3: =IFERROR(MATCH(TRUE,INDEX(AE3:AK3>=0,0),0)-2+(-INDEX(AE3:AK3,MATCH(TRUE,INDEX(AE3:AK3>=0,0),0)-1))/INDEX(I3:O3,MATCH(TRUE,INDEX(AE3:AK3>=0,0),0)),"never") | R3: =NPV(Assumptions!$B$149,J3:O3)+I3 | S3: =(G3-D3*Assumptions!$B$10/Assumptions!$B$33*MAX(0,1-E3/Assumptions!$B$6)/(1+Assumptions!$B$149)^E3)/(IF(1>E3,0,IF(1<=F3,C3,MIN(C3,Assumptions!$B$77)*INDEX(Assumptions!$B$71:$B$76,1)*Assumptions!$B$58))/(1+Assumptions!$B$149)^1+IF(2>E3,0,IF(2<=F3,C3,MIN(C3,Assumptions!$B$77)*INDEX(Assumptions!$B$71:$B$76,2)*Assumptions!$B$58))/(1+Assumptions!$B$149)^2+IF(3>E3,0,IF(3<=F3,C3,MIN(C3,Assumptions!$B$77)*INDEX(Assumptions!$B$71:$B$76,3)*Assumptions!$B$58))/(1+Assumptions!$B$149)^3+IF(4>E3,0,IF(4<=F3,C3,MIN(C3,Assumptions!$B$77)*INDEX(Assumptions!$B$71:$B$76,4)*Assumptions!$B$58))/(1+Assumptions!$B$149)^4+IF(5>E3,0,IF(5<=F3,C3,MIN(C3,Assumptions!$B$77)*INDEX(Assumptions!$B$71:$B$76,5)*Assumptions!$B$58))/(1+Assumptions!$B$149)^5+IF(6>E3,0,IF(6<=F3,C3,MIN(C3,Assumptions!$B$77)*INDEX(Assumptions!$B$71:$B$76,6)*Assumptions!$B$58))/(1+Assumptions!$B$149)^6) | T3: =(IF(D3=1,Assumptions!$B$9/E3+Assumptions!$B$10/Assumptions!$B$6,Assumptions!$B$9/E3+(Assumptions!$B$11-Assumptions!$B$9)/Assumptions!$B$6)/Assumptions!$B$33)/C3 | U3: =Assumptions!$B$54*G3 | V3: =I3+U3 | W3: =J3-IF(1<=F3,$U3/F3,0) | X3: =K3-IF(2<=F3,$U3/F3,0) | Y3: =L3-IF(3<=F3,$U3/F3,0) | Z3: =M3-IF(4<=F3,$U3/F3,0) | AA3: =N3-IF(5<=F3,$U3/F3,0) | AB3: =O3-IF(6<=F3,$U3/F3,0) | AC3: =IFERROR(IRR(V3:AB3),IF(V3>=0,"no equity at risk",-1)) | AD3: =IFERROR(MATCH(TRUE,INDEX(AL3:AR3>=0,0),0)-2+(-INDEX(AL3:AR3,MATCH(TRUE,INDEX(AL3:AR3>=0,0),0)-1))/INDEX(V3:AB3,MATCH(TRUE,INDEX(AL3:AR3>=0,0),0)),"never") | AE3: =SUM($I3:I3) | AF3: =SUM($I3:J3) | AG3: =SUM($I3:K3) | AH3: =SUM($I3:L3) | AI3: =SUM($I3:M3) | AJ3: =SUM($I3:N3) | AK3: =SUM($I3:O3) | AL3: =SUM($V3:V3) | AM3: =SUM($V3:W3) | AN3: =SUM($V3:X3) | AO3: =SUM($V3:Y3) | AP3: =SUM($V3:Z3) | AQ3: =SUM($V3:AA3) | AR3: =SUM($V3:AB3)
A4: 3 | B4: Installed book ($12M, Hopper-era capex) | C4: =Assumptions!$B$44*(1-0) | D4: 1 | E4: =Assumptions!$B$5 | F4: =Assumptions!$B$50 | G4: =IF(D4=1,Assumptions!$B$9+Assumptions!$B$10,Assumptions!$B$11)/Assumptions!$B$33 | H4: =1-Assumptions!$B$42-(Assumptions!$B$38+(1-D4)*Assumptions!$B$39/Assumptions!$B$33)/C4 | I4: =-G4 | J4: =IF(1>E4,0,IF(1<=F4,C4,MIN(C4,Assumptions!$B$77)*INDEX(Assumptions!$B$71:$B$76,1)*Assumptions!$B$58))-IF(1>E4,0,IF(1>E4,0,IF(1<=F4,C4,MIN(C4,Assumptions!$B$77)*INDEX(Assumptions!$B$71:$B$76,1)*Assumptions!$B$58))*Assumptions!$B$42+Assumptions!$B$38*IF(1<=F4,1,Assumptions!$B$58)+(1-D4)*Assumptions!$B$39/Assumptions!$B$33)+IF(1=E4,D4*Assumptions!$B$10/Assumptions!$B$33*MAX(0,1-E4/Assumptions!$B$6),0) | K4: =IF(2>E4,0,IF(2<=F4,C4,MIN(C4,Assumptions!$B$77)*INDEX(Assumptions!$B$71:$B$76,2)*Assumptions!$B$58))-IF(2>E4,0,IF(2>E4,0,IF(2<=F4,C4,MIN(C4,Assumptions!$B$77)*INDEX(Assumptions!$B$71:$B$76,2)*Assumptions!$B$58))*Assumptions!$B$42+Assumptions!$B$38*IF(2<=F4,1,Assumptions!$B$58)+(1-D4)*Assumptions!$B$39/Assumptions!$B$33)+IF(2=E4,D4*Assumptions!$B$10/Assumptions!$B$33*MAX(0,1-E4/Assumptions!$B$6),0) | L4: =IF(3>E4,0,IF(3<=F4,C4,MIN(C4,Assumptions!$B$77)*INDEX(Assumptions!$B$71:$B$76,3)*Assumptions!$B$58))-IF(3>E4,0,IF(3>E4,0,IF(3<=F4,C4,MIN(C4,Assumptions!$B$77)*INDEX(Assumptions!$B$71:$B$76,3)*Assumptions!$B$58))*Assumptions!$B$42+Assumptions!$B$38*IF(3<=F4,1,Assumptions!$B$58)+(1-D4)*Assumptions!$B$39/Assumptions!$B$33)+IF(3=E4,D4*Assumptions!$B$10/Assumptions!$B$33*MAX(0,1-E4/Assumptions!$B$6),0) | M4: =IF(4>E4,0,IF(4<=F4,C4,MIN(C4,Assumptions!$B$77)*INDEX(Assumptions!$B$71:$B$76,4)*Assumptions!$B$58))-IF(4>E4,0,IF(4>E4,0,IF(4<=F4,C4,MIN(C4,Assumptions!$B$77)*INDEX(Assumptions!$B$71:$B$76,4)*Assumptions!$B$58))*Assumptions!$B$42+Assumptions!$B$38*IF(4<=F4,1,Assumptions!$B$58)+(1-D4)*Assumptions!$B$39/Assumptions!$B$33)+IF(4=E4,D4*Assumptions!$B$10/Assumptions!$B$33*MAX(0,1-E4/Assumptions!$B$6),0) | N4: =IF(5>E4,0,IF(5<=F4,C4,MIN(C4,Assumptions!$B$77)*INDEX(Assumptions!$B$71:$B$76,5)*Assumptions!$B$58))-IF(5>E4,0,IF(5>E4,0,IF(5<=F4,C4,MIN(C4,Assumptions!$B$77)*INDEX(Assumptions!$B$71:$B$76,5)*Assumptions!$B$58))*Assumptions!$B$42+Assumptions!$B$38*IF(5<=F4,1,Assumptions!$B$58)+(1-D4)*Assumptions!$B$39/Assumptions!$B$33)+IF(5=E4,D4*Assumptions!$B$10/Assumptions!$B$33*MAX(0,1-E4/Assumptions!$B$6),0) | O4: =IF(6>E4,0,IF(6<=F4,C4,MIN(C4,Assumptions!$B$77)*INDEX(Assumptions!$B$71:$B$76,6)*Assumptions!$B$58))-IF(6>E4,0,IF(6>E4,0,IF(6<=F4,C4,MIN(C4,Assumptions!$B$77)*INDEX(Assumptions!$B$71:$B$76,6)*Assumptions!$B$58))*Assumptions!$B$42+Assumptions!$B$38*IF(6<=F4,1,Assumptions!$B$58)+(1-D4)*Assumptions!$B$39/Assumptions!$B$33)+IF(6=E4,D4*Assumptions!$B$10/Assumptions!$B$33*MAX(0,1-E4/Assumptions!$B$6),0) | P4: =IFERROR(IRR(I4:O4),-1) | Q4: =IFERROR(MATCH(TRUE,INDEX(AE4:AK4>=0,0),0)-2+(-INDEX(AE4:AK4,MATCH(TRUE,INDEX(AE4:AK4>=0,0),0)-1))/INDEX(I4:O4,MATCH(TRUE,INDEX(AE4:AK4>=0,0),0)),"never") | R4: =NPV(Assumptions!$B$149,J4:O4)+I4 | S4: =(G4-D4*Assumptions!$B$10/Assumptions!$B$33*MAX(0,1-E4/Assumptions!$B$6)/(1+Assumptions!$B$149)^E4)/(IF(1>E4,0,IF(1<=F4,C4,MIN(C4,Assumptions!$B$77)*INDEX(Assumptions!$B$71:$B$76,1)*Assumptions!$B$58))/(1+Assumptions!$B$149)^1+IF(2>E4,0,IF(2<=F4,C4,MIN(C4,Assumptions!$B$77)*INDEX(Assumptions!$B$71:$B$76,2)*Assumptions!$B$58))/(1+Assumptions!$B$149)^2+IF(3>E4,0,IF(3<=F4,C4,MIN(C4,Assumptions!$B$77)*INDEX(Assumptions!$B$71:$B$76,3)*Assumptions!$B$58))/(1+Assumptions!$B$149)^3+IF(4>E4,0,IF(4<=F4,C4,MIN(C4,Assumptions!$B$77)*INDEX(Assumptions!$B$71:$B$76,4)*Assumptions!$B$58))/(1+Assumptions!$B$149)^4+IF(5>E4,0,IF(5<=F4,C4,MIN(C4,Assumptions!$B$77)*INDEX(Assumptions!$B$71:$B$76,5)*Assumptions!$B$58))/(1+Assumptions!$B$149)^5+IF(6>E4,0,IF(6<=F4,C4,MIN(C4,Assumptions!$B$77)*INDEX(Assumptions!$B$71:$B$76,6)*Assumptions!$B$58))/(1+Assumptions!$B$149)^6) | T4: =(IF(D4=1,Assumptions!$B$9/E4+Assumptions!$B$10/Assumptions!$B$6,Assumptions!$B$9/E4+(Assumptions!$B$11-Assumptions!$B$9)/Assumptions!$B$6)/Assumptions!$B$33)/C4 | U4: =Assumptions!$B$54*G4 | V4: =I4+U4 | W4: =J4-IF(1<=F4,$U4/F4,0) | X4: =K4-IF(2<=F4,$U4/F4,0) | Y4: =L4-IF(3<=F4,$U4/F4,0) | Z4: =M4-IF(4<=F4,$U4/F4,0) | AA4: =N4-IF(5<=F4,$U4/F4,0) | AB4: =O4-IF(6<=F4,$U4/F4,0) | AC4: =IFERROR(IRR(V4:AB4),IF(V4>=0,"no equity at risk",-1)) | AD4: =IFERROR(MATCH(TRUE,INDEX(AL4:AR4>=0,0),0)-2+(-INDEX(AL4:AR4,MATCH(TRUE,INDEX(AL4:AR4>=0,0),0)-1))/INDEX(V4:AB4,MATCH(TRUE,INDEX(AL4:AR4>=0,0),0)),"never") | AE4: =SUM($I4:I4) | AF4: =SUM($I4:J4) | AG4: =SUM($I4:K4) | AH4: =SUM($I4:L4) | AI4: =SUM($I4:M4) | AJ4: =SUM($I4:N4) | AK4: =SUM($I4:O4) | AL4: =SUM($V4:V4) | AM4: =SUM($V4:W4) | AN4: =SUM($V4:X4) | AO4: =SUM($V4:Y4) | AP4: =SUM($V4:Z4) | AQ4: =SUM($V4:AA4) | AR4: =SUM($V4:AB4)
A5: 4 | B5: Installed book ($12M, Hopper-era capex) | C5: =Assumptions!$B$44*(1-0) | D5: 0 | E5: =Assumptions!$B$3 | F5: =Assumptions!$B$50 | G5: =IF(D5=1,Assumptions!$B$9+Assumptions!$B$10,Assumptions!$B$11)/Assumptions!$B$33 | H5: =1-Assumptions!$B$42-(Assumptions!$B$38+(1-D5)*Assumptions!$B$39/Assumptions!$B$33)/C5 | I5: =-G5 | J5: =IF(1>E5,0,IF(1<=F5,C5,MIN(C5,Assumptions!$B$77)*INDEX(Assumptions!$B$71:$B$76,1)*Assumptions!$B$58))-IF(1>E5,0,IF(1>E5,0,IF(1<=F5,C5,MIN(C5,Assumptions!$B$77)*INDEX(Assumptions!$B$71:$B$76,1)*Assumptions!$B$58))*Assumptions!$B$42+Assumptions!$B$38*IF(1<=F5,1,Assumptions!$B$58)+(1-D5)*Assumptions!$B$39/Assumptions!$B$33)+IF(1=E5,D5*Assumptions!$B$10/Assumptions!$B$33*MAX(0,1-E5/Assumptions!$B$6),0) | K5: =IF(2>E5,0,IF(2<=F5,C5,MIN(C5,Assumptions!$B$77)*INDEX(Assumptions!$B$71:$B$76,2)*Assumptions!$B$58))-IF(2>E5,0,IF(2>E5,0,IF(2<=F5,C5,MIN(C5,Assumptions!$B$77)*INDEX(Assumptions!$B$71:$B$76,2)*Assumptions!$B$58))*Assumptions!$B$42+Assumptions!$B$38*IF(2<=F5,1,Assumptions!$B$58)+(1-D5)*Assumptions!$B$39/Assumptions!$B$33)+IF(2=E5,D5*Assumptions!$B$10/Assumptions!$B$33*MAX(0,1-E5/Assumptions!$B$6),0) | L5: =IF(3>E5,0,IF(3<=F5,C5,MIN(C5,Assumptions!$B$77)*INDEX(Assumptions!$B$71:$B$76,3)*Assumptions!$B$58))-IF(3>E5,0,IF(3>E5,0,IF(3<=F5,C5,MIN(C5,Assumptions!$B$77)*INDEX(Assumptions!$B$71:$B$76,3)*Assumptions!$B$58))*Assumptions!$B$42+Assumptions!$B$38*IF(3<=F5,1,Assumptions!$B$58)+(1-D5)*Assumptions!$B$39/Assumptions!$B$33)+IF(3=E5,D5*Assumptions!$B$10/Assumptions!$B$33*MAX(0,1-E5/Assumptions!$B$6),0) | M5: =IF(4>E5,0,IF(4<=F5,C5,MIN(C5,Assumptions!$B$77)*INDEX(Assumptions!$B$71:$B$76,4)*Assumptions!$B$58))-IF(4>E5,0,IF(4>E5,0,IF(4<=F5,C5,MIN(C5,Assumptions!$B$77)*INDEX(Assumptions!$B$71:$B$76,4)*Assumptions!$B$58))*Assumptions!$B$42+Assumptions!$B$38*IF(4<=F5,1,Assumptions!$B$58)+(1-D5)*Assumptions!$B$39/Assumptions!$B$33)+IF(4=E5,D5*Assumptions!$B$10/Assumptions!$B$33*MAX(0,1-E5/Assumptions!$B$6),0) | N5: =IF(5>E5,0,IF(5<=F5,C5,MIN(C5,Assumptions!$B$77)*INDEX(Assumptions!$B$71:$B$76,5)*Assumptions!$B$58))-IF(5>E5,0,IF(5>E5,0,IF(5<=F5,C5,MIN(C5,Assumptions!$B$77)*INDEX(Assumptions!$B$71:$B$76,5)*Assumptions!$B$58))*Assumptions!$B$42+Assumptions!$B$38*IF(5<=F5,1,Assumptions!$B$58)+(1-D5)*Assumptions!$B$39/Assumptions!$B$33)+IF(5=E5,D5*Assumptions!$B$10/Assumptions!$B$33*MAX(0,1-E5/Assumptions!$B$6),0) | O5: =IF(6>E5,0,IF(6<=F5,C5,MIN(C5,Assumptions!$B$77)*INDEX(Assumptions!$B$71:$B$76,6)*Assumptions!$B$58))-IF(6>E5,0,IF(6>E5,0,IF(6<=F5,C5,MIN(C5,Assumptions!$B$77)*INDEX(Assumptions!$B$71:$B$76,6)*Assumptions!$B$58))*Assumptions!$B$42+Assumptions!$B$38*IF(6<=F5,1,Assumptions!$B$58)+(1-D5)*Assumptions!$B$39/Assumptions!$B$33)+IF(6=E5,D5*Assumptions!$B$10/Assumptions!$B$33*MAX(0,1-E5/Assumptions!$B$6),0) | P5: =IFERROR(IRR(I5:O5),-1) | Q5: =IFERROR(MATCH(TRUE,INDEX(AE5:AK5>=0,0),0)-2+(-INDEX(AE5:AK5,MATCH(TRUE,INDEX(AE5:AK5>=0,0),0)-1))/INDEX(I5:O5,MATCH(TRUE,INDEX(AE5:AK5>=0,0),0)),"never") | R5: =NPV(Assumptions!$B$149,J5:O5)+I5 | S5: =(G5-D5*Assumptions!$B$10/Assumptions!$B$33*MAX(0,1-E5/Assumptions!$B$6)/(1+Assumptions!$B$149)^E5)/(IF(1>E5,0,IF(1<=F5,C5,MIN(C5,Assumptions!$B$77)*INDEX(Assumptions!$B$71:$B$76,1)*Assumptions!$B$58))/(1+Assumptions!$B$149)^1+IF(2>E5,0,IF(2<=F5,C5,MIN(C5,Assumptions!$B$77)*INDEX(Assumptions!$B$71:$B$76,2)*Assumptions!$B$58))/(1+Assumptions!$B$149)^2+IF(3>E5,0,IF(3<=F5,C5,MIN(C5,Assumptions!$B$77)*INDEX(Assumptions!$B$71:$B$76,3)*Assumptions!$B$58))/(1+Assumptions!$B$149)^3+IF(4>E5,0,IF(4<=F5,C5,MIN(C5,Assumptions!$B$77)*INDEX(Assumptions!$B$71:$B$76,4)*Assumptions!$B$58))/(1+Assumptions!$B$149)^4+IF(5>E5,0,IF(5<=F5,C5,MIN(C5,Assumptions!$B$77)*INDEX(Assumptions!$B$71:$B$76,5)*Assumptions!$B$58))/(1+Assumptions!$B$149)^5+IF(6>E5,0,IF(6<=F5,C5,MIN(C5,Assumptions!$B$77)*INDEX(Assumptions!$B$71:$B$76,6)*Assumptions!$B$58))/(1+Assumptions!$B$149)^6) | T5: =(IF(D5=1,Assumptions!$B$9/E5+Assumptions!$B$10/Assumptions!$B$6,Assumptions!$B$9/E5+(Assumptions!$B$11-Assumptions!$B$9)/Assumptions!$B$6)/Assumptions!$B$33)/C5 | U5: =Assumptions!$B$54*G5 | V5: =I5+U5 | W5: =J5-IF(1<=F5,$U5/F5,0) | X5: =K5-IF(2<=F5,$U5/F5,0) | Y5: =L5-IF(3<=F5,$U5/F5,0) | Z5: =M5-IF(4<=F5,$U5/F5,0) | AA5: =N5-IF(5<=F5,$U5/F5,0) | AB5: =O5-IF(6<=F5,$U5/F5,0) | AC5: =IFERROR(IRR(V5:AB5),IF(V5>=0,"no equity at risk",-1)) | AD5: =IFERROR(MATCH(TRUE,INDEX(AL5:AR5>=0,0),0)-2+(-INDEX(AL5:AR5,MATCH(TRUE,INDEX(AL5:AR5>=0,0),0)-1))/INDEX(V5:AB5,MATCH(TRUE,INDEX(AL5:AR5>=0,0),0)),"never") | AE5: =SUM($I5:I5) | AF5: =SUM($I5:J5) | AG5: =SUM($I5:K5) | AH5: =SUM($I5:L5) | AI5: =SUM($I5:M5) | AJ5: =SUM($I5:N5) | AK5: =SUM($I5:O5) | AL5: =SUM($V5:V5) | AM5: =SUM($V5:W5) | AN5: =SUM($V5:X5) | AO5: =SUM($V5:Y5) | AP5: =SUM($V5:Z5) | AQ5: =SUM($V5:AA5) | AR5: =SUM($V5:AB5)
A6: 5 | B6: Installed book ($12M, Hopper-era capex) | C6: =Assumptions!$B$44*(1-0) | D6: 0 | E6: =Assumptions!$B$4 | F6: =Assumptions!$B$50 | G6: =IF(D6=1,Assumptions!$B$9+Assumptions!$B$10,Assumptions!$B$11)/Assumptions!$B$33 | H6: =1-Assumptions!$B$42-(Assumptions!$B$38+(1-D6)*Assumptions!$B$39/Assumptions!$B$33)/C6 | I6: =-G6 | J6: =IF(1>E6,0,IF(1<=F6,C6,MIN(C6,Assumptions!$B$77)*INDEX(Assumptions!$B$71:$B$76,1)*Assumptions!$B$58))-IF(1>E6,0,IF(1>E6,0,IF(1<=F6,C6,MIN(C6,Assumptions!$B$77)*INDEX(Assumptions!$B$71:$B$76,1)*Assumptions!$B$58))*Assumptions!$B$42+Assumptions!$B$38*IF(1<=F6,1,Assumptions!$B$58)+(1-D6)*Assumptions!$B$39/Assumptions!$B$33)+IF(1=E6,D6*Assumptions!$B$10/Assumptions!$B$33*MAX(0,1-E6/Assumptions!$B$6),0) | K6: =IF(2>E6,0,IF(2<=F6,C6,MIN(C6,Assumptions!$B$77)*INDEX(Assumptions!$B$71:$B$76,2)*Assumptions!$B$58))-IF(2>E6,0,IF(2>E6,0,IF(2<=F6,C6,MIN(C6,Assumptions!$B$77)*INDEX(Assumptions!$B$71:$B$76,2)*Assumptions!$B$58))*Assumptions!$B$42+Assumptions!$B$38*IF(2<=F6,1,Assumptions!$B$58)+(1-D6)*Assumptions!$B$39/Assumptions!$B$33)+IF(2=E6,D6*Assumptions!$B$10/Assumptions!$B$33*MAX(0,1-E6/Assumptions!$B$6),0) | L6: =IF(3>E6,0,IF(3<=F6,C6,MIN(C6,Assumptions!$B$77)*INDEX(Assumptions!$B$71:$B$76,3)*Assumptions!$B$58))-IF(3>E6,0,IF(3>E6,0,IF(3<=F6,C6,MIN(C6,Assumptions!$B$77)*INDEX(Assumptions!$B$71:$B$76,3)*Assumptions!$B$58))*Assumptions!$B$42+Assumptions!$B$38*IF(3<=F6,1,Assumptions!$B$58)+(1-D6)*Assumptions!$B$39/Assumptions!$B$33)+IF(3=E6,D6*Assumptions!$B$10/Assumptions!$B$33*MAX(0,1-E6/Assumptions!$B$6),0) | M6: =IF(4>E6,0,IF(4<=F6,C6,MIN(C6,Assumptions!$B$77)*INDEX(Assumptions!$B$71:$B$76,4)*Assumptions!$B$58))-IF(4>E6,0,IF(4>E6,0,IF(4<=F6,C6,MIN(C6,Assumptions!$B$77)*INDEX(Assumptions!$B$71:$B$76,4)*Assumptions!$B$58))*Assumptions!$B$42+Assumptions!$B$38*IF(4<=F6,1,Assumptions!$B$58)+(1-D6)*Assumptions!$B$39/Assumptions!$B$33)+IF(4=E6,D6*Assumptions!$B$10/Assumptions!$B$33*MAX(0,1-E6/Assumptions!$B$6),0) | N6: =IF(5>E6,0,IF(5<=F6,C6,MIN(C6,Assumptions!$B$77)*INDEX(Assumptions!$B$71:$B$76,5)*Assumptions!$B$58))-IF(5>E6,0,IF(5>E6,0,IF(5<=F6,C6,MIN(C6,Assumptions!$B$77)*INDEX(Assumptions!$B$71:$B$76,5)*Assumptions!$B$58))*Assumptions!$B$42+Assumptions!$B$38*IF(5<=F6,1,Assumptions!$B$58)+(1-D6)*Assumptions!$B$39/Assumptions!$B$33)+IF(5=E6,D6*Assumptions!$B$10/Assumptions!$B$33*MAX(0,1-E6/Assumptions!$B$6),0) | O6: =IF(6>E6,0,IF(6<=F6,C6,MIN(C6,Assumptions!$B$77)*INDEX(Assumptions!$B$71:$B$76,6)*Assumptions!$B$58))-IF(6>E6,0,IF(6>E6,0,IF(6<=F6,C6,MIN(C6,Assumptions!$B$77)*INDEX(Assumptions!$B$71:$B$76,6)*Assumptions!$B$58))*Assumptions!$B$42+Assumptions!$B$38*IF(6<=F6,1,Assumptions!$B$58)+(1-D6)*Assumptions!$B$39/Assumptions!$B$33)+IF(6=E6,D6*Assumptions!$B$10/Assumptions!$B$33*MAX(0,1-E6/Assumptions!$B$6),0) | P6: =IFERROR(IRR(I6:O6),-1) | Q6: =IFERROR(MATCH(TRUE,INDEX(AE6:AK6>=0,0),0)-2+(-INDEX(AE6:AK6,MATCH(TRUE,INDEX(AE6:AK6>=0,0),0)-1))/INDEX(I6:O6,MATCH(TRUE,INDEX(AE6:AK6>=0,0),0)),"never") | R6: =NPV(Assumptions!$B$149,J6:O6)+I6 | S6: =(G6-D6*Assumptions!$B$10/Assumptions!$B$33*MAX(0,1-E6/Assumptions!$B$6)/(1+Assumptions!$B$149)^E6)/(IF(1>E6,0,IF(1<=F6,C6,MIN(C6,Assumptions!$B$77)*INDEX(Assumptions!$B$71:$B$76,1)*Assumptions!$B$58))/(1+Assumptions!$B$149)^1+IF(2>E6,0,IF(2<=F6,C6,MIN(C6,Assumptions!$B$77)*INDEX(Assumptions!$B$71:$B$76,2)*Assumptions!$B$58))/(1+Assumptions!$B$149)^2+IF(3>E6,0,IF(3<=F6,C6,MIN(C6,Assumptions!$B$77)*INDEX(Assumptions!$B$71:$B$76,3)*Assumptions!$B$58))/(1+Assumptions!$B$149)^3+IF(4>E6,0,IF(4<=F6,C6,MIN(C6,Assumptions!$B$77)*INDEX(Assumptions!$B$71:$B$76,4)*Assumptions!$B$58))/(1+Assumptions!$B$149)^4+IF(5>E6,0,IF(5<=F6,C6,MIN(C6,Assumptions!$B$77)*INDEX(Assumptions!$B$71:$B$76,5)*Assumptions!$B$58))/(1+Assumptions!$B$149)^5+IF(6>E6,0,IF(6<=F6,C6,MIN(C6,Assumptions!$B$77)*INDEX(Assumptions!$B$71:$B$76,6)*Assumptions!$B$58))/(1+Assumptions!$B$149)^6) | T6: =(IF(D6=1,Assumptions!$B$9/E6+Assumptions!$B$10/Assumptions!$B$6,Assumptions!$B$9/E6+(Assumptions!$B$11-Assumptions!$B$9)/Assumptions!$B$6)/Assumptions!$B$33)/C6 | U6: =Assumptions!$B$54*G6 | V6: =I6+U6 | W6: =J6-IF(1<=F6,$U6/F6,0) | X6: =K6-IF(2<=F6,$U6/F6,0) | Y6: =L6-IF(3<=F6,$U6/F6,0) | Z6: =M6-IF(4<=F6,$U6/F6,0) | AA6: =N6-IF(5<=F6,$U6/F6,0) | AB6: =O6-IF(6<=F6,$U6/F6,0) | AC6: =IFERROR(IRR(V6:AB6),IF(V6>=0,"no equity at risk",-1)) | AD6: =IFERROR(MATCH(TRUE,INDEX(AL6:AR6>=0,0),0)-2+(-INDEX(AL6:AR6,MATCH(TRUE,INDEX(AL6:AR6>=0,0),0)-1))/INDEX(V6:AB6,MATCH(TRUE,INDEX(AL6:AR6>=0,0),0)),"never") | AE6: =SUM($I6:I6) | AF6: =SUM($I6:J6) | AG6: =SUM($I6:K6) | AH6: =SUM($I6:L6) | AI6: =SUM($I6:M6) | AJ6: =SUM($I6:N6) | AK6: =SUM($I6:O6) | AL6: =SUM($V6:V6) | AM6: =SUM($V6:W6) | AN6: =SUM($V6:X6) | AO6: =SUM($V6:Y6) | AP6: =SUM($V6:Z6) | AQ6: =SUM($V6:AA6) | AR6: =SUM($V6:AB6)
A7: 6 | B7: Installed book ($12M, Hopper-era capex) | C7: =Assumptions!$B$44*(1-0) | D7: 0 | E7: =Assumptions!$B$5 | F7: =Assumptions!$B$50 | G7: =IF(D7=1,Assumptions!$B$9+Assumptions!$B$10,Assumptions!$B$11)/Assumptions!$B$33 | H7: =1-Assumptions!$B$42-(Assumptions!$B$38+(1-D7)*Assumptions!$B$39/Assumptions!$B$33)/C7 | I7: =-G7 | J7: =IF(1>E7,0,IF(1<=F7,C7,MIN(C7,Assumptions!$B$77)*INDEX(Assumptions!$B$71:$B$76,1)*Assumptions!$B$58))-IF(1>E7,0,IF(1>E7,0,IF(1<=F7,C7,MIN(C7,Assumptions!$B$77)*INDEX(Assumptions!$B$71:$B$76,1)*Assumptions!$B$58))*Assumptions!$B$42+Assumptions!$B$38*IF(1<=F7,1,Assumptions!$B$58)+(1-D7)*Assumptions!$B$39/Assumptions!$B$33)+IF(1=E7,D7*Assumptions!$B$10/Assumptions!$B$33*MAX(0,1-E7/Assumptions!$B$6),0) | K7: =IF(2>E7,0,IF(2<=F7,C7,MIN(C7,Assumptions!$B$77)*INDEX(Assumptions!$B$71:$B$76,2)*Assumptions!$B$58))-IF(2>E7,0,IF(2>E7,0,IF(2<=F7,C7,MIN(C7,Assumptions!$B$77)*INDEX(Assumptions!$B$71:$B$76,2)*Assumptions!$B$58))*Assumptions!$B$42+Assumptions!$B$38*IF(2<=F7,1,Assumptions!$B$58)+(1-D7)*Assumptions!$B$39/Assumptions!$B$33)+IF(2=E7,D7*Assumptions!$B$10/Assumptions!$B$33*MAX(0,1-E7/Assumptions!$B$6),0) | L7: =IF(3>E7,0,IF(3<=F7,C7,MIN(C7,Assumptions!$B$77)*INDEX(Assumptions!$B$71:$B$76,3)*Assumptions!$B$58))-IF(3>E7,0,IF(3>E7,0,IF(3<=F7,C7,MIN(C7,Assumptions!$B$77)*INDEX(Assumptions!$B$71:$B$76,3)*Assumptions!$B$58))*Assumptions!$B$42+Assumptions!$B$38*IF(3<=F7,1,Assumptions!$B$58)+(1-D7)*Assumptions!$B$39/Assumptions!$B$33)+IF(3=E7,D7*Assumptions!$B$10/Assumptions!$B$33*MAX(0,1-E7/Assumptions!$B$6),0) | M7: =IF(4>E7,0,IF(4<=F7,C7,MIN(C7,Assumptions!$B$77)*INDEX(Assumptions!$B$71:$B$76,4)*Assumptions!$B$58))-IF(4>E7,0,IF(4>E7,0,IF(4<=F7,C7,MIN(C7,Assumptions!$B$77)*INDEX(Assumptions!$B$71:$B$76,4)*Assumptions!$B$58))*Assumptions!$B$42+Assumptions!$B$38*IF(4<=F7,1,Assumptions!$B$58)+(1-D7)*Assumptions!$B$39/Assumptions!$B$33)+IF(4=E7,D7*Assumptions!$B$10/Assumptions!$B$33*MAX(0,1-E7/Assumptions!$B$6),0) | N7: =IF(5>E7,0,IF(5<=F7,C7,MIN(C7,Assumptions!$B$77)*INDEX(Assumptions!$B$71:$B$76,5)*Assumptions!$B$58))-IF(5>E7,0,IF(5>E7,0,IF(5<=F7,C7,MIN(C7,Assumptions!$B$77)*INDEX(Assumptions!$B$71:$B$76,5)*Assumptions!$B$58))*Assumptions!$B$42+Assumptions!$B$38*IF(5<=F7,1,Assumptions!$B$58)+(1-D7)*Assumptions!$B$39/Assumptions!$B$33)+IF(5=E7,D7*Assumptions!$B$10/Assumptions!$B$33*MAX(0,1-E7/Assumptions!$B$6),0) | O7: =IF(6>E7,0,IF(6<=F7,C7,MIN(C7,Assumptions!$B$77)*INDEX(Assumptions!$B$71:$B$76,6)*Assumptions!$B$58))-IF(6>E7,0,IF(6>E7,0,IF(6<=F7,C7,MIN(C7,Assumptions!$B$77)*INDEX(Assumptions!$B$71:$B$76,6)*Assumptions!$B$58))*Assumptions!$B$42+Assumptions!$B$38*IF(6<=F7,1,Assumptions!$B$58)+(1-D7)*Assumptions!$B$39/Assumptions!$B$33)+IF(6=E7,D7*Assumptions!$B$10/Assumptions!$B$33*MAX(0,1-E7/Assumptions!$B$6),0) | P7: =IFERROR(IRR(I7:O7),-1) | Q7: =IFERROR(MATCH(TRUE,INDEX(AE7:AK7>=0,0),0)-2+(-INDEX(AE7:AK7,MATCH(TRUE,INDEX(AE7:AK7>=0,0),0)-1))/INDEX(I7:O7,MATCH(TRUE,INDEX(AE7:AK7>=0,0),0)),"never") | R7: =NPV(Assumptions!$B$149,J7:O7)+I7 | S7: =(G7-D7*Assumptions!$B$10/Assumptions!$B$33*MAX(0,1-E7/Assumptions!$B$6)/(1+Assumptions!$B$149)^E7)/(IF(1>E7,0,IF(1<=F7,C7,MIN(C7,Assumptions!$B$77)*INDEX(Assumptions!$B$71:$B$76,1)*Assumptions!$B$58))/(1+Assumptions!$B$149)^1+IF(2>E7,0,IF(2<=F7,C7,MIN(C7,Assumptions!$B$77)*INDEX(Assumptions!$B$71:$B$76,2)*Assumptions!$B$58))/(1+Assumptions!$B$149)^2+IF(3>E7,0,IF(3<=F7,C7,MIN(C7,Assumptions!$B$77)*INDEX(Assumptions!$B$71:$B$76,3)*Assumptions!$B$58))/(1+Assumptions!$B$149)^3+IF(4>E7,0,IF(4<=F7,C7,MIN(C7,Assumptions!$B$77)*INDEX(Assumptions!$B$71:$B$76,4)*Assumptions!$B$58))/(1+Assumptions!$B$149)^4+IF(5>E7,0,IF(5<=F7,C7,MIN(C7,Assumptions!$B$77)*INDEX(Assumptions!$B$71:$B$76,5)*Assumptions!$B$58))/(1+Assumptions!$B$149)^5+IF(6>E7,0,IF(6<=F7,C7,MIN(C7,Assumptions!$B$77)*INDEX(Assumptions!$B$71:$B$76,6)*Assumptions!$B$58))/(1+Assumptions!$B$149)^6) | T7: =(IF(D7=1,Assumptions!$B$9/E7+Assumptions!$B$10/Assumptions!$B$6,Assumptions!$B$9/E7+(Assumptions!$B$11-Assumptions!$B$9)/Assumptions!$B$6)/Assumptions!$B$33)/C7 | U7: =Assumptions!$B$54*G7 | V7: =I7+U7 | W7: =J7-IF(1<=F7,$U7/F7,0) | X7: =K7-IF(2<=F7,$U7/F7,0) | Y7: =L7-IF(3<=F7,$U7/F7,0) | Z7: =M7-IF(4<=F7,$U7/F7,0) | AA7: =N7-IF(5<=F7,$U7/F7,0) | AB7: =O7-IF(6<=F7,$U7/F7,0) | AC7: =IFERROR(IRR(V7:AB7),IF(V7>=0,"no equity at risk",-1)) | AD7: =IFERROR(MATCH(TRUE,INDEX(AL7:AR7>=0,0),0)-2+(-INDEX(AL7:AR7,MATCH(TRUE,INDEX(AL7:AR7>=0,0),0)-1))/INDEX(V7:AB7,MATCH(TRUE,INDEX(AL7:AR7>=0,0),0)),"never") | AE7: =SUM($I7:I7) | AF7: =SUM($I7:J7) | AG7: =SUM($I7:K7) | AH7: =SUM($I7:L7) | AI7: =SUM($I7:M7) | AJ7: =SUM($I7:N7) | AK7: =SUM($I7:O7) | AL7: =SUM($V7:V7) | AM7: =SUM($V7:W7) | AN7: =SUM($V7:X7) | AO7: =SUM($V7:Y7) | AP7: =SUM($V7:Z7) | AQ7: =SUM($V7:AA7) | AR7: =SUM($V7:AB7)
A8: 7 | B8: Q2 deals low ($20M) | C8: =Assumptions!$B$45*(1-0) | D8: 1 | E8: =Assumptions!$B$3 | F8: =Assumptions!$B$50 | G8: =IF(D8=1,Assumptions!$B$25+Assumptions!$B$26,Assumptions!$B$27)/Assumptions!$B$33 | H8: =1-Assumptions!$B$42-(Assumptions!$B$38+(1-D8)*Assumptions!$B$39/Assumptions!$B$33)/C8 | I8: =-G8 | J8: =IF(1>E8,0,IF(1<=F8,C8,MIN(C8,Assumptions!$B$77)*INDEX(Assumptions!$B$71:$B$76,1)*Assumptions!$B$58))-IF(1>E8,0,IF(1>E8,0,IF(1<=F8,C8,MIN(C8,Assumptions!$B$77)*INDEX(Assumptions!$B$71:$B$76,1)*Assumptions!$B$58))*Assumptions!$B$42+Assumptions!$B$38*IF(1<=F8,1,Assumptions!$B$58)+(1-D8)*Assumptions!$B$39/Assumptions!$B$33)+IF(1=E8,D8*Assumptions!$B$26/Assumptions!$B$33*MAX(0,1-E8/Assumptions!$B$6),0) | K8: =IF(2>E8,0,IF(2<=F8,C8,MIN(C8,Assumptions!$B$77)*INDEX(Assumptions!$B$71:$B$76,2)*Assumptions!$B$58))-IF(2>E8,0,IF(2>E8,0,IF(2<=F8,C8,MIN(C8,Assumptions!$B$77)*INDEX(Assumptions!$B$71:$B$76,2)*Assumptions!$B$58))*Assumptions!$B$42+Assumptions!$B$38*IF(2<=F8,1,Assumptions!$B$58)+(1-D8)*Assumptions!$B$39/Assumptions!$B$33)+IF(2=E8,D8*Assumptions!$B$26/Assumptions!$B$33*MAX(0,1-E8/Assumptions!$B$6),0) | L8: =IF(3>E8,0,IF(3<=F8,C8,MIN(C8,Assumptions!$B$77)*INDEX(Assumptions!$B$71:$B$76,3)*Assumptions!$B$58))-IF(3>E8,0,IF(3>E8,0,IF(3<=F8,C8,MIN(C8,Assumptions!$B$77)*INDEX(Assumptions!$B$71:$B$76,3)*Assumptions!$B$58))*Assumptions!$B$42+Assumptions!$B$38*IF(3<=F8,1,Assumptions!$B$58)+(1-D8)*Assumptions!$B$39/Assumptions!$B$33)+IF(3=E8,D8*Assumptions!$B$26/Assumptions!$B$33*MAX(0,1-E8/Assumptions!$B$6),0) | M8: =IF(4>E8,0,IF(4<=F8,C8,MIN(C8,Assumptions!$B$77)*INDEX(Assumptions!$B$71:$B$76,4)*Assumptions!$B$58))-IF(4>E8,0,IF(4>E8,0,IF(4<=F8,C8,MIN(C8,Assumptions!$B$77)*INDEX(Assumptions!$B$71:$B$76,4)*Assumptions!$B$58))*Assumptions!$B$42+Assumptions!$B$38*IF(4<=F8,1,Assumptions!$B$58)+(1-D8)*Assumptions!$B$39/Assumptions!$B$33)+IF(4=E8,D8*Assumptions!$B$26/Assumptions!$B$33*MAX(0,1-E8/Assumptions!$B$6),0) | N8: =IF(5>E8,0,IF(5<=F8,C8,MIN(C8,Assumptions!$B$77)*INDEX(Assumptions!$B$71:$B$76,5)*Assumptions!$B$58))-IF(5>E8,0,IF(5>E8,0,IF(5<=F8,C8,MIN(C8,Assumptions!$B$77)*INDEX(Assumptions!$B$71:$B$76,5)*Assumptions!$B$58))*Assumptions!$B$42+Assumptions!$B$38*IF(5<=F8,1,Assumptions!$B$58)+(1-D8)*Assumptions!$B$39/Assumptions!$B$33)+IF(5=E8,D8*Assumptions!$B$26/Assumptions!$B$33*MAX(0,1-E8/Assumptions!$B$6),0) | O8: =IF(6>E8,0,IF(6<=F8,C8,MIN(C8,Assumptions!$B$77)*INDEX(Assumptions!$B$71:$B$76,6)*Assumptions!$B$58))-IF(6>E8,0,IF(6>E8,0,IF(6<=F8,C8,MIN(C8,Assumptions!$B$77)*INDEX(Assumptions!$B$71:$B$76,6)*Assumptions!$B$58))*Assumptions!$B$42+Assumptions!$B$38*IF(6<=F8,1,Assumptions!$B$58)+(1-D8)*Assumptions!$B$39/Assumptions!$B$33)+IF(6=E8,D8*Assumptions!$B$26/Assumptions!$B$33*MAX(0,1-E8/Assumptions!$B$6),0) | P8: =IFERROR(IRR(I8:O8),-1) | Q8: =IFERROR(MATCH(TRUE,INDEX(AE8:AK8>=0,0),0)-2+(-INDEX(AE8:AK8,MATCH(TRUE,INDEX(AE8:AK8>=0,0),0)-1))/INDEX(I8:O8,MATCH(TRUE,INDEX(AE8:AK8>=0,0),0)),"never") | R8: =NPV(Assumptions!$B$149,J8:O8)+I8 | S8: =(G8-D8*Assumptions!$B$26/Assumptions!$B$33*MAX(0,1-E8/Assumptions!$B$6)/(1+Assumptions!$B$149)^E8)/(IF(1>E8,0,IF(1<=F8,C8,MIN(C8,Assumptions!$B$77)*INDEX(Assumptions!$B$71:$B$76,1)*Assumptions!$B$58))/(1+Assumptions!$B$149)^1+IF(2>E8,0,IF(2<=F8,C8,MIN(C8,Assumptions!$B$77)*INDEX(Assumptions!$B$71:$B$76,2)*Assumptions!$B$58))/(1+Assumptions!$B$149)^2+IF(3>E8,0,IF(3<=F8,C8,MIN(C8,Assumptions!$B$77)*INDEX(Assumptions!$B$71:$B$76,3)*Assumptions!$B$58))/(1+Assumptions!$B$149)^3+IF(4>E8,0,IF(4<=F8,C8,MIN(C8,Assumptions!$B$77)*INDEX(Assumptions!$B$71:$B$76,4)*Assumptions!$B$58))/(1+Assumptions!$B$149)^4+IF(5>E8,0,IF(5<=F8,C8,MIN(C8,Assumptions!$B$77)*INDEX(Assumptions!$B$71:$B$76,5)*Assumptions!$B$58))/(1+Assumptions!$B$149)^5+IF(6>E8,0,IF(6<=F8,C8,MIN(C8,Assumptions!$B$77)*INDEX(Assumptions!$B$71:$B$76,6)*Assumptions!$B$58))/(1+Assumptions!$B$149)^6) | T8: =(IF(D8=1,Assumptions!$B$25/E8+Assumptions!$B$26/Assumptions!$B$6,Assumptions!$B$25/E8+(Assumptions!$B$27-Assumptions!$B$25)/Assumptions!$B$6)/Assumptions!$B$33)/C8 | U8: =Assumptions!$B$54*G8 | V8: =I8+U8 | W8: =J8-IF(1<=F8,$U8/F8,0) | X8: =K8-IF(2<=F8,$U8/F8,0) | Y8: =L8-IF(3<=F8,$U8/F8,0) | Z8: =M8-IF(4<=F8,$U8/F8,0) | AA8: =N8-IF(5<=F8,$U8/F8,0) | AB8: =O8-IF(6<=F8,$U8/F8,0) | AC8: =IFERROR(IRR(V8:AB8),IF(V8>=0,"no equity at risk",-1)) | AD8: =IFERROR(MATCH(TRUE,INDEX(AL8:AR8>=0,0),0)-2+(-INDEX(AL8:AR8,MATCH(TRUE,INDEX(AL8:AR8>=0,0),0)-1))/INDEX(V8:AB8,MATCH(TRUE,INDEX(AL8:AR8>=0,0),0)),"never") | AE8: =SUM($I8:I8) | AF8: =SUM($I8:J8) | AG8: =SUM($I8:K8) | AH8: =SUM($I8:L8) | AI8: =SUM($I8:M8) | AJ8: =SUM($I8:N8) | AK8: =SUM($I8:O8) | AL8: =SUM($V8:V8) | AM8: =SUM($V8:W8) | AN8: =SUM($V8:X8) | AO8: =SUM($V8:Y8) | AP8: =SUM($V8:Z8) | AQ8: =SUM($V8:AA8) | AR8: =SUM($V8:AB8)
A9: 8 | B9: Q2 deals low ($20M) | C9: =Assumptions!$B$45*(1-0) | D9: 1 | E9: =Assumptions!$B$4 | F9: =Assumptions!$B$50 | G9: =IF(D9=1,Assumptions!$B$25+Assumptions!$B$26,Assumptions!$B$27)/Assumptions!$B$33 | H9: =1-Assumptions!$B$42-(Assumptions!$B$38+(1-D9)*Assumptions!$B$39/Assumptions!$B$33)/C9 | I9: =-G9 | J9: =IF(1>E9,0,IF(1<=F9,C9,MIN(C9,Assumptions!$B$77)*INDEX(Assumptions!$B$71:$B$76,1)*Assumptions!$B$58))-IF(1>E9,0,IF(1>E9,0,IF(1<=F9,C9,MIN(C9,Assumptions!$B$77)*INDEX(Assumptions!$B$71:$B$76,1)*Assumptions!$B$58))*Assumptions!$B$42+Assumptions!$B$38*IF(1<=F9,1,Assumptions!$B$58)+(1-D9)*Assumptions!$B$39/Assumptions!$B$33)+IF(1=E9,D9*Assumptions!$B$26/Assumptions!$B$33*MAX(0,1-E9/Assumptions!$B$6),0) | K9: =IF(2>E9,0,IF(2<=F9,C9,MIN(C9,Assumptions!$B$77)*INDEX(Assumptions!$B$71:$B$76,2)*Assumptions!$B$58))-IF(2>E9,0,IF(2>E9,0,IF(2<=F9,C9,MIN(C9,Assumptions!$B$77)*INDEX(Assumptions!$B$71:$B$76,2)*Assumptions!$B$58))*Assumptions!$B$42+Assumptions!$B$38*IF(2<=F9,1,Assumptions!$B$58)+(1-D9)*Assumptions!$B$39/Assumptions!$B$33)+IF(2=E9,D9*Assumptions!$B$26/Assumptions!$B$33*MAX(0,1-E9/Assumptions!$B$6),0) | L9: =IF(3>E9,0,IF(3<=F9,C9,MIN(C9,Assumptions!$B$77)*INDEX(Assumptions!$B$71:$B$76,3)*Assumptions!$B$58))-IF(3>E9,0,IF(3>E9,0,IF(3<=F9,C9,MIN(C9,Assumptions!$B$77)*INDEX(Assumptions!$B$71:$B$76,3)*Assumptions!$B$58))*Assumptions!$B$42+Assumptions!$B$38*IF(3<=F9,1,Assumptions!$B$58)+(1-D9)*Assumptions!$B$39/Assumptions!$B$33)+IF(3=E9,D9*Assumptions!$B$26/Assumptions!$B$33*MAX(0,1-E9/Assumptions!$B$6),0) | M9: =IF(4>E9,0,IF(4<=F9,C9,MIN(C9,Assumptions!$B$77)*INDEX(Assumptions!$B$71:$B$76,4)*Assumptions!$B$58))-IF(4>E9,0,IF(4>E9,0,IF(4<=F9,C9,MIN(C9,Assumptions!$B$77)*INDEX(Assumptions!$B$71:$B$76,4)*Assumptions!$B$58))*Assumptions!$B$42+Assumptions!$B$38*IF(4<=F9,1,Assumptions!$B$58)+(1-D9)*Assumptions!$B$39/Assumptions!$B$33)+IF(4=E9,D9*Assumptions!$B$26/Assumptions!$B$33*MAX(0,1-E9/Assumptions!$B$6),0) | N9: =IF(5>E9,0,IF(5<=F9,C9,MIN(C9,Assumptions!$B$77)*INDEX(Assumptions!$B$71:$B$76,5)*Assumptions!$B$58))-IF(5>E9,0,IF(5>E9,0,IF(5<=F9,C9,MIN(C9,Assumptions!$B$77)*INDEX(Assumptions!$B$71:$B$76,5)*Assumptions!$B$58))*Assumptions!$B$42+Assumptions!$B$38*IF(5<=F9,1,Assumptions!$B$58)+(1-D9)*Assumptions!$B$39/Assumptions!$B$33)+IF(5=E9,D9*Assumptions!$B$26/Assumptions!$B$33*MAX(0,1-E9/Assumptions!$B$6),0) | O9: =IF(6>E9,0,IF(6<=F9,C9,MIN(C9,Assumptions!$B$77)*INDEX(Assumptions!$B$71:$B$76,6)*Assumptions!$B$58))-IF(6>E9,0,IF(6>E9,0,IF(6<=F9,C9,MIN(C9,Assumptions!$B$77)*INDEX(Assumptions!$B$71:$B$76,6)*Assumptions!$B$58))*Assumptions!$B$42+Assumptions!$B$38*IF(6<=F9,1,Assumptions!$B$58)+(1-D9)*Assumptions!$B$39/Assumptions!$B$33)+IF(6=E9,D9*Assumptions!$B$26/Assumptions!$B$33*MAX(0,1-E9/Assumptions!$B$6),0) | P9: =IFERROR(IRR(I9:O9),-1) | Q9: =IFERROR(MATCH(TRUE,INDEX(AE9:AK9>=0,0),0)-2+(-INDEX(AE9:AK9,MATCH(TRUE,INDEX(AE9:AK9>=0,0),0)-1))/INDEX(I9:O9,MATCH(TRUE,INDEX(AE9:AK9>=0,0),0)),"never") | R9: =NPV(Assumptions!$B$149,J9:O9)+I9 | S9: =(G9-D9*Assumptions!$B$26/Assumptions!$B$33*MAX(0,1-E9/Assumptions!$B$6)/(1+Assumptions!$B$149)^E9)/(IF(1>E9,0,IF(1<=F9,C9,MIN(C9,Assumptions!$B$77)*INDEX(Assumptions!$B$71:$B$76,1)*Assumptions!$B$58))/(1+Assumptions!$B$149)^1+IF(2>E9,0,IF(2<=F9,C9,MIN(C9,Assumptions!$B$77)*INDEX(Assumptions!$B$71:$B$76,2)*Assumptions!$B$58))/(1+Assumptions!$B$149)^2+IF(3>E9,0,IF(3<=F9,C9,MIN(C9,Assumptions!$B$77)*INDEX(Assumptions!$B$71:$B$76,3)*Assumptions!$B$58))/(1+Assumptions!$B$149)^3+IF(4>E9,0,IF(4<=F9,C9,MIN(C9,Assumptions!$B$77)*INDEX(Assumptions!$B$71:$B$76,4)*Assumptions!$B$58))/(1+Assumptions!$B$149)^4+IF(5>E9,0,IF(5<=F9,C9,MIN(C9,Assumptions!$B$77)*INDEX(Assumptions!$B$71:$B$76,5)*Assumptions!$B$58))/(1+Assumptions!$B$149)^5+IF(6>E9,0,IF(6<=F9,C9,MIN(C9,Assumptions!$B$77)*INDEX(Assumptions!$B$71:$B$76,6)*Assumptions!$B$58))/(1+Assumptions!$B$149)^6) | T9: =(IF(D9=1,Assumptions!$B$25/E9+Assumptions!$B$26/Assumptions!$B$6,Assumptions!$B$25/E9+(Assumptions!$B$27-Assumptions!$B$25)/Assumptions!$B$6)/Assumptions!$B$33)/C9 | U9: =Assumptions!$B$54*G9 | V9: =I9+U9 | W9: =J9-IF(1<=F9,$U9/F9,0) | X9: =K9-IF(2<=F9,$U9/F9,0) | Y9: =L9-IF(3<=F9,$U9/F9,0) | Z9: =M9-IF(4<=F9,$U9/F9,0) | AA9: =N9-IF(5<=F9,$U9/F9,0) | AB9: =O9-IF(6<=F9,$U9/F9,0) | AC9: =IFERROR(IRR(V9:AB9),IF(V9>=0,"no equity at risk",-1)) | AD9: =IFERROR(MATCH(TRUE,INDEX(AL9:AR9>=0,0),0)-2+(-INDEX(AL9:AR9,MATCH(TRUE,INDEX(AL9:AR9>=0,0),0)-1))/INDEX(V9:AB9,MATCH(TRUE,INDEX(AL9:AR9>=0,0),0)),"never") | AE9: =SUM($I9:I9) | AF9: =SUM($I9:J9) | AG9: =SUM($I9:K9) | AH9: =SUM($I9:L9) | AI9: =SUM($I9:M9) | AJ9: =SUM($I9:N9) | AK9: =SUM($I9:O9) | AL9: =SUM($V9:V9) | AM9: =SUM($V9:W9) | AN9: =SUM($V9:X9) | AO9: =SUM($V9:Y9) | AP9: =SUM($V9:Z9) | AQ9: =SUM($V9:AA9) | AR9: =SUM($V9:AB9)
A10: 9 | B10: Q2 deals low ($20M) | C10: =Assumptions!$B$45*(1-0) | D10: 1 | E10: =Assumptions!$B$5 | F10: =Assumptions!$B$50 | G10: =IF(D10=1,Assumptions!$B$25+Assumptions!$B$26,Assumptions!$B$27)/Assumptions!$B$33 | H10: =1-Assumptions!$B$42-(Assumptions!$B$38+(1-D10)*Assumptions!$B$39/Assumptions!$B$33)/C10 | I10: =-G10 | J10: =IF(1>E10,0,IF(1<=F10,C10,MIN(C10,Assumptions!$B$77)*INDEX(Assumptions!$B$71:$B$76,1)*Assumptions!$B$58))-IF(1>E10,0,IF(1>E10,0,IF(1<=F10,C10,MIN(C10,Assumptions!$B$77)*INDEX(Assumptions!$B$71:$B$76,1)*Assumptions!$B$58))*Assumptions!$B$42+Assumptions!$B$38*IF(1<=F10,1,Assumptions!$B$58)+(1-D10)*Assumptions!$B$39/Assumptions!$B$33)+IF(1=E10,D10*Assumptions!$B$26/Assumptions!$B$33*MAX(0,1-E10/Assumptions!$B$6),0) | K10: =IF(2>E10,0,IF(2<=F10,C10,MIN(C10,Assumptions!$B$77)*INDEX(Assumptions!$B$71:$B$76,2)*Assumptions!$B$58))-IF(2>E10,0,IF(2>E10,0,IF(2<=F10,C10,MIN(C10,Assumptions!$B$77)*INDEX(Assumptions!$B$71:$B$76,2)*Assumptions!$B$58))*Assumptions!$B$42+Assumptions!$B$38*IF(2<=F10,1,Assumptions!$B$58)+(1-D10)*Assumptions!$B$39/Assumptions!$B$33)+IF(2=E10,D10*Assumptions!$B$26/Assumptions!$B$33*MAX(0,1-E10/Assumptions!$B$6),0) | L10: =IF(3>E10,0,IF(3<=F10,C10,MIN(C10,Assumptions!$B$77)*INDEX(Assumptions!$B$71:$B$76,3)*Assumptions!$B$58))-IF(3>E10,0,IF(3>E10,0,IF(3<=F10,C10,MIN(C10,Assumptions!$B$77)*INDEX(Assumptions!$B$71:$B$76,3)*Assumptions!$B$58))*Assumptions!$B$42+Assumptions!$B$38*IF(3<=F10,1,Assumptions!$B$58)+(1-D10)*Assumptions!$B$39/Assumptions!$B$33)+IF(3=E10,D10*Assumptions!$B$26/Assumptions!$B$33*MAX(0,1-E10/Assumptions!$B$6),0) | M10: =IF(4>E10,0,IF(4<=F10,C10,MIN(C10,Assumptions!$B$77)*INDEX(Assumptions!$B$71:$B$76,4)*Assumptions!$B$58))-IF(4>E10,0,IF(4>E10,0,IF(4<=F10,C10,MIN(C10,Assumptions!$B$77)*INDEX(Assumptions!$B$71:$B$76,4)*Assumptions!$B$58))*Assumptions!$B$42+Assumptions!$B$38*IF(4<=F10,1,Assumptions!$B$58)+(1-D10)*Assumptions!$B$39/Assumptions!$B$33)+IF(4=E10,D10*Assumptions!$B$26/Assumptions!$B$33*MAX(0,1-E10/Assumptions!$B$6),0) | N10: =IF(5>E10,0,IF(5<=F10,C10,MIN(C10,Assumptions!$B$77)*INDEX(Assumptions!$B$71:$B$76,5)*Assumptions!$B$58))-IF(5>E10,0,IF(5>E10,0,IF(5<=F10,C10,MIN(C10,Assumptions!$B$77)*INDEX(Assumptions!$B$71:$B$76,5)*Assumptions!$B$58))*Assumptions!$B$42+Assumptions!$B$38*IF(5<=F10,1,Assumptions!$B$58)+(1-D10)*Assumptions!$B$39/Assumptions!$B$33)+IF(5=E10,D10*Assumptions!$B$26/Assumptions!$B$33*MAX(0,1-E10/Assumptions!$B$6),0) | O10: =IF(6>E10,0,IF(6<=F10,C10,MIN(C10,Assumptions!$B$77)*INDEX(Assumptions!$B$71:$B$76,6)*Assumptions!$B$58))-IF(6>E10,0,IF(6>E10,0,IF(6<=F10,C10,MIN(C10,Assumptions!$B$77)*INDEX(Assumptions!$B$71:$B$76,6)*Assumptions!$B$58))*Assumptions!$B$42+Assumptions!$B$38*IF(6<=F10,1,Assumptions!$B$58)+(1-D10)*Assumptions!$B$39/Assumptions!$B$33)+IF(6=E10,D10*Assumptions!$B$26/Assumptions!$B$33*MAX(0,1-E10/Assumptions!$B$6),0) | P10: =IFERROR(IRR(I10:O10),-1) | Q10: =IFERROR(MATCH(TRUE,INDEX(AE10:AK10>=0,0),0)-2+(-INDEX(AE10:AK10,MATCH(TRUE,INDEX(AE10:AK10>=0,0),0)-1))/INDEX(I10:O10,MATCH(TRUE,INDEX(AE10:AK10>=0,0),0)),"never") | R10: =NPV(Assumptions!$B$149,J10:O10)+I10 | S10: =(G10-D10*Assumptions!$B$26/Assumptions!$B$33*MAX(0,1-E10/Assumptions!$B$6)/(1+Assumptions!$B$149)^E10)/(IF(1>E10,0,IF(1<=F10,C10,MIN(C10,Assumptions!$B$77)*INDEX(Assumptions!$B$71:$B$76,1)*Assumptions!$B$58))/(1+Assumptions!$B$149)^1+IF(2>E10,0,IF(2<=F10,C10,MIN(C10,Assumptions!$B$77)*INDEX(Assumptions!$B$71:$B$76,2)*Assumptions!$B$58))/(1+Assumptions!$B$149)^2+IF(3>E10,0,IF(3<=F10,C10,MIN(C10,Assumptions!$B$77)*INDEX(Assumptions!$B$71:$B$76,3)*Assumptions!$B$58))/(1+Assumptions!$B$149)^3+IF(4>E10,0,IF(4<=F10,C10,MIN(C10,Assumptions!$B$77)*INDEX(Assumptions!$B$71:$B$76,4)*Assumptions!$B$58))/(1+Assumptions!$B$149)^4+IF(5>E10,0,IF(5<=F10,C10,MIN(C10,Assumptions!$B$77)*INDEX(Assumptions!$B$71:$B$76,5)*Assumptions!$B$58))/(1+Assumptions!$B$149)^5+IF(6>E10,0,IF(6<=F10,C10,MIN(C10,Assumptions!$B$77)*INDEX(Assumptions!$B$71:$B$76,6)*Assumptions!$B$58))/(1+Assumptions!$B$149)^6) | T10: =(IF(D10=1,Assumptions!$B$25/E10+Assumptions!$B$26/Assumptions!$B$6,Assumptions!$B$25/E10+(Assumptions!$B$27-Assumptions!$B$25)/Assumptions!$B$6)/Assumptions!$B$33)/C10 | U10: =Assumptions!$B$54*G10 | V10: =I10+U10 | W10: =J10-IF(1<=F10,$U10/F10,0) | X10: =K10-IF(2<=F10,$U10/F10,0) | Y10: =L10-IF(3<=F10,$U10/F10,0) | Z10: =M10-IF(4<=F10,$U10/F10,0) | AA10: =N10-IF(5<=F10,$U10/F10,0) | AB10: =O10-IF(6<=F10,$U10/F10,0) | AC10: =IFERROR(IRR(V10:AB10),IF(V10>=0,"no equity at risk",-1)) | AD10: =IFERROR(MATCH(TRUE,INDEX(AL10:AR10>=0,0),0)-2+(-INDEX(AL10:AR10,MATCH(TRUE,INDEX(AL10:AR10>=0,0),0)-1))/INDEX(V10:AB10,MATCH(TRUE,INDEX(AL10:AR10>=0,0),0)),"never") | AE10: =SUM($I10:I10) | AF10: =SUM($I10:J10) | AG10: =SUM($I10:K10) | AH10: =SUM($I10:L10) | AI10: =SUM($I10:M10) | AJ10: =SUM($I10:N10) | AK10: =SUM($I10:O10) | AL10: =SUM($V10:V10) | AM10: =SUM($V10:W10) | AN10: =SUM($V10:X10) | AO10: =SUM($V10:Y10) | AP10: =SUM($V10:Z10) | AQ10: =SUM($V10:AA10) | AR10: =SUM($V10:AB10)
A11: 10 | B11: Q2 deals low ($20M) | C11: =Assumptions!$B$45*(1-0) | D11: 0 | E11: =Assumptions!$B$3 | F11: =Assumptions!$B$50 | G11: =IF(D11=1,Assumptions!$B$25+Assumptions!$B$26,Assumptions!$B$27)/Assumptions!$B$33 | H11: =1-Assumptions!$B$42-(Assumptions!$B$38+(1-D11)*Assumptions!$B$39/Assumptions!$B$33)/C11 | I11: =-G11 | J11: =IF(1>E11,0,IF(1<=F11,C11,MIN(C11,Assumptions!$B$77)*INDEX(Assumptions!$B$71:$B$76,1)*Assumptions!$B$58))-IF(1>E11,0,IF(1>E11,0,IF(1<=F11,C11,MIN(C11,Assumptions!$B$77)*INDEX(Assumptions!$B$71:$B$76,1)*Assumptions!$B$58))*Assumptions!$B$42+Assumptions!$B$38*IF(1<=F11,1,Assumptions!$B$58)+(1-D11)*Assumptions!$B$39/Assumptions!$B$33)+IF(1=E11,D11*Assumptions!$B$26/Assumptions!$B$33*MAX(0,1-E11/Assumptions!$B$6),0) | K11: =IF(2>E11,0,IF(2<=F11,C11,MIN(C11,Assumptions!$B$77)*INDEX(Assumptions!$B$71:$B$76,2)*Assumptions!$B$58))-IF(2>E11,0,IF(2>E11,0,IF(2<=F11,C11,MIN(C11,Assumptions!$B$77)*INDEX(Assumptions!$B$71:$B$76,2)*Assumptions!$B$58))*Assumptions!$B$42+Assumptions!$B$38*IF(2<=F11,1,Assumptions!$B$58)+(1-D11)*Assumptions!$B$39/Assumptions!$B$33)+IF(2=E11,D11*Assumptions!$B$26/Assumptions!$B$33*MAX(0,1-E11/Assumptions!$B$6),0) | L11: =IF(3>E11,0,IF(3<=F11,C11,MIN(C11,Assumptions!$B$77)*INDEX(Assumptions!$B$71:$B$76,3)*Assumptions!$B$58))-IF(3>E11,0,IF(3>E11,0,IF(3<=F11,C11,MIN(C11,Assumptions!$B$77)*INDEX(Assumptions!$B$71:$B$76,3)*Assumptions!$B$58))*Assumptions!$B$42+Assumptions!$B$38*IF(3<=F11,1,Assumptions!$B$58)+(1-D11)*Assumptions!$B$39/Assumptions!$B$33)+IF(3=E11,D11*Assumptions!$B$26/Assumptions!$B$33*MAX(0,1-E11/Assumptions!$B$6),0) | M11: =IF(4>E11,0,IF(4<=F11,C11,MIN(C11,Assumptions!$B$77)*INDEX(Assumptions!$B$71:$B$76,4)*Assumptions!$B$58))-IF(4>E11,0,IF(4>E11,0,IF(4<=F11,C11,MIN(C11,Assumptions!$B$77)*INDEX(Assumptions!$B$71:$B$76,4)*Assumptions!$B$58))*Assumptions!$B$42+Assumptions!$B$38*IF(4<=F11,1,Assumptions!$B$58)+(1-D11)*Assumptions!$B$39/Assumptions!$B$33)+IF(4=E11,D11*Assumptions!$B$26/Assumptions!$B$33*MAX(0,1-E11/Assumptions!$B$6),0) | N11: =IF(5>E11,0,IF(5<=F11,C11,MIN(C11,Assumptions!$B$77)*INDEX(Assumptions!$B$71:$B$76,5)*Assumptions!$B$58))-IF(5>E11,0,IF(5>E11,0,IF(5<=F11,C11,MIN(C11,Assumptions!$B$77)*INDEX(Assumptions!$B$71:$B$76,5)*Assumptions!$B$58))*Assumptions!$B$42+Assumptions!$B$38*IF(5<=F11,1,Assumptions!$B$58)+(1-D11)*Assumptions!$B$39/Assumptions!$B$33)+IF(5=E11,D11*Assumptions!$B$26/Assumptions!$B$33*MAX(0,1-E11/Assumptions!$B$6),0) | O11: =IF(6>E11,0,IF(6<=F11,C11,MIN(C11,Assumptions!$B$77)*INDEX(Assumptions!$B$71:$B$76,6)*Assumptions!$B$58))-IF(6>E11,0,IF(6>E11,0,IF(6<=F11,C11,MIN(C11,Assumptions!$B$77)*INDEX(Assumptions!$B$71:$B$76,6)*Assumptions!$B$58))*Assumptions!$B$42+Assumptions!$B$38*IF(6<=F11,1,Assumptions!$B$58)+(1-D11)*Assumptions!$B$39/Assumptions!$B$33)+IF(6=E11,D11*Assumptions!$B$26/Assumptions!$B$33*MAX(0,1-E11/Assumptions!$B$6),0) | P11: =IFERROR(IRR(I11:O11),-1) | Q11: =IFERROR(MATCH(TRUE,INDEX(AE11:AK11>=0,0),0)-2+(-INDEX(AE11:AK11,MATCH(TRUE,INDEX(AE11:AK11>=0,0),0)-1))/INDEX(I11:O11,MATCH(TRUE,INDEX(AE11:AK11>=0,0),0)),"never") | R11: =NPV(Assumptions!$B$149,J11:O11)+I11 | S11: =(G11-D11*Assumptions!$B$26/Assumptions!$B$33*MAX(0,1-E11/Assumptions!$B$6)/(1+Assumptions!$B$149)^E11)/(IF(1>E11,0,IF(1<=F11,C11,MIN(C11,Assumptions!$B$77)*INDEX(Assumptions!$B$71:$B$76,1)*Assumptions!$B$58))/(1+Assumptions!$B$149)^1+IF(2>E11,0,IF(2<=F11,C11,MIN(C11,Assumptions!$B$77)*INDEX(Assumptions!$B$71:$B$76,2)*Assumptions!$B$58))/(1+Assumptions!$B$149)^2+IF(3>E11,0,IF(3<=F11,C11,MIN(C11,Assumptions!$B$77)*INDEX(Assumptions!$B$71:$B$76,3)*Assumptions!$B$58))/(1+Assumptions!$B$149)^3+IF(4>E11,0,IF(4<=F11,C11,MIN(C11,Assumptions!$B$77)*INDEX(Assumptions!$B$71:$B$76,4)*Assumptions!$B$58))/(1+Assumptions!$B$149)^4+IF(5>E11,0,IF(5<=F11,C11,MIN(C11,Assumptions!$B$77)*INDEX(Assumptions!$B$71:$B$76,5)*Assumptions!$B$58))/(1+Assumptions!$B$149)^5+IF(6>E11,0,IF(6<=F11,C11,MIN(C11,Assumptions!$B$77)*INDEX(Assumptions!$B$71:$B$76,6)*Assumptions!$B$58))/(1+Assumptions!$B$149)^6) | T11: =(IF(D11=1,Assumptions!$B$25/E11+Assumptions!$B$26/Assumptions!$B$6,Assumptions!$B$25/E11+(Assumptions!$B$27-Assumptions!$B$25)/Assumptions!$B$6)/Assumptions!$B$33)/C11 | U11: =Assumptions!$B$54*G11 | V11: =I11+U11 | W11: =J11-IF(1<=F11,$U11/F11,0) | X11: =K11-IF(2<=F11,$U11/F11,0) | Y11: =L11-IF(3<=F11,$U11/F11,0) | Z11: =M11-IF(4<=F11,$U11/F11,0) | AA11: =N11-IF(5<=F11,$U11/F11,0) | AB11: =O11-IF(6<=F11,$U11/F11,0) | AC11: =IFERROR(IRR(V11:AB11),IF(V11>=0,"no equity at risk",-1)) | AD11: =IFERROR(MATCH(TRUE,INDEX(AL11:AR11>=0,0),0)-2+(-INDEX(AL11:AR11,MATCH(TRUE,INDEX(AL11:AR11>=0,0),0)-1))/INDEX(V11:AB11,MATCH(TRUE,INDEX(AL11:AR11>=0,0),0)),"never") | AE11: =SUM($I11:I11) | AF11: =SUM($I11:J11) | AG11: =SUM($I11:K11) | AH11: =SUM($I11:L11) | AI11: =SUM($I11:M11) | AJ11: =SUM($I11:N11) | AK11: =SUM($I11:O11) | AL11: =SUM($V11:V11) | AM11: =SUM($V11:W11) | AN11: =SUM($V11:X11) | AO11: =SUM($V11:Y11) | AP11: =SUM($V11:Z11) | AQ11: =SUM($V11:AA11) | AR11: =SUM($V11:AB11)
A12: 11 | B12: Q2 deals low ($20M) | C12: =Assumptions!$B$45*(1-0) | D12: 0 | E12: =Assumptions!$B$4 | F12: =Assumptions!$B$50 | G12: =IF(D12=1,Assumptions!$B$25+Assumptions!$B$26,Assumptions!$B$27)/Assumptions!$B$33 | H12: =1-Assumptions!$B$42-(Assumptions!$B$38+(1-D12)*Assumptions!$B$39/Assumptions!$B$33)/C12 | I12: =-G12 | J12: =IF(1>E12,0,IF(1<=F12,C12,MIN(C12,Assumptions!$B$77)*INDEX(Assumptions!$B$71:$B$76,1)*Assumptions!$B$58))-IF(1>E12,0,IF(1>E12,0,IF(1<=F12,C12,MIN(C12,Assumptions!$B$77)*INDEX(Assumptions!$B$71:$B$76,1)*Assumptions!$B$58))*Assumptions!$B$42+Assumptions!$B$38*IF(1<=F12,1,Assumptions!$B$58)+(1-D12)*Assumptions!$B$39/Assumptions!$B$33)+IF(1=E12,D12*Assumptions!$B$26/Assumptions!$B$33*MAX(0,1-E12/Assumptions!$B$6),0) | K12: =IF(2>E12,0,IF(2<=F12,C12,MIN(C12,Assumptions!$B$77)*INDEX(Assumptions!$B$71:$B$76,2)*Assumptions!$B$58))-IF(2>E12,0,IF(2>E12,0,IF(2<=F12,C12,MIN(C12,Assumptions!$B$77)*INDEX(Assumptions!$B$71:$B$76,2)*Assumptions!$B$58))*Assumptions!$B$42+Assumptions!$B$38*IF(2<=F12,1,Assumptions!$B$58)+(1-D12)*Assumptions!$B$39/Assumptions!$B$33)+IF(2=E12,D12*Assumptions!$B$26/Assumptions!$B$33*MAX(0,1-E12/Assumptions!$B$6),0) | L12: =IF(3>E12,0,IF(3<=F12,C12,MIN(C12,Assumptions!$B$77)*INDEX(Assumptions!$B$71:$B$76,3)*Assumptions!$B$58))-IF(3>E12,0,IF(3>E12,0,IF(3<=F12,C12,MIN(C12,Assumptions!$B$77)*INDEX(Assumptions!$B$71:$B$76,3)*Assumptions!$B$58))*Assumptions!$B$42+Assumptions!$B$38*IF(3<=F12,1,Assumptions!$B$58)+(1-D12)*Assumptions!$B$39/Assumptions!$B$33)+IF(3=E12,D12*Assumptions!$B$26/Assumptions!$B$33*MAX(0,1-E12/Assumptions!$B$6),0) | M12: =IF(4>E12,0,IF(4<=F12,C12,MIN(C12,Assumptions!$B$77)*INDEX(Assumptions!$B$71:$B$76,4)*Assumptions!$B$58))-IF(4>E12,0,IF(4>E12,0,IF(4<=F12,C12,MIN(C12,Assumptions!$B$77)*INDEX(Assumptions!$B$71:$B$76,4)*Assumptions!$B$58))*Assumptions!$B$42+Assumptions!$B$38*IF(4<=F12,1,Assumptions!$B$58)+(1-D12)*Assumptions!$B$39/Assumptions!$B$33)+IF(4=E12,D12*Assumptions!$B$26/Assumptions!$B$33*MAX(0,1-E12/Assumptions!$B$6),0) | N12: =IF(5>E12,0,IF(5<=F12,C12,MIN(C12,Assumptions!$B$77)*INDEX(Assumptions!$B$71:$B$76,5)*Assumptions!$B$58))-IF(5>E12,0,IF(5>E12,0,IF(5<=F12,C12,MIN(C12,Assumptions!$B$77)*INDEX(Assumptions!$B$71:$B$76,5)*Assumptions!$B$58))*Assumptions!$B$42+Assumptions!$B$38*IF(5<=F12,1,Assumptions!$B$58)+(1-D12)*Assumptions!$B$39/Assumptions!$B$33)+IF(5=E12,D12*Assumptions!$B$26/Assumptions!$B$33*MAX(0,1-E12/Assumptions!$B$6),0) | O12: =IF(6>E12,0,IF(6<=F12,C12,MIN(C12,Assumptions!$B$77)*INDEX(Assumptions!$B$71:$B$76,6)*Assumptions!$B$58))-IF(6>E12,0,IF(6>E12,0,IF(6<=F12,C12,MIN(C12,Assumptions!$B$77)*INDEX(Assumptions!$B$71:$B$76,6)*Assumptions!$B$58))*Assumptions!$B$42+Assumptions!$B$38*IF(6<=F12,1,Assumptions!$B$58)+(1-D12)*Assumptions!$B$39/Assumptions!$B$33)+IF(6=E12,D12*Assumptions!$B$26/Assumptions!$B$33*MAX(0,1-E12/Assumptions!$B$6),0) | P12: =IFERROR(IRR(I12:O12),-1) | Q12: =IFERROR(MATCH(TRUE,INDEX(AE12:AK12>=0,0),0)-2+(-INDEX(AE12:AK12,MATCH(TRUE,INDEX(AE12:AK12>=0,0),0)-1))/INDEX(I12:O12,MATCH(TRUE,INDEX(AE12:AK12>=0,0),0)),"never") | R12: =NPV(Assumptions!$B$149,J12:O12)+I12 | S12: =(G12-D12*Assumptions!$B$26/Assumptions!$B$33*MAX(0,1-E12/Assumptions!$B$6)/(1+Assumptions!$B$149)^E12)/(IF(1>E12,0,IF(1<=F12,C12,MIN(C12,Assumptions!$B$77)*INDEX(Assumptions!$B$71:$B$76,1)*Assumptions!$B$58))/(1+Assumptions!$B$149)^1+IF(2>E12,0,IF(2<=F12,C12,MIN(C12,Assumptions!$B$77)*INDEX(Assumptions!$B$71:$B$76,2)*Assumptions!$B$58))/(1+Assumptions!$B$149)^2+IF(3>E12,0,IF(3<=F12,C12,MIN(C12,Assumptions!$B$77)*INDEX(Assumptions!$B$71:$B$76,3)*Assumptions!$B$58))/(1+Assumptions!$B$149)^3+IF(4>E12,0,IF(4<=F12,C12,MIN(C12,Assumptions!$B$77)*INDEX(Assumptions!$B$71:$B$76,4)*Assumptions!$B$58))/(1+Assumptions!$B$149)^4+IF(5>E12,0,IF(5<=F12,C12,MIN(C12,Assumptions!$B$77)*INDEX(Assumptions!$B$71:$B$76,5)*Assumptions!$B$58))/(1+Assumptions!$B$149)^5+IF(6>E12,0,IF(6<=F12,C12,MIN(C12,Assumptions!$B$77)*INDEX(Assumptions!$B$71:$B$76,6)*Assumptions!$B$58))/(1+Assumptions!$B$149)^6) | T12: =(IF(D12=1,Assumptions!$B$25/E12+Assumptions!$B$26/Assumptions!$B$6,Assumptions!$B$25/E12+(Assumptions!$B$27-Assumptions!$B$25)/Assumptions!$B$6)/Assumptions!$B$33)/C12 | U12: =Assumptions!$B$54*G12 | V12: =I12+U12 | W12: =J12-IF(1<=F12,$U12/F12,0) | X12: =K12-IF(2<=F12,$U12/F12,0) | Y12: =L12-IF(3<=F12,$U12/F12,0) | Z12: =M12-IF(4<=F12,$U12/F12,0) | AA12: =N12-IF(5<=F12,$U12/F12,0) | AB12: =O12-IF(6<=F12,$U12/F12,0) | AC12: =IFERROR(IRR(V12:AB12),IF(V12>=0,"no equity at risk",-1)) | AD12: =IFERROR(MATCH(TRUE,INDEX(AL12:AR12>=0,0),0)-2+(-INDEX(AL12:AR12,MATCH(TRUE,INDEX(AL12:AR12>=0,0),0)-1))/INDEX(V12:AB12,MATCH(TRUE,INDEX(AL12:AR12>=0,0),0)),"never") | AE12: =SUM($I12:I12) | AF12: =SUM($I12:J12) | AG12: =SUM($I12:K12) | AH12: =SUM($I12:L12) | AI12: =SUM($I12:M12) | AJ12: =SUM($I12:N12) | AK12: =SUM($I12:O12) | AL12: =SUM($V12:V12) | AM12: =SUM($V12:W12) | AN12: =SUM($V12:X12) | AO12: =SUM($V12:Y12) | AP12: =SUM($V12:Z12) | AQ12: =SUM($V12:AA12) | AR12: =SUM($V12:AB12)
A13: 12 | B13: Q2 deals low ($20M) | C13: =Assumptions!$B$45*(1-0) | D13: 0 | E13: =Assumptions!$B$5 | F13: =Assumptions!$B$50 | G13: =IF(D13=1,Assumptions!$B$25+Assumptions!$B$26,Assumptions!$B$27)/Assumptions!$B$33 | H13: =1-Assumptions!$B$42-(Assumptions!$B$38+(1-D13)*Assumptions!$B$39/Assumptions!$B$33)/C13 | I13: =-G13 | J13: =IF(1>E13,0,IF(1<=F13,C13,MIN(C13,Assumptions!$B$77)*INDEX(Assumptions!$B$71:$B$76,1)*Assumptions!$B$58))-IF(1>E13,0,IF(1>E13,0,IF(1<=F13,C13,MIN(C13,Assumptions!$B$77)*INDEX(Assumptions!$B$71:$B$76,1)*Assumptions!$B$58))*Assumptions!$B$42+Assumptions!$B$38*IF(1<=F13,1,Assumptions!$B$58)+(1-D13)*Assumptions!$B$39/Assumptions!$B$33)+IF(1=E13,D13*Assumptions!$B$26/Assumptions!$B$33*MAX(0,1-E13/Assumptions!$B$6),0) | K13: =IF(2>E13,0,IF(2<=F13,C13,MIN(C13,Assumptions!$B$77)*INDEX(Assumptions!$B$71:$B$76,2)*Assumptions!$B$58))-IF(2>E13,0,IF(2>E13,0,IF(2<=F13,C13,MIN(C13,Assumptions!$B$77)*INDEX(Assumptions!$B$71:$B$76,2)*Assumptions!$B$58))*Assumptions!$B$42+Assumptions!$B$38*IF(2<=F13,1,Assumptions!$B$58)+(1-D13)*Assumptions!$B$39/Assumptions!$B$33)+IF(2=E13,D13*Assumptions!$B$26/Assumptions!$B$33*MAX(0,1-E13/Assumptions!$B$6),0) | L13: =IF(3>E13,0,IF(3<=F13,C13,MIN(C13,Assumptions!$B$77)*INDEX(Assumptions!$B$71:$B$76,3)*Assumptions!$B$58))-IF(3>E13,0,IF(3>E13,0,IF(3<=F13,C13,MIN(C13,Assumptions!$B$77)*INDEX(Assumptions!$B$71:$B$76,3)*Assumptions!$B$58))*Assumptions!$B$42+Assumptions!$B$38*IF(3<=F13,1,Assumptions!$B$58)+(1-D13)*Assumptions!$B$39/Assumptions!$B$33)+IF(3=E13,D13*Assumptions!$B$26/Assumptions!$B$33*MAX(0,1-E13/Assumptions!$B$6),0) | M13: =IF(4>E13,0,IF(4<=F13,C13,MIN(C13,Assumptions!$B$77)*INDEX(Assumptions!$B$71:$B$76,4)*Assumptions!$B$58))-IF(4>E13,0,IF(4>E13,0,IF(4<=F13,C13,MIN(C13,Assumptions!$B$77)*INDEX(Assumptions!$B$71:$B$76,4)*Assumptions!$B$58))*Assumptions!$B$42+Assumptions!$B$38*IF(4<=F13,1,Assumptions!$B$58)+(1-D13)*Assumptions!$B$39/Assumptions!$B$33)+IF(4=E13,D13*Assumptions!$B$26/Assumptions!$B$33*MAX(0,1-E13/Assumptions!$B$6),0) | N13: =IF(5>E13,0,IF(5<=F13,C13,MIN(C13,Assumptions!$B$77)*INDEX(Assumptions!$B$71:$B$76,5)*Assumptions!$B$58))-IF(5>E13,0,IF(5>E13,0,IF(5<=F13,C13,MIN(C13,Assumptions!$B$77)*INDEX(Assumptions!$B$71:$B$76,5)*Assumptions!$B$58))*Assumptions!$B$42+Assumptions!$B$38*IF(5<=F13,1,Assumptions!$B$58)+(1-D13)*Assumptions!$B$39/Assumptions!$B$33)+IF(5=E13,D13*Assumptions!$B$26/Assumptions!$B$33*MAX(0,1-E13/Assumptions!$B$6),0) | O13: =IF(6>E13,0,IF(6<=F13,C13,MIN(C13,Assumptions!$B$77)*INDEX(Assumptions!$B$71:$B$76,6)*Assumptions!$B$58))-IF(6>E13,0,IF(6>E13,0,IF(6<=F13,C13,MIN(C13,Assumptions!$B$77)*INDEX(Assumptions!$B$71:$B$76,6)*Assumptions!$B$58))*Assumptions!$B$42+Assumptions!$B$38*IF(6<=F13,1,Assumptions!$B$58)+(1-D13)*Assumptions!$B$39/Assumptions!$B$33)+IF(6=E13,D13*Assumptions!$B$26/Assumptions!$B$33*MAX(0,1-E13/Assumptions!$B$6),0) | P13: =IFERROR(IRR(I13:O13),-1) | Q13: =IFERROR(MATCH(TRUE,INDEX(AE13:AK13>=0,0),0)-2+(-INDEX(AE13:AK13,MATCH(TRUE,INDEX(AE13:AK13>=0,0),0)-1))/INDEX(I13:O13,MATCH(TRUE,INDEX(AE13:AK13>=0,0),0)),"never") | R13: =NPV(Assumptions!$B$149,J13:O13)+I13 | S13: =(G13-D13*Assumptions!$B$26/Assumptions!$B$33*MAX(0,1-E13/Assumptions!$B$6)/(1+Assumptions!$B$149)^E13)/(IF(1>E13,0,IF(1<=F13,C13,MIN(C13,Assumptions!$B$77)*INDEX(Assumptions!$B$71:$B$76,1)*Assumptions!$B$58))/(1+Assumptions!$B$149)^1+IF(2>E13,0,IF(2<=F13,C13,MIN(C13,Assumptions!$B$77)*INDEX(Assumptions!$B$71:$B$76,2)*Assumptions!$B$58))/(1+Assumptions!$B$149)^2+IF(3>E13,0,IF(3<=F13,C13,MIN(C13,Assumptions!$B$77)*INDEX(Assumptions!$B$71:$B$76,3)*Assumptions!$B$58))/(1+Assumptions!$B$149)^3+IF(4>E13,0,IF(4<=F13,C13,MIN(C13,Assumptions!$B$77)*INDEX(Assumptions!$B$71:$B$76,4)*Assumptions!$B$58))/(1+Assumptions!$B$149)^4+IF(5>E13,0,IF(5<=F13,C13,MIN(C13,Assumptions!$B$77)*INDEX(Assumptions!$B$71:$B$76,5)*Assumptions!$B$58))/(1+Assumptions!$B$149)^5+IF(6>E13,0,IF(6<=F13,C13,MIN(C13,Assumptions!$B$77)*INDEX(Assumptions!$B$71:$B$76,6)*Assumptions!$B$58))/(1+Assumptions!$B$149)^6) | T13: =(IF(D13=1,Assumptions!$B$25/E13+Assumptions!$B$26/Assumptions!$B$6,Assumptions!$B$25/E13+(Assumptions!$B$27-Assumptions!$B$25)/Assumptions!$B$6)/Assumptions!$B$33)/C13 | U13: =Assumptions!$B$54*G13 | V13: =I13+U13 | W13: =J13-IF(1<=F13,$U13/F13,0) | X13: =K13-IF(2<=F13,$U13/F13,0) | Y13: =L13-IF(3<=F13,$U13/F13,0) | Z13: =M13-IF(4<=F13,$U13/F13,0) | AA13: =N13-IF(5<=F13,$U13/F13,0) | AB13: =O13-IF(6<=F13,$U13/F13,0) | AC13: =IFERROR(IRR(V13:AB13),IF(V13>=0,"no equity at risk",-1)) | AD13: =IFERROR(MATCH(TRUE,INDEX(AL13:AR13>=0,0),0)-2+(-INDEX(AL13:AR13,MATCH(TRUE,INDEX(AL13:AR13>=0,0),0)-1))/INDEX(V13:AB13,MATCH(TRUE,INDEX(AL13:AR13>=0,0),0)),"never") | AE13: =SUM($I13:I13) | AF13: =SUM($I13:J13) | AG13: =SUM($I13:K13) | AH13: =SUM($I13:L13) | AI13: =SUM($I13:M13) | AJ13: =SUM($I13:N13) | AK13: =SUM($I13:O13) | AL13: =SUM($V13:V13) | AM13: =SUM($V13:W13) | AN13: =SUM($V13:X13) | AO13: =SUM($V13:Y13) | AP13: =SUM($V13:Z13) | AQ13: =SUM($V13:AA13) | AR13: =SUM($V13:AB13)
A14: 13 | B14: Q2 deals high ($25M) | C14: =Assumptions!$B$46*(1-0) | D14: 1 | E14: =Assumptions!$B$3 | F14: =Assumptions!$B$50 | G14: =IF(D14=1,Assumptions!$B$25+Assumptions!$B$26,Assumptions!$B$27)/Assumptions!$B$33 | H14: =1-Assumptions!$B$42-(Assumptions!$B$38+(1-D14)*Assumptions!$B$39/Assumptions!$B$33)/C14 | I14: =-G14 | J14: =IF(1>E14,0,IF(1<=F14,C14,MIN(C14,Assumptions!$B$77)*INDEX(Assumptions!$B$71:$B$76,1)*Assumptions!$B$58))-IF(1>E14,0,IF(1>E14,0,IF(1<=F14,C14,MIN(C14,Assumptions!$B$77)*INDEX(Assumptions!$B$71:$B$76,1)*Assumptions!$B$58))*Assumptions!$B$42+Assumptions!$B$38*IF(1<=F14,1,Assumptions!$B$58)+(1-D14)*Assumptions!$B$39/Assumptions!$B$33)+IF(1=E14,D14*Assumptions!$B$26/Assumptions!$B$33*MAX(0,1-E14/Assumptions!$B$6),0) | K14: =IF(2>E14,0,IF(2<=F14,C14,MIN(C14,Assumptions!$B$77)*INDEX(Assumptions!$B$71:$B$76,2)*Assumptions!$B$58))-IF(2>E14,0,IF(2>E14,0,IF(2<=F14,C14,MIN(C14,Assumptions!$B$77)*INDEX(Assumptions!$B$71:$B$76,2)*Assumptions!$B$58))*Assumptions!$B$42+Assumptions!$B$38*IF(2<=F14,1,Assumptions!$B$58)+(1-D14)*Assumptions!$B$39/Assumptions!$B$33)+IF(2=E14,D14*Assumptions!$B$26/Assumptions!$B$33*MAX(0,1-E14/Assumptions!$B$6),0) | L14: =IF(3>E14,0,IF(3<=F14,C14,MIN(C14,Assumptions!$B$77)*INDEX(Assumptions!$B$71:$B$76,3)*Assumptions!$B$58))-IF(3>E14,0,IF(3>E14,0,IF(3<=F14,C14,MIN(C14,Assumptions!$B$77)*INDEX(Assumptions!$B$71:$B$76,3)*Assumptions!$B$58))*Assumptions!$B$42+Assumptions!$B$38*IF(3<=F14,1,Assumptions!$B$58)+(1-D14)*Assumptions!$B$39/Assumptions!$B$33)+IF(3=E14,D14*Assumptions!$B$26/Assumptions!$B$33*MAX(0,1-E14/Assumptions!$B$6),0) | M14: =IF(4>E14,0,IF(4<=F14,C14,MIN(C14,Assumptions!$B$77)*INDEX(Assumptions!$B$71:$B$76,4)*Assumptions!$B$58))-IF(4>E14,0,IF(4>E14,0,IF(4<=F14,C14,MIN(C14,Assumptions!$B$77)*INDEX(Assumptions!$B$71:$B$76,4)*Assumptions!$B$58))*Assumptions!$B$42+Assumptions!$B$38*IF(4<=F14,1,Assumptions!$B$58)+(1-D14)*Assumptions!$B$39/Assumptions!$B$33)+IF(4=E14,D14*Assumptions!$B$26/Assumptions!$B$33*MAX(0,1-E14/Assumptions!$B$6),0) | N14: =IF(5>E14,0,IF(5<=F14,C14,MIN(C14,Assumptions!$B$77)*INDEX(Assumptions!$B$71:$B$76,5)*Assumptions!$B$58))-IF(5>E14,0,IF(5>E14,0,IF(5<=F14,C14,MIN(C14,Assumptions!$B$77)*INDEX(Assumptions!$B$71:$B$76,5)*Assumptions!$B$58))*Assumptions!$B$42+Assumptions!$B$38*IF(5<=F14,1,Assumptions!$B$58)+(1-D14)*Assumptions!$B$39/Assumptions!$B$33)+IF(5=E14,D14*Assumptions!$B$26/Assumptions!$B$33*MAX(0,1-E14/Assumptions!$B$6),0) | O14: =IF(6>E14,0,IF(6<=F14,C14,MIN(C14,Assumptions!$B$77)*INDEX(Assumptions!$B$71:$B$76,6)*Assumptions!$B$58))-IF(6>E14,0,IF(6>E14,0,IF(6<=F14,C14,MIN(C14,Assumptions!$B$77)*INDEX(Assumptions!$B$71:$B$76,6)*Assumptions!$B$58))*Assumptions!$B$42+Assumptions!$B$38*IF(6<=F14,1,Assumptions!$B$58)+(1-D14)*Assumptions!$B$39/Assumptions!$B$33)+IF(6=E14,D14*Assumptions!$B$26/Assumptions!$B$33*MAX(0,1-E14/Assumptions!$B$6),0) | P14: =IFERROR(IRR(I14:O14),-1) | Q14: =IFERROR(MATCH(TRUE,INDEX(AE14:AK14>=0,0),0)-2+(-INDEX(AE14:AK14,MATCH(TRUE,INDEX(AE14:AK14>=0,0),0)-1))/INDEX(I14:O14,MATCH(TRUE,INDEX(AE14:AK14>=0,0),0)),"never") | R14: =NPV(Assumptions!$B$149,J14:O14)+I14 | S14: =(G14-D14*Assumptions!$B$26/Assumptions!$B$33*MAX(0,1-E14/Assumptions!$B$6)/(1+Assumptions!$B$149)^E14)/(IF(1>E14,0,IF(1<=F14,C14,MIN(C14,Assumptions!$B$77)*INDEX(Assumptions!$B$71:$B$76,1)*Assumptions!$B$58))/(1+Assumptions!$B$149)^1+IF(2>E14,0,IF(2<=F14,C14,MIN(C14,Assumptions!$B$77)*INDEX(Assumptions!$B$71:$B$76,2)*Assumptions!$B$58))/(1+Assumptions!$B$149)^2+IF(3>E14,0,IF(3<=F14,C14,MIN(C14,Assumptions!$B$77)*INDEX(Assumptions!$B$71:$B$76,3)*Assumptions!$B$58))/(1+Assumptions!$B$149)^3+IF(4>E14,0,IF(4<=F14,C14,MIN(C14,Assumptions!$B$77)*INDEX(Assumptions!$B$71:$B$76,4)*Assumptions!$B$58))/(1+Assumptions!$B$149)^4+IF(5>E14,0,IF(5<=F14,C14,MIN(C14,Assumptions!$B$77)*INDEX(Assumptions!$B$71:$B$76,5)*Assumptions!$B$58))/(1+Assumptions!$B$149)^5+IF(6>E14,0,IF(6<=F14,C14,MIN(C14,Assumptions!$B$77)*INDEX(Assumptions!$B$71:$B$76,6)*Assumptions!$B$58))/(1+Assumptions!$B$149)^6) | T14: =(IF(D14=1,Assumptions!$B$25/E14+Assumptions!$B$26/Assumptions!$B$6,Assumptions!$B$25/E14+(Assumptions!$B$27-Assumptions!$B$25)/Assumptions!$B$6)/Assumptions!$B$33)/C14 | U14: =Assumptions!$B$54*G14 | V14: =I14+U14 | W14: =J14-IF(1<=F14,$U14/F14,0) | X14: =K14-IF(2<=F14,$U14/F14,0) | Y14: =L14-IF(3<=F14,$U14/F14,0) | Z14: =M14-IF(4<=F14,$U14/F14,0) | AA14: =N14-IF(5<=F14,$U14/F14,0) | AB14: =O14-IF(6<=F14,$U14/F14,0) | AC14: =IFERROR(IRR(V14:AB14),IF(V14>=0,"no equity at risk",-1)) | AD14: =IFERROR(MATCH(TRUE,INDEX(AL14:AR14>=0,0),0)-2+(-INDEX(AL14:AR14,MATCH(TRUE,INDEX(AL14:AR14>=0,0),0)-1))/INDEX(V14:AB14,MATCH(TRUE,INDEX(AL14:AR14>=0,0),0)),"never") | AE14: =SUM($I14:I14) | AF14: =SUM($I14:J14) | AG14: =SUM($I14:K14) | AH14: =SUM($I14:L14) | AI14: =SUM($I14:M14) | AJ14: =SUM($I14:N14) | AK14: =SUM($I14:O14) | AL14: =SUM($V14:V14) | AM14: =SUM($V14:W14) | AN14: =SUM($V14:X14) | AO14: =SUM($V14:Y14) | AP14: =SUM($V14:Z14) | AQ14: =SUM($V14:AA14) | AR14: =SUM($V14:AB14)
A15: 14 | B15: Q2 deals high ($25M) | C15: =Assumptions!$B$46*(1-0) | D15: 1 | E15: =Assumptions!$B$4 | F15: =Assumptions!$B$50 | G15: =IF(D15=1,Assumptions!$B$25+Assumptions!$B$26,Assumptions!$B$27)/Assumptions!$B$33 | H15: =1-Assumptions!$B$42-(Assumptions!$B$38+(1-D15)*Assumptions!$B$39/Assumptions!$B$33)/C15 | I15: =-G15 | J15: =IF(1>E15,0,IF(1<=F15,C15,MIN(C15,Assumptions!$B$77)*INDEX(Assumptions!$B$71:$B$76,1)*Assumptions!$B$58))-IF(1>E15,0,IF(1>E15,0,IF(1<=F15,C15,MIN(C15,Assumptions!$B$77)*INDEX(Assumptions!$B$71:$B$76,1)*Assumptions!$B$58))*Assumptions!$B$42+Assumptions!$B$38*IF(1<=F15,1,Assumptions!$B$58)+(1-D15)*Assumptions!$B$39/Assumptions!$B$33)+IF(1=E15,D15*Assumptions!$B$26/Assumptions!$B$33*MAX(0,1-E15/Assumptions!$B$6),0) | K15: =IF(2>E15,0,IF(2<=F15,C15,MIN(C15,Assumptions!$B$77)*INDEX(Assumptions!$B$71:$B$76,2)*Assumptions!$B$58))-IF(2>E15,0,IF(2>E15,0,IF(2<=F15,C15,MIN(C15,Assumptions!$B$77)*INDEX(Assumptions!$B$71:$B$76,2)*Assumptions!$B$58))*Assumptions!$B$42+Assumptions!$B$38*IF(2<=F15,1,Assumptions!$B$58)+(1-D15)*Assumptions!$B$39/Assumptions!$B$33)+IF(2=E15,D15*Assumptions!$B$26/Assumptions!$B$33*MAX(0,1-E15/Assumptions!$B$6),0) | L15: =IF(3>E15,0,IF(3<=F15,C15,MIN(C15,Assumptions!$B$77)*INDEX(Assumptions!$B$71:$B$76,3)*Assumptions!$B$58))-IF(3>E15,0,IF(3>E15,0,IF(3<=F15,C15,MIN(C15,Assumptions!$B$77)*INDEX(Assumptions!$B$71:$B$76,3)*Assumptions!$B$58))*Assumptions!$B$42+Assumptions!$B$38*IF(3<=F15,1,Assumptions!$B$58)+(1-D15)*Assumptions!$B$39/Assumptions!$B$33)+IF(3=E15,D15*Assumptions!$B$26/Assumptions!$B$33*MAX(0,1-E15/Assumptions!$B$6),0) | M15: =IF(4>E15,0,IF(4<=F15,C15,MIN(C15,Assumptions!$B$77)*INDEX(Assumptions!$B$71:$B$76,4)*Assumptions!$B$58))-IF(4>E15,0,IF(4>E15,0,IF(4<=F15,C15,MIN(C15,Assumptions!$B$77)*INDEX(Assumptions!$B$71:$B$76,4)*Assumptions!$B$58))*Assumptions!$B$42+Assumptions!$B$38*IF(4<=F15,1,Assumptions!$B$58)+(1-D15)*Assumptions!$B$39/Assumptions!$B$33)+IF(4=E15,D15*Assumptions!$B$26/Assumptions!$B$33*MAX(0,1-E15/Assumptions!$B$6),0) | N15: =IF(5>E15,0,IF(5<=F15,C15,MIN(C15,Assumptions!$B$77)*INDEX(Assumptions!$B$71:$B$76,5)*Assumptions!$B$58))-IF(5>E15,0,IF(5>E15,0,IF(5<=F15,C15,MIN(C15,Assumptions!$B$77)*INDEX(Assumptions!$B$71:$B$76,5)*Assumptions!$B$58))*Assumptions!$B$42+Assumptions!$B$38*IF(5<=F15,1,Assumptions!$B$58)+(1-D15)*Assumptions!$B$39/Assumptions!$B$33)+IF(5=E15,D15*Assumptions!$B$26/Assumptions!$B$33*MAX(0,1-E15/Assumptions!$B$6),0) | O15: =IF(6>E15,0,IF(6<=F15,C15,MIN(C15,Assumptions!$B$77)*INDEX(Assumptions!$B$71:$B$76,6)*Assumptions!$B$58))-IF(6>E15,0,IF(6>E15,0,IF(6<=F15,C15,MIN(C15,Assumptions!$B$77)*INDEX(Assumptions!$B$71:$B$76,6)*Assumptions!$B$58))*Assumptions!$B$42+Assumptions!$B$38*IF(6<=F15,1,Assumptions!$B$58)+(1-D15)*Assumptions!$B$39/Assumptions!$B$33)+IF(6=E15,D15*Assumptions!$B$26/Assumptions!$B$33*MAX(0,1-E15/Assumptions!$B$6),0) | P15: =IFERROR(IRR(I15:O15),-1) | Q15: =IFERROR(MATCH(TRUE,INDEX(AE15:AK15>=0,0),0)-2+(-INDEX(AE15:AK15,MATCH(TRUE,INDEX(AE15:AK15>=0,0),0)-1))/INDEX(I15:O15,MATCH(TRUE,INDEX(AE15:AK15>=0,0),0)),"never") | R15: =NPV(Assumptions!$B$149,J15:O15)+I15 | S15: =(G15-D15*Assumptions!$B$26/Assumptions!$B$33*MAX(0,1-E15/Assumptions!$B$6)/(1+Assumptions!$B$149)^E15)/(IF(1>E15,0,IF(1<=F15,C15,MIN(C15,Assumptions!$B$77)*INDEX(Assumptions!$B$71:$B$76,1)*Assumptions!$B$58))/(1+Assumptions!$B$149)^1+IF(2>E15,0,IF(2<=F15,C15,MIN(C15,Assumptions!$B$77)*INDEX(Assumptions!$B$71:$B$76,2)*Assumptions!$B$58))/(1+Assumptions!$B$149)^2+IF(3>E15,0,IF(3<=F15,C15,MIN(C15,Assumptions!$B$77)*INDEX(Assumptions!$B$71:$B$76,3)*Assumptions!$B$58))/(1+Assumptions!$B$149)^3+IF(4>E15,0,IF(4<=F15,C15,MIN(C15,Assumptions!$B$77)*INDEX(Assumptions!$B$71:$B$76,4)*Assumptions!$B$58))/(1+Assumptions!$B$149)^4+IF(5>E15,0,IF(5<=F15,C15,MIN(C15,Assumptions!$B$77)*INDEX(Assumptions!$B$71:$B$76,5)*Assumptions!$B$58))/(1+Assumptions!$B$149)^5+IF(6>E15,0,IF(6<=F15,C15,MIN(C15,Assumptions!$B$77)*INDEX(Assumptions!$B$71:$B$76,6)*Assumptions!$B$58))/(1+Assumptions!$B$149)^6) | T15: =(IF(D15=1,Assumptions!$B$25/E15+Assumptions!$B$26/Assumptions!$B$6,Assumptions!$B$25/E15+(Assumptions!$B$27-Assumptions!$B$25)/Assumptions!$B$6)/Assumptions!$B$33)/C15 | U15: =Assumptions!$B$54*G15 | V15: =I15+U15 | W15: =J15-IF(1<=F15,$U15/F15,0) | X15: =K15-IF(2<=F15,$U15/F15,0) | Y15: =L15-IF(3<=F15,$U15/F15,0) | Z15: =M15-IF(4<=F15,$U15/F15,0) | AA15: =N15-IF(5<=F15,$U15/F15,0) | AB15: =O15-IF(6<=F15,$U15/F15,0) | AC15: =IFERROR(IRR(V15:AB15),IF(V15>=0,"no equity at risk",-1)) | AD15: =IFERROR(MATCH(TRUE,INDEX(AL15:AR15>=0,0),0)-2+(-INDEX(AL15:AR15,MATCH(TRUE,INDEX(AL15:AR15>=0,0),0)-1))/INDEX(V15:AB15,MATCH(TRUE,INDEX(AL15:AR15>=0,0),0)),"never") | AE15: =SUM($I15:I15) | AF15: =SUM($I15:J15) | AG15: =SUM($I15:K15) | AH15: =SUM($I15:L15) | AI15: =SUM($I15:M15) | AJ15: =SUM($I15:N15) | AK15: =SUM($I15:O15) | AL15: =SUM($V15:V15) | AM15: =SUM($V15:W15) | AN15: =SUM($V15:X15) | AO15: =SUM($V15:Y15) | AP15: =SUM($V15:Z15) | AQ15: =SUM($V15:AA15) | AR15: =SUM($V15:AB15)
A16: 15 | B16: Q2 deals high ($25M) | C16: =Assumptions!$B$46*(1-0) | D16: 1 | E16: =Assumptions!$B$5 | F16: =Assumptions!$B$50 | G16: =IF(D16=1,Assumptions!$B$25+Assumptions!$B$26,Assumptions!$B$27)/Assumptions!$B$33 | H16: =1-Assumptions!$B$42-(Assumptions!$B$38+(1-D16)*Assumptions!$B$39/Assumptions!$B$33)/C16 | I16: =-G16 | J16: =IF(1>E16,0,IF(1<=F16,C16,MIN(C16,Assumptions!$B$77)*INDEX(Assumptions!$B$71:$B$76,1)*Assumptions!$B$58))-IF(1>E16,0,IF(1>E16,0,IF(1<=F16,C16,MIN(C16,Assumptions!$B$77)*INDEX(Assumptions!$B$71:$B$76,1)*Assumptions!$B$58))*Assumptions!$B$42+Assumptions!$B$38*IF(1<=F16,1,Assumptions!$B$58)+(1-D16)*Assumptions!$B$39/Assumptions!$B$33)+IF(1=E16,D16*Assumptions!$B$26/Assumptions!$B$33*MAX(0,1-E16/Assumptions!$B$6),0) | K16: =IF(2>E16,0,IF(2<=F16,C16,MIN(C16,Assumptions!$B$77)*INDEX(Assumptions!$B$71:$B$76,2)*Assumptions!$B$58))-IF(2>E16,0,IF(2>E16,0,IF(2<=F16,C16,MIN(C16,Assumptions!$B$77)*INDEX(Assumptions!$B$71:$B$76,2)*Assumptions!$B$58))*Assumptions!$B$42+Assumptions!$B$38*IF(2<=F16,1,Assumptions!$B$58)+(1-D16)*Assumptions!$B$39/Assumptions!$B$33)+IF(2=E16,D16*Assumptions!$B$26/Assumptions!$B$33*MAX(0,1-E16/Assumptions!$B$6),0) | L16: =IF(3>E16,0,IF(3<=F16,C16,MIN(C16,Assumptions!$B$77)*INDEX(Assumptions!$B$71:$B$76,3)*Assumptions!$B$58))-IF(3>E16,0,IF(3>E16,0,IF(3<=F16,C16,MIN(C16,Assumptions!$B$77)*INDEX(Assumptions!$B$71:$B$76,3)*Assumptions!$B$58))*Assumptions!$B$42+Assumptions!$B$38*IF(3<=F16,1,Assumptions!$B$58)+(1-D16)*Assumptions!$B$39/Assumptions!$B$33)+IF(3=E16,D16*Assumptions!$B$26/Assumptions!$B$33*MAX(0,1-E16/Assumptions!$B$6),0) | M16: =IF(4>E16,0,IF(4<=F16,C16,MIN(C16,Assumptions!$B$77)*INDEX(Assumptions!$B$71:$B$76,4)*Assumptions!$B$58))-IF(4>E16,0,IF(4>E16,0,IF(4<=F16,C16,MIN(C16,Assumptions!$B$77)*INDEX(Assumptions!$B$71:$B$76,4)*Assumptions!$B$58))*Assumptions!$B$42+Assumptions!$B$38*IF(4<=F16,1,Assumptions!$B$58)+(1-D16)*Assumptions!$B$39/Assumptions!$B$33)+IF(4=E16,D16*Assumptions!$B$26/Assumptions!$B$33*MAX(0,1-E16/Assumptions!$B$6),0) | N16: =IF(5>E16,0,IF(5<=F16,C16,MIN(C16,Assumptions!$B$77)*INDEX(Assumptions!$B$71:$B$76,5)*Assumptions!$B$58))-IF(5>E16,0,IF(5>E16,0,IF(5<=F16,C16,MIN(C16,Assumptions!$B$77)*INDEX(Assumptions!$B$71:$B$76,5)*Assumptions!$B$58))*Assumptions!$B$42+Assumptions!$B$38*IF(5<=F16,1,Assumptions!$B$58)+(1-D16)*Assumptions!$B$39/Assumptions!$B$33)+IF(5=E16,D16*Assumptions!$B$26/Assumptions!$B$33*MAX(0,1-E16/Assumptions!$B$6),0) | O16: =IF(6>E16,0,IF(6<=F16,C16,MIN(C16,Assumptions!$B$77)*INDEX(Assumptions!$B$71:$B$76,6)*Assumptions!$B$58))-IF(6>E16,0,IF(6>E16,0,IF(6<=F16,C16,MIN(C16,Assumptions!$B$77)*INDEX(Assumptions!$B$71:$B$76,6)*Assumptions!$B$58))*Assumptions!$B$42+Assumptions!$B$38*IF(6<=F16,1,Assumptions!$B$58)+(1-D16)*Assumptions!$B$39/Assumptions!$B$33)+IF(6=E16,D16*Assumptions!$B$26/Assumptions!$B$33*MAX(0,1-E16/Assumptions!$B$6),0) | P16: =IFERROR(IRR(I16:O16),-1) | Q16: =IFERROR(MATCH(TRUE,INDEX(AE16:AK16>=0,0),0)-2+(-INDEX(AE16:AK16,MATCH(TRUE,INDEX(AE16:AK16>=0,0),0)-1))/INDEX(I16:O16,MATCH(TRUE,INDEX(AE16:AK16>=0,0),0)),"never") | R16: =NPV(Assumptions!$B$149,J16:O16)+I16 | S16: =(G16-D16*Assumptions!$B$26/Assumptions!$B$33*MAX(0,1-E16/Assumptions!$B$6)/(1+Assumptions!$B$149)^E16)/(IF(1>E16,0,IF(1<=F16,C16,MIN(C16,Assumptions!$B$77)*INDEX(Assumptions!$B$71:$B$76,1)*Assumptions!$B$58))/(1+Assumptions!$B$149)^1+IF(2>E16,0,IF(2<=F16,C16,MIN(C16,Assumptions!$B$77)*INDEX(Assumptions!$B$71:$B$76,2)*Assumptions!$B$58))/(1+Assumptions!$B$149)^2+IF(3>E16,0,IF(3<=F16,C16,MIN(C16,Assumptions!$B$77)*INDEX(Assumptions!$B$71:$B$76,3)*Assumptions!$B$58))/(1+Assumptions!$B$149)^3+IF(4>E16,0,IF(4<=F16,C16,MIN(C16,Assumptions!$B$77)*INDEX(Assumptions!$B$71:$B$76,4)*Assumptions!$B$58))/(1+Assumptions!$B$149)^4+IF(5>E16,0,IF(5<=F16,C16,MIN(C16,Assumptions!$B$77)*INDEX(Assumptions!$B$71:$B$76,5)*Assumptions!$B$58))/(1+Assumptions!$B$149)^5+IF(6>E16,0,IF(6<=F16,C16,MIN(C16,Assumptions!$B$77)*INDEX(Assumptions!$B$71:$B$76,6)*Assumptions!$B$58))/(1+Assumptions!$B$149)^6) | T16: =(IF(D16=1,Assumptions!$B$25/E16+Assumptions!$B$26/Assumptions!$B$6,Assumptions!$B$25/E16+(Assumptions!$B$27-Assumptions!$B$25)/Assumptions!$B$6)/Assumptions!$B$33)/C16 | U16: =Assumptions!$B$54*G16 | V16: =I16+U16 | W16: =J16-IF(1<=F16,$U16/F16,0) | X16: =K16-IF(2<=F16,$U16/F16,0) | Y16: =L16-IF(3<=F16,$U16/F16,0) | Z16: =M16-IF(4<=F16,$U16/F16,0) | AA16: =N16-IF(5<=F16,$U16/F16,0) | AB16: =O16-IF(6<=F16,$U16/F16,0) | AC16: =IFERROR(IRR(V16:AB16),IF(V16>=0,"no equity at risk",-1)) | AD16: =IFERROR(MATCH(TRUE,INDEX(AL16:AR16>=0,0),0)-2+(-INDEX(AL16:AR16,MATCH(TRUE,INDEX(AL16:AR16>=0,0),0)-1))/INDEX(V16:AB16,MATCH(TRUE,INDEX(AL16:AR16>=0,0),0)),"never") | AE16: =SUM($I16:I16) | AF16: =SUM($I16:J16) | AG16: =SUM($I16:K16) | AH16: =SUM($I16:L16) | AI16: =SUM($I16:M16) | AJ16: =SUM($I16:N16) | AK16: =SUM($I16:O16) | AL16: =SUM($V16:V16) | AM16: =SUM($V16:W16) | AN16: =SUM($V16:X16) | AO16: =SUM($V16:Y16) | AP16: =SUM($V16:Z16) | AQ16: =SUM($V16:AA16) | AR16: =SUM($V16:AB16)
A17: 16 | B17: Q2 deals high ($25M) | C17: =Assumptions!$B$46*(1-0) | D17: 0 | E17: =Assumptions!$B$3 | F17: =Assumptions!$B$50 | G17: =IF(D17=1,Assumptions!$B$25+Assumptions!$B$26,Assumptions!$B$27)/Assumptions!$B$33 | H17: =1-Assumptions!$B$42-(Assumptions!$B$38+(1-D17)*Assumptions!$B$39/Assumptions!$B$33)/C17 | I17: =-G17 | J17: =IF(1>E17,0,IF(1<=F17,C17,MIN(C17,Assumptions!$B$77)*INDEX(Assumptions!$B$71:$B$76,1)*Assumptions!$B$58))-IF(1>E17,0,IF(1>E17,0,IF(1<=F17,C17,MIN(C17,Assumptions!$B$77)*INDEX(Assumptions!$B$71:$B$76,1)*Assumptions!$B$58))*Assumptions!$B$42+Assumptions!$B$38*IF(1<=F17,1,Assumptions!$B$58)+(1-D17)*Assumptions!$B$39/Assumptions!$B$33)+IF(1=E17,D17*Assumptions!$B$26/Assumptions!$B$33*MAX(0,1-E17/Assumptions!$B$6),0) | K17: =IF(2>E17,0,IF(2<=F17,C17,MIN(C17,Assumptions!$B$77)*INDEX(Assumptions!$B$71:$B$76,2)*Assumptions!$B$58))-IF(2>E17,0,IF(2>E17,0,IF(2<=F17,C17,MIN(C17,Assumptions!$B$77)*INDEX(Assumptions!$B$71:$B$76,2)*Assumptions!$B$58))*Assumptions!$B$42+Assumptions!$B$38*IF(2<=F17,1,Assumptions!$B$58)+(1-D17)*Assumptions!$B$39/Assumptions!$B$33)+IF(2=E17,D17*Assumptions!$B$26/Assumptions!$B$33*MAX(0,1-E17/Assumptions!$B$6),0) | L17: =IF(3>E17,0,IF(3<=F17,C17,MIN(C17,Assumptions!$B$77)*INDEX(Assumptions!$B$71:$B$76,3)*Assumptions!$B$58))-IF(3>E17,0,IF(3>E17,0,IF(3<=F17,C17,MIN(C17,Assumptions!$B$77)*INDEX(Assumptions!$B$71:$B$76,3)*Assumptions!$B$58))*Assumptions!$B$42+Assumptions!$B$38*IF(3<=F17,1,Assumptions!$B$58)+(1-D17)*Assumptions!$B$39/Assumptions!$B$33)+IF(3=E17,D17*Assumptions!$B$26/Assumptions!$B$33*MAX(0,1-E17/Assumptions!$B$6),0) | M17: =IF(4>E17,0,IF(4<=F17,C17,MIN(C17,Assumptions!$B$77)*INDEX(Assumptions!$B$71:$B$76,4)*Assumptions!$B$58))-IF(4>E17,0,IF(4>E17,0,IF(4<=F17,C17,MIN(C17,Assumptions!$B$77)*INDEX(Assumptions!$B$71:$B$76,4)*Assumptions!$B$58))*Assumptions!$B$42+Assumptions!$B$38*IF(4<=F17,1,Assumptions!$B$58)+(1-D17)*Assumptions!$B$39/Assumptions!$B$33)+IF(4=E17,D17*Assumptions!$B$26/Assumptions!$B$33*MAX(0,1-E17/Assumptions!$B$6),0) | N17: =IF(5>E17,0,IF(5<=F17,C17,MIN(C17,Assumptions!$B$77)*INDEX(Assumptions!$B$71:$B$76,5)*Assumptions!$B$58))-IF(5>E17,0,IF(5>E17,0,IF(5<=F17,C17,MIN(C17,Assumptions!$B$77)*INDEX(Assumptions!$B$71:$B$76,5)*Assumptions!$B$58))*Assumptions!$B$42+Assumptions!$B$38*IF(5<=F17,1,Assumptions!$B$58)+(1-D17)*Assumptions!$B$39/Assumptions!$B$33)+IF(5=E17,D17*Assumptions!$B$26/Assumptions!$B$33*MAX(0,1-E17/Assumptions!$B$6),0) | O17: =IF(6>E17,0,IF(6<=F17,C17,MIN(C17,Assumptions!$B$77)*INDEX(Assumptions!$B$71:$B$76,6)*Assumptions!$B$58))-IF(6>E17,0,IF(6>E17,0,IF(6<=F17,C17,MIN(C17,Assumptions!$B$77)*INDEX(Assumptions!$B$71:$B$76,6)*Assumptions!$B$58))*Assumptions!$B$42+Assumptions!$B$38*IF(6<=F17,1,Assumptions!$B$58)+(1-D17)*Assumptions!$B$39/Assumptions!$B$33)+IF(6=E17,D17*Assumptions!$B$26/Assumptions!$B$33*MAX(0,1-E17/Assumptions!$B$6),0) | P17: =IFERROR(IRR(I17:O17),-1) | Q17: =IFERROR(MATCH(TRUE,INDEX(AE17:AK17>=0,0),0)-2+(-INDEX(AE17:AK17,MATCH(TRUE,INDEX(AE17:AK17>=0,0),0)-1))/INDEX(I17:O17,MATCH(TRUE,INDEX(AE17:AK17>=0,0),0)),"never") | R17: =NPV(Assumptions!$B$149,J17:O17)+I17 | S17: =(G17-D17*Assumptions!$B$26/Assumptions!$B$33*MAX(0,1-E17/Assumptions!$B$6)/(1+Assumptions!$B$149)^E17)/(IF(1>E17,0,IF(1<=F17,C17,MIN(C17,Assumptions!$B$77)*INDEX(Assumptions!$B$71:$B$76,1)*Assumptions!$B$58))/(1+Assumptions!$B$149)^1+IF(2>E17,0,IF(2<=F17,C17,MIN(C17,Assumptions!$B$77)*INDEX(Assumptions!$B$71:$B$76,2)*Assumptions!$B$58))/(1+Assumptions!$B$149)^2+IF(3>E17,0,IF(3<=F17,C17,MIN(C17,Assumptions!$B$77)*INDEX(Assumptions!$B$71:$B$76,3)*Assumptions!$B$58))/(1+Assumptions!$B$149)^3+IF(4>E17,0,IF(4<=F17,C17,MIN(C17,Assumptions!$B$77)*INDEX(Assumptions!$B$71:$B$76,4)*Assumptions!$B$58))/(1+Assumptions!$B$149)^4+IF(5>E17,0,IF(5<=F17,C17,MIN(C17,Assumptions!$B$77)*INDEX(Assumptions!$B$71:$B$76,5)*Assumptions!$B$58))/(1+Assumptions!$B$149)^5+IF(6>E17,0,IF(6<=F17,C17,MIN(C17,Assumptions!$B$77)*INDEX(Assumptions!$B$71:$B$76,6)*Assumptions!$B$58))/(1+Assumptions!$B$149)^6) | T17: =(IF(D17=1,Assumptions!$B$25/E17+Assumptions!$B$26/Assumptions!$B$6,Assumptions!$B$25/E17+(Assumptions!$B$27-Assumptions!$B$25)/Assumptions!$B$6)/Assumptions!$B$33)/C17 | U17: =Assumptions!$B$54*G17 | V17: =I17+U17 | W17: =J17-IF(1<=F17,$U17/F17,0) | X17: =K17-IF(2<=F17,$U17/F17,0) | Y17: =L17-IF(3<=F17,$U17/F17,0) | Z17: =M17-IF(4<=F17,$U17/F17,0) | AA17: =N17-IF(5<=F17,$U17/F17,0) | AB17: =O17-IF(6<=F17,$U17/F17,0) | AC17: =IFERROR(IRR(V17:AB17),IF(V17>=0,"no equity at risk",-1)) | AD17: =IFERROR(MATCH(TRUE,INDEX(AL17:AR17>=0,0),0)-2+(-INDEX(AL17:AR17,MATCH(TRUE,INDEX(AL17:AR17>=0,0),0)-1))/INDEX(V17:AB17,MATCH(TRUE,INDEX(AL17:AR17>=0,0),0)),"never") | AE17: =SUM($I17:I17) | AF17: =SUM($I17:J17) | AG17: =SUM($I17:K17) | AH17: =SUM($I17:L17) | AI17: =SUM($I17:M17) | AJ17: =SUM($I17:N17) | AK17: =SUM($I17:O17) | AL17: =SUM($V17:V17) | AM17: =SUM($V17:W17) | AN17: =SUM($V17:X17) | AO17: =SUM($V17:Y17) | AP17: =SUM($V17:Z17) | AQ17: =SUM($V17:AA17) | AR17: =SUM($V17:AB17)
