Workbook

Sheet Cover
A1: Nebius (NBIS) driver-based model
A2: VERSION v0.7 – PROVISIONAL
A3: Build date: 2026-10-04. v0.3 base approved (terminal excludes Q4'30 spend for post-horizon MW and that MW; GPU capex lead 3 qtrs vs billing; history scenario-invariant; bear replacement at bear price path; bull Blackwell 6.25% cut after Rubin + next-gen -1.7%/yr).
A4: v0.7 changes: GB300 IT ($22M) and gross ($26.4M) co-equal (basis not disclosed by management); payback note + tests ($32M capex, $2M opex, prepayments counted); Rubin new deals priced directly at $18M/IT MW-yr (bull 20 / bear 16; no IT/gross toggle; short-term $40-50M tranche GB300-only); Rubin capex $41M leased (bull 41, bear 48.5; $32M outer-bull sensitivity; owned $56M), low-medium confidence; $775M facility $0 drawn in base; Aug-26 converts counted once; 2027 funding plan (remaining ATM + 2 x $5B converts on Aug-26 terms; bear ATM at -40%, converts shut) with post-funding per-share values; converts debt vs shares at the solved price (original principal), full-conversion and NSS counts; Avride burn added back when Avride is valued (bull double count fixed). v0.6 changes: multi-year new-deal $/MW flat nominal within generation through 2028 then -3%/yr (bear -6%/yr from 2027; 31% post-Rubin stress separate) - removes per-chip ageing double count; one linked new-deal input ($/GPU-hr x GPUs/IT MW x hours x occupancy); Rubin 1.2x GB300 per GPU-hr; payback and asset-floor checks (Payback_Floor tab); stake values per Filings Note 5. v0.5 changes: short-term tranche = 5% of TOTAL avg active MW at $45M x 85% occupancy (tests 2/10%, 0% floor); unsold new MW priced separately from RPO-contracted MW (sens $18/22/25); 6/30 deferred revenue released on Reported current/non-current split, new prepayments straight-line over 4 yrs; backlog floor checks; new-deal $/MW basis selector (IT $22M base; gross-equivalent $26.4M/IT MW); prepayments by customer type (signed Microsoft/Meta 0% new; new hyperscaler 30%; other 38.5% -> 22.5% for 2028+ signings); closing deferred revenue run-off deducted from EV (cash double-count fix); SFC: none in model. v0.4 changes: split capex lead (shell/power 3 qtrs, GPUs 2 qtrs ahead of billing); price path year 2+ decline (-2.5/-6/-9.5%) + post-Rubin cut in all scenarios; terminal g from fundamentals (g = RR x RONC, reinvestment deducted); Rubin premium vs GB300 open input at per-MW parity; MW-basis selector; CLT1 rent/prepay; Inferize, June-exit, Vineland-shutdown and peer-margin switches; Funding and Bridge tabs. Also: new-deal pricing for 2027+ MW (multi-year $22M/IT MW-yr + 10% short-term $45M with post-Rubin cut/recovery); customer prepayments 38.5% of new-build capex (toggle); Vineland shutdown wired to Capacity table at $14.5M/IT MW-yr + Bloom-slip toggle; Capacity proposed MW path as MWSel 4 scenario (not base); GPU history anchored to ~30k at 3/31/25.
A5: Key outputs (live, current scenario)
A6: Scenario | B6: =CHOOSE(Scen,"BULL","BASE","BEAR") -> BASE
A7: DCF EV ($M) | B7: =V_EV -> -183.73714
A8: FD value / share ($) | B8: =V_PS -> 0.01
A9: 12-month PT ($) | B9: =V_PT -> 0
A10: First quarter liquidity < 0 | B10: =Liq_NegQ -> Q1'28
A11: Market EV ($M) | B11: =V_MKTEV -> 74654.719
A13: Notes - open items
A14: OPEN: FY26 capex below the $20-25B guide (Aug 12 2026 call): v0.3 $18.1B (~$1.9B short); v0.4 split lead $16.7B (~$3.3B short); possible early 2027 shell/power or deposits not in the path. Check: Checks 'FY26 capex vs company guide'. | B14: Owner: Filings / Capacity
A15: OPEN: funding plan is ESTIMATED, not guidance. Base pre-plan YE27 liquidity -$13.5B (v0.6 -$9.5B: facility $0, Rubin capex $41M) -> plan sized at ATM 12.27M sh + 2 x $6.4B converts (Aug-26 terms) to reach ~MinCash $2B at YE27; first negative quarter moves Q2'27 -> Q1'28; 2028-30 still needs ~$36B more. | B15: Owner: Capacity
A16: OPEN: Rubin new-deal revenue $18M/IT MW-yr direct (bull 20 / bear 16; two contracts, medium-low) and Rubin capex $41M leased / $56M owned (bull 41, bear 48.5; $32M outer bull only) - LOW-MEDIUM confidence; Capacity reconciles networking ($3.6M vs GB300 $6.1M) Tuesday. Base EV swings -$5.3B / +$5.6B on Rubin revenue $16/$20M. | B16: Owner: GPU Market
A17: OPEN: AIB CLT1 prepayment (undisclosed; default $0) and Inferize price (press $100-150M, toggle off). | B17: Owner: Filings
A18: OPEN: Vineland shutdown default OFF (VinShutSel 0); scenarios/weights are Capacity judgment (prob-weighted Q4'26 loss ~$68M at $14.5M/IT MW-yr vs Capacity ~$67M); SLA credits undisclosed; genset power saving not credited. | B18: Owner: Capacity
A19: OPEN: Capacity proposed MW path is a scenario only (MWSel 4) until Capacity's Tuesday file; new-deal $/MW basis (IT vs gross) medium-low confidence; short-term share 10% is an estimate. | B19: Owner: Capacity / Filings
A20: OPEN: ARR scope / whether $3.0B ARR includes signed-not-billing tranches; unexplained ARR residual ~$0.6B shown as a line, not plugged. | B20: Owner: Filings
A21: OPEN: YE27 ~950 MW IT normalization is a placeholder pending Capacity's basis column. | B21: Owner: Capacity
A22: OPEN: Q3'26 transfer into service (model $4,702M) pending Q3 filing; depreciation start dates (material weakness) flagged. | B22: Owner: Filings
A23: FLAGS: base DCF EV ~ -$0.2B (IT) / +$2.3B (gross) -> equity value and per-share $0 on BOTH bases (DCF EV below asset floor $3.6B); bull EV $90.4B (>3x base); bear EV -$25.7B; bull YE27 liquidity -$3.4B even after plan; bear ATM 61.8M sh at $145.69 exceeds ~20% AGM issuance authority (~57.5M); FY26 capex $16.9B below $20-25B guide; FY30 margin 70.2% above peer +8pp; IT payback 28 mo vs mgmt 22 (gross 22.6) - test does not discriminate (fits IT at $32M capex, $2M opex, or prepayments counted). See Checks and Payback_Floor. | B23: Owner: Modeling / GPU Market

Sheet README
A1: Nebius (NBIS) driver model - README
A3: Save path: /workspace/nebius/model/nebius_model.xlsx. Quarterly Q1'24-Q2'26 actuals (Hist, tagged Reported/Derived/Estimated/Not disclosed + best estimate + source), Q3'26-Q4'30 forecast, FY roll-ups AI:AO.
A4: Scenario: Inputs!D4 (1 Bull / 2 Base / 3 Bear). Blue = input; orange = placeholder; yellow = estimated/consensus; black = formula.
A5: Flow: Inputs -> Sites (contracted / energized [Capacity file] / mgmt-connected; MWSel; BillLag; PUE basis) -> Pricing -> Contracts (tranches, power ceiling, Q4 bridge) -> Revenue (3 books) -> Capex_DA (vintage cohorts, PISLag, impairment, cap. interest, dep-yield) -> Financing -> PnL -> CashFlow -> Shares -> Valuation (DCF, dilution solve, EV bridge, EV/MW) -> KPIs / Outputs / Sensitivity / Checks.
A6: Circularity: no Excel iterative calc needed. Valuation solves value/share by 15 unrolled fixed-point steps; DilPxMode 1 = SharePx for quarterly dilution.
A7: Converts: DilMethod 1 if-converted all / 2 ITM only (default; step dilution at conversion prices) / 3 net-share. Converted principal is removed from debt (Checks row 1).
A8: Static snapshot tables on Outputs / Sensitivity / Valuation memo rows / Checks (bull 3x, scenario-invariance) come from LibreOffice recalcs in snap.py; re-run snap.py after changing inputs.

Sheet Bridge
A1: EV bridge v0.1 -> v0.3 -> v0.4 (STATIC, filled by snap.py)
A2: Base scenario. Each row = cumulative settings recomputed in the CURRENT model (bug fixes such as the renewal-formula bracket and scenario-invariant history are in every row). $B and $/share are FD value/share.
A4: Step | B4: DCF EV $B | C4: Change $B | D4: FD $/share | E4: Change $/sh | F4: 12m PT $ | G4: FY26 rev $M | H4: FY27 rev $M | I4: FY28 rev $M | J4: FY27 EBITDA $M | K4: YE27 liquidity $M | L4: First neg. qtr
A5: v0.1 (as reported) | B5: 45.499764 | D5: 117.21424 | F5: 132.45209 | G5: 2400.637 | H5: 8242.0189 | I5: 22266.612 | J5: 4575.8582 | K5: -4456.7617 | L5: Q4'27
A6: + fleet ratio forecast-only / capex on driver MW (FixMgmt) | B6: 48.823167 | C6: 3.3234033 | D6: 127.47273 | E6: 10.258497 | F6: 144.04419 | G6: 2400.637 | H6: 8242.0189 | I6: 22266.612 | J6: 4606.0461 | K6: -4408.0848 | L6: Q4'27
A7: + terminal on Q4'30 exit incl. Q1'31 MW (include both) | B7: 102.75467 | C7: 53.931501 | D7: 277.20861 | E7: 149.73587 | F7: 313.24573 | G7: 2400.637 | H7: 8242.0189 | I7: 22266.612 | J7: 4606.0461 | K7: -4408.0848 | L7: Q4'27
A8: + TV run-off floor | B8: 102.75467 | C8: 0 | D8: 277.20861 | E8: 0 | F8: 313.24573 | G8: 2400.637 | H8: 8242.0189 | I8: 22266.612 | J8: 4606.0461 | K8: -4408.0848 | L8: Q4'27
A9: + owned-site O&M | B9: 91.634048 | C9: -11.12062 | D9: 247.25781 | E9: -29.950795 | F9: 279.40133 | G9: 2400.637 | H9: 8242.0189 | I9: 22266.612 | J9: 4517.4726 | K9: -4518.475 | L9: Q4'27
A10: + H2'26 repricing (= v0.2) | B10: 102.45081 | C10: 10.816757 | D10: 276.36392 | E10: 29.106113 | F10: 312.29124 | G10: 2425.3295 | H10: 8517.5153 | I10: 22648.736 | J10: 4713.075 | K10: -4310.0666 | L10: Q4'27
A11: + exclude both Q4'30 spend & Q1'31 MW | B11: 86.363871 | C11: -16.086934 | D11: 233.08315 | E11: -43.280772 | F11: 263.38396 | G11: 2425.3295 | H11: 8517.5153 | I11: 22648.736 | J11: 4713.075 | K11: -4310.0666 | L11: Q4'27
A12: + GPU capex lead 3 qtrs (= v0.3) | B12: 94.115927 | C12: 7.7520558 | D12: 248.19387 | E12: 15.110715 | F12: 280.45907 | G12: 2425.3295 | H12: 8517.5153 | I12: 22648.736 | J12: 4713.075 | K12: -7264.8692 | L12: Q2'27
A13: + split capex lead: shell/power 3, GPUs 2 qtrs | B13: 87.921521 | C13: -6.1944054 | D13: 233.7087 | E13: -14.485164 | F13: 264.09084 | G13: 2425.3295 | H13: 8517.5153 | I13: 22648.736 | J13: 4713.075 | K13: -7160.9335 | L13: Q3'27
A14: + price path: post-Rubin cut 22% + -6%/yr from year 2 | B14: 94.973211 | C14: 7.0516897 | D14: 252.68078 | E14: 18.972078 | F14: 285.52928 | G14: 2425.3295 | H14: 8102.5841 | I14: 22384.539 | J14: 4418.4739 | K14: -7450.3255 | L14: Q3'27
A15: + Rubin premium at per-MW parity (1.56x GB300) | B15: 153.79061 | C15: 58.817396 | D15: 406.65048 | E15: 153.9697 | F15: 459.51504 | G15: 2425.3295 | H15: 8140.6586 | I15: 24633.629 | J15: 4445.5068 | K15: -7423.7798 | L15: Q3'27
A16: + CLT1 rent $2.2M/IT MW-yr | B16: 154.02622 | C16: 0.23561158 | D16: 407.25495 | E16: 0.60447567 | F16: 460.1981 | G16: 2425.3295 | H16: 8140.6586 | I16: 24633.629 | J16: 4447.4208 | K16: -7421.8657 | L16: Q3'27
A17: + terminal g from fundamentals | B17: 125.81969 | C17: -28.206529 | D17: 334.88941 | E17: -72.365546 | F17: 378.42503 | G17: 2425.3295 | H17: 8140.6586 | I17: 24633.629 | J17: 4447.4208 | K17: -7421.8657 | L17: Q3'27
... A34: + 2027 funding plan: ATM 12.27M sh + 2 x $6.4B converts; post-funding per-share (= v0.7) | B34: -0.18373714 | C34: 0.12485947 | D34: 0.01 | E34: 0 | F34: 0 | G34: 2423.4083 | H34: 7621.7173 | I34: 19606.895 | J34: 4078.9726 | K34: 2073.2027 | L34: Q1'28
A37: Horizon per-share values (FD value/share rolled at Ke; excludes future funding dilution - see Funding tab)
A38: Scenario | B38: Today | C38: 6-month | D38: 12-month PT | E38: 3-year
A39: Base (live) | B39: 0.01 | C39: 0 | D39: 0 | E39: 0
A40: Bull | B40: 235.23358 | C40: 248.77456 | D40: 263.27824 | E40: 330.25623
A41: Bear | B41: 0.01 | C41: 0 | D41: 0 | E41: 0
A44: New-MW pricing vs IREN >$20M/IT MW-yr ($M per IT MW-yr). GB300 GPU-hour engine (legacy fleet) at Oct-1 list x RealRes x Util_Res; new 2027+ MW at new-deal blend (col G)
A45: Scenario | B45: GB300 gross | C45: net leased (-$2.2M rent) | D45: net owned (-O&M) | E45: Rubin gross | F45: IREN gross / leased / owned | G45: New-deal blend gross
A46: Base (live) | B46: 30.157546 | C46: 27.957546 | D46: 29.407546 | E46: 23.160995 | F46: 20.0 / 17.8 / 19.25 | G46: 22.39175
A47: Bull | B47: 43.041696 | C47: 40.841696 | D47: 42.291696 | E47: 33.056023 | F47: 20.0 / 17.8 / 19.25 | G47: 25.742188
A48: Bear | B48: 22.272793 | C48: 20.072793 | D48: 21.522793 | E48: 17.105505 | F48: 20.0 / 17.8 / 19.25 | G48: 19.881353
A51: v0.5 BASE RANGE: 12m PT ($/share) by short-term share (of TOTAL active MW) x new-deal $/MW basis, with / without prepayment decay (STATIC). Green = base; yellow = supported tests; orange = gross-MW basis (alternative reading of slide); red = equity floored at 0
A52: Prepayment decay ON (base) | B52: ST share 0% (floor) | C52: ST share 2% | D52: ST share 5% | E52: ST share 10%
A53: IT basis $22M/IT MW | B53: 0 | C53: 0 | D53: 0 | E53: 0
A54: Gross-MW basis = $26.4M/IT MW | B54: 0 | C54: 0 | D54: 0 | E54: 0
A55: EV $B / YE27 liq $B / 1st neg - IT | B55: -3.3 / 1.9 / Q1'28 | C55: -2.1 / 2.0 / Q1'28 | D55: -0.2 / 2.1 / Q1'28 | E55: 2.9 / 2.2 / Q1'28
A56: EV $B / YE27 liq $B / 1st neg - gross | B56: 0.1 / 2.3 / Q1'28 | C56: 1.0 / 2.4 / Q1'28 | D56: 2.3 / 2.4 / Q1'28 | E56: 4.6 / 2.5 / Q1'28
A58: Prepayment decay OFF (other deals 38.5% flat) | B58: ST share 0% (floor) | C58: ST share 2% | D58: ST share 5% | E58: ST share 10%
A59: IT basis $22M/IT MW | B59: 0 | C59: 0 | D59: 0 | E59: 0
A60: Gross-MW basis = $26.4M/IT MW | B60: 0 | C60: 0 | D60: 0 | E60: 0.57124883
A61: EV $B / YE27 liq $B / 1st neg - IT | B61: -1.5 / 1.9 / Q1'28 | C61: -0.3 / 2.0 / Q1'28 | D61: 1.6 / 2.1 / Q1'28 | E61: 4.7 / 2.2 / Q1'28
A62: EV $B / YE27 liq $B / 1st neg - gross | B62: 1.8 / 2.3 / Q1'28 | C62: 2.7 / 2.4 / Q1'28 | D62: 4.1 / 2.4 / Q1'28 | E62: 6.4 / 2.5 / Q1'28

Sheet Payback_Floor
A1: Payback check, new-deal price cases, EBITDA per IT MW by generation, and asset floor (live formulas). Inputs blue.
A3: Leased GB300 capex per IT MW ($M; GPU + network + storage, no shell) | B3: 41.3 | C3: Capacity gpu_mw_capex.xlsx colo base (~$41M)
A4: Leased Vera Rubin capex per IT MW ($M) - base (LOW-MEDIUM confidence) | B4: 41 | C4: v0.7: flat to GB300 (SemiAnalysis TCO; Capacity at MS rack cost $42-48M); bull 41, bear 48.5, outer bull 32 (soft)
A5: Owned GB300 capex per IT MW ($M, incl. shell/power) | B5: 53 | C5: Capacity owned base 53 (range 43-70)
A6: Owned Vera Rubin capex per IT MW ($M) | B6: 56 | C6: v0.7: $53-59M (base 56); was 43
A7: Opex per IT MW-yr (rent $2.0-2.5M + power + ops), fixed across generations | B7: 4.5 | C7: Range $4-5M; does NOT fall at the Rubin switch
A8: Management payback target (months) | B8: 22 | C8: Q2'26 letter: 1 year 10 months, prepayments excluded (footnote basis)
A9: Asset life for unlevered IRR (yrs; capex at t0, flat EBITDA, no residual, pre-tax) | B9: 5 | C9: GPU life 5 yrs (model base)
A10: A) New-deal price cases - $/IT MW-yr next to implied $/GPU-hr. GB300: one linked input (ND_Px x 491 x 8,760 x ND_Occ), IT vs gross toggle. RUBIN: direct $/IT MW-yr (no IT/gross toggle)
A11: Case | B11: IT reading $M/IT MW | C11: IT $/GPU-hr | D11: Gross reading $M/IT MW | E11: Gross $/GPU-hr | F11: $/GPU-hr at 400/MW (ref only)
A12: GB300 NVL72 (491 GPUs/IT MW) | B12: =MYRate -> 22 | C12: =ND_Px -> 5.1148992 | D12: =MYRate*ND_GrossX -> 26.410758 | E12: =ND_Px*ND_GrossX -> 6.1403803
A13: Vera Rubin $16M/IT MW [bear] | B13: =16 -> 16 | C13: =16*1000000/(GPUMW_N*8760) -> 5.7077626 | D13: same (no toggle) | F13: =16*1000000/(RubinGPUMW_D*8760) -> 4.56621
A14: Vera Rubin $18M/IT MW [base] | B14: =18 -> 18 | C14: =18*1000000/(GPUMW_N*8760) -> 6.4212329 | D14: same (no toggle) | F14: =18*1000000/(RubinGPUMW_D*8760) -> 5.1369863
A15: Vera Rubin $20M/IT MW [bull] | B15: =20 -> 20 | C15: =20*1000000/(GPUMW_N*8760) -> 7.1347032 | D15: same (no toggle) | F15: =20*1000000/(RubinGPUMW_D*8760) -> 5.7077626
A16: Vera Rubin at live RubinMW | B16: =RubinMW -> 18 | C16: =RubinMW*1000000/(GPUMW_N*8760) -> 6.4212329 | D16: same (no toggle) | F16: =RubinMW*1000000/(RubinGPUMW_D*8760) -> 5.1369863
A17: Benchmarks: IREN new 3-yr GB300 ~$4.65/GPU-hr (>$20M/IT MW); Rubin: Anthropic-Nscale ~$16.2M/MW (6-yr, MW basis unknown); WhiteFiber-Prime Intellect 576 VR200 ~$108.2M/3 yrs = ~$7.15/GPU-hr (~$20M/IT MW if packages counted, medium). GB300 basis not disclosed by management.
A19: B) EBITDA per IT MW-yr by generation (opex fixed across generations; Rubin = RubinMW, no toggle)
B20: GB300 IT | C20: Rubin (RubinMW) | D20: Change | E20: GB300 gross | F20: Rubin (RubinMW) | G20: Change
A21: Revenue per IT MW-yr | B21: =B12 -> 22 | C21: =RubinMW -> 18 | D21: =C21/B21-1 -> -0.18181818 | E21: =D12 -> 26.410758 | F21: =RubinMW -> 18 | G21: =F21/E21-1 -> -0.31845954
A22: Opex per IT MW-yr (PB_Opex) | B22: =PB_Opex -> 4.5 | C22: =PB_Opex -> 4.5 | E22: =PB_Opex -> 4.5 | F22: =PB_Opex -> 4.5
A23: EBITDA per IT MW-yr | B23: =B21-B22 -> 17.5 | C23: =C21-C22 -> 13.5 | D23: =C23/B23-1 -> -0.22857143 | E23: =E21-E22 -> 21.910758 | F23: =F21-F22 -> 13.5 | G23: =F23/E23-1 -> -0.38386431
A24: Memo: model's own leased opex/IT MW = RentMW x PUE + power (PUE x 8,760 x PowerPx) + OM_MW | B24: =RentMW*PUE+PUE*8760*PowerPx/1000000+OM_MW -> 4.38375
A26: C) PAYBACK (months) = capex / (revenue - opex) x 12; prepayments EXCLUDED unless stated. Flag = within +/-3 months of 22. IRR = unlevered pre-tax, capex at t0, flat EBITDA over PB_Life, no residual
A27: Case | B27: IT / Rubin payback | C27: flag | D27: Gross $26.4M payback | E27: flag | F27: capex $M/IT MW | G27: opex | H27: revenue IT $M | I27: EBITDA/IT MW (IT) | J27: IRR (IT) | K27: IRR (gross)
A28: Leased GB300 | B28: =IFERROR(F28*1/(H28-G28)*12,999) -> 28.32 | C28: =IF(ISNUMBER(B28),IF(ABS(B28-PB_Target)<=3,"WITHIN +/-3","outside"),"") -> outside | D28: =IFERROR(F28*1/(MYRate*ND_GrossX-G28)*12,999) -> 22.619026 | E28: =IF(ISNUMBER(D28),IF(ABS(D28-PB_Target)<=3,"WITHIN +/-3","outside"),"") -> WITHIN +/-3 | F28: =PB_CapGB -> 41.3 | G28: =PB_Opex -> 4.5 | H28: =MYRate -> 22 | I28: =H28-G28 -> 17.5 | J28: =IFERROR(RATE(PB_Life,I28,-F28*1),-1) -> 0.3166364 | K28: =IFERROR(RATE(PB_Life,MYRate*ND_GrossX-G28,-F28*1),-1) -> 0.44685417
A29: Leased Vera Rubin BASE: $18M rev / $41M capex | B29: =IFERROR(F29*1/(H29-G29)*12,999) -> 36.444444 | C29: =IF(ISNUMBER(B29),IF(ABS(B29-PB_Target)<=3,"WITHIN +/-3","outside"),"") -> outside | D29: n/a (no toggle) | E29: =IF(ISNUMBER(D29),IF(ABS(D29-PB_Target)<=3,"WITHIN +/-3","outside"),"") | F29: =41 -> 41 | G29: =PB_Opex -> 4.5 | H29: =18 -> 18 | I29: =H29-G29 -> 13.5 | J29: =IFERROR(RATE(PB_Life,I29,-F29*1),-1) -> 0.19303446
A30: Leased Vera Rubin BULL: $20M / $41M | B30: =IFERROR(F30*1/(H30-G30)*12,999) -> 31.741935 | C30: =IF(ISNUMBER(B30),IF(ABS(B30-PB_Target)<=3,"WITHIN +/-3","outside"),"") -> outside | D30: n/a (no toggle) | E30: =IF(ISNUMBER(D30),IF(ABS(D30-PB_Target)<=3,"WITHIN +/-3","outside"),"") | F30: =41 -> 41 | G30: =PB_Opex -> 4.5 | H30: =20 -> 20 | I30: =H30-G30 -> 15.5 | J30: =IFERROR(RATE(PB_Life,I30,-F30*1),-1) -> 0.25811256
A31: Leased Vera Rubin BEAR: $16M / $48.5M | B31: =IFERROR(F31*1/(H31-G31)*12,999) -> 50.608696 | C31: =IF(ISNUMBER(B31),IF(ABS(B31-PB_Target)<=3,"WITHIN +/-3","outside"),"") -> outside | D31: n/a (no toggle) | E31: =IF(ISNUMBER(D31),IF(ABS(D31-PB_Target)<=3,"WITHIN +/-3","outside"),"") | F31: =48.5 -> 48.5 | G31: =PB_Opex -> 4.5 | H31: =16 -> 16 | I31: =H31-G31 -> 11.5 | J31: =IFERROR(RATE(PB_Life,I31,-F31*1),-1) -> 0.059561689
A32: Leased Vera Rubin OUTER BULL (sensitivity only; $32M capex is soft): $20M / $32M | B32: =IFERROR(F32*1/(H32-G32)*12,999) -> 24.774194 | C32: =IF(ISNUMBER(B32),IF(ABS(B32-PB_Target)<=3,"WITHIN +/-3","outside"),"") -> WITHIN +/-3 | D32: n/a (no toggle) | E32: =IF(ISNUMBER(D32),IF(ABS(D32-PB_Target)<=3,"WITHIN +/-3","outside"),"") | F32: =32 -> 32 | G32: =PB_Opex -> 4.5 | H32: =20 -> 20 | I32: =H32-G32 -> 15.5 | J32: =IFERROR(RATE(PB_Life,I32,-F32*1),-1) -> 0.39154272
A33: Owned GB300 (memo, base 53) | B33: =IFERROR(F33*1/(H33-G33)*12,999) -> 36.342857 | C33: =IF(ISNUMBER(B33),IF(ABS(B33-PB_Target)<=3,"WITHIN +/-3","outside"),"") -> outside | D33: =IFERROR(F33*1/(MYRate*ND_GrossX-G33)*12,999) -> 29.026837 | E33: =IF(ISNUMBER(D33),IF(ABS(D33-PB_Target)<=3,"WITHIN +/-3","outside"),"") -> outside | F33: =PB_CapOwnGB -> 53 | G33: =PB_Opex -> 4.5 | H33: =MYRate -> 22 | I33: =H33-G33 -> 17.5 | J33: =IFERROR(RATE(PB_Life,I33,-F33*1),-1) -> 0.19429148 | K33: =IFERROR(RATE(PB_Life,MYRate*ND_GrossX-G33,-F33*1),-1) -> 0.3035931
A34: Owned Vera Rubin (memo, base 56) at $18M | B34: =IFERROR(F34*1/(H34-G34)*12,999) -> 49.777778 | C34: =IF(ISNUMBER(B34),IF(ABS(B34-PB_Target)<=3,"WITHIN +/-3","outside"),"") -> outside | D34: n/a (no toggle) | E34: =IF(ISNUMBER(D34),IF(ABS(D34-PB_Target)<=3,"WITHIN +/-3","outside"),"") | F34: =PB_CapOwnRubin -> 56 | G34: =PB_Opex -> 4.5 | H34: =18 -> 18 | I34: =H34-G34 -> 13.5 | J34: =IFERROR(RATE(PB_Life,I34,-F34*1),-1) -> 0.065672474
A35: MODEL'S OWN: GB300-era path capex (avg PathRateIT 2027) + model opex | B35: =IFERROR(F35*1/(H35-G35)*12,999) -> 28.377577 | C35: =IF(ISNUMBER(B35),IF(ABS(B35-PB_Target)<=3,"WITHIN +/-3","outside"),"") -> outside | D35: =IFERROR(F35*1/(MYRate*ND_GrossX-G35)*12,999) -> 22.695161 | E35: =IF(ISNUMBER(D35),IF(ABS(D35-PB_Target)<=3,"WITHIN +/-3","outside"),"") -> WITHIN +/-3 | F35: =AVERAGE(INDEX(PathRateIT,1,13),INDEX(PathRateIT,1,14),INDEX(PathRateIT,1,15),INDEX(PathRateIT,1,16)) -> 41.658875 | G35: =PB_OpexModel -> 4.38375 | H35: =MYRate -> 22 | I35: =H35-G35 -> 17.61625 | J35: =IFERROR(RATE(PB_Life,I35,-F35*1),-1) -> 0.31555325 | K35: =IFERROR(RATE(PB_Life,MYRate*ND_GrossX-G35,-F35*1),-1) -> 0.44474446
A36: MODEL'S OWN: Rubin-era path capex (avg PathRateIT 2029) + model opex, live RubinMW | B36: =IFERROR(F36*1/(H36-G36)*12,999) -> 38.974819 | C36: =IF(ISNUMBER(B36),IF(ABS(B36-PB_Target)<=3,"WITHIN +/-3","outside"),"") -> outside | D36: n/a (no toggle) | E36: =IF(ISNUMBER(D36),IF(ABS(D36-PB_Target)<=3,"WITHIN +/-3","outside"),"") | F36: =AVERAGE(INDEX(PathRateIT,1,21),INDEX(PathRateIT,1,22),INDEX(PathRateIT,1,23),INDEX(PathRateIT,1,24)) -> 44.22424 | G36: =PB_OpexModel -> 4.38375 | H36: =RubinMW -> 18 | I36: =H36-G36 -> 13.61625 | J36: =IFERROR(RATE(PB_Life,I36,-F36*1),-1) -> 0.1634783
A37: TEST: GB300 IT at $32M capex/IT MW (IT fits 22 mo only at ~$32M = 12 x 32 / (22 - 4.5)) | B37: =IFERROR(F37*1/(H37-G37)*12,999) -> 21.942857 | C37: =IF(ISNUMBER(B37),IF(ABS(B37-PB_Target)<=3,"WITHIN +/-3","outside"),"") -> WITHIN +/-3 | D37: =IFERROR(F37*1/(MYRate*ND_GrossX-G37)*12,999) -> 17.525637 | E37: =IF(ISNUMBER(D37),IF(ABS(D37-PB_Target)<=3,"WITHIN +/-3","outside"),"") -> outside | F37: =32 -> 32 | G37: =PB_Opex -> 4.5 | H37: =MYRate -> 22 | I37: =H37-G37 -> 17.5 | J37: =IFERROR(RATE(PB_Life,I37,-F37*1),-1) -> 0.46615308 | K37: =IFERROR(RATE(PB_Life,MYRate*ND_GrossX-G37,-F37*1),-1) -> 0.62411873
A38: TEST: GB300 IT with lower opex $2M/IT MW-yr (ex-rent definition) | B38: =IFERROR(F38*1/(H38-G38)*12,999) -> 24.78 | C38: =IF(ISNUMBER(B38),IF(ABS(B38-PB_Target)<=3,"WITHIN +/-3","outside"),"") -> WITHIN +/-3 | D38: =IFERROR(F38*1/(MYRate*ND_GrossX-G38)*12,999) -> 20.302524 | E38: =IF(ISNUMBER(D38),IF(ABS(D38-PB_Target)<=3,"WITHIN +/-3","outside"),"") -> WITHIN +/-3 | F38: =PB_CapGB -> 41.3 | G38: =2 -> 2 | H38: =MYRate -> 22 | I38: =H38-G38 -> 20 | J38: =IFERROR(RATE(PB_Life,I38,-F38*1),-1) -> 0.39140505 | K38: =IFERROR(RATE(PB_Life,MYRate*ND_GrossX-G38,-F38*1),-1) -> 0.51764538
A39: TEST: GB300 IT with prepayments counted as cash (55% of capex on 70% of deals = 38.5%) | B39: =IFERROR(F39*(1-0.55*0.7)/(H39-G39)*12,999) -> 17.4168 | C39: =IF(ISNUMBER(B39),IF(ABS(B39-PB_Target)<=3,"WITHIN +/-3","outside"),"") -> outside | D39: =IFERROR(F39*(1-0.55*0.7)/(MYRate*ND_GrossX-G39)*12,999) -> 13.910701 | E39: =IF(ISNUMBER(D39),IF(ABS(D39-PB_Target)<=3,"WITHIN +/-3","outside"),"") -> outside | F39: =PB_CapGB -> 41.3 | G39: =PB_Opex -> 4.5 | H39: =MYRate -> 22 | I39: =H39-G39 -> 17.5 | J39: =IFERROR(RATE(PB_Life,I39,-F39*(1-0.55*0.7)),-1) -> 0.62891035 | K39: =IFERROR(RATE(PB_Life,MYRate*ND_GrossX-G39,-F39*(1-0.55*0.7)),-1) -> 0.81937141
A40: Implied GB300 revenue/IT MW if management's 22 months INCLUDES prepayments (capex x 61.5% x 12 / 22 + opex) | H40: =PB_CapGB*(1-0.55*0.7)*12/PB_Target+PB_Opex -> 18.354273
A41: NOTE (payback test): the gross reading fits management's 22 months only if capex is accurate to within ~20% (the IT reading fits at ~$32M leased GB300 capex/IT MW = 12 x 32 / (22 - 4.5)); management's opex definition is undisclosed (lower opex shortens IT payback); and if management's payback INCLUDES prepayments it would imply revenue BELOW the IT reading (~$18.4M vs $22M). The test therefore does not discriminate between IT and gross: both rows are kept co-equal, basis not disclosed by management.
A44: D) ASSET FLOOR: PV of EBITDA margin on signed RPO + stakes - net debt - capex still needed for contracted MW ($M)
A45: RPO schedule assumption: 36% ($13.5B) evenly Jul'26-Jun'28 (Q2'26 Note 2); remainder 64% spread evenly Jul'28-Jun'31 (12 qtrs; ~avg remaining tenor: Microsoft 5-yr from late 2025, Meta #2 5-yr from 2027 - assumption). Margin = model adj. EBITDA margin by quarter (FY30 margin after 2030); pre-tax; discounted at WACC from ValDate.
A46: RPO total ($M) | B46: =RPO_Tot -> 37490
A47: PV of margin - window Jul'26-Jun'28 | B47: =SUMPRODUCT((Q_Idx>LastHist)*(Q_Idx<=LastHist+8)*(RPO_Tot*RPO24Pct/8)*PL_EBITDA/PL_Rev*1/(1+WACC)^((Q_End-ValDate)/365.25)) -> 6422.2778
A48: PV of margin - remainder, Jul'28-Dec'30 (10 qtrs in horizon) | B48: =SUMPRODUCT((Q_Idx>LastHist+8)*(Q_Idx<=28)*(RPO_Tot*(1-RPO24Pct)/12)*PL_EBITDA/PL_Rev*1/(1+WACC)^((Q_End-ValDate)/365.25)) -> 9749.3336
A49: PV of margin - remainder, Q1-Q2'31 at FY30 margin | B49: =RPO_Tot*(1-RPO24Pct)/12*V_M30*(1/(1+WACC)^((INDEX(Q_End,1,28)+91-ValDate)/365.25)+1/(1+WACC)^((INDEX(Q_End,1,28)+182-ValDate)/365.25)) -> 1734.7952
A50: PV of margin on signed RPO (pre-tax) | B50: =PF_PV1+PF_PV2+PF_PV3 -> 17906.407
A51: memo: after tax at TaxRate (no D&A shield) | B51: =PF_PV*(1-TaxRate) -> 13286.554
A52: Contracted MW not yet delivered at 6/30 (Microsoft T5-T9 + Meta; backstop & TBD excluded) | B52: =Contracts!$D$12*(Contracts!$H$12>LastHist)*(1-Contracts!$I$12)+Contracts!$D$13*(Contracts!$H$13>LastHist)*(1-Contracts!$I$13)+Contracts!$D$14*(Contracts!$H$14>LastHist)*(1-Contracts!$I$14)+Contracts!$D$15*(Contracts!$H$15>LastHist)*(1-Contracts!$I$15)+Contracts!$D$16*(Contracts!$H$16>LastHist)*(1-Contracts!$I$16)+Contracts!$D$17*(Contracts!$H$17>LastHist)*(1-Contracts!$I$17)+Contracts!$D$18*(Contracts!$H$18>LastHist)*(1-Contracts!$I$18)+Contracts!$D$19*(Contracts!$H$19>LastHist)*(1-Contracts!$I$19)+Contracts!$D$20*(Contracts!$H$20>LastHist)*(1-Contracts!$I$20)+Contracts!$D$21*(Contracts!$H$21>LastHist)*(1-Contracts!$I$21)+Contracts!$D$22*(Contracts!$H$22>LastHist)*(1-Contracts!$I$22)+Contracts!$D$23*(Contracts!$H$23>LastHist)*(1-Contracts!$I$23)+Contracts!$D$24*(Contracts!$H$24>LastHist)*(1-Contracts!$I$24)+Contracts!$D$25*(Contracts!$H$25>LastHist)*(1-Contracts!$I$25)+Contracts!$D$26*(Contracts!$H$26>LastHist)*(1-Contracts!$I$26)+Contracts!$D$27*(Contracts!$H$27>LastHist)*(1-Contracts!$I$27) -> 293.33333
A53: Capex still needed for contracted MW (Microsoft/Vineland owned GB300 PB_CapOwnGB; Meta by gen: Rubin PB_CapRubin, Blackwell PB_CapGB) - gross, CIP already spent NOT netted (conservative) | B53: =Contracts!$D$12*(Contracts!$H$12>LastHist)*(1-Contracts!$I$12)*PB_CapOwnGB+Contracts!$D$13*(Contracts!$H$13>LastHist)*(1-Contracts!$I$13)*PB_CapOwnGB+Contracts!$D$14*(Contracts!$H$14>LastHist)*(1-Contracts!$I$14)*PB_CapOwnGB+Contracts!$D$15*(Contracts!$H$15>LastHist)*(1-Contracts!$I$15)*PB_CapOwnGB+Contracts!$D$16*(Contracts!$H$16>LastHist)*(1-Contracts!$I$16)*PB_CapOwnGB+Contracts!$D$17*(Contracts!$H$17>LastHist)*(1-Contracts!$I$17)*PB_CapOwnGB+Contracts!$D$18*(Contracts!$H$18>LastHist)*(1-Contracts!$I$18)*PB_CapOwnGB+Contracts!$D$19*(Contracts!$H$19>LastHist)*(1-Contracts!$I$19)*PB_CapOwnGB+Contracts!$D$20*(Contracts!$H$20>LastHist)*(1-Contracts!$I$20)*PB_CapOwnGB+Contracts!$D$21*(Contracts!$H$21>LastHist)*(1-Contracts!$I$21)*PB_CapOwnGB+Contracts!$D$22*(Contracts!$H$22>LastHist)*(1-Contracts!$I$22)*PB_CapOwnGB+Contracts!$D$23*(Contracts!$H$23>LastHist)*(1-Contracts!$I$23)*PB_CapGB+Contracts!$D$24*(Contracts!$H$24>LastHist)*(1-Contracts!$I$24)*PB_CapGB+Contracts!$D$25*(Contracts!$H$25>LastHist)*(1-Contracts!$I$25)*PB_CapRubin+Contracts!$D$26*(Contracts!$H$26>LastHist)*(1-Contracts!$I$26)*PB_CapRubin+Contracts!$D$27*(Contracts!$H$27>LastHist)*(1-Contracts!$I$27)*PB_CapRubin -> 14266.667
A54: Operating asset floor (EV-equivalent) = PV margin - capex needed | B54: =PF_PV-PF_Cap -> 3639.7399
A55: Net debt at the conservative floor price (secured + converts OTM at that price at principal - cash; Q3'26) | B55: =V_ODEBT+CHOOSE(DilMethod,0,SUMPRODUCT((PF_PS1<=V_TrPX)*((CVDebtBasis=1)*V_TrO+(CVDebtBasis=2)*V_TrB)),SUMPRODUCT(((CVDebtBasis=1)*V_TrO+(CVDebtBasis=2)*V_TrB)))-V_CASH -> 1826.6999
A56: Stakes - conservative (carrying values, Note 5: ClickHouse 1,517.7 + Toloka 86.5 + VC 13.8 + other 2.5; Avride $0) | B56: =1620.5 -> 1620.5
A57: Stakes - mark (ClickHouse $4.2B est., Toloka FV 130.6, VC/other 16.3, Avride $0) | B57: =CH_Hi+TO_Hi+Other_Val -> 4346.9
A58: Stakes - high (mark + Avride $2.75B Caplight, LOW confidence) + PV of Avride burn added back (credit value AND remove burn - v0.7 double-count fix) | B58: =PF_S2+AV_Hi-AVBurnOn*AVBurnQ*(SUM(Valuation!$F$12:$AG$12)+4*(1+V_g)/(WACC-V_g)*V_DF28) -> 8827.6108
A59: Equity floor - conservative (at solved floor price) | B59: =PF_EV-V_ODEBT-CHOOSE(DilMethod,0,SUMPRODUCT((PF_PS1<=V_TrPX)*((CVDebtBasis=1)*V_TrO+(CVDebtBasis=2)*V_TrB)),SUMPRODUCT(((CVDebtBasis=1)*V_TrO+(CVDebtBasis=2)*V_TrB)))+V_CASH+PF_S1 -> 3433.54
A60: Equity floor - mark | B60: =PF_EV-V_ODEBT-CHOOSE(DilMethod,0,SUMPRODUCT((PF_PS2<=V_TrPX)*((CVDebtBasis=1)*V_TrO+(CVDebtBasis=2)*V_TrB)),SUMPRODUCT(((CVDebtBasis=1)*V_TrO+(CVDebtBasis=2)*V_TrB)))+V_CASH+PF_S2 -> 6159.94
A61: Equity floor - high | B61: =PF_EV-V_ODEBT-CHOOSE(DilMethod,0,SUMPRODUCT((PF_PS3<=V_TrPX)*((CVDebtBasis=1)*V_TrO+(CVDebtBasis=2)*V_TrB)),SUMPRODUCT(((CVDebtBasis=1)*V_TrO+(CVDebtBasis=2)*V_TrB)))+V_CASH+PF_S3 -> 10640.651
A62: Equity floor per FD share - conservative / mark / high ($): solved jointly with price-dependent convert count (cols C-D; iteration in cols H-J) | B62: =PF_PS1x -> 10.902715 | C62: =PF_PS2x -> 19.560007 | D62: =PF_PS3x -> 33.787862 | E62: =CHOOSE(DilMethod,SUMPRODUCT(V_TrO,V_TrRT)/1000,SUMPRODUCT((PF_PS1>V_TrPX)*V_TrO*V_TrRT)/1000,SUMPRODUCT(((V_TrO*V_TrRT/1000*PF_PS1-((CVDebtBasis=1)*V_TrO+(CVDebtBasis=2)*V_TrB))>0)*(V_TrO*V_TrRT/1000*PF_PS1-((CVDebtBasis=1)*V_TrO+(CVDebtBasis=2)*V_TrB)))/PF_PS1) -> 0 | F62: <- convert shares at conservative floor price (M)
A63: Base DCF EV (live) | B63: =V_EV -> -183.73714
A64: FLAG: DCF EV vs operating asset floor | B64: =IF(V_EV<PF_EV,"FLAG: DCF EV below asset floor","OK: DCF EV above asset floor") -> FLAG: DCF EV below asset floor
G66: Floor price iteration | H66: cons | I66: mark | J66: high
H67: =10 -> 10 | I67: =10 -> 10 | J67: =10 -> 10
H68: =MAX(0.01,(PF_EV-V_ODEBT-CHOOSE(DilMethod,0,SUMPRODUCT((H67<=V_TrPX)*((CVDebtBasis=1)*V_TrO+(CVDebtBasis=2)*V_TrB)),SUMPRODUCT(((CVDebtBasis=1)*V_TrO+(CVDebtBasis=2)*V_TrB)))+V_CASH+PF_S1)/(V_BASIC+V_RSU+Options*MAX(0,1-OptK/H67)+CHOOSE(DilMethod,SUMPRODUCT(V_TrO,V_TrRT)/1000,SUMPRODUCT((H67>V_TrPX)*V_TrO*V_TrRT)/1000,SUMPRODUCT(((V_TrO*V_TrRT/1000*H67-((CVDebtBasis=1)*V_TrO+(CVDebtBasis=2)*V_TrB))>0)*(V_TrO*V_TrRT/1000*H67-((CVDebtBasis=1)*V_TrO+(CVDebtBasis=2)*V_TrB)))/H67))) -> 10.902715 | I68: =MAX(0.01,(PF_EV-V_ODEBT-CHOOSE(DilMethod,0,SUMPRODUCT((I67<=V_TrPX)*((CVDebtBasis=1)*V_TrO+(CVDebtBasis=2)*V_TrB)),SUMPRODUCT(((CVDebtBasis=1)*V_TrO+(CVDebtBasis=2)*V_TrB)))+V_CASH+PF_S2)/(V_BASIC+V_RSU+Options*MAX(0,1-OptK/I67)+CHOOSE(DilMethod,SUMPRODUCT(V_TrO,V_TrRT)/1000,SUMPRODUCT((I67>V_TrPX)*V_TrO*V_TrRT)/1000,SUMPRODUCT(((V_TrO*V_TrRT/1000*I67-((CVDebtBasis=1)*V_TrO+(CVDebtBasis=2)*V_TrB))>0)*(V_TrO*V_TrRT/1000*I67-((CVDebtBasis=1)*V_TrO+(CVDebtBasis=2)*V_TrB)))/I67))) -> 19.560007 | J68: =MAX(0.01,(PF_EV-V_ODEBT-CHOOSE(DilMethod,0,SUMPRODUCT((J67<=V_TrPX)*((CVDebtBasis=1)*V_TrO+(CVDebtBasis=2)*V_TrB)),SUMPRODUCT(((CVDebtBasis=1)*V_TrO+(CVDebtBasis=2)*V_TrB)))+V_CASH+PF_S3)/(V_BASIC+V_RSU+Options*MAX(0,1-OptK/J67)+CHOOSE(DilMethod,SUMPRODUCT(V_TrO,V_TrRT)/1000,SUMPRODUCT((J67>V_TrPX)*V_TrO*V_TrRT)/1000,SUMPRODUCT(((V_TrO*V_TrRT/1000*J67-((CVDebtBasis=1)*V_TrO+(CVDebtBasis=2)*V_TrB))>0)*(V_TrO*V_TrRT/1000*J67-((CVDebtBasis=1)*V_TrO+(CVDebtBasis=2)*V_TrB)))/J67))) -> 33.787862
H69: =MAX(0.01,(PF_EV-V_ODEBT-CHOOSE(DilMethod,0,SUMPRODUCT((H68<=V_TrPX)*((CVDebtBasis=1)*V_TrO+(CVDebtBasis=2)*V_TrB)),SUMPRODUCT(((CVDebtBasis=1)*V_TrO+(CVDebtBasis=2)*V_TrB)))+V_CASH+PF_S1)/(V_BASIC+V_RSU+Options*MAX(0,1-OptK/H68)+CHOOSE(DilMethod,SUMPRODUCT(V_TrO,V_TrRT)/1000,SUMPRODUCT((H68>V_TrPX)*V_TrO*V_TrRT)/1000,SUMPRODUCT(((V_TrO*V_TrRT/1000*H68-((CVDebtBasis=1)*V_TrO+(CVDebtBasis=2)*V_TrB))>0)*(V_TrO*V_TrRT/1000*H68-((CVDebtBasis=1)*V_TrO+(CVDebtBasis=2)*V_TrB)))/H68))) -> 10.902715 | I69: =MAX(0.01,(PF_EV-V_ODEBT-CHOOSE(DilMethod,0,SUMPRODUCT((I68<=V_TrPX)*((CVDebtBasis=1)*V_TrO+(CVDebtBasis=2)*V_TrB)),SUMPRODUCT(((CVDebtBasis=1)*V_TrO+(CVDebtBasis=2)*V_TrB)))+V_CASH+PF_S2)/(V_BASIC+V_RSU+Options*MAX(0,1-OptK/I68)+CHOOSE(DilMethod,SUMPRODUCT(V_TrO,V_TrRT)/1000,SUMPRODUCT((I68>V_TrPX)*V_TrO*V_TrRT)/1000,SUMPRODUCT(((V_TrO*V_TrRT/1000*I68-((CVDebtBasis=1)*V_TrO+(CVDebtBasis=2)*V_TrB))>0)*(V_TrO*V_TrRT/1000*I68-((CVDebtBasis=1)*V_TrO+(CVDebtBasis=2)*V_TrB)))/I68))) -> 19.560007 | J69: =MAX(0.01,(PF_EV-V_ODEBT-CHOOSE(DilMethod,0,SUMPRODUCT((J68<=V_TrPX)*((CVDebtBasis=1)*V_TrO+(CVDebtBasis=2)*V_TrB)),SUMPRODUCT(((CVDebtBasis=1)*V_TrO+(CVDebtBasis=2)*V_TrB)))+V_CASH+PF_S3)/(V_BASIC+V_RSU+Options*MAX(0,1-OptK/J68)+CHOOSE(DilMethod,SUMPRODUCT(V_TrO,V_TrRT)/1000,SUMPRODUCT((J68>V_TrPX)*V_TrO*V_TrRT)/1000,SUMPRODUCT(((V_TrO*V_TrRT/1000*J68-((CVDebtBasis=1)*V_TrO+(CVDebtBasis=2)*V_TrB))>0)*(V_TrO*V_TrRT/1000*J68-((CVDebtBasis=1)*V_TrO+(CVDebtBasis=2)*V_TrB)))/J68))) -> 33.787862
H70: =MAX(0.01,(PF_EV-V_ODEBT-CHOOSE(DilMethod,0,SUMPRODUCT((H69<=V_TrPX)*((CVDebtBasis=1)*V_TrO+(CVDebtBasis=2)*V_TrB)),SUMPRODUCT(((CVDebtBasis=1)*V_TrO+(CVDebtBasis=2)*V_TrB)))+V_CASH+PF_S1)/(V_BASIC+V_RSU+Options*MAX(0,1-OptK/H69)+CHOOSE(DilMethod,SUMPRODUCT(V_TrO,V_TrRT)/1000,SUMPRODUCT((H69>V_TrPX)*V_TrO*V_TrRT)/1000,SUMPRODUCT(((V_TrO*V_TrRT/1000*H69-((CVDebtBasis=1)*V_TrO+(CVDebtBasis=2)*V_TrB))>0)*(V_TrO*V_TrRT/1000*H69-((CVDebtBasis=1)*V_TrO+(CVDebtBasis=2)*V_TrB)))/H69))) -> 10.902715 | I70: =MAX(0.01,(PF_EV-V_ODEBT-CHOOSE(DilMethod,0,SUMPRODUCT((I69<=V_TrPX)*((CVDebtBasis=1)*V_TrO+(CVDebtBasis=2)*V_TrB)),SUMPRODUCT(((CVDebtBasis=1)*V_TrO+(CVDebtBasis=2)*V_TrB)))+V_CASH+PF_S2)/(V_BASIC+V_RSU+Options*MAX(0,1-OptK/I69)+CHOOSE(DilMethod,SUMPRODUCT(V_TrO,V_TrRT)/1000,SUMPRODUCT((I69>V_TrPX)*V_TrO*V_TrRT)/1000,SUMPRODUCT(((V_TrO*V_TrRT/1000*I69-((CVDebtBasis=1)*V_TrO+(CVDebtBasis=2)*V_TrB))>0)*(V_TrO*V_TrRT/1000*I69-((CVDebtBasis=1)*V_TrO+(CVDebtBasis=2)*V_TrB)))/I69))) -> 19.560007 | J70: =MAX(0.01,(PF_EV-V_ODEBT-CHOOSE(DilMethod,0,SUMPRODUCT((J69<=V_TrPX)*((CVDebtBasis=1)*V_TrO+(CVDebtBasis=2)*V_TrB)),SUMPRODUCT(((CVDebtBasis=1)*V_TrO+(CVDebtBasis=2)*V_TrB)))+V_CASH+PF_S3)/(V_BASIC+V_RSU+Options*MAX(0,1-OptK/J69)+CHOOSE(DilMethod,SUMPRODUCT(V_TrO,V_TrRT)/1000,SUMPRODUCT((J69>V_TrPX)*V_TrO*V_TrRT)/1000,SUMPRODUCT(((V_TrO*V_TrRT/1000*J69-((CVDebtBasis=1)*V_TrO+(CVDebtBasis=2)*V_TrB))>0)*(V_TrO*V_TrRT/1000*J69-((CVDebtBasis=1)*V_TrO+(CVDebtBasis=2)*V_TrB)))/J69))) -> 33.787862
H71: =MAX(0.01,(PF_EV-V_ODEBT-CHOOSE(DilMethod,0,SUMPRODUCT((H70<=V_TrPX)*((CVDebtBasis=1)*V_TrO+(CVDebtBasis=2)*V_TrB)),SUMPRODUCT(((CVDebtBasis=1)*V_TrO+(CVDebtBasis=2)*V_TrB)))+V_CASH+PF_S1)/(V_BASIC+V_RSU+Options*MAX(0,1-OptK/H70)+CHOOSE(DilMethod,SUMPRODUCT(V_TrO,V_TrRT)/1000,SUMPRODUCT((H70>V_TrPX)*V_TrO*V_TrRT)/1000,SUMPRODUCT(((V_TrO*V_TrRT/1000*H70-((CVDebtBasis=1)*V_TrO+(CVDebtBasis=2)*V_TrB))>0)*(V_TrO*V_TrRT/1000*H70-((CVDebtBasis=1)*V_TrO+(CVDebtBasis=2)*V_TrB)))/H70))) -> 10.902715 | I71: =MAX(0.01,(PF_EV-V_ODEBT-CHOOSE(DilMethod,0,SUMPRODUCT((I70<=V_TrPX)*((CVDebtBasis=1)*V_TrO+(CVDebtBasis=2)*V_TrB)),SUMPRODUCT(((CVDebtBasis=1)*V_TrO+(CVDebtBasis=2)*V_TrB)))+V_CASH+PF_S2)/(V_BASIC+V_RSU+Options*MAX(0,1-OptK/I70)+CHOOSE(DilMethod,SUMPRODUCT(V_TrO,V_TrRT)/1000,SUMPRODUCT((I70>V_TrPX)*V_TrO*V_TrRT)/1000,SUMPRODUCT(((V_TrO*V_TrRT/1000*I70-((CVDebtBasis=1)*V_TrO+(CVDebtBasis=2)*V_TrB))>0)*(V_TrO*V_TrRT/1000*I70-((CVDebtBasis=1)*V_TrO+(CVDebtBasis=2)*V_TrB)))/I70))) -> 19.560007 | J71: =MAX(0.01,(PF_EV-V_ODEBT-CHOOSE(DilMethod,0,SUMPRODUCT((J70<=V_TrPX)*((CVDebtBasis=1)*V_TrO+(CVDebtBasis=2)*V_TrB)),SUMPRODUCT(((CVDebtBasis=1)*V_TrO+(CVDebtBasis=2)*V_TrB)))+V_CASH+PF_S3)/(V_BASIC+V_RSU+Options*MAX(0,1-OptK/J70)+CHOOSE(DilMethod,SUMPRODUCT(V_TrO,V_TrRT)/1000,SUMPRODUCT((J70>V_TrPX)*V_TrO*V_TrRT)/1000,SUMPRODUCT(((V_TrO*V_TrRT/1000*J70-((CVDebtBasis=1)*V_TrO+(CVDebtBasis=2)*V_TrB))>0)*(V_TrO*V_TrRT/1000*J70-((CVDebtBasis=1)*V_TrO+(CVDebtBasis=2)*V_TrB)))/J70))) -> 33.787862
H72: =MAX(0.01,(PF_EV-V_ODEBT-CHOOSE(DilMethod,0,SUMPRODUCT((H71<=V_TrPX)*((CVDebtBasis=1)*V_TrO+(CVDebtBasis=2)*V_TrB)),SUMPRODUCT(((CVDebtBasis=1)*V_TrO+(CVDebtBasis=2)*V_TrB)))+V_CASH+PF_S1)/(V_BASIC+V_RSU+Options*MAX(0,1-OptK/H71)+CHOOSE(DilMethod,SUMPRODUCT(V_TrO,V_TrRT)/1000,SUMPRODUCT((H71>V_TrPX)*V_TrO*V_TrRT)/1000,SUMPRODUCT(((V_TrO*V_TrRT/1000*H71-((CVDebtBasis=1)*V_TrO+(CVDebtBasis=2)*V_TrB))>0)*(V_TrO*V_TrRT/1000*H71-((CVDebtBasis=1)*V_TrO+(CVDebtBasis=2)*V_TrB)))/H71))) -> 10.902715 | I72: =MAX(0.01,(PF_EV-V_ODEBT-CHOOSE(DilMethod,0,SUMPRODUCT((I71<=V_TrPX)*((CVDebtBasis=1)*V_TrO+(CVDebtBasis=2)*V_TrB)),SUMPRODUCT(((CVDebtBasis=1)*V_TrO+(CVDebtBasis=2)*V_TrB)))+V_CASH+PF_S2)/(V_BASIC+V_RSU+Options*MAX(0,1-OptK/I71)+CHOOSE(DilMethod,SUMPRODUCT(V_TrO,V_TrRT)/1000,SUMPRODUCT((I71>V_TrPX)*V_TrO*V_TrRT)/1000,SUMPRODUCT(((V_TrO*V_TrRT/1000*I71-((CVDebtBasis=1)*V_TrO+(CVDebtBasis=2)*V_TrB))>0)*(V_TrO*V_TrRT/1000*I71-((CVDebtBasis=1)*V_TrO+(CVDebtBasis=2)*V_TrB)))/I71))) -> 19.560007 | J72: =MAX(0.01,(PF_EV-V_ODEBT-CHOOSE(DilMethod,0,SUMPRODUCT((J71<=V_TrPX)*((CVDebtBasis=1)*V_TrO+(CVDebtBasis=2)*V_TrB)),SUMPRODUCT(((CVDebtBasis=1)*V_TrO+(CVDebtBasis=2)*V_TrB)))+V_CASH+PF_S3)/(V_BASIC+V_RSU+Options*MAX(0,1-OptK/J71)+CHOOSE(DilMethod,SUMPRODUCT(V_TrO,V_TrRT)/1000,SUMPRODUCT((J71>V_TrPX)*V_TrO*V_TrRT)/1000,SUMPRODUCT(((V_TrO*V_TrRT/1000*J71-((CVDebtBasis=1)*V_TrO+(CVDebtBasis=2)*V_TrB))>0)*(V_TrO*V_TrRT/1000*J71-((CVDebtBasis=1)*V_TrO+(CVDebtBasis=2)*V_TrB)))/J71))) -> 33.787862
H73: =MAX(0.01,(PF_EV-V_ODEBT-CHOOSE(DilMethod,0,SUMPRODUCT((H72<=V_TrPX)*((CVDebtBasis=1)*V_TrO+(CVDebtBasis=2)*V_TrB)),SUMPRODUCT(((CVDebtBasis=1)*V_TrO+(CVDebtBasis=2)*V_TrB)))+V_CASH+PF_S1)/(V_BASIC+V_RSU+Options*MAX(0,1-OptK/H72)+CHOOSE(DilMethod,SUMPRODUCT(V_TrO,V_TrRT)/1000,SUMPRODUCT((H72>V_TrPX)*V_TrO*V_TrRT)/1000,SUMPRODUCT(((V_TrO*V_TrRT/1000*H72-((CVDebtBasis=1)*V_TrO+(CVDebtBasis=2)*V_TrB))>0)*(V_TrO*V_TrRT/1000*H72-((CVDebtBasis=1)*V_TrO+(CVDebtBasis=2)*V_TrB)))/H72))) -> 10.902715 | I73: =MAX(0.01,(PF_EV-V_ODEBT-CHOOSE(DilMethod,0,SUMPRODUCT((I72<=V_TrPX)*((CVDebtBasis=1)*V_TrO+(CVDebtBasis=2)*V_TrB)),SUMPRODUCT(((CVDebtBasis=1)*V_TrO+(CVDebtBasis=2)*V_TrB)))+V_CASH+PF_S2)/(V_BASIC+V_RSU+Options*MAX(0,1-OptK/I72)+CHOOSE(DilMethod,SUMPRODUCT(V_TrO,V_TrRT)/1000,SUMPRODUCT((I72>V_TrPX)*V_TrO*V_TrRT)/1000,SUMPRODUCT(((V_TrO*V_TrRT/1000*I72-((CVDebtBasis=1)*V_TrO+(CVDebtBasis=2)*V_TrB))>0)*(V_TrO*V_TrRT/1000*I72-((CVDebtBasis=1)*V_TrO+(CVDebtBasis=2)*V_TrB)))/I72))) -> 19.560007 | J73: =MAX(0.01,(PF_EV-V_ODEBT-CHOOSE(DilMethod,0,SUMPRODUCT((J72<=V_TrPX)*((CVDebtBasis=1)*V_TrO+(CVDebtBasis=2)*V_TrB)),SUMPRODUCT(((CVDebtBasis=1)*V_TrO+(CVDebtBasis=2)*V_TrB)))+V_CASH+PF_S3)/(V_BASIC+V_RSU+Options*MAX(0,1-OptK/J72)+CHOOSE(DilMethod,SUMPRODUCT(V_TrO,V_TrRT)/1000,SUMPRODUCT((J72>V_TrPX)*V_TrO*V_TrRT)/1000,SUMPRODUCT(((V_TrO*V_TrRT/1000*J72-((CVDebtBasis=1)*V_TrO+(CVDebtBasis=2)*V_TrB))>0)*(V_TrO*V_TrRT/1000*J72-((CVDebtBasis=1)*V_TrO+(CVDebtBasis=2)*V_TrB)))/J72))) -> 33.787862
H74: =MAX(0.01,(PF_EV-V_ODEBT-CHOOSE(DilMethod,0,SUMPRODUCT((H73<=V_TrPX)*((CVDebtBasis=1)*V_TrO+(CVDebtBasis=2)*V_TrB)),SUMPRODUCT(((CVDebtBasis=1)*V_TrO+(CVDebtBasis=2)*V_TrB)))+V_CASH+PF_S1)/(V_BASIC+V_RSU+Options*MAX(0,1-OptK/H73)+CHOOSE(DilMethod,SUMPRODUCT(V_TrO,V_TrRT)/1000,SUMPRODUCT((H73>V_TrPX)*V_TrO*V_TrRT)/1000,SUMPRODUCT(((V_TrO*V_TrRT/1000*H73-((CVDebtBasis=1)*V_TrO+(CVDebtBasis=2)*V_TrB))>0)*(V_TrO*V_TrRT/1000*H73-((CVDebtBasis=1)*V_TrO+(CVDebtBasis=2)*V_TrB)))/H73))) -> 10.902715 | I74: =MAX(0.01,(PF_EV-V_ODEBT-CHOOSE(DilMethod,0,SUMPRODUCT((I73<=V_TrPX)*((CVDebtBasis=1)*V_TrO+(CVDebtBasis=2)*V_TrB)),SUMPRODUCT(((CVDebtBasis=1)*V_TrO+(CVDebtBasis=2)*V_TrB)))+V_CASH+PF_S2)/(V_BASIC+V_RSU+Options*MAX(0,1-OptK/I73)+CHOOSE(DilMethod,SUMPRODUCT(V_TrO,V_TrRT)/1000,SUMPRODUCT((I73>V_TrPX)*V_TrO*V_TrRT)/1000,SUMPRODUCT(((V_TrO*V_TrRT/1000*I73-((CVDebtBasis=1)*V_TrO+(CVDebtBasis=2)*V_TrB))>0)*(V_TrO*V_TrRT/1000*I73-((CVDebtBasis=1)*V_TrO+(CVDebtBasis=2)*V_TrB)))/I73))) -> 19.560007 | J74: =MAX(0.01,(PF_EV-V_ODEBT-CHOOSE(DilMethod,0,SUMPRODUCT((J73<=V_TrPX)*((CVDebtBasis=1)*V_TrO+(CVDebtBasis=2)*V_TrB)),SUMPRODUCT(((CVDebtBasis=1)*V_TrO+(CVDebtBasis=2)*V_TrB)))+V_CASH+PF_S3)/(V_BASIC+V_RSU+Options*MAX(0,1-OptK/J73)+CHOOSE(DilMethod,SUMPRODUCT(V_TrO,V_TrRT)/1000,SUMPRODUCT((J73>V_TrPX)*V_TrO*V_TrRT)/1000,SUMPRODUCT(((V_TrO*V_TrRT/1000*J73-((CVDebtBasis=1)*V_TrO+(CVDebtBasis=2)*V_TrB))>0)*(V_TrO*V_TrRT/1000*J73-((CVDebtBasis=1)*V_TrO+(CVDebtBasis=2)*V_TrB)))/J73))) -> 33.787862
H75: =MAX(0.01,(PF_EV-V_ODEBT-CHOOSE(DilMethod,0,SUMPRODUCT((H74<=V_TrPX)*((CVDebtBasis=1)*V_TrO+(CVDebtBasis=2)*V_TrB)),SUMPRODUCT(((CVDebtBasis=1)*V_TrO+(CVDebtBasis=2)*V_TrB)))+V_CASH+PF_S1)/(V_BASIC+V_RSU+Options*MAX(0,1-OptK/H74)+CHOOSE(DilMethod,SUMPRODUCT(V_TrO,V_TrRT)/1000,SUMPRODUCT((H74>V_TrPX)*V_TrO*V_TrRT)/1000,SUMPRODUCT(((V_TrO*V_TrRT/1000*H74-((CVDebtBasis=1)*V_TrO+(CVDebtBasis=2)*V_TrB))>0)*(V_TrO*V_TrRT/1000*H74-((CVDebtBasis=1)*V_TrO+(CVDebtBasis=2)*V_TrB)))/H74))) -> 10.902715 | I75: =MAX(0.01,(PF_EV-V_ODEBT-CHOOSE(DilMethod,0,SUMPRODUCT((I74<=V_TrPX)*((CVDebtBasis=1)*V_TrO+(CVDebtBasis=2)*V_TrB)),SUMPRODUCT(((CVDebtBasis=1)*V_TrO+(CVDebtBasis=2)*V_TrB)))+V_CASH+PF_S2)/(V_BASIC+V_RSU+Options*MAX(0,1-OptK/I74)+CHOOSE(DilMethod,SUMPRODUCT(V_TrO,V_TrRT)/1000,SUMPRODUCT((I74>V_TrPX)*V_TrO*V_TrRT)/1000,SUMPRODUCT(((V_TrO*V_TrRT/1000*I74-((CVDebtBasis=1)*V_TrO+(CVDebtBasis=2)*V_TrB))>0)*(V_TrO*V_TrRT/1000*I74-((CVDebtBasis=1)*V_TrO+(CVDebtBasis=2)*V_TrB)))/I74))) -> 19.560007 | J75: =MAX(0.01,(PF_EV-V_ODEBT-CHOOSE(DilMethod,0,SUMPRODUCT((J74<=V_TrPX)*((CVDebtBasis=1)*V_TrO+(CVDebtBasis=2)*V_TrB)),SUMPRODUCT(((CVDebtBasis=1)*V_TrO+(CVDebtBasis=2)*V_TrB)))+V_CASH+PF_S3)/(V_BASIC+V_RSU+Options*MAX(0,1-OptK/J74)+CHOOSE(DilMethod,SUMPRODUCT(V_TrO,V_TrRT)/1000,SUMPRODUCT((J74>V_TrPX)*V_TrO*V_TrRT)/1000,SUMPRODUCT(((V_TrO*V_TrRT/1000*J74-((CVDebtBasis=1)*V_TrO+(CVDebtBasis=2)*V_TrB))>0)*(V_TrO*V_TrRT/1000*J74-((CVDebtBasis=1)*V_TrO+(CVDebtBasis=2)*V_TrB)))/J74))) -> 33.787862
H76: =MAX(0.01,(PF_EV-V_ODEBT-CHOOSE(DilMethod,0,SUMPRODUCT((H75<=V_TrPX)*((CVDebtBasis=1)*V_TrO+(CVDebtBasis=2)*V_TrB)),SUMPRODUCT(((CVDebtBasis=1)*V_TrO+(CVDebtBasis=2)*V_TrB)))+V_CASH+PF_S1)/(V_BASIC+V_RSU+Options*MAX(0,1-OptK/H75)+CHOOSE(DilMethod,SUMPRODUCT(V_TrO,V_TrRT)/1000,SUMPRODUCT((H75>V_TrPX)*V_TrO*V_TrRT)/1000,SUMPRODUCT(((V_TrO*V_TrRT/1000*H75-((CVDebtBasis=1)*V_TrO+(CVDebtBasis=2)*V_TrB))>0)*(V_TrO*V_TrRT/1000*H75-((CVDebtBasis=1)*V_TrO+(CVDebtBasis=2)*V_TrB)))/H75))) -> 10.902715 | I76: =MAX(0.01,(PF_EV-V_ODEBT-CHOOSE(DilMethod,0,SUMPRODUCT((I75<=V_TrPX)*((CVDebtBasis=1)*V_TrO+(CVDebtBasis=2)*V_TrB)),SUMPRODUCT(((CVDebtBasis=1)*V_TrO+(CVDebtBasis=2)*V_TrB)))+V_CASH+PF_S2)/(V_BASIC+V_RSU+Options*MAX(0,1-OptK/I75)+CHOOSE(DilMethod,SUMPRODUCT(V_TrO,V_TrRT)/1000,SUMPRODUCT((I75>V_TrPX)*V_TrO*V_TrRT)/1000,SUMPRODUCT(((V_TrO*V_TrRT/1000*I75-((CVDebtBasis=1)*V_TrO+(CVDebtBasis=2)*V_TrB))>0)*(V_TrO*V_TrRT/1000*I75-((CVDebtBasis=1)*V_TrO+(CVDebtBasis=2)*V_TrB)))/I75))) -> 19.560007 | J76: =MAX(0.01,(PF_EV-V_ODEBT-CHOOSE(DilMethod,0,SUMPRODUCT((J75<=V_TrPX)*((CVDebtBasis=1)*V_TrO+(CVDebtBasis=2)*V_TrB)),SUMPRODUCT(((CVDebtBasis=1)*V_TrO+(CVDebtBasis=2)*V_TrB)))+V_CASH+PF_S3)/(V_BASIC+V_RSU+Options*MAX(0,1-OptK/J75)+CHOOSE(DilMethod,SUMPRODUCT(V_TrO,V_TrRT)/1000,SUMPRODUCT((J75>V_TrPX)*V_TrO*V_TrRT)/1000,SUMPRODUCT(((V_TrO*V_TrRT/1000*J75-((CVDebtBasis=1)*V_TrO+(CVDebtBasis=2)*V_TrB))>0)*(V_TrO*V_TrRT/1000*J75-((CVDebtBasis=1)*V_TrO+(CVDebtBasis=2)*V_TrB)))/J75))) -> 33.787862
H77: =MAX(0.01,(PF_EV-V_ODEBT-CHOOSE(DilMethod,0,SUMPRODUCT((H76<=V_TrPX)*((CVDebtBasis=1)*V_TrO+(CVDebtBasis=2)*V_TrB)),SUMPRODUCT(((CVDebtBasis=1)*V_TrO+(CVDebtBasis=2)*V_TrB)))+V_CASH+PF_S1)/(V_BASIC+V_RSU+Options*MAX(0,1-OptK/H76)+CHOOSE(DilMethod,SUMPRODUCT(V_TrO,V_TrRT)/1000,SUMPRODUCT((H76>V_TrPX)*V_TrO*V_TrRT)/1000,SUMPRODUCT(((V_TrO*V_TrRT/1000*H76-((CVDebtBasis=1)*V_TrO+(CVDebtBasis=2)*V_TrB))>0)*(V_TrO*V_TrRT/1000*H76-((CVDebtBasis=1)*V_TrO+(CVDebtBasis=2)*V_TrB)))/H76))) -> 10.902715 | I77: =MAX(0.01,(PF_EV-V_ODEBT-CHOOSE(DilMethod,0,SUMPRODUCT((I76<=V_TrPX)*((CVDebtBasis=1)*V_TrO+(CVDebtBasis=2)*V_TrB)),SUMPRODUCT(((CVDebtBasis=1)*V_TrO+(CVDebtBasis=2)*V_TrB)))+V_CASH+PF_S2)/(V_BASIC+V_RSU+Options*MAX(0,1-OptK/I76)+CHOOSE(DilMethod,SUMPRODUCT(V_TrO,V_TrRT)/1000,SUMPRODUCT((I76>V_TrPX)*V_TrO*V_TrRT)/1000,SUMPRODUCT(((V_TrO*V_TrRT/1000*I76-((CVDebtBasis=1)*V_TrO+(CVDebtBasis=2)*V_TrB))>0)*(V_TrO*V_TrRT/1000*I76-((CVDebtBasis=1)*V_TrO+(CVDebtBasis=2)*V_TrB)))/I76))) -> 19.560007 | J77: =MAX(0.01,(PF_EV-V_ODEBT-CHOOSE(DilMethod,0,SUMPRODUCT((J76<=V_TrPX)*((CVDebtBasis=1)*V_TrO+(CVDebtBasis=2)*V_TrB)),SUMPRODUCT(((CVDebtBasis=1)*V_TrO+(CVDebtBasis=2)*V_TrB)))+V_CASH+PF_S3)/(V_BASIC+V_RSU+Options*MAX(0,1-OptK/J76)+CHOOSE(DilMethod,SUMPRODUCT(V_TrO,V_TrRT)/1000,SUMPRODUCT((J76>V_TrPX)*V_TrO*V_TrRT)/1000,SUMPRODUCT(((V_TrO*V_TrRT/1000*J76-((CVDebtBasis=1)*V_TrO+(CVDebtBasis=2)*V_TrB))>0)*(V_TrO*V_TrRT/1000*J76-((CVDebtBasis=1)*V_TrO+(CVDebtBasis=2)*V_TrB)))/J76))) -> 33.787862
H78: =MAX(0.01,(PF_EV-V_ODEBT-CHOOSE(DilMethod,0,SUMPRODUCT((H77<=V_TrPX)*((CVDebtBasis=1)*V_TrO+(CVDebtBasis=2)*V_TrB)),SUMPRODUCT(((CVDebtBasis=1)*V_TrO+(CVDebtBasis=2)*V_TrB)))+V_CASH+PF_S1)/(V_BASIC+V_RSU+Options*MAX(0,1-OptK/H77)+CHOOSE(DilMethod,SUMPRODUCT(V_TrO,V_TrRT)/1000,SUMPRODUCT((H77>V_TrPX)*V_TrO*V_TrRT)/1000,SUMPRODUCT(((V_TrO*V_TrRT/1000*H77-((CVDebtBasis=1)*V_TrO+(CVDebtBasis=2)*V_TrB))>0)*(V_TrO*V_TrRT/1000*H77-((CVDebtBasis=1)*V_TrO+(CVDebtBasis=2)*V_TrB)))/H77))) -> 10.902715 | I78: =MAX(0.01,(PF_EV-V_ODEBT-CHOOSE(DilMethod,0,SUMPRODUCT((I77<=V_TrPX)*((CVDebtBasis=1)*V_TrO+(CVDebtBasis=2)*V_TrB)),SUMPRODUCT(((CVDebtBasis=1)*V_TrO+(CVDebtBasis=2)*V_TrB)))+V_CASH+PF_S2)/(V_BASIC+V_RSU+Options*MAX(0,1-OptK/I77)+CHOOSE(DilMethod,SUMPRODUCT(V_TrO,V_TrRT)/1000,SUMPRODUCT((I77>V_TrPX)*V_TrO*V_TrRT)/1000,SUMPRODUCT(((V_TrO*V_TrRT/1000*I77-((CVDebtBasis=1)*V_TrO+(CVDebtBasis=2)*V_TrB))>0)*(V_TrO*V_TrRT/1000*I77-((CVDebtBasis=1)*V_TrO+(CVDebtBasis=2)*V_TrB)))/I77))) -> 19.560007 | J78: =MAX(0.01,(PF_EV-V_ODEBT-CHOOSE(DilMethod,0,SUMPRODUCT((J77<=V_TrPX)*((CVDebtBasis=1)*V_TrO+(CVDebtBasis=2)*V_TrB)),SUMPRODUCT(((CVDebtBasis=1)*V_TrO+(CVDebtBasis=2)*V_TrB)))+V_CASH+PF_S3)/(V_BASIC+V_RSU+Options*MAX(0,1-OptK/J77)+CHOOSE(DilMethod,SUMPRODUCT(V_TrO,V_TrRT)/1000,SUMPRODUCT((J77>V_TrPX)*V_TrO*V_TrRT)/1000,SUMPRODUCT(((V_TrO*V_TrRT/1000*J77-((CVDebtBasis=1)*V_TrO+(CVDebtBasis=2)*V_TrB))>0)*(V_TrO*V_TrRT/1000*J77-((CVDebtBasis=1)*V_TrO+(CVDebtBasis=2)*V_TrB)))/J77))) -> 33.787862
H79: =MAX(0.01,(PF_EV-V_ODEBT-CHOOSE(DilMethod,0,SUMPRODUCT((H78<=V_TrPX)*((CVDebtBasis=1)*V_TrO+(CVDebtBasis=2)*V_TrB)),SUMPRODUCT(((CVDebtBasis=1)*V_TrO+(CVDebtBasis=2)*V_TrB)))+V_CASH+PF_S1)/(V_BASIC+V_RSU+Options*MAX(0,1-OptK/H78)+CHOOSE(DilMethod,SUMPRODUCT(V_TrO,V_TrRT)/1000,SUMPRODUCT((H78>V_TrPX)*V_TrO*V_TrRT)/1000,SUMPRODUCT(((V_TrO*V_TrRT/1000*H78-((CVDebtBasis=1)*V_TrO+(CVDebtBasis=2)*V_TrB))>0)*(V_TrO*V_TrRT/1000*H78-((CVDebtBasis=1)*V_TrO+(CVDebtBasis=2)*V_TrB)))/H78))) -> 10.902715 | I79: =MAX(0.01,(PF_EV-V_ODEBT-CHOOSE(DilMethod,0,SUMPRODUCT((I78<=V_TrPX)*((CVDebtBasis=1)*V_TrO+(CVDebtBasis=2)*V_TrB)),SUMPRODUCT(((CVDebtBasis=1)*V_TrO+(CVDebtBasis=2)*V_TrB)))+V_CASH+PF_S2)/(V_BASIC+V_RSU+Options*MAX(0,1-OptK/I78)+CHOOSE(DilMethod,SUMPRODUCT(V_TrO,V_TrRT)/1000,SUMPRODUCT((I78>V_TrPX)*V_TrO*V_TrRT)/1000,SUMPRODUCT(((V_TrO*V_TrRT/1000*I78-((CVDebtBasis=1)*V_TrO+(CVDebtBasis=2)*V_TrB))>0)*(V_TrO*V_TrRT/1000*I78-((CVDebtBasis=1)*V_TrO+(CVDebtBasis=2)*V_TrB)))/I78))) -> 19.560007 | J79: =MAX(0.01,(PF_EV-V_ODEBT-CHOOSE(DilMethod,0,SUMPRODUCT((J78<=V_TrPX)*((CVDebtBasis=1)*V_TrO+(CVDebtBasis=2)*V_TrB)),SUMPRODUCT(((CVDebtBasis=1)*V_TrO+(CVDebtBasis=2)*V_TrB)))+V_CASH+PF_S3)/(V_BASIC+V_RSU+Options*MAX(0,1-OptK/J78)+CHOOSE(DilMethod,SUMPRODUCT(V_TrO,V_TrRT)/1000,SUMPRODUCT((J78>V_TrPX)*V_TrO*V_TrRT)/1000,SUMPRODUCT(((V_TrO*V_TrRT/1000*J78-((CVDebtBasis=1)*V_TrO+(CVDebtBasis=2)*V_TrB))>0)*(V_TrO*V_TrRT/1000*J78-((CVDebtBasis=1)*V_TrO+(CVDebtBasis=2)*V_TrB)))/J78))) -> 33.787862
... H82: =MAX(0.01,(PF_EV-V_ODEBT-CHOOSE(DilMethod,0,SUMPRODUCT((H81<=V_TrPX)*((CVDebtBasis=1)*V_TrO+(CVDebtBasis=2)*V_TrB)),SUMPRODUCT(((CVDebtBasis=1)*V_TrO+(CVDebtBasis=2)*V_TrB)))+V_CASH+PF_S1)/(V_BASIC+V_RSU+Options*MAX(0,1-OptK/H81)+CHOOSE(DilMethod,SUMPRODUCT(V_TrO,V_TrRT)/1000,SUMPRODUCT((H81>V_TrPX)*V_TrO*V_TrRT)/1000,SUMPRODUCT(((V_TrO*V_TrRT/1000*H81-((CVDebtBasis=1)*V_TrO+(CVDebtBasis=2)*V_TrB))>0)*(V_TrO*V_TrRT/1000*H81-((CVDebtBasis=1)*V_TrO+(CVDebtBasis=2)*V_TrB)))/H81))) -> 10.902715 | I82: =MAX(0.01,(PF_EV-V_ODEBT-CHOOSE(DilMethod,0,SUMPRODUCT((I81<=V_TrPX)*((CVDebtBasis=1)*V_TrO+(CVDebtBasis=2)*V_TrB)),SUMPRODUCT(((CVDebtBasis=1)*V_TrO+(CVDebtBasis=2)*V_TrB)))+V_CASH+PF_S2)/(V_BASIC+V_RSU+Options*MAX(0,1-OptK/I81)+CHOOSE(DilMethod,SUMPRODUCT(V_TrO,V_TrRT)/1000,SUMPRODUCT((I81>V_TrPX)*V_TrO*V_TrRT)/1000,SUMPRODUCT(((V_TrO*V_TrRT/1000*I81-((CVDebtBasis=1)*V_TrO+(CVDebtBasis=2)*V_TrB))>0)*(V_TrO*V_TrRT/1000*I81-((CVDebtBasis=1)*V_TrO+(CVDebtBasis=2)*V_TrB)))/I81))) -> 19.560007 | J82: =MAX(0.01,(PF_EV-V_ODEBT-CHOOSE(DilMethod,0,SUMPRODUCT((J81<=V_TrPX)*((CVDebtBasis=1)*V_TrO+(CVDebtBasis=2)*V_TrB)),SUMPRODUCT(((CVDebtBasis=1)*V_TrO+(CVDebtBasis=2)*V_TrB)))+V_CASH+PF_S3)/(V_BASIC+V_RSU+Options*MAX(0,1-OptK/J81)+CHOOSE(DilMethod,SUMPRODUCT(V_TrO,V_TrRT)/1000,SUMPRODUCT((J81>V_TrPX)*V_TrO*V_TrRT)/1000,SUMPRODUCT(((V_TrO*V_TrRT/1000*J81-((CVDebtBasis=1)*V_TrO+(CVDebtBasis=2)*V_TrB))>0)*(V_TrO*V_TrRT/1000*J81-((CVDebtBasis=1)*V_TrO+(CVDebtBasis=2)*V_TrB)))/J81))) -> 33.787862
H83: =IF(H82<=0.011,0,H82) -> 10.902715 | I83: =IF(I82<=0.011,0,I82) -> 19.560007 | J83: =IF(J82<=0.011,0,J82) -> 33.787862

Sheet Funding
A1: LEGACY v0.4 parametric funding illustration (v0.7 plan is wired in Inputs FP_*, CashFlow, Valuation POST-FUNDING block) - ESTIMATED (illustrative; DCF value/share already reflects capex; dilution arises only from issuing equity/converts vs model value)
A4: Gap
A5: Minimum liquidity Q3'26-Q4'27 (no plug) | B5: =MIN(INDEX(Liq,1,11):INDEX(Liq,1,16)) -> 2073.2027
A6: Minimum liquidity Q3'26-Q4'28 (no plug) | B6: =MIN(INDEX(Liq,1,11):INDEX(Liq,1,20)) -> -13352.424
A7: Funding need through FY27 = MinCash - min liquidity | B7: =MAX(0,MinCash-FU_Min27) -> 0
A8: Funding need through FY28 | B8: =MAX(0,MinCash-FU_Min28) -> 15352.424
A9: Plan target (1 = through FY27, 2 = through FY28) | B9: 1
A10: Plan target ($M) | B10: =IF(FU_TgtSel=2,FU_Gap28,FU_Gap27) -> 0
A11: Model FD value/share (V_PS) and implied FD shares (M) | B11: =V_PS -> 0.01
A12: FD shares at value (M) = V_EQ / V_PS | B12: =IFERROR(V_EQ/V_PS,0) -> -925362.45
A14: Source inputs (Estimated)
A15: ATM: shares remaining (M) | B15: =ATM_Rem -> 12.270507
A16: ATM: issue price = SharePx x (1 - discount/fees) | B16: =SharePx*(1-FU_ATMd) -> 237.9538
A17: ATM discount + fees | B17: 0.02
A18: Customer prepayments: incremental beyond PrepayPct ($M) | B18: 1500 | C18: Q2 letter: >$9B prepayments in 2026; 70% of deals, 50-60% of capex
A19: Prepayment price concession (% of amount, PV cost) | B19: 0
A20: ABS / GPU-backed debt: LTV on GPU net book value at Q2'27 | B20: 0.5
A21: GPU net book value at Q2'27 ($M) | B21: =INDEX(NBV_H,1,14)+INDEX(NBV_B,1,14)+INDEX(NBV_N,1,14) -> 26559.023
A22: ABS capacity ($M) = LTV x GPU NBV, capped | B22: =MIN(FU_LTV*FU_NBV,FU_ABSCap) -> 5000
A23: ABS cap ($M) | B23: 5000
A24: ABS interest rate | B24: 0.09 | C24: memo: cost in WACC; no share dilution
A25: New converts: amount ($M) | B25: 3000
A26: Conversion premium | B26: 0.35
A27: Conversion price | B27: =SharePx*(1+FU_CVPrem) -> 327.7935
A29: Per-source effect if used ALONE at full size (value/share = (V_EQ + equity-like proceeds) / (shares + new shares)) | B29: Proceeds $M | C29: New shares M | D29: Value/share $ | E29: Change $/sh | F29: Dilution %
A30: ATM (all 12.27M sh) | B30: =FU_ATMsh*FU_ATMpx -> 2919.8138 | C30: =FU_ATMsh -> 12.270507 | D30: =(V_EQ+FU_ATMsh*FU_ATMpx)/(FU_N+FU_ATMsh) -> 0.0068447717 | E30: =D30-FU_V -> -0.0031552283 | F30: =IFERROR(C30/FU_N,0) -> -1.3260217e-05
A31: Customer prepayments | B31: =FU_PreAmt -> 1500 | C31: =0 -> 0 | D31: =FU_V-FU_PreAmt*FU_PreCost/FU_N -> 0.01 | E31: =D31-FU_V -> 0 | F31: =IFERROR(C31/FU_N,0) -> 0
A32: ABS / GPU-backed debt | B32: =FU_ABSMax -> 5000 | C32: =0 -> 0 | D32: =FU_V -> 0.01 | E32: =D32-FU_V -> 0 | F32: =IFERROR(C32/FU_N,0) -> 0
A33: New converts (if converted when value > conv. price) | B33: =FU_CVAmt -> 3000 | C33: =IF(FU_V>FU_CVPx,FU_CVAmt/FU_CVPx,0) -> 0 | D33: =IF(FU_V>FU_CVPx,(V_EQ+FU_CVAmt)/(FU_N+FU_CVAmt/FU_CVPx),FU_V) -> 0.01 | E33: =D33-FU_V -> 0 | F33: =IFERROR(C33/FU_N,0) -> 0
A35: Combined plan to fill the target: order prepayments -> ATM -> ABS -> converts
A36: Prepayments used | B36: =MIN(FU_PreAmt,FU_Tgt) -> 0
A37: ATM used ($M) | B37: =MIN(FU_ATMsh*FU_ATMpx,FU_Tgt-FU_P1) -> 0
A38: ABS used | B38: =MIN(FU_ABSMax,FU_Tgt-FU_P1-FU_P2) -> 0
A39: Converts used | B39: =MIN(FU_CVAmt,FU_Tgt-FU_P1-FU_P2-FU_P3) -> 0
A40: Unfunded remainder (needs equity plug / more sources) | B40: =FU_Tgt-FU_P1-FU_P2-FU_P3-FU_P4 -> 0
A41: New shares: ATM + converts (if converted) | B41: =IFERROR(FU_P2/FU_ATMpx,0)+IF(FU_V>FU_CVPx,FU_P4/FU_CVPx,0) -> 0
A42: Combined value/share | B42: =(V_EQ+FU_P2+IF(FU_V>FU_CVPx,FU_P4,0)-FU_P1*FU_PreCost)/(FU_N+FU_Sh) -> 0.01
A43: Change vs model value/share ($) | B43: =FU_VC-FU_V -> 0
A44: Dilution (% of FD shares) | B44: =IFERROR(FU_Sh/FU_N,0) -> 0
A45: Memo: ABS annual interest ($M) | B45: =FU_P3*FU_ABSr -> 0

Sheet Outputs
A1: Outputs - key metrics at valuation-date horizons
A2: Horizon quarter = last quarter end on/before EDATE(ValDate, months). LTM = 4 quarters ending at horizon. Per-share value rolled forward at Ke.
A4: Metric | B4: Valuation qtr | C4: +6 months | D4: +1 year | E4: +3 years
A5: Quarter index | B5: =MATCH(EDATE(ValDate,0),Q_End,1) -> 11 | C5: =MATCH(EDATE(ValDate,6),Q_End,1) -> 13 | D5: =MATCH(EDATE(ValDate,12),Q_End,1) -> 15 | E5: =MATCH(EDATE(ValDate,36),Q_End,1) -> 23
A6: Quarter | B6: =INDEX(Q_Lab,1,B5) -> Q3'26 | C6: =INDEX(Q_Lab,1,C5) -> Q1'27 | D6: =INDEX(Q_Lab,1,D5) -> Q3'27 | E6: =INDEX(Q_Lab,1,E5) -> Q3'29
A7: Months from ValDate | B7: 0 | C7: 6 | D7: 12 | E7: 36
A8: Revenue - quarter ($M) | B8: =INDEX(PL_Rev,1,B$5) -> 653.68337 | C8: =INDEX(PL_Rev,1,C$5) -> 1059.3883 | D8: =INDEX(PL_Rev,1,D$5) -> 2170.782 | E8: =INDEX(PL_Rev,1,E$5) -> 8123.4662
A9: Revenue - LTM ($M) | B9: =SUMPRODUCT(PL_Rev*(Q_Idx>B$5-4)*(Q_Idx<=B$5)) -> 1862.6834 | C9: =SUMPRODUCT(PL_Rev*(Q_Idx>C$5-4)*(Q_Idx<=C$5)) -> 3083.7967 | D9: =SUMPRODUCT(PL_Rev*(Q_Idx>D$5-4)*(Q_Idx<=D$5)) -> 5575.8715 | E9: =SUMPRODUCT(PL_Rev*(Q_Idx>E$5-4)*(Q_Idx<=E$5)) -> 27732.463
A10: Adj. EBITDA - quarter ($M) | B10: =INDEX(PL_EBITDA,1,B$5) -> 273.75168 | C10: =INDEX(PL_EBITDA,1,C$5) -> 547.36903 | D10: =INDEX(PL_EBITDA,1,D$5) -> 1159.8695 | E10: =INDEX(PL_EBITDA,1,E$5) -> 5460.4878
A11: Adj. EBITDA - LTM ($M) | B11: =SUMPRODUCT(PL_EBITDA*(Q_Idx>B$5-4)*(Q_Idx<=B$5)) -> 654.45168 | C11: =SUMPRODUCT(PL_EBITDA*(Q_Idx>C$5-4)*(Q_Idx<=C$5)) -> 1386.3889 | D11: =SUMPRODUCT(PL_EBITDA*(Q_Idx>D$5-4)*(Q_Idx<=D$5)) -> 2849.9514 | E11: =SUMPRODUCT(PL_EBITDA*(Q_Idx>E$5-4)*(Q_Idx<=E$5)) -> 18351.187
A12: EBIT - LTM ($M) | B12: =SUMPRODUCT(PL_EBIT*(Q_Idx>B$5-4)*(Q_Idx<=B$5)) -> -877.88226 | C12: =SUMPRODUCT(PL_EBIT*(Q_Idx>C$5-4)*(Q_Idx<=C$5)) -> -1069.6541 | D12: =SUMPRODUCT(PL_EBIT*(Q_Idx>D$5-4)*(Q_Idx<=D$5)) -> -1068.7157 | E12: =SUMPRODUCT(PL_EBIT*(Q_Idx>E$5-4)*(Q_Idx<=E$5)) -> 2247.9261
A13: Free cash flow - LTM ($M) | B13: =SUMPRODUCT(CF_FCF*(Q_Idx>B$5-4)*(Q_Idx<=B$5)) -> -2123.7999 | C13: =SUMPRODUCT(CF_FCF*(Q_Idx>C$5-4)*(Q_Idx<=C$5)) -> -12090.252 | D13: =SUMPRODUCT(CF_FCF*(Q_Idx>D$5-4)*(Q_Idx<=D$5)) -> -22445.528 | E13: =SUMPRODUCT(CF_FCF*(Q_Idx>E$5-4)*(Q_Idx<=E$5)) -> -24513.378
A14: Net debt ($M, model) | B14: =INDEX(CF_NetDebt,1,B$5) -> 2021.7601 | C14: =INDEX(CF_NetDebt,1,C$5) -> 9319.7963 | D14: =INDEX(CF_NetDebt,1,D$5) -> 22209.834 | E14: =INDEX(CF_NetDebt,1,E$5) -> 46068.497
A15: Diluted shares (M, at DilPx) | B15: =INDEX(Sh_Dil,1,B$5) -> 314.92525 | C15: =INDEX(Sh_Dil,1,C$5) -> 327.19575 | D15: =INDEX(Sh_Dil,1,D$5) -> 327.19575 | E15: =INDEX(Sh_Dil,1,E$5) -> 411.98313
A16: Active IT MW | B16: =INDEX(MW_Act,1,B$5) -> 173 | C16: =INDEX(MW_Act,1,C$5) -> 292.4 | D16: =INDEX(MW_Act,1,D$5) -> 545.1 | E16: =INDEX(MW_Act,1,E$5) -> 1875
A17: Energized IT MW (Capacity) | B17: =INDEX(MW_En,1,B$5) -> 207.5 | C17: =INDEX(MW_En,1,C$5) -> 416.4 | D17: =INDEX(MW_En,1,D$5) -> 684.5 | E17: =INDEX(MW_En,1,E$5) -> 1875
A18: Implied value per share - FD, rolled at Ke ($) | B18: =V_PS*(1+Ke)^(B$7/12) -> 0.01 | C18: =V_PS*(1+Ke)^(C$7/12) -> 0.010630146 | D18: =V_PS*(1+Ke)^(D$7/12) -> 0.0113 | E18: =V_PS*(1+Ke)^(E$7/12) -> 0.01442897
A19: Implied value per share - 308.69M-style basic ($) | B19: =V_PSB*(1+Ke)^(B$7/12) -> -29.976967 | C19: =V_PSB*(1+Ke)^(C$7/12) -> -31.865953 | D19: =V_PSB*(1+Ke)^(D$7/12) -> -33.873973 | E19: =V_PSB*(1+Ke)^(E$7/12) -> -43.253676
A21: Valuation summary
A22: DCF EV ($M) | B22: =V_EV -> -183.73714
A23: Market EV at SharePx ($M) | B23: =V_MKTEV -> 74654.719
A24: FD value / share at solved price ($) | B24: =V_PS -> 0.01
A25: 12-month PT ($) | B25: =V_PT -> 0
A26: Upside vs SharePx | B26: =V_UP -> -1
A27: Share price ($) | B27: =SharePx -> 242.81
A28: Off-B/S weight used | B28: =OffBSWt -> 0.5
A29: Scenario | B29: =CHOOSE(Scen,"BULL","BASE","BEAR") -> BASE
A32: Model vs consensus (Skeptic, Oct 2 2026) | B32: FY2026 | C32: FY2027 | D32: FY2028
A33: Revenue - model | B33: =SUMIF(Q_Yr,2026,PL_Rev) -> 2423.4083 | C33: =SUMIF(Q_Yr,2027,PL_Rev) -> 7621.7173 | D33: =SUMIF(Q_Yr,2028,PL_Rev) -> 19606.895
A34: Revenue - consensus | B34: =INDEX(Cons_Rev,1,3) -> 3340 | C34: =INDEX(Cons_Rev,1,4) -> 12300 | D34: =INDEX(Cons_Rev,1,5) -> 23000
A35: Revenue - model / consensus - 1 | B35: =IF(N(B34)=0,"n/a",B33/B34-1) -> -0.27442864 | C35: =IF(N(C34)=0,"n/a",C33/C34-1) -> -0.38034818 | D35: =IF(N(D34)=0,"n/a",D33/D34-1) -> -0.14752632
A36: Adj. EBITDA - model | B36: =SUMIF(Q_Yr,2026,PL_EBITDA) -> 968.51992 | C36: =SUMIF(Q_Yr,2027,PL_EBITDA) -> 4078.9726 | D36: =SUMIF(Q_Yr,2028,PL_EBITDA) -> 12202.26
A37: Adj. EBITDA - consensus | B37: =INDEX(Cons_EB,1,3) -> 1390 | C37: =INDEX(Cons_EB,1,4) -> 6730 | D37: =INDEX(Cons_EB,1,5) -> 13980
A38: Adj. EBITDA - model / consensus - 1 | B38: =IF(N(B37)=0,"n/a",B36/B37-1) -> -0.30322308 | C38: =IF(N(C37)=0,"n/a",C36/C37-1) -> -0.39391195 | D38: =IF(N(D37)=0,"n/a",D36/D37-1) -> -0.12716309
A39: Capex - model | B39: =SUMIF(Q_Yr,2026,Capex) -> 16850.342 | C39: =SUMIF(Q_Yr,2027,Capex) -> 32170.734 | D39: =SUMIF(Q_Yr,2028,Capex) -> 29456.038
A40: Capex - consensus | B40: =INDEX(Cons_Cx,1,3) -> 0 | C40: =INDEX(Cons_Cx,1,4) -> 29100 | D40: =INDEX(Cons_Cx,1,5) -> 0
A41: Capex - model / consensus - 1 | B41: =IF(N(B40)=0,"n/a",B39/B40-1) -> n/a | C41: =IF(N(C40)=0,"n/a",C39/C40-1) -> 0.10552352 | D41: =IF(N(D40)=0,"n/a",D39/D40-1) -> n/a
A43: MW sources at YE26 / YE27 (IT MW) | B43: Q4'26 | C43: Q4'27
A44: Energized - Capacity, IT-normalized (YE27 ~950 IT = PLACEHOLDER pending Capacity's Tue basis column; named 185/305/424 & 764/1,069/1,374 mixed basis + unseen) | B44: =INDEX(MW_En,1,12) -> 292.4 | C44: =INDEX(MW_En,1,16) -> 950
A45: Mgmt connected guide (800MW-1GW YE26; 1.8 GW YE27) | B45: =INDEX(MW_Gd,1,12) -> 900 | C45: =INDEX(MW_Gd,1,16) -> 1800
A46: Contracted | B46: =INDEX(MW_Contr,1,12) -> 4000 | C46: =INDEX(MW_Contr,1,16) -> 4000
A47: Active MW driving revenue | B47: =INDEX(MW_Act,1,12) -> 207.5 | C47: =INDEX(MW_Act,1,16) -> 684.5
A50: Comparison vs Skeptic v2 (model columns for low/high/stress are STATIC snapshots written by snap.py)
B51: Model | C51: Skeptic v2 | D51: Model / Sk - 1
A52: FY27 revenue - low (model: bear) | B52: 3988.8042 | C52: =Sk_Rev27Lo -> 7000 | D52: =IFERROR(B52/C52-1,"") -> -0.43017083
A53: FY27 revenue - base (1-qtr lag) | B53: =SUMIF(Q_Yr,2027,PL_Rev) -> 7621.7173 | C53: =Sk_Rev27Base -> 9900 | D53: =IFERROR(B53/C53-1,"") -> -0.23012956
A54: FY27 revenue - high (model: bull) | B54: 12743.599 | C54: =Sk_Rev27Hi -> 12900 | D54: =IFERROR(B54/C54-1,"") -> -0.012124129
A55: FY27 revenue - STRESS (2-qtr energized lag) | B55: 6370.2023 | C55: =Sk_Rev27St -> 7600 | D55: =IFERROR(B55/C55-1,"") -> -0.16181548
A56: FY28 revenue - base | B56: =SUMIF(Q_Yr,2028,PL_Rev) -> 19606.895 | C56: =Sk_Rev28 -> 25300 | D56: =IFERROR(B56/C56-1,"") -> -0.22502393
A57: Market EV / FY27 adj. EBITDA - Nebius | B57: =V_EVEB27 -> 18.302334 | C57: =Sk_EVEB27 -> 11.1 | D57: =IFERROR(B57/C57-1,"") -> 0.64885894
A58: EV / FY27 EBITDA - CoreWeave (Skeptic) | B58: =CRWV_EVEB27 -> 4.8 | C58: =CRWV_EVEB27 -> 4.8 | D58: =IFERROR(B58/C58-1,"") -> 0
A60: Funding runway (CashFlow tab)
A61: Starting liquidity ($M) | B61: =Liq_Start -> 13792.1
A62: First quarter liquidity < 0 (Skeptic rerun: Q2'27) | B62: =Liq_NegQ -> Q1'28
A63: Liquidity Q1'27 / Q2'27 / YE27 ($B) | B63: =INDEX(Liq,1,13)/1000 -> 11.003336 | C63: =INDEX(Liq,1,14)/1000 -> 5.5153868 | D63: =INDEX(Liq,1,16)/1000 -> 2.0732027
A65: Funding runway: capex toggle side by side (STATIC, snap.py)
B66: Path-consistent (CapexMode 2, method 3) | C66: Consensus (CapexMode 1)
A67: First quarter liquidity < 0 | B67: Q1'28 | C67: Q2'28
A68: YE27 liquidity ($M) | B68: 2073.2027 | C68: 5168.0937
A69: FY27 capex ($M) | B69: 32170.734 | C69: 29100
A71: Price-cycle leg alone (Blackwell cut after Rubin; 50% reserved renewal in FY27; base MW path) vs base, STATIC ($M)
B72: FY27 revenue | C72: FY27 adj. EBITDA | D72: FY28 revenue | E72: FY28 adj. EBITDA | F72: Skeptic 03 v3.4 FY27 rev | G72: Skeptic 03 v3.4 FY28 rev
A73: Price-cycle leg, BULL cut 6.25% (base MW path, 50% renewal FY27) | B73: 190.63575 | C73: 135.35138 | D73: 98.428529 | E73: 74.805682 | F73: -77 | G73: -370
A74: Price-cycle leg, BASE cut 22% (base MW path, 50% renewal FY27) | B74: 0 | C74: 0 | D74: 0 | E74: 0 | F74: -271 | G74: -1290
A75: Price-cycle leg, BEAR cut 31% (base MW path, 50% renewal FY27) | B75: -108.93471 | C75: -77.343645 | D75: -56.244874 | E75: -42.746104 | F75: -383 | G75: -1810
A78: Comparison vs Skeptic v3.2 (skeptic_03_depreciation.xlsx). NOTE: Skeptic's path run uses CONSENSUS EBITDA; ours is bottom-up. Model values STATIC from snap.py
B79: Model zero qtr | C79: Skeptic zero qtr | D79: Model YE27 ($B) | E79: Skeptic YE27 ($B) | F79: Model YE28 ($B) | G79: Skeptic YE28 ($B)
A80: Path-tied capex - base | B80: Q1'28 | C80: =Sk3_ZeroQ -> Q4'27 | D80: 2.0732027 | E80: =Sk3_YE27 -> -0.15 | F80: -13.352424 | G80: =Sk3_YE28 -> -6.8
A81: Low (model: bear scenario) | B81: Q1'28 | C81: =Sk3L_ZeroQ -> never thru 2030 | D81: 2.1223919 | E81: =Sk3L_YE27 -> 7.1 | F81: -20.289705 | G81: =Sk3L_YE28 -> 1.5
A82: High (model: bull scenario) | B82: Q3'27 | C82: =Sk3H_ZeroQ -> Q3'27 | D82: -3.3740848 | E82: =Sk3H_YE27 -> -7.4 | F82: -9.1405711 | G82: =Sk3H_YE28 -> -15.6
A83: Consensus capex | B83: Q2'28 | C83: =Sk3C_ZeroQ -> Q2'27 | D83: 5.1680937 | E83: =Sk3C_YE27 -> -9.9 | F83: -10.369193
A85: DCF EV at GPU life ($B): model vs Skeptic v3.2 (market EV ~$74.7B)
B86: 4 yrs | C86: 5 yrs | D86: 6 yrs
A87: Model DCF EV | B87: -13.073551 | C87: -0.18373714 | D87: 8.6489722
A88: Skeptic v3.2 DCF EV | B88: =Sk3_DCF4 -> negative | C88: =Sk3_DCF5 -> 2.3 | D88: =Sk3_DCF6 -> 16.3
A89: Market EV | B89: =V_MKTEV/1000 -> 74.654719
A91: v0.3 -> v0.4 by scenario (full bridge on Bridge tab), STATIC
B92: DCF EV $M | C92: FD equity $M | D92: FD $/share | E92: 12m PT | F92: Q2'26 util | G92: FY27 rev | H92: FY27 EBITDA
A93: BRIDGE + GPU capex lead 3 qtrs (= v0.3) | B93: 94115.927 | C93: 91653.075 | D93: 248.19387 | E93: 280.45907 | F93: 0.95395587 | G93: 8517.5153 | H93: 4713.075
A94: Base (live) | B94: -183.73714 | C94: -9253.6245 | D94: 0.01 | E94: 0 | F94: 0.82509879 | G94: 7621.7173 | H94: 4078.9726
A95: BULL - v0.3 settings | B95: 363040.19 | C95: 366980.9 | D95: 943.04461 | E95: 1056.21 | F95: 0.95395587 | G95: 14376.39 | H95: 8852.2672
A96: Bull | B96: 90449.136 | C96: 86835.892 | D96: 235.23358 | E96: 263.27824 | F96: 0.82509879 | G96: 12743.599 | H96: 7677.9073
A97: BEAR - v0.3 settings | B97: -21541.186 | C97: -31992.244 | D97: 0.01 | E97: 0.0115 | F97: 0.95395587 | G97: 3424.4744 | H97: 1375.1706
A98: Bear | B98: -25664.894 | C98: -33987.78 | D98: 0.01 | E98: 0 | F98: 0.82509879 | G98: 3988.8042 | H98: 1764.5581
A99: MEMO: include-both terminal (TermBase=1) | B99: -7484.7981 | C99: -16554.686 | D99: 0.01 | E99: 0 | F99: 0.82509879 | G99: 7621.7173 | H99: 4078.9726
A100: Base w/ mgmt connected guide MW (MWSel=3) | B100: 32246.702 | C100: 13551.031 | D100: 43.013418 | E100: 56.531017 | F100: 0.82509879 | G100: 21866.995 | H100: 12687.893

Sheet Checks
A1: Checks
A3: Check | B3: Model | C3: Target / tolerance | D3: Status | E3: Note
A4: CRITICAL: convert counted in BOTH shares and debt (solved price, chosen weight) | B4: =IF(DilMethod=1,SUMPRODUCT((((CVDebtBasis=1)*Valuation!$E$79:$E$90+(CVDebtBasis=2)*Valuation!$F$79:$F$90))),IF(DilMethod=2,SUMPRODUCT((V_PSolve>Valuation!$H$79:$H$90)*(((CVDebtBasis=1)*Valuation!$E$79:$E$90+(CVDebtBasis=2)*Valuation!$F$79:$F$90))),0))+V_CVDEBT-SUMPRODUCT((((CVDebtBasis=1)*Valuation!$E$79:$E$90+(CVDebtBasis=2)*Valuation!$F$79:$F$90))) -> 0 | C4: 0 | D4: =IF(ABS(B4)<0.5,"OK","DOUBLE COUNT") -> OK | E4: If-converted + debt-counted must equal total (CVDebtBasis: 1 original principal, 2 accreted); net-share (3) keeps principal as debt by design
A5: CRITICAL: same at SharePx (market EV) | B5: =IF(DilMethod=1,SUMPRODUCT((((CVDebtBasis=1)*Valuation!$E$79:$E$90+(CVDebtBasis=2)*Valuation!$F$79:$F$90))),IF(DilMethod=2,SUMPRODUCT((SharePx>Valuation!$H$79:$H$90)*(((CVDebtBasis=1)*Valuation!$E$79:$E$90+(CVDebtBasis=2)*Valuation!$F$79:$F$90))),0))+V_CVDmkt-SUMPRODUCT((((CVDebtBasis=1)*Valuation!$E$79:$E$90+(CVDebtBasis=2)*Valuation!$F$79:$F$90))) -> 0 | C5: 0 | D5: =IF(ABS(B5)<0.5,"OK","DOUBLE COUNT") -> OK
A6: Economic basic shares at Q3'26 (M) = 271.86 + 15.77 + 21.07 | B6: =INDEX(Sh_EconBasic,1,11) -> 308.69115 | C6: 308.69 | D6: =IF(ABS(B6-C6)<0.05,"OK","CHECK") -> OK
A7: Fully diluted at $242.81 EXCL. unsold ATM vs Filings CapStructure | B7: =V_FDmkt -> 369.22679 | C7: =FD_Filings -> 369.2 | D7: =IF(ABS(B7-C7)<2,"OK","CHECK") -> OK | E7: nebius_filings.xlsx CapStructure
A8: Fully diluted at $242.81 INCL. 12.27M ATM vs Filings | B8: =V_FDmkt+ATM_Rem -> 381.4973 | C8: =FD_FilingsATM -> 381.5 | D8: =IF(ABS(B8-C8)<2,"OK","CHECK") -> OK | E8: ATM is a funding source, not in today's count
A9: ITM convert shares at $242.81 (six ITM) | B9: =V_ITMsh -> 50.021939 | C9: =ITM_Sh_Chk -> 50.03 | D9: =IF(ABS(B9-C9)<0.5,"OK","CHECK") -> OK | E9: Steps at $324.65 / $313.46 / $183.22 / $180.31 / $138.75 / $51.45
A10: ITM convert principal at $242.81 ($M orig.) | B10: =V_ITMprin -> 7675 | C10: =ITM_Prin_Chk -> 7680 | D10: =IF(ABS(B10-C10)<15,"OK","CHECK") -> OK
A11: Market EV at $242.81 ($M), CapStructure basis vs Filings ~74.7B | B11: =V_MKTEV -> 74654.719 | C11: 74700 | D11: =IF(ABS(B11/C11-1)<0.01,"OK","CHECK") -> OK | E11: 6/30 balance + Aug notes + exchange; unrestricted cash only
A12: Dilution solve convergence |P15-P14| | B12: =V_CONV -> 0 | C12: 0.01 | D12: =IF(B12<C12,"OK","NOT CONVERGED") -> OK
A13: Microsoft implied TCV vs reported ($M) | B13: =MSFT_Chk -> 0 | C13: 0 | D13: =IF(ABS(B13)<5,"OK","CHECK") -> OK
A14: Quarters (pre-Bloom) Microsoft revenue exceeds ~$350M/qtr genset ceiling | B14: =SUMPRODUCT((MS_CeilChk>0)*(Q_Idx<IF(BloomOn=1,BloomIdx,99))) -> 0 | C14: 0 | D14: =IF(B14=0,"OK","CHECK") -> OK
A15: Q4 bridge: unseen MW vs Skeptic/Capacity 83-200 MW | B15: =BR_MW25 -> 92.646129 | C15: =UnseenChkHi -> 200 | D15: =BR_Chk -> OK - overlaps 83-200 MW
A16: History capex split = reported (sum abs diff) | B16: =SUMPRODUCT(ABS(N(+CapexChk))) -> 0 | C16: 0 | D16: =IF(B16<1,"OK","CHECK") -> OK
A17: Q2'26 book (a) share vs GPU Market 45% (40-46%) | B17: =INDEX(Book_A,1,10)/INDEX(AI_Model,1,10) -> 0.46063494 | C17: =MixA_Q2 -> 0.45 | D17: =IF(AND(ROUND(B17,2)>=0.4,ROUND(B17,2)<=0.46),"OK","CALIBRATE") -> OK
A18: Q2'26 book (b) share vs ~50% (44-57%) | B18: =INDEX(Book_B,1,10)/INDEX(AI_Model,1,10) -> 0.46986058 | C18: =MixB_Q2 -> 0.5 | D18: =IF(AND(B18>=0.44,B18<=0.57),"OK","CALIBRATE") -> OK
A19: Q2'26 book (c) share vs ~4% (1.3-9%) | B19: =INDEX(Book_C,1,10)/INDEX(AI_Model,1,10) -> 0.069504476 | C19: =MixC_Q2 -> 0.04 | D19: =IF(AND(B19>=0.013,B19<=0.09),"OK","CALIBRATE") -> OK
A20: Depreciation-yield flags (drop after chip availability) | B20: =SUM(DepYldFlag) -> 1 | C20: 0 | D20: =IF(B20=0,"OK","FLAG - review PIS dates") -> FLAG - review PIS dates | E20: Material weakness over depreciation start dates
A21: Q3'26 transfer into service | B21: =Q3TransChk -> PENDING (model 4,702) | D21: =B21 -> PENDING (model 4,702)
A22: Sites: named-site energized imports tie to Capacity file COMPANY row (sum abs diff) | B22: =SUMPRODUCT(ABS(CapTie)) -> 0 | C22: 0 | D22: =IF(B22<1,"OK","CHECK") -> OK
A23: Q2'26 tie: model AI cloud revenue vs actual $574.9M | B23: =INDEX(AI_Model,1,10) -> 574.9 | C23: =INDEX(H_AIRev,1,10) -> 574.9 | D23: =IF(ABS(B23/C23-1)<0.01,"OK","CHECK") -> OK | E23: Utilization calibrated
A24: Implied Q2'26 utilization (books b+c) | B24: =UtilQ2 -> 0.82509879 | C24: 40-100% | D24: =UtilFlag -> OK (40-100%) | E24: Flag (not forced) if outside 40-100%
A25: (a) Q2'26 revenue per GPU-hour of capacity (annualized AI rev / GPUs / 8,760) | B25: =INDEX(AI_Model,1,10)*4*1000000/INDEX(GPU_End,1,10)/8760 -> 2.9670688 | C25: =Chk_RevGPUhr -> 3.27 | D25: =IF(ABS(B25/C25-1)<=0.1,"OK","CHECK") -> OK | E25: +/-10% (GPU Market, Derived)
A26: (b) Q2'26 annualized AI rev per $ avg gross servers in service | B26: =INDEX(AI_Model,1,10)*4/AVERAGE(INDEX(H_SRV,1,9),INDEX(H_SRV,1,10)) -> 0.46501658 | C26: =Chk_RevSrv -> 0.46 | D26: =IF(ABS(B26/C26-1)<=0.1,"OK","CHECK") -> OK | E26: Filings, Derived
A27: (b3) Capacity server ceiling: Q2'26 GPUs x $45-60k (high end) vs $5.2B servers in service | B27: =INDEX(GPU_End,1,10)*Chk_SrvHi/1000000 -> 5308.5 | C27: =Chk_SrvCap -> 5197.7 | D27: =IF(B27<=C27,"OK: "&TEXT(INDEX(GPU_End,1,10)*Chk_SrvLo/1000000,"#,##0")&"-"&TEXT(B27,"#,##0")&" <= 5,198; implied $"&TEXT(C27*1000000/INDEX(GPU_End,1,10),"#,##0")&"/GPU","FLAG") -> FLAG | E27: Capacity, Estimated
A28: (b2) Modeled in-service GPU cost at 6/30 (GPUs x $/GPU) vs $5.2B servers | B28: =(INDEX(GPU_End_H,1,10)*GPUCost_H+INDEX(GPU_End_B,1,10)*GPUCost_B+INDEX(GPU_End_N,1,10)*GPUCost_N)/1000000 -> 4489.925 | C28: =Chk_SrvCap -> 5197.7 | D28: =IF(B28<=C28,"OK","FLAG: exceeds servers in service") -> OK
A29: (c) Q2'26 revenue per energized MW ($M/yr) | B29: =INDEX(AI_Model,1,10)*4/INDEX(MW_En,1,10) -> 13.292486 | C29: =Chk_RevEnMW -> 13 | D29: =IF(ABS(B29/C29-1)<=0.15,"OK","CHECK") -> OK | E29: ~$13M (2.30B / ~173 MW)
A30: Q2'26 contract (book a) IT MW as share of energized MW | B30: =INDEX(A_MW,1,10)/INDEX(MW_En,1,10) -> 0.58580925 | C30: info | D30: ="INFO" -> INFO | E30: Microsoft GPU use capped at Vineland energized IT MW (39 MW Q2'26) + Meta #1 48 MW (TCV/ACV-derived) vs 173 MW energized; v0.1 fix took Q2'26 utilization from 133% to ~92%
A31: Q2'26 energized MW (Capacity base, IT) | B31: =INDEX(MW_En,1,10) -> 173 | C31: 173 | D31: =IF(ABS(B31-C31)<3,"OK","CHECK") -> OK
A32: Q2'26 GPUs: model (Capacity 'GPUs deployed' ~80,416 + GPU anchor gap if GPUAnchorOn) | B32: =INDEX(GPU_End,1,10) -> 88475 | C32: =80416+GPUAnchorD -> 88475 | D32: =IF(ABS(B32/C32-1)<0.01,IF(GPUAnchorOn=1,"INFO: anchored to ~30k at 3/31/25 (+"&TEXT(GPUAnchorD,"#,##0")&" vs Capacity file); Q2 utilization "&TEXT(UtilQ2,"0.0%"),"OK"),"CHECK") -> INFO: anchored to ~30k at 3/31/25 (+8,059 vs Capacity file); Q2 utilization 82.5%
A33: Unexplained ARR residual at 6/30 (June run-rate basis; NOT unseen capacity) | B33: =ARR_Res -> 597.13511 | C33: =ARR_ResTeamLo&"-"&ARR_ResTeamHi -> 650-700 | D33: ="INFO: model "&TEXT(ARR_Res,"#,##0")&" = "&TEXT(ARR_ResMW_TLo,"0")&"-"&TEXT(ARR_ResMW_THi,"0")&" MW-eq at team $13.3-13.5M/MW (model June RR "&TEXT(ARR_RR,"#,##0")&" = $"&TEXT(ARR_RRMW,"0.0")&"M/MW); team-basis residual "&TEXT(ARR_ResTB_Lo,"#,##0")&"-"&TEXT(ARR_ResTB_Hi,"#,##0") -> INFO: model 597 = 44-45 MW-eq at team $13.3-13.5M/MW (model June RR 2,403 = $13.9M/MW); team-basis residual 665-699 | E33: Pending Filings on ARR scope / signed-not-billing
A34: Adj. EBITDA margin FY28 - model vs consensus (flag if > +5pp) | B34: =SUMIF(Q_Yr,2028,PL_EBITDA)/SUMIF(Q_Yr,2028,PL_Rev) -> 0.62234537 | C34: =MarginCons28 -> 0.60782609 | D34: =IF(B34-C34>0.05,"FLAG: model margin > consensus +5pp","OK") -> OK | E34: Skeptic consensus 13.98/23.0
A35: Adj. EBITDA margin FY30 - model vs peer ~62% (flag if > +8pp) | B35: =SUMIF(Q_Yr,2030,PL_EBITDA)/SUMIF(Q_Yr,2030,PL_Rev) -> 0.70212902 | C35: =MarginPeer -> 0.62 | D35: =IF(B35-C35>0.08,"FLAG: above peer +8pp - review opex/MW and revenue/MW","OK") -> FLAG: above peer +8pp - review opex/MW and revenue/MW | E35: CoreWeave ~62% placeholder
A36: FY30 margin sensitivity: PD + SG&A held at FY28 % of revenue (vs placeholder step-down) | B36: =SUMIF(Q_Yr,2030,PL_EBITDA)/SUMIF(Q_Yr,2030,PL_Rev)-(1-OpexHold)*((INDEX(PDpct,1,2028-FYBase)+INDEX(SGApct,1,2028-FYBase))-(INDEX(PDpct,1,2030-FYBase)+INDEX(SGApct,1,2030-FYBase))) -> 0.65212902 | C36: =MarginPeer -> 0.62 | D36: =IF(B36-C36>0.08,"FLAG: still above peer +8pp","INFO: within +8pp of peer") -> INFO: within +8pp of peer | E36: PD 8% + SG&A 10% (FY28) instead of 6% + 7% (FY30); toggle OpexHold=1 for full model effect (Sensitivity)
A37: FY30 opex per avg IT MW ($M/MW-yr: COR + PD + SG&A ex-SBC) | B37: =(SUMIF(Q_Yr,2030,PL_Rev)-SUMIF(Q_Yr,2030,PL_EBITDA))/(SUMIF(Q_Yr,2030,MW_Avg)/4) -> 5.6347815 | C37: info | D37: ="INFO: revenue/MW "&TEXT(SUMIF(Q_Yr,2030,PL_Rev)/(SUMIF(Q_Yr,2030,MW_Avg)/4),"0.0") -> INFO: revenue/MW 18.9
A38: FY26 capex vs company guide $20-25B (Aug 12 2026 call) | B38: =SUMIF(Q_Yr,2026,Capex) -> 16850.342 | C38: 20,000-25,000 | D38: =IF(AND(B38>=20000*0.9,B38<=25000*1.1),"OK (within guide +/-10%)","FLAG: outside guide") -> FLAG: outside guide | E38: Fact base: FY2026 capex guidance $20-25B (call transcript, CFO); GPULead calibration
A39: Bull DCF EV vs 3x base (STATIC, snap.py) | B39: =V_EVBullS -> 90449.136 | C39: =3*V_EVBaseS -> -551.21142 | D39: =IF(V_EVBaseS=0,"run snap.py",IF(B39>C39,"FLAG: bull EV > 3x base - review bull drivers","OK")) -> FLAG: bull EV > 3x base - review bull drivers | E39: Bull/base EVs from snapshot
A40: Q2'26 calibration scenario-invariant: utilization bull / bear minus base (STATIC) | B40: =MAX(ABS(V_UtBullS-V_UtBaseS),ABS(V_UtBearS-V_UtBaseS)) -> 0 | C40: 0 | D40: =IF(V_UtBaseS=0,"run snap.py",IF(B40<0.0005,"OK: all scenarios tie $574.9M at "&TEXT(V_UtBaseS,"0.0%"),"FLAG: history depends on scenario")) -> OK: all scenarios tie $574.9M at 82.5%
A41: Implied blended realization vs OD list, Q2'26 books (b)+(c) (billed GPU-hours at Q2 avg list) vs GPU Market 0.72-0.80 | B41: =(INDEX(Book_B,1,LastHist)+INDEX(Book_C,1,LastHist))*1000000/((INDEX(NCA_H,1,LastHist)*ODq_H+INDEX(NCA_B,1,LastHist)*ODq_B+INDEX(NCA_N,1,LastHist)*ODq_N)*INDEX(Q_Hrs,1,LastHist)*UtilQ2) -> 0.74385588 | C41: 0.72-0.80 | D41: =IF(AND(B41>=0.72,B41<=0.8),"OK: within GPU Market range",IF(B41<0.72,"INFO: below range","FLAG: above range")) -> OK: within GPU Market range | E41: Reserved RealRes_B 0.72 x ResSh + on-demand/spot mix
A42: New-deal pricing: model new-MW gross revenue per IT MW-yr (NewDealOn: blended multi-year + short-term at Q1'27 vintage; off: GB300 at Oct-1 list x RealRes x Util_Res) vs IREN >$20M (3-yr GB300-class ~$4.65/GPU-hr) | B42: =IF(NewDealOn=1,RM_ND,RM_GB300) -> 22.39175 | C42: 20 | D42: =IF(B42>C42*1.25,"FLAG: model new-MW pricing >1.25x IREN benchmark",IF(B42<C42*0.8,"INFO: below benchmark","OK: multi-year "&TEXT(RM_MY,"0.0")&"; blended net leased "&TEXT(RM_ND_L,"0.0")&" vs 17.8; GPU-hour GB300 engine "&TEXT(RM_GB300,"0.0")&" (legacy only)")) -> OK: multi-year 22.0; blended net leased 20.2 vs 17.8; GPU-hour GB300 engine 30.2 (legacy only) | E42: Short-term tranche (STShare) at $40-50M included in blend; IREN excludes short-term
A43: Vineland shutdown: probability-weighted Q4'26 Microsoft revenue at risk at VinRevMW vs Capacity ~$67M | B43: =VinExpQ4 -> 68.035291 | C43: 67 | D43: =IF(ABS(B43-C43)<=3,"OK: ties ~$67M (Capacity, Derived); VinShutSel="&VinShutSel,"FLAG: differs from Capacity tie-out") -> OK: ties ~$67M (Capacity, Derived); VinShutSel=0 | E43: vineland_shutdown.xlsx weights; $14.5M/IT MW-yr
A44: Backlog floor: model AI cloud revenue Jul'26-Jun'28 minus RPO recognised in window (~$13.5B) = implied revenue from deals signed after Q2'26 | B44: =SUMPRODUCT((Q_Idx>LastHist)*(Q_Idx<=LastHist+8)*AI_Model)-RPO_Tot*RPO24Pct -> 4069.2864 | C44: =RPO_Tot*RPO24Pct -> 13496.4 | D44: =IF(B44<0,"FLAG: model below contracted backlog","INFO: "&TEXT(B44/(B44+C44),"0%")&" of window revenue unsold at 6/30 (~"&TEXT(B44/(B44+C44)*SUMPRODUCT((Q_Idx>LastHist)*(Q_Idx<=LastHist+8)*MW_Avg)/8,"0")&" of avg "&TEXT(SUMPRODUCT((Q_Idx>LastHist)*(Q_Idx<=LastHist+8)*MW_Avg)/8,"0")&" active MW, revenue-weighted); sold share of new 2027+ MW "&TEXT(RPO_Sold,"0%")) -> INFO: 23% of window revenue unsold at 6/30 (~112 of avg 485 active MW, revenue-weighted); sold share of new 2027+ MW 52% | E44: Q2'26 Note 2: RPO $37.49B, 36% Jul'26-Jun'28
A45: Backlog cash floor Jul'26-Jun'28 = RPO in window - 6/30 DR recognised within 24 months (DR_24 base $2.25B; range $2.0-2.5B) | B45: =RPO_Tot*RPO24Pct-DR_24 -> 11246.4 | C45: 11,000-11,500 | D45: ="INFO: range "&TEXT(RPO_Tot*RPO24Pct-2500,"#,##0")&"-"&TEXT(RPO_Tot*RPO24Pct-2000,"#,##0")&"; model cash revenue in window (AI rev - DR release) "&TEXT(SUMPRODUCT((Q_Idx>LastHist)*(Q_Idx<=LastHist+8)*(AI_Model-CF_DRRel)),"#,##0") -> INFO: range 10,996-11,496; model cash revenue in window (AI rev - DR release) 13,381 | E45: DR 6/30: current $979.4M, non-current $4,995.8M (Reported)
A46: Payback (months) vs mgmt 1y10m (22), prepayments excluded: GB300 leased IT / gross; Rubin leased base / bear (no toggle) | B46: =PB_GB_IT -> 28.32 | C46: =PB_Target -> 22 | D46: ="INFO: GB300 "&TEXT(PB_GB_IT,"0")&" / "&TEXT(PB_GB_Gr,"0")&" mo (IT / gross); Rubin base "&TEXT(PB_RU_IT,"0")&" / bear "&TEXT(PB_RU_Gr,"0")&" mo; IRR GB300 IT "&TEXT(PB_GB_IRR,"0%")&", Rubin base "&TEXT(PB_RU_IRR,"0%")&"; IT fits 22 only at ~$32M capex, or if prepayments counted (implied rev "&TEXT(PB_ImplRevPre,"0.0")&")" -> INFO: GB300 28 / 23 mo (IT / gross); Rubin base 36 / bear 51 mo; IRR GB300 IT 32%, Rubin base 19%; IT fits 22 only at ~$32M capex, or if prepayments counted (implied rev 18.4) | E46: Payback_Floor tab C; basis not disclosed by management
A47: EBITDA per IT MW-yr by generation (IT reading): GB300 vs Rubin at RubinMW (direct); opex fixed | B47: =PB_EBGB -> 17.5 | C47: =PB_EBRubin -> 13.5 | D47: ="INFO: GB300 "&TEXT(PB_EBGB,"0.0")&" -> Rubin "&TEXT(PB_EBRubin,"0.0")&" ("&TEXT(PB_EBRubin/PB_EBGB-1,"0%")&"); Rubin leased capex "&TEXT(CPM_Lease_VR,"0.0")&" (low-medium confidence)" -> INFO: GB300 17.5 -> Rubin 13.5 (-23%); Rubin leased capex 41.0 (low-medium confidence) | E47: v0.7: Rubin capex flat to GB300 in base
A48: Asset floor: DCF EV vs PV(RPO margin) - capex for contracted MW | B48: =V_EV -> -183.73714 | C48: =PF_EV -> 3639.7399 | D48: =IF(B48<C48,"FLAG: DCF EV below asset floor","OK: DCF EV above floor")&"; equity floor $/sh (price-dependent FD count) "&TEXT(PF_PS1,"0.0")&" cons / "&TEXT(PF_PS2,"0.0")&" mark / "&TEXT(PF_PS3,"0.0")&" high" -> FLAG: DCF EV below asset floor; equity floor $/sh (price-dependent FD count) 10.9 cons / 19.6 mark / 33.8 high | E48: Payback_Floor tab D
A49: Revenue double-count: prepayments in revenue? (new-deal $20-25M/MW is revenue-recognition basis excl. prepayment, Q2 deck fn 2) | B49: =0 -> 0 | C49: 0 | D49: ="OK: prepayments are cash timing only (CashFlow: Prepayments received / DR release); revenue engine = MW x $/MW and GPU-hours, no reference to prepayments or DR" -> OK: prepayments are cash timing only (CashFlow: Prepayments received / DR release); revenue engine = MW x $/MW and GPU-hours, no reference to prepayments or DR | E49: Formula audit v0.5
A50: Cash double-count: DR release reduces later cash (CFO = EBITDA + prepayments - release); closing Q4'30 DR run-off deducted from EV ($M) | B50: =V_DRAdj -> -7119.9038 | C50: =-V_DR30 -> -12442.234 | D50: ="INFO: within-horizon release "&TEXT(SUM(CF_DRRel),"#,##0")&" deducted from cash; post-horizon run-off PV "&TEXT(-V_DRAdj,"#,##0")&" deducted (DRTermOn="&DRTermOn&"); closing DR "&TEXT(V_DR30,"#,##0") -> INFO: within-horizon release 20,611 deducted from cash; post-horizon run-off PV 7,120 deducted (DRTermOn=1); closing DR 12,442 | E50: v0.5 fix: before, terminal UFCF counted the unreleased prepaid balance as cash again
A51: Prepayments: total new prepayments FY26H2-FY30 / new-build capex (signed Microsoft/Meta 0%, new hyperscaler HSPre, other 38.5% -> 22.5%) | B51: =SUM(CF_Prepay)/SUMPRODUCT((Q_Idx>LastHist)*CapNew) -> 0.24422334 | C51: info | D51: ="INFO: HSPre "&TEXT(HSPre,"0%")&"; other 2028+ "&TEXT(PrepayPct28,"0.0%")&"; decay "&PrepayDecayOn -> INFO: HSPre 30%; other 2028+ 22.5%; decay 1
A52: Significant financing component (ASC 606): SFC revenue gross-up in model revenue/EBITDA used for DCF | B52: =0 -> 0 | C52: 0 | D52: ="OK: none (no SFC gross-up, no SFC interest; DCF on cash flows). Implied advance financing cost <= "&TEXT(V_SFCRate,"0.0%")&"/yr (Estimated upper bound)" -> OK: none (no SFC gross-up, no SFC interest; DCF on cash flows). Implied advance financing cost <= 3.7%/yr (Estimated upper bound) | E52: Reported history may embed a small SFC gross-up (not disclosed separately)
A53: GPU history anchor: model GPUs at 3/31/2025 vs ~30,000 actual (20-F) | B53: =INDEX(GPU_End,1,5) -> 30000 | C53: =GPU_Q125 -> 30000 | D53: =IF(ABS(B53-C53)<500,"OK: anchored (gap "&TEXT(GPUAnchorD,"#,##0")&" GPUs vs Capacity file)","FLAG: Capacity file "&TEXT(B53,"#,##0")&" vs ~30,000 actual (GPUAnchorOn=0)") -> OK: anchored (gap 8,059 GPUs vs Capacity file) | E53: Single GPU calibration point; Kansas City likely live Q1'25 at 5-15 MW
A54: Rubin $/GPU-hr premium vs GB300 (model) vs per-MW parity (GPUs/MW GB300 / Rubin) | B54: =Rubin_Prem -> 1.2 | C54: =GPUMW_B/GPUMW_N -> 1.5625 | D54: =IF(ABS(B54-C54)<0.01,"INFO: at parity (OPEN input, no public Rubin price)",IF(B54<C54,"INFO: Rubin revenue/MW below GB300","INFO: Rubin revenue/MW above GB300")) -> INFO: Rubin revenue/MW below GB300 | E54: Sensitivity 1.0x / 1.25x / 1.53x
A55: History MW basis (1 Capacity 173 / 2 company ~190 both history & forward / 3 mismatch test) | B55: =HistMWBasis -> 1 | C55: 1 | D55: ="INFO: Q2 energized basis "&TEXT(INDEX(MW_Act,1,LastHist),"0")&" MW; Q2 rev/MW $"&TEXT(INDEX(H_AIRev,1,LastHist)*4/INDEX(MW_Act,1,LastHist),"0.0")&"M" -> INFO: Q2 energized basis 173 MW; Q2 rev/MW $13.3M | E55: Same basis must drive history calibration and forward path
A56: June step-up vs March: monthly $M and IT MW at take-or-pay pricing (upper end) | B56: =ARR_Step -> 88 | C56: =ARR_StepMW -> 88 | D56: ="INFO: ~"&TEXT(ARR_StepMW,"0")&" MW at $12M/MW take-or-pay (fewer if reserved at Q2 renewal rates); JuneExitOn="&JuneExitOn -> INFO: ~88 MW at $12M/MW take-or-pay (fewer if reserved at Q2 renewal rates); JuneExitOn=0
A57: DCF EV sign (negative = plan destroys value at WACC; equity floored at 0) | B57: =V_EV -> -183.73714 | C57: 0 | D57: =IF(B57<0,"FLAG: EV<0; FD value/share floored at 0","OK") -> FLAG: EV<0; FD value/share floored at 0
A58: Terminal value basis | B58: =V_TV -> 71675.44 | C58: =V_TVB -> 59466.846 | D58: =V_TVBasis -> RUN-OFF (reinvestment value-destroying) | E58: Run-off floor when replacement capex exceeds terminal cash generation
A59: Funding runway: first quarter liquidity < 0 (after v0.7 funding plan when FP_On; no plug) | B59: =Liq_NegQ -> Q1'28 | C59: Skeptic: Q2'27 | D59: ="INFO" -> INFO
A60: Opening liquidity: Aug-26 converts counted ONCE (runway gross row + CashFlow net row, Q3'26 only); 6/30 cash $8,042M excludes them | B60: =SUM(Liq_Aug) -> 5750 | C60: =AugGross -> 5750 | D60: =IF(AND(ABS(B60-C60)<0.5,ABS(SUMPRODUCT((Q_Idx<>11)*Liq_Aug))<0.5,ABS(INDEX(H_Cash,1,LastHist)-CS_Cash)<0.5,ABS(SUM(CF_CVProc)-SUM(CF_FPConv)-AugNet)<0.5),"OK: once (runway Q3'26 gross 5,750; CashFlow Q3'26 net 5,680)","DOUBLE/MISSING") -> OK: once (runway Q3'26 gross 5,750; CashFlow Q3'26 net 5,680) | E60: Runway row '+ Aug-2026 converts gross' (CashFlow tab) and 'Convert issuance proceeds (net)' row
A61: $775M asset-backed facility drawn in base (LoanOn) | B61: =SecAmt*LoanOn -> 0 | C61: 0 | D61: =IF(LoanOn=0,"OK: $0 drawn (undisclosed); $775M sensitivity","INFO: $775M drawn sensitivity") -> OK: $0 drawn (undisclosed); $775M sensitivity | E61: SOFR+2.50%; cash, debt, interest and runway all switch together
A62: Liquidity after funding plan: min Q3'26-Q4'27 vs MinCash | B62: =MIN(INDEX(Liq,1,11):INDEX(Liq,1,16)) -> 2073.2027 | C62: =MinCash -> 2000 | D62: =IF(FP_On=0,"INFO: plan off",IF(B62>=C62,"OK: gap through YE27 closed","FLAG: plan does not close the FY27 gap"))&"; min to Q4'30 "&TEXT(MIN(Liq),"#,##0") -> OK: gap through YE27 closed; min to Q4'30 -36,275 | E62: Plan is ESTIMATED (not guidance); 2028+ needs further raises
A63: Convert waterfall at $147 (existing notes): converting principal / full-conversion shares vs ~$3.34B / ~26.2M | B63: =SUMPRODUCT((147>Valuation!$H$79:$H$90)*Valuation!$E$79:$E$90) -> 3337.5 | C63: 3337.5 | D63: =IF(ABS(B63-C63)<5,"OK","CHECK")&"; shares "&TEXT(SUMPRODUCT((147>Valuation!$H$79:$H$90)*Valuation!$E$79:$E$90*Valuation!$G$79:$G$90)/1000,"0.0")&"M; at $46 debt "&TEXT(SUMPRODUCT((46<=Valuation!$H$79:$H$90)*Valuation!$E$79:$E$90),"#,##0") -> OK; shares 26.2M; at $46 debt 13,425 | E63: Parent reference: $46 all OTM ($13.4B debt); $147 26.2M sh; $243 all but Feb-30/Feb-34
A64: Post-funding FD shares at solved price (M) vs pre-funding | B64: =V_SHF -> 327.19575 | C64: =V_SH -> 314.92525 | D64: ="INFO: +"&TEXT(V_SHF-V_SH,"0.0")&"M (ATM "&TEXT(V_FPSh,"0.0")&"M); full-conv "&TEXT(V_SHFFull,"0.0")&" / NSS "&TEXT(V_SHFNSS,"0.0")&"; value/share pre "&TEXT(V_PS,"0.0")&" -> post "&TEXT(V_PSF,"0.0") -> INFO: +12.3M (ATM 12.3M); full-conv 327.2 / NSS 327.2; value/share pre 0.0 -> post 0.0
A65: Avride: value credited (V_AV) vs PV burn add-back (V_AVAdd) - credit value AND add back burn, or neither | B65: =V_AV -> 0 | C65: =V_AVAdd -> 0 | D65: =IF(V_AV=0,"OK: Avride $0, burn kept in EBITDA",IF(V_AVAdd>0,"OK: burn added back (no double count)","FLAG: double count")) -> OK: Avride $0, burn kept in EBITDA
A66: Red-graded sites (count) | B66: =RedSites -> 5 | D66: ="INFO" -> INFO
A67: FY27 EBIT vs Skeptic at live life | B67: =SUMIF(Q_Yr,2027,PL_EBIT) -> -984.89813 | C67: =CHOOSE(MATCH(Life_B,{4,5,6},1),SkEBIT4,SkEBIT5,SkEBIT6) -> 1980 | D67: ="INFO" -> INFO | E67: See Sensitivity 4/5/6

Sheet Inputs
A1: Inputs & Assumptions (scenario-driven)
A2: Blue = input. Fill: orange = PLACEHOLDER (no source yet), yellow = Estimated/Consensus, none = Reported/Derived. Live column = CHOOSE(Scenario, Bull, Base, Bear). Owners fill/replace their cells; never overwrite formulas.
A4: Scenario selector (1 = Bull, 2 = Base, 3 = Bear) | D4: 2 | E4: =CHOOSE(Scen,"BULL","BASE","BEAR") -> BASE
A6: Scalar input | B6: Unit | C6: Bull | D6: Base | E6: Bear | F6: LIVE | J6: Owner | K6: Status | L6: Source / method
A7: General
A8: Valuation date | B8: date | C8: — | D8: 46299 | E8: — | F8: =D8 -> 46299 | J8: Modeling | K8: Input | L8: Pitch valuation date; drives DCF discounting and Outputs horizons
A9: Last actual quarter index (10 = Q2'26) | B9: # | C9: — | D9: 10 | E9: — | F9: =D9 -> 10 | J9: Modeling | K9: Input | L9: Roll forward to 11 when Q3'26 is reported
A10: Fiscal-year base (year before first model year) | B10: yr | C10: — | D10: 2023 | E10: — | F10: =D10 -> 2023 | J10: Modeling | K10: Input | L10: Structural: annual-input column = FY - FYBase
A11: Current share price (NBIS) | B11: $/sh | C11: — | D11: 242.81 | E11: — | F11: =D11 -> 242.81 | J11: Skeptic | K11: Reported | L11: Oct 2 2026 close per Skeptic (/workspace/nebius/skeptic/01_priced_in.xlsx), medium confidence; used for convert ITM test, TSM, equity raises
A12: MW block that drives revenue (1 contracted, 2 energized est. [Capacity, default], 3 mgmt-connected guide, 4 Capacity proposed path [scenario, not base until Tuesday file]) | B12: # | C12: — | D12: 2 | E12: — | F12: =D12 -> 2 | J12: Modeling | K12: Input | L12: Default = Capacity energized base (estimated live IT load); guided path kept as comparison only
A13: Energized (live IT load) -> billing lag, MW source 2 | B13: qtrs | C13: 1 | D13: 1 | E13: 1 | F13: =CHOOSE(Scen,C13,D13,E13) -> 1 | J13: Capacity | K13: Estimated | L13: Base 1 qtr. 2 qtrs = STRESS case (Sensitivity snapshot), not the bear default
A14: IT capex method (1 = GPUs x $/GPU, 2 = flat $M per IT MW, 3 = site path: new energized IT MW x per-site $/MW by ownership & generation [default]) | B14: # | C14: — | D14: 3 | E14: — | F14: =D14 -> 3 | J14: Modeling | K14: Input | L14: Method 3 = path-consistent per Capacity gpu_mw_capex.xlsx
A15: Owned site all-in capex per IT MW - GB200 | B15: $M/MW | C15: — | D15: 42 | E15: — | F15: =D15 -> 42 | J15: Capacity | K15: Estimated | L15: /workspace/nebius/capacity/gpu_mw_capex.xlsx CapexPerMW (incl ~$10-12.5M shell+power)
A16: Owned site all-in capex per IT MW - GB300 | B16: $M/MW | C16: — | D16: 53 | E16: — | F16: =D16 -> 53 | J16: Capacity | K16: Estimated | L16: as above
A17: Owned site all-in capex per IT MW - Vera Rubin (LOW-MEDIUM confidence) | B17: $M/MW | C17: 53 | D17: 56 | E17: 59 | F17: =CHOOSE(Scen,C17,D17,E17) -> 56 | J17: Capacity | K17: Estimated | L17: v0.7: $53-59M (base 56) = leased $41-48.5M + shell/power; was $43M. Capacity reconciles networking Tuesday
A18: Owned site capex per IT MW - Hopper/B200/B300 (GB200 proxy) | B18: $M/MW | C18: — | D18: 42 | E18: — | F18: =D18 -> 42 | J18: Capacity | K18: Estimated | L18: proxy
A19: Leased/colo capex per IT MW - GB200 (and Hopper/B200/B300 stand-ins); IT only, rent in opex | B19: $M/MW | C19: — | D19: 30 | E19: — | F19: =D19 -> 30 | J19: Capacity | K19: Estimated | L19: gpu_mw_capex.xlsx (Capacity), medium confidence
A20: Leased/colo capex per IT MW - GB300 (Vineland, most leased builds) | B20: $M/MW | C20: — | D20: 41 | E20: — | F20: =D20 -> 41 | J20: Capacity | K20: Estimated | L20: gpu_mw_capex.xlsx (Capacity), medium confidence
A21: Leased/colo capex per IT MW - Vera Rubin (LOW-MEDIUM confidence) | B21: $M/MW | C21: 41 | D21: 41 | E21: 48.5 | F21: =CHOOSE(Scen,C21,D21,E21) -> 41 | J21: Capacity/Skeptic | K21: Estimated | L21: v0.7: base $41M flat to GB300 (SemiAnalysis TCO 1.51-1.56x/GPU-hr at 320 vs 491 GPUs/IT MW -> ~0.98-1.02x GB300 per MW; Capacity at Morgan Stanley rack cost: leased $42-48M); bull $41M; bear $48.5M (Skeptic $45-52M midpoint: 0.65x racks/MW x MS 1.68-1.95x rack cost). $32M = OUTER-BULL sensitivity only (soft: ~$6.0M rack ~1.2x GB300; networking $3.6M looks low vs GB300 $6.1M - Capacity reconciles Tuesday)
A22: v0.2 fix: GPU fleet MW-ratio only in forecast + capex follows DRIVER MW (1 = on) | B22: 0/1 | C22: — | D22: 1 | E22: — | F22: =D22 -> 1 | J22: Modeling | K22: Input | L22: Off = v0.1 behaviour (history fleet scaled by selected MW block; capex followed energized path only)
A23: Terminal basis: 2 = EXCLUDE BOTH Q4'30-onward spend for MW billing after Q4'30 and that MW (terminal = Q4'30 exit run-rate x 4) [default, conservative]; 1 = INCLUDE BOTH (memo only: run-rate scaled x(MW Q4'30 + MW billing Q1'31)/MW Q4'30, unsourced ~1.2x step-up); 0 = v0.1 (FY2030 x (1+TG), Q4'30 spend charged) | B23: 0/1/2 | C23: — | D23: 2 | E23: — | F23: =D23 -> 2 | J23: Modeling | K23: Input | L23: v0.2 decision (Oct 4): do not credit unbilled capacity on an unsourced step-up; 'include both' EV shown as memo row in Valuation
A24: Terminal value floor: max(Gordon/blend, run-off value of existing fleet with no reinvestment) (1 = on) | B24: 0/1 | C24: — | D24: 1 | E24: — | F24: =D24 -> 1 | J24: Modeling | K24: Input | L24: Operator would stop replacing GPUs at negative NPV; TV cannot be below run-off (>= 0)
A25: Owned-site O&M (facility staff, maintenance, insurance, property tax) | B25: $M/IT MW-yr | C25: — | D25: 0.75 | E25: — | F25: =D25 -> 0.75 | J25: Capacity | K25: Placeholder | L25: Leased sites carry this inside rent; owned sites had none in v0.1. Placeholder pending Capacity
A26: H2'26 repricing: Q2 list avg (H100 $2.95->$3.85 Jun-26), legacy reserved book renews +30% at 50%/12 months, new GPUs at current list (1 = on) | B26: 0/1 | C26: — | D26: 1 | E26: — | F26: =D26 -> 1 | J26: GPU Market | K26: Input | L26: Off = v0.1 (Q2 at Jun list; reserved = lagged list)
A27: Reserved renewal repricing vs expiring contract | B27: % | C27: — | D27: 0.3 | E27: — | F27: =D27 -> 0.3 | J27: Filings | K27: Reported | L27: Q2'26 letter: >30% repricing on renewals
A28: H100 on-demand list - Q2'26 average | B28: $/GPU-hr | C28: — | D28: =(2*2.95+3.85)/3 -> 3.25 | E28: — | F28: =D28 -> 3.25 | J28: GPU Market | K28: Derived | L28: Archived nebius.com/prices: $2.95 Apr-May -> $3.85 from Jun 2026 (Reported pages); Q2 avg derived
A29: Team June run-rate per MW - low | B29: $M/MW-yr | C29: — | D29: 13.3 | E29: — | F29: =D29 -> 13.3 | J29: Modeling | K29: Estimated | L29: June list + renewals signed by 6/30
A30: Team June run-rate per MW - high | B30: $M/MW-yr | C30: — | D30: 13.5 | E30: — | F30: =D30 -> 13.5 | J30: Modeling | K30: Estimated
A31: Team estimate: unexplained ARR residual - low | B31: $M | C31: — | D31: 650 | E31: — | F31: =D31 -> 650 | J31: Modeling | K31: Estimated | L31: ~45-50 MW
A32: Team estimate: unexplained ARR residual - high | B32: $M | C32: — | D32: 700 | E32: — | F32: =D32 -> 700 | J32: Modeling | K32: Estimated
A33: Consensus FY28 adj. EBITDA margin (13.98 / 23.0) | B33: % | C33: — | D33: =13.98/23 -> 0.60782609 | E33: — | F33: =D33 -> 0.60782609 | J33: Skeptic | K33: Estimated | L33: 01_priced_in.xlsx
A34: Peer adj. EBITDA margin reference (CoreWeave ~62%) | B34: % | C34: — | D34: 0.62 | E34: — | F34: =D34 -> 0.62 | J34: GPU Market | K34: Placeholder | L34: pending GPU Market comps
A35: Cap Microsoft GPU consumption at Vineland energized IT MW (Capacity) (1 = on) | B35: 0/1 | C35: — | D35: 1 | E35: — | F35: =D35 -> 1 | J35: Modeling | K35: Input | L35: Fix for Q2'26 utilization: MSFT delivered-tranche MW (53 MW) exceeded Vineland energized (39 MW / 19,157 GPUs)
A36: GPU end-of-life replacement capex in forecast (1 = on) | B36: 0/1 | C36: — | D36: 1 | E36: — | F36: =D36 -> 1 | J36: Modeling | K36: Input | L36: Cohort reaching GPU life is replaced at original cost (fleet persists in Capacity file)
A37: History MW basis: 1 = Capacity named-site (173 MW Q2'26) [default]; 2 = company-implied (~190 MW, ~$12M rev/installed MW) applied to history AND forward path (+uplift); 3 = MISMATCH test: history at 190, forward on 173 path | B37: # | C37: — | D37: 1 | E37: — | F37: =D37 -> 1 | J37: Capacity/Skeptic | K37: Input | L37: Revenue/MW in history and the forward MW path must use the same basis (2); 3 only quantifies Skeptic's ~11% claim
A38: Company-implied installed MW at Q2'26 (Q2 letter ~$12M revenue per installed MW) | B38: MW | C38: — | D38: 190 | E38: — | F38: =D38 -> 190 | J38: Filings | K38: Derived | L38: ~$2.3B annualized / ~$12M per MW
A39: AIB CLT1 colocation rent (12-yr), per IT MW-yr | B39: $M/IT MW-yr | C39: — | D39: 2.2 | E39: — | F39: =D39 -> 2.2 | J39: Capacity | K39: Estimated | L39: CLT1-sourced ~$2.2M per MW-yr (Capacity); applied via differential vs generic leased rent (RentMW x PUE)
A40: Nebius prepayment to AIB to fund CLT1 build (outflow Q4'26-Q2'27, equal thirds) | B40: $M | C40: — | D40: 0 | E40: — | F40: =D40 -> 0 | J40: Filings | K40: Placeholder | L40: Amount undisclosed (AIB 8-K Sep 30 2026); sensitivity $250M / $500M; liquidity only
A41: Inferize acquisition cash outflow Q4'26 (1 = on) | B41: 0/1 | C41: — | D41: 0 | E41: — | F41: =D41 -> 0 | J41: Filings | K41: Placeholder | L41: 6-K Oct 1 2026: terms undisclosed; PRESS-REPORTED $100-150M (unconfirmed)
A42: Inferize purchase price (press-reported, unconfirmed) | B42: $M | C42: — | D42: 130 | E42: — | F42: =D42 -> 130 | J42: Filings | K42: Placeholder | L42: Press $100-150M; liquidity only
A43: Q3'26 starts from June exit run-rate: AI cloud revenue >= reported ARR / 4 before new MW (overlay held flat in $) | B43: 0/1 | C43: — | D43: 0 | E43: — | F43: =D43 -> 0 | J43: Filings | K43: Input | L43: Filings: ARR = June recognized AI cloud revenue x 12 (no signed-not-billing). Overlay not tied to MW; power/rent not added (EBITDA margin on overlay = 1 - other COR - PD - SG&A %)
A44: March 2026 AI cloud revenue (monthly) | B44: $M/mo | C44: — | D44: 162 | E44: — | F44: =D44 -> 162 | J44: Filings | K44: Estimated | L44: ~$160M (Filings); June $250M = $3.0B / 12
A45: Sensitivity: cap adj. EBITDA margin at MarginPeer from PeerMarginYr (cost overlay) | B45: 0/1 | C45: — | D45: 0 | E45: — | F45: =D45 -> 0 | J45: GPU Market | K45: Input
A46: First year of peer-margin cap | B46: yr | C46: — | D46: 2028 | E46: — | F46: =D46 -> 2028 | J46: Modeling | K46: Input
A47: Vineland shutdown scenario (Capacity vineland_shutdown.xlsx): 0 off; 1 no shutdown; 2 partial 50% 2m; 3 partial minor-source 2m; 4 full 1m; 5 full 2m; 6 full 3m; 7 probability-weighted | B47: # | C47: — | D47: 0 | E47: — | F47: =D47 -> 0 | J47: Capacity | K47: Estimated | L47: Outage from Nov 7 2026 (NJDEP order Sep 22 + 45 days); ~102.5 MW IT genset-fed; scenarios & weights = Capacity judgment. SLA credits not disclosed (note only); genset power saving not credited
A48: Microsoft revenue per IT MW-yr for outage loss | B48: $M/IT MW-yr | C48: — | D48: 14.5 | E48: — | F48: =D48 -> 14.5 | J48: Capacity | K48: Derived | L48: $17.4B TCV / 5 yrs / 240 MW IT; probability-weighted Q4'26 loss ~$67-68M
A49: Bloom slips 2 quarters: Vineland T5-T9 (2027) billing and Bloom go-live +2 qtrs (1 = on) | B49: 0/1 | C49: — | D49: 0 | E49: — | F49: =D49 -> 0 | J49: Capacity | K49: Input
A50: New-deal pricing for 2027+ new non-contract MW: multi-year $/IT MW-yr tranche + short-term tranche (1 = on) | B50: 0/1 | C50: — | D50: 1 | E50: — | F50: =D50 -> 1 | J50: Filings | K50: Input | L50: Q2'26 letter: new deals >$20M/MW, landmark $20-25M ACV/MW (basis likely IT, medium-low); <=6-month deals $40-50M/MW (one signed). Legacy (Q4'26) non-contract fleet stays on GPU-hour pricing
A51: First quarter of new-deal pricing | B51: idx | C51: — | D51: 13 | E51: — | F51: =D51 -> 13 | J51: Filings | K51: Input | L51: Q1'27
A52: NEW-DEAL GB300 $/GPU-hr (multi-year, IT reading) - the ONE linked new-deal price input | B52: $/GPU-hr | C52: 5.8123855 | D52: 5.1148992 | E52: 4.6499084 | F52: =CHOOSE(Scen,C52,D52,E52) -> 5.1148992 | J52: Filings | K52: Derived | L52: Calibrated: $22M/IT MW = $5.12/GPU-hr x 491 GPUs/IT MW x 8,760 h x 100% (take-or-pay); IREN new 3-yr GB300 ~$4.65 (= bear $20M); bull $25M = $5.81
A53: GB300 NVL72 GPUs per IT MW (new-deal calibration) | B53: GPU/MW | C53: — | D53: 491 | E53: — | F53: =D53 -> 491 | J53: Capacity | K53: Estimated | L53: gpu_mw_capex.xlsx base; 409 per gross MW
A54: New-deal occupancy (multi-year take-or-pay) | B54: % | C54: — | D54: 1 | E54: — | F54: =D54 -> 1 | J54: Filings | K54: Estimated | L54: Take-or-pay = 100%
A55: Multi-year GB300 ACV per IT MW-yr = ND_Px x ND_GPUMW_GB x 8,760 x ND_Occ (derived; do not overwrite - change ND_Px) | B55: $M/IT MW-yr | C55: — | D55: =ND_Px*ND_GPUMW_GB*8760*ND_Occ/1000000 -> 22 | E55: — | F55: =D55 -> 22 | J55: Filings | K55: Derived | L55: IT reading $22M <-> $5.12/GPU-hr; gross reading (NDBasis 2) x 491/409 = $26.4M <-> $6.14
A56: Multi-year $/MW path: 1 = v0.6 flat nominal within generation, then MYDecl/yr from MYDeclIdx (no per-chip ageing stacked); 0 = v0.5 Blackwell per-chip list path (double count) | B56: 0/1 | C56: — | D56: 1 | E56: — | F56: =D56 -> 1 | J56: Modeling | K56: Estimated | L56: Team consensus v0.6: -6%/yr was per-chip on-demand ageing; Rubin switch handled by Rubin_Prem x GPUs/MW only
A57: Multi-year new-deal $/MW change per yr (within generation) | B57: %/yr | C57: -0.0125 | D57: -0.03 | E57: -0.06 | F57: =CHOOSE(Scen,C57,D57,E57) -> -0.03 | J57: Modeling | K57: Estimated | L57: Base flat through 2028 then -3%/yr; bear -6%/yr from 2027; bull -1.25%/yr from 2029 (base ratio -3/-6 applied to bull's -2.5% chip ageing)
A58: First quarter of multi-year $/MW decline | B58: idx | C58: 21 | D58: 21 | E58: 13 | F58: =CHOOSE(Scen,C58,D58,E58) -> 21 | J58: Modeling | K58: Estimated | L58: Base/bull Q1'29; bear Q1'27
A59: STRESS: one-off 31% cut to new-deal $/MW once Rubin ships (never stacked with -6%/yr; sensitivity only) | B59: 0/1 | C59: — | D59: 0 | E59: — | F59: =D59 -> 0 | J59: Skeptic | K59: Estimated
A60: Stress cut | B60: % | C60: — | D60: 0.31 | E60: — | F60: =D60 -> 0.31 | J60: Skeptic | K60: Estimated
A61: Rubin new-deal $/MW = GB300 $/MW x Rubin_Prem x GPUMW_N / ND_GPUMW_GB (1 = v0.6; 0 = v0.5 single $/MW for all generations) | B61: 0/1 | C61: — | D61: 1 | E61: — | F61: =D61 -> 1 | J61: Modeling | K61: Input | L61: Rubin at 1.2x and 320 GPUs/IT MW: $17.2M/IT MW (IT reading), -22% vs GB300
A62: Rubin new-deal revenue: 1 = direct $/IT MW-yr (RubinMW; v0.7, no IT/gross toggle); 0 = v0.6 GB300 x Rubin_Prem x 320/491 | B62: # | C62: — | D62: 1 | E62: — | F62: =D62 -> 1 | J62: Modeling | K62: Input | L62: IT/gross toggle applies to GB300-era deals only (avoids Filings-flagged double count)
A63: Rubin multi-year ACV per IT MW-yr (new deals, signing at Rubin availability; then MYDecl path within generation) | B63: $M/IT MW-yr | C63: 20 | D63: 18 | E63: 16 | F63: =CHOOSE(Scen,C63,D63,E63) -> 18 | J63: GPU Market | K63: Estimated | L63: Two contracts: Anthropic-Nscale ~$16.2M/MW (6-yr, MW basis unknown); WhiteFiber-Prime Intellect 576 VR200 ~$108.2M/3 yrs = ~$7.15/GPU-hr ~ $20M/IT MW if packages counted (medium). Base 18 / bull 20 / bear 16. Implied $/GPU-hr at 320 packages/IT MW: 6.42 / 7.13 / 5.71
A64: Rubin density for $/GPU-hr reference only (sensitivity; not used in revenue) | B64: GPU/MW | C64: — | D64: 400 | E64: — | F64: =D64 -> 400 | J64: Capacity | K64: Estimated | L64: 320 vs 400 packages/IT MW: reference only
A65: Short-term (<=6-month) tranche share of TOTAL average active IT MW (from Q1'27) | B65: % | C65: — | D65: 0.05 | E65: — | F65: =D65 -> 0.05 | J65: GPU Market | K65: Estimated | L65: v0.5: 5% of total capacity (on-demand/self-serve ~4% of Q2'26 revenue; one short-term deal signed); tests 2% / 10%; 0% floor row
A66: Short-term tranche mode: 1 = v0.5 share of TOTAL active MW x STOcc; 0 = v0.4 share of new 2027+ MW, no occupancy haircut | B66: 0/1 | C66: — | D66: 1 | E66: — | F66: =D66 -> 1 | J66: Modeling | K66: Input
A67: Deferred revenue release: 1 = v0.5 (6/30 balance on Reported split; new prepayments straight-line over DR_AmortQ); 0 = v0.4 (balance / DR_AmortQ geometric) | B67: 0/1 | C67: — | D67: 1 | E67: — | F67: =D67 -> 1 | J67: Modeling | K67: Input
A68: Short-term tranche occupancy between deals | B68: % | C68: — | D68: 0.85 | E68: — | F68: =D68 -> 0.85 | J68: GPU Market | K68: Estimated | L68: $45M x 85% ~ $38M per IT MW-yr effective yield
A69: Multi-year GB300-equivalent ACV for UNSOLD new MW ($M/IT MW-yr; contracted backlog stays at MYRate; Rubin scales by the same ratio) | B69: $M/IT MW-yr | C69: — | D69: =MYRate -> 22 | E69: — | F69: =D69 -> 22 | J69: Skeptic | K69: Estimated | L69: Headline sens $18 / $22 / $25 (Skeptic); default = MYRate; contracted vs unsold from RPO until Capacity site tags (Tuesday)
A70: Remaining performance obligations at 6/30/26 | B70: $M | C70: — | D70: 37490 | E70: — | F70: =D70 -> 37490 | J70: Filings | K70: Reported | L70: Q2'26 6-K Note 2
A71: Share of RPO recognised Jul'26-Jun'28 | B71: % | C71: — | D71: 0.36 | E71: — | F71: =D71 -> 0.36 | J71: Filings | K71: Reported | L71: Q2'26 Note 2 (~$13.5B)
A72: 6/30/26 deferred revenue - current (recognised within 12 months) | B72: $M | C72: — | D72: 979.4 | E72: — | F72: =D72 -> 979.4 | J72: Filings | K72: Reported | L72: Q2'26 6-K balance sheet; non-current $4,995.8M; total $5,975.2M; YE25 $1,577.5M (only $154.3M recognised in H1'26)
A73: 6/30/26 deferred revenue recognised within 24 months | B73: $M | C73: — | D73: 2250 | E73: — | F73: =D73 -> 2250 | J73: Filings | K73: Estimated | L73: $2.0-2.5B: months 13-24 at 1.0-1.5x the $979.4M current portion
A74: Quarters to release the remainder of the 6/30 balance after month 24 | B74: qtrs | C74: — | D74: 12 | E74: — | F74: =D74 -> 12 | J74: Filings | K74: Estimated | L74: Strategic contracts recognised over 1-5 yrs; tail Q3'28-Q2'31 (2 qtrs after horizon fall into the DR run-off deduction)
A75: New-deal $/MW basis: 1 = per IT MW [base; Filings: same axis as 2026 base $12M/MW ~ 250 MW active path, medium]; 2 = slide is per GROSS MW -> MYRate x ND_GrossX per IT MW | B75: # | C75: — | D75: 1 | E75: — | F75: =D75 -> 1 | J75: Filings | K75: Estimated
A76: Gross-to-IT conversion for new-deal $/MW (GPUs per IT MW / GPUs per gross MW = 491/409) | B76: x | C76: — | D76: 1.200489 | E76: — | F76: =D76 -> 1.200489 | J76: Capacity | K76: Estimated | L76: Capacity: 409 GPUs/gross MW vs 491/IT MW -> $22M per gross MW ~ $26.4M per IT MW
A77: Short-term tranche $/IT MW-yr (near on-demand) | B77: $M/IT MW-yr | C77: 50 | D77: 45 | E77: 40 | F77: =CHOOSE(Scen,C77,D77,E77) -> 45 | J77: Filings | K77: Reported | L77: Q2'26 letter: Q3 short-term deals >$40M; $40-50M range
A78: Short-term tranche ($40-50M) on GB300-era capacity only (1 = v0.7; 0 = v0.6 any generation) | B78: 0/1 | C78: — | D78: 1 | E78: — | F78: =D78 -> 1 | J78: Filings | K78: Input | L78: $40-50M is a GB300 rate, not a Rubin rate
A79: Short-term tranche recovers to list after post-Rubin cut (cut PxCyc for 3 qtrs after Rubin ships, then linear recovery over 2 qtrs) | B79: 0/1 | C79: 1 | D79: 1 | E79: 0 | F79: =CHOOSE(Scen,C79,D79,E79) -> 1 | J79: GPU Market | K79: Estimated | L79: Bull 6.25% with recovery; base 22% with recovery; bear 31% no recovery. Reprices every 6 months
A80: New-deal customer prepayments in liquidity (1 = on) | B80: 0/1 | C80: — | D80: 1 | E80: — | F80: =D80 -> 1 | J80: Filings | K80: Reported | L80: 70% of deals x 55% of capex = 38.5% of new-build capex, received at capex time, released to revenue over DR_AmortQ
A81: Prepayment decay by signing period (1 = on; 0 = flat PrepayPct for all new non-hyperscaler deals) | B81: 0/1 | C81: — | D81: 1 | E81: — | F81: =D81 -> 1 | J81: Skeptic | K81: Estimated | L81: v0.5: Neolab/other new deals 38.5% before Rubin ships, 22.5% for 2028+ signings; bull keeps 38.5%; bear 0% beyond already signed
A82: Prepayment % of new-build capex - other new deals, capex in 2027 (Rubin ships Q1'27) | B82: % | C82: 0.385 | D82: 0.385 | E82: 0 | F82: =CHOOSE(Scen,C82,D82,E82) -> 0.385 | J82: Skeptic | K82: Estimated | L82: Capex leads signing by ~2-4 qtrs, so 2027 capex treated as pre-Rubin signings (input); bear 0% beyond already-signed
A83: Prepayment % of new-build capex - other new deals, 2028+ signings (capex from PrepayIdx28) | B83: % | C83: 0.385 | D83: 0.225 | E83: 0 | F83: =CHOOSE(Scen,C83,D83,E83) -> 0.225 | J83: Skeptic | K83: Estimated | L83: Bull keeps 38.5%; bear 0%
A84: First capex quarter at the 2028+ prepayment rate | B84: idx | C84: — | D84: 17 | E84: — | F84: =D84 -> 17 | J84: Skeptic | K84: Estimated | L84: Q1'28
A85: Prepayment % of related capex - NEW hyperscaler capacity (future IG / hyperscaler tranches) | B85: % | C85: 0.4 | D85: 0.3 | E85: 0 | F85: =CHOOSE(Scen,C85,D85,E85) -> 0.3 | J85: GPU Market | K85: Estimated | L85: Range 20-40%: Microsoft-Nebius ~40% (~$7.0B of $17.39B), Microsoft-IREN ~20% (GPU Market, medium); bull 40%, bear 0%. Existing signed Microsoft/Meta tranches: 0% new prepayment (advances already in 6/30 DR $5,975M)
A86: Closing deferred revenue at Q4'30 runs off as non-cash revenue after the horizon: deduct PV from EV (1 = on) | B86: 0/1 | C86: — | D86: 1 | E86: — | F86: =D86 -> 1 | J86: Modeling | K86: Input | L86: v0.5 cash double-count fix: terminal UFCF is EBITDA-based, so the unreleased prepaid balance would otherwise be counted as cash twice
A87: Prepayment by customer type (1 = v0.5: signed Microsoft/Meta 0%, new hyperscaler HSPre, other deals at rate path; 0 = v0.4 flat PrepayPct on all new-build capex) | B87: 0/1 | C87: — | D87: 1 | E87: — | F87: =D87 -> 1 | J87: Modeling | K87: Input
A88: Prepayment base: 1 = new-build capex (GPU + shell + power) [v0.4]; 0 = total capex (v0.3) | B88: 0/1 | C88: — | D88: 1 | E88: — | F88: =D88 -> 1 | J88: Filings | K88: Input
A89: GPU history anchor: ~30,000 GPUs at 3/31/2025 (single quarter-end actual) - add gap vs Capacity file to fleet from Q1'25 (1 = on) | B89: 0/1 | C89: — | D89: 1 | E89: — | F89: =D89 -> 1 | J89: Filings | K89: Reported | L89: FY24 20-F: ~30,000 GPUs at 3/31/2025 (the ~38k was a target). Kansas City likely live Q1'25 at 5-15 MW (Capacity, Estimated) - gap carried as Hopper-era fleet
A90: GPUs at 3/31/2025 (actual) | B90: GPUs | C90: — | D90: 30000 | E90: — | F90: =D90 -> 30000 | J90: Filings | K90: Reported | L90: FY24 20-F
A91: Replacement capex at scenario GPU price path: cohort cost x (1 + annual list-price change of its gen)^(life yrs) (1 = on) | B91: 0/1 | C91: 0 | D91: 0 | E91: 1 | F91: =CHOOSE(Scen,C91,D91,E91) -> 0 | J91: Modeling | K91: Input | L91: Bear on for internal consistency (bear rental prices fall 20-30%/yr; constant-$ replacement overstated capex vs revenue). Base/bull off (constant $, conservative); see Sensitivity
A92: Hold product development + SG&A at FY28 % of revenue for FY29-30 (1 = on; sensitivity) | B92: 0/1 | C92: — | D92: 0 | E92: — | F92: =D92 -> 0 | J92: Modeling | K92: Input | L92: Default 0 = placeholder step-down (PD 8%->6%, SG&A 10%->7%)
A93: Terminal capex: 1 = max(D&A, GPU replacement + non-GPU + growth reinvestment); 0 = D&A x MaintRatio (old) | B93: 0/1 | C93: — | D93: 1 | E93: — | F93: =D93 -> 1 | J93: Modeling | K93: Input
A94: Reserved book renewal pace (share of book repricing to current list per quarter from RenewIdx) | B94: %/qtr | C94: — | D94: 0.125 | E94: — | F94: =D94 -> 0.125 | J94: GPU Market | K94: Estimated | L94: Nebius reserved terms max 24 months (3/6/12 mo 2024; 6/12/24 on H200); Q2 letter >30% repricing on renewals. 50% of the reserved book renews within FY27 in ALL scenarios (12.5%/qtr from Q1'27, 100% by Q4'28). GPU Market archived pricing pages, Estimated
A95: Renewal schedule start quarter (first quarter after 6/30) | B95: idx | C95: — | D95: 11 | E95: — | F95: =D95 -> 11 | J95: GPU Market | K95: Estimated | L95: Q1'27
A96: Skeptic v3.2 path-tied capex base: first quarter liquidity < 0 | B96: qtr | C96: — | D96: Q4'27 | E96: — | F96: =D96 -> Q4'27 | J96: Skeptic | K96: Estimated | L96: /workspace/nebius/skeptic/skeptic_03_depreciation.xlsx; Skeptic path run uses CONSENSUS EBITDA
A97: Skeptic v3.2 base YE27 liquidity | B97: $B | C97: — | D97: -0.15 | E97: — | F97: =D97 -> -0.15 | J97: Skeptic | K97: Estimated
A98: Skeptic v3.2 base YE28 liquidity | B98: $B | C98: — | D98: -6.8 | E98: — | F98: =D98 -> -6.8 | J98: Skeptic | K98: Estimated
A99: Skeptic v3.2 low: first quarter < 0 | B99: qtr | C99: — | D99: never thru 2030 | E99: — | F99: =D99 -> never thru 2030 | J99: Skeptic | K99: Estimated
A100: Skeptic v3.2 low YE27 liquidity | B100: $B | C100: — | D100: 7.1 | E100: — | F100: =D100 -> 7.1 | J100: Skeptic | K100: Estimated
A101: Skeptic v3.2 low YE28 liquidity | B101: $B | C101: — | D101: 1.5 | E101: — | F101: =D101 -> 1.5 | J101: Skeptic | K101: Estimated
A102: Skeptic v3.2 high: first quarter < 0 | B102: qtr | C102: — | D102: Q3'27 | E102: — | F102: =D102 -> Q3'27 | J102: Skeptic | K102: Estimated
...

Sheet Timeline
A1: Timeline (one column per quarter, Q1'24-Q4'30)
A3: Quarter | F3: Q1'24 | G3: Q2'24 | H3: Q3'24 | I3: Q4'24 | J3: Q1'25 | K3: Q2'25 | L3: Q3'25 | M3: Q4'25 | N3: Q1'26 | O3: Q2'26 | P3: Q3'26 | Q3: Q4'26 | R3: Q1'27 | S3: Q2'27 | T3: Q3'27 | U3: Q4'27 | V3: Q1'28 | W3: Q2'28 | X3: Q3'28 | Y3: Q4'28 | Z3: Q1'29 | AA3: Q2'29 | AB3: Q3'29 | AC3: Q4'29 | AD3: Q1'30 | AE3: Q2'30 | AF3: Q3'30 | AG3: Q4'30
A4: Period end | E4: 45291 | F4: 45382 | G4: 45473 | H4: 45565 | I4: 45657 | J4: 45747 | K4: 45838 | L4: 45930 | M4: 46022 | N4: 46112 | O4: 46203 | P4: 46295 | Q4: 46387 | R4: 46477 | S4: 46568 | T4: 46660 | U4: 46752 | V4: 46843 | W4: 46934 | X4: 47026 | Y4: 47118 | Z4: 47208 | AA4: 47299 | AB4: 47391 | AC4: 47483 | AD4: 47573 | AE4: 47664 | AF4: 47756 | AG4: 47848
A5: Index | E5: 0 | F5: 1 | G5: 2 | H5: 3 | I5: 4 | J5: 5 | K5: 6 | L5: 7 | M5: 8 | N5: 9 | O5: 10 | P5: 11 | Q5: 12 | R5: 13 | S5: 14 | T5: 15 | U5: 16 | V5: 17 | W5: 18 | X5: 19 | Y5: 20 | Z5: 21 | AA5: 22 | AB5: 23 | AC5: 24 | AD5: 25 | AE5: 26 | AF5: 27 | AG5: 28
A6: A/F | F6: =IF(F5<=LastHist,"A","F") -> A | G6: =IF(G5<=LastHist,"A","F") -> A | H6: =IF(H5<=LastHist,"A","F") -> A | I6: =IF(I5<=LastHist,"A","F") -> A | J6: =IF(J5<=LastHist,"A","F") -> A | K6: =IF(K5<=LastHist,"A","F") -> A | L6: =IF(L5<=LastHist,"A","F") -> A | M6: =IF(M5<=LastHist,"A","F") -> A | ... AG6: =IF(AG5<=LastHist,"A","F") -> F
A7: Fiscal year | F7: =YEAR(F4) -> 2024 | G7: =YEAR(G4) -> 2024 | H7: =YEAR(H4) -> 2024 | I7: =YEAR(I4) -> 2024 | J7: =YEAR(J4) -> 2025 | K7: =YEAR(K4) -> 2025 | L7: =YEAR(L4) -> 2025 | M7: =YEAR(M4) -> 2025 | ... AG7: =YEAR(AG4) -> 2030
A8: Days | F8: =F4-E4 -> 91 | G8: =G4-F4 -> 91 | H8: =H4-G4 -> 92 | I8: =I4-H4 -> 92 | J8: =J4-I4 -> 90 | K8: =K4-J4 -> 91 | L8: =L4-K4 -> 92 | M8: =M4-L4 -> 92 | ... AG8: =AG4-AF4 -> 92
A9: Hours | F9: =F8*24 -> 2184 | G9: =G8*24 -> 2184 | H9: =H8*24 -> 2208 | I9: =I8*24 -> 2208 | J9: =J8*24 -> 2160 | K9: =K8*24 -> 2184 | L9: =L8*24 -> 2208 | M9: =M8*24 -> 2208 | ... AG9: =AG8*24 -> 2208

Sheet Hist
A1: Historical inputs Q1'24-Q2'26 with Reported / Derived / Estimated / Not disclosed tags
A2: Each metric = 5 rows: value as disclosed | tag | best estimate (numeric) | method/source | VALUE USED (= value if disclosed, else best estimate). No silent gaps: every quarter carries a tag. Other tabs link to the VALUE USED row only.
A3: Metric | B3: Unit | C3: Owner | D3: Notes | F3: Q1'24 | G3: Q2'24 | H3: Q3'24 | I3: Q4'24 | J3: Q1'25 | K3: Q2'25 | L3: Q3'25 | M3: Q4'25 | N3: Q1'26 | O3: Q2'26
F4: 45382 | G4: 45473 | H4: 45565 | I4: 45657 | J4: 45747 | K4: 45838 | L4: 45930 | M4: 46022 | N4: 46112 | O4: 46203
A6: Group revenue | B6: $M | C6: Filings | D6: Continuing ops. Q1'24 figure is on the pre-restatement basis (Q1'25 PR) - flag. | F6: 11.4 | G6: 14.5 | H6: 32.1 | I6: 35.2 | J6: 50.9 | K6: 105.1 | L6: 146.1 | M6: 227.7 | N6: 399 | O6: 582.3
A7: tag | F7: Reported | G7: Reported | H7: Reported | I7: Reported | J7: Reported | K7: Reported | L7: Reported | M7: Reported | N7: Reported | O7: Reported
A8: best estimate
A9: method / source | F9: Q1'25 6-K PR comparatives (pre-Toloka-deconsolidation basis) | G9: Q2'25 6-K PR comparative | H9: Q3'25 6-K PR comparative (restated) | I9: Q4'25 6-K PR comparative | J9: Q1'26 6-K PR comparative (restated) | K9: Q2'26 6-K PR comparative | L9: Q3'25 6-K PR | M9: Q4'25 6-K PR | N9: Q1'26 6-K PR | O9: Q2'26 6-K PR (acc. 0001104659-26-094568)
A10: VALUE USED | F10: =IF(F7="Not disclosed",F8,F6) -> 11.4 | G10: =IF(G7="Not disclosed",G8,G6) -> 14.5 | H10: =IF(H7="Not disclosed",H8,H6) -> 32.1 | I10: =IF(I7="Not disclosed",I8,I6) -> 35.2 | J10: =IF(J7="Not disclosed",J8,J6) -> 50.9 | K10: =IF(K7="Not disclosed",K8,K6) -> 105.1 | L10: =IF(L7="Not disclosed",L8,L6) -> 146.1 | M10: =IF(M7="Not disclosed",M8,M6) -> 227.7 | ... O10: =IF(O7="Not disclosed",O8,O6) -> 582.3
A12: Nebius AI cloud revenue | B12: $M | C12: Filings | D12: Segment disclosure; earlier quarters derived from YoY growth or estimated as % of group | F12: n.d. | G12: n.d. | H12: n.d. | I12: n.d. | J12: 41.4 | K12: 93.6 | L12: n.d. | M12: 214.2 | N12: 389.7 | O12: 574.9
A13: tag | F13: Not disclosed | G13: Not disclosed | H13: Not disclosed | I13: Not disclosed | J13: Derived | K13: Derived | L13: Not disclosed | M13: Reported | N13: Reported | O13: Reported
A14: best estimate | F14: 10.3 | G14: 13.1 | H14: 28.9 | I14: 31.7 | L14: 138.8
A15: method / source | F15: Est = 90% of group revenue (pre-2025 mix; Avride/TripleTen remainder) | G15: Est = 90% of group revenue (pre-2025 mix; Avride/TripleTen remainder) | H15: Est = 90% of group revenue (pre-2025 mix; Avride/TripleTen remainder) | I15: Est = 90% of group revenue (pre-2025 mix; Avride/TripleTen remainder) | J15: Derived: Q1'26 $389.7M / (1+841%) | K15: Derived: Q2'26 $574.9M / (1+514%) | L15: Est = 95% of group revenue | M15: Q4'25 letter | N15: Q1'26 letter | O15: Q2'26 letter
A16: VALUE USED | F16: =IF(F13="Not disclosed",F14,F12) -> 10.3 | G16: =IF(G13="Not disclosed",G14,G12) -> 13.1 | H16: =IF(H13="Not disclosed",H14,H12) -> 28.9 | I16: =IF(I13="Not disclosed",I14,I12) -> 31.7 | J16: =IF(J13="Not disclosed",J14,J12) -> 41.4 | K16: =IF(K13="Not disclosed",K14,K12) -> 93.6 | L16: =IF(L13="Not disclosed",L14,L12) -> 138.8 | M16: =IF(M13="Not disclosed",M14,M12) -> 214.2 | ... O16: =IF(O13="Not disclosed",O14,O12) -> 574.9
A18: ARR (last-month AI cloud revenue x 12) | B18: $M | C18: Filings | D18: Mgmt definition; Q2'25/Q1'25 derived from stated YoY growth | F18: n.d. | G18: n.d. | H18: n.d. | I18: 90 | J18: 248 | K18: 430 | L18: 551 | M18: 1250 | N18: 1920 | O18: 3000
A19: tag | F19: Not disclosed | G19: Not disclosed | H19: Not disclosed | I19: Reported | J19: Derived | K19: Derived | L19: Reported | M19: Reported | N19: Reported | O19: Reported
A20: best estimate | F20: 41.04 | G20: 52.2 | H20: 115.56
A21: method / source | F21: Est = AI cloud revenue est x 4 (run-rate proxy) | G21: Est = AI cloud revenue est x 4 (run-rate proxy) | H21: Est = AI cloud revenue est x 4 (run-rate proxy) | I21: Q4'25 letter ARR chart (Dec-24 $90M) | J21: Derived: $1.92B / (1+674%) | K21: Derived: $3.0B / (1+598%) | L21: Q4'25 letter: 'more than doubled from $551M' | M21: Q4'25 letter | N21: Q1'26 letter ($1.92B) | O21: Q2'26 letter
A22: VALUE USED | F22: =IF(F19="Not disclosed",F20,F18) -> 41.04 | G22: =IF(G19="Not disclosed",G20,G18) -> 52.2 | H22: =IF(H19="Not disclosed",H20,H18) -> 115.56 | I22: =IF(I19="Not disclosed",I20,I18) -> 90 | J22: =IF(J19="Not disclosed",J20,J18) -> 248 | K22: =IF(K19="Not disclosed",K20,K18) -> 430 | L22: =IF(L19="Not disclosed",L20,L18) -> 551 | M22: =IF(M19="Not disclosed",M20,M18) -> 1250 | ... O22: =IF(O19="Not disclosed",O20,O18) -> 3000
A24: Cost of revenues | B24: $M | C24: Filings | D24: GAAP incl. SBC. Q1'24/Q2'24 estimated by splitting (revenue - adj. EBITDA) on Q3'24 mix | F24: n.d. | G24: n.d. | H24: 9.9 | I24: 21.1 | J24: 24.7 | K24: 30.1 | L24: 42.9 | M24: 68.5 | N24: 103.8 | O24: 133.6
A25: tag | F25: Not disclosed | G25: Not disclosed | H25: Reported | I25: Reported | J25: Reported | K25: Reported | L25: Reported | M25: Reported | N25: Reported | O25: Reported
A26: best estimate | F26: 9.1 | G26: 8.1
A27: method / source | F27: Est: (rev - adj EBITDA) x Q3'24 COR share | G27: Est: (rev - adj EBITDA) x Q3'24 COR share | H27: Q3'25 6-K PR comparative (restated) | I27: Q4'25 6-K PR comparative | J27: Q1'26 6-K PR comparative (restated) | K27: Q2'26 6-K PR comparative | L27: Q3'25 6-K PR | M27: Q4'25 6-K PR | N27: Q1'26 6-K PR | O27: Q2'26 6-K PR (acc. 0001104659-26-094568)
A28: VALUE USED | F28: =IF(F25="Not disclosed",F26,F24) -> 9.1 | G28: =IF(G25="Not disclosed",G26,G24) -> 8.1 | H28: =IF(H25="Not disclosed",H26,H24) -> 9.9 | I28: =IF(I25="Not disclosed",I26,I24) -> 21.1 | J28: =IF(J25="Not disclosed",J26,J24) -> 24.7 | K28: =IF(K25="Not disclosed",K26,K24) -> 30.1 | L28: =IF(L25="Not disclosed",L26,L24) -> 42.9 | M28: =IF(M25="Not disclosed",M26,M24) -> 68.5 | ... O28: =IF(O25="Not disclosed",O26,O24) -> 133.6
A30: Product development | B30: $M | C30: Filings | D30: GAAP incl. SBC. Q1'24/Q2'24 estimated by splitting (revenue - adj. EBITDA) on Q3'24 mix; Q2'26 incl. $115.9M one-off Eigen AI | F30: n.d. | G30: n.d. | H30: 31.4 | I30: 31.9 | J30: 36.5 | K30: 42.8 | L30: 44.9 | M30: 53.1 | N30: 67.4 | O30: 191
A31: tag | F31: Not disclosed | G31: Not disclosed | H31: Reported | I31: Reported | J31: Reported | K31: Reported | L31: Reported | M31: Reported | N31: Reported | O31: Reported
A32: best estimate | F32: 29 | G32: 25.6
A33: method / source | F33: Est: (rev - adj EBITDA) x Q3'24 PD share | G33: Est: (rev - adj EBITDA) x Q3'24 PD share | H33: Q3'25 6-K PR comparative (restated) | I33: Q4'25 6-K PR comparative | J33: Q1'26 6-K PR comparative (restated) | K33: Q2'26 6-K PR comparative | L33: Q3'25 6-K PR | M33: Q4'25 6-K PR | N33: Q1'26 6-K PR | O33: Q2'26 6-K PR (acc. 0001104659-26-094568)
A34: VALUE USED | F34: =IF(F31="Not disclosed",F32,F30) -> 29 | G34: =IF(G31="Not disclosed",G32,G30) -> 25.6 | H34: =IF(H31="Not disclosed",H32,H30) -> 31.4 | I34: =IF(I31="Not disclosed",I32,I30) -> 31.9 | J34: =IF(J31="Not disclosed",J32,J30) -> 36.5 | K34: =IF(K31="Not disclosed",K32,K30) -> 42.8 | L34: =IF(L31="Not disclosed",L32,L30) -> 44.9 | M34: =IF(M31="Not disclosed",M32,M30) -> 53.1 | ... O34: =IF(O31="Not disclosed",O32,O30) -> 191
A36: Sales, general & administrative | B36: $M | C36: Filings | D36: GAAP incl. SBC. Q1'24/Q2'24 estimated by splitting (revenue - adj. EBITDA) on Q3'24 mix | F36: n.d. | G36: n.d. | H36: 47.9 | I36: 85.4 | J36: 60.9 | K36: 68.2 | L36: 89.5 | M36: 159.9 | N36: 143.8 | O36: 173.9
A37: tag | F37: Not disclosed | G37: Not disclosed | H37: Reported | I37: Reported | J37: Reported | K37: Reported | L37: Reported | M37: Reported | N37: Reported | O37: Reported
A38: best estimate | F38: 44.2 | G38: 39
A39: method / source | F39: Est: (rev - adj EBITDA) x Q3'24 SG&A share | G39: Est: (rev - adj EBITDA) x Q3'24 SG&A share | H39: Q3'25 6-K PR comparative (restated) | I39: Q4'25 6-K PR comparative | J39: Q1'26 6-K PR comparative (restated) | K39: Q2'26 6-K PR comparative | L39: Q3'25 6-K PR | M39: Q4'25 6-K PR | N39: Q1'26 6-K PR | O39: Q2'26 6-K PR (acc. 0001104659-26-094568)
A40: VALUE USED | F40: =IF(F37="Not disclosed",F38,F36) -> 44.2 | G40: =IF(G37="Not disclosed",G38,G36) -> 39 | H40: =IF(H37="Not disclosed",H38,H36) -> 47.9 | I40: =IF(I37="Not disclosed",I38,I36) -> 85.4 | J40: =IF(J37="Not disclosed",J38,J36) -> 60.9 | K40: =IF(K37="Not disclosed",K38,K36) -> 68.2 | L40: =IF(L37="Not disclosed",L38,L36) -> 89.5 | M40: =IF(M37="Not disclosed",M38,M36) -> 159.9 | ... O40: =IF(O37="Not disclosed",O38,O36) -> 173.9
A42: Depreciation & amortization | B42: $M | C42: Filings | F42: 8.9 | G42: 11.4 | H42: 23.5 | I42: 33.3 | J42: 49.1 | K42: 75.2 | L42: 99 | M42: 180.7 | N42: 212 | O42: 259.7
A43: tag | F43: Reported | G43: Reported | H43: Reported | I43: Reported | J43: Reported | K43: Reported | L43: Reported | M43: Reported | N43: Reported | O43: Reported
A44: best estimate
A45: method / source | F45: Q1'25 6-K PR comparatives (pre-Toloka-deconsolidation basis) | G45: Q2'25 6-K PR comparative | H45: Q3'25 6-K PR comparative (restated) | I45: Q4'25 6-K PR comparative | J45: Q1'26 6-K PR comparative (restated) | K45: Q2'26 6-K PR comparative | L45: Q3'25 6-K PR | M45: Q4'25 6-K PR | N45: Q1'26 6-K PR | O45: Q2'26 6-K PR (acc. 0001104659-26-094568)
A46: VALUE USED | F46: =IF(F43="Not disclosed",F44,F42) -> 8.9 | G46: =IF(G43="Not disclosed",G44,G42) -> 11.4 | H46: =IF(H43="Not disclosed",H44,H42) -> 23.5 | I46: =IF(I43="Not disclosed",I44,I42) -> 33.3 | J46: =IF(J43="Not disclosed",J44,J42) -> 49.1 | K46: =IF(K43="Not disclosed",K44,K42) -> 75.2 | L46: =IF(L43="Not disclosed",L44,L42) -> 99 | M46: =IF(M43="Not disclosed",M44,M42) -> 180.7 | ... O46: =IF(O43="Not disclosed",O44,O42) -> 259.7
A48: D&A excluding 4->5 yr life change | B48: $M | C48: Filings | D48: Q1'26 benefit $43.1M, Q2'26 $43.0M (FY26 guided $167.6M); = reported + benefit | F48: 8.9 | G48: 11.4 | H48: 23.5 | I48: 33.3 | J48: 49.1 | K48: 75.2 | L48: 99 | M48: 180.7 | N48: 255.1 | O48: 302.7
A49: tag | F49: Reported | G49: Reported | H49: Reported | I49: Reported | J49: Reported | K49: Reported | L49: Reported | M49: Reported | N49: Derived | O49: Derived
A50: best estimate
A51: method / source | F51: Q1'25 6-K PR comparatives (pre-Toloka-deconsolidation basis) | G51: Q2'25 6-K PR comparative | H51: Q3'25 6-K PR comparative (restated) | I51: Q4'25 6-K PR comparative | J51: Q1'26 6-K PR comparative (restated) | K51: Q2'26 6-K PR comparative | L51: Q3'25 6-K PR | M51: Q4'25 6-K PR | N51: Derived: 212.0 + 43.1 (Q1'26 6-K Note 1) | O51: Derived: 259.7 + 43.0 (Q2'26 6-K Note 1)
A52: VALUE USED | F52: =IF(F49="Not disclosed",F50,F48) -> 8.9 | G52: =IF(G49="Not disclosed",G50,G48) -> 11.4 | H52: =IF(H49="Not disclosed",H50,H48) -> 23.5 | I52: =IF(I49="Not disclosed",I50,I48) -> 33.3 | J52: =IF(J49="Not disclosed",J50,J48) -> 49.1 | K52: =IF(K49="Not disclosed",K50,K48) -> 75.2 | L52: =IF(L49="Not disclosed",L50,L48) -> 99 | M52: =IF(M49="Not disclosed",M50,M48) -> 180.7 | ... O52: =IF(O49="Not disclosed",O50,O48) -> 302.7
A54: PP&E, net (end of period) | B54: $M | C54: Filings | D54: Q1'24 not comparable (pre-divestiture); /workspace/nebius/filings/nebius_filings.xlsx Quarterly | F54: n.d. | G54: 328.3 | H54: 475.3 | I54: 846.7 | J54: 1334.1 | K54: 1789.4 | L54: 3314.4 | M54: 5553.3 | N54: 7131.7 | O54: 13045.2
A55: tag | F55: Not disclosed | G55: Reported | H55: Reported | I55: Reported | J55: Reported | K55: Reported | L55: Reported | M55: Reported | N55: Reported | O55: Reported
A56: best estimate | F56: 250
A57: method / source | F57: Est: Q2'24 less Q2 capex net of D&A | G57: Q2'25 6-K PR comparative | H57: Q3'25 6-K PR comparative (restated) | I57: Q4'25 6-K PR comparative | J57: Q1'26 6-K PR comparative (restated) | K57: Q2'26 6-K PR comparative | L57: Q3'25 6-K PR | M57: Q4'25 6-K PR | N57: Q1'26 6-K PR | O57: Q2'26 6-K PR (acc. 0001104659-26-094568)
A58: VALUE USED | F58: =IF(F55="Not disclosed",F56,F54) -> 250 | G58: =IF(G55="Not disclosed",G56,G54) -> 328.3 | H58: =IF(H55="Not disclosed",H56,H54) -> 475.3 | I58: =IF(I55="Not disclosed",I56,I54) -> 846.7 | J58: =IF(J55="Not disclosed",J56,J54) -> 1334.1 | K58: =IF(K55="Not disclosed",K56,K54) -> 1789.4 | L58: =IF(L55="Not disclosed",L56,L54) -> 3314.4 | M58: =IF(M55="Not disclosed",M56,M54) -> 5553.3 | ... O58: =IF(O55="Not disclosed",O56,O54) -> 13045.2
A60: Assets not yet in use (CIP / not placed in service) | B60: $M | C60: Filings | D60: Note 7 of Q1/Q2'26 statements (Filings & Capital); pre-Q4'25 not disclosed | F60: n.d. | G60: n.d. | H60: n.d. | I60: n.d. | J60: n.d. | K60: n.d. | L60: n.d. | M60: 2417.4 | N60: 2427.9 | O60: 7836.4
A61: tag | F61: Not disclosed | G61: Not disclosed | H61: Not disclosed | I61: Not disclosed | J61: Not disclosed | K61: Not disclosed | L61: Not disclosed | M61: Reported | N61: Reported | O61: Reported
A62: best estimate
A63: method / source | F63: Not disclosed (no best estimate; yield check starts Q1'26) | G63: Not disclosed (no best estimate; yield check starts Q1'26) | H63: Not disclosed (no best estimate; yield check starts Q1'26) | I63: Not disclosed (no best estimate; yield check starts Q1'26) | J63: Not disclosed (no best estimate; yield check starts Q1'26) | K63: Not disclosed (no best estimate; yield check starts Q1'26) | L63: Not disclosed (no best estimate; yield check starts Q1'26) | M63: Q1/Q2'26 6-K Note 7 | N63: Q1/Q2'26 6-K Note 7 | O63: Q1/Q2'26 6-K Note 7
A64: VALUE USED | F64: =IF(F61="Not disclosed",F62,F60) -> 0 | G64: =IF(G61="Not disclosed",G62,G60) -> 0 | H64: =IF(H61="Not disclosed",H62,H60) -> 0 | I64: =IF(I61="Not disclosed",I62,I60) -> 0 | J64: =IF(J61="Not disclosed",J62,J60) -> 0 | K64: =IF(K61="Not disclosed",K62,K60) -> 0 | L64: =IF(L61="Not disclosed",L62,L60) -> 0 | M64: =IF(M61="Not disclosed",M62,M60) -> 2417.4 | ... O64: =IF(O61="Not disclosed",O62,O60) -> 7836.4
A66: In-service gross PP&E | B66: $M | C66: Filings | D66: Derived = gross PP&E - assets not yet in use (Note 7) | F66: n.d. | G66: n.d. | H66: n.d. | I66: n.d. | J66: n.d. | K66: n.d. | L66: n.d. | M66: 3772.9 | N66: 5548.7 | O66: 6313.1
A67: tag | F67: Not disclosed | G67: Not disclosed | H67: Not disclosed | I67: Not disclosed | J67: Not disclosed | K67: Not disclosed | L67: Not disclosed | M67: Derived | N67: Derived | O67: Derived
A68: best estimate
A69: method / source | F69: Not disclosed | G69: Not disclosed | H69: Not disclosed | I69: Not disclosed | J69: Not disclosed | K69: Not disclosed | L69: Not disclosed | M69: Derived, Note 7 | N69: Derived, Note 7 | O69: Derived, Note 7
A70: VALUE USED | F70: =IF(F67="Not disclosed",F68,F66) -> 0 | G70: =IF(G67="Not disclosed",G68,G66) -> 0 | H70: =IF(H67="Not disclosed",H68,H66) -> 0 | I70: =IF(I67="Not disclosed",I68,I66) -> 0 | J70: =IF(J67="Not disclosed",J68,J66) -> 0 | K70: =IF(K67="Not disclosed",K68,K66) -> 0 | L70: =IF(L67="Not disclosed",L68,L66) -> 0 | M70: =IF(M67="Not disclosed",M68,M66) -> 3772.9 | ... O70: =IF(O67="Not disclosed",O68,O66) -> 6313.1
A72: of which servers & network equipment (gross, in service) | B72: $M | C72: Filings | D72: Note 7 | F72: n.d. | G72: n.d. | H72: n.d. | I72: n.d. | J72: n.d. | K72: n.d. | L72: n.d. | M72: 3123.6 | N72: 4692.7 | O72: 5197.7
A73: tag | F73: Not disclosed | G73: Not disclosed | H73: Not disclosed | I73: Not disclosed | J73: Not disclosed | K73: Not disclosed | L73: Not disclosed | M73: Reported | N73: Reported | O73: Reported
A74: best estimate
A75: method / source | F75: Not disclosed | G75: Not disclosed | H75: Not disclosed | I75: Not disclosed | J75: Not disclosed | K75: Not disclosed | L75: Not disclosed | M75: Note 7 | N75: Note 7 | O75: Note 7
A76: VALUE USED | F76: =IF(F73="Not disclosed",F74,F72) -> 0 | G76: =IF(G73="Not disclosed",G74,G72) -> 0 | H76: =IF(H73="Not disclosed",H74,H72) -> 0 | I76: =IF(I73="Not disclosed",I74,I72) -> 0 | J76: =IF(J73="Not disclosed",J74,J72) -> 0 | K76: =IF(K73="Not disclosed",K74,K72) -> 0 | L76: =IF(L73="Not disclosed",L74,L72) -> 0 | M76: =IF(M73="Not disclosed",M74,M72) -> 3123.6 | ... O76: =IF(O73="Not disclosed",O74,O72) -> 5197.7
A78: PP&E depreciation (excl. intangible amortization) | B78: $M | C78: Filings | D78: Note 7; pre-Q1'26 best estimate = total D&A | F78: n.d. | G78: n.d. | H78: n.d. | I78: n.d. | J78: n.d. | K78: n.d. | L78: n.d. | M78: n.d. | N78: 208.8 | O78: 253.8
A79: tag | F79: Not disclosed | G79: Not disclosed | H79: Not disclosed | I79: Not disclosed | J79: Not disclosed | K79: Not disclosed | L79: Not disclosed | M79: Not disclosed | N79: Reported | O79: Reported
A80: best estimate | F80: 8.9 | G80: 11.4 | H80: 23.5 | I80: 33.3 | J80: 49.1 | K80: 75.2 | L80: 99 | M80: 180.7
A81: method / source | F81: Est = total D&A (amortization small) | G81: Est = total D&A (amortization small) | H81: Est = total D&A (amortization small) | I81: Est = total D&A (amortization small) | J81: Est = total D&A (amortization small) | K81: Est = total D&A (amortization small) | L81: Est = total D&A (amortization small) | M81: Est = total D&A (amortization small) | N81: Note 7 | O81: Note 7
A82: VALUE USED | F82: =IF(F79="Not disclosed",F80,F78) -> 8.9 | G82: =IF(G79="Not disclosed",G80,G78) -> 11.4 | H82: =IF(H79="Not disclosed",H80,H78) -> 23.5 | I82: =IF(I79="Not disclosed",I80,I78) -> 33.3 | J82: =IF(J79="Not disclosed",J80,J78) -> 49.1 | K82: =IF(K79="Not disclosed",K80,K78) -> 75.2 | L82: =IF(L79="Not disclosed",L80,L78) -> 99 | M82: =IF(M79="Not disclosed",M80,M78) -> 180.7 | ... O82: =IF(O79="Not disclosed",O80,O78) -> 253.8
A84: Capitalized interest | B84: $M | C84: Filings | D84: Note 12: Q2'26 $40.2M vs $107.5M gross convert interest | F84: n.d. | G84: n.d. | H84: n.d. | I84: n.d. | J84: n.d. | K84: n.d. | L84: n.d. | M84: n.d. | N84: 15.7 | O84: 40.2
A85: tag | F85: Not disclosed | G85: Not disclosed | H85: Not disclosed | I85: Not disclosed | J85: Not disclosed | K85: Not disclosed | L85: Not disclosed | M85: Not disclosed | N85: Reported | O85: Reported
A86: best estimate | F86: 0 | G86: 0 | H86: 0 | I86: 0 | J86: 0 | K86: 0 | L86: 0 | M86: 0
A87: method / source | F87: Not disclosed; est 0 | G87: Not disclosed; est 0 | H87: Not disclosed; est 0 | I87: Not disclosed; est 0 | J87: Not disclosed; est 0 | K87: Not disclosed; est 0 | L87: Not disclosed; est 0 | M87: Not disclosed; est 0 | N87: Note 12 | O87: Note 12
A88: VALUE USED | F88: =IF(F85="Not disclosed",F86,F84) -> 0 | G88: =IF(G85="Not disclosed",G86,G84) -> 0 | H88: =IF(H85="Not disclosed",H86,H84) -> 0 | I88: =IF(I85="Not disclosed",I86,I84) -> 0 | J88: =IF(J85="Not disclosed",J86,J84) -> 0 | K88: =IF(K85="Not disclosed",K86,K84) -> 0 | L88: =IF(L85="Not disclosed",L86,L84) -> 0 | M88: =IF(M85="Not disclosed",M86,M84) -> 0 | ... O88: =IF(O85="Not disclosed",O86,O84) -> 40.2
A90: Adjusted EBITDA (group) | B90: $M | C90: Filings | D90: Q1'24 on pre-restatement basis | F90: -70.9 | G90: -58.1 | H90: -45.9 | I90: -63.9 | J90: -53.7 | K90: -21 | L90: -5.2 | M90: 15 | N90: 129.5 | O90: 236.2
A91: tag | F91: Reported | G91: Reported | H91: Reported | I91: Reported | J91: Reported | K91: Reported | L91: Reported | M91: Reported | N91: Reported | O91: Reported
A92: best estimate
A93: method / source | F93: Q1'25 6-K PR comparatives (pre-Toloka-deconsolidation basis) | G93: Q2'25 6-K PR comparative | H93: Q3'25 6-K PR comparative (restated) | I93: Q4'25 6-K PR comparative | J93: Q1'26 6-K PR comparative (restated) | K93: Q2'26 6-K PR comparative | L93: Q3'25 6-K PR | M93: Q4'25 6-K PR | N93: Q1'26 6-K PR | O93: Q2'26 6-K PR (acc. 0001104659-26-094568)
A94: VALUE USED | F94: =IF(F91="Not disclosed",F92,F90) -> -70.9 | G94: =IF(G91="Not disclosed",G92,G90) -> -58.1 | H94: =IF(H91="Not disclosed",H92,H90) -> -45.9 | I94: =IF(I91="Not disclosed",I92,I90) -> -63.9 | J94: =IF(J91="Not disclosed",J92,J90) -> -53.7 | K94: =IF(K91="Not disclosed",K92,K90) -> -21 | L94: =IF(L91="Not disclosed",L92,L90) -> -5.2 | M94: =IF(M91="Not disclosed",M92,M90) -> 15 | ... O94: =IF(O91="Not disclosed",O92,O90) -> 236.2
A96: Capex (purchases of PP&E + intangibles, cash) | B96: $M | C96: Filings | D96: FY24 cash capex $807.5M; FY25 $4,066.0M (20-F FY25 cash-flow) | F96: n.d. | G96: n.d. | H96: n.d. | I96: 417.6 | J96: 544 | K96: 510.6 | L96: 955.5 | M96: 2056 | N96: 2472.9 | O96: 5657.4
A97: tag | F97: Not disclosed | G97: Not disclosed | H97: Not disclosed | I97: Reported | J97: Reported | K97: Reported | L97: Reported | M97: Reported | N97: Derived | O97: Reported
A98: best estimate | F98: 130 | G98: 130 | H98: 129.9
A99: method / source | F99: Est: (FY24 807.5 - Q4'24 417.6) / 3 - split not disclosed | G99: Est: (FY24 807.5 - Q4'24 417.6) / 3 - split not disclosed | H99: Est: (FY24 807.5 - Q4'24 417.6) / 3 - split not disclosed | I99: Q4'24 PR | J99: Q1'25 letter | K99: Q2'25 letter | L99: Q3'25 letter | M99: 20-F FY25 cash flow (FY 4,066.0 less 9M) | N99: Derived: 1H26 8,130.3 - Q2 5,657.4 | O99: Q2'26 PR (Filings)
A100: VALUE USED | F100: =IF(F97="Not disclosed",F98,F96) -> 130 | G100: =IF(G97="Not disclosed",G98,G96) -> 130 | H100: =IF(H97="Not disclosed",H98,H96) -> 129.9 | I100: =IF(I97="Not disclosed",I98,I96) -> 417.6 | J100: =IF(J97="Not disclosed",J98,J96) -> 544 | K100: =IF(K97="Not disclosed",K98,K96) -> 510.6 | L100: =IF(L97="Not disclosed",L98,L96) -> 955.5 | M100: =IF(M97="Not disclosed",M98,M96) -> 2056 | ... O100: =IF(O97="Not disclosed",O98,O96) -> 5657.4
A102: Cash & equivalents (ex-restricted) | B102: $M | C102: Filings | F102: n.d. | G102: n.d. | H102: n.d. | I102: 2434.7 | J102: 1447 | K102: 1679.3 | L102: 4794.8 | M102: 3678.1 | N102: 9298.2 | O102: 8042.1
A103: tag | F103: Not disclosed | G103: Not disclosed | H103: Not disclosed | I103: Reported | J103: Reported | K103: Reported | L103: Reported | M103: Reported | N103: Reported | O103: Reported
A104: best estimate | F104: 2288.2 | G104: 2288.2 | H104: 2288.2
A105: method / source | F105: Est: carry Q3'24 balance (not loaded) | G105: Est: carry Q3'24 balance (not loaded) | H105: Q3'24 PR (pre-restatement) as best estimate | I105: Q4'25 6-K PR comparative | J105: Q1'26 6-K PR comparative (restated) | K105: Q2'26 6-K PR comparative | L105: Q3'25 6-K PR | M105: Q4'25 6-K PR | N105: Q1'26 6-K PR | O105: Q2'26 6-K PR (acc. 0001104659-26-094568)
A106: VALUE USED | F106: =IF(F103="Not disclosed",F104,F102) -> 2288.2 | G106: =IF(G103="Not disclosed",G104,G102) -> 2288.2 | H106: =IF(H103="Not disclosed",H104,H102) -> 2288.2 | I106: =IF(I103="Not disclosed",I104,I102) -> 2434.7 | J106: =IF(J103="Not disclosed",J104,J102) -> 1447 | K106: =IF(K103="Not disclosed",K104,K102) -> 1679.3 | L106: =IF(L103="Not disclosed",L104,L102) -> 4794.8 | M106: =IF(M103="Not disclosed",M104,M102) -> 3678.1 | ... O106: =IF(O103="Not disclosed",O104,O102) -> 8042.1
A108: Shares issued & outstanding (Class A + B, ex-treasury) | B108: M sh | C108: Filings | F108: n.d. | G108: n.d. | H108: 199.34012 | I108: 235.7536 | J108: 238.10883 | K108: 238.70509 | L108: 251.80722 | M108: 253.01697 | N108: 253.89819 | O108: 271.85522
A109: tag | F109: Not disclosed | G109: Not disclosed | H109: Reported | I109: Reported | J109: Reported | K109: Reported | L109: Reported | M109: Reported | N109: Reported | O109: Reported
A110: best estimate | F110: 199.34 | G110: 199.34
A111: method / source | F111: Est: carry Q3'24 (pre-restructuring counts not comparable) | G111: Est: carry Q3'24 (pre-restructuring counts not comparable) | H111: Q3'25 6-K PR comparative (restated) | I111: Q4'25 6-K PR comparative | J111: Q1'26 6-K PR comparative (restated) | K111: Q2'26 6-K PR comparative | L111: Q3'25 6-K PR | M111: Q4'25 6-K PR | N111: Q1'26 6-K PR | O111: Q2'26 6-K PR (acc. 0001104659-26-094568)
A112: VALUE USED | F112: =IF(F109="Not disclosed",F110,F108) -> 199.34 | G112: =IF(G109="Not disclosed",G110,G108) -> 199.34 | H112: =IF(H109="Not disclosed",H110,H108) -> 199.34012 | I112: =IF(I109="Not disclosed",I110,I108) -> 235.7536 | J112: =IF(J109="Not disclosed",J110,J108) -> 238.10883 | K112: =IF(K109="Not disclosed",K110,K108) -> 238.70509 | L112: =IF(L109="Not disclosed",L110,L108) -> 251.80722 | M112: =IF(M109="Not disclosed",M110,M108) -> 253.01697 | ... O112: =IF(O109="Not disclosed",O110,O108) -> 271.85522
A114: Active power (IT MW consumed) | B114: MW | C114: Capacity | D114: Only YE25 disclosed (~170 MW). Est = 170 x group revenue / Q4'25 revenue (pre-2026) or linear path to 900 MW by Q2'27 (2026) | F114: n.d. | G114: n.d. | H114: n.d. | I114: n.d. | J114: n.d. | K114: n.d. | L114: n.d. | M114: 170 | N114: n.d. | O114: n.d.
A115: tag | F115: Not disclosed | G115: Not disclosed | H115: Not disclosed | I115: Not disclosed | J115: Not disclosed | K115: Not disclosed | L115: Not disclosed | M115: Reported | N115: Not disclosed | O115: Not disclosed
A116: best estimate | F116: 8.5 | G116: 10.8 | H116: 24 | I116: 26.3 | J116: 38 | K116: 78.5 | L116: 109.1 | N116: 291.7 | O116: 413.3
A117: method / source | F117: Est: revenue-proportional to YE25 170 MW (YE24 ~25 MW connected per Q3'25 letter = sanity check) | G117: Est: revenue-proportional to YE25 170 MW (YE24 ~25 MW connected per Q3'25 letter = sanity check) | H117: Est: revenue-proportional to YE25 170 MW (YE24 ~25 MW connected per Q3'25 letter = sanity check) | I117: Est: revenue-proportional to YE25 170 MW (YE24 ~25 MW connected per Q3'25 letter = sanity check) | J117: Est: revenue-proportional to YE25 170 MW (YE24 ~25 MW connected per Q3'25 letter = sanity check) | K117: Est: revenue-proportional to YE25 170 MW (YE24 ~25 MW connected per Q3'25 letter = sanity check) | L117: Est: revenue-proportional to YE25 170 MW (YE24 ~25 MW connected per Q3'25 letter = sanity check) | M117: Q4'25 letter: ~170 MW active | N117: Est: linear 170 MW (Q4'25) -> 900 MW (Q2'27; 800MW-1GW connected YE26, active through 1H27 per Q2'26 call) | O117: Est: linear 170 MW (Q4'25) -> 900 MW (Q2'27; 800MW-1GW connected YE26, active through 1H27 per Q2'26 call)
A118: VALUE USED | F118: =IF(F115="Not disclosed",F116,F114) -> 8.5 | G118: =IF(G115="Not disclosed",G116,G114) -> 10.8 | H118: =IF(H115="Not disclosed",H116,H114) -> 24 | I118: =IF(I115="Not disclosed",I116,I114) -> 26.3 | J118: =IF(J115="Not disclosed",J116,J114) -> 38 | K118: =IF(K115="Not disclosed",K116,K114) -> 78.5 | L118: =IF(L115="Not disclosed",L116,L114) -> 109.1 | M118: =IF(M115="Not disclosed",M116,M114) -> 170 | ... O118: =IF(O115="Not disclosed",O116,O114) -> 413.3
A120: Contracted power (portfolio) | B120: MW | C120: Capacity/Filings | D120: Contracted = land + power commitments, not built | F120: n.d. | G120: n.d. | H120: n.d. | I120: n.d. | J120: n.d. | K120: n.d. | L120: n.d. | M120: 2000 | N120: n.d. | O120: 3500
...

Sheet Sites
A1: Sites
A2: Site-by-site MW: three blocks (contracted / energized estimate [Capacity] / mgmt-guided). Selector Inputs!MWSel picks the revenue driver. All MW converted to IT basis via PUE where basis = Facility.
A3: Line item | B3: Unit | C3: Owner | D3: Tag / source / method | E3: Open | F3: =Timeline!F3 -> Q1'24 | G3: =Timeline!G3 -> Q2'24 | H3: =Timeline!H3 -> Q3'24 | I3: =Timeline!I3 -> Q4'24 | J3: =Timeline!J3 -> Q1'25 | K3: =Timeline!K3 -> Q2'25 | L3: =Timeline!L3 -> Q3'25 | M3: =Timeline!M3 -> Q4'25 | ... AG3: =Timeline!AG3 -> Q4'30 | AI3: FY2024 | AJ3: FY2025 | AK3: FY2026 | AL3: FY2027 | AM3: FY2028 | AN3: FY2029 | AO3: FY2030
A4: Period end | F4: =Timeline!F4 -> 45382 | G4: =Timeline!G4 -> 45473 | H4: =Timeline!H4 -> 45565 | I4: =Timeline!I4 -> 45657 | J4: =Timeline!J4 -> 45747 | K4: =Timeline!K4 -> 45838 | L4: =Timeline!L4 -> 45930 | M4: =Timeline!M4 -> 46022 | ... AG4: =Timeline!AG4 -> 47848
A5: Index | E5: 0 | F5: =Timeline!F5 -> 1 | G5: =Timeline!G5 -> 2 | H5: =Timeline!H5 -> 3 | I5: =Timeline!I5 -> 4 | J5: =Timeline!J5 -> 5 | K5: =Timeline!K5 -> 6 | L5: =Timeline!L5 -> 7 | M5: =Timeline!M5 -> 8 | ... AG5: =Timeline!AG5 -> 28
A6: A = actual / F = forecast | F6: =Timeline!F6 -> A | G6: =Timeline!G6 -> A | H6: =Timeline!H6 -> A | I6: =Timeline!I6 -> A | J6: =Timeline!J6 -> A | K6: =Timeline!K6 -> A | L6: =Timeline!L6 -> A | M6: =Timeline!M6 -> A | ... AG6: =Timeline!AG6 -> F
A7: Fiscal year | F7: =Timeline!F7 -> 2024 | G7: =Timeline!G7 -> 2024 | H7: =Timeline!H7 -> 2024 | I7: =Timeline!I7 -> 2024 | J7: =Timeline!J7 -> 2025 | K7: =Timeline!K7 -> 2025 | L7: =Timeline!L7 -> 2025 | M7: =Timeline!M7 -> 2025 | ... AG7: =Timeline!AG7 -> 2030 | AI7: 2024 | AJ7: 2025 | AK7: 2026 | AL7: 2027 | AM7: 2028 | AN7: 2029 | AO7: 2030
A10: Site metadata (ownership switches shell+power between capex [Owned] and rent [Leased-colo / Build-to-suit lease]; MW basis flag converts Facility MW to IT MW via PUE)
A11: Site | B11: Ownership | C11: MW basis | D11: Capacity-file basis / notes | E11: Risk grade | F11: IT factor | G11: Owned? | H11: Go-live idx - early (bull) | I11: Go-live idx - base | J11: Go-live idx - late (bear) | K11: Go-live (live) | L11: Evidence tag | M11: Owner / due | N11: GPU generation | O11: Capex $M/IT MW | P11: of which shell+power
A12: Vineland NJ (DataOne) | B12: Build-to-suit lease | C12: IT | D12: file basis: IT; Vineland leased from DataOne; Bloom PPA power | E12: Red | F12: =IF(C12="Facility",1/PUE,1) -> 1 | G12: =IF(B12="Owned",1,0) -> 0 | H12: 8 | I12: 8 | J12: 8 | K12: =IF(N(CHOOSE(Scen,H12,I12,J12))=0,"n/a",INDEX(Q_Lab,1,CHOOSE(Scen,H12,I12,J12))) -> Q4'25 | M12: Capacity & Power - due Tue Oct 6 (prefill = first non-zero energized qtr in Capacity file) | N12: GB300 NVL72 | O12: =IF(B12="Owned",IF(N12="GB300 NVL72",CPM_Own_GB300,IF(N12="Vera Rubin NVL72",CPM_Own_VR,IF(N12="GB200 NVL72",CPM_Own_GB200,CPM_Own_Other))),IF(N12="GB300 NVL72",CPM_Lease_GB300,IF(N12="Vera Rubin NVL72",CPM_Lease_VR,CPM_Lease))) -> 41 | P12: =IF(B12="Owned",CPM_SP,0) -> 0
A13: Independence MO (Eastgate) | B13: Owned | C13: Facility | D13: file basis: stated/unknown | E13: Green | F13: =IF(C13="Facility",1/PUE,1) -> 0.8 | G13: =IF(B13="Owned",1,0) -> 1 | H13: 15 | I13: 15 | J13: 16 | K13: =IF(N(CHOOSE(Scen,H13,I13,J13))=0,"n/a",INDEX(Q_Lab,1,CHOOSE(Scen,H13,I13,J13))) -> Q3'27 | M13: Capacity & Power - due Tue Oct 6 (prefill = first non-zero energized qtr in Capacity file) | N13: Vera Rubin NVL72 | O13: =IF(B13="Owned",IF(N13="GB300 NVL72",CPM_Own_GB300,IF(N13="Vera Rubin NVL72",CPM_Own_VR,IF(N13="GB200 NVL72",CPM_Own_GB200,CPM_Own_Other))),IF(N13="GB300 NVL72",CPM_Lease_GB300,IF(N13="Vera Rubin NVL72",CPM_Lease_VR,CPM_Lease))) -> 56 | P13: =IF(B13="Owned",CPM_SP,0) -> 11.25
A14: Butler Twp PA (Highridge) | B14: Owned | C14: Facility | D14: file basis: stated/unknown | E14: Red | F14: =IF(C14="Facility",1/PUE,1) -> 0.8 | G14: =IF(B14="Owned",1,0) -> 1 | H14: 16 | I14: 16 | J14: 20 | K14: =IF(N(CHOOSE(Scen,H14,I14,J14))=0,"n/a",INDEX(Q_Lab,1,CHOOSE(Scen,H14,I14,J14))) -> Q4'27 | M14: Capacity & Power - due Tue Oct 6 (prefill = first non-zero energized qtr in Capacity file) | N14: Vera Rubin NVL72 | O14: =IF(B14="Owned",IF(N14="GB300 NVL72",CPM_Own_GB300,IF(N14="Vera Rubin NVL72",CPM_Own_VR,IF(N14="GB200 NVL72",CPM_Own_GB200,CPM_Own_Other))),IF(N14="GB300 NVL72",CPM_Lease_GB300,IF(N14="Vera Rubin NVL72",CPM_Lease_VR,CPM_Lease))) -> 56 | P14: =IF(B14="Owned",CPM_SP,0) -> 11.25
A15: Birmingham AL (BHM01, Oxmoor) | B15: Owned | C15: Facility | D15: file basis: stated/unknown | E15: Yellow | F15: =IF(C15="Facility",1/PUE,1) -> 0.8 | G15: =IF(B15="Owned",1,0) -> 1 | H15: 13 | I15: 13 | J15: 15 | K15: =IF(N(CHOOSE(Scen,H15,I15,J15))=0,"n/a",INDEX(Q_Lab,1,CHOOSE(Scen,H15,I15,J15))) -> Q1'27 | M15: Capacity & Power - due Tue Oct 6 (prefill = first non-zero energized qtr in Capacity file) | N15: Vera Rubin NVL72 | O15: =IF(B15="Owned",IF(N15="GB300 NVL72",CPM_Own_GB300,IF(N15="Vera Rubin NVL72",CPM_Own_VR,IF(N15="GB200 NVL72",CPM_Own_GB200,CPM_Own_Other))),IF(N15="GB300 NVL72",CPM_Lease_GB300,IF(N15="Vera Rubin NVL72",CPM_Lease_VR,CPM_Lease))) -> 56 | P15: =IF(B15="Owned",CPM_SP,0) -> 11.25
A16: Bethune FR (Azur Datacenter, ex-Bridgestone) | B16: Leased-colo | C16: Facility | D16: file basis: stated/unknown; Bethune 0/30/60 MW YE26 (Capacity) | E16: Yellow | F16: =IF(C16="Facility",1/PUE,1) -> 0.8 | G16: =IF(B16="Owned",1,0) -> 0 | H16: 12 | I16: 12 | J16: 13 | K16: =IF(N(CHOOSE(Scen,H16,I16,J16))=0,"n/a",INDEX(Q_Lab,1,CHOOSE(Scen,H16,I16,J16))) -> Q4'26 | M16: Capacity & Power - due Tue Oct 6 (prefill = first non-zero energized qtr in Capacity file) | N16: GB300 NVL72 | O16: =IF(B16="Owned",IF(N16="GB300 NVL72",CPM_Own_GB300,IF(N16="Vera Rubin NVL72",CPM_Own_VR,IF(N16="GB200 NVL72",CPM_Own_GB200,CPM_Own_Other))),IF(N16="GB300 NVL72",CPM_Lease_GB300,IF(N16="Vera Rubin NVL72",CPM_Lease_VR,CPM_Lease))) -> 41 | P16: =IF(B16="Owned",CPM_SP,0) -> 0
A17: Lappeenranta FI (Pajarila / Polarnode) | B17: Owned | C17: Facility | D17: file basis: stated/unknown | E17: Green | F17: =IF(C17="Facility",1/PUE,1) -> 0.8 | G17: =IF(B17="Owned",1,0) -> 1 | H17: 14 | I17: 14 | J17: 16 | K17: =IF(N(CHOOSE(Scen,H17,I17,J17))=0,"n/a",INDEX(Q_Lab,1,CHOOSE(Scen,H17,I17,J17))) -> Q2'27 | M17: Capacity & Power - due Tue Oct 6 (prefill = first non-zero energized qtr in Capacity file) | N17: Vera Rubin NVL72 | O17: =IF(B17="Owned",IF(N17="GB300 NVL72",CPM_Own_GB300,IF(N17="Vera Rubin NVL72",CPM_Own_VR,IF(N17="GB200 NVL72",CPM_Own_GB200,CPM_Own_Other))),IF(N17="GB300 NVL72",CPM_Lease_GB300,IF(N17="Vera Rubin NVL72",CPM_Lease_VR,CPM_Lease))) -> 56 | P17: =IF(B17="Owned",CPM_SP,0) -> 11.25
A18: Mantsala FI #1 | B18: Owned | C18: IT | D18: file basis: stated/unknown | E18: Green | F18: =IF(C18="Facility",1/PUE,1) -> 1 | G18: =IF(B18="Owned",1,0) -> 1 | H18: 1 | I18: 1 | J18: 1 | K18: =IF(N(CHOOSE(Scen,H18,I18,J18))=0,"n/a",INDEX(Q_Lab,1,CHOOSE(Scen,H18,I18,J18))) -> Q1'24 | M18: Capacity & Power - due Tue Oct 6 (prefill = first non-zero energized qtr in Capacity file) | N18: GB300 NVL72 | O18: =IF(B18="Owned",IF(N18="GB300 NVL72",CPM_Own_GB300,IF(N18="Vera Rubin NVL72",CPM_Own_VR,IF(N18="GB200 NVL72",CPM_Own_GB200,CPM_Own_Other))),IF(N18="GB300 NVL72",CPM_Lease_GB300,IF(N18="Vera Rubin NVL72",CPM_Lease_VR,CPM_Lease))) -> 53 | P18: =IF(B18="Owned",CPM_SP,0) -> 11.25
A19: Mantsala FI #2 (Kapuli) | B19: Owned | C19: Facility | D19: file basis: stated/unknown | E19: Yellow | F19: =IF(C19="Facility",1/PUE,1) -> 0.8 | G19: =IF(B19="Owned",1,0) -> 1 | H19: 16 | I19: 16 | J19: 17 | K19: =IF(N(CHOOSE(Scen,H19,I19,J19))=0,"n/a",INDEX(Q_Lab,1,CHOOSE(Scen,H19,I19,J19))) -> Q4'27 | M19: Capacity & Power - due Tue Oct 6 (prefill = first non-zero energized qtr in Capacity file) | N19: Vera Rubin NVL72 | O19: =IF(B19="Owned",IF(N19="GB300 NVL72",CPM_Own_GB300,IF(N19="Vera Rubin NVL72",CPM_Own_VR,IF(N19="GB200 NVL72",CPM_Own_GB200,CPM_Own_Other))),IF(N19="GB300 NVL72",CPM_Lease_GB300,IF(N19="Vera Rubin NVL72",CPM_Lease_VR,CPM_Lease))) -> 56 | P19: =IF(B19="Owned",CPM_SP,0) -> 11.25
A20: Kansas City MO (Patmos) | B20: Leased-colo | C20: IT | D20: file basis: stated/unknown | E20: Green | F20: =IF(C20="Facility",1/PUE,1) -> 1 | G20: =IF(B20="Owned",1,0) -> 0 | H20: 6 | I20: 6 | J20: 6 | K20: =IF(N(CHOOSE(Scen,H20,I20,J20))=0,"n/a",INDEX(Q_Lab,1,CHOOSE(Scen,H20,I20,J20))) -> Q2'25 | M20: Capacity & Power - due Tue Oct 6 (prefill = first non-zero energized qtr in Capacity file) | N20: B200 (HGX) | O20: =IF(B20="Owned",IF(N20="GB300 NVL72",CPM_Own_GB300,IF(N20="Vera Rubin NVL72",CPM_Own_VR,IF(N20="GB200 NVL72",CPM_Own_GB200,CPM_Own_Other))),IF(N20="GB300 NVL72",CPM_Lease_GB300,IF(N20="Vera Rubin NVL72",CPM_Lease_VR,CPM_Lease))) -> 30 | P20: =IF(B20="Owned",CPM_SP,0) -> 0
A21: Paris (Equinix PA10) | B21: Leased-colo | C21: IT | D21: file basis: stated/unknown | E21: Green | F21: =IF(C21="Facility",1/PUE,1) -> 1 | G21: =IF(B21="Owned",1,0) -> 0 | H21: 4 | I21: 4 | J21: 4 | K21: =IF(N(CHOOSE(Scen,H21,I21,J21))=0,"n/a",INDEX(Q_Lab,1,CHOOSE(Scen,H21,I21,J21))) -> Q4'24 | M21: Capacity & Power - due Tue Oct 6 (prefill = first non-zero energized qtr in Capacity file) | N21: Hopper H100/H200 | O21: =IF(B21="Owned",IF(N21="GB300 NVL72",CPM_Own_GB300,IF(N21="Vera Rubin NVL72",CPM_Own_VR,IF(N21="GB200 NVL72",CPM_Own_GB200,CPM_Own_Other))),IF(N21="GB300 NVL72",CPM_Lease_GB300,IF(N21="Vera Rubin NVL72",CPM_Lease_VR,CPM_Lease))) -> 30 | P21: =IF(B21="Owned",CPM_SP,0) -> 0
A22: Keflavik IS (Verne) | B22: Leased-colo | C22: IT | D22: file basis: stated/unknown | E22: Green | F22: =IF(C22="Facility",1/PUE,1) -> 1 | G22: =IF(B22="Owned",1,0) -> 0 | H22: 5 | I22: 5 | J22: 5 | K22: =IF(N(CHOOSE(Scen,H22,I22,J22))=0,"n/a",INDEX(Q_Lab,1,CHOOSE(Scen,H22,I22,J22))) -> Q1'25 | M22: Capacity & Power - due Tue Oct 6 (prefill = first non-zero energized qtr in Capacity file) | N22: Hopper H100/H200 | O22: =IF(B22="Owned",IF(N22="GB300 NVL72",CPM_Own_GB300,IF(N22="Vera Rubin NVL72",CPM_Own_VR,IF(N22="GB200 NVL72",CPM_Own_GB200,CPM_Own_Other))),IF(N22="GB300 NVL72",CPM_Lease_GB300,IF(N22="Vera Rubin NVL72",CPM_Lease_VR,CPM_Lease))) -> 30 | P22: =IF(B22="Owned",CPM_SP,0) -> 0
A23: London Longcross (Ark LP01) | B23: Leased-colo | C23: IT | D23: file basis: stated/unknown | E23: Green | F23: =IF(C23="Facility",1/PUE,1) -> 1 | G23: =IF(B23="Owned",1,0) -> 0 | H23: 8 | I23: 8 | J23: 8 | K23: =IF(N(CHOOSE(Scen,H23,I23,J23))=0,"n/a",INDEX(Q_Lab,1,CHOOSE(Scen,H23,I23,J23))) -> Q4'25 | M23: Capacity & Power - due Tue Oct 6 (prefill = first non-zero energized qtr in Capacity file) | N23: B300 (HGX) | O23: =IF(B23="Owned",IF(N23="GB300 NVL72",CPM_Own_GB300,IF(N23="Vera Rubin NVL72",CPM_Own_VR,IF(N23="GB200 NVL72",CPM_Own_GB200,CPM_Own_Other))),IF(N23="GB300 NVL72",CPM_Lease_GB300,IF(N23="Vera Rubin NVL72",CPM_Lease_VR,CPM_Lease))) -> 30 | P23: =IF(B23="Owned",CPM_SP,0) -> 0
A24: Harlow UK (Kao Data KLON-02/03) | B24: Leased-colo | C24: IT | D24: file basis: stated/unknown | E24: Yellow | F24: =IF(C24="Facility",1/PUE,1) -> 1 | G24: =IF(B24="Owned",1,0) -> 0 | H24: 12 | I24: 12 | J24: 13 | K24: =IF(N(CHOOSE(Scen,H24,I24,J24))=0,"n/a",INDEX(Q_Lab,1,CHOOSE(Scen,H24,I24,J24))) -> Q4'26 | M24: Capacity & Power - due Tue Oct 6 (prefill = first non-zero energized qtr in Capacity file) | N24: B300 (HGX) | O24: =IF(B24="Owned",IF(N24="GB300 NVL72",CPM_Own_GB300,IF(N24="Vera Rubin NVL72",CPM_Own_VR,IF(N24="GB200 NVL72",CPM_Own_GB200,CPM_Own_Other))),IF(N24="GB300 NVL72",CPM_Lease_GB300,IF(N24="Vera Rubin NVL72",CPM_Lease_VR,CPM_Lease))) -> 30 | P24: =IF(B24="Owned",CPM_SP,0) -> 0
A25: UK 3rd new deployment (unnamed) | B25: Leased-colo | C25: IT | D25: file basis: stated/unknown | E25: Red | F25: =IF(C25="Facility",1/PUE,1) -> 1 | G25: =IF(B25="Owned",1,0) -> 0 | K25: =IF(N(CHOOSE(Scen,H25,I25,J25))=0,"n/a",INDEX(Q_Lab,1,CHOOSE(Scen,H25,I25,J25))) -> n/a | M25: Capacity & Power - due Tue Oct 6 (prefill = first non-zero energized qtr in Capacity file) | N25: n/d | O25: =IF(B25="Owned",IF(N25="GB300 NVL72",CPM_Own_GB300,IF(N25="Vera Rubin NVL72",CPM_Own_VR,IF(N25="GB200 NVL72",CPM_Own_GB200,CPM_Own_Other))),IF(N25="GB300 NVL72",CPM_Lease_GB300,IF(N25="Vera Rubin NVL72",CPM_Lease_VR,CPM_Lease))) -> 30 | P25: =IF(B25="Owned",CPM_SP,0) -> 0
A26: Modi'in IL (Mega Or) | B26: Leased-colo | C26: IT | D26: file basis: IT | E26: Green | F26: =IF(C26="Facility",1/PUE,1) -> 1 | G26: =IF(B26="Owned",1,0) -> 0 | H26: 8 | I26: 8 | J26: 8 | K26: =IF(N(CHOOSE(Scen,H26,I26,J26))=0,"n/a",INDEX(Q_Lab,1,CHOOSE(Scen,H26,I26,J26))) -> Q4'25 | M26: Capacity & Power - due Tue Oct 6 (prefill = first non-zero energized qtr in Capacity file) | N26: B200 (HGX) | O26: =IF(B26="Owned",IF(N26="GB300 NVL72",CPM_Own_GB300,IF(N26="Vera Rubin NVL72",CPM_Own_VR,IF(N26="GB200 NVL72",CPM_Own_GB200,CPM_Own_Other))),IF(N26="GB300 NVL72",CPM_Lease_GB300,IF(N26="Vera Rubin NVL72",CPM_Lease_VR,CPM_Lease))) -> 30 | P26: =IF(B26="Owned",CPM_SP,0) -> 0
A27: Masmiyya IL (Mega DC) | B27: Leased-colo | C27: Facility | D27: file basis: stated/unknown | E27: Yellow | F27: =IF(C27="Facility",1/PUE,1) -> 0.8 | G27: =IF(B27="Owned",1,0) -> 0 | H27: 12 | I27: 12 | J27: 13 | K27: =IF(N(CHOOSE(Scen,H27,I27,J27))=0,"n/a",INDEX(Q_Lab,1,CHOOSE(Scen,H27,I27,J27))) -> Q4'26 | M27: Capacity & Power - due Tue Oct 6 (prefill = first non-zero energized qtr in Capacity file) | N27: GB300 NVL72 | O27: =IF(B27="Owned",IF(N27="GB300 NVL72",CPM_Own_GB300,IF(N27="Vera Rubin NVL72",CPM_Own_VR,IF(N27="GB200 NVL72",CPM_Own_GB200,CPM_Own_Other))),IF(N27="GB300 NVL72",CPM_Lease_GB300,IF(N27="Vera Rubin NVL72",CPM_Lease_VR,CPM_Lease))) -> 41 | P27: =IF(B27="Owned",CPM_SP,0) -> 0
A28: Beit Shemesh IL (Mega DC) | B28: Leased-colo | C28: Facility | D28: file basis: stated/unknown | E28: Yellow | F28: =IF(C28="Facility",1/PUE,1) -> 0.8 | G28: =IF(B28="Owned",1,0) -> 0 | H28: 12 | I28: 12 | J28: 13 | K28: =IF(N(CHOOSE(Scen,H28,I28,J28))=0,"n/a",INDEX(Q_Lab,1,CHOOSE(Scen,H28,I28,J28))) -> Q4'26 | M28: Capacity & Power - due Tue Oct 6 (prefill = first non-zero energized qtr in Capacity file) | N28: GB300 NVL72 | O28: =IF(B28="Owned",IF(N28="GB300 NVL72",CPM_Own_GB300,IF(N28="Vera Rubin NVL72",CPM_Own_VR,IF(N28="GB200 NVL72",CPM_Own_GB200,CPM_Own_Other))),IF(N28="GB300 NVL72",CPM_Lease_GB300,IF(N28="Vera Rubin NVL72",CPM_Lease_VR,CPM_Lease))) -> 41 | P28: =IF(B28="Owned",CPM_SP,0) -> 0
A29: Madrid-Getafe ES (Merlin Edged) | B29: Leased-colo | C29: IT | D29: file basis: stated/unknown | E29: Green | F29: =IF(C29="Facility",1/PUE,1) -> 1 | G29: =IF(B29="Owned",1,0) -> 0 | H29: 11 | I29: 11 | J29: 11 | K29: =IF(N(CHOOSE(Scen,H29,I29,J29))=0,"n/a",INDEX(Q_Lab,1,CHOOSE(Scen,H29,I29,J29))) -> Q3'26 | M29: Capacity & Power - due Tue Oct 6 (prefill = first non-zero energized qtr in Capacity file) | N29: B300 (HGX) | O29: =IF(B29="Owned",IF(N29="GB300 NVL72",CPM_Own_GB300,IF(N29="Vera Rubin NVL72",CPM_Own_VR,IF(N29="GB200 NVL72",CPM_Own_GB200,CPM_Own_Other))),IF(N29="GB300 NVL72",CPM_Lease_GB300,IF(N29="Vera Rubin NVL72",CPM_Lease_VR,CPM_Lease))) -> 30 | P29: =IF(B29="Owned",CPM_SP,0) -> 0
A30: Tallinn EE (Greenergy Huuru) | B30: Leased-colo | C30: IT | D30: file basis: stated/unknown | E30: Yellow | F30: =IF(C30="Facility",1/PUE,1) -> 1 | G30: =IF(B30="Owned",1,0) -> 0 | H30: 12 | I30: 12 | J30: 13 | K30: =IF(N(CHOOSE(Scen,H30,I30,J30))=0,"n/a",INDEX(Q_Lab,1,CHOOSE(Scen,H30,I30,J30))) -> Q4'26 | M30: Capacity & Power - due Tue Oct 6 (prefill = first non-zero energized qtr in Capacity file) | N30: GB300 NVL72 | O30: =IF(B30="Owned",IF(N30="GB300 NVL72",CPM_Own_GB300,IF(N30="Vera Rubin NVL72",CPM_Own_VR,IF(N30="GB200 NVL72",CPM_Own_GB200,CPM_Own_Other))),IF(N30="GB300 NVL72",CPM_Lease_GB300,IF(N30="Vera Rubin NVL72",CPM_Lease_VR,CPM_Lease))) -> 41 | P30: =IF(B30="Owned",CPM_SP,0) -> 0
A31: Minnesota (RMA roles, likely colo live) | B31: Leased-colo | C31: IT | D31: file basis: stated/unknown; PLACEHOLDER low/base/high on Inputs (Capacity & Power) | E31: Yellow | F31: =IF(C31="Facility",1/PUE,1) -> 1 | G31: =IF(B31="Owned",1,0) -> 0 | K31: =IF(N(CHOOSE(Scen,H31,I31,J31))=0,"n/a",INDEX(Q_Lab,1,CHOOSE(Scen,H31,I31,J31))) -> n/a | M31: Capacity & Power - due Tue Oct 6 (prefill = first non-zero energized qtr in Capacity file) | N31: n/d | O31: =IF(B31="Owned",IF(N31="GB300 NVL72",CPM_Own_GB300,IF(N31="Vera Rubin NVL72",CPM_Own_VR,IF(N31="GB200 NVL72",CPM_Own_GB200,CPM_Own_Other))),IF(N31="GB300 NVL72",CPM_Lease_GB300,IF(N31="Vera Rubin NVL72",CPM_Lease_VR,CPM_Lease))) -> 30 | P31: =IF(B31="Owned",CPM_SP,0) -> 0
A32: Oklahoma (7 DC roles, live-looking) | B32: Leased-colo | C32: IT | D32: file basis: stated/unknown; PLACEHOLDER low/base/high on Inputs (Capacity & Power) | E32: Yellow | F32: =IF(C32="Facility",1/PUE,1) -> 1 | G32: =IF(B32="Owned",1,0) -> 0 | K32: =IF(N(CHOOSE(Scen,H32,I32,J32))=0,"n/a",INDEX(Q_Lab,1,CHOOSE(Scen,H32,I32,J32))) -> n/a | M32: Capacity & Power - due Tue Oct 6 (prefill = first non-zero energized qtr in Capacity file) | N32: n/d | O32: =IF(B32="Owned",IF(N32="GB300 NVL72",CPM_Own_GB300,IF(N32="Vera Rubin NVL72",CPM_Own_VR,IF(N32="GB200 NVL72",CPM_Own_GB200,CPM_Own_Other))),IF(N32="GB300 NVL72",CPM_Lease_GB300,IF(N32="Vera Rubin NVL72",CPM_Lease_VR,CPM_Lease))) -> 30 | P32: =IF(B32="Owned",CPM_SP,0) -> 0
A33: France 2nd colo (unnamed; possibly eu-west2) | B33: Leased-colo | C33: IT | D33: file basis: stated/unknown | E33: Yellow | F33: =IF(C33="Facility",1/PUE,1) -> 1 | G33: =IF(B33="Owned",1,0) -> 0 | K33: =IF(N(CHOOSE(Scen,H33,I33,J33))=0,"n/a",INDEX(Q_Lab,1,CHOOSE(Scen,H33,I33,J33))) -> n/a | M33: Capacity & Power - due Tue Oct 6 (prefill = first non-zero energized qtr in Capacity file) | N33: n/d | O33: =IF(B33="Owned",IF(N33="GB300 NVL72",CPM_Own_GB300,IF(N33="Vera Rubin NVL72",CPM_Own_VR,IF(N33="GB200 NVL72",CPM_Own_GB200,CPM_Own_Other))),IF(N33="GB300 NVL72",CPM_Lease_GB300,IF(N33="Vera Rubin NVL72",CPM_Lease_VR,CPM_Lease))) -> 30 | P33: =IF(B33="Owned",CPM_SP,0) -> 0
A34: AIB CLT1 (South Carolina) | B34: Leased-colo | C34: IT | D34: file basis: IT | E34: Red | F34: =IF(C34="Facility",1/PUE,1) -> 1 | G34: =IF(B34="Owned",1,0) -> 0 | H34: 15 | I34: 15 | J34: 17 | K34: =IF(N(CHOOSE(Scen,H34,I34,J34))=0,"n/a",INDEX(Q_Lab,1,CHOOSE(Scen,H34,I34,J34))) -> Q3'27 | M34: Capacity & Power - due Tue Oct 6 (prefill = first non-zero energized qtr in Capacity file) | N34: Vera Rubin NVL72 | O34: =IF(B34="Owned",IF(N34="GB300 NVL72",CPM_Own_GB300,IF(N34="Vera Rubin NVL72",CPM_Own_VR,IF(N34="GB200 NVL72",CPM_Own_GB200,CPM_Own_Other))),IF(N34="GB300 NVL72",CPM_Lease_GB300,IF(N34="Vera Rubin NVL72",CPM_Lease_VR,CPM_Lease))) -> 41 | P34: =IF(B34="Owned",CPM_SP,0) -> 0
A35: Other unidentified (colo not yet visible) | B35: Leased-colo | C35: IT | D35: file basis: n/a; PLACEHOLDER low/base/high on Inputs (Capacity & Power) | E35: Red | F35: =IF(C35="Facility",1/PUE,1) -> 1 | G35: =IF(B35="Owned",1,0) -> 0 | K35: =IF(N(CHOOSE(Scen,H35,I35,J35))=0,"n/a",INDEX(Q_Lab,1,CHOOSE(Scen,H35,I35,J35))) -> n/a | M35: Capacity & Power - due Tue Oct 6 (prefill = first non-zero energized qtr in Capacity file) | N35: n/d | O35: =IF(B35="Owned",IF(N35="GB300 NVL72",CPM_Own_GB300,IF(N35="Vera Rubin NVL72",CPM_Own_VR,IF(N35="GB200 NVL72",CPM_Own_GB200,CPM_Own_Other))),IF(N35="GB300 NVL72",CPM_Lease_GB300,IF(N35="Vera Rubin NVL72",CPM_Lease_VR,CPM_Lease))) -> 30 | P35: =IF(B35="Owned",CPM_SP,0) -> 0
A36: Other / unallocated portfolio MW (plug to portfolio total) | B36: Mixed | C36: IT | D36: Owned share from Inputs!OwnedSh | E36: Yellow | F36: =IF(C36="Facility",1/PUE,1) -> 1
A39: Capacity-file import: energized MW low / base / high by site (as stated basis) - Capacity & Power, /workspace/nebius/capacity/nebius_capacity.xlsx 'Quarterly MW' (copied values, as of Oct 4 2026 build)
A40: Vineland NJ (DataOne) - low | B40: MW | C40: Capacity | D40: Capacity file | F40: 0 | G40: 0 | H40: 0 | I40: 0 | J40: 0 | K40: 0 | L40: 0 | M40: 21.8 | N40: 30 | O40: 33 | P40: 57 | Q40: 57 | R40: 57 | S40: 107 | T40: 160 | U40: 230 | V40: 230 | W40: 230 | X40: 230 | Y40: 230 | Z40: 230 | AA40: 230 | AB40: 230 | AC40: 230 | AD40: 230 | AE40: 230 | AF40: 230 | AG40: 230 | AI40: =INDEX($F40:$AG40,1,MATCH(AI$7,$F$7:$AG$7,1)) -> 0 | AJ40: =INDEX($F40:$AG40,1,MATCH(AJ$7,$F$7:$AG$7,1)) -> 21.8 | AK40: =INDEX($F40:$AG40,1,MATCH(AK$7,$F$7:$AG$7,1)) -> 57 | AL40: =INDEX($F40:$AG40,1,MATCH(AL$7,$F$7:$AG$7,1)) -> 230 | AM40: =INDEX($F40:$AG40,1,MATCH(AM$7,$F$7:$AG$7,1)) -> 230 | AN40: =INDEX($F40:$AG40,1,MATCH(AN$7,$F$7:$AG$7,1)) -> 230 | AO40: =INDEX($F40:$AG40,1,MATCH(AO$7,$F$7:$AG$7,1)) -> 230
A41: Vineland NJ (DataOne) - base | B41: MW | C41: Capacity | D41: Capacity file | F41: 0 | G41: 0 | H41: 0 | I41: 0 | J41: 0 | K41: 0 | L41: 0 | M41: 26.2 | N41: 37.5 | O41: 39 | P41: 66 | Q41: 81.8 | R41: 118.5 | S41: 168.5 | T41: 205 | U41: 240 | V41: 240 | W41: 240 | X41: 240 | Y41: 240 | Z41: 240 | AA41: 240 | AB41: 240 | AC41: 240 | AD41: 240 | AE41: 240 | AF41: 240 | AG41: 240 | AI41: =INDEX($F41:$AG41,1,MATCH(AI$7,$F$7:$AG$7,1)) -> 0 | AJ41: =INDEX($F41:$AG41,1,MATCH(AJ$7,$F$7:$AG$7,1)) -> 26.2 | AK41: =INDEX($F41:$AG41,1,MATCH(AK$7,$F$7:$AG$7,1)) -> 81.8 | AL41: =INDEX($F41:$AG41,1,MATCH(AL$7,$F$7:$AG$7,1)) -> 240 | AM41: =INDEX($F41:$AG41,1,MATCH(AM$7,$F$7:$AG$7,1)) -> 240 | AN41: =INDEX($F41:$AG41,1,MATCH(AN$7,$F$7:$AG$7,1)) -> 240 | AO41: =INDEX($F41:$AG41,1,MATCH(AO$7,$F$7:$AG$7,1)) -> 240
A42: Vineland NJ (DataOne) - high | B42: MW | C42: Capacity | D42: Capacity file | F42: 0 | G42: 0 | H42: 0 | I42: 0 | J42: 0 | K42: 0 | L42: 0 | M42: 30.6 | N42: 45 | O42: 45 | P42: 75 | Q42: 106.6 | R42: 180 | S42: 230 | T42: 250 | U42: 250 | V42: 250 | W42: 250 | X42: 250 | Y42: 250 | Z42: 250 | AA42: 250 | AB42: 250 | AC42: 250 | AD42: 250 | AE42: 250 | AF42: 250 | AG42: 250 | AI42: =INDEX($F42:$AG42,1,MATCH(AI$7,$F$7:$AG$7,1)) -> 0 | AJ42: =INDEX($F42:$AG42,1,MATCH(AJ$7,$F$7:$AG$7,1)) -> 30.6 | AK42: =INDEX($F42:$AG42,1,MATCH(AK$7,$F$7:$AG$7,1)) -> 106.6 | AL42: =INDEX($F42:$AG42,1,MATCH(AL$7,$F$7:$AG$7,1)) -> 250 | AM42: =INDEX($F42:$AG42,1,MATCH(AM$7,$F$7:$AG$7,1)) -> 250 | AN42: =INDEX($F42:$AG42,1,MATCH(AN$7,$F$7:$AG$7,1)) -> 250 | AO42: =INDEX($F42:$AG42,1,MATCH(AO$7,$F$7:$AG$7,1)) -> 250
A43: Independence MO (Eastgate) - low | B43: MW | C43: Capacity | D43: Capacity file | F43: 0 | G43: 0 | H43: 0 | I43: 0 | J43: 0 | K43: 0 | L43: 0 | M43: 0 | N43: 0 | O43: 0 | P43: 0 | Q43: 0 | R43: 0 | S43: 0 | T43: 0 | U43: 50 | V43: 50 | W43: 100 | X43: 100 | Y43: 200 | Z43: 200 | AA43: 300 | AB43: 300 | AC43: 500 | AD43: 500 | AE43: 500 | AF43: 500 | AG43: 700 | AI43: =INDEX($F43:$AG43,1,MATCH(AI$7,$F$7:$AG$7,1)) -> 0 | AJ43: =INDEX($F43:$AG43,1,MATCH(AJ$7,$F$7:$AG$7,1)) -> 0 | AK43: =INDEX($F43:$AG43,1,MATCH(AK$7,$F$7:$AG$7,1)) -> 0 | AL43: =INDEX($F43:$AG43,1,MATCH(AL$7,$F$7:$AG$7,1)) -> 50 | AM43: =INDEX($F43:$AG43,1,MATCH(AM$7,$F$7:$AG$7,1)) -> 200 | AN43: =INDEX($F43:$AG43,1,MATCH(AN$7,$F$7:$AG$7,1)) -> 500 | AO43: =INDEX($F43:$AG43,1,MATCH(AO$7,$F$7:$AG$7,1)) -> 700
A44: Independence MO (Eastgate) - base | B44: MW | C44: Capacity | D44: Capacity file | F44: 0 | G44: 0 | H44: 0 | I44: 0 | J44: 0 | K44: 0 | L44: 0 | M44: 0 | N44: 0 | O44: 0 | P44: 0 | Q44: 0 | R44: 0 | S44: 0 | T44: 50 | U44: 125 | V44: 125 | W44: 175 | X44: 175 | Y44: 225 | Z44: 225 | AA44: 450 | AB44: 450 | AC44: 650 | AD44: 650 | AE44: 650 | AF44: 650 | AG44: 950 | AI44: =INDEX($F44:$AG44,1,MATCH(AI$7,$F$7:$AG$7,1)) -> 0 | AJ44: =INDEX($F44:$AG44,1,MATCH(AJ$7,$F$7:$AG$7,1)) -> 0 | AK44: =INDEX($F44:$AG44,1,MATCH(AK$7,$F$7:$AG$7,1)) -> 0 | AL44: =INDEX($F44:$AG44,1,MATCH(AL$7,$F$7:$AG$7,1)) -> 125 | AM44: =INDEX($F44:$AG44,1,MATCH(AM$7,$F$7:$AG$7,1)) -> 225 | AN44: =INDEX($F44:$AG44,1,MATCH(AN$7,$F$7:$AG$7,1)) -> 650 | AO44: =INDEX($F44:$AG44,1,MATCH(AO$7,$F$7:$AG$7,1)) -> 950
A45: Independence MO (Eastgate) - high | B45: MW | C45: Capacity | D45: Capacity file | F45: 0 | G45: 0 | H45: 0 | I45: 0 | J45: 0 | K45: 0 | L45: 0 | M45: 0 | N45: 0 | O45: 0 | P45: 0 | Q45: 0 | R45: 0 | S45: 0 | T45: 100 | U45: 200 | V45: 200 | W45: 250 | X45: 250 | Y45: 250 | Z45: 250 | AA45: 600 | AB45: 600 | AC45: 800 | AD45: 800 | AE45: 800 | AF45: 800 | AG45: 1200 | AI45: =INDEX($F45:$AG45,1,MATCH(AI$7,$F$7:$AG$7,1)) -> 0 | AJ45: =INDEX($F45:$AG45,1,MATCH(AJ$7,$F$7:$AG$7,1)) -> 0 | AK45: =INDEX($F45:$AG45,1,MATCH(AK$7,$F$7:$AG$7,1)) -> 0 | AL45: =INDEX($F45:$AG45,1,MATCH(AL$7,$F$7:$AG$7,1)) -> 200 | AM45: =INDEX($F45:$AG45,1,MATCH(AM$7,$F$7:$AG$7,1)) -> 250 | AN45: =INDEX($F45:$AG45,1,MATCH(AN$7,$F$7:$AG$7,1)) -> 800 | AO45: =INDEX($F45:$AG45,1,MATCH(AO$7,$F$7:$AG$7,1)) -> 1200
A46: Butler Twp PA (Highridge) - low | B46: MW | C46: Capacity | D46: Capacity file | F46: 0 | G46: 0 | H46: 0 | I46: 0 | J46: 0 | K46: 0 | L46: 0 | M46: 0 | N46: 0 | O46: 0 | P46: 0 | Q46: 0 | R46: 0 | S46: 0 | T46: 0 | U46: 0 | V46: 0 | W46: 0 | X46: 0 | Y46: 130 | Z46: 130 | AA46: 260 | AB46: 260 | AC46: 400 | AD46: 400 | AE46: 400 | AF46: 400 | AG46: 660 | AI46: =INDEX($F46:$AG46,1,MATCH(AI$7,$F$7:$AG$7,1)) -> 0 | AJ46: =INDEX($F46:$AG46,1,MATCH(AJ$7,$F$7:$AG$7,1)) -> 0 | AK46: =INDEX($F46:$AG46,1,MATCH(AK$7,$F$7:$AG$7,1)) -> 0 | AL46: =INDEX($F46:$AG46,1,MATCH(AL$7,$F$7:$AG$7,1)) -> 0 | AM46: =INDEX($F46:$AG46,1,MATCH(AM$7,$F$7:$AG$7,1)) -> 130 | AN46: =INDEX($F46:$AG46,1,MATCH(AN$7,$F$7:$AG$7,1)) -> 400 | AO46: =INDEX($F46:$AG46,1,MATCH(AO$7,$F$7:$AG$7,1)) -> 660
A47: Butler Twp PA (Highridge) - base | B47: MW | C47: Capacity | D47: Capacity file | F47: 0 | G47: 0 | H47: 0 | I47: 0 | J47: 0 | K47: 0 | L47: 0 | M47: 0 | N47: 0 | O47: 0 | P47: 0 | Q47: 0 | R47: 0 | S47: 0 | T47: 0 | U47: 65 | V47: 130 | W47: 130 | X47: 130 | Y47: 265 | Z47: 265 | AA47: 460 | AB47: 460 | AC47: 700 | AD47: 700 | AE47: 700 | AF47: 700 | AG47: 930 | AI47: =INDEX($F47:$AG47,1,MATCH(AI$7,$F$7:$AG$7,1)) -> 0 | AJ47: =INDEX($F47:$AG47,1,MATCH(AJ$7,$F$7:$AG$7,1)) -> 0 | AK47: =INDEX($F47:$AG47,1,MATCH(AK$7,$F$7:$AG$7,1)) -> 0 | AL47: =INDEX($F47:$AG47,1,MATCH(AL$7,$F$7:$AG$7,1)) -> 65 | AM47: =INDEX($F47:$AG47,1,MATCH(AM$7,$F$7:$AG$7,1)) -> 265 | AN47: =INDEX($F47:$AG47,1,MATCH(AN$7,$F$7:$AG$7,1)) -> 700 | AO47: =INDEX($F47:$AG47,1,MATCH(AO$7,$F$7:$AG$7,1)) -> 930
A48: Butler Twp PA (Highridge) - high | B48: MW | C48: Capacity | D48: Capacity file | F48: 0 | G48: 0 | H48: 0 | I48: 0 | J48: 0 | K48: 0 | L48: 0 | M48: 0 | N48: 0 | O48: 0 | P48: 0 | Q48: 0 | R48: 0 | S48: 0 | T48: 0 | U48: 130 | V48: 260 | W48: 260 | X48: 260 | Y48: 400 | Z48: 400 | AA48: 660 | AB48: 660 | AC48: 1000 | AD48: 1000 | AE48: 1000 | AF48: 1000 | AG48: 1200 | AI48: =INDEX($F48:$AG48,1,MATCH(AI$7,$F$7:$AG$7,1)) -> 0 | AJ48: =INDEX($F48:$AG48,1,MATCH(AJ$7,$F$7:$AG$7,1)) -> 0 | AK48: =INDEX($F48:$AG48,1,MATCH(AK$7,$F$7:$AG$7,1)) -> 0 | AL48: =INDEX($F48:$AG48,1,MATCH(AL$7,$F$7:$AG$7,1)) -> 130 | AM48: =INDEX($F48:$AG48,1,MATCH(AM$7,$F$7:$AG$7,1)) -> 400 | AN48: =INDEX($F48:$AG48,1,MATCH(AN$7,$F$7:$AG$7,1)) -> 1000 | AO48: =INDEX($F48:$AG48,1,MATCH(AO$7,$F$7:$AG$7,1)) -> 1200
A49: Birmingham AL (BHM01, Oxmoor) - low | B49: MW | C49: Capacity | D49: Capacity file | F49: 0 | G49: 0 | H49: 0 | I49: 0 | J49: 0 | K49: 0 | L49: 0 | M49: 0 | N49: 0 | O49: 0 | P49: 0 | Q49: 0 | R49: 0 | S49: 0 | T49: 25 | U49: 50 | V49: 50 | W49: 100 | X49: 100 | Y49: 200 | Z49: 200 | AA49: 200 | AB49: 200 | AC49: 300 | AD49: 300 | AE49: 300 | AF49: 300 | AG49: 300 | AI49: =INDEX($F49:$AG49,1,MATCH(AI$7,$F$7:$AG$7,1)) -> 0 | AJ49: =INDEX($F49:$AG49,1,MATCH(AJ$7,$F$7:$AG$7,1)) -> 0 | AK49: =INDEX($F49:$AG49,1,MATCH(AK$7,$F$7:$AG$7,1)) -> 0 | AL49: =INDEX($F49:$AG49,1,MATCH(AL$7,$F$7:$AG$7,1)) -> 50 | AM49: =INDEX($F49:$AG49,1,MATCH(AM$7,$F$7:$AG$7,1)) -> 200 | AN49: =INDEX($F49:$AG49,1,MATCH(AN$7,$F$7:$AG$7,1)) -> 300 | AO49: =INDEX($F49:$AG49,1,MATCH(AO$7,$F$7:$AG$7,1)) -> 300
A50: Birmingham AL (BHM01, Oxmoor) - base | B50: MW | C50: Capacity | D50: Capacity file | F50: 0 | G50: 0 | H50: 0 | I50: 0 | J50: 0 | K50: 0 | L50: 0 | M50: 0 | N50: 0 | O50: 0 | P50: 0 | Q50: 0 | R50: 12.5 | S50: 25 | T50: 50 | U50: 75 | V50: 75 | W50: 150 | X50: 150 | Y50: 250 | Z50: 250 | AA50: 250 | AB50: 250 | AC50: 300 | AD50: 300 | AE50: 300 | AF50: 300 | AG50: 300 | AI50: =INDEX($F50:$AG50,1,MATCH(AI$7,$F$7:$AG$7,1)) -> 0 | AJ50: =INDEX($F50:$AG50,1,MATCH(AJ$7,$F$7:$AG$7,1)) -> 0 | AK50: =INDEX($F50:$AG50,1,MATCH(AK$7,$F$7:$AG$7,1)) -> 0 | AL50: =INDEX($F50:$AG50,1,MATCH(AL$7,$F$7:$AG$7,1)) -> 75 | AM50: =INDEX($F50:$AG50,1,MATCH(AM$7,$F$7:$AG$7,1)) -> 250 | AN50: =INDEX($F50:$AG50,1,MATCH(AN$7,$F$7:$AG$7,1)) -> 300 | AO50: =INDEX($F50:$AG50,1,MATCH(AO$7,$F$7:$AG$7,1)) -> 300
A51: Birmingham AL (BHM01, Oxmoor) - high | B51: MW | C51: Capacity | D51: Capacity file | F51: 0 | G51: 0 | H51: 0 | I51: 0 | J51: 0 | K51: 0 | L51: 0 | M51: 0 | N51: 0 | O51: 0 | P51: 0 | Q51: 0 | R51: 25 | S51: 50 | T51: 75 | U51: 100 | V51: 100 | W51: 200 | X51: 200 | Y51: 300 | Z51: 300 | AA51: 300 | AB51: 300 | AC51: 300 | AD51: 300 | AE51: 300 | AF51: 300 | AG51: 300 | AI51: =INDEX($F51:$AG51,1,MATCH(AI$7,$F$7:$AG$7,1)) -> 0 | AJ51: =INDEX($F51:$AG51,1,MATCH(AJ$7,$F$7:$AG$7,1)) -> 0 | AK51: =INDEX($F51:$AG51,1,MATCH(AK$7,$F$7:$AG$7,1)) -> 0 | AL51: =INDEX($F51:$AG51,1,MATCH(AL$7,$F$7:$AG$7,1)) -> 100 | AM51: =INDEX($F51:$AG51,1,MATCH(AM$7,$F$7:$AG$7,1)) -> 300 | AN51: =INDEX($F51:$AG51,1,MATCH(AN$7,$F$7:$AG$7,1)) -> 300 | AO51: =INDEX($F51:$AG51,1,MATCH(AO$7,$F$7:$AG$7,1)) -> 300
... A78: Harlow UK (Kao Data KLON-02/03) - high | B78: MW | C78: Capacity | D78: Capacity file | F78: 0 | G78: 0 | H78: 0 | I78: 0 | J78: 0 | K78: 0 | L78: 0 | M78: 0 | N78: 0 | O78: 0 | P78: 0 | Q78: 4.4 | R78: 22 | S78: 22 | T78: 22 | U78: 22 | V78: 22 | W78: 22 | X78: 22 | Y78: 22 | Z78: 22 | AA78: 22 | AB78: 22 | AC78: 22 | AD78: 22 | AE78: 22 | AF78: 22 | AG78: 22 | AI78: =INDEX($F78:$AG78,1,MATCH(AI$7,$F$7:$AG$7,1)) -> 0 | AJ78: =INDEX($F78:$AG78,1,MATCH(AJ$7,$F$7:$AG$7,1)) -> 0 | AK78: =INDEX($F78:$AG78,1,MATCH(AK$7,$F$7:$AG$7,1)) -> 4.4 | AL78: =INDEX($F78:$AG78,1,MATCH(AL$7,$F$7:$AG$7,1)) -> 22 | AM78: =INDEX($F78:$AG78,1,MATCH(AM$7,$F$7:$AG$7,1)) -> 22 | AN78: =INDEX($F78:$AG78,1,MATCH(AN$7,$F$7:$AG$7,1)) -> 22 | AO78: =INDEX($F78:$AG78,1,MATCH(AO$7,$F$7:$AG$7,1)) -> 22
A79: UK 3rd new deployment (unnamed) - low | B79: MW | C79: Capacity | D79: Capacity file | AI79: =INDEX($F79:$AG79,1,MATCH(AI$7,$F$7:$AG$7,1)) -> 0 | AJ79: =INDEX($F79:$AG79,1,MATCH(AJ$7,$F$7:$AG$7,1)) -> 0 | AK79: =INDEX($F79:$AG79,1,MATCH(AK$7,$F$7:$AG$7,1)) -> 0 | AL79: =INDEX($F79:$AG79,1,MATCH(AL$7,$F$7:$AG$7,1)) -> 0 | AM79: =INDEX($F79:$AG79,1,MATCH(AM$7,$F$7:$AG$7,1)) -> 0 | AN79: =INDEX($F79:$AG79,1,MATCH(AN$7,$F$7:$AG$7,1)) -> 0 | AO79: =INDEX($F79:$AG79,1,MATCH(AO$7,$F$7:$AG$7,1)) -> 0
A80: UK 3rd new deployment (unnamed) - base | B80: MW | C80: Capacity | D80: Capacity file | AI80: =INDEX($F80:$AG80,1,MATCH(AI$7,$F$7:$AG$7,1)) -> 0 | AJ80: =INDEX($F80:$AG80,1,MATCH(AJ$7,$F$7:$AG$7,1)) -> 0 | AK80: =INDEX($F80:$AG80,1,MATCH(AK$7,$F$7:$AG$7,1)) -> 0 | AL80: =INDEX($F80:$AG80,1,MATCH(AL$7,$F$7:$AG$7,1)) -> 0 | AM80: =INDEX($F80:$AG80,1,MATCH(AM$7,$F$7:$AG$7,1)) -> 0 | AN80: =INDEX($F80:$AG80,1,MATCH(AN$7,$F$7:$AG$7,1)) -> 0 | AO80: =INDEX($F80:$AG80,1,MATCH(AO$7,$F$7:$AG$7,1)) -> 0
A81: UK 3rd new deployment (unnamed) - high | B81: MW | C81: Capacity | D81: Capacity file | AI81: =INDEX($F81:$AG81,1,MATCH(AI$7,$F$7:$AG$7,1)) -> 0 | AJ81: =INDEX($F81:$AG81,1,MATCH(AJ$7,$F$7:$AG$7,1)) -> 0 | AK81: =INDEX($F81:$AG81,1,MATCH(AK$7,$F$7:$AG$7,1)) -> 0 | AL81: =INDEX($F81:$AG81,1,MATCH(AL$7,$F$7:$AG$7,1)) -> 0 | AM81: =INDEX($F81:$AG81,1,MATCH(AM$7,$F$7:$AG$7,1)) -> 0 | AN81: =INDEX($F81:$AG81,1,MATCH(AN$7,$F$7:$AG$7,1)) -> 0 | AO81: =INDEX($F81:$AG81,1,MATCH(AO$7,$F$7:$AG$7,1)) -> 0
A82: Modi'in IL (Mega Or) - low | B82: MW | C82: Capacity | D82: Capacity file | F82: 0 | G82: 0 | H82: 0 | I82: 0 | J82: 0 | K82: 0 | L82: 0 | M82: 8 | N82: 8 | O82: 8 | P82: 8 | Q82: 8 | R82: 8 | S82: 8 | T82: 8 | U82: 8 | V82: 8 | W82: 8 | X82: 8 | Y82: 8 | Z82: 8 | AA82: 8 | AB82: 8 | AC82: 8 | AD82: 8 | AE82: 8 | AF82: 8 | AG82: 8 | AI82: =INDEX($F82:$AG82,1,MATCH(AI$7,$F$7:$AG$7,1)) -> 0 | AJ82: =INDEX($F82:$AG82,1,MATCH(AJ$7,$F$7:$AG$7,1)) -> 8 | AK82: =INDEX($F82:$AG82,1,MATCH(AK$7,$F$7:$AG$7,1)) -> 8 | AL82: =INDEX($F82:$AG82,1,MATCH(AL$7,$F$7:$AG$7,1)) -> 8 | AM82: =INDEX($F82:$AG82,1,MATCH(AM$7,$F$7:$AG$7,1)) -> 8 | AN82: =INDEX($F82:$AG82,1,MATCH(AN$7,$F$7:$AG$7,1)) -> 8 | AO82: =INDEX($F82:$AG82,1,MATCH(AO$7,$F$7:$AG$7,1)) -> 8
A83: Modi'in IL (Mega Or) - base | B83: MW | C83: Capacity | D83: Capacity file | F83: 0 | G83: 0 | H83: 0 | I83: 0 | J83: 0 | K83: 0 | L83: 0 | M83: 8 | N83: 8 | O83: 8 | P83: 8 | Q83: 8 | R83: 8 | S83: 8 | T83: 8 | U83: 8 | V83: 8 | W83: 8 | X83: 8 | Y83: 8 | Z83: 8 | AA83: 8 | AB83: 8 | AC83: 8 | AD83: 8 | AE83: 8 | AF83: 8 | AG83: 8 | AI83: =INDEX($F83:$AG83,1,MATCH(AI$7,$F$7:$AG$7,1)) -> 0 | AJ83: =INDEX($F83:$AG83,1,MATCH(AJ$7,$F$7:$AG$7,1)) -> 8 | AK83: =INDEX($F83:$AG83,1,MATCH(AK$7,$F$7:$AG$7,1)) -> 8 | AL83: =INDEX($F83:$AG83,1,MATCH(AL$7,$F$7:$AG$7,1)) -> 8 | AM83: =INDEX($F83:$AG83,1,MATCH(AM$7,$F$7:$AG$7,1)) -> 8 | AN83: =INDEX($F83:$AG83,1,MATCH(AN$7,$F$7:$AG$7,1)) -> 8 | AO83: =INDEX($F83:$AG83,1,MATCH(AO$7,$F$7:$AG$7,1)) -> 8
A84: Modi'in IL (Mega Or) - high | B84: MW | C84: Capacity | D84: Capacity file | F84: 0 | G84: 0 | H84: 0 | I84: 0 | J84: 0 | K84: 0 | L84: 0 | M84: 8 | N84: 8 | O84: 8 | P84: 8 | Q84: 8 | R84: 8 | S84: 8 | T84: 8 | U84: 8 | V84: 8 | W84: 8 | X84: 8 | Y84: 8 | Z84: 8 | AA84: 8 | AB84: 8 | AC84: 8 | AD84: 8 | AE84: 8 | AF84: 8 | AG84: 8 | AI84: =INDEX($F84:$AG84,1,MATCH(AI$7,$F$7:$AG$7,1)) -> 0 | AJ84: =INDEX($F84:$AG84,1,MATCH(AJ$7,$F$7:$AG$7,1)) -> 8 | AK84: =INDEX($F84:$AG84,1,MATCH(AK$7,$F$7:$AG$7,1)) -> 8 | AL84: =INDEX($F84:$AG84,1,MATCH(AL$7,$F$7:$AG$7,1)) -> 8 | AM84: =INDEX($F84:$AG84,1,MATCH(AM$7,$F$7:$AG$7,1)) -> 8 | AN84: =INDEX($F84:$AG84,1,MATCH(AN$7,$F$7:$AG$7,1)) -> 8 | AO84: =INDEX($F84:$AG84,1,MATCH(AO$7,$F$7:$AG$7,1)) -> 8
A85: Masmiyya IL (Mega DC) - low | B85: MW | C85: Capacity | D85: Capacity file | F85: 0 | G85: 0 | H85: 0 | I85: 0 | J85: 0 | K85: 0 | L85: 0 | M85: 0 | N85: 0 | O85: 0 | P85: 0 | Q85: 0 | R85: 11 | S85: 22 | T85: 22 | U85: 22 | V85: 22 | W85: 22 | X85: 22 | Y85: 22 | Z85: 22 | AA85: 22 | AB85: 22 | AC85: 22 | AD85: 22 | AE85: 22 | AF85: 22 | AG85: 22 | AI85: =INDEX($F85:$AG85,1,MATCH(AI$7,$F$7:$AG$7,1)) -> 0 | AJ85: =INDEX($F85:$AG85,1,MATCH(AJ$7,$F$7:$AG$7,1)) -> 0 | AK85: =INDEX($F85:$AG85,1,MATCH(AK$7,$F$7:$AG$7,1)) -> 0 | AL85: =INDEX($F85:$AG85,1,MATCH(AL$7,$F$7:$AG$7,1)) -> 22 | AM85: =INDEX($F85:$AG85,1,MATCH(AM$7,$F$7:$AG$7,1)) -> 22 | AN85: =INDEX($F85:$AG85,1,MATCH(AN$7,$F$7:$AG$7,1)) -> 22 | AO85: =INDEX($F85:$AG85,1,MATCH(AO$7,$F$7:$AG$7,1)) -> 22
A86: Masmiyya IL (Mega DC) - base | B86: MW | C86: Capacity | D86: Capacity file | F86: 0 | G86: 0 | H86: 0 | I86: 0 | J86: 0 | K86: 0 | L86: 0 | M86: 0 | N86: 0 | O86: 0 | P86: 0 | Q86: 11 | R86: 16.5 | S86: 22 | T86: 22 | U86: 22 | V86: 22 | W86: 22 | X86: 22 | Y86: 22 | Z86: 22 | AA86: 22 | AB86: 22 | AC86: 22 | AD86: 22 | AE86: 22 | AF86: 22 | AG86: 22 | AI86: =INDEX($F86:$AG86,1,MATCH(AI$7,$F$7:$AG$7,1)) -> 0 | AJ86: =INDEX($F86:$AG86,1,MATCH(AJ$7,$F$7:$AG$7,1)) -> 0 | AK86: =INDEX($F86:$AG86,1,MATCH(AK$7,$F$7:$AG$7,1)) -> 11 | AL86: =INDEX($F86:$AG86,1,MATCH(AL$7,$F$7:$AG$7,1)) -> 22 | AM86: =INDEX($F86:$AG86,1,MATCH(AM$7,$F$7:$AG$7,1)) -> 22 | AN86: =INDEX($F86:$AG86,1,MATCH(AN$7,$F$7:$AG$7,1)) -> 22 | AO86: =INDEX($F86:$AG86,1,MATCH(AO$7,$F$7:$AG$7,1)) -> 22
A87: Masmiyya IL (Mega DC) - high | B87: MW | C87: Capacity | D87: Capacity file | F87: 0 | G87: 0 | H87: 0 | I87: 0 | J87: 0 | K87: 0 | L87: 0 | M87: 0 | N87: 0 | O87: 0 | P87: 0 | Q87: 22 | R87: 22 | S87: 22 | T87: 22 | U87: 22 | V87: 22 | W87: 22 | X87: 22 | Y87: 22 | Z87: 22 | AA87: 22 | AB87: 22 | AC87: 22 | AD87: 22 | AE87: 22 | AF87: 22 | AG87: 22 | AI87: =INDEX($F87:$AG87,1,MATCH(AI$7,$F$7:$AG$7,1)) -> 0 | AJ87: =INDEX($F87:$AG87,1,MATCH(AJ$7,$F$7:$AG$7,1)) -> 0 | AK87: =INDEX($F87:$AG87,1,MATCH(AK$7,$F$7:$AG$7,1)) -> 22 | AL87: =INDEX($F87:$AG87,1,MATCH(AL$7,$F$7:$AG$7,1)) -> 22 | AM87: =INDEX($F87:$AG87,1,MATCH(AM$7,$F$7:$AG$7,1)) -> 22 | AN87: =INDEX($F87:$AG87,1,MATCH(AN$7,$F$7:$AG$7,1)) -> 22 | AO87: =INDEX($F87:$AG87,1,MATCH(AO$7,$F$7:$AG$7,1)) -> 22
A88: Beit Shemesh IL (Mega DC) - low | B88: MW | C88: Capacity | D88: Capacity file | F88: 0 | G88: 0 | H88: 0 | I88: 0 | J88: 0 | K88: 0 | L88: 0 | M88: 0 | N88: 0 | O88: 0 | P88: 0 | Q88: 0 | R88: 20 | S88: 39 | T88: 58 | U88: 58 | V88: 58 | W88: 58 | X88: 58 | Y88: 58 | Z88: 58 | AA88: 58 | AB88: 58 | AC88: 58 | AD88: 58 | AE88: 58 | AF88: 58 | AG88: 58 | AI88: =INDEX($F88:$AG88,1,MATCH(AI$7,$F$7:$AG$7,1)) -> 0 | AJ88: =INDEX($F88:$AG88,1,MATCH(AJ$7,$F$7:$AG$7,1)) -> 0 | AK88: =INDEX($F88:$AG88,1,MATCH(AK$7,$F$7:$AG$7,1)) -> 0 | AL88: =INDEX($F88:$AG88,1,MATCH(AL$7,$F$7:$AG$7,1)) -> 58 | AM88: =INDEX($F88:$AG88,1,MATCH(AM$7,$F$7:$AG$7,1)) -> 58 | AN88: =INDEX($F88:$AG88,1,MATCH(AN$7,$F$7:$AG$7,1)) -> 58 | AO88: =INDEX($F88:$AG88,1,MATCH(AO$7,$F$7:$AG$7,1)) -> 58
A89: Beit Shemesh IL (Mega DC) - base | B89: MW | C89: Capacity | D89: Capacity file | F89: 0 | G89: 0 | H89: 0 | I89: 0 | J89: 0 | K89: 0 | L89: 0 | M89: 0 | N89: 0 | O89: 0 | P89: 0 | Q89: 19.5 | R89: 39 | S89: 48.5 | T89: 58 | U89: 58 | V89: 58 | W89: 58 | X89: 58 | Y89: 58 | Z89: 58 | AA89: 58 | AB89: 58 | AC89: 58 | AD89: 58 | AE89: 58 | AF89: 58 | AG89: 58 | AI89: =INDEX($F89:$AG89,1,MATCH(AI$7,$F$7:$AG$7,1)) -> 0 | AJ89: =INDEX($F89:$AG89,1,MATCH(AJ$7,$F$7:$AG$7,1)) -> 0 | AK89: =INDEX($F89:$AG89,1,MATCH(AK$7,$F$7:$AG$7,1)) -> 19.5 | AL89: =INDEX($F89:$AG89,1,MATCH(AL$7,$F$7:$AG$7,1)) -> 58 | AM89: =INDEX($F89:$AG89,1,MATCH(AM$7,$F$7:$AG$7,1)) -> 58 | AN89: =INDEX($F89:$AG89,1,MATCH(AN$7,$F$7:$AG$7,1)) -> 58 | AO89: =INDEX($F89:$AG89,1,MATCH(AO$7,$F$7:$AG$7,1)) -> 58
A90: Beit Shemesh IL (Mega DC) - high | B90: MW | C90: Capacity | D90: Capacity file | F90: 0 | G90: 0 | H90: 0 | I90: 0 | J90: 0 | K90: 0 | L90: 0 | M90: 0 | N90: 0 | O90: 0 | P90: 0 | Q90: 39 | R90: 58 | S90: 58 | T90: 58 | U90: 58 | V90: 58 | W90: 58 | X90: 58 | Y90: 58 | Z90: 58 | AA90: 58 | AB90: 58 | AC90: 58 | AD90: 58 | AE90: 58 | AF90: 58 | AG90: 58 | AI90: =INDEX($F90:$AG90,1,MATCH(AI$7,$F$7:$AG$7,1)) -> 0 | AJ90: =INDEX($F90:$AG90,1,MATCH(AJ$7,$F$7:$AG$7,1)) -> 0 | AK90: =INDEX($F90:$AG90,1,MATCH(AK$7,$F$7:$AG$7,1)) -> 39 | AL90: =INDEX($F90:$AG90,1,MATCH(AL$7,$F$7:$AG$7,1)) -> 58 | AM90: =INDEX($F90:$AG90,1,MATCH(AM$7,$F$7:$AG$7,1)) -> 58 | AN90: =INDEX($F90:$AG90,1,MATCH(AN$7,$F$7:$AG$7,1)) -> 58 | AO90: =INDEX($F90:$AG90,1,MATCH(AO$7,$F$7:$AG$7,1)) -> 58
A91: Madrid-Getafe ES (Merlin Edged) - low | B91: MW | C91: Capacity | D91: Capacity file | F91: 0 | G91: 0 | H91: 0 | I91: 0 | J91: 0 | K91: 0 | L91: 0 | M91: 0 | N91: 0 | O91: 0 | P91: 6 | Q91: 9 | R91: 18 | S91: 18 | T91: 18 | U91: 18 | V91: 18 | W91: 18 | X91: 18 | Y91: 18 | Z91: 18 | AA91: 18 | AB91: 18 | AC91: 18 | AD91: 18 | AE91: 18 | AF91: 18 | AG91: 18 | AI91: =INDEX($F91:$AG91,1,MATCH(AI$7,$F$7:$AG$7,1)) -> 0 | AJ91: =INDEX($F91:$AG91,1,MATCH(AJ$7,$F$7:$AG$7,1)) -> 0 | AK91: =INDEX($F91:$AG91,1,MATCH(AK$7,$F$7:$AG$7,1)) -> 9 | AL91: =INDEX($F91:$AG91,1,MATCH(AL$7,$F$7:$AG$7,1)) -> 18 | AM91: =INDEX($F91:$AG91,1,MATCH(AM$7,$F$7:$AG$7,1)) -> 18 | AN91: =INDEX($F91:$AG91,1,MATCH(AN$7,$F$7:$AG$7,1)) -> 18 | AO91: =INDEX($F91:$AG91,1,MATCH(AO$7,$F$7:$AG$7,1)) -> 18
A92: Madrid-Getafe ES (Merlin Edged) - base | B92: MW | C92: Capacity | D92: Capacity file | F92: 0 | G92: 0 | H92: 0 | I92: 0 | J92: 0 | K92: 0 | L92: 0 | M92: 0 | N92: 0 | O92: 0 | P92: 7.5 | Q92: 13.5 | R92: 18 | S92: 18 | T92: 18 | U92: 18 | V92: 18 | W92: 18 | X92: 18 | Y92: 18 | Z92: 18 | AA92: 18 | AB92: 18 | AC92: 18 | AD92: 18 | AE92: 18 | AF92: 18 | AG92: 18 | AI92: =INDEX($F92:$AG92,1,MATCH(AI$7,$F$7:$AG$7,1)) -> 0 | AJ92: =INDEX($F92:$AG92,1,MATCH(AJ$7,$F$7:$AG$7,1)) -> 0 | AK92: =INDEX($F92:$AG92,1,MATCH(AK$7,$F$7:$AG$7,1)) -> 13.5 | AL92: =INDEX($F92:$AG92,1,MATCH(AL$7,$F$7:$AG$7,1)) -> 18 | AM92: =INDEX($F92:$AG92,1,MATCH(AM$7,$F$7:$AG$7,1)) -> 18 | AN92: =INDEX($F92:$AG92,1,MATCH(AN$7,$F$7:$AG$7,1)) -> 18 | AO92: =INDEX($F92:$AG92,1,MATCH(AO$7,$F$7:$AG$7,1)) -> 18
A93: Madrid-Getafe ES (Merlin Edged) - high | B93: MW | C93: Capacity | D93: Capacity file | F93: 0 | G93: 0 | H93: 0 | I93: 0 | J93: 0 | K93: 0 | L93: 0 | M93: 0 | N93: 0 | O93: 0 | P93: 9 | Q93: 18 | R93: 18 | S93: 18 | T93: 18 | U93: 18 | V93: 18 | W93: 18 | X93: 18 | Y93: 18 | Z93: 18 | AA93: 18 | AB93: 18 | AC93: 18 | AD93: 18 | AE93: 18 | AF93: 18 | AG93: 18 | AI93: =INDEX($F93:$AG93,1,MATCH(AI$7,$F$7:$AG$7,1)) -> 0 | AJ93: =INDEX($F93:$AG93,1,MATCH(AJ$7,$F$7:$AG$7,1)) -> 0 | AK93: =INDEX($F93:$AG93,1,MATCH(AK$7,$F$7:$AG$7,1)) -> 18 | AL93: =INDEX($F93:$AG93,1,MATCH(AL$7,$F$7:$AG$7,1)) -> 18 | AM93: =INDEX($F93:$AG93,1,MATCH(AM$7,$F$7:$AG$7,1)) -> 18 | AN93: =INDEX($F93:$AG93,1,MATCH(AN$7,$F$7:$AG$7,1)) -> 18 | AO93: =INDEX($F93:$AG93,1,MATCH(AO$7,$F$7:$AG$7,1)) -> 18
... A96: Tallinn EE (Greenergy Huuru) - high | B96: MW | C96: Capacity | D96: Capacity file | F96: 0 | G96: 0 | H96: 0 | I96: 0 | J96: 0 | K96: 0 | L96: 0 | M96: 0 | N96: 0 | O96: 0 | P96: 0 | Q96: 22 | R96: 22 | S96: 22 | T96: 22 | U96: 22 | V96: 22 | W96: 22 | X96: 22 | Y96: 22 | Z96: 22 | AA96: 22 | AB96: 22 | AC96: 22 | AD96: 22 | AE96: 22 | AF96: 22 | AG96: 22 | AI96: =INDEX($F96:$AG96,1,MATCH(AI$7,$F$7:$AG$7,1)) -> 0 | AJ96: =INDEX($F96:$AG96,1,MATCH(AJ$7,$F$7:$AG$7,1)) -> 0 | AK96: =INDEX($F96:$AG96,1,MATCH(AK$7,$F$7:$AG$7,1)) -> 22 | AL96: =INDEX($F96:$AG96,1,MATCH(AL$7,$F$7:$AG$7,1)) -> 22 | AM96: =INDEX($F96:$AG96,1,MATCH(AM$7,$F$7:$AG$7,1)) -> 22 | AN96: =INDEX($F96:$AG96,1,MATCH(AN$7,$F$7:$AG$7,1)) -> 22 | AO96: =INDEX($F96:$AG96,1,MATCH(AO$7,$F$7:$AG$7,1)) -> 22
A97: Minnesota (RMA roles, likely colo live) - low | B97: MW | C97: Capacity | D97: PLACEHOLDER (Inputs, due Tue Oct 6) | F97: =IF(F$5>=12,Inputs!$E$168,0) -> 0 | G97: =IF(G$5>=12,Inputs!$E$168,0) -> 0 | H97: =IF(H$5>=12,Inputs!$E$168,0) -> 0 | I97: =IF(I$5>=12,Inputs!$E$168,0) -> 0 | J97: =IF(J$5>=12,Inputs!$E$168,0) -> 0 | K97: =IF(K$5>=12,Inputs!$E$168,0) -> 0 | L97: =IF(L$5>=12,Inputs!$E$168,0) -> 0 | M97: =IF(M$5>=12,Inputs!$E$168,0) -> 0 | ... AG97: =IF(AG$5>=12,Inputs!$E$168,0) -> 0 | AI97: =INDEX($F97:$AG97,1,MATCH(AI$7,$F$7:$AG$7,1)) -> 0 | AJ97: =INDEX($F97:$AG97,1,MATCH(AJ$7,$F$7:$AG$7,1)) -> 0 | AK97: =INDEX($F97:$AG97,1,MATCH(AK$7,$F$7:$AG$7,1)) -> 0 | AL97: =INDEX($F97:$AG97,1,MATCH(AL$7,$F$7:$AG$7,1)) -> 0 | AM97: =INDEX($F97:$AG97,1,MATCH(AM$7,$F$7:$AG$7,1)) -> 0 | AN97: =INDEX($F97:$AG97,1,MATCH(AN$7,$F$7:$AG$7,1)) -> 0 | AO97: =INDEX($F97:$AG97,1,MATCH(AO$7,$F$7:$AG$7,1)) -> 0
A98: Minnesota (RMA roles, likely colo live) - base | B98: MW | C98: Capacity | D98: PLACEHOLDER (Inputs, due Tue Oct 6) | F98: =IF(F$5>=12,Inputs!$D$168,0) -> 0 | G98: =IF(G$5>=12,Inputs!$D$168,0) -> 0 | H98: =IF(H$5>=12,Inputs!$D$168,0) -> 0 | I98: =IF(I$5>=12,Inputs!$D$168,0) -> 0 | J98: =IF(J$5>=12,Inputs!$D$168,0) -> 0 | K98: =IF(K$5>=12,Inputs!$D$168,0) -> 0 | L98: =IF(L$5>=12,Inputs!$D$168,0) -> 0 | M98: =IF(M$5>=12,Inputs!$D$168,0) -> 0 | ... AG98: =IF(AG$5>=12,Inputs!$D$168,0) -> 0 | AI98: =INDEX($F98:$AG98,1,MATCH(AI$7,$F$7:$AG$7,1)) -> 0 | AJ98: =INDEX($F98:$AG98,1,MATCH(AJ$7,$F$7:$AG$7,1)) -> 0 | AK98: =INDEX($F98:$AG98,1,MATCH(AK$7,$F$7:$AG$7,1)) -> 0 | AL98: =INDEX($F98:$AG98,1,MATCH(AL$7,$F$7:$AG$7,1)) -> 0 | AM98: =INDEX($F98:$AG98,1,MATCH(AM$7,$F$7:$AG$7,1)) -> 0 | AN98: =INDEX($F98:$AG98,1,MATCH(AN$7,$F$7:$AG$7,1)) -> 0 | AO98: =INDEX($F98:$AG98,1,MATCH(AO$7,$F$7:$AG$7,1)) -> 0
A99: Minnesota (RMA roles, likely colo live) - high | B99: MW | C99: Capacity | D99: PLACEHOLDER (Inputs, due Tue Oct 6) | F99: =IF(F$5>=12,Inputs!$C$168,0) -> 0 | G99: =IF(G$5>=12,Inputs!$C$168,0) -> 0 | H99: =IF(H$5>=12,Inputs!$C$168,0) -> 0 | I99: =IF(I$5>=12,Inputs!$C$168,0) -> 0 | J99: =IF(J$5>=12,Inputs!$C$168,0) -> 0 | K99: =IF(K$5>=12,Inputs!$C$168,0) -> 0 | L99: =IF(L$5>=12,Inputs!$C$168,0) -> 0 | M99: =IF(M$5>=12,Inputs!$C$168,0) -> 0 | ... AG99: =IF(AG$5>=12,Inputs!$C$168,0) -> 0 | AI99: =INDEX($F99:$AG99,1,MATCH(AI$7,$F$7:$AG$7,1)) -> 0 | AJ99: =INDEX($F99:$AG99,1,MATCH(AJ$7,$F$7:$AG$7,1)) -> 0 | AK99: =INDEX($F99:$AG99,1,MATCH(AK$7,$F$7:$AG$7,1)) -> 0 | AL99: =INDEX($F99:$AG99,1,MATCH(AL$7,$F$7:$AG$7,1)) -> 0 | AM99: =INDEX($F99:$AG99,1,MATCH(AM$7,$F$7:$AG$7,1)) -> 0 | AN99: =INDEX($F99:$AG99,1,MATCH(AN$7,$F$7:$AG$7,1)) -> 0 | AO99: =INDEX($F99:$AG99,1,MATCH(AO$7,$F$7:$AG$7,1)) -> 0
A100: Oklahoma (7 DC roles, live-looking) - low | B100: MW | C100: Capacity | D100: PLACEHOLDER (Inputs, due Tue Oct 6) | F100: =IF(F$5>=12,Inputs!$E$167,0) -> 0 | G100: =IF(G$5>=12,Inputs!$E$167,0) -> 0 | H100: =IF(H$5>=12,Inputs!$E$167,0) -> 0 | I100: =IF(I$5>=12,Inputs!$E$167,0) -> 0 | J100: =IF(J$5>=12,Inputs!$E$167,0) -> 0 | K100: =IF(K$5>=12,Inputs!$E$167,0) -> 0 | L100: =IF(L$5>=12,Inputs!$E$167,0) -> 0 | M100: =IF(M$5>=12,Inputs!$E$167,0) -> 0 | ... AG100: =IF(AG$5>=12,Inputs!$E$167,0) -> 0 | AI100: =INDEX($F100:$AG100,1,MATCH(AI$7,$F$7:$AG$7,1)) -> 0 | AJ100: =INDEX($F100:$AG100,1,MATCH(AJ$7,$F$7:$AG$7,1)) -> 0 | AK100: =INDEX($F100:$AG100,1,MATCH(AK$7,$F$7:$AG$7,1)) -> 0 | AL100: =INDEX($F100:$AG100,1,MATCH(AL$7,$F$7:$AG$7,1)) -> 0 | AM100: =INDEX($F100:$AG100,1,MATCH(AM$7,$F$7:$AG$7,1)) -> 0 | AN100: =INDEX($F100:$AG100,1,MATCH(AN$7,$F$7:$AG$7,1)) -> 0 | AO100: =INDEX($F100:$AG100,1,MATCH(AO$7,$F$7:$AG$7,1)) -> 0
A101: Oklahoma (7 DC roles, live-looking) - base | B101: MW | C101: Capacity | D101: PLACEHOLDER (Inputs, due Tue Oct 6) | F101: =IF(F$5>=12,Inputs!$D$167,0) -> 0 | G101: =IF(G$5>=12,Inputs!$D$167,0) -> 0 | H101: =IF(H$5>=12,Inputs!$D$167,0) -> 0 | I101: =IF(I$5>=12,Inputs!$D$167,0) -> 0 | J101: =IF(J$5>=12,Inputs!$D$167,0) -> 0 | K101: =IF(K$5>=12,Inputs!$D$167,0) -> 0 | L101: =IF(L$5>=12,Inputs!$D$167,0) -> 0 | M101: =IF(M$5>=12,Inputs!$D$167,0) -> 0 | ... AG101: =IF(AG$5>=12,Inputs!$D$167,0) -> 0 | AI101: =INDEX($F101:$AG101,1,MATCH(AI$7,$F$7:$AG$7,1)) -> 0 | AJ101: =INDEX($F101:$AG101,1,MATCH(AJ$7,$F$7:$AG$7,1)) -> 0 | AK101: =INDEX($F101:$AG101,1,MATCH(AK$7,$F$7:$AG$7,1)) -> 0 | AL101: =INDEX($F101:$AG101,1,MATCH(AL$7,$F$7:$AG$7,1)) -> 0 | AM101: =INDEX($F101:$AG101,1,MATCH(AM$7,$F$7:$AG$7,1)) -> 0 | AN101: =INDEX($F101:$AG101,1,MATCH(AN$7,$F$7:$AG$7,1)) -> 0 | AO101: =INDEX($F101:$AG101,1,MATCH(AO$7,$F$7:$AG$7,1)) -> 0
A102: Oklahoma (7 DC roles, live-looking) - high | B102: MW | C102: Capacity | D102: PLACEHOLDER (Inputs, due Tue Oct 6) | F102: =IF(F$5>=12,Inputs!$C$167,0) -> 0 | G102: =IF(G$5>=12,Inputs!$C$167,0) -> 0 | H102: =IF(H$5>=12,Inputs!$C$167,0) -> 0 | I102: =IF(I$5>=12,Inputs!$C$167,0) -> 0 | J102: =IF(J$5>=12,Inputs!$C$167,0) -> 0 | K102: =IF(K$5>=12,Inputs!$C$167,0) -> 0 | L102: =IF(L$5>=12,Inputs!$C$167,0) -> 0 | M102: =IF(M$5>=12,Inputs!$C$167,0) -> 0 | ... AG102: =IF(AG$5>=12,Inputs!$C$167,0) -> 0 | AI102: =INDEX($F102:$AG102,1,MATCH(AI$7,$F$7:$AG$7,1)) -> 0 | AJ102: =INDEX($F102:$AG102,1,MATCH(AJ$7,$F$7:$AG$7,1)) -> 0 | AK102: =INDEX($F102:$AG102,1,MATCH(AK$7,$F$7:$AG$7,1)) -> 0 | AL102: =INDEX($F102:$AG102,1,MATCH(AL$7,$F$7:$AG$7,1)) -> 0 | AM102: =INDEX($F102:$AG102,1,MATCH(AM$7,$F$7:$AG$7,1)) -> 0 | AN102: =INDEX($F102:$AG102,1,MATCH(AN$7,$F$7:$AG$7,1)) -> 0 | AO102: =INDEX($F102:$AG102,1,MATCH(AO$7,$F$7:$AG$7,1)) -> 0
A103: France 2nd colo (unnamed; possibly eu-west2) - low | B103: MW | C103: Capacity | D103: Capacity file | AI103: =INDEX($F103:$AG103,1,MATCH(AI$7,$F$7:$AG$7,1)) -> 0 | AJ103: =INDEX($F103:$AG103,1,MATCH(AJ$7,$F$7:$AG$7,1)) -> 0 | AK103: =INDEX($F103:$AG103,1,MATCH(AK$7,$F$7:$AG$7,1)) -> 0 | AL103: =INDEX($F103:$AG103,1,MATCH(AL$7,$F$7:$AG$7,1)) -> 0 | AM103: =INDEX($F103:$AG103,1,MATCH(AM$7,$F$7:$AG$7,1)) -> 0 | AN103: =INDEX($F103:$AG103,1,MATCH(AN$7,$F$7:$AG$7,1)) -> 0 | AO103: =INDEX($F103:$AG103,1,MATCH(AO$7,$F$7:$AG$7,1)) -> 0
A104: France 2nd colo (unnamed; possibly eu-west2) - base | B104: MW | C104: Capacity | D104: Capacity file | AI104: =INDEX($F104:$AG104,1,MATCH(AI$7,$F$7:$AG$7,1)) -> 0 | AJ104: =INDEX($F104:$AG104,1,MATCH(AJ$7,$F$7:$AG$7,1)) -> 0 | AK104: =INDEX($F104:$AG104,1,MATCH(AK$7,$F$7:$AG$7,1)) -> 0 | AL104: =INDEX($F104:$AG104,1,MATCH(AL$7,$F$7:$AG$7,1)) -> 0 | AM104: =INDEX($F104:$AG104,1,MATCH(AM$7,$F$7:$AG$7,1)) -> 0 | AN104: =INDEX($F104:$AG104,1,MATCH(AN$7,$F$7:$AG$7,1)) -> 0 | AO104: =INDEX($F104:$AG104,1,MATCH(AO$7,$F$7:$AG$7,1)) -> 0
A105: France 2nd colo (unnamed; possibly eu-west2) - high | B105: MW | C105: Capacity | D105: Capacity file | AI105: =INDEX($F105:$AG105,1,MATCH(AI$7,$F$7:$AG$7,1)) -> 0 | AJ105: =INDEX($F105:$AG105,1,MATCH(AJ$7,$F$7:$AG$7,1)) -> 0 | AK105: =INDEX($F105:$AG105,1,MATCH(AK$7,$F$7:$AG$7,1)) -> 0 | AL105: =INDEX($F105:$AG105,1,MATCH(AL$7,$F$7:$AG$7,1)) -> 0 | AM105: =INDEX($F105:$AG105,1,MATCH(AM$7,$F$7:$AG$7,1)) -> 0 | AN105: =INDEX($F105:$AG105,1,MATCH(AN$7,$F$7:$AG$7,1)) -> 0 | AO105: =INDEX($F105:$AG105,1,MATCH(AO$7,$F$7:$AG$7,1)) -> 0
A106: AIB CLT1 (South Carolina) - low | B106: MW | C106: Capacity | D106: Capacity file | F106: 0 | G106: 0 | H106: 0 | I106: 0 | J106: 0 | K106: 0 | L106: 0 | M106: 0 | N106: 0 | O106: 0 | P106: 0 | Q106: 0 | R106: 0 | S106: 0 | T106: 0 | U106: 0 | V106: 25 | W106: 25 | X106: 50 | Y106: 50 | Z106: 50 | AA106: 50 | AB106: 50 | AC106: 50 | AD106: 50 | AE106: 50 | AF106: 50 | AG106: 50 | AI106: =INDEX($F106:$AG106,1,MATCH(AI$7,$F$7:$AG$7,1)) -> 0 | AJ106: =INDEX($F106:$AG106,1,MATCH(AJ$7,$F$7:$AG$7,1)) -> 0 | AK106: =INDEX($F106:$AG106,1,MATCH(AK$7,$F$7:$AG$7,1)) -> 0 | AL106: =INDEX($F106:$AG106,1,MATCH(AL$7,$F$7:$AG$7,1)) -> 0 | AM106: =INDEX($F106:$AG106,1,MATCH(AM$7,$F$7:$AG$7,1)) -> 50 | AN106: =INDEX($F106:$AG106,1,MATCH(AN$7,$F$7:$AG$7,1)) -> 50 | AO106: =INDEX($F106:$AG106,1,MATCH(AO$7,$F$7:$AG$7,1)) -> 50
A107: AIB CLT1 (South Carolina) - base | B107: MW | C107: Capacity | D107: Capacity file | F107: 0 | G107: 0 | H107: 0 | I107: 0 | J107: 0 | K107: 0 | L107: 0 | M107: 0 | N107: 0 | O107: 0 | P107: 0 | Q107: 0 | R107: 0 | S107: 0 | T107: 12.5 | U107: 25 | V107: 37.5 | W107: 37.5 | X107: 50 | Y107: 50 | Z107: 50 | AA107: 50 | AB107: 50 | AC107: 50 | AD107: 50 | AE107: 50 | AF107: 50 | AG107: 50 | AI107: =INDEX($F107:$AG107,1,MATCH(AI$7,$F$7:$AG$7,1)) -> 0 | AJ107: =INDEX($F107:$AG107,1,MATCH(AJ$7,$F$7:$AG$7,1)) -> 0 | AK107: =INDEX($F107:$AG107,1,MATCH(AK$7,$F$7:$AG$7,1)) -> 0 | AL107: =INDEX($F107:$AG107,1,MATCH(AL$7,$F$7:$AG$7,1)) -> 25 | AM107: =INDEX($F107:$AG107,1,MATCH(AM$7,$F$7:$AG$7,1)) -> 50 | AN107: =INDEX($F107:$AG107,1,MATCH(AN$7,$F$7:$AG$7,1)) -> 50 | AO107: =INDEX($F107:$AG107,1,MATCH(AO$7,$F$7:$AG$7,1)) -> 50
A108: AIB CLT1 (South Carolina) - high | B108: MW | C108: Capacity | D108: Capacity file | F108: 0 | G108: 0 | H108: 0 | I108: 0 | J108: 0 | K108: 0 | L108: 0 | M108: 0 | N108: 0 | O108: 0 | P108: 0 | Q108: 0 | R108: 0 | S108: 0 | T108: 25 | U108: 50 | V108: 50 | W108: 50 | X108: 50 | Y108: 50 | Z108: 50 | AA108: 50 | AB108: 50 | AC108: 50 | AD108: 50 | AE108: 50 | AF108: 50 | AG108: 50 | AI108: =INDEX($F108:$AG108,1,MATCH(AI$7,$F$7:$AG$7,1)) -> 0 | AJ108: =INDEX($F108:$AG108,1,MATCH(AJ$7,$F$7:$AG$7,1)) -> 0 | AK108: =INDEX($F108:$AG108,1,MATCH(AK$7,$F$7:$AG$7,1)) -> 0 | AL108: =INDEX($F108:$AG108,1,MATCH(AL$7,$F$7:$AG$7,1)) -> 50 | AM108: =INDEX($F108:$AG108,1,MATCH(AM$7,$F$7:$AG$7,1)) -> 50 | AN108: =INDEX($F108:$AG108,1,MATCH(AN$7,$F$7:$AG$7,1)) -> 50 | AO108: =INDEX($F108:$AG108,1,MATCH(AO$7,$F$7:$AG$7,1)) -> 50
A109: Other unidentified (colo not yet visible) - low | B109: MW | C109: Capacity | D109: PLACEHOLDER (Inputs, due Tue Oct 6) | F109: =IF(F$5>=12,Inputs!$E$169,0) -> 0 | G109: =IF(G$5>=12,Inputs!$E$169,0) -> 0 | H109: =IF(H$5>=12,Inputs!$E$169,0) -> 0 | I109: =IF(I$5>=12,Inputs!$E$169,0) -> 0 | J109: =IF(J$5>=12,Inputs!$E$169,0) -> 0 | K109: =IF(K$5>=12,Inputs!$E$169,0) -> 0 | L109: =IF(L$5>=12,Inputs!$E$169,0) -> 0 | M109: =IF(M$5>=12,Inputs!$E$169,0) -> 0 | ... AG109: =IF(AG$5>=12,Inputs!$E$169,0) -> 0 | AI109: =INDEX($F109:$AG109,1,MATCH(AI$7,$F$7:$AG$7,1)) -> 0 | AJ109: =INDEX($F109:$AG109,1,MATCH(AJ$7,$F$7:$AG$7,1)) -> 0 | AK109: =INDEX($F109:$AG109,1,MATCH(AK$7,$F$7:$AG$7,1)) -> 0 | AL109: =INDEX($F109:$AG109,1,MATCH(AL$7,$F$7:$AG$7,1)) -> 0 | AM109: =INDEX($F109:$AG109,1,MATCH(AM$7,$F$7:$AG$7,1)) -> 0 | AN109: =INDEX($F109:$AG109,1,MATCH(AN$7,$F$7:$AG$7,1)) -> 0 | AO109: =INDEX($F109:$AG109,1,MATCH(AO$7,$F$7:$AG$7,1)) -> 0
A110: Other unidentified (colo not yet visible) - base | B110: MW | C110: Capacity | D110: PLACEHOLDER (Inputs, due Tue Oct 6) | F110: =IF(F$5>=12,Inputs!$D$169,0) -> 0 | G110: =IF(G$5>=12,Inputs!$D$169,0) -> 0 | H110: =IF(H$5>=12,Inputs!$D$169,0) -> 0 | I110: =IF(I$5>=12,Inputs!$D$169,0) -> 0 | J110: =IF(J$5>=12,Inputs!$D$169,0) -> 0 | K110: =IF(K$5>=12,Inputs!$D$169,0) -> 0 | L110: =IF(L$5>=12,Inputs!$D$169,0) -> 0 | M110: =IF(M$5>=12,Inputs!$D$169,0) -> 0 | ... AG110: =IF(AG$5>=12,Inputs!$D$169,0) -> 0 | AI110: =INDEX($F110:$AG110,1,MATCH(AI$7,$F$7:$AG$7,1)) -> 0 | AJ110: =INDEX($F110:$AG110,1,MATCH(AJ$7,$F$7:$AG$7,1)) -> 0 | AK110: =INDEX($F110:$AG110,1,MATCH(AK$7,$F$7:$AG$7,1)) -> 0 | AL110: =INDEX($F110:$AG110,1,MATCH(AL$7,$F$7:$AG$7,1)) -> 0 | AM110: =INDEX($F110:$AG110,1,MATCH(AM$7,$F$7:$AG$7,1)) -> 0 | AN110: =INDEX($F110:$AG110,1,MATCH(AN$7,$F$7:$AG$7,1)) -> 0 | AO110: =INDEX($F110:$AG110,1,MATCH(AO$7,$F$7:$AG$7,1)) -> 0
A111: Other unidentified (colo not yet visible) - high | B111: MW | C111: Capacity | D111: PLACEHOLDER (Inputs, due Tue Oct 6) | F111: =IF(F$5>=12,Inputs!$C$169,0) -> 0 | G111: =IF(G$5>=12,Inputs!$C$169,0) -> 0 | H111: =IF(H$5>=12,Inputs!$C$169,0) -> 0 | I111: =IF(I$5>=12,Inputs!$C$169,0) -> 0 | J111: =IF(J$5>=12,Inputs!$C$169,0) -> 0 | K111: =IF(K$5>=12,Inputs!$C$169,0) -> 0 | L111: =IF(L$5>=12,Inputs!$C$169,0) -> 0 | M111: =IF(M$5>=12,Inputs!$C$169,0) -> 0 | ... AG111: =IF(AG$5>=12,Inputs!$C$169,0) -> 0 | AI111: =INDEX($F111:$AG111,1,MATCH(AI$7,$F$7:$AG$7,1)) -> 0 | AJ111: =INDEX($F111:$AG111,1,MATCH(AJ$7,$F$7:$AG$7,1)) -> 0 | AK111: =INDEX($F111:$AG111,1,MATCH(AK$7,$F$7:$AG$7,1)) -> 0 | AL111: =INDEX($F111:$AG111,1,MATCH(AL$7,$F$7:$AG$7,1)) -> 0 | AM111: =INDEX($F111:$AG111,1,MATCH(AM$7,$F$7:$AG$7,1)) -> 0 | AN111: =INDEX($F111:$AG111,1,MATCH(AN$7,$F$7:$AG$7,1)) -> 0 | AO111: =INDEX($F111:$AG111,1,MATCH(AO$7,$F$7:$AG$7,1)) -> 0
A112: Capacity file: identified sites energized base (as stated, mixed basis) | B112: MW | C112: Capacity | D112: COMPANY row, copied | F112: 25 | G112: 25 | H112: 25 | I112: 30 | J112: 40 | K112: 45 | L112: 62.5 | M112: 147.7 | N112: 171.5 | O112: 173 | P112: 207.5 | Q112: 304.5 | R112: 444.7 | S112: 591.7 | T112: 751.5 | U112: 1069 | V112: 1181.5 | W112: 1376.5 | X112: 1389 | Y112: 1799 | Z112: 1799 | AA112: 2219 | AB112: 2219 | AC112: 2804 | AD112: 2804 | AE112: 2804 | AF112: 2804 | AG112: 3379 | AI112: =INDEX($F112:$AG112,1,MATCH(AI$7,$F$7:$AG$7,1)) -> 30 | AJ112: =INDEX($F112:$AG112,1,MATCH(AJ$7,$F$7:$AG$7,1)) -> 147.7 | AK112: =INDEX($F112:$AG112,1,MATCH(AK$7,$F$7:$AG$7,1)) -> 304.5 | AL112: =INDEX($F112:$AG112,1,MATCH(AL$7,$F$7:$AG$7,1)) -> 1069 | AM112: =INDEX($F112:$AG112,1,MATCH(AM$7,$F$7:$AG$7,1)) -> 1799 | AN112: =INDEX($F112:$AG112,1,MATCH(AN$7,$F$7:$AG$7,1)) -> 2804 | AO112: =INDEX($F112:$AG112,1,MATCH(AO$7,$F$7:$AG$7,1)) -> 3379
A113: Model: sum of named-site base imports (as stated) | B113: MW | C113: Modeling | F113: =N(F41)+N(F44)+N(F47)+N(F50)+N(F53)+N(F56)+N(F59)+N(F62)+N(F65)+N(F68)+N(F71)+N(F74)+N(F77)+N(F80)+N(F83)+N(F86)+N(F89)+N(F92)+N(F95)+N(F104)+N(F107) -> 25 | G113: =N(G41)+N(G44)+N(G47)+N(G50)+N(G53)+N(G56)+N(G59)+N(G62)+N(G65)+N(G68)+N(G71)+N(G74)+N(G77)+N(G80)+N(G83)+N(G86)+N(G89)+N(G92)+N(G95)+N(G104)+N(G107) -> 25 | H113: =N(H41)+N(H44)+N(H47)+N(H50)+N(H53)+N(H56)+N(H59)+N(H62)+N(H65)+N(H68)+N(H71)+N(H74)+N(H77)+N(H80)+N(H83)+N(H86)+N(H89)+N(H92)+N(H95)+N(H104)+N(H107) -> 25 | I113: =N(I41)+N(I44)+N(I47)+N(I50)+N(I53)+N(I56)+N(I59)+N(I62)+N(I65)+N(I68)+N(I71)+N(I74)+N(I77)+N(I80)+N(I83)+N(I86)+N(I89)+N(I92)+N(I95)+N(I104)+N(I107) -> 30 | J113: =N(J41)+N(J44)+N(J47)+N(J50)+N(J53)+N(J56)+N(J59)+N(J62)+N(J65)+N(J68)+N(J71)+N(J74)+N(J77)+N(J80)+N(J83)+N(J86)+N(J89)+N(J92)+N(J95)+N(J104)+N(J107) -> 40 | K113: =N(K41)+N(K44)+N(K47)+N(K50)+N(K53)+N(K56)+N(K59)+N(K62)+N(K65)+N(K68)+N(K71)+N(K74)+N(K77)+N(K80)+N(K83)+N(K86)+N(K89)+N(K92)+N(K95)+N(K104)+N(K107) -> 45 | L113: =N(L41)+N(L44)+N(L47)+N(L50)+N(L53)+N(L56)+N(L59)+N(L62)+N(L65)+N(L68)+N(L71)+N(L74)+N(L77)+N(L80)+N(L83)+N(L86)+N(L89)+N(L92)+N(L95)+N(L104)+N(L107) -> 62.5 | M113: =N(M41)+N(M44)+N(M47)+N(M50)+N(M53)+N(M56)+N(M59)+N(M62)+N(M65)+N(M68)+N(M71)+N(M74)+N(M77)+N(M80)+N(M83)+N(M86)+N(M89)+N(M92)+N(M95)+N(M104)+N(M107) -> 147.7 | ... AG113: =N(AG41)+N(AG44)+N(AG47)+N(AG50)+N(AG53)+N(AG56)+N(AG59)+N(AG62)+N(AG65)+N(AG68)+N(AG71)+N(AG74)+N(AG77)+N(AG80)+N(AG83)+N(AG86)+N(AG89)+N(AG92)+N(AG95)+N(AG104)+N(AG107) -> 3379 | AI113: =INDEX($F113:$AG113,1,MATCH(AI$7,$F$7:$AG$7,1)) -> 30 | AJ113: =INDEX($F113:$AG113,1,MATCH(AJ$7,$F$7:$AG$7,1)) -> 147.7 | AK113: =INDEX($F113:$AG113,1,MATCH(AK$7,$F$7:$AG$7,1)) -> 304.5 | AL113: =INDEX($F113:$AG113,1,MATCH(AL$7,$F$7:$AG$7,1)) -> 1069 | AM113: =INDEX($F113:$AG113,1,MATCH(AM$7,$F$7:$AG$7,1)) -> 1799 | AN113: =INDEX($F113:$AG113,1,MATCH(AN$7,$F$7:$AG$7,1)) -> 2804 | AO113: =INDEX($F113:$AG113,1,MATCH(AO$7,$F$7:$AG$7,1)) -> 3379
A114: Tie check (model - file; should be 0) | B114: MW | C114: Modeling | F114: =F113-F112 -> 0 | G114: =G113-G112 -> 0 | H114: =H113-H112 -> 0 | I114: =I113-I112 -> 0 | J114: =J113-J112 -> 0 | K114: =K113-K112 -> 0 | L114: =L113-L112 -> 0 | M114: =M113-M112 -> 0 | ... AG114: =AG113-AG112 -> 0 | AI114: =INDEX($F114:$AG114,1,MATCH(AI$7,$F$7:$AG$7,1)) -> 0 | AJ114: =INDEX($F114:$AG114,1,MATCH(AJ$7,$F$7:$AG$7,1)) -> 0 | AK114: =INDEX($F114:$AG114,1,MATCH(AK$7,$F$7:$AG$7,1)) -> 0 | AL114: =INDEX($F114:$AG114,1,MATCH(AL$7,$F$7:$AG$7,1)) -> 0 | AM114: =INDEX($F114:$AG114,1,MATCH(AM$7,$F$7:$AG$7,1)) -> 0 | AN114: =INDEX($F114:$AG114,1,MATCH(AN$7,$F$7:$AG$7,1)) -> 0 | AO114: =INDEX($F114:$AG114,1,MATCH(AO$7,$F$7:$AG$7,1)) -> 0
A116: Block 1 - CONTRACTED MW (land + power commitments; pipeline, not revenue capacity)
A117: Vineland NJ (DataOne) | B117: MW | C117: Capacity | J117: 300 | K117: 300 | L117: 300 | M117: 300 | N117: 300 | O117: 300 | P117: 300 | Q117: 300 | R117: 300 | S117: 300 | T117: 300 | U117: 300 | V117: 300 | W117: 300 | X117: 300 | Y117: 300 | Z117: 300 | AA117: 300 | AB117: 300 | AC117: 300 | AD117: 300 | AE117: 300 | AF117: 300 | AG117: 300 | AI117: =INDEX($F117:$AG117,1,MATCH(AI$7,$F$7:$AG$7,1)) -> 0 | AJ117: =INDEX($F117:$AG117,1,MATCH(AJ$7,$F$7:$AG$7,1)) -> 300 | AK117: =INDEX($F117:$AG117,1,MATCH(AK$7,$F$7:$AG$7,1)) -> 300 | AL117: =INDEX($F117:$AG117,1,MATCH(AL$7,$F$7:$AG$7,1)) -> 300 | AM117: =INDEX($F117:$AG117,1,MATCH(AM$7,$F$7:$AG$7,1)) -> 300 | AN117: =INDEX($F117:$AG117,1,MATCH(AN$7,$F$7:$AG$7,1)) -> 300 | AO117: =INDEX($F117:$AG117,1,MATCH(AO$7,$F$7:$AG$7,1)) -> 300
