Workbook

Sheet Cover
A1: Nebius (NBIS) driver-based model
A2: VERSION v0.8b – DRAFT FOR REVIEW (v0.8 + funding stack: prepay / ABS / uncontracted pricing toggles; backstop at $52.6M owned Rubin)
A3: Build date: 2026-10-04. v0.3 base approved (terminal excludes Q4'30 spend for post-horizon MW and that MW; GPU capex lead 3 qtrs vs billing; history scenario-invariant; bear replacement at bear price path; bull Blackwell 6.25% cut after Rubin + next-gen -1.7%/yr).
A4: v0.7d changes (each a Bridge step): (1) new shares added to Sh_Basic / fully diluted at the headline issue price (Shares tab plan rows; authority check vs ~82M); (2) off-B/S commitments weight 50% -> 0%: the $19.0B energy + lease commitments are the same rent / power already deducted in EBITDA (double count removed; EV unchanged, equity +$9.5B); (3) Vineland T5-T9 billing aligned to Capacity v2 billing-start quarters (no extra 4-qtr ramp / 50% start quarter): FY27 $447M -> $1,159.5M; (4) HEADLINE PT = SELF-CONSISTENT: ATM, equity top-ups and re-funded converts issued at the solved PT itself (fixed point); spot ($242.81) and path issuance kept as MEMO rows that depend on market access at today's price. v0.7c changes kept: shared floor bridge, Rubin $16.2M derived premium, fit-out out of leased Rubin, idle Vineland MW, 3-yr option, run-off residual, re-sized funding, Vineland T1-T4 bear sensitivity.
A5: Key outputs (live, current scenario)
A6: Scenario | B6: =CHOOSE(Scen,"BULL","BASE","BEAR") -> BASE
A7: DCF EV ($M) | B7: =V_EV -> -898.81401
A8: FD value / share ($) | B8: =V_PS -> 0.01
A9: 12-month PT ($) | B9: =V_PT -> 3.970466
A10: First quarter liquidity < 0 | B10: =Liq_NegQ -> none to Q4'30
A11: Market EV ($M) | B11: =V_MKTEV -> 74654.719
A12: NOTE: Headline PT = self-consistent issuance; spot-issuance PT is a memo that assumes continued market access at today's price.
A13: Notes - open items
A14: OPEN: FY26 capex below the $20-25B guide (Aug 12 2026 call): v0.3 $18.1B (~$1.9B short); v0.4 split lead $16.7B (~$3.3B short); possible early 2027 shell/power or deposits not in the path. Check: Checks 'FY26 capex vs company guide'. | B14: Owner: Filings / Capacity
A15: HEADLINE PT is SELF-CONSISTENT (PTBasis 1): every new share is issued at the solved PT. Base $4.00 / gross $12.70 / bull $401 / bear $0 (no positive fixed point - existing equity under water at any issue price). MEMO (depends on market access at today's price): spot $242.81 issuance base $88.9 / bull $364 / bear $33.9; path to PT over 8 qtrs base $30.3 / bull $390 / bear $0. Shares needed vs ~82M authority: base ~11.0B issued + 2.3B convert reserve; bull ~87M + 22M; bear unbounded -> EGM / not financeable on these terms. | B15: Owner: Capacity
A16: v0.7d: off-B/S commitments weight 0% (rent / power already in EBITDA; in-horizon rent + power $11.7B, FY30 run-rate $3.9B/yr vs $19.0B commitments; not in capex). MSFT T5-T9 billing at Capacity v2 start quarters (T5-T6 Q2'27, T7-T9 Q3'27, full run-rate): FY27 T5-T9 $1,159.5M (was $447M with extra 4-qtr ramp + 50% start quarter). Billing lag 1 qtr unchanged. | B16: Owner: GPU Market
A17: OPEN: AIB CLT1 prepayment (undisclosed; default $0) and Inferize price (press $100-150M, toggle off). | B17: Owner: Filings
A18: OPEN: Vineland shutdown default OFF (VinShutSel 0); scenarios/weights are Capacity judgment (prob-weighted Q4'26 loss ~$68M at $14.5M/IT MW-yr vs Capacity ~$67M); SLA credits undisclosed; genset power saving not credited. | B18: Owner: Capacity
A19: OPEN: Capacity proposed MW path is a scenario only (MWSel 4) until Capacity's Tuesday file; new-deal $/MW basis (IT vs gross) medium-low confidence; short-term share 10% is an estimate. | B19: Owner: Capacity / Filings
A20: OPEN: ARR scope / whether $3.0B ARR includes signed-not-billing tranches; unexplained ARR residual ~$0.6B shown as a line, not plugged. | B20: Owner: Filings
A21: OPEN: YE27 ~950 MW IT normalization is a placeholder pending Capacity's basis column. | B21: Owner: Capacity
A22: OPEN: Q3'26 transfer into service (model $4,702M) pending Q3 filing; depreciation start dates (material weakness) flagged. | B22: Owner: Filings
A23: FLAGS: DCF EV (-$0.9B) below asset floor EV ($5.6B pre-tax; ~$1.3B after tax): floor is pre-tax and excludes uncontracted reinvestment; DCF most sensitive to Rubin $/MW, GPU life and tax. Bull EV >> 3x base; bear EV < 0; FY26 capex $17.6B below guide; issuance far above authority in base/bear. See Checks. | B23: Owner: Modeling / GPU Market
A24: v0.8 results (static; solved values; live toggles StopBuild / BackstopMW / StopCommitWt on Inputs)
A25: v0.8 STOP BUILDING (StopBuild=1; Estimated): only signed capacity is built after Q1'27 billing (= sites energized by YE26), plus Meta backstop MW if on. ATM plan and 2027 plan converts are off; equity top-ups only to the $1.0B buffer, at the self-consistent PT. Base: EV $9.8B (build plan -$0.9B), self-consistent PT $13.9, spot memo $19.2, ~138M new shares (convert refunding at PT) vs ~82M authority, YE27 liquidity $3.3B. This includes $3.7B of signed lease + energy commitments for the cut MW (50% x pro-rata share). At 0% it is $27.3 and at 100% $0.5. Bull $125.4 / bear $0 (EV -$2.6B) / gross $15.6. Asset floor $24.3/sh (self-consistent) sits between the 50% and 0% commitment cases. | B25: Owner: Modeling
A26: v0.8 BREAKEVEN NEW-DEAL PRICE ($M per IT MW-yr). Unit NPV = 0, after tax and corporate costs (Payback_Floor G): leased GB300 17.9 / 18.4 / 18.9 at 9 / 10 / 11% WACC; owned Rubin ($52.6M) 18.2 / 18.9 / 19.6. Full model (GB300 and Rubin prices scaled together, Rubin = 1.0125x GB300): build EV = stop EV at GB300 $16.2 / $16.9 / $17.6M; build PT = stop PT at $15.7 / $16.3 / $16.9M. Today: $16.0M GB300 / $16.2M Rubin. Solved by bisection, 2026-10-05. | B26: Owner: Modeling
A27: v0.8 WHAT HAS TO BE TRUE for a self-consistent PT of $242.81 (GB300 / Rubin $M per IT MW-yr): (A) price only, $24.4 / $24.7; (B) WACC 9% + GPU life 6 yrs, $18.9 / $19.2; (C) B + bull Rubin capex ($45.8M owned / $33.3M leased), $17.5 / $17.8; (D) WACC 10% + life 6 + bull Rubin capex, $19.4 / $19.7; (E) WACC 9% only, $20.5 / $20.7. Even at $242.81, authority need is ~170-210M shares vs ~82M. | B27: Owner: Modeling
A28: v0.8 META BACKSTOP toggle (BackstopMW 0/150/190; FY25 20-F p.75 terms Reported, MW mapping Derived / low): placed on the owned Rubin halls, billing from Q3'27, $16M ($14.5M bear) placeholder. It counts as contracted, is off-RPO and is EXCLUDED from the asset floor. Build plan base PT $4.0 -> $6.6 / $6.9 (150 / 190 MW). Stop-building $13.9 -> $21.9 / $24.1. v0.8b builds stop-case backstop MW at $52.6M owned Rubin (v0.8 had $26.2 / $29.6 at the ~$40M path rate). In the build plan the halls are already in the Capacity path at their own site rates. At $16M the backstop is below the $19.6M owned-Rubin breakeven, so stop EV falls ($9.8B -> $9.0B); PT rises because the cut-MW commitments shrink. In bear, 190 MW exceeds the YE27 uncontracted fleet by ~34 MW. | B28: Owner: Filings / Capacity
A29: v0.8 FUNDING RECONCILIATION (Funding tab): Capacity ~$17.5B uncontracted capex vs model capex Q3'26-Q4'27 $43.3B = uncontracted new-build $32.0B (capex spent ahead of go-live for 2028 MW + model path vs CSV) + contracted-MW $10.3B + maintenance / lease prepay $1.1B. Equity need Q3'26-Q4'30 $41.7B = capex $111.0B - EBITDA $61.7B + tax / interest $1.8B - net new prepayments $3.7B + convert maturities $8.0B + liquidity build $4.6B - converts $18.4B. Uncontracted split per Capacity uncontracted_split.csv: model YE27 non-contract MW 418 vs CSV ~430-480 incl. 96 MW existing self-serve; stop cut 271 MW at YE27 vs CSV 2027 go-lives 255 MW. | B29: Owner: Capacity / Modeling
A30: v0.8b FUNDING STACK (Funding_Stack tab; self-consistent PT, 11% WACC unless stated). BUILD: base $4.0 -> +prepay 55% $13.5 -> +ABS 50% $13.9 -> +uncontracted $20M $108.4 -> $22.5M $171.0 -> +backstop 190 $159.3 (backstop at $16M replaces $22.5M MW). All layers: (b) blended WACC 10.7% (ABS 5.4% of capex) $173.2; (c) 9% $266.0 = UPPER BOUND, double counts cheap debt; (d) Skeptic full stack (prepay 55%, ABS 50%, Rubin $20M, 9%) at uncontracted $20M $207.7 / $22.5M $283.6. | B30: Owner: Modeling
A31: v0.8b STOP BUILDING with the same layers: base $13.9; prepay and uncontracted-price layers do nothing (no new deals); ABS 50% $11.2 (idle cash pays interest); +backstop 190 $15.7; (b) blended 8.8% $24.3; (c) 9% $23.5; (d) $16.7. Shares needed: build all-layers 102-133M, (c) / (d22.5) ~85M vs ~82M authority; stop 79-172M. | B31: Owner: Modeling
A32: v0.8b CAVEATS: with self-consistent issuance, financing mix moves PT only through cost and timing (prepayments valued as interest-free customer funding, no price concession); cheap debt shows up only through WACC. The uncontracted premium on 2028-30 vintages persists into the terminal value (renewal after Q4'30 not modelled). Legacy 147 MW GPU-hour fleet not repriced. ABS only on new contracted-MW capex; it displaces 2027 plan converts first. Convert coupons funded by top-ups are not charged in the self-consistent equity value (pre-existing; ABS interest is charged). | B32: Owner: Modeling

Sheet README
A1: Nebius (NBIS) driver model - README
A3: Save path: /workspace/nebius/model/nebius_model.xlsx. Quarterly Q1'24-Q2'26 actuals (Hist, tagged Reported/Derived/Estimated/Not disclosed + best estimate + source), Q3'26-Q4'30 forecast, FY roll-ups AI:AO.
A4: Scenario: Inputs!D4 (1 Bull / 2 Base / 3 Bear). Blue = input; orange = placeholder; yellow = estimated/consensus; black = formula.
A5: Flow: Inputs -> Sites (contracted / energized [Capacity file] / mgmt-connected; MWSel; BillLag; PUE basis) -> Pricing -> Contracts (tranches, power ceiling, Q4 bridge) -> Revenue (3 books) -> Capex_DA (vintage cohorts, PISLag, impairment, cap. interest, dep-yield) -> Financing -> PnL -> CashFlow -> Shares -> Valuation (DCF, dilution solve, EV bridge, EV/MW) -> KPIs / Outputs / Sensitivity / Checks.
A6: Circularity: no Excel iterative calc needed. Valuation solves value/share by 15 unrolled fixed-point steps; DilPxMode 1 = SharePx for quarterly dilution.
A7: Converts: DilMethod 1 if-converted all / 2 ITM only (default; step dilution at conversion prices) / 3 net-share. Converted principal is removed from debt (Checks row 1).
A8: Static snapshot tables on Outputs / Sensitivity / Valuation memo rows / Checks (bull 3x, scenario-invariance) come from LibreOffice recalcs in snap.py; re-run snap.py after changing inputs.

Sheet Bridge
A1: EV bridge v0.1 -> v0.3 -> v0.4 (STATIC, filled by snap.py)
A2: Base scenario. Each row = cumulative settings recomputed in the CURRENT model (bug fixes such as the renewal-formula bracket and scenario-invariant history are in every row). $B and $/share are FD value/share.
A4: Step | B4: DCF EV $B | C4: Change $B | D4: FD $/share | E4: Change $/sh | F4: 12m PT $ | G4: FY26 rev $M | H4: FY27 rev $M | I4: FY28 rev $M | J4: FY27 EBITDA $M | K4: YE27 liquidity $M | L4: First neg. qtr
A5: v0.1 (as reported) | B5: 41.053548 | D5: 103.5364 | F5: 116.99613 | G5: 2400.637 | H5: 8242.0189 | I5: 22266.612 | J5: 4575.8582 | K5: -4456.7617 | L5: Q4'27
A6: + fleet ratio forecast-only / capex on driver MW (FixMgmt) | B6: 46.917572 | C6: 5.8640242 | D6: 121.61057 | E6: 18.074176 | F6: 137.41995 | G6: 2400.637 | H6: 8242.0189 | I6: 22266.612 | J6: 4606.0461 | K6: -4408.0848 | L6: Q4'27
A7: + terminal on Q4'30 exit incl. Q1'31 MW (include both) | B7: 100.18581 | C7: 53.268235 | D7: 270.29726 | E7: 148.68669 | F7: 305.43591 | G7: 2400.637 | H7: 8242.0189 | I7: 22266.612 | J7: 4606.0461 | K7: -4408.0848 | L7: Q4'27
A8: + TV run-off floor | B8: 100.18581 | C8: 0 | D8: 270.29726 | E8: 0 | F8: 305.43591 | G8: 2400.637 | H8: 8242.0189 | I8: 22266.612 | J8: 4606.0461 | K8: -4408.0848 | L8: Q4'27
A9: + owned-site O&M | B9: 89.065186 | C9: -11.12062 | D9: 240.34647 | E9: -29.950795 | F9: 271.59151 | G9: 2400.637 | H9: 8242.0189 | I9: 22266.612 | J9: 4517.4726 | K9: -4518.475 | L9: Q4'27
A10: + H2'26 repricing (= v0.2) | B10: 99.881943 | C10: 10.816757 | D10: 269.45258 | E10: 29.106113 | F10: 304.48142 | G10: 2425.3295 | H10: 8517.5153 | I10: 22648.736 | J10: 4713.075 | K10: -4310.0666 | L10: Q4'27
A11: + exclude both Q4'30 spend & Q1'31 MW | B11: 86.363741 | C11: -13.518202 | D11: 233.0828 | E11: -36.369776 | F11: 263.38357 | G11: 2425.3295 | H11: 8517.5153 | I11: 22648.736 | J11: 4713.075 | K11: -4310.0666 | L11: Q4'27
A12: + GPU capex lead 3 qtrs (= v0.3) | B12: 94.115788 | C12: 7.7520471 | D12: 248.1935 | E12: 15.110692 | F12: 280.45865 | G12: 2425.3295 | H12: 8517.5153 | I12: 22648.736 | J12: 4713.075 | K12: -7264.9716 | L12: Q2'27
A13: + split capex lead: shell/power 3, GPUs 2 qtrs | B13: 87.921392 | C13: -6.1943968 | D13: 233.70836 | E13: -14.48514 | F13: 264.09044 | G13: 2425.3295 | H13: 8517.5153 | I13: 22648.736 | J13: 4713.075 | K13: -7160.9335 | L13: Q3'27
A14: + price path: post-Rubin cut 22% + -6%/yr from year 2 | B14: 94.973087 | C14: 7.0516956 | D14: 252.68045 | E14: 18.972094 | F14: 285.52891 | G14: 2425.3295 | H14: 8102.5841 | I14: 22384.539 | J14: 4418.4739 | K14: -7450.3255 | L14: Q3'27
A15: + Rubin premium at per-MW parity (1.56x GB300) | B15: 153.79048 | C15: 58.817396 | D15: 406.65016 | E15: 153.96971 | F15: 459.51468 | G15: 2425.3295 | H15: 8140.6586 | I15: 24633.629 | J15: 4445.5068 | K15: -7423.7798 | L15: Q3'27
A16: + CLT1 rent $2.2M/IT MW-yr | B16: 154.02609 | C16: 0.23561158 | D16: 407.25464 | E16: 0.60447567 | F16: 460.19774 | G16: 2425.3295 | H16: 8140.6586 | I16: 24633.629 | J16: 4447.4208 | K16: -7421.8657 | L16: Q3'27
A17: + terminal g from fundamentals | B17: 125.81957 | C17: -28.206529 | D17: 334.88909 | E17: -72.365546 | F17: 378.42467 | G17: 2425.3295 | H17: 8140.6586 | I17: 24633.629 | J17: 4447.4208 | K17: -7421.8657 | L17: Q3'27
... A61: v0.8b: funding-stack toggles (prepay / ABS / uncontracted price) added OFF; backstop built at $52.6M owned Rubin when stop-building (no base change) (= v0.8b) | B61: -0.89881401 | C61: 0 | D61: 0.01 | E61: 0 | F61: 3.970466 | G61: 2465.0795 | H61: 8209.2404 | I61: 19716.797 | J61: 4213.144 | K61: 1000 | L61: none to Q4'30
A64: Horizon per-share values (FD value/share rolled at Ke; excludes future funding dilution - see Funding tab)
A65: Scenario | B65: Today | C65: 6-month | D65: 12-month PT | E65: 3-year
A66: Base (live) | B66: 0.01 | C66: 3.7351002 | D66: 3.970466 | E66: 5.0698881
A67: Bull | B67: 355.02686 | C67: 378.92296 | D67: 401.01436 | E67: 503.03242
A68: Bear | B68: 0.01 | C68: 0 | D68: 0 | E68: 0
A71: New-MW pricing vs IREN >$20M/IT MW-yr ($M per IT MW-yr). GB300 GPU-hour engine (legacy fleet) at Oct-1 list x RealRes x Util_Res; new 2027+ MW at new-deal blend (col G)
A72: Scenario | B72: GB300 gross | C72: net leased (-$2.2M rent) | D72: net owned (-O&M) | E72: Rubin gross | F72: IREN gross / leased / owned | G72: New-deal blend gross
A73: Base (live) | B73: 27.424348 | C73: 25.224348 | D73: 26.674348 | E73: 27.267343 | F73: 20.0 / 17.8 / 19.25 | G73: 16.69175
A74: Bull | B74: 43.041696 | C74: 40.841696 | D74: 42.291696 | E74: 46.963273 | F74: 20.0 / 17.8 / 19.25 | G74: 19.092188
A75: Bear | B75: 22.272793 | C75: 20.072793 | D75: 21.522793 | E75: 21.871882 | F75: 20.0 / 17.8 / 19.25 | G75: 14.736556
A78: v0.5 BASE RANGE: 12m PT ($/share) by short-term share (of TOTAL active MW) x new-deal $/MW basis, with / without prepayment decay (STATIC). Green = base; yellow = supported tests; orange = gross-MW basis (alternative reading of slide); red = equity floored at 0
A79: Prepayment decay ON (base) | B79: ST share 0% (floor) | C79: ST share 2% | D79: ST share 5% | E79: ST share 10%
A80: IT basis $22M/IT MW | B80: 0 | C80: 0 | D80: 3.970466 | E80: 25.700617
A81: Gross-MW basis = $26.4M/IT MW | B81: 0 | C81: 5.0002958 | D81: 12.730892 | E81: 42.044423
A82: EV $B / YE27 liq $B / 1st neg - IT | B82: -5.5 / 1.0 / none to Q4'30 | C82: -3.6 / 1.0 / none to Q4'30 | D82: -0.9 / 1.0 / none to Q4'30 | E82: 5.4 / 1.0 / none to Q4'30
A83: EV $B / YE27 liq $B / 1st neg - gross | B83: -2.1 / 1.0 / none to Q4'30 | C83: -0.5 / 1.0 / none to Q4'30 | D83: 1.7 / 1.0 / none to Q4'30 | E83: 10.1 / 1.0 / none to Q4'30
A85: Prepayment decay OFF (other deals 38.5% flat) | B85: ST share 0% (floor) | C85: ST share 2% | D85: ST share 5% | E85: ST share 10%
A86: IT basis $22M/IT MW | B86: 0 | C86: 0 | D86: 4.6286253 | E86: 26.363339
A87: Gross-MW basis = $26.4M/IT MW | B87: 0.46693069 | C87: 5.6603151 | D87: 13.390912 | E87: 42.707144
A88: EV $B / YE27 liq $B / 1st neg - IT | B88: -4.7 / 1.0 / none to Q4'30 | C88: -2.8 / 1.0 / none to Q4'30 | D88: -0.1 / 1.0 / none to Q4'30 | E88: 6.2 / 1.0 / none to Q4'30
A89: EV $B / YE27 liq $B / 1st neg - gross | B89: -1.2 / 1.0 / none to Q4'30 | C89: 0.3 / 1.0 / none to Q4'30 | D89: 2.6 / 1.0 / none to Q4'30 | E89: 10.9 / 1.0 / none to Q4'30

Sheet Payback_Floor
A1: Payback check, new-deal price cases, EBITDA per IT MW by generation, and asset floor (live formulas). Inputs blue.
A3: Leased GB300 capex per IT MW ($M; GPU + network + storage, no shell) = CPM_Lease_GB300 (rack-based) | B3: =CPM_Lease_GB300 -> 36.7875 | C3: v0.7b: 6.8 racks x GB_RackPx + $6.1M network (v0.7 41.3) | E3: Owned opex per IT MW-yr (power + ops, NO rent) = OwnOpex | F3: =IF(OwnOpexOn=1,OwnOpex,LoadFactor*PUE*8760*PowerPx/1000000+OM_MW) -> 2.25
A4: Leased Vera Rubin capex per IT MW ($M) - live scenario = CPM_Lease_VR | B4: =CPM_Lease_VR -> 40.1 | C4: Capacity v2 ex $1M colo fit-out (v0.7c): $33.3 / 40.1 / 48.2M bull/base/bear (racks $6.7/7.8/9.1M; network $5.3M) | E4: Owned data hall + power/cooling $M/IT MW (in owned capex; not replaced on GPU cycle) = CPM_SP | F4: =CPM_SP -> 12.5
A5: Owned GB300 capex per IT MW ($M, incl. data hall) = CPM_Own_GB300 | B5: =CPM_Own_GB300 -> 49.2875 | C5: v0.7b: rack-based + $12.5M hall (v0.7 53) | E5: Data hall economic life (yrs; residual only) = HallLife | F5: =HallLife -> 18
A6: Owned Vera Rubin capex per IT MW ($M) = CPM_Own_VR | B6: =CPM_Own_VR -> 52.6 | C6: Capacity v2 base $52.6M (v0.7 56) | E6: GPU/server residual at refresh (% of servers+network) = GPU_Resid | F6: =GPU_Resid -> 0.15
A7: Opex per IT MW-yr (rent $2.0-2.5M + power + ops), fixed across generations | B7: 4.5 | C7: Range $4-5M; does NOT fall at the Rubin switch | E7: WACC (NPV discount rate) | F7: =WACC -> 0.11
A8: Management payback target (months) | B8: 22 | C8: Q2'26 letter: 1 year 10 months, prepayments excluded (footnote basis) | E8: Corporate opex % revenue FY29 (other COR + PD + SG&A ex-SBC; for after-tax NPV incl. overhead) | F8: =OtherCOR+INDEX(PDpct,1,2029-FYBase)+INDEX(SGApct,1,2029-FYBase) -> 0.21
A9: Asset life for unlevered IRR (yrs; capex at t0, flat EBITDA, residual at end: GPUs GPU_Resid, owned data hall at HallLife) | B9: 5 | C9: GPU life 5 yrs (model base)
A10: A) New-deal price cases - $/IT MW-yr next to implied $/GPU-hr. GB300: one linked input (ND_Px x 491 x 8,760 x ND_Occ), IT vs gross toggle. RUBIN: direct $/IT MW-yr (no IT/gross toggle)
A11: Case | B11: IT reading $M/IT MW | C11: IT $/GPU-hr | D11: Gross reading $M/IT MW | E11: Gross $/GPU-hr | F11: $/GPU-hr at 400/MW (ref only)
A12: GB300 NVL72 (491 GPUs/IT MW) | B12: =MYRate -> 16 | C12: =ND_Px -> 3.7199267 | D12: =MYRate*ND_GrossX -> 19.207824 | E12: =ND_Px*ND_GrossX -> 4.4657311
A13: Vera Rubin $14.5M/IT MW [bear] | B13: =14.5 -> 14.5 | C13: =14.5*1000000/(GPUMW_N*8760) -> 5.1726598 | D13: same (no toggle) | F13: =14.5*1000000/(RubinGPUMW_D*8760) -> 4.1381279
A14: Vera Rubin $16.2M/IT MW [base] | B14: =16.2 -> 16.2 | C14: =16.2*1000000/(GPUMW_N*8760) -> 5.7791096 | D14: same (no toggle) | F14: =16.2*1000000/(RubinGPUMW_D*8760) -> 4.6232877
A15: Vera Rubin $20M/IT MW [bull] | B15: =20 -> 20 | C15: =20*1000000/(GPUMW_N*8760) -> 7.1347032 | D15: same (no toggle) | F15: =20*1000000/(RubinGPUMW_D*8760) -> 5.7077626
A16: Vera Rubin at live RubinMW | B16: =RubinMW -> 16.2 | C16: =RubinMW*1000000/(GPUMW_N*8760) -> 5.7791096 | D16: same (no toggle) | F16: =RubinMW*1000000/(RubinGPUMW_D*8760) -> 4.6232877
A17: Benchmarks: IREN new 3-yr GB300 ~$4.65/GPU-hr (>$20M/IT MW); Rubin: Anthropic-Nscale ~$16.2M/MW (6-yr, MW basis unknown); WhiteFiber-Prime Intellect 576 VR200 ~$108.2M/3 yrs = ~$7.15/GPU-hr (~$20M/IT MW if packages counted, medium). GB300 basis not disclosed by management.
A19: B) EBITDA per IT MW-yr by generation (opex fixed across generations; Rubin = RubinMW, no toggle)
B20: GB300 IT | C20: Rubin (RubinMW) | D20: Change | E20: GB300 gross | F20: Rubin (RubinMW) | G20: Change
A21: Revenue per IT MW-yr | B21: =B12 -> 16 | C21: =RubinMW -> 16.2 | D21: =C21/B21-1 -> 0.0125 | E21: =D12 -> 19.207824 | F21: =RubinMW -> 16.2 | G21: =F21/E21-1 -> -0.15659369
A22: Opex per IT MW-yr (PB_Opex) | B22: =PB_Opex -> 4.5 | C22: =PB_Opex -> 4.5 | E22: =PB_Opex -> 4.5 | F22: =PB_Opex -> 4.5
A23: EBITDA per IT MW-yr | B23: =B21-B22 -> 11.5 | C23: =C21-C22 -> 11.7 | D23: =C23/B23-1 -> 0.017391304 | E23: =E21-E22 -> 14.707824 | F23: =F21-F22 -> 11.7 | G23: =F23/E23-1 -> -0.20450503
A24: Memo: model's own opex/IT MW-yr - B: LEASED = RentMW x PUE + power (LoadFactor x PUE x 8,760 x PowerPx); C: OWNED = power + O&M, no rent (PB_OpexOwn) | B24: =RentMW*PUE+LoadFactor*PUE*8760*PowerPx/1000000 -> 3.4695 | C24: =PB_OpexOwn -> 2.25
A26: C) PAYBACK (months) = capex / (revenue - opex) x 12; prepayments EXCLUDED unless stated. Flag = within +/-3 months of 22. IRR = unlevered pre-tax, capex at t0, flat EBITDA over PB_Life, residual at end (col L). NPV per IT MW at WACC: N pre-tax; O after tax (site level, book D&A shield); P after tax incl. corporate opex PB_Corp
A27: Case | B27: IT / Rubin payback | C27: flag | D27: Gross (MYRate x ND_GrossX) payback | E27: flag | F27: capex $M/IT MW | G27: opex | H27: revenue IT $M | I27: EBITDA/IT MW (IT) | J27: IRR (IT, with residual) | K27: IRR (gross, with residual) | L27: residual at yr PB_Life $M/MW | M27: IRR (IT) no residual [v0.7 basis] | N27: NPV/MW pre-tax @WACC | O27: NPV/MW after tax (site) | P27: NPV/MW after tax incl. corporate opex | Q27: of which data hall $M/MW
A28: Leased GB300 (capex incl. $1.6M lease prepayment) | B28: =IFERROR(F28*1/(H28-G28)*12,999) -> 40.056522 | C28: =IF(ISNUMBER(B28),IF(ABS(B28-PB_Target)<=3,"WITHIN +/-3","outside"),"") -> outside | D28: =IFERROR(F28*1/(MYRate*ND_GrossX-G28)*12,999) -> 31.320065 | E28: =IF(ISNUMBER(D28),IF(ABS(D28-PB_Target)<=3,"WITHIN +/-3","outside"),"") -> outside | F28: =PB_CapGB+LeasePrepayOn*LeasePrepay -> 38.3875 | G28: =PB_Opex -> 4.5 | H28: =MYRate -> 16 | I28: =H28-G28 -> 11.5 | J28: =IFERROR(RATE(PB_Life,I28,-F28*1,L28),-1) -> 0.18099946 | K28: =IFERROR(RATE(PB_Life,MYRate*ND_GrossX-G28,-F28*1,L28),-1) -> 0.28669829 | L28: =PB_Resid*(F28-Q28)+Q28*MAX(0,1-PB_Life/PB_HallLife) -> 5.758125 | M28: =IFERROR(RATE(PB_Life,I28,-F28*1),-1) -> 0.15178413 | N28: =-F28*1+I28*(1-(1+PB_WACC)^-PB_Life)/PB_WACC+L28*(1+PB_WACC)^-PB_Life -> 7.5324826 | O28: =-F28*1+(I28-TaxRate*MAX(0,I28-((F28-Q28)/PB_Life+Q28*(ShellMW/(ShellMW+PowerMW)/Life_Shell+PowerMW/(ShellMW+PowerMW)/Life_Pow))))*(1-(1+PB_WACC)^-PB_Life)/PB_WACC+(PB_Resid*(F28-Q28)*(1-TaxRate)+Q28*MAX(0,1-PB_Life/PB_HallLife)-TaxRate*(Q28*MAX(0,1-PB_Life/PB_HallLife)-Q28*MAX(0,1-PB_Life*(ShellMW/(ShellMW+PowerMW)/Life_Shell+PowerMW/(ShellMW+PowerMW)/Life_Pow))))*(1+PB_WACC)^-PB_Life -> 3.0059414 | P28: =-F28*1+((I28-PB_Corp*H28)-TaxRate*MAX(0,I28-PB_Corp*H28-((F28-Q28)/PB_Life+Q28*(ShellMW/(ShellMW+PowerMW)/Life_Shell+PowerMW/(ShellMW+PowerMW)/Life_Pow))))*(1-(1+PB_WACC)^-PB_Life)/PB_WACC+(PB_Resid*(F28-Q28)*(1-TaxRate)+Q28*MAX(0,1-PB_Life/PB_HallLife)-TaxRate*(Q28*MAX(0,1-PB_Life/PB_HallLife)-Q28*MAX(0,1-PB_Life*(ShellMW/(ShellMW+PowerMW)/Life_Shell+PowerMW/(ShellMW+PowerMW)/Life_Pow))))*(1+PB_WACC)^-PB_Life -> -6.2083733 | Q28: =0 -> 0
A29: Leased Vera Rubin BASE: $16.2M rev / $40.1M capex ex fit-out (+ lease prepayment) | B29: =IFERROR(F29*1/(H29-G29)*12,999) -> 42.769231 | C29: =IF(ISNUMBER(B29),IF(ABS(B29-PB_Target)<=3,"WITHIN +/-3","outside"),"") -> outside | D29: n/a (no toggle) | E29: =IF(ISNUMBER(D29),IF(ABS(D29-PB_Target)<=3,"WITHIN +/-3","outside"),"") | F29: =40.1+LeasePrepayOn*LeasePrepay -> 41.7 | G29: =PB_Opex -> 4.5 | H29: =16.2 -> 16.2 | I29: =H29-G29 -> 11.7 | J29: =IFERROR(RATE(PB_Life,I29,-F29*1,L29),-1) -> 0.15599431 | L29: =PB_Resid*(F29-Q29)+Q29*MAX(0,1-PB_Life/PB_HallLife) -> 6.255 | M29: =IFERROR(RATE(PB_Life,I29,-F29*1),-1) -> 0.12459659 | N29: =-F29*1+I29*(1-(1+PB_WACC)^-PB_Life)/PB_WACC+L29*(1+PB_WACC)^-PB_Life -> 5.2540332 | O29: =-F29*1+(I29-TaxRate*MAX(0,I29-((F29-Q29)/PB_Life+Q29*(ShellMW/(ShellMW+PowerMW)/Life_Shell+PowerMW/(ShellMW+PowerMW)/Life_Pow))))*(1-(1+PB_WACC)^-PB_Life)/PB_WACC+(PB_Resid*(F29-Q29)*(1-TaxRate)+Q29*MAX(0,1-PB_Life/PB_HallLife)-TaxRate*(Q29*MAX(0,1-PB_Life/PB_HallLife)-Q29*MAX(0,1-PB_Life*(ShellMW/(ShellMW+PowerMW)/Life_Shell+PowerMW/(ShellMW+PowerMW)/Life_Pow))))*(1+PB_WACC)^-PB_Life -> 1.0924281 | P29: =-F29*1+((I29-PB_Corp*H29)-TaxRate*MAX(0,I29-PB_Corp*H29-((F29-Q29)/PB_Life+Q29*(ShellMW/(ShellMW+PowerMW)/Life_Shell+PowerMW/(ShellMW+PowerMW)/Life_Pow))))*(1-(1+PB_WACC)^-PB_Life)/PB_WACC+(PB_Resid*(F29-Q29)*(1-TaxRate)+Q29*MAX(0,1-PB_Life/PB_HallLife)-TaxRate*(Q29*MAX(0,1-PB_Life/PB_HallLife)-Q29*MAX(0,1-PB_Life*(ShellMW/(ShellMW+PowerMW)/Life_Shell+PowerMW/(ShellMW+PowerMW)/Life_Pow))))*(1+PB_WACC)^-PB_Life -> -8.2771143 | Q29: =0 -> 0
A30: Leased Vera Rubin BULL: $20M / $33.3M (+ lease prepayment) | B30: =IFERROR(F30*1/(H30-G30)*12,999) -> 27.019355 | C30: =IF(ISNUMBER(B30),IF(ABS(B30-PB_Target)<=3,"WITHIN +/-3","outside"),"") -> outside | D30: n/a (no toggle) | E30: =IF(ISNUMBER(D30),IF(ABS(D30-PB_Target)<=3,"WITHIN +/-3","outside"),"") | F30: =33.3+LeasePrepayOn*LeasePrepay -> 34.9 | G30: =PB_Opex -> 4.5 | H30: =20 -> 20 | I30: =H30-G30 -> 15.5 | J30: =IFERROR(RATE(PB_Life,I30,-F30*1,L30),-1) -> 0.36041626 | L30: =PB_Resid*(F30-Q30)+Q30*MAX(0,1-PB_Life/PB_HallLife) -> 5.235 | M30: =IFERROR(RATE(PB_Life,I30,-F30*1),-1) -> 0.34214898 | N30: =-F30*1+I30*(1-(1+PB_WACC)^-PB_Life)/PB_WACC+L30*(1+PB_WACC)^-PB_Life -> 25.493121 | O30: =-F30*1+(I30-TaxRate*MAX(0,I30-((F30-Q30)/PB_Life+Q30*(ShellMW/(ShellMW+PowerMW)/Life_Shell+PowerMW/(ShellMW+PowerMW)/Life_Pow))))*(1-(1+PB_WACC)^-PB_Life)/PB_WACC+(PB_Resid*(F30-Q30)*(1-TaxRate)+Q30*MAX(0,1-PB_Life/PB_HallLife)-TaxRate*(Q30*MAX(0,1-PB_Life/PB_HallLife)-Q30*MAX(0,1-PB_Life*(ShellMW/(ShellMW+PowerMW)/Life_Shell+PowerMW/(ShellMW+PowerMW)/Life_Pow))))*(1+PB_WACC)^-PB_Life -> 16.567415 | P30: =-F30*1+((I30-PB_Corp*H30)-TaxRate*MAX(0,I30-PB_Corp*H30-((F30-Q30)/PB_Life+Q30*(ShellMW/(ShellMW+PowerMW)/Life_Shell+PowerMW/(ShellMW+PowerMW)/Life_Pow))))*(1-(1+PB_WACC)^-PB_Life)/PB_WACC+(PB_Resid*(F30-Q30)*(1-TaxRate)+Q30*MAX(0,1-PB_Life/PB_HallLife)-TaxRate*(Q30*MAX(0,1-PB_Life/PB_HallLife)-Q30*MAX(0,1-PB_Life*(ShellMW/(ShellMW+PowerMW)/Life_Shell+PowerMW/(ShellMW+PowerMW)/Life_Pow))))*(1+PB_WACC)^-PB_Life -> 5.0495219 | Q30: =0 -> 0
A31: Leased Vera Rubin BEAR: $14.5M / $48.2M (+ lease prepayment) | B31: =IFERROR(F31*1/(H31-G31)*12,999) -> 59.76 | C31: =IF(ISNUMBER(B31),IF(ABS(B31-PB_Target)<=3,"WITHIN +/-3","outside"),"") -> outside | D31: n/a (no toggle) | E31: =IF(ISNUMBER(D31),IF(ABS(D31-PB_Target)<=3,"WITHIN +/-3","outside"),"") | F31: =48.2+LeasePrepayOn*LeasePrepay -> 49.8 | G31: =PB_Opex -> 4.5 | H31: =14.5 -> 14.5 | I31: =H31-G31 -> 10 | J31: =IFERROR(RATE(PB_Life,I31,-F31*1,L31),-1) -> 0.045623873 | L31: =PB_Resid*(F31-Q31)+Q31*MAX(0,1-PB_Life/PB_HallLife) -> 7.47 | M31: =IFERROR(RATE(PB_Life,I31,-F31*1),-1) -> 0.0013374963 | N31: =-F31*1+I31*(1-(1+PB_WACC)^-PB_Life)/PB_WACC+L31*(1+PB_WACC)^-PB_Life -> -8.4079484 | O31: =-F31*1+(I31-TaxRate*MAX(0,I31-((F31-Q31)/PB_Life+Q31*(ShellMW/(ShellMW+PowerMW)/Life_Shell+PowerMW/(ShellMW+PowerMW)/Life_Pow))))*(1-(1+PB_WACC)^-PB_Life)/PB_WACC+(PB_Resid*(F31-Q31)*(1-TaxRate)+Q31*MAX(0,1-PB_Life/PB_HallLife)-TaxRate*(Q31*MAX(0,1-PB_Life/PB_HallLife)-Q31*MAX(0,1-PB_Life*(ShellMW/(ShellMW+PowerMW)/Life_Shell+PowerMW/(ShellMW+PowerMW)/Life_Pow))))*(1+PB_WACC)^-PB_Life -> -9.5898251 | P31: =-F31*1+((I31-PB_Corp*H31)-TaxRate*MAX(0,I31-PB_Corp*H31-((F31-Q31)/PB_Life+Q31*(ShellMW/(ShellMW+PowerMW)/Life_Shell+PowerMW/(ShellMW+PowerMW)/Life_Pow))))*(1-(1+PB_WACC)^-PB_Life)/PB_WACC+(PB_Resid*(F31-Q31)*(1-TaxRate)+Q31*MAX(0,1-PB_Life/PB_HallLife)-TaxRate*(Q31*MAX(0,1-PB_Life/PB_HallLife)-Q31*MAX(0,1-PB_Life*(ShellMW/(ShellMW+PowerMW)/Life_Shell+PowerMW/(ShellMW+PowerMW)/Life_Pow))))*(1+PB_WACC)^-PB_Life -> -20.80569 | Q31: =0 -> 0
A32: Leased Vera Rubin: bull price $20M at base capex $40.1M (+ lease prepayment) | B32: =IFERROR(F32*1/(H32-G32)*12,999) -> 32.283871 | C32: =IF(ISNUMBER(B32),IF(ABS(B32-PB_Target)<=3,"WITHIN +/-3","outside"),"") -> outside | D32: n/a (no toggle) | E32: =IF(ISNUMBER(D32),IF(ABS(D32-PB_Target)<=3,"WITHIN +/-3","outside"),"") | F32: =40.1+LeasePrepayOn*LeasePrepay -> 41.7 | G32: =PB_Opex -> 4.5 | H32: =20 -> 20 | I32: =H32-G32 -> 15.5 | J32: =IFERROR(RATE(PB_Life,I32,-F32*1,L32),-1) -> 0.27258496 | L32: =PB_Resid*(F32-Q32)+Q32*MAX(0,1-PB_Life/PB_HallLife) -> 6.255 | M32: =IFERROR(RATE(PB_Life,I32,-F32*1),-1) -> 0.24981099 | N32: =-F32*1+I32*(1-(1+PB_WACC)^-PB_Life)/PB_WACC+L32*(1+PB_WACC)^-PB_Life -> 19.298442 | O32: =-F32*1+(I32-TaxRate*MAX(0,I32-((F32-Q32)/PB_Life+Q32*(ShellMW/(ShellMW+PowerMW)/Life_Shell+PowerMW/(ShellMW+PowerMW)/Life_Pow))))*(1-(1+PB_WACC)^-PB_Life)/PB_WACC+(PB_Resid*(F32-Q32)*(1-TaxRate)+Q32*MAX(0,1-PB_Life/PB_HallLife)-TaxRate*(Q32*MAX(0,1-PB_Life/PB_HallLife)-Q32*MAX(0,1-PB_Life*(ShellMW/(ShellMW+PowerMW)/Life_Shell+PowerMW/(ShellMW+PowerMW)/Life_Pow))))*(1+PB_WACC)^-PB_Life -> 11.513379 | P32: =-F32*1+((I32-PB_Corp*H32)-TaxRate*MAX(0,I32-PB_Corp*H32-((F32-Q32)/PB_Life+Q32*(ShellMW/(ShellMW+PowerMW)/Life_Shell+PowerMW/(ShellMW+PowerMW)/Life_Pow))))*(1-(1+PB_WACC)^-PB_Life)/PB_WACC+(PB_Resid*(F32-Q32)*(1-TaxRate)+Q32*MAX(0,1-PB_Life/PB_HallLife)-TaxRate*(Q32*MAX(0,1-PB_Life/PB_HallLife)-Q32*MAX(0,1-PB_Life*(ShellMW/(ShellMW+PowerMW)/Life_Shell+PowerMW/(ShellMW+PowerMW)/Life_Pow))))*(1+PB_WACC)^-PB_Life -> -0.0045140967 | Q32: =0 -> 0
A33: Owned GB300 (memo, rack-based servers+network + 12.5 hall), opex NO rent | B33: =IFERROR(F33*1/(H33-G33)*12,999) -> 43.014545 | C33: =IF(ISNUMBER(B33),IF(ABS(B33-PB_Target)<=3,"WITHIN +/-3","outside"),"") -> outside | D33: =IFERROR(F33*1/(MYRate*ND_GrossX-G33)*12,999) -> 34.877706 | E33: =IF(ISNUMBER(D33),IF(ABS(D33-PB_Target)<=3,"WITHIN +/-3","outside"),"") -> outside | F33: =PB_CapOwnGB -> 49.2875 | G33: =PB_OpexOwn -> 2.25 | H33: =MYRate -> 16 | I33: =H33-G33 -> 13.75 | J33: =IFERROR(RATE(PB_Life,I33,-F33*1,L33),-1) -> 0.18055757 | K33: =IFERROR(RATE(PB_Life,MYRate*ND_GrossX-G33,-F33*1,L33),-1) -> 0.25979558 | L33: =PB_Resid*(F33-Q33)+Q33*MAX(0,1-PB_Life/PB_HallLife) -> 14.545903 | M33: =IFERROR(RATE(PB_Life,I33,-F33*1),-1) -> 0.12227576 | N33: =-F33*1+I33*(1-(1+PB_WACC)^-PB_Life)/PB_WACC+L33*(1+PB_WACC)^-PB_Life -> 10.163369 | O33: =-F33*1+(I33-TaxRate*MAX(0,I33-((F33-Q33)/PB_Life+Q33*(ShellMW/(ShellMW+PowerMW)/Life_Shell+PowerMW/(ShellMW+PowerMW)/Life_Pow))))*(1-(1+PB_WACC)^-PB_Life)/PB_WACC+(PB_Resid*(F33-Q33)*(1-TaxRate)+Q33*MAX(0,1-PB_Life/PB_HallLife)-TaxRate*(Q33*MAX(0,1-PB_Life/PB_HallLife)-Q33*MAX(0,1-PB_Life*(ShellMW/(ShellMW+PowerMW)/Life_Shell+PowerMW/(ShellMW+PowerMW)/Life_Pow))))*(1+PB_WACC)^-PB_Life -> 3.9543452 | P33: =-F33*1+((I33-PB_Corp*H33)-TaxRate*MAX(0,I33-PB_Corp*H33-((F33-Q33)/PB_Life+Q33*(ShellMW/(ShellMW+PowerMW)/Life_Shell+PowerMW/(ShellMW+PowerMW)/Life_Pow))))*(1-(1+PB_WACC)^-PB_Life)/PB_WACC+(PB_Resid*(F33-Q33)*(1-TaxRate)+Q33*MAX(0,1-PB_Life/PB_HallLife)-TaxRate*(Q33*MAX(0,1-PB_Life/PB_HallLife)-Q33*MAX(0,1-PB_Life*(ShellMW/(ShellMW+PowerMW)/Life_Shell+PowerMW/(ShellMW+PowerMW)/Life_Pow))))*(1+PB_WACC)^-PB_Life -> -5.2599696 | Q33: =PB_Hall -> 12.5
A34: Owned Vera Rubin (memo, base 52.6 = 40.1 + 12.5 hall) at $16.2M, opex NO rent | B34: =IFERROR(F34*1/(H34-G34)*12,999) -> 45.247312 | C34: =IF(ISNUMBER(B34),IF(ABS(B34-PB_Target)<=3,"WITHIN +/-3","outside"),"") -> outside | D34: n/a (no toggle) | E34: =IF(ISNUMBER(D34),IF(ABS(D34-PB_Target)<=3,"WITHIN +/-3","outside"),"") | F34: =PB_CapOwnRubin -> 52.6 | G34: =PB_OpexOwn -> 2.25 | H34: =16.2 -> 16.2 | I34: =H34-G34 -> 13.95 | J34: =IFERROR(RATE(PB_Life,I34,-F34*1,L34),-1) -> 0.16174147 | L34: =PB_Resid*(F34-Q34)+Q34*MAX(0,1-PB_Life/PB_HallLife) -> 15.042778 | M34: =IFERROR(RATE(PB_Life,I34,-F34*1),-1) -> 0.1020925 | N34: =-F34*1+I34*(1-(1+PB_WACC)^-PB_Life)/PB_WACC+L34*(1+PB_WACC)^-PB_Life -> 7.8849198 | O34: =-F34*1+(I34-TaxRate*MAX(0,I34-((F34-Q34)/PB_Life+Q34*(ShellMW/(ShellMW+PowerMW)/Life_Shell+PowerMW/(ShellMW+PowerMW)/Life_Pow))))*(1-(1+PB_WACC)^-PB_Life)/PB_WACC+(PB_Resid*(F34-Q34)*(1-TaxRate)+Q34*MAX(0,1-PB_Life/PB_HallLife)-TaxRate*(Q34*MAX(0,1-PB_Life/PB_HallLife)-Q34*MAX(0,1-PB_Life*(ShellMW/(ShellMW+PowerMW)/Life_Shell+PowerMW/(ShellMW+PowerMW)/Life_Pow))))*(1+PB_WACC)^-PB_Life -> 2.0408319 | P34: =-F34*1+((I34-PB_Corp*H34)-TaxRate*MAX(0,I34-PB_Corp*H34-((F34-Q34)/PB_Life+Q34*(ShellMW/(ShellMW+PowerMW)/Life_Shell+PowerMW/(ShellMW+PowerMW)/Life_Pow))))*(1-(1+PB_WACC)^-PB_Life)/PB_WACC+(PB_Resid*(F34-Q34)*(1-TaxRate)+Q34*MAX(0,1-PB_Life/PB_HallLife)-TaxRate*(Q34*MAX(0,1-PB_Life/PB_HallLife)-Q34*MAX(0,1-PB_Life*(ShellMW/(ShellMW+PowerMW)/Life_Shell+PowerMW/(ShellMW+PowerMW)/Life_Pow))))*(1+PB_WACC)^-PB_Life -> -7.2886618 | Q34: =PB_Hall -> 12.5
A35: MODEL'S OWN: GB300-era path capex (avg PathRateIT + PathRateSP 2027) + model opex at 2027 owned share | B35: =IFERROR(F35*1/(H35-G35)*12,999) -> 39.761788 | C35: =IF(ISNUMBER(B35),IF(ABS(B35-PB_Target)<=3,"WITHIN +/-3","outside"),"") -> outside | D35: =IFERROR(F35*1/(MYRate*ND_GrossX-G35)*12,999) -> 31.788082 | E35: =IF(ISNUMBER(D35),IF(ABS(D35-PB_Target)<=3,"WITHIN +/-3","outside"),"") -> outside | F35: =AVERAGE(INDEX(PathRateIT,1,13),INDEX(PathRateIT,1,14),INDEX(PathRateIT,1,15),INDEX(PathRateIT,1,16))+AVERAGE(INDEX(PathRateSP,1,13),INDEX(PathRateSP,1,14),INDEX(PathRateSP,1,15),INDEX(PathRateSP,1,16))+(1-AVERAGE(INDEX(MW_OwnSh,1,13),INDEX(MW_OwnSh,1,14),INDEX(MW_OwnSh,1,15),INDEX(MW_OwnSh,1,16)))*LeasePrepayOn*LeasePrepay -> 42.373983 | G35: =(1-AVERAGE(INDEX(MW_OwnSh,1,13),INDEX(MW_OwnSh,1,14),INDEX(MW_OwnSh,1,15),INDEX(MW_OwnSh,1,16)))*PB_OpexModel+AVERAGE(INDEX(MW_OwnSh,1,13),INDEX(MW_OwnSh,1,14),INDEX(MW_OwnSh,1,15),INDEX(MW_OwnSh,1,16))*PB_OpexModelOwn -> 3.2116466 | H35: =MYRate -> 16 | I35: =H35-G35 -> 12.788353 | J35: =IFERROR(RATE(PB_Life,I35,-F35*1,L35),-1) -> 0.19251992 | K35: =IFERROR(RATE(PB_Life,MYRate*ND_GrossX-G35,-F35*1,L35),-1) -> 0.28655563 | L35: =PB_Resid*(F35-Q35)+Q35*MAX(0,1-PB_Life/PB_HallLife) -> 8.4189077 | M35: =IFERROR(RATE(PB_Life,I35,-F35*1),-1) -> 0.15491891 | N35: =-F35*1+I35*(1-(1+PB_WACC)^-PB_Life)/PB_WACC+L35*(1+PB_WACC)^-PB_Life -> 9.886666 | O35: =-F35*1+(I35-TaxRate*MAX(0,I35-((F35-Q35)/PB_Life+Q35*(ShellMW/(ShellMW+PowerMW)/Life_Shell+PowerMW/(ShellMW+PowerMW)/Life_Pow))))*(1-(1+PB_WACC)^-PB_Life)/PB_WACC+(PB_Resid*(F35-Q35)*(1-TaxRate)+Q35*MAX(0,1-PB_Life/PB_HallLife)-TaxRate*(Q35*MAX(0,1-PB_Life/PB_HallLife)-Q35*MAX(0,1-PB_Life*(ShellMW/(ShellMW+PowerMW)/Life_Shell+PowerMW/(ShellMW+PowerMW)/Life_Pow))))*(1+PB_WACC)^-PB_Life -> 4.4065546 | P35: =-F35*1+((I35-PB_Corp*H35)-TaxRate*MAX(0,I35-PB_Corp*H35-((F35-Q35)/PB_Life+Q35*(ShellMW/(ShellMW+PowerMW)/Life_Shell+PowerMW/(ShellMW+PowerMW)/Life_Pow))))*(1-(1+PB_WACC)^-PB_Life)/PB_WACC+(PB_Resid*(F35-Q35)*(1-TaxRate)+Q35*MAX(0,1-PB_Life/PB_HallLife)-TaxRate*(Q35*MAX(0,1-PB_Life/PB_HallLife)-Q35*MAX(0,1-PB_Life*(ShellMW/(ShellMW+PowerMW)/Life_Shell+PowerMW/(ShellMW+PowerMW)/Life_Pow))))*(1+PB_WACC)^-PB_Life -> -4.8077602 | Q35: =AVERAGE(INDEX(PathRateSP,1,13),INDEX(PathRateSP,1,14),INDEX(PathRateSP,1,15),INDEX(PathRateSP,1,16)) -> 3.6049111
A36: MODEL'S OWN: Rubin-era path capex (avg PathRateIT + PathRateSP 2029) + model opex at 2029 owned share, live RubinMW | B36: =IFERROR(F36*1/(H36-G36)*12,999) -> 45.655859 | C36: =IF(ISNUMBER(B36),IF(ABS(B36-PB_Target)<=3,"WITHIN +/-3","outside"),"") -> outside | D36: n/a (no toggle) | E36: =IF(ISNUMBER(D36),IF(ABS(D36-PB_Target)<=3,"WITHIN +/-3","outside"),"") | F36: =AVERAGE(INDEX(PathRateIT,1,21),INDEX(PathRateIT,1,22),INDEX(PathRateIT,1,23),INDEX(PathRateIT,1,24))+AVERAGE(INDEX(PathRateSP,1,21),INDEX(PathRateSP,1,22),INDEX(PathRateSP,1,23),INDEX(PathRateSP,1,24))+(1-AVERAGE(INDEX(MW_OwnSh,1,21),INDEX(MW_OwnSh,1,22),INDEX(MW_OwnSh,1,23),INDEX(MW_OwnSh,1,24)))*LeasePrepayOn*LeasePrepay -> 51.11772 | G36: =(1-AVERAGE(INDEX(MW_OwnSh,1,21),INDEX(MW_OwnSh,1,22),INDEX(MW_OwnSh,1,23),INDEX(MW_OwnSh,1,24)))*PB_OpexModel+AVERAGE(INDEX(MW_OwnSh,1,21),INDEX(MW_OwnSh,1,22),INDEX(MW_OwnSh,1,23),INDEX(MW_OwnSh,1,24))*PB_OpexModelOwn -> 2.7644267 | H36: =RubinMW -> 16.2 | I36: =H36-G36 -> 13.435573 | J36: =IFERROR(RATE(PB_Life,I36,-F36*1,L36),-1) -> 0.15601631 | L36: =PB_Resid*(F36-Q36)+Q36*MAX(0,1-PB_Life/PB_HallLife) -> 13.860735 | M36: =IFERROR(RATE(PB_Life,I36,-F36*1),-1) -> 0.098572153 | N36: =-F36*1+I36*(1-(1+PB_WACC)^-PB_Life)/PB_WACC+L36*(1+PB_WACC)^-PB_Life -> 6.7644469 | O36: =-F36*1+(I36-TaxRate*MAX(0,I36-((F36-Q36)/PB_Life+Q36*(ShellMW/(ShellMW+PowerMW)/Life_Shell+PowerMW/(ShellMW+PowerMW)/Life_Pow))))*(1-(1+PB_WACC)^-PB_Life)/PB_WACC+(PB_Resid*(F36-Q36)*(1-TaxRate)+Q36*MAX(0,1-PB_Life/PB_HallLife)-TaxRate*(Q36*MAX(0,1-PB_Life/PB_HallLife)-Q36*MAX(0,1-PB_Life*(ShellMW/(ShellMW+PowerMW)/Life_Shell+PowerMW/(ShellMW+PowerMW)/Life_Pow))))*(1+PB_WACC)^-PB_Life -> 1.345444 | P36: =-F36*1+((I36-PB_Corp*H36)-TaxRate*MAX(0,I36-PB_Corp*H36-((F36-Q36)/PB_Life+Q36*(ShellMW/(ShellMW+PowerMW)/Life_Shell+PowerMW/(ShellMW+PowerMW)/Life_Pow))))*(1-(1+PB_WACC)^-PB_Life)/PB_WACC+(PB_Resid*(F36-Q36)*(1-TaxRate)+Q36*MAX(0,1-PB_Life/PB_HallLife)-TaxRate*(Q36*MAX(0,1-PB_Life/PB_HallLife)-Q36*MAX(0,1-PB_Life*(ShellMW/(ShellMW+PowerMW)/Life_Shell+PowerMW/(ShellMW+PowerMW)/Life_Pow))))*(1+PB_WACC)^-PB_Life -> -7.9840497 | Q36: =AVERAGE(INDEX(PathRateSP,1,21),INDEX(PathRateSP,1,22),INDEX(PathRateSP,1,23),INDEX(PathRateSP,1,24)) -> 10.822852
A37: TEST: GB300 IT at $32M capex/IT MW (IT fits 22 mo only at ~$32M = 12 x 32 / (22 - 4.5)) | B37: =IFERROR(F37*1/(H37-G37)*12,999) -> 33.391304 | C37: =IF(ISNUMBER(B37),IF(ABS(B37-PB_Target)<=3,"WITHIN +/-3","outside"),"") -> outside | D37: =IFERROR(F37*1/(MYRate*ND_GrossX-G37)*12,999) -> 26.108553 | E37: =IF(ISNUMBER(D37),IF(ABS(D37-PB_Target)<=3,"WITHIN +/-3","outside"),"") -> outside | F37: =32 -> 32 | G37: =PB_Opex -> 4.5 | H37: =MYRate -> 16 | I37: =H37-G37 -> 11.5 | J37: =IFERROR(RATE(PB_Life,I37,-F37*1,L37),-1) -> 0.25725984 | K37: =IFERROR(RATE(PB_Life,MYRate*ND_GrossX-G37,-F37*1,L37),-1) -> 0.37878174 | L37: =PB_Resid*(F37-Q37)+Q37*MAX(0,1-PB_Life/PB_HallLife) -> 4.8 | M37: =IFERROR(RATE(PB_Life,I37,-F37*1),-1) -> 0.23355169 | N37: =-F37*1+I37*(1-(1+PB_WACC)^-PB_Life)/PB_WACC+L37*(1+PB_WACC)^-PB_Life -> 13.351382 | O37: =-F37*1+(I37-TaxRate*MAX(0,I37-((F37-Q37)/PB_Life+Q37*(ShellMW/(ShellMW+PowerMW)/Life_Shell+PowerMW/(ShellMW+PowerMW)/Life_Pow))))*(1-(1+PB_WACC)^-PB_Life)/PB_WACC+(PB_Resid*(F37-Q37)*(1-TaxRate)+Q37*MAX(0,1-PB_Life/PB_HallLife)-TaxRate*(Q37*MAX(0,1-PB_Life/PB_HallLife)-Q37*MAX(0,1-PB_Life*(ShellMW/(ShellMW+PowerMW)/Life_Shell+PowerMW/(ShellMW+PowerMW)/Life_Pow))))*(1+PB_WACC)^-PB_Life -> 7.7533907 | P37: =-F37*1+((I37-PB_Corp*H37)-TaxRate*MAX(0,I37-PB_Corp*H37-((F37-Q37)/PB_Life+Q37*(ShellMW/(ShellMW+PowerMW)/Life_Shell+PowerMW/(ShellMW+PowerMW)/Life_Pow))))*(1-(1+PB_WACC)^-PB_Life)/PB_WACC+(PB_Resid*(F37-Q37)*(1-TaxRate)+Q37*MAX(0,1-PB_Life/PB_HallLife)-TaxRate*(Q37*MAX(0,1-PB_Life/PB_HallLife)-Q37*MAX(0,1-PB_Life*(ShellMW/(ShellMW+PowerMW)/Life_Shell+PowerMW/(ShellMW+PowerMW)/Life_Pow))))*(1+PB_WACC)^-PB_Life -> -1.4609241 | Q37: =0 -> 0
A38: TEST: GB300 IT with lower opex $2M/IT MW-yr (ex-rent definition) | B38: =IFERROR(F38*1/(H38-G38)*12,999) -> 31.532143 | C38: =IF(ISNUMBER(B38),IF(ABS(B38-PB_Target)<=3,"WITHIN +/-3","outside"),"") -> outside | D38: =IFERROR(F38*1/(MYRate*ND_GrossX-G38)*12,999) -> 25.654028 | E38: =IF(ISNUMBER(D38),IF(ABS(D38-PB_Target)<=3,"WITHIN +/-3","outside"),"") -> outside | F38: =PB_CapGB -> 36.7875 | G38: =2 -> 2 | H38: =MYRate -> 16 | I38: =H38-G38 -> 14 | J38: =IFERROR(RATE(PB_Life,I38,-F38*1,L38),-1) -> 0.28352737 | K38: =IFERROR(RATE(PB_Life,MYRate*ND_GrossX-G38,-F38*1,L38),-1) -> 0.38838216 | L38: =PB_Resid*(F38-Q38)+Q38*MAX(0,1-PB_Life/PB_HallLife) -> 5.518125 | M38: =IFERROR(RATE(PB_Life,I38,-F38*1),-1) -> 0.26139045 | N38: =-F38*1+I38*(1-(1+PB_WACC)^-PB_Life)/PB_WACC+L38*(1+PB_WACC)^-PB_Life -> 18.229797 | O38: =-F38*1+(I38-TaxRate*MAX(0,I38-((F38-Q38)/PB_Life+Q38*(ShellMW/(ShellMW+PowerMW)/Life_Shell+PowerMW/(ShellMW+PowerMW)/Life_Pow))))*(1-(1+PB_WACC)^-PB_Life)/PB_WACC+(PB_Resid*(F38-Q38)*(1-TaxRate)+Q38*MAX(0,1-PB_Life/PB_HallLife)-TaxRate*(Q38*MAX(0,1-PB_Life/PB_HallLife)-Q38*MAX(0,1-PB_Life*(ShellMW/(ShellMW+PowerMW)/Life_Shell+PowerMW/(ShellMW+PowerMW)/Life_Pow))))*(1+PB_WACC)^-PB_Life -> 11.051015 | P38: =-F38*1+((I38-PB_Corp*H38)-TaxRate*MAX(0,I38-PB_Corp*H38-((F38-Q38)/PB_Life+Q38*(ShellMW/(ShellMW+PowerMW)/Life_Shell+PowerMW/(ShellMW+PowerMW)/Life_Pow))))*(1-(1+PB_WACC)^-PB_Life)/PB_WACC+(PB_Resid*(F38-Q38)*(1-TaxRate)+Q38*MAX(0,1-PB_Life/PB_HallLife)-TaxRate*(Q38*MAX(0,1-PB_Life/PB_HallLife)-Q38*MAX(0,1-PB_Life*(ShellMW/(ShellMW+PowerMW)/Life_Shell+PowerMW/(ShellMW+PowerMW)/Life_Pow))))*(1+PB_WACC)^-PB_Life -> 1.8367006 | Q38: =0 -> 0
A39: TEST: GB300 IT with prepayments counted as cash (55% of capex on 70% of deals = 38.5%) | B39: =IFERROR(F39*(1-0.55*0.7)/(H39-G39)*12,999) -> 23.607978 | C39: =IF(ISNUMBER(B39),IF(ABS(B39-PB_Target)<=3,"WITHIN +/-3","outside"),"") -> WITHIN +/-3 | D39: =IFERROR(F39*(1-0.55*0.7)/(MYRate*ND_GrossX-G39)*12,999) -> 18.459002 | E39: =IF(ISNUMBER(D39),IF(ABS(D39-PB_Target)<=3,"WITHIN +/-3","outside"),"") -> outside | F39: =PB_CapGB -> 36.7875 | G39: =PB_Opex -> 4.5 | H39: =MYRate -> 16 | I39: =H39-G39 -> 11.5 | J39: =IFERROR(RATE(PB_Life,I39,-F39*(1-0.55*0.7),L39),-1) -> 0.4447945 | K39: =IFERROR(RATE(PB_Life,MYRate*ND_GrossX-G39,-F39*(1-0.55*0.7),L39),-1) -> 0.60247519 | L39: =PB_Resid*(F39-Q39)+Q39*MAX(0,1-PB_Life/PB_HallLife) -> 5.518125 | M39: =IFERROR(RATE(PB_Life,I39,-F39*(1-0.55*0.7)),-1) -> 0.42038044 | N39: =-F39*(1-0.55*0.7)+I39*(1-(1+PB_WACC)^-PB_Life)/PB_WACC+L39*(1+PB_WACC)^-PB_Life -> 23.153242 | O39: =-F39*(1-0.55*0.7)+(I39-TaxRate*MAX(0,I39-((F39-Q39)/PB_Life+Q39*(ShellMW/(ShellMW+PowerMW)/Life_Shell+PowerMW/(ShellMW+PowerMW)/Life_Pow))))*(1-(1+PB_WACC)^-PB_Life)/PB_WACC+(PB_Resid*(F39-Q39)*(1-TaxRate)+Q39*MAX(0,1-PB_Life/PB_HallLife)-TaxRate*(Q39*MAX(0,1-PB_Life/PB_HallLife)-Q39*MAX(0,1-PB_Life*(ShellMW/(ShellMW+PowerMW)/Life_Shell+PowerMW/(ShellMW+PowerMW)/Life_Pow))))*(1+PB_WACC)^-PB_Life -> 18.358314 | P39: =-F39*(1-0.55*0.7)+((I39-PB_Corp*H39)-TaxRate*MAX(0,I39-PB_Corp*H39-((F39-Q39)/PB_Life+Q39*(ShellMW/(ShellMW+PowerMW)/Life_Shell+PowerMW/(ShellMW+PowerMW)/Life_Pow))))*(1-(1+PB_WACC)^-PB_Life)/PB_WACC+(PB_Resid*(F39-Q39)*(1-TaxRate)+Q39*MAX(0,1-PB_Life/PB_HallLife)-TaxRate*(Q39*MAX(0,1-PB_Life/PB_HallLife)-Q39*MAX(0,1-PB_Life*(ShellMW/(ShellMW+PowerMW)/Life_Shell+PowerMW/(ShellMW+PowerMW)/Life_Pow))))*(1+PB_WACC)^-PB_Life -> 9.1439991 | Q39: =0 -> 0
A40: Implied GB300 revenue/IT MW if management's 22 months INCLUDES prepayments (capex x 61.5% x 12 / 22 + opex) | H40: =PB_CapGB*(1-0.55*0.7)*12/PB_Target+PB_Opex -> 16.840534
A41: NOTE (v0.7b): the 2027+ new-deal price is now set from CONTRACTS ($16M/IT MW base = $3.72/GPU-hr; 5-yr deals $14.5-16M: Microsoft ~$14.5M, Astra ~$15.9M), NOT calibrated to management's 22-month payback. At $16M no row fits 22 months ex-prepayments; with prepayments counted as cash (38.5% of capex) leased GB300 does (~24 months). Management's payback therefore most likely INCLUDES prepayments and/or uses lower opex. Col D 'gross' = MYRate x ND_GrossX (sensitivity only).
A44: D) ASSET FLOOR: PV of EBITDA margin on signed RPO + stakes - net debt - capex still needed for contracted MW ($M)
A45: RPO schedule assumption: 36% ($13.5B) evenly Jul'26-Jun'28 (Q2'26 Note 2); remainder 64% spread evenly Jul'28-Jun'31 (12 qtrs; ~avg remaining tenor: Microsoft 5-yr from late 2025, Meta #2 5-yr from 2027 - assumption). Margin = model adj. EBITDA margin by quarter (FY30 margin after 2030); pre-tax; discounted at WACC from ValDate.
A46: RPO total ($M) | B46: =RPO_Tot -> 37490
A47: PV of margin - window Jul'26-Jun'28 | B47: =SUMPRODUCT((Q_Idx>LastHist)*(Q_Idx<=LastHist+8)*(RPO_Tot*RPO24Pct/8)*PL_EBITDA/PL_Rev*1/(1+WACC)^((Q_End-ValDate)/365.25)) -> 6089.7399
A48: PV of margin - remainder, Jul'28-Dec'30 (10 qtrs in horizon) | B48: =SUMPRODUCT((Q_Idx>LastHist+8)*(Q_Idx<=28)*(RPO_Tot*(1-RPO24Pct)/12)*PL_EBITDA/PL_Rev*1/(1+WACC)^((Q_End-ValDate)/365.25)) -> 9069.337
A49: PV of margin - remainder, Q1-Q2'31 at FY30 margin | B49: =RPO_Tot*(1-RPO24Pct)/12*V_M30*(1/(1+WACC)^((INDEX(Q_End,1,28)+91-ValDate)/365.25)+1/(1+WACC)^((INDEX(Q_End,1,28)+182-ValDate)/365.25)) -> 1616.8827
A50: PV of margin on signed RPO (pre-tax) | B50: =PF_PV1+PF_PV2+PF_PV3 -> 16775.96
A51: memo: after tax at TaxRate (no D&A shield) | B51: =PF_PV*(1-TaxRate) -> 12447.762
A52: Contracted MW not yet delivered at 6/30 (Microsoft T5-T9 + Meta; backstop & TBD excluded) | B52: =Contracts!$D$12*(Contracts!$H$12>LastHist)*(1-Contracts!$I$12)+Contracts!$D$13*(Contracts!$H$13>LastHist)*(1-Contracts!$I$13)+Contracts!$D$14*(Contracts!$H$14>LastHist)*(1-Contracts!$I$14)+Contracts!$D$15*(Contracts!$H$15>LastHist)*(1-Contracts!$I$15)+Contracts!$D$16*(Contracts!$H$16>LastHist)*(1-Contracts!$I$16)+Contracts!$D$17*(Contracts!$H$17>LastHist)*(1-Contracts!$I$17)+Contracts!$D$18*(Contracts!$H$18>LastHist)*(1-Contracts!$I$18)+Contracts!$D$19*(Contracts!$H$19>LastHist)*(1-Contracts!$I$19)+Contracts!$D$20*(Contracts!$H$20>LastHist)*(1-Contracts!$I$20)+Contracts!$D$21*(Contracts!$H$21>LastHist)*(1-Contracts!$I$21)+Contracts!$D$22*(Contracts!$H$22>LastHist)*(1-Contracts!$I$22)+Contracts!$D$23*(Contracts!$H$23>LastHist)*(1-Contracts!$I$23)+Contracts!$D$24*(Contracts!$H$24>LastHist)*(1-Contracts!$I$24)+Contracts!$D$25*(Contracts!$H$25>LastHist)*(1-Contracts!$I$25)+Contracts!$D$26*(Contracts!$H$26>LastHist)*(1-Contracts!$I$26) -> 293.33333
A53: Capex still needed for contracted MW (Microsoft/Vineland = build-to-suit LEASE -> leased GB300 PB_CapGB [v0.7b; was owned 53]; Meta by gen: Rubin PB_CapRubin, Blackwell PB_CapGB) - gross, CIP already spent NOT netted (conservative) | B53: =Contracts!$D$12*(Contracts!$H$12>LastHist)*(1-Contracts!$I$12)*PB_CapGB+Contracts!$D$13*(Contracts!$H$13>LastHist)*(1-Contracts!$I$13)*PB_CapGB+Contracts!$D$14*(Contracts!$H$14>LastHist)*(1-Contracts!$I$14)*PB_CapGB+Contracts!$D$15*(Contracts!$H$15>LastHist)*(1-Contracts!$I$15)*PB_CapGB+Contracts!$D$16*(Contracts!$H$16>LastHist)*(1-Contracts!$I$16)*PB_CapGB+Contracts!$D$17*(Contracts!$H$17>LastHist)*(1-Contracts!$I$17)*PB_CapGB+Contracts!$D$18*(Contracts!$H$18>LastHist)*(1-Contracts!$I$18)*PB_CapGB+Contracts!$D$19*(Contracts!$H$19>LastHist)*(1-Contracts!$I$19)*PB_CapGB+Contracts!$D$20*(Contracts!$H$20>LastHist)*(1-Contracts!$I$20)*PB_CapGB+Contracts!$D$21*(Contracts!$H$21>LastHist)*(1-Contracts!$I$21)*PB_CapGB+Contracts!$D$22*(Contracts!$H$22>LastHist)*(1-Contracts!$I$22)*PB_CapGB+Contracts!$D$23*(Contracts!$H$23>LastHist)*(1-Contracts!$I$23)*PB_CapGB+Contracts!$D$24*(Contracts!$H$24>LastHist)*(1-Contracts!$I$24)*PB_CapGB+Contracts!$D$25*(Contracts!$H$25>LastHist)*(1-Contracts!$I$25)*PB_CapRubin+Contracts!$D$26*(Contracts!$H$26>LastHist)*(1-Contracts!$I$26)*PB_CapRubin -> 11144.333
A54: Operating asset floor (EV-equivalent) = PV margin - capex needed | B54: =PF_PV-PF_Cap -> 5631.6262
A55: Net debt at the conservative floor price (secured + converts OTM at that price at principal - cash; Q3'26) | B55: =V_ODEBT+CHOOSE(DilMethod,0,SUMPRODUCT((PF_PS1<=V_TrPX)*((CVDebtBasis=1)*V_TrO+(CVDebtBasis>=2)*V_TrB)),SUMPRODUCT(((CVDebtBasis=1)*V_TrO+(CVDebtBasis>=2)*V_TrB)))-V_CASH -> 1976.5947
A56: Stakes - conservative (carrying values, Note 5: ClickHouse 1,517.7 + Toloka 86.5 + VC 13.8 + other 2.5; Avride $0) | B56: =1620.5 -> 1620.5
A57: Stakes - mark (ClickHouse $4.2B est., Toloka FV 130.6, VC/other 16.3, Avride $0) | B57: =CH_Hi+TO_Hi+Other_Val -> 4346.9
A58: Stakes - high (mark + Avride $2.75B Caplight, LOW confidence) + PV of Avride burn added back (credit value AND remove burn - v0.7 double-count fix) | B58: =PF_S2+AV_Hi-AVBurnOn*AVBurnQ*(SUM(Valuation!$F$12:$AG$12)+4*(1+V_g)/(WACC-V_g)*V_DF28) -> 8827.6108
A59: Equity floor - conservative (at solved floor price) | B59: =PF_EV-V_ODEBT-CHOOSE(DilMethod,0,SUMPRODUCT((PF_PS1<=V_TrPX)*((CVDebtBasis=1)*V_TrO+(CVDebtBasis>=2)*V_TrB)),SUMPRODUCT(((CVDebtBasis=1)*V_TrO+(CVDebtBasis>=2)*V_TrB)))+V_CASH+PF_S1 -> 5275.5315
A60: Equity floor - mark | B60: =PF_EV-V_ODEBT-CHOOSE(DilMethod,0,SUMPRODUCT((PF_PS2<=V_TrPX)*((CVDebtBasis=1)*V_TrO+(CVDebtBasis>=2)*V_TrB)),SUMPRODUCT(((CVDebtBasis=1)*V_TrO+(CVDebtBasis>=2)*V_TrB)))+V_CASH+PF_S2 -> 8001.9315
A61: Equity floor - high | B61: =PF_EV-V_ODEBT-CHOOSE(DilMethod,0,SUMPRODUCT((PF_PS3<=V_TrPX)*((CVDebtBasis=1)*V_TrO+(CVDebtBasis>=2)*V_TrB)),SUMPRODUCT(((CVDebtBasis=1)*V_TrO+(CVDebtBasis>=2)*V_TrB)))+V_CASH+PF_S3 -> 12482.642
A62: LEGACY v0.7b floor bridge (no off-B/S commitments, no funding, carrying-value stakes) - per FD share cons / mark / high ($) [memo; superseded by shared bridge when BridgeFix=1] | B62: =PF_PS1x -> 16.751694 | C62: =PF_PS2x -> 25.408987 | D62: =PF_PS3x -> 39.636842 | E62: =CHOOSE(DilMethod,SUMPRODUCT(V_TrO,V_TrRT)/1000,SUMPRODUCT((PF_PS1>V_TrPX)*V_TrO*V_TrRT)/1000,SUMPRODUCT(((V_TrO*V_TrRT/1000*PF_PS1-((CVDebtBasis=1)*V_TrO+(CVDebtBasis>=2)*V_TrB))>0)*(V_TrO*V_TrRT/1000*PF_PS1-((CVDebtBasis=1)*V_TrO+(CVDebtBasis>=2)*V_TrB)))/PF_PS1) -> 0 | F62: <- convert shares at conservative floor price (M)
A63: HEADLINE equity floor per share - SHARED bridge identical to DCF (OffBSWt x commitments, converts carrying, cash, DR placeholder, V_SOTP, funding cash & shares at the HEADLINE issue-price basis PTBasis); BridgeFix=0 -> legacy cons | B63: =IF(BridgeFix=1,IF(AND(PTBasis=1,FP_On=1),PF_PSSC,PF_PSH),PF_PS1x) -> 24.250164
A64: Base DCF EV (live) | B64: =V_EV -> -898.81401
A65: FLAG: DCF EV vs operating asset floor | B65: =IF(V_EV<PF_EV,"FLAG: DCF EV below asset floor","OK: DCF EV above asset floor") -> FLAG: DCF EV below asset floor
G67: Floor price iteration | H67: cons | I67: mark | J67: high | K67: SHARED pre-fund | L67: SHARED post-fund | M67: DCF EV same code (post) | N67: SHARED floor, SELF-CONSISTENT issue price (v) | O67: issue price P
H68: =10 -> 10 | I68: =10 -> 10 | J68: =10 -> 10 | K68: =10 -> 10 | L68: =10 -> 10 | M68: =10 -> 10 | N68: =SharePx -> 242.81 | O68: =SharePx -> 242.81
H69: =MAX(0.01,(PF_EV-V_ODEBT-CHOOSE(DilMethod,0,SUMPRODUCT((H68<=V_TrPX)*((CVDebtBasis=1)*V_TrO+(CVDebtBasis>=2)*V_TrB)),SUMPRODUCT(((CVDebtBasis=1)*V_TrO+(CVDebtBasis>=2)*V_TrB)))+V_CASH+PF_S1)/(V_BASIC+V_RSU+Options*MAX(0,1-OptK/H68)+CHOOSE(DilMethod,SUMPRODUCT(V_TrO,V_TrRT)/1000,SUMPRODUCT((H68>V_TrPX)*V_TrO*V_TrRT)/1000,SUMPRODUCT(((V_TrO*V_TrRT/1000*H68-((CVDebtBasis=1)*V_TrO+(CVDebtBasis>=2)*V_TrB))>0)*(V_TrO*V_TrRT/1000*H68-((CVDebtBasis=1)*V_TrO+(CVDebtBasis>=2)*V_TrB)))/H68))) -> 16.751694 | I69: =MAX(0.01,(PF_EV-V_ODEBT-CHOOSE(DilMethod,0,SUMPRODUCT((I68<=V_TrPX)*((CVDebtBasis=1)*V_TrO+(CVDebtBasis>=2)*V_TrB)),SUMPRODUCT(((CVDebtBasis=1)*V_TrO+(CVDebtBasis>=2)*V_TrB)))+V_CASH+PF_S2)/(V_BASIC+V_RSU+Options*MAX(0,1-OptK/I68)+CHOOSE(DilMethod,SUMPRODUCT(V_TrO,V_TrRT)/1000,SUMPRODUCT((I68>V_TrPX)*V_TrO*V_TrRT)/1000,SUMPRODUCT(((V_TrO*V_TrRT/1000*I68-((CVDebtBasis=1)*V_TrO+(CVDebtBasis>=2)*V_TrB))>0)*(V_TrO*V_TrRT/1000*I68-((CVDebtBasis=1)*V_TrO+(CVDebtBasis>=2)*V_TrB)))/I68))) -> 25.408987 | J69: =MAX(0.01,(PF_EV-V_ODEBT-CHOOSE(DilMethod,0,SUMPRODUCT((J68<=V_TrPX)*((CVDebtBasis=1)*V_TrO+(CVDebtBasis>=2)*V_TrB)),SUMPRODUCT(((CVDebtBasis=1)*V_TrO+(CVDebtBasis>=2)*V_TrB)))+V_CASH+PF_S3)/(V_BASIC+V_RSU+Options*MAX(0,1-OptK/J68)+CHOOSE(DilMethod,SUMPRODUCT(V_TrO,V_TrRT)/1000,SUMPRODUCT((J68>V_TrPX)*V_TrO*V_TrRT)/1000,SUMPRODUCT(((V_TrO*V_TrRT/1000*J68-((CVDebtBasis=1)*V_TrO+(CVDebtBasis>=2)*V_TrB))>0)*(V_TrO*V_TrRT/1000*J68-((CVDebtBasis=1)*V_TrO+(CVDebtBasis>=2)*V_TrB)))/J68))) -> 39.636842 | K69: =MAX(0.01,(PF_EV-OffBSWt*V_OFF-V_ODEBT-CHOOSE(DilMethod,0,SUMPRODUCT((K68<=V_TrPX)*((CVDebtBasis=1)*V_TrO+(CVDebtBasis>=2)*V_TrB)),SUMPRODUCT(((CVDebtBasis=1)*V_TrO+(CVDebtBasis>=2)*V_TrB)))+V_CASH+V_SOTP)/(V_BASIC+V_RSU+Options*MAX(0,1-OptK/K68)+CHOOSE(DilMethod,SUMPRODUCT(V_TrO,V_TrRT)/1000,SUMPRODUCT((K68>V_TrPX)*V_TrO*V_TrRT)/1000,SUMPRODUCT(((V_TrO*V_TrRT/1000*K68-((CVDebtBasis=1)*V_TrO+(CVDebtBasis>=2)*V_TrB))>0)*(V_TrO*V_TrRT/1000*K68-((CVDebtBasis=1)*V_TrO+(CVDebtBasis>=2)*V_TrB)))/K68))) -> 18.764275 | L69: =MAX(0.01,(PF_EV-OffBSWt*V_OFF-V_ODEBT-CHOOSE(DilMethod,0,SUMPRODUCT((L68<=V_TrPX)*((CVDebtBasis=1)*V_TrOP+(CVDebtBasis>=2)*V_TrBP)),SUMPRODUCT(((CVDebtBasis=1)*V_TrOP+(CVDebtBasis>=2)*V_TrBP)))+V_CASH+V_SOTP+V_FPCash)/(V_BASIC+V_FPSh+V_RSU+Options*MAX(0,1-OptK/L68)+CHOOSE(DilMethod,SUMPRODUCT(V_TrOP,V_TrRT)/1000,SUMPRODUCT((L68>V_TrPX)*V_TrOP*V_TrRT)/1000,SUMPRODUCT(((V_TrOP*V_TrRT/1000*L68-((CVDebtBasis=1)*V_TrOP+(CVDebtBasis>=2)*V_TrBP))>0)*(V_TrOP*V_TrRT/1000*L68-((CVDebtBasis=1)*V_TrOP+(CVDebtBasis>=2)*V_TrBP)))/L68))) -> 91.638369 | M69: =MAX(0.01,(V_EV-OffBSWt*V_OFF-V_ODEBT-CHOOSE(DilMethod,0,SUMPRODUCT((M68<=V_TrPX)*((CVDebtBasis=1)*V_TrOP+(CVDebtBasis>=2)*V_TrBP)),SUMPRODUCT(((CVDebtBasis=1)*V_TrOP+(CVDebtBasis>=2)*V_TrBP)))+V_CASH+V_SOTP+V_FPCash)/(V_BASIC+V_FPSh+V_RSU+Options*MAX(0,1-OptK/M68)+CHOOSE(DilMethod,SUMPRODUCT(V_TrOP,V_TrRT)/1000,SUMPRODUCT((M68>V_TrPX)*V_TrOP*V_TrRT)/1000,SUMPRODUCT(((V_TrOP*V_TrRT/1000*M68-((CVDebtBasis=1)*V_TrOP+(CVDebtBasis>=2)*V_TrBP))>0)*(V_TrOP*V_TrRT/1000*M68-((CVDebtBasis=1)*V_TrOP+(CVDebtBasis>=2)*V_TrBP)))/M68))) -> 78.701021 | N69: =MAX(0.01,((PF_EV-OffBSWt*V_OFF-V_ODEBT-CHOOSE(DilMethod,0,SUMPRODUCT((N68<=V_TrPXsc)*((CVDebtBasis=1)*V_TrOP+(CVDebtBasis>=2)*V_TrBP)),SUMPRODUCT(((CVDebtBasis=1)*V_TrOP+(CVDebtBasis>=2)*V_TrBP)))+V_CASH+V_SOTP+V_FPCash)-MAX(0,V_EqIss0+FP_On*SUMPRODUCT(V_TrWin*V_TrPM*V_TrAcc*(V_TrSpot-((O69)>=V_TrEff)*(1-V_TrPlan))))/((1+Ke)*(1-SC_Disc)))/(V_BASIC+V_RSU+Options*MAX(0,1-OptK/N68)+CHOOSE(DilMethod,SUMPRODUCT(V_TrOP,V_TrRT)/1000,SUMPRODUCT((N68>V_TrPXsc)*V_TrOP*V_TrRT)/1000,SUMPRODUCT(((V_TrOP*V_TrRT/1000*N68-((CVDebtBasis=1)*V_TrOP+(CVDebtBasis>=2)*V_TrBP))>0)*(V_TrOP*V_TrRT/1000*N68-((CVDebtBasis=1)*V_TrOP+(CVDebtBasis>=2)*V_TrBP)))/N68)+FP_On*SUMPRODUCT(V_TrWin*V_TrPM*V_TrRT/1000*((O69)>=V_TrEff)*(1-V_TrPlan)))) -> 44.0391 | O69: =MAX(0.01,N68*(1+Ke)*(1-SC_Disc)) -> 274.3753
H70: =MAX(0.01,(PF_EV-V_ODEBT-CHOOSE(DilMethod,0,SUMPRODUCT((H69<=V_TrPX)*((CVDebtBasis=1)*V_TrO+(CVDebtBasis>=2)*V_TrB)),SUMPRODUCT(((CVDebtBasis=1)*V_TrO+(CVDebtBasis>=2)*V_TrB)))+V_CASH+PF_S1)/(V_BASIC+V_RSU+Options*MAX(0,1-OptK/H69)+CHOOSE(DilMethod,SUMPRODUCT(V_TrO,V_TrRT)/1000,SUMPRODUCT((H69>V_TrPX)*V_TrO*V_TrRT)/1000,SUMPRODUCT(((V_TrO*V_TrRT/1000*H69-((CVDebtBasis=1)*V_TrO+(CVDebtBasis>=2)*V_TrB))>0)*(V_TrO*V_TrRT/1000*H69-((CVDebtBasis=1)*V_TrO+(CVDebtBasis>=2)*V_TrB)))/H69))) -> 16.751694 | I70: =MAX(0.01,(PF_EV-V_ODEBT-CHOOSE(DilMethod,0,SUMPRODUCT((I69<=V_TrPX)*((CVDebtBasis=1)*V_TrO+(CVDebtBasis>=2)*V_TrB)),SUMPRODUCT(((CVDebtBasis=1)*V_TrO+(CVDebtBasis>=2)*V_TrB)))+V_CASH+PF_S2)/(V_BASIC+V_RSU+Options*MAX(0,1-OptK/I69)+CHOOSE(DilMethod,SUMPRODUCT(V_TrO,V_TrRT)/1000,SUMPRODUCT((I69>V_TrPX)*V_TrO*V_TrRT)/1000,SUMPRODUCT(((V_TrO*V_TrRT/1000*I69-((CVDebtBasis=1)*V_TrO+(CVDebtBasis>=2)*V_TrB))>0)*(V_TrO*V_TrRT/1000*I69-((CVDebtBasis=1)*V_TrO+(CVDebtBasis>=2)*V_TrB)))/I69))) -> 25.408987 | J70: =MAX(0.01,(PF_EV-V_ODEBT-CHOOSE(DilMethod,0,SUMPRODUCT((J69<=V_TrPX)*((CVDebtBasis=1)*V_TrO+(CVDebtBasis>=2)*V_TrB)),SUMPRODUCT(((CVDebtBasis=1)*V_TrO+(CVDebtBasis>=2)*V_TrB)))+V_CASH+PF_S3)/(V_BASIC+V_RSU+Options*MAX(0,1-OptK/J69)+CHOOSE(DilMethod,SUMPRODUCT(V_TrO,V_TrRT)/1000,SUMPRODUCT((J69>V_TrPX)*V_TrO*V_TrRT)/1000,SUMPRODUCT(((V_TrO*V_TrRT/1000*J69-((CVDebtBasis=1)*V_TrO+(CVDebtBasis>=2)*V_TrB))>0)*(V_TrO*V_TrRT/1000*J69-((CVDebtBasis=1)*V_TrO+(CVDebtBasis>=2)*V_TrB)))/J69))) -> 39.636842 | K70: =MAX(0.01,(PF_EV-OffBSWt*V_OFF-V_ODEBT-CHOOSE(DilMethod,0,SUMPRODUCT((K69<=V_TrPX)*((CVDebtBasis=1)*V_TrO+(CVDebtBasis>=2)*V_TrB)),SUMPRODUCT(((CVDebtBasis=1)*V_TrO+(CVDebtBasis>=2)*V_TrB)))+V_CASH+V_SOTP)/(V_BASIC+V_RSU+Options*MAX(0,1-OptK/K69)+CHOOSE(DilMethod,SUMPRODUCT(V_TrO,V_TrRT)/1000,SUMPRODUCT((K69>V_TrPX)*V_TrO*V_TrRT)/1000,SUMPRODUCT(((V_TrO*V_TrRT/1000*K69-((CVDebtBasis=1)*V_TrO+(CVDebtBasis>=2)*V_TrB))>0)*(V_TrO*V_TrRT/1000*K69-((CVDebtBasis=1)*V_TrO+(CVDebtBasis>=2)*V_TrB)))/K69))) -> 18.764275 | L70: =MAX(0.01,(PF_EV-OffBSWt*V_OFF-V_ODEBT-CHOOSE(DilMethod,0,SUMPRODUCT((L69<=V_TrPX)*((CVDebtBasis=1)*V_TrOP+(CVDebtBasis>=2)*V_TrBP)),SUMPRODUCT(((CVDebtBasis=1)*V_TrOP+(CVDebtBasis>=2)*V_TrBP)))+V_CASH+V_SOTP+V_FPCash)/(V_BASIC+V_FPSh+V_RSU+Options*MAX(0,1-OptK/L69)+CHOOSE(DilMethod,SUMPRODUCT(V_TrOP,V_TrRT)/1000,SUMPRODUCT((L69>V_TrPX)*V_TrOP*V_TrRT)/1000,SUMPRODUCT(((V_TrOP*V_TrRT/1000*L69-((CVDebtBasis=1)*V_TrOP+(CVDebtBasis>=2)*V_TrBP))>0)*(V_TrOP*V_TrRT/1000*L69-((CVDebtBasis=1)*V_TrOP+(CVDebtBasis>=2)*V_TrBP)))/L69))) -> 91.499621 | M70: =MAX(0.01,(V_EV-OffBSWt*V_OFF-V_ODEBT-CHOOSE(DilMethod,0,SUMPRODUCT((M69<=V_TrPX)*((CVDebtBasis=1)*V_TrOP+(CVDebtBasis>=2)*V_TrBP)),SUMPRODUCT(((CVDebtBasis=1)*V_TrOP+(CVDebtBasis>=2)*V_TrBP)))+V_CASH+V_SOTP+V_FPCash)/(V_BASIC+V_FPSh+V_RSU+Options*MAX(0,1-OptK/M69)+CHOOSE(DilMethod,SUMPRODUCT(V_TrOP,V_TrRT)/1000,SUMPRODUCT((M69>V_TrPX)*V_TrOP*V_TrRT)/1000,SUMPRODUCT(((V_TrOP*V_TrRT/1000*M69-((CVDebtBasis=1)*V_TrOP+(CVDebtBasis>=2)*V_TrBP))>0)*(V_TrOP*V_TrRT/1000*M69-((CVDebtBasis=1)*V_TrOP+(CVDebtBasis>=2)*V_TrBP)))/M69))) -> 78.645427 | N70: =MAX(0.01,((PF_EV-OffBSWt*V_OFF-V_ODEBT-CHOOSE(DilMethod,0,SUMPRODUCT((N69<=V_TrPXsc)*((CVDebtBasis=1)*V_TrOP+(CVDebtBasis>=2)*V_TrBP)),SUMPRODUCT(((CVDebtBasis=1)*V_TrOP+(CVDebtBasis>=2)*V_TrBP)))+V_CASH+V_SOTP+V_FPCash)-MAX(0,V_EqIss0+FP_On*SUMPRODUCT(V_TrWin*V_TrPM*V_TrAcc*(V_TrSpot-((O70)>=V_TrEff)*(1-V_TrPlan))))/((1+Ke)*(1-SC_Disc)))/(V_BASIC+V_RSU+Options*MAX(0,1-OptK/N69)+CHOOSE(DilMethod,SUMPRODUCT(V_TrOP,V_TrRT)/1000,SUMPRODUCT((N69>V_TrPXsc)*V_TrOP*V_TrRT)/1000,SUMPRODUCT(((V_TrOP*V_TrRT/1000*N69-((CVDebtBasis=1)*V_TrOP+(CVDebtBasis>=2)*V_TrBP))>0)*(V_TrOP*V_TrRT/1000*N69-((CVDebtBasis=1)*V_TrOP+(CVDebtBasis>=2)*V_TrBP)))/N69)+FP_On*SUMPRODUCT(V_TrWin*V_TrPM*V_TrRT/1000*((O70)>=V_TrEff)*(1-V_TrPlan)))) -> 24.250164 | O70: =MAX(0.01,N69*(1+Ke)*(1-SC_Disc)) -> 49.764182
H71: =MAX(0.01,(PF_EV-V_ODEBT-CHOOSE(DilMethod,0,SUMPRODUCT((H70<=V_TrPX)*((CVDebtBasis=1)*V_TrO+(CVDebtBasis>=2)*V_TrB)),SUMPRODUCT(((CVDebtBasis=1)*V_TrO+(CVDebtBasis>=2)*V_TrB)))+V_CASH+PF_S1)/(V_BASIC+V_RSU+Options*MAX(0,1-OptK/H70)+CHOOSE(DilMethod,SUMPRODUCT(V_TrO,V_TrRT)/1000,SUMPRODUCT((H70>V_TrPX)*V_TrO*V_TrRT)/1000,SUMPRODUCT(((V_TrO*V_TrRT/1000*H70-((CVDebtBasis=1)*V_TrO+(CVDebtBasis>=2)*V_TrB))>0)*(V_TrO*V_TrRT/1000*H70-((CVDebtBasis=1)*V_TrO+(CVDebtBasis>=2)*V_TrB)))/H70))) -> 16.751694 | I71: =MAX(0.01,(PF_EV-V_ODEBT-CHOOSE(DilMethod,0,SUMPRODUCT((I70<=V_TrPX)*((CVDebtBasis=1)*V_TrO+(CVDebtBasis>=2)*V_TrB)),SUMPRODUCT(((CVDebtBasis=1)*V_TrO+(CVDebtBasis>=2)*V_TrB)))+V_CASH+PF_S2)/(V_BASIC+V_RSU+Options*MAX(0,1-OptK/I70)+CHOOSE(DilMethod,SUMPRODUCT(V_TrO,V_TrRT)/1000,SUMPRODUCT((I70>V_TrPX)*V_TrO*V_TrRT)/1000,SUMPRODUCT(((V_TrO*V_TrRT/1000*I70-((CVDebtBasis=1)*V_TrO+(CVDebtBasis>=2)*V_TrB))>0)*(V_TrO*V_TrRT/1000*I70-((CVDebtBasis=1)*V_TrO+(CVDebtBasis>=2)*V_TrB)))/I70))) -> 25.408987 | J71: =MAX(0.01,(PF_EV-V_ODEBT-CHOOSE(DilMethod,0,SUMPRODUCT((J70<=V_TrPX)*((CVDebtBasis=1)*V_TrO+(CVDebtBasis>=2)*V_TrB)),SUMPRODUCT(((CVDebtBasis=1)*V_TrO+(CVDebtBasis>=2)*V_TrB)))+V_CASH+PF_S3)/(V_BASIC+V_RSU+Options*MAX(0,1-OptK/J70)+CHOOSE(DilMethod,SUMPRODUCT(V_TrO,V_TrRT)/1000,SUMPRODUCT((J70>V_TrPX)*V_TrO*V_TrRT)/1000,SUMPRODUCT(((V_TrO*V_TrRT/1000*J70-((CVDebtBasis=1)*V_TrO+(CVDebtBasis>=2)*V_TrB))>0)*(V_TrO*V_TrRT/1000*J70-((CVDebtBasis=1)*V_TrO+(CVDebtBasis>=2)*V_TrB)))/J70))) -> 39.636842 | K71: =MAX(0.01,(PF_EV-OffBSWt*V_OFF-V_ODEBT-CHOOSE(DilMethod,0,SUMPRODUCT((K70<=V_TrPX)*((CVDebtBasis=1)*V_TrO+(CVDebtBasis>=2)*V_TrB)),SUMPRODUCT(((CVDebtBasis=1)*V_TrO+(CVDebtBasis>=2)*V_TrB)))+V_CASH+V_SOTP)/(V_BASIC+V_RSU+Options*MAX(0,1-OptK/K70)+CHOOSE(DilMethod,SUMPRODUCT(V_TrO,V_TrRT)/1000,SUMPRODUCT((K70>V_TrPX)*V_TrO*V_TrRT)/1000,SUMPRODUCT(((V_TrO*V_TrRT/1000*K70-((CVDebtBasis=1)*V_TrO+(CVDebtBasis>=2)*V_TrB))>0)*(V_TrO*V_TrRT/1000*K70-((CVDebtBasis=1)*V_TrO+(CVDebtBasis>=2)*V_TrB)))/K70))) -> 18.764275 | L71: =MAX(0.01,(PF_EV-OffBSWt*V_OFF-V_ODEBT-CHOOSE(DilMethod,0,SUMPRODUCT((L70<=V_TrPX)*((CVDebtBasis=1)*V_TrOP+(CVDebtBasis>=2)*V_TrBP)),SUMPRODUCT(((CVDebtBasis=1)*V_TrOP+(CVDebtBasis>=2)*V_TrBP)))+V_CASH+V_SOTP+V_FPCash)/(V_BASIC+V_FPSh+V_RSU+Options*MAX(0,1-OptK/L70)+CHOOSE(DilMethod,SUMPRODUCT(V_TrOP,V_TrRT)/1000,SUMPRODUCT((L70>V_TrPX)*V_TrOP*V_TrRT)/1000,SUMPRODUCT(((V_TrOP*V_TrRT/1000*L70-((CVDebtBasis=1)*V_TrOP+(CVDebtBasis>=2)*V_TrBP))>0)*(V_TrOP*V_TrRT/1000*L70-((CVDebtBasis=1)*V_TrOP+(CVDebtBasis>=2)*V_TrBP)))/L70))) -> 91.501406 | M71: =MAX(0.01,(V_EV-OffBSWt*V_OFF-V_ODEBT-CHOOSE(DilMethod,0,SUMPRODUCT((M70<=V_TrPX)*((CVDebtBasis=1)*V_TrOP+(CVDebtBasis>=2)*V_TrBP)),SUMPRODUCT(((CVDebtBasis=1)*V_TrOP+(CVDebtBasis>=2)*V_TrBP)))+V_CASH+V_SOTP+V_FPCash)/(V_BASIC+V_FPSh+V_RSU+Options*MAX(0,1-OptK/M70)+CHOOSE(DilMethod,SUMPRODUCT(V_TrOP,V_TrRT)/1000,SUMPRODUCT((M70>V_TrPX)*V_TrOP*V_TrRT)/1000,SUMPRODUCT(((V_TrOP*V_TrRT/1000*M70-((CVDebtBasis=1)*V_TrOP+(CVDebtBasis>=2)*V_TrBP))>0)*(V_TrOP*V_TrRT/1000*M70-((CVDebtBasis=1)*V_TrOP+(CVDebtBasis>=2)*V_TrBP)))/M70))) -> 78.645427 | N71: =MAX(0.01,((PF_EV-OffBSWt*V_OFF-V_ODEBT-CHOOSE(DilMethod,0,SUMPRODUCT((N70<=V_TrPXsc)*((CVDebtBasis=1)*V_TrOP+(CVDebtBasis>=2)*V_TrBP)),SUMPRODUCT(((CVDebtBasis=1)*V_TrOP+(CVDebtBasis>=2)*V_TrBP)))+V_CASH+V_SOTP+V_FPCash)-MAX(0,V_EqIss0+FP_On*SUMPRODUCT(V_TrWin*V_TrPM*V_TrAcc*(V_TrSpot-((O71)>=V_TrEff)*(1-V_TrPlan))))/((1+Ke)*(1-SC_Disc)))/(V_BASIC+V_RSU+Options*MAX(0,1-OptK/N70)+CHOOSE(DilMethod,SUMPRODUCT(V_TrOP,V_TrRT)/1000,SUMPRODUCT((N70>V_TrPXsc)*V_TrOP*V_TrRT)/1000,SUMPRODUCT(((V_TrOP*V_TrRT/1000*N70-((CVDebtBasis=1)*V_TrOP+(CVDebtBasis>=2)*V_TrBP))>0)*(V_TrOP*V_TrRT/1000*N70-((CVDebtBasis=1)*V_TrOP+(CVDebtBasis>=2)*V_TrBP)))/N70)+FP_On*SUMPRODUCT(V_TrWin*V_TrPM*V_TrRT/1000*((O71)>=V_TrEff)*(1-V_TrPlan)))) -> 24.250164 | O71: =MAX(0.01,N70*(1+Ke)*(1-SC_Disc)) -> 27.402685
H72: =MAX(0.01,(PF_EV-V_ODEBT-CHOOSE(DilMethod,0,SUMPRODUCT((H71<=V_TrPX)*((CVDebtBasis=1)*V_TrO+(CVDebtBasis>=2)*V_TrB)),SUMPRODUCT(((CVDebtBasis=1)*V_TrO+(CVDebtBasis>=2)*V_TrB)))+V_CASH+PF_S1)/(V_BASIC+V_RSU+Options*MAX(0,1-OptK/H71)+CHOOSE(DilMethod,SUMPRODUCT(V_TrO,V_TrRT)/1000,SUMPRODUCT((H71>V_TrPX)*V_TrO*V_TrRT)/1000,SUMPRODUCT(((V_TrO*V_TrRT/1000*H71-((CVDebtBasis=1)*V_TrO+(CVDebtBasis>=2)*V_TrB))>0)*(V_TrO*V_TrRT/1000*H71-((CVDebtBasis=1)*V_TrO+(CVDebtBasis>=2)*V_TrB)))/H71))) -> 16.751694 | I72: =MAX(0.01,(PF_EV-V_ODEBT-CHOOSE(DilMethod,0,SUMPRODUCT((I71<=V_TrPX)*((CVDebtBasis=1)*V_TrO+(CVDebtBasis>=2)*V_TrB)),SUMPRODUCT(((CVDebtBasis=1)*V_TrO+(CVDebtBasis>=2)*V_TrB)))+V_CASH+PF_S2)/(V_BASIC+V_RSU+Options*MAX(0,1-OptK/I71)+CHOOSE(DilMethod,SUMPRODUCT(V_TrO,V_TrRT)/1000,SUMPRODUCT((I71>V_TrPX)*V_TrO*V_TrRT)/1000,SUMPRODUCT(((V_TrO*V_TrRT/1000*I71-((CVDebtBasis=1)*V_TrO+(CVDebtBasis>=2)*V_TrB))>0)*(V_TrO*V_TrRT/1000*I71-((CVDebtBasis=1)*V_TrO+(CVDebtBasis>=2)*V_TrB)))/I71))) -> 25.408987 | J72: =MAX(0.01,(PF_EV-V_ODEBT-CHOOSE(DilMethod,0,SUMPRODUCT((J71<=V_TrPX)*((CVDebtBasis=1)*V_TrO+(CVDebtBasis>=2)*V_TrB)),SUMPRODUCT(((CVDebtBasis=1)*V_TrO+(CVDebtBasis>=2)*V_TrB)))+V_CASH+PF_S3)/(V_BASIC+V_RSU+Options*MAX(0,1-OptK/J71)+CHOOSE(DilMethod,SUMPRODUCT(V_TrO,V_TrRT)/1000,SUMPRODUCT((J71>V_TrPX)*V_TrO*V_TrRT)/1000,SUMPRODUCT(((V_TrO*V_TrRT/1000*J71-((CVDebtBasis=1)*V_TrO+(CVDebtBasis>=2)*V_TrB))>0)*(V_TrO*V_TrRT/1000*J71-((CVDebtBasis=1)*V_TrO+(CVDebtBasis>=2)*V_TrB)))/J71))) -> 39.636842 | K72: =MAX(0.01,(PF_EV-OffBSWt*V_OFF-V_ODEBT-CHOOSE(DilMethod,0,SUMPRODUCT((K71<=V_TrPX)*((CVDebtBasis=1)*V_TrO+(CVDebtBasis>=2)*V_TrB)),SUMPRODUCT(((CVDebtBasis=1)*V_TrO+(CVDebtBasis>=2)*V_TrB)))+V_CASH+V_SOTP)/(V_BASIC+V_RSU+Options*MAX(0,1-OptK/K71)+CHOOSE(DilMethod,SUMPRODUCT(V_TrO,V_TrRT)/1000,SUMPRODUCT((K71>V_TrPX)*V_TrO*V_TrRT)/1000,SUMPRODUCT(((V_TrO*V_TrRT/1000*K71-((CVDebtBasis=1)*V_TrO+(CVDebtBasis>=2)*V_TrB))>0)*(V_TrO*V_TrRT/1000*K71-((CVDebtBasis=1)*V_TrO+(CVDebtBasis>=2)*V_TrB)))/K71))) -> 18.764275 | L72: =MAX(0.01,(PF_EV-OffBSWt*V_OFF-V_ODEBT-CHOOSE(DilMethod,0,SUMPRODUCT((L71<=V_TrPX)*((CVDebtBasis=1)*V_TrOP+(CVDebtBasis>=2)*V_TrBP)),SUMPRODUCT(((CVDebtBasis=1)*V_TrOP+(CVDebtBasis>=2)*V_TrBP)))+V_CASH+V_SOTP+V_FPCash)/(V_BASIC+V_FPSh+V_RSU+Options*MAX(0,1-OptK/L71)+CHOOSE(DilMethod,SUMPRODUCT(V_TrOP,V_TrRT)/1000,SUMPRODUCT((L71>V_TrPX)*V_TrOP*V_TrRT)/1000,SUMPRODUCT(((V_TrOP*V_TrRT/1000*L71-((CVDebtBasis=1)*V_TrOP+(CVDebtBasis>=2)*V_TrBP))>0)*(V_TrOP*V_TrRT/1000*L71-((CVDebtBasis=1)*V_TrOP+(CVDebtBasis>=2)*V_TrBP)))/L71))) -> 91.501383 | M72: =MAX(0.01,(V_EV-OffBSWt*V_OFF-V_ODEBT-CHOOSE(DilMethod,0,SUMPRODUCT((M71<=V_TrPX)*((CVDebtBasis=1)*V_TrOP+(CVDebtBasis>=2)*V_TrBP)),SUMPRODUCT(((CVDebtBasis=1)*V_TrOP+(CVDebtBasis>=2)*V_TrBP)))+V_CASH+V_SOTP+V_FPCash)/(V_BASIC+V_FPSh+V_RSU+Options*MAX(0,1-OptK/M71)+CHOOSE(DilMethod,SUMPRODUCT(V_TrOP,V_TrRT)/1000,SUMPRODUCT((M71>V_TrPX)*V_TrOP*V_TrRT)/1000,SUMPRODUCT(((V_TrOP*V_TrRT/1000*M71-((CVDebtBasis=1)*V_TrOP+(CVDebtBasis>=2)*V_TrBP))>0)*(V_TrOP*V_TrRT/1000*M71-((CVDebtBasis=1)*V_TrOP+(CVDebtBasis>=2)*V_TrBP)))/M71))) -> 78.645427 | N72: =MAX(0.01,((PF_EV-OffBSWt*V_OFF-V_ODEBT-CHOOSE(DilMethod,0,SUMPRODUCT((N71<=V_TrPXsc)*((CVDebtBasis=1)*V_TrOP+(CVDebtBasis>=2)*V_TrBP)),SUMPRODUCT(((CVDebtBasis=1)*V_TrOP+(CVDebtBasis>=2)*V_TrBP)))+V_CASH+V_SOTP+V_FPCash)-MAX(0,V_EqIss0+FP_On*SUMPRODUCT(V_TrWin*V_TrPM*V_TrAcc*(V_TrSpot-((O72)>=V_TrEff)*(1-V_TrPlan))))/((1+Ke)*(1-SC_Disc)))/(V_BASIC+V_RSU+Options*MAX(0,1-OptK/N71)+CHOOSE(DilMethod,SUMPRODUCT(V_TrOP,V_TrRT)/1000,SUMPRODUCT((N71>V_TrPXsc)*V_TrOP*V_TrRT)/1000,SUMPRODUCT(((V_TrOP*V_TrRT/1000*N71-((CVDebtBasis=1)*V_TrOP+(CVDebtBasis>=2)*V_TrBP))>0)*(V_TrOP*V_TrRT/1000*N71-((CVDebtBasis=1)*V_TrOP+(CVDebtBasis>=2)*V_TrBP)))/N71)+FP_On*SUMPRODUCT(V_TrWin*V_TrPM*V_TrRT/1000*((O72)>=V_TrEff)*(1-V_TrPlan)))) -> 24.250164 | O72: =MAX(0.01,N71*(1+Ke)*(1-SC_Disc)) -> 27.402685
H73: =MAX(0.01,(PF_EV-V_ODEBT-CHOOSE(DilMethod,0,SUMPRODUCT((H72<=V_TrPX)*((CVDebtBasis=1)*V_TrO+(CVDebtBasis>=2)*V_TrB)),SUMPRODUCT(((CVDebtBasis=1)*V_TrO+(CVDebtBasis>=2)*V_TrB)))+V_CASH+PF_S1)/(V_BASIC+V_RSU+Options*MAX(0,1-OptK/H72)+CHOOSE(DilMethod,SUMPRODUCT(V_TrO,V_TrRT)/1000,SUMPRODUCT((H72>V_TrPX)*V_TrO*V_TrRT)/1000,SUMPRODUCT(((V_TrO*V_TrRT/1000*H72-((CVDebtBasis=1)*V_TrO+(CVDebtBasis>=2)*V_TrB))>0)*(V_TrO*V_TrRT/1000*H72-((CVDebtBasis=1)*V_TrO+(CVDebtBasis>=2)*V_TrB)))/H72))) -> 16.751694 | I73: =MAX(0.01,(PF_EV-V_ODEBT-CHOOSE(DilMethod,0,SUMPRODUCT((I72<=V_TrPX)*((CVDebtBasis=1)*V_TrO+(CVDebtBasis>=2)*V_TrB)),SUMPRODUCT(((CVDebtBasis=1)*V_TrO+(CVDebtBasis>=2)*V_TrB)))+V_CASH+PF_S2)/(V_BASIC+V_RSU+Options*MAX(0,1-OptK/I72)+CHOOSE(DilMethod,SUMPRODUCT(V_TrO,V_TrRT)/1000,SUMPRODUCT((I72>V_TrPX)*V_TrO*V_TrRT)/1000,SUMPRODUCT(((V_TrO*V_TrRT/1000*I72-((CVDebtBasis=1)*V_TrO+(CVDebtBasis>=2)*V_TrB))>0)*(V_TrO*V_TrRT/1000*I72-((CVDebtBasis=1)*V_TrO+(CVDebtBasis>=2)*V_TrB)))/I72))) -> 25.408987 | J73: =MAX(0.01,(PF_EV-V_ODEBT-CHOOSE(DilMethod,0,SUMPRODUCT((J72<=V_TrPX)*((CVDebtBasis=1)*V_TrO+(CVDebtBasis>=2)*V_TrB)),SUMPRODUCT(((CVDebtBasis=1)*V_TrO+(CVDebtBasis>=2)*V_TrB)))+V_CASH+PF_S3)/(V_BASIC+V_RSU+Options*MAX(0,1-OptK/J72)+CHOOSE(DilMethod,SUMPRODUCT(V_TrO,V_TrRT)/1000,SUMPRODUCT((J72>V_TrPX)*V_TrO*V_TrRT)/1000,SUMPRODUCT(((V_TrO*V_TrRT/1000*J72-((CVDebtBasis=1)*V_TrO+(CVDebtBasis>=2)*V_TrB))>0)*(V_TrO*V_TrRT/1000*J72-((CVDebtBasis=1)*V_TrO+(CVDebtBasis>=2)*V_TrB)))/J72))) -> 39.636842 | K73: =MAX(0.01,(PF_EV-OffBSWt*V_OFF-V_ODEBT-CHOOSE(DilMethod,0,SUMPRODUCT((K72<=V_TrPX)*((CVDebtBasis=1)*V_TrO+(CVDebtBasis>=2)*V_TrB)),SUMPRODUCT(((CVDebtBasis=1)*V_TrO+(CVDebtBasis>=2)*V_TrB)))+V_CASH+V_SOTP)/(V_BASIC+V_RSU+Options*MAX(0,1-OptK/K72)+CHOOSE(DilMethod,SUMPRODUCT(V_TrO,V_TrRT)/1000,SUMPRODUCT((K72>V_TrPX)*V_TrO*V_TrRT)/1000,SUMPRODUCT(((V_TrO*V_TrRT/1000*K72-((CVDebtBasis=1)*V_TrO+(CVDebtBasis>=2)*V_TrB))>0)*(V_TrO*V_TrRT/1000*K72-((CVDebtBasis=1)*V_TrO+(CVDebtBasis>=2)*V_TrB)))/K72))) -> 18.764275 | L73: =MAX(0.01,(PF_EV-OffBSWt*V_OFF-V_ODEBT-CHOOSE(DilMethod,0,SUMPRODUCT((L72<=V_TrPX)*((CVDebtBasis=1)*V_TrOP+(CVDebtBasis>=2)*V_TrBP)),SUMPRODUCT(((CVDebtBasis=1)*V_TrOP+(CVDebtBasis>=2)*V_TrBP)))+V_CASH+V_SOTP+V_FPCash)/(V_BASIC+V_FPSh+V_RSU+Options*MAX(0,1-OptK/L72)+CHOOSE(DilMethod,SUMPRODUCT(V_TrOP,V_TrRT)/1000,SUMPRODUCT((L72>V_TrPX)*V_TrOP*V_TrRT)/1000,SUMPRODUCT(((V_TrOP*V_TrRT/1000*L72-((CVDebtBasis=1)*V_TrOP+(CVDebtBasis>=2)*V_TrBP))>0)*(V_TrOP*V_TrRT/1000*L72-((CVDebtBasis=1)*V_TrOP+(CVDebtBasis>=2)*V_TrBP)))/L72))) -> 91.501384 | M73: =MAX(0.01,(V_EV-OffBSWt*V_OFF-V_ODEBT-CHOOSE(DilMethod,0,SUMPRODUCT((M72<=V_TrPX)*((CVDebtBasis=1)*V_TrOP+(CVDebtBasis>=2)*V_TrBP)),SUMPRODUCT(((CVDebtBasis=1)*V_TrOP+(CVDebtBasis>=2)*V_TrBP)))+V_CASH+V_SOTP+V_FPCash)/(V_BASIC+V_FPSh+V_RSU+Options*MAX(0,1-OptK/M72)+CHOOSE(DilMethod,SUMPRODUCT(V_TrOP,V_TrRT)/1000,SUMPRODUCT((M72>V_TrPX)*V_TrOP*V_TrRT)/1000,SUMPRODUCT(((V_TrOP*V_TrRT/1000*M72-((CVDebtBasis=1)*V_TrOP+(CVDebtBasis>=2)*V_TrBP))>0)*(V_TrOP*V_TrRT/1000*M72-((CVDebtBasis=1)*V_TrOP+(CVDebtBasis>=2)*V_TrBP)))/M72))) -> 78.645427 | N73: =MAX(0.01,((PF_EV-OffBSWt*V_OFF-V_ODEBT-CHOOSE(DilMethod,0,SUMPRODUCT((N72<=V_TrPXsc)*((CVDebtBasis=1)*V_TrOP+(CVDebtBasis>=2)*V_TrBP)),SUMPRODUCT(((CVDebtBasis=1)*V_TrOP+(CVDebtBasis>=2)*V_TrBP)))+V_CASH+V_SOTP+V_FPCash)-MAX(0,V_EqIss0+FP_On*SUMPRODUCT(V_TrWin*V_TrPM*V_TrAcc*(V_TrSpot-((O73)>=V_TrEff)*(1-V_TrPlan))))/((1+Ke)*(1-SC_Disc)))/(V_BASIC+V_RSU+Options*MAX(0,1-OptK/N72)+CHOOSE(DilMethod,SUMPRODUCT(V_TrOP,V_TrRT)/1000,SUMPRODUCT((N72>V_TrPXsc)*V_TrOP*V_TrRT)/1000,SUMPRODUCT(((V_TrOP*V_TrRT/1000*N72-((CVDebtBasis=1)*V_TrOP+(CVDebtBasis>=2)*V_TrBP))>0)*(V_TrOP*V_TrRT/1000*N72-((CVDebtBasis=1)*V_TrOP+(CVDebtBasis>=2)*V_TrBP)))/N72)+FP_On*SUMPRODUCT(V_TrWin*V_TrPM*V_TrRT/1000*((O73)>=V_TrEff)*(1-V_TrPlan)))) -> 24.250164 | O73: =MAX(0.01,N72*(1+Ke)*(1-SC_Disc)) -> 27.402685
H74: =MAX(0.01,(PF_EV-V_ODEBT-CHOOSE(DilMethod,0,SUMPRODUCT((H73<=V_TrPX)*((CVDebtBasis=1)*V_TrO+(CVDebtBasis>=2)*V_TrB)),SUMPRODUCT(((CVDebtBasis=1)*V_TrO+(CVDebtBasis>=2)*V_TrB)))+V_CASH+PF_S1)/(V_BASIC+V_RSU+Options*MAX(0,1-OptK/H73)+CHOOSE(DilMethod,SUMPRODUCT(V_TrO,V_TrRT)/1000,SUMPRODUCT((H73>V_TrPX)*V_TrO*V_TrRT)/1000,SUMPRODUCT(((V_TrO*V_TrRT/1000*H73-((CVDebtBasis=1)*V_TrO+(CVDebtBasis>=2)*V_TrB))>0)*(V_TrO*V_TrRT/1000*H73-((CVDebtBasis=1)*V_TrO+(CVDebtBasis>=2)*V_TrB)))/H73))) -> 16.751694 | I74: =MAX(0.01,(PF_EV-V_ODEBT-CHOOSE(DilMethod,0,SUMPRODUCT((I73<=V_TrPX)*((CVDebtBasis=1)*V_TrO+(CVDebtBasis>=2)*V_TrB)),SUMPRODUCT(((CVDebtBasis=1)*V_TrO+(CVDebtBasis>=2)*V_TrB)))+V_CASH+PF_S2)/(V_BASIC+V_RSU+Options*MAX(0,1-OptK/I73)+CHOOSE(DilMethod,SUMPRODUCT(V_TrO,V_TrRT)/1000,SUMPRODUCT((I73>V_TrPX)*V_TrO*V_TrRT)/1000,SUMPRODUCT(((V_TrO*V_TrRT/1000*I73-((CVDebtBasis=1)*V_TrO+(CVDebtBasis>=2)*V_TrB))>0)*(V_TrO*V_TrRT/1000*I73-((CVDebtBasis=1)*V_TrO+(CVDebtBasis>=2)*V_TrB)))/I73))) -> 25.408987 | J74: =MAX(0.01,(PF_EV-V_ODEBT-CHOOSE(DilMethod,0,SUMPRODUCT((J73<=V_TrPX)*((CVDebtBasis=1)*V_TrO+(CVDebtBasis>=2)*V_TrB)),SUMPRODUCT(((CVDebtBasis=1)*V_TrO+(CVDebtBasis>=2)*V_TrB)))+V_CASH+PF_S3)/(V_BASIC+V_RSU+Options*MAX(0,1-OptK/J73)+CHOOSE(DilMethod,SUMPRODUCT(V_TrO,V_TrRT)/1000,SUMPRODUCT((J73>V_TrPX)*V_TrO*V_TrRT)/1000,SUMPRODUCT(((V_TrO*V_TrRT/1000*J73-((CVDebtBasis=1)*V_TrO+(CVDebtBasis>=2)*V_TrB))>0)*(V_TrO*V_TrRT/1000*J73-((CVDebtBasis=1)*V_TrO+(CVDebtBasis>=2)*V_TrB)))/J73))) -> 39.636842 | K74: =MAX(0.01,(PF_EV-OffBSWt*V_OFF-V_ODEBT-CHOOSE(DilMethod,0,SUMPRODUCT((K73<=V_TrPX)*((CVDebtBasis=1)*V_TrO+(CVDebtBasis>=2)*V_TrB)),SUMPRODUCT(((CVDebtBasis=1)*V_TrO+(CVDebtBasis>=2)*V_TrB)))+V_CASH+V_SOTP)/(V_BASIC+V_RSU+Options*MAX(0,1-OptK/K73)+CHOOSE(DilMethod,SUMPRODUCT(V_TrO,V_TrRT)/1000,SUMPRODUCT((K73>V_TrPX)*V_TrO*V_TrRT)/1000,SUMPRODUCT(((V_TrO*V_TrRT/1000*K73-((CVDebtBasis=1)*V_TrO+(CVDebtBasis>=2)*V_TrB))>0)*(V_TrO*V_TrRT/1000*K73-((CVDebtBasis=1)*V_TrO+(CVDebtBasis>=2)*V_TrB)))/K73))) -> 18.764275 | L74: =MAX(0.01,(PF_EV-OffBSWt*V_OFF-V_ODEBT-CHOOSE(DilMethod,0,SUMPRODUCT((L73<=V_TrPX)*((CVDebtBasis=1)*V_TrOP+(CVDebtBasis>=2)*V_TrBP)),SUMPRODUCT(((CVDebtBasis=1)*V_TrOP+(CVDebtBasis>=2)*V_TrBP)))+V_CASH+V_SOTP+V_FPCash)/(V_BASIC+V_FPSh+V_RSU+Options*MAX(0,1-OptK/L73)+CHOOSE(DilMethod,SUMPRODUCT(V_TrOP,V_TrRT)/1000,SUMPRODUCT((L73>V_TrPX)*V_TrOP*V_TrRT)/1000,SUMPRODUCT(((V_TrOP*V_TrRT/1000*L73-((CVDebtBasis=1)*V_TrOP+(CVDebtBasis>=2)*V_TrBP))>0)*(V_TrOP*V_TrRT/1000*L73-((CVDebtBasis=1)*V_TrOP+(CVDebtBasis>=2)*V_TrBP)))/L73))) -> 91.501384 | M74: =MAX(0.01,(V_EV-OffBSWt*V_OFF-V_ODEBT-CHOOSE(DilMethod,0,SUMPRODUCT((M73<=V_TrPX)*((CVDebtBasis=1)*V_TrOP+(CVDebtBasis>=2)*V_TrBP)),SUMPRODUCT(((CVDebtBasis=1)*V_TrOP+(CVDebtBasis>=2)*V_TrBP)))+V_CASH+V_SOTP+V_FPCash)/(V_BASIC+V_FPSh+V_RSU+Options*MAX(0,1-OptK/M73)+CHOOSE(DilMethod,SUMPRODUCT(V_TrOP,V_TrRT)/1000,SUMPRODUCT((M73>V_TrPX)*V_TrOP*V_TrRT)/1000,SUMPRODUCT(((V_TrOP*V_TrRT/1000*M73-((CVDebtBasis=1)*V_TrOP+(CVDebtBasis>=2)*V_TrBP))>0)*(V_TrOP*V_TrRT/1000*M73-((CVDebtBasis=1)*V_TrOP+(CVDebtBasis>=2)*V_TrBP)))/M73))) -> 78.645427 | N74: =MAX(0.01,((PF_EV-OffBSWt*V_OFF-V_ODEBT-CHOOSE(DilMethod,0,SUMPRODUCT((N73<=V_TrPXsc)*((CVDebtBasis=1)*V_TrOP+(CVDebtBasis>=2)*V_TrBP)),SUMPRODUCT(((CVDebtBasis=1)*V_TrOP+(CVDebtBasis>=2)*V_TrBP)))+V_CASH+V_SOTP+V_FPCash)-MAX(0,V_EqIss0+FP_On*SUMPRODUCT(V_TrWin*V_TrPM*V_TrAcc*(V_TrSpot-((O74)>=V_TrEff)*(1-V_TrPlan))))/((1+Ke)*(1-SC_Disc)))/(V_BASIC+V_RSU+Options*MAX(0,1-OptK/N73)+CHOOSE(DilMethod,SUMPRODUCT(V_TrOP,V_TrRT)/1000,SUMPRODUCT((N73>V_TrPXsc)*V_TrOP*V_TrRT)/1000,SUMPRODUCT(((V_TrOP*V_TrRT/1000*N73-((CVDebtBasis=1)*V_TrOP+(CVDebtBasis>=2)*V_TrBP))>0)*(V_TrOP*V_TrRT/1000*N73-((CVDebtBasis=1)*V_TrOP+(CVDebtBasis>=2)*V_TrBP)))/N73)+FP_On*SUMPRODUCT(V_TrWin*V_TrPM*V_TrRT/1000*((O74)>=V_TrEff)*(1-V_TrPlan)))) -> 24.250164 | O74: =MAX(0.01,N73*(1+Ke)*(1-SC_Disc)) -> 27.402685
H75: =MAX(0.01,(PF_EV-V_ODEBT-CHOOSE(DilMethod,0,SUMPRODUCT((H74<=V_TrPX)*((CVDebtBasis=1)*V_TrO+(CVDebtBasis>=2)*V_TrB)),SUMPRODUCT(((CVDebtBasis=1)*V_TrO+(CVDebtBasis>=2)*V_TrB)))+V_CASH+PF_S1)/(V_BASIC+V_RSU+Options*MAX(0,1-OptK/H74)+CHOOSE(DilMethod,SUMPRODUCT(V_TrO,V_TrRT)/1000,SUMPRODUCT((H74>V_TrPX)*V_TrO*V_TrRT)/1000,SUMPRODUCT(((V_TrO*V_TrRT/1000*H74-((CVDebtBasis=1)*V_TrO+(CVDebtBasis>=2)*V_TrB))>0)*(V_TrO*V_TrRT/1000*H74-((CVDebtBasis=1)*V_TrO+(CVDebtBasis>=2)*V_TrB)))/H74))) -> 16.751694 | I75: =MAX(0.01,(PF_EV-V_ODEBT-CHOOSE(DilMethod,0,SUMPRODUCT((I74<=V_TrPX)*((CVDebtBasis=1)*V_TrO+(CVDebtBasis>=2)*V_TrB)),SUMPRODUCT(((CVDebtBasis=1)*V_TrO+(CVDebtBasis>=2)*V_TrB)))+V_CASH+PF_S2)/(V_BASIC+V_RSU+Options*MAX(0,1-OptK/I74)+CHOOSE(DilMethod,SUMPRODUCT(V_TrO,V_TrRT)/1000,SUMPRODUCT((I74>V_TrPX)*V_TrO*V_TrRT)/1000,SUMPRODUCT(((V_TrO*V_TrRT/1000*I74-((CVDebtBasis=1)*V_TrO+(CVDebtBasis>=2)*V_TrB))>0)*(V_TrO*V_TrRT/1000*I74-((CVDebtBasis=1)*V_TrO+(CVDebtBasis>=2)*V_TrB)))/I74))) -> 25.408987 | J75: =MAX(0.01,(PF_EV-V_ODEBT-CHOOSE(DilMethod,0,SUMPRODUCT((J74<=V_TrPX)*((CVDebtBasis=1)*V_TrO+(CVDebtBasis>=2)*V_TrB)),SUMPRODUCT(((CVDebtBasis=1)*V_TrO+(CVDebtBasis>=2)*V_TrB)))+V_CASH+PF_S3)/(V_BASIC+V_RSU+Options*MAX(0,1-OptK/J74)+CHOOSE(DilMethod,SUMPRODUCT(V_TrO,V_TrRT)/1000,SUMPRODUCT((J74>V_TrPX)*V_TrO*V_TrRT)/1000,SUMPRODUCT(((V_TrO*V_TrRT/1000*J74-((CVDebtBasis=1)*V_TrO+(CVDebtBasis>=2)*V_TrB))>0)*(V_TrO*V_TrRT/1000*J74-((CVDebtBasis=1)*V_TrO+(CVDebtBasis>=2)*V_TrB)))/J74))) -> 39.636842 | K75: =MAX(0.01,(PF_EV-OffBSWt*V_OFF-V_ODEBT-CHOOSE(DilMethod,0,SUMPRODUCT((K74<=V_TrPX)*((CVDebtBasis=1)*V_TrO+(CVDebtBasis>=2)*V_TrB)),SUMPRODUCT(((CVDebtBasis=1)*V_TrO+(CVDebtBasis>=2)*V_TrB)))+V_CASH+V_SOTP)/(V_BASIC+V_RSU+Options*MAX(0,1-OptK/K74)+CHOOSE(DilMethod,SUMPRODUCT(V_TrO,V_TrRT)/1000,SUMPRODUCT((K74>V_TrPX)*V_TrO*V_TrRT)/1000,SUMPRODUCT(((V_TrO*V_TrRT/1000*K74-((CVDebtBasis=1)*V_TrO+(CVDebtBasis>=2)*V_TrB))>0)*(V_TrO*V_TrRT/1000*K74-((CVDebtBasis=1)*V_TrO+(CVDebtBasis>=2)*V_TrB)))/K74))) -> 18.764275 | L75: =MAX(0.01,(PF_EV-OffBSWt*V_OFF-V_ODEBT-CHOOSE(DilMethod,0,SUMPRODUCT((L74<=V_TrPX)*((CVDebtBasis=1)*V_TrOP+(CVDebtBasis>=2)*V_TrBP)),SUMPRODUCT(((CVDebtBasis=1)*V_TrOP+(CVDebtBasis>=2)*V_TrBP)))+V_CASH+V_SOTP+V_FPCash)/(V_BASIC+V_FPSh+V_RSU+Options*MAX(0,1-OptK/L74)+CHOOSE(DilMethod,SUMPRODUCT(V_TrOP,V_TrRT)/1000,SUMPRODUCT((L74>V_TrPX)*V_TrOP*V_TrRT)/1000,SUMPRODUCT(((V_TrOP*V_TrRT/1000*L74-((CVDebtBasis=1)*V_TrOP+(CVDebtBasis>=2)*V_TrBP))>0)*(V_TrOP*V_TrRT/1000*L74-((CVDebtBasis=1)*V_TrOP+(CVDebtBasis>=2)*V_TrBP)))/L74))) -> 91.501384 | M75: =MAX(0.01,(V_EV-OffBSWt*V_OFF-V_ODEBT-CHOOSE(DilMethod,0,SUMPRODUCT((M74<=V_TrPX)*((CVDebtBasis=1)*V_TrOP+(CVDebtBasis>=2)*V_TrBP)),SUMPRODUCT(((CVDebtBasis=1)*V_TrOP+(CVDebtBasis>=2)*V_TrBP)))+V_CASH+V_SOTP+V_FPCash)/(V_BASIC+V_FPSh+V_RSU+Options*MAX(0,1-OptK/M74)+CHOOSE(DilMethod,SUMPRODUCT(V_TrOP,V_TrRT)/1000,SUMPRODUCT((M74>V_TrPX)*V_TrOP*V_TrRT)/1000,SUMPRODUCT(((V_TrOP*V_TrRT/1000*M74-((CVDebtBasis=1)*V_TrOP+(CVDebtBasis>=2)*V_TrBP))>0)*(V_TrOP*V_TrRT/1000*M74-((CVDebtBasis=1)*V_TrOP+(CVDebtBasis>=2)*V_TrBP)))/M74))) -> 78.645427 | N75: =MAX(0.01,((PF_EV-OffBSWt*V_OFF-V_ODEBT-CHOOSE(DilMethod,0,SUMPRODUCT((N74<=V_TrPXsc)*((CVDebtBasis=1)*V_TrOP+(CVDebtBasis>=2)*V_TrBP)),SUMPRODUCT(((CVDebtBasis=1)*V_TrOP+(CVDebtBasis>=2)*V_TrBP)))+V_CASH+V_SOTP+V_FPCash)-MAX(0,V_EqIss0+FP_On*SUMPRODUCT(V_TrWin*V_TrPM*V_TrAcc*(V_TrSpot-((O75)>=V_TrEff)*(1-V_TrPlan))))/((1+Ke)*(1-SC_Disc)))/(V_BASIC+V_RSU+Options*MAX(0,1-OptK/N74)+CHOOSE(DilMethod,SUMPRODUCT(V_TrOP,V_TrRT)/1000,SUMPRODUCT((N74>V_TrPXsc)*V_TrOP*V_TrRT)/1000,SUMPRODUCT(((V_TrOP*V_TrRT/1000*N74-((CVDebtBasis=1)*V_TrOP+(CVDebtBasis>=2)*V_TrBP))>0)*(V_TrOP*V_TrRT/1000*N74-((CVDebtBasis=1)*V_TrOP+(CVDebtBasis>=2)*V_TrBP)))/N74)+FP_On*SUMPRODUCT(V_TrWin*V_TrPM*V_TrRT/1000*((O75)>=V_TrEff)*(1-V_TrPlan)))) -> 24.250164 | O75: =MAX(0.01,N74*(1+Ke)*(1-SC_Disc)) -> 27.402685
H76: =MAX(0.01,(PF_EV-V_ODEBT-CHOOSE(DilMethod,0,SUMPRODUCT((H75<=V_TrPX)*((CVDebtBasis=1)*V_TrO+(CVDebtBasis>=2)*V_TrB)),SUMPRODUCT(((CVDebtBasis=1)*V_TrO+(CVDebtBasis>=2)*V_TrB)))+V_CASH+PF_S1)/(V_BASIC+V_RSU+Options*MAX(0,1-OptK/H75)+CHOOSE(DilMethod,SUMPRODUCT(V_TrO,V_TrRT)/1000,SUMPRODUCT((H75>V_TrPX)*V_TrO*V_TrRT)/1000,SUMPRODUCT(((V_TrO*V_TrRT/1000*H75-((CVDebtBasis=1)*V_TrO+(CVDebtBasis>=2)*V_TrB))>0)*(V_TrO*V_TrRT/1000*H75-((CVDebtBasis=1)*V_TrO+(CVDebtBasis>=2)*V_TrB)))/H75))) -> 16.751694 | I76: =MAX(0.01,(PF_EV-V_ODEBT-CHOOSE(DilMethod,0,SUMPRODUCT((I75<=V_TrPX)*((CVDebtBasis=1)*V_TrO+(CVDebtBasis>=2)*V_TrB)),SUMPRODUCT(((CVDebtBasis=1)*V_TrO+(CVDebtBasis>=2)*V_TrB)))+V_CASH+PF_S2)/(V_BASIC+V_RSU+Options*MAX(0,1-OptK/I75)+CHOOSE(DilMethod,SUMPRODUCT(V_TrO,V_TrRT)/1000,SUMPRODUCT((I75>V_TrPX)*V_TrO*V_TrRT)/1000,SUMPRODUCT(((V_TrO*V_TrRT/1000*I75-((CVDebtBasis=1)*V_TrO+(CVDebtBasis>=2)*V_TrB))>0)*(V_TrO*V_TrRT/1000*I75-((CVDebtBasis=1)*V_TrO+(CVDebtBasis>=2)*V_TrB)))/I75))) -> 25.408987 | J76: =MAX(0.01,(PF_EV-V_ODEBT-CHOOSE(DilMethod,0,SUMPRODUCT((J75<=V_TrPX)*((CVDebtBasis=1)*V_TrO+(CVDebtBasis>=2)*V_TrB)),SUMPRODUCT(((CVDebtBasis=1)*V_TrO+(CVDebtBasis>=2)*V_TrB)))+V_CASH+PF_S3)/(V_BASIC+V_RSU+Options*MAX(0,1-OptK/J75)+CHOOSE(DilMethod,SUMPRODUCT(V_TrO,V_TrRT)/1000,SUMPRODUCT((J75>V_TrPX)*V_TrO*V_TrRT)/1000,SUMPRODUCT(((V_TrO*V_TrRT/1000*J75-((CVDebtBasis=1)*V_TrO+(CVDebtBasis>=2)*V_TrB))>0)*(V_TrO*V_TrRT/1000*J75-((CVDebtBasis=1)*V_TrO+(CVDebtBasis>=2)*V_TrB)))/J75))) -> 39.636842 | K76: =MAX(0.01,(PF_EV-OffBSWt*V_OFF-V_ODEBT-CHOOSE(DilMethod,0,SUMPRODUCT((K75<=V_TrPX)*((CVDebtBasis=1)*V_TrO+(CVDebtBasis>=2)*V_TrB)),SUMPRODUCT(((CVDebtBasis=1)*V_TrO+(CVDebtBasis>=2)*V_TrB)))+V_CASH+V_SOTP)/(V_BASIC+V_RSU+Options*MAX(0,1-OptK/K75)+CHOOSE(DilMethod,SUMPRODUCT(V_TrO,V_TrRT)/1000,SUMPRODUCT((K75>V_TrPX)*V_TrO*V_TrRT)/1000,SUMPRODUCT(((V_TrO*V_TrRT/1000*K75-((CVDebtBasis=1)*V_TrO+(CVDebtBasis>=2)*V_TrB))>0)*(V_TrO*V_TrRT/1000*K75-((CVDebtBasis=1)*V_TrO+(CVDebtBasis>=2)*V_TrB)))/K75))) -> 18.764275 | L76: =MAX(0.01,(PF_EV-OffBSWt*V_OFF-V_ODEBT-CHOOSE(DilMethod,0,SUMPRODUCT((L75<=V_TrPX)*((CVDebtBasis=1)*V_TrOP+(CVDebtBasis>=2)*V_TrBP)),SUMPRODUCT(((CVDebtBasis=1)*V_TrOP+(CVDebtBasis>=2)*V_TrBP)))+V_CASH+V_SOTP+V_FPCash)/(V_BASIC+V_FPSh+V_RSU+Options*MAX(0,1-OptK/L75)+CHOOSE(DilMethod,SUMPRODUCT(V_TrOP,V_TrRT)/1000,SUMPRODUCT((L75>V_TrPX)*V_TrOP*V_TrRT)/1000,SUMPRODUCT(((V_TrOP*V_TrRT/1000*L75-((CVDebtBasis=1)*V_TrOP+(CVDebtBasis>=2)*V_TrBP))>0)*(V_TrOP*V_TrRT/1000*L75-((CVDebtBasis=1)*V_TrOP+(CVDebtBasis>=2)*V_TrBP)))/L75))) -> 91.501384 | M76: =MAX(0.01,(V_EV-OffBSWt*V_OFF-V_ODEBT-CHOOSE(DilMethod,0,SUMPRODUCT((M75<=V_TrPX)*((CVDebtBasis=1)*V_TrOP+(CVDebtBasis>=2)*V_TrBP)),SUMPRODUCT(((CVDebtBasis=1)*V_TrOP+(CVDebtBasis>=2)*V_TrBP)))+V_CASH+V_SOTP+V_FPCash)/(V_BASIC+V_FPSh+V_RSU+Options*MAX(0,1-OptK/M75)+CHOOSE(DilMethod,SUMPRODUCT(V_TrOP,V_TrRT)/1000,SUMPRODUCT((M75>V_TrPX)*V_TrOP*V_TrRT)/1000,SUMPRODUCT(((V_TrOP*V_TrRT/1000*M75-((CVDebtBasis=1)*V_TrOP+(CVDebtBasis>=2)*V_TrBP))>0)*(V_TrOP*V_TrRT/1000*M75-((CVDebtBasis=1)*V_TrOP+(CVDebtBasis>=2)*V_TrBP)))/M75))) -> 78.645427 | N76: =MAX(0.01,((PF_EV-OffBSWt*V_OFF-V_ODEBT-CHOOSE(DilMethod,0,SUMPRODUCT((N75<=V_TrPXsc)*((CVDebtBasis=1)*V_TrOP+(CVDebtBasis>=2)*V_TrBP)),SUMPRODUCT(((CVDebtBasis=1)*V_TrOP+(CVDebtBasis>=2)*V_TrBP)))+V_CASH+V_SOTP+V_FPCash)-MAX(0,V_EqIss0+FP_On*SUMPRODUCT(V_TrWin*V_TrPM*V_TrAcc*(V_TrSpot-((O76)>=V_TrEff)*(1-V_TrPlan))))/((1+Ke)*(1-SC_Disc)))/(V_BASIC+V_RSU+Options*MAX(0,1-OptK/N75)+CHOOSE(DilMethod,SUMPRODUCT(V_TrOP,V_TrRT)/1000,SUMPRODUCT((N75>V_TrPXsc)*V_TrOP*V_TrRT)/1000,SUMPRODUCT(((V_TrOP*V_TrRT/1000*N75-((CVDebtBasis=1)*V_TrOP+(CVDebtBasis>=2)*V_TrBP))>0)*(V_TrOP*V_TrRT/1000*N75-((CVDebtBasis=1)*V_TrOP+(CVDebtBasis>=2)*V_TrBP)))/N75)+FP_On*SUMPRODUCT(V_TrWin*V_TrPM*V_TrRT/1000*((O76)>=V_TrEff)*(1-V_TrPlan)))) -> 24.250164 | O76: =MAX(0.01,N75*(1+Ke)*(1-SC_Disc)) -> 27.402685
H77: =MAX(0.01,(PF_EV-V_ODEBT-CHOOSE(DilMethod,0,SUMPRODUCT((H76<=V_TrPX)*((CVDebtBasis=1)*V_TrO+(CVDebtBasis>=2)*V_TrB)),SUMPRODUCT(((CVDebtBasis=1)*V_TrO+(CVDebtBasis>=2)*V_TrB)))+V_CASH+PF_S1)/(V_BASIC+V_RSU+Options*MAX(0,1-OptK/H76)+CHOOSE(DilMethod,SUMPRODUCT(V_TrO,V_TrRT)/1000,SUMPRODUCT((H76>V_TrPX)*V_TrO*V_TrRT)/1000,SUMPRODUCT(((V_TrO*V_TrRT/1000*H76-((CVDebtBasis=1)*V_TrO+(CVDebtBasis>=2)*V_TrB))>0)*(V_TrO*V_TrRT/1000*H76-((CVDebtBasis=1)*V_TrO+(CVDebtBasis>=2)*V_TrB)))/H76))) -> 16.751694 | I77: =MAX(0.01,(PF_EV-V_ODEBT-CHOOSE(DilMethod,0,SUMPRODUCT((I76<=V_TrPX)*((CVDebtBasis=1)*V_TrO+(CVDebtBasis>=2)*V_TrB)),SUMPRODUCT(((CVDebtBasis=1)*V_TrO+(CVDebtBasis>=2)*V_TrB)))+V_CASH+PF_S2)/(V_BASIC+V_RSU+Options*MAX(0,1-OptK/I76)+CHOOSE(DilMethod,SUMPRODUCT(V_TrO,V_TrRT)/1000,SUMPRODUCT((I76>V_TrPX)*V_TrO*V_TrRT)/1000,SUMPRODUCT(((V_TrO*V_TrRT/1000*I76-((CVDebtBasis=1)*V_TrO+(CVDebtBasis>=2)*V_TrB))>0)*(V_TrO*V_TrRT/1000*I76-((CVDebtBasis=1)*V_TrO+(CVDebtBasis>=2)*V_TrB)))/I76))) -> 25.408987 | J77: =MAX(0.01,(PF_EV-V_ODEBT-CHOOSE(DilMethod,0,SUMPRODUCT((J76<=V_TrPX)*((CVDebtBasis=1)*V_TrO+(CVDebtBasis>=2)*V_TrB)),SUMPRODUCT(((CVDebtBasis=1)*V_TrO+(CVDebtBasis>=2)*V_TrB)))+V_CASH+PF_S3)/(V_BASIC+V_RSU+Options*MAX(0,1-OptK/J76)+CHOOSE(DilMethod,SUMPRODUCT(V_TrO,V_TrRT)/1000,SUMPRODUCT((J76>V_TrPX)*V_TrO*V_TrRT)/1000,SUMPRODUCT(((V_TrO*V_TrRT/1000*J76-((CVDebtBasis=1)*V_TrO+(CVDebtBasis>=2)*V_TrB))>0)*(V_TrO*V_TrRT/1000*J76-((CVDebtBasis=1)*V_TrO+(CVDebtBasis>=2)*V_TrB)))/J76))) -> 39.636842 | K77: =MAX(0.01,(PF_EV-OffBSWt*V_OFF-V_ODEBT-CHOOSE(DilMethod,0,SUMPRODUCT((K76<=V_TrPX)*((CVDebtBasis=1)*V_TrO+(CVDebtBasis>=2)*V_TrB)),SUMPRODUCT(((CVDebtBasis=1)*V_TrO+(CVDebtBasis>=2)*V_TrB)))+V_CASH+V_SOTP)/(V_BASIC+V_RSU+Options*MAX(0,1-OptK/K76)+CHOOSE(DilMethod,SUMPRODUCT(V_TrO,V_TrRT)/1000,SUMPRODUCT((K76>V_TrPX)*V_TrO*V_TrRT)/1000,SUMPRODUCT(((V_TrO*V_TrRT/1000*K76-((CVDebtBasis=1)*V_TrO+(CVDebtBasis>=2)*V_TrB))>0)*(V_TrO*V_TrRT/1000*K76-((CVDebtBasis=1)*V_TrO+(CVDebtBasis>=2)*V_TrB)))/K76))) -> 18.764275 | L77: =MAX(0.01,(PF_EV-OffBSWt*V_OFF-V_ODEBT-CHOOSE(DilMethod,0,SUMPRODUCT((L76<=V_TrPX)*((CVDebtBasis=1)*V_TrOP+(CVDebtBasis>=2)*V_TrBP)),SUMPRODUCT(((CVDebtBasis=1)*V_TrOP+(CVDebtBasis>=2)*V_TrBP)))+V_CASH+V_SOTP+V_FPCash)/(V_BASIC+V_FPSh+V_RSU+Options*MAX(0,1-OptK/L76)+CHOOSE(DilMethod,SUMPRODUCT(V_TrOP,V_TrRT)/1000,SUMPRODUCT((L76>V_TrPX)*V_TrOP*V_TrRT)/1000,SUMPRODUCT(((V_TrOP*V_TrRT/1000*L76-((CVDebtBasis=1)*V_TrOP+(CVDebtBasis>=2)*V_TrBP))>0)*(V_TrOP*V_TrRT/1000*L76-((CVDebtBasis=1)*V_TrOP+(CVDebtBasis>=2)*V_TrBP)))/L76))) -> 91.501384 | M77: =MAX(0.01,(V_EV-OffBSWt*V_OFF-V_ODEBT-CHOOSE(DilMethod,0,SUMPRODUCT((M76<=V_TrPX)*((CVDebtBasis=1)*V_TrOP+(CVDebtBasis>=2)*V_TrBP)),SUMPRODUCT(((CVDebtBasis=1)*V_TrOP+(CVDebtBasis>=2)*V_TrBP)))+V_CASH+V_SOTP+V_FPCash)/(V_BASIC+V_FPSh+V_RSU+Options*MAX(0,1-OptK/M76)+CHOOSE(DilMethod,SUMPRODUCT(V_TrOP,V_TrRT)/1000,SUMPRODUCT((M76>V_TrPX)*V_TrOP*V_TrRT)/1000,SUMPRODUCT(((V_TrOP*V_TrRT/1000*M76-((CVDebtBasis=1)*V_TrOP+(CVDebtBasis>=2)*V_TrBP))>0)*(V_TrOP*V_TrRT/1000*M76-((CVDebtBasis=1)*V_TrOP+(CVDebtBasis>=2)*V_TrBP)))/M76))) -> 78.645427 | N77: =MAX(0.01,((PF_EV-OffBSWt*V_OFF-V_ODEBT-CHOOSE(DilMethod,0,SUMPRODUCT((N76<=V_TrPXsc)*((CVDebtBasis=1)*V_TrOP+(CVDebtBasis>=2)*V_TrBP)),SUMPRODUCT(((CVDebtBasis=1)*V_TrOP+(CVDebtBasis>=2)*V_TrBP)))+V_CASH+V_SOTP+V_FPCash)-MAX(0,V_EqIss0+FP_On*SUMPRODUCT(V_TrWin*V_TrPM*V_TrAcc*(V_TrSpot-((O77)>=V_TrEff)*(1-V_TrPlan))))/((1+Ke)*(1-SC_Disc)))/(V_BASIC+V_RSU+Options*MAX(0,1-OptK/N76)+CHOOSE(DilMethod,SUMPRODUCT(V_TrOP,V_TrRT)/1000,SUMPRODUCT((N76>V_TrPXsc)*V_TrOP*V_TrRT)/1000,SUMPRODUCT(((V_TrOP*V_TrRT/1000*N76-((CVDebtBasis=1)*V_TrOP+(CVDebtBasis>=2)*V_TrBP))>0)*(V_TrOP*V_TrRT/1000*N76-((CVDebtBasis=1)*V_TrOP+(CVDebtBasis>=2)*V_TrBP)))/N76)+FP_On*SUMPRODUCT(V_TrWin*V_TrPM*V_TrRT/1000*((O77)>=V_TrEff)*(1-V_TrPlan)))) -> 24.250164 | O77: =MAX(0.01,N76*(1+Ke)*(1-SC_Disc)) -> 27.402685
H78: =MAX(0.01,(PF_EV-V_ODEBT-CHOOSE(DilMethod,0,SUMPRODUCT((H77<=V_TrPX)*((CVDebtBasis=1)*V_TrO+(CVDebtBasis>=2)*V_TrB)),SUMPRODUCT(((CVDebtBasis=1)*V_TrO+(CVDebtBasis>=2)*V_TrB)))+V_CASH+PF_S1)/(V_BASIC+V_RSU+Options*MAX(0,1-OptK/H77)+CHOOSE(DilMethod,SUMPRODUCT(V_TrO,V_TrRT)/1000,SUMPRODUCT((H77>V_TrPX)*V_TrO*V_TrRT)/1000,SUMPRODUCT(((V_TrO*V_TrRT/1000*H77-((CVDebtBasis=1)*V_TrO+(CVDebtBasis>=2)*V_TrB))>0)*(V_TrO*V_TrRT/1000*H77-((CVDebtBasis=1)*V_TrO+(CVDebtBasis>=2)*V_TrB)))/H77))) -> 16.751694 | I78: =MAX(0.01,(PF_EV-V_ODEBT-CHOOSE(DilMethod,0,SUMPRODUCT((I77<=V_TrPX)*((CVDebtBasis=1)*V_TrO+(CVDebtBasis>=2)*V_TrB)),SUMPRODUCT(((CVDebtBasis=1)*V_TrO+(CVDebtBasis>=2)*V_TrB)))+V_CASH+PF_S2)/(V_BASIC+V_RSU+Options*MAX(0,1-OptK/I77)+CHOOSE(DilMethod,SUMPRODUCT(V_TrO,V_TrRT)/1000,SUMPRODUCT((I77>V_TrPX)*V_TrO*V_TrRT)/1000,SUMPRODUCT(((V_TrO*V_TrRT/1000*I77-((CVDebtBasis=1)*V_TrO+(CVDebtBasis>=2)*V_TrB))>0)*(V_TrO*V_TrRT/1000*I77-((CVDebtBasis=1)*V_TrO+(CVDebtBasis>=2)*V_TrB)))/I77))) -> 25.408987 | J78: =MAX(0.01,(PF_EV-V_ODEBT-CHOOSE(DilMethod,0,SUMPRODUCT((J77<=V_TrPX)*((CVDebtBasis=1)*V_TrO+(CVDebtBasis>=2)*V_TrB)),SUMPRODUCT(((CVDebtBasis=1)*V_TrO+(CVDebtBasis>=2)*V_TrB)))+V_CASH+PF_S3)/(V_BASIC+V_RSU+Options*MAX(0,1-OptK/J77)+CHOOSE(DilMethod,SUMPRODUCT(V_TrO,V_TrRT)/1000,SUMPRODUCT((J77>V_TrPX)*V_TrO*V_TrRT)/1000,SUMPRODUCT(((V_TrO*V_TrRT/1000*J77-((CVDebtBasis=1)*V_TrO+(CVDebtBasis>=2)*V_TrB))>0)*(V_TrO*V_TrRT/1000*J77-((CVDebtBasis=1)*V_TrO+(CVDebtBasis>=2)*V_TrB)))/J77))) -> 39.636842 | K78: =MAX(0.01,(PF_EV-OffBSWt*V_OFF-V_ODEBT-CHOOSE(DilMethod,0,SUMPRODUCT((K77<=V_TrPX)*((CVDebtBasis=1)*V_TrO+(CVDebtBasis>=2)*V_TrB)),SUMPRODUCT(((CVDebtBasis=1)*V_TrO+(CVDebtBasis>=2)*V_TrB)))+V_CASH+V_SOTP)/(V_BASIC+V_RSU+Options*MAX(0,1-OptK/K77)+CHOOSE(DilMethod,SUMPRODUCT(V_TrO,V_TrRT)/1000,SUMPRODUCT((K77>V_TrPX)*V_TrO*V_TrRT)/1000,SUMPRODUCT(((V_TrO*V_TrRT/1000*K77-((CVDebtBasis=1)*V_TrO+(CVDebtBasis>=2)*V_TrB))>0)*(V_TrO*V_TrRT/1000*K77-((CVDebtBasis=1)*V_TrO+(CVDebtBasis>=2)*V_TrB)))/K77))) -> 18.764275 | L78: =MAX(0.01,(PF_EV-OffBSWt*V_OFF-V_ODEBT-CHOOSE(DilMethod,0,SUMPRODUCT((L77<=V_TrPX)*((CVDebtBasis=1)*V_TrOP+(CVDebtBasis>=2)*V_TrBP)),SUMPRODUCT(((CVDebtBasis=1)*V_TrOP+(CVDebtBasis>=2)*V_TrBP)))+V_CASH+V_SOTP+V_FPCash)/(V_BASIC+V_FPSh+V_RSU+Options*MAX(0,1-OptK/L77)+CHOOSE(DilMethod,SUMPRODUCT(V_TrOP,V_TrRT)/1000,SUMPRODUCT((L77>V_TrPX)*V_TrOP*V_TrRT)/1000,SUMPRODUCT(((V_TrOP*V_TrRT/1000*L77-((CVDebtBasis=1)*V_TrOP+(CVDebtBasis>=2)*V_TrBP))>0)*(V_TrOP*V_TrRT/1000*L77-((CVDebtBasis=1)*V_TrOP+(CVDebtBasis>=2)*V_TrBP)))/L77))) -> 91.501384 | M78: =MAX(0.01,(V_EV-OffBSWt*V_OFF-V_ODEBT-CHOOSE(DilMethod,0,SUMPRODUCT((M77<=V_TrPX)*((CVDebtBasis=1)*V_TrOP+(CVDebtBasis>=2)*V_TrBP)),SUMPRODUCT(((CVDebtBasis=1)*V_TrOP+(CVDebtBasis>=2)*V_TrBP)))+V_CASH+V_SOTP+V_FPCash)/(V_BASIC+V_FPSh+V_RSU+Options*MAX(0,1-OptK/M77)+CHOOSE(DilMethod,SUMPRODUCT(V_TrOP,V_TrRT)/1000,SUMPRODUCT((M77>V_TrPX)*V_TrOP*V_TrRT)/1000,SUMPRODUCT(((V_TrOP*V_TrRT/1000*M77-((CVDebtBasis=1)*V_TrOP+(CVDebtBasis>=2)*V_TrBP))>0)*(V_TrOP*V_TrRT/1000*M77-((CVDebtBasis=1)*V_TrOP+(CVDebtBasis>=2)*V_TrBP)))/M77))) -> 78.645427 | N78: =MAX(0.01,((PF_EV-OffBSWt*V_OFF-V_ODEBT-CHOOSE(DilMethod,0,SUMPRODUCT((N77<=V_TrPXsc)*((CVDebtBasis=1)*V_TrOP+(CVDebtBasis>=2)*V_TrBP)),SUMPRODUCT(((CVDebtBasis=1)*V_TrOP+(CVDebtBasis>=2)*V_TrBP)))+V_CASH+V_SOTP+V_FPCash)-MAX(0,V_EqIss0+FP_On*SUMPRODUCT(V_TrWin*V_TrPM*V_TrAcc*(V_TrSpot-((O78)>=V_TrEff)*(1-V_TrPlan))))/((1+Ke)*(1-SC_Disc)))/(V_BASIC+V_RSU+Options*MAX(0,1-OptK/N77)+CHOOSE(DilMethod,SUMPRODUCT(V_TrOP,V_TrRT)/1000,SUMPRODUCT((N77>V_TrPXsc)*V_TrOP*V_TrRT)/1000,SUMPRODUCT(((V_TrOP*V_TrRT/1000*N77-((CVDebtBasis=1)*V_TrOP+(CVDebtBasis>=2)*V_TrBP))>0)*(V_TrOP*V_TrRT/1000*N77-((CVDebtBasis=1)*V_TrOP+(CVDebtBasis>=2)*V_TrBP)))/N77)+FP_On*SUMPRODUCT(V_TrWin*V_TrPM*V_TrRT/1000*((O78)>=V_TrEff)*(1-V_TrPlan)))) -> 24.250164 | O78: =MAX(0.01,N77*(1+Ke)*(1-SC_Disc)) -> 27.402685
H79: =MAX(0.01,(PF_EV-V_ODEBT-CHOOSE(DilMethod,0,SUMPRODUCT((H78<=V_TrPX)*((CVDebtBasis=1)*V_TrO+(CVDebtBasis>=2)*V_TrB)),SUMPRODUCT(((CVDebtBasis=1)*V_TrO+(CVDebtBasis>=2)*V_TrB)))+V_CASH+PF_S1)/(V_BASIC+V_RSU+Options*MAX(0,1-OptK/H78)+CHOOSE(DilMethod,SUMPRODUCT(V_TrO,V_TrRT)/1000,SUMPRODUCT((H78>V_TrPX)*V_TrO*V_TrRT)/1000,SUMPRODUCT(((V_TrO*V_TrRT/1000*H78-((CVDebtBasis=1)*V_TrO+(CVDebtBasis>=2)*V_TrB))>0)*(V_TrO*V_TrRT/1000*H78-((CVDebtBasis=1)*V_TrO+(CVDebtBasis>=2)*V_TrB)))/H78))) -> 16.751694 | I79: =MAX(0.01,(PF_EV-V_ODEBT-CHOOSE(DilMethod,0,SUMPRODUCT((I78<=V_TrPX)*((CVDebtBasis=1)*V_TrO+(CVDebtBasis>=2)*V_TrB)),SUMPRODUCT(((CVDebtBasis=1)*V_TrO+(CVDebtBasis>=2)*V_TrB)))+V_CASH+PF_S2)/(V_BASIC+V_RSU+Options*MAX(0,1-OptK/I78)+CHOOSE(DilMethod,SUMPRODUCT(V_TrO,V_TrRT)/1000,SUMPRODUCT((I78>V_TrPX)*V_TrO*V_TrRT)/1000,SUMPRODUCT(((V_TrO*V_TrRT/1000*I78-((CVDebtBasis=1)*V_TrO+(CVDebtBasis>=2)*V_TrB))>0)*(V_TrO*V_TrRT/1000*I78-((CVDebtBasis=1)*V_TrO+(CVDebtBasis>=2)*V_TrB)))/I78))) -> 25.408987 | J79: =MAX(0.01,(PF_EV-V_ODEBT-CHOOSE(DilMethod,0,SUMPRODUCT((J78<=V_TrPX)*((CVDebtBasis=1)*V_TrO+(CVDebtBasis>=2)*V_TrB)),SUMPRODUCT(((CVDebtBasis=1)*V_TrO+(CVDebtBasis>=2)*V_TrB)))+V_CASH+PF_S3)/(V_BASIC+V_RSU+Options*MAX(0,1-OptK/J78)+CHOOSE(DilMethod,SUMPRODUCT(V_TrO,V_TrRT)/1000,SUMPRODUCT((J78>V_TrPX)*V_TrO*V_TrRT)/1000,SUMPRODUCT(((V_TrO*V_TrRT/1000*J78-((CVDebtBasis=1)*V_TrO+(CVDebtBasis>=2)*V_TrB))>0)*(V_TrO*V_TrRT/1000*J78-((CVDebtBasis=1)*V_TrO+(CVDebtBasis>=2)*V_TrB)))/J78))) -> 39.636842 | K79: =MAX(0.01,(PF_EV-OffBSWt*V_OFF-V_ODEBT-CHOOSE(DilMethod,0,SUMPRODUCT((K78<=V_TrPX)*((CVDebtBasis=1)*V_TrO+(CVDebtBasis>=2)*V_TrB)),SUMPRODUCT(((CVDebtBasis=1)*V_TrO+(CVDebtBasis>=2)*V_TrB)))+V_CASH+V_SOTP)/(V_BASIC+V_RSU+Options*MAX(0,1-OptK/K78)+CHOOSE(DilMethod,SUMPRODUCT(V_TrO,V_TrRT)/1000,SUMPRODUCT((K78>V_TrPX)*V_TrO*V_TrRT)/1000,SUMPRODUCT(((V_TrO*V_TrRT/1000*K78-((CVDebtBasis=1)*V_TrO+(CVDebtBasis>=2)*V_TrB))>0)*(V_TrO*V_TrRT/1000*K78-((CVDebtBasis=1)*V_TrO+(CVDebtBasis>=2)*V_TrB)))/K78))) -> 18.764275 | L79: =MAX(0.01,(PF_EV-OffBSWt*V_OFF-V_ODEBT-CHOOSE(DilMethod,0,SUMPRODUCT((L78<=V_TrPX)*((CVDebtBasis=1)*V_TrOP+(CVDebtBasis>=2)*V_TrBP)),SUMPRODUCT(((CVDebtBasis=1)*V_TrOP+(CVDebtBasis>=2)*V_TrBP)))+V_CASH+V_SOTP+V_FPCash)/(V_BASIC+V_FPSh+V_RSU+Options*MAX(0,1-OptK/L78)+CHOOSE(DilMethod,SUMPRODUCT(V_TrOP,V_TrRT)/1000,SUMPRODUCT((L78>V_TrPX)*V_TrOP*V_TrRT)/1000,SUMPRODUCT(((V_TrOP*V_TrRT/1000*L78-((CVDebtBasis=1)*V_TrOP+(CVDebtBasis>=2)*V_TrBP))>0)*(V_TrOP*V_TrRT/1000*L78-((CVDebtBasis=1)*V_TrOP+(CVDebtBasis>=2)*V_TrBP)))/L78))) -> 91.501384 | M79: =MAX(0.01,(V_EV-OffBSWt*V_OFF-V_ODEBT-CHOOSE(DilMethod,0,SUMPRODUCT((M78<=V_TrPX)*((CVDebtBasis=1)*V_TrOP+(CVDebtBasis>=2)*V_TrBP)),SUMPRODUCT(((CVDebtBasis=1)*V_TrOP+(CVDebtBasis>=2)*V_TrBP)))+V_CASH+V_SOTP+V_FPCash)/(V_BASIC+V_FPSh+V_RSU+Options*MAX(0,1-OptK/M78)+CHOOSE(DilMethod,SUMPRODUCT(V_TrOP,V_TrRT)/1000,SUMPRODUCT((M78>V_TrPX)*V_TrOP*V_TrRT)/1000,SUMPRODUCT(((V_TrOP*V_TrRT/1000*M78-((CVDebtBasis=1)*V_TrOP+(CVDebtBasis>=2)*V_TrBP))>0)*(V_TrOP*V_TrRT/1000*M78-((CVDebtBasis=1)*V_TrOP+(CVDebtBasis>=2)*V_TrBP)))/M78))) -> 78.645427 | N79: =MAX(0.01,((PF_EV-OffBSWt*V_OFF-V_ODEBT-CHOOSE(DilMethod,0,SUMPRODUCT((N78<=V_TrPXsc)*((CVDebtBasis=1)*V_TrOP+(CVDebtBasis>=2)*V_TrBP)),SUMPRODUCT(((CVDebtBasis=1)*V_TrOP+(CVDebtBasis>=2)*V_TrBP)))+V_CASH+V_SOTP+V_FPCash)-MAX(0,V_EqIss0+FP_On*SUMPRODUCT(V_TrWin*V_TrPM*V_TrAcc*(V_TrSpot-((O79)>=V_TrEff)*(1-V_TrPlan))))/((1+Ke)*(1-SC_Disc)))/(V_BASIC+V_RSU+Options*MAX(0,1-OptK/N78)+CHOOSE(DilMethod,SUMPRODUCT(V_TrOP,V_TrRT)/1000,SUMPRODUCT((N78>V_TrPXsc)*V_TrOP*V_TrRT)/1000,SUMPRODUCT(((V_TrOP*V_TrRT/1000*N78-((CVDebtBasis=1)*V_TrOP+(CVDebtBasis>=2)*V_TrBP))>0)*(V_TrOP*V_TrRT/1000*N78-((CVDebtBasis=1)*V_TrOP+(CVDebtBasis>=2)*V_TrBP)))/N78)+FP_On*SUMPRODUCT(V_TrWin*V_TrPM*V_TrRT/1000*((O79)>=V_TrEff)*(1-V_TrPlan)))) -> 24.250164 | O79: =MAX(0.01,N78*(1+Ke)*(1-SC_Disc)) -> 27.402685
H80: =MAX(0.01,(PF_EV-V_ODEBT-CHOOSE(DilMethod,0,SUMPRODUCT((H79<=V_TrPX)*((CVDebtBasis=1)*V_TrO+(CVDebtBasis>=2)*V_TrB)),SUMPRODUCT(((CVDebtBasis=1)*V_TrO+(CVDebtBasis>=2)*V_TrB)))+V_CASH+PF_S1)/(V_BASIC+V_RSU+Options*MAX(0,1-OptK/H79)+CHOOSE(DilMethod,SUMPRODUCT(V_TrO,V_TrRT)/1000,SUMPRODUCT((H79>V_TrPX)*V_TrO*V_TrRT)/1000,SUMPRODUCT(((V_TrO*V_TrRT/1000*H79-((CVDebtBasis=1)*V_TrO+(CVDebtBasis>=2)*V_TrB))>0)*(V_TrO*V_TrRT/1000*H79-((CVDebtBasis=1)*V_TrO+(CVDebtBasis>=2)*V_TrB)))/H79))) -> 16.751694 | I80: =MAX(0.01,(PF_EV-V_ODEBT-CHOOSE(DilMethod,0,SUMPRODUCT((I79<=V_TrPX)*((CVDebtBasis=1)*V_TrO+(CVDebtBasis>=2)*V_TrB)),SUMPRODUCT(((CVDebtBasis=1)*V_TrO+(CVDebtBasis>=2)*V_TrB)))+V_CASH+PF_S2)/(V_BASIC+V_RSU+Options*MAX(0,1-OptK/I79)+CHOOSE(DilMethod,SUMPRODUCT(V_TrO,V_TrRT)/1000,SUMPRODUCT((I79>V_TrPX)*V_TrO*V_TrRT)/1000,SUMPRODUCT(((V_TrO*V_TrRT/1000*I79-((CVDebtBasis=1)*V_TrO+(CVDebtBasis>=2)*V_TrB))>0)*(V_TrO*V_TrRT/1000*I79-((CVDebtBasis=1)*V_TrO+(CVDebtBasis>=2)*V_TrB)))/I79))) -> 25.408987 | J80: =MAX(0.01,(PF_EV-V_ODEBT-CHOOSE(DilMethod,0,SUMPRODUCT((J79<=V_TrPX)*((CVDebtBasis=1)*V_TrO+(CVDebtBasis>=2)*V_TrB)),SUMPRODUCT(((CVDebtBasis=1)*V_TrO+(CVDebtBasis>=2)*V_TrB)))+V_CASH+PF_S3)/(V_BASIC+V_RSU+Options*MAX(0,1-OptK/J79)+CHOOSE(DilMethod,SUMPRODUCT(V_TrO,V_TrRT)/1000,SUMPRODUCT((J79>V_TrPX)*V_TrO*V_TrRT)/1000,SUMPRODUCT(((V_TrO*V_TrRT/1000*J79-((CVDebtBasis=1)*V_TrO+(CVDebtBasis>=2)*V_TrB))>0)*(V_TrO*V_TrRT/1000*J79-((CVDebtBasis=1)*V_TrO+(CVDebtBasis>=2)*V_TrB)))/J79))) -> 39.636842 | K80: =MAX(0.01,(PF_EV-OffBSWt*V_OFF-V_ODEBT-CHOOSE(DilMethod,0,SUMPRODUCT((K79<=V_TrPX)*((CVDebtBasis=1)*V_TrO+(CVDebtBasis>=2)*V_TrB)),SUMPRODUCT(((CVDebtBasis=1)*V_TrO+(CVDebtBasis>=2)*V_TrB)))+V_CASH+V_SOTP)/(V_BASIC+V_RSU+Options*MAX(0,1-OptK/K79)+CHOOSE(DilMethod,SUMPRODUCT(V_TrO,V_TrRT)/1000,SUMPRODUCT((K79>V_TrPX)*V_TrO*V_TrRT)/1000,SUMPRODUCT(((V_TrO*V_TrRT/1000*K79-((CVDebtBasis=1)*V_TrO+(CVDebtBasis>=2)*V_TrB))>0)*(V_TrO*V_TrRT/1000*K79-((CVDebtBasis=1)*V_TrO+(CVDebtBasis>=2)*V_TrB)))/K79))) -> 18.764275 | L80: =MAX(0.01,(PF_EV-OffBSWt*V_OFF-V_ODEBT-CHOOSE(DilMethod,0,SUMPRODUCT((L79<=V_TrPX)*((CVDebtBasis=1)*V_TrOP+(CVDebtBasis>=2)*V_TrBP)),SUMPRODUCT(((CVDebtBasis=1)*V_TrOP+(CVDebtBasis>=2)*V_TrBP)))+V_CASH+V_SOTP+V_FPCash)/(V_BASIC+V_FPSh+V_RSU+Options*MAX(0,1-OptK/L79)+CHOOSE(DilMethod,SUMPRODUCT(V_TrOP,V_TrRT)/1000,SUMPRODUCT((L79>V_TrPX)*V_TrOP*V_TrRT)/1000,SUMPRODUCT(((V_TrOP*V_TrRT/1000*L79-((CVDebtBasis=1)*V_TrOP+(CVDebtBasis>=2)*V_TrBP))>0)*(V_TrOP*V_TrRT/1000*L79-((CVDebtBasis=1)*V_TrOP+(CVDebtBasis>=2)*V_TrBP)))/L79))) -> 91.501384 | M80: =MAX(0.01,(V_EV-OffBSWt*V_OFF-V_ODEBT-CHOOSE(DilMethod,0,SUMPRODUCT((M79<=V_TrPX)*((CVDebtBasis=1)*V_TrOP+(CVDebtBasis>=2)*V_TrBP)),SUMPRODUCT(((CVDebtBasis=1)*V_TrOP+(CVDebtBasis>=2)*V_TrBP)))+V_CASH+V_SOTP+V_FPCash)/(V_BASIC+V_FPSh+V_RSU+Options*MAX(0,1-OptK/M79)+CHOOSE(DilMethod,SUMPRODUCT(V_TrOP,V_TrRT)/1000,SUMPRODUCT((M79>V_TrPX)*V_TrOP*V_TrRT)/1000,SUMPRODUCT(((V_TrOP*V_TrRT/1000*M79-((CVDebtBasis=1)*V_TrOP+(CVDebtBasis>=2)*V_TrBP))>0)*(V_TrOP*V_TrRT/1000*M79-((CVDebtBasis=1)*V_TrOP+(CVDebtBasis>=2)*V_TrBP)))/M79))) -> 78.645427 | N80: =MAX(0.01,((PF_EV-OffBSWt*V_OFF-V_ODEBT-CHOOSE(DilMethod,0,SUMPRODUCT((N79<=V_TrPXsc)*((CVDebtBasis=1)*V_TrOP+(CVDebtBasis>=2)*V_TrBP)),SUMPRODUCT(((CVDebtBasis=1)*V_TrOP+(CVDebtBasis>=2)*V_TrBP)))+V_CASH+V_SOTP+V_FPCash)-MAX(0,V_EqIss0+FP_On*SUMPRODUCT(V_TrWin*V_TrPM*V_TrAcc*(V_TrSpot-((O80)>=V_TrEff)*(1-V_TrPlan))))/((1+Ke)*(1-SC_Disc)))/(V_BASIC+V_RSU+Options*MAX(0,1-OptK/N79)+CHOOSE(DilMethod,SUMPRODUCT(V_TrOP,V_TrRT)/1000,SUMPRODUCT((N79>V_TrPXsc)*V_TrOP*V_TrRT)/1000,SUMPRODUCT(((V_TrOP*V_TrRT/1000*N79-((CVDebtBasis=1)*V_TrOP+(CVDebtBasis>=2)*V_TrBP))>0)*(V_TrOP*V_TrRT/1000*N79-((CVDebtBasis=1)*V_TrOP+(CVDebtBasis>=2)*V_TrBP)))/N79)+FP_On*SUMPRODUCT(V_TrWin*V_TrPM*V_TrRT/1000*((O80)>=V_TrEff)*(1-V_TrPlan)))) -> 24.250164 | O80: =MAX(0.01,N79*(1+Ke)*(1-SC_Disc)) -> 27.402685
... H83: =MAX(0.01,(PF_EV-V_ODEBT-CHOOSE(DilMethod,0,SUMPRODUCT((H82<=V_TrPX)*((CVDebtBasis=1)*V_TrO+(CVDebtBasis>=2)*V_TrB)),SUMPRODUCT(((CVDebtBasis=1)*V_TrO+(CVDebtBasis>=2)*V_TrB)))+V_CASH+PF_S1)/(V_BASIC+V_RSU+Options*MAX(0,1-OptK/H82)+CHOOSE(DilMethod,SUMPRODUCT(V_TrO,V_TrRT)/1000,SUMPRODUCT((H82>V_TrPX)*V_TrO*V_TrRT)/1000,SUMPRODUCT(((V_TrO*V_TrRT/1000*H82-((CVDebtBasis=1)*V_TrO+(CVDebtBasis>=2)*V_TrB))>0)*(V_TrO*V_TrRT/1000*H82-((CVDebtBasis=1)*V_TrO+(CVDebtBasis>=2)*V_TrB)))/H82))) -> 16.751694 | I83: =MAX(0.01,(PF_EV-V_ODEBT-CHOOSE(DilMethod,0,SUMPRODUCT((I82<=V_TrPX)*((CVDebtBasis=1)*V_TrO+(CVDebtBasis>=2)*V_TrB)),SUMPRODUCT(((CVDebtBasis=1)*V_TrO+(CVDebtBasis>=2)*V_TrB)))+V_CASH+PF_S2)/(V_BASIC+V_RSU+Options*MAX(0,1-OptK/I82)+CHOOSE(DilMethod,SUMPRODUCT(V_TrO,V_TrRT)/1000,SUMPRODUCT((I82>V_TrPX)*V_TrO*V_TrRT)/1000,SUMPRODUCT(((V_TrO*V_TrRT/1000*I82-((CVDebtBasis=1)*V_TrO+(CVDebtBasis>=2)*V_TrB))>0)*(V_TrO*V_TrRT/1000*I82-((CVDebtBasis=1)*V_TrO+(CVDebtBasis>=2)*V_TrB)))/I82))) -> 25.408987 | J83: =MAX(0.01,(PF_EV-V_ODEBT-CHOOSE(DilMethod,0,SUMPRODUCT((J82<=V_TrPX)*((CVDebtBasis=1)*V_TrO+(CVDebtBasis>=2)*V_TrB)),SUMPRODUCT(((CVDebtBasis=1)*V_TrO+(CVDebtBasis>=2)*V_TrB)))+V_CASH+PF_S3)/(V_BASIC+V_RSU+Options*MAX(0,1-OptK/J82)+CHOOSE(DilMethod,SUMPRODUCT(V_TrO,V_TrRT)/1000,SUMPRODUCT((J82>V_TrPX)*V_TrO*V_TrRT)/1000,SUMPRODUCT(((V_TrO*V_TrRT/1000*J82-((CVDebtBasis=1)*V_TrO+(CVDebtBasis>=2)*V_TrB))>0)*(V_TrO*V_TrRT/1000*J82-((CVDebtBasis=1)*V_TrO+(CVDebtBasis>=2)*V_TrB)))/J82))) -> 39.636842 | K83: =MAX(0.01,(PF_EV-OffBSWt*V_OFF-V_ODEBT-CHOOSE(DilMethod,0,SUMPRODUCT((K82<=V_TrPX)*((CVDebtBasis=1)*V_TrO+(CVDebtBasis>=2)*V_TrB)),SUMPRODUCT(((CVDebtBasis=1)*V_TrO+(CVDebtBasis>=2)*V_TrB)))+V_CASH+V_SOTP)/(V_BASIC+V_RSU+Options*MAX(0,1-OptK/K82)+CHOOSE(DilMethod,SUMPRODUCT(V_TrO,V_TrRT)/1000,SUMPRODUCT((K82>V_TrPX)*V_TrO*V_TrRT)/1000,SUMPRODUCT(((V_TrO*V_TrRT/1000*K82-((CVDebtBasis=1)*V_TrO+(CVDebtBasis>=2)*V_TrB))>0)*(V_TrO*V_TrRT/1000*K82-((CVDebtBasis=1)*V_TrO+(CVDebtBasis>=2)*V_TrB)))/K82))) -> 18.764275 | L83: =MAX(0.01,(PF_EV-OffBSWt*V_OFF-V_ODEBT-CHOOSE(DilMethod,0,SUMPRODUCT((L82<=V_TrPX)*((CVDebtBasis=1)*V_TrOP+(CVDebtBasis>=2)*V_TrBP)),SUMPRODUCT(((CVDebtBasis=1)*V_TrOP+(CVDebtBasis>=2)*V_TrBP)))+V_CASH+V_SOTP+V_FPCash)/(V_BASIC+V_FPSh+V_RSU+Options*MAX(0,1-OptK/L82)+CHOOSE(DilMethod,SUMPRODUCT(V_TrOP,V_TrRT)/1000,SUMPRODUCT((L82>V_TrPX)*V_TrOP*V_TrRT)/1000,SUMPRODUCT(((V_TrOP*V_TrRT/1000*L82-((CVDebtBasis=1)*V_TrOP+(CVDebtBasis>=2)*V_TrBP))>0)*(V_TrOP*V_TrRT/1000*L82-((CVDebtBasis=1)*V_TrOP+(CVDebtBasis>=2)*V_TrBP)))/L82))) -> 91.501384 | M83: =MAX(0.01,(V_EV-OffBSWt*V_OFF-V_ODEBT-CHOOSE(DilMethod,0,SUMPRODUCT((M82<=V_TrPX)*((CVDebtBasis=1)*V_TrOP+(CVDebtBasis>=2)*V_TrBP)),SUMPRODUCT(((CVDebtBasis=1)*V_TrOP+(CVDebtBasis>=2)*V_TrBP)))+V_CASH+V_SOTP+V_FPCash)/(V_BASIC+V_FPSh+V_RSU+Options*MAX(0,1-OptK/M82)+CHOOSE(DilMethod,SUMPRODUCT(V_TrOP,V_TrRT)/1000,SUMPRODUCT((M82>V_TrPX)*V_TrOP*V_TrRT)/1000,SUMPRODUCT(((V_TrOP*V_TrRT/1000*M82-((CVDebtBasis=1)*V_TrOP+(CVDebtBasis>=2)*V_TrBP))>0)*(V_TrOP*V_TrRT/1000*M82-((CVDebtBasis=1)*V_TrOP+(CVDebtBasis>=2)*V_TrBP)))/M82))) -> 78.645427 | N83: =MAX(0.01,((PF_EV-OffBSWt*V_OFF-V_ODEBT-CHOOSE(DilMethod,0,SUMPRODUCT((N82<=V_TrPXsc)*((CVDebtBasis=1)*V_TrOP+(CVDebtBasis>=2)*V_TrBP)),SUMPRODUCT(((CVDebtBasis=1)*V_TrOP+(CVDebtBasis>=2)*V_TrBP)))+V_CASH+V_SOTP+V_FPCash)-MAX(0,V_EqIss0+FP_On*SUMPRODUCT(V_TrWin*V_TrPM*V_TrAcc*(V_TrSpot-((O83)>=V_TrEff)*(1-V_TrPlan))))/((1+Ke)*(1-SC_Disc)))/(V_BASIC+V_RSU+Options*MAX(0,1-OptK/N82)+CHOOSE(DilMethod,SUMPRODUCT(V_TrOP,V_TrRT)/1000,SUMPRODUCT((N82>V_TrPXsc)*V_TrOP*V_TrRT)/1000,SUMPRODUCT(((V_TrOP*V_TrRT/1000*N82-((CVDebtBasis=1)*V_TrOP+(CVDebtBasis>=2)*V_TrBP))>0)*(V_TrOP*V_TrRT/1000*N82-((CVDebtBasis=1)*V_TrOP+(CVDebtBasis>=2)*V_TrBP)))/N82)+FP_On*SUMPRODUCT(V_TrWin*V_TrPM*V_TrRT/1000*((O83)>=V_TrEff)*(1-V_TrPlan)))) -> 24.250164 | O83: =MAX(0.01,N82*(1+Ke)*(1-SC_Disc)) -> 27.402685
H84: =IF(H83<=0.011,0,H83) -> 16.751694 | I84: =IF(I83<=0.011,0,I83) -> 25.408987 | J84: =IF(J83<=0.011,0,J83) -> 39.636842 | K84: =IF(K83<=0.011,0,K83) -> 18.764275 | L84: =IF(L83<=0.011,0,L83) -> 91.501384 | M84: =IF(M83<=0.011,0,M83) -> 78.645427 | N84: =MAX(0.01,((PF_EV-OffBSWt*V_OFF-V_ODEBT-CHOOSE(DilMethod,0,SUMPRODUCT((N83<=V_TrPXsc)*((CVDebtBasis=1)*V_TrOP+(CVDebtBasis>=2)*V_TrBP)),SUMPRODUCT(((CVDebtBasis=1)*V_TrOP+(CVDebtBasis>=2)*V_TrBP)))+V_CASH+V_SOTP+V_FPCash)-MAX(0,V_EqIss0+FP_On*SUMPRODUCT(V_TrWin*V_TrPM*V_TrAcc*(V_TrSpot-((O84)>=V_TrEff)*(1-V_TrPlan))))/((1+Ke)*(1-SC_Disc)))/(V_BASIC+V_RSU+Options*MAX(0,1-OptK/N83)+CHOOSE(DilMethod,SUMPRODUCT(V_TrOP,V_TrRT)/1000,SUMPRODUCT((N83>V_TrPXsc)*V_TrOP*V_TrRT)/1000,SUMPRODUCT(((V_TrOP*V_TrRT/1000*N83-((CVDebtBasis=1)*V_TrOP+(CVDebtBasis>=2)*V_TrBP))>0)*(V_TrOP*V_TrRT/1000*N83-((CVDebtBasis=1)*V_TrOP+(CVDebtBasis>=2)*V_TrBP)))/N83)+FP_On*SUMPRODUCT(V_TrWin*V_TrPM*V_TrRT/1000*((O84)>=V_TrEff)*(1-V_TrPlan)))) -> 24.250164 | O84: =MAX(0.01,N83*(1+Ke)*(1-SC_Disc)) -> 27.402685
K85: Floor value/sh on shared bridge (FP_On -> post-funding) / x(1+Ke) / DCF replica check vs V_PSF | N85: =MAX(0.01,((PF_EV-OffBSWt*V_OFF-V_ODEBT-CHOOSE(DilMethod,0,SUMPRODUCT((N84<=V_TrPXsc)*((CVDebtBasis=1)*V_TrOP+(CVDebtBasis>=2)*V_TrBP)),SUMPRODUCT(((CVDebtBasis=1)*V_TrOP+(CVDebtBasis>=2)*V_TrBP)))+V_CASH+V_SOTP+V_FPCash)-MAX(0,V_EqIss0+FP_On*SUMPRODUCT(V_TrWin*V_TrPM*V_TrAcc*(V_TrSpot-((O85)>=V_TrEff)*(1-V_TrPlan))))/((1+Ke)*(1-SC_Disc)))/(V_BASIC+V_RSU+Options*MAX(0,1-OptK/N84)+CHOOSE(DilMethod,SUMPRODUCT(V_TrOP,V_TrRT)/1000,SUMPRODUCT((N84>V_TrPXsc)*V_TrOP*V_TrRT)/1000,SUMPRODUCT(((V_TrOP*V_TrRT/1000*N84-((CVDebtBasis=1)*V_TrOP+(CVDebtBasis>=2)*V_TrBP))>0)*(V_TrOP*V_TrRT/1000*N84-((CVDebtBasis=1)*V_TrOP+(CVDebtBasis>=2)*V_TrBP)))/N84)+FP_On*SUMPRODUCT(V_TrWin*V_TrPM*V_TrRT/1000*((O85)>=V_TrEff)*(1-V_TrPlan)))) -> 24.250164 | O85: =MAX(0.01,N84*(1+Ke)*(1-SC_Disc)) -> 27.402685
K86: =IF(FP_On=1,PF_PSSF,PF_PSS) -> 91.501384 | L86: =PF_PSHead*(1+Ke) -> 27.402685 | M86: =PF_DCFRep-IF(FP_On=1,V_PSSpot,V_PS) -> 0 | N86: =MAX(0.01,((PF_EV-OffBSWt*V_OFF-V_ODEBT-CHOOSE(DilMethod,0,SUMPRODUCT((N85<=V_TrPXsc)*((CVDebtBasis=1)*V_TrOP+(CVDebtBasis>=2)*V_TrBP)),SUMPRODUCT(((CVDebtBasis=1)*V_TrOP+(CVDebtBasis>=2)*V_TrBP)))+V_CASH+V_SOTP+V_FPCash)-MAX(0,V_EqIss0+FP_On*SUMPRODUCT(V_TrWin*V_TrPM*V_TrAcc*(V_TrSpot-((O86)>=V_TrEff)*(1-V_TrPlan))))/((1+Ke)*(1-SC_Disc)))/(V_BASIC+V_RSU+Options*MAX(0,1-OptK/N85)+CHOOSE(DilMethod,SUMPRODUCT(V_TrOP,V_TrRT)/1000,SUMPRODUCT((N85>V_TrPXsc)*V_TrOP*V_TrRT)/1000,SUMPRODUCT(((V_TrOP*V_TrRT/1000*N85-((CVDebtBasis=1)*V_TrOP+(CVDebtBasis>=2)*V_TrBP))>0)*(V_TrOP*V_TrRT/1000*N85-((CVDebtBasis=1)*V_TrOP+(CVDebtBasis>=2)*V_TrBP)))/N85)+FP_On*SUMPRODUCT(V_TrWin*V_TrPM*V_TrRT/1000*((O86)>=V_TrEff)*(1-V_TrPlan)))) -> 24.250164 | O86: =MAX(0.01,N85*(1+Ke)*(1-SC_Disc)) -> 27.402685
A87: E) PRICE CHECK - $/GPU-hr implied by new-deal $/IT MW (live scenario). Price is NOT calibrated off the 22-month payback. | E87: Rubin vs GB300 (leased, live scenario) | N87: =MAX(0.01,((PF_EV-OffBSWt*V_OFF-V_ODEBT-CHOOSE(DilMethod,0,SUMPRODUCT((N86<=V_TrPXsc)*((CVDebtBasis=1)*V_TrOP+(CVDebtBasis>=2)*V_TrBP)),SUMPRODUCT(((CVDebtBasis=1)*V_TrOP+(CVDebtBasis>=2)*V_TrBP)))+V_CASH+V_SOTP+V_FPCash)-MAX(0,V_EqIss0+FP_On*SUMPRODUCT(V_TrWin*V_TrPM*V_TrAcc*(V_TrSpot-((O87)>=V_TrEff)*(1-V_TrPlan))))/((1+Ke)*(1-SC_Disc)))/(V_BASIC+V_RSU+Options*MAX(0,1-OptK/N86)+CHOOSE(DilMethod,SUMPRODUCT(V_TrOP,V_TrRT)/1000,SUMPRODUCT((N86>V_TrPXsc)*V_TrOP*V_TrRT)/1000,SUMPRODUCT(((V_TrOP*V_TrRT/1000*N86-((CVDebtBasis=1)*V_TrOP+(CVDebtBasis>=2)*V_TrBP))>0)*(V_TrOP*V_TrRT/1000*N86-((CVDebtBasis=1)*V_TrOP+(CVDebtBasis>=2)*V_TrBP)))/N86)+FP_On*SUMPRODUCT(V_TrWin*V_TrPM*V_TrRT/1000*((O87)>=V_TrEff)*(1-V_TrPlan)))) -> 24.250164 | O87: =MAX(0.01,N86*(1+Ke)*(1-SC_Disc)) -> 27.402685
A88: GB300 multi-year new deal (MYRate, IT reading) $M/IT MW-yr | $/GPU-hr at 491 | B88: =MYRate -> 16 | C88: =B88*1000000/(491*8760) -> 3.7199267 | E88: per-GPU-hr price multiple | F88: =PX_Ratio -> 1.5535547 | N88: =MAX(0.01,((PF_EV-OffBSWt*V_OFF-V_ODEBT-CHOOSE(DilMethod,0,SUMPRODUCT((N87<=V_TrPXsc)*((CVDebtBasis=1)*V_TrOP+(CVDebtBasis>=2)*V_TrBP)),SUMPRODUCT(((CVDebtBasis=1)*V_TrOP+(CVDebtBasis>=2)*V_TrBP)))+V_CASH+V_SOTP+V_FPCash)-MAX(0,V_EqIss0+FP_On*SUMPRODUCT(V_TrWin*V_TrPM*V_TrAcc*(V_TrSpot-((O88)>=V_TrEff)*(1-V_TrPlan))))/((1+Ke)*(1-SC_Disc)))/(V_BASIC+V_RSU+Options*MAX(0,1-OptK/N87)+CHOOSE(DilMethod,SUMPRODUCT(V_TrOP,V_TrRT)/1000,SUMPRODUCT((N87>V_TrPXsc)*V_TrOP*V_TrRT)/1000,SUMPRODUCT(((V_TrOP*V_TrRT/1000*N87-((CVDebtBasis=1)*V_TrOP+(CVDebtBasis>=2)*V_TrBP))>0)*(V_TrOP*V_TrRT/1000*N87-((CVDebtBasis=1)*V_TrOP+(CVDebtBasis>=2)*V_TrBP)))/N87)+FP_On*SUMPRODUCT(V_TrWin*V_TrPM*V_TrRT/1000*((O88)>=V_TrEff)*(1-V_TrPlan)))) -> 24.250164 | O88: =MAX(0.01,N87*(1+Ke)*(1-SC_Disc)) -> 27.402685
A89: GB300 gross reading (MYRate x ND_GrossX) per IT MW | $/GPU-hr at 491 | B89: =MYRate*ND_GrossX -> 19.207824 | C89: =B89*1000000/(491*8760) -> 4.4657311 | E89: $/IT MW price multiple (RubinMW / MYRate) | F89: =RubinMW/MYRate -> 1.0125 | N89: =MAX(0.01,((PF_EV-OffBSWt*V_OFF-V_ODEBT-CHOOSE(DilMethod,0,SUMPRODUCT((N88<=V_TrPXsc)*((CVDebtBasis=1)*V_TrOP+(CVDebtBasis>=2)*V_TrBP)),SUMPRODUCT(((CVDebtBasis=1)*V_TrOP+(CVDebtBasis>=2)*V_TrBP)))+V_CASH+V_SOTP+V_FPCash)-MAX(0,V_EqIss0+FP_On*SUMPRODUCT(V_TrWin*V_TrPM*V_TrAcc*(V_TrSpot-((O89)>=V_TrEff)*(1-V_TrPlan))))/((1+Ke)*(1-SC_Disc)))/(V_BASIC+V_RSU+Options*MAX(0,1-OptK/N88)+CHOOSE(DilMethod,SUMPRODUCT(V_TrOP,V_TrRT)/1000,SUMPRODUCT((N88>V_TrPXsc)*V_TrOP*V_TrRT)/1000,SUMPRODUCT(((V_TrOP*V_TrRT/1000*N88-((CVDebtBasis=1)*V_TrOP+(CVDebtBasis>=2)*V_TrBP))>0)*(V_TrOP*V_TrRT/1000*N88-((CVDebtBasis=1)*V_TrOP+(CVDebtBasis>=2)*V_TrBP)))/N88)+FP_On*SUMPRODUCT(V_TrWin*V_TrPM*V_TrRT/1000*((O89)>=V_TrEff)*(1-V_TrPlan)))) -> 24.250164 | O89: =MAX(0.01,N88*(1+Ke)*(1-SC_Disc)) -> 27.402685
A90: Q2'26 letter ACV midpoint $22.5M (ACV_Q2) if GB300 at 491/IT MW | $/GPU-hr (vs MSFT $3.37, Astra $3.70, IREN ~$4.65) | B90: =ACV_Q2 -> 22.5 | C90: =B90*1000000/(491*8760) -> 5.2311469 | E90: capex multiple (CPM_Lease_VR / CPM_Lease_GB300) | F90: =CPM_Lease_VR/CPM_Lease_GB300 -> 1.0900442 | N90: =MAX(0.01,((PF_EV-OffBSWt*V_OFF-V_ODEBT-CHOOSE(DilMethod,0,SUMPRODUCT((N89<=V_TrPXsc)*((CVDebtBasis=1)*V_TrOP+(CVDebtBasis>=2)*V_TrBP)),SUMPRODUCT(((CVDebtBasis=1)*V_TrOP+(CVDebtBasis>=2)*V_TrBP)))+V_CASH+V_SOTP+V_FPCash)-MAX(0,V_EqIss0+FP_On*SUMPRODUCT(V_TrWin*V_TrPM*V_TrAcc*(V_TrSpot-((O90)>=V_TrEff)*(1-V_TrPlan))))/((1+Ke)*(1-SC_Disc)))/(V_BASIC+V_RSU+Options*MAX(0,1-OptK/N89)+CHOOSE(DilMethod,SUMPRODUCT(V_TrOP,V_TrRT)/1000,SUMPRODUCT((N89>V_TrPXsc)*V_TrOP*V_TrRT)/1000,SUMPRODUCT(((V_TrOP*V_TrRT/1000*N89-((CVDebtBasis=1)*V_TrOP+(CVDebtBasis>=2)*V_TrBP))>0)*(V_TrOP*V_TrRT/1000*N89-((CVDebtBasis=1)*V_TrOP+(CVDebtBasis>=2)*V_TrBP)))/N89)+FP_On*SUMPRODUCT(V_TrWin*V_TrPM*V_TrRT/1000*((O90)>=V_TrEff)*(1-V_TrPlan)))) -> 24.250164 | O90: =MAX(0.01,N89*(1+Ke)*(1-SC_Disc)) -> 27.402685
A91: Vera Rubin new deal (RubinMW) | $/GPU-hr at 320 (col D: Rubin / GB300 per GPU-hr) | B91: =RubinMW -> 16.2 | C91: =B91*1000000/(GPUMW_N*8760) -> 5.7791096 | D91: =C91/C88 -> 1.5535547 | E91: price-to-capex: Rubin (RubinMW / CPM_Lease_VR) | F91: =RubinMW/CPM_Lease_VR -> 0.40399002 | N91: =MAX(0.01,((PF_EV-OffBSWt*V_OFF-V_ODEBT-CHOOSE(DilMethod,0,SUMPRODUCT((N90<=V_TrPXsc)*((CVDebtBasis=1)*V_TrOP+(CVDebtBasis>=2)*V_TrBP)),SUMPRODUCT(((CVDebtBasis=1)*V_TrOP+(CVDebtBasis>=2)*V_TrBP)))+V_CASH+V_SOTP+V_FPCash)-MAX(0,V_EqIss0+FP_On*SUMPRODUCT(V_TrWin*V_TrPM*V_TrAcc*(V_TrSpot-((O91)>=V_TrEff)*(1-V_TrPlan))))/((1+Ke)*(1-SC_Disc)))/(V_BASIC+V_RSU+Options*MAX(0,1-OptK/N90)+CHOOSE(DilMethod,SUMPRODUCT(V_TrOP,V_TrRT)/1000,SUMPRODUCT((N90>V_TrPXsc)*V_TrOP*V_TrRT)/1000,SUMPRODUCT(((V_TrOP*V_TrRT/1000*N90-((CVDebtBasis=1)*V_TrOP+(CVDebtBasis>=2)*V_TrBP))>0)*(V_TrOP*V_TrRT/1000*N90-((CVDebtBasis=1)*V_TrOP+(CVDebtBasis>=2)*V_TrBP)))/N90)+FP_On*SUMPRODUCT(V_TrWin*V_TrPM*V_TrRT/1000*((O91)>=V_TrEff)*(1-V_TrPlan)))) -> 24.250164 | O91: =MAX(0.01,N90*(1+Ke)*(1-SC_Disc)) -> 27.402685
E92: price-to-capex: GB300 (MYRate / CPM_Lease_GB300) | F92: =MYRate/CPM_Lease_GB300 -> 0.43493034 | N92: =MAX(0.01,((PF_EV-OffBSWt*V_OFF-V_ODEBT-CHOOSE(DilMethod,0,SUMPRODUCT((N91<=V_TrPXsc)*((CVDebtBasis=1)*V_TrOP+(CVDebtBasis>=2)*V_TrBP)),SUMPRODUCT(((CVDebtBasis=1)*V_TrOP+(CVDebtBasis>=2)*V_TrBP)))+V_CASH+V_SOTP+V_FPCash)-MAX(0,V_EqIss0+FP_On*SUMPRODUCT(V_TrWin*V_TrPM*V_TrAcc*(V_TrSpot-((O92)>=V_TrEff)*(1-V_TrPlan))))/((1+Ke)*(1-SC_Disc)))/(V_BASIC+V_RSU+Options*MAX(0,1-OptK/N91)+CHOOSE(DilMethod,SUMPRODUCT(V_TrOP,V_TrRT)/1000,SUMPRODUCT((N91>V_TrPXsc)*V_TrOP*V_TrRT)/1000,SUMPRODUCT(((V_TrOP*V_TrRT/1000*N91-((CVDebtBasis=1)*V_TrOP+(CVDebtBasis>=2)*V_TrBP))>0)*(V_TrOP*V_TrRT/1000*N91-((CVDebtBasis=1)*V_TrOP+(CVDebtBasis>=2)*V_TrBP)))/N91)+FP_On*SUMPRODUCT(V_TrWin*V_TrPM*V_TrRT/1000*((O92)>=V_TrEff)*(1-V_TrPlan)))) -> 24.250164 | O92: =MAX(0.01,N91*(1+Ke)*(1-SC_Disc)) -> 27.402685
E93: FLAG if Rubin price-to-capex > GB300 by >10% | F93: =IF(PX_PCR>1.1*PX_PCG,"FLAG: Rubin price/capex much better than GB300 ("&TEXT(PX_PCR/PX_PCG,"0.00")&"x)","OK: Rubin price/capex "&TEXT(PX_PCR/PX_PCG,"0.00")&"x GB300") -> OK: Rubin price/capex 0.93x GB300 | N93: =MAX(0.01,((PF_EV-OffBSWt*V_OFF-V_ODEBT-CHOOSE(DilMethod,0,SUMPRODUCT((N92<=V_TrPXsc)*((CVDebtBasis=1)*V_TrOP+(CVDebtBasis>=2)*V_TrBP)),SUMPRODUCT(((CVDebtBasis=1)*V_TrOP+(CVDebtBasis>=2)*V_TrBP)))+V_CASH+V_SOTP+V_FPCash)-MAX(0,V_EqIss0+FP_On*SUMPRODUCT(V_TrWin*V_TrPM*V_TrAcc*(V_TrSpot-((O93)>=V_TrEff)*(1-V_TrPlan))))/((1+Ke)*(1-SC_Disc)))/(V_BASIC+V_RSU+Options*MAX(0,1-OptK/N92)+CHOOSE(DilMethod,SUMPRODUCT(V_TrOP,V_TrRT)/1000,SUMPRODUCT((N92>V_TrPXsc)*V_TrOP*V_TrRT)/1000,SUMPRODUCT(((V_TrOP*V_TrRT/1000*N92-((CVDebtBasis=1)*V_TrOP+(CVDebtBasis>=2)*V_TrBP))>0)*(V_TrOP*V_TrRT/1000*N92-((CVDebtBasis=1)*V_TrOP+(CVDebtBasis>=2)*V_TrBP)))/N92)+FP_On*SUMPRODUCT(V_TrWin*V_TrPM*V_TrRT/1000*((O93)>=V_TrEff)*(1-V_TrPlan)))) -> 24.250164 | O93: =MAX(0.01,N92*(1+Ke)*(1-SC_Disc)) -> 27.402685
A94: F) REVENUE DILUTION CROSS-CHECK ONLY (Peer KPIs payback_dilution.xlsx Nebius_Path): rev/MW = SS x (1 - k x new MW / avg MW); SS mixes legacy at L0 with new MW at P_new. NOT layered on the price path (would double count) | N94: =MAX(0.01,((PF_EV-OffBSWt*V_OFF-V_ODEBT-CHOOSE(DilMethod,0,SUMPRODUCT((N93<=V_TrPXsc)*((CVDebtBasis=1)*V_TrOP+(CVDebtBasis>=2)*V_TrBP)),SUMPRODUCT(((CVDebtBasis=1)*V_TrOP+(CVDebtBasis>=2)*V_TrBP)))+V_CASH+V_SOTP+V_FPCash)-MAX(0,V_EqIss0+FP_On*SUMPRODUCT(V_TrWin*V_TrPM*V_TrAcc*(V_TrSpot-((O94)>=V_TrEff)*(1-V_TrPlan))))/((1+Ke)*(1-SC_Disc)))/(V_BASIC+V_RSU+Options*MAX(0,1-OptK/N93)+CHOOSE(DilMethod,SUMPRODUCT(V_TrOP,V_TrRT)/1000,SUMPRODUCT((N93>V_TrPXsc)*V_TrOP*V_TrRT)/1000,SUMPRODUCT(((V_TrOP*V_TrRT/1000*N93-((CVDebtBasis=1)*V_TrOP+(CVDebtBasis>=2)*V_TrBP))>0)*(V_TrOP*V_TrRT/1000*N93-((CVDebtBasis=1)*V_TrOP+(CVDebtBasis>=2)*V_TrBP)))/N93)+FP_On*SUMPRODUCT(V_TrWin*V_TrPM*V_TrRT/1000*((O94)>=V_TrEff)*(1-V_TrPlan)))) -> 24.250164 | O94: =MAX(0.01,N93*(1+Ke)*(1-SC_Disc)) -> 27.402685
A95: k (dilution slope; range 0.43-0.62) | B95: 0.522 | N95: =MAX(0.01,((PF_EV-OffBSWt*V_OFF-V_ODEBT-CHOOSE(DilMethod,0,SUMPRODUCT((N94<=V_TrPXsc)*((CVDebtBasis=1)*V_TrOP+(CVDebtBasis>=2)*V_TrBP)),SUMPRODUCT(((CVDebtBasis=1)*V_TrOP+(CVDebtBasis>=2)*V_TrBP)))+V_CASH+V_SOTP+V_FPCash)-MAX(0,V_EqIss0+FP_On*SUMPRODUCT(V_TrWin*V_TrPM*V_TrAcc*(V_TrSpot-((O95)>=V_TrEff)*(1-V_TrPlan))))/((1+Ke)*(1-SC_Disc)))/(V_BASIC+V_RSU+Options*MAX(0,1-OptK/N94)+CHOOSE(DilMethod,SUMPRODUCT(V_TrOP,V_TrRT)/1000,SUMPRODUCT((N94>V_TrPXsc)*V_TrOP*V_TrRT)/1000,SUMPRODUCT(((V_TrOP*V_TrRT/1000*N94-((CVDebtBasis=1)*V_TrOP+(CVDebtBasis>=2)*V_TrBP))>0)*(V_TrOP*V_TrRT/1000*N94-((CVDebtBasis=1)*V_TrOP+(CVDebtBasis>=2)*V_TrBP)))/N94)+FP_On*SUMPRODUCT(V_TrWin*V_TrPM*V_TrRT/1000*((O95)>=V_TrEff)*(1-V_TrPlan)))) -> 24.250164 | O95: =MAX(0.01,N94*(1+Ke)*(1-SC_Disc)) -> 27.402685
A96: P_new $M/IT MW-yr (Nebius-Microsoft $17.1M) | B96: 17.086 | N96: =MAX(0.01,((PF_EV-OffBSWt*V_OFF-V_ODEBT-CHOOSE(DilMethod,0,SUMPRODUCT((N95<=V_TrPXsc)*((CVDebtBasis=1)*V_TrOP+(CVDebtBasis>=2)*V_TrBP)),SUMPRODUCT(((CVDebtBasis=1)*V_TrOP+(CVDebtBasis>=2)*V_TrBP)))+V_CASH+V_SOTP+V_FPCash)-MAX(0,V_EqIss0+FP_On*SUMPRODUCT(V_TrWin*V_TrPM*V_TrAcc*(V_TrSpot-((O96)>=V_TrEff)*(1-V_TrPlan))))/((1+Ke)*(1-SC_Disc)))/(V_BASIC+V_RSU+Options*MAX(0,1-OptK/N95)+CHOOSE(DilMethod,SUMPRODUCT(V_TrOP,V_TrRT)/1000,SUMPRODUCT((N95>V_TrPXsc)*V_TrOP*V_TrRT)/1000,SUMPRODUCT(((V_TrOP*V_TrRT/1000*N95-((CVDebtBasis=1)*V_TrOP+(CVDebtBasis>=2)*V_TrBP))>0)*(V_TrOP*V_TrRT/1000*N95-((CVDebtBasis=1)*V_TrOP+(CVDebtBasis>=2)*V_TrBP)))/N95)+FP_On*SUMPRODUCT(V_TrWin*V_TrPM*V_TrRT/1000*((O96)>=V_TrEff)*(1-V_TrPlan)))) -> 24.250164 | O96: =MAX(0.01,N95*(1+Ke)*(1-SC_Disc)) -> 27.402685
A97: L0 = Q2'26 AI rev x 4 / avg Q2'26 energized IT MW | B97: =574.9*4/AVERAGE(INDEX(MW_En,1,9),INDEX(MW_En,1,10)) -> 13.011225 | N97: =MAX(0.01,((PF_EV-OffBSWt*V_OFF-V_ODEBT-CHOOSE(DilMethod,0,SUMPRODUCT((N96<=V_TrPXsc)*((CVDebtBasis=1)*V_TrOP+(CVDebtBasis>=2)*V_TrBP)),SUMPRODUCT(((CVDebtBasis=1)*V_TrOP+(CVDebtBasis>=2)*V_TrBP)))+V_CASH+V_SOTP+V_FPCash)-MAX(0,V_EqIss0+FP_On*SUMPRODUCT(V_TrWin*V_TrPM*V_TrAcc*(V_TrSpot-((O97)>=V_TrEff)*(1-V_TrPlan))))/((1+Ke)*(1-SC_Disc)))/(V_BASIC+V_RSU+Options*MAX(0,1-OptK/N96)+CHOOSE(DilMethod,SUMPRODUCT(V_TrOP,V_TrRT)/1000,SUMPRODUCT((N96>V_TrPXsc)*V_TrOP*V_TrRT)/1000,SUMPRODUCT(((V_TrOP*V_TrRT/1000*N96-((CVDebtBasis=1)*V_TrOP+(CVDebtBasis>=2)*V_TrBP))>0)*(V_TrOP*V_TrRT/1000*N96-((CVDebtBasis=1)*V_TrOP+(CVDebtBasis>=2)*V_TrBP)))/N96)+FP_On*SUMPRODUCT(V_TrWin*V_TrPM*V_TrRT/1000*((O97)>=V_TrEff)*(1-V_TrPlan)))) -> 24.250164 | O97: =MAX(0.01,N96*(1+Ke)*(1-SC_Disc)) -> 27.402685
A98: Quarter idx | B98: End energized IT MW | C98: Avg MW | D98: New MW | E98: SS $M/MW-yr | F98: Rev/MW diluted | G98: Implied AI rev $M | H98: Model AI rev $M | N98: =MAX(0.01,((PF_EV-OffBSWt*V_OFF-V_ODEBT-CHOOSE(DilMethod,0,SUMPRODUCT((N97<=V_TrPXsc)*((CVDebtBasis=1)*V_TrOP+(CVDebtBasis>=2)*V_TrBP)),SUMPRODUCT(((CVDebtBasis=1)*V_TrOP+(CVDebtBasis>=2)*V_TrBP)))+V_CASH+V_SOTP+V_FPCash)-MAX(0,V_EqIss0+FP_On*SUMPRODUCT(V_TrWin*V_TrPM*V_TrAcc*(V_TrSpot-((O98)>=V_TrEff)*(1-V_TrPlan))))/((1+Ke)*(1-SC_Disc)))/(V_BASIC+V_RSU+Options*MAX(0,1-OptK/N97)+CHOOSE(DilMethod,SUMPRODUCT(V_TrOP,V_TrRT)/1000,SUMPRODUCT((N97>V_TrPXsc)*V_TrOP*V_TrRT)/1000,SUMPRODUCT(((V_TrOP*V_TrRT/1000*N97-((CVDebtBasis=1)*V_TrOP+(CVDebtBasis>=2)*V_TrBP))>0)*(V_TrOP*V_TrRT/1000*N97-((CVDebtBasis=1)*V_TrOP+(CVDebtBasis>=2)*V_TrBP)))/N97)+FP_On*SUMPRODUCT(V_TrWin*V_TrPM*V_TrRT/1000*((O98)>=V_TrEff)*(1-V_TrPlan)))) -> 24.250164 | O98: =MAX(0.01,N97*(1+Ke)*(1-SC_Disc)) -> 27.402685
A99: =11 -> 11 | B99: =INDEX(MW_En,1,11) -> 216.9897 | C99: =AVERAGE(INDEX(MW_En,1,10),INDEX(MW_En,1,11)) -> 199.7397 | D99: =MAX(0,INDEX(MW_En,1,11)-INDEX(MW_En,1,10)) -> 34.5 | E99: =(DX_L0*AVERAGE(INDEX(MW_En,1,9),INDEX(MW_En,1,10))+DX_P*MAX(0,C99-AVERAGE(INDEX(MW_En,1,9),INDEX(MW_En,1,10))))/C99 -> 13.480435 | F99: =E99*(1-DX_k*D99/C99) -> 12.265007 | G99: =F99*C99/4 -> 612.45221 | H99: =INDEX(AIRev,1,11) -> 667.13841 | N99: =IF(N98<=0.011,0,N98) -> 24.250164
A100: =12 -> 12 | B100: =INDEX(MW_En,1,12) -> 301.7195 | C100: =AVERAGE(INDEX(MW_En,1,11),INDEX(MW_En,1,12)) -> 259.3546 | D100: =MAX(0,INDEX(MW_En,1,12)-INDEX(MW_En,1,11)) -> 84.7298 | E100: =(DX_L0*AVERAGE(INDEX(MW_En,1,9),INDEX(MW_En,1,10))+DX_P*MAX(0,C100-AVERAGE(INDEX(MW_En,1,9),INDEX(MW_En,1,10))))/C100 -> 14.309205 | F100: =E100*(1-DX_k*D100/C100) -> 11.868989 | G100: =F100*C100/4 -> 769.56925 | H100: =INDEX(AIRev,1,12) -> 801.39417
A101: =13 -> 13 | B101: =INDEX(MW_En,1,13) -> 453.79225 | C101: =AVERAGE(INDEX(MW_En,1,12),INDEX(MW_En,1,13)) -> 377.75588 | D101: =MAX(0,INDEX(MW_En,1,13)-INDEX(MW_En,1,12)) -> 152.07275 | E101: =(DX_L0*AVERAGE(INDEX(MW_En,1,9),INDEX(MW_En,1,10))+DX_P*MAX(0,C101-AVERAGE(INDEX(MW_En,1,9),INDEX(MW_En,1,10))))/C101 -> 15.179545 | F101: =E101*(1-DX_k*D101/C101) -> 11.989701 | G101: =F101*C101/4 -> 1132.295 | H101: =INDEX(AIRev,1,13) -> 1019.7944
A102: =14 -> 14 | B102: =INDEX(MW_En,1,14) -> 629.5368 | C102: =AVERAGE(INDEX(MW_En,1,13),INDEX(MW_En,1,14)) -> 541.66453 | D102: =MAX(0,INDEX(MW_En,1,14)-INDEX(MW_En,1,13)) -> 175.74455 | E102: =(DX_L0*AVERAGE(INDEX(MW_En,1,9),INDEX(MW_En,1,10))+DX_P*MAX(0,C102-AVERAGE(INDEX(MW_En,1,9),INDEX(MW_En,1,10))))/C102 -> 15.756442 | F102: =E102*(1-DX_k*D102/C102) -> 13.087862 | G102: =F102*C102/4 -> 1772.3077 | H102: =INDEX(AIRev,1,14) -> 1625.1205
A103: =15 -> 15 | B103: =INDEX(MW_En,1,15) -> 812.6073 | C103: =AVERAGE(INDEX(MW_En,1,14),INDEX(MW_En,1,15)) -> 721.07205 | D103: =MAX(0,INDEX(MW_En,1,15)-INDEX(MW_En,1,14)) -> 183.0705 | E103: =(DX_L0*AVERAGE(INDEX(MW_En,1,9),INDEX(MW_En,1,10))+DX_P*MAX(0,C103-AVERAGE(INDEX(MW_En,1,9),INDEX(MW_En,1,10))))/C103 -> 16.087245 | F103: =E103*(1-DX_k*D103/C103) -> 13.955222 | G103: =F103*C103/4 -> 2515.6801 | H103: =INDEX(AIRev,1,15) -> 2454.0415
A104: =16 -> 16 | B104: =INDEX(MW_En,1,16) -> 1081.9108 | C104: =AVERAGE(INDEX(MW_En,1,15),INDEX(MW_En,1,16)) -> 947.25905 | D104: =MAX(0,INDEX(MW_En,1,16)-INDEX(MW_En,1,15)) -> 269.3035 | E104: =(DX_L0*AVERAGE(INDEX(MW_En,1,9),INDEX(MW_En,1,10))+DX_P*MAX(0,C104-AVERAGE(INDEX(MW_En,1,9),INDEX(MW_En,1,10))))/C104 -> 16.325728 | F104: =E104*(1-DX_k*D104/C104) -> 13.902935 | G104: =F104*C104/4 -> 3292.4203 | H104: =INDEX(AIRev,1,16) -> 3077.9173
A105: FY27 AI cloud revenue: dilution cross-check | model | gap (model - cross-check) | B105: =SUM(G101:G104) -> 8712.7031 | C105: =SUM(H101:H104) -> 8176.8737 | D105: =C105-B105 -> -535.82943
A108: G) v0.8 BREAKEVEN NEW-DEAL PRICE ($M per IT MW-yr) at which a new uncontracted MW is NPV-zero: after tax, after corporate costs (PB_Corp x revenue), capex at t0, flat EBITDA over PB_Life, residual as section C (col P basis). Solved in closed form (P is linear in price).
A109: Case (section C row) | B109: WACC 9% | C109: WACC 10% | D109: WACC 11% | E109: live WACC | F109: current price | G109: capex $M/IT MW | H109: opex
A110: Leased GB300 (row 28) | B110: =IF(((F28-TaxRate*((F28-Q28)/PB_Life+Q28*(ShellMW/(ShellMW+PowerMW)/Life_Shell+PowerMW/(ShellMW+PowerMW)/Life_Pow))*((1-(1+0.09)^-PB_Life)/0.09)-(PB_Resid*(F28-Q28)*(1-TaxRate)+Q28*MAX(0,1-PB_Life/PB_HallLife)-TaxRate*(Q28*MAX(0,1-PB_Life/PB_HallLife)-Q28*MAX(0,1-PB_Life*(ShellMW/(ShellMW+PowerMW)/Life_Shell+PowerMW/(ShellMW+PowerMW)/Life_Pow))))*((1+0.09)^-PB_Life))/((1-TaxRate)*(1-PB_Corp)*((1-(1+0.09)^-PB_Life)/0.09))+G28/(1-PB_Corp))*(1-PB_Corp)-G28-((F28-Q28)/PB_Life+Q28*(ShellMW/(ShellMW+PowerMW)/Life_Shell+PowerMW/(ShellMW+PowerMW)/Life_Pow))>=0,((F28-TaxRate*((F28-Q28)/PB_Life+Q28*(ShellMW/(ShellMW+PowerMW)/Life_Shell+PowerMW/(ShellMW+PowerMW)/Life_Pow))*((1-(1+0.09)^-PB_Life)/0.09)-(PB_Resid*(F28-Q28)*(1-TaxRate)+Q28*MAX(0,1-PB_Life/PB_HallLife)-TaxRate*(Q28*MAX(0,1-PB_Life/PB_HallLife)-Q28*MAX(0,1-PB_Life*(ShellMW/(ShellMW+PowerMW)/Life_Shell+PowerMW/(ShellMW+PowerMW)/Life_Pow))))*((1+0.09)^-PB_Life))/((1-TaxRate)*(1-PB_Corp)*((1-(1+0.09)^-PB_Life)/0.09))+G28/(1-PB_Corp)),((F28-(PB_Resid*(F28-Q28)*(1-TaxRate)+Q28*MAX(0,1-PB_Life/PB_HallLife)-TaxRate*(Q28*MAX(0,1-PB_Life/PB_HallLife)-Q28*MAX(0,1-PB_Life*(ShellMW/(ShellMW+PowerMW)/Life_Shell+PowerMW/(ShellMW+PowerMW)/Life_Pow))))*((1+0.09)^-PB_Life))/((1-PB_Corp)*((1-(1+0.09)^-PB_Life)/0.09))+G28/(1-PB_Corp))) -> 17.935505 | C110: =IF(((F28-TaxRate*((F28-Q28)/PB_Life+Q28*(ShellMW/(ShellMW+PowerMW)/Life_Shell+PowerMW/(ShellMW+PowerMW)/Life_Pow))*((1-(1+0.1)^-PB_Life)/0.1)-(PB_Resid*(F28-Q28)*(1-TaxRate)+Q28*MAX(0,1-PB_Life/PB_HallLife)-TaxRate*(Q28*MAX(0,1-PB_Life/PB_HallLife)-Q28*MAX(0,1-PB_Life*(ShellMW/(ShellMW+PowerMW)/Life_Shell+PowerMW/(ShellMW+PowerMW)/Life_Pow))))*((1+0.1)^-PB_Life))/((1-TaxRate)*(1-PB_Corp)*((1-(1+0.1)^-PB_Life)/0.1))+G28/(1-PB_Corp))*(1-PB_Corp)-G28-((F28-Q28)/PB_Life+Q28*(ShellMW/(ShellMW+PowerMW)/Life_Shell+PowerMW/(ShellMW+PowerMW)/Life_Pow))>=0,((F28-TaxRate*((F28-Q28)/PB_Life+Q28*(ShellMW/(ShellMW+PowerMW)/Life_Shell+PowerMW/(ShellMW+PowerMW)/Life_Pow))*((1-(1+0.1)^-PB_Life)/0.1)-(PB_Resid*(F28-Q28)*(1-TaxRate)+Q28*MAX(0,1-PB_Life/PB_HallLife)-TaxRate*(Q28*MAX(0,1-PB_Life/PB_HallLife)-Q28*MAX(0,1-PB_Life*(ShellMW/(ShellMW+PowerMW)/Life_Shell+PowerMW/(ShellMW+PowerMW)/Life_Pow))))*((1+0.1)^-PB_Life))/((1-TaxRate)*(1-PB_Corp)*((1-(1+0.1)^-PB_Life)/0.1))+G28/(1-PB_Corp)),((F28-(PB_Resid*(F28-Q28)*(1-TaxRate)+Q28*MAX(0,1-PB_Life/PB_HallLife)-TaxRate*(Q28*MAX(0,1-PB_Life/PB_HallLife)-Q28*MAX(0,1-PB_Life*(ShellMW/(ShellMW+PowerMW)/Life_Shell+PowerMW/(ShellMW+PowerMW)/Life_Pow))))*((1+0.1)^-PB_Life))/((1-PB_Corp)*((1-(1+0.1)^-PB_Life)/0.1))+G28/(1-PB_Corp))) -> 18.398617 | D110: =IF(((F28-TaxRate*((F28-Q28)/PB_Life+Q28*(ShellMW/(ShellMW+PowerMW)/Life_Shell+PowerMW/(ShellMW+PowerMW)/Life_Pow))*((1-(1+0.11)^-PB_Life)/0.11)-(PB_Resid*(F28-Q28)*(1-TaxRate)+Q28*MAX(0,1-PB_Life/PB_HallLife)-TaxRate*(Q28*MAX(0,1-PB_Life/PB_HallLife)-Q28*MAX(0,1-PB_Life*(ShellMW/(ShellMW+PowerMW)/Life_Shell+PowerMW/(ShellMW+PowerMW)/Life_Pow))))*((1+0.11)^-PB_Life))/((1-TaxRate)*(1-PB_Corp)*((1-(1+0.11)^-PB_Life)/0.11))+G28/(1-PB_Corp))*(1-PB_Corp)-G28-((F28-Q28)/PB_Life+Q28*(ShellMW/(ShellMW+PowerMW)/Life_Shell+PowerMW/(ShellMW+PowerMW)/Life_Pow))>=0,((F28-TaxRate*((F28-Q28)/PB_Life+Q28*(ShellMW/(ShellMW+PowerMW)/Life_Shell+PowerMW/(ShellMW+PowerMW)/Life_Pow))*((1-(1+0.11)^-PB_Life)/0.11)-(PB_Resid*(F28-Q28)*(1-TaxRate)+Q28*MAX(0,1-PB_Life/PB_HallLife)-TaxRate*(Q28*MAX(0,1-PB_Life/PB_HallLife)-Q28*MAX(0,1-PB_Life*(ShellMW/(ShellMW+PowerMW)/Life_Shell+PowerMW/(ShellMW+PowerMW)/Life_Pow))))*((1+0.11)^-PB_Life))/((1-TaxRate)*(1-PB_Corp)*((1-(1+0.11)^-PB_Life)/0.11))+G28/(1-PB_Corp)),((F28-(PB_Resid*(F28-Q28)*(1-TaxRate)+Q28*MAX(0,1-PB_Life/PB_HallLife)-TaxRate*(Q28*MAX(0,1-PB_Life/PB_HallLife)-Q28*MAX(0,1-PB_Life*(ShellMW/(ShellMW+PowerMW)/Life_Shell+PowerMW/(ShellMW+PowerMW)/Life_Pow))))*((1+0.11)^-PB_Life))/((1-PB_Corp)*((1-(1+0.11)^-PB_Life)/0.11))+G28/(1-PB_Corp))) -> 18.865675 | E110: =IF(((F28-TaxRate*((F28-Q28)/PB_Life+Q28*(ShellMW/(ShellMW+PowerMW)/Life_Shell+PowerMW/(ShellMW+PowerMW)/Life_Pow))*((1-(1+PB_WACC)^-PB_Life)/PB_WACC)-(PB_Resid*(F28-Q28)*(1-TaxRate)+Q28*MAX(0,1-PB_Life/PB_HallLife)-TaxRate*(Q28*MAX(0,1-PB_Life/PB_HallLife)-Q28*MAX(0,1-PB_Life*(ShellMW/(ShellMW+PowerMW)/Life_Shell+PowerMW/(ShellMW+PowerMW)/Life_Pow))))*((1+PB_WACC)^-PB_Life))/((1-TaxRate)*(1-PB_Corp)*((1-(1+PB_WACC)^-PB_Life)/PB_WACC))+G28/(1-PB_Corp))*(1-PB_Corp)-G28-((F28-Q28)/PB_Life+Q28*(ShellMW/(ShellMW+PowerMW)/Life_Shell+PowerMW/(ShellMW+PowerMW)/Life_Pow))>=0,((F28-TaxRate*((F28-Q28)/PB_Life+Q28*(ShellMW/(ShellMW+PowerMW)/Life_Shell+PowerMW/(ShellMW+PowerMW)/Life_Pow))*((1-(1+PB_WACC)^-PB_Life)/PB_WACC)-(PB_Resid*(F28-Q28)*(1-TaxRate)+Q28*MAX(0,1-PB_Life/PB_HallLife)-TaxRate*(Q28*MAX(0,1-PB_Life/PB_HallLife)-Q28*MAX(0,1-PB_Life*(ShellMW/(ShellMW+PowerMW)/Life_Shell+PowerMW/(ShellMW+PowerMW)/Life_Pow))))*((1+PB_WACC)^-PB_Life))/((1-TaxRate)*(1-PB_Corp)*((1-(1+PB_WACC)^-PB_Life)/PB_WACC))+G28/(1-PB_Corp)),((F28-(PB_Resid*(F28-Q28)*(1-TaxRate)+Q28*MAX(0,1-PB_Life/PB_HallLife)-TaxRate*(Q28*MAX(0,1-PB_Life/PB_HallLife)-Q28*MAX(0,1-PB_Life*(ShellMW/(ShellMW+PowerMW)/Life_Shell+PowerMW/(ShellMW+PowerMW)/Life_Pow))))*((1+PB_WACC)^-PB_Life))/((1-PB_Corp)*((1-(1+PB_WACC)^-PB_Life)/PB_WACC))+G28/(1-PB_Corp))) -> 18.865675 | F110: =H28 -> 16 | G110: =F28 -> 38.3875 | H110: =G28 -> 4.5
...

Sheet Funding
A1: LEGACY v0.4 parametric funding illustration (v0.7 plan is wired in Inputs FP_*, CashFlow, Valuation POST-FUNDING block) - ESTIMATED (illustrative; DCF value/share already reflects capex; dilution arises only from issuing equity/converts vs model value)
A4: Gap
A5: Minimum liquidity Q3'26-Q4'27 (no plug) | B5: =MIN(INDEX(Liq,1,11):INDEX(Liq,1,16)) -> 1000
A6: Minimum liquidity Q3'26-Q4'28 (no plug) | B6: =MIN(INDEX(Liq,1,11):INDEX(Liq,1,20)) -> 1000
A7: Funding need through FY27 = MinCash - min liquidity | B7: =MAX(0,MinCash-FU_Min27) -> 1000
A8: Funding need through FY28 | B8: =MAX(0,MinCash-FU_Min28) -> 1000
A9: Plan target (1 = through FY27, 2 = through FY28) | B9: 1
A10: Plan target ($M) | B10: =IF(FU_TgtSel=2,FU_Gap28,FU_Gap27) -> 1000
A11: Model FD value/share (V_PS) and implied FD shares (M) | B11: =V_PS -> 0.01
A12: FD shares at value (M) = V_EQ / V_PS | B12: =IFERROR(V_EQ/V_PS,0) -> -62109.621
A14: Source inputs (Estimated)
A15: ATM: shares remaining (M) | B15: =ATM_Rem -> 12.270507
A16: ATM: issue price = SharePx x (1 - discount/fees) | B16: =SharePx*(1-FU_ATMd) -> 237.9538
A17: ATM discount + fees | B17: 0.02
A18: Customer prepayments: incremental beyond PrepayPct ($M) | B18: 1500 | C18: Q2 letter: >$9B prepayments in 2026; 70% of deals, 50-60% of capex
A19: Prepayment price concession (% of amount, PV cost) | B19: 0
A20: ABS / GPU-backed debt: LTV on GPU net book value at Q2'27 | B20: 0.5
A21: GPU net book value at Q2'27 ($M) | B21: =INDEX(NBV_H,1,14)+INDEX(NBV_B,1,14)+INDEX(NBV_N,1,14) -> 29053.325
A22: ABS capacity ($M) = LTV x GPU NBV, capped | B22: =MIN(FU_LTV*FU_NBV,FU_ABSCap) -> 5000
A23: ABS cap ($M) | B23: 5000
A24: ABS interest rate | B24: 0.09 | C24: memo: cost in WACC; no share dilution
A25: New converts: amount ($M) | B25: 3000
A26: Conversion premium | B26: 0.35
A27: Conversion price | B27: =SharePx*(1+FU_CVPrem) -> 327.7935
A29: Per-source effect if used ALONE at full size (value/share = (V_EQ + equity-like proceeds) / (shares + new shares)) | B29: Proceeds $M | C29: New shares M | D29: Value/share $ | E29: Change $/sh | F29: Dilution %
A30: ATM (all 12.27M sh) | B30: =FU_ATMsh*FU_ATMpx -> 2919.8138 | C30: =FU_ATMsh -> 12.270507 | D30: =(V_EQ+FU_ATMsh*FU_ATMpx)/(FU_N+FU_ATMsh) -> -0.037017965 | E30: =D30-FU_V -> -0.047017965 | F30: =IFERROR(C30/FU_N,0) -> -0.0001975621
A31: Customer prepayments | B31: =FU_PreAmt -> 1500 | C31: =0 -> 0 | D31: =FU_V-FU_PreAmt*FU_PreCost/FU_N -> 0.01 | E31: =D31-FU_V -> 0 | F31: =IFERROR(C31/FU_N,0) -> 0
A32: ABS / GPU-backed debt | B32: =FU_ABSMax -> 5000 | C32: =0 -> 0 | D32: =FU_V -> 0.01 | E32: =D32-FU_V -> 0 | F32: =IFERROR(C32/FU_N,0) -> 0
A33: New converts (if converted when value > conv. price) | B33: =FU_CVAmt -> 3000 | C33: =IF(FU_V>FU_CVPx,FU_CVAmt/FU_CVPx,0) -> 0 | D33: =IF(FU_V>FU_CVPx,(V_EQ+FU_CVAmt)/(FU_N+FU_CVAmt/FU_CVPx),FU_V) -> 0.01 | E33: =D33-FU_V -> 0 | F33: =IFERROR(C33/FU_N,0) -> 0
A35: Combined plan to fill the target: order prepayments -> ATM -> ABS -> converts
A36: Prepayments used | B36: =MIN(FU_PreAmt,FU_Tgt) -> 1000
A37: ATM used ($M) | B37: =MIN(FU_ATMsh*FU_ATMpx,FU_Tgt-FU_P1) -> 0
A38: ABS used | B38: =MIN(FU_ABSMax,FU_Tgt-FU_P1-FU_P2) -> 0
A39: Converts used | B39: =MIN(FU_CVAmt,FU_Tgt-FU_P1-FU_P2-FU_P3) -> 0
A40: Unfunded remainder (needs equity plug / more sources) | B40: =FU_Tgt-FU_P1-FU_P2-FU_P3-FU_P4 -> 0
A41: New shares: ATM + converts (if converted) | B41: =IFERROR(FU_P2/FU_ATMpx,0)+IF(FU_V>FU_CVPx,FU_P4/FU_CVPx,0) -> 0
A42: Combined value/share | B42: =(V_EQ+FU_P2+IF(FU_V>FU_CVPx,FU_P4,0)-FU_P1*FU_PreCost)/(FU_N+FU_Sh) -> 0.01
A43: Change vs model value/share ($) | B43: =FU_VC-FU_V -> 0
A44: Dilution (% of FD shares) | B44: =IFERROR(FU_Sh/FU_N,0) -> 0
A45: Memo: ABS annual interest ($M) | B45: =FU_P3*FU_ABSr -> 0
A47: v0.8 RECONCILIATION: Capacity ~$17-18B capex for uncontracted MW vs model funding need (col B = Q3'26-Q4'27; col D = Q3'26-Q4'30). Signs: + = needs funding, ( ) = funds itself
B48: Q3'26-Q4'27 | D48: Q3'26-Q4'30
A49: Capacity estimate: capex for uncontracted MW to YE27 (~$17-18B; owned Rubin ~165 MW x $52.6M + leased ~230-250 MW; Capacity, Estimated) | B49: 17500 | D49: =B49 -> 17500
A50: Model: new-build capex on UNCONTRACTED MW (CapNew x (1 - signed share)) - incl. capex spent ahead of go-live (GPULead / DCLead) for sites billing in 2027-28 | B50: =SUMPRODUCT((Q_Idx>=11)*(Q_Idx<=16)*(CapNew*(1-CF_SigSh))) -> 31957.222 | D50: =SUMPRODUCT((Q_Idx>=11)*(Q_Idx<=28)*(CapNew*(1-CF_SigSh))) -> 94186.748
A51: timing / scope difference vs Capacity (model - Capacity; col D = post-YE27 uncontracted build) | B51: =B50-B49 -> 14457.222 | D51: =D50-B49 -> 76686.748
A52: + new-build capex on CONTRACTED MW (Microsoft T5-T9, Meta; no new prepayment on signed deals) | B52: =SUMPRODUCT((Q_Idx>=11)*(Q_Idx<=16)*(CapNew*CF_SigSh)) -> 10258.928 | D52: =SUMPRODUCT((Q_Idx>=11)*(Q_Idx<=28)*(CapNew*CF_SigSh)) -> 10258.928
A53: + maintenance capex + GPU refresh / replacement + lease prepayments - after-tax residual proceeds | B53: =SUMPRODUCT((Q_Idx>=11)*(Q_Idx<=16)*(CapMaint+CapRepl+CapLPre-CapResid)) -> 1050.7145 | D53: =SUMPRODUCT((Q_Idx>=11)*(Q_Idx<=28)*(CapMaint+CapRepl+CapLPre-CapResid)) -> 6546.4371
A54: TOTAL CAPEX (net of residual) | B54: =SUMPRODUCT((Q_Idx>=11)*(Q_Idx<=16)*(Capex-CapResid)) -> 43266.864 | D54: =SUMPRODUCT((Q_Idx>=11)*(Q_Idx<=28)*(Capex-CapResid)) -> 110992.11
A55: - Adj. EBITDA (rent, power, opex and corporate burn are netted here) | B55: =SUMPRODUCT((Q_Idx>=11)*(Q_Idx<=16)*(-PL_EBITDA)) -> -4798.7348 | D55: =SUMPRODUCT((Q_Idx>=11)*(Q_Idx<=28)*(-PL_EBITDA)) -> -61666.541
A56: + cash taxes + net cash interest (coupons + secured - interest income; plug interest excluded as in the runway) | B56: =SUMPRODUCT((Q_Idx>=11)*(Q_Idx<=16)*(PL_Tax+CV_cpn+Sec_Int+ABS_Int-CF_IntInc)) -> 215.10887 | D56: =SUMPRODUCT((Q_Idx>=11)*(Q_Idx<=28)*(PL_Tax+CV_cpn+Sec_Int+ABS_Int-CF_IntInc)) -> 1801.9845
A57: - net new customer prepayments (new prepayments - deferred revenue released) | B57: =SUMPRODUCT((Q_Idx>=11)*(Q_Idx<=16)*(-(CF_Prepay-CF_DRRel))) -> -4835.3 | D57: =SUMPRODUCT((Q_Idx>=11)*(Q_Idx<=28)*(-(CF_Prepay-CF_DRRel))) -> -3651.6492
A58: + other investing (CLT1 prepayment, Inferize) | B58: =SUMPRODUCT((Q_Idx>=11)*(Q_Idx<=16)*(-CF_OthInv)) -> 0 | D58: =SUMPRODUCT((Q_Idx>=11)*(Q_Idx<=28)*(-CF_OthInv)) -> 0
A59: + convert maturities / redemptions + secured + ABS repayments | B59: =SUMPRODUCT((Q_Idx>=11)*(Q_Idx<=16)*(CV_rep-MIN(0,Sec_Flow)+ABS_Rep)) -> 0 | D59: =SUMPRODUCT((Q_Idx>=11)*(Q_Idx<=28)*(CV_rep-MIN(0,Sec_Flow)+ABS_Rep)) -> 8019
A60: + change in liquidity (end - 6/30 cash $8.0B; minimum buffer FP_MinBuf) | B60: =INDEX(Liq,1,16)-CS_Cash -> -7042.1 | D60: =INDEX(Liq,1,28)-CS_Cash -> 4618.2812
A61: GROSS EXTERNAL FUNDING NEED | B61: =SUM(B54:B60) -> 26805.838 | D61: =SUM(D54:D60) -> 60113.188
A62: - debt-like sources: Aug-26 converts ($5.75B gross) + funding-plan converts (net) + secured draws + ABS draws on contracted MW | B62: =SUMPRODUCT((Q_Idx>=11)*(Q_Idx<=16)*(-(Liq_Aug+CF_FPConv+MAX(0,Sec_Flow)+ABS_Draw))) -> -18394.174 | D62: =SUMPRODUCT((Q_Idx>=11)*(Q_Idx<=28)*(-(Liq_Aug+CF_FPConv+MAX(0,Sec_Flow)+ABS_Draw))) -> -18394.174
A63: EQUITY NEED (ATM + equity top-ups) | B63: =B61+B62 -> 8411.6641 | D63: =D61+D62 -> 41719.014
A64: check: model ATM + top-ups (should equal the line above) | B64: =SUMPRODUCT((Q_Idx>=11)*(Q_Idx<=16)*(CF_ATM+FP_EqTop)) -> 8411.6641 | D64: =SUMPRODUCT((Q_Idx>=11)*(Q_Idx<=28)*(CF_ATM+FP_EqTop)) -> 41719.014
A65: Why they differ: Capacity's figure is only the capex for uncontracted MW live by YE27. The model's funding need adds contracted-MW capex (no new prepayment on signed deals), maintenance / refresh, convert maturities, the liquidity buffer, and all 2028-30 build. It nets operating EBITDA and new prepayments. '~$43B' = model capex Q3'26-Q4'27 (col B total capex); equity need Q3'26-Q4'30 = col D.

Sheet Funding_Stack
A1: v0.8b FUNDING STACK - live toggles (Inputs: NDPrepayOn/NDPrepayPct, ABS_LTC/ABS_Spread/ABS_Term, UncPxOn/UncPx/UncRenew, BackstopMW) and static grid (self-consistent PT basis)
A3: New-deal prepayment toggle (NDPrepayOn) / share of new-build capex on non-signed MW | B3: =NDPrepayOn -> 0
A4: NDPrepayPct | B4: =NDPrepayPct -> 0.55
A5: ABS loan-to-cost on contracted-MW capex (ABS_LTC) | B5: =ABS_LTC -> 0
A6: ABS rate = SOFR + spread | B6: =SOFR+ABS_Spread -> 0.065
A7: ABS after-tax cost = rate x (1 - TaxRate) | B7: =FS_Kd*(1-TaxRate) -> 0.04823
A8: Unsold new-MW price toggle (UncPxOn) / UncPx $M per IT MW-yr | B8: =IF(UncPxOn=1,UncPx,0) -> 0
A9: Meta backstop MW | B9: =BackstopMW -> 0
A10: Stop building | B10: =StopBuild -> 0
A11: New prepayments Q3'26-Q4'30 ($M) | B11: =SUMPRODUCT((Q_Idx>=11)*(Q_Idx<=28)*CF_Prepay) -> 20079.989
A12: ABS draws Q3'26-Q4'30 ($M) | B12: =SUMPRODUCT((Q_Idx>=11)*(Q_Idx<=28)*ABS_Draw) -> 0
A13: ABS peak balance ($M) | B13: =MAX(ABS_Bal) -> 0
A14: ABS interest Q3'26-Q4'30 ($M) | B14: =SUMPRODUCT((Q_Idx>=11)*(Q_Idx<=28)*ABS_Int) -> 0
A15: Total capex Q3'26-Q4'30 ($M) | B15: =SUMPRODUCT((Q_Idx>=11)*(Q_Idx<=28)*Capex) -> 111441.91
A16: ABS share of funding mix = ABS draws / total capex Q3'26-Q4'30 | B16: =IFERROR(FS_ABS/FS_Cx,0) -> 0
A17: Base WACC implied for the rest of the mix | B17: 0.11
A18: BLENDED WACC = ABS share x after-tax ABS cost + (1 - share) x base 11% | B18: =FS_wABS*FS_Kdat+(1-FS_wABS)*FS_WBase -> 0.11
A19: Equity top-ups + ATM Q3'26-Q4'30 ($M) | B19: =SUMPRODUCT((Q_Idx>=11)*(Q_Idx<=28)*(FP_EqTop+CF_ATM)) -> 41719.014
A20: 2027 plan converts (net, $M) | B20: =SUM(CF_FPConv) -> 12644.174
A21: Self-consistent PT (live) / EV / new shares / YE27 liquidity | B21: =V_PT -> 3.970466 | C21: =V_EV -> -898.81401 | D21: =V_NewShHead -> 10991.22 | E21: =INDEX(Liq,1,16) -> 1000
A24: STATIC GRID (fs_grid.py; full recalcs) - see rows below
A25: BUILD PLAN (base 11% WACC unless stated)
A26: Layer / case | B26: Self-consistent PT $ | C26: EV $M | D26: New shares M (headline) | E26: Authority need M (vs ~82) | F26: YE27 liquidity $M | G26: Spot-issuance PT memo $ | H26: New prepayments $M | I26: ABS draws $M | J26: ABS interest $M | K26: Plan converts net $M | L26: ATM + top-ups $M | M26: WACC used
A27: base (v0.8) | B27: 3.970466 | C27: -898.81401 | D27: 10991.22 | E27: 13262.174 | F27: 1000 | G27: 88.869332 | H27: 20079.989 | I27: 0 | J27: 0 | K27: 12644.174 | L27: 41719.014 | M27: 0.11
A28: + prepay 55% | B28: 13.510189 | C28: 4052.2467 | D28: 1405.8624 | E28: 2073.266 | F28: 5634.4432 | G28: 58.101767 | H28: 51802.711 | I28: 0 | J28: 0 | K28: 12644.174 | L28: 17072.217 | M28: 0.11
A29: + ABS 50% on contracted MW | B29: 13.903524 | C29: 4052.2467 | D29: 1577.9848 | E29: 1966.6189 | F29: 5323.5951 | G29: 63.806779 | H29: 51802.711 | I29: 5129.4639 | J29: 922.64173 | K29: 7577.1556 | L29: 20018.3 | M29: 0.11
A30: + uncontracted $20M | B30: 108.36584 | C30: 30859.002 | D30: 173.68937 | E30: 223.55179 | F30: 5342.3245 | G30: 132.1827 | H30: 51802.711 | I30: 5129.4639 | J30: 922.64173 | K30: 7577.1556 | L30: 16819.261 | M30: 0.11
A31: + uncontracted $22.5M (instead of $20M) | B31: 171.02473 | C31: 49130.832 | D31: 102.43453 | E31: 134.02869 | F31: 5354.0644 | G31: 181.32948 | H31: 51802.711 | I31: 5129.4639 | J31: 922.64173 | K31: 7577.1556 | L31: 15278.917 | M31: 0.11
A32: + Meta backstop 190 MW (all layers) | B32: 159.30451 | C32: 45586.196 | D32: 102.95124 | E32: 132.90501 | F32: 5686.6768 | G32: 170.80456 | H32: 50816.423 | I32: 6026.0894 | J32: 1084.3705 | K32: 6691.4456 | L32: 14311.234 | M32: 0.11
A33: (b) all layers, blended WACC 10.67% (ABS share 5.4% of capex at after-tax SOFR+2.5%) | B33: 173.16122 | C33: 49849.25 | D33: 95.743941 | E33: 123.30074 | F33: 5686.6768 | G33: 182.60451 | H33: 50816.423 | I33: 6026.0894 | J33: 1084.3705 | K33: 6691.4456 | L33: 14311.234 | M33: 0.1066725
A34: (c) all layers, WACC 9% - UPPER BOUND: double counts cheap debt | B34: 265.95422 | C34: 78956.744 | D34: 66.907954 | E34: 84.850026 | F34: 5686.6768 | G34: 261.9086 | H34: 50816.423 | I34: 6026.0894 | J34: 1084.3705 | K34: 6691.4456 | L34: 14311.234 | M34: 0.09
A35: (d) Skeptic full stack: uncontracted $20M, prepay 55%, ABS 50%, Rubin $20M, WACC 9% | B35: 207.67705 | C35: 59560.799 | D35: 93.627018 | E35: 119.64522 | F35: 5361.6847 | G35: 212.32597 | H35: 51802.711 | I35: 5129.4639 | J35: 922.64173 | K35: 7577.1556 | L35: 16724.224 | M35: 0.09
A36: (d) Skeptic full stack: uncontracted $22.5M, prepay 55%, ABS 50%, Rubin $20M, WACC 9% | B36: 283.63632 | C36: 84726.506 | D36: 66.525018 | E36: 85.575408 | F36: 5378.3396 | G36: 276.77789 | H36: 51802.711 | I36: 5129.4639 | J36: 922.64173 | K36: 7577.1556 | L36: 15154.109 | M36: 0.09
A38: STOP BUILDING / CONTRACTED ONLY (same layers; uncontracted price layers have no MW to act on)
A39: Layer / case | B39: Self-consistent PT $ | C39: EV $M | D39: New shares M (headline) | E39: Authority need M (vs ~82) | F39: YE27 liquidity $M | G39: Spot-issuance PT memo $ | H39: New prepayments $M | I39: ABS draws $M | J39: ABS interest $M | K39: Plan converts net $M | L39: ATM + top-ups $M | M39: WACC used
A40: base (v0.8) | B40: 13.888664 | C40: 9765.2328 | D40: 138.33224 | E40: 138.33224 | F40: 3283.2818 | G40: 19.191197 | H40: 0 | I40: 0 | J40: 0 | K40: 0 | L40: 0 | M40: 0.11
A41: + prepay 55% | B41: 13.888664 | C41: 9765.2328 | D41: 138.33224 | E41: 138.33224 | F41: 3283.2818 | G41: 19.191197 | H41: 0 | I41: 0 | J41: 0 | K41: 0 | L41: 0 | M41: 0.11
A42: + ABS 50% on contracted MW | B42: 11.168929 | C42: 9765.2328 | D42: 172.01739 | E42: 172.01739 | F42: 7643.9961 | G42: 16.580054 | H42: 0 | I42: 4707.2117 | J42: 848.6396 | K42: 0 | L42: 0 | M42: 0.11
A43: + uncontracted $20M | B43: 11.168929 | C43: 9765.2328 | D43: 172.01739 | E43: 172.01739 | F43: 7643.9961 | G43: 16.580054 | H43: 0 | I43: 4707.2117 | J43: 848.6396 | K43: 0 | L43: 0 | M43: 0.11
A44: + uncontracted $22.5M (instead of $20M) | B44: 11.168929 | C44: 9765.2328 | D44: 172.01739 | E44: 172.01739 | F44: 7643.9961 | G44: 16.580054 | H44: 0 | I44: 4707.2117 | J44: 848.6396 | K44: 0 | L44: 0 | M44: 0.11
A45: + Meta backstop 190 MW (all layers) | B45: 15.667637 | C45: 9354.589 | D45: 122.62538 | E45: 122.62538 | F45: 2793.1041 | G45: 20.899141 | H45: 0 | I45: 9704.2117 | J45: 1750.9141 | K45: 0 | L45: 0 | M45: 0.11
A46: (b) all layers, blended WACC 8.82% (ABS share 35.3% of capex at after-tax SOFR+2.5%) | B46: 24.261764 | C46: 11749.728 | D46: 79.188389 | E46: 79.188389 | F46: 2793.1041 | G46: 29.150127 | H46: 0 | I46: 9704.2117 | J46: 1750.9141 | K46: 0 | L46: 0 | M46: 0.088199602
A47: (c) all layers, WACC 9% - UPPER BOUND: double counts cheap debt | B47: 23.504972 | C47: 11538.814 | D47: 81.738027 | E47: 81.738027 | F47: 2793.1041 | G47: 28.423551 | H47: 0 | I47: 9704.2117 | J47: 1750.9141 | K47: 0 | L47: 0 | M47: 0.09
A48: (d) Skeptic full stack: uncontracted $20M, prepay 55%, ABS 50%, Rubin $20M, WACC 9% | B48: 16.689823 | C48: 11303.878 | D48: 115.11506 | E48: 115.11506 | F48: 7643.9961 | G48: 21.880513 | H48: 0 | I48: 4707.2117 | J48: 848.6396 | K48: 0 | L48: 0 | M48: 0.09
A49: (d) Skeptic full stack: uncontracted $22.5M, prepay 55%, ABS 50%, Rubin $20M, WACC 9% | B49: 16.689823 | C49: 11303.878 | D49: 115.11506 | E49: 115.11506 | F49: 7643.9961 | G49: 21.880513 | H49: 0 | I49: 4707.2117 | J49: 848.6396 | K49: 0 | L49: 0 | M49: 0.09
A51: Static values from full recalcs (fs_runs.py, 2026-10-05). Layers are cumulative top to bottom; '$22.5M' replaces '$20M'. Toggles: NDPrepayOn/NDPrepayPct, ABS_LTC, UncPxOn/UncPx, BackstopMW, StopBuild, WACC.
A52: Self-consistent basis: issuing at the solved PT is value-neutral, so financing only moves PT through its cost (ABS interest, convert accretion) or through EV (prepayment timing). Cheap debt shows up only via a lower WACC (row b).
A53: (b) blended WACC = ABS share of Q3'26-Q4'30 capex x (SOFR 4.0% + 2.5%) x (1 - 25.8%) + rest x 11%. (c) 9% is an upper bound that double counts the cheap debt; in STOP the blended WACC (8.8%) is already below 9%.
A54: Prepayments: no price concession assumed (FU_PreCost 0); valued as interest-free customer funding at WACC. ABS: new contracted-MW capex only (6/30 fleet not refinanced); displaces the 2027 plan converts first (ABS_CVOff); in STOP it adds idle cash and costs interest.
A55: Uncontracted price: applies to UNSOLD new 2027+ non-contract MW (new non-contract ~271 MW at YE27, ~1.5 GW by 2030, less the RPO-sold share); legacy GPU-hour fleet (147 MW) unchanged; 3-yr renewal re-prices 2027 vintages in 2030; 2028-30 vintages keep the premium into the terminal (renewal after Q4'30 not modelled - overstates).

Sheet Outputs
A1: Outputs - key metrics at valuation-date horizons
A2: Horizon quarter = last quarter end on/before EDATE(ValDate, months). LTM = 4 quarters ending at horizon. Per-share value rolled forward at Ke.
A4: Metric | B4: Valuation qtr | C4: +6 months | D4: +1 year | E4: +3 years
A5: Quarter index | B5: =MATCH(EDATE(ValDate,0),Q_End,1) -> 11 | C5: =MATCH(EDATE(ValDate,6),Q_End,1) -> 13 | D5: =MATCH(EDATE(ValDate,12),Q_End,1) -> 15 | E5: =MATCH(EDATE(ValDate,36),Q_End,1) -> 23
A6: Quarter | B6: =INDEX(Q_Lab,1,B5) -> Q3'26 | C6: =INDEX(Q_Lab,1,C5) -> Q1'27 | D6: =INDEX(Q_Lab,1,D5) -> Q3'27 | E6: =INDEX(Q_Lab,1,E5) -> Q3'29
A7: Months from ValDate | B7: 0 | C7: 6 | D7: 12 | E7: 36
A8: Revenue - quarter ($M) | B8: =INDEX(PL_Rev,1,B$5) -> 674.68641 | C8: =INDEX(PL_Rev,1,C$5) -> 1027.6473 | D8: =INDEX(PL_Rev,1,D$5) -> 2462.2117 | E8: =INDEX(PL_Rev,1,E$5) -> 7804.0448
A9: Revenue - LTM ($M) | B9: =SUMPRODUCT(PL_Rev*(Q_Idx>B$5-4)*(Q_Idx<=B$5)) -> 1883.6864 | C9: =SUMPRODUCT(PL_Rev*(Q_Idx>C$5-4)*(Q_Idx<=C$5)) -> 3093.7268 | D9: =SUMPRODUCT(PL_Rev*(Q_Idx>D$5-4)*(Q_Idx<=D$5)) -> 5932.0826 | E9: =SUMPRODUCT(PL_Rev*(Q_Idx>E$5-4)*(Q_Idx<=E$5)) -> 26947.665
A10: Adj. EBITDA - quarter ($M) | B10: =INDEX(PL_EBITDA,1,B$5) -> 263.55961 | C10: =INDEX(PL_EBITDA,1,C$5) -> 503.88198 | D10: =INDEX(PL_EBITDA,1,D$5) -> 1282.6887 | E10: =INDEX(PL_EBITDA,1,E$5) -> 4879.0268
A11: Adj. EBITDA - LTM ($M) | B11: =SUMPRODUCT(PL_EBITDA*(Q_Idx>B$5-4)*(Q_Idx<=B$5)) -> 644.25961 | C11: =SUMPRODUCT(PL_EBITDA*(Q_Idx>C$5-4)*(Q_Idx<=C$5)) -> 1325.6728 | D11: =SUMPRODUCT(PL_EBITDA*(Q_Idx>D$5-4)*(Q_Idx<=D$5)) -> 2937.9595 | E11: =SUMPRODUCT(PL_EBITDA*(Q_Idx>E$5-4)*(Q_Idx<=E$5)) -> 16566.051
A12: EBIT - LTM ($M) | B12: =SUMPRODUCT(PL_EBIT*(Q_Idx>B$5-4)*(Q_Idx<=B$5)) -> -888.91445 | C12: =SUMPRODUCT(PL_EBIT*(Q_Idx>C$5-4)*(Q_Idx<=C$5)) -> -1120.7018 | D12: =SUMPRODUCT(PL_EBIT*(Q_Idx>D$5-4)*(Q_Idx<=D$5)) -> -1102.3992 | E12: =SUMPRODUCT(PL_EBIT*(Q_Idx>E$5-4)*(Q_Idx<=E$5)) -> 677.9823
A13: Free cash flow - LTM ($M) | B13: =SUMPRODUCT(CF_FCF*(Q_Idx>B$5-4)*(Q_Idx<=B$5)) -> -2187.8369 | C13: =SUMPRODUCT(CF_FCF*(Q_Idx>C$5-4)*(Q_Idx<=C$5)) -> -13212.663 | D13: =SUMPRODUCT(CF_FCF*(Q_Idx>D$5-4)*(Q_Idx<=D$5)) -> -28091.954 | E13: =SUMPRODUCT(CF_FCF*(Q_Idx>E$5-4)*(Q_Idx<=E$5)) -> -20429.323
A14: Net debt ($M, model) | B14: =INDEX(CF_NetDebt,1,B$5) -> 2084.3193 | C14: =INDEX(CF_NetDebt,1,C$5) -> 10440.171 | D14: =INDEX(CF_NetDebt,1,D$5) -> 26450.643 | E14: =INDEX(CF_NetDebt,1,E$5) -> 46977.217
A15: Diluted shares (M, at DilPx) | B15: =INDEX(Sh_Dil,1,B$5) -> 314.92525 | C15: =INDEX(Sh_Dil,1,C$5) -> 1065.3162 | D15: =INDEX(Sh_Dil,1,D$5) -> 1534.8116 | E15: =INDEX(Sh_Dil,1,E$5) -> 10848.154
A16: Active IT MW | B16: =INDEX(MW_Act,1,B$5) -> 182.4897 | C16: =INDEX(MW_Act,1,C$5) -> 301.7195 | D16: =INDEX(MW_Act,1,D$5) -> 629.5368 | E16: =INDEX(MW_Act,1,E$5) -> 1963.8213
A17: Energized IT MW (Capacity) | B17: =INDEX(MW_En,1,B$5) -> 216.9897 | C17: =INDEX(MW_En,1,C$5) -> 453.79225 | D17: =INDEX(MW_En,1,D$5) -> 812.6073 | E17: =INDEX(MW_En,1,E$5) -> 1963.8213
A18: Implied value per share - FD, rolled at Ke ($) | B18: =V_PS*(1+Ke)^(B$7/12) -> 0.01 | C18: =V_PS*(1+Ke)^(C$7/12) -> 0.010630146 | D18: =V_PS*(1+Ke)^(D$7/12) -> 0.0113 | E18: =V_PS*(1+Ke)^(E$7/12) -> 0.01442897
A19: Implied value per share - 308.69M-style basic ($) | B19: =V_PSB*(1+Ke)^(B$7/12) -> -2.0120311 | C19: =V_PSB*(1+Ke)^(C$7/12) -> -2.1388184 | D19: =V_PSB*(1+Ke)^(D$7/12) -> -2.2735952 | E19: =V_PSB*(1+Ke)^(E$7/12) -> -2.9031537
A21: Valuation summary
A22: DCF EV ($M) | B22: =V_EV -> -898.81401
A23: Market EV at SharePx ($M) | B23: =V_MKTEV -> 74654.719
A24: FD value / share at solved price ($) | B24: =V_PS -> 0.01
A25: 12-month PT ($) - SELF-CONSISTENT headline | B25: =V_PT -> 3.970466
A26: MEMO: PT if issuing at spot $242.81 (needs market access at today's price) | B26: =V_PTSpot -> 88.869332
A27: Shares needed vs ~82M authority (M) | B27: =V_AuthNeed -> 13262.174
A28: Upside vs SharePx | B28: =V_UP -> -0.98364785
A29: Share price ($) | B29: =SharePx -> 242.81
A30: Off-B/S weight used | B30: =OffBSWt -> 0
A31: Scenario | B31: =CHOOSE(Scen,"BULL","BASE","BEAR") -> BASE
A32: Model vs consensus (Skeptic, Oct 2 2026) | B32: FY2026 | C32: FY2027 | D32: FY2028
A33: Revenue - model | B33: =SUMIF(Q_Yr,2026,PL_Rev) -> 2465.0795 | C33: =SUMIF(Q_Yr,2027,PL_Rev) -> 8209.2404 | D33: =SUMIF(Q_Yr,2028,PL_Rev) -> 19716.797
A34: Revenue - consensus | B34: =INDEX(Cons_Rev,1,3) -> 3340 | C34: =INDEX(Cons_Rev,1,4) -> 12300 | D34: =INDEX(Cons_Rev,1,5) -> 23000
A35: Revenue - model / consensus - 1 | B35: =IF(N(B34)=0,"n/a",B33/B34-1) -> -0.26195223 | C35: =IF(N(C34)=0,"n/a",C33/C34-1) -> -0.33258208 | D35: =IF(N(D34)=0,"n/a",D33/D34-1) -> -0.14274797
A36: Adj. EBITDA - model | B36: =SUMIF(Q_Yr,2026,PL_EBITDA) -> 951.29083 | C36: =SUMIF(Q_Yr,2027,PL_EBITDA) -> 4213.144 | D36: =SUMIF(Q_Yr,2028,PL_EBITDA) -> 11402.704
A37: Adj. EBITDA - consensus | B37: =INDEX(Cons_EB,1,3) -> 1390 | C37: =INDEX(Cons_EB,1,4) -> 6730 | D37: =INDEX(Cons_EB,1,5) -> 13980
A38: Adj. EBITDA - model / consensus - 1 | B38: =IF(N(B37)=0,"n/a",B36/B37-1) -> -0.31561811 | C38: =IF(N(C37)=0,"n/a",C36/C37-1) -> -0.37397563 | D38: =IF(N(D37)=0,"n/a",D36/D37-1) -> -0.18435594
A39: Capex - model | B39: =SUMIF(Q_Yr,2026,Capex) -> 17617.717 | C39: =SUMIF(Q_Yr,2027,Capex) -> 33779.447 | D39: =SUMIF(Q_Yr,2028,Capex) -> 26949.043
A40: Capex - consensus | B40: =INDEX(Cons_Cx,1,3) -> 0 | C40: =INDEX(Cons_Cx,1,4) -> 29100 | D40: =INDEX(Cons_Cx,1,5) -> 0
A41: Capex - model / consensus - 1 | B41: =IF(N(B40)=0,"n/a",B39/B40-1) -> n/a | C41: =IF(N(C40)=0,"n/a",C39/C40-1) -> 0.16080574 | D41: =IF(N(D40)=0,"n/a",D39/D40-1) -> n/a
A43: MW sources at YE26 / YE27 (IT MW) | B43: Q4'26 | C43: Q4'27
A44: Energized - Capacity, IT-normalized (YE27 ~950 IT = PLACEHOLDER pending Capacity's Tue basis column; named 185/305/424 & 764/1,069/1,374 mixed basis + unseen) | B44: =INDEX(MW_En,1,12) -> 301.7195 | C44: =INDEX(MW_En,1,16) -> 1081.9108
A45: Mgmt connected guide (800MW-1GW YE26; 1.8 GW YE27) | B45: =INDEX(MW_Gd,1,12) -> 900 | C45: =INDEX(MW_Gd,1,16) -> 1800
A46: Contracted | B46: =INDEX(MW_Contr,1,12) -> 4000 | C46: =INDEX(MW_Contr,1,16) -> 4000
A47: Active MW driving revenue | B47: =INDEX(MW_Act,1,12) -> 216.9897 | C47: =INDEX(MW_Act,1,16) -> 812.6073
A50: Comparison vs Skeptic v2 (model columns for low/high/stress are STATIC snapshots written by snap.py)
B51: Model | C51: Skeptic v2 | D51: Model / Sk - 1
A52: FY27 revenue - low (model: bear) | B52: 4287.2002 | C52: =Sk_Rev27Lo -> 7000 | D52: =IFERROR(B52/C52-1,"") -> -0.38754282
A53: FY27 revenue - base (1-qtr lag) | B53: =SUMIF(Q_Yr,2027,PL_Rev) -> 8209.2404 | C53: =Sk_Rev27Base -> 9900 | D53: =IFERROR(B53/C53-1,"") -> -0.1707838
A54: FY27 revenue - high (model: bull) | B54: 13514.65 | C54: =Sk_Rev27Hi -> 12900 | D54: =IFERROR(B54/C54-1,"") -> 0.047647282
A55: FY27 revenue - STRESS (2-qtr energized lag) | B55: 6911.0703 | C55: =Sk_Rev27St -> 7600 | D55: =IFERROR(B55/C55-1,"") -> -0.09064864
A56: FY28 revenue - base | B56: =SUMIF(Q_Yr,2028,PL_Rev) -> 19716.797 | C56: =Sk_Rev28 -> 25300 | D56: =IFERROR(B56/C56-1,"") -> -0.22067998
A57: Market EV / FY27 adj. EBITDA - Nebius | B57: =V_EVEB27 -> 17.71948 | C57: =Sk_EVEB27 -> 11.1 | D57: =IFERROR(B57/C57-1,"") -> 0.59634951
A58: EV / FY27 EBITDA - CoreWeave (Skeptic) | B58: =CRWV_EVEB27 -> 4.8 | C58: =CRWV_EVEB27 -> 4.8 | D58: =IFERROR(B58/C58-1,"") -> 0
A60: Funding runway (CashFlow tab)
A61: Starting liquidity ($M) | B61: =Liq_Start -> 13792.1
A62: First quarter liquidity < 0 (Skeptic rerun: Q2'27) | B62: =Liq_NegQ -> none to Q4'30
A63: Liquidity Q1'27 / Q2'27 / YE27 ($B) | B63: =INDEX(Liq,1,13)/1000 -> 9.8809261 | C63: =INDEX(Liq,1,14)/1000 -> 2.4237444 | D63: =INDEX(Liq,1,16)/1000 -> 1
A65: Funding runway: capex toggle side by side (STATIC, snap.py)
B66: Path-consistent (CapexMode 2, method 3) | C66: Consensus (CapexMode 1)
A67: First quarter liquidity < 0 | B67: none to Q4'30 | C67: none to Q4'30
A68: YE27 liquidity ($M) | B68: 1000 | C68: 1000
A69: FY27 capex ($M) | B69: 33779.447 | C69: 29100
A71: Price-cycle leg alone (Blackwell cut after Rubin; 50% reserved renewal in FY27; base MW path) vs base, STATIC ($M)
B72: FY27 revenue | C72: FY27 adj. EBITDA | D72: FY28 revenue | E72: FY28 adj. EBITDA | F72: Skeptic 03 v3.4 FY27 rev | G72: Skeptic 03 v3.4 FY28 rev
A73: Price-cycle leg, BULL cut 6.25% (base MW path, 50% renewal FY27) | B73: 224.55172 | C73: 159.43172 | D73: 132.83896 | E73: 100.95761 | F73: -77 | G73: -370
A74: Price-cycle leg, BASE cut 22% (base MW path, 50% renewal FY27) | B74: 0 | C74: 0 | D74: 0 | E74: 0 | F74: -271 | G74: -1290
A75: Price-cycle leg, BEAR cut 31% (base MW path, 50% renewal FY27) | B75: -128.31527 | C75: -91.103843 | D75: -75.907976 | E75: -57.690062 | F75: -383 | G75: -1810
A78: Comparison vs Skeptic v3.2 (skeptic_03_depreciation.xlsx). NOTE: Skeptic's path run uses CONSENSUS EBITDA; ours is bottom-up. Model values STATIC from snap.py
B79: Model zero qtr | C79: Skeptic zero qtr | D79: Model YE27 ($B) | E79: Skeptic YE27 ($B) | F79: Model YE28 ($B) | G79: Skeptic YE28 ($B)
A80: Path-tied capex - base | B80: none to Q4'30 | C80: =Sk3_ZeroQ -> Q4'27 | D80: 1 | E80: =Sk3_YE27 -> -0.15 | F80: 1 | G80: =Sk3_YE28 -> -6.8
A81: Low (model: bear scenario) | B81: none to Q4'30 | C81: =Sk3L_ZeroQ -> never thru 2030 | D81: 1 | E81: =Sk3L_YE27 -> 7.1 | F81: 1 | G81: =Sk3L_YE28 -> 1.5
A82: High (model: bull scenario) | B82: none to Q4'30 | C82: =Sk3H_ZeroQ -> Q3'27 | D82: 1 | E82: =Sk3H_YE27 -> -7.4 | F82: 1 | G82: =Sk3H_YE28 -> -15.6
A83: Consensus capex | B83: none to Q4'30 | C83: =Sk3C_ZeroQ -> Q2'27 | D83: 1 | E83: =Sk3C_YE27 -> -9.9 | F83: 1
A85: DCF EV at GPU life ($B): model vs Skeptic v3.2 (market EV ~$74.7B)
B86: 4 yrs | C86: 5 yrs | D86: 6 yrs
A87: Model DCF EV | B87: -12.667059 | C87: -0.89881401 | D87: 10.53397
A88: Skeptic v3.2 DCF EV | B88: =Sk3_DCF4 -> negative | C88: =Sk3_DCF5 -> 2.3 | D88: =Sk3_DCF6 -> 16.3
A89: Market EV | B89: =V_MKTEV/1000 -> 74.654719
A91: v0.3 -> v0.4 by scenario (full bridge on Bridge tab), STATIC
B92: DCF EV $M | C92: FD equity $M | D92: FD $/share | E92: 12m PT | F92: Q2'26 util | G92: FY27 rev | H92: FY27 EBITDA
A93: BRIDGE + GPU capex lead 3 qtrs (= v0.3) | B93: 94115.788 | C93: 91652.936 | D93: 248.1935 | E93: 280.45865 | F93: 0.95395587 | G93: 8517.5153 | H93: 4713.075
A94: Base (live) | B94: -898.81401 | C94: -621.09621 | D94: 0.01 | E94: 3.970466 | F94: 0.75031956 | G94: 8209.2404 | H94: 4213.144
A95: BULL - v0.3 settings | B95: 363040.05 | C95: 366980.75 | D95: 943.04424 | E95: 1056.2095 | F95: 0.95395587 | G95: 14376.39 | H95: 8852.2672
A96: Bull | B96: 125480.86 | C96: 137784.26 | D96: 355.02686 | E96: 401.01436 | F96: 0.75031956 | G96: 13514.65 | H96: 7841.1009
A97: BEAR - v0.3 settings | B97: -21541.186 | C97: -33504.358 | D97: 0.01 | E97: 0.0115 | F97: 0.95395587 | G97: 3424.4744 | H97: 1375.1706
A98: Bear | B98: -34363.024 | C98: -34087.87 | D98: 0.01 | E98: 0 | F98: 0.75031956 | G98: 4287.2002 | H98: 1840.9429
A99: MEMO: include-both terminal (TermBase=1) | B99: -6992.1634 | C99: -6714.4456 | D99: 0.01 | E99: 0 | F99: 0.75031956 | G99: 8209.2404 | H99: 4213.144
A100: Base w/ mgmt connected guide MW (MWSel=3) | B100: 23077.318 | C100: 11564.276 | D100: 36.720702 | E100: 71.901478 | F100: 0.75031956 | G100: 19284.088 | H100: 10382.05

Sheet Checks
A1: Checks
A3: Check | B3: Model | C3: Target / tolerance | D3: Status | E3: Note
A4: CRITICAL: convert counted in BOTH shares and debt (solved price, chosen weight) | B4: =IF(DilMethod=1,SUMPRODUCT((((CVDebtBasis=1)*Valuation!$E$80:$E$91+(CVDebtBasis>=2)*Valuation!$F$80:$F$91))),IF(DilMethod=2,SUMPRODUCT((V_PSolve>Valuation!$H$80:$H$91)*(((CVDebtBasis=1)*Valuation!$E$80:$E$91+(CVDebtBasis>=2)*Valuation!$F$80:$F$91))),0))+V_CVDEBT-SUMPRODUCT((((CVDebtBasis=1)*Valuation!$E$80:$E$91+(CVDebtBasis>=2)*Valuation!$F$80:$F$91))) -> 0 | C4: 0 | D4: =IF(ABS(B4)<0.5,"OK","DOUBLE COUNT") -> OK | E4: If-converted + debt-counted must equal total (CVDebtBasis: 1 original principal, 2 accreted); net-share (3) keeps principal as debt by design
A5: CRITICAL: same at SharePx (market EV) | B5: =IF(DilMethod=1,SUMPRODUCT((((CVDebtBasis=1)*Valuation!$E$80:$E$91+(CVDebtBasis>=2)*Valuation!$F$80:$F$91))),IF(DilMethod=2,SUMPRODUCT((SharePx>Valuation!$H$80:$H$91)*(((CVDebtBasis=1)*Valuation!$E$80:$E$91+(CVDebtBasis>=2)*Valuation!$F$80:$F$91))),0))+V_CVDmkt-SUMPRODUCT((((CVDebtBasis=1)*Valuation!$E$80:$E$91+(CVDebtBasis>=2)*Valuation!$F$80:$F$91))) -> 0 | C5: 0 | D5: =IF(ABS(B5)<0.5,"OK","DOUBLE COUNT") -> OK
A6: Economic basic shares at Q3'26 (M) = 271.86 + 15.77 + 21.07 | B6: =INDEX(Sh_EconBasic,1,11) -> 308.69115 | C6: 308.69 | D6: =IF(ABS(B6-C6)<0.05,"OK","CHECK") -> OK
A7: Fully diluted at $242.81 EXCL. unsold ATM vs Filings CapStructure | B7: =V_FDmkt -> 369.22679 | C7: =FD_Filings -> 369.2 | D7: =IF(ABS(B7-C7)<2,"OK","CHECK") -> OK | E7: nebius_filings.xlsx CapStructure
A8: Fully diluted at $242.81 INCL. 12.27M ATM vs Filings | B8: =V_FDmkt+ATM_Rem -> 381.4973 | C8: =FD_FilingsATM -> 381.5 | D8: =IF(ABS(B8-C8)<2,"OK","CHECK") -> OK | E8: ATM is a funding source, not in today's count
A9: ITM convert shares at $242.81 (six ITM) | B9: =V_ITMsh -> 50.021939 | C9: =ITM_Sh_Chk -> 50.03 | D9: =IF(ABS(B9-C9)<0.5,"OK","CHECK") -> OK | E9: Steps at $324.65 / $313.46 / $183.22 / $180.31 / $138.75 / $51.45
A10: ITM convert principal at $242.81 ($M orig.) | B10: =V_ITMprin -> 7675 | C10: =ITM_Prin_Chk -> 7680 | D10: =IF(ABS(B10-C10)<15,"OK","CHECK") -> OK
A11: Market EV at $242.81 ($M), CapStructure basis vs Filings ~74.7B | B11: =V_MKTEV -> 74654.719 | C11: 74700 | D11: =IF(ABS(B11/C11-1)<0.01,"OK","CHECK") -> OK | E11: 6/30 balance + Aug notes + exchange; unrestricted cash only
A12: Dilution solve convergence |P15-P14| | B12: =V_CONV -> 0 | C12: 0.01 | D12: =IF(B12<C12,"OK","NOT CONVERGED") -> OK
A13: Microsoft implied TCV vs reported ($M) | B13: =MSFT_Chk -> 0 | C13: 0 | D13: =IF(ABS(B13)<5,"OK","CHECK") -> OK
A14: Quarters (pre-Bloom) Microsoft revenue exceeds ~$350M/qtr genset ceiling | B14: =SUMPRODUCT((MS_CeilChk>0)*(Q_Idx<IF(BloomOn=1,BloomIdx,99))) -> 0 | C14: 0 | D14: =IF(B14=0,"OK","CHECK") -> OK
A15: Q4 bridge: unseen MW vs Skeptic/Capacity 83-200 MW | B15: =BR_MW25 -> 92.646129 | C15: =UnseenChkHi -> 200 | D15: =BR_Chk -> OK - overlaps 83-200 MW
A16: History capex split = reported (sum abs diff) | B16: =SUMPRODUCT(ABS(N(+CapexChk))) -> 0 | C16: 0 | D16: =IF(B16<1,"OK","CHECK") -> OK
A17: Q2'26 book (a) share vs GPU Market 45% (40-46%) | B17: =INDEX(Book_A,1,10)/INDEX(AI_Model,1,10) -> 0.46063494 | C17: =MixA_Q2 -> 0.45 | D17: =IF(AND(ROUND(B17,2)>=0.4,ROUND(B17,2)<=0.46),"OK","CALIBRATE") -> OK
A18: Q2'26 book (b) share vs ~50% (44-57%) | B18: =INDEX(Book_B,1,10)/INDEX(AI_Model,1,10) -> 0.46991652 | C18: =MixB_Q2 -> 0.5 | D18: =IF(AND(B18>=0.44,B18<=0.57),"OK","CALIBRATE") -> OK
A19: Q2'26 book (c) share vs ~4% (1.3-9%) | B19: =INDEX(Book_C,1,10)/INDEX(AI_Model,1,10) -> 0.06944854 | C19: =MixC_Q2 -> 0.04 | D19: =IF(AND(B19>=0.013,B19<=0.09),"OK","CALIBRATE") -> OK
A20: Depreciation-yield flags (drop after chip availability) | B20: =SUM(DepYldFlag) -> 1 | C20: 0 | D20: =IF(B20=0,"OK","FLAG - review PIS dates") -> FLAG - review PIS dates | E20: Material weakness over depreciation start dates
A21: Q3'26 transfer into service | B21: =Q3TransChk -> PENDING (model 4,702) | D21: =B21 -> PENDING (model 4,702)
A22: Sites: named-site energized imports tie to Capacity file COMPANY row (sum abs diff) | B22: =SUMPRODUCT(ABS(CapTie)) -> 0 | C22: 0 | D22: =IF(B22<1,"OK","CHECK") -> OK
A23: Q2'26 tie: model AI cloud revenue vs actual $574.9M | B23: =INDEX(AI_Model,1,10) -> 574.9 | C23: =INDEX(H_AIRev,1,10) -> 574.9 | D23: =IF(ABS(B23/C23-1)<0.01,"OK","CHECK") -> OK | E23: Utilization calibrated
A24: Implied Q2'26 utilization (books b+c) | B24: =UtilQ2 -> 0.75031956 | C24: 40-100% | D24: =UtilFlag -> OK (40-100%) | E24: Flag (not forced) if outside 40-100%
A25: (a) Q2'26 revenue per GPU-hour of capacity (annualized AI rev / GPUs / 8,760) | B25: =INDEX(AI_Model,1,10)*4*1000000/INDEX(GPU_End,1,10)/8760 -> 2.8618773 | C25: =Chk_RevGPUhr -> 3.27 | D25: =IF(ABS(B25/C25-1)<=0.1,"OK","CHECK") -> CHECK | E25: +/-10% (GPU Market, Derived)
A26: (b) Q2'26 annualized AI rev per $ avg gross servers in service | B26: =INDEX(AI_Model,1,10)*4/AVERAGE(INDEX(H_SRV,1,9),INDEX(H_SRV,1,10)) -> 0.46501658 | C26: =Chk_RevSrv -> 0.46 | D26: =IF(ABS(B26/C26-1)<=0.1,"OK","CHECK") -> OK | E26: Filings, Derived
A27: (b3) Capacity server ceiling: Q2'26 GPUs x $45-60k (high end) vs $5.2B servers in service | B27: =INDEX(GPU_End,1,10)*Chk_SrvHi/1000000 -> 5503.62 | C27: =Chk_SrvCap -> 5197.7 | D27: =IF(B27<=C27,"OK: "&TEXT(INDEX(GPU_End,1,10)*Chk_SrvLo/1000000,"#,##0")&"-"&TEXT(B27,"#,##0")&" <= 5,198; implied $"&TEXT(C27*1000000/INDEX(GPU_End,1,10),"#,##0")&"/GPU","FLAG") -> FLAG | E27: Capacity, Estimated
A28: (b2) Modeled in-service GPU cost at 6/30 (GPUs x $/GPU) vs $5.2B servers | B28: =(INDEX(GPU_End_H,1,10)*GPUCost_H+INDEX(GPU_End_B,1,10)*GPUCost_B+INDEX(GPU_End_N,1,10)*GPUCost_N)/1000000 -> 4753.62 | C28: =Chk_SrvCap -> 5197.7 | D28: =IF(B28<=C28,"OK","FLAG: exceeds servers in service") -> OK
A29: (c) Q2'26 revenue per energized MW ($M/yr) | B29: =INDEX(AI_Model,1,10)*4/INDEX(MW_En,1,10) -> 12.601259 | C29: =Chk_RevEnMW -> 13 | D29: =IF(ABS(B29/C29-1)<=0.15,"OK","CHECK") -> OK | E29: ~$13M (2.30B / ~173 MW)
A30: Q2'26 contract (book a) IT MW as share of energized MW | B30: =INDEX(A_MW,1,10)/INDEX(MW_En,1,10) -> 0.55534641 | C30: info | D30: ="INFO" -> INFO | E30: Microsoft GPU use capped at Vineland energized IT MW (39 MW Q2'26) + Meta #1 48 MW (TCV/ACV-derived) vs 173 MW energized; v0.1 fix took Q2'26 utilization from 133% to ~92%
A31: Q2'26 energized MW (Capacity base, IT) | B31: =INDEX(MW_En,1,10) -> 182.4897 | C31: 173 | D31: =IF(ABS(B31-C31)<3,"OK","CHECK") -> CHECK
A32: Q2'26 GPUs: model (Capacity 'GPUs deployed' ~80,416 + GPU anchor gap if GPUAnchorOn) | B32: =INDEX(GPU_End,1,10) -> 91727 | C32: =80416+GPUAnchorD -> 82990 | D32: =IF(ABS(B32/C32-1)<0.01,IF(GPUAnchorOn=1,"INFO: anchored to ~30k at 3/31/25 (+"&TEXT(GPUAnchorD,"#,##0")&" vs Capacity file); Q2 utilization "&TEXT(UtilQ2,"0.0%"),"OK"),"CHECK") -> CHECK
A33: Unexplained ARR residual at 6/30 (June run-rate basis; NOT unseen capacity) | B33: =ARR_Res -> 543.05136 | C33: =ARR_ResTeamLo&"-"&ARR_ResTeamHi -> 650-700 | D33: ="INFO: model "&TEXT(ARR_Res,"#,##0")&" = "&TEXT(ARR_ResMW_TLo,"0")&"-"&TEXT(ARR_ResMW_THi,"0")&" MW-eq at team $13.3-13.5M/MW (model June RR "&TEXT(ARR_RR,"#,##0")&" = $"&TEXT(ARR_RRMW,"0.0")&"M/MW); team-basis residual "&TEXT(ARR_ResTB_Lo,"#,##0")&"-"&TEXT(ARR_ResTB_Hi,"#,##0") -> INFO: model 543 = 40-41 MW-eq at team $13.3-13.5M/MW (model June RR 2,457 = $13.5M/MW); team-basis residual 536-573 | E33: Pending Filings on ARR scope / signed-not-billing
A34: Adj. EBITDA margin FY28 - model vs consensus (flag if > +5pp) | B34: =SUMIF(Q_Yr,2028,PL_EBITDA)/SUMIF(Q_Yr,2028,PL_Rev) -> 0.57832437 | C34: =MarginCons28 -> 0.60782609 | D34: =IF(B34-C34>0.05,"FLAG: model margin > consensus +5pp","OK") -> OK | E34: Skeptic consensus 13.98/23.0
A35: Adj. EBITDA margin FY30 - model vs peer ~62% (flag if > +8pp) | B35: =SUMIF(Q_Yr,2030,PL_EBITDA)/SUMIF(Q_Yr,2030,PL_Rev) -> 0.65440592 | C35: =MarginPeer -> 0.62 | D35: =IF(B35-C35>0.08,"FLAG: above peer +8pp - review opex/MW and revenue/MW","OK") -> OK | E35: CoreWeave ~62% placeholder
A36: FY30 margin sensitivity: PD + SG&A held at FY28 % of revenue (vs placeholder step-down) | B36: =SUMIF(Q_Yr,2030,PL_EBITDA)/SUMIF(Q_Yr,2030,PL_Rev)-(1-OpexHold)*((INDEX(PDpct,1,2028-FYBase)+INDEX(SGApct,1,2028-FYBase))-(INDEX(PDpct,1,2030-FYBase)+INDEX(SGApct,1,2030-FYBase))) -> 0.60440592 | C36: =MarginPeer -> 0.62 | D36: =IF(B36-C36>0.08,"FLAG: still above peer +8pp","INFO: within +8pp of peer") -> INFO: within +8pp of peer | E36: PD 8% + SG&A 10% (FY28) instead of 6% + 7% (FY30); toggle OpexHold=1 for full model effect (Sensitivity)
A37: FY30 opex per avg IT MW ($M/MW-yr: COR + PD + SG&A ex-SBC) | B37: =(SUMIF(Q_Yr,2030,PL_Rev)-SUMIF(Q_Yr,2030,PL_EBITDA))/(SUMIF(Q_Yr,2030,MW_Avg)/4) -> 6.0190465 | C37: info | D37: ="INFO: revenue/MW "&TEXT(SUMIF(Q_Yr,2030,PL_Rev)/(SUMIF(Q_Yr,2030,MW_Avg)/4),"0.0") -> INFO: revenue/MW 17.4
A38: FY26 capex vs company guide $20-25B (Aug 12 2026 call) | B38: =SUMIF(Q_Yr,2026,Capex) -> 17617.717 | C38: 20,000-25,000 | D38: =IF(AND(B38>=20000*0.9,B38<=25000*1.1),"OK (within guide +/-10%)","FLAG: outside guide") -> FLAG: outside guide | E38: Fact base: FY2026 capex guidance $20-25B (call transcript, CFO); GPULead calibration
A39: Bull DCF EV vs 3x base (STATIC, snap.py) | B39: =V_EVBullS -> 125480.86 | C39: =3*V_EVBaseS -> -2696.442 | D39: =IF(V_EVBaseS=0,"run snap.py",IF(B39>C39,"FLAG: bull EV > 3x base - review bull drivers","OK")) -> FLAG: bull EV > 3x base - review bull drivers | E39: Bull/base EVs from snapshot
A40: Q2'26 calibration scenario-invariant: utilization bull / bear minus base (STATIC) | B40: =MAX(ABS(V_UtBullS-V_UtBaseS),ABS(V_UtBearS-V_UtBaseS)) -> 0 | C40: 0 | D40: =IF(V_UtBaseS=0,"run snap.py",IF(B40<0.0005,"OK: all scenarios tie $574.9M at "&TEXT(V_UtBaseS,"0.0%"),"FLAG: history depends on scenario")) -> OK: all scenarios tie $574.9M at 75.0%
A41: Implied blended realization vs OD list, Q2'26 books (b)+(c) (billed GPU-hours at Q2 avg list) vs GPU Market 0.72-0.80 | B41: =(INDEX(Book_B,1,LastHist)+INDEX(Book_C,1,LastHist))*1000000/((INDEX(NCA_H,1,LastHist)*ODq_H+INDEX(NCA_B,1,LastHist)*ODq_B+INDEX(NCA_N,1,LastHist)*ODq_N)*INDEX(Q_Hrs,1,LastHist)*UtilQ2) -> 0.74376734 | C41: 0.72-0.80 | D41: =IF(AND(B41>=0.72,B41<=0.8),"OK: within GPU Market range",IF(B41<0.72,"INFO: below range","FLAG: above range")) -> OK: within GPU Market range | E41: Reserved RealRes_B 0.72 x ResSh + on-demand/spot mix
A42: New-deal pricing: model new-MW gross revenue per IT MW-yr (NewDealOn: blended multi-year + short-term at Q1'27 vintage; off: GB300 at Oct-1 list x RealRes x Util_Res) vs IREN >$20M (3-yr GB300-class ~$4.65/GPU-hr) | B42: =IF(NewDealOn=1,RM_ND,RM_GB300) -> 16.69175 | C42: 20 | D42: =IF(B42>C42*1.25,"FLAG: model new-MW pricing >1.25x IREN benchmark",IF(B42<C42*0.8,"INFO: below benchmark","OK: multi-year "&TEXT(RM_MY,"0.0")&"; blended net leased "&TEXT(RM_ND_L,"0.0")&" vs 17.8; GPU-hour GB300 engine "&TEXT(RM_GB300,"0.0")&" (legacy only)")) -> OK: multi-year 16.0; blended net leased 14.5 vs 17.8; GPU-hour GB300 engine 27.4 (legacy only) | E42: Short-term tranche (STShare) at $40-50M included in blend; IREN excludes short-term
A43: Vineland shutdown: probability-weighted Q4'26 Microsoft revenue at risk at VinRevMW vs Capacity ~$67M | B43: =VinExpQ4 -> 68.035291 | C43: 67 | D43: =IF(ABS(B43-C43)<=3,"OK: ties ~$67M (Capacity, Derived); VinShutSel="&VinShutSel,"FLAG: differs from Capacity tie-out") -> OK: ties ~$67M (Capacity, Derived); VinShutSel=0 | E43: vineland_shutdown.xlsx weights; $14.5M/IT MW-yr
A44: Backlog floor: model AI cloud revenue Jul'26-Jun'28 minus RPO recognised in window (~$13.5B) = implied revenue from deals signed after Q2'26 | B44: =SUMPRODUCT((Q_Idx>LastHist)*(Q_Idx<=LastHist+8)*AI_Model)-RPO_Tot*RPO24Pct -> 4893.7958 | C44: =RPO_Tot*RPO24Pct -> 13496.4 | D44: =IF(B44<0,"FLAG: model below contracted backlog","INFO: "&TEXT(B44/(B44+C44),"0%")&" of window revenue unsold at 6/30 (~"&TEXT(B44/(B44+C44)*SUMPRODUCT((Q_Idx>LastHist)*(Q_Idx<=LastHist+8)*MW_Avg)/8,"0")&" of avg "&TEXT(SUMPRODUCT((Q_Idx>LastHist)*(Q_Idx<=LastHist+8)*MW_Avg)/8,"0")&" active MW, revenue-weighted); sold share of new 2027+ MW "&TEXT(RPO_Sold,"0%")) -> INFO: 27% of window revenue unsold at 6/30 (~145 of avg 545 active MW, revenue-weighted); sold share of new 2027+ MW 41% | E44: Q2'26 Note 2: RPO $37.49B, 36% Jul'26-Jun'28
A45: Backlog cash floor Jul'26-Jun'28 = RPO in window - 6/30 DR recognised within 24 months (DR_24 base $2.25B; range $2.0-2.5B) | B45: =RPO_Tot*RPO24Pct-DR_24 -> 11246.4 | C45: 11,000-11,500 | D45: ="INFO: range "&TEXT(RPO_Tot*RPO24Pct-2500,"#,##0")&"-"&TEXT(RPO_Tot*RPO24Pct-2000,"#,##0")&"; model cash revenue in window (AI rev - DR release) "&TEXT(SUMPRODUCT((Q_Idx>LastHist)*(Q_Idx<=LastHist+8)*(AI_Model-CF_DRRel)),"#,##0") -> INFO: range 10,996-11,496; model cash revenue in window (AI rev - DR release) 14,565 | E45: DR 6/30: current $979.4M, non-current $4,995.8M (Reported)
A46: Payback (months) vs mgmt 1y10m (22), prepayments excluded: GB300 leased IT / gross; Rubin leased base / bear (no toggle) | B46: =PB_GB_IT -> 40.056522 | C46: =PB_Target -> 22 | D46: ="INFO: GB300 "&TEXT(PB_GB_IT,"0")&" / "&TEXT(PB_GB_Gr,"0")&" mo (IT / gross); Rubin base "&TEXT(PB_RU_IT,"0")&" / bear "&TEXT(PB_RU_Gr,"0")&" mo; IRR GB300 IT "&TEXT(PB_GB_IRR,"0%")&", Rubin base "&TEXT(PB_RU_IRR,"0%")&"; IT fits 22 only at ~$32M capex, or if prepayments counted (implied rev "&TEXT(PB_ImplRevPre,"0.0")&")" -> INFO: GB300 40 / 31 mo (IT / gross); Rubin base 43 / bear 60 mo; IRR GB300 IT 18%, Rubin base 16%; IT fits 22 only at ~$32M capex, or if prepayments counted (implied rev 16.8) | E46: Payback_Floor tab C; basis not disclosed by management
A47: EBITDA per IT MW-yr by generation (IT reading): GB300 vs Rubin at RubinMW (direct); opex fixed | B47: =PB_EBGB -> 11.5 | C47: =PB_EBRubin -> 11.7 | D47: ="INFO: GB300 "&TEXT(PB_EBGB,"0.0")&" -> Rubin "&TEXT(PB_EBRubin,"0.0")&" ("&TEXT(PB_EBRubin/PB_EBGB-1,"0%")&"); Rubin leased capex "&TEXT(CPM_Lease_VR,"0.0")&" (low-medium confidence)" -> INFO: GB300 11.5 -> Rubin 11.7 (2%); Rubin leased capex 40.1 (low-medium confidence) | E47: v0.7: Rubin capex flat to GB300 in base
A48: Asset floor: DCF EV vs PV(RPO margin) - capex for contracted MW | B48: =V_EV -> -898.81401 | C48: =PF_EV -> 5631.6262 | D48: =IF(B48<C48,"FLAG: DCF EV below asset floor","OK: DCF EV above floor")&"; SHARED-bridge floor $/sh "&TEXT(PF_PSHead,"0.00")&" vs DCF "&TEXT(V_PSHead,"0.00")&IF(AND(BridgeFix=1,V_EV>=PF_EV,PF_PSHead>V_PSHead+0.01)," FLAG: floor/sh above DCF/sh with EV above floor","")&IF(ABS(PF_RepChk)>0.01," FLAG: DCF replica mismatch","")&"; legacy equity floor $/sh "&TEXT(PF_PS1,"0.0")&" cons / "&TEXT(PF_PS2,"0.0")&" mark / "&TEXT(PF_PS3,"0.0")&" high" -> FLAG: DCF EV below asset floor; SHARED-bridge floor $/sh 24.25 vs DCF 3.51; legacy equity floor $/sh 16.8 cons / 25.4 mark / 39.6 high | E48: Payback_Floor tab D
A49: Revenue double-count: prepayments in revenue? (new-deal $20-25M/MW is revenue-recognition basis excl. prepayment, Q2 deck fn 2) | B49: =0 -> 0 | C49: 0 | D49: ="OK: prepayments are cash timing only (CashFlow: Prepayments received / DR release); revenue engine = MW x $/MW and GPU-hours, no reference to prepayments or DR" -> OK: prepayments are cash timing only (CashFlow: Prepayments received / DR release); revenue engine = MW x $/MW and GPU-hours, no reference to prepayments or DR | E49: Formula audit v0.5
A50: Cash double-count: DR release reduces later cash (CFO = EBITDA + prepayments - release); closing Q4'30 DR run-off deducted from EV ($M) | B50: =V_DRAdj -> -5508.7224 | C50: =-V_DR30 -> -9626.6492 | D50: ="INFO: within-horizon release "&TEXT(SUM(CF_DRRel),"#,##0")&" deducted from cash; post-horizon run-off PV "&TEXT(-V_DRAdj,"#,##0")&" deducted (DRTermOn="&DRTermOn&"); closing DR "&TEXT(V_DR30,"#,##0") -> INFO: within-horizon release 16,428 deducted from cash; post-horizon run-off PV 5,509 deducted (DRTermOn=1); closing DR 9,627 | E50: v0.5 fix: before, terminal UFCF counted the unreleased prepaid balance as cash again
A51: Prepayments: total new prepayments FY26H2-FY30 / new-build capex (signed Microsoft/Meta 0%, new hyperscaler HSPre, other 38.5% -> 22.5%) | B51: =SUM(CF_Prepay)/SUMPRODUCT((Q_Idx>LastHist)*CapNew) -> 0.19225295 | C51: info | D51: ="INFO: HSPre "&TEXT(HSPre,"0%")&"; other 2028+ "&TEXT(PrepayPct28,"0.0%")&"; decay "&PrepayDecayOn -> INFO: HSPre 30%; other 2028+ 22.5%; decay 1
A52: Significant financing component (ASC 606): SFC revenue gross-up in model revenue/EBITDA used for DCF | B52: =0 -> 0 | C52: 0 | D52: ="OK: none (no SFC gross-up, no SFC interest; DCF on cash flows). Implied advance financing cost <= "&TEXT(V_SFCRate,"0.0%")&"/yr (Estimated upper bound)" -> OK: none (no SFC gross-up, no SFC interest; DCF on cash flows). Implied advance financing cost <= 3.7%/yr (Estimated upper bound) | E52: Reported history may embed a small SFC gross-up (not disclosed separately)
A53: GPU history anchor: model GPUs at 3/31/2025 vs ~30,000 actual (20-F) | B53: =INDEX(GPU_End,1,5) -> 30000 | C53: =GPU_Q125 -> 30000 | D53: =IF(ABS(B53-C53)<500,"OK: anchored (gap "&TEXT(GPUAnchorD,"#,##0")&" GPUs vs Capacity file)","FLAG: Capacity file "&TEXT(B53,"#,##0")&" vs ~30,000 actual (GPUAnchorOn=0)") -> OK: anchored (gap 2,574 GPUs vs Capacity file) | E53: Single GPU calibration point; Kansas City likely live Q1'25 at 5-15 MW
A54: Rubin pricing (v0.7c): implied per-GPU-hr multiple to GB300 (derived from RubinMW) vs capex multiple | B54: =PX_Ratio -> 1.5535547 | C54: =PX_CapRatio -> 1.0900442 | D54: =PX_Flag&"; $/MW price multiple "&TEXT(PX_MWRatio,"0.00")&"x vs capex multiple "&TEXT(PX_CapRatio,"0.00")&"x" -> OK: Rubin price/capex 0.93x GB300; $/MW price multiple 1.01x vs capex multiple 1.09x | E54: Rubin_Prem is now an output (no 1.2x input)
A55: History MW basis (1 Capacity 173 / 2 company ~190 both history & forward / 3 mismatch test) | B55: =HistMWBasis -> 1 | C55: 1 | D55: ="INFO: Q2 energized basis "&TEXT(INDEX(MW_Act,1,LastHist),"0")&" MW; Q2 rev/MW $"&TEXT(INDEX(H_AIRev,1,LastHist)*4/INDEX(MW_Act,1,LastHist),"0.0")&"M" -> INFO: Q2 energized basis 182 MW; Q2 rev/MW $12.6M | E55: Same basis must drive history calibration and forward path
A56: June step-up vs March: monthly $M and IT MW at take-or-pay pricing (upper end) | B56: =ARR_Step -> 88 | C56: =ARR_StepMW -> 88 | D56: ="INFO: ~"&TEXT(ARR_StepMW,"0")&" MW at $12M/MW take-or-pay (fewer if reserved at Q2 renewal rates); JuneExitOn="&JuneExitOn -> INFO: ~88 MW at $12M/MW take-or-pay (fewer if reserved at Q2 renewal rates); JuneExitOn=0
A57: DCF EV sign (negative = plan destroys value at WACC; equity floored at 0) | B57: =V_EV -> -898.81401 | C57: 0 | D57: =IF(B57<0,"FLAG: EV<0; FD value/share floored at 0","OK") -> FLAG: EV<0; FD value/share floored at 0
A58: Terminal value basis | B58: =V_TV -> 71868.054 | C58: =V_TVB -> 61488.841 | D58: =V_TVBasis -> RUN-OFF (reinvestment value-destroying) | E58: Run-off floor when replacement capex exceeds terminal cash generation
A59: Funding runway: first quarter liquidity < 0 (after v0.7 funding plan when FP_On; no plug) | B59: =Liq_NegQ -> none to Q4'30 | C59: Skeptic: Q2'27 | D59: ="INFO" -> INFO
A60: Opening liquidity: Aug-26 converts counted ONCE (runway gross row + CashFlow net row, Q3'26 only); 6/30 cash $8,042M excludes them | B60: =SUM(Liq_Aug) -> 5750 | C60: =AugGross -> 5750 | D60: =IF(AND(ABS(B60-C60)<0.5,ABS(SUMPRODUCT((Q_Idx<>11)*Liq_Aug))<0.5,ABS(INDEX(H_Cash,1,LastHist)-CS_Cash)<0.5,ABS(SUM(CF_CVProc)-SUM(CF_FPConv)-AugNet)<0.5),"OK: once (runway Q3'26 gross 5,750; CashFlow Q3'26 net 5,680)","DOUBLE/MISSING") -> OK: once (runway Q3'26 gross 5,750; CashFlow Q3'26 net 5,680) | E60: Runway row '+ Aug-2026 converts gross' (CashFlow tab) and 'Convert issuance proceeds (net)' row
A61: $775M asset-backed facility drawn in base (LoanOn) | B61: =SecAmt*LoanOn -> 0 | C61: 0 | D61: =IF(LoanOn=0,"OK: $0 drawn (undisclosed); $775M sensitivity","INFO: $775M drawn sensitivity") -> OK: $0 drawn (undisclosed); $775M sensitivity | E61: SOFR+2.50%; cash, debt, interest and runway all switch together
A62: Liquidity after funding plan: min every quarter Q3'26-Q4'30 vs buffer (FP_MinBuf if re-sized, else MinCash) | B62: =MIN(INDEX(Liq,1,11):INDEX(Liq,1,28)) -> 1000 | C62: =IF(FP_Resize=1,FP_MinBuf,MinCash) -> 1000 | D62: =IF(FP_On=0,"INFO: plan off",IF(B62>=C62-0.5,"OK: every quarter >= buffer","FLAG: plan does not close the gap"))&"; YE27 "&TEXT(INDEX(Liq,1,16),"#,##0")&"; top-up equity "&TEXT(SUM(FP_EqTop),"#,##0")&" / "&TEXT(SUM(FP_EqTopSh),"0.0")&"M sh" -> OK: every quarter >= buffer; YE27 1,000; top-up equity 38,740 / 164.5M sh | E62: Plan is ESTIMATED (not guidance)
A63: Convert waterfall at $147 (existing notes): converting principal / full-conversion shares vs ~$3.34B / ~26.2M | B63: =SUMPRODUCT((147>Valuation!$H$80:$H$91)*Valuation!$E$80:$E$91) -> 3337.5 | C63: 3337.5 | D63: =IF(ABS(B63-C63)<5,"OK","CHECK")&"; shares "&TEXT(SUMPRODUCT((147>Valuation!$H$80:$H$91)*Valuation!$E$80:$E$91*Valuation!$G$80:$G$91)/1000,"0.0")&"M; at $46 debt "&TEXT(SUMPRODUCT((46<=Valuation!$H$80:$H$91)*Valuation!$E$80:$E$91),"#,##0") -> OK; shares 26.2M; at $46 debt 13,425 | E63: Parent reference: $46 all OTM ($13.4B debt); $147 26.2M sh; $243 all but Feb-30/Feb-34
A64: Post-funding FD shares at solved price (M) vs pre-funding | B64: =V_SHF -> 506.47495 | C64: =V_SH -> 314.92525 | D64: ="INFO: +"&TEXT(V_SHF-V_SH,"0.0")&"M (ATM "&TEXT(V_FPSh,"0.0")&"M); full-conv "&TEXT(V_SHFFull,"0.0")&" / NSS "&TEXT(V_SHFNSS,"0.0")&"; value/share pre "&TEXT(V_PS,"0.0")&" -> post "&TEXT(V_PSF,"0.0") -> INFO: +191.5M (ATM 189.8M); full-conv 506.5 / NSS 505.1; value/share pre 0.0 -> post 78.6
A65: AUTHORITY (v0.7d): shares needed at the HEADLINE basis = new shares issued through FP_PostQ + 2027 plan-convert reserve vs ~82M available (AuthAvail: ~64M 20% AGM authority + treasury) | B65: =V_AuthNeed -> 13262.174 | C65: =AuthAvail -> 82 | D65: =IF(B65<=C65,"OK: within authority","FLAG: needs "&TEXT(B65-C65,"#,##0")&"M more (EGM approval)")&"; issued "&TEXT(V_NewShHead,"#,##0.0")&"M + convert reserve "&TEXT(V_CVResHead,"#,##0.0")&"M; spot basis "&TEXT(V_FPSh+SUMPRODUCT(V_TrPlanE*V_TrRT)/1000,"#,##0")&"M" -> FLAG: needs 13,180M more (EGM approval); issued 10,991.2M + convert reserve 2,271.0M; spot basis 227M | E65: Not a model cap
A66: Sh_Basic tie (v0.7d): plan shares in Shares tab (after V_Q through FP_PostQ) = valuation new shares at the headline basis | B66: =SUMPRODUCT((Q_Idx>V_Q)*(Q_Idx<=FP_PostQ)*Sh_PlanFlow) -> 10991.22 | C66: =V_NewShHead -> 10991.22 | D66: =IF(FP_On=0,"INFO: plan off",IF(ABS(B66-C66)<0.5,"OK","CHECK: "&TEXT(B66-C66,"0.0")))&IF(ABS(V_EqIssPre)>0.5," FLAG: top-up at/before V_Q","") -> OK
A67: Self-consistent PT fixed point converged (|S30 - S29|) and path memo (|T40 - T39|) | B67: =V_CONVSC -> 0 | C67: =V_CONVPT -> 2.5415812e-05 | D67: =IF(AND(V_CONVSC<0.05,V_CONVPT<0.05),"OK","CHECK convergence")&"; SC PT "&TEXT(V_PTSC,"0.00")&" | spot memo "&TEXT(V_PTSpot,"0.00")&" | path memo "&TEXT(V_PTPath,"0.00") -> OK; SC PT 3.97 | spot memo 88.87 | path memo 30.25
A68: NVIDIA pre-funded warrant counted exactly once: economic basic = 271.86 issued + 15.77 exchange + 21.07 warrant (= 308.69); market EV equity uses the same 308.69 | B68: =V_BASIC -> 308.69115 | C68: =271.855218+ExchShares+NVDA_W -> 308.69115 | D68: =IF(AND(ABS(V_BASIC-(271.855218+ExchShares+NVDA_W))<0.05,ABS(V_MKTEQ/SharePx-V_BASIC)<0.05),"OK: once in basic, market EV and FD","FLAG: warrant count mismatch") -> OK: once in basic, market EV and FD
A69: Financing does not change unlevered EV (CapIntFix): UFCF tax excludes capitalized-interest D&A | B69: =CapIntFix -> 1 | C69: =1 -> 1 | D69: =IF(CapIntFix=1,"OK","FLAG: capitalized interest flows into UFCF tax") -> OK
A70: Avride: value credited (V_AV) vs PV burn add-back (V_AVAdd) - credit value AND add back burn, or neither | B70: =V_AV -> 0 | C70: =V_AVAdd -> 0 | D70: =IF(V_AV=0,"OK: Avride $0, burn kept in EBITDA",IF(V_AVAdd>0,"OK: burn added back (no double count)","FLAG: double count")) -> OK: Avride $0, burn kept in EBITDA
A71: Red-graded sites (count) | B71: =RedSites -> 5 | D71: ="INFO" -> INFO
A72: FY27 EBIT vs Skeptic at live life | B72: =SUMIF(Q_Yr,2027,PL_EBIT) -> -1135.4902 | C72: =CHOOSE(MATCH(Life_B,{4,5,6},1),SkEBIT4,SkEBIT5,SkEBIT6) -> 1980 | D72: ="INFO" -> INFO | E72: See Sensitivity 4/5/6

Sheet Inputs
A1: Inputs & Assumptions (scenario-driven)
A2: Blue = input. Fill: orange = PLACEHOLDER (no source yet), yellow = Estimated/Consensus, none = Reported/Derived. Live column = CHOOSE(Scenario, Bull, Base, Bear). Owners fill/replace their cells; never overwrite formulas.
A4: Scenario selector (1 = Bull, 2 = Base, 3 = Bear) | D4: 2 | E4: =CHOOSE(Scen,"BULL","BASE","BEAR") -> BASE
A6: Scalar input | B6: Unit | C6: Bull | D6: Base | E6: Bear | F6: LIVE | J6: Owner | K6: Status | L6: Source / method
A7: General
A8: Valuation date | B8: date | C8: — | D8: 46299 | E8: — | F8: =D8 -> 46299 | J8: Modeling | K8: Input | L8: Pitch valuation date; drives DCF discounting and Outputs horizons
A9: Last actual quarter index (10 = Q2'26) | B9: # | C9: — | D9: 10 | E9: — | F9: =D9 -> 10 | J9: Modeling | K9: Input | L9: Roll forward to 11 when Q3'26 is reported
A10: Fiscal-year base (year before first model year) | B10: yr | C10: — | D10: 2023 | E10: — | F10: =D10 -> 2023 | J10: Modeling | K10: Input | L10: Structural: annual-input column = FY - FYBase
A11: Current share price (NBIS) | B11: $/sh | C11: — | D11: 242.81 | E11: — | F11: =D11 -> 242.81 | J11: Skeptic | K11: Reported | L11: Oct 2 2026 close per Skeptic (/workspace/nebius/skeptic/01_priced_in.xlsx), medium confidence; used for convert ITM test, TSM, equity raises
A12: MW block that drives revenue (1 contracted, 2 energized est. [Capacity, default], 3 mgmt-connected guide, 4 Capacity proposed path [scenario, not base until Tuesday file]) | B12: # | C12: — | D12: 2 | E12: — | F12: =D12 -> 2 | J12: Modeling | K12: Input | L12: Default = Capacity energized base (estimated live IT load); guided path kept as comparison only
A13: Energized (live IT load) -> billing lag, MW source 2 | B13: qtrs | C13: 1 | D13: 1 | E13: 1 | F13: =CHOOSE(Scen,C13,D13,E13) -> 1 | J13: Capacity | K13: Estimated | L13: Base 1 qtr. 2 qtrs = STRESS case (Sensitivity snapshot), not the bear default
A14: IT capex method (1 = GPUs x $/GPU, 2 = flat $M per IT MW, 3 = site path: new energized IT MW x per-site $/MW by ownership & generation [default]) | B14: # | C14: — | D14: 3 | E14: — | F14: =D14 -> 3 | J14: Modeling | K14: Input | L14: Method 3 = path-consistent per Capacity gpu_mw_capex.xlsx
A15: Owned site all-in capex per IT MW - GB200 | B15: $M/MW | C15: — | D15: 42 | E15: — | F15: =D15 -> 42 | J15: Capacity | K15: Estimated | L15: /workspace/nebius/capacity/gpu_mw_capex.xlsx CapexPerMW (incl ~$10-12.5M shell+power)
A16: GB300 capex from rack price (1 = racks/IT MW x GB_RackPx + network; owned adds CPM_SP; 0 = v0.7 flat $41M leased / $53M owned) | B16: 0/1 | C16: — | D16: 1 | E16: — | F16: =D16 -> 1 | J16: Capacity/GPU Market | K16: Input
A17: GB300 NVL72 rack price (servers incl. NVLink; ex network) | B17: $M/rack | C17: — | D17: 4.5 | E17: — | F17: =D17 -> 4.5 | J17: Capacity | K17: Reported | L17: gpu_mw_capex.xlsx v2 'GB300 rack price' tab (sourced): base $4.5M, range $4.0-5.0M (MS BOM $4.0M, Loop $3.85M, Wolfe $4.3M, Data Gravity $4.97M; stress $6.25M)
A18: GB300 NVL72 racks per IT MW | B18: racks/IT MW | C18: — | D18: =491/72 -> 6.8194444 | E18: — | F18: =D18 -> 6.8194444 | J18: Capacity | K18: Derived | L18: 491 GPUs/IT MW / 72 = 6.82
A19: GB300 network + storage per IT MW | B19: $M/IT MW | C19: — | D19: 6.1 | E19: — | F19: =D19 -> 6.1 | J19: Capacity | K19: Derived | L19: gpu_mw_capex.xlsx CapexPerMW GB300 base
A20: Owned site all-in capex per IT MW - GB300 (RackOn: rack-based servers+network + CPM_SP hall) | B20: $M/MW | C20: — | D20: =IF(RackOn=1,GB_Racks*GB_RackPx+GB_NetMW+CPM_SP,53) -> 49.2875 | E20: — | F20: =D20 -> 49.2875 | J20: Capacity | K20: Derived | L20: v0.7 53 = 34.1 servers + 6.1 network + 12.5 hall
A21: Owned site all-in capex per IT MW - Vera Rubin (LOW-MEDIUM confidence) | B21: $M/MW | C21: 45.8 | D21: 52.6 | E21: 60.7 | F21: =CHOOSE(Scen,C21,D21,E21) -> 52.6 | J21: Capacity | K21: Estimated | L21: Capacity gpu_mw_capex v2: base $52.6M (= leased 41.1 - 1.0 fit-out + 12.5 hall); bull 45.8 / bear 60.7 same build-up; v0.7 56 (53/59)
A22: Owned site capex per IT MW - Hopper/B200/B300 (GB200 proxy) | B22: $M/MW | C22: — | D22: 42 | E22: — | F22: =D22 -> 42 | J22: Capacity | K22: Estimated | L22: proxy
A23: Leased/colo capex per IT MW - GB200 (and Hopper/B200/B300 stand-ins); IT only, rent in opex | B23: $M/MW | C23: — | D23: 30 | E23: — | F23: =D23 -> 30 | J23: Capacity | K23: Estimated | L23: gpu_mw_capex.xlsx (Capacity), medium confidence
A24: Leased/colo capex per IT MW - GB300 (RackOn: racks x rack price + network; no hall slice - rent covers the building) | B24: $M/MW | C24: — | D24: =IF(RackOn=1,GB_Racks*GB_RackPx+GB_NetMW,41) -> 36.7875 | E24: — | F24: =D24 -> 36.7875 | J24: Capacity | K24: Derived | L24: 6.82 x $4.5M + $6.1M = $36.8M (range $31.4-42.3M, Capacity v2); v0.7 41. NOTE: Capacity's leased Rubin $41.1M includes ~$1M colo fit-out; GB300 here excludes it (per team spec)
A25: Leased/colo capex per IT MW - Vera Rubin, EX $1M colo fit-out (rent is the only building cost; same as GB300) (LOW-MEDIUM confidence) | B25: $M/MW | C25: 33.3 | D25: 40.1 | E25: 48.2 | F25: =CHOOSE(Scen,C25,D25,E25) -> 40.1 | J25: Capacity/Skeptic | K25: Estimated | L25: v0.7: base $41M flat to GB300 (SemiAnalysis TCO 1.51-1.56x/GPU-hr at 320 vs 491 GPUs/IT MW -> ~0.98-1.02x GB300 per MW; Capacity at Morgan Stanley rack cost: leased $42-48M); bull $41M; bear $48.5M (Skeptic $45-52M midpoint: 0.65x racks/MW x MS 1.68-1.95x rack cost). $32M = OUTER-BULL sensitivity only (soft: ~$6.0M rack ~1.2x GB300; networking $3.6M looks low vs GB300 $6.1M - Capacity reconciles Tuesday)
A26: v0.2 fix: GPU fleet MW-ratio only in forecast + capex follows DRIVER MW (1 = on) | B26: 0/1 | C26: — | D26: 1 | E26: — | F26: =D26 -> 1 | J26: Modeling | K26: Input | L26: Off = v0.1 behaviour (history fleet scaled by selected MW block; capex followed energized path only)
A27: Terminal basis: 2 = EXCLUDE BOTH Q4'30-onward spend for MW billing after Q4'30 and that MW (terminal = Q4'30 exit run-rate x 4) [default, conservative]; 1 = INCLUDE BOTH (memo only: run-rate scaled x(MW Q4'30 + MW billing Q1'31)/MW Q4'30, unsourced ~1.2x step-up); 0 = v0.1 (FY2030 x (1+TG), Q4'30 spend charged) | B27: 0/1/2 | C27: — | D27: 2 | E27: — | F27: =D27 -> 2 | J27: Modeling | K27: Input | L27: v0.2 decision (Oct 4): do not credit unbilled capacity on an unsourced step-up; 'include both' EV shown as memo row in Valuation
A28: Terminal value floor: max(Gordon/blend, run-off value of existing fleet with no reinvestment) (1 = on) | B28: 0/1 | C28: — | D28: 1 | E28: — | F28: =D28 -> 1 | J28: Modeling | K28: Input | L28: Operator would stop replacing GPUs at negative NPV; TV cannot be below run-off (>= 0)
A29: Owned-site O&M (facility staff, maintenance, insurance, property tax) | B29: $M/IT MW-yr | C29: — | D29: 0.75 | E29: — | F29: =D29 -> 0.75 | J29: Capacity | K29: Placeholder | L29: Leased sites carry this inside rent; owned sites had none in v0.1. Placeholder pending Capacity
A30: Lease prepayments as upfront cost on NEW leased IT MW (1 = on) | B30: 0/1 | C30: — | D30: 1 | E30: — | F30: =D30 -> 1 | J30: Filings | K30: Input
A31: Lease prepayment per new leased IT MW (prepaid rent at commencement; capitalised, amortised over Life_Pow) | B31: $M/IT MW | C31: — | D31: 1.6 | E31: — | F31: =D31 -> 1.6 | J31: Filings | K31: Derived | L31: 6/30/26 prepayments on not-yet-commenced leases $612.4M / ~383 leased IT MW starting by YE27 (Capacity v2)
A32: New customer prepayment inflow: 1 = % of new-build capex (v0.7); 2 = Q2'26 pace $1.2B/qtr [base]; 3 = guidance case: $4.5B in H2'26 (>$9B FY26 guide), then Q2 pace | B32: # | C32: — | D32: 2 | E32: — | F32: =D32 -> 2 | J32: Filings | K32: Derived | L32: Q2'26 revenue note: deferred revenue +~$3.2B Q1, +~$1.2B Q2
A33: Q2'26-pace new prepayments per quarter | B33: $M/qtr | C33: — | D33: 1200 | E33: — | F33: =D33 -> 1200 | J33: Filings | K33: Derived | L33: Deferred revenue added ~$1.2B in Q2'26
A34: Guidance case: new prepayments H2'26 total | B34: $M | C34: — | D34: 4500 | E34: — | F34: =D34 -> 4500 | J34: Filings | K34: Derived | L34: FY26 guide >$9B less H1 ~$4.4B
A35: Last quarter of the fixed-pace prepayment path (capex-linked % after) | B35: idx | C35: — | D35: 20 | E35: — | F35: =D35 -> 20 | J35: Modeling | K35: Estimated | L35: Q4'28; 2029+ reverts to capex-linked % (PrepayMode 1 logic)
A36: PLACEHOLDER: share of deferred-revenue balance treated as debt-like (refundable) at valuation | B36: % | C36: 0 | D36: 0 | E36: 0.25 | F36: =CHOOSE(Scen,C36,D36,E36) -> 0 | J36: Filings | K36: Placeholder | L36: NOT DISCLOSED: filing says balance includes 'amounts that may be refundable'; bear placeholder 25%
A37: Bloom slip / Vineland loss: slipped or lost Microsoft MW sit IDLE (not re-sold to new-deal books) (1 = v0.7c fix) | B37: 0/1 | C37: — | D37: 1 | E37: — | F37: =D37 -> 1 | J37: Capacity | K37: Input | L37: v0.7b: slipped T5-T9 GPUs were re-priced as new 2027+ deals, offsetting most of the slip
A38: BEAR SENS: Vineland T1-T4 permanently lost if generators must stop before fuel cells run (1 = on) | B38: 0/1 | C38: — | D38: 0 | E38: — | F38: =D38 -> 0 | J38: Capacity | K38: Estimated | L38: 4 x ~26.7 = ~107 IT MW, ~$1.55B/yr at $14.49M/IT MW; trigger ~Nov 6-9 2026 (NJDEP 45-day deadline)
A39: Vineland T1-T4 SLA-credit step on (1) | B39: 0/1 | C39: — | D39: 1 | E39: — | F39: =D39 -> 1 | J39: Capacity | K39: Input | L39: Step (i); step (ii) = permanent loss (VinLossOn)
A40: Vineland T1-T4 permanent-loss step on (1) | B40: 0/1 | C40: — | D40: 1 | E40: — | F40: =D40 -> 1 | J40: Capacity | K40: Input
A41: PLACEHOLDER: SLA credits as % of T1-T4 revenue (Q4'26 + Q1'27) | B41: % | C41: — | D41: 0.1 | E41: — | F41: =D41 -> 0.1 | J41: Capacity | K41: Placeholder | L41: NOT DISCLOSED - placeholder 10% for 2 quarters
A42: First quarter T1-T4 revenue permanently lost | B42: idx | C42: — | D42: 14 | E42: — | F42: =D42 -> 14 | J42: Capacity | K42: Estimated | L42: Q2'27
A43: Quarters lost T1-T4 GPUs sit idle before redeployment to new-deal books | B43: qtrs | C43: — | D43: 2 | E43: — | F43: =D43 -> 2 | J43: Capacity | K43: Estimated | L43: Redeployed at the live scenario's GB300 new-deal price (bear $14.5M) after 2 qtrs
A44: 3-yr GB300 new deals re-price at renewal to the then-prevailing curve (1 = on) | B44: 0/1 | C44: — | D44: 0 | E44: — | F44: =D44 -> 0 | J44: Contracts | K44: Input | L44: Option (v0.7c); bear sensitivity
A45: Share of new GB300 MW on 3-yr deals (re-price at year 3) | B45: % | C45: 0 | D45: 0 | E45: 0.4 | F45: =CHOOSE(Scen,C45,D45,E45) -> 0 | J45: Contracts | K45: Estimated | L45: Bear 40%
A46: Funding plan re-sized to the live gap: ATM (remaining 12.27M sh) -> 2027 converts (same terms) -> equity top-up each quarter to FP_MinBuf (1 = v0.7c) | B46: 0/1 | C46: — | D46: 1 | E46: — | F46: =D46 -> 1 | J46: Modeling | K46: Estimated
A47: Minimum liquidity buffer every quarter (re-sized plan) | B47: $M | C47: — | D47: 1000 | E47: — | F47: =D47 -> 1000 | J47: Modeling | K47: Input
A48: Last quarter of equity top-up (and post-funding count date when FP_Resize) | B48: idx | C48: — | D48: 28 | E48: — | F48: =D48 -> 28 | J48: Modeling | K48: Input | L48: Q4'30 = every quarter of the horizon
A49: Equity top-up issue price discount to SharePx (scenario issuance price path, flat) | B49: % | C49: 0 | D49: 0.03 | E49: 0.4 | F49: =CHOOSE(Scen,C49,D49,E49) -> 0.03 | J49: Modeling | K49: Estimated | L49: Base 3% (EqDisc), bull 0%, bear 40% (as bear ATM)
A50: v0.8 SCENARIO 'contracted only / stop building': after StopIdx only signed capacity is built (contract tranches incl. Meta backstop if on); non-contract fleet frozen at its StopIdx level; no new-deal prepayments or lease prepayments | B50: 0/1 | C50: — | D50: 0 | E50: — | F50: =D50 -> 0 | J50: Modeling | K50: Input | L50: Uncontracted 2027+ slice per Capacity uncontracted_split.csv (Birmingham, Lappeenranta, Butler, Kapuli owned Rubin; Beit Shemesh, UK3, CLT1 leased) and all later growth is not built
A51: Stop-building: last quarter whose ACTIVE (billing) MW is kept - Q1'27 = sites energized by YE26 (EnLag 1 qtr); ATM plan + 2027 plan converts switched off, equity top-ups only to FP_MinBuf at the self-consistent PT | B51: idx | C51: — | D51: 13 | E51: — | F51: =D51 -> 13 | J51: Capacity | K51: Estimated | L51: Q1'27 billing = sites live by YE26 (Oklahoma, Newport, Harlow, Masmiyya, Tallinn) are built / capex largely spent
A52: Stop-building: share of signed leases-not-commenced + energy commitments ($17.4B), pro rata to the cut MW, still paid with no modeled rent / power (net of sublease / resale) | B52: % | C52: — | D52: 0.5 | E52: — | F52: =D52 -> 0.5 | J52: Modeling | K52: Estimated | L52: Only when StopBuild = 1; 0% / 100% as range
A53: v0.8b FUNDING STACK: new-deal prepayment toggle (1 = prepayments = NDPrepayPct x new-build capex on NON-signed MW; replaces PrepayMode pace / PrepayPct27/28 / HSPre; signed tranches 0%) | B53: 0/1 | C53: — | D53: 0 | E53: — | F53: =D53 -> 0 | J53: Modeling | K53: Input | L53: 0 = v0.8 logic
A54: v0.8b: new-deal prepayment share of new-build capex (non-signed MW) when NDPrepayOn = 1: 0% / 25% / 55% | B54: % | C54: — | D54: 0.55 | E54: — | F54: =D54 -> 0.55 | J54: Filings | K54: Estimated | L54: Q2'26 letter: prepayments fund 50-60% of capex on deals that carry them
A55: v0.8b: asset-backed debt on CONTRACTED MW only (signed Microsoft / Meta incl. Meta backstop): loan-to-cost on their new-build capex 0 / 25 / 50% | B55: % | C55: — | D55: 0 | E55: — | F55: =D55 -> 0 | J55: Modeling | K55: Input | L55: Drawn with capex; none on uncontracted MW; existing 6/30 fleet not refinanced
A56: v0.8b: ABS spread over SOFR | B56: % | C56: — | D56: 0.025 | E56: — | F56: =D56 -> 0.025 | J56: Filings | K56: Estimated | L56: SOFR + 2.50%
A57: v0.8b: ABS straight-line amortisation over contract term from billing start | B57: qtrs | C57: — | D57: 20 | E57: — | F57: =D57 -> 20 | J57: Contracts | K57: Estimated | L57: 5-yr Microsoft / Meta / backstop terms
A58: v0.8b: UNSOLD new 2027+ non-contract MW priced at UncPx (both generations, flat then MYDecl path) on 3-yr terms; contracted / RPO-sold MW unchanged | B58: 0/1 | C58: — | D58: 0 | E58: — | F58: =D58 -> 0 | J58: Skeptic | K58: Input | L58: Legacy GPU-hour fleet (147 MW at Q1'27) stays on books (b)/(c)
A59: v0.8b: unsold new-MW price when UncPxOn = 1 ($M per IT MW-yr): 16 / 20 / 22.5 | B59: $M/IT MW-yr | C59: — | D59: 20 | E59: — | F59: =D59 -> 20 | J59: Skeptic | K59: Estimated
A60: v0.8b: 3-yr terms - unsold vintages re-price at year 3 (2027 vintages -> 2030) to the prevailing new-deal curve (ND_Px GB300 / RubinMW Rubin path) | B60: 0/1 | C60: — | D60: 1 | E60: — | F60: =D60 -> 1 | J60: Skeptic | K60: Input
A61: Meta backstop: covered IT MW (0 / 150 / 190), applied first to the owned Rubin halls (Birmingham 56, Lappeenranta 46, Butler 48, Kapuli 15 = 165 MW) | B61: IT MW | C61: — | D61: 0 | E61: — | F61: =D61 -> 0 | J61: Filings | K61: Derived | L61: FY25 20-F p.75 (Reported terms): Meta buys unsold capacity on certain clusters for 5 yrs from deployment, up to $15B (~$3B/yr = ~190 MW at $16M or ~150 MW at $20M). MW mapping Derived / low confidence. Off-RPO (not in signed backlog / floor)
A62: Meta backstop price ($M per IT MW-yr) - PLACEHOLDER | B62: $M/IT MW-yr | C62: 16 | D62: 16 | E62: 14.5 | F62: =CHOOSE(Scen,C62,D62,E62) -> 16 | J62: Filings | K62: Placeholder | L62: Bear $14.5M (below $16M)
A63: Meta backstop billing start (MW-weighted owned Rubin hall go-live: Q1'27 56 / Q2'27 46 / Q4'27 63) | B63: idx | C63: — | D63: 15 | E63: — | F63: =D63 -> 15 | J63: Capacity | K63: Estimated | L63: Q3'27
A64: HEADLINE PT issuance-price basis: 1 = SELF-CONSISTENT (ATM, top-ups and convert terms priced at the solved PT itself; fixed point) [v0.7d]; 2 = MEMO spot SharePx x (1 - disc) (v0.7c; depends on market access at today's price); 3 = MEMO path from spot to the path's own PT over FP_PathQ (depends on market access at today's price) | B64: # | C64: — | D64: 1 | E64: — | F64: =D64 -> 1 | J64: Modeling | K64: Input | L64: v0.7d: headline no longer rests on issuing at ~$236 against ~$0 of value
A65: Self-consistent basis: issue discount to the solved PT | B65: % | C65: — | D65: 0 | E65: — | F65: =D65 -> 0 | J65: Modeling | K65: Input | L65: 0 = issue at the PT itself (per spec)
A66: Path memo: quarters over which the issue price moves linearly from SharePx to the path PT | B66: qtrs | C66: — | D66: 8 | E66: — | F66: =D66 -> 8 | J66: Modeling | K66: Estimated | L66: 8 = Q3'28; flat after
A67: Share-issuance authority available now (~64M under the 20% AGM authority + treasury) | B67: M sh | C67: — | D67: 82 | E67: — | F67: =D67 -> 82 | J67: Filings | K67: Estimated | L67: ~82M per team (AGM 20% x 322M = 64.4M + treasury; medium confidence); more needs an EGM
A68: Run-off terminal value includes the 15% after-tax GPU residual as each exit-fleet cohort retires (1 = v0.7c fix) | B68: 0/1 | C68: — | D68: 1 | E68: — | F68: =D68 -> 1 | J68: Modeling | K68: Input | L68: v0.7b run-off TV (the binding TV basis) dropped hardware to zero at end of life; going-concern TV already netted V_GResid
A69: Asset floor on the IDENTICAL EV-to-equity bridge as the DCF (1 = v0.7c) | B69: 0/1 | C69: — | D69: 1 | E69: — | F69: =D69 -> 1 | J69: Modeling | K69: Input | L69: Same OffBSWt x commitments, converts (carrying), cash, refundable-DR placeholder, SOTP, funding cash & shares
A70: v0.7b fix: owned-site opex = OwnOpex all-in (power + O&M, NO rent); O&M = OwnOpex - power per IT MW (1 = on; 0 = OM_MW) | B70: 0/1 | C70: — | D70: 1 | E70: — | F70: =D70 -> 1 | J70: Capacity | K70: Input | L70: Leased sites pay RentMW x PUE (shell+power) + power; owned sites carry the building in capex
A71: Owned-site opex per IT MW-yr, all-in power + ops, no rent | B71: $M/IT MW-yr | C71: — | D71: 2.25 | E71: — | F71: =D71 -> 2.25 | J71: Capacity | K71: Estimated | L71: Capacity: $2.0-2.5M per IT MW-yr (use 2.25)
A72: Residual / resale credit for retired GPUs+servers at refresh (% of original cohort cost) | B72: % | C72: 0.15 | D72: 0.15 | E72: 0 | F72: =CHOOSE(Scen,C72,D72,E72) -> 0.15 | J72: GPU Market | K72: Estimated | L72: gpu_price_history.xlsx: base 15% (range 10-25%, LOW confidence); bear 0. H100 median $4.09 (Mar-24) -> $3.99; A100 neocloud +~12%/yr
A73: Data hall + power ECONOMIC life (residual value in payback/IRR/NPV only; book lives Life_Shell / Life_Pow) | B73: yrs | C73: — | D73: 18 | E73: — | F73: =D73 -> 18 | J73: Capacity | K73: Estimated | L73: Economic-life estimate only (15-20+ yrs); not a book life
A74: v0.7b fix: UFCF tax and terminal D&A exclude capitalized-interest depreciation (financing must not change unlevered EV) (1 = on) | B74: 0/1 | C74: — | D74: 1 | E74: — | F74: =D74 -> 1 | J74: Modeling | K74: Input
A75: Capacity file version: 1 = v1 (YE27 ~950 IT MW energized), 2 = v2 (Oct 4 22:33 ET; YE26 ~302 / YE27 ~1,082 IT MW, Basis-tab IT factors) | B75: # | C75: — | D75: 2 | E75: — | F75: =D75 -> 2 | J75: Capacity | K75: Input | L75: v2 adds Newport UK, Oklahoma, Minnesota, UK 3rd, CLT1 from file; new MW carry own path capex
A76: Issued share capital incl. treasury at AGM (220.4 Class A + 68.1 treasury + 33.5 Class B) | B76: M sh | C76: — | D76: 322 | E76: — | F76: =D76 -> 322 | J76: Filings | K76: Reported | L76: AGM notice items 13-15 (Aug-26): 5-yr authority to issue up to 20% of issued capital
A77: Board issuance authority (% of issued capital, rises as shares are issued) | B77: % | C77: — | D77: 0.2 | E77: — | F77: =D77 -> 0.2 | J77: Filings | K77: Reported | L77: Base authority ~64M + treasury (medium confidence); board can seek more at an EGM
A78: H2'26 repricing: Q2 list avg (H100 $2.95->$3.85 Jun-26), legacy reserved book renews +30% at 50%/12 months, new GPUs at current list (1 = on) | B78: 0/1 | C78: — | D78: 1 | E78: — | F78: =D78 -> 1 | J78: GPU Market | K78: Input | L78: Off = v0.1 (Q2 at Jun list; reserved = lagged list)
A79: Reserved renewal repricing vs expiring contract | B79: % | C79: — | D79: 0.3 | E79: — | F79: =D79 -> 0.3 | J79: Filings | K79: Reported | L79: Q2'26 letter: >30% repricing on renewals
A80: H100 on-demand list - Q2'26 average | B80: $/GPU-hr | C80: — | D80: =(2*2.95+3.85)/3 -> 3.25 | E80: — | F80: =D80 -> 3.25 | J80: GPU Market | K80: Derived | L80: Archived nebius.com/prices: $2.95 Apr-May -> $3.85 from Jun 2026 (Reported pages); Q2 avg derived
A81: Team June run-rate per MW - low | B81: $M/MW-yr | C81: — | D81: 13.3 | E81: — | F81: =D81 -> 13.3 | J81: Modeling | K81: Estimated | L81: June list + renewals signed by 6/30
A82: Team June run-rate per MW - high | B82: $M/MW-yr | C82: — | D82: 13.5 | E82: — | F82: =D82 -> 13.5 | J82: Modeling | K82: Estimated
A83: Team estimate: unexplained ARR residual - low | B83: $M | C83: — | D83: 650 | E83: — | F83: =D83 -> 650 | J83: Modeling | K83: Estimated | L83: ~45-50 MW
A84: Team estimate: unexplained ARR residual - high | B84: $M | C84: — | D84: 700 | E84: — | F84: =D84 -> 700 | J84: Modeling | K84: Estimated
A85: Consensus FY28 adj. EBITDA margin (13.98 / 23.0) | B85: % | C85: — | D85: =13.98/23 -> 0.60782609 | E85: — | F85: =D85 -> 0.60782609 | J85: Skeptic | K85: Estimated | L85: 01_priced_in.xlsx
A86: Peer adj. EBITDA margin reference (CoreWeave ~62%) | B86: % | C86: — | D86: 0.62 | E86: — | F86: =D86 -> 0.62 | J86: GPU Market | K86: Placeholder | L86: pending GPU Market comps
A87: Cap Microsoft GPU consumption at Vineland energized IT MW (Capacity) (1 = on) | B87: 0/1 | C87: — | D87: 1 | E87: — | F87: =D87 -> 1 | J87: Modeling | K87: Input | L87: Fix for Q2'26 utilization: MSFT delivered-tranche MW (53 MW) exceeded Vineland energized (39 MW / 19,157 GPUs)
A88: GPU end-of-life replacement capex in forecast (1 = on) | B88: 0/1 | C88: — | D88: 1 | E88: — | F88: =D88 -> 1 | J88: Modeling | K88: Input | L88: Cohort reaching GPU life is replaced at original cost (fleet persists in Capacity file)
A89: History MW basis: 1 = Capacity named-site (173 MW Q2'26) [default]; 2 = company-implied (~190 MW, ~$12M rev/installed MW) applied to history AND forward path (+uplift); 3 = MISMATCH test: history at 190, forward on 173 path | B89: # | C89: — | D89: 1 | E89: — | F89: =D89 -> 1 | J89: Capacity/Skeptic | K89: Input | L89: Revenue/MW in history and the forward MW path must use the same basis (2); 3 only quantifies Skeptic's ~11% claim
