Workbook

Sheet GPUsPerMW
A1: GPUs per MW by NVIDIA generation – IT-MW and gross (facility) MW basis. Blue = input; black = formula. GPU = one GPU package (VR NVL72 = 72 packages; NVIDIA's 'NVL144' naming counts 144 dies).
A2: Method: kW/GPU at system = unit kW / GPUs per unit; All-in IT kW/GPU = × (1 + overhead for scale-out network, storage, mgmt/CPU nodes outside the unit); GPUs/IT-MW = 1000 / all-in kW; Gross kW/GPU = IT kW × PUE; GPUs/gross-MW = 1000 / gross kW. Low case = high power + high overhead + high PUE; High case = low power + low overhead + low PUE.
A4: Generation | B4: Scenario | C4: Unit | D4: Unit power kW (input) | E4: GPUs per unit (input) | F4: kW/GPU at unit | G4: Overhead % (input) | H4: All-in IT kW/GPU | I4: GPUs per IT MW | J4: PUE used (input) | K4: Gross kW/GPU | L4: GPUs per gross MW | M4: Tag | N4: Basis / sources
A5: Hopper H100/H200 | B5: Low | C5: HGX/DGX 8-GPU | D5: 10.2 | E5: 8 | F5: =D5/E5 -> 1.275 | G5: 0.18 | H5: =F5*(1+G5) -> 1.5045 | I5: =1000/H5 -> 664.67265 | J5: 1.45 | K5: =H5*J5 -> 2.181525 | L5: =1000/K5 -> 458.39493 | M5: Estimated (spec Reported; overhead/PUE Estimated) | N5: Low: 10.2 kW max (S1) + 18% overhead (heavier storage/mgmt) + PUE 1.45 (older air-cooled colo)
A6: Hopper H100/H200 | B6: Base | C6: HGX/DGX 8-GPU | D6: 10.2 | E6: 8 | F6: =D6/E6 -> 1.275 | G6: 0.1 | H6: =F6*(1+G6) -> 1.4025 | I6: =1000/H6 -> 713.01248 | J6: 1.3 | K6: =H6*J6 -> 1.82325 | L6: =1000/K6 -> 548.47114 | M6: Estimated (spec Reported; overhead/PUE Estimated) | N6: Base: 10.2 kW (S1); +10% ≈ SuperPOD switches/mgmt ~9% of server load (S2) and SemiAnalysis H100 ~1.4 kW all-in (S6); PUE 1.30 air-cooled colo (Estimated)
A7: Hopper H100/H200 | B7: High | C7: HGX/DGX 8-GPU | D7: 9.2 | E7: 8 | F7: =D7/E7 -> 1.15 | G7: 0.07 | H7: =F7*(1+G7) -> 1.2305 | I7: =1000/H7 -> 812.67777 | J7: 1.1 | K7: =H7*J7 -> 1.35355 | L7: =1000/K7 -> 738.79798 | M7: Estimated (spec Reported; overhead/PUE Estimated) | N7: High: provisioned at ~90% of nameplate (Estimated, common power-capping practice) + 7% + PUE 1.10 (Nebius Finland 'leading PUE', S16)
A8: Blackwell B200 (HGX) | B8: Low | C8: HGX/DGX 8-GPU | D8: 14.3 | E8: 8 | F8: =D8/E8 -> 1.7875 | G8: 0.18 | H8: =F8*(1+G8) -> 2.10925 | I8: =1000/H8 -> 474.10217 | J8: 1.45 | K8: =H8*J8 -> 3.0584125 | L8: =1000/K8 -> 326.96701 | M8: Estimated (spec Reported; overhead/PUE Estimated) | N8: Low: 14.3 kW max (S3) +18% + PUE 1.45
A9: Blackwell B200 (HGX) | B9: Base | C9: HGX/DGX 8-GPU | D9: 14.3 | E9: 8 | F9: =D9/E9 -> 1.7875 | G9: 0.1 | H9: =F9*(1+G9) -> 1.96625 | I9: =1000/H9 -> 508.58233 | J9: 1.3 | K9: =H9*J9 -> 2.556125 | L9: =1000/K9 -> 391.21717 | M9: Estimated (spec Reported; overhead/PUE Estimated) | N9: Base: 14.3 kW (S3) +10% + PUE 1.30 (air-cooled colo e.g. Modi'in/KC)
A10: Blackwell B200 (HGX) | B10: High | C10: HGX/DGX 8-GPU | D10: 13 | E10: 8 | F10: =D10/E10 -> 1.625 | G10: 0.07 | H10: =F10*(1+G10) -> 1.73875 | I10: =1000/H10 -> 575.12581 | J10: 1.1 | K10: =H10*J10 -> 1.912625 | L10: =1000/K10 -> 522.84164 | M10: Estimated (spec Reported; overhead/PUE Estimated) | N10: High: ~91% of nameplate (Estimated) +7% + PUE 1.10
A11: GB200 NVL72 | B11: Low | C11: NVL72 rack | D11: 132 | E11: 72 | F11: =D11/E11 -> 1.8333333 | G11: 0.12 | H11: =F11*(1+G11) -> 2.0533333 | I11: =1000/H11 -> 487.01299 | J11: 1.35 | K11: =H11*J11 -> 2.772 | L11: =1000/K11 -> 360.75036 | M11: Estimated (spec Reported; overhead/PUE Estimated) | N11: Low: 132 kW rack (top of 120-132 kW range, S6/HPE) +12% + PUE 1.35
A12: GB200 NVL72 | B12: Base | C12: NVL72 rack | D12: 125 | E12: 72 | F12: =D12/E12 -> 1.7361111 | G12: 0.07 | H12: =F12*(1+G12) -> 1.8576389 | I12: =1000/H12 -> 538.31776 | J12: 1.2 | K12: =H12*J12 -> 2.2291667 | L12: =1000/K12 -> 448.59813 | M12: Estimated (spec Reported; overhead/PUE Estimated) | N12: Base: 125 kW (mid of ~120-132 kW) +7% (NVLink switches already in rack) → 1.86 kW ≈ SemiAnalysis 1.87 kW all-in (S6); PUE 1.20 liquid-cooled
A13: GB200 NVL72 | B13: High | C13: NVL72 rack | D13: 120 | E13: 72 | F13: =D13/E13 -> 1.6666667 | G13: 0.05 | H13: =F13*(1+G13) -> 1.75 | I13: =1000/H13 -> 571.42857 | J13: 1.1 | K13: =H13*J13 -> 1.925 | L13: =1000/K13 -> 519.48052 | M13: Estimated (spec Reported; overhead/PUE Estimated) | N13: High: 120 kW +5% + PUE 1.10
A14: Blackwell Ultra B300 (HGX) | B14: Low | C14: HGX/DGX 8-GPU | D14: 15 | E14: 8 | F14: =D14/E14 -> 1.875 | G14: 0.18 | H14: =F14*(1+G14) -> 2.2125 | I14: =1000/H14 -> 451.9774 | J14: 1.45 | K14: =H14*J14 -> 3.208125 | L14: =1000/K14 -> 311.70855 | M14: Estimated (spec Reported; overhead/PUE Estimated) | N14: Low: 15 kW (DGX B300 AC est., S4) +18% + PUE 1.45
A15: Blackwell Ultra B300 (HGX) | B15: Base | C15: HGX/DGX 8-GPU | D15: 14.5 | E15: 8 | F15: =D15/E15 -> 1.8125 | G15: 0.1 | H15: =F15*(1+G15) -> 1.99375 | I15: =1000/H15 -> 501.5674 | J15: 1.3 | K15: =H15*J15 -> 2.591875 | L15: =1000/K15 -> 385.82108 | M15: Estimated (spec Reported; overhead/PUE Estimated) | N15: Base: 14.5 kW (DGX B300, S4) +10% + PUE 1.30
A16: Blackwell Ultra B300 (HGX) | B16: High | C16: HGX/DGX 8-GPU | D16: 14 | E16: 8 | F16: =D16/E16 -> 1.75 | G16: 0.07 | H16: =F16*(1+G16) -> 1.8725 | I16: =1000/H16 -> 534.04539 | J16: 1.1 | K16: =H16*J16 -> 2.05975 | L16: =1000/K16 -> 485.49581 | M16: Estimated (spec Reported; overhead/PUE Estimated) | N16: High: ~14 kW (nvidia.com, S4) +7% + PUE 1.10
... A22: Vera Rubin NVL72 (VR200; 'NVL144' dies) | B22: High | C22: NVL72 rack | D22: 190 | E22: 72 | F22: =D22/E22 -> 2.6388889 | G22: 0.05 | H22: =F22*(1+G22) -> 2.7708333 | I22: =1000/H22 -> 360.90226 | J22: 1.1 | K22: =H22*J22 -> 3.0479167 | L22: =1000/K22 -> 328.09296 | M22: Estimated (spec Reported; overhead/PUE Estimated) | N22: High: ~190 kW Max-Q (S7) +5% + PUE 1.10
A24: Summary – GPUs per MW (rounded in display)
A25: Generation | B25: IT-MW Low | C25: IT-MW Base | D25: IT-MW High | E25: Gross-MW Low | F25: Gross-MW Base | G25: Gross-MW High | H25: PUE Low/Base/High
A26: Hopper H100/H200 | B26: =I5 -> 664.67265 | C26: =I6 -> 713.01248 | D26: =I7 -> 812.67777 | E26: =L5 -> 458.39493 | F26: =L6 -> 548.47114 | G26: =L7 -> 738.79798 | H26: =TEXT(J5,"0.00")&" / "&TEXT(J6,"0.00")&" / "&TEXT(J7,"0.00") -> 1.45 / 1.30 / 1.10
A27: Blackwell B200 (HGX) | B27: =I8 -> 474.10217 | C27: =I9 -> 508.58233 | D27: =I10 -> 575.12581 | E27: =L8 -> 326.96701 | F27: =L9 -> 391.21717 | G27: =L10 -> 522.84164 | H27: =TEXT(J8,"0.00")&" / "&TEXT(J9,"0.00")&" / "&TEXT(J10,"0.00") -> 1.45 / 1.30 / 1.10
A28: GB200 NVL72 | B28: =I11 -> 487.01299 | C28: =I12 -> 538.31776 | D28: =I13 -> 571.42857 | E28: =L11 -> 360.75036 | F28: =L12 -> 448.59813 | G28: =L13 -> 519.48052 | H28: =TEXT(J11,"0.00")&" / "&TEXT(J12,"0.00")&" / "&TEXT(J13,"0.00") -> 1.35 / 1.20 / 1.10
A29: Blackwell Ultra B300 (HGX) | B29: =I14 -> 451.9774 | C29: =I15 -> 501.5674 | D29: =I16 -> 534.04539 | E29: =L14 -> 311.70855 | F29: =L15 -> 385.82108 | G29: =L16 -> 485.49581 | H29: =TEXT(J14,"0.00")&" / "&TEXT(J15,"0.00")&" / "&TEXT(J16,"0.00") -> 1.45 / 1.30 / 1.10
A30: GB300 NVL72 | B30: =I17 -> 452.7163 | C30: =I18 -> 491.16584 | D30: =I19 -> 519.48052 | E30: =L17 -> 335.34541 | F30: =L18 -> 409.30486 | G30: =L19 -> 472.25502 | H30: =TEXT(J17,"0.00")&" / "&TEXT(J18,"0.00")&" / "&TEXT(J19,"0.00") -> 1.35 / 1.20 / 1.10
A31: Vera Rubin NVL72 (VR200; 'NVL144' dies) | B31: =I20 -> 279.50311 | C31: =I21 -> 320.42724 | D31: =I22 -> 360.90226 | E31: =L20 -> 207.03934 | F31: =L21 -> 267.0227 | G31: =L22 -> 328.09296 | H31: =TEXT(J20,"0.00")&" / "&TEXT(J21,"0.00")&" / "&TEXT(J22,"0.00") -> 1.35 / 1.20 / 1.10
A33: Notes: (1) Spec power is max/nameplate; actual average draw is typically lower, so operators that provision on measured draw can fit more GPUs per MW (that is the High case). (2) Overhead covers scale-out fabric, storage, CPU/management nodes outside the GPU unit; in-rack NVLink switches are already inside NVL72 rack power. (3) PUE converts IT MW to gross/facility MW; Nebius does not disclose IT vs gross for its MW KPIs (see Nebius checks).

Sheet CapexPerMW
A1: Capex per MW by generation – split GPU/server, networking+storage, DC shell+power (owned) vs colocation (lease instead of shell). US$ millions per IT MW unless noted. Blue = input.
A2: Density uses the Base GPUs/IT-MW from GPUsPerMW for all three price cases (isolates price uncertainty). Owned total = GPU/server + network/storage + DC shell/power. Colo capex = GPU/server + network/storage + Nebius in-hall fit-out; lease shown separately and as PV (lease-equivalent capex).
A3: Global inputs: | B3: Colo lease discount rate | C3: 0.08 | D3: Lease term (yrs) | E3: 10 | F3: Annuity factor | G3: =(1-(1+C3)^-E3)/C3 -> 6.7100814
A5: Generation | B5: Scenario | C5: GPUs/IT MW (base, link) | D5: Unit price $M (server/rack, input) | E5: Network+storage+other $M per unit (input) | F5: GPUs per unit | G5: All-in $k/GPU | H5: GPU/server $M/MW | I5: Network+storage $M/MW | J5: DC shell+power $M/MW IT (owned, input) | K5: Owned total $M/IT MW | L5: Owned total $M/gross MW (base PUE) | M5: Implied $B per GW (IT) | N5: Colo in-hall fit-out $M/MW (input) | O5: Colo capex $M/IT MW | P5: Colo lease $/kW-mo (input) | Q5: Lease $M/MW-yr | R5: PV lease $M/MW | S5: Colo lease-equivalent $M/IT MW | T5: Tag | U5: Price / DC-cost basis
A6: Hopper H100/H200 | B6: Low | C6: =GPUsPerMW!I6 -> 713.01248 | D6: 0.19 | E6: 0.05 | F6: 8 | G6: =(D6+E6)/F6*1000 -> 30 | H6: =C6*D6/F6 -> 16.934046 | I6: =C6*E6/F6 -> 4.456328 | J6: 7 | K6: =H6+I6+J6 -> 28.390374 | L6: =K6/GPUsPerMW!J6 -> 21.838749 | M6: =K6 -> 28.390374 | N6: 0.5 | O6: =H6+I6+N6 -> 21.890374 | P6: 150 | Q6: =P6*1000*12/1000000 -> 1.8 | R6: =Q6*$G$3 -> 12.078147 | S6: =O6+R6 -> 33.968521 | T6: Estimated (prices = third-party Reported/Estimated; see basis) | U6: Server $190k (SemiAnalysis H100 2025, S6); +$50k net/storage; DC $7M/MW (IREN Horizon-type brownfield $6-7M/MW IT, S26); lease $150/kW-mo
A7: Hopper H100/H200 | B7: Base | C7: =GPUsPerMW!I6 -> 713.01248 | D7: 0.23 | E7: 0.06 | F7: 8 | G7: =(D7+E7)/F7*1000 -> 36.25 | H7: =C7*D7/F7 -> 20.499109 | I7: =C7*E7/F7 -> 5.3475936 | J7: 10 | K7: =H7+I7+J7 -> 35.846702 | L7: =K7/GPUsPerMW!J6 -> 27.574386 | M7: =K7 -> 35.846702 | N7: 1 | O7: =H7+I7+N7 -> 26.846702 | P7: 175 | Q7: =P7*1000*12/1000000 -> 2.1 | R7: =Q7*$G$3 -> 14.091171 | S7: =O7+R7 -> 40.937873 | T7: Estimated (prices = third-party Reported/Estimated; see basis) | U7: Server $230k (Estimated: between H100 $190k and higher-HBM H200; no primary H200 price found – low confidence); +$60k net/storage (=SemiAnalysis $250k all-in less $190k server, S6); DC $10M/MW air-cooled (Estimated between JLL $11.3M shell-core and IREN $6-7M, S12/S26); lease $175 (S13)
A8: Hopper H100/H200 | B8: High | C8: =GPUsPerMW!I6 -> 713.01248 | D8: 0.28 | E8: 0.08 | F8: 8 | G8: =(D8+E8)/F8*1000 -> 45 | H8: =C8*D8/F8 -> 24.955437 | I8: =C8*E8/F8 -> 7.1301248 | J8: 14 | K8: =H8+I8+J8 -> 46.085561 | L8: =K8/GPUsPerMW!J6 -> 35.450432 | M8: =K8 -> 46.085561 | N8: 2 | O8: =H8+I8+N8 -> 34.085561 | P8: 205 | Q8: =P8*1000*12/1000000 -> 2.46 | R8: =Q8*$G$3 -> 16.5068 | S8: =O8+R8 -> 50.592362 | T8: Estimated (prices = third-party Reported/Estimated; see basis) | U8: Server $280k (Estimated, 2024-vintage H200 pricing; low confidence); +$80k; DC $14M/MW; lease $205 (S13)
A9: Blackwell B200 (HGX) | B9: Low | C9: =GPUsPerMW!I9 -> 508.58233 | D9: 0.36 | E9: 0.065 | F9: 8 | G9: =(D9+E9)/F9*1000 -> 53.125 | H9: =C9*D9/F9 -> 22.886205 | I9: =C9*E9/F9 -> 4.1322314 | J9: 7 | K9: =H9+I9+J9 -> 34.018436 | L9: =K9/GPUsPerMW!J9 -> 26.168028 | M9: =K9 -> 34.018436 | N9: 0.5 | O9: =H9+I9+N9 -> 27.518436 | P9: 150 | Q9: =P9*1000*12/1000000 -> 1.8 | R9: =Q9*$G$3 -> 12.078147 | S9: =O9+R9 -> 39.596583 | T9: Estimated (prices = third-party Reported/Estimated; see basis) | U9: Server $360k (low end S10); net $65k (Estimated: H100 $60k scaled for 400/800G); DC $7M
A10: Blackwell B200 (HGX) | B10: Base | C10: =GPUsPerMW!I9 -> 508.58233 | D10: 0.43 | E10: 0.08 | F10: 8 | G10: =(D10+E10)/F10*1000 -> 63.75 | H10: =C10*D10/F10 -> 27.3363 | I10: =C10*E10/F10 -> 5.0858233 | J10: 10 | K10: =H10+I10+J10 -> 42.422123 | L10: =K10/GPUsPerMW!J9 -> 32.632403 | M10: =K10 -> 42.422123 | N10: 1 | O10: =H10+I10+N10 -> 33.422123 | P10: 175 | Q10: =P10*1000*12/1000000 -> 2.1 | R10: =Q10*$G$3 -> 14.091171 | S10: =O10+R10 -> 47.513294 | T10: Estimated (prices = third-party Reported/Estimated; see basis) | U10: Server $430k (typical $420-500k, S10); net $80k (Estimated); DC $10M/MW air (Estimated)
A11: Blackwell B200 (HGX) | B11: High | C11: =GPUsPerMW!I9 -> 508.58233 | D11: 0.5 | E11: 0.11 | F11: 8 | G11: =(D11+E11)/F11*1000 -> 76.25 | H11: =C11*D11/F11 -> 31.786395 | I11: =C11*E11/F11 -> 6.993007 | J11: 14 | K11: =H11+I11+J11 -> 52.779402 | L11: =K11/GPUsPerMW!J9 -> 40.59954 | M11: =K11 -> 52.779402 | N11: 2 | O11: =H11+I11+N11 -> 40.779402 | P11: 205 | Q11: =P11*1000*12/1000000 -> 2.46 | R11: =Q11*$G$3 -> 16.5068 | S11: =O11+R11 -> 57.286203 | T11: Estimated (prices = third-party Reported/Estimated; see basis) | U11: Server $500k (S10); net $110k; DC $14M
A12: GB200 NVL72 | B12: Low | C12: =GPUsPerMW!I12 -> 538.31776 | D12: 2.8 | E12: 0.6 | F12: 72 | G12: =(D12+E12)/F12*1000 -> 47.222222 | H12: =C12*D12/F12 -> 20.934579 | I12: =C12*E12/F12 -> 4.4859813 | J12: 8 | K12: =H12+I12+J12 -> 33.420561 | L12: =K12/GPUsPerMW!J12 -> 27.850467 | M12: =K12 -> 33.420561 | N12: 0.5 | O12: =H12+I12+N12 -> 25.920561 | P12: 150 | Q12: =P12*1000*12/1000000 -> 1.8 | R12: =Q12*$G$3 -> 12.078147 | S12: =O12+R12 -> 37.998707 | T12: Estimated (prices = third-party Reported/Estimated; see basis) | U12: Rack $2.8M (Tom's low, S8); net/storage $0.6M; DC $8M liquid (IREN-type, S26 +liquid)
A13: GB200 NVL72 | B13: Base | C13: =GPUsPerMW!I12 -> 538.31776 | D13: 3.1 | E13: 0.8 | F13: 72 | G13: =(D13+E13)/F13*1000 -> 54.166667 | H13: =C13*D13/F13 -> 23.17757 | I13: =C13*E13/F13 -> 5.9813084 | J13: 12.5 | K13: =H13+I13+J13 -> 41.658879 | L13: =K13/GPUsPerMW!J12 -> 34.715732 | M13: =K13 -> 41.658879 | N13: 1 | O13: =H13+I13+N13 -> 30.158879 | P13: 175 | Q13: =P13*1000*12/1000000 -> 2.1 | R13: =Q13*$G$3 -> 14.091171 | S13: =O13+R13 -> 44.250049 | T13: Estimated (prices = third-party Reported/Estimated; see basis) | U13: Rack $3.1M, all-in $3.9M (SemiAnalysis, S6); DC $12.5M/MW (Crusoe Abilene $15B/1.2GW, S31; ≈JLL $11.3M +10% liquid, S12)
A14: GB200 NVL72 | B14: High | C14: =GPUsPerMW!I12 -> 538.31776 | D14: 3.4 | E14: 1 | F14: 72 | G14: =(D14+E14)/F14*1000 -> 61.111111 | H14: =C14*D14/F14 -> 25.420561 | I14: =C14*E14/F14 -> 7.4766355 | J14: 17.6 | K14: =H14+I14+J14 -> 50.497196 | L14: =K14/GPUsPerMW!J12 -> 42.080997 | M14: =K14 -> 50.497196 | N14: 2 | O14: =H14+I14+N14 -> 34.897196 | P14: 205 | Q14: =P14*1000*12/1000000 -> 2.46 | R14: =Q14*$G$3 -> 16.5068 | S14: =O14+R14 -> 51.403997 | T14: Estimated (prices = third-party Reported/Estimated; see basis) | U14: Rack $3.4M (Tom's high, S8); net $1.0M; DC $17.6M (Cushman all-in avg excl. GPUs, S11)
A15: Blackwell Ultra B300 (HGX) | B15: Low | C15: =GPUsPerMW!I15 -> 501.5674 | D15: 0.42 | E15: 0.07 | F15: 8 | G15: =(D15+E15)/F15*1000 -> 61.25 | H15: =C15*D15/F15 -> 26.332288 | I15: =C15*E15/F15 -> 4.3887147 | J15: 7 | K15: =H15+I15+J15 -> 37.721003 | L15: =K15/GPUsPerMW!J15 -> 29.016156 | M15: =K15 -> 37.721003 | N15: 0.5 | O15: =H15+I15+N15 -> 31.221003 | P15: 150 | Q15: =P15*1000*12/1000000 -> 1.8 | R15: =Q15*$G$3 -> 12.078147 | S15: =O15+R15 -> 43.29915 | T15: Estimated (prices = third-party Reported/Estimated; see basis) | U15: Server $420k (Supermicro listed config, S10); net $70k; DC $7M
A16: Blackwell Ultra B300 (HGX) | B16: Base | C16: =GPUsPerMW!I15 -> 501.5674 | D16: 0.55 | E16: 0.09 | F16: 8 | G16: =(D16+E16)/F16*1000 -> 80 | H16: =C16*D16/F16 -> 34.482759 | I16: =C16*E16/F16 -> 5.6426332 | J16: 10 | K16: =H16+I16+J16 -> 50.125392 | L16: =K16/GPUsPerMW!J15 -> 38.557994 | M16: =K16 -> 50.125392 | N16: 1 | O16: =H16+I16+N16 -> 41.125392 | P16: 175 | Q16: =P16*1000*12/1000000 -> 2.1 | R16: =Q16*$G$3 -> 14.091171 | S16: =O16+R16 -> 55.216563 | T16: Estimated (prices = third-party Reported/Estimated; see basis) | U16: Server $550k (planning range $550-650k, S10); net $90k (Estimated, 800G CX-8); DC $10M
A17: Blackwell Ultra B300 (HGX) | B17: High | C17: =GPUsPerMW!I15 -> 501.5674 | D17: 0.65 | E17: 0.12 | F17: 8 | G17: =(D17+E17)/F17*1000 -> 96.25 | H17: =C17*D17/F17 -> 40.752351 | I17: =C17*E17/F17 -> 7.523511 | J17: 14 | K17: =H17+I17+J17 -> 62.275862 | L17: =K17/GPUsPerMW!J15 -> 47.904509 | M17: =K17 -> 62.275862 | N17: 2 | O17: =H17+I17+N17 -> 50.275862 | P17: 205 | Q17: =P17*1000*12/1000000 -> 2.46 | R17: =Q17*$G$3 -> 16.5068 | S17: =O17+R17 -> 66.782662 | T17: Estimated (prices = third-party Reported/Estimated; see basis) | U17: Server $650k (S10); net $120k; DC $14M
A18: GB300 NVL72 | B18: Low | C18: =GPUsPerMW!I18 -> 491.16584 | D18: ='GB300 rack price'!C21 -> 4 | E18: ='GB300 rack price'!C25 -> 0.6 | F18: 72 | G18: =(D18+E18)/F18*1000 -> 63.888889 | H18: =C18*D18/F18 -> 27.286991 | I18: =C18*E18/F18 -> 4.0930486 | J18: 8 | K18: =H18+I18+J18 -> 39.38004 | L18: =K18/GPUsPerMW!J18 -> 32.8167 | M18: =K18 -> 39.38004 | N18: 0.5 | O18: =H18+I18+N18 -> 31.88004 | P18: 150 | Q18: =P18*1000*12/1000000 -> 1.8 | R18: =Q18*$G$3 -> 12.078147 | S18: =O18+R18 -> 43.958186 | T18: Estimated (prices = third-party Reported/Estimated; see basis) | U18: LINKED to 'GB300 rack price' sheet. Rack $4.0M (Morgan Stanley BOM ~$4.0M S35; Loop $3.7-4.0M S37); net+storage+install $0.6M; DC $8M
A19: GB300 NVL72 | B19: Base | C19: =GPUsPerMW!I18 -> 491.16584 | D19: ='GB300 rack price'!D21 -> 4.5 | E19: ='GB300 rack price'!D25 -> 0.9 | F19: 72 | G19: =(D19+E19)/F19*1000 -> 75 | H19: =C19*D19/F19 -> 30.697865 | I19: =C19*E19/F19 -> 6.139573 | J19: 12.5 | K19: =H19+I19+J19 -> 49.337438 | L19: =K19/GPUsPerMW!J18 -> 41.114531 | M19: =K19 -> 49.337438 | N19: 1 | O19: =H19+I19+N19 -> 37.837438 | P19: 175 | Q19: =P19*1000*12/1000000 -> 2.1 | R19: =Q19*$G$3 -> 14.091171 | S19: =O19+R19 -> 51.928609 | T19: Estimated (prices = third-party Reported/Estimated; see basis) | U19: LINKED. Rack $4.5M (between hyperscale-volume $4.0-4.3M S35/S36 and small-order PO ~$5.0M S9; IREN all-in ~$70k/GPU incl IB S39); +$0.9M ≈ SemiAnalysis GB200 $3.9M-$3.1M = $0.8M (S6) scaled for 800G CX-8; DC $12.5M
A20: GB300 NVL72 | B20: High | C20: =GPUsPerMW!I18 -> 491.16584 | D20: ='GB300 rack price'!E21 -> 5 | E20: ='GB300 rack price'!E25 -> 1.2 | F20: 72 | G20: =(D20+E20)/F20*1000 -> 86.111111 | H20: =C20*D20/F20 -> 34.108739 | I20: =C20*E20/F20 -> 8.1860973 | J20: 17.6 | K20: =H20+I20+J20 -> 59.894836 | L20: =K20/GPUsPerMW!J18 -> 49.912363 | M20: =K20 -> 59.894836 | N20: 2 | O20: =H20+I20+N20 -> 44.294836 | P20: 205 | Q20: =P20*1000*12/1000000 -> 2.46 | R20: =Q20*$G$3 -> 16.5068 | S20: =O20+R20 -> 60.801636 | T20: Estimated (prices = third-party Reported/Estimated; see basis) | U20: LINKED. Rack $5.0M (Data Gravity small-order POs, S9); +$1.2M; DC $17.6M (S11). Stress (not used): Tom's $6-6.5M inference config (S8)
A21: Vera Rubin NVL72 (VR200; 'NVL144' dies) | B21: Low | C21: =GPUsPerMW!I21 -> 320.42724 | D21: 6.7 | E21: 0.9 | F21: 72 | G21: =(D21+E21)/F21*1000 -> 105.55556 | H21: =C21*D21/F21 -> 29.817534 | I21: =C21*E21/F21 -> 4.0053405 | J21: 8 | K21: =H21+I21+J21 -> 41.822875 | L21: =K21/GPUsPerMW!J21 -> 34.852396 | M21: =K21 -> 41.822875 | N21: 0.5 | O21: =H21+I21+N21 -> 34.322875 | P21: 150 | Q21: =P21*1000*12/1000000 -> 1.8 | R21: =Q21*$G$3 -> 12.078147 | S21: =O21+R21 -> 46.401021 | T21: Estimated (prices = third-party Reported/Estimated; see basis) | U21: v2: Rack $6.7M (MS BOM if hyperscaler buys SOCAMM direct, S35; Tom's $5-7M S8, Wolfe $5-6M S36 are older/lower); +$0.9M; DC $8M
A22: Vera Rubin NVL72 (VR200; 'NVL144' dies) | B22: Base | C22: =GPUsPerMW!I21 -> 320.42724 | D22: 7.8 | E22: 1.2 | F22: 72 | G22: =(D22+E22)/F22*1000 -> 125 | H22: =C22*D22/F22 -> 34.712951 | I22: =C22*E22/F22 -> 5.3404539 | J22: 12.5 | K22: =H22+I22+J22 -> 52.553405 | L22: =K22/GPUsPerMW!J21 -> 43.794504 | M22: =K22 -> 52.553405 | N22: 1 | O22: =H22+I22+N22 -> 41.053405 | P22: 175 | Q22: =P22*1000*12/1000000 -> 2.1 | R22: =Q22*$G$3 -> 14.091171 | S22: =O22+R22 -> 55.144575 | T22: Estimated (prices = third-party Reported/Estimated; see basis) | U22: v2: Rack $7.8M (Morgan Stanley ODM BOM May-26, S35; was $6.0M in v1); +$1.2M (v1 $0.8M too low: CX-9 1.6T doubles per-GPU scale-out bandwidth vs GB300's $0.9M; in-rack NAND offsets only storage); DC $12.5M. Colo capex ≈ team base $41M
A23: Vera Rubin NVL72 (VR200; 'NVL144' dies) | B23: High | C23: =GPUsPerMW!I21 -> 320.42724 | D23: 9.1 | E23: 1.5 | F23: 72 | G23: =(D23+E23)/F23*1000 -> 147.22222 | H23: =C23*D23/F23 -> 40.498442 | I23: =C23*E23/F23 -> 6.6755674 | J23: 17.6 | K23: =H23+I23+J23 -> 64.77401 | L23: =K23/GPUsPerMW!J21 -> 53.978341 | M23: =K23 -> 64.77401 | N23: 2 | O23: =H23+I23+N23 -> 49.17401 | P23: 205 | Q23: =P23*1000*12/1000000 -> 2.46 | R23: =Q23*$G$3 -> 16.5068 | S23: =O23+R23 -> 65.68081 | T23: Estimated (prices = third-party Reported/Estimated; see basis) | U23: v2: Rack $9.1M (Bernstein, HBM4 $53/GB, S38); +$1.5M; DC $17.6M. Colo capex ≈ team bear $48.5M
A25: Summary – Owned all-in capex $M per IT MW (Low / Base / High) and colo capex (excl. lease)
A26: Generation | B26: Owned Low | C26: Owned Base | D26: Owned High | E26: Owned Base $M/gross MW | F26: Colo capex Base | G26: Colo lease-equiv Base | H26: GPU+net share of owned Base
A27: Hopper H100/H200 | B27: =K6 -> 28.390374 | C27: =K7 -> 35.846702 | D27: =K8 -> 46.085561 | E27: =L7 -> 27.574386 | F27: =O7 -> 26.846702 | G27: =S7 -> 40.937873 | H27: =(H7+I7)/K7 -> 0.72103431
A28: Blackwell B200 (HGX) | B28: =K9 -> 34.018436 | C28: =K10 -> 42.422123 | D28: =K11 -> 52.779402 | E28: =L10 -> 32.632403 | F28: =O10 -> 33.422123 | G28: =S10 -> 47.513294 | H28: =(H10+I10)/K10 -> 0.76427394
A29: GB200 NVL72 | B29: =K12 -> 33.420561 | C29: =K13 -> 41.658879 | D29: =K14 -> 50.497196 | E29: =L13 -> 34.715732 | F29: =O13 -> 30.158879 | G29: =S13 -> 44.250049 | H29: =(H13+I13)/K13 -> 0.69994391
A30: Blackwell Ultra B300 (HGX) | B30: =K15 -> 37.721003 | C30: =K16 -> 50.125392 | D30: =K17 -> 62.275862 | E30: =L16 -> 38.557994 | F30: =O16 -> 41.125392 | G30: =S16 -> 55.216563 | H30: =(H16+I16)/K16 -> 0.80050031
A31: GB300 NVL72 | B31: =K18 -> 39.38004 | C31: =K19 -> 49.337438 | D31: =K20 -> 59.894836 | E31: =L19 -> 41.114531 | F31: =O19 -> 37.837438 | G31: =S19 -> 51.928609 | H31: =(H19+I19)/K19 -> 0.7466427
A32: Vera Rubin NVL72 (VR200; 'NVL144' dies) | B32: =K21 -> 41.822875 | C32: =K22 -> 52.553405 | D32: =K23 -> 64.77401 | E32: =L22 -> 43.794504 | F32: =O22 -> 41.053405 | G32: =S22 -> 55.144575 | H32: =(H22+I22)/K22 -> 0.76214671
A34: Cross-checks: Jensen Huang $50-60B per GW all-in (S34) ≈ $50-60M/MW; Bernstein $35B/GW (S34); Barclays 65-70% compute+networking (S34) vs our GPU+net share column; IREN $5.8B GPUs+ancillary / 200 MW IT = $29M/MW (Peers). Basis of external $/GW (IT vs gross) is generally NOT stated.

Sheet GB300 rack price
A1: GB300 NVL72 rack price – sourced input (v2, Oct 4 2026). Rack price INCLUDES 18 compute trays (72 B300 + 36 Grace, ConnectX-8 NICs) and 9 in-rack NVLink switch trays + in-rack liquid cooling (S35/S46/S9). EXCLUDES scale-out fabric (leaf/spine switches, optics), front-end/storage network, storage, install/integration, DC. Blue = input.
A3: # | B3: Source | C3: Date | D3: Price $M / rack | E3: Per GPU $k | F3: What's included | G3: Buyer/volume | H3: Tag | I3: URL / ID
A4: 1 | B4: Loop Capital (Apple order ~$1B / ~250 systems) | C4: 2025-03-24 | D4: 3.85 | E4: =D4/72*1000 -> 53.472222 | F4: System (Dell/SMCI), range $3.7-4.0M; scope n/s | G4: Large (Apple) | H4: Reported (sell-side via press) | I4: S37
A5: 2 | B5: Morgan Stanley BOM (Howard Kao) | C5: 2026-05-21 | D5: 4 | E5: =D5/72*1000 -> 55.555556 | F5: ODM rack price, in-rack NVLink + cooling; no scale-out | G5: ODM sell-in | H5: Reported (secondary) | I5: S35
A6: 3 | B6: Wolfe Research supply-chain checks | C6: 2026-01-30 | D6: 4.3 | E6: =D6/72*1000 -> 59.722222 | F6: 'Reported prices' per rack | G6: n/s | H6: Reported (sell-side via press) | I6: S36
A7: 4 | B7: Data Gravity purchase orders | C7: 2026-08-31 | D7: 4.97 | E7: =D7/72*1000 -> 69.027778 | F7: EXW rack, no CDU ('just under $5.0M'); +$32k with CDU; deployed ~$5.7M excl core switching, storage, DC | G7: Small orders | H7: Reported (third-party) | I7: S9
A8: 5 | B8: Tom's Hardware source (inference-optimized config) | C8: 2026-03-24 | D8: 6.25 | E8: =D8/72*1000 -> 86.805556 | F8: Range $6-6.5M; config/warranty differ; many online quotes = ODM price w/o warranty | G8: n/s | H8: Reported (press) | I8: S8
A9: 6 | B9: IREN Aug-2025 order: 2.4k B300+GB300 for ~$168M | C9: 2025-08-28 | D9: =168/2400*72 -> 5.04 | E9: =D9/72*1000 -> 70 | F9: ALL-IN incl servers, InfiniBand, cabling, software (blended HGX B300 + GB300) | G9: Small (2.4k GPUs) | H9: Derived (company $ & count) | I9: S39
A10: 7 | B10: IREN-Dell Microsoft GB300 $5.8B / 76k GPUs | C10: 2025-11-03 | D10: =5800/76000*72 -> 5.4947368 | E10: =D10/72*1000 -> 76.315789 | F10: ALL-IN 'GPUs and ancillary'; GPU count from secondary site | G10: Large (Dell) | H10: Derived (count unverified) | I10: S25/S42
A11: 8 | B11: GB200 ref: SemiAnalysis hyperscaler rack / all-in | C11: 2025-08-20 | D11: 3.1 | E11: =D11/72*1000 -> 43.055556 | F11: Rack $3.1M; all-in incl networking, storage, other $3.9M (+$0.8M, +26%) | G11: Hyperscaler | H11: Reported (third-party) | I11: S6
A12: 9 | B12: GB200 ref: Wolfe / Tom's | C12: 2026 | D12: 3 | E12: =D12/72*1000 -> 41.666667 | F12: Wolfe ~$3.0M; Tom's $2.8-3.4M | G12: n/s | H12: Reported (press) | I12: S36/S8
A19: Selected inputs ($M)
A20: Item | B20: Unit | C20: Low | D20: Base | E20: High | F20: Stress | G20: Basis
A21: GB300 NVL72 rack price | B21: $M/rack | C21: 4 | D21: 4.5 | E21: 5 | F21: 6.25 | G21: Low = MS BOM / Loop (hyperscale-type volume); Base = midpoint of volume ($4.0-4.3M) and small-order POs ($5.0M) – Nebius buys at >100k-GPU scale (S43) but via OEM/ODM in a memory-inflation year; High = Data Gravity POs; Stress = Tom's
A22: Racks per IT MW (base density, link) | B22: racks | C22: =GPUsPerMW!I18/72 -> 6.8217477 | D22: =GPUsPerMW!I18/72 -> 6.8217477 | E22: =GPUsPerMW!I18/72 -> 6.8217477 | F22: =GPUsPerMW!I18/72 -> 6.8217477 | G22: 491 GPUs/IT MW (137 kW + 7%)
A23: Compute $M/IT MW | B23: $M/MW | C23: =C21*C22 -> 27.286991 | D23: =D21*D22 -> 30.697865 | E23: =E21*E22 -> 34.108739 | F23: =F21*F22 -> 42.635923 | G23: Derived
A24: memo: scale-out fabric only $k/GPU (2-tier 800G) | B24: $k/GPU | C24: 1.6 | D24: 2.5 | E24: 4 | F24: 4 | G24: Hedgehog Spectrum-X 1,024 GPUs $1.6-2.2k (S45); larger 3-tier clusters + optics higher (Estimated)
A25: Network+storage+install/other $M/rack | B25: $M/rack | C25: 0.6 | D25: 0.9 | E25: 1.2 | F25: 1.2 | G25: Bucket = scale-out + front-end + storage + install/integration. SemiAnalysis GB200 all-in +$0.8M/rack (S6); Data Gravity +$0.7M deploy (S9) before core switching/storage; GB300 800G CX-8. NICs + NVLink already in rack price
A26: Network etc. $M/IT MW | B26: $M/MW | C26: =C25*C22 -> 4.0930486 | D26: =D25*D22 -> 6.139573 | E26: =E25*E22 -> 8.1860973 | F26: =F25*F22 -> 8.1860973 | G26: Derived ($6.1M base unchanged)
A27: Compute + network $M/IT MW | B27: $M/MW | C27: =C23+C26 -> 31.38004 | D27: =D23+D26 -> 36.837438 | E27: =E23+E26 -> 42.294836 | F27: =F23+F26 -> 50.822021 | G27: Compare to cutoff
A28: Colo fit-out $M/IT MW | B28: $M/MW | C28: 0.5 | D28: 1 | E28: 2 | F28: 2 | G28: as CapexPerMW
A29: Leased capex (no shell) $M/IT MW | B29: $M/MW | C29: =C27+C28 -> 31.88004 | D29: =D27+D28 -> 37.837438 | E29: =E27+E28 -> 44.294836 | F29: =F27+F28 -> 52.822021 | G29: Equals CapexPerMW colo capex
A30: IT-reading cutoff (team) | B30: $M/MW | C30: 33 | D30: 33 | E30: 33 | F30: 33 | G30: Team breakeven for IT reading of $20-25M ACV/MW & 22-mo payback
A31: Headroom vs cutoff (+ = IT reading works) | B31: $M/MW | C31: =C30-C27 -> 1.6199604 | D31: =D30-D27 -> -3.8374378 | E31: =E30-E27 -> -9.2948359 | F31: =F30-F27 -> -17.822021 | G31: Derived
A32: Breakeven rack price at this network cost | B32: $M/rack | C32: =C30/C22-C25 -> 4.23747 | D32: =D30/D22-D25 -> 3.93747 | E32: =E30/E22-E25 -> 3.63747 | F32: =F30/F22-F25 -> 3.63747 | G32: Derived
A33: Breakeven GPUs/IT MW at this rack+network | B33: GPU/MW | C33: =C30/(C21+C25)*72 -> 516.52174 | D33: =D30/(D21+D25)*72 -> 440 | E33: =E30/(E21+E25)*72 -> 383.22581 | F33: =F30/(F21+F25)*72 -> 318.92617 | G33: Derived – IREN's $5.8B/200 MW IT/76k = 380/IT MW passes
A35: Density sensitivity – compute+network $M/IT MW at base prices
A36: GPUs/IT MW | B36: Racks/MW | C36: Compute+net $M/MW | D36: vs $33M
A37: 380 | B37: =A37/72 -> 5.2777778 | C37: =B37*($D$21+$D$25) -> 28.5 | D37: =$D$30-C37 -> 4.5
A38: 453 | B38: =A38/72 -> 6.2916667 | C38: =B38*($D$21+$D$25) -> 33.975 | D38: =$D$30-C38 -> -0.975
A39: 491 | B39: =A39/72 -> 6.8194444 | C39: =B39*($D$21+$D$25) -> 36.825 | D39: =$D$30-C39 -> -3.825
A40: 519 | B40: =A40/72 -> 7.2083333 | C40: =B40*($D$21+$D$25) -> 38.925 | D40: =$D$30-C40 -> -5.925
A42: Peer cross-checks: IREN-Dell $5.8B / 200 MW IT = $29.0M/IT MW all-in GPU+ancillary (S25) – below the cutoff but at lower density (~380/MW if 76k GPUs; at 491/MW it would imply ~$4.25M per rack incl network). IREN all-in ~$70k/GPU on small 2025 order incl InfiniBand (S39) = $5.0M per 72 GPUs all-in → $34.4M/IT MW at 491/MW. Rubin cross-check (GPU Market team): MS VR $7.8M ÷ 1.95 = $4.0M; Bernstein $9.1M ÷ 1.68 = $5.4M mixes Bernstein's price with MS's ratio (ratio is internal to MS's BOM) – treat as upper bound only.

Sheet Nebius checks
A1: Nebius-implied cross-checks (inputs blue = Reported from disclosures/sources; formulas = Derived)
A3: Check | B3: Input A | C3: Value A | D3: Input B | E3: Value B | F3: Derived | G3: Unit | H3: Model comparison | I3: Model value | J3: Tag | K3: Interpretation | L3: Source
A4: Modi'in B200 density | B4: GPUs | C4: 4000 | D4: MW | E4: 8 | F4: =C4/E4 -> 500 | G4: GPUs/MW | H4: B200 base GPUs/IT MW | I4: =GPUsPerMW!I9 -> 508.58233 | J4: Derived | K4: 500/MW ≈ model 508/IT-MW (vs ~391/gross MW) → the 8 MW reads as IT/critical load, or near-IT | L4: S18
A5: Longcross B300 – phase 1 | B5: GPUs | C5: 4000 | D5: MW | E5: 16 | F5: =C5/E5 -> 250 | G5: GPUs/MW | H5: B300 base GPUs/IT MW | I5: =GPUsPerMW!I15 -> 501.5674 | J5: Derived | K5: 250/MW is ~half of model density → phase 1 did not fill the 16 MW | L5: S18
A6: Longcross B300 – ph1+ph2 on 16 MW | B6: GPUs | C6: 7000 | D6: MW | E6: 16 | F6: =C6/E6 -> 437.5 | G6: GPUs/MW | H6: B300 base GPUs/gross MW | I6: =GPUsPerMW!L15 -> 385.82108 | J6: Derived | K6: 438/MW sits between gross (386) and IT (502) model density | L6: S18
A7: Longcross B300 – ph1+ph2 on 19 MW | B7: GPUs | C7: 7000 | D7: MW | E7: 19 | F7: =C7/E7 -> 368.42105 | G7: GPUs/MW | H7: B300 base GPUs/gross MW | I7: =GPUsPerMW!L15 -> 385.82108 | J7: Derived | K7: 368/MW ≈ gross-MW basis | L7: S18
A8: Patmos KC full build (landlord claim) | B8: GPUs | C8: 35000 | D8: MW | E8: 40 | F8: =C8/E8 -> 875 | G8: GPUs/MW | H8: H200 HIGH-case GPUs/IT MW | I8: =GPUsPerMW!I7 -> 812.67777 | J8: Derived | K8: 875/MW is above even the high-case Hopper IT density (~813) → the landlord's marketing claim isn't physically consistent; don't use it | L8: S18
A9: YE2024 GPUs vs connected MW | B9: >20k GPUs (Estimated from target) | C9: 20000 | D9: MW connected YE24 | E9: 25 | F9: =C9/E9 -> 800 | G9: GPUs/MW | H9: H100/H200 base GPUs/IT MW | I9: =GPUsPerMW!I6 -> 713.01248 | J9: Derived | K9: ~800/MW is above base IT density (713) → GPU count likely includes GPUs not yet energized, or MW is understated | L9: S18
A10: End-Q1'25 GPUs vs est. MW | B10: GPUs (Reported ~38k) | C10: 38000 | D10: MW est. = 25 YE24 + 10 Keflavik (+0 KC live Apr-25) | E10: 35 | F10: =C10/E10 -> 1085.7143 | G10: GPUs/MW | H10: H100/H200 high GPUs/IT MW | I10: =GPUsPerMW!I7 -> 812.67777 | J10: Derived (MW Estimated) | K10: ~1,086/MW is physically implausible for Hopper → '38k' must include GPUs delivered or allocated but not yet powered. Don't back out MW from GPU counts | L10: S18
A11: YE2025 in-service servers+network per active MW | B11: Gross servers & network $M | C11: 3123.6 | D11: Active MW YE25 | E11: 170 | F11: =C11/E11 -> 18.374118 | G11: $M/MW | H11: Hopper base GPU+net $M/IT MW | I11: =CapexPerMW!H7+CapexPerMW!I7 -> 25.846702 | J11: Derived | K11: $18.4M/MW is below the model's ~$25.9M/IT MW for Hopper. Possible reasons: active MW is close to gross, GPUs were bought cheaply, or part of the active hardware sits in 'assets not yet in use' | L11: S16/S18
A12: YE2025 upper bound incl. assets not in use | B12: Servers+network + AnYU $M | C12: =3123.6+2417.4 -> 5541 | D12: Active MW YE25 | E12: 170 | F12: =C12/E12 -> 32.594118 | G12: $M/MW | H12: B200 base GPU+net $M/IT MW | I12: =CapexPerMW!H10+CapexPerMW!I10 -> 32.422123 | J12: Derived | K12: Upper bound. Assets not yet in use (AnYU) include prepayments and DC infrastructure for future MW, so this overstates $/active MW | L12: S16
A13: Q2'26 in-service servers+network per active MW | B13: Gross server & network equipment Jun-26 $M | C13: 5197.7 | D13: Active MW Q2'26 (team input) | E13: 183 | F13: =C13/E13 -> 28.402732 | G13: $M/MW | H13: GB300 base GPU+net $M/IT MW | I13: =CapexPerMW!H19+CapexPerMW!I19 -> 36.837438 | J13: Derived | K13: $28.4M/active MW: above Hopper model GPU+net (~$25.9M/IT MW @713/MW) and below GB300 base (~$36.8M) → consistent with active MW = IT and a Hopper-heavy in-service fleet plus a Blackwell tail (~25-30% Blackwell by MW at model prices). If active MW were gross (÷1.2 → 152 IT MW) it would be $34M/IT MW, i.e. a near-all-Blackwell fleet, which the GPU mix doesn't support. Caveat: vintage pricing and partially-energized MW | L13: S48
A14: 2026 capex guide / connected MW added – low | B14: Capex guide low $B | C14: 16 | D14: MW added (800-220) | E14: 580 | F14: =C14*1000/E14 -> 27.586207 | G14: $M/MW | H14: GB300 base owned $M/IT MW | I14: =CapexPerMW!K19 -> 49.337438 | J14: Derived | K14: $27.6M per connected MW added. Understated because GPUs for capacity connected late in 2026 are bought in 1H27 | L14: S14/S18
A15: 2026 capex guide / connected MW added – high | B15: Capex guide high $B | C15: 20 | D15: MW added (1000-220) | E15: 780 | F15: =C15*1000/E15 -> 25.641026 | G15: $M/MW | H15: — | J15: Derived | K15: $25.6M/MW; range across both ends ≈ $20.5-34.5M/MW (16/0.78 to 20/0.58) | L15: S14/S18
A16: DC build share of 2026 capex | B16: Capex mid $B | C16: 18 | D16: DC share | E16: 0.2 | F16: =C16*E16*1000/680 -> 5.2941176 | G16: $M/MW (on 680 MW mid added) | H16: DC shell base liquid $M/MW | I16: =CapexPerMW!J19 -> 12.5 | J16: Derived | K16: ~$5.3M/MW of DC capex per connected MW added. Well below $12.5M owned-build cost, which fits a colo-heavy 2026 (Vineland, Béthune, Israel and UK are leased) plus spend on land/power for 2027+ sites | L16: S14
A17: Payback-implied capex/MW (base) | B17: ACV $M/MW (Q2 deals mid) | C17: 22.5 | D17: Payback yrs (1y10m) | E17: =1+10/12 -> 1.8333333 | F17: =C17*E17*0.6 -> 24.75 | G17: $M/MW | H17: GB300 base GPU+net $M/IT MW | I17: =CapexPerMW!H19+CapexPerMW!I19 -> 36.837438 | J17: Estimated | K17: capex ≈ payback × ACV × contribution margin (60% assumed; AI-cloud adj. EBITDA 50%, S15) = ~$24.8M/MW; range 18.3 (20 × 0.5) to 32.1 (25 × 0.7). Sits below the GB300 GPU+net model → per-MW denominator likely gross/contracted MW and/or the payback excludes DC shell | L17: S15
A18: Microsoft ACV per MW (Vineland) | B18: TCV $B / 5 yrs | C18: 17.4 | D18: MW (Nebius 'up to 300') | E18: 300 | F18: =C18/5*1000/E18 -> 11.6 | G18: $M ACV/MW | H18: Nebius '2026 base' ACV/MW (Q2 letter) | I18: 12 | J18: Derived | K18: [RETIRED 10/9: gross-MW basis; use $14.49M per IT MW = $17.4B/5/240 IT MW, D] $11.6M/MW on 300 MW, close to the ~$12M '2026 base' ACV/MW in the Q2 letter. On ~240 MW IT it would be $14.5M/MW | L18: S15/S19
A19: Vineland: max facility supply (installed) | B19: Bloom installed MW | C19: 328 | D19: Grid MW (mechanical) | E19: 5 | F19: =C19+E19 -> 333 | G19: MW supply | H19: 300 MW as IT × base PUE 1.20 | I19: =300*1.2 -> 360 | J19: Derived | K19: 333 MW installed supply < 360 MW needed if 300 MW were IT at PUE 1.2 → 300 MW reads as facility/gross | L19: S20/S23
A20: Vineland: firm supply (guaranteed) | B20: Bloom guaranteed MW | C20: 250 | D20: Grid MW | E20: 5 | F20: =C20+E20 -> 255 | G20: MW supply | H20: Implied IT if 300 = gross, PUE 1.2-1.3 | I20: =300/1.25 -> 240 | J20: Estimated | K20: ~255 MW firm supply; implied IT ≈ 231-250 MW (300/1.3 to 300/1.2) | L20: S23
A21: Vineland: 150k GB300 claim vs power | B21: GPUs (secondary claim) | C21: 150000 | D21: GB300 base all-in IT kW/GPU | E21: =GPUsPerMW!H18 -> 2.0359722 | F21: =C21*E21/1000 -> 305.39583 | G21: MW IT needed | H21: × base PUE → gross MW | I21: =F21*GPUsPerMW!J18 -> 366.475 | J21: Derived | K21: Needs ~305 MW IT / ~366 MW gross, more than the 333 MW installed supply → the '>150k GB300' claim (S23, unverified) is probably overstated, or a mix with lower-power parts
A23: MW basis – what Nebius says
A24: Active MW: defined as 'power being consumed by installed, operational IT equipment' (Q1'26 letter, S17). Read literally, that is IT-equipment draw, so IT basis (Reported wording; Nebius never uses the terms 'IT load' or 'critical' explicitly).
A25: Connected MW: 'power connected into fully built and equipped data centers' (S17); Q2'25: includes active power plus power 'fully provisioned… can be activated immediately upon GPU installation'. The basis is ambiguous; it reads as facility/provisioned capacity (Estimated).
A26: Contracted MW: land + power commitments (S17), i.e. utility/grid or generation capacity, so gross basis (Estimated).
A27: Site MW (Vineland 300, Lappeenranta 310, Independence 1.2 GW, PA 1.2 GW, etc.) are never labelled IT or gross. AIB (50 MW critical IT / 65 MW utility, ratio 1.30) and IREN/Nscale (Monarch 6.5 GW IT / 8 GW gross, ratio 1.23) show the typical gap.
A28: Vineland verdict (Estimated, medium confidence): '300 MW' is most consistent with FACILITY/gross power, implying ~230-250 MW IT. Evidence: Nebius 'expandable up to a total of 300 MW' (no label, S19); nj.com 'draw about 300 MW of power' (S21); Bloom 328 MW installed (Nebius PR, S20) / ~250 MW guaranteed (S23) + 5 MW grid for mechanical load (S23). DataOne says fuel cells feed 'data halls and associated mechanical loads' (S22), so the fuel-cell output must cover IT + cooling, and 300 MW IT × PUE ≥1.2 = ≥360 MW exceeds the 333 MW installed. Counter-evidence: Measured AI claims '315 MW IT capacity' (secondary, no primary cite, S23); DataOne cites a 'maximum capacity of 350MW' (S22); Courier-Post says the Bloom plant is 'capable of 374 MW' (S21). The planning-board agendas (S24) give square footage only, no MW.

Sheet Peers
A1: Peer disclosures – GPUs per MW and $ per MW (inputs blue; Derived formulas)
A3: Peer | B3: Datapoint | C3: Input A | D3: Value A | E3: Input B | F3: Value B | G3: Derived | H3: Unit | I3: MW basis stated? | J3: Generation | K3: Tag | L3: Comment | M3: Source
A4: IREN | B4: Microsoft GB300 GPU+ancillary capex per IT MW | C4: Dell purchase $B | D4: 5.8 | E4: IT MW (Horizon 1-4) | F4: 200 | G4: =D4*1000/F4 -> 29 | H4: $M/MW IT | I4: IT (critical) | J4: GB300 NVL72 | K4: Derived | L4: $29M/MW IT is GPU+ancillary only. Below our GB300 base GPU+net of ~$40M/IT MW → either IREN provisions fewer GPUs per IT MW (~360-410/MW at $70-80k/GPU) or Dell pricing is ~$4M/rack all-in | M4: S25
A5: IREN | B5: Horizon 1 DC build (low) per IT MW | C5: Capex $M | D5: 300 | E5: IT MW | F5: 50 | G5: =D5/F5 -> 6 | H5: $M/MW IT | I5: IT | J5: DC shell (liquid) | K5: Derived | L5: $6.0-7.0M/MW IT ($4.0-4.7M on the 75 MW design figure). Texas brownfield with an existing substation, so a low-end anchor | M5: S26
A6: IREN | B6: Horizon 1 DC build (high) per IT MW | C6: Capex $M | D6: 350 | E6: IT MW | F6: 50 | G6: =D6/F6 -> 7 | H6: $M/MW IT | I6: IT | J6: DC shell (liquid) | K6: Derived | M6: S26
A7: IREN | B7: Microsoft ACV per IT MW | C7: TCV $B/5y | D7: 9.7 | E7: IT MW | F7: 200 | G7: =D7/5*1000/F7 -> 9.7 | H7: $M ACV/MW IT | I7: IT | J7: GB300 | K7: Derived | L7: $9.7M/MW IT vs Nebius MSFT $14.49M per IT MW (D; $11.6M on 300 MW gross retired 10/9) | M7: S25
A8: IREN | B8: New contracts revenue per IT MW (Reported) | C8: Rev $M/MW IT | D8: 20 | E8: Payback yrs | F8: 2 | G8: =D8*F8 -> 40 | H8: $M/MW (rev × payback; upper bound on GPU capex) | I8: IT | J8: Blackwell/GB300 | K8: Derived | L8: Upper bound. GPU capex = payback × (rev − direct costs), so it is < $40M/MW | M8: S27
A9: CoreWeave | B9: PP&E net per active MW (YE25) | C9: PP&E net $M | D9: 30557 | E9: Active MW | F9: 850 | G9: =D9/F9 -> 35.949412 | H9: $M/MW | I9: not stated | J9: Mixed H100-GB300 | K9: Derived | L9: Mostly leased DCs, so this is ≈ GPU+network on a net (depreciated) basis; includes CIP for future MW | M9: S28
A10: CoreWeave | B10: PP&E net per active MW (Q2'26) | C10: PP&E net $M | D10: 46736 | E10: Active MW | F10: 1500 | G10: =D10/F10 -> 31.157333 | H10: $M/MW | I10: not stated | J10: Mixed | K10: Derived | L10: $31.2M/MW | M10: S28
A11: CoreWeave | B11: 2026 capex guide mid / active MW added | C11: Capex mid $B | D11: 37 | E11: MW added (1850-850) | F11: 1000 | G11: =D11*1000/F11 -> 37 | H11: $M/MW added | I11: not stated | J11: GB300/VR | K11: Derived | L11: ~$37M per incremental active MW (the guide is from a secondary summary, so verify it) | M11: S29/S28
A12: Nscale | B12: GPUs per MW (portfolio) | C12: GPUs active+contracted | D12: 461000 | E12: MW active+contracted | F12: 1365 | G12: =D12/F12 -> 337.72894 | H12: GPUs/MW | I12: not stated | J12: GB300/VR mix | K12: Derived | L12: 338/MW. Between our GB300 gross (~409) and VR gross (~267) | M12: S30
A13: Nscale | B13: SIN02 Portugal – VR NVL72 | C13: GPUs | D13: 66000 | E13: MW | F13: 200 | G13: =D13/F13 -> 330 | H13: GPUs/MW | I13: not stated ('200 MW powered land') | J13: Vera Rubin NVL72 | K13: Derived | L13: 330/MW ≈ our VR base IT (320) → if 200 MW is gross, this implies higher density or a lower-power VR profile | M13: S30
A14: Nscale | B14: Monarch IT/gross ratio | C14: Gross GW | D14: 8 | E14: IT GW | F14: 6.5 | G14: =D14/F14 -> 1.2307692 | H14: gross/IT | I14: both | J14: — | K14: Derived | L14: 1.23 PUE-equivalent (includes behind-the-meter generation losses) | M14: S30
A15: AIB/Nebius | B15: SE US lease IT vs utility | C15: Utility MW | D15: 65 | E15: Critical IT MW | F15: 50 | G15: =D15/F15 -> 1.3 | H15: gross/IT | I15: both | J15: n/d | K15: Derived | L15: 1.30 ratio on a Nebius-contracted site | M15: S18
A16: Oracle/OpenAI | B16: Stargate Abilene GB200 | C16: GPUs | D16: 450000 | E16: MW | F16: 1200 | G16: =D16/F16 -> 375 | H16: GPUs/MW | I16: not stated | J16: GB200 NVL72 | K16: Derived | L16: 375/MW, below our GB200 gross base (~448) → 1.2 GW is likely utility/gross with headroom | M16: S32
A17: Crusoe | B17: Abilene JV $ per MW | C17: JV $B | D17: 15 | E17: MW | F17: 1200 | G17: =D17*1000/F17 -> 12.5 | H17: $M/MW | I17: not stated | J17: DC shell+power | K17: Derived | L17: $12.5M/MW DC (no GPUs) | M17: S31
A18: Crusoe | B18: Abilene phase 1 $ per MW | C18: Financing $B | D18: 3.4 | E18: MW (200+) | F18: 200 | G18: =D18*1000/F18 -> 17 | H18: $M/MW | I18: not stated | J18: DC shell+power | K18: Derived | L18: ≤$17M/MW ('200+ MW') | M18: S31
A19: Lambda | B19: Kansas City launch density | C19: GPUs (>) | D19: 10000 | E19: MW at launch | F19: 24 | G19: =D19/F19 -> 416.66667 | H19: GPUs/MW | I19: not stated | J19: B300 (Blackwell Ultra) | K19: Derived | L19: ≥417/MW. Between B300 gross (386) and IT (502) | M19: S33
A20: Supermicro | B20: VR NVL72 blueprint | C20: GPUs per SU | D20: 1152 | E20: MW envelope | F20: 5 | G20: =D20/F20 -> 230.4 | H20: GPUs/MW (envelope) | I20: envelope (gross-like) | J20: Vera Rubin NVL72 | K20: Derived | L20: 230/MW envelope; 16 racks × 227 kW = 3.63 MW IT → envelope/IT 1.38 | M20: S7
A21: NVIDIA (Huang) | B21: All-in $ per GW (low) | C21: $B per GW | D21: 50 | E21: — | F21: 1 | G21: =D21/F21 -> 50 | H21: $M/MW | I21: not stated | J21: Blackwell/Rubin | K21: Reported | L21: $50-60M/MW all-in | M21: S34
A22: NVIDIA (Huang) | B22: All-in $ per GW (high) | C22: $B per GW | D22: 60 | E22: — | F22: 1 | G22: =D22/F22 -> 60 | H22: $M/MW | I22: not stated | J22: Blackwell/Rubin | K22: Reported | M22: S34
A23: Bernstein | B23: All-in $ per GW | C23: $B per GW | D23: 35 | E23: GPU share | F23: 0.39 | G23: =D23*F23 -> 13.65 | H23: $B GPUs per GW | I23: not stated | J23: GB200/Rubin | K23: Derived | L23: GPUs ~$13.7B/GW; land+buildings ~10% | M23: S34
A24: Cushman & Wakefield | B24: Greenfield DC all-in excl. GPUs | C24: $M/MW avg | D24: 17.6 | E24: Range low/high | F24: 8.9-23.3 | G24: =D24 -> 17.6 | H24: $M/MW | I24: per MW (basis n/s) | J24: DC | K24: Reported | L24: +21% vs Q4-24 | M24: S11
A25: Colocation market | B25: Wholesale rent 10 MW+ | C25: $/kW-mo | D25: 165 | E25: 3-10 MW | F25: 175 | G25: =D25*12*1000/1000000 -> 1.98 | H25: $M/MW-yr | I25: per kW leased (IT) | J25: — | K25: Derived | L25: ≈$2.0-2.5M per MW-yr ($165-205) | M25: S13

Sheet Sources
A1: ID | B1: Description / datapoints used | C1: URL / path | D1: Tag
A2: S1 | B2: NVIDIA DGX H100/H200 User Guide – system power 10.2 kW max | C2: https://docs.nvidia.com/dgx/dgxh100-user-guide/introduction-to-dgxh100.html | D2: Reported
A3: S2 | B3: NVIDIA DGX SuperPOD H100 data center design – 127 DGX = 1,295 kW + ~116 kW IB/mgmt/storage switches (EAP) | C3: https://docs.nvidia.com/dgx-superpod/design-guides/dgx-superpod-data-center-design-h100/latest/planning.html | D3: Reported
A4: S3 | B4: NVIDIA DGX B200 User Guide – 14.3 kW max | C4: https://docs.nvidia.com/dgx/dgxb200-user-guide/introduction-to-dgxb200.html | D4: Reported
A5: S4 | B5: NVIDIA DGX B300 User Guide / DC best practices – 14.5 kW (busbar) / 15 kW (AC) est., 19-19.7 kW peak; nvidia.com ~14 kW | C5: https://docs.nvidia.com/dgx/dgxb300-user-guide/introduction-to-dgxb300.html ; https://docs.nvidia.com/dgx-pdf/data-center-best-practices-with-dgx-b300-v1.pdf | D5: Reported
A6: S5 | B6: NVIDIA NVL72 AI Factory ref. arch – GB300 NVL72 'up to 142 kW'; Lenovo 135 kW TDP (155 peak); HPE 132-140 kW | C6: https://docs.nvidia.com/enterprise-reference-architectures/nvl72-ai-factory/latest/components.html ; https://lenovopress.lenovo.com/lp2357-lenovo-nvidia-gb300-nvl72-rack-scale-ai ; https://buy.hpe.com/emea_europe/en/compute/rack-scale-system/nvidia-nvl-system/nvidia-gb300-nvl72-by-hpe/p/1014890105 | D6: Reported
A7: S6 | B7: SemiAnalysis InferenceX – GB200 NVL72: 1,200 W TDP, 1.87 kW all-in per GPU; SemiAnalysis H100 vs GB200 (Aug-2025): H100 server ~$190k, all-in ~$250k/server; GB200 NVL72 rack $3.1M, all-in ~$3.9M | C7: https://inferencex.semianalysis.com/chips/gb200-nvl72 ; https://newsletter.semianalysis.com/p/h100-vs-gb200-nvl72-training-benchmarks | D7: Reported (third-party estimate)
A8: S7 | B8: Vera Rubin NVL72 rack power – NVIDIA does not publish; Ming-Chi Kuo est. ~190 kW Max-Q / ~230 kW Max-P (via Spheron); Supermicro sizes VR NVL72 SU at 227 kW/rack; 1,152 GPUs (16 racks) per 5 MW envelope | C8: https://www.spheron.network/blog/nvidia-vera-rubin-nvl72-guide/ ; https://www.securities.io/supermicro-ships-nvidia-vera-rubin-nvl72-racks-with-dlc-2-cooling/ | D8: Estimated (third-party)
A9: S8 | B9: Tom's Hardware (Mar 24 2026) – GB200 NVL72 $2.8-3.4M; GB300 NVL72 $6-6.5M; VR200 NVL72 $5-7M incl ~$1M NAND; VR300 NVL144 $7-8.8M | C9: https://www.tomshardware.com/tech-industry/artificial-intelligence/price-of-nvidias-vera-rubin-nvl72-racks-skyrockets-to-as-much-as-usd8-8-million-apiece-but-server-makers-margins-will-be-tight-nvidia-is-moving-closer-to-shipping-entire-full-scale-systems | D9: Reported (press/source)
A10: S9 | B10: Data Gravity (Aug 31 2026) – GB300 NVL72 POs just under $5.0M; ~$5.7M deployed (excl. DC, core switching, storage); 132-140 kW | C10: https://www.datagravity.dev/p/how-much-does-an-nvidia-nvl72-cost | D10: Reported (third-party)
A11: S10 | B11: HGX B200 server $360-560k (typical $420-500k); HGX B300 $420-750k (planning $550-650k) – vendor/blog price surveys | C11: https://www.mercatus-ai.com/blog/b200-server-price ; https://gpusmith.com/articles/en/nvidia-hgx-b300-price-specs | D11: Estimated (third-party, low confidence)
A12: S11 | B12: Cushman & Wakefield 2026 DC Development Cost Guide (Sep 3 2026) – all-in greenfield US/Canada avg $17.6M/MW excl. chips/GPUs; costs +21%/MW vs Q4-24; powered land $584k/MW | C12: https://ir.cushmanwakefield.com/news/press-release-details/2026/Cushman--Wakefield-Releases-2026-Data-Center-Development-Cost-Guide-Citing-21-Rise-in-Per-MW-Construction-Costs/default.aspx | D12: Reported
... A49: S48 | B49: Nebius Q2'26 6-K Ex-99.2 Note 7 (Aug 12 2026) – server & network equipment gross $3,123.6M (Dec-25) / $5,197.7M (Jun-26); assets not yet in use $7,836.4M; active MW ~183 (team input, Q2'26 letter) | C49: /workspace/nebius/comps_raw/nb_q2_fs.txt ; https://www.sec.gov/Archives/edgar/data/1513845/000110465926094568/tm2622968d1_ex99-2.htm | D49: Reported (MW = team input)
