Workbook

Sheet README
A1: Nebius (NBIS) capacity model - built 2026-10-04 (ET) by Capacity & Power analyst. Public information only. Script: /workspace/nebius/capacity/build_capacity.py
A3: DEFINITIONS (Nebius, Q1-26 letter): contracted = power secured by contracted land and power commitments; connected = power connected into fully built and equipped DCs; active = power consumed by installed operational IT equipment, available for revenue.
A4: 'Energized MW' in this workbook = my estimate of power physically live at the site (closest to 'active'). It is NOT 'connected' (built-and-equipped, may not be powered) and NOT 'contracted'.
A5: MW BASIS: Nebius never states IT vs gross. Site rows use the stated basis (mostly unknown/gross). Vineland energized rows are IT MW (alt-data power-bounded); Modi'in and AIB are IT. Company totals therefore mix bases (1.1-1.45x PUE ambiguity).
A7: MAPPING FOR MODELING: Energized low -> Bear; Energized base (midpoint formula) -> Base; Energized high -> Bull. Contracted MW is not a revenue driver.
A8: BILLING LAG (Estimated): revenue/billing lags energization by >= 1 quarter for new capacity (commission DC, network, clusters, platform, onboarding: Q2-26 call "takes a few months"; active through 1H27). Exception: Vineland T1-T4 billing at reported delivery dates.
A9: Rates context (Q2-26 letter): ~$12M/MW/yr 2026 installed base; >$20M/MW Q2 new deals ($20-25M ACV/MW); >$40M/MW Q3 short-term deals.
A10: CAPEX (corrected): FY26 capex guide $20-25B (CFO, Q2-26 call Aug 12 2026; not in an SEC filing). On +580-780 MW connected (220 -> 800-1,000) = $25.6-43.1M per connected MW (Derived: 20,000/780 and 25,000/580). Earlier $16-20B figure superseded.
A12: YE2026 ENERGIZED (identified sites, this model): see Quarterly MW Q4 2026 company rows. Revised from prior ~330/600/800 after alt-data: Vineland capped at the generator ceiling (~107 MW IT) until Bloom is confirmed; Bethune 120 MW at risk; Birmingham/Independence revenue 2027.
A13: PLUG ROW: = mgmt reported/guided figure - identified base. At YE26 it shows the MW that must come from undisclosed sites (MN, OK, France 2nd, UK 3rd) or from counting built-but-unpowered halls as "connected" for the guide to be met. It is a reconciliation, not an estimate.
A14: GPUs: energized base MW x GPUs/MW (gpu_mw_capex.xlsx base rows; gross column for stated-basis sites, IT column for IT-basis sites). Reported GPU counts ran ahead of powered MW (delivered-not-powered): never back MW out of GPU counts.
A15: GPU vintage: generation per site is mostly ASSUMED (Nebius rarely discloses per site). 2027+ owned sites assumed Vera Rubin. Cohort rows = quarterly MW additions for vintage depreciation (servers 5-yr life from Jan 2026 per 20-F).
... A18: Verification grades and rationale: /workspace/nebius/capacity/site_verification.md. Alt-data: /workspace/nebius/capacity/altdata/altdata_timelines.xlsx.

Sheet Summary
A1: SUMMARY (v2) - Nebius energized / connected / leased MW. Base = midpoint; IT/gross via Basis tab. All projections Estimated.
A3: Metric | B3: YE26 low | C3: YE26 base | D3: YE26 high | E3: YE27 low | G3: YE27 base | H3: YE27 high | I3: Tag | J3: Source / note
A4: Energized MW - stated basis (mixed) | B4: ='Quarterly MW'!P124 -> 200 | C4: ='Quarterly MW'!P126 -> 319.5 | D4: ='Quarterly MW'!P125 -> 439 | E4: ='Quarterly MW'!T124 -> 864 | G4: ='Quarterly MW'!T126 -> 1212.5 | H4: ='Quarterly MW'!T125 -> 1561 | I4: Derived/Estimated
A5: Energized MW - IT-normalized | B5: ='Quarterly MW'!P135 -> 189.48951 | C5: ='Quarterly MW'!P136 -> 301.72028 | D5: ='Quarterly MW'!P137 -> 413.95105 | E5: ='Quarterly MW'!T135 -> 794.61375 | G5: ='Quarterly MW'!T136 -> 1081.9246 | H5: ='Quarterly MW'!T137 -> 1369.2355 | I5: Derived/Estimated
A6: Energized MW - gross-normalized | B6: ='Quarterly MW'!P138 -> 226 | C6: ='Quarterly MW'!P139 -> 368.6 | D6: ='Quarterly MW'!P140 -> 511.2 | E6: ='Quarterly MW'!T138 -> 989.85 | G6: ='Quarterly MW'!T139 -> 1363.975 | H6: ='Quarterly MW'!T140 -> 1738.1 | I6: Derived/Estimated
A7: Connected MW (gross/shell, bottom-up) | B7: ='Quarterly MW'!P141 -> 561 | C7: ='Quarterly MW'!P142 -> 941 | D7: ='Quarterly MW'!P143 -> 1195 | E7: ='Quarterly MW'!T141 -> 1249 | G7: ='Quarterly MW'!T142 -> 1882 | H7: ='Quarterly MW'!T143 -> 2517 | I7: Derived/Estimated
A8: Modeling placeholder YE27 energized IT MW | G8: 950
A9: Ours (IT base) minus 950 placeholder | G9: =G5-G8 -> 131.9246
A10: Mgmt guide: connected | C10: 800-1,000 | G10: ~1,800-2,000 (YE26 + >1 GW/yr)
A11: Vineland Bloom slips 2Q: IT MW lost at YE27 | G11: ='Quarterly MW'!T146 -> 66.5
A12: Billing MW (IT) at quarter-end: base / Bloom-slip | C12: ='Quarterly MW'!P147 -> 257.65618 | G12: ='Quarterly MW'!T147 -> 852.61375 | H12: ='Quarterly MW'!T148 -> 772.61375
A14: LEASED vs OWNED IT MW (for Note 12 $12.05B signed-not-commenced lease check: leased IT MW x $2.0-2.5M/IT MW/yr)
A15: Site | B15: Owned/leased | C15: Contracted MW (stated) | D15: Contracted IT MW | E15: Energized IT YE25 (base) | F15: Energized IT YE26 (base) | G15: Energized IT YE27 (base) | H15: Contracted IT not yet energized at YE26 | I15: Tag | J15: Note
A16: Vineland NJ (DataOne) | B16: leased | C16: ='Quarterly MW'!T3 -> 300 | D16: 240 | E16: =N('Quarterly MW'!L6) -> 26.2 | F16: =N('Quarterly MW'!P6) -> 81.8 | G16: =N('Quarterly MW'!T6) -> 235 | H16: =IF(ISNUMBER(D16),MAX(0,D16-N(F16)),"n/d") -> 158.2 | I16: Derived/Estimated | J16: Operating PUE 1.2 for liquid-cooled GB300 (team ceiling formula); design ratio 300/240 = 1.25
A17: Bethune FR (Azur Datacenter, ex-Bridgestone) | B17: leased | C17: ='Quarterly MW'!T23 -> 240 | D17: =IF(ISNUMBER('Quarterly MW'!T23),'Quarterly MW'!T23/Basis!$G$6,"n/d") -> 184.61538 | E17: =N('Quarterly MW'!L26)/Basis!$G$6 -> 0 | F17: =N('Quarterly MW'!P26)/Basis!$G$6 -> 23.076923 | G17: =N('Quarterly MW'!T26)/Basis!$G$6 -> 138.46154 | H17: =IF(ISNUMBER(D17),MAX(0,D17-N(F17)),"n/d") -> 161.53846 | I17: Derived/Estimated | J17: Northern France climate; peer range
A18: Kansas City MO (Patmos) | B18: leased | C18: ='Quarterly MW'!T43 -> 40 | D18: =IF(ISNUMBER('Quarterly MW'!T43),'Quarterly MW'!T43,"n/d") -> 40 | E18: =N('Quarterly MW'!L46) -> 20 | F18: =N('Quarterly MW'!P46) -> 20 | G18: =N('Quarterly MW'!T46) -> 30 | H18: =IF(ISNUMBER(D18),MAX(0,D18-N(F18)),"n/d") -> 20 | I18: Derived/Estimated | J18: Air-cooled Hopper/B200 retrofit; colo leases usually priced on critical IT
A19: Paris (Equinix PA10) | B19: leased | C19: ='Quarterly MW'!T48 -> 5 | D19: =IF(ISNUMBER('Quarterly MW'!T48),'Quarterly MW'!T48,"n/d") -> 5 | E19: =N('Quarterly MW'!L51) -> 5 | F19: =N('Quarterly MW'!P51) -> 5 | G19: =N('Quarterly MW'!T51) -> 5 | H19: =IF(ISNUMBER(D19),MAX(0,D19-N(F19)),"n/d") -> 0 | I19: Derived/Estimated | J19: Equinix urban colo
A20: Keflavik IS (Verne) | B20: leased | C20: ='Quarterly MW'!T53 -> 10 | D20: =IF(ISNUMBER('Quarterly MW'!T53),'Quarterly MW'!T53,"n/d") -> 10 | E20: =N('Quarterly MW'!L56) -> 10 | F20: =N('Quarterly MW'!P56) -> 10 | G20: =N('Quarterly MW'!T56) -> 10 | H20: =IF(ISNUMBER(D20),MAX(0,D20-N(F20)),"n/d") -> 0 | I20: Derived/Estimated | J20: Iceland free cooling
A21: London Longcross (Ark LP01) | B21: leased | C21: ='Quarterly MW'!T58 -> 19 | D21: =IF(ISNUMBER('Quarterly MW'!T58),'Quarterly MW'!T58/Basis!$G$13,"n/d") -> 14.615385 | E21: =N('Quarterly MW'!L61)/Basis!$G$13 -> 12.307692 | F21: =N('Quarterly MW'!P61)/Basis!$G$13 -> 13.461538 | G21: =N('Quarterly MW'!T61)/Basis!$G$13 -> 14.615385 | H21: =IF(ISNUMBER(D21),MAX(0,D21-N(F21)),"n/d") -> 1.1538462 | I21: Derived/Estimated | J21: Air-cooled HGX B300
A22: Harlow UK (Kao Data KLON-02/03) | B22: leased | C22: ='Quarterly MW'!T63 -> 22 | D22: =IF(ISNUMBER('Quarterly MW'!T63),'Quarterly MW'!T63,"n/d") -> 22 | E22: =N('Quarterly MW'!L66) -> 0 | F22: =N('Quarterly MW'!P66) -> 2.2 | G22: =N('Quarterly MW'!T66) -> 22 | H22: =IF(ISNUMBER(D22),MAX(0,D22-N(F22)),"n/d") -> 19.8 | I22: Derived/Estimated | J22: Kao Data design PUE ~1.2 (Estimated)
A23: Newport UK (Vantage CWL1) | B23: leased | C23: ='Quarterly MW'!T68 -> n/d | D23: 43 | E23: =N('Quarterly MW'!L71) -> 0 | F23: =N('Quarterly MW'!P71) -> 5 | G23: =N('Quarterly MW'!T71) -> 31.5 | H23: =IF(ISNUMBER(D23),MAX(0,D23-N(F23)),"n/d") -> 38 | I23: Derived/Estimated | J23: UK colo
A24: UK 3rd new deployment (lead: Green Mountain LON-East, Romford) | B24: leased | C24: ='Quarterly MW'!T73 -> n/d | D24: n/d | E24: =N('Quarterly MW'!L76) -> 0 | F24: =N('Quarterly MW'!P76) -> 0 | G24: =N('Quarterly MW'!T76) -> 7 | H24: =IF(ISNUMBER(D24),MAX(0,D24-N(F24)),"n/d") -> n/d | I24: Derived/Estimated | J24: UK colo
A25: Modi'in IL (Mega Or) | B25: leased | C25: ='Quarterly MW'!T78 -> 8 | D25: =IF(ISNUMBER('Quarterly MW'!T78),'Quarterly MW'!T78,"n/d") -> 8 | E25: =N('Quarterly MW'!L81) -> 8 | F25: =N('Quarterly MW'!P81) -> 8 | G25: =N('Quarterly MW'!T81) -> 8 | H25: =IF(ISNUMBER(D25),MAX(0,D25-N(F25)),"n/d") -> 0 | I25: Derived/Estimated | J25: Israel climate
A26: Masmiyya IL (Mega DC) | B26: leased | C26: ='Quarterly MW'!T83 -> 22 | D26: =IF(ISNUMBER('Quarterly MW'!T83),'Quarterly MW'!T83,"n/d") -> 22 | E26: =N('Quarterly MW'!L86) -> 0 | F26: =N('Quarterly MW'!P86) -> 5.5 | G26: =N('Quarterly MW'!T86) -> 22 | H26: =IF(ISNUMBER(D26),MAX(0,D26-N(F26)),"n/d") -> 16.5 | I26: Derived/Estimated | J26: Israel climate
A27: Beit Shemesh IL (Mega DC) | B27: leased | C27: ='Quarterly MW'!T88 -> 58 | D27: =IF(ISNUMBER('Quarterly MW'!T88),'Quarterly MW'!T88,"n/d") -> 58 | E27: =N('Quarterly MW'!L91) -> 0 | F27: =N('Quarterly MW'!P91) -> 0 | G27: =N('Quarterly MW'!T91) -> 58 | H27: =IF(ISNUMBER(D27),MAX(0,D27-N(F27)),"n/d") -> 58 | I27: Derived/Estimated | J27: Israel climate
A28: Madrid-Getafe ES (Merlin Edged) | B28: leased | C28: ='Quarterly MW'!T93 -> 18 | D28: =IF(ISNUMBER('Quarterly MW'!T93),'Quarterly MW'!T93,"n/d") -> 18 | E28: =N('Quarterly MW'!L96) -> 0 | F28: =N('Quarterly MW'!P96) -> 13.5 | G28: =N('Quarterly MW'!T96) -> 18 | H28: =IF(ISNUMBER(D28),MAX(0,D28-N(F28)),"n/d") -> 4.5 | I28: Derived/Estimated | J28: Madrid climate
A29: Tallinn EE (Greenergy Huuru) | B29: leased | C29: ='Quarterly MW'!T98 -> 22 | D29: =IF(ISNUMBER('Quarterly MW'!T98),'Quarterly MW'!T98,"n/d") -> 22 | E29: =N('Quarterly MW'!L101) -> 0 | F29: =N('Quarterly MW'!P101) -> 11 | G29: =N('Quarterly MW'!T101) -> 22 | H29: =IF(ISNUMBER(D29),MAX(0,D29-N(F29)),"n/d") -> 11 | I29: Derived/Estimated | J29: Baltic climate
A30: Minnesota colo (us-north1, Woodbury) | B30: leased | C30: ='Quarterly MW'!T103 -> n/d | D30: n/d | E30: =N('Quarterly MW'!L106) -> 0 | F30: =N('Quarterly MW'!P106) -> 10 | G30: =N('Quarterly MW'!T106) -> 10 | H30: =IF(ISNUMBER(D30),MAX(0,D30-N(F30)),"n/d") -> n/d | I30: Derived/Estimated | J30: US colo
A31: Oklahoma colo (unnamed) | B31: leased | C31: ='Quarterly MW'!T108 -> n/d | D31: n/d | E31: =N('Quarterly MW'!L111) -> 0 | F31: =N('Quarterly MW'!P111) -> 25 | G31: =N('Quarterly MW'!T111) -> 100 | H31: =IF(ISNUMBER(D31),MAX(0,D31-N(F31)),"n/d") -> n/d | I31: Derived/Estimated | J31: US colo, liquid cooling
A32: France 2nd colo (unnamed; possibly eu-west2) | B32: leased | C32: ='Quarterly MW'!T113 -> n/d | D32: n/d | E32: n/d | F32: n/d | G32: n/d | H32: =IF(ISNUMBER(D32),MAX(0,D32-N(F32)),"n/d") -> n/d | I32: Derived/Estimated | J32: n/d
A33: AIB CLT1 (Moore, Spartanburg County SC; Lockhart Power) | B33: leased | C33: ='Quarterly MW'!T118 -> 50 | D33: =IF(ISNUMBER('Quarterly MW'!T118),'Quarterly MW'!T118,"n/d") -> 50 | E33: =N('Quarterly MW'!L121) -> 0 | F33: =N('Quarterly MW'!P121) -> 0 | G33: =N('Quarterly MW'!T121) -> 25 | H33: =IF(ISNUMBER(D33),MAX(0,D33-N(F33)),"n/d") -> 50 | I33: Derived/Estimated | J33: 65/50 = 1.30
A34: TOTAL leased | D34: =SUM(D16:D33) -> 737.23077 | E34: =SUM(E16:E33) -> 81.507692 | F34: =SUM(F16:F33) -> 233.53846 | G34: =SUM(G16:G33) -> 756.57692 | H34: =SUM(H16:H33) -> 538.69231
A35: TOTAL owned (IT-normalized energized) | E35: =N('Quarterly MW'!L11)/Basis!$G$3+N('Quarterly MW'!L16)/Basis!$G$4+N('Quarterly MW'!L21)/Basis!$G$5+N('Quarterly MW'!L31)/Basis!$G$7+N('Quarterly MW'!L36)/Basis!$G$8+N('Quarterly MW'!L41)/Basis!$G$9 -> 56.818182 | F35: =N('Quarterly MW'!P11)/Basis!$G$3+N('Quarterly MW'!P16)/Basis!$G$4+N('Quarterly MW'!P21)/Basis!$G$5+N('Quarterly MW'!P31)/Basis!$G$7+N('Quarterly MW'!P36)/Basis!$G$8+N('Quarterly MW'!P41)/Basis!$G$9 -> 68.181818 | G35: =N('Quarterly MW'!T11)/Basis!$G$3+N('Quarterly MW'!T16)/Basis!$G$4+N('Quarterly MW'!T21)/Basis!$G$5+N('Quarterly MW'!T31)/Basis!$G$7+N('Quarterly MW'!T36)/Basis!$G$8+N('Quarterly MW'!T41)/Basis!$G$9 -> 325.34768
A36: Illustrative: rent on leased contracted IT MW not yet energized at YE26, $M/yr @ $2.0M / $2.5M | B36: =H34*2 -> 1077.3846 | C36: =H34*2.5 -> 1346.7308
A38: LEASES SIGNED NOT COMMENCED (Q2'26 6-K Ex.99.2 lease note) vs our leased IT MW
A39: Leases signed not commenced at 6/30/26, undiscounted $M | B39: 12054.1 | I39: Reported | J39: Q2'26 interim FS (6-K Ex.99.2) lease note; primarily DC facilities + equipment; commencing 2026-2027; terms up to 12 yrs; $612.4M prepaid
A40: Same at 12/31/25, $M (terms up to 11 yrs; $271.0M prepaid) | B40: 9759.6 | I40: Reported | J40: FY25 20-F Note 8
A41: ROU assets 6/30/26 $M (YE25 918.8; H1 additions 996.2) | B41: 1855.1 | I41: Reported | J41: Q2'26 interim FS lease note
A42: Term assumption (yrs) - Filings check uses 12 (max disclosed) | B42: 12 | I42: Estimated | J42: Filings team check; disclosed as "up to 12 years"
A43: Alt term assumption (yrs) | B43: 10 | I43: Estimated | J43: sensitivity: average term below the maximum
A44: Implied annual payments $M/yr @ 12 yrs | B44: =B39/B42 -> 1004.5083 | I44: Derived | J44: undiscounted / term
A45: Filings check: implied leased IT MW @ $2.0M/IT MW-yr | B45: =B44/2 -> 502.25417 | I45: Derived | J45: Filings rough check (400-500 MW range)
A46: Filings check: implied leased IT MW @ $2.5M/IT MW-yr | B46: =B44/2.5 -> 401.80333 | I46: Derived | J46: Filings rough check
A47: OURS: leased IT MW energized (commenced proxy) YE25 | B47: =N('Quarterly MW'!L6)+N('Quarterly MW'!L26)/Basis!$G$6+N('Quarterly MW'!L46)+N('Quarterly MW'!L51)+N('Quarterly MW'!L56)+N('Quarterly MW'!L61)/Basis!$G$13+N('Quarterly MW'!L66)+N('Quarterly MW'!L71)+N('Quarterly MW'!L76)+N('Quarterly MW'!L81)+N('Quarterly MW'!L86)+N('Quarterly MW'!L91)+N('Quarterly MW'!L96)+N('Quarterly MW'!L101)+N('Quarterly MW'!L106)+N('Quarterly MW'!L111)+N('Quarterly MW'!L121) -> 81.507692 | I47: Derived | J47: sum of leased sites, IT-normalized base
A48: OURS: leased IT MW energized at 6/30/26 (already commenced proxy) | B48: =N('Quarterly MW'!N6)+N('Quarterly MW'!N26)/Basis!$G$6+N('Quarterly MW'!N46)+N('Quarterly MW'!N51)+N('Quarterly MW'!N56)+N('Quarterly MW'!N61)/Basis!$G$13+N('Quarterly MW'!N66)+N('Quarterly MW'!N71)+N('Quarterly MW'!N76)+N('Quarterly MW'!N81)+N('Quarterly MW'!N86)+N('Quarterly MW'!N91)+N('Quarterly MW'!N96)+N('Quarterly MW'!N101)+N('Quarterly MW'!N106)+N('Quarterly MW'!N111)+N('Quarterly MW'!N121) -> 114.30769 | I48: Derived | J48: sum of leased sites, IT-normalized base
A49: OURS: leased IT MW commencing in 2026 (YE26 - YE25) | B49: =N('Quarterly MW'!P6)+N('Quarterly MW'!P26)/Basis!$G$6+N('Quarterly MW'!P46)+N('Quarterly MW'!P51)+N('Quarterly MW'!P56)+N('Quarterly MW'!P61)/Basis!$G$13+N('Quarterly MW'!P66)+N('Quarterly MW'!P71)+N('Quarterly MW'!P76)+N('Quarterly MW'!P81)+N('Quarterly MW'!P86)+N('Quarterly MW'!P91)+N('Quarterly MW'!P96)+N('Quarterly MW'!P101)+N('Quarterly MW'!P106)+N('Quarterly MW'!P111)+N('Quarterly MW'!P121)-B47 -> 152.03077 | I49: Derived | J49: energization as commencement proxy
A50: OURS: leased IT MW commencing in 2027 (YE27 - YE26) | B50: =N('Quarterly MW'!T6)+N('Quarterly MW'!T26)/Basis!$G$6+N('Quarterly MW'!T46)+N('Quarterly MW'!T51)+N('Quarterly MW'!T56)+N('Quarterly MW'!T61)/Basis!$G$13+N('Quarterly MW'!T66)+N('Quarterly MW'!T71)+N('Quarterly MW'!T76)+N('Quarterly MW'!T81)+N('Quarterly MW'!T86)+N('Quarterly MW'!T91)+N('Quarterly MW'!T96)+N('Quarterly MW'!T101)+N('Quarterly MW'!T106)+N('Quarterly MW'!T111)+N('Quarterly MW'!T121)-(N('Quarterly MW'!P6)+N('Quarterly MW'!P26)/Basis!$G$6+N('Quarterly MW'!P46)+N('Quarterly MW'!P51)+N('Quarterly MW'!P56)+N('Quarterly MW'!P61)/Basis!$G$13+N('Quarterly MW'!P66)+N('Quarterly MW'!P71)+N('Quarterly MW'!P76)+N('Quarterly MW'!P81)+N('Quarterly MW'!P86)+N('Quarterly MW'!P91)+N('Quarterly MW'!P96)+N('Quarterly MW'!P101)+N('Quarterly MW'!P106)+N('Quarterly MW'!P111)+N('Quarterly MW'!P121)) -> 523.03846 | I50: Derived | J50: energization as commencement proxy
A51: OURS: leased IT MW commencing 7/1/26 - 12/31/27 (comparable to the $12.05B pool) | B51: =N('Quarterly MW'!T6)+N('Quarterly MW'!T26)/Basis!$G$6+N('Quarterly MW'!T46)+N('Quarterly MW'!T51)+N('Quarterly MW'!T56)+N('Quarterly MW'!T61)/Basis!$G$13+N('Quarterly MW'!T66)+N('Quarterly MW'!T71)+N('Quarterly MW'!T76)+N('Quarterly MW'!T81)+N('Quarterly MW'!T86)+N('Quarterly MW'!T91)+N('Quarterly MW'!T96)+N('Quarterly MW'!T101)+N('Quarterly MW'!T106)+N('Quarterly MW'!T111)+N('Quarterly MW'!T121)-B48 -> 642.26923 | I51: Derived | J51: YE27 leased energized - 6/30/26 leased energized
A52: of which excl. Vineland (build-to-suit lease may have commenced Nov-25 with T1) | B52: =N('Quarterly MW'!T26)/Basis!$G$6+N('Quarterly MW'!T46)+N('Quarterly MW'!T51)+N('Quarterly MW'!T56)+N('Quarterly MW'!T61)/Basis!$G$13+N('Quarterly MW'!T66)+N('Quarterly MW'!T71)+N('Quarterly MW'!T76)+N('Quarterly MW'!T81)+N('Quarterly MW'!T86)+N('Quarterly MW'!T91)+N('Quarterly MW'!T96)+N('Quarterly MW'!T101)+N('Quarterly MW'!T106)+N('Quarterly MW'!T111)+N('Quarterly MW'!T121)-(N('Quarterly MW'!N26)/Basis!$G$6+N('Quarterly MW'!N46)+N('Quarterly MW'!N51)+N('Quarterly MW'!N56)+N('Quarterly MW'!N61)/Basis!$G$13+N('Quarterly MW'!N66)+N('Quarterly MW'!N71)+N('Quarterly MW'!N76)+N('Quarterly MW'!N81)+N('Quarterly MW'!N86)+N('Quarterly MW'!N91)+N('Quarterly MW'!N96)+N('Quarterly MW'!N101)+N('Quarterly MW'!N106)+N('Quarterly MW'!N111)+N('Quarterly MW'!N121)) -> 446.26923 | I52: Derived | J52: same excl. VIN
A53: OURS: contracted leased IT MW not energized at 6/30/26 (named sites; n/d excluded) | B53: =D34-B48 -> 622.92308 | I53: Derived | J53: contracted leased IT total - energized at 6/30/26
A54: Implied rent $M per IT MW-yr if OUR pool MW is right @ 12 yrs | B54: =B44/B51 -> 1.5639988 | I54: Derived | J54: $12.05B / 12 / our pool MW
A55: Implied rent $M per IT MW-yr if OUR pool MW is right @ 10 yrs | B55: =B39/B43/B51 -> 1.8767986 | I55: Derived | J55: sensitivity
A56: Implied rent excl. Vineland @ 12 yrs | B56: =B44/B52 -> 2.2509021 | I56: Derived | J56: if Vineland lease already commenced
A57: less leases likely signed after 6/30/26 (AIB CLT1 Sep 30; Newport Aug 13; UK3 lead Sep 1) - YE27 IT MW | B57: =N('Quarterly MW'!T121)+N('Quarterly MW'!T71)+N('Quarterly MW'!T76) -> 63.5 | I57: Derived | J57: excluded: cannot be in the 6/30/26 not-commenced pool
A58: OURS: comparable pool excl. Vineland and post-6/30 signings | B58: =B52-B57 -> 382.76923 | I58: Derived | J58: best like-for-like vs Filings 400-500
A59: Implied rent $M per IT MW-yr on comparable pool @ 12 yrs | B59: =B44/B58 -> 2.6243184 | I59: Derived | J59: $12.05B / 12 / comparable pool
A60: VERDICT (Derived/Estimated): Including Vineland, our leased MW commencing 7/1/26-YE27 (~642 IT MW) is ABOVE the 400-500 MW check, i.e. not short. Like-for-like (Vineland build-to-suit likely commenced with T1 in Nov-25; AIB/Newport/UK3 signed after 6/30) our pool is ~383 IT MW, slightly BELOW 400-500, implying ~$2.6M/IT MW-yr at a 12-yr term. Leased MW and the $2.0-2.5M rent therefore bracket the disclosure; if anything the rent assumption looks slightly LOW (or more MW than modeled commence by YE27, e.g. Bethune/Beit Shemesh ahead of our base, larger OK). The pool also includes equipment leases, which would lower implied DC rent. No site-level ladder is disclosed, so this is a range check, not a reconciliation.
A61: Caveats: Vineland is a build-to-suit lease that has partly commenced (T1-T4); Note 12 composition by site is not disclosed; MN/OK/FR2/UK3 contracted MW n/d (excluded); AIB CLT1 rent ~>=$1.3B/12y/50MW = ~$2.2M/IT MW/yr (Derived, AIB deck) is a direct check on the $2.0-2.5M range.
A63: Q2'26 RECONCILIATION (~190 MW implied vs model)
A64: Q2-26 AI cloud revenue $M | B64: 574.9 | I64: Reported | J64: https://www.sec.gov/Archives/edgar/data/1513845/000110465926094568/tm2622968d1_ex99-2.htm
A65: 2026 base ACV per MW $M/yr (letter chart "ACV per MW... $12M 2026 base"; ACV = annual contract value, NOT capex) | B65: 12 | I65: Reported | J65: https://www.sec.gov/Archives/edgar/data/1513845/000110465926094568/tm2622968d1_ex99-2.htm p.1 + footnote 1
A66: Implied average billing MW in Q2 = rev x 4 / ACV | B66: =B64*4/B65 -> 191.63333 | I66: Derived
A67: June-26 exit: ARR $3.0B / $12M | B67: =3000/B65 -> 250 | I67: Derived | J67: ARR = last month x 12 (letter footnote)
A68: v1 model Q2-26 identified base (stated basis) | B68: 173 | I68: Reported | J68: nebius_capacity_v1.xlsx
A69: v2 model Q2-26 identified base (stated basis) | B69: ='Quarterly MW'!N126 -> 193 | I69: Derived | J69: adds MN 10 + OK 10 (Estimated)
A70: v2 model Q2-26 IT-normalized base | B70: ='Quarterly MW'!N136 -> 182.48951 | I70: Derived
A71: v2 model Q2-26 gross-normalized base | B71: ='Quarterly MW'!N139 -> 219.45 | I71: Derived
A72: Sensitivity: Vineland at 2 delivered tranches (2 x 26.7 IT) instead of altdata 39 | B72: =2*'Vineland tranche track'!$B$16-'Quarterly MW'!N6 -> 14.333333 | I72: Derived | J72: equal-split tranche MW vs thermal-bounded 39
A73: Result: the ~190 MW figure is a REVENUE-implied AVERAGE billing MW on Nebius's own (active = IT-consumed) basis. The gap to 173 closes mainly through MN + OK colos (~20 MW, live by Q2 per on-site jobs) -> v2 Q2-26 base ~193; IT-normalizing pulls it down (owned Mantsala 75 at PUE 1.1 and Longcross gross) while Vineland at tranche-equal-split (53 vs 39 IT) would add ~14. KC (20 in Q2-26) is unchanged in Q2-26; its re-anchoring affects 2025 history.
A75: GPU ANCHOR CHECK (Q1'25)
A76: Company-stated GPUs deployed at Mar 31 2025 | B76: 30000
A77: Modeled GPUs Q1-25 (v2, GPUs deployed tab) | B77: ='GPUs deployed'!I34 -> 27426
A78: Modeled / stated | B78: =B77/B76 -> 0.9142
A79: Energized MW Q1-25 (stated basis, v2) | B79: ='Quarterly MW'!I126 -> 50
A80: Gross MW needed for 30k Hopper at gross density | B80: =30000/'GPUs deployed'!$C$2 -> 54.694622

Sheet Sites
A1: Site | B1: Country | C1: Ownership type | D1: Contract tag | E1: Contract tag evidence | F1: Contracted MW | G1: MW basis (IT/gross/unknown) | H1: PUE (where disclosed) | I1: Mgmt go-live | J1: My evidence-based go-live | K1: Risk grade | L1: GPU generation | M1: YE26 energized low | N1: YE26 energized high | O1: YE26 energized base | P1: Key sources
A2: Vineland NJ (DataOne) | B2: USA | C2: Build-to-suit (DataOne owns shell; Nebius tenant) | D2: Microsoft | E2: Reported: 6-K Sep 2025 / 20-F: MSFT served from Vineland | F2: 300 | G2: Contracted 300 = gross (Estimated); energized rows = IT MW (altdata power-bounded) | H2: not disclosed (IT est. uses PUE 1.2-1.35, Estimated) | I2: Phase 1 summer 2025; all 9 MSFT tranches during 2025-26; Vineland in 2026 connected power (Q2-26 call) | J2: ~107 MW IT ceiling on rented gensets through YE26; Bloom-powered remainder 1H-2H 2027 | K2: Yellow/Red | L2: GB300 NVL72 (assumed; not disclosed by Nebius) | M2: ='Quarterly MW'!P4 -> 57 | N2: ='Quarterly MW'!P5 -> 106.6 | O2: ='Quarterly MW'!P6 -> 81.8 | P2: https://www.sec.gov/Archives/edgar/data/1513845/000110465925088312/tm2525580d1_6k.htm; https://www.sec.gov/Archives/edgar/data/1513845/000110465926052948/nbis-20251231x20f.htm; https://www.sec.gov/Archives/edgar/data/1513845/000110465926094568/tm2622968d1_ex99-2.htm; https://www.fool.com/earnings/call-transcripts/2026/08/19/nebius-nbis-q2-2026-earnings-call-transcript/ (cached /workspace/nebius/src/q2t.txt); https://www.enr.com/articles/63695-inside-the-vineland-data-center-power-dispute; https://newjerseymonitor.com/2026/10/01/nj-data-center-polluted-air-for-nearly-a-year-before-regulators-intervened/; https://www.nj.gov/governor/news/2026/20260922a.shtml; https://hntrbrk.com/breaking-news/vineland; https://whyy.org/articles/vineland-planning-board-approves-data-center-plan/; /workspace/nebius/capacity/altdata/altdata_timelines.xlsx (Timeline, Vineland_MW)
A3: Independence MO (Eastgate) | B3: USA | C3: Owned greenfield | D3: unassigned (Meta #2 candidate - assumed) | E3: assumed: Meta #2 = multiple undisclosed locations; Phase 1 Q3-27 is after Meta #2 1H27 tranches | F3: 1200 | G3: unknown (likely gross/utility) | H3: not disclosed | I3: Operational 2027 (Q1-26 letter); IPL initial power 2H26 | J3: Phase 1 ~Q3 2027; 600 MW not before 2029 | K3: Green | L3: Vera Rubin NVL72 (assumed; company-level VR statement) | M3: ='Quarterly MW'!P9 -> 0 | N3: ='Quarterly MW'!P10 -> 0 | O3: ='Quarterly MW'!P11 -> 0 | P3: https://nebius.com/independencemo; https://www.independencemo.gov/sites/default/files/2026-02/Nebius%20x%20Independence%2C%20MO.cleaned.pdf; https://citizenportal.ai/articles/7477161 (Independence PUAB: IPP PPA/ESA timeline); https://ded.mo.gov/press-room/nebius-breaks-ground-gigawatt-scale-ai-factory-independence; https://www.sec.gov/Archives/edgar/data/1513845/000110465926059872/tm2614392d1_ex99-2.htm; /workspace/nebius/capacity/altdata/altdata_timelines.xlsx (Timeline, Vineland_MW)
A4: Butler Twp PA (Highridge) | B4: USA | C4: Owned greenfield | D4: unassigned | E4: not disclosed | F4: 1200 | G4: unknown (PPL ESA = utility/gross) | H4: not disclosed | I4: 260 MW by Oct 2027; 660 MW Jan 2029; 1,000+ MW Nov 2029 | J4: First MW Q4 2027 at best; base ~Q2 2028-2029 (PPL lines late-27 to early-29; 3-yr build) | K4: Red | L4: Vera Rubin NVL72 (assumed) | M4: ='Quarterly MW'!P14 -> 0 | N4: ='Quarterly MW'!P15 -> 0 | O4: ='Quarterly MW'!P16 -> 0 | P4: https://nebius.com/schuylkillcountypa; https://www.republicanherald.com/2026/09/01/nebius-gets-green-light-to-expand-its-data-center-plan-in-butler-twp/; https://www.republicanherald.com/2026/04/24/butler-twp-switchyard-to-anchor-data-center-in-ppl-powerline-overhaul/; https://www.datacenterdynamics.com/en/news/nebius-details-plans-for-12gw-data-center-campus-in-pennsylvania/; /workspace/nebius/capacity/altdata/altdata_timelines.xlsx (Timeline, Vineland_MW)
A5: Birmingham AL (BHM01, Oxmoor) | B5: USA | C5: Owned brownfield | D5: unassigned | E5: not disclosed | F5: 300 | G5: unknown (300 MW is press figure, not Nebius) | H5: not disclosed | I5: Initial-phase energization Q4 2026 (Nebius page); operational 2027 (Q1-26 letter) | J5: 115 kV NLT Dec 31 2026; first revenue MW 2027; 230 kV Oct 2027 | K5: Yellow | L5: Vera Rubin NVL72 (assumed) | M5: ='Quarterly MW'!P19 -> 0 | N5: ='Quarterly MW'!P20 -> 0 | O5: ='Quarterly MW'!P21 -> 0 | P5: https://nebius.com/birminghamal; https://abc3340.com/resources/pdf/9222f76a-3063-46e4-aee7-796b30ed611f-NebiusResponsestoCityLetter_Redacted.pdf; https://bhamnow.com/2026/05/18/40-million-permits-birmingham-data-center/; https://www.wbhm.org/local-news/2026-09-18/action-picks-up-in-lawsuits-targeting-birmingham-data-center; /workspace/nebius/capacity/altdata/altdata_timelines.xlsx (Timeline, Vineland_MW)
A6: Bethune FR (Azur Datacenter, ex-Bridgestone) | B6: France | C6: Colocation (20-F); Azur finances/builds | D6: Meta (#2 likely) - press | E6: La Voix du Nord 2026-09-24: part of site 'fera travailler l'IA de Meta' (Estimated mapping to Meta #2) | F6: 240 | G6: unknown | H6: not disclosed | I6: First capacity late summer 2026; ~120 MW YE26; 240 MW 2027 | J6: Start Q4 2026 (~27 MW initial); 120 MW ~1H27; prefect ICPE decision pending | K6: Yellow | L6: GB300 NVL72 (Estimated: EUR4M/rack per press) | M6: ='Quarterly MW'!P24 -> 0 | N6: ='Quarterly MW'!P25 -> 60 | O6: ='Quarterly MW'!P26 -> 30 | P6: https://www.reuters.com/technology/amsterdam-based-ai-firm-nebius-build-240mw-data-centre-near-lille-france-2026-02-12/; https://www.lavoixdunord.fr/1740138/article/2026-09-24/la-premiere-ia-factory-des-hauts-de-france-va-bientot-prendre-vie-bethune; https://www.nordfranceinvest.com/success-story/dutch-company-nebius-is-setting-up-the-first-ai-data-center-in-the-hauts-de-france-region/; https://presseagence.fr/bethune-numerique-un-projet-de-datacenter-soumis-a-consultation-publique/; /workspace/nebius/capacity/altdata/altdata_timelines.xlsx (Timeline, Vineland_MW)
A7: Lappeenranta FI (Pajarila / Polarnode) | B7: Finland | C7: Owned per Nebius; Polarnode says Nebius 'operates' its campus (conflict) | D7: unassigned | E7: not disclosed | F7: 310 | G7: unknown | H7: not disclosed | I7: First capacity to customers 2027 | J7: First building H1 2027 (Fira); substation spring 2027 | K7: Green | L7: Vera Rubin NVL72 (assumed; PR: Blackwell & Rubin) | M7: ='Quarterly MW'!P29 -> 0 | N7: ='Quarterly MW'!P30 -> 0 | O7: ='Quarterly MW'!P31 -> 0 | P7: https://nebius.com/newsroom/nebius-to-construct-310-mw-ai-factory-in-finland; https://fira.fi/en/tiedote/construction-and-project-development-company-fira-selected-as-main-contractor-for-one-of-europes-largest-ai-data-center-projects/; https://www.caverion.com/newsroom/releases/2026/caverion-to-deliver-eur-15-million-substation-for-nebius-data-center-in-finland-creating-jobs-for-more-than-80-professionals/
A8: Mantsala FI #1 | B8: Finland | C8: Owned | D8: self-serve (assumed); Meta #1 site not disclosed | E8: assumed | F8: 75 | G8: unknown; PUE ~1.1 (company) | H8: ~1.1 (Nebius, company statement) | I8: 75 MW end-2025/early-2026 | J8: 75 MW built (completed early 2026) | K8: Green | L8: Hopper (first 25 MW) + GB300 NVL72 (expansion, Estimated split) | M8: ='Quarterly MW'!P34 -> 75 | N8: ='Quarterly MW'!P35 -> 75 | O8: ='Quarterly MW'!P36 -> 75 | P8: https://assets.nebius.com/assets/6590d0a0-0fc4-4396-bc3f-f52a9ccb770e/20260331%20Nebius%20to%20construct%20310%20MW%20AI%20factory%20in%20Finland.pdf; /workspace/nebius/capacity/altdata/altdata_timelines.xlsx (Timeline, Vineland_MW)
A9: Mantsala FI #2 (Kapuli) | B9: Finland | C9: Owned (implied) | D9: unassigned | E9: not disclosed | F9: 70 | G9: unknown (70 MW substation) | H9: not disclosed | I9: Capacity 'from 2027' | J9: Q4 2027 earliest (substation completes autumn 2027) | K9: Yellow | L9: Vera Rubin NVL72 (assumed) | M9: ='Quarterly MW'!P39 -> 0 | N9: ='Quarterly MW'!P40 -> 0 | O9: ='Quarterly MW'!P41 -> 0 | P9: https://www.assemblincaverion.com/news-and-media/news/2026/caverion-finland-strengthens-its-position-in-the-data-centre-market-and-will-deliver-a-eur-15-million-substation-for-ai-cloud-company-nebius/; https://www.datacenterdynamics.com/en/news/nebius-expands-european-presence-announces-deployment-in-estonia-and-second-data-center-in-m%C3%A4nts%C3%A4l%C3%A4-finland/
A10: Kansas City MO (Patmos) | B10: USA | C10: Colocation | D10: self-serve (assumed) | E10: assumed | F10: 40 | G10: unknown | H10: not disclosed | I10: 5 MW live Apr 2025; expandable to 40 MW | J10: Operational; Nebius share of 35 MW facility not disclosed | K10: Green | L10: H200 (first 5 MW) + B200 (rest) | M10: ='Quarterly MW'!P44 -> 5 | N10: ='Quarterly MW'!P45 -> 35 | O10: ='Quarterly MW'!P46 -> 20 | P10: https://www.datacenterdynamics.com/en/news/nebius-to-deploy-5mw-nvidia-h200-cluster-at-patmos-data-center-in-kansas-city-missouri/; https://www.datacenterdynamics.com/en/news/patmos-adds-10mw-of-capacity-at-kansas-city-data-center/; https://careers.nebius.com/?gh_jid=4975997101
A11: Paris (Equinix PA10) | B11: France | C11: Colocation | D11: self-serve (assumed) | E11: assumed | F11: 5 | G11: unknown; MW not disclosed (5 = 3rd-party) | H11: not disclosed | I11: Live Nov 2024 | J11: Operational | K11: Green | L11: Hopper H100/H200 | M11: ='Quarterly MW'!P49 -> 5 | N11: ='Quarterly MW'!P50 -> 5 | O11: ='Quarterly MW'!P51 -> 5 | P11: https://dcatlas.io/en/explore/facilities/nebius-equinix-paris (3rd-party, low confidence); https://docs.nebius.com/overview/regions (accessed 2026-10-04)
A12: Keflavik IS (Verne) | B12: Iceland | C12: Colocation | D12: self-serve (assumed) | E12: assumed | F12: 10 | G12: unknown | H12: not disclosed | I12: Live Mar 2025 | J12: Operational (private region) | K12: Green | L12: Hopper H100/H200 | M12: ='Quarterly MW'!P54 -> 10 | N12: ='Quarterly MW'!P55 -> 10 | O12: ='Quarterly MW'!P56 -> 10 | P12: https://nebius.com/blog/posts/300-mw-new-jersey-and-iceland-regions; https://docs.nebius.com/overview/regions (accessed 2026-10-04)
A13: London Longcross (Ark LP01) | B13: UK | C13: Colocation | D13: self-serve (assumed) | E13: assumed | F13: 19 | G13: unknown (GPU/MW fit suggests gross) | H13: not disclosed | I13: Launched Nov 2025; 16 MW live + 3 MW in delivery (Jun 2026); LP02 36 MW (Nebius share n/d) | J13: 19 MW by ~Q4 2026; LP02 share/timing not disclosed | K13: Green | L13: B300 (HGX) | M13: ='Quarterly MW'!P59 -> 16 | N13: ='Quarterly MW'!P60 -> 19 | O13: ='Quarterly MW'!P61 -> 17.5 | P13: https://datacentrenews.uk/story/nebius-fills-ark-s-longcross-data-centre-to-capacity; https://www.datacenterdynamics.com/en/news/ark-dc-to-add-new-building-to-longcross-data-center-campus-outside-london-uk/; https://docs.nebius.com/overview/regions (accessed 2026-10-04)
A14: Harlow UK (Kao Data KLON-02/03) | B14: UK | C14: Colocation (10-yr) | D14: self-serve (assumed) | E14: assumed | F14: 22 | G14: unknown | H14: not disclosed | I14: UK 65 MW fully ramped 2027 | J14: KLON-03 completion end-2026; MW early 2027 | K14: Green | L14: B300 (HGX) (assumed; docs uk-south2 lists RTX PRO 6000) | M14: ='Quarterly MW'!P64 -> 0 | N14: ='Quarterly MW'!P65 -> 4.4 | O14: ='Quarterly MW'!P66 -> 2.2 | P14: https://www.datacenterdynamics.com/en/news/nebius-signs-22mw-capacity-agreement-with-kao-data-in-the-uk/; https://www.linkedin.com/posts/infratil_klon-03-development-update-activity-7404073674942656512-l6mm; https://nebius.com/newsroom/nebius-expands-in-uk-with-more-nvidia-powered-infrastructure-more-customers-and-more-cloud-capabilities-for-agentic-and-enterprise-ai
A15: Newport UK (Vantage CWL1) | B15: UK | C15: Colocation (Vantage) | D15: self-serve (assumed) | E15: assumed | F15: not disclosed | G15: not stated (MW not disclosed) | H15: not disclosed | I15: Announced Aug 13 2026; part of UK 65 MW fully ramped 2027 | J15: Newport + UK 3rd = 65 - 22 (Harlow) = 43 MW by 2027 (Derived); Newport ~29 if LON-East is the 3rd site (low) | K15: Yellow | L15: not disclosed (B300/GB300 assumed) | M15: ='Quarterly MW'!P69 -> 0 | N15: ='Quarterly MW'!P70 -> 10 | O15: ='Quarterly MW'!P71 -> 5 | P15: https://vantage-dc.com/news/vantage-data-centers-and-nebius-expand-uk-ai-infrastructure-with-first-deployment-in-south-wales-ai-growth-zone/; https://nebius.com/newsroom/nebius-expands-in-uk-with-more-nvidia-powered-infrastructure-more-customers-and-more-cloud-capabilities-for-agentic-and-enterprise-ai; https://boards-api.greenhouse.io/v1/boards/nebius/jobs?content=true (accessed 2026-10-04) (Newport jobs 4883814101 Jun 19, 4959471101 Aug 27)
A16: UK 3rd new deployment (lead: Green Mountain LON-East, Romford) | B16: UK | C16: not disclosed | D16: unassigned | E16: not disclosed | F16: not disclosed | G16: unknown | H16: not disclosed | I16: Part of 65 MW UK by 2027 | J16: Lead only: Green Mountain LON-East 14 MW to unnamed neocloud (Sep 1 2026) + Nebius East London job (Feb 2); low confidence | K16: Red | L16: not disclosed | M16: ='Quarterly MW'!P74 -> 0 | N16: ='Quarterly MW'!P75 -> 0 | O16: ='Quarterly MW'!P76 -> 0 | P16: https://nebius.com/newsroom/nebius-expands-in-uk-with-more-nvidia-powered-infrastructure-more-customers-and-more-cloud-capabilities-for-agentic-and-enterprise-ai; https://www.datacenterdynamics.com/en/news/green-mountain-secures-neocloud-customer-at-data-center-in-london-uk/
A17: Modi'in IL (Mega Or) | B17: Israel | C17: Colocation | D17: self-serve (assumed); 25% to Israel Innovation Authority | E17: Reported (IIA share) | F17: 8 | G17: IT (4,000 B200 / 8 MW = 500/MW fits IT model) | H17: not disclosed | I17: Launched Oct 2025 | J17: Operational | K17: Green | L17: B200 (HGX) | M17: ='Quarterly MW'!P79 -> 8 | N17: ='Quarterly MW'!P80 -> 8 | O17: ='Quarterly MW'!P81 -> 8 | P17: https://nebius.com/newsroom/nebius-brings-nvidia-blackwell-to-israel-with-one-of-the-country-s-first-ai-infrastructure-deployments; https://www.datacenterdynamics.com/en/news/nebius-signs-80mw-data-center-lease-with-mega-or-in-israel/
A18: Masmiyya IL (Mega DC) | B18: Israel | C18: Colocation (5-yr) | D18: unassigned | E18: not disclosed | F18: 22 | G18: unknown | H18: not disclosed | I18: Delivery Q3 2026 (landlord) | J18: Mega Or Q2-26 deck: Yoav construction completion Q4 2026 -> Q4-26/Q2-27 | K18: Yellow | L18: GB300 NVL72 (assumed) | M18: ='Quarterly MW'!P84 -> 0 | N18: ='Quarterly MW'!P85 -> 11 | O18: ='Quarterly MW'!P86 -> 5.5 | P18: https://www.datacenterdynamics.com/en/news/nebius-signs-80mw-data-center-lease-with-mega-or-in-israel/; https://www.calcalistech.com/ctechnews/article/25ue6vi49; https://www.deeptase.co.il/en/analysis/4873
A19: Beit Shemesh IL (Mega DC) | B19: Israel | C19: Colocation (5-yr) | D19: unassigned | E19: not disclosed | F19: 58 | G19: unknown | H19: not disclosed | I19: Staged Q3 2026 - Q1 2027 (landlord) | J19: Mega Or Q2-26 deck: completion Q2 2027 -> staged Q1-Q4 2027 | K19: Yellow | L19: GB300 NVL72 (assumed) | M19: ='Quarterly MW'!P89 -> 0 | N19: ='Quarterly MW'!P90 -> 0 | O19: ='Quarterly MW'!P91 -> 0 | P19: https://www.datacenterdynamics.com/en/news/nebius-signs-80mw-data-center-lease-with-mega-or-in-israel/; https://www.calcalistech.com/ctechnews/article/25ue6vi49; https://www.deeptase.co.il/en/analysis/4873
A20: Madrid-Getafe ES (Merlin Edged) | B20: Spain | C20: Colocation | D20: self-serve (assumed) | E20: assumed | F20: 18 | G20: unknown | H20: not disclosed | I20: Phase 1 live Sep 2026; phases 2-3 'coming weeks' | J20: Phase 1 live; 18 MW by Q4 2026-Q1 2027 | K20: Green | L20: B300 (HGX) (RTX PRO 6000 phase 1 not modeled) | M20: ='Quarterly MW'!P94 -> 9 | N20: ='Quarterly MW'!P95 -> 18 | O20: ='Quarterly MW'!P96 -> 13.5 | P20: https://www.linkedin.com/feed/update/urn:li:activity:7505906816590073857; https://www.merlinproperties.com/dia-a-dia/firmamos-un-contrato-de-18-mw-con-nebius-para-nuestro-date-center-madrid-getafe/; https://docs.nebius.com/overview/regions (accessed 2026-10-04)
A21: Tallinn EE (Greenergy Huuru) | B21: Estonia | C21: Colocation | D21: unassigned | E21: not disclosed | F21: 22 | G21: unknown | H21: not disclosed | I21: 22 MW first phase later in 2026 | J21: Q4 2026-Q2 2027; Estonian govt security review discussed at Cabinet (Aug 2026) | K21: Yellow | L21: GB300 NVL72 (assumed) | M21: ='Quarterly MW'!P99 -> 0 | N21: ='Quarterly MW'!P100 -> 22 | O21: ='Quarterly MW'!P101 -> 11 | P21: https://news.err.ee/1610109073/baltics-first-ai-factory-to-open-in-estonia; https://www.datacenterdynamics.com/en/news/nebius-expands-european-presence-announces-deployment-in-estonia-and-second-data-center-in-m%C3%A4nts%C3%A4l%C3%A4-finland/
A22: Minnesota colo (us-north1, Woodbury) | B22: USA | C22: Colocation (20-F) | D22: self-serve (assumed) | E22: assumed | F22: not disclosed | G22: unknown | H22: not disclosed | I22: Secured Feb 2026 | J22: us-north1 Woodbury; likely IronGate MSP01 (15 MW live, fully leased; inference) | K22: Yellow | L22: B300 (HGX) | M22: ='Quarterly MW'!P104 -> 5 | N22: ='Quarterly MW'!P105 -> 15 | O22: ='Quarterly MW'!P106 -> 10 | P22: https://www.sec.gov/Archives/edgar/data/1513845/000110465926052948/nbis-20251231x20f.htm; https://docs.nebius.com/overview/regions (accessed 2026-10-04); https://woodburynewsnet.org/7933/business/what-woodbury-residents-should-know-about-irongates-two-data-centers/; https://boards-api.greenhouse.io/v1/boards/nebius/jobs?content=true (accessed 2026-10-04)
A23: Oklahoma colo (unnamed) | B23: USA | C23: Colocation (20-F) | D23: unassigned | E23: not disclosed | F23: >100 (map category) | G23: unknown | H23: not disclosed | I23: Secured Feb 2026 | J23: Q2-26 letter map: Sites >100MW; 8 on-site roles since Mar 2 2026; town/landlord not found | K23: Yellow/Red | L23: not disclosed | M23: ='Quarterly MW'!P109 -> 10 | N23: ='Quarterly MW'!P110 -> 40 | O23: ='Quarterly MW'!P111 -> 25 | P23: https://www.sec.gov/Archives/edgar/data/1513845/000110465926052948/nbis-20251231x20f.htm; https://assets.nebius.com/assets/a6ecfd85-a6cb-4967-8ef7-9a25bd261f9c/SHLQ226.pdf (p.2 map); https://boards-api.greenhouse.io/v1/boards/nebius/jobs?content=true (accessed 2026-10-04)
A24: France 2nd colo (unnamed; possibly eu-west2) | B24: France | C24: Colocation (20-F) | D24: unassigned | E24: not disclosed | F24: not disclosed | G24: unknown | H24: not disclosed | I24: Secured Feb 2026 | J24: eu-west2 (France, B300) live in docs - mapping is inference; MW n/d -> in plug | K24: Yellow | L24: B300 (HGX) (inference) | M24: ='Quarterly MW'!P114 -> n/d | N24: ='Quarterly MW'!P115 -> n/d | O24: ='Quarterly MW'!P116 -> n/d | P24: https://www.sec.gov/Archives/edgar/data/1513845/000110465926052948/nbis-20251231x20f.htm; https://docs.nebius.com/overview/regions (accessed 2026-10-04)
A25: AIB CLT1 (Moore, Spartanburg County SC; Lockhart Power) | B25: USA | C25: Colocation/lease (12-yr) | D25: unassigned | E25: not disclosed | F25: 50 | G25: IT (50 MW critical IT on 65 MW utility ESA) | H25: 65/50 = 1.30 implied (Derived) | I25: Hall 1 (25 MW) ~month 10, Hall 2 ~month 14 after Oct 1 2026 ESA start | J25: Hall 1 ~Q3-Q4 2027; permits only submitted; project financing not arranged | K25: Red | L25: Vera Rubin NVL72 (assumed) | M25: ='Quarterly MW'!P119 -> 0 | N25: ='Quarterly MW'!P120 -> 0 | O25: ='Quarterly MW'!P121 -> 0 | P25: http://archive.fast-edgar.com/20260930/AB2ZM22DL222P26L222Q2MY2R6GDZ222ZQ82/ea030723301ex99-1.htm (AIB 8-K Ex.99.1, Sep 30 2026); https://www.globenewswire.com/news-release/2026/09/30/3371855/0/en/aib-data-centers-signs-contract-with-nebius-for-ai-data-center-capacity.html; https://www.sec.gov/Archives/edgar/data/2070542/000121390026036810/ea0282624-10k_blockchain.htm

Sheet Quarterly MW
A1: Site | B1: Block | C1: Basis | D1: Tag (hist / proj) | E1: Q1 2024 | F1: Q2 2024 | G1: Q3 2024 | H1: Q4 2024 | I1: Q1 2025 | J1: Q2 2025 | K1: Q3 2025 | L1: Q4 2025 | M1: Q1 2026 | N1: Q2 2026 | O1: Q3 2026 | P1: Q4 2026 | Q1: Q1 2027 | R1: Q2 2027 | S1: Q3 2027 | T1: Q4 2027 | U1: Q1 2028 | V1: Q2 2028 | W1: Q3 2028 | X1: Q4 2028 | Y1: Q1 2029 | Z1: Q2 2029 | AA1: Q3 2029 | AB1: Q4 2029 | AC1: Q1 2030 | AD1: Q2 2030 | AE1: Q3 2030 | AF1: Q4 2030
A2: History Q1'24-Q2'26 (tags per cell in Tags_Sources); projections Q3'26-Q4'30 = Estimated. Base = midpoint of low/high (formula). Blue = input, black = formula.
A3: Vineland NJ (DataOne) | B3: Contracted MW | C3: gross/unknown | I3: 300 | J3: 300 | K3: 300 | L3: 300 | M3: 300 | N3: 300 | O3: 300 | P3: 300 | Q3: 300 | R3: 300 | S3: 300 | T3: 300 | U3: 300 | V3: 300 | W3: 300 | X3: 300 | Y3: 300 | Z3: 300 | AA3: 300 | AB3: 300 | AC3: 300 | AD3: 300 | AE3: 300 | AF3: 300
A4: Vineland NJ (DataOne) | B4: Energized MW low | C4: IT | E4: 0 | F4: 0 | G4: 0 | H4: 0 | I4: 0 | J4: 0 | K4: 0 | L4: =ROUND((5+16*1.982)*0.8/1.35,1) -> 21.8 | M4: 30 | N4: 33 | O4: 57 | P4: 57 | Q4: 57 | R4: 107 | S4: 160 | T4: 230 | U4: 230 | V4: 230 | W4: 230 | X4: 230 | Y4: 230 | Z4: 230 | AA4: 230 | AB4: 230 | AC4: 230 | AD4: 230 | AE4: 230 | AF4: 230
A5: Vineland NJ (DataOne) | B5: Energized MW high | C5: IT | E5: 0 | F5: 0 | G5: 0 | H5: 0 | I5: 0 | J5: 0 | K5: 0 | L5: =ROUND((5+16*1.982)/1.2,1) -> 30.6 | M5: 45 | N5: 45 | O5: 75 | P5: =ROUND((5+62*1.982)/1.2,1) -> 106.6 | Q5: 180 | R5: 230 | S5: 240 | T5: 240 | U5: 240 | V5: 240 | W5: 240 | X5: 240 | Y5: 240 | Z5: 240 | AA5: 240 | AB5: 240 | AC5: 240 | AD5: 240 | AE5: 240 | AF5: 240
A6: Vineland NJ (DataOne) | B6: Energized MW base (=midpoint) | C6: IT | E6: =(E4+E5)/2 -> 0 | F6: =(F4+F5)/2 -> 0 | G6: =(G4+G5)/2 -> 0 | H6: =(H4+H5)/2 -> 0 | I6: =(I4+I5)/2 -> 0 | J6: =(J4+J5)/2 -> 0 | K6: =(K4+K5)/2 -> 0 | L6: =(L4+L5)/2 -> 26.2 | ... AF6: =(AF4+AF5)/2 -> 235
A7: Vineland NJ (DataOne) | B7: Mgmt figure | C7: as stated | L7: 100 | P7: 300
A8: Independence MO (Eastgate) | B8: Contracted MW | C8: gross/unknown | L8: 1200 | M8: 1200 | N8: 1200 | O8: 1200 | P8: 1200 | Q8: 1200 | R8: 1200 | S8: 1200 | T8: 1200 | U8: 1200 | V8: 1200 | W8: 1200 | X8: 1200 | Y8: 1200 | Z8: 1200 | AA8: 1200 | AB8: 1200 | AC8: 1200 | AD8: 1200 | AE8: 1200 | AF8: 1200
A9: Independence MO (Eastgate) | B9: Energized MW low | C9: stated/unknown | E9: 0 | F9: 0 | G9: 0 | H9: 0 | I9: 0 | J9: 0 | K9: 0 | L9: 0 | M9: 0 | N9: 0 | O9: 0 | P9: 0 | Q9: 0 | R9: 0 | S9: 0 | T9: 50 | U9: 50 | V9: 100 | W9: 100 | X9: 200 | Y9: 200 | Z9: 300 | AA9: 300 | AB9: 500 | AC9: 500 | AD9: 500 | AE9: 500 | AF9: 700
A10: Independence MO (Eastgate) | B10: Energized MW high | C10: stated/unknown | E10: 0 | F10: 0 | G10: 0 | H10: 0 | I10: 0 | J10: 0 | K10: 0 | L10: 0 | M10: 0 | N10: 0 | O10: 0 | P10: 0 | Q10: 0 | R10: 0 | S10: 100 | T10: 200 | U10: 200 | V10: 250 | W10: 250 | X10: 250 | Y10: 250 | Z10: 600 | AA10: 600 | AB10: 800 | AC10: 800 | AD10: 800 | AE10: 800 | AF10: 1200
A11: Independence MO (Eastgate) | B11: Energized MW base (=midpoint) | C11: stated/unknown | E11: =(E9+E10)/2 -> 0 | F11: =(F9+F10)/2 -> 0 | G11: =(G9+G10)/2 -> 0 | H11: =(H9+H10)/2 -> 0 | I11: =(I9+I10)/2 -> 0 | J11: =(J9+J10)/2 -> 0 | K11: =(K9+K10)/2 -> 0 | L11: =(L9+L10)/2 -> 0 | ... AF11: =(AF9+AF10)/2 -> 950
A12: Independence MO (Eastgate) | B12: Mgmt figure | C12: as stated | O12: IPL 200 MW late Q3 2026 | T12: operational 2027
A13: Butler Twp PA (Highridge) | B13: Contracted MW | C13: gross/unknown | N13: 1200 | O13: 1200 | P13: 1200 | Q13: 1200 | R13: 1200 | S13: 1200 | T13: 1200 | U13: 1200 | V13: 1200 | W13: 1200 | X13: 1200 | Y13: 1200 | Z13: 1200 | AA13: 1200 | AB13: 1200 | AC13: 1200 | AD13: 1200 | AE13: 1200 | AF13: 1200
A14: Butler Twp PA (Highridge) | B14: Energized MW low | C14: stated/unknown | E14: 0 | F14: 0 | G14: 0 | H14: 0 | I14: 0 | J14: 0 | K14: 0 | L14: 0 | M14: 0 | N14: 0 | O14: 0 | P14: 0 | Q14: 0 | R14: 0 | S14: 0 | T14: 0 | U14: 0 | V14: 0 | W14: 0 | X14: 130 | Y14: 130 | Z14: 260 | AA14: 260 | AB14: 400 | AC14: 400 | AD14: 400 | AE14: 400 | AF14: 660
A15: Butler Twp PA (Highridge) | B15: Energized MW high | C15: stated/unknown | E15: 0 | F15: 0 | G15: 0 | H15: 0 | I15: 0 | J15: 0 | K15: 0 | L15: 0 | M15: 0 | N15: 0 | O15: 0 | P15: 0 | Q15: 0 | R15: 0 | S15: 0 | T15: 130 | U15: 260 | V15: 260 | W15: 260 | X15: 400 | Y15: 400 | Z15: 660 | AA15: 660 | AB15: 1000 | AC15: 1000 | AD15: 1000 | AE15: 1000 | AF15: 1200
A16: Butler Twp PA (Highridge) | B16: Energized MW base (=midpoint) | C16: stated/unknown | E16: =(E14+E15)/2 -> 0 | F16: =(F14+F15)/2 -> 0 | G16: =(G14+G15)/2 -> 0 | H16: =(H14+H15)/2 -> 0 | I16: =(I14+I15)/2 -> 0 | J16: =(J14+J15)/2 -> 0 | K16: =(K14+K15)/2 -> 0 | L16: =(L14+L15)/2 -> 0 | ... AF16: =(AF14+AF15)/2 -> 930
A17: Butler Twp PA (Highridge) | B17: Mgmt figure | C17: as stated | T17: 260 | Y17: 660 | AB17: 1000
A18: Birmingham AL (BHM01, Oxmoor) | B18: Contracted MW | C18: gross/unknown | K18: 300 | L18: 300 | M18: 300 | N18: 300 | O18: 300 | P18: 300 | Q18: 300 | R18: 300 | S18: 300 | T18: 300 | U18: 300 | V18: 300 | W18: 300 | X18: 300 | Y18: 300 | Z18: 300 | AA18: 300 | AB18: 300 | AC18: 300 | AD18: 300 | AE18: 300 | AF18: 300
A19: Birmingham AL (BHM01, Oxmoor) | B19: Energized MW low | C19: stated/unknown | E19: 0 | F19: 0 | G19: 0 | H19: 0 | I19: 0 | J19: 0 | K19: 0 | L19: 0 | M19: 0 | N19: 0 | O19: 0 | P19: 0 | Q19: 0 | R19: 0 | S19: 25 | T19: 50 | U19: 50 | V19: 100 | W19: 100 | X19: 200 | Y19: 200 | Z19: 200 | AA19: 200 | AB19: 300 | AC19: 300 | AD19: 300 | AE19: 300 | AF19: 300
A20: Birmingham AL (BHM01, Oxmoor) | B20: Energized MW high | C20: stated/unknown | E20: 0 | F20: 0 | G20: 0 | H20: 0 | I20: 0 | J20: 0 | K20: 0 | L20: 0 | M20: 0 | N20: 0 | O20: 0 | P20: 0 | Q20: 25 | R20: 50 | S20: 75 | T20: 100 | U20: 100 | V20: 200 | W20: 200 | X20: 300 | Y20: 300 | Z20: 300 | AA20: 300 | AB20: 300 | AC20: 300 | AD20: 300 | AE20: 300 | AF20: 300
A21: Birmingham AL (BHM01, Oxmoor) | B21: Energized MW base (=midpoint) | C21: stated/unknown | E21: =(E19+E20)/2 -> 0 | F21: =(F19+F20)/2 -> 0 | G21: =(G19+G20)/2 -> 0 | H21: =(H19+H20)/2 -> 0 | I21: =(I19+I20)/2 -> 0 | J21: =(J19+J20)/2 -> 0 | K21: =(K19+K20)/2 -> 0 | L21: =(L19+L20)/2 -> 0 | ... AF21: =(AF19+AF20)/2 -> 300
A22: Birmingham AL (BHM01, Oxmoor) | B22: Mgmt figure | C22: as stated | P22: initial energization (MW n/d)
A23: Bethune FR (Azur Datacenter, ex-Bridgestone) | B23: Contracted MW | C23: gross/unknown | M23: 240 | N23: 240 | O23: 240 | P23: 240 | Q23: 240 | R23: 240 | S23: 240 | T23: 240 | U23: 240 | V23: 240 | W23: 240 | X23: 240 | Y23: 240 | Z23: 240 | AA23: 240 | AB23: 240 | AC23: 240 | AD23: 240 | AE23: 240 | AF23: 240
A24: Bethune FR (Azur Datacenter, ex-Bridgestone) | B24: Energized MW low | C24: stated/unknown | E24: 0 | F24: 0 | G24: 0 | H24: 0 | I24: 0 | J24: 0 | K24: 0 | L24: 0 | M24: 0 | N24: 0 | O24: 0 | P24: 0 | Q24: 27 | R24: 60 | S24: 60 | T24: 120 | U24: 120 | V24: 120 | W24: 120 | X24: 240 | Y24: 240 | Z24: 240 | AA24: 240 | AB24: 240 | AC24: 240 | AD24: 240 | AE24: 240 | AF24: 240
A25: Bethune FR (Azur Datacenter, ex-Bridgestone) | B25: Energized MW high | C25: stated/unknown | E25: 0 | F25: 0 | G25: 0 | H25: 0 | I25: 0 | J25: 0 | K25: 0 | L25: 0 | M25: 0 | N25: 0 | O25: 0 | P25: 60 | Q25: 120 | R25: 180 | S25: 180 | T25: 240 | U25: 240 | V25: 240 | W25: 240 | X25: 240 | Y25: 240 | Z25: 240 | AA25: 240 | AB25: 240 | AC25: 240 | AD25: 240 | AE25: 240 | AF25: 240
A26: Bethune FR (Azur Datacenter, ex-Bridgestone) | B26: Energized MW base (=midpoint) | C26: stated/unknown | E26: =(E24+E25)/2 -> 0 | F26: =(F24+F25)/2 -> 0 | G26: =(G24+G25)/2 -> 0 | H26: =(H24+H25)/2 -> 0 | I26: =(I24+I25)/2 -> 0 | J26: =(J24+J25)/2 -> 0 | K26: =(K24+K25)/2 -> 0 | L26: =(L24+L25)/2 -> 0 | ... AF26: =(AF24+AF25)/2 -> 240
A27: Bethune FR (Azur Datacenter, ex-Bridgestone) | B27: Mgmt figure | C27: as stated | O27: first capacity | P27: 120 | T27: 240
A28: Lappeenranta FI (Pajarila / Polarnode) | B28: Contracted MW | C28: gross/unknown | M28: 310 | N28: 310 | O28: 310 | P28: 310 | Q28: 310 | R28: 310 | S28: 310 | T28: 310 | U28: 310 | V28: 310 | W28: 310 | X28: 310 | Y28: 310 | Z28: 310 | AA28: 310 | AB28: 310 | AC28: 310 | AD28: 310 | AE28: 310 | AF28: 310
A29: Lappeenranta FI (Pajarila / Polarnode) | B29: Energized MW low | C29: stated/unknown | E29: 0 | F29: 0 | G29: 0 | H29: 0 | I29: 0 | J29: 0 | K29: 0 | L29: 0 | M29: 0 | N29: 0 | O29: 0 | P29: 0 | Q29: 0 | R29: 0 | S29: 0 | T29: 35 | U29: 35 | V29: 70 | W29: 70 | X29: 140 | Y29: 140 | Z29: 140 | AA29: 140 | AB29: 220 | AC29: 220 | AD29: 220 | AE29: 220 | AF29: 310
A30: Lappeenranta FI (Pajarila / Polarnode) | B30: Energized MW high | C30: stated/unknown | E30: 0 | F30: 0 | G30: 0 | H30: 0 | I30: 0 | J30: 0 | K30: 0 | L30: 0 | M30: 0 | N30: 0 | O30: 0 | P30: 0 | Q30: 0 | R30: 35 | S30: 70 | T30: 70 | U30: 70 | V30: 140 | W30: 140 | X30: 200 | Y30: 200 | Z30: 200 | AA30: 200 | AB30: 310 | AC30: 310 | AD30: 310 | AE30: 310 | AF30: 310
A31: Lappeenranta FI (Pajarila / Polarnode) | B31: Energized MW base (=midpoint) | C31: stated/unknown | E31: =(E29+E30)/2 -> 0 | F31: =(F29+F30)/2 -> 0 | G31: =(G29+G30)/2 -> 0 | H31: =(H29+H30)/2 -> 0 | I31: =(I29+I30)/2 -> 0 | J31: =(J29+J30)/2 -> 0 | K31: =(K29+K30)/2 -> 0 | L31: =(L29+L30)/2 -> 0 | ... AF31: =(AF29+AF30)/2 -> 310
A32: Lappeenranta FI (Pajarila / Polarnode) | B32: Mgmt figure | C32: as stated | T32: first capacity 2027
A33: Mantsala FI #1 | B33: Contracted MW | C33: gross/unknown | H33: 75 | I33: 75 | J33: 75 | K33: 75 | L33: 75 | M33: 75 | N33: 75 | O33: 75 | P33: 75 | Q33: 75 | R33: 75 | S33: 75 | T33: 75 | U33: 75 | V33: 75 | W33: 75 | X33: 75 | Y33: 75 | Z33: 75 | AA33: 75 | AB33: 75 | AC33: 75 | AD33: 75 | AE33: 75 | AF33: 75
A34: Mantsala FI #1 | B34: Energized MW low | C34: stated/unknown | E34: 25 | F34: 25 | G34: 25 | H34: 25 | I34: 25 | J34: 25 | K34: 25 | L34: 50 | M34: 75 | N34: 75 | O34: 75 | P34: 75 | Q34: 75 | R34: 75 | S34: 75 | T34: 75 | U34: 75 | V34: 75 | W34: 75 | X34: 75 | Y34: 75 | Z34: 75 | AA34: 75 | AB34: 75 | AC34: 75 | AD34: 75 | AE34: 75 | AF34: 75
A35: Mantsala FI #1 | B35: Energized MW high | C35: stated/unknown | E35: 25 | F35: 25 | G35: 25 | H35: 25 | I35: 25 | J35: 25 | K35: 50 | L35: 75 | M35: 75 | N35: 75 | O35: 75 | P35: 75 | Q35: 75 | R35: 75 | S35: 75 | T35: 75 | U35: 75 | V35: 75 | W35: 75 | X35: 75 | Y35: 75 | Z35: 75 | AA35: 75 | AB35: 75 | AC35: 75 | AD35: 75 | AE35: 75 | AF35: 75
A36: Mantsala FI #1 | B36: Energized MW base (=midpoint) | C36: stated/unknown | E36: =(E34+E35)/2 -> 25 | F36: =(F34+F35)/2 -> 25 | G36: =(G34+G35)/2 -> 25 | H36: =(H34+H35)/2 -> 25 | I36: =(I34+I35)/2 -> 25 | J36: =(J34+J35)/2 -> 25 | K36: =(K34+K35)/2 -> 37.5 | L36: =(L34+L35)/2 -> 62.5 | ... AF36: =(AF34+AF35)/2 -> 75
A37: Mantsala FI #1 | B37: Mgmt figure | C37: as stated | L37: 75
A38: Mantsala FI #2 (Kapuli) | B38: Contracted MW | C38: gross/unknown | N38: 70 | O38: 70 | P38: 70 | Q38: 70 | R38: 70 | S38: 70 | T38: 70 | U38: 70 | V38: 70 | W38: 70 | X38: 70 | Y38: 70 | Z38: 70 | AA38: 70 | AB38: 70 | AC38: 70 | AD38: 70 | AE38: 70 | AF38: 70
A39: Mantsala FI #2 (Kapuli) | B39: Energized MW low | C39: stated/unknown | E39: 0 | F39: 0 | G39: 0 | H39: 0 | I39: 0 | J39: 0 | K39: 0 | L39: 0 | M39: 0 | N39: 0 | O39: 0 | P39: 0 | Q39: 0 | R39: 0 | S39: 0 | T39: 0 | U39: 35 | V39: 70 | W39: 70 | X39: 70 | Y39: 70 | Z39: 70 | AA39: 70 | AB39: 70 | AC39: 70 | AD39: 70 | AE39: 70 | AF39: 70
A40: Mantsala FI #2 (Kapuli) | B40: Energized MW high | C40: stated/unknown | E40: 0 | F40: 0 | G40: 0 | H40: 0 | I40: 0 | J40: 0 | K40: 0 | L40: 0 | M40: 0 | N40: 0 | O40: 0 | P40: 0 | Q40: 0 | R40: 0 | S40: 0 | T40: 35 | U40: 70 | V40: 70 | W40: 70 | X40: 70 | Y40: 70 | Z40: 70 | AA40: 70 | AB40: 70 | AC40: 70 | AD40: 70 | AE40: 70 | AF40: 70
A41: Mantsala FI #2 (Kapuli) | B41: Energized MW base (=midpoint) | C41: stated/unknown | E41: =(E39+E40)/2 -> 0 | F41: =(F39+F40)/2 -> 0 | G41: =(G39+G40)/2 -> 0 | H41: =(H39+H40)/2 -> 0 | I41: =(I39+I40)/2 -> 0 | J41: =(J39+J40)/2 -> 0 | K41: =(K39+K40)/2 -> 0 | L41: =(L39+L40)/2 -> 0 | ... AF41: =(AF39+AF40)/2 -> 70
A42: Mantsala FI #2 (Kapuli) | B42: Mgmt figure | C42: as stated | T42: from 2027
A43: Kansas City MO (Patmos) | B43: Contracted MW | C43: gross/unknown | H43: 40 | I43: 40 | J43: 40 | K43: 40 | L43: 40 | M43: 40 | N43: 40 | O43: 40 | P43: 40 | Q43: 40 | R43: 40 | S43: 40 | T43: 40 | U43: 40 | V43: 40 | W43: 40 | X43: 40 | Y43: 40 | Z43: 40 | AA43: 40 | AB43: 40 | AC43: 40 | AD43: 40 | AE43: 40 | AF43: 40
A44: Kansas City MO (Patmos) | B44: Energized MW low | C44: stated/unknown | E44: 0 | F44: 0 | G44: 0 | H44: 0 | I44: 5 | J44: 5 | K44: 5 | L44: 5 | M44: 5 | N44: 5 | O44: 5 | P44: 5 | Q44: 5 | R44: 5 | S44: 5 | T44: 20 | U44: 20 | V44: 20 | W44: 20 | X44: 20 | Y44: 20 | Z44: 20 | AA44: 20 | AB44: 20 | AC44: 20 | AD44: 20 | AE44: 20 | AF44: 20
A45: Kansas City MO (Patmos) | B45: Energized MW high | C45: stated/unknown | E45: 0 | F45: 0 | G45: 0 | H45: 0 | I45: 15 | J45: 15 | K45: 15 | L45: 35 | M45: 35 | N45: 35 | O45: 35 | P45: 35 | Q45: 35 | R45: 35 | S45: 35 | T45: 40 | U45: 40 | V45: 40 | W45: 40 | X45: 40 | Y45: 40 | Z45: 40 | AA45: 40 | AB45: 40 | AC45: 40 | AD45: 40 | AE45: 40 | AF45: 40
A46: Kansas City MO (Patmos) | B46: Energized MW base (=midpoint) | C46: stated/unknown | E46: =(E44+E45)/2 -> 0 | F46: =(F44+F45)/2 -> 0 | G46: =(G44+G45)/2 -> 0 | H46: =(H44+H45)/2 -> 0 | I46: =(I44+I45)/2 -> 10 | J46: =(J44+J45)/2 -> 10 | K46: =(K44+K45)/2 -> 10 | L46: =(L44+L45)/2 -> 20 | ... AF46: =(AF44+AF45)/2 -> 30
A47: Kansas City MO (Patmos) | B47: Mgmt figure | C47: as stated | I47: 5
A48: Paris (Equinix PA10) | B48: Contracted MW | C48: gross/unknown | G48: 5 | H48: 5 | I48: 5 | J48: 5 | K48: 5 | L48: 5 | M48: 5 | N48: 5 | O48: 5 | P48: 5 | Q48: 5 | R48: 5 | S48: 5 | T48: 5 | U48: 5 | V48: 5 | W48: 5 | X48: 5 | Y48: 5 | Z48: 5 | AA48: 5 | AB48: 5 | AC48: 5 | AD48: 5 | AE48: 5 | AF48: 5
A49: Paris (Equinix PA10) | B49: Energized MW low | C49: stated/unknown | E49: 0 | F49: 0 | G49: 0 | H49: 5 | I49: 5 | J49: 5 | K49: 5 | L49: 5 | M49: 5 | N49: 5 | O49: 5 | P49: 5 | Q49: 5 | R49: 5 | S49: 5 | T49: 5 | U49: 5 | V49: 5 | W49: 5 | X49: 5 | Y49: 5 | Z49: 5 | AA49: 5 | AB49: 5 | AC49: 5 | AD49: 5 | AE49: 5 | AF49: 5
A50: Paris (Equinix PA10) | B50: Energized MW high | C50: stated/unknown | E50: 0 | F50: 0 | G50: 0 | H50: 5 | I50: 5 | J50: 5 | K50: 5 | L50: 5 | M50: 5 | N50: 5 | O50: 5 | P50: 5 | Q50: 5 | R50: 5 | S50: 5 | T50: 5 | U50: 5 | V50: 5 | W50: 5 | X50: 5 | Y50: 5 | Z50: 5 | AA50: 5 | AB50: 5 | AC50: 5 | AD50: 5 | AE50: 5 | AF50: 5
A51: Paris (Equinix PA10) | B51: Energized MW base (=midpoint) | C51: stated/unknown | E51: =(E49+E50)/2 -> 0 | F51: =(F49+F50)/2 -> 0 | G51: =(G49+G50)/2 -> 0 | H51: =(H49+H50)/2 -> 5 | I51: =(I49+I50)/2 -> 5 | J51: =(J49+J50)/2 -> 5 | K51: =(K49+K50)/2 -> 5 | L51: =(L49+L50)/2 -> 5 | ... AF51: =(AF49+AF50)/2 -> 5
A52: Paris (Equinix PA10) | B52: Mgmt figure | C52: as stated
A53: Keflavik IS (Verne) | B53: Contracted MW | C53: gross/unknown | H53: 10 | I53: 10 | J53: 10 | K53: 10 | L53: 10 | M53: 10 | N53: 10 | O53: 10 | P53: 10 | Q53: 10 | R53: 10 | S53: 10 | T53: 10 | U53: 10 | V53: 10 | W53: 10 | X53: 10 | Y53: 10 | Z53: 10 | AA53: 10 | AB53: 10 | AC53: 10 | AD53: 10 | AE53: 10 | AF53: 10
A54: Keflavik IS (Verne) | B54: Energized MW low | C54: stated/unknown | E54: 0 | F54: 0 | G54: 0 | H54: 0 | I54: 10 | J54: 10 | K54: 10 | L54: 10 | M54: 10 | N54: 10 | O54: 10 | P54: 10 | Q54: 10 | R54: 10 | S54: 10 | T54: 10 | U54: 10 | V54: 10 | W54: 10 | X54: 10 | Y54: 10 | Z54: 10 | AA54: 10 | AB54: 10 | AC54: 10 | AD54: 10 | AE54: 10 | AF54: 10
A55: Keflavik IS (Verne) | B55: Energized MW high | C55: stated/unknown | E55: 0 | F55: 0 | G55: 0 | H55: 0 | I55: 10 | J55: 10 | K55: 10 | L55: 10 | M55: 10 | N55: 10 | O55: 10 | P55: 10 | Q55: 10 | R55: 10 | S55: 10 | T55: 10 | U55: 10 | V55: 10 | W55: 10 | X55: 10 | Y55: 10 | Z55: 10 | AA55: 10 | AB55: 10 | AC55: 10 | AD55: 10 | AE55: 10 | AF55: 10
A56: Keflavik IS (Verne) | B56: Energized MW base (=midpoint) | C56: stated/unknown | E56: =(E54+E55)/2 -> 0 | F56: =(F54+F55)/2 -> 0 | G56: =(G54+G55)/2 -> 0 | H56: =(H54+H55)/2 -> 0 | I56: =(I54+I55)/2 -> 10 | J56: =(J54+J55)/2 -> 10 | K56: =(K54+K55)/2 -> 10 | L56: =(L54+L55)/2 -> 10 | ... AF56: =(AF54+AF55)/2 -> 10
A57: Keflavik IS (Verne) | B57: Mgmt figure | C57: as stated
A58: London Longcross (Ark LP01) | B58: Contracted MW | C58: gross/unknown | J58: 16 | K58: 16 | L58: 16 | M58: 16 | N58: 19 | O58: 19 | P58: 19 | Q58: 19 | R58: 19 | S58: 19 | T58: 19 | U58: 19 | V58: 19 | W58: 19 | X58: 19 | Y58: 19 | Z58: 19 | AA58: 19 | AB58: 19 | AC58: 19 | AD58: 19 | AE58: 19 | AF58: 19
A59: London Longcross (Ark LP01) | B59: Energized MW low | C59: stated/unknown | E59: 0 | F59: 0 | G59: 0 | H59: 0 | I59: 0 | J59: 0 | K59: 0 | L59: 16 | M59: 16 | N59: 16 | O59: 16 | P59: 16 | Q59: 19 | R59: 19 | S59: 19 | T59: 19 | U59: 19 | V59: 19 | W59: 19 | X59: 19 | Y59: 19 | Z59: 19 | AA59: 19 | AB59: 19 | AC59: 19 | AD59: 19 | AE59: 19 | AF59: 19
A60: London Longcross (Ark LP01) | B60: Energized MW high | C60: stated/unknown | E60: 0 | F60: 0 | G60: 0 | H60: 0 | I60: 0 | J60: 0 | K60: 0 | L60: 16 | M60: 16 | N60: 16 | O60: 16 | P60: 19 | Q60: 19 | R60: 19 | S60: 19 | T60: 19 | U60: 19 | V60: 19 | W60: 19 | X60: 19 | Y60: 19 | Z60: 19 | AA60: 19 | AB60: 19 | AC60: 19 | AD60: 19 | AE60: 19 | AF60: 19
A61: London Longcross (Ark LP01) | B61: Energized MW base (=midpoint) | C61: stated/unknown | E61: =(E59+E60)/2 -> 0 | F61: =(F59+F60)/2 -> 0 | G61: =(G59+G60)/2 -> 0 | H61: =(H59+H60)/2 -> 0 | I61: =(I59+I60)/2 -> 0 | J61: =(J59+J60)/2 -> 0 | K61: =(K59+K60)/2 -> 0 | L61: =(L59+L60)/2 -> 16 | ... AF61: =(AF59+AF60)/2 -> 19
A62: London Longcross (Ark LP01) | B62: Mgmt figure | C62: as stated | L62: 16 | P62: 19
A63: Harlow UK (Kao Data KLON-02/03) | B63: Contracted MW | C63: gross/unknown | N63: 22 | O63: 22 | P63: 22 | Q63: 22 | R63: 22 | S63: 22 | T63: 22 | U63: 22 | V63: 22 | W63: 22 | X63: 22 | Y63: 22 | Z63: 22 | AA63: 22 | AB63: 22 | AC63: 22 | AD63: 22 | AE63: 22 | AF63: 22
A64: Harlow UK (Kao Data KLON-02/03) | B64: Energized MW low | C64: stated/unknown | E64: 0 | F64: 0 | G64: 0 | H64: 0 | I64: 0 | J64: 0 | K64: 0 | L64: 0 | M64: 0 | N64: 0 | O64: 0 | P64: 0 | Q64: 4.4 | R64: 4.4 | S64: 22 | T64: 22 | U64: 22 | V64: 22 | W64: 22 | X64: 22 | Y64: 22 | Z64: 22 | AA64: 22 | AB64: 22 | AC64: 22 | AD64: 22 | AE64: 22 | AF64: 22
A65: Harlow UK (Kao Data KLON-02/03) | B65: Energized MW high | C65: stated/unknown | E65: 0 | F65: 0 | G65: 0 | H65: 0 | I65: 0 | J65: 0 | K65: 0 | L65: 0 | M65: 0 | N65: 0 | O65: 0 | P65: 4.4 | Q65: 22 | R65: 22 | S65: 22 | T65: 22 | U65: 22 | V65: 22 | W65: 22 | X65: 22 | Y65: 22 | Z65: 22 | AA65: 22 | AB65: 22 | AC65: 22 | AD65: 22 | AE65: 22 | AF65: 22
A66: Harlow UK (Kao Data KLON-02/03) | B66: Energized MW base (=midpoint) | C66: stated/unknown | E66: =(E64+E65)/2 -> 0 | F66: =(F64+F65)/2 -> 0 | G66: =(G64+G65)/2 -> 0 | H66: =(H64+H65)/2 -> 0 | I66: =(I64+I65)/2 -> 0 | J66: =(J64+J65)/2 -> 0 | K66: =(K64+K65)/2 -> 0 | L66: =(L64+L65)/2 -> 0 | ... AF66: =(AF64+AF65)/2 -> 22
A67: Harlow UK (Kao Data KLON-02/03) | B67: Mgmt figure | C67: as stated | T67: 22
A68: Newport UK (Vantage CWL1) | B68: Contracted MW | C68: gross/unknown | E68: n/d | F68: n/d | G68: n/d | H68: n/d | I68: n/d | J68: n/d | K68: n/d | L68: n/d | M68: n/d | N68: n/d | O68: n/d | P68: n/d | Q68: n/d | R68: n/d | S68: n/d | T68: n/d | U68: n/d | V68: n/d | W68: n/d | X68: n/d | Y68: n/d | Z68: n/d | AA68: n/d | AB68: n/d | AC68: n/d | AD68: n/d | AE68: n/d | AF68: n/d
A69: Newport UK (Vantage CWL1) | B69: Energized MW low | C69: stated/unknown | E69: 0 | F69: 0 | G69: 0 | H69: 0 | I69: 0 | J69: 0 | K69: 0 | L69: 0 | M69: 0 | N69: 0 | O69: 0 | P69: 0 | Q69: 5 | R69: 10 | S69: 15 | T69: 20 | U69: 20 | V69: 20 | W69: 20 | X69: 20 | Y69: 20 | Z69: 20 | AA69: 20 | AB69: 20 | AC69: 20 | AD69: 20 | AE69: 20 | AF69: 20
A70: Newport UK (Vantage CWL1) | B70: Energized MW high | C70: stated/unknown | E70: 0 | F70: 0 | G70: 0 | H70: 0 | I70: 0 | J70: 0 | K70: 0 | L70: 0 | M70: 0 | N70: 0 | O70: 0 | P70: 10 | Q70: 25 | R70: 35 | S70: 43 | T70: 43 | U70: 43 | V70: 43 | W70: 43 | X70: 43 | Y70: 43 | Z70: 43 | AA70: 43 | AB70: 43 | AC70: 43 | AD70: 43 | AE70: 43 | AF70: 43
A71: Newport UK (Vantage CWL1) | B71: Energized MW base (=midpoint) | C71: stated/unknown | E71: =(E69+E70)/2 -> 0 | F71: =(F69+F70)/2 -> 0 | G71: =(G69+G70)/2 -> 0 | H71: =(H69+H70)/2 -> 0 | I71: =(I69+I70)/2 -> 0 | J71: =(J69+J70)/2 -> 0 | K71: =(K69+K70)/2 -> 0 | L71: =(L69+L70)/2 -> 0 | ... AF71: =(AF69+AF70)/2 -> 31.5
A72: Newport UK (Vantage CWL1) | B72: Mgmt figure | C72: as stated | T72: 43 incl. UK3 (Derived)
A73: UK 3rd new deployment (lead: Green Mountain LON-East, Romford) | B73: Contracted MW | C73: gross/unknown | E73: n/d | F73: n/d | G73: n/d | H73: n/d | I73: n/d | J73: n/d | K73: n/d | L73: n/d | M73: n/d | N73: n/d | O73: n/d | P73: n/d | Q73: n/d | R73: n/d | S73: n/d | T73: n/d | U73: n/d | V73: n/d | W73: n/d | X73: n/d | Y73: n/d | Z73: n/d | AA73: n/d | AB73: n/d | AC73: n/d | AD73: n/d | AE73: n/d | AF73: n/d
A74: UK 3rd new deployment (lead: Green Mountain LON-East, Romford) | B74: Energized MW low | C74: stated/unknown | E74: 0 | F74: 0 | G74: 0 | H74: 0 | I74: 0 | J74: 0 | K74: 0 | L74: 0 | M74: 0 | N74: 0 | O74: 0 | P74: 0 | Q74: 0 | R74: 0 | S74: 0 | T74: 0 | U74: 0 | V74: 0 | W74: 0 | X74: 0 | Y74: 0 | Z74: 0 | AA74: 0 | AB74: 0 | AC74: 0 | AD74: 0 | AE74: 0 | AF74: 0
A75: UK 3rd new deployment (lead: Green Mountain LON-East, Romford) | B75: Energized MW high | C75: stated/unknown | E75: 0 | F75: 0 | G75: 0 | H75: 0 | I75: 0 | J75: 0 | K75: 0 | L75: 0 | M75: 0 | N75: 0 | O75: 0 | P75: 0 | Q75: 0 | R75: 5 | S75: 12 | T75: 14 | U75: 14 | V75: 14 | W75: 14 | X75: 14 | Y75: 14 | Z75: 14 | AA75: 14 | AB75: 14 | AC75: 14 | AD75: 14 | AE75: 14 | AF75: 14
A76: UK 3rd new deployment (lead: Green Mountain LON-East, Romford) | B76: Energized MW base (=midpoint) | C76: stated/unknown | E76: =(E74+E75)/2 -> 0 | F76: =(F74+F75)/2 -> 0 | G76: =(G74+G75)/2 -> 0 | H76: =(H74+H75)/2 -> 0 | I76: =(I74+I75)/2 -> 0 | J76: =(J74+J75)/2 -> 0 | K76: =(K74+K75)/2 -> 0 | L76: =(L74+L75)/2 -> 0 | ... AF76: =(AF74+AF75)/2 -> 7
A77: UK 3rd new deployment (lead: Green Mountain LON-East, Romford) | B77: Mgmt figure | C77: as stated
A78: Modi'in IL (Mega Or) | B78: Contracted MW | C78: gross/unknown | J78: 8 | K78: 8 | L78: 8 | M78: 8 | N78: 8 | O78: 8 | P78: 8 | Q78: 8 | R78: 8 | S78: 8 | T78: 8 | U78: 8 | V78: 8 | W78: 8 | X78: 8 | Y78: 8 | Z78: 8 | AA78: 8 | AB78: 8 | AC78: 8 | AD78: 8 | AE78: 8 | AF78: 8
A79: Modi'in IL (Mega Or) | B79: Energized MW low | C79: IT | E79: 0 | F79: 0 | G79: 0 | H79: 0 | I79: 0 | J79: 0 | K79: 0 | L79: 8 | M79: 8 | N79: 8 | O79: 8 | P79: 8 | Q79: 8 | R79: 8 | S79: 8 | T79: 8 | U79: 8 | V79: 8 | W79: 8 | X79: 8 | Y79: 8 | Z79: 8 | AA79: 8 | AB79: 8 | AC79: 8 | AD79: 8 | AE79: 8 | AF79: 8
A80: Modi'in IL (Mega Or) | B80: Energized MW high | C80: IT | E80: 0 | F80: 0 | G80: 0 | H80: 0 | I80: 0 | J80: 0 | K80: 0 | L80: 8 | M80: 8 | N80: 8 | O80: 8 | P80: 8 | Q80: 8 | R80: 8 | S80: 8 | T80: 8 | U80: 8 | V80: 8 | W80: 8 | X80: 8 | Y80: 8 | Z80: 8 | AA80: 8 | AB80: 8 | AC80: 8 | AD80: 8 | AE80: 8 | AF80: 8
A81: Modi'in IL (Mega Or) | B81: Energized MW base (=midpoint) | C81: IT | E81: =(E79+E80)/2 -> 0 | F81: =(F79+F80)/2 -> 0 | G81: =(G79+G80)/2 -> 0 | H81: =(H79+H80)/2 -> 0 | I81: =(I79+I80)/2 -> 0 | J81: =(J79+J80)/2 -> 0 | K81: =(K79+K80)/2 -> 0 | L81: =(L79+L80)/2 -> 8 | ... AF81: =(AF79+AF80)/2 -> 8
A82: Modi'in IL (Mega Or) | B82: Mgmt figure | C82: as stated
A83: Masmiyya IL (Mega DC) | B83: Contracted MW | C83: gross/unknown | M83: 22 | N83: 22 | O83: 22 | P83: 22 | Q83: 22 | R83: 22 | S83: 22 | T83: 22 | U83: 22 | V83: 22 | W83: 22 | X83: 22 | Y83: 22 | Z83: 22 | AA83: 22 | AB83: 22 | AC83: 22 | AD83: 22 | AE83: 22 | AF83: 22
A84: Masmiyya IL (Mega DC) | B84: Energized MW low | C84: stated/unknown | E84: 0 | F84: 0 | G84: 0 | H84: 0 | I84: 0 | J84: 0 | K84: 0 | L84: 0 | M84: 0 | N84: 0 | O84: 0 | P84: 0 | Q84: 0 | R84: 11 | S84: 22 | T84: 22 | U84: 22 | V84: 22 | W84: 22 | X84: 22 | Y84: 22 | Z84: 22 | AA84: 22 | AB84: 22 | AC84: 22 | AD84: 22 | AE84: 22 | AF84: 22
A85: Masmiyya IL (Mega DC) | B85: Energized MW high | C85: stated/unknown | E85: 0 | F85: 0 | G85: 0 | H85: 0 | I85: 0 | J85: 0 | K85: 0 | L85: 0 | M85: 0 | N85: 0 | O85: 0 | P85: 11 | Q85: 22 | R85: 22 | S85: 22 | T85: 22 | U85: 22 | V85: 22 | W85: 22 | X85: 22 | Y85: 22 | Z85: 22 | AA85: 22 | AB85: 22 | AC85: 22 | AD85: 22 | AE85: 22 | AF85: 22
A86: Masmiyya IL (Mega DC) | B86: Energized MW base (=midpoint) | C86: stated/unknown | E86: =(E84+E85)/2 -> 0 | F86: =(F84+F85)/2 -> 0 | G86: =(G84+G85)/2 -> 0 | H86: =(H84+H85)/2 -> 0 | I86: =(I84+I85)/2 -> 0 | J86: =(J84+J85)/2 -> 0 | K86: =(K84+K85)/2 -> 0 | L86: =(L84+L85)/2 -> 0 | ... AF86: =(AF84+AF85)/2 -> 22
A87: Masmiyya IL (Mega DC) | B87: Mgmt figure | C87: as stated | O87: 22
A88: Beit Shemesh IL (Mega DC) | B88: Contracted MW | C88: gross/unknown | M88: 58 | N88: 58 | O88: 58 | P88: 58 | Q88: 58 | R88: 58 | S88: 58 | T88: 58 | U88: 58 | V88: 58 | W88: 58 | X88: 58 | Y88: 58 | Z88: 58 | AA88: 58 | AB88: 58 | AC88: 58 | AD88: 58 | AE88: 58 | AF88: 58
A89: Beit Shemesh IL (Mega DC) | B89: Energized MW low | C89: stated/unknown | E89: 0 | F89: 0 | G89: 0 | H89: 0 | I89: 0 | J89: 0 | K89: 0 | L89: 0 | M89: 0 | N89: 0 | O89: 0 | P89: 0 | Q89: 0 | R89: 20 | S89: 39 | T89: 58 | U89: 58 | V89: 58 | W89: 58 | X89: 58 | Y89: 58 | Z89: 58 | AA89: 58 | AB89: 58 | AC89: 58 | AD89: 58 | AE89: 58 | AF89: 58
A90: Beit Shemesh IL (Mega DC) | B90: Energized MW high | C90: stated/unknown | E90: 0 | F90: 0 | G90: 0 | H90: 0 | I90: 0 | J90: 0 | K90: 0 | L90: 0 | M90: 0 | N90: 0 | O90: 0 | P90: 0 | Q90: 20 | R90: 39 | S90: 58 | T90: 58 | U90: 58 | V90: 58 | W90: 58 | X90: 58 | Y90: 58 | Z90: 58 | AA90: 58 | AB90: 58 | AC90: 58 | AD90: 58 | AE90: 58 | AF90: 58
A91: Beit Shemesh IL (Mega DC) | B91: Energized MW base (=midpoint) | C91: stated/unknown | E91: =(E89+E90)/2 -> 0 | F91: =(F89+F90)/2 -> 0 | G91: =(G89+G90)/2 -> 0 | H91: =(H89+H90)/2 -> 0 | I91: =(I89+I90)/2 -> 0 | J91: =(J89+J90)/2 -> 0 | K91: =(K89+K90)/2 -> 0 | L91: =(L89+L90)/2 -> 0 | ... AF91: =(AF89+AF90)/2 -> 58
A92: Beit Shemesh IL (Mega DC) | B92: Mgmt figure | C92: as stated | Q92: 58
A93: Madrid-Getafe ES (Merlin Edged) | B93: Contracted MW | C93: gross/unknown | N93: 18 | O93: 18 | P93: 18 | Q93: 18 | R93: 18 | S93: 18 | T93: 18 | U93: 18 | V93: 18 | W93: 18 | X93: 18 | Y93: 18 | Z93: 18 | AA93: 18 | AB93: 18 | AC93: 18 | AD93: 18 | AE93: 18 | AF93: 18
A94: Madrid-Getafe ES (Merlin Edged) | B94: Energized MW low | C94: stated/unknown | E94: 0 | F94: 0 | G94: 0 | H94: 0 | I94: 0 | J94: 0 | K94: 0 | L94: 0 | M94: 0 | N94: 0 | O94: 6 | P94: 9 | Q94: 18 | R94: 18 | S94: 18 | T94: 18 | U94: 18 | V94: 18 | W94: 18 | X94: 18 | Y94: 18 | Z94: 18 | AA94: 18 | AB94: 18 | AC94: 18 | AD94: 18 | AE94: 18 | AF94: 18
A95: Madrid-Getafe ES (Merlin Edged) | B95: Energized MW high | C95: stated/unknown | E95: 0 | F95: 0 | G95: 0 | H95: 0 | I95: 0 | J95: 0 | K95: 0 | L95: 0 | M95: 0 | N95: 0 | O95: 9 | P95: 18 | Q95: 18 | R95: 18 | S95: 18 | T95: 18 | U95: 18 | V95: 18 | W95: 18 | X95: 18 | Y95: 18 | Z95: 18 | AA95: 18 | AB95: 18 | AC95: 18 | AD95: 18 | AE95: 18 | AF95: 18
A96: Madrid-Getafe ES (Merlin Edged) | B96: Energized MW base (=midpoint) | C96: stated/unknown | E96: =(E94+E95)/2 -> 0 | F96: =(F94+F95)/2 -> 0 | G96: =(G94+G95)/2 -> 0 | H96: =(H94+H95)/2 -> 0 | I96: =(I94+I95)/2 -> 0 | J96: =(J94+J95)/2 -> 0 | K96: =(K94+K95)/2 -> 0 | L96: =(L94+L95)/2 -> 0 | ... AF96: =(AF94+AF95)/2 -> 18
A97: Madrid-Getafe ES (Merlin Edged) | B97: Mgmt figure | C97: as stated | O97: 18
A98: Tallinn EE (Greenergy Huuru) | B98: Contracted MW | C98: gross/unknown | N98: 22 | O98: 22 | P98: 22 | Q98: 22 | R98: 22 | S98: 22 | T98: 22 | U98: 22 | V98: 22 | W98: 22 | X98: 22 | Y98: 22 | Z98: 22 | AA98: 22 | AB98: 22 | AC98: 22 | AD98: 22 | AE98: 22 | AF98: 22
A99: Tallinn EE (Greenergy Huuru) | B99: Energized MW low | C99: stated/unknown | E99: 0 | F99: 0 | G99: 0 | H99: 0 | I99: 0 | J99: 0 | K99: 0 | L99: 0 | M99: 0 | N99: 0 | O99: 0 | P99: 0 | Q99: 11 | R99: 22 | S99: 22 | T99: 22 | U99: 22 | V99: 22 | W99: 22 | X99: 22 | Y99: 22 | Z99: 22 | AA99: 22 | AB99: 22 | AC99: 22 | AD99: 22 | AE99: 22 | AF99: 22
A100: Tallinn EE (Greenergy Huuru) | B100: Energized MW high | C100: stated/unknown | E100: 0 | F100: 0 | G100: 0 | H100: 0 | I100: 0 | J100: 0 | K100: 0 | L100: 0 | M100: 0 | N100: 0 | O100: 0 | P100: 22 | Q100: 22 | R100: 22 | S100: 22 | T100: 22 | U100: 22 | V100: 22 | W100: 22 | X100: 22 | Y100: 22 | Z100: 22 | AA100: 22 | AB100: 22 | AC100: 22 | AD100: 22 | AE100: 22 | AF100: 22
...

Sheet GPUs deployed
A1: Generation | B1: GPUs per IT MW (base) | C1: GPUs per gross MW (base) | D1: Source cell | E1: Tag
A2: Hopper H100/H200 | B2: 713 | C2: 548.5 | D2: GPUsPerMW!I6 / L6 | E2: Estimated
A3: B200 (HGX) | B3: 508.6 | C3: 391.2 | D3: GPUsPerMW!I9 / L9 | E3: Estimated
A4: B300 (HGX) | B4: 501.6 | C4: 385.8 | D4: GPUsPerMW!I15 / L15 | E4: Estimated
A5: GB300 NVL72 | B5: 491.2 | C5: 409.3 | D5: GPUsPerMW!I18 / L18 | E5: Estimated
A6: Vera Rubin NVL72 | B6: 320 | C6: 267 | D6: GPUsPerMW!I21 / L21 | E6: Estimated
A8: RTX PRO 6000 not modeled in gpu_mw_capex.xlsx -> Madrid phase 1 / KC RTX share treated as B300/B200 (Estimated).
A10: Site | B10: Generation | C10: MW basis col | D10: Note | E10: Q1 2024 | F10: Q2 2024 | G10: Q3 2024 | H10: Q4 2024 | I10: Q1 2025 | J10: Q2 2025 | K10: Q3 2025 | L10: Q4 2025 | M10: Q1 2026 | N10: Q2 2026 | O10: Q3 2026 | P10: Q4 2026 | Q10: Q1 2027 | R10: Q2 2027 | S10: Q3 2027 | T10: Q4 2027 | U10: Q1 2028 | V10: Q2 2028 | W10: Q3 2028 | X10: Q4 2028 | Y10: Q1 2029 | Z10: Q2 2029 | AA10: Q3 2029 | AB10: Q4 2029 | AC10: Q1 2030 | AD10: Q2 2030 | AE10: Q3 2030 | AF10: Q4 2030
A11: Vineland NJ (DataOne) | B11: GB300 NVL72 | C11: IT | E11: =ROUND('Quarterly MW'!E6*$B$5,0) -> 0 | F11: =ROUND('Quarterly MW'!F6*$B$5,0) -> 0 | G11: =ROUND('Quarterly MW'!G6*$B$5,0) -> 0 | H11: =ROUND('Quarterly MW'!H6*$B$5,0) -> 0 | I11: =ROUND('Quarterly MW'!I6*$B$5,0) -> 0 | J11: =ROUND('Quarterly MW'!J6*$B$5,0) -> 0 | K11: =ROUND('Quarterly MW'!K6*$B$5,0) -> 0 | L11: =ROUND('Quarterly MW'!L6*$B$5,0) -> 12869 | ... AF11: =ROUND('Quarterly MW'!AF6*$B$5,0) -> 115432
A12: Independence MO (Eastgate) | B12: Vera Rubin NVL72 | C12: gross | E12: =ROUND('Quarterly MW'!E11*$C$6,0) -> 0 | F12: =ROUND('Quarterly MW'!F11*$C$6,0) -> 0 | G12: =ROUND('Quarterly MW'!G11*$C$6,0) -> 0 | H12: =ROUND('Quarterly MW'!H11*$C$6,0) -> 0 | I12: =ROUND('Quarterly MW'!I11*$C$6,0) -> 0 | J12: =ROUND('Quarterly MW'!J11*$C$6,0) -> 0 | K12: =ROUND('Quarterly MW'!K11*$C$6,0) -> 0 | L12: =ROUND('Quarterly MW'!L11*$C$6,0) -> 0 | ... AF12: =ROUND('Quarterly MW'!AF11*$C$6,0) -> 253650
A13: Butler Twp PA (Highridge) | B13: Vera Rubin NVL72 | C13: gross | E13: =ROUND('Quarterly MW'!E16*$C$6,0) -> 0 | F13: =ROUND('Quarterly MW'!F16*$C$6,0) -> 0 | G13: =ROUND('Quarterly MW'!G16*$C$6,0) -> 0 | H13: =ROUND('Quarterly MW'!H16*$C$6,0) -> 0 | I13: =ROUND('Quarterly MW'!I16*$C$6,0) -> 0 | J13: =ROUND('Quarterly MW'!J16*$C$6,0) -> 0 | K13: =ROUND('Quarterly MW'!K16*$C$6,0) -> 0 | L13: =ROUND('Quarterly MW'!L16*$C$6,0) -> 0 | ... AF13: =ROUND('Quarterly MW'!AF16*$C$6,0) -> 248310
A14: Birmingham AL (BHM01, Oxmoor) | B14: Vera Rubin NVL72 | C14: gross | E14: =ROUND('Quarterly MW'!E21*$C$6,0) -> 0 | F14: =ROUND('Quarterly MW'!F21*$C$6,0) -> 0 | G14: =ROUND('Quarterly MW'!G21*$C$6,0) -> 0 | H14: =ROUND('Quarterly MW'!H21*$C$6,0) -> 0 | I14: =ROUND('Quarterly MW'!I21*$C$6,0) -> 0 | J14: =ROUND('Quarterly MW'!J21*$C$6,0) -> 0 | K14: =ROUND('Quarterly MW'!K21*$C$6,0) -> 0 | L14: =ROUND('Quarterly MW'!L21*$C$6,0) -> 0 | ... AF14: =ROUND('Quarterly MW'!AF21*$C$6,0) -> 80100
A15: Bethune FR (Azur Datacenter, ex-Bridgestone) | B15: GB300 NVL72 | C15: gross | E15: =ROUND('Quarterly MW'!E26*$C$5,0) -> 0 | F15: =ROUND('Quarterly MW'!F26*$C$5,0) -> 0 | G15: =ROUND('Quarterly MW'!G26*$C$5,0) -> 0 | H15: =ROUND('Quarterly MW'!H26*$C$5,0) -> 0 | I15: =ROUND('Quarterly MW'!I26*$C$5,0) -> 0 | J15: =ROUND('Quarterly MW'!J26*$C$5,0) -> 0 | K15: =ROUND('Quarterly MW'!K26*$C$5,0) -> 0 | L15: =ROUND('Quarterly MW'!L26*$C$5,0) -> 0 | ... AF15: =ROUND('Quarterly MW'!AF26*$C$5,0) -> 98232
A16: Lappeenranta FI (Pajarila / Polarnode) | B16: Vera Rubin NVL72 | C16: gross | E16: =ROUND('Quarterly MW'!E31*$C$6,0) -> 0 | F16: =ROUND('Quarterly MW'!F31*$C$6,0) -> 0 | G16: =ROUND('Quarterly MW'!G31*$C$6,0) -> 0 | H16: =ROUND('Quarterly MW'!H31*$C$6,0) -> 0 | I16: =ROUND('Quarterly MW'!I31*$C$6,0) -> 0 | J16: =ROUND('Quarterly MW'!J31*$C$6,0) -> 0 | K16: =ROUND('Quarterly MW'!K31*$C$6,0) -> 0 | L16: =ROUND('Quarterly MW'!L31*$C$6,0) -> 0 | ... AF16: =ROUND('Quarterly MW'!AF31*$C$6,0) -> 82770
A17: Mantsala FI #1 | B17: Hopper first 25 MW + GB300 above | C17: gross | E17: =ROUND(MIN('Quarterly MW'!E36,25)*$C$2+MAX('Quarterly MW'!E36-25,0)*$C$5,0) -> 13713 | F17: =ROUND(MIN('Quarterly MW'!F36,25)*$C$2+MAX('Quarterly MW'!F36-25,0)*$C$5,0) -> 13713 | G17: =ROUND(MIN('Quarterly MW'!G36,25)*$C$2+MAX('Quarterly MW'!G36-25,0)*$C$5,0) -> 13713 | H17: =ROUND(MIN('Quarterly MW'!H36,25)*$C$2+MAX('Quarterly MW'!H36-25,0)*$C$5,0) -> 13713 | I17: =ROUND(MIN('Quarterly MW'!I36,25)*$C$2+MAX('Quarterly MW'!I36-25,0)*$C$5,0) -> 13713 | J17: =ROUND(MIN('Quarterly MW'!J36,25)*$C$2+MAX('Quarterly MW'!J36-25,0)*$C$5,0) -> 13713 | K17: =ROUND(MIN('Quarterly MW'!K36,25)*$C$2+MAX('Quarterly MW'!K36-25,0)*$C$5,0) -> 18829 | L17: =ROUND(MIN('Quarterly MW'!L36,25)*$C$2+MAX('Quarterly MW'!L36-25,0)*$C$5,0) -> 29061 | ... AF17: =ROUND(MIN('Quarterly MW'!AF36,25)*$C$2+MAX('Quarterly MW'!AF36-25,0)*$C$5,0) -> 34178
A18: Mantsala FI #2 (Kapuli) | B18: Vera Rubin NVL72 | C18: gross | E18: =ROUND('Quarterly MW'!E41*$C$6,0) -> 0 | F18: =ROUND('Quarterly MW'!F41*$C$6,0) -> 0 | G18: =ROUND('Quarterly MW'!G41*$C$6,0) -> 0 | H18: =ROUND('Quarterly MW'!H41*$C$6,0) -> 0 | I18: =ROUND('Quarterly MW'!I41*$C$6,0) -> 0 | J18: =ROUND('Quarterly MW'!J41*$C$6,0) -> 0 | K18: =ROUND('Quarterly MW'!K41*$C$6,0) -> 0 | L18: =ROUND('Quarterly MW'!L41*$C$6,0) -> 0 | ... AF18: =ROUND('Quarterly MW'!AF41*$C$6,0) -> 18690
A19: Kansas City MO (Patmos) | B19: H200 first 10 MW + B200 above (v2) | C19: gross | E19: =ROUND(MIN('Quarterly MW'!E46,10)*$C$2+MAX('Quarterly MW'!E46-10,0)*$C$3,0) -> 0 | F19: =ROUND(MIN('Quarterly MW'!F46,10)*$C$2+MAX('Quarterly MW'!F46-10,0)*$C$3,0) -> 0 | G19: =ROUND(MIN('Quarterly MW'!G46,10)*$C$2+MAX('Quarterly MW'!G46-10,0)*$C$3,0) -> 0 | H19: =ROUND(MIN('Quarterly MW'!H46,10)*$C$2+MAX('Quarterly MW'!H46-10,0)*$C$3,0) -> 0 | I19: =ROUND(MIN('Quarterly MW'!I46,10)*$C$2+MAX('Quarterly MW'!I46-10,0)*$C$3,0) -> 5485 | J19: =ROUND(MIN('Quarterly MW'!J46,10)*$C$2+MAX('Quarterly MW'!J46-10,0)*$C$3,0) -> 5485 | K19: =ROUND(MIN('Quarterly MW'!K46,10)*$C$2+MAX('Quarterly MW'!K46-10,0)*$C$3,0) -> 5485 | L19: =ROUND(MIN('Quarterly MW'!L46,10)*$C$2+MAX('Quarterly MW'!L46-10,0)*$C$3,0) -> 9397 | ... AF19: =ROUND(MIN('Quarterly MW'!AF46,10)*$C$2+MAX('Quarterly MW'!AF46-10,0)*$C$3,0) -> 13309
A20: Paris (Equinix PA10) | B20: Hopper H100/H200 | C20: gross | E20: =ROUND('Quarterly MW'!E51*$C$2,0) -> 0 | F20: =ROUND('Quarterly MW'!F51*$C$2,0) -> 0 | G20: =ROUND('Quarterly MW'!G51*$C$2,0) -> 0 | H20: =ROUND('Quarterly MW'!H51*$C$2,0) -> 2743 | I20: =ROUND('Quarterly MW'!I51*$C$2,0) -> 2743 | J20: =ROUND('Quarterly MW'!J51*$C$2,0) -> 2743 | K20: =ROUND('Quarterly MW'!K51*$C$2,0) -> 2743 | L20: =ROUND('Quarterly MW'!L51*$C$2,0) -> 2743 | ... AF20: =ROUND('Quarterly MW'!AF51*$C$2,0) -> 2743
A21: Keflavik IS (Verne) | B21: Hopper H100/H200 | C21: gross | E21: =ROUND('Quarterly MW'!E56*$C$2,0) -> 0 | F21: =ROUND('Quarterly MW'!F56*$C$2,0) -> 0 | G21: =ROUND('Quarterly MW'!G56*$C$2,0) -> 0 | H21: =ROUND('Quarterly MW'!H56*$C$2,0) -> 0 | I21: =ROUND('Quarterly MW'!I56*$C$2,0) -> 5485 | J21: =ROUND('Quarterly MW'!J56*$C$2,0) -> 5485 | K21: =ROUND('Quarterly MW'!K56*$C$2,0) -> 5485 | L21: =ROUND('Quarterly MW'!L56*$C$2,0) -> 5485 | ... AF21: =ROUND('Quarterly MW'!AF56*$C$2,0) -> 5485
A22: London Longcross (Ark LP01) | B22: B300 (HGX) | C22: gross | E22: =ROUND('Quarterly MW'!E61*$C$4,0) -> 0 | F22: =ROUND('Quarterly MW'!F61*$C$4,0) -> 0 | G22: =ROUND('Quarterly MW'!G61*$C$4,0) -> 0 | H22: =ROUND('Quarterly MW'!H61*$C$4,0) -> 0 | I22: =ROUND('Quarterly MW'!I61*$C$4,0) -> 0 | J22: =ROUND('Quarterly MW'!J61*$C$4,0) -> 0 | K22: =ROUND('Quarterly MW'!K61*$C$4,0) -> 0 | L22: =ROUND('Quarterly MW'!L61*$C$4,0) -> 6173 | ... AF22: =ROUND('Quarterly MW'!AF61*$C$4,0) -> 7330
A23: Harlow UK (Kao Data KLON-02/03) | B23: B300 (HGX) | C23: gross | E23: =ROUND('Quarterly MW'!E66*$C$4,0) -> 0 | F23: =ROUND('Quarterly MW'!F66*$C$4,0) -> 0 | G23: =ROUND('Quarterly MW'!G66*$C$4,0) -> 0 | H23: =ROUND('Quarterly MW'!H66*$C$4,0) -> 0 | I23: =ROUND('Quarterly MW'!I66*$C$4,0) -> 0 | J23: =ROUND('Quarterly MW'!J66*$C$4,0) -> 0 | K23: =ROUND('Quarterly MW'!K66*$C$4,0) -> 0 | L23: =ROUND('Quarterly MW'!L66*$C$4,0) -> 0 | ... AF23: =ROUND('Quarterly MW'!AF66*$C$4,0) -> 8488
A24: Newport UK (Vantage CWL1) | B24: GB300 NVL72 | C24: gross | E24: =ROUND('Quarterly MW'!E71*$C$5,0) -> 0 | F24: =ROUND('Quarterly MW'!F71*$C$5,0) -> 0 | G24: =ROUND('Quarterly MW'!G71*$C$5,0) -> 0 | H24: =ROUND('Quarterly MW'!H71*$C$5,0) -> 0 | I24: =ROUND('Quarterly MW'!I71*$C$5,0) -> 0 | J24: =ROUND('Quarterly MW'!J71*$C$5,0) -> 0 | K24: =ROUND('Quarterly MW'!K71*$C$5,0) -> 0 | L24: =ROUND('Quarterly MW'!L71*$C$5,0) -> 0 | ... AF24: =ROUND('Quarterly MW'!AF71*$C$5,0) -> 12893
A25: UK 3rd new deployment (lead: Green Mountain LON-East, Romford) | B25: GB300 NVL72 | C25: gross | E25: =ROUND('Quarterly MW'!E76*$C$5,0) -> 0 | F25: =ROUND('Quarterly MW'!F76*$C$5,0) -> 0 | G25: =ROUND('Quarterly MW'!G76*$C$5,0) -> 0 | H25: =ROUND('Quarterly MW'!H76*$C$5,0) -> 0 | I25: =ROUND('Quarterly MW'!I76*$C$5,0) -> 0 | J25: =ROUND('Quarterly MW'!J76*$C$5,0) -> 0 | K25: =ROUND('Quarterly MW'!K76*$C$5,0) -> 0 | L25: =ROUND('Quarterly MW'!L76*$C$5,0) -> 0 | ... AF25: =ROUND('Quarterly MW'!AF76*$C$5,0) -> 2865
A26: Modi'in IL (Mega Or) | B26: B200 (HGX) | C26: IT | E26: =ROUND('Quarterly MW'!E81*$B$3,0) -> 0 | F26: =ROUND('Quarterly MW'!F81*$B$3,0) -> 0 | G26: =ROUND('Quarterly MW'!G81*$B$3,0) -> 0 | H26: =ROUND('Quarterly MW'!H81*$B$3,0) -> 0 | I26: =ROUND('Quarterly MW'!I81*$B$3,0) -> 0 | J26: =ROUND('Quarterly MW'!J81*$B$3,0) -> 0 | K26: =ROUND('Quarterly MW'!K81*$B$3,0) -> 0 | L26: =ROUND('Quarterly MW'!L81*$B$3,0) -> 4069 | ... AF26: =ROUND('Quarterly MW'!AF81*$B$3,0) -> 4069
A27: Masmiyya IL (Mega DC) | B27: GB300 NVL72 | C27: gross | E27: =ROUND('Quarterly MW'!E86*$C$5,0) -> 0 | F27: =ROUND('Quarterly MW'!F86*$C$5,0) -> 0 | G27: =ROUND('Quarterly MW'!G86*$C$5,0) -> 0 | H27: =ROUND('Quarterly MW'!H86*$C$5,0) -> 0 | I27: =ROUND('Quarterly MW'!I86*$C$5,0) -> 0 | J27: =ROUND('Quarterly MW'!J86*$C$5,0) -> 0 | K27: =ROUND('Quarterly MW'!K86*$C$5,0) -> 0 | L27: =ROUND('Quarterly MW'!L86*$C$5,0) -> 0 | ... AF27: =ROUND('Quarterly MW'!AF86*$C$5,0) -> 9005
A28: Beit Shemesh IL (Mega DC) | B28: GB300 NVL72 | C28: gross | E28: =ROUND('Quarterly MW'!E91*$C$5,0) -> 0 | F28: =ROUND('Quarterly MW'!F91*$C$5,0) -> 0 | G28: =ROUND('Quarterly MW'!G91*$C$5,0) -> 0 | H28: =ROUND('Quarterly MW'!H91*$C$5,0) -> 0 | I28: =ROUND('Quarterly MW'!I91*$C$5,0) -> 0 | J28: =ROUND('Quarterly MW'!J91*$C$5,0) -> 0 | K28: =ROUND('Quarterly MW'!K91*$C$5,0) -> 0 | L28: =ROUND('Quarterly MW'!L91*$C$5,0) -> 0 | ... AF28: =ROUND('Quarterly MW'!AF91*$C$5,0) -> 23739
A29: Madrid-Getafe ES (Merlin Edged) | B29: B300 (HGX) | C29: gross | E29: =ROUND('Quarterly MW'!E96*$C$4,0) -> 0 | F29: =ROUND('Quarterly MW'!F96*$C$4,0) -> 0 | G29: =ROUND('Quarterly MW'!G96*$C$4,0) -> 0 | H29: =ROUND('Quarterly MW'!H96*$C$4,0) -> 0 | I29: =ROUND('Quarterly MW'!I96*$C$4,0) -> 0 | J29: =ROUND('Quarterly MW'!J96*$C$4,0) -> 0 | K29: =ROUND('Quarterly MW'!K96*$C$4,0) -> 0 | L29: =ROUND('Quarterly MW'!L96*$C$4,0) -> 0 | ... AF29: =ROUND('Quarterly MW'!AF96*$C$4,0) -> 6944
A30: Tallinn EE (Greenergy Huuru) | B30: GB300 NVL72 | C30: gross | E30: =ROUND('Quarterly MW'!E101*$C$5,0) -> 0 | F30: =ROUND('Quarterly MW'!F101*$C$5,0) -> 0 | G30: =ROUND('Quarterly MW'!G101*$C$5,0) -> 0 | H30: =ROUND('Quarterly MW'!H101*$C$5,0) -> 0 | I30: =ROUND('Quarterly MW'!I101*$C$5,0) -> 0 | J30: =ROUND('Quarterly MW'!J101*$C$5,0) -> 0 | K30: =ROUND('Quarterly MW'!K101*$C$5,0) -> 0 | L30: =ROUND('Quarterly MW'!L101*$C$5,0) -> 0 | ... AF30: =ROUND('Quarterly MW'!AF101*$C$5,0) -> 9005
A31: Minnesota colo (us-north1, Woodbury) | B31: B300 (HGX) | C31: gross | E31: =ROUND('Quarterly MW'!E106*$C$4,0) -> 0 | F31: =ROUND('Quarterly MW'!F106*$C$4,0) -> 0 | G31: =ROUND('Quarterly MW'!G106*$C$4,0) -> 0 | H31: =ROUND('Quarterly MW'!H106*$C$4,0) -> 0 | I31: =ROUND('Quarterly MW'!I106*$C$4,0) -> 0 | J31: =ROUND('Quarterly MW'!J106*$C$4,0) -> 0 | K31: =ROUND('Quarterly MW'!K106*$C$4,0) -> 0 | L31: =ROUND('Quarterly MW'!L106*$C$4,0) -> 0 | ... AF31: =ROUND('Quarterly MW'!AF106*$C$4,0) -> 3858
A32: Oklahoma colo (unnamed) | B32: GB300 NVL72 | C32: gross | E32: =ROUND('Quarterly MW'!E111*$C$5,0) -> 0 | F32: =ROUND('Quarterly MW'!F111*$C$5,0) -> 0 | G32: =ROUND('Quarterly MW'!G111*$C$5,0) -> 0 | H32: =ROUND('Quarterly MW'!H111*$C$5,0) -> 0 | I32: =ROUND('Quarterly MW'!I111*$C$5,0) -> 0 | J32: =ROUND('Quarterly MW'!J111*$C$5,0) -> 0 | K32: =ROUND('Quarterly MW'!K111*$C$5,0) -> 0 | L32: =ROUND('Quarterly MW'!L111*$C$5,0) -> 0 | ... AF32: =ROUND('Quarterly MW'!AF111*$C$5,0) -> 40930
A33: AIB CLT1 (Moore, Spartanburg County SC; Lockhart Power) | B33: Vera Rubin NVL72 | C33: IT | E33: =ROUND('Quarterly MW'!E121*$B$6,0) -> 0 | F33: =ROUND('Quarterly MW'!F121*$B$6,0) -> 0 | G33: =ROUND('Quarterly MW'!G121*$B$6,0) -> 0 | H33: =ROUND('Quarterly MW'!H121*$B$6,0) -> 0 | I33: =ROUND('Quarterly MW'!I121*$B$6,0) -> 0 | J33: =ROUND('Quarterly MW'!J121*$B$6,0) -> 0 | K33: =ROUND('Quarterly MW'!K121*$B$6,0) -> 0 | L33: =ROUND('Quarterly MW'!L121*$B$6,0) -> 0 | ... AF33: =ROUND('Quarterly MW'!AF121*$B$6,0) -> 16000
A34: TOTAL modeled GPUs (identified sites) | E34: =SUM(E11:E33) -> 13713 | F34: =SUM(F11:F33) -> 13713 | G34: =SUM(G11:G33) -> 13713 | H34: =SUM(H11:H33) -> 16456 | I34: =SUM(I11:I33) -> 27426 | J34: =SUM(J11:J33) -> 27426 | K34: =SUM(K11:K33) -> 32542 | L34: =SUM(L11:L33) -> 69797 | ... AF34: =SUM(AF11:AF33) -> 1098025
A35: Reported GPU counts (company) | D35: GPU counts have run AHEAD of powered MW (delivered-not-powered); do not back MW out of them | G35: 10000 | H35: 20000 | I35: 30000
A36: Reported site GPU counts | D36: Modi'in 4,000 HGX B200 (Oct 2025); Longcross 4,000 B300 phase 1 (+3,000 phase 2, timing n/d); Mantsala 'up to 60,000' = potential, not deployed | L36: =4000+4000 -> 8000

Sheet GPU vintage
A1: Site | B1: Row type | C1: Generation (assumed) | D1: Note | E1: Q1 2024 | F1: Q2 2024 | G1: Q3 2024 | H1: Q4 2024 | I1: Q1 2025 | J1: Q2 2025 | K1: Q3 2025 | L1: Q4 2025 | M1: Q1 2026 | N1: Q2 2026 | O1: Q3 2026 | P1: Q4 2026 | Q1: Q1 2027 | R1: Q2 2027 | S1: Q3 2027 | T1: Q4 2027 | U1: Q1 2028 | V1: Q2 2028 | W1: Q3 2028 | X1: Q4 2028 | Y1: Q1 2029 | Z1: Q2 2029 | AA1: Q3 2029 | AB1: Q4 2029 | AC1: Q1 2030 | AD1: Q2 2030 | AE1: Q3 2030 | AF1: Q4 2030
A2: Vineland NJ (DataOne) | B2: Generation in service | C2: GB300 NVL72 | E2: =IF('Quarterly MW'!E6>0,"GB300 NVL72","") | F2: =IF('Quarterly MW'!F6>0,"GB300 NVL72","") | G2: =IF('Quarterly MW'!G6>0,"GB300 NVL72","") | H2: =IF('Quarterly MW'!H6>0,"GB300 NVL72","") | I2: =IF('Quarterly MW'!I6>0,"GB300 NVL72","") | J2: =IF('Quarterly MW'!J6>0,"GB300 NVL72","") | K2: =IF('Quarterly MW'!K6>0,"GB300 NVL72","") | L2: =IF('Quarterly MW'!L6>0,"GB300 NVL72","") -> GB300 NVL72 | ... AF2: =IF('Quarterly MW'!AF6>0,"GB300 NVL72","") -> GB300 NVL72
A3: Vineland NJ (DataOne) | B3: MW added this quarter (vintage cohort) | C3: GB300 NVL72 | E3: ='Quarterly MW'!E6-0 -> 0 | F3: ='Quarterly MW'!F6-'Quarterly MW'!E6 -> 0 | G3: ='Quarterly MW'!G6-'Quarterly MW'!F6 -> 0 | H3: ='Quarterly MW'!H6-'Quarterly MW'!G6 -> 0 | I3: ='Quarterly MW'!I6-'Quarterly MW'!H6 -> 0 | J3: ='Quarterly MW'!J6-'Quarterly MW'!I6 -> 0 | K3: ='Quarterly MW'!K6-'Quarterly MW'!J6 -> 0 | L3: ='Quarterly MW'!L6-'Quarterly MW'!K6 -> 26.2 | M3: ='Quarterly MW'!M6-'Quarterly MW'!L6 -> 11.3 | ... AF3: ='Quarterly MW'!AF6-'Quarterly MW'!AE6 -> 0
A4: Independence MO (Eastgate) | B4: Generation in service | C4: Vera Rubin NVL72 | E4: =IF('Quarterly MW'!E11>0,"Vera Rubin NVL72","") | F4: =IF('Quarterly MW'!F11>0,"Vera Rubin NVL72","") | G4: =IF('Quarterly MW'!G11>0,"Vera Rubin NVL72","") | H4: =IF('Quarterly MW'!H11>0,"Vera Rubin NVL72","") | I4: =IF('Quarterly MW'!I11>0,"Vera Rubin NVL72","") | J4: =IF('Quarterly MW'!J11>0,"Vera Rubin NVL72","") | K4: =IF('Quarterly MW'!K11>0,"Vera Rubin NVL72","") | L4: =IF('Quarterly MW'!L11>0,"Vera Rubin NVL72","") | ... AF4: =IF('Quarterly MW'!AF11>0,"Vera Rubin NVL72","") -> Vera Rubin NVL72
A5: Independence MO (Eastgate) | B5: MW added this quarter (vintage cohort) | C5: Vera Rubin NVL72 | E5: ='Quarterly MW'!E11-0 -> 0 | F5: ='Quarterly MW'!F11-'Quarterly MW'!E11 -> 0 | G5: ='Quarterly MW'!G11-'Quarterly MW'!F11 -> 0 | H5: ='Quarterly MW'!H11-'Quarterly MW'!G11 -> 0 | I5: ='Quarterly MW'!I11-'Quarterly MW'!H11 -> 0 | J5: ='Quarterly MW'!J11-'Quarterly MW'!I11 -> 0 | K5: ='Quarterly MW'!K11-'Quarterly MW'!J11 -> 0 | L5: ='Quarterly MW'!L11-'Quarterly MW'!K11 -> 0 | M5: ='Quarterly MW'!M11-'Quarterly MW'!L11 -> 0 | ... AF5: ='Quarterly MW'!AF11-'Quarterly MW'!AE11 -> 300
A6: Butler Twp PA (Highridge) | B6: Generation in service | C6: Vera Rubin NVL72 | E6: =IF('Quarterly MW'!E16>0,"Vera Rubin NVL72","") | F6: =IF('Quarterly MW'!F16>0,"Vera Rubin NVL72","") | G6: =IF('Quarterly MW'!G16>0,"Vera Rubin NVL72","") | H6: =IF('Quarterly MW'!H16>0,"Vera Rubin NVL72","") | I6: =IF('Quarterly MW'!I16>0,"Vera Rubin NVL72","") | J6: =IF('Quarterly MW'!J16>0,"Vera Rubin NVL72","") | K6: =IF('Quarterly MW'!K16>0,"Vera Rubin NVL72","") | L6: =IF('Quarterly MW'!L16>0,"Vera Rubin NVL72","") | ... AF6: =IF('Quarterly MW'!AF16>0,"Vera Rubin NVL72","") -> Vera Rubin NVL72
A7: Butler Twp PA (Highridge) | B7: MW added this quarter (vintage cohort) | C7: Vera Rubin NVL72 | E7: ='Quarterly MW'!E16-0 -> 0 | F7: ='Quarterly MW'!F16-'Quarterly MW'!E16 -> 0 | G7: ='Quarterly MW'!G16-'Quarterly MW'!F16 -> 0 | H7: ='Quarterly MW'!H16-'Quarterly MW'!G16 -> 0 | I7: ='Quarterly MW'!I16-'Quarterly MW'!H16 -> 0 | J7: ='Quarterly MW'!J16-'Quarterly MW'!I16 -> 0 | K7: ='Quarterly MW'!K16-'Quarterly MW'!J16 -> 0 | L7: ='Quarterly MW'!L16-'Quarterly MW'!K16 -> 0 | M7: ='Quarterly MW'!M16-'Quarterly MW'!L16 -> 0 | ... AF7: ='Quarterly MW'!AF16-'Quarterly MW'!AE16 -> 230
A8: Birmingham AL (BHM01, Oxmoor) | B8: Generation in service | C8: Vera Rubin NVL72 | E8: =IF('Quarterly MW'!E21>0,"Vera Rubin NVL72","") | F8: =IF('Quarterly MW'!F21>0,"Vera Rubin NVL72","") | G8: =IF('Quarterly MW'!G21>0,"Vera Rubin NVL72","") | H8: =IF('Quarterly MW'!H21>0,"Vera Rubin NVL72","") | I8: =IF('Quarterly MW'!I21>0,"Vera Rubin NVL72","") | J8: =IF('Quarterly MW'!J21>0,"Vera Rubin NVL72","") | K8: =IF('Quarterly MW'!K21>0,"Vera Rubin NVL72","") | L8: =IF('Quarterly MW'!L21>0,"Vera Rubin NVL72","") | ... AF8: =IF('Quarterly MW'!AF21>0,"Vera Rubin NVL72","") -> Vera Rubin NVL72
A9: Birmingham AL (BHM01, Oxmoor) | B9: MW added this quarter (vintage cohort) | C9: Vera Rubin NVL72 | E9: ='Quarterly MW'!E21-0 -> 0 | F9: ='Quarterly MW'!F21-'Quarterly MW'!E21 -> 0 | G9: ='Quarterly MW'!G21-'Quarterly MW'!F21 -> 0 | H9: ='Quarterly MW'!H21-'Quarterly MW'!G21 -> 0 | I9: ='Quarterly MW'!I21-'Quarterly MW'!H21 -> 0 | J9: ='Quarterly MW'!J21-'Quarterly MW'!I21 -> 0 | K9: ='Quarterly MW'!K21-'Quarterly MW'!J21 -> 0 | L9: ='Quarterly MW'!L21-'Quarterly MW'!K21 -> 0 | M9: ='Quarterly MW'!M21-'Quarterly MW'!L21 -> 0 | ... AF9: ='Quarterly MW'!AF21-'Quarterly MW'!AE21 -> 0
A10: Bethune FR (Azur Datacenter, ex-Bridgestone) | B10: Generation in service | C10: GB300 NVL72 | E10: =IF('Quarterly MW'!E26>0,"GB300 NVL72","") | F10: =IF('Quarterly MW'!F26>0,"GB300 NVL72","") | G10: =IF('Quarterly MW'!G26>0,"GB300 NVL72","") | H10: =IF('Quarterly MW'!H26>0,"GB300 NVL72","") | I10: =IF('Quarterly MW'!I26>0,"GB300 NVL72","") | J10: =IF('Quarterly MW'!J26>0,"GB300 NVL72","") | K10: =IF('Quarterly MW'!K26>0,"GB300 NVL72","") | L10: =IF('Quarterly MW'!L26>0,"GB300 NVL72","") | ... AF10: =IF('Quarterly MW'!AF26>0,"GB300 NVL72","") -> GB300 NVL72
A11: Bethune FR (Azur Datacenter, ex-Bridgestone) | B11: MW added this quarter (vintage cohort) | C11: GB300 NVL72 | E11: ='Quarterly MW'!E26-0 -> 0 | F11: ='Quarterly MW'!F26-'Quarterly MW'!E26 -> 0 | G11: ='Quarterly MW'!G26-'Quarterly MW'!F26 -> 0 | H11: ='Quarterly MW'!H26-'Quarterly MW'!G26 -> 0 | I11: ='Quarterly MW'!I26-'Quarterly MW'!H26 -> 0 | J11: ='Quarterly MW'!J26-'Quarterly MW'!I26 -> 0 | K11: ='Quarterly MW'!K26-'Quarterly MW'!J26 -> 0 | L11: ='Quarterly MW'!L26-'Quarterly MW'!K26 -> 0 | M11: ='Quarterly MW'!M26-'Quarterly MW'!L26 -> 0 | ... AF11: ='Quarterly MW'!AF26-'Quarterly MW'!AE26 -> 0
A12: Lappeenranta FI (Pajarila / Polarnode) | B12: Generation in service | C12: Vera Rubin NVL72 | E12: =IF('Quarterly MW'!E31>0,"Vera Rubin NVL72","") | F12: =IF('Quarterly MW'!F31>0,"Vera Rubin NVL72","") | G12: =IF('Quarterly MW'!G31>0,"Vera Rubin NVL72","") | H12: =IF('Quarterly MW'!H31>0,"Vera Rubin NVL72","") | I12: =IF('Quarterly MW'!I31>0,"Vera Rubin NVL72","") | J12: =IF('Quarterly MW'!J31>0,"Vera Rubin NVL72","") | K12: =IF('Quarterly MW'!K31>0,"Vera Rubin NVL72","") | L12: =IF('Quarterly MW'!L31>0,"Vera Rubin NVL72","") | ... AF12: =IF('Quarterly MW'!AF31>0,"Vera Rubin NVL72","") -> Vera Rubin NVL72
A13: Lappeenranta FI (Pajarila / Polarnode) | B13: MW added this quarter (vintage cohort) | C13: Vera Rubin NVL72 | E13: ='Quarterly MW'!E31-0 -> 0 | F13: ='Quarterly MW'!F31-'Quarterly MW'!E31 -> 0 | G13: ='Quarterly MW'!G31-'Quarterly MW'!F31 -> 0 | H13: ='Quarterly MW'!H31-'Quarterly MW'!G31 -> 0 | I13: ='Quarterly MW'!I31-'Quarterly MW'!H31 -> 0 | J13: ='Quarterly MW'!J31-'Quarterly MW'!I31 -> 0 | K13: ='Quarterly MW'!K31-'Quarterly MW'!J31 -> 0 | L13: ='Quarterly MW'!L31-'Quarterly MW'!K31 -> 0 | M13: ='Quarterly MW'!M31-'Quarterly MW'!L31 -> 0 | ... AF13: ='Quarterly MW'!AF31-'Quarterly MW'!AE31 -> 45
A14: Mantsala FI #1 | B14: Generation in service | C14: Hopper (first 25 MW) + GB300 NVL72 (expansion, Estimated split) | E14: =IF('Quarterly MW'!E36>25,"Hopper+GB300",IF('Quarterly MW'!E36>0,"Hopper","")) -> Hopper | F14: =IF('Quarterly MW'!F36>25,"Hopper+GB300",IF('Quarterly MW'!F36>0,"Hopper","")) -> Hopper | G14: =IF('Quarterly MW'!G36>25,"Hopper+GB300",IF('Quarterly MW'!G36>0,"Hopper","")) -> Hopper | H14: =IF('Quarterly MW'!H36>25,"Hopper+GB300",IF('Quarterly MW'!H36>0,"Hopper","")) -> Hopper | I14: =IF('Quarterly MW'!I36>25,"Hopper+GB300",IF('Quarterly MW'!I36>0,"Hopper","")) -> Hopper | J14: =IF('Quarterly MW'!J36>25,"Hopper+GB300",IF('Quarterly MW'!J36>0,"Hopper","")) -> Hopper | K14: =IF('Quarterly MW'!K36>25,"Hopper+GB300",IF('Quarterly MW'!K36>0,"Hopper","")) -> Hopper+GB300 | L14: =IF('Quarterly MW'!L36>25,"Hopper+GB300",IF('Quarterly MW'!L36>0,"Hopper","")) -> Hopper+GB300 | ... AF14: =IF('Quarterly MW'!AF36>25,"Hopper+GB300",IF('Quarterly MW'!AF36>0,"Hopper","")) -> Hopper+GB300
A15: Mantsala FI #1 | B15: MW added this quarter (vintage cohort) | C15: Hopper (first 25 MW) + GB300 NVL72 (expansion, Estimated split) | E15: ='Quarterly MW'!E36-0 -> 25 | F15: ='Quarterly MW'!F36-'Quarterly MW'!E36 -> 0 | G15: ='Quarterly MW'!G36-'Quarterly MW'!F36 -> 0 | H15: ='Quarterly MW'!H36-'Quarterly MW'!G36 -> 0 | I15: ='Quarterly MW'!I36-'Quarterly MW'!H36 -> 0 | J15: ='Quarterly MW'!J36-'Quarterly MW'!I36 -> 0 | K15: ='Quarterly MW'!K36-'Quarterly MW'!J36 -> 12.5 | L15: ='Quarterly MW'!L36-'Quarterly MW'!K36 -> 25 | M15: ='Quarterly MW'!M36-'Quarterly MW'!L36 -> 12.5 | ... AF15: ='Quarterly MW'!AF36-'Quarterly MW'!AE36 -> 0
A16: Mantsala FI #2 (Kapuli) | B16: Generation in service | C16: Vera Rubin NVL72 | E16: =IF('Quarterly MW'!E41>0,"Vera Rubin NVL72","") | F16: =IF('Quarterly MW'!F41>0,"Vera Rubin NVL72","") | G16: =IF('Quarterly MW'!G41>0,"Vera Rubin NVL72","") | H16: =IF('Quarterly MW'!H41>0,"Vera Rubin NVL72","") | I16: =IF('Quarterly MW'!I41>0,"Vera Rubin NVL72","") | J16: =IF('Quarterly MW'!J41>0,"Vera Rubin NVL72","") | K16: =IF('Quarterly MW'!K41>0,"Vera Rubin NVL72","") | L16: =IF('Quarterly MW'!L41>0,"Vera Rubin NVL72","") | ... AF16: =IF('Quarterly MW'!AF41>0,"Vera Rubin NVL72","") -> Vera Rubin NVL72
A17: Mantsala FI #2 (Kapuli) | B17: MW added this quarter (vintage cohort) | C17: Vera Rubin NVL72 | E17: ='Quarterly MW'!E41-0 -> 0 | F17: ='Quarterly MW'!F41-'Quarterly MW'!E41 -> 0 | G17: ='Quarterly MW'!G41-'Quarterly MW'!F41 -> 0 | H17: ='Quarterly MW'!H41-'Quarterly MW'!G41 -> 0 | I17: ='Quarterly MW'!I41-'Quarterly MW'!H41 -> 0 | J17: ='Quarterly MW'!J41-'Quarterly MW'!I41 -> 0 | K17: ='Quarterly MW'!K41-'Quarterly MW'!J41 -> 0 | L17: ='Quarterly MW'!L41-'Quarterly MW'!K41 -> 0 | M17: ='Quarterly MW'!M41-'Quarterly MW'!L41 -> 0 | ... AF17: ='Quarterly MW'!AF41-'Quarterly MW'!AE41 -> 0
A18: Kansas City MO (Patmos) | B18: Generation in service | C18: H200 (first 5 MW) + B200 (rest) | E18: =IF('Quarterly MW'!E46>10,"H200+B200",IF('Quarterly MW'!E46>0,"H200","")) | F18: =IF('Quarterly MW'!F46>10,"H200+B200",IF('Quarterly MW'!F46>0,"H200","")) | G18: =IF('Quarterly MW'!G46>10,"H200+B200",IF('Quarterly MW'!G46>0,"H200","")) | H18: =IF('Quarterly MW'!H46>10,"H200+B200",IF('Quarterly MW'!H46>0,"H200","")) | I18: =IF('Quarterly MW'!I46>10,"H200+B200",IF('Quarterly MW'!I46>0,"H200","")) -> H200 | J18: =IF('Quarterly MW'!J46>10,"H200+B200",IF('Quarterly MW'!J46>0,"H200","")) -> H200 | K18: =IF('Quarterly MW'!K46>10,"H200+B200",IF('Quarterly MW'!K46>0,"H200","")) -> H200 | L18: =IF('Quarterly MW'!L46>10,"H200+B200",IF('Quarterly MW'!L46>0,"H200","")) -> H200+B200 | ... AF18: =IF('Quarterly MW'!AF46>10,"H200+B200",IF('Quarterly MW'!AF46>0,"H200","")) -> H200+B200
A19: Kansas City MO (Patmos) | B19: MW added this quarter (vintage cohort) | C19: H200 (first 5 MW) + B200 (rest) | E19: ='Quarterly MW'!E46-0 -> 0 | F19: ='Quarterly MW'!F46-'Quarterly MW'!E46 -> 0 | G19: ='Quarterly MW'!G46-'Quarterly MW'!F46 -> 0 | H19: ='Quarterly MW'!H46-'Quarterly MW'!G46 -> 0 | I19: ='Quarterly MW'!I46-'Quarterly MW'!H46 -> 10 | J19: ='Quarterly MW'!J46-'Quarterly MW'!I46 -> 0 | K19: ='Quarterly MW'!K46-'Quarterly MW'!J46 -> 0 | L19: ='Quarterly MW'!L46-'Quarterly MW'!K46 -> 10 | M19: ='Quarterly MW'!M46-'Quarterly MW'!L46 -> 0 | ... AF19: ='Quarterly MW'!AF46-'Quarterly MW'!AE46 -> 0
A20: Paris (Equinix PA10) | B20: Generation in service | C20: Hopper H100/H200 | E20: =IF('Quarterly MW'!E51>0,"Hopper H100/H200","") | F20: =IF('Quarterly MW'!F51>0,"Hopper H100/H200","") | G20: =IF('Quarterly MW'!G51>0,"Hopper H100/H200","") | H20: =IF('Quarterly MW'!H51>0,"Hopper H100/H200","") -> Hopper H100/H200 | I20: =IF('Quarterly MW'!I51>0,"Hopper H100/H200","") -> Hopper H100/H200 | J20: =IF('Quarterly MW'!J51>0,"Hopper H100/H200","") -> Hopper H100/H200 | K20: =IF('Quarterly MW'!K51>0,"Hopper H100/H200","") -> Hopper H100/H200 | L20: =IF('Quarterly MW'!L51>0,"Hopper H100/H200","") -> Hopper H100/H200 | ... AF20: =IF('Quarterly MW'!AF51>0,"Hopper H100/H200","") -> Hopper H100/H200
A21: Paris (Equinix PA10) | B21: MW added this quarter (vintage cohort) | C21: Hopper H100/H200 | E21: ='Quarterly MW'!E51-0 -> 0 | F21: ='Quarterly MW'!F51-'Quarterly MW'!E51 -> 0 | G21: ='Quarterly MW'!G51-'Quarterly MW'!F51 -> 0 | H21: ='Quarterly MW'!H51-'Quarterly MW'!G51 -> 5 | I21: ='Quarterly MW'!I51-'Quarterly MW'!H51 -> 0 | J21: ='Quarterly MW'!J51-'Quarterly MW'!I51 -> 0 | K21: ='Quarterly MW'!K51-'Quarterly MW'!J51 -> 0 | L21: ='Quarterly MW'!L51-'Quarterly MW'!K51 -> 0 | M21: ='Quarterly MW'!M51-'Quarterly MW'!L51 -> 0 | ... AF21: ='Quarterly MW'!AF51-'Quarterly MW'!AE51 -> 0
A22: Keflavik IS (Verne) | B22: Generation in service | C22: Hopper H100/H200 | E22: =IF('Quarterly MW'!E56>0,"Hopper H100/H200","") | F22: =IF('Quarterly MW'!F56>0,"Hopper H100/H200","") | G22: =IF('Quarterly MW'!G56>0,"Hopper H100/H200","") | H22: =IF('Quarterly MW'!H56>0,"Hopper H100/H200","") | I22: =IF('Quarterly MW'!I56>0,"Hopper H100/H200","") -> Hopper H100/H200 | J22: =IF('Quarterly MW'!J56>0,"Hopper H100/H200","") -> Hopper H100/H200 | K22: =IF('Quarterly MW'!K56>0,"Hopper H100/H200","") -> Hopper H100/H200 | L22: =IF('Quarterly MW'!L56>0,"Hopper H100/H200","") -> Hopper H100/H200 | ... AF22: =IF('Quarterly MW'!AF56>0,"Hopper H100/H200","") -> Hopper H100/H200
A23: Keflavik IS (Verne) | B23: MW added this quarter (vintage cohort) | C23: Hopper H100/H200 | E23: ='Quarterly MW'!E56-0 -> 0 | F23: ='Quarterly MW'!F56-'Quarterly MW'!E56 -> 0 | G23: ='Quarterly MW'!G56-'Quarterly MW'!F56 -> 0 | H23: ='Quarterly MW'!H56-'Quarterly MW'!G56 -> 0 | I23: ='Quarterly MW'!I56-'Quarterly MW'!H56 -> 10 | J23: ='Quarterly MW'!J56-'Quarterly MW'!I56 -> 0 | K23: ='Quarterly MW'!K56-'Quarterly MW'!J56 -> 0 | L23: ='Quarterly MW'!L56-'Quarterly MW'!K56 -> 0 | M23: ='Quarterly MW'!M56-'Quarterly MW'!L56 -> 0 | ... AF23: ='Quarterly MW'!AF56-'Quarterly MW'!AE56 -> 0
A24: London Longcross (Ark LP01) | B24: Generation in service | C24: B300 (HGX) | E24: =IF('Quarterly MW'!E61>0,"B300 (HGX)","") | F24: =IF('Quarterly MW'!F61>0,"B300 (HGX)","") | G24: =IF('Quarterly MW'!G61>0,"B300 (HGX)","") | H24: =IF('Quarterly MW'!H61>0,"B300 (HGX)","") | I24: =IF('Quarterly MW'!I61>0,"B300 (HGX)","") | J24: =IF('Quarterly MW'!J61>0,"B300 (HGX)","") | K24: =IF('Quarterly MW'!K61>0,"B300 (HGX)","") | L24: =IF('Quarterly MW'!L61>0,"B300 (HGX)","") -> B300 (HGX) | ... AF24: =IF('Quarterly MW'!AF61>0,"B300 (HGX)","") -> B300 (HGX)
A25: London Longcross (Ark LP01) | B25: MW added this quarter (vintage cohort) | C25: B300 (HGX) | E25: ='Quarterly MW'!E61-0 -> 0 | F25: ='Quarterly MW'!F61-'Quarterly MW'!E61 -> 0 | G25: ='Quarterly MW'!G61-'Quarterly MW'!F61 -> 0 | H25: ='Quarterly MW'!H61-'Quarterly MW'!G61 -> 0 | I25: ='Quarterly MW'!I61-'Quarterly MW'!H61 -> 0 | J25: ='Quarterly MW'!J61-'Quarterly MW'!I61 -> 0 | K25: ='Quarterly MW'!K61-'Quarterly MW'!J61 -> 0 | L25: ='Quarterly MW'!L61-'Quarterly MW'!K61 -> 16 | M25: ='Quarterly MW'!M61-'Quarterly MW'!L61 -> 0 | ... AF25: ='Quarterly MW'!AF61-'Quarterly MW'!AE61 -> 0
A26: Harlow UK (Kao Data KLON-02/03) | B26: Generation in service | C26: B300 (HGX) | E26: =IF('Quarterly MW'!E66>0,"B300 (HGX)","") | F26: =IF('Quarterly MW'!F66>0,"B300 (HGX)","") | G26: =IF('Quarterly MW'!G66>0,"B300 (HGX)","") | H26: =IF('Quarterly MW'!H66>0,"B300 (HGX)","") | I26: =IF('Quarterly MW'!I66>0,"B300 (HGX)","") | J26: =IF('Quarterly MW'!J66>0,"B300 (HGX)","") | K26: =IF('Quarterly MW'!K66>0,"B300 (HGX)","") | L26: =IF('Quarterly MW'!L66>0,"B300 (HGX)","") | ... AF26: =IF('Quarterly MW'!AF66>0,"B300 (HGX)","") -> B300 (HGX)
A27: Harlow UK (Kao Data KLON-02/03) | B27: MW added this quarter (vintage cohort) | C27: B300 (HGX) | E27: ='Quarterly MW'!E66-0 -> 0 | F27: ='Quarterly MW'!F66-'Quarterly MW'!E66 -> 0 | G27: ='Quarterly MW'!G66-'Quarterly MW'!F66 -> 0 | H27: ='Quarterly MW'!H66-'Quarterly MW'!G66 -> 0 | I27: ='Quarterly MW'!I66-'Quarterly MW'!H66 -> 0 | J27: ='Quarterly MW'!J66-'Quarterly MW'!I66 -> 0 | K27: ='Quarterly MW'!K66-'Quarterly MW'!J66 -> 0 | L27: ='Quarterly MW'!L66-'Quarterly MW'!K66 -> 0 | M27: ='Quarterly MW'!M66-'Quarterly MW'!L66 -> 0 | ... AF27: ='Quarterly MW'!AF66-'Quarterly MW'!AE66 -> 0
A28: Newport UK (Vantage CWL1) | B28: Generation in service | C28: GB300 NVL72 | E28: =IF('Quarterly MW'!E71>0,"GB300 NVL72","") | F28: =IF('Quarterly MW'!F71>0,"GB300 NVL72","") | G28: =IF('Quarterly MW'!G71>0,"GB300 NVL72","") | H28: =IF('Quarterly MW'!H71>0,"GB300 NVL72","") | I28: =IF('Quarterly MW'!I71>0,"GB300 NVL72","") | J28: =IF('Quarterly MW'!J71>0,"GB300 NVL72","") | K28: =IF('Quarterly MW'!K71>0,"GB300 NVL72","") | L28: =IF('Quarterly MW'!L71>0,"GB300 NVL72","") | ... AF28: =IF('Quarterly MW'!AF71>0,"GB300 NVL72","") -> GB300 NVL72
A29: Newport UK (Vantage CWL1) | B29: MW added this quarter (vintage cohort) | C29: GB300 NVL72 | E29: ='Quarterly MW'!E71-0 -> 0 | F29: ='Quarterly MW'!F71-'Quarterly MW'!E71 -> 0 | G29: ='Quarterly MW'!G71-'Quarterly MW'!F71 -> 0 | H29: ='Quarterly MW'!H71-'Quarterly MW'!G71 -> 0 | I29: ='Quarterly MW'!I71-'Quarterly MW'!H71 -> 0 | J29: ='Quarterly MW'!J71-'Quarterly MW'!I71 -> 0 | K29: ='Quarterly MW'!K71-'Quarterly MW'!J71 -> 0 | L29: ='Quarterly MW'!L71-'Quarterly MW'!K71 -> 0 | M29: ='Quarterly MW'!M71-'Quarterly MW'!L71 -> 0 | ... AF29: ='Quarterly MW'!AF71-'Quarterly MW'!AE71 -> 0
A30: UK 3rd new deployment (lead: Green Mountain LON-East, Romford) | B30: Generation in service | C30: GB300 NVL72 | E30: =IF('Quarterly MW'!E76>0,"GB300 NVL72","") | F30: =IF('Quarterly MW'!F76>0,"GB300 NVL72","") | G30: =IF('Quarterly MW'!G76>0,"GB300 NVL72","") | H30: =IF('Quarterly MW'!H76>0,"GB300 NVL72","") | I30: =IF('Quarterly MW'!I76>0,"GB300 NVL72","") | J30: =IF('Quarterly MW'!J76>0,"GB300 NVL72","") | K30: =IF('Quarterly MW'!K76>0,"GB300 NVL72","") | L30: =IF('Quarterly MW'!L76>0,"GB300 NVL72","") | ... AF30: =IF('Quarterly MW'!AF76>0,"GB300 NVL72","") -> GB300 NVL72
A31: UK 3rd new deployment (lead: Green Mountain LON-East, Romford) | B31: MW added this quarter (vintage cohort) | C31: GB300 NVL72 | E31: ='Quarterly MW'!E76-0 -> 0 | F31: ='Quarterly MW'!F76-'Quarterly MW'!E76 -> 0 | G31: ='Quarterly MW'!G76-'Quarterly MW'!F76 -> 0 | H31: ='Quarterly MW'!H76-'Quarterly MW'!G76 -> 0 | I31: ='Quarterly MW'!I76-'Quarterly MW'!H76 -> 0 | J31: ='Quarterly MW'!J76-'Quarterly MW'!I76 -> 0 | K31: ='Quarterly MW'!K76-'Quarterly MW'!J76 -> 0 | L31: ='Quarterly MW'!L76-'Quarterly MW'!K76 -> 0 | M31: ='Quarterly MW'!M76-'Quarterly MW'!L76 -> 0 | ... AF31: ='Quarterly MW'!AF76-'Quarterly MW'!AE76 -> 0
A32: Modi'in IL (Mega Or) | B32: Generation in service | C32: B200 (HGX) | E32: =IF('Quarterly MW'!E81>0,"B200 (HGX)","") | F32: =IF('Quarterly MW'!F81>0,"B200 (HGX)","") | G32: =IF('Quarterly MW'!G81>0,"B200 (HGX)","") | H32: =IF('Quarterly MW'!H81>0,"B200 (HGX)","") | I32: =IF('Quarterly MW'!I81>0,"B200 (HGX)","") | J32: =IF('Quarterly MW'!J81>0,"B200 (HGX)","") | K32: =IF('Quarterly MW'!K81>0,"B200 (HGX)","") | L32: =IF('Quarterly MW'!L81>0,"B200 (HGX)","") -> B200 (HGX) | ... AF32: =IF('Quarterly MW'!AF81>0,"B200 (HGX)","") -> B200 (HGX)
A33: Modi'in IL (Mega Or) | B33: MW added this quarter (vintage cohort) | C33: B200 (HGX) | E33: ='Quarterly MW'!E81-0 -> 0 | F33: ='Quarterly MW'!F81-'Quarterly MW'!E81 -> 0 | G33: ='Quarterly MW'!G81-'Quarterly MW'!F81 -> 0 | H33: ='Quarterly MW'!H81-'Quarterly MW'!G81 -> 0 | I33: ='Quarterly MW'!I81-'Quarterly MW'!H81 -> 0 | J33: ='Quarterly MW'!J81-'Quarterly MW'!I81 -> 0 | K33: ='Quarterly MW'!K81-'Quarterly MW'!J81 -> 0 | L33: ='Quarterly MW'!L81-'Quarterly MW'!K81 -> 8 | M33: ='Quarterly MW'!M81-'Quarterly MW'!L81 -> 0 | ... AF33: ='Quarterly MW'!AF81-'Quarterly MW'!AE81 -> 0
A34: Masmiyya IL (Mega DC) | B34: Generation in service | C34: GB300 NVL72 | E34: =IF('Quarterly MW'!E86>0,"GB300 NVL72","") | F34: =IF('Quarterly MW'!F86>0,"GB300 NVL72","") | G34: =IF('Quarterly MW'!G86>0,"GB300 NVL72","") | H34: =IF('Quarterly MW'!H86>0,"GB300 NVL72","") | I34: =IF('Quarterly MW'!I86>0,"GB300 NVL72","") | J34: =IF('Quarterly MW'!J86>0,"GB300 NVL72","") | K34: =IF('Quarterly MW'!K86>0,"GB300 NVL72","") | L34: =IF('Quarterly MW'!L86>0,"GB300 NVL72","") | ... AF34: =IF('Quarterly MW'!AF86>0,"GB300 NVL72","") -> GB300 NVL72
A35: Masmiyya IL (Mega DC) | B35: MW added this quarter (vintage cohort) | C35: GB300 NVL72 | E35: ='Quarterly MW'!E86-0 -> 0 | F35: ='Quarterly MW'!F86-'Quarterly MW'!E86 -> 0 | G35: ='Quarterly MW'!G86-'Quarterly MW'!F86 -> 0 | H35: ='Quarterly MW'!H86-'Quarterly MW'!G86 -> 0 | I35: ='Quarterly MW'!I86-'Quarterly MW'!H86 -> 0 | J35: ='Quarterly MW'!J86-'Quarterly MW'!I86 -> 0 | K35: ='Quarterly MW'!K86-'Quarterly MW'!J86 -> 0 | L35: ='Quarterly MW'!L86-'Quarterly MW'!K86 -> 0 | M35: ='Quarterly MW'!M86-'Quarterly MW'!L86 -> 0 | ... AF35: ='Quarterly MW'!AF86-'Quarterly MW'!AE86 -> 0
A36: Beit Shemesh IL (Mega DC) | B36: Generation in service | C36: GB300 NVL72 | E36: =IF('Quarterly MW'!E91>0,"GB300 NVL72","") | F36: =IF('Quarterly MW'!F91>0,"GB300 NVL72","") | G36: =IF('Quarterly MW'!G91>0,"GB300 NVL72","") | H36: =IF('Quarterly MW'!H91>0,"GB300 NVL72","") | I36: =IF('Quarterly MW'!I91>0,"GB300 NVL72","") | J36: =IF('Quarterly MW'!J91>0,"GB300 NVL72","") | K36: =IF('Quarterly MW'!K91>0,"GB300 NVL72","") | L36: =IF('Quarterly MW'!L91>0,"GB300 NVL72","") | ... AF36: =IF('Quarterly MW'!AF91>0,"GB300 NVL72","") -> GB300 NVL72
A37: Beit Shemesh IL (Mega DC) | B37: MW added this quarter (vintage cohort) | C37: GB300 NVL72 | E37: ='Quarterly MW'!E91-0 -> 0 | F37: ='Quarterly MW'!F91-'Quarterly MW'!E91 -> 0 | G37: ='Quarterly MW'!G91-'Quarterly MW'!F91 -> 0 | H37: ='Quarterly MW'!H91-'Quarterly MW'!G91 -> 0 | I37: ='Quarterly MW'!I91-'Quarterly MW'!H91 -> 0 | J37: ='Quarterly MW'!J91-'Quarterly MW'!I91 -> 0 | K37: ='Quarterly MW'!K91-'Quarterly MW'!J91 -> 0 | L37: ='Quarterly MW'!L91-'Quarterly MW'!K91 -> 0 | M37: ='Quarterly MW'!M91-'Quarterly MW'!L91 -> 0 | ... AF37: ='Quarterly MW'!AF91-'Quarterly MW'!AE91 -> 0
A38: Madrid-Getafe ES (Merlin Edged) | B38: Generation in service | C38: B300 (HGX) | E38: =IF('Quarterly MW'!E96>0,"B300 (HGX)","") | F38: =IF('Quarterly MW'!F96>0,"B300 (HGX)","") | G38: =IF('Quarterly MW'!G96>0,"B300 (HGX)","") | H38: =IF('Quarterly MW'!H96>0,"B300 (HGX)","") | I38: =IF('Quarterly MW'!I96>0,"B300 (HGX)","") | J38: =IF('Quarterly MW'!J96>0,"B300 (HGX)","") | K38: =IF('Quarterly MW'!K96>0,"B300 (HGX)","") | L38: =IF('Quarterly MW'!L96>0,"B300 (HGX)","") | ... AF38: =IF('Quarterly MW'!AF96>0,"B300 (HGX)","") -> B300 (HGX)
A39: Madrid-Getafe ES (Merlin Edged) | B39: MW added this quarter (vintage cohort) | C39: B300 (HGX) | E39: ='Quarterly MW'!E96-0 -> 0 | F39: ='Quarterly MW'!F96-'Quarterly MW'!E96 -> 0 | G39: ='Quarterly MW'!G96-'Quarterly MW'!F96 -> 0 | H39: ='Quarterly MW'!H96-'Quarterly MW'!G96 -> 0 | I39: ='Quarterly MW'!I96-'Quarterly MW'!H96 -> 0 | J39: ='Quarterly MW'!J96-'Quarterly MW'!I96 -> 0 | K39: ='Quarterly MW'!K96-'Quarterly MW'!J96 -> 0 | L39: ='Quarterly MW'!L96-'Quarterly MW'!K96 -> 0 | M39: ='Quarterly MW'!M96-'Quarterly MW'!L96 -> 0 | ... AF39: ='Quarterly MW'!AF96-'Quarterly MW'!AE96 -> 0
A40: Tallinn EE (Greenergy Huuru) | B40: Generation in service | C40: GB300 NVL72 | E40: =IF('Quarterly MW'!E101>0,"GB300 NVL72","") | F40: =IF('Quarterly MW'!F101>0,"GB300 NVL72","") | G40: =IF('Quarterly MW'!G101>0,"GB300 NVL72","") | H40: =IF('Quarterly MW'!H101>0,"GB300 NVL72","") | I40: =IF('Quarterly MW'!I101>0,"GB300 NVL72","") | J40: =IF('Quarterly MW'!J101>0,"GB300 NVL72","") | K40: =IF('Quarterly MW'!K101>0,"GB300 NVL72","") | L40: =IF('Quarterly MW'!L101>0,"GB300 NVL72","") | ... AF40: =IF('Quarterly MW'!AF101>0,"GB300 NVL72","") -> GB300 NVL72
A41: Tallinn EE (Greenergy Huuru) | B41: MW added this quarter (vintage cohort) | C41: GB300 NVL72 | E41: ='Quarterly MW'!E101-0 -> 0 | F41: ='Quarterly MW'!F101-'Quarterly MW'!E101 -> 0 | G41: ='Quarterly MW'!G101-'Quarterly MW'!F101 -> 0 | H41: ='Quarterly MW'!H101-'Quarterly MW'!G101 -> 0 | I41: ='Quarterly MW'!I101-'Quarterly MW'!H101 -> 0 | J41: ='Quarterly MW'!J101-'Quarterly MW'!I101 -> 0 | K41: ='Quarterly MW'!K101-'Quarterly MW'!J101 -> 0 | L41: ='Quarterly MW'!L101-'Quarterly MW'!K101 -> 0 | M41: ='Quarterly MW'!M101-'Quarterly MW'!L101 -> 0 | ... AF41: ='Quarterly MW'!AF101-'Quarterly MW'!AE101 -> 0
A42: Minnesota colo (us-north1, Woodbury) | B42: Generation in service | C42: B300 (HGX) | E42: =IF('Quarterly MW'!E106>0,"B300 (HGX)","") | F42: =IF('Quarterly MW'!F106>0,"B300 (HGX)","") | G42: =IF('Quarterly MW'!G106>0,"B300 (HGX)","") | H42: =IF('Quarterly MW'!H106>0,"B300 (HGX)","") | I42: =IF('Quarterly MW'!I106>0,"B300 (HGX)","") | J42: =IF('Quarterly MW'!J106>0,"B300 (HGX)","") | K42: =IF('Quarterly MW'!K106>0,"B300 (HGX)","") | L42: =IF('Quarterly MW'!L106>0,"B300 (HGX)","") | ... AF42: =IF('Quarterly MW'!AF106>0,"B300 (HGX)","") -> B300 (HGX)
A43: Minnesota colo (us-north1, Woodbury) | B43: MW added this quarter (vintage cohort) | C43: B300 (HGX) | E43: ='Quarterly MW'!E106-0 -> 0 | F43: ='Quarterly MW'!F106-'Quarterly MW'!E106 -> 0 | G43: ='Quarterly MW'!G106-'Quarterly MW'!F106 -> 0 | H43: ='Quarterly MW'!H106-'Quarterly MW'!G106 -> 0 | I43: ='Quarterly MW'!I106-'Quarterly MW'!H106 -> 0 | J43: ='Quarterly MW'!J106-'Quarterly MW'!I106 -> 0 | K43: ='Quarterly MW'!K106-'Quarterly MW'!J106 -> 0 | L43: ='Quarterly MW'!L106-'Quarterly MW'!K106 -> 0 | M43: ='Quarterly MW'!M106-'Quarterly MW'!L106 -> 10 | ... AF43: ='Quarterly MW'!AF106-'Quarterly MW'!AE106 -> 0
A44: Oklahoma colo (unnamed) | B44: Generation in service | C44: GB300 NVL72 | E44: =IF('Quarterly MW'!E111>0,"GB300 NVL72","") | F44: =IF('Quarterly MW'!F111>0,"GB300 NVL72","") | G44: =IF('Quarterly MW'!G111>0,"GB300 NVL72","") | H44: =IF('Quarterly MW'!H111>0,"GB300 NVL72","") | I44: =IF('Quarterly MW'!I111>0,"GB300 NVL72","") | J44: =IF('Quarterly MW'!J111>0,"GB300 NVL72","") | K44: =IF('Quarterly MW'!K111>0,"GB300 NVL72","") | L44: =IF('Quarterly MW'!L111>0,"GB300 NVL72","") | ... AF44: =IF('Quarterly MW'!AF111>0,"GB300 NVL72","") -> GB300 NVL72
A45: Oklahoma colo (unnamed) | B45: MW added this quarter (vintage cohort) | C45: GB300 NVL72 | E45: ='Quarterly MW'!E111-0 -> 0 | F45: ='Quarterly MW'!F111-'Quarterly MW'!E111 -> 0 | G45: ='Quarterly MW'!G111-'Quarterly MW'!F111 -> 0 | H45: ='Quarterly MW'!H111-'Quarterly MW'!G111 -> 0 | I45: ='Quarterly MW'!I111-'Quarterly MW'!H111 -> 0 | J45: ='Quarterly MW'!J111-'Quarterly MW'!I111 -> 0 | K45: ='Quarterly MW'!K111-'Quarterly MW'!J111 -> 0 | L45: ='Quarterly MW'!L111-'Quarterly MW'!K111 -> 0 | M45: ='Quarterly MW'!M111-'Quarterly MW'!L111 -> 0 | ... AF45: ='Quarterly MW'!AF111-'Quarterly MW'!AE111 -> 0
A46: AIB CLT1 (Moore, Spartanburg County SC; Lockhart Power) | B46: Generation in service | C46: Vera Rubin NVL72 | E46: =IF('Quarterly MW'!E121>0,"Vera Rubin NVL72","") | F46: =IF('Quarterly MW'!F121>0,"Vera Rubin NVL72","") | G46: =IF('Quarterly MW'!G121>0,"Vera Rubin NVL72","") | H46: =IF('Quarterly MW'!H121>0,"Vera Rubin NVL72","") | I46: =IF('Quarterly MW'!I121>0,"Vera Rubin NVL72","") | J46: =IF('Quarterly MW'!J121>0,"Vera Rubin NVL72","") | K46: =IF('Quarterly MW'!K121>0,"Vera Rubin NVL72","") | L46: =IF('Quarterly MW'!L121>0,"Vera Rubin NVL72","") | ... AF46: =IF('Quarterly MW'!AF121>0,"Vera Rubin NVL72","") -> Vera Rubin NVL72
A47: AIB CLT1 (Moore, Spartanburg County SC; Lockhart Power) | B47: MW added this quarter (vintage cohort) | C47: Vera Rubin NVL72 | E47: ='Quarterly MW'!E121-0 -> 0 | F47: ='Quarterly MW'!F121-'Quarterly MW'!E121 -> 0 | G47: ='Quarterly MW'!G121-'Quarterly MW'!F121 -> 0 | H47: ='Quarterly MW'!H121-'Quarterly MW'!G121 -> 0 | I47: ='Quarterly MW'!I121-'Quarterly MW'!H121 -> 0 | J47: ='Quarterly MW'!J121-'Quarterly MW'!I121 -> 0 | K47: ='Quarterly MW'!K121-'Quarterly MW'!J121 -> 0 | L47: ='Quarterly MW'!L121-'Quarterly MW'!K121 -> 0 | M47: ='Quarterly MW'!M121-'Quarterly MW'!L121 -> 0 | ... AF47: ='Quarterly MW'!AF121-'Quarterly MW'!AE121 -> 0

Sheet Vineland tranche track
A1: Vineland (Microsoft) tranche track - 9 tranches, $17,392.9M take-or-pay (20-F), ~$6,958.1M upfront, billing through Oct 2031
A3: Tranche count | B3: 9
A4: Contract value $M | B4: 17392.9
A5: Upfront payments $M | B5: 6958.1
A6: Site contracted MW (gross) | B6: 300
A7: IT MW at full build (mid of 230-250, Estimated) | B7: 240
A8: Genset count | B8: 62
A9: Genset MW each | B9: 1.982
A10: Grid MW | B10: 5
A11: PUE for ceiling | B11: 1.2
A12: Q2-26 group revenue $M | B12: 582.3
A13: Top customer share Q2-26 (customer C) | B13: 0.24
A15: MW per tranche, gross (EQUAL-SPLIT ASSUMPTION) | B15: =$B$6/$B$3 -> 33.333333
A16: MW per tranche, IT (equal split assumption) | B16: =$B$7/$B$3 -> 26.666667
A17: Generator ceiling, gross MW | B17: =$B$8*$B$9+$B$10 -> 127.884
A18: Generator ceiling, IT MW | B18: =ROUND(($B$8*$B$9+$B$10)/$B$11,1) -> 106.6
A19: Max tranches supportable on gensets (IT basis, equal split) | B19: =ROUNDDOWN(B18/B16,1) -> 3.9
A20: TCV per tranche $M (equal split) | B20: =$B$4/$B$3 -> 1932.5444
A21: Quarterly revenue per tranche $M (TCV/tranche / 20 qtrs) | B21: =B20/20 -> 96.627222
A22: Full run-rate $M/qtr (TCV/20) | B22: =$B$4/20 -> 869.645
A23: Q2-26 implied top-customer revenue $M | B23: =$B$12*$B$13 -> 139.752
A24: Q2-26 equal-split expectation for T1+T2 $M | B24: =2*B21 -> 193.25444
A25: Q2-26 top customer as % of full MSFT run-rate | B25: =B23/B22 -> 0.16070006
A28: Tranche | B28: Delivery (reported) | C28: Physical evidence / date | D28: Power source | E28: Est. MW gross (equal split, assumption) | F28: Est. MW IT (equal split) | G28: Cumulative IT MW | H28: Within genset ceiling? | I28: Est. billing start - Low (Bear) | J28: Est. billing start - Base | K28: Est. billing start - High (Bull) | L28: Risk type | M28: Tag | N28: Source | O28: Owned/leased | P28: GPU generation | Q28: Customer | R28: Contracted vs unsold | S28: Go-live (energized) low | T28: Go-live base | U28: Go-live high | V28: Go-live tag | W28: Billing start if Bloom slips 2Q | X28: Billing MW IT (equal split)
A29: T1 | B29: Nov 2025 (20-F) | C29: Oct 2025: 16 gensets (31.7 MW) start operating (DataOne letter to NJDEP) | D29: Rented Cat G3516H gensets | E29: =$B$15 -> 33.333333 | F29: =$B$16 -> 26.666667 | G29: =SUM($F$29:F29) -> 26.666667 | H29: =IF(G29<=$B$18+0.5,"yes","NO - needs Bloom") -> yes | I29: Q4 2025 | J29: Q4 2025 | K29: Q4 2025 | L29: Delivered; SLA/availability exposure if gensets must stop (NJDEP ~Nov 2026 deadline) | M29: Reported (delivery); Estimated (MW) | N29: https://www.sec.gov/Archives/edgar/data/1513845/000110465926052948/nbis-20251231x20f.htm; https://newjerseymonitor.com/2026/10/01/nj-data-center-polluted-air-for-nearly-a-year-before-regulators-intervened/ | O29: Leased (build-to-suit; DataOne owns shell) | P29: GB300 NVL72 (assumed; not disclosed) | Q29: Microsoft | R29: Contracted (take-or-pay) | S29: Q4 2025 | T29: Q4 2025 | U29: Q4 2025 | V29: Reported | W29: Q4 2025 | X29: =F29 -> 26.666667
A30: T2 | B30: Feb 2026 (20-F) | C30: Feb 2026: +16 gensets (32 total, 63.4 MW); city report "Phase 1 generators are online" | D30: Rented gensets | E30: =$B$15 -> 33.333333 | F30: =$B$16 -> 26.666667 | G30: =SUM($F$29:F30) -> 53.333333 | H30: =IF(G30<=$B$18+0.5,"yes","NO - needs Bloom") -> yes | I30: Q1 2026 | J30: Q1 2026 | K30: Q1 2026 | L30: Delivered; same SLA exposure | M30: Reported (delivery); Estimated (MW) | N30: https://www.sec.gov/Archives/edgar/data/1513845/000110465926052948/nbis-20251231x20f.htm; https://newjerseymonitor.com/2026/10/01/nj-data-center-polluted-air-for-nearly-a-year-before-regulators-intervened/ | O30: Leased (build-to-suit; DataOne owns shell) | P30: GB300 NVL72 (assumed; not disclosed) | Q30: Microsoft | R30: Contracted (take-or-pay) | S30: Q1 2026 | T30: Q1 2026 | U30: Q1 2026 | V30: Reported | W30: Q1 2026 | X30: =F30 -> 26.666667
A31: T3 | B31: Jul-Aug 2026 ("two tranches over the past month", Q2-26 letter Aug 12) | C31: Jun 2026: all 62 gensets fired (122.9 MW); >=45 running Aug (thermal drone); DataOne: >=3 of 14 halls operating early Aug | D31: Rented gensets | E31: =$B$15 -> 33.333333 | F31: =$B$16 -> 26.666667 | G31: =SUM($F$29:F31) -> 80 | H31: =IF(G31<=$B$18+0.5,"yes","NO - needs Bloom") -> yes | I31: Q3 2026 | J31: Q3 2026 | K31: Q3 2026 | L31: Delivered; same SLA exposure | M31: Reported (delivery); Estimated (MW, quarter) | N31: https://www.sec.gov/Archives/edgar/data/1513845/000110465926094568/tm2622968d1_ex99-2.htm; https://floodlightnews.org/new-jersey-dataones-illegal-still-running/; /workspace/nebius/capacity/altdata/altdata_timelines.xlsx (Timeline, Vineland_MW) | O31: Leased (build-to-suit; DataOne owns shell) | P31: GB300 NVL72 (assumed; not disclosed) | Q31: Microsoft | R31: Contracted (take-or-pay) | S31: Q3 2026 | T31: Q3 2026 | U31: Q3 2026 | V31: Reported | W31: Q3 2026 | X31: =F31 -> 26.666667
A32: T4 | B32: Jul-Aug 2026 (as T3) | C32: As T3. Cum. 4 x 26.7 IT = 107 MW = genset ceiling: no headroom | D32: Rented gensets | E32: =$B$15 -> 33.333333 | F32: =$B$16 -> 26.666667 | G32: =SUM($F$29:F32) -> 106.66667 | H32: =IF(G32<=$B$18+0.5,"yes","NO - needs Bloom") -> yes | I32: Q3 2026 | J32: Q3 2026 | K32: Q3 2026 | L32: Delivered; at ceiling - SLA risk if any units fail/curtailed | M32: Reported (delivery); Estimated (MW) | N32: https://www.sec.gov/Archives/edgar/data/1513845/000110465926094568/tm2622968d1_ex99-2.htm; https://www.enr.com/articles/63695-inside-the-vineland-data-center-power-dispute | O32: Leased (build-to-suit; DataOne owns shell) | P32: GB300 NVL72 (assumed; not disclosed) | Q32: Microsoft | R32: Contracted (take-or-pay) | S32: Q3 2026 | T32: Q3 2026 | U32: Q3 2026 | V32: Reported | W32: Q3 2026 | X32: =F32 -> 26.666667
A33: T5 | B33: Not yet ("continue to deliver the remaining tranches", Q2-26 call) | C33: Bloom units being placed (Sep 8 2026 imagery, low conf.); stop-construction order Aug 10 (lift not publicly confirmed); site plan approved Aug 17 | D33: Bloom fuel cells (328 MW installed / ~250 MW guaranteed) | E33: =$B$15 -> 33.333333 | F33: =$B$16 -> 26.666667 | G33: =SUM($F$29:F33) -> 133.33333 | H33: =IF(G33<=$B$18+0.5,"yes","NO - needs Bloom") -> NO - needs Bloom | I33: Q3 2027 | J33: Q2 2027 | K33: Q1 2027 | L33: TERMINATION/SLA risk (delivery after "during 2025 and 2026" window + grace period), not demand risk | M33: Estimated | N33: https://www.fool.com/earnings/call-transcripts/2026/08/19/nebius-nbis-q2-2026-earnings-call-transcript/ (cached /workspace/nebius/src/q2t.txt); https://hntrbrk.com/breaking-news/vineland; https://whyy.org/articles/vineland-planning-board-approves-data-center-plan/ | O33: Leased (build-to-suit; DataOne owns shell) | P33: GB300 NVL72 (assumed; not disclosed) | Q33: Microsoft | R33: Contracted (take-or-pay) | S33: Q2 2027 | T33: Q1 2027 | U33: Q4 2026 | V33: Estimated | W33: Q4 2027 | X33: =F33 -> 26.666667
A34: T6 | B34: Not yet | C34: As T5 | D34: Bloom | E34: =$B$15 -> 33.333333 | F34: =$B$16 -> 26.666667 | G34: =SUM($F$29:F34) -> 160 | H34: =IF(G34<=$B$18+0.5,"yes","NO - needs Bloom") -> NO - needs Bloom | I34: Q3 2027 | J34: Q2 2027 | K34: Q1 2027 | L34: Termination/SLA risk | M34: Estimated | N34: /workspace/nebius/capacity/altdata/altdata_timelines.xlsx (Timeline, Vineland_MW) | O34: Leased (build-to-suit; DataOne owns shell) | P34: GB300 NVL72 (assumed; not disclosed) | Q34: Microsoft | R34: Contracted (take-or-pay) | S34: Q2 2027 | T34: Q1 2027 | U34: Q4 2026 | V34: Estimated | W34: Q4 2027 | X34: =F34 -> 26.666667
A35: T7 | B35: Not yet | C35: As T5 | D35: Bloom | E35: =$B$15 -> 33.333333 | F35: =$B$16 -> 26.666667 | G35: =SUM($F$29:F35) -> 186.66667 | H35: =IF(G35<=$B$18+0.5,"yes","NO - needs Bloom") -> NO - needs Bloom | I35: Q4 2027 | J35: Q3 2027 | K35: Q2 2027 | L35: Termination/SLA risk | M35: Estimated | N35: /workspace/nebius/capacity/altdata/altdata_timelines.xlsx (Timeline, Vineland_MW) | O35: Leased (build-to-suit; DataOne owns shell) | P35: GB300 NVL72 (assumed; not disclosed) | Q35: Microsoft | R35: Contracted (take-or-pay) | S35: Q3 2027 | T35: Q2 2027 | U35: Q1 2027 | V35: Estimated | W35: Q1 2028 | X35: =F35 -> 26.666667
A36: T8 | B36: Not yet | C36: As T5 | D36: Bloom | E36: =$B$15 -> 33.333333 | F36: =$B$16 -> 26.666667 | G36: =SUM($F$29:F36) -> 213.33333 | H36: =IF(G36<=$B$18+0.5,"yes","NO - needs Bloom") -> NO - needs Bloom | I36: Q4 2027 | J36: Q3 2027 | K36: Q2 2027 | L36: Termination/SLA risk | M36: Estimated | N36: /workspace/nebius/capacity/altdata/altdata_timelines.xlsx (Timeline, Vineland_MW) | O36: Leased (build-to-suit; DataOne owns shell) | P36: GB300 NVL72 (assumed; not disclosed) | Q36: Microsoft | R36: Contracted (take-or-pay) | S36: Q3 2027 | T36: Q2 2027 | U36: Q1 2027 | V36: Estimated | W36: Q1 2028 | X36: =F36 -> 26.666667
A37: T9 | B37: Not yet | C37: As T5 | D37: Bloom | E37: =$B$15 -> 33.333333 | F37: =$B$16 -> 26.666667 | G37: =SUM($F$29:F37) -> 240 | H37: =IF(G37<=$B$18+0.5,"yes","NO - needs Bloom") -> NO - needs Bloom | I37: Q1 2028 | J37: Q3 2027 | K37: Q2 2027 | L37: Termination/SLA risk | M37: Estimated | N37: /workspace/nebius/capacity/altdata/altdata_timelines.xlsx (Timeline, Vineland_MW) | O37: Leased (build-to-suit; DataOne owns shell) | P37: GB300 NVL72 (assumed; not disclosed) | Q37: Microsoft | R37: Contracted (take-or-pay) | S37: Q4 2027 | T37: Q2 2027 | U37: Q1 2027 | V37: Estimated | W37: Q1 2028 | X37: =F37 -> 26.666667
A40: CONCLUSION: The Q2-26 letter says "all capacity tranches" delivered, but the call says "all the tranches that we were required to deliver ... up to date" and "continue to deliver the remaining tranches". Read: >=4 of 9 delivered (T1 Nov-25, T2 Feb-26, two in Jul/Aug-26); 5 remain.
A41: Physical cap: 62 rented gensets (122.9 MW) + ~5 MW grid = ~128 MW gross / ~107 MW IT ceiling. That supports ~4 equal tranches (4 x 26.7 IT = 107). T5-T9 (~5/9 of TCV) need Bloom fuel cells, which were stop-ordered Aug 10 2026 and not yet confirmed energized.
A42: Team hypothesis ("delivered = handed over; last tranche billing ~Q4-26") is NOT supported: the full run-rate needs Bloom; base case full billing Q3 2027.
A43: Q2-26 revenue check: top customer 24% x $582.3M = ~$140M vs equal-split T1+T2 = ~$193M. Either T1/T2 are smaller than 1/9 each (consistent with 16 gensets per tranche, ~27 IT MW) or customer C is not Microsoft (not disclosed).
A44: Dated risk: NJDEP AO ($1.07M, ~Sep 22 2026) gives 45 days to file for and obtain air permits or stop running the generators -> ~early/mid Nov 2026. If the gensets stop before Bloom is live, T1-T4 hit availability failures -> SLA credits / tranche-termination rights (20-F). This is a delivery/termination/SLA risk, NOT demand risk.
A45: Billing lag: T1-T4 billing assumed to start at delivery (reported dates). T5-T9 billing = Bloom energization + >=1 quarter (Estimated).

Sheet Tags_Sources
A1: Sheet | B1: Cell | C1: Value / formula | D1: Tag | E1: Source | F1: Note
A2: Sites | B2: C2 | C2: Build-to-suit (DataOne owns shell; Nebius tenant) | D2: Reported | E2: https://www.sec.gov/Archives/edgar/data/1513845/000110465925088312/tm2525580d1_6k.htm; https://www.sec.gov/Archives/edgar/data/1513845/000110465926052948/nbis-20251231x20f.htm; https://www.sec.gov/Archives/edgar/data/1513845/000110465926094568/tm2622968d1_ex99-2.htm; https://www.fool.com/earnings/call-transcripts/2026/08/19/nebius-nbis-q2-2026-earnings-call-transcript/ (cached /workspace/nebius/src/q2t.txt); https://www.enr.com/articles/63695-inside-the-vineland-data-center-power-dispute; https://newjerseymonitor.com/2026/10/01/nj-data-center-polluted-air-for-nearly-a-year-before-regulators-intervened/; https://www.nj.gov/governor/news/2026/20260922a.shtml; https://hntrbrk.com/breaking-news/vineland; https://whyy.org/articles/vineland-planning-board-approves-data-center-plan/; /workspace/nebius/capacity/altdata/altdata_timelines.xlsx (Timeline, Vineland_MW)
A3: Sites | B3: D2 | C3: Microsoft | D3: Reported | E3: Reported: 6-K Sep 2025 / 20-F: MSFT served from Vineland
A4: Sites | B4: F2 | C4: 300 | D4: Reported | E4: https://www.sec.gov/Archives/edgar/data/1513845/000110465925088312/tm2525580d1_6k.htm; https://www.sec.gov/Archives/edgar/data/1513845/000110465926052948/nbis-20251231x20f.htm; https://www.sec.gov/Archives/edgar/data/1513845/000110465926094568/tm2622968d1_ex99-2.htm; https://www.fool.com/earnings/call-transcripts/2026/08/19/nebius-nbis-q2-2026-earnings-call-transcript/ (cached /workspace/nebius/src/q2t.txt); https://www.enr.com/articles/63695-inside-the-vineland-data-center-power-dispute; https://newjerseymonitor.com/2026/10/01/nj-data-center-polluted-air-for-nearly-a-year-before-regulators-intervened/; https://www.nj.gov/governor/news/2026/20260922a.shtml; https://hntrbrk.com/breaking-news/vineland; https://whyy.org/articles/vineland-planning-board-approves-data-center-plan/; /workspace/nebius/capacity/altdata/altdata_timelines.xlsx (Timeline, Vineland_MW)
A5: Sites | B5: G2 | C5: Contracted 300 = gross (Estimated); energized rows = IT MW (altdata power-bounded) | D5: Estimated | E5: /workspace/nebius/capacity/gpu_mw_capex.xlsx sec.4; /workspace/nebius/capacity/site_list.xlsx / site_list.md
A6: Sites | B6: H2 | C6: not disclosed (IT est. uses PUE 1.2-1.35, Estimated) | D6: Reported | E6: https://www.sec.gov/Archives/edgar/data/1513845/000110465925088312/tm2525580d1_6k.htm; https://www.sec.gov/Archives/edgar/data/1513845/000110465926052948/nbis-20251231x20f.htm; https://www.sec.gov/Archives/edgar/data/1513845/000110465926094568/tm2622968d1_ex99-2.htm; https://www.fool.com/earnings/call-transcripts/2026/08/19/nebius-nbis-q2-2026-earnings-call-transcript/ (cached /workspace/nebius/src/q2t.txt); https://www.enr.com/articles/63695-inside-the-vineland-data-center-power-dispute; https://newjerseymonitor.com/2026/10/01/nj-data-center-polluted-air-for-nearly-a-year-before-regulators-intervened/; https://www.nj.gov/governor/news/2026/20260922a.shtml; https://hntrbrk.com/breaking-news/vineland; https://whyy.org/articles/vineland-planning-board-approves-data-center-plan/; /workspace/nebius/capacity/altdata/altdata_timelines.xlsx (Timeline, Vineland_MW)
A7: Sites | B7: I2 | C7: Phase 1 summer 2025; all 9 MSFT tranches during 2025-26; Vineland in 2026 connected power (Q2-26 call) | D7: Reported | E7: https://www.sec.gov/Archives/edgar/data/1513845/000110465925088312/tm2525580d1_6k.htm; https://www.sec.gov/Archives/edgar/data/1513845/000110465926052948/nbis-20251231x20f.htm; https://www.sec.gov/Archives/edgar/data/1513845/000110465926094568/tm2622968d1_ex99-2.htm; https://www.fool.com/earnings/call-transcripts/2026/08/19/nebius-nbis-q2-2026-earnings-call-transcript/ (cached /workspace/nebius/src/q2t.txt); https://www.enr.com/articles/63695-inside-the-vineland-data-center-power-dispute; https://newjerseymonitor.com/2026/10/01/nj-data-center-polluted-air-for-nearly-a-year-before-regulators-intervened/; https://www.nj.gov/governor/news/2026/20260922a.shtml; https://hntrbrk.com/breaking-news/vineland; https://whyy.org/articles/vineland-planning-board-approves-data-center-plan/; /workspace/nebius/capacity/altdata/altdata_timelines.xlsx (Timeline, Vineland_MW)
A8: Sites | B8: J2 | C8: ~107 MW IT ceiling on rented gensets through YE26; Bloom-powered remainder 1H-2H 2027 | D8: Estimated | E8: https://www.sec.gov/Archives/edgar/data/1513845/000110465925088312/tm2525580d1_6k.htm; https://www.sec.gov/Archives/edgar/data/1513845/000110465926052948/nbis-20251231x20f.htm; https://www.sec.gov/Archives/edgar/data/1513845/000110465926094568/tm2622968d1_ex99-2.htm; https://www.fool.com/earnings/call-transcripts/2026/08/19/nebius-nbis-q2-2026-earnings-call-transcript/ (cached /workspace/nebius/src/q2t.txt); https://www.enr.com/articles/63695-inside-the-vineland-data-center-power-dispute; https://newjerseymonitor.com/2026/10/01/nj-data-center-polluted-air-for-nearly-a-year-before-regulators-intervened/; https://www.nj.gov/governor/news/2026/20260922a.shtml; https://hntrbrk.com/breaking-news/vineland; https://whyy.org/articles/vineland-planning-board-approves-data-center-plan/; /workspace/nebius/capacity/altdata/altdata_timelines.xlsx (Timeline, Vineland_MW)
A9: Sites | B9: K2 | C9: Yellow/Red | D9: Estimated | E9: see site_verification.md
A10: Sites | B10: L2 | C10: GB300 NVL72 (assumed; not disclosed by Nebius) | D10: Estimated | E10: https://www.sec.gov/Archives/edgar/data/1513845/000110465925088312/tm2525580d1_6k.htm; https://www.sec.gov/Archives/edgar/data/1513845/000110465926052948/nbis-20251231x20f.htm; https://www.sec.gov/Archives/edgar/data/1513845/000110465926094568/tm2622968d1_ex99-2.htm; https://www.fool.com/earnings/call-transcripts/2026/08/19/nebius-nbis-q2-2026-earnings-call-transcript/ (cached /workspace/nebius/src/q2t.txt); https://www.enr.com/articles/63695-inside-the-vineland-data-center-power-dispute; https://newjerseymonitor.com/2026/10/01/nj-data-center-polluted-air-for-nearly-a-year-before-regulators-intervened/; https://www.nj.gov/governor/news/2026/20260922a.shtml; https://hntrbrk.com/breaking-news/vineland; https://whyy.org/articles/vineland-planning-board-approves-data-center-plan/; /workspace/nebius/capacity/altdata/altdata_timelines.xlsx (Timeline, Vineland_MW)
A11: Sites | B11: C3 | C11: Owned greenfield | D11: Reported | E11: https://nebius.com/independencemo; https://www.independencemo.gov/sites/default/files/2026-02/Nebius%20x%20Independence%2C%20MO.cleaned.pdf; https://citizenportal.ai/articles/7477161 (Independence PUAB: IPP PPA/ESA timeline); https://ded.mo.gov/press-room/nebius-breaks-ground-gigawatt-scale-ai-factory-independence; https://www.sec.gov/Archives/edgar/data/1513845/000110465926059872/tm2614392d1_ex99-2.htm; /workspace/nebius/capacity/altdata/altdata_timelines.xlsx (Timeline, Vineland_MW)
A12: Sites | B12: D3 | C12: unassigned (Meta #2 candidate - assumed) | D12: Estimated | E12: assumed: Meta #2 = multiple undisclosed locations; Phase 1 Q3-27 is after Meta #2 1H27 tranches
A13: Sites | B13: F3 | C13: 1200 | D13: Reported | E13: https://nebius.com/independencemo; https://www.independencemo.gov/sites/default/files/2026-02/Nebius%20x%20Independence%2C%20MO.cleaned.pdf; https://citizenportal.ai/articles/7477161 (Independence PUAB: IPP PPA/ESA timeline); https://ded.mo.gov/press-room/nebius-breaks-ground-gigawatt-scale-ai-factory-independence; https://www.sec.gov/Archives/edgar/data/1513845/000110465926059872/tm2614392d1_ex99-2.htm; /workspace/nebius/capacity/altdata/altdata_timelines.xlsx (Timeline, Vineland_MW)
... A365: Quarterly MW | B365: U9 | C365: 50 | D365: Estimated | E365: carried forward from Q4 2027
A366: Quarterly MW | B366: V9 | C366: 100 | D366: Estimated
A367: Quarterly MW | B367: W9 | C367: 100 | D367: Estimated | E367: carried forward from Q2 2028
A368: Quarterly MW | B368: X9 | C368: 200 | D368: Estimated | E368: Power capped ~250 MW until 2029 study
A369: Quarterly MW | B369: Y9 | C369: 200 | D369: Estimated | E369: carried forward from Q4 2028
A370: Quarterly MW | B370: Z9 | C370: 300 | D370: Estimated | E370: IPL 600 MW early 2029 (study)
A371: Quarterly MW | B371: AA9 | C371: 300 | D371: Estimated | E371: carried forward from Q2 2029
A372: Quarterly MW | B372: AB9 | C372: 500 | D372: Estimated
A373: Quarterly MW | B373: AC9 | C373: 500 | D373: Estimated | E373: carried forward from Q4 2029
A374: Quarterly MW | B374: AD9 | C374: 500 | D374: Estimated | E374: carried forward from Q4 2029
A375: Quarterly MW | B375: AE9 | C375: 500 | D375: Estimated | E375: carried forward from Q4 2029
A376: Quarterly MW | B376: AF9 | C376: 700 | D376: Estimated | E376: 1.2 GW needs on-site generation (evaluating)
A377: Quarterly MW | B377: E10 | C377: 0 | D377: Derived | E377: Not yet energized (0 before first anchor)
A378: Quarterly MW | B378: F10 | C378: 0 | D378: Derived | E378: Not yet energized (0 before first anchor)
A379: Quarterly MW | B379: G10 | C379: 0 | D379: Derived | E379: Not yet energized (0 before first anchor)
A380: Quarterly MW | B380: H10 | C380: 0 | D380: Derived | E380: Not yet energized (0 before first anchor)
A381: Quarterly MW | B381: I10 | C381: 0 | D381: Derived | E381: Not yet energized (0 before first anchor)
A382: Quarterly MW | B382: J10 | C382: 0 | D382: Derived | E382: Not yet energized (0 before first anchor)
A383: Quarterly MW | B383: K10 | C383: 0 | D383: Derived | E383: Not yet energized (0 before first anchor)
A384: Quarterly MW | B384: L10 | C384: 0 | D384: Derived | E384: Not yet energized (0 before first anchor)
... A393: Quarterly MW | B393: U10 | C393: 200 | D393: Estimated | E393: carried forward from Q4 2027
A394: Quarterly MW | B394: V10 | C394: 250 | D394: Estimated
A395: Quarterly MW | B395: W10 | C395: 250 | D395: Estimated | E395: carried forward from Q2 2028
A396: Quarterly MW | B396: X10 | C396: 250 | D396: Estimated | E396: Power capped ~250 MW until 2029 study
A397: Quarterly MW | B397: Y10 | C397: 250 | D397: Estimated | E397: carried forward from Q4 2028
A398: Quarterly MW | B398: Z10 | C398: 600 | D398: Estimated | E398: IPL 600 MW early 2029 (study)
A399: Quarterly MW | B399: AA10 | C399: 600 | D399: Estimated | E399: carried forward from Q2 2029
A400: Quarterly MW | B400: AB10 | C400: 800 | D400: Estimated
A401: Quarterly MW | B401: AC10 | C401: 800 | D401: Estimated | E401: carried forward from Q4 2029
A402: Quarterly MW | B402: AD10 | C402: 800 | D402: Estimated | E402: carried forward from Q4 2029
A403: Quarterly MW | B403: AE10 | C403: 800 | D403: Estimated | E403: carried forward from Q4 2029
A404: Quarterly MW | B404: AF10 | C404: 1200 | D404: Estimated | E404: 1.2 GW needs on-site generation (evaluating)
A405: Quarterly MW | B405: E11 | C405: formula: =(E9+E10)/2 | D405: Derived | E405: midpoint of low and high
A406: Quarterly MW | B406: F11 | C406: formula: =(F9+F10)/2 | D406: Derived | E406: midpoint of low and high
A407: Quarterly MW | B407: G11 | C407: formula: =(G9+G10)/2 | D407: Derived | E407: midpoint of low and high
A408: Quarterly MW | B408: H11 | C408: formula: =(H9+H10)/2 | D408: Derived | E408: midpoint of low and high
A409: Quarterly MW | B409: I11 | C409: formula: =(I9+I10)/2 | D409: Derived | E409: midpoint of low and high
A410: Quarterly MW | B410: J11 | C410: formula: =(J9+J10)/2 | D410: Derived | E410: midpoint of low and high
A411: Quarterly MW | B411: K11 | C411: formula: =(K9+K10)/2 | D411: Derived | E411: midpoint of low and high
A412: Quarterly MW | B412: L11 | C412: formula: =(L9+L10)/2 | D412: Derived | E412: midpoint of low and high
... A469: Quarterly MW | B469: T14 | C469: 0 | D469: Estimated | E469: Mgmt 260 MW Oct 2027; final land-dev plan pending; PPL 230 kV lines late-27 to early-29
A470: Quarterly MW | B470: U14 | C470: 0 | D470: Estimated
A471: Quarterly MW | B471: V14 | C471: 0 | D471: Estimated | E471: carried forward from Q1 2028
A472: Quarterly MW | B472: W14 | C472: 0 | D472: Estimated | E472: carried forward from Q1 2028
A473: Quarterly MW | B473: X14 | C473: 130 | D473: Estimated
A474: Quarterly MW | B474: Y14 | C474: 130 | D474: Estimated | E474: carried forward from Q4 2028
A475: Quarterly MW | B475: Z14 | C475: 260 | D475: Estimated | E475: Mgmt 660 MW Jan 2029
A476: Quarterly MW | B476: AA14 | C476: 260 | D476: Estimated | E476: carried forward from Q2 2029
A477: Quarterly MW | B477: AB14 | C477: 400 | D477: Estimated | E477: Mgmt 1,000+ MW Nov 2029
A478: Quarterly MW | B478: AC14 | C478: 400 | D478: Estimated | E478: carried forward from Q4 2029
A479: Quarterly MW | B479: AD14 | C479: 400 | D479: Estimated | E479: carried forward from Q4 2029
A480: Quarterly MW | B480: AE14 | C480: 400 | D480: Estimated | E480: carried forward from Q4 2029
A481: Quarterly MW | B481: AF14 | C481: 660 | D481: Estimated
A482: Quarterly MW | B482: E15 | C482: 0 | D482: Derived | E482: Not yet energized (0 before first anchor)
A483: Quarterly MW | B483: F15 | C483: 0 | D483: Derived | E483: Not yet energized (0 before first anchor)
A484: Quarterly MW | B484: G15 | C484: 0 | D484: Derived | E484: Not yet energized (0 before first anchor)
A485: Quarterly MW | B485: H15 | C485: 0 | D485: Derived | E485: Not yet energized (0 before first anchor)
A486: Quarterly MW | B486: I15 | C486: 0 | D486: Derived | E486: Not yet energized (0 before first anchor)
A487: Quarterly MW | B487: J15 | C487: 0 | D487: Derived | E487: Not yet energized (0 before first anchor)
A488: Quarterly MW | B488: K15 | C488: 0 | D488: Derived | E488: Not yet energized (0 before first anchor)
A489: Quarterly MW | B489: L15 | C489: 0 | D489: Derived | E489: Not yet energized (0 before first anchor)
A490: Quarterly MW | B490: M15 | C490: 0 | D490: Derived | E490: Not yet energized (0 before first anchor)
A491: Quarterly MW | B491: N15 | C491: 0 | D491: Derived | E491: Not yet energized (0 before first anchor)
A492: Quarterly MW | B492: O15 | C492: 0 | D492: Derived | E492: Not yet energized (0 before first anchor)
A493: Quarterly MW | B493: P15 | C493: 0 | D493: Derived | E493: Not yet energized (0 before first anchor)
... A497: Quarterly MW | B497: T15 | C497: 130 | D497: Estimated | E497: Mgmt 260 MW Oct 2027; final land-dev plan pending; PPL 230 kV lines late-27 to early-29
A498: Quarterly MW | B498: U15 | C498: 260 | D498: Estimated
A499: Quarterly MW | B499: V15 | C499: 260 | D499: Estimated | E499: carried forward from Q1 2028
A500: Quarterly MW | B500: W15 | C500: 260 | D500: Estimated | E500: carried forward from Q1 2028
A501: Quarterly MW | B501: X15 | C501: 400 | D501: Estimated
A502: Quarterly MW | B502: Y15 | C502: 400 | D502: Estimated | E502: carried forward from Q4 2028
A503: Quarterly MW | B503: Z15 | C503: 660 | D503: Estimated | E503: Mgmt 660 MW Jan 2029
A504: Quarterly MW | B504: AA15 | C504: 660 | D504: Estimated | E504: carried forward from Q2 2029
A505: Quarterly MW | B505: AB15 | C505: 1000 | D505: Estimated | E505: Mgmt 1,000+ MW Nov 2029
A506: Quarterly MW | B506: AC15 | C506: 1000 | D506: Estimated | E506: carried forward from Q4 2029
A507: Quarterly MW | B507: AD15 | C507: 1000 | D507: Estimated | E507: carried forward from Q4 2029
A508: Quarterly MW | B508: AE15 | C508: 1000 | D508: Estimated | E508: carried forward from Q4 2029
A509: Quarterly MW | B509: AF15 | C509: 1200 | D509: Estimated
A510: Quarterly MW | B510: E16 | C510: formula: =(E14+E15)/2 | D510: Derived | E510: midpoint of low and high
A511: Quarterly MW | B511: F16 | C511: formula: =(F14+F15)/2 | D511: Derived | E511: midpoint of low and high
A512: Quarterly MW | B512: G16 | C512: formula: =(G14+G15)/2 | D512: Derived | E512: midpoint of low and high
A513: Quarterly MW | B513: H16 | C513: formula: =(H14+H15)/2 | D513: Derived | E513: midpoint of low and high
A514: Quarterly MW | B514: I16 | C514: formula: =(I14+I15)/2 | D514: Derived | E514: midpoint of low and high
A515: Quarterly MW | B515: J16 | C515: formula: =(J14+J15)/2 | D515: Derived | E515: midpoint of low and high
A516: Quarterly MW | B516: K16 | C516: formula: =(K14+K15)/2 | D516: Derived | E516: midpoint of low and high
A517: Quarterly MW | B517: L16 | C517: formula: =(L14+L15)/2 | D517: Derived | E517: midpoint of low and high
A518: Quarterly MW | B518: M16 | C518: formula: =(M14+M15)/2 | D518: Derived | E518: midpoint of low and high
...

Sheet Basis
A1: Site | B1: Key | C1: Ownership | D1: Stated MW basis (IT / gross / not stated) | E1: Evidence for basis | F1: Treated as (for normalization) | G1: Gross/IT factor (PUE-based) | H1: Factor tag | I1: Factor basis / PUE assumption | J1: Source
A2: Vineland NJ (DataOne) | B2: VIN | C2: leased | D2: IT (energized rows); contracted 300 = gross | E2: Energized rows are power-bounded IT (gensets/1.2); 300 MW gross vs Bloom 328 installed + 5 grid supply (gpu_mw_capex.md) | F2: IT | G2: 1.2 | H2: Estimated | I2: Operating PUE 1.2 for liquid-cooled GB300 (team ceiling formula); design ratio 300/240 = 1.25 | J2: /workspace/nebius/peers/comparison.xlsx (Contracts_$MWyr, Sites tabs)
A3: Independence MO (Eastgate) | B3: IND | C3: owned | D3: not stated | E3: Utility (IPL/IPP) power figures | F3: gross | G3: 1.35 | H3: Estimated | I3: Peer utility-to-IT design ratios 1.30-1.52 (AIB 65/50, Crusoe 900/672, Denton 394/262, Helios 800/526; peers comparison.xlsx); operating PUE ~1.2-1.3 | J3: /workspace/nebius/peers/comparison.xlsx (Contracts_$MWyr, Sites tabs)
A4: Butler Twp PA (Highridge) | B4: BUT | C4: owned | D4: not stated | E4: PPL ESA = utility load | F4: gross | G4: 1.35 | H4: Estimated | I4: as IND | J4: /workspace/nebius/peers/comparison.xlsx (Contracts_$MWyr, Sites tabs)
A5: Birmingham AL (BHM01, Oxmoor) | B5: BHM | C5: owned | D5: not stated | E5: 300 MW press figure; Alabama Power 115/230 kV | F5: gross | G5: 1.35 | H5: Estimated | I5: as IND | J5: /workspace/nebius/peers/comparison.xlsx (Contracts_$MWyr, Sites tabs)
A6: Bethune FR (Azur Datacenter, ex-Bridgestone) | B6: BET | C6: leased | D6: not stated | E6: 240 MW grid connection (press) | F6: gross | G6: 1.3 | H6: Estimated | I6: Northern France climate; peer range | J6: /workspace/nebius/peers/comparison.xlsx (Contracts_$MWyr, Sites tabs)
A7: Lappeenranta FI (Pajarila / Polarnode) | B7: LAP | C7: owned | D7: not stated | E7: 310 MW site/substation figures | F7: gross | G7: 1.15 | H7: Estimated | I7: Nordic free cooling (Mantsala-class) | J7: /workspace/nebius/peers/comparison.xlsx (Contracts_$MWyr, Sites tabs)
A8: Mantsala FI #1 | B8: MA1 | C8: owned | D8: not stated | E8: 75 MW site figure; Nebius cites "one of the world's leading PUE" | F8: gross | G8: 1.1 | H8: Estimated | I8: PUE ~1.1 (company statements per site_list; 20-F gives no number) | J8: /workspace/nebius/peers/comparison.xlsx (Contracts_$MWyr, Sites tabs)
A9: Mantsala FI #2 (Kapuli) | B9: MA2 | C9: owned | D9: not stated | E9: 70 MW substation (Caverion) | F9: gross | G9: 1.15 | H9: Estimated | I9: Nordic | J9: /workspace/nebius/peers/comparison.xlsx (Contracts_$MWyr, Sites tabs)
A10: Kansas City MO (Patmos) | B10: KC | C10: leased | D10: not stated | E10: Colo; Patmos facility MW | F10: IT | G10: 1.35 | H10: Estimated | I10: Air-cooled Hopper/B200 retrofit; colo leases usually priced on critical IT | J10: /workspace/nebius/peers/comparison.xlsx (Contracts_$MWyr, Sites tabs)
A11: Paris (Equinix PA10) | B11: PAR | C11: leased | D11: not stated | E11: Colo; 5 MW third-party | F11: IT | G11: 1.35 | H11: Estimated | I11: Equinix urban colo | J11: /workspace/nebius/peers/comparison.xlsx (Contracts_$MWyr, Sites tabs)
A12: Keflavik IS (Verne) | B12: KEF | C12: leased | D12: not stated | E12: Colo (Verne) | F12: IT | G12: 1.15 | H12: Estimated | I12: Iceland free cooling | J12: /workspace/nebius/peers/comparison.xlsx (Contracts_$MWyr, Sites tabs)
A13: London Longcross (Ark LP01) | B13: LON | C13: leased | D13: gross (Derived) | E13: 7,000 B300 on 19 MW = 368/MW fits gross density (gpu_mw_capex.xlsx Nebius checks) | F13: gross | G13: 1.3 | H13: Estimated | I13: Air-cooled HGX B300 | J13: /workspace/nebius/peers/comparison.xlsx (Contracts_$MWyr, Sites tabs)
... A25: AIB CLT1 (Moore, Spartanburg County SC; Lockhart Power) | B25: AIB | C25: leased | D25: IT (Reported) | E25: "50 MW of critical IT capacity" on 65 MW utility ESA (AIB PR Sep 30 2026) | F25: IT | G25: 1.3 | H25: Derived | I25: 65/50 = 1.30 | J25: https://www.globenewswire.com/news-release/2026/09/30/3371855/0/en/aib-data-centers-signs-contract-with-nebius-for-ai-data-center-capacity.html
A27: Peer conversion evidence (peers/comparison.xlsx): AIB CLT1 65 MW utility / 50 MW IT = 1.30; Crusoe-Microsoft Abilene 900 gross / 672 IT = 1.34; Crusoe-Oracle Abilene 1.2 GW / ~843 IT = 1.42; Vantage Port Washington ~1.3 GW / ~902 IT = 1.44; Core Scientific Denton 394 grid / 262 IT = 1.50; Galaxy Helios 800 / 526 IT = 1.52. These are DESIGN (utility-to-IT) ratios incl. headroom; operating PUE for liquid-cooled builds is lower (~1.15-1.3). Factors here sit between the two (Estimated).
A28: IT-normalized MW = energized MW / factor if treated as gross, else as stated. Gross MW = energized MW x factor if treated as IT, else as stated. n/d sites excluded.

Sheet Capacity tranches
A1: Tranche / block | B1: Site | C1: Owned/leased | D1: GPU generation | E1: Customer | F1: Contracted vs unsold | G1: MW (stated) | H1: MW IT (normalized, YE27 base) | I1: Go-live low | J1: Go-live base | K1: Go-live high | L1: Go-live tag | M1: Evidence | N1: Source
A2: Microsoft T1-T9 (see Vineland tranche track) | B2: Vineland NJ (DataOne) | C2: leased | D2: GB300 NVL72 (assumed) | E2: Microsoft | F2: Contracted ($17.39B TCV, 9 tranches) | G2: 300 | H2: 240 | I2: Q4 2025 | J2: Q4 2025 | K2: Q4 2025 | L2: Reported (T1); T5-T9 Estimated | M2: T1 Nov-25, T2 Feb-26, T3-T4 Jul/Aug-26; T5-T9 need Bloom | N2: https://www.sec.gov/Archives/edgar/data/1513845/000110465926052948/nbis-20251231x20f.htm
A3: Meta #1 (2 tranches, $2.88B, 5-yr) | B3: site not disclosed | C3: n/d | D3: n/d | E3: Meta | F3: Contracted; delivered (T1 Nov/Dec-25, T2 Feb-26) | G3: n/d | H3: n/d | I3: Q4 2025 | J3: Q4 2025 | K3: Q4 2025 | L3: Reported | M3: 20-F: first tranche Nov 2025 (Dec 2025 in FS note), second Feb 2026; MW not disclosed (peer file ~50 IT MW = unsourced, E low) | N3: https://www.sec.gov/Archives/edgar/data/1513845/000110465926052948/nbis-20251231x20f.htm
A4: Meta #2 dedicated ($12B, 5-yr, Vera Rubin, multiple locations) | B4: n/d (Bethune likely per press) | C4: n/d | D4: Vera Rubin NVL72 (Reported) | E4: Meta | F4: Contracted | G4: n/d | H4: n/d | I4: Q1 2027 | J4: Q1 2027 | K4: Q2 2027 | L4: Reported (start "early 2027" / 1H27) | M4: 20-F: delivery expected to commence early 2027; plus up to $15B Meta backstop for unsold capacity of certain clusters | N4: https://www.sec.gov/Archives/edgar/data/1513845/000110465926052948/nbis-20251231x20f.htm
A5: Q2-26 large AI-cloud deals (4 deals, avg >$1B TCV; e.g. Reflection, Cohere) | B5: n/d | C5: n/d | D5: n/d (new-gen) | E5: Q2 neolab deals | F5: Contracted | G5: n/d | H5: n/d | I5: Q4 2026 | J5: Q4 2026 | K5: Q1 2027 | L5: Reported (from late Q4 2026) | M5: ACV $20-25M/MW; "start coming online from late Q4 and onwards" (Q2-26 call); MW = TCV/(term x ACV) but term not disclosed -> n/d | N5: https://www.sec.gov/Archives/edgar/data/1513845/000110465926094568/tm2622968d1_ex99-2.htm; https://www.fool.com/earnings/call-transcripts/2026/08/19/nebius-nbis-q2-2026-earnings-call-transcript/ (cached /workspace/nebius/src/q2t.txt)
A6: Independence MO (Eastgate) - site block | B6: Independence MO (Eastgate) | C6: owned | D6: Vera Rubin NVL72 | E6: unassigned (Meta #2 candidate - assumed) | F6: Contracted | G6: 1200 | H6: ='Quarterly MW'!T11/Basis!$G$3 -> 92.592593 | I6: Q4 2027 | J6: Q3 2027 | K6: Q3 2027 | L6: Estimated (first quarter with energized MW > 0) | M6: Phase 1 ~Q3 2027; 600 MW not before 2029 | N6: https://nebius.com/independencemo; https://www.independencemo.gov/sites/default/files/2026-02/Nebius%20x%20Independence%2C%20MO.cleaned.pdf; https://citizenportal.ai/articles/7477161 (Independence PUAB: IPP PPA/ESA timeline); https://ded.mo.gov/press-room/nebius-breaks-ground-gigawatt-scale-ai-facto
A7: Butler Twp PA (Highridge) - site block | B7: Butler Twp PA (Highridge) | C7: owned | D7: Vera Rubin NVL72 | E7: unassigned | F7: Unsold / self-serve or undisclosed customer (not disclosed) | G7: 1200 | H7: ='Quarterly MW'!T16/Basis!$G$4 -> 48.148148 | I7: Q4 2028 | J7: Q4 2027 | K7: Q4 2027 | L7: Estimated (first quarter with energized MW > 0) | M7: First MW Q4 2027 at best; base ~Q2 2028-2029 (PPL lines late-27 to early-29; 3-yr build) | N7: https://nebius.com/schuylkillcountypa; https://www.republicanherald.com/2026/09/01/nebius-gets-green-light-to-expand-its-data-center-plan-in-butler-twp/; https://www.republicanherald.com/2026/04/24/butler-twp-switchyard-to-anchor-data-center-in-ppl-powerline-overhaul/; https://www.datacenterdynamics
A8: Birmingham AL (BHM01, Oxmoor) - site block | B8: Birmingham AL (BHM01, Oxmoor) | C8: owned | D8: Vera Rubin NVL72 | E8: unassigned | F8: Unsold / self-serve or undisclosed customer (not disclosed) | G8: 300 | H8: ='Quarterly MW'!T21/Basis!$G$5 -> 55.555556 | I8: Q3 2027 | J8: Q1 2027 | K8: Q1 2027 | L8: Estimated (first quarter with energized MW > 0) | M8: 115 kV NLT Dec 31 2026; first revenue MW 2027; 230 kV Oct 2027 | N8: https://nebius.com/birminghamal; https://abc3340.com/resources/pdf/9222f76a-3063-46e4-aee7-796b30ed611f-NebiusResponsestoCityLetter_Redacted.pdf; https://bhamnow.com/2026/05/18/40-million-permits-birmingham-data-center/; https://www.wbhm.org/local-news/2026-09-18/action-picks-up-in-lawsuits-targetin
A9: Bethune FR (Azur Datacenter, ex-Bridgestone) - site block | B9: Bethune FR (Azur Datacenter, ex-Bridgestone) | C9: leased | D9: GB300 NVL72 | E9: Meta (#2 likely) - press | F9: Contracted | G9: 240 | H9: ='Quarterly MW'!T26/Basis!$G$6 -> 138.46154 | I9: Q1 2027 | J9: Q4 2026 | K9: Q4 2026 | L9: Estimated (first quarter with energized MW > 0) | M9: Start Q4 2026 (~27 MW initial); 120 MW ~1H27; prefect ICPE decision pending | N9: https://www.reuters.com/technology/amsterdam-based-ai-firm-nebius-build-240mw-data-centre-near-lille-france-2026-02-12/; https://www.lavoixdunord.fr/1740138/article/2026-09-24/la-premiere-ia-factory-des-hauts-de-france-va-bientot-prendre-vie-bethune; https://www.nordfranceinvest.com/success-story/du
A10: Lappeenranta FI (Pajarila / Polarnode) - site block | B10: Lappeenranta FI (Pajarila / Polarnode) | C10: owned | D10: Vera Rubin NVL72 | E10: unassigned | F10: Unsold / self-serve or undisclosed customer (not disclosed) | G10: 310 | H10: ='Quarterly MW'!T31/Basis!$G$7 -> 45.652174 | I10: Q4 2027 | J10: Q2 2027 | K10: Q2 2027 | L10: Estimated (first quarter with energized MW > 0) | M10: First building H1 2027 (Fira); substation spring 2027 | N10: https://nebius.com/newsroom/nebius-to-construct-310-mw-ai-factory-in-finland; https://fira.fi/en/tiedote/construction-and-project-development-company-fira-selected-as-main-contractor-for-one-of-europes-largest-ai-data-center-projects/; https://www.caverion.com/newsroom/releases/2026/caverion-to-deli
A11: Mantsala FI #1 - site block | B11: Mantsala FI #1 | C11: owned | D11: Hopper (first 25 MW) + GB300 NVL72 (expansion, Estimated split) | E11: self-serve (assumed); Meta #1 site not disclosed | F11: Contracted | G11: 75 | H11: ='Quarterly MW'!T36/Basis!$G$8 -> 68.181818 | I11: Q1 2024 | J11: Q1 2024 | K11: Q1 2024 | L11: Estimated (first quarter with energized MW > 0) | M11: 75 MW built (completed early 2026) | N11: https://assets.nebius.com/assets/6590d0a0-0fc4-4396-bc3f-f52a9ccb770e/20260331%20Nebius%20to%20construct%20310%20MW%20AI%20factory%20in%20Finland.pdf; /workspace/nebius/capacity/altdata/altdata_timelines.xlsx (Timeline, Vineland_MW)
A12: Mantsala FI #2 (Kapuli) - site block | B12: Mantsala FI #2 (Kapuli) | C12: owned | D12: Vera Rubin NVL72 | E12: unassigned | F12: Unsold / self-serve or undisclosed customer (not disclosed) | G12: 70 | H12: ='Quarterly MW'!T41/Basis!$G$9 -> 15.217391 | I12: Q1 2028 | J12: Q4 2027 | K12: Q4 2027 | L12: Estimated (first quarter with energized MW > 0) | M12: Q4 2027 earliest (substation completes autumn 2027) | N12: https://www.assemblincaverion.com/news-and-media/news/2026/caverion-finland-strengthens-its-position-in-the-data-centre-market-and-will-deliver-a-eur-15-million-substation-for-ai-cloud-company-nebius/; https://www.datacenterdynamics.com/en/news/nebius-expands-european-presence-announces-deployment-i
A13: Kansas City MO (Patmos) - site block | B13: Kansas City MO (Patmos) | C13: leased | D13: H200 (first 5 MW) + B200 (rest) | E13: self-serve (assumed) | F13: Unsold / self-serve or undisclosed customer (not disclosed) | G13: 40 | H13: ='Quarterly MW'!T46 -> 30 | I13: Q1 2025 | J13: Q1 2025 | K13: Q1 2025 | L13: Estimated (first quarter with energized MW > 0) | M13: Operational; Nebius share of 35 MW facility not disclosed | N13: https://www.datacenterdynamics.com/en/news/nebius-to-deploy-5mw-nvidia-h200-cluster-at-patmos-data-center-in-kansas-city-missouri/; https://www.datacenterdynamics.com/en/news/patmos-adds-10mw-of-capacity-at-kansas-city-data-center/; https://careers.nebius.com/?gh_jid=4975997101
A14: Paris (Equinix PA10) - site block | B14: Paris (Equinix PA10) | C14: leased | D14: Hopper H100/H200 | E14: self-serve (assumed) | F14: Unsold / self-serve or undisclosed customer (not disclosed) | G14: 5 | H14: ='Quarterly MW'!T51 -> 5 | I14: Q4 2024 | J14: Q4 2024 | K14: Q4 2024 | L14: Estimated (first quarter with energized MW > 0) | M14: Operational | N14: https://dcatlas.io/en/explore/facilities/nebius-equinix-paris (3rd-party, low confidence); https://docs.nebius.com/overview/regions (accessed 2026-10-04)
A15: Keflavik IS (Verne) - site block | B15: Keflavik IS (Verne) | C15: leased | D15: Hopper H100/H200 | E15: self-serve (assumed) | F15: Unsold / self-serve or undisclosed customer (not disclosed) | G15: 10 | H15: ='Quarterly MW'!T56 -> 10 | I15: Q1 2025 | J15: Q1 2025 | K15: Q1 2025 | L15: Estimated (first quarter with energized MW > 0) | M15: Operational (private region) | N15: https://nebius.com/blog/posts/300-mw-new-jersey-and-iceland-regions; https://docs.nebius.com/overview/regions (accessed 2026-10-04)
A16: London Longcross (Ark LP01) - site block | B16: London Longcross (Ark LP01) | C16: leased | D16: B300 (HGX) | E16: self-serve (assumed) | F16: Unsold / self-serve or undisclosed customer (not disclosed) | G16: 19 | H16: ='Quarterly MW'!T61/Basis!$G$13 -> 14.615385 | I16: Q4 2025 | J16: Q4 2025 | K16: Q4 2025 | L16: Estimated (first quarter with energized MW > 0) | M16: 19 MW by ~Q4 2026; LP02 share/timing not disclosed | N16: https://datacentrenews.uk/story/nebius-fills-ark-s-longcross-data-centre-to-capacity; https://www.datacenterdynamics.com/en/news/ark-dc-to-add-new-building-to-longcross-data-center-campus-outside-london-uk/; https://docs.nebius.com/overview/regions (accessed 2026-10-04)
A17: Harlow UK (Kao Data KLON-02/03) - site block | B17: Harlow UK (Kao Data KLON-02/03) | C17: leased | D17: B300 (HGX) | E17: self-serve (assumed) | F17: Unsold / self-serve or undisclosed customer (not disclosed) | G17: 22 | H17: ='Quarterly MW'!T66 -> 22 | I17: Q1 2027 | J17: Q4 2026 | K17: Q4 2026 | L17: Estimated (first quarter with energized MW > 0) | M17: KLON-03 completion end-2026; MW early 2027 | N17: https://www.datacenterdynamics.com/en/news/nebius-signs-22mw-capacity-agreement-with-kao-data-in-the-uk/; https://www.linkedin.com/posts/infratil_klon-03-development-update-activity-7404073674942656512-l6mm; https://nebius.com/newsroom/nebius-expands-in-uk-with-more-nvidia-powered-infrastructure-mor
A18: Newport UK (Vantage CWL1) - site block | B18: Newport UK (Vantage CWL1) | C18: leased | D18: GB300 NVL72 | E18: self-serve (assumed) | F18: Unsold / self-serve or undisclosed customer (not disclosed) | G18: n/d | H18: ='Quarterly MW'!T71 -> 31.5 | I18: Q1 2027 | J18: Q4 2026 | K18: Q4 2026 | L18: Estimated (first quarter with energized MW > 0) | M18: Newport + UK 3rd = 65 - 22 (Harlow) = 43 MW by 2027 (Derived); Newport ~29 if LON-East is the 3rd site (low) | N18: https://vantage-dc.com/news/vantage-data-centers-and-nebius-expand-uk-ai-infrastructure-with-first-deployment-in-south-wales-ai-growth-zone/; https://nebius.com/newsroom/nebius-expands-in-uk-with-more-nvidia-powered-infrastructure-more-customers-and-more-cloud-capabilities-for-agentic-and-enterprise
A19: UK 3rd new deployment (lead: Green Mountain LON-East, Romford) - site block | B19: UK 3rd new deployment (lead: Green Mountain LON-East, Romford) | C19: leased | D19: GB300 NVL72 | E19: unassigned | F19: Unsold / self-serve or undisclosed customer (not disclosed) | G19: n/d | H19: ='Quarterly MW'!T76 -> 7 | I19: after Q4 2030 | J19: Q2 2027 | K19: Q2 2027 | L19: Estimated (first quarter with energized MW > 0) | M19: Lead only: Green Mountain LON-East 14 MW to unnamed neocloud (Sep 1 2026) + Nebius East London job (Feb 2); low confidence | N19: https://nebius.com/newsroom/nebius-expands-in-uk-with-more-nvidia-powered-infrastructure-more-customers-and-more-cloud-capabilities-for-agentic-and-enterprise-ai; https://www.datacenterdynamics.com/en/news/green-mountain-secures-neocloud-customer-at-data-center-in-london-uk/
A20: Modi'in IL (Mega Or) - site block | B20: Modi'in IL (Mega Or) | C20: leased | D20: B200 (HGX) | E20: self-serve (assumed); 25% to Israel Innovation Authority | F20: Unsold / self-serve or undisclosed customer (not disclosed) | G20: 8 | H20: ='Quarterly MW'!T81 -> 8 | I20: Q4 2025 | J20: Q4 2025 | K20: Q4 2025 | L20: Estimated (first quarter with energized MW > 0) | M20: Operational | N20: https://nebius.com/newsroom/nebius-brings-nvidia-blackwell-to-israel-with-one-of-the-country-s-first-ai-infrastructure-deployments; https://www.datacenterdynamics.com/en/news/nebius-signs-80mw-data-center-lease-with-mega-or-in-israel/
A21: Masmiyya IL (Mega DC) - site block | B21: Masmiyya IL (Mega DC) | C21: leased | D21: GB300 NVL72 | E21: unassigned | F21: Unsold / self-serve or undisclosed customer (not disclosed) | G21: 22 | H21: ='Quarterly MW'!T86 -> 22 | I21: Q2 2027 | J21: Q4 2026 | K21: Q4 2026 | L21: Estimated (first quarter with energized MW > 0) | M21: Mega Or Q2-26 deck: Yoav construction completion Q4 2026 -> Q4-26/Q2-27 | N21: https://www.datacenterdynamics.com/en/news/nebius-signs-80mw-data-center-lease-with-mega-or-in-israel/; https://www.calcalistech.com/ctechnews/article/25ue6vi49; https://www.deeptase.co.il/en/analysis/4873
A22: Beit Shemesh IL (Mega DC) - site block | B22: Beit Shemesh IL (Mega DC) | C22: leased | D22: GB300 NVL72 | E22: unassigned | F22: Unsold / self-serve or undisclosed customer (not disclosed) | G22: 58 | H22: ='Quarterly MW'!T91 -> 58 | I22: Q2 2027 | J22: Q1 2027 | K22: Q1 2027 | L22: Estimated (first quarter with energized MW > 0) | M22: Mega Or Q2-26 deck: completion Q2 2027 -> staged Q1-Q4 2027 | N22: https://www.datacenterdynamics.com/en/news/nebius-signs-80mw-data-center-lease-with-mega-or-in-israel/; https://www.calcalistech.com/ctechnews/article/25ue6vi49; https://www.deeptase.co.il/en/analysis/4873
A23: Madrid-Getafe ES (Merlin Edged) - site block | B23: Madrid-Getafe ES (Merlin Edged) | C23: leased | D23: B300 (HGX) | E23: self-serve (assumed) | F23: Unsold / self-serve or undisclosed customer (not disclosed) | G23: 18 | H23: ='Quarterly MW'!T96 -> 18 | I23: Q3 2026 | J23: Q3 2026 | K23: Q3 2026 | L23: Estimated (first quarter with energized MW > 0) | M23: Phase 1 live; 18 MW by Q4 2026-Q1 2027 | N23: https://www.linkedin.com/feed/update/urn:li:activity:7505906816590073857; https://www.merlinproperties.com/dia-a-dia/firmamos-un-contrato-de-18-mw-con-nebius-para-nuestro-date-center-madrid-getafe/; https://docs.nebius.com/overview/regions (accessed 2026-10-04)
A24: Tallinn EE (Greenergy Huuru) - site block | B24: Tallinn EE (Greenergy Huuru) | C24: leased | D24: GB300 NVL72 | E24: unassigned | F24: Unsold / self-serve or undisclosed customer (not disclosed) | G24: 22 | H24: ='Quarterly MW'!T101 -> 22 | I24: Q1 2027 | J24: Q4 2026 | K24: Q4 2026 | L24: Estimated (first quarter with energized MW > 0) | M24: Q4 2026-Q2 2027; Estonian govt security review discussed at Cabinet (Aug 2026) | N24: https://news.err.ee/1610109073/baltics-first-ai-factory-to-open-in-estonia; https://www.datacenterdynamics.com/en/news/nebius-expands-european-presence-announces-deployment-in-estonia-and-second-data-center-in-m%C3%A4nts%C3%A4l%C3%A4-finland/
A25: Minnesota colo (us-north1, Woodbury) - site block | B25: Minnesota colo (us-north1, Woodbury) | C25: leased | D25: B300 (HGX) | E25: self-serve (assumed) | F25: Unsold / self-serve or undisclosed customer (not disclosed) | G25: n/d | H25: ='Quarterly MW'!T106 -> 10 | I25: Q1 2026 | J25: Q1 2026 | K25: Q1 2026 | L25: Estimated (first quarter with energized MW > 0) | M25: us-north1 Woodbury; likely IronGate MSP01 (15 MW live, fully leased; inference) | N25: https://www.sec.gov/Archives/edgar/data/1513845/000110465926052948/nbis-20251231x20f.htm; https://docs.nebius.com/overview/regions (accessed 2026-10-04); https://woodburynewsnet.org/7933/business/what-woodbury-residents-should-know-about-irongates-two-data-centers/; https://boards-api.greenhouse.io/
A26: Oklahoma colo (unnamed) - site block | B26: Oklahoma colo (unnamed) | C26: leased | D26: GB300 NVL72 | E26: unassigned | F26: Unsold / self-serve or undisclosed customer (not disclosed) | G26: >100 (map category) | H26: ='Quarterly MW'!T111 -> 100 | I26: Q3 2026 | J26: Q2 2026 | K26: Q2 2026 | L26: Estimated (first quarter with energized MW > 0) | M26: Q2-26 letter map: Sites >100MW; 8 on-site roles since Mar 2 2026; town/landlord not found | N26: https://www.sec.gov/Archives/edgar/data/1513845/000110465926052948/nbis-20251231x20f.htm; https://assets.nebius.com/assets/a6ecfd85-a6cb-4967-8ef7-9a25bd261f9c/SHLQ226.pdf (p.2 map); https://boards-api.greenhouse.io/v1/boards/nebius/jobs?content=true (accessed 2026-10-04)
A27: France 2nd colo (unnamed; possibly eu-west2) - site block | B27: France 2nd colo (unnamed; possibly eu-west2) | C27: leased | D27: B300 (HGX) (inference) | E27: unassigned | F27: Unsold / self-serve or undisclosed customer (not disclosed) | G27: n/d | H27: n/d | I27: n/d | J27: n/d | K27: n/d | L27: Estimated (first quarter with energized MW > 0) | M27: eu-west2 (France, B300) live in docs - mapping is inference; MW n/d -> in plug | N27: https://www.sec.gov/Archives/edgar/data/1513845/000110465926052948/nbis-20251231x20f.htm; https://docs.nebius.com/overview/regions (accessed 2026-10-04)
A28: AIB CLT1 (Moore, Spartanburg County SC; Lockhart Power) - site block | B28: AIB CLT1 (Moore, Spartanburg County SC; Lockhart Power) | C28: leased | D28: Vera Rubin NVL72 | E28: unassigned | F28: Unsold / self-serve or undisclosed customer (not disclosed) | G28: 50 | H28: ='Quarterly MW'!T121 -> 25 | I28: Q1 2028 | J28: Q3 2027 | K28: Q3 2027 | L28: Estimated (first quarter with energized MW > 0) | M28: Hall 1 ~Q3-Q4 2027; permits only submitted; project financing not arranged | N28: http://archive.fast-edgar.com/20260930/AB2ZM22DL222P26L222Q2MY2R6GDZ222ZQ82/ea030723301ex99-1.htm (AIB 8-K Ex.99.1, Sep 30 2026); https://www.globenewswire.com/news-release/2026/09/30/3371855/0/en/aib-data-centers-signs-contract-with-nebius-for-ai-data-center-capacity.html; https://www.sec.gov/Archi

Sheet Alt path
A1: quarter | B1: metric | C1: low | D1: base | E1: high | F1: model_low | G1: model_base | H1: model_high | I1: delta_base | J1: changed | K1: tag | L1: basis | M1: notes
A2: Q3 2026 | B2: active (energized) MW | C2: 192 | D2: 227.5 | E2: 278 | F2: 182 | G2: 207.5 | H2: 233 | I2: 20 | J2: YES | K2: Estimated | L2: mixed IT/stated (as nebius_capacity.xlsx identified-site rows) + adjustments in unseen_capacity.md | M2: Oklahoma colo (new row): +10; Minnesota colo (new row): +10; Newport (Vantage CWL1) + UK 3rd (new row): +0
A3: Q3 2026 | B3: connected MW | C3: 295 | D3: 353 | E3: 412 | G3: 207.5 | I3: 145.5 | J3: YES (new bottom-up line; model has only mgmt figure + plug) | K3: Estimated | L3: gross/shell where built & powered but not active; mgmt guide YE26 800-1,000 MW connected (Reported, Q2 2026 call) | M3: no mgmt figure
A4: Q4 2026 | B4: active (energized) MW | C4: 147.2 | D4: 319.5 | E4: 504 | F4: 185 | G4: 304.5 | H4: 424 | I4: 15 | J4: YES | K4: Estimated | L4: mixed IT/stated (as nebius_capacity.xlsx identified-site rows) + adjustments in unseen_capacity.md | M4: Vineland (shutdown low case): +0; Oklahoma colo (new row): +25; Minnesota colo (new row): +10; Newport (Vantage CWL1) + UK 3rd (new row): +5; Masmiyya (timing slip): -5.5; Beit Shemesh (timing slip): -19.5
A5: Q4 2026 | B5: connected MW | C5: 561 | D5: 941 | E5: 1195 | G5: 800 | I5: 141 | J5: YES (new bottom-up line; model has only mgmt figure + plug) | K5: Estimated | L5: gross/shell where built & powered but not active; mgmt guide YE26 800-1,000 MW connected (Reported, Q2 2026 call) | M5: mgmt guide: 800-1000
A6: Q1 2027 | B6: active (energized) MW | C6: 274.4 | D6: 485.2 | E6: 764 | F6: 270.4 | G6: 444.7 | H6: 619 | I6: 40.5 | J6: YES | K6: Estimated | L6: mixed IT/stated (as nebius_capacity.xlsx identified-site rows) + adjustments in unseen_capacity.md | M6: Oklahoma colo (new row): +50; Minnesota colo (new row): +10; Newport (Vantage CWL1) + UK 3rd (new row): +15; Masmiyya (timing slip): -5.5; Beit Shemesh (timing slip): -29
A7: Q1 2027 | B7: connected MW | C7: 626.4 | D7: 1078 | E7: 1322 | G7: 444.7 | I7: 633.3 | J7: YES (new bottom-up line; model has only mgmt figure + plug) | K7: Estimated | L7: gross/shell where built & powered but not active; mgmt guide YE26 800-1,000 MW connected (Reported, Q2 2026 call) | M7: no mgmt figure
A8: Q2 2027 | B8: active (energized) MW | C8: 429.4 | D8: 682.2 | E8: 967 | F8: 394.4 | G8: 591.7 | H8: 789 | I8: 90.5 | J8: YES | K8: Estimated | L8: mixed IT/stated (as nebius_capacity.xlsx identified-site rows) + adjustments in unseen_capacity.md | M8: Oklahoma colo (new row): +75; Minnesota colo (new row): +10; Newport (Vantage CWL1) + UK 3rd (new row): +25; Masmiyya (timing slip): +0; Beit Shemesh (timing slip): -19.5
A9: Q2 2027 | B9: connected MW | C9: 763.4 | D9: 1243 | E9: 1577 | G9: 591.7 | I9: 651.3 | J9: YES (new bottom-up line; model has only mgmt figure + plug) | K9: Estimated | L9: gross/shell where built & powered but not active; mgmt guide YE26 800-1,000 MW connected (Reported, Q2 2026 call) | M9: no mgmt figure
A10: Q3 2027 | B10: active (energized) MW | C10: 590 | D10: 899.5 | E10: 1202 | F10: 509 | G10: 751.5 | H10: 994 | I10: 148 | J10: YES | K10: Estimated | L10: mixed IT/stated (as nebius_capacity.xlsx identified-site rows) + adjustments in unseen_capacity.md | M10: Oklahoma colo (new row): +100; Minnesota colo (new row): +10; Newport (Vantage CWL1) + UK 3rd (new row): +35; Beit Shemesh (timing slip): -9.5; AIB CLT1 (hall timing): +12.5
A11: Q3 2027 | B11: connected MW | C11: 990 | D11: 1382 | E11: 2017 | G11: 751.5 | I11: 630.5 | J11: YES (new bottom-up line; model has only mgmt figure + plug) | K11: Estimated | L11: gross/shell where built & powered but not active; mgmt guide YE26 800-1,000 MW connected (Reported, Q2 2026 call) | M11: no mgmt figure
A12: Q4 2027 | B12: active (energized) MW | C12: 899 | D12: 1222 | E12: 1582 | F12: 764 | G12: 1069 | H12: 1374 | I12: 153 | J12: YES | K12: Estimated | L12: mixed IT/stated (as nebius_capacity.xlsx identified-site rows) + adjustments in unseen_capacity.md | M12: Oklahoma colo (new row): +100; Minnesota colo (new row): +10; Newport (Vantage CWL1) + UK 3rd (new row): +43
A13: Q4 2027 | B13: connected MW | C13: 1249 | D13: 1882 | E13: 2517 | G13: 1800 | I13: 82 | J13: YES (new bottom-up line; model has only mgmt figure + plug) | K13: Estimated | L13: gross/shell where built & powered but not active; mgmt guide YE26 800-1,000 MW connected (Reported, Q2 2026 call) | M13: mgmt guide: 1800-2000
A16: Q4 2027 ACTIVE base: split of difference vs v1 file (nebius_capacity_v1.xlsx)
A17: Component | B17: Alt path (CSV) vs v1, MW | C17: v2 model vs v1, MW | D17: Tag | E17: Detail
A18: New sites (OK, MN, Newport, UK 3rd) | B18: 153 | C18: =(N('Quarterly MW'!T111)-0)+(N('Quarterly MW'!T106)-0)+(N('Quarterly MW'!T71)-0)+(N('Quarterly MW'!T76)-0) -> 148.5 | D18: Derived | E18: OK +100, MN +10, Newport+UK3 +43 in CSV
A19: Pulled-forward / slipped sites (CLT1, Israel, KC) | B19: 0 | C19: =(N('Quarterly MW'!T121)-25)+(N('Quarterly MW'!T86)-22)+(N('Quarterly MW'!T91)-58)+(N('Quarterly MW'!T46)-30) -> 0 | D19: Derived | E19: CSV: CLT1 +12.5 and Israel -29 occur in Q3 2027 / earlier, net 0 at Q4 2027
A20: Basis / cap change (Vineland 240 IT cap) | B20: 0 | C20: =(N('Quarterly MW'!T6)-240) -> -5 | D20: Derived | E20: CSV kept 240 base; v2 caps high at 240 -> base 235
A21: Total | B21: =SUM(B18:B20) -> 153 | C21: =SUM(C18:C20) -> 143.5
A22: Check: v1 total Q4 2027 base | B22: 1069 | C22: ='Quarterly MW'!T126 -> 1212.5
A23: Memo: IT-normalization effect on v2 Q4 2027 base (IT-normalized minus stated) | C23: ='Quarterly MW'!T136-'Quarterly MW'!T126 -> -130.5754
