Workbook

Sheet Deferred_Rollforward
A1: Nebius (NBIS) — Deferred revenue (contract liabilities) roll-forward
A2: USD millions. Blue = inputs [R/hardcoded]. Black = live formulas [D]. Tags: [R] Reported, [D] Derived, [E] Estimated. ND = not disclosed.
A3: Sources: YE25 20-F Note (Deferred Revenue / RPO); Q1'26 / Q2'26 interim FS Note 1 (~p.F-15 / F-18); quarterly 6-K PR balance sheets & cash flows (tm2427209, tm257185, tm2515580, tm2522866, tm2530882, tm266173).
A5: Quarter | B5: Period end | C5: Open (total) | D5: Tag Open | E5: Adds (gross proxy) | F5: Tag Adds | G5: Recognized from opening | H5: Tag Recog | I5: Other / restatement / FX | J5: Tag Other | K5: Close (total) | L5: Tag Close | M5: Check: Open+Adds-Recog+Other | N5: Tie (Close - Check)
A6: Q4'24 | B6: 2024-12-31 | C6: 17.4 | D6: [R] | E6: =K6-C6+G6-I6 | F6: [D] net | G6: 0 | H6: ND→0 | I6: -0.2 | J6: [D] | K6: 16.3 | L6: [R] | M6: =C6+E6-G6+I6 | N6: =K6-M6
A7: Q1'25 | B7: 2025-03-31 | C7: 16.3 | D7: [R] | E7: =K7-C7+G7-I7 | F7: [D] net | G7: 0 | H7: ND→0 | I7: 0 | J7: [E] | K7: 19 | L7: [R] | M7: =C7+E7-G7+I7 | N7: =K7-M7
A8: Q2'25 | B8: 2025-06-30 | C8: 19 | D8: [R] | E8: =K8-C8+G8-I8 | F8: [D] | G8: 3.2 | H8: [R] | I8: 0 | J8: [E] | K8: 19.3 | L8: [R] | M8: =C8+E8-G8+I8 | N8: =K8-M8
A9: Q3'25 | B9: 2025-09-30 | C9: 19.3 | D9: [R] | E9: =K9-C9+G9-I9 | F9: [D] net | G9: 0 | H9: ND→0 | I9: 0 | J9: [E] | K9: 15.6 | L9: [R] | M9: =C9+E9-G9+I9 | N9: =K9-M9
A10: Q4'25 | B10: 2025-12-31 | C10: 15.6 | D10: [R] | E10: =K10-C10+G10-I10 | F10: [D] net | G10: 0 | H10: ND→0 | I10: 0 | J10: [E] | K10: 1577.5 | L10: [R] | M10: =C10+E10-G10+I10 | N10: =K10-M10
A11: Q1'26 | B11: 2026-03-31 | C11: 1577.5 | D11: [R] | E11: =K11-C11+G11-I11 | F11: [D] | G11: 23.5 | H11: [D] | I11: 0 | J11: [E] | K11: 4778.1 | L11: [R] | M11: =C11+E11-G11+I11 | N11: =K11-M11
A12: Q2'26 | B12: 2026-06-30 | C12: 4778.1 | D12: [R] | E12: =K12-C12+G12-I12 | F12: [D] | G12: 130.8 | H12: [R] | I12: 0 | J12: [E] | K12: 5975.2 | L12: [R] | M12: =C12+E12-G12+I12 | N12: =K12-M12
A15: Current vs non-current split (balance sheet)
A16: Quarter | B16: Period end | C16: Current | D16: Tag | E16: Non-current | F16: Tag | G16: Total (formula) | H16: Current % of total
A17: Q4'24 | B17: 2024-12-31 | C17: 16.3 | D17: [R] | E17: 0 | F17: [R] | G17: =C17+E17 | H17: =IF(G17=0,0,C17/G17)
A18: Q1'25 | B18: 2025-03-31 | C18: 19 | D18: [R] | E18: 0 | F18: [R] | G18: =C18+E18 | H18: =IF(G18=0,0,C18/G18)
A19: Q2'25 | B19: 2025-06-30 | C19: 19.3 | D19: [R] | E19: 0 | F19: [R] | G19: =C19+E19 | H19: =IF(G19=0,0,C19/G19)
A20: Q3'25 | B20: 2025-09-30 | C20: 15.6 | D20: [R] | E20: 0 | F20: [R] | G20: =C20+E20 | H20: =IF(G20=0,0,C20/G20)
A21: Q4'25 | B21: 2025-12-31 | C21: 275.5 | D21: [R] | E21: 1302 | F21: [R] | G21: =C21+E21 | H21: =IF(G21=0,0,C21/G21)
A22: Q1'26 | B22: 2026-03-31 | C22: 685.6 | D22: [R] | E22: 4092.5 | F22: [R] | G22: =C22+E22 | H22: =IF(G22=0,0,C22/G22)
A23: Q2'26 | B23: 2026-06-30 | C23: 979.4 | D23: [R] | E23: 4995.8 | F23: [R] | G23: =C23+E23 | H23: =IF(G23=0,0,C23/G23)
A25: CF cross-check (Increase/(decrease) in deferred revenue from statements of cash flows)
A26: Quarter | B26: CF deferred change | C26: Tag | D26: BS net change (Close-Open) | E26: Tag | F26: Delta CF vs BS
A27: Q4'24 | B27: -0.4 | C27: [R] | D27: =Deferred_Rollforward!K6-Deferred_Rollforward!C6 | E27: [D] | F27: =B27-D27
A28: Q1'25 | B28: ND | C28: ND | D28: =Deferred_Rollforward!K7-Deferred_Rollforward!C7 | E28: [D] | F28: n/a
A29: Q2'25 | B29: ND | C29: ND | D29: =Deferred_Rollforward!K8-Deferred_Rollforward!C8 | E29: [D] | F29: n/a
A30: Q3'25 | B30: -3.8 | C30: [R] | D30: =Deferred_Rollforward!K9-Deferred_Rollforward!C9 | E30: [D] | F30: =B30-D30
A31: Q4'25 | B31: 1566.5 | C31: [R] | D31: =Deferred_Rollforward!K10-Deferred_Rollforward!C10 | E31: [D] | F31: =B31-D31
A32: Q1'26 | B32: 3198 | C32: [R] | D32: =Deferred_Rollforward!K11-Deferred_Rollforward!C11 | E32: [D] | F32: =B32-D32
A33: Q2'26 | B33: 1197 | C33: [R] | D33: =Deferred_Rollforward!K12-Deferred_Rollforward!C12 | E33: [D] | F33: =B33-D33
A35: Interpretation notes (credit timing)
A36: 1. Release rate (see Release_Rate tab) collapses from TripleTen-like ~17% in Q2'25 (tiny base) to ~1.5–2.7% in Q1–Q2'26 once multi-billion strategic prepays sit on the BS.
A37: 2. KEY EVIDENCE = current/non-current split: at 6/30/26 only $979.4M / $5,975.2M = 16.4% classified current [D from R]. That is management's ASC 210 estimate of what releases within 12 months — not a modeling guess.
A38: 3. Tiny $130.8M Q2'26 draw on $4,778.1M opening is therefore NOT primarily "prepays arrived on the last day of the quarter." Late-quarter arrivals inflate ending balance / adds, but the stock of deferred is structurally long-dated (1–5 years per note [R]; ~84% non-current).
A39: 4. Inference [E, medium confidence]: recognition is delivery/capacity-go-live linked over multi-year reserved-capacity terms. Consistent with MSFT monthly invoicing of non-upfront through Oct-2031 and note language "before performance obligations are fulfilled."
A40: 5. Back-loaded credit-vs-billing schedule (IREN–MSFT peer: 20% prepay credited after month 24) is NOT disclosed for Nebius — see prepay_credit_schedule_search.md. Do not equate RPO timing buckets with invoice-credit timing.
A41: 6. Amounts may be refundable [R] — deferred is not pure non-refundable customer deposits.
A42: 7. Same-period additions recognized in-period are not disclosed; Adds formula = Close−Open+RecogFromOpen−Other therefore equals gross adds minus same-period-add recognition (a lower bound on gross prepays when Recog known).

Sheet Release_Rate
A1: Release rate = Recognized from opening deferred ÷ Opening balance
A2: Only quarters with disclosed (or cleanly derived) recognized-from-opening are computed. ND quarters left blank.
A4: Quarter | B4: Opening | C4: Recognized from opening | D4: Tag Recog | E4: Release rate | F4: Tag Rate | G4: Commentary
A5: Q2'25 | B5: =Deferred_Rollforward!C8 | C5: =Deferred_Rollforward!G8 | D5: [R] | E5: =IF(B5=0,"n/a",C5/B5) | F5: [D] | G5: High turnover on ~$19 TripleTen-scale base; not comparable to strategic-prepay era.
A6: Q1'26 | B6: =Deferred_Rollforward!C11 | C6: =Deferred_Rollforward!G11 | D6: [D] | E6: =IF(B6=0,"n/a",C6/B6) | F6: [D] | G6: Recog $23.5 derived as 1H $154.3 − Q2 $130.8. Rate ~1.5% on $1.58B open after YE25 prepay wave.
A7: Q2'26 | B7: =Deferred_Rollforward!C12 | C7: =Deferred_Rollforward!G12 | D7: [R] | E7: =IF(B7=0,"n/a",C7/B7) | F7: [D] | G7: Recog $130.8 [R] / open $4,778.1 → ~2.7%. Still tiny vs multi-billion stock; capacity not yet delivering most prepaid services.
A9: Annual reference (YE25 20-F)
A10: FY2025 recognized from YE24 opening | B10: 16.3 | C10: [R]
A11: YE24 opening | B11: 16.3
A12: FY25 annual release rate | B12: =B10/B11 | C12: [D]
A14: Current-portion implied 12-month release (stock view, not quarterly flow)
A15: At 6/30/26: Current / Total | B15: =Deferred_Rollforward!C23/Deferred_Rollforward!G23 | C15: [D]
A16: This 16.4% is the company's own ≤12-month recognition estimate for the deferred stock — far above the ~2.7% single-quarter flow rate, and far below a 1/5 flat annual 20% if evenly amortized over 5 years. Pattern = back-weighted within the 1–5 year window and/or capacity still ramping into service.

Sheet RPO_Timing
A1: Remaining performance obligations (RPO) — timing split
A2: No ≤12-month / 1–2y / 2–5y / >5y split is disclosed. Only 0–24 months, months 25–48, and thereafter. Practical expedient: excludes performance obligations with original duration ≤1 year.
A4: As-of date | B4: RPO total $M | C4: Tag | D4: 0–24 months % | E4: 0–24 months $M | F4: 25–48 months % | G4: 25–48 months $M | H4: Thereafter % | I4: Thereafter $M | J4: Window end (0–24) | K4: Exclusions / notes
A5: 2025-12-31 | B5: 21333 | C5: [R] | D5: 0.28 | E5: =B5*D5 | F5: 0.39 | G5: =B5*F5 | H5: =1-D5-F5 | I5: =B5*H5 | J5: 2027-12-31 | K5: Excludes orig. duration ≤1y; includes estimate of variable consideration. [R]
A6: 2026-03-31 | B6: 33585.3 | C6: [R] | D6: 0.29 | E6: =B6*D6 | F6: 0.39 | G6: =B6*F6 | H6: =1-D6-F6 | I6: =B6*H6 | J6: 2028-03-31 | K6: Same expedient. AI cloud not explicitly restated in Q1 note excerpt.
A7: 2026-06-30 | B7: 37490.6 | C7: [R] | D7: 0.36 | E7: =B7*D7 | F7: 0.4 | G7: =B7*F7 | H7: =1-D7-F7 | I7: =B7*H7 | J7: 2028-06-30 | K7: Fully attributed to Nebius AI cloud [R].
A9: Composition bridge at 6/30/26
A10: RPO total | B10: =B7
A11: Less: deferred revenue (billed/prepaid) | B11: 5975.2 | C11: [R]
A12: Unbilled contracted RPO | B12: =B10-B11 | C12: [D]
A14: Call / letter language (not a GAAP RPO figure)
A15: Q2'26 call/letter: "~$40B" / "more than $40 billion" contracted backlog / customer commitments [R call]. Round-number vs $37.5B GAAP RPO; treat as management characterization, not a separate audited backlog.
A17: NO disclosure of: ≤12-month RPO; 1–2 / 2–5 / >5 year buckets; invoice-level prepayment credit schedule.

Sheet FY27_Coverage
A1: FY27 revenue coverage — contracted vs Street / guide
A2: No ≤12-month RPO split exists. Coverage uses disclosed proxies only; crude allocations tagged [E].
A4: Benchmarks
A5: Street FY27 revenue (team consensus) | B5: 12300 | C5: [E]
A6: FY26 group revenue guide (low) | B6: 3000 | C6: [R]
A7: FY26 group revenue guide (high) | B7: 3400 | C7: [R]
A8: 1H26 group revenue actual | B8: 981.3 | C8: [R]
A9: Implied 2H26 from mid guide | B9: =(B6+B7)/2-B8 | C9: [D]
A10: Implied 2H26 from low / high guide | B10: =B6-B8 | C10: =B7-B8
A12: Proxy A — Current deferred (≤12 months of prepaid revenue only)
A13: Current deferred 6/30/26 | B13: 979.4 | C13: [R]
A14: Coverage of Street FY27 | B14: =B13/B5 | C14: [D]
A15: Note: current deferred covers ONLY the prepaid slice expected in 12 months — excludes unbilled contracted revenue that will be invoiced as delivered. Severe understatement of contracted FY27.
A17: Proxy B — RPO 0–24 month bucket (through 6/30/28)
A18: RPO 0–24m $M | B18: =RPO_Timing!E7 | C18: [D]
A19: Less: implied 2H26 (mid) | B19: =B9
A20: Residual for FY27 + 1H28 | B20: =B18-B19 | C20: [D]
A21: Crude even-split FY27 share of residual (2/3 of FY27+1H28) | B21: =B20*2/3 | C21: [E]
A22: Alt: even monthly over full 24m → FY27 = 12/24 of bucket | B22: =B18*12/24 | C22: [E]
A23: Street FY27 minus crude FY27 contracted (even 12/24) | B23: =B5-B22 | C23: [E]
A24: Implied still-unsigned / to-book for Street FY27 (even-split case) | B24: =B23 | C24: [E]
A25: Coverage ratio (even 12/24 contracted / Street) | B25: =B22/B5 | C25: [E]
A27: Proxy C — Named contracts (schedule context, not a FY27 allocation)
A28: Microsoft TCV (up to) | B28: 17392.9 | C28: [R]
A29: Microsoft aggregate upfront | B29: 6958.1 | C29: [R]
A30: Microsoft non-upfront (monthly through Oct-2031) | B30: =B28-B29 | C30: [D]
A31: Meta 2025 agreement TCV | B31: 2880.7 | C31: [R]
A32: Meta 2026 dedicated capacity (deliveries from early 2027) | B32: 12000 | C32: [R]
A33: Meta 2026 backstop (up to, unsold capacity) | B33: 15000 | C33: [R]
A34: 2026 customer prepayments guided | B34: 9000 | C34: [R] >
A36: Bottom line
A37: No company ≤12-month RPO split. Best reported near-term proxies: (1) current deferred $979.4M; (2) 0–24m RPO ~$13.5B through 6/30/28; (3) MSFT monthly remainder + Meta 2026 $12B starting early 2027. Under a flat 12/24 allocation of the 0–24m bucket, ~$6.7B looks contracted into calendar 2027 vs Street $12.3B → roughly ~$5.6B of Street FY27 still needs bookings/delivery mix beyond that crude cut [E]. If recognition is back-loaded inside the 0–24m window (consistent with deferred current-only 16%), FY27 contracted could be higher — still a modeling assumption.

Sheet Sources
A1: Sources registry
A3: ID | B3: Document | C3: Location / page | D3: What used | E3: URL / path
A4: S1 | B4: YE25 20-F | C4: Note Deferred Revenue / RPO (~p.F-18 / F-34); BS deferred lines; Note 1 MSFT/Meta | D4: YE24/YE25 deferred $16.3 / $1,577.5; FY recog; RPO $21,333.0 28%/39%; MSFT $17,392.9 / upfront $6,958.1 | E4: edgar/nbis-20251231x20f.htm.txt
A5: S2 | B5: Q1'26 interim FS (6-K ex99.2) | C5: Note Deferred Revenue / RPO (~p.F-15); BS | D5: Deferred $4,778.1; +$3,200.6; RPO $33,585.3 29%/39%; cur/NC 685.6/4092.5 | E5: edgar/nbis-20260331xex99d2.htm.txt
A6: S3 | B6: Q2'26 interim FS (6-K ex99.2) | C6: Note Deferred Revenue / RPO p.F-18–F-19; BS; CF | D6: Deferred $5,975.2; recog $130.8 / 1H $154.3; +$1,197.1; RPO $37,490.6 36%/40%; cur/NC 979.4/4995.8 | E6: edgar/nbis-20260812xex99d2.htm.txt
A7: S4 | B7: Q3'24 PR 6-K ex99.1 | C7: Balance sheet | D7: Deferred $17.4 at 9/30/24 | E7: edgar/tm2427209d1_ex99-1.htm.txt
A8: S5 | B8: Q4'24 PR 6-K ex99.1 | C8: Balance sheet | D8: Deferred $16.5 (later restated to $16.3) | E8: edgar/tm257185d1_ex99-1.htm.txt
A9: S6 | B9: Q1'25 PR 6-K ex99.1 | C9: Balance sheet | D9: Deferred $19.0 at 3/31/25 | E9: edgar/tm2515580d1_ex99-1.htm.txt
A10: S7 | B10: Q2'25 PR 6-K ex99.1 | C10: Balance sheet | D10: Deferred $19.3 at 6/30/25 | E10: edgar/tm2522866d1_ex99-1.htm.txt
A11: S8 | B11: Q3'25 PR 6-K ex99.1 | C11: BS + CF | D11: Deferred $15.6; CF deferred -$3.8 | E11: edgar/tm2530882d1_ex99-1.htm.txt
A12: S9 | B12: Q4'25 PR 6-K ex99.1 | C12: BS + CF | D12: Cur 275.5 + NC 1,302.0; CF Q4 +1,566.5 / Q4'24 comp -0.4 | E12: edgar/tm266173d1_ex99-1.htm.txt
A13: S10 | B13: Q1'26 PR 6-K ex99.1 | C13: BS + CF | D13: CF deferred +3,198.0 | E13: edgar/tm2614392d1_ex99-1.htm.txt
A14: S11 | B14: Q2'26 PR / letter | C14: ex99.1 CF; ex99.2 letter | D14: CF +1,197.0; >$9B 2026 prepays; ~$40B commitments language | E14: edgar/tm2622968d1_ex99-1.htm.txt; altdata/mined_text/Q2-26_letter.txt
... A17: S14 | B17: 6-K 2026-03-16 Meta | C17: Ex.99.1 | D17: Meta 2026 $12B dedicated + $15B backstop; deliveries early 2027 | E17: acc 0001104659-26-027886

Sheet Checks
A1: Tie-out checks — Open + Adds − Recognized ± Other = Close
A3: Quarter | B3: Open | C3: Adds | D3: Recog | E3: Other | F3: Implied Close | G3: Reported Close | H3: Diff | I3: PASS?
A4: =Deferred_Rollforward!A6 | B4: =Deferred_Rollforward!C6 | C4: =Deferred_Rollforward!E6 | D4: =Deferred_Rollforward!G6 | E4: =Deferred_Rollforward!I6 | F4: =B4+C4-D4+E4 | G4: =Deferred_Rollforward!K6 | H4: =G4-F4 | I4: =IF(ABS(H4)<0.05,"PASS","FAIL")
A5: =Deferred_Rollforward!A7 | B5: =Deferred_Rollforward!C7 | C5: =Deferred_Rollforward!E7 | D5: =Deferred_Rollforward!G7 | E5: =Deferred_Rollforward!I7 | F5: =B5+C5-D5+E5 | G5: =Deferred_Rollforward!K7 | H5: =G5-F5 | I5: =IF(ABS(H5)<0.05,"PASS","FAIL")
A6: =Deferred_Rollforward!A8 | B6: =Deferred_Rollforward!C8 | C6: =Deferred_Rollforward!E8 | D6: =Deferred_Rollforward!G8 | E6: =Deferred_Rollforward!I8 | F6: =B6+C6-D6+E6 | G6: =Deferred_Rollforward!K8 | H6: =G6-F6 | I6: =IF(ABS(H6)<0.05,"PASS","FAIL")
A7: =Deferred_Rollforward!A9 | B7: =Deferred_Rollforward!C9 | C7: =Deferred_Rollforward!E9 | D7: =Deferred_Rollforward!G9 | E7: =Deferred_Rollforward!I9 | F7: =B7+C7-D7+E7 | G7: =Deferred_Rollforward!K9 | H7: =G7-F7 | I7: =IF(ABS(H7)<0.05,"PASS","FAIL")
A8: =Deferred_Rollforward!A10 | B8: =Deferred_Rollforward!C10 | C8: =Deferred_Rollforward!E10 | D8: =Deferred_Rollforward!G10 | E8: =Deferred_Rollforward!I10 | F8: =B8+C8-D8+E8 | G8: =Deferred_Rollforward!K10 | H8: =G8-F8 | I8: =IF(ABS(H8)<0.05,"PASS","FAIL")
A9: =Deferred_Rollforward!A11 | B9: =Deferred_Rollforward!C11 | C9: =Deferred_Rollforward!E11 | D9: =Deferred_Rollforward!G11 | E9: =Deferred_Rollforward!I11 | F9: =B9+C9-D9+E9 | G9: =Deferred_Rollforward!K11 | H9: =G9-F9 | I9: =IF(ABS(H9)<0.05,"PASS","FAIL")
A10: =Deferred_Rollforward!A12 | B10: =Deferred_Rollforward!C12 | C10: =Deferred_Rollforward!E12 | D10: =Deferred_Rollforward!G12 | E10: =Deferred_Rollforward!I12 | F10: =B10+C10-D10+E10 | G10: =Deferred_Rollforward!K12 | H10: =G10-F10 | I10: =IF(ABS(H10)<0.05,"PASS","FAIL")
A12: Current+NC = Total deferred
A13: Quarter | B13: Cur+NC | C13: Rollforward Close | D13: Diff | E13: PASS?
A14: =Deferred_Rollforward!A17 | B14: =Deferred_Rollforward!G17 | C14: =Deferred_Rollforward!K6 | D14: =C14-B14 | E14: =IF(ABS(D14)<0.05,"PASS","FAIL")
A15: =Deferred_Rollforward!A18 | B15: =Deferred_Rollforward!G18 | C15: =Deferred_Rollforward!K7 | D15: =C15-B15 | E15: =IF(ABS(D15)<0.05,"PASS","FAIL")
A16: =Deferred_Rollforward!A19 | B16: =Deferred_Rollforward!G19 | C16: =Deferred_Rollforward!K8 | D16: =C16-B16 | E16: =IF(ABS(D16)<0.05,"PASS","FAIL")
A17: =Deferred_Rollforward!A20 | B17: =Deferred_Rollforward!G20 | C17: =Deferred_Rollforward!K9 | D17: =C17-B17 | E17: =IF(ABS(D17)<0.05,"PASS","FAIL")
A18: =Deferred_Rollforward!A21 | B18: =Deferred_Rollforward!G21 | C18: =Deferred_Rollforward!K10 | D18: =C18-B18 | E18: =IF(ABS(D18)<0.05,"PASS","FAIL")
A19: =Deferred_Rollforward!A22 | B19: =Deferred_Rollforward!G22 | C19: =Deferred_Rollforward!K11 | D19: =C19-B19 | E19: =IF(ABS(D19)<0.05,"PASS","FAIL")
A20: =Deferred_Rollforward!A23 | B20: =Deferred_Rollforward!G23 | C20: =Deferred_Rollforward!K12 | D20: =C20-B20 | E20: =IF(ABS(D20)<0.05,"PASS","FAIL")
A22: Q1'26 recog derivation check: 1H $154.3 − Q2 $130.8 = $23.5
A23: Q1'26 recog [D] | B23: 154.3 | C23: 130.8 | D23: =B23-C23
A24: vs rollforward input | D24: =D23-Deferred_Rollforward!G11 | E24: =IF(ABS(D24)<0.05,"PASS","FAIL")
A26: RPO % buckets sum to 100%
A27: =RPO_Timing!A5 | B27: =RPO_Timing!D5+RPO_Timing!F5+RPO_Timing!H5 | C27: =IF(ABS(B27-1)<0.001,"PASS","FAIL")
A28: =RPO_Timing!A6 | B28: =RPO_Timing!D6+RPO_Timing!F6+RPO_Timing!H6 | C28: =IF(ABS(B28-1)<0.001,"PASS","FAIL")
A29: =RPO_Timing!A7 | B29: =RPO_Timing!D7+RPO_Timing!F7+RPO_Timing!H7 | C29: =IF(ABS(B29-1)<0.001,"PASS","FAIL")
A31: Known limitations
A32: • Recognized-from-opening ND for Q4'24, Q1'25, Q3'25, Q4'25 → Adds on those rows = Close−Open−Other (net change), understating gross prepays.
A33: • Q4'24 open uses unrestated 9/30/24 $17.4 vs restated YE24 close $16.3; -$0.2 Other is a bridge estimate for the $16.5→$16.3 restatement only (residual vs CF -$0.4 unexplained at $0.1–0.7 level — immaterial to strategic-prepay analysis).
A34: • No full interim FS notes for 2025 quarters (only PR BS/CF); nothing further on EDGAR indexes beyond what is local.
A35: • RPO percentages disclosed without $ precision beyond one decimal on %; $ bucket amounts are derived.
A36: • Same-period additions recognized within the quarter never disclosed separately.
