Workbook

Sheet Inputs
A1: Input | B1: Value | C1: Unit | D1: Tag | E1: Source
A2: Class A outstanding 6/30/26 | B2: 238400165 | C2: sh | D2: R | E2: Q2 PR outstanding shares; 6-K 8/12/26 acc 0001104659-26-094568
A3: Class B outstanding 6/30/26 | B3: 33455053 | C3: sh | D3: R | E3: Q2 PR
A4: NVIDIA pre-funded warrant (unexercised) | B4: 21065936 | C4: sh | D4: R | E4: Q2FS Note 14; 6-K 8/12/26 acc 0001104659-26-094844
A5: If-converted shares, Q2 (anti-dilutive, weighted avg) | B5: 65416804 | C5: sh | D5: R | E5: Q2FS Note 1 EPS
A6: Jun-2029 2.00% notes exchanged (orig. principal) | B6: 400 | C6: $M | D6: R | E6: 6-K 8/24/26 Ex.99.1 acc 0001104659-26-100347
A7: Jun-2031 3.00% notes exchanged (orig. principal) | B7: 400 | C7: $M | D7: R | E7: same
A8: Conversion rate Jun-2029/Jun-2031 notes | B8: 19.4363 | C8: sh per $1,000 | D8: R | E8: Jun-2025 offering 6-K; Q2FS Note 12
A9: Notes Exchange Price, 2029 notes | B9: 4403.18 | C9: $ per $1,000 | D9: R | E9: Form of Exchange Agreement, Ex.4.5 to 6-K 8/24/26
A10: Notes Exchange Price, 2031 notes | B10: 4413.18 | C10: $ per $1,000 | D10: R | E10: same
A11: Coupon 2029 notes | B11: 0.02 | C11: p.a. | D11: R | E11: notes terms
A12: Coupon 2031 notes | B12: 0.03 | C12: p.a. | D12: R | E12: notes terms
A13: Accrued-interest days 6/5/26 to settlement (30/360) | B13: 76 | C13: days | D13: E | E13: ASSUMPTION: 30/360, T+2 settlement 8/21/26; 79 days if 8/24 (adds ~744 sh)
... A36: AGM Item 13 authority | B36: 0.2 | C36: of issued A+B | D36: R | E36: 6-K 8/26/26 AGM results

Sheet FD_Bridge
A1: # | B1: Step | C1: Shares | D1: Tag | E1: Source / math
A2: 1 | B2: Class A outstanding 6/30/26 | C2: =Inputs!$B$2 -> 238400165 | D2: R | E2: Q2 PR
A3: 2 | B3: Class B outstanding 6/30/26 | C3: =Inputs!$B$3 -> 33455053 | D3: R | E3: Q2 PR
A4: 3 | B4: NVIDIA pre-funded warrant (unexercised; $0.0001 strike) | C4: =Inputs!$B$4 -> 21065936 | D4: R | E4: Q2FS Note 14
A5: 4 | B5: If-converted, all convert series at 6/30 (Q2 weighted avg) | C5: =Inputs!$B$5 -> 65416804 | D5: R | E5: Q2FS Note 1
A6: FD0 | B6: FD at 6/30/26 (team PT base) = rows 1-4 | C6: =SUM(C2:C5) -> 358337958 | D6: D | E6: Should equal 358,337,958
A7: 5 | B7: Less: conversion shares of $400M Jun-2029 notes exchanged | C7: =-Inputs!$B$6*1000*Inputs!$B$8 -> -7774520 | D7: D | E7: 400,000 bonds x 19.4363
A8: 6 | B8: Less: conversion shares of $400M Jun-2031 notes exchanged | C8: =-Inputs!$B$7*1000*Inputs!$B$8 -> -7774520 | D8: D | E8: 400,000 bonds x 19.4363
A9: 7 | B9: Plus: Aug exchange shares, 2029 notes | C9: =ROUNDDOWN(Inputs!$B$6*1000*(Inputs!$B$9+1000*Inputs!$B$11*Inputs!$B$13/360)/Inputs!$B$14,0) -> 7873876 | D9: D (day count E) | E9: Ex.4.5: (Exchange Price x amount + accrued int.) / Share Price, rounded down
A10: 8 | B10: Plus: Aug exchange shares, 2031 notes | C10: =ROUNDDOWN(Inputs!$B$7*1000*(Inputs!$B$10+1000*Inputs!$B$12*Inputs!$B$13/360)/Inputs!$B$14,0) -> 7895512 | D10: D (day count E) | E10: same
A11: 9 | B11: Plus: if-converted, new $3,450M 0.50% Feb-2030 notes | C11: =Inputs!$B$16*1000*Inputs!$B$17 -> 11006190 | D11: D (rate R) | E11: 3,450,000 bonds x 3.1902
A12: 10 | B12: Plus: if-converted, new $2,300M 4.50% Feb-2034 notes | C12: =Inputs!$B$18*1000*Inputs!$B$19 -> 7084460 | D12: D (rate R) | E12: 2,300,000 bonds x 3.0802
A13: 11 | B13: Post-10/5/26 changes disclosed | C13: =Inputs!$B$20 -> 0 | D13: D | E13: None found on EDGAR / newsroom through 10/8 AM
A14: FD1 | B14: FD PRO FORMA after Aug-26 transactions = FD0 + rows 5-11 | C14: =C6+SUM(C7:C13) -> 376648956 | D14: D | E14: Target ~376,648,956
B16: Change vs 6/30 FD (shares) | C16: =C14-C6 -> 18310998 | D16: D
B17: Change vs 6/30 FD (%) | C17: =C14/C6-1 -> 0.0510998 | D17: D
B18: Check: FD0 - 358,337,958 (should be 0) | C18: =C6-358337958 -> 0 | D18: D
B19: Check: FD1 - 376,648,956 (should be 0) | C19: =C14-376648956 -> 0 | D19: D
B20: Derived exchange shares total (rows 7+8) | C20: =C9+C10 -> 15769388 | D20: D | E20: vs company "approximately 15.8M"
B21: Inducement vs straight conversion (rows 5..8) | C21: =C7+C8+C9+C10 -> 220348 | D21: D | E21: extra shares over conversion value
A23: Memo | B23: Alt: FD using company "~15.8M" instead of derived count | C23: =C14-(C9+C10)+Inputs!$B$15 -> 376679568 | D23: R/D | E23: Use if a reader wants only Reported exchange count
A24: Memo | B24: Sensitivity: 79 accrual days (8/24 settlement) adds | C24: =ROUNDDOWN(Inputs!$B$6*1000*(Inputs!$B$9+1000*Inputs!$B$11*79/360)/Inputs!$B$14,0)+ROUNDDOWN(Inputs!$B$7*1000*(Inputs!$B$10+1000*Inputs!$B$12*79/360)/Inputs!$B$14,0)-(C9+C10) -> 744 | D24: E | E24: immaterial
A25: Memo | B25: Class A outstanding pro forma (Q3 baseline, before ATM/RSU deliveries) | C25: =Inputs!$B$2+C9+C10 -> 254169553 | D25: D | E25: Anything above at 9/30 => ATM/other issuance
A26: Memo | B26: Point-in-time cross-check: old if-converted from principal x rates (pre-exchange) | C26: =975000*19.4363+3162500*7.2072+2587500*5.4579+1750000*5.546 -> 65570979 | D26: D | E26: vs Q2 WA 65,416,804 (~0.2% diff)
A27: Memo | B27: RSUs outstanding 6/30 (EXCLUDED from FD) | C27: =Inputs!$B$21 -> 6234091 | D27: R | E27: Footnote: team FD excludes RSUs/options
A28: Memo | B28: Options outstanding 6/30 (EXCLUDED; WAEP $88.65) | C28: =Inputs!$B$22 -> 6740600 | D28: R | E28: Treasury-stock method not applied
A29: Memo | B29: FD incl. all RSUs + options (gross upper bound, no TSM) | C29: =C14+Inputs!$B$21+Inputs!$B$22 -> 389623647 | D29: D | E29: upper bound only
A30: Memo | B30: Alt PT convention: new 2030/2034 notes OTM at ref. price -> treat as debt, drop their shares | C30: =C14-C11-C12 -> 358558306 | D30: D | E30: pair with keeping new notes in debt (see PT_Consistency)

Sheet PT_Consistency
A1: Item | B1: $M | C1: Tag | D1: Treatment / math
A2: Convertible notes carrying 6/30 (all old series) | B2: =Inputs!$B$28 -> 8499 | C2: R | D2: Remove from net debt if all old series are if-converted (they are in the 65.4M)
A3: of which exchanged $800M (pro-rata carrying of Jun-29/Jun-31) | B3: =(Inputs!$B$6/Inputs!$B$31)*Inputs!$B$29+(Inputs!$B$7/Inputs!$B$31)*Inputs!$B$30 -> 822.5641 | C3: D | D3: Retired 8/24 for shares; no cash. Already gone post-Aug; do NOT also remove again
A4: Old converts remaining carrying post-exchange | B4: =B2-B3 -> 7676.4359 | C4: D | D4: Remove from debt (if-converted)
A5: New notes original principal (face) - remove from debt when if-converted | B5: =Inputs!$B$24 -> 5750 | C5: R | D5: $3,450M + $2,300M; Q3 carrying ND
A6: New notes accreted principal at maturity (memo) | B6: =Inputs!$B$16*Inputs!$B$26+Inputs!$B$18*Inputs!$B$27 -> 6670 | C6: D | D6: 3,450x1.10 + 2,300x1.25; the debt claim if NOT converted
A7: Cash to KEEP: new notes net proceeds | B7: =Inputs!$B$25 -> 5680 | C7: R (co. estimate) | D7: Add to 6/30 cash 8,042.1 for pro forma (ignores Q3 burn)
A8: Exchange cash flow | B8: =0 -> 0 | C8: R | D8: Exchange was notes-for-shares; accrued interest settled in shares
A9: Capped calls / hedges | B9: =0 -> 0 | C9: R | D9: None on any series (fact base / offering docs)
A10: Debt NOT removed: $775M secured facility (drawn ND) | B10: =Inputs!$B$34 -> 775 | C10: R | D10: Keep as debt; full draw is an assumption [E]
A11: Debt NOT removed: current debt 6/30 | B11: =Inputs!$B$32 -> 46.7 | C11: R | D11: Keep
A12: Pro forma cash (6/30 cash + new-note net proceeds) | B12: =Inputs!$B$33+B7 -> 13722.1 | C12: D | D12: Excl. restricted 1,056.0; excl. Q3 OCF/capex
A14: Moneyness at reference price $237.15 (10/7 close) [R third-party] | B14: Conv. price $ | C14: ITM?
A15: Jun-2029 / Jun-2031 (remaining $87.5M each) | B15: 51.45 | C15: =IF(Inputs!$B$35>B15,"ITM","OTM") -> ITM | D15: Conv. prices R
A16: Sep-2030 / Sep-2032 | B16: 138.75 | C16: =IF(Inputs!$B$35>B16,"ITM","OTM") -> ITM | D16: Conv. prices R
A17: Mar-2031 | B17: 183.22 | C17: =IF(Inputs!$B$35>B17,"ITM","OTM") -> ITM | D17: Conv. prices R
A18: Mar-2033 | B18: 180.31 | C18: =IF(Inputs!$B$35>B18,"ITM","OTM") -> ITM | D18: Conv. prices R
A19: NEW Feb-2030 | B19: 313.46 | C19: =IF(Inputs!$B$35>B19,"ITM","OTM") -> OTM | D19: Conv. prices R
A20: NEW Feb-2034 | B20: 324.65 | C20: =IF(Inputs!$B$35>B20,"ITM","OTM") -> OTM | D20: Conv. prices R
A22: Rule | D22: Shares and debt must match: if a series is if-converted, drop its debt; if treated as debt (e.g. OTM new notes), drop its shares. Team default = all if-converted (FD 376.6M) => remove ALL convert debt and keep new-note cash.

Sheet Headroom
A1: Item | B1: (i) Exchange shares from TREASURY | C1: (ii) Exchange shares NEWLY ISSUED | D1: Tag / math
A2: Class A issued (post-exchange) | B2: =Inputs!$B$23 -> 288585891 | C2: =Inputs!$B$23+FD_Bridge!C9+FD_Bridge!C10 -> 304355279 | D2: R / D
A3: Treasury (6/30 = issued - outstanding; less exchange shares if from treasury) | B3: =Inputs!$B$23-Inputs!$B$2-(FD_Bridge!C9+FD_Bridge!C10) -> 34416338 | C3: =Inputs!$B$23-Inputs!$B$2 -> 50185726 | D3: D
A4: AGM 20% pool = 20% x (Class A issued + Class B) | B4: =Inputs!$B$36*(B2+Inputs!$B$3) -> 64408189 | C4: =Inputs!$B$36*(C2+Inputs!$B$3) -> 67562066 | D4: D
A5: Gross no-vote headroom | B5: =B3+B4 -> 98824527 | C5: =C3+C4 -> 1.1774779e+08 | D5: D
A6: Less: unexercised NVIDIA warrant | B6: =-Inputs!$B$4 -> -21065936 | C6: =-Inputs!$B$4 -> -21065936 | D6: R
A7: NET no-vote headroom | B7: =B5+B6 -> 77758591 | C7: =C5+C6 -> 96681856 | D7: D
A8: Memo: team 6/30 snapshot net headroom | B8: 93527979 | C8: 93527979 | D8: D (prior note)
A10: Reasoning | B10: Exchange settled 8/24, one day BEFORE AGM authority (8/25). Source of shares (treasury vs new issue) ND. Q2 ATM shares came from treasury [R] -> treasury case (i) is the conservative ~78M. Case (ii) ~97M if newly issued under prior authority (raises issued capital and the 20% pool). Further reduced share-for-share by any Q3 ATM sales (ND) and RSU/option deliveries from treasury (ND, small).
