Workbook

Sheet README
A1: Nebius Group (NBIS) consolidated KPI history | B1: Built 2026-10-05 08:31 ET by Filings & Capital. Script: /workspace/nebius/filings/kpi/kpi_build.py. Public information only.
A2: Tabs | B2: KPI (main grid, 10 quarters), Prices_Monthly (market inputs feeding quarter averages), Checks (tie-outs), Sources (one row per populated cell: tag, source with URL, note).
A3: Tags | B3: Reported = number as printed in an SEC filing / company page / snapshot. Derived = live formula on Reported inputs (or arithmetic on reported totals, math shown). Estimated = a team model value or a formula using one (method in Sources). n.d. = not disclosed / input missing; never filled.
A4: Colours | B4: Blue = Reported input; black = formula on Reported/Derived inputs; orange italic = Estimated (input, or a formula that uses an Estimated input); grey = n.d.
A5: ARR | B5: Annualized run-rate revenue = Nebius AI cloud revenue from the last month of the quarter x 12 (Q2-26 shareholder letter, footnote 4; same wording Q1-26). Q3-25/Q4-25 letters: "revenue from the last month of the quarter multiplied by 12"; Q1-25 letter: "revenue for last month of the period multiplied by twelve". 2024 values read from the Oct-2024 investor presentation chart; Dec-24 $90M from Q4-24 PR.
A6: MW basis | B6: Energized MW is the Capacity & Power team ESTIMATE of power physically live (closest to Nebius "active power"); not "connected" (built and equipped) or "contracted" (land + power secured). Nebius never states IT vs gross. Vineland, Modi'in and AIB rows are IT MW; others as stated (mostly gross/unknown), so totals mix bases (1.1-1.45x PUE ambiguity). Management figures: YE24 25 MW CONNECTED; YE25 ~170 MW ACTIVE.
A7: Quarter-end vs average | B7: Stock measures (MW, GPUs, PP&E) are quarter-end. Per-unit revenue KPIs are shown on average (opening+closing)/2 and, where noted, quarter-end. With fast build-outs the two can differ a lot (e.g., Q4-25 GPUs 31.8k -> 69.0k).
A8: GPUs | B8: Modeled = energized base MW x GPUs per MW by generation (capacity/gpu_mw_capex.xlsx); company counts are sparse: only actual is ~30,000 deployed at 31-Mar-25 (FY24 20-F; the earlier ~38k from the Feb-25 call was a forward-looking target, superseded); Q3-24 ~10k and Q4-24 >20k are Estimated/targets and ran ahead of powered MW. Generation per site mostly assumed by the Capacity team.
A9: Implied utilization | B9: AI cloud revenue / (average modeled GPUs x hours in quarter x fleet-weighted blended LIST price). It mixes utilization with the realized-vs-list discount (commit deals up to 35% below list; large contracts lower), and revenue includes non-GPU-hour items. Hopper priced at H100 list; GB300 (no public price) proxied by B300 list (Q2-26) or B200 list (earlier, floor). Treat as an index, not a measured utilization.
A10: Capex per MW | B10: Cash capex / change in energized MW. Capex largely funds capacity not yet energized (assets not yet in use rose $2.4B -> $7.8B in 1H26), so quarterly ratios are "n.m." when MW added <= 5 MW; use trailing-4Q and the placed-in-service basis (change in gross in-service PP&E / MW added).
A11: June step-up | B11: ARR/12 (implied last-month revenue) vs AI cloud quarter monthly average. Q2-26: $250M vs $191.6M (+30%); Q1-26: $160M vs $129.9M.
A12: Restatements | B12: Revenue/OCF on latest restated basis (Toloka deconsolidated Q2-25, in discontinued ops). Small company rounding differences noted in Sources (e.g., Q2-25 OCF 167.7 vs 167.9; Q3-24 34.9 vs 34.8).
A13: Inputs | B13: Filings: /workspace/nebius/filings/nebius_filings.xlsx (Quarterly tab via quarterly_rows.json) + edgar/*.txt. Capacity: /workspace/nebius/capacity/nebius_capacity.xlsx (Quarterly MW rows 119-125, GPUs deployed rows 11-31). Market: /workspace/nebius/market/gpu_price_history.xlsx (Price_History_Quarterly, Price_History_Monthly, Monthly_FFill, H100_Nebius_vs_Medians).

Sheet KPI
A1: Nebius Group (NBIS) - consolidated tagged KPI history, Q1 2024 - Q2 2026. $M unless noted. Blue = Reported input; black = formula on Reported/Derived inputs; orange italic = Estimated (input, or formula using an Estimated input); grey = n.d. Per-cell sources in Sources tab.
A3: Metric | B3: Unit | C3: Q1 2024 | D3: Q2 2024 | E3: Q3 2024 | F3: Q4 2024 | G3: Q1 2025 | H3: Q2 2025 | I3: Q3 2025 | J3: Q4 2025 | K3: Q1 2026 | L3: Q2 2026 | M3: Basis / caveat | N3: Owner / origin
A4: A. Financials (Filings & Capital: nebius_filings.xlsx Quarterly tab; SEC filings)
A5: Group revenue (continuing ops, restated) | B5: $M | C5: 9.7 | D5: 14.5 | E5: 32.1 | F5: 35.2 | G5: 50.9 | H5: 105.1 | I5: 146.1 | J5: 227.7 | K5: 399 | L5: 582.3 | N5: Filings & Capital
A6: Nebius AI cloud segment revenue | B6: $M | C6: n.d. | D6: n.d. | E6: 27.1 | F6: 23.8 | G6: 41.4 | H6: 93.7 | I6: 131.1 | J6: 214.1 | K6: 389.7 | L6: 574.9 | M6: Segment revenue; Q1/Q2 2024 split not disclosed (H1-24 total 17.4). | N6: Filings & Capital
A7: ARR (as stated; last-month revenue x12) | B7: $M | C7: 32 | D7: 45 | E7: 121 | F7: 90 | G7: 249 | H7: 430 | I7: 551 | J7: 1250 | K7: 1920 | L7: 3000 | M7: Pre-Q1-26 letters: "revenue from the last month of the quarter x12"; Q1-26 on: "Nebius AI cloud revenue from the last month of the quarter multiplied by 12". 2024 values from Oct-24 investor presentation chart. | N7: Filings & Capital
A8: Adjusted EBITDA - group | B8: $M | C8: -58.4 | D8: -58.1 | E8: -45.9 | F8: -63.9 | G8: -53.7 | H8: -21 | I8: -5.2 | J8: 15 | K8: 129.5 | L8: 236.2 | N8: Filings & Capital
A9: Adjusted EBITDA - Nebius AI cloud segment | B9: $M | C9: n.d. | D9: n.d. | E9: -21.5 | F9: -38.5 | G9: -27.4 | H9: 9.5 | I9: 25.1 | J9: 51.8 | K9: 174 | L9: 285.7 | N9: Filings & Capital
A10: Depreciation & amortization | B10: $M | C10: 8.9 | D10: 11.4 | E10: 23.5 | F10: 33.3 | G10: 49.1 | H10: 75.2 | I10: 99 | J10: 180.7 | K10: 212 | L10: 259.7 | N10: Filings & Capital
A11: Capex - cash purchases of PP&E and intangibles | B11: $M | C11: 58.9 | D11: 159 | E11: 172.1 | F11: 417.5 | G11: 543.9 | H11: 510.6 | I11: 955.5 | J11: 2056 | K11: 2472.9 | L11: 5657.4 | M11: Cash flow statement, continuing ops. | N11: Filings & Capital
A12: PP&E, net (period end) | B12: $M | C12: n.d. | D12: 328.3 | E12: 475.3 | F12: 846.7 | G12: 1334.1 | H12: 1789.4 | I12: 3314.4 | J12: 5553.3 | K12: 7131.7 | L12: 13045.2 | N12: Filings & Capital
A13: Cash & cash equivalents (period end) | B13: $M | C13: n.d. | D13: 2325.5 | E13: 2288.2 | F13: 2434.7 | G13: 1447 | H13: 1679.3 | I13: 4794.8 | J13: 3678.1 | K13: 9298.2 | L13: 8042.1 | N13: Filings & Capital
A14: Total debt, carrying (period end) | B14: $M | C14: n.d. | D14: 6.5 | E14: 6.2 | F14: 6.1 | G14: 6.2 | H14: 986.2 | I14: 4106.8 | J14: 4127.7 | K14: 8450.4 | L14: 8545.7 | N14: Filings & Capital
A15: Deferred revenue, total (period end) | B15: $M | C15: n.d. | D15: n.d. | E15: n.d. | F15: 16.3 | G15: 19 | H15: 19.3 | I15: 15.6 | J15: 1577.5 | K15: 4778.1 | L15: 5975.2 | N15: Filings & Capital
A16: Remaining performance obligations (period end) | B16: $M | C16: n.d. | D16: n.d. | E16: n.d. | F16: n.d. | G16: n.d. | H16: n.d. | I16: n.d. | J16: 21333 | K16: 33585.3 | L16: 37490.6 | N16: Filings & Capital
A17: Shares issued & outstanding (period end; excl. NVIDIA pre-funded warrant) | B17: shares | C17: n.d. | D17: 293850159 | E17: 199340118 | F17: 235753600 | G17: 238108831 | H17: 238705092 | I17: 251807222 | J17: 253016971 | K17: 253898194 | L17: 271855218 | M17: Excludes 21,065,936 NVIDIA pre-funded warrant shares (unexercised). | N17: Filings & Capital
A18: Weighted-average shares - basic | B18: shares | C18: n.d. | D18: n.d. | E18: 246595139 | F18: 217546859 | G18: 237916047 | H18: 238520244 | I18: 245256157 | J18: 252412097 | K18: 258298911 | L18: 280381615 | N18: Filings & Capital
A19: Customer concentration (>10% of revenue) | B19: text | C19: n.d. | D19: n.d. | E19: n.d. | F19: FY24: A 27%, C 11% | G19: n.d. | H19: A 39%, B 15% | I19: n.d. | J19: FY25: A 25%, B 15% | K19: n.d. | L19: C 24%, D 21%, E 14% | N19: Filings & Capital
A20: Net cash from operating activities - continuing ops | B20: $M | C20: -63 | D20: -99 | E20: -34.8 | F20: -73.1 | G20: -184.1 | H20: -167.7 | I20: -80.6 | J20: 834.3 | K20: 2258 | L20: 2246.1 | M20: Quarterly; latest restated basis (Toloka in discontinued ops). | N20: Filings & Capital (new)
A21: Change in deferred revenue (cash flow statement, operating) | B21: $M | C21: n.d. | D21: n.d. | E21: 3.7 | F21: -0.4 | G21: 2.4 | H21: 0.6 | I21: -3.8 | J21: 1566.5 | K21: 3198 | L21: 1197 | M21: Increase = cash collected ahead of revenue (customer prepayments). | N21: Filings & Capital (new)
A22: OCF excluding change in deferred revenue | B22: $M | C22: n.d. | D22: n.d. | E22: =E20-E21 | F22: =F20-F21 | G22: =G20-G21 | H22: =H20-H21 | I22: =I20-I21 | J22: =J20-J21 | K22: =K20-K21 | L22: =L20-L21 | M22: OCF minus change in deferred revenue (prepayment-free operating cash). | N22: Derived
A23: Server and network equipment, gross (in service) | B23: $M | C23: n.d. | D23: n.d. | E23: n.d. | F23: 794.9 | G23: n.d. | H23: n.d. | I23: n.d. | J23: 3123.6 | K23: 4692.7 | L23: 5197.7 | M23: PP&E note breakdown only in 20-F and 2026 interim statements; 2024/2025 interim OFRs give no breakdown. | N23: Filings & Capital (new)
A24: Assets not yet in use (gross; under installation incl. prepayments) | B24: $M | C24: n.d. | D24: n.d. | E24: n.d. | F24: 163.8 | G24: n.d. | H24: n.d. | I24: n.d. | J24: 2417.4 | K24: 2427.9 | L24: 7836.4 | M24: FY24 20-F showed 163.9 for Dec-24 (later 163.8) | N24: Filings & Capital (new)
A25: PP&E, gross (total before accumulated depreciation) | B25: $M | C25: n.d. | D25: n.d. | E25: n.d. | F25: 1083 | G25: n.d. | H25: n.d. | I25: n.d. | J25: 6190.3 | K25: 7976.6 | L25: 14149.5 | N25: Filings & Capital (new)
A26: PP&E gross in service (= gross - assets not yet in use) | B26: $M | C26: n.d. | D26: n.d. | E26: n.d. | F26: =F25-F24 | G26: n.d. | H26: n.d. | I26: n.d. | J26: =J25-J24 | K26: =K25-K24 | L26: =L25-L24 | N26: Derived
A27: Change in assets not yet in use (QoQ) | B27: $M | C27: n.d. | D27: n.d. | E27: n.d. | F27: n.d. | G27: n.d. | H27: n.d. | I27: n.d. | J27: n.d. | K27: =K24-J24 | L27: =L24-K24 | M27: Derived: period-end ANIU minus prior period-end ANIU from Note 7. Positive = net additions to installation pipeline (purchases/prepayments exceed transfers into service). Only where consecutive breakdowns exist (Q4-24→Q4-25 annual gap skipped; Q1-26 and Q2-26 QoQ). | N27: Derived
A28: Servers placed in service (QoQ change in server & network equipment, gross) | B28: $M | C28: n.d. | D28: n.d. | E28: n.d. | F28: n.d. | G28: n.d. | H28: n.d. | I28: n.d. | J28: n.d. | K28: =K23-J23 | L28: =L23-K23 | M28: Derived: QoQ change in Server and network equipment, gross (Note 7). Proxy for servers transferred into service; does not equal -Δ ANIU because new purchases enter ANIU first. Available Q1-26 (vs YE25) and Q2-26 (vs Q1-26). | N28: Derived
A29: B. Capacity & Power (capacity/nebius_capacity.xlsx; Capacity & Power team - tags carried)
A30: Energized MW - company total incl. plug (Capacity base case) | B30: MW | C30: 25 | D30: 25 | E30: 25 | F30: 25 | G30: 50 | H30: 50 | I30: 62.5 | J30: 170 | K30: 181.5 | L30: 193 | M30: Ties to mgmt figures where given (YE25 ~170 MW active). Capacity Quarterly MW row 130 (Total incl. plug). MIXED basis: Vineland, Modi'in, AIB = IT MW; other sites as stated (mostly gross/unknown). Closest to Nebius "active" power; NOT connected or contracted. | N30: Capacity & Power
A31: Energized MW - identified sites, low | B31: MW | C31: 25 | D31: 25 | E31: 25 | F31: 30 | G31: 45 | H31: 45 | I31: 45 | J31: 115.8 | K31: 154 | L31: 157 | M31: Excludes plug for undisclosed sites. Capacity Quarterly MW row 124. | N31: Capacity & Power
A32: Energized MW - identified sites, high | B32: MW | C32: 25 | D32: 25 | E32: 25 | F32: 30 | G32: 55 | H32: 55 | I32: 80 | J32: 179.6 | K32: 209 | L32: 229 | M32: Excludes plug. Capacity Quarterly MW row 125. | N32: Capacity & Power
A33: MW as stated by management | B33: MW | C33: n.d. | D33: n.d. | E33: n.d. | F33: 25 | G33: n.d. | H33: n.d. | I33: n.d. | J33: 170 | K33: n.d. | L33: n.d. | M33: YE24 = connected (Q3-25 letter chart); YE25 = ACTIVE (Q4-25 letter). Different definitions. | N33: Capacity & Power / filings
A34: GPUs deployed - modeled (Capacity: energized MW x GPUs/MW) | B34: GPUs | C34: 13713 | D34: 13713 | E34: 13713 | F34: 16456 | G34: 27426 | H34: 27426 | I34: 32542 | J34: 69797 | K34: 84323 | L34: 89153 | M34: Modeled from MW, not a company count. Company counts ran ahead of powered MW. | N34: Capacity & Power
A35: of which Hopper (H100-class; Mantsala first 25 MW, Paris, Keflavik) | B35: GPUs | C35: 13713 | D35: 13713 | E35: 13713 | F35: 16456 | G35: 21941 | H35: 21941 | I35: 21941 | J35: 21941 | K35: 21941 | L35: 21941 | M35: Generation per site mostly ASSUMED by Capacity team (GPU vintage tab). | N35: Capacity & Power (split by Filings)
A36: of which H200 (Kansas City first 10 MW @ 548.5 GPUs/MW) | B36: GPUs | C36: 0 | D36: 0 | E36: 0 | F36: 0 | G36: 5485 | H36: 5485 | I36: 5485 | J36: 5485 | K36: 5485 | L36: 5485 | M36: Generation per site mostly ASSUMED by Capacity team (GPU vintage tab). | N36: Capacity & Power (split by Filings)
A37: of which B200 (Kansas City expansion, Modi'in) | B37: GPUs | C37: 0 | D37: 0 | E37: 0 | F37: 0 | G37: 0 | H37: 0 | I37: 0 | J37: 7981 | K37: 7981 | L37: 7981 | M37: Generation per site mostly ASSUMED by Capacity team (GPU vintage tab). | N37: Capacity & Power (split by Filings)
A38: of which B300 HGX (Longcross) | B38: GPUs | C38: 0 | D38: 0 | E38: 0 | F38: 0 | G38: 0 | H38: 0 | I38: 0 | J38: 6173 | K38: 10031 | L38: 10031 | M38: Generation per site mostly ASSUMED by Capacity team (GPU vintage tab). | N38: Capacity & Power (split by Filings)
A39: of which GB300 NVL72 (Vineland, Mantsala expansion) | B39: GPUs | C39: 0 | D39: 0 | E39: 0 | F39: 0 | G39: 0 | H39: 0 | I39: 5116 | J39: 28217 | K39: 38885 | L39: 43715 | M39: Generation per site mostly ASSUMED by Capacity team (GPU vintage tab). | N39: Capacity & Power (split by Filings)
A40: GPU count as stated by company (for comparison) | B40: GPUs | C40: n.d. | D40: n.d. | E40: 10000 | F40: 20000 | G40: 30000 | H40: n.d. | I40: n.d. | J40: n.d. | K40: n.d. | L40: n.d. | M40: Not used in formulas. | N40: Capacity & Power / filings
A41: C. GPU list pricing (GPU Market & Comps: market/gpu_price_history.xlsx)
A42: Nebius H100 SXM on-demand list - quarter-end (latest snapshot in quarter) | B42: $/GPU-hr | C42: 4.85 | D42: 4.85 | E42: 3.5 | F42: 2.95 | G42: 2.95 | H42: 2.95 | I42: 2.95 | J42: 2.95 | K42: 2.95 | L42: 3.85 | M42: Public on-demand list; commitments "up to 35% less" (nebius.com/prices). | N42: GPU Market & Comps
A43: Nebius H200 on-demand list - quarter-end (latest snapshot in quarter) | B43: $/GPU-hr | C43: n.d. | D43: n.d. | E43: n.d. | F43: 3.5 | G43: 3.5 | H43: 3.5 | I43: 3.5 | J43: 3.5 | K43: 3.5 | L43: 4.5 | M43: Public on-demand list; commitments "up to 35% less" (nebius.com/prices). | N43: GPU Market & Comps
A44: Nebius B200 on-demand list - quarter-end (latest snapshot in quarter) | B44: $/GPU-hr | C44: n.d. | D44: n.d. | E44: n.d. | F44: n.d. | G44: n.d. | H44: n.d. | I44: 5.5 | J44: 5.5 | K44: 5.5 | L44: 7.15 | M44: Public on-demand list; commitments "up to 35% less" (nebius.com/prices). | N44: GPU Market & Comps
A45: Nebius B300 on-demand list - quarter-end (latest snapshot in quarter) | B45: $/GPU-hr | C45: n.d. | D45: n.d. | E45: n.d. | F45: n.d. | G45: n.d. | H45: n.d. | I45: n.d. | J45: n.d. | K45: n.d. | L45: 7.85 | M45: Public on-demand list; commitments "up to 35% less" (nebius.com/prices). | N45: GPU Market & Comps
A46: Nebius H100 SXM on-demand list - quarter average (3 months) | B46: $/GPU-hr | C46: =AVERAGE(Prices_Monthly!B4:D4) | D46: =AVERAGE(Prices_Monthly!E4:G4) | E46: =AVERAGE(Prices_Monthly!H4:J4) | F46: =AVERAGE(Prices_Monthly!K4:M4) | G46: =AVERAGE(Prices_Monthly!N4:P4) | H46: =AVERAGE(Prices_Monthly!Q4:S4) | I46: =AVERAGE(Prices_Monthly!T4:V4) | J46: =AVERAGE(Prices_Monthly!W4:Y4) | K46: =AVERAGE(Prices_Monthly!Z4:AB4) | L46: =AVERAGE(Prices_Monthly!AC4:AE4) | M46: AVERAGE of Prices_Monthly; orange if any month forward-filled. | N46: Derived from GPU Market & Comps
A47: Nebius H200 on-demand list - quarter average (3 months) | B47: $/GPU-hr | C47: n.d. | D47: n.d. | E47: n.d. | F47: =AVERAGE(Prices_Monthly!K5:M5) | G47: =AVERAGE(Prices_Monthly!N5:P5) | H47: =AVERAGE(Prices_Monthly!Q5:S5) | I47: =AVERAGE(Prices_Monthly!T5:V5) | J47: =AVERAGE(Prices_Monthly!W5:Y5) | K47: =AVERAGE(Prices_Monthly!Z5:AB5) | L47: =AVERAGE(Prices_Monthly!AC5:AE5) | M47: AVERAGE of Prices_Monthly; orange if any month forward-filled. | N47: Derived from GPU Market & Comps
A48: Nebius B200 on-demand list - quarter average (3 months) | B48: $/GPU-hr | C48: n.d. | D48: n.d. | E48: n.d. | F48: n.d. | G48: n.d. | H48: n.d. | I48: =AVERAGE(Prices_Monthly!T6:V6) | J48: =AVERAGE(Prices_Monthly!W6:Y6) | K48: =AVERAGE(Prices_Monthly!Z6:AB6) | L48: =AVERAGE(Prices_Monthly!AC6:AE6) | M48: AVERAGE of Prices_Monthly; orange if any month forward-filled. | N48: Derived from GPU Market & Comps
A49: Nebius B300 on-demand list - quarter average (3 months) | B49: $/GPU-hr | C49: n.d. | D49: n.d. | E49: n.d. | F49: n.d. | G49: n.d. | H49: n.d. | I49: n.d. | J49: n.d. | K49: n.d. | L49: =AVERAGE(Prices_Monthly!AC7:AE7) | M49: AVERAGE of Prices_Monthly; orange if any month forward-filled. | N49: Derived from GPU Market & Comps
A50: Neocloud median H100 SXM on-demand (last month of quarter) | B50: $/GPU-hr | C50: 4.09 | D50: 4.09 | E50: 3.49 | F50: 2.99 | G50: 2.99 | H50: 3.445 | I50: 2.99 | J50: 2.99 | K50: 3.44 | L50: 3.99 | M50: Forward-filled median across neoclouds (n in source tab). | N50: GPU Market & Comps
A51: Price used for B300 / GB300 GPUs (proxy) | B51: $/GPU-hr | C51: n.d. | D51: n.d. | E51: n.d. | F51: n.d. | G51: n.d. | H51: n.d. | I51: =I48 | J51: =J48 | K51: =K48 | L51: =L49 | M51: GB300 has no public Nebius price ("contact us"). Proxy = B300 quarter-avg list when listed (Q2-26), else B200 quarter-avg list (floor). | N51: Filings (method)
A52: Fleet-weighted blended list price (quarter avg) | B52: $/GPU-hr | C52: =(C35*C46)/C34 | D52: =(D35*D46)/D34 | E52: =(E35*E46)/E34 | F52: =(F35*F46)/F34 | G52: =(G35*G46+G36*G47)/G34 | H52: =(H35*H46+H36*H47)/H34 | I52: =(I35*I46+I36*I47+(I38+I39)*I51)/I34 | J52: =(J35*J46+J36*J47+J37*J48+(J38+J39)*J51)/J34 | K52: =(K35*K46+K36*K47+K37*K48+(K38+K39)*K51)/K34 | L52: =(L35*L46+L36*L47+L37*L48+(L38+L39)*L51)/L34 | M52: Hopper priced at H100 list (H200 mix unknown -> conservative). Weights = modeled GPUs at quarter end. | N52: Derived (Estimated inputs)
A53: D. Derived KPIs (live formulas; n.d. where an input is missing)
A54: Hours in quarter | B54: hours | C54: =91*24 | D54: =91*24 | E54: =92*24 | F54: =92*24 | G54: =90*24 | H54: =91*24 | I54: =92*24 | J54: =92*24 | K54: =90*24 | L54: =91*24 | M54: calendar days x 24 | N54: Derived
A55: Average GPUs in quarter (opening+closing)/2 | B55: GPUs | C55: n.d. | D55: =AVERAGE(C34,D34) | E55: =AVERAGE(D34,E34) | F55: =AVERAGE(E34,F34) | G55: =AVERAGE(F34,G34) | H55: =AVERAGE(G34,H34) | I55: =AVERAGE(H34,I34) | J55: =AVERAGE(I34,J34) | K55: =AVERAGE(J34,K34) | L55: =AVERAGE(K34,L34) | M55: Q1-24 n.d. (no Q4-23 model value). | N55: Derived
A56: Implied realized revenue per GPU-hour (AI cloud rev / avg GPUs / hours) | B56: $/GPU-hr | C56: n.d. | D56: n.d. | E56: =E6*1000000/(E55*E54) | F56: =F6*1000000/(F55*F54) | G56: =G6*1000000/(G55*G54) | H56: =H6*1000000/(H55*H54) | I56: =I6*1000000/(I55*I54) | J56: =J6*1000000/(J55*J54) | K56: =K6*1000000/(K55*K54) | L56: =L6*1000000/(L55*L54) | M56: Revenue includes non-GPU-hour items (Token Factory, storage, software, asset-light). | N56: Derived
A57: Implied utilization = AI cloud rev / (avg GPUs x hours x blended list $/GPU-hr) | B57: % | C57: n.d. | D57: n.d. | E57: =E6*1000000/(E55*E54*E52) | F57: =F6*1000000/(F55*F54*F52) | G57: =G6*1000000/(G55*G54*G52) | H57: =H6*1000000/(H55*H54*H52) | I57: =I6*1000000/(I55*I54*I52) | J57: =J6*1000000/(J55*J54*J52) | K57: =K6*1000000/(K55*K54*K52) | L57: =L6*1000000/(L55*L54*L52) | M57: Mixes utilization with realized-vs-list discount (commit deals priced below list); >100% possible if modeled GPUs understate fleet or revenue includes non-GPU items. Indicative only. | N57: Derived
A58: Implied utilization on quarter-end GPUs (variant) | B58: % | C58: n.d. | D58: n.d. | E58: =E6*1000000/(E34*E54*E52) | F58: =F6*1000000/(F34*F54*F52) | G58: =G6*1000000/(G34*G54*G52) | H58: =H6*1000000/(H34*H54*H52) | I58: =I6*1000000/(I34*I54*I52) | J58: =J6*1000000/(J34*J54*J52) | K58: =K6*1000000/(K34*K54*K52) | L58: =L6*1000000/(L34*L54*L52) | M58: Lower bound vs average-GPU version when fleet is growing. | N58: Derived
A59: AI cloud revenue per energized MW, annualized (quarter-end MW) | B59: $M/MW-yr | C59: n.d. | D59: n.d. | E59: =E6*4/E30 | F59: =F6*4/F30 | G59: =G6*4/G30 | H59: =H6*4/H30 | I59: =I6*4/I30 | J59: =J6*4/J30 | K59: =K6*4/K30 | L59: =L6*4/L30 | M59: Mixed IT/gross MW basis. Compare: Q2-26 letter ~$12M/MW 2026 installed base; >$20M/MW new deals. | N59: Derived
A60: AI cloud revenue per energized MW, annualized (average MW) | B60: $M/MW-yr | C60: n.d. | D60: n.d. | E60: =E6*4/AVERAGE(D30,E30) | F60: =F6*4/AVERAGE(E30,F30) | G60: =G6*4/AVERAGE(F30,G30) | H60: =H6*4/AVERAGE(G30,H30) | I60: =I6*4/AVERAGE(H30,I30) | J60: =J6*4/AVERAGE(I30,J30) | K60: =K6*4/AVERAGE(J30,K30) | L60: =L6*4/AVERAGE(K30,L30) | N60: Derived
A61: AI cloud revenue per MW as stated by mgmt (YE MW), annualized | B61: $M/MW-yr | C61: n.d. | D61: n.d. | E61: n.d. | F61: =F6*4/F33 | G61: n.d. | H61: n.d. | I61: n.d. | J61: =J6*4/J33 | K61: n.d. | L61: n.d. | M61: Only where mgmt gave a MW figure (YE25 active). | N61: Derived
A62: AI cloud revenue per GPU, annualized (average GPUs) | B62: $K/GPU-yr | C62: n.d. | D62: n.d. | E62: =E6*4*1000/E55 | F62: =F6*4*1000/F55 | G62: =G6*4*1000/G55 | H62: =H6*4*1000/H55 | I62: =I6*4*1000/I55 | J62: =J6*4*1000/J55 | K62: =K6*4*1000/K55 | L62: =L6*4*1000/L55 | N62: Derived
A63: Change in energized MW vs prior quarter | B63: MW | C63: n.d. | D63: =D30-C30 | E63: =E30-D30 | F63: =F30-E30 | G63: =G30-F30 | H63: =H30-G30 | I63: =I30-H30 | J63: =J30-I30 | K63: =K30-J30 | L63: =L30-K30 | N63: Derived
A64: Cash capex per MW added (quarter) | B64: $M/MW | C64: n.d. | D64: =IF(D63<=5,"n.m. (dMW<=5)",D11/D63) | E64: =IF(E63<=5,"n.m. (dMW<=5)",E11/E63) | F64: =IF(F63<=5,"n.m. (dMW<=5)",F11/F63) | G64: =IF(G63<=5,"n.m. (dMW<=5)",G11/G63) | H64: =IF(H63<=5,"n.m. (dMW<=5)",H11/H63) | I64: =IF(I63<=5,"n.m. (dMW<=5)",I11/I63) | J64: =IF(J63<=5,"n.m. (dMW<=5)",J11/J63) | K64: =IF(K63<=5,"n.m. (dMW<=5)",K11/K63) | L64: =IF(L63<=5,"n.m. (dMW<=5)",L11/L63) | M64: Capex funds future capacity (assets not yet in use); quarterly ratio not meaningful when MW added is ~0. | N64: Derived
A65: Cash capex per MW added, trailing 4 quarters | B65: $M/MW | C65: n.d. | D65: n.d. | E65: n.d. | F65: n.d. | G65: =IF(G30-C30<=5,"n.m. (dMW<=5)",SUM(D11:G11)/(G30-C30)) | H65: =IF(H30-D30<=5,"n.m. (dMW<=5)",SUM(E11:H11)/(H30-D30)) | I65: =IF(I30-E30<=5,"n.m. (dMW<=5)",SUM(F11:I11)/(I30-E30)) | J65: =IF(J30-F30<=5,"n.m. (dMW<=5)",SUM(G11:J11)/(J30-F30)) | K65: =IF(K30-G30<=5,"n.m. (dMW<=5)",SUM(H11:K11)/(K30-G30)) | L65: =IF(L30-H30<=5,"n.m. (dMW<=5)",SUM(I11:L11)/(L30-H30)) | N65: Derived
A66: Placed-in-service PP&E per MW added (gross in-service PP&E change / MW change) | B66: $M/MW | C66: n.d. | D66: n.d. | E66: n.d. | F66: n.d. | G66: n.d. | H66: n.d. | I66: n.d. | J66: n.d. | K66: =IF(K30-J30<=5,"n.m. (dMW<=5)",(K26-J26)/(K30-J30)) | L66: =IF(L30-K30<=5,"n.m. (dMW<=5)",(L26-K26)/(L30-K30)) | M66: Quarterly where consecutive breakdowns exist (Q1-26, Q2-26). | N66: Derived
A67: Placed-in-service PP&E per MW added, FY basis (Q4 prior -> Q4) | B67: $M/MW | C67: n.d. | D67: n.d. | E67: n.d. | F67: n.d. | G67: n.d. | H67: n.d. | I67: n.d. | J67: =(J26-F26)/(J30-F30) | K67: n.d. | L67: n.d. | M67: FY2025 only (Dec-24 -> Dec-25 breakdowns). | N67: Derived
A68: ARR / 12 = implied last-month AI cloud revenue | B68: $M | C68: =C7/12 | D68: =D7/12 | E68: =E7/12 | F68: =F7/12 | G68: =G7/12 | H68: =H7/12 | I68: =I7/12 | J68: =J7/12 | ... L68: =L7/12 | M68: Definition: last month of quarter x12 (Q2-26 letter footnote 4). | N68: Derived
A69: AI cloud revenue - quarter monthly average | B69: $M | C69: n.d. | D69: n.d. | E69: =E6/3 | F69: =F6/3 | G69: =G6/3 | H69: =H6/3 | I69: =I6/3 | J69: =J6/3 | K69: =K6/3 | L69: =L6/3 | N69: Derived
A70: Last-month vs quarter-average step-up | B70: % | C70: n.d. | D70: n.d. | E70: =E68/E69-1 | F70: =F68/F69-1 | G70: =G68/G69-1 | H70: =H68/H69-1 | I70: =I68/I69-1 | J70: =J68/J69-1 | K70: =K68/K69-1 | L70: =L68/L69-1 | M70: Pre-2026 ARR scope = "revenue" (core AI infra; 2024 from presentation charts) vs AI cloud segment revenue: scope mismatch possible. | N70: Derived
A71: Annualized AI cloud revenue per $1 server & network equipment in service (period end) | B71: $/$ | C71: n.d. | D71: n.d. | E71: n.d. | F71: =F6*4/F23 | G71: n.d. | H71: n.d. | I71: n.d. | J71: =J6*4/J23 | K71: =K6*4/K23 | L71: =L6*4/L23 | M71: Gross cost basis. | N71: Derived
A72: Annualized AI cloud revenue per $1 server & network equipment in service (average) | B72: $/$ | C72: n.d. | D72: n.d. | E72: n.d. | F72: n.d. | G72: n.d. | H72: n.d. | I72: n.d. | J72: n.d. | K72: =K6*4/AVERAGE(J23,K23) | L72: =L6*4/AVERAGE(K23,L23) | N72: Derived
A73: AI cloud adj. EBITDA per energized MW, annualized (average MW) | B73: $M/MW-yr | C73: n.d. | D73: n.d. | E73: =E9*4/AVERAGE(D30,E30) | F73: =F9*4/AVERAGE(E30,F30) | G73: =G9*4/AVERAGE(F30,G30) | H73: =H9*4/AVERAGE(G30,H30) | I73: =I9*4/AVERAGE(H30,I30) | J73: =J9*4/AVERAGE(I30,J30) | K73: =K9*4/AVERAGE(J30,K30) | L73: =L9*4/AVERAGE(K30,L30) | N73: Derived
A74: Change in deferred revenue as % of capex | B74: % | C74: n.d. | D74: n.d. | E74: =E21/E11 | F74: =F21/F11 | G74: =G21/G11 | H74: =H21/H11 | I74: =I21/I11 | J74: =J21/J11 | K74: =K21/K11 | L74: =L21/L11 | M74: Prepayment funding of capex. | N74: Derived

Sheet Prices_Monthly
A1: Nebius public on-demand list prices, $/GPU-hr, monthly (GPU Market & Comps team: gpu_price_history.xlsx). Blue = observed in a Wayback/live snapshot that month (Reported); orange italic = carried forward from the last observation (Estimated, forward-fill); grey = no observation yet.
A3: SKU | B3: 2024-01 | C3: 2024-02 | D3: 2024-03 | E3: 2024-04 | F3: 2024-05 | G3: 2024-06 | H3: 2024-07 | I3: 2024-08 | J3: 2024-09 | K3: 2024-10 | L3: 2024-11 | M3: 2024-12 | N3: 2025-01 | O3: 2025-02 | P3: 2025-03 | Q3: 2025-04 | R3: 2025-05 | S3: 2025-06 | T3: 2025-07 | U3: 2025-08 | V3: 2025-09 | W3: 2025-10 | X3: 2025-11 | Y3: 2025-12 | Z3: 2026-01 | AA3: 2026-02 | AB3: 2026-03 | AC3: 2026-04 | AD3: 2026-05 | AE3: 2026-06
A4: Nebius H100 SXM on-demand | B4: 4.85 | C4: 4.85 | D4: 4.85 | E4: 4.85 | F4: 4.85 | G4: 4.85 | H4: 4.85 | I4: 4.85 | J4: 3.5 | K4: 3.5 | L4: 2.95 | M4: 2.95 | N4: 2.95 | O4: 2.95 | P4: 2.95 | Q4: 2.95 | R4: 2.95 | S4: 2.95 | T4: 2.95 | U4: 2.95 | V4: 2.95 | W4: 2.95 | X4: 2.95 | Y4: 2.95 | Z4: 2.95 | AA4: 2.95 | AB4: 2.95 | AC4: 2.95 | AD4: 2.95 | AE4: 3.85
A5: Nebius H200 on-demand | B5: n.d. | C5: n.d. | D5: n.d. | E5: n.d. | F5: n.d. | G5: n.d. | H5: n.d. | I5: n.d. | J5: n.d. | K5: 4.85 | L5: 3.5 | M5: 3.5 | N5: 3.5 | O5: 3.5 | P5: 3.5 | Q5: 3.5 | R5: 3.5 | S5: 3.5 | T5: 3.5 | U5: 3.5 | V5: 3.5 | W5: 3.5 | X5: 3.5 | Y5: 3.5 | Z5: 3.5 | AA5: 3.5 | AB5: 3.5 | AC5: 3.5 | AD5: 3.5 | AE5: 4.5
A6: Nebius B200 on-demand | B6: n.d. | C6: n.d. | D6: n.d. | E6: n.d. | F6: n.d. | G6: n.d. | H6: n.d. | I6: n.d. | J6: n.d. | K6: n.d. | L6: n.d. | M6: n.d. | N6: n.d. | O6: n.d. | P6: n.d. | Q6: n.d. | R6: n.d. | S6: n.d. | T6: 5.5 | U6: 5.5 | V6: 5.5 | W6: 5.5 | X6: 5.5 | Y6: 5.5 | Z6: 5.5 | AA6: 5.5 | AB6: 5.5 | AC6: 5.5 | AD6: 5.5 | AE6: 7.15
A7: Nebius B300 on-demand | B7: n.d. | C7: n.d. | D7: n.d. | E7: n.d. | F7: n.d. | G7: n.d. | H7: n.d. | I7: n.d. | J7: n.d. | K7: n.d. | L7: n.d. | M7: n.d. | N7: n.d. | O7: n.d. | P7: n.d. | Q7: n.d. | R7: n.d. | S7: n.d. | T7: n.d. | U7: n.d. | V7: n.d. | W7: n.d. | X7: n.d. | Y7: n.d. | Z7: n.d. | AA7: n.d. | AB7: n.d. | AC7: 6.1 | AD7: 6.1 | AE7: 7.85

Sheet Checks
A1: Checks: Q2 2026 tie-outs to filings and cross-team references (live formulas).
A3: Check | B3: Workbook value (formula) | C3: Expected | D3: Difference | E3: Result | F3: Expected source
A4: AI cloud segment revenue Q2-26 ($M) | B4: =KPI!L6 | C4: 574.9 | D4: =B4-C4 | E4: =IF(ABS(D4)<=0.25,"PASS","CHECK") | F4: 6-K 2026-08-12 acc 0001104659-26-094844 nbis-20260812xex99d2.htm Note 15 segment table | https://www.sec.gov/Archives/edgar/data/1513845/000110465926094844/nbis-20260812xex99d2.htm
A5: ARR end-Jun-26 ($M) | B5: =KPI!L7 | C5: 3000 | D5: =B5-C5 | E5: =IF(ABS(D5)<=0.25,"PASS","CHECK") | F5: 6-K 2026-08-12 acc 0001104659-26-094568 tm2622968d1_ex99-2.htm p.9 ("ARR reached $3.0 billion") | https://www.sec.gov/Archives/edgar/data/1513845/000110465926094568/tm2622968d1_ex99-2.htm
A6: Deferred revenue 30-Jun-26 ($M) = current 979.4 + non-current 4,995.8 | B6: =KPI!L15 | C6: =979.4+4995.8 | D6: =B6-C6 | E6: =IF(ABS(D6)<=0.25,"PASS","CHECK") | F6: 6-K 2026-08-12 acc 0001104659-26-094844 nbis-20260812xex99d2.htm balance sheet p.F-3 | https://www.sec.gov/Archives/edgar/data/1513845/000110465926094844/nbis-20260812xex99d2.htm
A7: RPO 30-Jun-26 ($M) | B7: =KPI!L16 | C7: 37490.6 | D7: =B7-C7 | E7: =IF(ABS(D7)<=0.25,"PASS","CHECK") | F7: 6-K 2026-08-12 acc 0001104659-26-094844 nbis-20260812xex99d2.htm Note 1 p.F-19 | https://www.sec.gov/Archives/edgar/data/1513845/000110465926094844/nbis-20260812xex99d2.htm
A8: Segment sum = group revenue Q2-26 (574.9+1.0+10.0-3.6) | B8: =KPI!L5 | C8: =574.9+1.0+10.0-3.6 | D8: =B8-C8 | E8: =IF(ABS(D8)<=0.25,"PASS","CHECK") | F8: 6-K 2026-08-12 acc 0001104659-26-094844 nbis-20260812xex99d2.htm Note 15 | https://www.sec.gov/Archives/edgar/data/1513845/000110465926094844/nbis-20260812xex99d2.htm
A9: ARR/12 = June AI cloud revenue ($M) | B9: =KPI!L68 | C9: 250 | D9: =B9-C9 | E9: =IF(ABS(D9)<=0.25,"PASS","CHECK") | F9: Q2-26 letter (ARR $3.0B / 12)
A10: Q2-26 AI cloud monthly average ($M) | B10: =KPI!L69 | C10: =574.9/3 | D10: =B10-C10 | E10: =IF(ABS(D10)<=0.25,"PASS","CHECK") | F10: arithmetic
A11: FY25 OCF: sum of quarters = 401.9 (20-F) | B11: =SUM(KPI!G20:J20) | C11: 401.9 | D11: =B11-C11 | E11: =IF(ABS(D11)<=0.25,"PASS","CHECK") | F11: 20-F 2026-04-30 acc 0001104659-26-052948 nbis-20251231x20f.htm cash flow statement p.F-12 | https://www.sec.gov/Archives/edgar/data/1513845/000110465926052948/nbis-20251231x20f.htm
A12: 1H26 OCF: sum = 4,504.1 | B12: =SUM(KPI!K20:L20) | C12: 4504.1 | D12: =B12-C12 | E12: =IF(ABS(D12)<=0.25,"PASS","CHECK") | F12: 6-K 2026-08-12 acc 0001104659-26-094568 tm2622968d1_ex99-1.htm cash flow statement | https://www.sec.gov/Archives/edgar/data/1513845/000110465926094568/tm2622968d1_ex99-1.htm
A13: 1H26 change in deferred revenue = 4,395.0 | B13: =SUM(KPI!K21:L21) | C13: 4395 | D13: =B13-C13 | E13: =IF(ABS(D13)<=0.25,"PASS","CHECK") | F13: 6-K 2026-08-12 acc 0001104659-26-094568 tm2622968d1_ex99-1.htm cash flow statement | https://www.sec.gov/Archives/edgar/data/1513845/000110465926094568/tm2622968d1_ex99-1.htm
A14: Deferred revenue YE24 ($M) | B14: =KPI!F15 | C14: 16.3 | D14: =B14-C14 | E14: =IF(ABS(D14)<=0.25,"PASS","CHECK") | F14: 6-K 2025-08-07 acc 0001104659-25-075028 tm2522866d1_ex99-1.htm BS comparative Dec-24 | https://www.sec.gov/Archives/edgar/data/1513845/000110465925075028/tm2522866d1_ex99-1.htm / 20-F 2026-04-30 acc 0001104659-26-052948 nbis-20251231x20f.htm BS | https://www.sec.gov/Archives/edgar/data/1513845/000110465926052948/nbis-20251231x20f.htm
A15: Deferred revenue 30-Jun-25 ($M) | B15: =KPI!H15 | C15: 19.3 | D15: =B15-C15 | E15: =IF(ABS(D15)<=0.25,"PASS","CHECK") | F15: 6-K 2025-08-07 acc 0001104659-25-075028 tm2522866d1_ex99-1.htm BS Jun-30-2025 | https://www.sec.gov/Archives/edgar/data/1513845/000110465925075028/tm2522866d1_ex99-1.htm
A16: Q1-26 servers placed in service = 4692.7-3123.6 | B16: =KPI!K28 | C16: =4692.7-3123.6 | D16: =B16-C16 | E16: =IF(ABS(D16)<=0.25,"PASS","CHECK") | F16: 6-K 2026-05-20 acc 0001104659-26-064092 nbis-20260331xex99d2.htm Note 7 | https://www.sec.gov/Archives/edgar/data/1513845/000110465926064092/nbis-20260331xex99d2.htm vs YE25
A17: Q2-26 servers placed in service = 5197.7-4692.7 | B17: =KPI!L28 | C17: =5197.7-4692.7 | D17: =B17-C17 | E17: =IF(ABS(D17)<=0.25,"PASS","CHECK") | F17: 6-K 2026-08-12 acc 0001104659-26-094844 nbis-20260812xex99d2.htm Note 7 | https://www.sec.gov/Archives/edgar/data/1513845/000110465926094844/nbis-20260812xex99d2.htm vs Q1FS
A18: Q1-26 Δ ANIU = 2427.9-2417.4 | B18: =KPI!K27 | C18: =2427.9-2417.4 | D18: =B18-C18 | E18: =IF(ABS(D18)<=0.25,"PASS","CHECK") | F18: 6-K 2026-05-20 acc 0001104659-26-064092 nbis-20260331xex99d2.htm Note 7 | https://www.sec.gov/Archives/edgar/data/1513845/000110465926064092/nbis-20260331xex99d2.htm
A19: Q2-26 Δ ANIU = 7836.4-2427.9 | B19: =KPI!L27 | C19: =7836.4-2427.9 | D19: =B19-C19 | E19: =IF(ABS(D19)<=0.25,"PASS","CHECK") | F19: 6-K 2026-08-12 acc 0001104659-26-094844 nbis-20260812xex99d2.htm Note 7 | https://www.sec.gov/Archives/edgar/data/1513845/000110465926094844/nbis-20260812xex99d2.htm
A20: FY24 OCF: sum of quarters = (269.9) | B20: =SUM(KPI!C20:F20) | C20: -269.9 | D20: =B20-C20 | E20: =IF(ABS(D20)<=0.25,"PASS","CHECK") | F20: 20-F 2026-04-30 acc 0001104659-26-052948 nbis-20251231x20f.htm cash flow statement | https://www.sec.gov/Archives/edgar/data/1513845/000110465926052948/nbis-20251231x20f.htm
A21: PP&E gross - accumulated depreciation = net 30-Jun-26 | B21: =KPI!L25-1104.3 | C21: =KPI!L12 | D21: =B21-C21 | E21: =IF(ABS(D21)<=0.25,"PASS","CHECK") | F21: 6-K 2026-08-12 acc 0001104659-26-094844 nbis-20260812xex99d2.htm Note 7 p.F-23 | https://www.sec.gov/Archives/edgar/data/1513845/000110465926094844/nbis-20260812xex99d2.htm
A22: Energized MW Q2-26 (Capacity team reference ~193) | B22: =KPI!L30 | C22: 193 | D22: =B22-C22 | E22: =IF(ABS(D22)<=0.5,"PASS","CHECK") | F22: Capacity & Power Quarterly MW row 130 Q2-26
A23: Modeled GPUs Q2-26 (Capacity team reference ~89,153) | B23: =KPI!L34 | C23: 89153 | D23: =B23-C23 | E23: =IF(ABS(D23)<=100,"PASS","CHECK") | F23: Capacity & Power GPUs deployed row 34 Q2-26 (tolerance 100)
A24: GPU generation split sums to total Q2-26 | B24: =SUM(KPI!L35:L39) | C24: =KPI!L34 | D24: =B24-C24 | E24: =IF(ABS(D24)<=0.25,"PASS","CHECK") | F24: internal
A26: Filings & Capital n.d. notes (2026-10-05)
A27: RPO before YE25: FIRST disclosure = YE25 20-F $21,333.0 [R] at 12/31/25. No RPO $ in FY24 20-F or 2025 quarterly 6-Ks/letters searched. Leave Q1’24–Q3’25 n.d. Detail: kpi_nd_notes.md
A28: Mid-2025 PP&E Note 7: Q1’25 / Q2’25 / Q3’25 LACK servers & ANIU roll. Disclosed at YE24, YE25, Q1’26, Q2’26 (H1’26) only. Do not invent fills. Detail: kpi_nd_notes.md

Sheet Sources
A1: Sheet | B1: Cell | C1: Metric | D1: Period | E1: Value / formula | F1: Tag | G1: Source (form date acc doc ref | URL, or file/sheet/cell) | H1: Note / derivation
A2: Prices_Monthly | B2: B4 | C2: Nebius H100 SXM on-demand | D2: 2024-01 | E2: 4.85 | F2: Estimated | G2: /workspace/nebius/market/gpu_price_history.xlsx Monthly_FFill 'Nebius | H100 SXM 80GB | on-demand | PAYG' 2024-01 | H2: no snapshot this month; carried forward from last observation (market-team forward-fill)
A3: Prices_Monthly | B3: C4 | C3: Nebius H100 SXM on-demand | D3: 2024-02 | E3: 4.85 | F3: Estimated | G3: /workspace/nebius/market/gpu_price_history.xlsx Monthly_FFill 'Nebius | H100 SXM 80GB | on-demand | PAYG' 2024-02 | H3: no snapshot this month; carried forward from last observation (market-team forward-fill)
A4: Prices_Monthly | B4: D4 | C4: Nebius H100 SXM on-demand | D4: 2024-03 | E4: 4.85 | F4: Reported | G4: /workspace/nebius/market/gpu_price_history.xlsx Price_History_Monthly 'Nebius | H100 SXM 80GB | on-demand | PAYG' 2024-03 (snapshot rows in Price_History_Long; nebius.com/prices via web.archive.org)
A5: Prices_Monthly | B5: E4 | C5: Nebius H100 SXM on-demand | D5: 2024-04 | E5: 4.85 | F5: Estimated | G5: /workspace/nebius/market/gpu_price_history.xlsx Monthly_FFill 'Nebius | H100 SXM 80GB | on-demand | PAYG' 2024-04 | H5: no snapshot this month; carried forward from last observation (market-team forward-fill)
A6: Prices_Monthly | B6: F4 | C6: Nebius H100 SXM on-demand | D6: 2024-05 | E6: 4.85 | F6: Reported | G6: /workspace/nebius/market/gpu_price_history.xlsx Price_History_Monthly 'Nebius | H100 SXM 80GB | on-demand | PAYG' 2024-05 (snapshot rows in Price_History_Long; nebius.com/prices via web.archive.org)
A7: Prices_Monthly | B7: G4 | C7: Nebius H100 SXM on-demand | D7: 2024-06 | E7: 4.85 | F7: Estimated | G7: /workspace/nebius/market/gpu_price_history.xlsx Monthly_FFill 'Nebius | H100 SXM 80GB | on-demand | PAYG' 2024-06 | H7: no snapshot this month; carried forward from last observation (market-team forward-fill)
A8: Prices_Monthly | B8: H4 | C8: Nebius H100 SXM on-demand | D8: 2024-07 | E8: 4.85 | F8: Reported | G8: /workspace/nebius/market/gpu_price_history.xlsx Price_History_Monthly 'Nebius | H100 SXM 80GB | on-demand | PAYG' 2024-07 (snapshot rows in Price_History_Long; nebius.com/prices via web.archive.org)
A9: Prices_Monthly | B9: I4 | C9: Nebius H100 SXM on-demand | D9: 2024-08 | E9: 4.85 | F9: Reported | G9: /workspace/nebius/market/gpu_price_history.xlsx Price_History_Monthly 'Nebius | H100 SXM 80GB | on-demand | PAYG' 2024-08 (snapshot rows in Price_History_Long; nebius.com/prices via web.archive.org)
A10: Prices_Monthly | B10: J4 | C10: Nebius H100 SXM on-demand | D10: 2024-09 | E10: 3.5 | F10: Reported | G10: /workspace/nebius/market/gpu_price_history.xlsx Price_History_Monthly 'Nebius | H100 SXM 80GB | on-demand | PAYG' 2024-09 (snapshot rows in Price_History_Long; nebius.com/prices via web.archive.org)
A11: Prices_Monthly | B11: K4 | C11: Nebius H100 SXM on-demand | D11: 2024-10 | E11: 3.5 | F11: Reported | G11: /workspace/nebius/market/gpu_price_history.xlsx Price_History_Monthly 'Nebius | H100 SXM 80GB | on-demand | PAYG' 2024-10 (snapshot rows in Price_History_Long; nebius.com/prices via web.archive.org)
A12: Prices_Monthly | B12: L4 | C12: Nebius H100 SXM on-demand | D12: 2024-11 | E12: 2.95 | F12: Reported | G12: /workspace/nebius/market/gpu_price_history.xlsx Price_History_Monthly 'Nebius | H100 SXM 80GB | on-demand | PAYG' 2024-11 (snapshot rows in Price_History_Long; nebius.com/prices via web.archive.org)
A13: Prices_Monthly | B13: M4 | C13: Nebius H100 SXM on-demand | D13: 2024-12 | E13: 2.95 | F13: Reported | G13: /workspace/nebius/market/gpu_price_history.xlsx Price_History_Monthly 'Nebius | H100 SXM 80GB | on-demand | PAYG' 2024-12 (snapshot rows in Price_History_Long; nebius.com/prices via web.archive.org)
A14: Prices_Monthly | B14: N4 | C14: Nebius H100 SXM on-demand | D14: 2025-01 | E14: 2.95 | F14: Reported | G14: /workspace/nebius/market/gpu_price_history.xlsx Price_History_Monthly 'Nebius | H100 SXM 80GB | on-demand | PAYG' 2025-01 (snapshot rows in Price_History_Long; nebius.com/prices via web.archive.org)
A15: Prices_Monthly | B15: O4 | C15: Nebius H100 SXM on-demand | D15: 2025-02 | E15: 2.95 | F15: Estimated | G15: /workspace/nebius/market/gpu_price_history.xlsx Monthly_FFill 'Nebius | H100 SXM 80GB | on-demand | PAYG' 2025-02 | H15: no snapshot this month; carried forward from last observation (market-team forward-fill)
A16: Prices_Monthly | B16: P4 | C16: Nebius H100 SXM on-demand | D16: 2025-03 | E16: 2.95 | F16: Reported | G16: /workspace/nebius/market/gpu_price_history.xlsx Price_History_Monthly 'Nebius | H100 SXM 80GB | on-demand | PAYG' 2025-03 (snapshot rows in Price_History_Long; nebius.com/prices via web.archive.org)
A17: Prices_Monthly | B17: Q4 | C17: Nebius H100 SXM on-demand | D17: 2025-04 | E17: 2.95 | F17: Reported | G17: /workspace/nebius/market/gpu_price_history.xlsx Price_History_Monthly 'Nebius | H100 SXM 80GB | on-demand | PAYG' 2025-04 (snapshot rows in Price_History_Long; nebius.com/prices via web.archive.org)
A18: Prices_Monthly | B18: R4 | C18: Nebius H100 SXM on-demand | D18: 2025-05 | E18: 2.95 | F18: Reported | G18: /workspace/nebius/market/gpu_price_history.xlsx Price_History_Monthly 'Nebius | H100 SXM 80GB | on-demand | PAYG' 2025-05 (snapshot rows in Price_History_Long; nebius.com/prices via web.archive.org)
A19: Prices_Monthly | B19: S4 | C19: Nebius H100 SXM on-demand | D19: 2025-06 | E19: 2.95 | F19: Reported | G19: /workspace/nebius/market/gpu_price_history.xlsx Price_History_Monthly 'Nebius | H100 SXM 80GB | on-demand | PAYG' 2025-06 (snapshot rows in Price_History_Long; nebius.com/prices via web.archive.org)
A20: Prices_Monthly | B20: T4 | C20: Nebius H100 SXM on-demand | D20: 2025-07 | E20: 2.95 | F20: Reported | G20: /workspace/nebius/market/gpu_price_history.xlsx Price_History_Monthly 'Nebius | H100 SXM 80GB | on-demand | PAYG' 2025-07 (snapshot rows in Price_History_Long; nebius.com/prices via web.archive.org)
A21: Prices_Monthly | B21: U4 | C21: Nebius H100 SXM on-demand | D21: 2025-08 | E21: 2.95 | F21: Reported | G21: /workspace/nebius/market/gpu_price_history.xlsx Price_History_Monthly 'Nebius | H100 SXM 80GB | on-demand | PAYG' 2025-08 (snapshot rows in Price_History_Long; nebius.com/prices via web.archive.org)
A22: Prices_Monthly | B22: V4 | C22: Nebius H100 SXM on-demand | D22: 2025-09 | E22: 2.95 | F22: Reported | G22: /workspace/nebius/market/gpu_price_history.xlsx Price_History_Monthly 'Nebius | H100 SXM 80GB | on-demand | PAYG' 2025-09 (snapshot rows in Price_History_Long; nebius.com/prices via web.archive.org)
A23: Prices_Monthly | B23: W4 | C23: Nebius H100 SXM on-demand | D23: 2025-10 | E23: 2.95 | F23: Reported | G23: /workspace/nebius/market/gpu_price_history.xlsx Price_History_Monthly 'Nebius | H100 SXM 80GB | on-demand | PAYG' 2025-10 (snapshot rows in Price_History_Long; nebius.com/prices via web.archive.org)
A24: Prices_Monthly | B24: X4 | C24: Nebius H100 SXM on-demand | D24: 2025-11 | E24: 2.95 | F24: Reported | G24: /workspace/nebius/market/gpu_price_history.xlsx Price_History_Monthly 'Nebius | H100 SXM 80GB | on-demand | PAYG' 2025-11 (snapshot rows in Price_History_Long; nebius.com/prices via web.archive.org)
A25: Prices_Monthly | B25: Y4 | C25: Nebius H100 SXM on-demand | D25: 2025-12 | E25: 2.95 | F25: Reported | G25: /workspace/nebius/market/gpu_price_history.xlsx Price_History_Monthly 'Nebius | H100 SXM 80GB | on-demand | PAYG' 2025-12 (snapshot rows in Price_History_Long; nebius.com/prices via web.archive.org)
A26: Prices_Monthly | B26: Z4 | C26: Nebius H100 SXM on-demand | D26: 2026-01 | E26: 2.95 | F26: Reported | G26: /workspace/nebius/market/gpu_price_history.xlsx Price_History_Monthly 'Nebius | H100 SXM 80GB | on-demand | PAYG' 2026-01 (snapshot rows in Price_History_Long; nebius.com/prices via web.archive.org)
A27: Prices_Monthly | B27: AA4 | C27: Nebius H100 SXM on-demand | D27: 2026-02 | E27: 2.95 | F27: Reported | G27: /workspace/nebius/market/gpu_price_history.xlsx Price_History_Monthly 'Nebius | H100 SXM 80GB | on-demand | PAYG' 2026-02 (snapshot rows in Price_History_Long; nebius.com/prices via web.archive.org)
... A31: Prices_Monthly | B31: AE4 | C31: Nebius H100 SXM on-demand | D31: 2026-06 | E31: 3.85 | F31: Reported | G31: /workspace/nebius/market/gpu_price_history.xlsx Price_History_Monthly 'Nebius | H100 SXM 80GB | on-demand | PAYG' 2026-06 (snapshot rows in Price_History_Long; nebius.com/prices via web.archive.org)
A32: Prices_Monthly | B32: B5 | C32: Nebius H200 on-demand | D32: 2024-01 | E32: n.d. | F32: not disclosed | G32: /workspace/nebius/market/gpu_price_history.xlsx (no observation) | H32: SKU not listed / no snapshot
A33: Prices_Monthly | B33: C5 | C33: Nebius H200 on-demand | D33: 2024-02 | E33: n.d. | F33: not disclosed | G33: /workspace/nebius/market/gpu_price_history.xlsx (no observation) | H33: SKU not listed / no snapshot
A34: Prices_Monthly | B34: D5 | C34: Nebius H200 on-demand | D34: 2024-03 | E34: n.d. | F34: not disclosed | G34: /workspace/nebius/market/gpu_price_history.xlsx (no observation) | H34: SKU not listed / no snapshot
A35: Prices_Monthly | B35: E5 | C35: Nebius H200 on-demand | D35: 2024-04 | E35: n.d. | F35: not disclosed | G35: /workspace/nebius/market/gpu_price_history.xlsx (no observation) | H35: SKU not listed / no snapshot
A36: Prices_Monthly | B36: F5 | C36: Nebius H200 on-demand | D36: 2024-05 | E36: n.d. | F36: not disclosed | G36: /workspace/nebius/market/gpu_price_history.xlsx (no observation) | H36: SKU not listed / no snapshot
A37: Prices_Monthly | B37: G5 | C37: Nebius H200 on-demand | D37: 2024-06 | E37: n.d. | F37: not disclosed | G37: /workspace/nebius/market/gpu_price_history.xlsx (no observation) | H37: SKU not listed / no snapshot
A38: Prices_Monthly | B38: H5 | C38: Nebius H200 on-demand | D38: 2024-07 | E38: n.d. | F38: not disclosed | G38: /workspace/nebius/market/gpu_price_history.xlsx (no observation) | H38: SKU not listed / no snapshot
A39: Prices_Monthly | B39: I5 | C39: Nebius H200 on-demand | D39: 2024-08 | E39: n.d. | F39: not disclosed | G39: /workspace/nebius/market/gpu_price_history.xlsx (no observation) | H39: SKU not listed / no snapshot
A40: Prices_Monthly | B40: J5 | C40: Nebius H200 on-demand | D40: 2024-09 | E40: n.d. | F40: not disclosed | G40: /workspace/nebius/market/gpu_price_history.xlsx (no observation) | H40: SKU not listed / no snapshot
A41: Prices_Monthly | B41: K5 | C41: Nebius H200 on-demand | D41: 2024-10 | E41: 4.85 | F41: Reported | G41: /workspace/nebius/market/gpu_price_history.xlsx Price_History_Monthly 'Nebius | H200 141GB | on-demand | PAYG' 2024-10 (snapshot rows in Price_History_Long; nebius.com/prices via web.archive.org)
A42: Prices_Monthly | B42: L5 | C42: Nebius H200 on-demand | D42: 2024-11 | E42: 3.5 | F42: Reported | G42: /workspace/nebius/market/gpu_price_history.xlsx Price_History_Monthly 'Nebius | H200 141GB | on-demand | PAYG' 2024-11 (snapshot rows in Price_History_Long; nebius.com/prices via web.archive.org)
A43: Prices_Monthly | B43: M5 | C43: Nebius H200 on-demand | D43: 2024-12 | E43: 3.5 | F43: Reported | G43: /workspace/nebius/market/gpu_price_history.xlsx Price_History_Monthly 'Nebius | H200 141GB | on-demand | PAYG' 2024-12 (snapshot rows in Price_History_Long; nebius.com/prices via web.archive.org)
A44: Prices_Monthly | B44: N5 | C44: Nebius H200 on-demand | D44: 2025-01 | E44: 3.5 | F44: Reported | G44: /workspace/nebius/market/gpu_price_history.xlsx Price_History_Monthly 'Nebius | H200 141GB | on-demand | PAYG' 2025-01 (snapshot rows in Price_History_Long; nebius.com/prices via web.archive.org)
A45: Prices_Monthly | B45: O5 | C45: Nebius H200 on-demand | D45: 2025-02 | E45: 3.5 | F45: Estimated | G45: /workspace/nebius/market/gpu_price_history.xlsx Monthly_FFill 'Nebius | H200 141GB | on-demand | PAYG' 2025-02 | H45: no snapshot this month; carried forward from last observation (market-team forward-fill)
A46: Prices_Monthly | B46: P5 | C46: Nebius H200 on-demand | D46: 2025-03 | E46: 3.5 | F46: Reported | G46: /workspace/nebius/market/gpu_price_history.xlsx Price_History_Monthly 'Nebius | H200 141GB | on-demand | PAYG' 2025-03 (snapshot rows in Price_History_Long; nebius.com/prices via web.archive.org)
A47: Prices_Monthly | B47: Q5 | C47: Nebius H200 on-demand | D47: 2025-04 | E47: 3.5 | F47: Reported | G47: /workspace/nebius/market/gpu_price_history.xlsx Price_History_Monthly 'Nebius | H200 141GB | on-demand | PAYG' 2025-04 (snapshot rows in Price_History_Long; nebius.com/prices via web.archive.org)
A48: Prices_Monthly | B48: R5 | C48: Nebius H200 on-demand | D48: 2025-05 | E48: 3.5 | F48: Reported | G48: /workspace/nebius/market/gpu_price_history.xlsx Price_History_Monthly 'Nebius | H200 141GB | on-demand | PAYG' 2025-05 (snapshot rows in Price_History_Long; nebius.com/prices via web.archive.org)
A49: Prices_Monthly | B49: S5 | C49: Nebius H200 on-demand | D49: 2025-06 | E49: 3.5 | F49: Reported | G49: /workspace/nebius/market/gpu_price_history.xlsx Price_History_Monthly 'Nebius | H200 141GB | on-demand | PAYG' 2025-06 (snapshot rows in Price_History_Long; nebius.com/prices via web.archive.org)
A50: Prices_Monthly | B50: T5 | C50: Nebius H200 on-demand | D50: 2025-07 | E50: 3.5 | F50: Reported | G50: /workspace/nebius/market/gpu_price_history.xlsx Price_History_Monthly 'Nebius | H200 141GB | on-demand | PAYG' 2025-07 (snapshot rows in Price_History_Long; nebius.com/prices via web.archive.org)
A51: Prices_Monthly | B51: U5 | C51: Nebius H200 on-demand | D51: 2025-08 | E51: 3.5 | F51: Reported | G51: /workspace/nebius/market/gpu_price_history.xlsx Price_History_Monthly 'Nebius | H200 141GB | on-demand | PAYG' 2025-08 (snapshot rows in Price_History_Long; nebius.com/prices via web.archive.org)
A52: Prices_Monthly | B52: V5 | C52: Nebius H200 on-demand | D52: 2025-09 | E52: 3.5 | F52: Reported | G52: /workspace/nebius/market/gpu_price_history.xlsx Price_History_Monthly 'Nebius | H200 141GB | on-demand | PAYG' 2025-09 (snapshot rows in Price_History_Long; nebius.com/prices via web.archive.org)
A53: Prices_Monthly | B53: W5 | C53: Nebius H200 on-demand | D53: 2025-10 | E53: 3.5 | F53: Reported | G53: /workspace/nebius/market/gpu_price_history.xlsx Price_History_Monthly 'Nebius | H200 141GB | on-demand | PAYG' 2025-10 (snapshot rows in Price_History_Long; nebius.com/prices via web.archive.org)
A54: Prices_Monthly | B54: X5 | C54: Nebius H200 on-demand | D54: 2025-11 | E54: 3.5 | F54: Reported | G54: /workspace/nebius/market/gpu_price_history.xlsx Price_History_Monthly 'Nebius | H200 141GB | on-demand | PAYG' 2025-11 (snapshot rows in Price_History_Long; nebius.com/prices via web.archive.org)
A55: Prices_Monthly | B55: Y5 | C55: Nebius H200 on-demand | D55: 2025-12 | E55: 3.5 | F55: Reported | G55: /workspace/nebius/market/gpu_price_history.xlsx Price_History_Monthly 'Nebius | H200 141GB | on-demand | PAYG' 2025-12 (snapshot rows in Price_History_Long; nebius.com/prices via web.archive.org)
A56: Prices_Monthly | B56: Z5 | C56: Nebius H200 on-demand | D56: 2026-01 | E56: 3.5 | F56: Reported | G56: /workspace/nebius/market/gpu_price_history.xlsx Price_History_Monthly 'Nebius | H200 141GB | on-demand | PAYG' 2026-01 (snapshot rows in Price_History_Long; nebius.com/prices via web.archive.org)
A57: Prices_Monthly | B57: AA5 | C57: Nebius H200 on-demand | D57: 2026-02 | E57: 3.5 | F57: Reported | G57: /workspace/nebius/market/gpu_price_history.xlsx Price_History_Monthly 'Nebius | H200 141GB | on-demand | PAYG' 2026-02 (snapshot rows in Price_History_Long; nebius.com/prices via web.archive.org)
... A61: Prices_Monthly | B61: AE5 | C61: Nebius H200 on-demand | D61: 2026-06 | E61: 4.5 | F61: Reported | G61: /workspace/nebius/market/gpu_price_history.xlsx Price_History_Monthly 'Nebius | H200 141GB | on-demand | PAYG' 2026-06 (snapshot rows in Price_History_Long; nebius.com/prices via web.archive.org)
A62: Prices_Monthly | B62: B6 | C62: Nebius B200 on-demand | D62: 2024-01 | E62: n.d. | F62: not disclosed | G62: /workspace/nebius/market/gpu_price_history.xlsx (no observation) | H62: SKU not listed / no snapshot
A63: Prices_Monthly | B63: C6 | C63: Nebius B200 on-demand | D63: 2024-02 | E63: n.d. | F63: not disclosed | G63: /workspace/nebius/market/gpu_price_history.xlsx (no observation) | H63: SKU not listed / no snapshot
A64: Prices_Monthly | B64: D6 | C64: Nebius B200 on-demand | D64: 2024-03 | E64: n.d. | F64: not disclosed | G64: /workspace/nebius/market/gpu_price_history.xlsx (no observation) | H64: SKU not listed / no snapshot
A65: Prices_Monthly | B65: E6 | C65: Nebius B200 on-demand | D65: 2024-04 | E65: n.d. | F65: not disclosed | G65: /workspace/nebius/market/gpu_price_history.xlsx (no observation) | H65: SKU not listed / no snapshot
A66: Prices_Monthly | B66: F6 | C66: Nebius B200 on-demand | D66: 2024-05 | E66: n.d. | F66: not disclosed | G66: /workspace/nebius/market/gpu_price_history.xlsx (no observation) | H66: SKU not listed / no snapshot
A67: Prices_Monthly | B67: G6 | C67: Nebius B200 on-demand | D67: 2024-06 | E67: n.d. | F67: not disclosed | G67: /workspace/nebius/market/gpu_price_history.xlsx (no observation) | H67: SKU not listed / no snapshot
A68: Prices_Monthly | B68: H6 | C68: Nebius B200 on-demand | D68: 2024-07 | E68: n.d. | F68: not disclosed | G68: /workspace/nebius/market/gpu_price_history.xlsx (no observation) | H68: SKU not listed / no snapshot
A69: Prices_Monthly | B69: I6 | C69: Nebius B200 on-demand | D69: 2024-08 | E69: n.d. | F69: not disclosed | G69: /workspace/nebius/market/gpu_price_history.xlsx (no observation) | H69: SKU not listed / no snapshot
A70: Prices_Monthly | B70: J6 | C70: Nebius B200 on-demand | D70: 2024-09 | E70: n.d. | F70: not disclosed | G70: /workspace/nebius/market/gpu_price_history.xlsx (no observation) | H70: SKU not listed / no snapshot
A71: Prices_Monthly | B71: K6 | C71: Nebius B200 on-demand | D71: 2024-10 | E71: n.d. | F71: not disclosed | G71: /workspace/nebius/market/gpu_price_history.xlsx (no observation) | H71: SKU not listed / no snapshot
A72: Prices_Monthly | B72: L6 | C72: Nebius B200 on-demand | D72: 2024-11 | E72: n.d. | F72: not disclosed | G72: /workspace/nebius/market/gpu_price_history.xlsx (no observation) | H72: SKU not listed / no snapshot
A73: Prices_Monthly | B73: M6 | C73: Nebius B200 on-demand | D73: 2024-12 | E73: n.d. | F73: not disclosed | G73: /workspace/nebius/market/gpu_price_history.xlsx (no observation) | H73: SKU not listed / no snapshot
... A79: Prices_Monthly | B79: S6 | C79: Nebius B200 on-demand | D79: 2025-06 | E79: n.d. | F79: not disclosed | G79: /workspace/nebius/market/gpu_price_history.xlsx (no observation) | H79: SKU not listed / no snapshot
A80: Prices_Monthly | B80: T6 | C80: Nebius B200 on-demand | D80: 2025-07 | E80: 5.5 | F80: Reported | G80: /workspace/nebius/market/gpu_price_history.xlsx Price_History_Monthly 'Nebius | B200 | on-demand | PAYG' 2025-07 (snapshot rows in Price_History_Long; nebius.com/prices via web.archive.org)
A81: Prices_Monthly | B81: U6 | C81: Nebius B200 on-demand | D81: 2025-08 | E81: 5.5 | F81: Reported | G81: /workspace/nebius/market/gpu_price_history.xlsx Price_History_Monthly 'Nebius | B200 | on-demand | PAYG' 2025-08 (snapshot rows in Price_History_Long; nebius.com/prices via web.archive.org)
A82: Prices_Monthly | B82: V6 | C82: Nebius B200 on-demand | D82: 2025-09 | E82: 5.5 | F82: Reported | G82: /workspace/nebius/market/gpu_price_history.xlsx Price_History_Monthly 'Nebius | B200 | on-demand | PAYG' 2025-09 (snapshot rows in Price_History_Long; nebius.com/prices via web.archive.org)
A83: Prices_Monthly | B83: W6 | C83: Nebius B200 on-demand | D83: 2025-10 | E83: 5.5 | F83: Reported | G83: /workspace/nebius/market/gpu_price_history.xlsx Price_History_Monthly 'Nebius | B200 | on-demand | PAYG' 2025-10 (snapshot rows in Price_History_Long; nebius.com/prices via web.archive.org)
A84: Prices_Monthly | B84: X6 | C84: Nebius B200 on-demand | D84: 2025-11 | E84: 5.5 | F84: Reported | G84: /workspace/nebius/market/gpu_price_history.xlsx Price_History_Monthly 'Nebius | B200 | on-demand | PAYG' 2025-11 (snapshot rows in Price_History_Long; nebius.com/prices via web.archive.org)
A85: Prices_Monthly | B85: Y6 | C85: Nebius B200 on-demand | D85: 2025-12 | E85: 5.5 | F85: Reported | G85: /workspace/nebius/market/gpu_price_history.xlsx Price_History_Monthly 'Nebius | B200 | on-demand | PAYG' 2025-12 (snapshot rows in Price_History_Long; nebius.com/prices via web.archive.org)
A86: Prices_Monthly | B86: Z6 | C86: Nebius B200 on-demand | D86: 2026-01 | E86: 5.5 | F86: Reported | G86: /workspace/nebius/market/gpu_price_history.xlsx Price_History_Monthly 'Nebius | B200 | on-demand | PAYG' 2026-01 (snapshot rows in Price_History_Long; nebius.com/prices via web.archive.org)
A87: Prices_Monthly | B87: AA6 | C87: Nebius B200 on-demand | D87: 2026-02 | E87: 5.5 | F87: Reported | G87: /workspace/nebius/market/gpu_price_history.xlsx Price_History_Monthly 'Nebius | B200 | on-demand | PAYG' 2026-02 (snapshot rows in Price_History_Long; nebius.com/prices via web.archive.org)
A88: Prices_Monthly | B88: AB6 | C88: Nebius B200 on-demand | D88: 2026-03 | E88: 5.5 | F88: Reported | G88: /workspace/nebius/market/gpu_price_history.xlsx Price_History_Monthly 'Nebius | B200 | on-demand | PAYG' 2026-03 (snapshot rows in Price_History_Long; nebius.com/prices via web.archive.org)
A89: Prices_Monthly | B89: AC6 | C89: Nebius B200 on-demand | D89: 2026-04 | E89: 5.5 | F89: Reported | G89: /workspace/nebius/market/gpu_price_history.xlsx Price_History_Monthly 'Nebius | B200 | on-demand | PAYG' 2026-04 (snapshot rows in Price_History_Long; nebius.com/prices via web.archive.org)
A90: Prices_Monthly | B90: AD6 | C90: Nebius B200 on-demand | D90: 2026-05 | E90: 5.5 | F90: Reported | G90: /workspace/nebius/market/gpu_price_history.xlsx Price_History_Monthly 'Nebius | B200 | on-demand | PAYG' 2026-05 (snapshot rows in Price_History_Long; nebius.com/prices via web.archive.org)
A91: Prices_Monthly | B91: AE6 | C91: Nebius B200 on-demand | D91: 2026-06 | E91: 7.15 | F91: Reported | G91: /workspace/nebius/market/gpu_price_history.xlsx Price_History_Monthly 'Nebius | B200 | on-demand | PAYG' 2026-06 (snapshot rows in Price_History_Long; nebius.com/prices via web.archive.org)
A92: Prices_Monthly | B92: B7 | C92: Nebius B300 on-demand | D92: 2024-01 | E92: n.d. | F92: not disclosed | G92: /workspace/nebius/market/gpu_price_history.xlsx (no observation) | H92: SKU not listed / no snapshot
A93: Prices_Monthly | B93: C7 | C93: Nebius B300 on-demand | D93: 2024-02 | E93: n.d. | F93: not disclosed | G93: /workspace/nebius/market/gpu_price_history.xlsx (no observation) | H93: SKU not listed / no snapshot
A94: Prices_Monthly | B94: D7 | C94: Nebius B300 on-demand | D94: 2024-03 | E94: n.d. | F94: not disclosed | G94: /workspace/nebius/market/gpu_price_history.xlsx (no observation) | H94: SKU not listed / no snapshot
A95: Prices_Monthly | B95: E7 | C95: Nebius B300 on-demand | D95: 2024-04 | E95: n.d. | F95: not disclosed | G95: /workspace/nebius/market/gpu_price_history.xlsx (no observation) | H95: SKU not listed / no snapshot
A96: Prices_Monthly | B96: F7 | C96: Nebius B300 on-demand | D96: 2024-05 | E96: n.d. | F96: not disclosed | G96: /workspace/nebius/market/gpu_price_history.xlsx (no observation) | H96: SKU not listed / no snapshot
A97: Prices_Monthly | B97: G7 | C97: Nebius B300 on-demand | D97: 2024-06 | E97: n.d. | F97: not disclosed | G97: /workspace/nebius/market/gpu_price_history.xlsx (no observation) | H97: SKU not listed / no snapshot
A98: Prices_Monthly | B98: H7 | C98: Nebius B300 on-demand | D98: 2024-07 | E98: n.d. | F98: not disclosed | G98: /workspace/nebius/market/gpu_price_history.xlsx (no observation) | H98: SKU not listed / no snapshot
A99: Prices_Monthly | B99: I7 | C99: Nebius B300 on-demand | D99: 2024-08 | E99: n.d. | F99: not disclosed | G99: /workspace/nebius/market/gpu_price_history.xlsx (no observation) | H99: SKU not listed / no snapshot
A100: Prices_Monthly | B100: J7 | C100: Nebius B300 on-demand | D100: 2024-09 | E100: n.d. | F100: not disclosed | G100: /workspace/nebius/market/gpu_price_history.xlsx (no observation) | H100: SKU not listed / no snapshot
A101: Prices_Monthly | B101: K7 | C101: Nebius B300 on-demand | D101: 2024-10 | E101: n.d. | F101: not disclosed | G101: /workspace/nebius/market/gpu_price_history.xlsx (no observation) | H101: SKU not listed / no snapshot
A102: Prices_Monthly | B102: L7 | C102: Nebius B300 on-demand | D102: 2024-11 | E102: n.d. | F102: not disclosed | G102: /workspace/nebius/market/gpu_price_history.xlsx (no observation) | H102: SKU not listed / no snapshot
A103: Prices_Monthly | B103: M7 | C103: Nebius B300 on-demand | D103: 2024-12 | E103: n.d. | F103: not disclosed | G103: /workspace/nebius/market/gpu_price_history.xlsx (no observation) | H103: SKU not listed / no snapshot
... A118: Prices_Monthly | B118: AB7 | C118: Nebius B300 on-demand | D118: 2026-03 | E118: n.d. | F118: not disclosed | G118: /workspace/nebius/market/gpu_price_history.xlsx (no observation) | H118: SKU not listed / no snapshot
A119: Prices_Monthly | B119: AC7 | C119: Nebius B300 on-demand | D119: 2026-04 | E119: 6.1 | F119: Reported | G119: /workspace/nebius/market/gpu_price_history.xlsx Price_History_Monthly 'Nebius | B300 | on-demand | PAYG' 2026-04 (snapshot rows in Price_History_Long; nebius.com/prices via web.archive.org)
A120: Prices_Monthly | B120: AD7 | C120: Nebius B300 on-demand | D120: 2026-05 | E120: 6.1 | F120: Reported | G120: /workspace/nebius/market/gpu_price_history.xlsx Price_History_Monthly 'Nebius | B300 | on-demand | PAYG' 2026-05 (snapshot rows in Price_History_Long; nebius.com/prices via web.archive.org)
A121: Prices_Monthly | B121: AE7 | C121: Nebius B300 on-demand | D121: 2026-06 | E121: 7.85 | F121: Reported | G121: /workspace/nebius/market/gpu_price_history.xlsx Price_History_Monthly 'Nebius | B300 | on-demand | PAYG' 2026-06 (snapshot rows in Price_History_Long; nebius.com/prices via web.archive.org)
A122: KPI | B122: C5 | C122: Group revenue (continuing ops, restated) | D122: Q1 2024 | E122: 9.7 | F122: Derived | G122: 6-K 2025-08-07 acc 0001104659-25-075028 tm2522866d1_ex99-1.htm H1 24.2 - Q2 14.5 | https://www.sec.gov/Archives/edgar/data/1513845/000110465925075028/tm2522866d1_ex99-1.htm | H122: restated ex-Toloka; orig. reported incl. Toloka 11.4
A123: KPI | B123: D5 | C123: Group revenue (continuing ops, restated) | D123: Q2 2024 | E123: 14.5 | F123: Reported | G123: 6-K 2025-08-07 acc 0001104659-25-075028 tm2522866d1_ex99-1.htm comparative | https://www.sec.gov/Archives/edgar/data/1513845/000110465925075028/tm2522866d1_ex99-1.htm
A124: KPI | B124: E5 | C124: Group revenue (continuing ops, restated) | D124: Q3 2024 | E124: 32.1 | F124: Reported | G124: 6-K 2025-11-12 acc 0001104659-25-109806 tm2530882d1_ex99-1.htm comparative | https://www.sec.gov/Archives/edgar/data/1513845/000110465925109806/tm2530882d1_ex99-1.htm | H124: orig. 43.3 incl. Toloka
A125: KPI | B125: F5 | C125: Group revenue (continuing ops, restated) | D125: Q4 2024 | E125: 35.2 | F125: Reported | G125: 6-K 2026-02-12 acc 0001104659-26-013946 tm266173d1_ex99-1.htm comparative | https://www.sec.gov/Archives/edgar/data/1513845/000110465926013946/tm266173d1_ex99-1.htm | H125: orig. 37.9 incl. Toloka
...
